{
  "type": "Feature",
  "properties": {
    "gn:admin1_code":"02",
    "gn:admin2_code":"2701407.0",
    "gn:asciiname":"Riachuelo",
    "gn:country_code":"BR",
    "gn:dem":88,
    "gn:feature_class":"P",
    "gn:feature_code":"PPL",
    "gn:name":"Riachuelo",
    "gn:population":0,
    "gn:timezone":"America/Maceio",
    "iso:country":"BR",
    "wof:name":"Riachuelo",
    "wof:placetype":"locality"
},
  "geometry": {"coordinates":[-36.23333,-9.85],"type":"Point"}
}