{
  "type": "Feature",
  "properties": {
    "gn:admin1_code":"5",
    "gn:admin2_code":"2902807.0",
    "gn:asciiname":"Santo Amaro",
    "gn:country_code":"BR",
    "gn:dem":471,
    "gn:feature_class":"P",
    "gn:feature_code":"PPL",
    "gn:name":"Santo Amaro",
    "gn:population":0,
    "gn:timezone":"America/Bahia",
    "iso:country":"BR",
    "name:bpy_x_preferred":[
        "\u09b8\u09be\u09a8\u09cd\u099f\u09cb \u0986\u09ae\u09be\u09b0\u09cb"
    ],
    "name:ceb_x_preferred":[
        "Santo Amaro"
    ],
    "name:deu_x_preferred":[
        "Santo Amaro"
    ],
    "name:fra_x_preferred":[
        "Santo Amaro"
    ],
    "name:ita_x_preferred":[
        "Santo Amaro"
    ],
    "name:mlg_x_preferred":[
        "Santo Amaro"
    ],
    "name:nld_x_preferred":[
        "Santo Amaro"
    ],
    "name:pol_x_preferred":[
        "Santo Amaro"
    ],
    "name:por_x_preferred":[
        "Santo Amaro"
    ],
    "name:rus_x_preferred":[
        "\u0421\u0430\u043d\u0442\u0443-\u0410\u043c\u0430\u0440\u0443"
    ],
    "name:swe_x_preferred":[
        "Santo Amaro"
    ],
    "name:vie_x_preferred":[
        "Santo Amaro"
    ],
    "wof:name":"Santo Amaro",
    "wof:placetype":"locality"
},
  "geometry": {"coordinates":[-41.13333,-13.63333],"type":"Point"}
}