{
  "type": "Feature",
  "properties": {
    "gn:admin1_code":"4",
    "gn:admin2_code":"1300102.0",
    "gn:asciiname":"Castanha-mirim",
    "gn:country_code":"BR",
    "gn:dem":35,
    "gn:feature_class":"P",
    "gn:feature_code":"PPL",
    "gn:name":"Castanha-mirim",
    "gn:population":0,
    "gn:timezone":"America/Manaus",
    "iso:country":"BR",
    "wof:name":"Castanha-mirim",
    "wof:placetype":"locality"
},
  "geometry": {"coordinates":[-62.19306,-4.2625],"type":"Point"}
}