{
  "type": "Feature",
  "properties": {
    "gn:admin1_code":"23",
    "gn:admin2_code":"4308201.0",
    "gn:asciiname":"Hercules Coradi",
    "gn:country_code":"BR",
    "gn:dem":702,
    "gn:feature_class":"P",
    "gn:feature_code":"PPL",
    "gn:name":"H\u00e9rcules Coradi",
    "gn:population":0,
    "gn:timezone":"America/Sao_Paulo",
    "iso:country":"BR",
    "name:por_x_preferred":[
        "H\u00e9rcules Coradi"
    ],
    "wof:name":"Hercules Coradi",
    "wof:placetype":"locality"
},
  "geometry": {"coordinates":[-51.1969,-29.0162],"type":"Point"}
}