{
  "type": "Feature",
  "properties": {
    "gn:admin1_code":"15",
    "gn:admin2_code":"3141405.0",
    "gn:asciiname":"Santos",
    "gn:country_code":"BR",
    "gn:dem":656,
    "gn:feature_class":"P",
    "gn:feature_code":"PPL",
    "gn:name":"Santos",
    "gn:population":0,
    "gn:timezone":"America/Sao_Paulo",
    "iso:country":"BR",
    "name:por_x_preferred":[
        "Santos"
    ],
    "wof:name":"Santos",
    "wof:placetype":"locality"
},
  "geometry": {"coordinates":[-41.56667,-16.35],"type":"Point"}
}