{
  "type": "Feature",
  "properties": {
    "gn:admin1_code":"18",
    "gn:admin2_code":"4104204.0",
    "gn:asciiname":"Sao Silvestre",
    "gn:country_code":"BR",
    "gn:dem":769,
    "gn:feature_class":"P",
    "gn:feature_code":"PPL",
    "gn:name":"S\u00e3o Silvestre",
    "gn:population":0,
    "gn:timezone":"America/Sao_Paulo",
    "iso:country":"BR",
    "name:und_x_variant":[
        "S\u00e3o Sylvestre",
        "S\u00e3o Silvestre"
    ],
    "wof:name":"Sao Silvestre",
    "wof:placetype":"locality"
},
  "geometry": {"coordinates":[-49.65468,-25.10595],"type":"Point"}
}