{
  "type": "Feature",
  "properties": {
    "gn:admin1_code":"18.0",
    "gn:admin2_code":"4101309.0",
    "gn:asciiname":"Bairro da Estrela",
    "gn:country_code":"BR",
    "gn:dem":826,
    "gn:feature_class":"P",
    "gn:feature_code":"PPL",
    "gn:name":"Bairro da Estrela",
    "gn:population":0,
    "gn:timezone":"America/Sao_Paulo",
    "iso:country":"BR",
    "name:por_x_preferred":[
        "Bairro da Estrela"
    ],
    "wof:name":"Bairro da Estrela",
    "wof:placetype":"locality"
},
  "geometry": {"coordinates":[-50.01419,-25.95207000000001],"type":"Point"}
}