{
  "type": "Feature",
  "properties": {
    "gn:admin1_code":"06",
    "gn:admin2_code":"2313351.0",
    "gn:asciiname":"Fazenda Maracata",
    "gn:country_code":"BR",
    "gn:dem":154,
    "gn:feature_class":"P",
    "gn:feature_code":"PPL",
    "gn:name":"Fazenda Maracat\u00e1",
    "gn:population":0,
    "gn:timezone":"America/Fortaleza",
    "iso:country":"BR",
    "wof:name":"Fazenda Maracata",
    "wof:placetype":"locality"
},
  "geometry": {"coordinates":[-39.55,-3.93333],"type":"Point"}
}