{
  "type": "Feature",
  "properties": {
    "gn:admin1_code":"14",
    "gn:admin2_code":"5101605.0",
    "gn:asciiname":"Porto Porobeu",
    "gn:cc2":"BR",
    "gn:country_code":"BR",
    "gn:dem":128,
    "gn:feature_class":"P",
    "gn:feature_code":"PPL",
    "gn:name":"P\u00f4rto Porobeu",
    "gn:population":0,
    "gn:timezone":"America/Cuiaba",
    "iso:country":"BR",
    "name:und_x_variant":[
        "Porto Santa Maria",
        "P\u00f4rto da Fazenda Santa Maria do Poboreu",
        "Porto do Fazenda Santa Maria",
        "Porto da Fazenda Santa Maria do Poborereu",
        "P\u00f4rto Porobeu"
    ],
    "wof:name":"Porto Porobeu",
    "wof:placetype":"locality"
},
  "geometry": {"coordinates":[-56.21666999999999,-16.95],"type":"Point"}
}