{
  "type": "Feature",
  "properties": {
    "gn:admin1_code":"21",
    "gn:admin2_code":"3303609.0",
    "gn:asciiname":"Engenheiro Nicanor Pereira",
    "gn:country_code":"BR",
    "gn:dem":42,
    "gn:feature_class":"P",
    "gn:feature_code":"PPL",
    "gn:name":"Engenheiro Nicanor Pereira",
    "gn:population":0,
    "gn:timezone":"America/Sao_Paulo",
    "iso:country":"BR",
    "name:por_x_preferred":[
        "Engenheiro Nicanor Pereira"
    ],
    "wof:name":"Engenheiro Nicanor Pereira",
    "wof:placetype":"locality"
},
  "geometry": {"coordinates":[-43.70528,-22.62417],"type":"Point"}
}