{
  "type": "Feature",
  "properties": {
    "gn:admin1_code":"02",
    "gn:admin2_code":"2705804.0",
    "gn:asciiname":"Olhos d'Agua do Casado",
    "gn:country_code":"BR",
    "gn:dem":222,
    "gn:feature_class":"P",
    "gn:feature_code":"PPL",
    "gn:name":"Olhos d\u2019\u00c1gua do Casado",
    "gn:population":0,
    "gn:timezone":"America/Maceio",
    "iso:country":"BR",
    "wof:name":"Olhos d'Agua do Casado",
    "wof:placetype":"locality"
},
  "geometry": {"coordinates":[-37.85,-9.51667],"type":"Point"}
}