{
  "type": "Feature",
  "properties": {
    "gn:admin1_code":"20",
    "gn:admin2_code":"2204006.0",
    "gn:asciiname":"Capoeiral",
    "gn:country_code":"BR",
    "gn:dem":257,
    "gn:feature_class":"P",
    "gn:feature_code":"PPL",
    "gn:name":"Capoeiral",
    "gn:population":0,
    "gn:timezone":"America/Fortaleza",
    "iso:country":"BR",
    "wof:name":"Capoeiral",
    "wof:placetype":"locality"
},
  "geometry": {"coordinates":[-42.21667,-6.38333],"type":"Point"}
}