{
  "type": "Feature",
  "properties": {
    "gn:admin1_code":"18.0",
    "gn:admin2_code":"4126207.0",
    "gn:asciiname":"Bairro dos Alves",
    "gn:country_code":"BR",
    "gn:dem":782,
    "gn:feature_class":"P",
    "gn:feature_code":"PPLL",
    "gn:name":"Bairro dos Alves",
    "gn:population":0,
    "gn:timezone":"America/Sao_Paulo",
    "iso:country":"BR",
    "name:por_x_preferred":[
        "Bairro dos Alves"
    ],
    "wof:name":"Bairro dos Alves",
    "wof:placetype":"locality"
},
  "geometry": {"coordinates":[-50.57737,-23.88496],"type":"Point"}
}