{
  "type": "Feature",
  "properties": {
    "gn:admin1_code":"21",
    "gn:admin2_code":"3304201.0",
    "gn:asciiname":"Bairro Surubi",
    "gn:country_code":"BR",
    "gn:dem":403,
    "gn:feature_class":"P",
    "gn:feature_code":"PPL",
    "gn:name":"Bairro Surubi",
    "gn:population":0,
    "gn:timezone":"America/Sao_Paulo",
    "iso:country":"BR",
    "name:por_x_preferred":[
        "Bairro Surubi"
    ],
    "wof:name":"Bairro Surubi",
    "wof:placetype":"locality"
},
  "geometry": {"coordinates":[-44.4323,-22.4664],"type":"Point"}
}