{
  "type": "Feature",
  "properties": {
    "gn:admin1_code":"5",
    "gn:admin2_code":"2933505.0",
    "gn:asciiname":"Rio das Almas",
    "gn:country_code":"BR",
    "gn:dem":134,
    "gn:feature_class":"P",
    "gn:feature_code":"PPL",
    "gn:name":"Rio das Almas",
    "gn:population":0,
    "gn:timezone":"America/Bahia",
    "iso:country":"BR",
    "wof:name":"Rio das Almas",
    "wof:placetype":"locality"
},
  "geometry": {"coordinates":[-39.48333,-13.68333],"type":"Point"}
}