{
  "type": "Feature",
  "properties": {
    "gn:admin1_code":"27",
    "gn:admin2_code":"3550605.0",
    "gn:asciiname":"Sitio Sao Jose",
    "gn:country_code":"BR",
    "gn:dem":1020,
    "gn:feature_class":"P",
    "gn:feature_code":"PPL",
    "gn:name":"S\u00edtio S\u00e3o Jos\u00e9",
    "gn:population":0,
    "gn:timezone":"America/Sao_Paulo",
    "iso:country":"BR",
    "name:por_x_preferred":[
        "S\u00edtio S\u00e3o Jos\u00e9"
    ],
    "wof:name":"Sitio Sao Jose",
    "wof:placetype":"locality"
},
  "geometry": {"coordinates":[-47.11049000000001,-23.59074],"type":"Point"}
}