{
  "type": "Feature",
  "properties": {
    "gn:admin1_code":"4",
    "gn:admin2_code":"1303809.0",
    "gn:asciiname":"Aruti",
    "gn:country_code":"BR",
    "gn:dem":49,
    "gn:feature_class":"P",
    "gn:feature_code":"PPL",
    "gn:name":"Aruti",
    "gn:population":0,
    "gn:timezone":"America/Manaus",
    "iso:country":"BR",
    "name:und_x_variant":[
        "Uaruti",
        "Uaruty",
        "Uarati",
        "Aruti"
    ],
    "wof:name":"Aruti",
    "wof:placetype":"locality"
},
  "geometry": {"coordinates":[-66.04543000000001,-0.2834],"type":"Point"}
}