{
  "type": "Feature",
  "properties": {
    "gn:admin1_code":"5",
    "gn:admin2_code":"2921906.0",
    "gn:asciiname":"Caraibas",
    "gn:country_code":"BR",
    "gn:dem":1028,
    "gn:feature_class":"P",
    "gn:feature_code":"PPL",
    "gn:name":"Cara\u00edbas",
    "gn:population":0,
    "gn:timezone":"America/Bahia",
    "iso:country":"BR",
    "wof:name":"Caraibas",
    "wof:placetype":"locality"
},
  "geometry": {"coordinates":[-41.48489,-12.96621],"type":"Point"}
}