{
  "type": "Feature",
  "properties": {
    "gn:admin1_code":"18",
    "gn:admin2_code":"4100202.0",
    "gn:asciiname":"Garganta do Leandro",
    "gn:cc2":"BR",
    "gn:country_code":"BR",
    "gn:dem":861,
    "gn:feature_class":"P",
    "gn:feature_code":"PPL",
    "gn:name":"Garganta do Leandro",
    "gn:population":0,
    "gn:timezone":"America/Sao_Paulo",
    "iso:country":"BR",
    "name:und_x_variant":[
        "Garganta do Lizandr\u00f3",
        "Garganta do Leandro"
    ],
    "wof:name":"Garganta do Leandro",
    "wof:placetype":"locality"
},
  "geometry": {"coordinates":[-49.05,-24.86667000000001],"type":"Point"}
}