{
  "type": "Feature",
  "properties": {
    "gn:admin1_code":"13",
    "gn:admin2_code":"2102101.0",
    "gn:asciiname":"Boca da Mata",
    "gn:country_code":"BR",
    "gn:dem":56,
    "gn:feature_class":"P",
    "gn:feature_code":"PPL",
    "gn:name":"Boca da Mata",
    "gn:population":0,
    "gn:timezone":"America/Fortaleza",
    "iso:country":"BR",
    "wof:name":"Boca da Mata",
    "wof:placetype":"locality"
},
  "geometry": {"coordinates":[-42.77944,-3.77917],"type":"Point"}
}