{
  "type": "Feature",
  "properties": {
    "gn:gn_country":"BR",
    "gn:gn_fcode":"PPL",
    "gn:gn_pop":0,
    "iso:country":"BR",
    "name:bpy_x_preferred":[
        "\u09b8\u09be\u09a8\u09cd\u099f\u09be \u099f\u09c7\u09b0\u09c7\u099c\u09bf\u09a8\u09b9\u09be"
    ],
    "name:deu_x_preferred":[
        "Santa Terezinha"
    ],
    "name:eng_x_preferred":[
        "Santa Terezinha"
    ],
    "name:eus_x_preferred":[
        "Santa Terezinha"
    ],
    "name:fra_x_preferred":[
        "Santa Terezinha"
    ],
    "name:hun_x_preferred":[
        "Santa Terezinha"
    ],
    "name:hye_x_preferred":[
        "\u054d\u0561\u0576\u057f\u0561 \u054f\u0565\u0580\u0565\u0566\u056b\u0576\u056b\u0561"
    ],
    "name:ita_x_preferred":[
        "Santa Terezinha"
    ],
    "name:kat_x_preferred":[
        "\u10e1\u10d0\u10dc\u10e2\u10d0-\u10e2\u10d4\u10e0\u10d4\u10d6\u10d8\u10dc\u10d8\u10d0"
    ],
    "name:nan_x_preferred":[
        "Santa Terezinha"
    ],
    "name:nld_x_preferred":[
        "Santa Terezinha"
    ],
    "name:nob_x_preferred":[
        "Santa Terezinha"
    ],
    "name:pol_x_preferred":[
        "Santa Terezinha"
    ],
    "name:por_x_preferred":[
        "Santa Terezinha"
    ],
    "name:ron_x_preferred":[
        "Santa Terezinha"
    ],
    "name:rus_x_preferred":[
        "\u0421\u0430\u043d\u0442\u0430-\u0422\u0435\u0440\u0435\u0437\u0438\u043d\u044c\u044f"
    ],
    "name:spa_x_preferred":[
        "Santa Terezinha"
    ],
    "name:unk_x_variant":[
        "Santa Teresinha"
    ],
    "name:vie_x_preferred":[
        "Santa Terezinha"
    ],
    "name:vol_x_preferred":[
        "Santa Terezinha"
    ],
    "name:war_x_preferred":[
        "Santa Terezinha"
    ],
    "name:zho_x_preferred":[
        "\u5723\u7279\u96f7\u6d4e\u5c3c\u4e9a"
    ],
    "qs_pg:aaroncc":"BR",
    "qs_pg:gn_country":"BR",
    "qs_pg:gn_fcode":"PPL",
    "qs_pg:gn_pop":0,
    "qs_pg:name":"Santa Teresinna",
    "qs_pg:name_adm0":"Brasil",
    "qs_pg:name_adm1":"Mato Grosso",
    "qs_pg:photos_9r":0,
    "qs_pg:photos_sr":0,
    "qs_pg:pop_sr":0,
    "qs_pg:qs_pg_placetype":"locality",
    "qs_pg:qs_pg_placetype_gp":"Town",
    "qs_pg:woe_adm0":23424768,
    "woe:adm0_id":23424768,
    "woe:name_adm0":"Brasil",
    "woe:name_adm1":"Mato Grosso",
    "woe:placetype":"Town",
    "wof:name":"Santa Teresinna",
    "wof:placetype":"locality"
},
  "geometry": {"coordinates":[-50.50306,-10.46972],"type":"Point"}
}