{
  "type": "Feature",
  "properties": {
    "gn:admin1_code":"18.0",
    "gn:admin2_code":"4126603.0",
    "gn:asciiname":"Sitio Amadeu Conrado",
    "gn:country_code":"BR",
    "gn:dem":790,
    "gn:feature_class":"P",
    "gn:feature_code":"PPL",
    "gn:name":"S\u00edtio Amadeu Conrado",
    "gn:population":0,
    "gn:timezone":"America/Sao_Paulo",
    "iso:country":"BR",
    "name:por_x_preferred":[
        "S\u00edtio Amadeu Conrado"
    ],
    "wof:name":"Sitio Amadeu Conrado",
    "wof:placetype":"locality"
},
  "geometry": {"coordinates":[-49.86600000000001,-23.6305],"type":"Point"}
}