{
  "type": "Feature",
  "properties": {
    "gn:admin1_code":"4",
    "gn:admin2_code":"1302702.0",
    "gn:asciiname":"Santo Antonio do Atininga",
    "gn:country_code":"BR",
    "gn:dem":40,
    "gn:feature_class":"P",
    "gn:feature_code":"PPL",
    "gn:name":"Santo Ant\u00f4nio do Atininga",
    "gn:population":0,
    "gn:timezone":"America/Manaus",
    "iso:country":"BR",
    "name:por_x_preferred":[
        "Santo Ant\u00f4nio do Atininga"
    ],
    "wof:name":"Santo Antonio do Atininga",
    "wof:placetype":"locality"
},
  "geometry": {"coordinates":[-60.96586,-5.60004],"type":"Point"}
}