{
  "type": "Feature",
  "properties": {
    "gn:admin1_code":"15",
    "gn:admin2_code":"3109006.0",
    "gn:asciiname":"Beira Serra",
    "gn:country_code":"BR",
    "gn:dem":917,
    "gn:feature_class":"P",
    "gn:feature_code":"PPL",
    "gn:name":"Beira Serra",
    "gn:population":0,
    "gn:timezone":"America/Sao_Paulo",
    "iso:country":"BR",
    "name:por_x_preferred":[
        "Beira Serra"
    ],
    "wof:name":"Beira Serra",
    "wof:placetype":"locality"
},
  "geometry": {"coordinates":[-43.9929,-20.2315],"type":"Point"}
}