{
  "type": "Feature",
  "properties": {
    "gn:admin1_code":"30",
    "gn:admin2_code":"2605103.0",
    "gn:asciiname":"Porteiras",
    "gn:country_code":"BR",
    "gn:dem":490,
    "gn:feature_class":"P",
    "gn:feature_code":"PPL",
    "gn:name":"Porteiras",
    "gn:population":0,
    "gn:timezone":"America/Recife",
    "iso:country":"BR",
    "name:bpy_x_preferred":[
        "\u09aa\u09cb\u09b0\u09cd\u099f\u09c7\u0987\u09b0\u09be\u09b8"
    ],
    "name:ceb_x_preferred":[
        "Porteiras"
    ],
    "name:eus_x_preferred":[
        "Porteiras"
    ],
    "name:fra_x_preferred":[
        "Porteiras"
    ],
    "name:ita_x_preferred":[
        "Porteiras"
    ],
    "name:kat_x_preferred":[
        "\u10de\u10dd\u10e0\u10e2\u10d4\u10d8\u10e0\u10d0\u10e1\u10d8"
    ],
    "name:kaz_x_preferred":[
        "\u041f\u043e\u0440\u0442\u0435\u0439\u0440\u0430\u0441"
    ],
    "name:nld_x_preferred":[
        "Porteiras"
    ],
    "name:nor_x_preferred":[
        "Porteiras"
    ],
    "name:por_x_preferred":[
        "Porteiras"
    ],
    "name:ron_x_preferred":[
        "Porteiras"
    ],
    "name:rus_x_preferred":[
        "\u041f\u043e\u0440\u0442\u0435\u0439\u0440\u0430\u0441"
    ],
    "name:swe_x_preferred":[
        "Porteiras"
    ],
    "name:vie_x_preferred":[
        "Porteiras"
    ],
    "name:vol_x_preferred":[
        "Porteiras"
    ],
    "name:war_x_preferred":[
        "Porteiras"
    ],
    "name:zho_x_preferred":[
        "\u6ce2\u5c14\u6cf0\u62c9\u65af"
    ],
    "wof:name":"Porteiras",
    "wof:placetype":"locality"
},
  "geometry": {"coordinates":[-37.73333,-8.28333],"type":"Point"}
}