{
  "type": "Feature",
  "properties": {
    "gn:admin1_code":"30",
    "gn:admin2_code":"2605103.0",
    "gn:asciiname":"Porteiras",
    "gn:country_code":"BR",
    "gn:dem":490,
    "gn:feature_class":"P",
    "gn:feature_code":"PPL",
    "gn:name":"Porteiras",
    "gn:population":0,
    "gn:timezone":"America/Recife",
    "iso:country":"BR",
    "wof:name":"Porteiras",
    "wof:placetype":"locality"
},
  "geometry": {"coordinates":[-37.73333,-8.28333],"type":"Point"}
}