{
  "type": "Feature",
  "properties": {
    "gn:admin1_code":"27",
    "gn:admin2_code":"3548609.0",
    "gn:asciiname":"Serrano",
    "gn:country_code":"BR",
    "gn:dem":900,
    "gn:feature_class":"P",
    "gn:feature_code":"PPLL",
    "gn:name":"Serrano",
    "gn:population":0,
    "gn:timezone":"America/Sao_Paulo",
    "iso:country":"BR",
    "name:por_x_preferred":[
        "Serrano"
    ],
    "wof:name":"Serrano",
    "wof:placetype":"locality"
},
  "geometry": {"coordinates":[-45.7441,-22.6986],"type":"Point"}
}