{
  "type": "Feature",
  "properties": {
    "gn:admin1_code":"27.0",
    "gn:admin2_code":"3550308.0",
    "gn:asciiname":"Bairro Jardim Itaim",
    "gn:country_code":"BR",
    "gn:dem":781,
    "gn:feature_class":"P",
    "gn:feature_code":"PPL",
    "gn:name":"Bairro Jardim Itaim",
    "gn:population":0,
    "gn:timezone":"America/Sao_Paulo",
    "iso:country":"BR",
    "name:por_x_preferred":[
        "Bairro Jardim Itaim"
    ],
    "wof:name":"Bairro Jardim Itaim",
    "wof:placetype":"locality"
},
  "geometry": {"coordinates":[-46.71368,-23.81031],"type":"Point"}
}