{
  "type": "Feature",
  "properties": {
    "gn:admin1_code":"20",
    "gn:admin2_code":"2203008.0",
    "gn:asciiname":"Cristalandia do Piaui",
    "gn:country_code":"BR",
    "gn:dem":472,
    "gn:feature_class":"P",
    "gn:feature_code":"PPL",
    "gn:name":"Cristal\u00e2ndia do Piau\u00ed",
    "gn:population":0,
    "gn:timezone":"America/Fortaleza",
    "iso:country":"BR",
    "name:bpy_x_preferred":[
        "\u0995\u09b0\u09bf\u09b8\u09cd\u099f\u09be\u09b2\u09be\u09a8\u09cd\u09a1\u09bf\u09af\u09bc\u09be \u09a1\u09cb \u09aa\u09bf\u09af\u09bc\u09be\u0989\u0987"
    ],
    "name:kat_x_preferred":[
        "\u10d9\u10e0\u10d8\u10e1\u10e2\u10d0\u10da\u10d0\u10dc\u10d3\u10d8\u10d0-\u10d3\u10e3-\u10de\u10d8\u10d0\u10e3\u10d8"
    ],
    "name:kaz_x_preferred":[
        "\u041a\u0440\u0438\u0441\u0442\u0430\u043b\u0430\u043d\u0434\u0438\u044f-\u0434\u0443-\u041f\u0438\u0430\u0443\u0438"
    ],
    "name:rus_x_preferred":[
        "\u041a\u0440\u0438\u0441\u0442\u0430\u043b\u0430\u043d\u0434\u0438\u044f-\u0434\u0443-\u041f\u0438\u0430\u0443\u0438"
    ],
    "name:zho_x_preferred":[
        "\u76ae\u5965\u4f0a\u5dde\u514b\u91cc\u65af\u5854\u5170\u8fea\u4e9a"
    ],
    "wof:name":"Cristalandia do Piaui",
    "wof:placetype":"locality"
},
  "geometry": {"coordinates":[-45.185,-10.65306],"type":"Point"}
}