{
  "type": "Feature",
  "properties": {
    "gn:admin1_code":"20",
    "gn:admin2_code":"2203008.0",
    "gn:asciiname":"Cristalandia do Piaui",
    "gn:country_code":"BR",
    "gn:dem":472,
    "gn:feature_class":"P",
    "gn:feature_code":"PPL",
    "gn:name":"Cristal\u00e2ndia do Piau\u00ed",
    "gn:population":0,
    "gn:timezone":"America/Fortaleza",
    "iso:country":"BR",
    "wof:name":"Cristalandia do Piaui",
    "wof:placetype":"locality"
},
  "geometry": {"coordinates":[-45.185,-10.65306],"type":"Point"}
}