{
  "type": "Feature",
  "properties": {
    "gn:admin1_code":"27.0",
    "gn:admin2_code":"3551108.0",
    "gn:asciiname":"Sao Bento",
    "gn:country_code":"BR",
    "gn:dem":578,
    "gn:feature_class":"P",
    "gn:feature_code":"PPLL",
    "gn:name":"S\u00e3o Bento",
    "gn:population":0,
    "gn:timezone":"America/Sao_Paulo",
    "iso:country":"BR",
    "name:por_x_preferred":[
        "S\u00e3o Bento"
    ],
    "wof:name":"Sao Bento",
    "wof:placetype":"locality"
},
  "geometry": {"coordinates":[-47.70475,-23.63879],"type":"Point"}
}