{
  "type": "Feature",
  "properties": {
    "gn:admin1_code":"18.0",
    "gn:admin2_code":"4113205.0",
    "gn:asciiname":"Sitio Josefa Sabatike",
    "gn:country_code":"BR",
    "gn:dem":786,
    "gn:feature_class":"P",
    "gn:feature_code":"PPL",
    "gn:name":"S\u00edtio Josefa Sabatike",
    "gn:population":0,
    "gn:timezone":"America/Sao_Paulo",
    "iso:country":"BR",
    "name:por_x_preferred":[
        "S\u00edtio Josefa Sabatike"
    ],
    "wof:name":"Sitio Josefa Sabatike",
    "wof:placetype":"locality"
},
  "geometry": {"coordinates":[-49.9331,-26.006],"type":"Point"}
}