{
  "type": "Feature",
  "properties": {
    "gn:admin1_code":"05",
    "gn:admin2_code":"2927101.0",
    "gn:asciiname":"Surubabel",
    "gn:country_code":"BR",
    "gn:dem":330,
    "gn:feature_class":"P",
    "gn:feature_code":"PPL",
    "gn:name":"Surubabel",
    "gn:population":0,
    "gn:timezone":"America/Bahia",
    "iso:country":"BR",
    "wof:name":"Surubabel",
    "wof:placetype":"locality"
},
  "geometry": {"coordinates":[-38.71667,-8.88333],"type":"Point"}
}