{
  "type": "Feature",
  "properties": {
    "gn:admin1_code":"18.0",
    "gn:admin2_code":"4126678.0",
    "gn:asciiname":"Sitio Gentil Alduan",
    "gn:country_code":"BR",
    "gn:dem":701,
    "gn:feature_class":"P",
    "gn:feature_code":"PPL",
    "gn:name":"S\u00edtio Gentil Alduan",
    "gn:population":0,
    "gn:timezone":"America/Sao_Paulo",
    "iso:country":"BR",
    "name:por_x_preferred":[
        "S\u00edtio Gentil Alduan"
    ],
    "wof:name":"Sitio Gentil Alduan",
    "wof:placetype":"locality"
},
  "geometry": {"coordinates":[-50.9946,-23.7676],"type":"Point"}
}