{
  "type": "Feature",
  "properties": {
    "gn:admin1_code":"02",
    "gn:admin2_code":"2705002.0",
    "gn:asciiname":"Poco Branco",
    "gn:country_code":"BR",
    "gn:dem":376,
    "gn:feature_class":"P",
    "gn:feature_code":"PPL",
    "gn:name":"Po\u00e7o Branco",
    "gn:population":0,
    "gn:timezone":"America/Maceio",
    "iso:country":"BR",
    "wof:name":"Poco Branco",
    "wof:placetype":"locality"
},
  "geometry": {"coordinates":[-37.81667,-8.93333],"type":"Point"}
}