{
  "type": "Feature",
  "properties": {
    "gn:admin1_code":"04",
    "gn:admin2_code":"1300680.0",
    "gn:asciiname":"Conceicao",
    "gn:country_code":"BR",
    "gn:dem":27,
    "gn:feature_class":"P",
    "gn:feature_code":"PPL",
    "gn:name":"Concei\u00e7\u00e3o",
    "gn:population":0,
    "gn:timezone":"America/Manaus",
    "iso:country":"BR",
    "wof:name":"Conceicao",
    "wof:placetype":"locality"
},
  "geometry": {"coordinates":[-57.78333000000001,-3.05],"type":"Point"}
}