{
  "type": "Feature",
  "properties": {
    "gn:admin1_code":"06",
    "gn:admin2_code":"2312700.0",
    "gn:asciiname":"Rosario (1)",
    "gn:country_code":"BR",
    "gn:dem":278,
    "gn:feature_class":"P",
    "gn:feature_code":"PPL",
    "gn:name":"Ros\u00e1rio (1)",
    "gn:population":0,
    "gn:timezone":"America/Fortaleza",
    "iso:country":"BR",
    "wof:name":"Rosario (1)",
    "wof:placetype":"locality"
},
  "geometry": {"coordinates":[-39.53333,-5.41667],"type":"Point"}
}