{
  "type": "Feature",
  "properties": {
    "gn:admin1_code":"18.0",
    "gn:admin2_code":"4120101.0",
    "gn:asciiname":"Sitio Leonardo G. da Costa",
    "gn:country_code":"BR",
    "gn:dem":828,
    "gn:feature_class":"P",
    "gn:feature_code":"PPL",
    "gn:name":"S\u00edtio Leonardo G. da Costa",
    "gn:population":0,
    "gn:timezone":"America/Sao_Paulo",
    "iso:country":"BR",
    "name:por_x_preferred":[
        "S\u00edtio Leonardo G. da Costa"
    ],
    "wof:name":"Sitio Leonardo G. da Costa",
    "wof:placetype":"locality"
},
  "geometry": {"coordinates":[-49.8875,-25.5688],"type":"Point"}
}