{
  "type": "Feature",
  "properties": {
    "gn:admin1_code":"4.0",
    "gn:admin2_code":"1300680.0",
    "gn:asciiname":"Vila Curaca",
    "gn:country_code":"BR",
    "gn:dem":23,
    "gn:feature_class":"P",
    "gn:feature_code":"PPL",
    "gn:name":"Vila Curaca",
    "gn:population":0,
    "gn:timezone":"America/Manaus",
    "iso:country":"BR",
    "name:por_x_preferred":[
        "Vila Curaca"
    ],
    "wof:name":"Vila Curaca",
    "wof:placetype":"locality"
},
  "geometry": {"coordinates":[-57.49367,-3.11583],"type":"Point"}
}