{
  "type": "Feature",
  "properties": {
    "gn:admin1_code":"5",
    "gn:admin2_code":"2903805.0",
    "gn:asciiname":"Barracao",
    "gn:country_code":"BR",
    "gn:dem":327,
    "gn:feature_class":"P",
    "gn:feature_code":"PPL",
    "gn:name":"Barrac\u00e3o",
    "gn:population":0,
    "gn:timezone":"America/Bahia",
    "iso:country":"BR",
    "wof:name":"Barracao",
    "wof:placetype":"locality"
},
  "geometry": {"coordinates":[-40.55,-12.63333],"type":"Point"}
}