{
  "type": "Feature",
  "properties": {
    "gn:admin1_code":"22",
    "gn:admin2_code":"2410009.0",
    "gn:asciiname":"Macambira",
    "gn:country_code":"BR",
    "gn:dem":292,
    "gn:feature_class":"P",
    "gn:feature_code":"PPL",
    "gn:name":"Macambira",
    "gn:population":0,
    "gn:timezone":"America/Fortaleza",
    "iso:country":"BR",
    "wof:name":"Macambira",
    "wof:placetype":"locality"
},
  "geometry": {"coordinates":[-37.98333,-6.28333],"type":"Point"}
}