{
  "type": "Feature",
  "properties": {
    "gn:admin1_code":"23",
    "gn:admin2_code":"4310439.0",
    "gn:asciiname":"Vila Segredo",
    "gn:country_code":"BR",
    "gn:dem":714,
    "gn:feature_class":"P",
    "gn:feature_code":"PPLL",
    "gn:name":"Vila Segredo",
    "gn:population":0,
    "gn:timezone":"America/Sao_Paulo",
    "iso:country":"BR",
    "wof:name":"Vila Segredo",
    "wof:placetype":"locality"
},
  "geometry": {"coordinates":[-51.37611,-28.76139],"type":"Point"}
}