{
  "type": "Feature",
  "properties": {
    "gn:admin1_code":"18.0",
    "gn:admin2_code":"4100202.0",
    "gn:asciiname":"Caraca",
    "gn:country_code":"BR",
    "gn:dem":330,
    "gn:feature_class":"P",
    "gn:feature_code":"PPLL",
    "gn:name":"Cara\u00e7a",
    "gn:population":0,
    "gn:timezone":"America/Sao_Paulo",
    "iso:country":"BR",
    "name:por_x_preferred":[
        "Cara\u00e7a"
    ],
    "wof:name":"Caraca",
    "wof:placetype":"locality"
},
  "geometry": {"coordinates":[-48.88326,-24.70127],"type":"Point"}
}