{
  "type": "Feature",
  "properties": {
    "gn:admin1_code":"21",
    "gn:admin2_code":"3306107.0",
    "gn:asciiname":"Coroas",
    "gn:country_code":"BR",
    "gn:dem":547,
    "gn:feature_class":"P",
    "gn:feature_code":"PPL",
    "gn:name":"Coroas",
    "gn:population":0,
    "gn:timezone":"America/Sao_Paulo",
    "iso:country":"BR",
    "name:por_x_preferred":[
        "Coroas"
    ],
    "wof:name":"Coroas",
    "wof:placetype":"locality"
},
  "geometry": {"coordinates":[-43.735,-22.12944],"type":"Point"}
}