{
  "type": "Feature",
  "properties": {
    "gn:admin1_code":"18.0",
    "gn:admin2_code":"4114302.0",
    "gn:asciiname":"Sitio Vicente Pucuss",
    "gn:country_code":"BR",
    "gn:dem":929,
    "gn:feature_class":"P",
    "gn:feature_code":"PPL",
    "gn:name":"S\u00edtio Vicente Pucuss",
    "gn:population":0,
    "gn:timezone":"America/Sao_Paulo",
    "iso:country":"BR",
    "name:por_x_preferred":[
        "S\u00edtio Vicente Pucuss"
    ],
    "wof:name":"Sitio Vicente Pucuss",
    "wof:placetype":"locality"
},
  "geometry": {"coordinates":[-49.3603,-25.7838],"type":"Point"}
}