{
  "type": "Feature",
  "properties": {
    "gn:admin1_code":"02",
    "gn:admin2_code":"2702553.0",
    "gn:asciiname":"Vassouras",
    "gn:country_code":"BR",
    "gn:dem":288,
    "gn:feature_class":"P",
    "gn:feature_code":"PPL",
    "gn:name":"Vassouras",
    "gn:population":0,
    "gn:timezone":"America/Maceio",
    "iso:country":"BR",
    "name:bpy_x_preferred":[
        "\u09ad\u09be\u09b8\u09b8\u09cc\u09b0\u09be\u09b8"
    ],
    "name:ceb_x_preferred":[
        "Vassouras"
    ],
    "name:deu_x_preferred":[
        "Vassouras"
    ],
    "name:epo_x_preferred":[
        "Vassouras"
    ],
    "name:eus_x_preferred":[
        "Vassouras"
    ],
    "name:fra_x_preferred":[
        "Vassouras"
    ],
    "name:hye_x_preferred":[
        "\u054e\u0561\u057d\u0578\u0580\u0561\u057d"
    ],
    "name:ita_x_preferred":[
        "Vassouras"
    ],
    "name:kat_x_preferred":[
        "\u10d5\u10d0\u10e1\u10dd\u10e0\u10d0\u10e1\u10d8"
    ],
    "name:kaz_x_preferred":[
        "\u0412\u0430\u0441\u043e\u0440\u0430\u0441"
    ],
    "name:nld_x_preferred":[
        "Vassouras"
    ],
    "name:nor_x_preferred":[
        "Vassouras"
    ],
    "name:pol_x_preferred":[
        "Vassouras"
    ],
    "name:por_x_preferred":[
        "Vassouras"
    ],
    "name:ron_x_preferred":[
        "Vassouras"
    ],
    "name:rus_x_preferred":[
        "\u0412\u0430\u0441\u043e\u0440\u0430\u0441"
    ],
    "name:spa_x_preferred":[
        "Vassouras"
    ],
    "name:srd_x_preferred":[
        "Vassouras"
    ],
    "name:swe_x_preferred":[
        "Vassouras"
    ],
    "name:vie_x_preferred":[
        "Vassouras"
    ],
    "name:vol_x_preferred":[
        "Vassouras"
    ],
    "name:war_x_preferred":[
        "Vassouras"
    ],
    "name:zho_x_preferred":[
        "\u74e6\u7d22\u62c9\u65af"
    ],
    "wof:name":"Vassouras",
    "wof:placetype":"locality"
},
  "geometry": {"coordinates":[-36.78333,-9.38333],"type":"Point"}
}