{
  "type": "Feature",
  "properties": {
    "gn:admin1_code":"27",
    "gn:admin2_code":"3551900.0",
    "gn:asciiname":"Figueira",
    "gn:cc2":"BR",
    "gn:country_code":"BR",
    "gn:dem":571,
    "gn:feature_class":"P",
    "gn:feature_code":"PPL",
    "gn:name":"Figueira",
    "gn:population":0,
    "gn:timezone":"America/Sao_Paulo",
    "iso:country":"BR",
    "name:ceb_x_preferred":[
        "Figueira"
    ],
    "name:deu_x_preferred":[
        "Figueira"
    ],
    "name:fra_x_preferred":[
        "Figueira"
    ],
    "name:glg_x_preferred":[
        "Figueira"
    ],
    "name:nld_x_preferred":[
        "Figueira"
    ],
    "name:por_x_preferred":[
        "Figueira"
    ],
    "name:rus_x_preferred":[
        "\u0424\u0438\u0433\u0435\u0439\u0440\u0430"
    ],
    "name:swe_x_preferred":[
        "Figueira"
    ],
    "name:ukr_x_preferred":[
        "\u0424\u0456\u0433\u0435\u0439\u0440\u0430"
    ],
    "name:und_x_variant":[
        "Camargo"
    ],
    "wof:name":"Figueira",
    "wof:placetype":"locality"
},
  "geometry": {"coordinates":[-48.75,-20.83333],"type":"Point"}
}