{
  "type": "Feature",
  "properties": {
    "gn:admin1_code":"27.0",
    "gn:admin2_code":"3528502.0",
    "gn:asciiname":"Sitio Pedra da Figueira",
    "gn:country_code":"BR",
    "gn:dem":841,
    "gn:feature_class":"P",
    "gn:feature_code":"PPL",
    "gn:name":"S\u00edtio Pedra da Figueira",
    "gn:population":0,
    "gn:timezone":"America/Sao_Paulo",
    "iso:country":"BR",
    "name:por_x_preferred":[
        "S\u00edtio Pedra da Figueira"
    ],
    "wof:name":"Sitio Pedra da Figueira",
    "wof:placetype":"locality"
},
  "geometry": {"coordinates":[-46.63145,-23.31458],"type":"Point"}
}