{
  "type": "Feature",
  "properties": {
    "gn:admin1_code":"14",
    "gn:admin2_code":"5105903.0",
    "gn:asciiname":"Mota",
    "gn:country_code":"BR",
    "gn:dem":211,
    "gn:feature_class":"P",
    "gn:feature_code":"PPL",
    "gn:name":"Mota",
    "gn:population":0,
    "gn:timezone":"America/Cuiaba",
    "iso:country":"BR",
    "name:ceb_x_preferred":[
        "Mota"
    ],
    "name:deu_x_preferred":[
        "Mota"
    ],
    "name:eus_x_preferred":[
        "Mota"
    ],
    "name:fra_x_preferred":[
        "Mota"
    ],
    "name:glg_x_preferred":[
        "Mota"
    ],
    "name:ita_x_preferred":[
        "Mota"
    ],
    "name:nld_x_preferred":[
        "Mota"
    ],
    "name:por_x_preferred":[
        "Mota"
    ],
    "name:rus_x_preferred":[
        "\u041c\u043e\u0442\u0430"
    ],
    "name:spa_x_preferred":[
        "Mota"
    ],
    "name:srp_x_preferred":[
        "Mota"
    ],
    "name:swe_x_preferred":[
        "Mota"
    ],
    "wof:name":"Mota",
    "wof:placetype":"locality"
},
  "geometry": {"coordinates":[-56.16667,-14.65],"type":"Point"}
}