{
  "type": "Feature",
  "properties": {
    "gn:admin1_code":"14",
    "gn:admin2_code":"5105903.0",
    "gn:asciiname":"Mota",
    "gn:country_code":"BR",
    "gn:dem":211,
    "gn:feature_class":"P",
    "gn:feature_code":"PPL",
    "gn:name":"Mota",
    "gn:population":0,
    "gn:timezone":"America/Cuiaba",
    "iso:country":"BR",
    "wof:name":"Mota",
    "wof:placetype":"locality"
},
  "geometry": {"coordinates":[-56.16667,-14.65],"type":"Point"}
}