{
  "type": "Feature",
  "properties": {
    "gn:admin1_code":"13",
    "gn:admin2_code":"2106672.0",
    "gn:asciiname":"Barra",
    "gn:country_code":"BR",
    "gn:dem":56,
    "gn:feature_class":"P",
    "gn:feature_code":"PPL",
    "gn:name":"Barra",
    "gn:population":0,
    "gn:timezone":"America/Fortaleza",
    "iso:country":"BR",
    "wof:name":"Barra",
    "wof:placetype":"locality"
},
  "geometry": {"coordinates":[-42.79028,-3.45806],"type":"Point"}
}