{
  "type": "Feature",
  "properties": {
    "gn:admin1_code":"23",
    "gn:admin2_code":"4320701.0",
    "gn:asciiname":"Arroio Bonito",
    "gn:country_code":"BR",
    "gn:dem":331,
    "gn:feature_class":"P",
    "gn:feature_code":"PPL",
    "gn:name":"Arroio Bonito",
    "gn:population":0,
    "gn:timezone":"America/Sao_Paulo",
    "iso:country":"BR",
    "wof:name":"Arroio Bonito",
    "wof:placetype":"locality"
},
  "geometry": {"coordinates":[-53.05,-29.36667000000001],"type":"Point"}
}