{
  "type": "Feature",
  "properties": {
    "gn:admin1_code":"23",
    "gn:admin2_code":"4313391.0",
    "gn:asciiname":"Rincao dos Cabrais",
    "gn:country_code":"BR",
    "gn:dem":60,
    "gn:feature_class":"P",
    "gn:feature_code":"PPL",
    "gn:name":"Rinc\u00e3o dos Cabrais",
    "gn:population":0,
    "gn:timezone":"America/Sao_Paulo",
    "iso:country":"BR",
    "wof:name":"Rincao dos Cabrais",
    "wof:placetype":"locality"
},
  "geometry": {"coordinates":[-52.95,-29.73333],"type":"Point"}
}