{
  "type": "Feature",
  "properties": {
    "gn:admin1_code":"06",
    "gn:admin2_code":"2309409.0",
    "gn:asciiname":"Lagoa dos Neris",
    "gn:country_code":"BR",
    "gn:dem":425,
    "gn:feature_class":"P",
    "gn:feature_code":"PPL",
    "gn:name":"Lagoa dos Neris",
    "gn:population":0,
    "gn:timezone":"America/Fortaleza",
    "iso:country":"BR",
    "wof:name":"Lagoa dos Neris",
    "wof:placetype":"locality"
},
  "geometry": {"coordinates":[-40.81667,-5.66667],"type":"Point"}
}