{
  "type": "Feature",
  "properties": {
    "gn:admin1_code":"21",
    "gn:admin2_code":"3305802.0",
    "gn:asciiname":"Miguelito",
    "gn:country_code":"BR",
    "gn:dem":1014,
    "gn:feature_class":"P",
    "gn:feature_code":"PPLL",
    "gn:name":"Miguelito",
    "gn:population":0,
    "gn:timezone":"America/Sao_Paulo",
    "iso:country":"BR",
    "name:nld_x_preferred":[
        "Miguelito"
    ],
    "name:por_x_preferred":[
        "Miguelito"
    ],
    "name:spa_x_preferred":[
        "Miguelito"
    ],
    "wof:name":"Miguelito",
    "wof:placetype":"locality"
},
  "geometry": {"coordinates":[-42.78193,-22.29676],"type":"Point"}
}