{
  "type": "Feature",
  "properties": {
    "gn:admin1_code":"18",
    "gn:admin2_code":"4109708.0",
    "gn:asciiname":"Santos Reis",
    "gn:country_code":"BR",
    "gn:dem":531,
    "gn:feature_class":"P",
    "gn:feature_code":"PPL",
    "gn:name":"Santos Reis",
    "gn:population":0,
    "gn:timezone":"America/Sao_Paulo",
    "iso:country":"BR",
    "wof:name":"Santos Reis",
    "wof:placetype":"locality"
},
  "geometry": {"coordinates":[-50.26667,-23.61667000000001],"type":"Point"}
}