{
  "type": "Feature",
  "properties": {
    "gn:admin1_code":"23",
    "gn:admin2_code":"4311155.0",
    "gn:asciiname":"Vinte e Um de Abril",
    "gn:cc2":"BR",
    "gn:country_code":"BR",
    "gn:dem":320,
    "gn:feature_class":"P",
    "gn:feature_code":"PPL",
    "gn:name":"Vinte e Um de Abril",
    "gn:population":0,
    "gn:timezone":"America/Sao_Paulo",
    "iso:country":"BR",
    "name:und_x_variant":[
        "21 de Abril",
        "Vinte e Um de Abril"
    ],
    "wof:name":"Vinte e Um de Abril",
    "wof:placetype":"locality"
},
  "geometry": {"coordinates":[-54.11666999999999,-28.63333],"type":"Point"}
}