{
  "type": "Feature",
  "properties": {
    "gn:admin1_code":"18.0",
    "gn:admin2_code":"4112801.0",
    "gn:asciiname":"Sitio Fausto B. Pinto",
    "gn:country_code":"BR",
    "gn:dem":613,
    "gn:feature_class":"P",
    "gn:feature_code":"PPL",
    "gn:name":"S\u00edtio Fausto B. Pinto",
    "gn:population":0,
    "gn:timezone":"America/Sao_Paulo",
    "iso:country":"BR",
    "name:por_x_preferred":[
        "S\u00edtio Fausto B. Pinto"
    ],
    "wof:name":"Sitio Fausto B. Pinto",
    "wof:placetype":"locality"
},
  "geometry": {"coordinates":[-49.90959,-23.47358],"type":"Point"}
}