{
  "type": "Feature",
  "properties": {
    "gn:admin1_code":"18",
    "gn:admin2_code":"4110706.0",
    "gn:asciiname":"Inacio Martins",
    "gn:cc2":"BR",
    "gn:country_code":"BR",
    "gn:dem":1161,
    "gn:feature_class":"P",
    "gn:feature_code":"PPL",
    "gn:name":"In\u00e1cio Martins",
    "gn:population":0,
    "gn:timezone":"America/Sao_Paulo",
    "iso:country":"BR",
    "name:und_x_variant":[
        "Guarapuavinha",
        "In\u00e1cio Martins"
    ],
    "wof:name":"Inacio Martins",
    "wof:placetype":"locality"
},
  "geometry": {"coordinates":[-51.13333,-25.51667],"type":"Point"}
}