{
  "type": "Feature",
  "properties": {
    "gn:admin1_code":"26.0",
    "gn:admin2_code":"4219358.0",
    "gn:asciiname":"Sabugueiro",
    "gn:country_code":"BR",
    "gn:dem":384,
    "gn:feature_class":"P",
    "gn:feature_code":"PPL",
    "gn:name":"Sabugueiro",
    "gn:population":0,
    "gn:timezone":"America/Sao_Paulo",
    "iso:country":"BR",
    "name:por_x_preferred":[
        "Sabugueiro"
    ],
    "wof:name":"Sabugueiro",
    "wof:placetype":"locality"
},
  "geometry": {"coordinates":[-49.8782,-26.8628],"type":"Point"}
}