{
  "type": "Feature",
  "properties": {
    "gn:admin1_code":"27",
    "gn:admin2_code":"3524600.0",
    "gn:asciiname":"Sitio Santa Cecilia",
    "gn:country_code":"BR",
    "gn:dem":116,
    "gn:feature_class":"P",
    "gn:feature_code":"PPL",
    "gn:name":"S\u00edtio Santa Cecilia",
    "gn:population":0,
    "gn:timezone":"America/Sao_Paulo",
    "iso:country":"BR",
    "name:por_x_preferred":[
        "S\u00edtio Santa Cecilia"
    ],
    "wof:name":"Sitio Santa Cecilia",
    "wof:placetype":"locality"
},
  "geometry": {"coordinates":[-48.0652,-24.8276],"type":"Point"}
}