{
  "type": "Feature",
  "properties": {
    "gn:admin1_code":"26",
    "gn:admin2_code":"4207205.0",
    "gn:asciiname":"Indaial de Cima",
    "gn:country_code":"BR",
    "gn:dem":31,
    "gn:feature_class":"P",
    "gn:feature_code":"PPL",
    "gn:name":"Indaial de Cima",
    "gn:population":0,
    "gn:timezone":"America/Sao_Paulo",
    "iso:country":"BR",
    "wof:name":"Indaial de Cima",
    "wof:placetype":"locality"
},
  "geometry": {"coordinates":[-48.93333,-28.35],"type":"Point"}
}