{
  "type": "Feature",
  "properties": {
    "gn:admin1_code":"13",
    "gn:admin2_code":"2111078.0",
    "gn:asciiname":"Brocos",
    "gn:country_code":"BR",
    "gn:dem":145,
    "gn:feature_class":"P",
    "gn:feature_code":"PPL",
    "gn:name":"Broc\u00f3s",
    "gn:population":0,
    "gn:timezone":"America/Fortaleza",
    "iso:country":"BR",
    "wof:name":"Brocos",
    "wof:placetype":"locality"
},
  "geometry": {"coordinates":[-43.81667,-5.08333],"type":"Point"}
}