{
  "type": "Feature",
  "properties": {
    "gn:admin1_code":"13",
    "gn:admin2_code":"2108603.0",
    "gn:asciiname":"Passe-Bem",
    "gn:country_code":"BR",
    "gn:dem":22,
    "gn:feature_class":"P",
    "gn:feature_code":"PPL",
    "gn:name":"Passe-Bem",
    "gn:population":0,
    "gn:timezone":"America/Fortaleza",
    "iso:country":"BR",
    "wof:name":"Passe-Bem",
    "wof:placetype":"locality"
},
  "geometry": {"coordinates":[-45.21667,-2.46667],"type":"Point"}
}