{
  "type": "Feature",
  "properties": {
    "gn:admin1_code":"5",
    "gn:admin2_code":"2920601.0",
    "gn:asciiname":"Pedrinhas",
    "gn:country_code":"BR",
    "gn:dem":98,
    "gn:feature_class":"P",
    "gn:feature_code":"PPL",
    "gn:name":"Pedrinhas",
    "gn:population":0,
    "gn:timezone":"America/Bahia",
    "iso:country":"BR",
    "name:bpy_x_preferred":[
        "\u09aa\u09c7\u09a1\u09cd\u09b0\u09bf\u09a8\u09b9\u09be\u09b8"
    ],
    "name:ceb_x_preferred":[
        "Pedrinhas"
    ],
    "name:epo_x_preferred":[
        "Pedrinhas"
    ],
    "name:eus_x_preferred":[
        "Pedrinhas"
    ],
    "name:fra_x_preferred":[
        "Pedrinhas"
    ],
    "name:ita_x_preferred":[
        "Pedrinhas"
    ],
    "name:nld_x_preferred":[
        "Pedrinhas"
    ],
    "name:nor_x_preferred":[
        "Pedrinhas"
    ],
    "name:por_x_preferred":[
        "Pedrinhas"
    ],
    "name:ron_x_preferred":[
        "Pedrinhas"
    ],
    "name:rus_x_preferred":[
        "\u041f\u0435\u0434\u0440\u0438\u043d\u044c\u044f\u0441"
    ],
    "name:spa_x_preferred":[
        "Pedrinhas"
    ],
    "name:swe_x_preferred":[
        "Pedrinhas"
    ],
    "name:vie_x_preferred":[
        "Pedrinhas"
    ],
    "name:vol_x_preferred":[
        "Pedrinhas"
    ],
    "name:war_x_preferred":[
        "Pedrinhas"
    ],
    "name:zho_x_preferred":[
        "\u4f69\u5fb7\u91cc\u5c3c\u4e9e\u65af"
    ],
    "wof:name":"Pedrinhas",
    "wof:placetype":"locality"
},
  "geometry": {"coordinates":[-38.93333,-12.76667],"type":"Point"}
}