{
  "type": "Feature",
  "properties": {
    "gn:admin1_code":"18.0",
    "gn:admin2_code":"4112306.0",
    "gn:asciiname":"Sitio Sao Tomas",
    "gn:country_code":"BR",
    "gn:dem":620,
    "gn:feature_class":"P",
    "gn:feature_code":"PPL",
    "gn:name":"S\u00edtio S\u00e3o Tom\u00e1s",
    "gn:population":0,
    "gn:timezone":"America/Sao_Paulo",
    "iso:country":"BR",
    "name:por_x_preferred":[
        "S\u00edtio S\u00e3o Tom\u00e1s"
    ],
    "wof:name":"Sitio Sao Tomas",
    "wof:placetype":"locality"
},
  "geometry": {"coordinates":[-50.18109000000001,-23.76013],"type":"Point"}
}