{
  "type": "Feature",
  "properties": {
    "gn:admin1_code":"6",
    "gn:admin2_code":"2311108.0",
    "gn:asciiname":"Barreiro (4)",
    "gn:country_code":"BR",
    "gn:dem":479,
    "gn:feature_class":"P",
    "gn:feature_code":"PPL",
    "gn:name":"Barreiro (4)",
    "gn:population":0,
    "gn:timezone":"America/Fortaleza",
    "iso:country":"BR",
    "wof:name":"Barreiro (4)",
    "wof:placetype":"locality"
},
  "geometry": {"coordinates":[-39.05,-7.58333],"type":"Point"}
}