{
  "type": "Feature",
  "properties": {
    "gn:admin1_code":"18.0",
    "gn:admin2_code":"4111704.0",
    "gn:asciiname":"Sitio Joao Domingos",
    "gn:country_code":"BR",
    "gn:dem":566,
    "gn:feature_class":"P",
    "gn:feature_code":"PPL",
    "gn:name":"S\u00edtio Jo\u00e3o Domingos",
    "gn:population":0,
    "gn:timezone":"America/Sao_Paulo",
    "iso:country":"BR",
    "name:por_x_preferred":[
        "S\u00edtio Jo\u00e3o Domingos"
    ],
    "wof:name":"Sitio Joao Domingos",
    "wof:placetype":"locality"
},
  "geometry": {"coordinates":[-50.08209,-23.75761],"type":"Point"}
}