{
  "type": "Feature",
  "properties": {
    "gn:admin1_code":"15",
    "gn:admin2_code":"3149150.0",
    "gn:asciiname":"Malhadinho",
    "gn:country_code":"BR",
    "gn:dem":451,
    "gn:feature_class":"P",
    "gn:feature_code":"PPL",
    "gn:name":"Malhadinho",
    "gn:population":0,
    "gn:timezone":"America/Sao_Paulo",
    "iso:country":"BR",
    "wof:name":"Malhadinho",
    "wof:placetype":"locality"
},
  "geometry": {"coordinates":[-44.15,-15.35],"type":"Point"}
}