{
  "type": "Feature",
  "properties": {
    "gn:admin1_code":"22",
    "gn:admin2_code":"2412104.0",
    "gn:asciiname":"Riacho do Cipo",
    "gn:country_code":"BR",
    "gn:dem":205,
    "gn:feature_class":"P",
    "gn:feature_code":"PPL",
    "gn:name":"Riacho do Cipo",
    "gn:population":0,
    "gn:timezone":"America/Fortaleza",
    "iso:country":"BR",
    "wof:name":"Riacho do Cipo",
    "wof:placetype":"locality"
},
  "geometry": {"coordinates":[-37.15,-6.66667],"type":"Point"}
}