{
  "type": "Feature",
  "properties": {
    "gn:admin1_code":"21",
    "gn:admin2_code":"3301009.0",
    "gn:asciiname":"Elesbao",
    "gn:country_code":"BR",
    "gn:dem":68,
    "gn:feature_class":"P",
    "gn:feature_code":"PPL",
    "gn:name":"Elesb\u00e3o",
    "gn:population":0,
    "gn:timezone":"America/Sao_Paulo",
    "iso:country":"BR",
    "name:por_x_preferred":[
        "Elesb\u00e3o"
    ],
    "wof:name":"Elesbao",
    "wof:placetype":"locality"
},
  "geometry": {"coordinates":[-41.65,-21.96667],"type":"Point"}
}