{
  "type": "Feature",
  "properties": {
    "gn:admin1_code":"18",
    "gn:admin2_code":"4110102.0",
    "gn:asciiname":"Lontrao",
    "gn:country_code":"BR",
    "gn:dem":824,
    "gn:feature_class":"P",
    "gn:feature_code":"PPL",
    "gn:name":"Lontr\u00e3o",
    "gn:population":0,
    "gn:timezone":"America/Sao_Paulo",
    "iso:country":"BR",
    "name:por_x_preferred":[
        "Lontr\u00e3o"
    ],
    "wof:name":"Lontrao",
    "wof:placetype":"locality"
},
  "geometry": {"coordinates":[-50.6609,-25.3271],"type":"Point"}
}