{
  "type": "Feature",
  "properties": {
    "gn:admin1_code":"27.0",
    "gn:admin2_code":"3509007.0",
    "gn:asciiname":"Alpes de Caieiras",
    "gn:country_code":"BR",
    "gn:dem":907,
    "gn:feature_class":"P",
    "gn:feature_code":"PPLL",
    "gn:name":"Alpes de Caieiras",
    "gn:population":0,
    "gn:timezone":"America/Sao_Paulo",
    "iso:country":"BR",
    "name:por_x_preferred":[
        "Alpes de Caieiras"
    ],
    "wof:name":"Alpes de Caieiras",
    "wof:placetype":"locality"
},
  "geometry": {"coordinates":[-46.67733,-23.37838],"type":"Point"}
}