{
  "type": "Feature",
  "properties": {
    "gn:admin1_code":"30",
    "gn:admin2_code":"2613909.0",
    "gn:asciiname":"Batalha",
    "gn:country_code":"BR",
    "gn:dem":645,
    "gn:feature_class":"P",
    "gn:feature_code":"PPL",
    "gn:name":"Batalha",
    "gn:population":0,
    "gn:timezone":"America/Recife",
    "iso:country":"BR",
    "name:bre_x_preferred":[
        "Batalha"
    ],
    "name:ceb_x_preferred":[
        "Batalha"
    ],
    "name:deu_x_preferred":[
        "Batalha"
    ],
    "name:fra_x_preferred":[
        "Batalha"
    ],
    "name:ita_x_preferred":[
        "Batalha"
    ],
    "name:nld_x_preferred":[
        "Batalha"
    ],
    "name:nor_x_preferred":[
        "Batalha"
    ],
    "name:por_x_preferred":[
        "Batalha"
    ],
    "name:ron_x_preferred":[
        "Batalha"
    ],
    "name:rus_x_preferred":[
        "\u0411\u0430\u0442\u0430\u043b\u044c\u044f"
    ],
    "name:spa_x_preferred":[
        "Batalha"
    ],
    "name:swe_x_preferred":[
        "Batalha"
    ],
    "name:ukr_x_preferred":[
        "\u0411\u0430\u0442\u0430\u043b\u044f"
    ],
    "name:vie_x_preferred":[
        "Batalha"
    ],
    "name:vol_x_preferred":[
        "Batalha"
    ],
    "wof:name":"Batalha",
    "wof:placetype":"locality"
},
  "geometry": {"coordinates":[-38.38333,-7.83333],"type":"Point"}
}