{
  "type": "Feature",
  "properties": {
    "gn:admin1_code":"15",
    "gn:admin2_code":"3164704.0",
    "gn:asciiname":"Morro Alto",
    "gn:country_code":"BR",
    "gn:dem":896,
    "gn:feature_class":"P",
    "gn:feature_code":"PPL",
    "gn:name":"Morro Alto",
    "gn:population":0,
    "gn:timezone":"America/Sao_Paulo",
    "iso:country":"BR",
    "name:por_x_preferred":[
        "Morro Alto"
    ],
    "wof:name":"Morro Alto",
    "wof:placetype":"locality"
},
  "geometry": {"coordinates":[-47.11667,-20.93333],"type":"Point"}
}