{
  "type": "Feature",
  "properties": {
    "gn:admin1_code":"18.0",
    "gn:admin2_code":"4106209.0",
    "gn:asciiname":"Sitio Sergio J. Leka",
    "gn:country_code":"BR",
    "gn:dem":823,
    "gn:feature_class":"P",
    "gn:feature_code":"PPL",
    "gn:name":"S\u00edtio S\u00e9rgio J. Leka",
    "gn:population":0,
    "gn:timezone":"America/Sao_Paulo",
    "iso:country":"BR",
    "name:por_x_preferred":[
        "S\u00edtio S\u00e9rgio J. Leka"
    ],
    "wof:name":"Sitio Sergio J. Leka",
    "wof:placetype":"locality"
},
  "geometry": {"coordinates":[-49.4847,-25.7884],"type":"Point"}
}