{
  "type": "Feature",
  "properties": {
    "gn:admin1_code":"8",
    "gn:admin2_code":"3203403.0",
    "gn:asciiname":"Pauliceia",
    "gn:country_code":"BR",
    "gn:dem":124,
    "gn:feature_class":"P",
    "gn:feature_code":"PPL",
    "gn:name":"Paulic\u00e9ia",
    "gn:population":0,
    "gn:timezone":"America/Sao_Paulo",
    "iso:country":"BR",
    "name:bpy_x_preferred":[
        "\u09aa\u09be\u0989\u09b2\u09bf\u0995\u09c7\u0987\u09af\u09bc\u09be"
    ],
    "name:ceb_x_preferred":[
        "Paulic\u00e9ia"
    ],
    "name:epo_x_preferred":[
        "Paulic\u00e9ia"
    ],
    "name:eus_x_preferred":[
        "Paulic\u00e9ia"
    ],
    "name:fra_x_preferred":[
        "Paulic\u00e9ia"
    ],
    "name:ita_x_preferred":[
        "Paulic\u00e9ia"
    ],
    "name:kaz_x_preferred":[
        "\u041f\u0430\u0443\u043b\u0438\u0441\u0435\u044f"
    ],
    "name:mlg_x_preferred":[
        "Paulic\u00e9ia"
    ],
    "name:nld_x_preferred":[
        "Paulic\u00e9ia"
    ],
    "name:nor_x_preferred":[
        "Paulic\u00e9ia"
    ],
    "name:pol_x_preferred":[
        "Paulic\u00e9ia"
    ],
    "name:por_x_preferred":[
        "Paulic\u00e9ia"
    ],
    "name:ron_x_preferred":[
        "Paulic\u00e9ia"
    ],
    "name:rus_x_preferred":[
        "\u041f\u0430\u0443\u043b\u0438\u0441\u0435\u044f"
    ],
    "name:spa_x_preferred":[
        "Paulic\u00e9ia"
    ],
    "name:swe_x_preferred":[
        "Paulic\u00e9ia"
    ],
    "name:vie_x_preferred":[
        "Paulic\u00e9ia"
    ],
    "name:vol_x_preferred":[
        "Paulic\u00e9ia"
    ],
    "name:war_x_preferred":[
        "Paulic\u00e9ia"
    ],
    "name:zho_x_preferred":[
        "\u4fdd\u5229\u585e\u4e9a"
    ],
    "wof:name":"Pauliceia",
    "wof:placetype":"locality"
},
  "geometry": {"coordinates":[-41.35,-21.11667000000001],"type":"Point"}
}