{
  "type": "Feature",
  "properties": {
    "iso:country":"BR",
    "name:por_x_preferred":[
        "Educandos"
    ],
    "qs:gn_adm0_cc":"BR",
    "qs:gn_fcode":"PPLX",
    "qs:gn_local":3663517,
    "qs:gn_namadm1":"04",
    "qs:gn_name":"Educandos",
    "qs:local_max":3574,
    "qs:local_sum":8876,
    "qs:localhoods":22,
    "qs:name":"Educandos",
    "qs:name_adm0":"Brasil",
    "qs:name_adm1":"Amazonas",
    "qs:name_adm2":"Manaus",
    "qs:name_local":"Manaus",
    "qs:photo_max":55,
    "qs:photo_sum":278,
    "qs:placetype":"Suburb",
    "qs:quad_count":29,
    "qs:woe_adm0":23424768,
    "qs:woe_adm1":2344847,
    "qs:woe_adm2":12578206,
    "qs:woe_lau":0,
    "qs:woe_local":455833,
    "qs:woe_ver":"7.10.0",
    "wof:lang":[
        "por"
    ],
    "wof:name":"Educandos",
    "wof:placetype":"neighbourhood"
},
  "geometry": {"coordinates":[-60.005955,-3.142184],"type":"Point"}
}