{
  "type": "Feature",
  "properties": {
    "gn:admin1_code":"18.0",
    "gn:admin2_code":"4111704.0",
    "gn:asciiname":"Sitio Devazilio",
    "gn:country_code":"BR",
    "gn:dem":489,
    "gn:feature_class":"P",
    "gn:feature_code":"PPL",
    "gn:name":"S\u00edtio Devaz\u00edlio",
    "gn:population":0,
    "gn:timezone":"America/Sao_Paulo",
    "iso:country":"BR",
    "name:por_x_preferred":[
        "S\u00edtio Devaz\u00edlio"
    ],
    "wof:name":"Sitio Devazilio",
    "wof:placetype":"locality"
},
  "geometry": {"coordinates":[-50.13464000000001,-23.70095],"type":"Point"}
}