{
  "type": "Feature",
  "properties": {
    "gn:admin1_code":"27.0",
    "gn:admin2_code":"3502705.0",
    "gn:asciiname":"Bairro Coreiropolis",
    "gn:country_code":"BR",
    "gn:dem":877,
    "gn:feature_class":"P",
    "gn:feature_code":"PPL",
    "gn:name":"Bairro Coreir\u00f3polis",
    "gn:population":0,
    "gn:timezone":"America/Sao_Paulo",
    "iso:country":"BR",
    "name:por_x_preferred":[
        "Bairro Coreir\u00f3polis"
    ],
    "wof:name":"Bairro Coreiropolis",
    "wof:placetype":"locality"
},
  "geometry": {"coordinates":[-48.83827,-24.52397],"type":"Point"}
}