{
  "type": "Feature",
  "properties": {
    "iso:country":"BR",
    "qs_pg:aaroncc":"BR",
    "qs_pg:name":"Ivoturucaia",
    "qs_pg:name_adm0":"Brasil",
    "qs_pg:name_adm1":"S\u00e3o Paulo",
    "qs_pg:photos":12,
    "qs_pg:photos_1k":2,
    "qs_pg:photos_9k":1,
    "qs_pg:photos_9r":1,
    "qs_pg:photos_all":12,
    "qs_pg:photos_sr":1,
    "qs_pg:pop_sr":0,
    "qs_pg:qs_pg_placetype":"locality",
    "qs_pg:qs_pg_placetype_gp":"Town",
    "qs_pg:woe_adm0":23424768,
    "woe:adm0_id":23424768,
    "woe:name_adm0":"Brasil",
    "woe:name_adm1":"S\u00e3o Paulo",
    "woe:placetype":"Town",
    "wof:name":"Ivoturucaia",
    "wof:placetype":"locality"
},
  "geometry": {"coordinates":[-46.822644,-23.148537],"type":"Point"}
}