{
  "type": "Feature",
  "properties": {
    "gn:admin1_code":"18",
    "gn:admin2_code":"4114302.0",
    "gn:asciiname":"Sitio Joao L. Nico",
    "gn:country_code":"BR",
    "gn:dem":889,
    "gn:feature_class":"P",
    "gn:feature_code":"PPL",
    "gn:name":"S\u00edtio Jo\u00e3o L. Nico",
    "gn:population":0,
    "gn:timezone":"America/Sao_Paulo",
    "iso:country":"BR",
    "name:por_x_preferred":[
        "S\u00edtio Jo\u00e3o L. Nico"
    ],
    "wof:name":"Sitio Joao L. Nico",
    "wof:placetype":"locality"
},
  "geometry": {"coordinates":[-49.21976,-25.87483],"type":"Point"}
}