{
  "type": "Feature",
  "properties": {
    "gn:admin1_code":"30",
    "gn:admin2_code":"2601805.0",
    "gn:asciiname":"Cabeceira",
    "gn:cc2":"BR",
    "gn:country_code":"BR",
    "gn:dem":420,
    "gn:feature_class":"P",
    "gn:feature_code":"PPL",
    "gn:name":"Cabeceira",
    "gn:population":0,
    "gn:timezone":"America/Recife",
    "iso:country":"BR",
    "name:und_x_variant":[
        "Cabaceira",
        "Cabeceira"
    ],
    "wof:name":"Cabeceira",
    "wof:placetype":"locality"
},
  "geometry": {"coordinates":[-38.03333,-8.45],"type":"Point"}
}