{
  "type": "Feature",
  "properties": {
    "gn:admin1_code":"18.0",
    "gn:admin2_code":"4101101.0",
    "gn:asciiname":"Sitio Porto de Moz",
    "gn:country_code":"BR",
    "gn:dem":390,
    "gn:feature_class":"P",
    "gn:feature_code":"PPL",
    "gn:name":"S\u00edtio Porto de Moz",
    "gn:population":0,
    "gn:timezone":"America/Sao_Paulo",
    "iso:country":"BR",
    "name:por_x_preferred":[
        "S\u00edtio Porto de Moz"
    ],
    "wof:name":"Sitio Porto de Moz",
    "wof:placetype":"locality"
},
  "geometry": {"coordinates":[-50.2008,-23.0026],"type":"Point"}
}