{
  "type": "Feature",
  "properties": {
    "gn:admin1_code":"15",
    "gn:admin2_code":"3145208.0",
    "gn:asciiname":"Boa Vista",
    "gn:country_code":"BR",
    "gn:dem":698,
    "gn:feature_class":"P",
    "gn:feature_code":"PPL",
    "gn:name":"Boa Vista",
    "gn:population":0,
    "gn:timezone":"America/Sao_Paulo",
    "iso:country":"BR",
    "name:por_x_preferred":[
        "Boa Vista"
    ],
    "name:und_x_variant":[
        "Boa Visa do Minas"
    ],
    "wof:name":"Boa Vista",
    "wof:placetype":"locality"
},
  "geometry": {"coordinates":[-44.95644,-19.82412],"type":"Point"}
}