{
  "type": "Feature",
  "properties": {
    "gn:admin1_code":"27.0",
    "gn:admin2_code":"3550308.0",
    "gn:asciiname":"Vila Isabel",
    "gn:country_code":"BR",
    "gn:dem":770,
    "gn:feature_class":"P",
    "gn:feature_code":"PPLL",
    "gn:name":"Vila Isabel",
    "gn:population":0,
    "gn:timezone":"America/Sao_Paulo",
    "iso:country":"BR",
    "name:ita_x_preferred":[
        "Vila Isabel"
    ],
    "name:por_x_preferred":[
        "Vila Isabel"
    ],
    "wof:name":"Vila Isabel",
    "wof:placetype":"locality"
},
  "geometry": {"coordinates":[-46.6564,-23.8649],"type":"Point"}
}