{
  "type": "Feature",
  "properties": {
    "gn:admin1_code":"5",
    "gn:admin2_code":"2927200.0",
    "gn:asciiname":"Lagoa do Martins",
    "gn:country_code":"BR",
    "gn:dem":575,
    "gn:feature_class":"P",
    "gn:feature_code":"PPL",
    "gn:name":"Lagoa do Martins",
    "gn:population":0,
    "gn:timezone":"America/Bahia",
    "iso:country":"BR",
    "wof:name":"Lagoa do Martins",
    "wof:placetype":"locality"
},
  "geometry": {"coordinates":[-40.73333,-12.11667],"type":"Point"}
}