{
  "type": "Feature",
  "properties": {
    "gn:admin1_code":"4",
    "gn:admin2_code":"1302207.0",
    "gn:asciiname":"Joanico",
    "gn:country_code":"BR",
    "gn:dem":62,
    "gn:feature_class":"P",
    "gn:feature_code":"PPL",
    "gn:name":"Joanico",
    "gn:population":0,
    "gn:timezone":"America/Manaus",
    "iso:country":"BR",
    "wof:name":"Joanico",
    "wof:placetype":"locality"
},
  "geometry": {"coordinates":[-66.42614,-3.85133],"type":"Point"}
}