{
  "type": "Feature",
  "properties": {
    "gn:admin1_code":"18.0",
    "gn:admin2_code":"4114302.0",
    "gn:asciiname":"Sitio Manoel P. Machado",
    "gn:country_code":"BR",
    "gn:dem":910,
    "gn:feature_class":"P",
    "gn:feature_code":"PPL",
    "gn:name":"S\u00edtio Manoel P. Machado",
    "gn:population":0,
    "gn:timezone":"America/Sao_Paulo",
    "iso:country":"BR",
    "name:por_x_preferred":[
        "S\u00edtio Manoel P. Machado"
    ],
    "wof:name":"Sitio Manoel P. Machado",
    "wof:placetype":"locality"
},
  "geometry": {"coordinates":[-49.3578,-25.8491],"type":"Point"}
}