{
  "type": "Feature",
  "properties": {
    "gn:admin1_code":"20.0",
    "gn:admin2_code":"2201200.0",
    "gn:asciiname":"Barreira do Otavio",
    "gn:country_code":"BR",
    "gn:dem":99,
    "gn:feature_class":"P",
    "gn:feature_code":"PPL",
    "gn:name":"Barreira do Ot\u00e1vio",
    "gn:population":0,
    "gn:timezone":"America/Fortaleza",
    "iso:country":"BR",
    "name:por_x_preferred":[
        "Barreira do Ot\u00e1vio"
    ],
    "wof:name":"Barreira do Otavio",
    "wof:placetype":"locality"
},
  "geometry": {"coordinates":[-42.45427,-4.12409],"type":"Point"}
}