{
  "type": "Feature",
  "properties": {
    "gn:admin1_code":"11",
    "gn:admin2_code":"5006903.0",
    "gn:asciiname":"Santa Eugenia",
    "gn:cc2":"BR",
    "gn:country_code":"BR",
    "gn:dem":212,
    "gn:feature_class":"P",
    "gn:feature_code":"PPL",
    "gn:name":"Santa Eug\u00eania",
    "gn:population":0,
    "gn:timezone":"America/Campo_Grande",
    "iso:country":"BR",
    "name:und_x_variant":[
        "Santa Lugenia",
        "Santa Eug\u00eania"
    ],
    "wof:name":"Santa Eugenia",
    "wof:placetype":"locality"
},
  "geometry": {"coordinates":[-57.05,-21.06667],"type":"Point"}
}