{
  "type": "Feature",
  "properties": {
    "gn:admin1_code":"11",
    "gn:admin2_code":"5006903.0",
    "gn:asciiname":"Carandazal",
    "gn:country_code":"BR",
    "gn:dem":82,
    "gn:feature_class":"P",
    "gn:feature_code":"PPL",
    "gn:name":"Carand\u00e0zal",
    "gn:population":0,
    "gn:timezone":"America/Campo_Grande",
    "iso:country":"BR",
    "wof:name":"Carandazal",
    "wof:placetype":"locality"
},
  "geometry": {"coordinates":[-57.88333000000001,-21.53333],"type":"Point"}
}