{
  "type": "Feature",
  "properties": {
    "gn:admin1_code":"18.0",
    "gn:admin2_code":"4104006.0",
    "gn:asciiname":"Sitio Orides Maciel",
    "gn:country_code":"BR",
    "gn:dem":846,
    "gn:feature_class":"P",
    "gn:feature_code":"PPL",
    "gn:name":"S\u00edtio Orides Maciel",
    "gn:population":0,
    "gn:timezone":"America/Sao_Paulo",
    "iso:country":"BR",
    "name:por_x_preferred":[
        "S\u00edtio Orides Maciel"
    ],
    "wof:name":"Sitio Orides Maciel",
    "wof:placetype":"locality"
},
  "geometry": {"coordinates":[-48.87897,-25.22086],"type":"Point"}
}