{
  "type": "Feature",
  "properties": {
    "gn:admin1_code":"21",
    "gn:admin2_code":"3301108.0",
    "gn:asciiname":"Porto Marinho",
    "gn:country_code":"BR",
    "gn:dem":79,
    "gn:feature_class":"P",
    "gn:feature_code":"PPL",
    "gn:name":"P\u00f4rto Marinho",
    "gn:population":0,
    "gn:timezone":"America/Sao_Paulo",
    "iso:country":"BR",
    "name:por_x_preferred":[
        "P\u00f4rto Marinho"
    ],
    "wof:name":"Porto Marinho",
    "wof:placetype":"locality"
},
  "geometry": {"coordinates":[-42.26667,-21.71667],"type":"Point"}
}