{
  "type": "Feature",
  "properties": {
    "gn:admin1_code":"5",
    "gn:admin2_code":"2932457.0",
    "gn:asciiname":"Rodoleiro",
    "gn:country_code":"BR",
    "gn:dem":828,
    "gn:feature_class":"P",
    "gn:feature_code":"PPL",
    "gn:name":"Rodoleiro",
    "gn:population":0,
    "gn:timezone":"America/Bahia",
    "iso:country":"BR",
    "name:und_x_variant":[
        "Rodeleiro",
        "Rodeieiro",
        "Rodoleiro"
    ],
    "wof:name":"Rodoleiro",
    "wof:placetype":"locality"
},
  "geometry": {"coordinates":[-41.46218,-10.62362],"type":"Point"}
}