{
  "type": "Feature",
  "properties": {
    "gn:admin1_code":"22",
    "gn:admin2_code":"2404309.0",
    "gn:asciiname":"Paus Brancos",
    "gn:country_code":"BR",
    "gn:dem":28,
    "gn:feature_class":"P",
    "gn:feature_code":"PPL",
    "gn:name":"Paus Brancos",
    "gn:population":0,
    "gn:timezone":"America/Fortaleza",
    "iso:country":"BR",
    "wof:name":"Paus Brancos",
    "wof:placetype":"locality"
},
  "geometry": {"coordinates":[-37.47917,-5.37361],"type":"Point"}
}