{
  "type": "Feature",
  "properties": {
    "gn:admin1_code":"30",
    "gn:admin2_code":"2615805.0",
    "gn:asciiname":"Baixa Velha",
    "gn:country_code":"BR",
    "gn:dem":748,
    "gn:feature_class":"P",
    "gn:feature_code":"PPL",
    "gn:name":"Baixa Velha",
    "gn:population":0,
    "gn:timezone":"America/Recife",
    "iso:country":"BR",
    "wof:name":"Baixa Velha",
    "wof:placetype":"locality"
},
  "geometry": {"coordinates":[-37.33333,-8.73333],"type":"Point"}
}