{
  "type": "Feature",
  "properties": {
    "gn:admin1_code":"18.0",
    "gn:admin2_code":"4126678.0",
    "gn:asciiname":"Sitio Joaquim Antonio",
    "gn:country_code":"BR",
    "gn:dem":679,
    "gn:feature_class":"P",
    "gn:feature_code":"PPL",
    "gn:name":"S\u00edtio Joaquim Ant\u00f4nio",
    "gn:population":0,
    "gn:timezone":"America/Sao_Paulo",
    "iso:country":"BR",
    "name:por_x_preferred":[
        "S\u00edtio Joaquim Ant\u00f4nio"
    ],
    "wof:name":"Sitio Joaquim Antonio",
    "wof:placetype":"locality"
},
  "geometry": {"coordinates":[-50.9843,-23.8906],"type":"Point"}
}