{
  "type": "Feature",
  "properties": {
    "gn:admin1_code":"14",
    "gn:admin2_code":"5106828.0",
    "gn:asciiname":"Registro do Jauru",
    "gn:cc2":"BR",
    "gn:country_code":"BR",
    "gn:dem":189,
    "gn:feature_class":"P",
    "gn:feature_code":"PPL",
    "gn:name":"Registro do Jauru",
    "gn:population":0,
    "gn:timezone":"America/Cuiaba",
    "iso:country":"BR",
    "name:und_x_variant":[
        "Registro",
        "Registro do Jauru"
    ],
    "wof:name":"Registro do Jauru",
    "wof:placetype":"locality"
},
  "geometry": {"coordinates":[-58.55,-15.75],"type":"Point"}
}