{
  "type": "Feature",
  "properties": {
    "gn:admin1_code":"18.0",
    "gn:admin2_code":"4114302.0",
    "gn:asciiname":"Sitio Jose Wosniak",
    "gn:country_code":"BR",
    "gn:dem":834,
    "gn:feature_class":"P",
    "gn:feature_code":"PPL",
    "gn:name":"S\u00edtio Jos\u00e9 Wosniak",
    "gn:population":0,
    "gn:timezone":"America/Sao_Paulo",
    "iso:country":"BR",
    "name:por_x_preferred":[
        "S\u00edtio Jos\u00e9 Wosniak"
    ],
    "wof:name":"Sitio Jose Wosniak",
    "wof:placetype":"locality"
},
  "geometry": {"coordinates":[-49.4376,-25.9051],"type":"Point"}
}