{
  "type": "Feature",
  "properties": {
    "gn:admin1_code":"26",
    "gn:admin2_code":"4205100.0",
    "gn:asciiname":"Gustavo Richard",
    "gn:country_code":"BR",
    "gn:dem":406,
    "gn:feature_class":"P",
    "gn:feature_code":"PPL",
    "gn:name":"Gustavo Richard",
    "gn:population":0,
    "gn:timezone":"America/Sao_Paulo",
    "iso:country":"BR",
    "wof:name":"Gustavo Richard",
    "wof:placetype":"locality"
},
  "geometry": {"coordinates":[-49.75,-26.98333],"type":"Point"}
}