{
  "type": "Feature",
  "properties": {
    "gn:admin1_code":"26.0",
    "gn:admin2_code":"4205407.0",
    "gn:asciiname":"Village",
    "gn:country_code":"BR",
    "gn:dem":18,
    "gn:elevation":"3.0",
    "gn:feature_class":"P",
    "gn:feature_code":"PPLL",
    "gn:name":"Village",
    "gn:population":0,
    "gn:timezone":"America/Sao_Paulo",
    "iso:country":"BR",
    "wof:name":"Village",
    "wof:placetype":"locality"
},
  "geometry": {"coordinates":[-48.47528,-27.60674],"type":"Point"}
}