{
  "type": "Feature",
  "properties": {
    "gn:admin1_code":"18.0",
    "gn:admin2_code":"4119202.0",
    "gn:asciiname":"Sitio Nivaldo Nunes",
    "gn:country_code":"BR",
    "gn:dem":877,
    "gn:feature_class":"P",
    "gn:feature_code":"PPL",
    "gn:name":"S\u00edtio Nivaldo Nunes",
    "gn:population":0,
    "gn:timezone":"America/Sao_Paulo",
    "iso:country":"BR",
    "name:por_x_preferred":[
        "S\u00edtio Nivaldo Nunes"
    ],
    "wof:name":"Sitio Nivaldo Nunes",
    "wof:placetype":"locality"
},
  "geometry": {"coordinates":[-50.15016,-23.92968],"type":"Point"}
}