{
  "type": "Feature",
  "properties": {
    "gn:admin1_code":"25",
    "gn:admin2_code":"1400472.0",
    "gn:asciiname":"Acaituba",
    "gn:country_code":"BR",
    "gn:dem":48,
    "gn:feature_class":"P",
    "gn:feature_code":"PPL",
    "gn:name":"A\u00e7aituba",
    "gn:population":0,
    "gn:timezone":"America/Boa_Vista",
    "iso:country":"BR",
    "wof:name":"Acaituba",
    "wof:placetype":"locality"
},
  "geometry": {"coordinates":[-61.55,0.65],"type":"Point"}
}