{
  "type": "Feature",
  "properties": {
    "gn:admin1_code":"4",
    "gn:admin2_code":"1303908.0",
    "gn:asciiname":"Castro Alves",
    "gn:country_code":"BR",
    "gn:dem":72,
    "gn:feature_class":"P",
    "gn:feature_code":"PPL",
    "gn:name":"Castro Alves",
    "gn:population":0,
    "gn:timezone":"America/Manaus",
    "iso:country":"BR",
    "name:ara_x_preferred":[
        "\u0643\u0627\u0633\u062a\u0631\u0648 \u0623\u0644\u0641\u064a\u0633"
    ],
    "name:bul_x_preferred":[
        "\u041a\u0430\u0441\u0442\u0440\u0443 \u0410\u043b\u0432\u0438\u0441"
    ],
    "name:epo_x_preferred":[
        "Castro Alves"
    ],
    "name:fra_x_preferred":[
        "Castro Alves"
    ],
    "name:grn_x_preferred":[
        "Castro Alves"
    ],
    "name:ido_x_preferred":[
        "Castro Alves"
    ],
    "name:ind_x_preferred":[
        "Castro Alves"
    ],
    "name:por_x_preferred":[
        "Castro Alves"
    ],
    "name:rus_x_preferred":[
        "\u041a\u0430\u0441\u0442\u0440\u0443 \u0410\u043b\u0432\u0438\u0441"
    ],
    "wof:name":"Castro Alves",
    "wof:placetype":"locality"
},
  "geometry": {"coordinates":[-68.95,-3.36667],"type":"Point"}
}