{
  "type": "Feature",
  "properties": {
    "gn:admin1_code":"27",
    "gn:admin2_code":"3552205.0",
    "gn:asciiname":"Aden",
    "gn:country_code":"BR",
    "gn:dem":594,
    "gn:feature_class":"P",
    "gn:feature_code":"PPLL",
    "gn:name":"\u00c1den",
    "gn:population":0,
    "gn:timezone":"America/Sao_Paulo",
    "iso:country":"BR",
    "wof:name":"Aden",
    "wof:placetype":"locality"
},
  "geometry": {"coordinates":[-47.40944,-23.41833],"type":"Point"}
}