{
  "type": "Feature",
  "properties": {
    "gn:admin1_code":"17",
    "gn:admin2_code":"2508802.0",
    "gn:asciiname":"Cupiras de Cima",
    "gn:country_code":"BR",
    "gn:dem":312,
    "gn:feature_class":"P",
    "gn:feature_code":"PPL",
    "gn:name":"Cupiras de Cima",
    "gn:population":0,
    "gn:timezone":"America/Fortaleza",
    "iso:country":"BR",
    "wof:name":"Cupiras de Cima",
    "wof:placetype":"locality"
},
  "geometry": {"coordinates":[-37.48333,-6.96667],"type":"Point"}
}