{
  "type": "Feature",
  "properties": {
    "gn:admin1_code":"02",
    "gn:admin2_code":"2704401.0",
    "gn:asciiname":"Murgo",
    "gn:country_code":"BR",
    "gn:dem":210,
    "gn:feature_class":"P",
    "gn:feature_code":"PPL",
    "gn:name":"Murgo",
    "gn:population":0,
    "gn:timezone":"America/Maceio",
    "iso:country":"BR",
    "wof:name":"Murgo",
    "wof:placetype":"locality"
},
  "geometry": {"coordinates":[-36.88333,-9.53333],"type":"Point"}
}