{
  "type": "Feature",
  "properties": {
    "gn:admin1_code":"27",
    "gn:admin2_code":"3514809.0",
    "gn:asciiname":"Pedro Cubas",
    "gn:country_code":"BR",
    "gn:dem":45,
    "gn:feature_class":"P",
    "gn:feature_code":"PPLL",
    "gn:name":"Pedro Cubas",
    "gn:population":0,
    "gn:timezone":"America/Sao_Paulo",
    "iso:country":"BR",
    "name:por_x_preferred":[
        "Pedro Cubas"
    ],
    "wof:name":"Pedro Cubas",
    "wof:placetype":"locality"
},
  "geometry": {"coordinates":[-48.27374,-24.56335],"type":"Point"}
}