{
  "type": "Feature",
  "properties": {
    "gn:admin1_code":"27",
    "gn:admin2_code":"3545209.0",
    "gn:asciiname":"Guarau",
    "gn:country_code":"BR",
    "gn:dem":526,
    "gn:feature_class":"P",
    "gn:feature_code":"PPL",
    "gn:name":"Guara\u00fa",
    "gn:population":0,
    "gn:timezone":"America/Sao_Paulo",
    "iso:country":"BR",
    "name:por_x_preferred":[
        "Guara\u00fa"
    ],
    "wof:name":"Guarau",
    "wof:placetype":"locality"
},
  "geometry": {"coordinates":[-47.31667,-23.21667],"type":"Point"}
}