{
  "type": "Feature",
  "properties": {
    "gn:admin1_code":"18",
    "gn:admin2_code":"4117057.0",
    "gn:asciiname":"Jacutinga",
    "gn:country_code":"BR",
    "gn:dem":853,
    "gn:feature_class":"P",
    "gn:feature_code":"PPL",
    "gn:name":"Jacutinga",
    "gn:population":0,
    "gn:timezone":"America/Sao_Paulo",
    "iso:country":"BR",
    "name:bpy_x_preferred":[
        "\u099c\u09be\u0995\u09c1\u099f\u09bf\u0999\u09cd\u0997\u09be"
    ],
    "name:ceb_x_preferred":[
        "Jacutinga"
    ],
    "name:deu_x_preferred":[
        "Jacutinga"
    ],
    "name:fra_x_preferred":[
        "Jacutinga"
    ],
    "name:hye_x_preferred":[
        "\u053a\u0561\u056f\u0578\u0582\u057f\u056b\u0576\u0563\u0561"
    ],
    "name:ita_x_preferred":[
        "Jacutinga"
    ],
    "name:nld_x_preferred":[
        "Jacutinga"
    ],
    "name:nor_x_preferred":[
        "Jacutinga"
    ],
    "name:pol_x_preferred":[
        "Jacutinga"
    ],
    "name:por_x_preferred":[
        "Jacutinga"
    ],
    "name:rus_x_preferred":[
        "\u0416\u0430\u043a\u0443\u0442\u0438\u043d\u0433\u0430"
    ],
    "name:sco_x_preferred":[
        "Jacutinga"
    ],
    "name:swe_x_preferred":[
        "Jacutinga"
    ],
    "name:vie_x_preferred":[
        "Jacutinga"
    ],
    "name:vol_x_preferred":[
        "Jacutinga"
    ],
    "wof:name":"Jacutinga",
    "wof:placetype":"locality"
},
  "geometry": {"coordinates":[-52.71666999999999,-25.26667],"type":"Point"}
}