{
  "type": "Feature",
  "properties": {
    "gn:admin1_code":"18",
    "gn:admin2_code":"4117057.0",
    "gn:asciiname":"Jacutinga",
    "gn:country_code":"BR",
    "gn:dem":853,
    "gn:feature_class":"P",
    "gn:feature_code":"PPL",
    "gn:name":"Jacutinga",
    "gn:population":0,
    "gn:timezone":"America/Sao_Paulo",
    "iso:country":"BR",
    "wof:name":"Jacutinga",
    "wof:placetype":"locality"
},
  "geometry": {"coordinates":[-52.71666999999999,-25.26667],"type":"Point"}
}