{
  "type": "Feature",
  "properties": {
    "gn:admin1_code":"06",
    "gn:admin2_code":"2308500.0",
    "gn:asciiname":"Morada Nova (2)",
    "gn:country_code":"BR",
    "gn:dem":401,
    "gn:feature_class":"P",
    "gn:feature_code":"PPL",
    "gn:name":"Morada Nova (2)",
    "gn:population":0,
    "gn:timezone":"America/Fortaleza",
    "iso:country":"BR",
    "wof:name":"Morada Nova (2)",
    "wof:placetype":"locality"
},
  "geometry": {"coordinates":[-39.95,-5.66667],"type":"Point"}
}