{
  "type": "Feature",
  "properties": {
    "gn:admin1_code":"14",
    "gn:admin2_code":"5103304.0",
    "gn:asciiname":"Lucaslandia",
    "gn:country_code":"BR",
    "gn:dem":616,
    "gn:feature_class":"P",
    "gn:feature_code":"PPL",
    "gn:name":"Lucasl\u00e2ndia",
    "gn:population":0,
    "gn:timezone":"America/Cuiaba",
    "iso:country":"BR",
    "wof:name":"Lucaslandia",
    "wof:placetype":"locality"
},
  "geometry": {"coordinates":[-59.8625,-13.25417],"type":"Point"}
}