{
  "type": "Feature",
  "properties": {
    "gn:admin1_code":"15.0",
    "gn:admin2_code":"3118007.0",
    "gn:asciiname":"Fellipe Dos Santos",
    "gn:country_code":"BR",
    "gn:dem":901,
    "gn:feature_class":"P",
    "gn:feature_code":"PPL",
    "gn:name":"Fellipe Dos Santos",
    "gn:population":0,
    "gn:timezone":"America/Sao_Paulo",
    "iso:country":"BR",
    "wof:name":"Fellipe Dos Santos",
    "wof:placetype":"locality"
},
  "geometry": {"coordinates":[-43.80112,-20.51639],"type":"Point"}
}