{
  "type": "Feature",
  "properties": {
    "gn:admin1_code":"5.0",
    "gn:admin2_code":"2926004.0",
    "gn:asciiname":"Jatoba",
    "gn:country_code":"BR",
    "gn:dem":418,
    "gn:feature_class":"P",
    "gn:feature_code":"PPL",
    "gn:name":"Jatoba",
    "gn:population":0,
    "gn:timezone":"America/Bahia",
    "iso:country":"BR",
    "name:por_x_preferred":[
        "Jatoba"
    ],
    "wof:name":"Jatoba",
    "wof:placetype":"locality"
},
  "geometry": {"coordinates":[-42.29334,-9.58781],"type":"Point"}
}