{
  "type": "Feature",
  "properties": {
    "gn:admin1_code":"27",
    "gn:admin2_code":"3519709.0",
    "gn:asciiname":"Sitio do Limoeiro",
    "gn:country_code":"BR",
    "gn:dem":925,
    "gn:feature_class":"P",
    "gn:feature_code":"PPL",
    "gn:name":"S\u00edtio do Limoeiro",
    "gn:population":0,
    "gn:timezone":"America/Sao_Paulo",
    "iso:country":"BR",
    "name:por_x_preferred":[
        "S\u00edtio do Limoeiro"
    ],
    "wof:name":"Sitio do Limoeiro",
    "wof:placetype":"locality"
},
  "geometry": {"coordinates":[-47.2058,-23.7979],"type":"Point"}
}