{
  "type": "Feature",
  "properties": {
    "gn:admin1_code":"4",
    "gn:admin2_code":"1302702.0",
    "gn:asciiname":"Restauraco",
    "gn:country_code":"BR",
    "gn:dem":34,
    "gn:feature_class":"P",
    "gn:feature_code":"PPL",
    "gn:name":"Restaura\u00e7o",
    "gn:population":0,
    "gn:timezone":"America/Manaus",
    "iso:country":"BR",
    "wof:name":"Restauraco",
    "wof:placetype":"locality"
},
  "geometry": {"coordinates":[-61.05722,-5.63528],"type":"Point"}
}