{
  "type": "Feature",
  "properties": {
    "gn:admin1_code":"18",
    "gn:admin2_code":"4127601.0",
    "gn:asciiname":"Sitio Julio P. dos Santos",
    "gn:country_code":"BR",
    "gn:dem":920,
    "gn:feature_class":"P",
    "gn:feature_code":"PPL",
    "gn:name":"S\u00edtio J\u00falio P. dos Santos",
    "gn:population":0,
    "gn:timezone":"America/Sao_Paulo",
    "iso:country":"BR",
    "name:por_x_preferred":[
        "S\u00edtio J\u00falio P. dos Santos"
    ],
    "wof:name":"Sitio Julio P. dos Santos",
    "wof:placetype":"locality"
},
  "geometry": {"coordinates":[-49.168,-25.8559],"type":"Point"}
}