{
  "type": "Feature",
  "properties": {
    "gn:admin1_code":"4",
    "gn:admin2_code":"1300201.0",
    "gn:asciiname":"Campina do Norte",
    "gn:country_code":"BR",
    "gn:dem":70,
    "gn:feature_class":"P",
    "gn:feature_code":"PPL",
    "gn:name":"Campina do Norte",
    "gn:population":0,
    "gn:timezone":"America/Eirunepe",
    "iso:country":"BR",
    "wof:name":"Campina do Norte",
    "wof:placetype":"locality"
},
  "geometry": {"coordinates":[-70.685,-4.20556],"type":"Point"}
}