{
  "type": "Feature",
  "properties": {
    "gn:admin1_code":"06",
    "gn:admin2_code":"2302404.0",
    "gn:asciiname":"Fernandes",
    "gn:country_code":"BR",
    "gn:dem":544,
    "gn:feature_class":"P",
    "gn:feature_code":"PPL",
    "gn:name":"Fernandes",
    "gn:population":0,
    "gn:timezone":"America/Fortaleza",
    "iso:country":"BR",
    "name:deu_x_preferred":[
        "Fernandes"
    ],
    "name:lav_x_preferred":[
        "Fernande\u0161s"
    ],
    "name:por_x_preferred":[
        "Fernandes"
    ],
    "name:rus_x_preferred":[
        "\u0424\u0435\u0440\u043d\u0430\u043d\u0434\u0435\u0448"
    ],
    "wof:name":"Fernandes",
    "wof:placetype":"locality"
},
  "geometry": {"coordinates":[-39.85,-4.88333],"type":"Point"}
}