{
  "type": "Feature",
  "properties": {
    "gn:admin1_code":"23",
    "gn:admin2_code":"4309308.0",
    "gn:asciiname":"Vila da Alegria",
    "gn:cc2":"BR",
    "gn:country_code":"BR",
    "gn:dem":50,
    "gn:feature_class":"P",
    "gn:feature_code":"PPL",
    "gn:name":"Vila da Alegria",
    "gn:population":0,
    "gn:timezone":"America/Sao_Paulo",
    "iso:country":"BR",
    "name:und_x_variant":[
        "Alegria",
        "Vila da Alegria"
    ],
    "wof:name":"Vila da Alegria",
    "wof:placetype":"locality"
},
  "geometry": {"coordinates":[-51.31667,-30.11667000000001],"type":"Point"}
}