{
  "type": "Feature",
  "properties": {
    "gn:admin1_code":"18.0",
    "gn:admin2_code":"4107751.0",
    "gn:asciiname":"Sitio Tomas Pratica",
    "gn:country_code":"BR",
    "gn:dem":559,
    "gn:feature_class":"P",
    "gn:feature_code":"PPL",
    "gn:name":"S\u00edtio Tom\u00e1s Pr\u00e1tica",
    "gn:population":0,
    "gn:timezone":"America/Sao_Paulo",
    "iso:country":"BR",
    "name:por_x_preferred":[
        "S\u00edtio Tom\u00e1s Pr\u00e1tica"
    ],
    "wof:name":"Sitio Tomas Pratica",
    "wof:placetype":"locality"
},
  "geometry": {"coordinates":[-50.39803,-23.88665],"type":"Point"}
}