{
  "type": "Feature",
  "properties": {
    "gn:admin1_code":"5",
    "gn:admin2_code":"2917607.0",
    "gn:asciiname":"Baixa Alegre",
    "gn:country_code":"BR",
    "gn:dem":637,
    "gn:feature_class":"P",
    "gn:feature_code":"PPL",
    "gn:name":"Baixa Alegre",
    "gn:population":0,
    "gn:timezone":"America/Bahia",
    "iso:country":"BR",
    "wof:name":"Baixa Alegre",
    "wof:placetype":"locality"
},
  "geometry": {"coordinates":[-40.01667,-13.38333],"type":"Point"}
}