{
  "type": "Feature",
  "properties": {
    "gn:admin1_code":"27.0",
    "gn:admin2_code":"3502903.0",
    "gn:asciiname":"Jundiacanga",
    "gn:country_code":"BR",
    "gn:dem":573,
    "gn:feature_class":"P",
    "gn:feature_code":"PPLL",
    "gn:name":"Jundiacanga",
    "gn:population":0,
    "gn:timezone":"America/Sao_Paulo",
    "iso:country":"BR",
    "name:por_x_preferred":[
        "Jundiacanga"
    ],
    "wof:name":"Jundiacanga",
    "wof:placetype":"locality"
},
  "geometry": {"coordinates":[-47.7056,-23.60516],"type":"Point"}
}