{
  "type": "Feature",
  "properties": {
    "gn:admin1_code":"30",
    "gn:admin2_code":"2612901.0",
    "gn:asciiname":"Dois Irmaos",
    "gn:country_code":"BR",
    "gn:dem":423,
    "gn:feature_class":"P",
    "gn:feature_code":"PPL",
    "gn:name":"Dois Irm\u00e3os",
    "gn:population":0,
    "gn:timezone":"America/Recife",
    "iso:country":"BR",
    "wof:name":"Dois Irmaos",
    "wof:placetype":"locality"
},
  "geometry": {"coordinates":[-35.95,-8.83333],"type":"Point"}
}