{
  "type": "Feature",
  "properties": {
    "gn:admin1_code":"18.0",
    "gn:admin2_code":"4116208.0",
    "gn:asciiname":"Sitio Aristeu R. de Oliveira",
    "gn:country_code":"BR",
    "gn:dem":15,
    "gn:feature_class":"P",
    "gn:feature_code":"PPL",
    "gn:name":"S\u00edtio Aristeu R. de Oliveira",
    "gn:population":0,
    "gn:timezone":"America/Sao_Paulo",
    "iso:country":"BR",
    "name:por_x_preferred":[
        "S\u00edtio Aristeu R. de Oliveira"
    ],
    "wof:name":"Sitio Aristeu R. de Oliveira",
    "wof:placetype":"locality"
},
  "geometry": {"coordinates":[-48.8401,-25.45849],"type":"Point"}
}