{
  "type": "Feature",
  "properties": {
    "gn:admin1_code":"18.0",
    "gn:admin2_code":"4112306.0",
    "gn:asciiname":"Sitio Custodio A. Santos",
    "gn:country_code":"BR",
    "gn:dem":605,
    "gn:feature_class":"P",
    "gn:feature_code":"PPL",
    "gn:name":"S\u00edtio Cust\u00f3dio A. Santos",
    "gn:population":0,
    "gn:timezone":"America/Sao_Paulo",
    "iso:country":"BR",
    "name:por_x_preferred":[
        "S\u00edtio Cust\u00f3dio A. Santos"
    ],
    "wof:name":"Sitio Custodio A. Santos",
    "wof:placetype":"locality"
},
  "geometry": {"coordinates":[-50.13891,-23.75389],"type":"Point"}
}