{
  "type": "Feature",
  "properties": {
    "gn:admin1_code":"26",
    "gn:admin2_code":"4214300.0",
    "gn:asciiname":"Rio Bonito",
    "gn:country_code":"BR",
    "gn:dem":746,
    "gn:feature_class":"P",
    "gn:feature_code":"PPL",
    "gn:name":"Rio Bonito",
    "gn:population":0,
    "gn:timezone":"America/Sao_Paulo",
    "iso:country":"BR",
    "name:ceb_x_preferred":[
        "Rio Bonito"
    ],
    "name:fra_x_preferred":[
        "Rio Bonito"
    ],
    "name:mlg_x_preferred":[
        "Rio Bonito"
    ],
    "name:por_x_preferred":[
        "Rio Bonito"
    ],
    "name:swe_x_preferred":[
        "Rio Bonito"
    ],
    "wof:name":"Rio Bonito",
    "wof:placetype":"locality"
},
  "geometry": {"coordinates":[-49.08333,-27.66667],"type":"Point"}
}