{
  "type": "Feature",
  "properties": {
    "gn:admin1_code":"20",
    "gn:admin2_code":"2202174.0",
    "gn:asciiname":"Gameleira",
    "gn:country_code":"BR",
    "gn:dem":104,
    "gn:feature_class":"P",
    "gn:feature_code":"PPL",
    "gn:name":"Gameleira",
    "gn:population":0,
    "gn:timezone":"America/Fortaleza",
    "iso:country":"BR",
    "wof:name":"Gameleira",
    "wof:placetype":"locality"
},
  "geometry": {"coordinates":[-42.49639000000001,-3.96417],"type":"Point"}
}