{
  "type": "Feature",
  "properties": {
    "gn:admin1_code":"21",
    "gn:admin2_code":"3300100.0",
    "gn:asciiname":"Jucaral",
    "gn:cc2":"BR",
    "gn:country_code":"BR",
    "gn:dem":199,
    "gn:feature_class":"P",
    "gn:feature_code":"PPL",
    "gn:name":"Ju\u00e7aral",
    "gn:population":0,
    "gn:timezone":"America/Sao_Paulo",
    "iso:country":"BR",
    "name:und_x_variant":[
        "Jussaral",
        "Ju\u00e7aral"
    ],
    "wof:name":"Jucaral",
    "wof:placetype":"locality"
},
  "geometry": {"coordinates":[-44.26667,-22.95],"type":"Point"}
}