{
  "type": "Feature",
  "properties": {
    "gn:admin1_code":"14",
    "gn:admin2_code":"5106505.0",
    "gn:asciiname":"Cupim",
    "gn:country_code":"BR",
    "gn:dem":142,
    "gn:feature_class":"P",
    "gn:feature_code":"PPL",
    "gn:name":"Cupim",
    "gn:population":0,
    "gn:timezone":"America/Cuiaba",
    "iso:country":"BR",
    "wof:name":"Cupim",
    "wof:placetype":"locality"
},
  "geometry": {"coordinates":[-56.83333,-16.26667],"type":"Point"}
}