{
  "type": "Feature",
  "properties": {
    "gn:admin1_code":"18",
    "gn:admin2_code":"4100301.0",
    "gn:asciiname":"Sitio Daniel Gornieki",
    "gn:country_code":"BR",
    "gn:dem":843,
    "gn:feature_class":"P",
    "gn:feature_code":"PPL",
    "gn:name":"S\u00edtio Daniel Gornieki",
    "gn:population":0,
    "gn:timezone":"America/Sao_Paulo",
    "iso:country":"BR",
    "name:por_x_preferred":[
        "S\u00edtio Daniel Gornieki"
    ],
    "wof:name":"Sitio Daniel Gornieki",
    "wof:placetype":"locality"
},
  "geometry": {"coordinates":[-49.31100000000001,-26.0726],"type":"Point"}
}