{
  "type": "Feature",
  "properties": {
    "gn:country":"BR",
    "gn:fcode":"PPLL",
    "gn:population":100,
    "iso:country":"BR",
    "qs_pg:aaroncc":"BR",
    "qs_pg:gn_country":"BR",
    "qs_pg:gn_fcode":"PPLL",
    "qs_pg:gn_pop":100,
    "qs_pg:name":"Garimpo Clareira",
    "qs_pg:photos_9r":0,
    "qs_pg:photos_sr":0,
    "qs_pg:pop_sr":1,
    "qs_pg:qs_pg_placetype":"locality",
    "wof:name":"Garimpo Clareira",
    "wof:placetype":"locality",
    "wof:population":100
},
  "geometry": {"coordinates":[-58.4222,-9.17353],"type":"Point"}
}