{
  "type": "Feature",
  "properties": {
    "gn:admin1_code":"8",
    "gn:admin2_code":"3205002.0",
    "gn:asciiname":"Bicanca",
    "gn:country_code":"BR",
    "gn:dem":18,
    "gn:feature_class":"P",
    "gn:feature_code":"PPL",
    "gn:name":"Bicanca",
    "gn:population":0,
    "gn:timezone":"America/Sao_Paulo",
    "iso:country":"BR",
    "name:por_x_preferred":[
        "Bicanca"
    ],
    "wof:name":"Bicanca",
    "wof:placetype":"locality"
},
  "geometry": {"coordinates":[-40.21667,-20.21667],"type":"Point"}
}