{
  "type": "Feature",
  "properties": {
    "iso:country":"BR",
    "name:por_x_preferred":[
        "Veraneio"
    ],
    "qs:gn_adm0_cc":"BR",
    "qs:gn_local":3467747,
    "qs:local_max":946,
    "qs:local_sum":2816,
    "qs:localhoods":12,
    "qs:name":"Veraneio",
    "qs:name_adm0":"Brasil",
    "qs:name_adm1":"Mato Grosso do Sul",
    "qs:name_adm2":"Campo Grande",
    "qs:name_local":"Campo Grande",
    "qs:photo_max":1,
    "qs:photo_sum":2,
    "qs:placetype":"Suburb",
    "qs:quad_count":2,
    "qs:woe_adm0":23424768,
    "qs:woe_adm1":2344853,
    "qs:woe_adm2":12579121,
    "qs:woe_lau":0,
    "qs:woe_local":455849,
    "qs:woe_ver":"7.10.0",
    "wof:lang":[
        "por"
    ],
    "wof:name":"Veraneio",
    "wof:placetype":"neighbourhood"
},
  "geometry": {"coordinates":[-54.525146,-20.437308],"type":"Point"}
}