{
  "type": "Feature",
  "properties": {
    "gn:admin1_code":"20",
    "gn:admin2_code":"2210383.0",
    "gn:asciiname":"Chapada do Acude",
    "gn:country_code":"BR",
    "gn:dem":201,
    "gn:feature_class":"P",
    "gn:feature_code":"PPL",
    "gn:name":"Chapada do Acude",
    "gn:population":0,
    "gn:timezone":"America/Fortaleza",
    "iso:country":"BR",
    "wof:name":"Chapada do Acude",
    "wof:placetype":"locality"
},
  "geometry": {"coordinates":[-42.28333,-5.76667],"type":"Point"}
}