{
  "type": "Feature",
  "properties": {
    "gn:admin1_code":"06",
    "gn:admin2_code":"2304202.0",
    "gn:asciiname":"Fazenda Bonfim",
    "gn:country_code":"BR",
    "gn:dem":915,
    "gn:feature_class":"P",
    "gn:feature_code":"PPL",
    "gn:name":"Fazenda Bonfim",
    "gn:population":0,
    "gn:timezone":"America/Fortaleza",
    "iso:country":"BR",
    "wof:name":"Fazenda Bonfim",
    "wof:placetype":"locality"
},
  "geometry": {"coordinates":[-39.53333,-7.33333],"type":"Point"}
}