{
  "type": "Feature",
  "properties": {
    "gn:admin1_code":"17",
    "gn:admin2_code":"2513307.0",
    "gn:asciiname":"Formigueiro",
    "gn:country_code":"BR",
    "gn:dem":266,
    "gn:feature_class":"P",
    "gn:feature_code":"PPL",
    "gn:name":"Formigueiro",
    "gn:population":0,
    "gn:timezone":"America/Fortaleza",
    "iso:country":"BR",
    "name:bpy_x_preferred":[
        "\u09ab\u09cb\u09b0\u09cd\u09ae\u09bf\u0997\u09c1\u09f1\u09c7\u0987\u09b0\u09cb"
    ],
    "name:ceb_x_preferred":[
        "Formigueiro"
    ],
    "name:epo_x_preferred":[
        "Formigueiro"
    ],
    "name:fra_x_preferred":[
        "Formigueiro"
    ],
    "name:ita_x_preferred":[
        "Formigueiro"
    ],
    "name:kaz_x_preferred":[
        "\u0424\u043e\u0440\u043c\u0438\u0433\u0435\u0439\u0440\u0443"
    ],
    "name:mlg_x_preferred":[
        "Formigueiro"
    ],
    "name:nld_x_preferred":[
        "Formigueiro"
    ],
    "name:nor_x_preferred":[
        "Formigueiro"
    ],
    "name:pol_x_preferred":[
        "Formigueiro"
    ],
    "name:ron_x_preferred":[
        "Formigueiro"
    ],
    "name:rus_x_preferred":[
        "\u0424\u043e\u0440\u043c\u0438\u0433\u0435\u0439\u0440\u0443"
    ],
    "name:spa_x_preferred":[
        "Formigueiro"
    ],
    "name:swe_x_preferred":[
        "Formigueiro"
    ],
    "name:vie_x_preferred":[
        "Formigueiro"
    ],
    "name:vol_x_preferred":[
        "Formigueiro"
    ],
    "name:war_x_preferred":[
        "Formigueiro"
    ],
    "name:zho_x_preferred":[
        "\u798f\u7c73\u76d6\u9c81"
    ],
    "wof:name":"Formigueiro",
    "wof:placetype":"locality"
},
  "geometry": {"coordinates":[-38.55,-6.75],"type":"Point"}
}