{
  "type": "Feature",
  "properties": {
    "gn:admin1_code":"17",
    "gn:admin2_code":"2513307.0",
    "gn:asciiname":"Formigueiro",
    "gn:country_code":"BR",
    "gn:dem":266,
    "gn:feature_class":"P",
    "gn:feature_code":"PPL",
    "gn:name":"Formigueiro",
    "gn:population":0,
    "gn:timezone":"America/Fortaleza",
    "iso:country":"BR",
    "wof:name":"Formigueiro",
    "wof:placetype":"locality"
},
  "geometry": {"coordinates":[-38.55,-6.75],"type":"Point"}
}