{
  "type": "Feature",
  "properties": {
    "gn:admin1_code":"15",
    "gn:admin2_code":"3134004.0",
    "gn:asciiname":"Antonio Dias",
    "gn:country_code":"BR",
    "gn:dem":475,
    "gn:feature_class":"P",
    "gn:feature_code":"PPL",
    "gn:name":"Ant\u00f4nio Dias",
    "gn:population":0,
    "gn:timezone":"America/Sao_Paulo",
    "iso:country":"BR",
    "name:por_x_preferred":[
        "Ant\u00f4nio Dias"
    ],
    "wof:name":"Antonio Dias",
    "wof:placetype":"locality"
},
  "geometry": {"coordinates":[-41.88333,-16.51667],"type":"Point"}
}