{
  "type": "Feature",
  "properties": {
    "gn:admin1_code":"26.0",
    "gn:admin2_code":"4210100.0",
    "gn:asciiname":"Sitio Julio O. Kuiavski",
    "gn:country_code":"BR",
    "gn:dem":869,
    "gn:feature_class":"P",
    "gn:feature_code":"PPL",
    "gn:name":"S\u00edtio J\u00falio O. Kuiavski",
    "gn:population":0,
    "gn:timezone":"America/Sao_Paulo",
    "iso:country":"BR",
    "name:por_x_preferred":[
        "S\u00edtio J\u00falio O. Kuiavski"
    ],
    "wof:name":"Sitio Julio O. Kuiavski",
    "wof:placetype":"locality"
},
  "geometry": {"coordinates":[-49.8674,-26.1796],"type":"Point"}
}