{
  "type": "Feature",
  "properties": {
    "gn:admin1_code":"27.0",
    "gn:admin2_code":"3545308.0",
    "gn:asciiname":"Cafundo",
    "gn:country_code":"BR",
    "gn:dem":611,
    "gn:feature_class":"P",
    "gn:feature_code":"PPLL",
    "gn:name":"Cafund\u00f3",
    "gn:population":0,
    "gn:timezone":"America/Sao_Paulo",
    "iso:country":"BR",
    "name:por_x_preferred":[
        "Cafund\u00f3"
    ],
    "wof:name":"Cafundo",
    "wof:placetype":"locality"
},
  "geometry": {"coordinates":[-47.65642,-23.6678],"type":"Point"}
}