{
  "type": "Feature",
  "properties": {
    "gn:admin1_code":"15",
    "gn:admin2_code":"3159506.0",
    "gn:asciiname":"Aldeiamento",
    "gn:cc2":"BR",
    "gn:country_code":"BR",
    "gn:dem":240,
    "gn:feature_class":"P",
    "gn:feature_code":"PPL",
    "gn:name":"Aldeiamento",
    "gn:population":0,
    "gn:timezone":"America/Sao_Paulo",
    "iso:country":"BR",
    "name:und_x_variant":[
        "Aldeamento",
        "Aldeiamento"
    ],
    "wof:name":"Aldeiamento",
    "wof:placetype":"locality"
},
  "geometry": {"coordinates":[-41.31667,-19.38333],"type":"Point"}
}