{
  "type": "Feature",
  "properties": {
    "gn:admin1_code":"23",
    "gn:admin2_code":"4306601.0",
    "gn:asciiname":"Passo do Alonso",
    "gn:country_code":"BR",
    "gn:dem":179,
    "gn:feature_class":"P",
    "gn:feature_code":"PPL",
    "gn:name":"Passo do Alonso",
    "gn:population":0,
    "gn:timezone":"America/Sao_Paulo",
    "iso:country":"BR",
    "wof:name":"Passo do Alonso",
    "wof:placetype":"locality"
},
  "geometry": {"coordinates":[-54.43333000000001,-31.23333],"type":"Point"}
}