{
  "type": "Feature",
  "properties": {
    "gn:admin1_code":"5",
    "gn:admin2_code":"2925956.0",
    "gn:asciiname":"Ipueira",
    "gn:country_code":"BR",
    "gn:dem":191,
    "gn:feature_class":"P",
    "gn:feature_code":"PPL",
    "gn:name":"Ipueira",
    "gn:population":0,
    "gn:timezone":"America/Bahia",
    "iso:country":"BR",
    "name:bpy_x_preferred":[
        "\u0987\u09aa\u09c1\u09af\u09bc\u09c7\u0987\u09b0\u09be"
    ],
    "name:ceb_x_preferred":[
        "Tinas"
    ],
    "name:epo_x_preferred":[
        "Ipueira"
    ],
    "name:eus_x_preferred":[
        "Ipueira"
    ],
    "name:fra_x_preferred":[
        "Ipueira"
    ],
    "name:ita_x_preferred":[
        "Ipueira"
    ],
    "name:kat_x_preferred":[
        "\u10d8\u10de\u10e3\u10d4\u10d8\u10e0\u10d0"
    ],
    "name:kaz_x_preferred":[
        "\u0418\u043f\u0443\u0435\u0439\u0440\u0430"
    ],
    "name:mlg_x_preferred":[
        "Ipueira"
    ],
    "name:nld_x_preferred":[
        "Ipueira"
    ],
    "name:nor_x_preferred":[
        "Ipueira"
    ],
    "name:por_x_preferred":[
        "Ipueira"
    ],
    "name:ron_x_preferred":[
        "Ipueira"
    ],
    "name:rus_x_preferred":[
        "\u0418\u043f\u0443\u044d\u0439\u0440\u0430"
    ],
    "name:spa_x_preferred":[
        "Ipueira"
    ],
    "name:swe_x_preferred":[
        "Ipueira"
    ],
    "name:vie_x_preferred":[
        "Ipueira"
    ],
    "name:vol_x_preferred":[
        "Ipueira"
    ],
    "name:war_x_preferred":[
        "Ipueira"
    ],
    "name:zho_x_preferred":[
        "\u4f0a\u666e\u57c3\u62c9"
    ],
    "wof:name":"Ipueira",
    "wof:placetype":"locality"
},
  "geometry": {"coordinates":[-39.55,-12.38333],"type":"Point"}
}