{
  "type": "Feature",
  "properties": {
    "gn:admin1_code":"5",
    "gn:admin2_code":"2925956.0",
    "gn:asciiname":"Ipueira",
    "gn:country_code":"BR",
    "gn:dem":191,
    "gn:feature_class":"P",
    "gn:feature_code":"PPL",
    "gn:name":"Ipueira",
    "gn:population":0,
    "gn:timezone":"America/Bahia",
    "iso:country":"BR",
    "wof:name":"Ipueira",
    "wof:placetype":"locality"
},
  "geometry": {"coordinates":[-39.55,-12.38333],"type":"Point"}
}