{
  "type": "Feature",
  "properties": {
    "gn:admin1_code":"14",
    "gn:admin2_code":"5106851.0",
    "gn:asciiname":"Palmeiras",
    "gn:cc2":"BR",
    "gn:country_code":"BR",
    "gn:dem":195,
    "gn:feature_class":"P",
    "gn:feature_code":"PPL",
    "gn:name":"Palmeiras",
    "gn:population":0,
    "gn:timezone":"America/Cuiaba",
    "iso:country":"BR",
    "name:und_x_variant":[
        "Burit\u00ed",
        "Palmeiras"
    ],
    "wof:name":"Palmeiras",
    "wof:placetype":"locality"
},
  "geometry": {"coordinates":[-57.25,-15.65],"type":"Point"}
}