{
  "type": "Feature",
  "properties": {
    "gn:admin1_code":"18.0",
    "gn:admin2_code":"4114302.0",
    "gn:asciiname":"Lagoa dos Perreira",
    "gn:country_code":"BR",
    "gn:dem":871,
    "gn:feature_class":"P",
    "gn:feature_code":"PPL",
    "gn:name":"Lagoa dos Perreira",
    "gn:population":0,
    "gn:timezone":"America/Sao_Paulo",
    "iso:country":"BR",
    "name:por_x_preferred":[
        "Lagoa dos Perreira"
    ],
    "wof:name":"Lagoa dos Perreira",
    "wof:placetype":"locality"
},
  "geometry": {"coordinates":[-49.3262,-25.9373],"type":"Point"}
}