{
  "type": "Feature",
  "properties": {
    "gn:admin1_code":"22",
    "gn:admin2_code":"2414753.0",
    "gn:asciiname":"Padre Cosme",
    "gn:country_code":"BR",
    "gn:dem":588,
    "gn:feature_class":"P",
    "gn:feature_code":"PPL",
    "gn:name":"Padre Cosme",
    "gn:population":0,
    "gn:timezone":"America/Fortaleza",
    "iso:country":"BR",
    "wof:name":"Padre Cosme",
    "wof:placetype":"locality"
},
  "geometry": {"coordinates":[-38.48333,-6.31667],"type":"Point"}
}