{
  "type": "Feature",
  "properties": {
    "gn:admin1_code":"5",
    "gn:admin2_code":"2909208.0",
    "gn:asciiname":"Cafufa",
    "gn:cc2":"BR",
    "gn:country_code":"BR",
    "gn:dem":268,
    "gn:feature_class":"P",
    "gn:feature_code":"PPL",
    "gn:name":"Cafufa",
    "gn:population":0,
    "gn:timezone":"America/Bahia",
    "iso:country":"BR",
    "name:und_x_variant":[
        "Cafut\u00e1",
        "Cafufa"
    ],
    "wof:name":"Cafufa",
    "wof:placetype":"locality"
},
  "geometry": {"coordinates":[-38.03333,-10.23333],"type":"Point"}
}