{
  "type": "Feature",
  "properties": {
    "gn:admin1_code":"18.0",
    "gn:admin2_code":"4101200.0",
    "gn:asciiname":"Sitio Joaquim Cavalcante",
    "gn:country_code":"BR",
    "gn:dem":21,
    "gn:feature_class":"P",
    "gn:feature_code":"PPL",
    "gn:name":"S\u00edtio Joaquim Cavalcante",
    "gn:population":0,
    "gn:timezone":"America/Sao_Paulo",
    "iso:country":"BR",
    "name:por_x_preferred":[
        "S\u00edtio Joaquim Cavalcante"
    ],
    "wof:name":"Sitio Joaquim Cavalcante",
    "wof:placetype":"locality"
},
  "geometry": {"coordinates":[-48.80711,-25.44461],"type":"Point"}
}