{
  "type": "Feature",
  "properties": {
    "gn:admin1_code":"31",
    "gn:admin2_code":"1722081.0",
    "gn:asciiname":"Gameleira",
    "gn:cc2":"BR",
    "gn:country_code":"BR",
    "gn:dem":202,
    "gn:feature_class":"P",
    "gn:feature_code":"PPL",
    "gn:name":"Gameleira",
    "gn:population":0,
    "gn:timezone":"America/Araguaina",
    "iso:country":"BR",
    "name:und_x_variant":[
        "Velame",
        "Gameleira"
    ],
    "wof:name":"Gameleira",
    "wof:placetype":"locality"
},
  "geometry": {"coordinates":[-48.11667,-6.76667],"type":"Point"}
}