{
  "type": "Feature",
  "properties": {
    "gn:admin1_code":"31",
    "gn:admin2_code":"1722081.0",
    "gn:asciiname":"Gameleira",
    "gn:cc2":"BR",
    "gn:country_code":"BR",
    "gn:dem":202,
    "gn:feature_class":"P",
    "gn:feature_code":"PPL",
    "gn:name":"Gameleira",
    "gn:population":0,
    "gn:timezone":"America/Araguaina",
    "iso:country":"BR",
    "name:bpy_x_preferred":[
        "\u0997\u09be\u09ae\u09c7\u09b2\u09af\u09bc\u09c7\u0987\u09b0\u09be"
    ],
    "name:eus_x_preferred":[
        "Gameleira"
    ],
    "name:fra_x_preferred":[
        "Gameleira"
    ],
    "name:ita_x_preferred":[
        "Gameleira"
    ],
    "name:kat_x_preferred":[
        "\u10d2\u10d0\u10db\u10d4\u10da\u10d4\u10d8\u10e0\u10d0"
    ],
    "name:mlg_x_preferred":[
        "Gameleira"
    ],
    "name:nld_x_preferred":[
        "Gameleira"
    ],
    "name:nor_x_preferred":[
        "Gameleira"
    ],
    "name:por_x_preferred":[
        "Gameleira"
    ],
    "name:ron_x_preferred":[
        "Gameleira"
    ],
    "name:rus_x_preferred":[
        "\u0413\u0430\u043c\u0435\u043b\u0435\u0439\u0440\u0430"
    ],
    "name:und_x_variant":[
        "Velame",
        "Gameleira"
    ],
    "name:vie_x_preferred":[
        "Gameleira"
    ],
    "name:vol_x_preferred":[
        "Gameleira"
    ],
    "name:war_x_preferred":[
        "Gameleira"
    ],
    "name:zho_x_preferred":[
        "\u52a0\u6885\u83b1\u62c9"
    ],
    "wof:name":"Gameleira",
    "wof:placetype":"locality"
},
  "geometry": {"coordinates":[-48.11667,-6.76667],"type":"Point"}
}