{
  "type": "Feature",
  "properties": {
    "gn:admin1_code":"06",
    "gn:admin2_code":"2307809.0",
    "gn:asciiname":"Tapera Velha",
    "gn:country_code":"BR",
    "gn:dem":18,
    "gn:feature_class":"P",
    "gn:feature_code":"PPL",
    "gn:name":"Tapera Velha",
    "gn:population":0,
    "gn:timezone":"America/Fortaleza",
    "iso:country":"BR",
    "wof:name":"Tapera Velha",
    "wof:placetype":"locality"
},
  "geometry": {"coordinates":[-40.13333,-3.13333],"type":"Point"}
}