{
  "type": "Feature",
  "properties": {
    "gn:admin1_code":"23",
    "gn:admin2_code":"4308201.0",
    "gn:asciiname":"Americo V Rech",
    "gn:country_code":"BR",
    "gn:dem":750,
    "gn:feature_class":"P",
    "gn:feature_code":"PPLL",
    "gn:name":"Am\u00e9rico V Rech",
    "gn:population":0,
    "gn:timezone":"America/Sao_Paulo",
    "iso:country":"BR",
    "name:por_x_preferred":[
        "Am\u00e9rico V Rech"
    ],
    "wof:name":"Americo V Rech",
    "wof:placetype":"locality"
},
  "geometry": {"coordinates":[-51.1167,-29.0491],"type":"Point"}
}