{
  "type": "Feature",
  "properties": {
    "gn:admin1_code":"17",
    "gn:admin2_code":"2515203.0",
    "gn:asciiname":"Capitao Mor",
    "gn:country_code":"BR",
    "gn:dem":803,
    "gn:feature_class":"P",
    "gn:feature_code":"PPL",
    "gn:name":"Capit\u00e3o Mor",
    "gn:population":0,
    "gn:timezone":"America/Recife",
    "iso:country":"BR",
    "wof:name":"Capitao Mor",
    "wof:placetype":"locality"
},
  "geometry": {"coordinates":[-37.06667,-8.23333],"type":"Point"}
}