{
  "type": "Feature",
  "properties": {
    "gn:admin1_code":"25",
    "gn:admin2_code":"1400027.0",
    "gn:asciiname":"Sao Jeronimo",
    "gn:country_code":"BR",
    "gn:dem":83,
    "gn:feature_class":"P",
    "gn:feature_code":"PPL",
    "gn:name":"S\u00e3o Jer\u00f4nimo",
    "gn:population":0,
    "gn:timezone":"America/Boa_Vista",
    "iso:country":"BR",
    "wof:name":"Sao Jeronimo",
    "wof:placetype":"locality"
},
  "geometry": {"coordinates":[-60.96666999999999,3.68333],"type":"Point"}
}