{
  "type": "Feature",
  "properties": {
    "gn:admin1_code":"27.0",
    "gn:admin2_code":"3554003.0",
    "gn:asciiname":"Turvo",
    "gn:country_code":"BR",
    "gn:dem":577,
    "gn:feature_class":"P",
    "gn:feature_code":"PPL",
    "gn:name":"Turvo",
    "gn:population":0,
    "gn:timezone":"America/Sao_Paulo",
    "iso:country":"BR",
    "name:por_x_preferred":[
        "Turvo"
    ],
    "wof:name":"Turvo",
    "wof:placetype":"locality"
},
  "geometry": {"coordinates":[-47.94993,-23.28133],"type":"Point"}
}