{
  "type": "Feature",
  "properties": {
    "gn:admin1_code":"27.0",
    "gn:admin2_code":"3554003.0",
    "gn:asciiname":"Turvo",
    "gn:country_code":"BR",
    "gn:dem":577,
    "gn:feature_class":"P",
    "gn:feature_code":"PPL",
    "gn:name":"Turvo",
    "gn:population":0,
    "gn:timezone":"America/Sao_Paulo",
    "iso:country":"BR",
    "name:bpy_x_preferred":[
        "\u099f\u09c1\u09b0\u09cd\u09ad\u09cb"
    ],
    "name:ceb_x_preferred":[
        "Turvo"
    ],
    "name:eus_x_preferred":[
        "Turvo"
    ],
    "name:fas_x_preferred":[
        "\u062a\u0648\u0631\u0648\u0648"
    ],
    "name:fra_x_preferred":[
        "Turvo"
    ],
    "name:ina_x_preferred":[
        "Turvo"
    ],
    "name:ita_x_preferred":[
        "Turvo"
    ],
    "name:kat_x_preferred":[
        "\u10e2\u10e3\u10e0\u10d5\u10e3"
    ],
    "name:nld_x_preferred":[
        "Turvo"
    ],
    "name:nor_x_preferred":[
        "Turvo"
    ],
    "name:oci_x_preferred":[
        "Turvo"
    ],
    "name:pol_x_preferred":[
        "Turvo"
    ],
    "name:por_x_preferred":[
        "Turvo"
    ],
    "name:rus_x_preferred":[
        "\u0422\u0443\u0440\u0432\u0443"
    ],
    "name:urd_x_preferred":[
        "\u062a\u0631\u0648\u0648"
    ],
    "name:vol_x_preferred":[
        "Turvo"
    ],
    "name:war_x_preferred":[
        "Turvo"
    ],
    "name:zho_x_preferred":[
        "\u56fe\u5c14\u6b66"
    ],
    "wof:name":"Turvo",
    "wof:placetype":"locality"
},
  "geometry": {"coordinates":[-47.94993,-23.28133],"type":"Point"}
}