{
  "type": "Feature",
  "properties": {
    "gn:admin1_code":"4",
    "gn:admin2_code":"1300631.0",
    "gn:asciiname":"Canaa",
    "gn:country_code":"BR",
    "gn:dem":19,
    "gn:feature_class":"P",
    "gn:feature_code":"PPL",
    "gn:name":"Cana\u00e3",
    "gn:population":0,
    "gn:timezone":"America/Manaus",
    "iso:country":"BR",
    "wof:name":"Canaa",
    "wof:placetype":"locality"
},
  "geometry": {"coordinates":[-60.96471999999999,-4.13472],"type":"Point"}
}