{
  "type": "Feature",
  "properties": {
    "gn:admin1_code":"27.0",
    "gn:admin2_code":"3509007.0",
    "gn:asciiname":"Vila Rosina",
    "gn:country_code":"BR",
    "gn:dem":784,
    "gn:feature_class":"P",
    "gn:feature_code":"PPL",
    "gn:name":"Vila Rosina",
    "gn:population":0,
    "gn:timezone":"America/Sao_Paulo",
    "iso:country":"BR",
    "name:por_x_preferred":[
        "Vila Rosina"
    ],
    "wof:name":"Vila Rosina",
    "wof:placetype":"locality"
},
  "geometry": {"coordinates":[-46.73751,-23.38558],"type":"Point"}
}