{
  "type": "Feature",
  "properties": {
    "gn:admin1_code":"18.0",
    "gn:admin2_code":"4109609.0",
    "gn:asciiname":"Sitio Lacridio Alves",
    "gn:country_code":"BR",
    "gn:dem":82,
    "gn:feature_class":"P",
    "gn:feature_code":"PPL",
    "gn:name":"S\u00edtio Lacr\u00eddio Alves",
    "gn:population":0,
    "gn:timezone":"America/Sao_Paulo",
    "iso:country":"BR",
    "name:por_x_preferred":[
        "S\u00edtio Lacr\u00eddio Alves"
    ],
    "wof:name":"Sitio Lacridio Alves",
    "wof:placetype":"locality"
},
  "geometry": {"coordinates":[-48.7894,-25.6925],"type":"Point"}
}