{
  "type": "Feature",
  "properties": {
    "gn:admin1_code":"13",
    "gn:admin2_code":"2103208.0",
    "gn:asciiname":"Cajui",
    "gn:country_code":"BR",
    "gn:dem":51,
    "gn:feature_class":"P",
    "gn:feature_code":"PPL",
    "gn:name":"Caju\u00ed",
    "gn:population":0,
    "gn:timezone":"America/Fortaleza",
    "iso:country":"BR",
    "wof:name":"Cajui",
    "wof:placetype":"locality"
},
  "geometry": {"coordinates":[-43.45833,-3.71528],"type":"Point"}
}