{
  "type": "Feature",
  "properties": {
    "gn:admin1_code":"16",
    "gn:admin2_code":"1502400.0",
    "gn:asciiname":"Antonio Matos",
    "gn:country_code":"BR",
    "gn:dem":45,
    "gn:feature_class":"P",
    "gn:feature_code":"PPL",
    "gn:name":"Ant\u00f4nio Matos",
    "gn:population":0,
    "gn:timezone":"America/Belem",
    "iso:country":"BR",
    "wof:name":"Antonio Matos",
    "wof:placetype":"locality"
},
  "geometry": {"coordinates":[-47.95423,-1.11207],"type":"Point"}
}