{
  "type": "Feature",
  "properties": {
    "gn:admin1_code":"18.0",
    "gn:admin2_code":"4127601.0",
    "gn:asciiname":"Sitio Joao Soezzeki",
    "gn:country_code":"BR",
    "gn:dem":935,
    "gn:feature_class":"P",
    "gn:feature_code":"PPL",
    "gn:name":"S\u00edtio Jo\u00e3o Soezzeki",
    "gn:population":0,
    "gn:timezone":"America/Sao_Paulo",
    "iso:country":"BR",
    "name:por_x_preferred":[
        "S\u00edtio Jo\u00e3o Soezzeki"
    ],
    "wof:name":"Sitio Joao Soezzeki",
    "wof:placetype":"locality"
},
  "geometry": {"coordinates":[-49.032,-25.9029],"type":"Point"}
}