{
  "type": "Feature",
  "properties": {
    "gn:admin1_code":"22",
    "gn:admin2_code":"2402600.0",
    "gn:asciiname":"Pastorador",
    "gn:country_code":"BR",
    "gn:dem":2,
    "gn:feature_class":"P",
    "gn:feature_code":"PPL",
    "gn:name":"Pastorador",
    "gn:population":0,
    "gn:timezone":"America/Fortaleza",
    "iso:country":"BR",
    "wof:name":"Pastorador",
    "wof:placetype":"locality"
},
  "geometry": {"coordinates":[-35.31667,-5.65],"type":"Point"}
}