{
  "type": "Feature",
  "properties": {
    "gn:admin1_code":"8",
    "gn:admin2_code":"3202405.0",
    "gn:asciiname":"Perocao",
    "gn:country_code":"BR",
    "gn:dem":1,
    "gn:feature_class":"P",
    "gn:feature_code":"PPL",
    "gn:name":"Pero\u00e7\u00e3o",
    "gn:population":0,
    "gn:timezone":"America/Sao_Paulo",
    "iso:country":"BR",
    "name:por_x_preferred":[
        "Pero\u00e7\u00e3o"
    ],
    "wof:name":"Perocao",
    "wof:placetype":"locality"
},
  "geometry": {"coordinates":[-40.42852,-20.59834],"type":"Point"}
}