{
  "type": "Feature",
  "properties": {
    "gn:admin1_code":"27",
    "gn:admin2_code":"3556453.0",
    "gn:asciiname":"Sitio Alecrim",
    "gn:country_code":"BR",
    "gn:dem":919,
    "gn:feature_class":"P",
    "gn:feature_code":"PPL",
    "gn:name":"S\u00edtio Alecrim",
    "gn:population":0,
    "gn:timezone":"America/Sao_Paulo",
    "iso:country":"BR",
    "name:por_x_preferred":[
        "S\u00edtio Alecrim"
    ],
    "wof:name":"Sitio Alecrim",
    "wof:placetype":"locality"
},
  "geometry": {"coordinates":[-47.00721,-23.64968],"type":"Point"}
}