{
  "type": "Feature",
  "properties": {
    "gn:admin1_code":"17",
    "gn:admin2_code":"2514503.0",
    "gn:asciiname":"Sotero",
    "gn:country_code":"BR",
    "gn:dem":750,
    "gn:feature_class":"P",
    "gn:feature_code":"PPL",
    "gn:name":"Sotero",
    "gn:population":0,
    "gn:timezone":"America/Fortaleza",
    "iso:country":"BR",
    "wof:name":"Sotero",
    "wof:placetype":"locality"
},
  "geometry": {"coordinates":[-38.65,-7.18333],"type":"Point"}
}