{
  "type": "Feature",
  "properties": {
    "gn:admin1_code":"23",
    "gn:admin2_code":"4323200.0",
    "gn:asciiname":"Barrinha",
    "gn:country_code":"BR",
    "gn:dem":478,
    "gn:feature_class":"P",
    "gn:feature_code":"PPL",
    "gn:name":"Barrinha",
    "gn:population":0,
    "gn:timezone":"America/Sao_Paulo",
    "iso:country":"BR",
    "wof:name":"Barrinha",
    "wof:placetype":"locality"
},
  "geometry": {"coordinates":[-52.66667,-28.55],"type":"Point"}
}