{
  "type": "Feature",
  "properties": {
    "gn:admin1_code":"04",
    "gn:admin2_code":"1302900.0",
    "gn:asciiname":"Castanhal",
    "gn:country_code":"BR",
    "gn:dem":15,
    "gn:feature_class":"P",
    "gn:feature_code":"PPL",
    "gn:name":"Castanhal",
    "gn:population":0,
    "gn:timezone":"America/Manaus",
    "iso:country":"BR",
    "wof:name":"Castanhal",
    "wof:placetype":"locality"
},
  "geometry": {"coordinates":[-58.15,-3.61667],"type":"Point"}
}