{
  "type": "Feature",
  "properties": {
    "gn:admin1_code":"18.0",
    "gn:admin2_code":"4104006.0",
    "gn:asciiname":"Capivari",
    "gn:country_code":"BR",
    "gn:dem":883,
    "gn:feature_class":"P",
    "gn:feature_code":"PPLL",
    "gn:name":"Capivari",
    "gn:population":0,
    "gn:timezone":"America/Sao_Paulo",
    "iso:country":"BR",
    "name:por_x_preferred":[
        "Capivari"
    ],
    "wof:name":"Capivari",
    "wof:placetype":"locality"
},
  "geometry": {"coordinates":[-48.86146,-25.17027],"type":"Point"}
}