{
  "type": "Feature",
  "properties": {
    "gn:admin1_code":"20",
    "gn:admin2_code":"2209203.0",
    "gn:asciiname":"Cabeceira do Riachao",
    "gn:country_code":"BR",
    "gn:dem":423,
    "gn:feature_class":"P",
    "gn:feature_code":"PPL",
    "gn:name":"Cabeceira do Riach\u00e3o",
    "gn:population":0,
    "gn:timezone":"America/Fortaleza",
    "iso:country":"BR",
    "wof:name":"Cabeceira do Riachao",
    "wof:placetype":"locality"
},
  "geometry": {"coordinates":[-45.72,-9.07139],"type":"Point"}
}