{
  "type": "Feature",
  "properties": {
    "gn:admin1_code":"06",
    "gn:admin2_code":"2307007.0",
    "gn:asciiname":"Lagoa da Salsa",
    "gn:country_code":"BR",
    "gn:dem":129,
    "gn:feature_class":"P",
    "gn:feature_code":"PPL",
    "gn:name":"Lagoa da Salsa",
    "gn:population":0,
    "gn:timezone":"America/Fortaleza",
    "iso:country":"BR",
    "wof:name":"Lagoa da Salsa",
    "wof:placetype":"locality"
},
  "geometry": {"coordinates":[-37.73333,-4.95],"type":"Point"}
}