{
  "type": "Feature",
  "properties": {
    "gn:admin1_code":"06",
    "gn:admin2_code":"2306603.0",
    "gn:asciiname":"Varzea Grande",
    "gn:country_code":"BR",
    "gn:dem":359,
    "gn:feature_class":"P",
    "gn:feature_code":"PPL",
    "gn:name":"V\u00e1rzea Grande",
    "gn:population":0,
    "gn:timezone":"America/Fortaleza",
    "iso:country":"BR",
    "wof:name":"Varzea Grande",
    "wof:placetype":"locality"
},
  "geometry": {"coordinates":[-39.45,-4.71667],"type":"Point"}
}