{
  "type": "Feature",
  "properties": {
    "gn:admin1_code":"14",
    "gn:admin2_code":"5103304.0",
    "gn:asciiname":"Barracao Queimado",
    "gn:country_code":"BR",
    "gn:dem":512,
    "gn:feature_class":"P",
    "gn:feature_code":"PPL",
    "gn:name":"Barrac\u00e3o Queimado",
    "gn:population":0,
    "gn:timezone":"America/Cuiaba",
    "iso:country":"BR",
    "wof:name":"Barracao Queimado",
    "wof:placetype":"locality"
},
  "geometry": {"coordinates":[-59.89583,-13.0875],"type":"Point"}
}