{
  "type": "Feature",
  "properties": {
    "gn:admin1_code":"6",
    "gn:admin2_code":"2300408.0",
    "gn:asciiname":"Alegre",
    "gn:country_code":"BR",
    "gn:dem":518,
    "gn:feature_class":"P",
    "gn:feature_code":"PPL",
    "gn:name":"Alegre",
    "gn:population":0,
    "gn:timezone":"America/Fortaleza",
    "iso:country":"BR",
    "name:cat_x_preferred":[
        "Alegre"
    ],
    "name:ceb_x_preferred":[
        "Alegre"
    ],
    "name:deu_x_preferred":[
        "Alegre"
    ],
    "name:fra_x_preferred":[
        "Alegre"
    ],
    "name:nld_x_preferred":[
        "Alegre"
    ],
    "name:srp_x_preferred":[
        "\u0410\u043b\u0435\u0433\u0440\u0435"
    ],
    "name:swe_x_preferred":[
        "Alegre"
    ],
    "wof:name":"Alegre",
    "wof:placetype":"locality"
},
  "geometry": {"coordinates":[-40.36667,-6.61667],"type":"Point"}
}