{
  "type": "Feature",
  "properties": {
    "gn:admin1_code":"5",
    "gn:admin2_code":"2905909.0",
    "gn:asciiname":"Alto do Bonfim",
    "gn:country_code":"BR",
    "gn:dem":477,
    "gn:feature_class":"P",
    "gn:feature_code":"PPL",
    "gn:name":"Alto do Bonfim",
    "gn:population":0,
    "gn:timezone":"America/Bahia",
    "iso:country":"BR",
    "wof:name":"Alto do Bonfim",
    "wof:placetype":"locality"
},
  "geometry": {"coordinates":[-43.36667,-9.66667],"type":"Point"}
}