{
  "type": "Feature",
  "properties": {
    "gn:admin1_code":"18.0",
    "gn:admin2_code":"4114302.0",
    "gn:asciiname":"Sitio Francisco Zanal",
    "gn:country_code":"BR",
    "gn:dem":921,
    "gn:feature_class":"P",
    "gn:feature_code":"PPL",
    "gn:name":"S\u00edtio Francisco Zanal",
    "gn:population":0,
    "gn:timezone":"America/Sao_Paulo",
    "iso:country":"BR",
    "name:por_x_preferred":[
        "S\u00edtio Francisco Zanal"
    ],
    "wof:name":"Sitio Francisco Zanal",
    "wof:placetype":"locality"
},
  "geometry": {"coordinates":[-49.315,-25.7539],"type":"Point"}
}