{
  "type": "Feature",
  "properties": {
    "gn:admin1_code":"4",
    "gn:admin2_code":"1303304.0",
    "gn:asciiname":"Canuma",
    "gn:country_code":"BR",
    "gn:dem":39,
    "gn:feature_class":"P",
    "gn:feature_code":"PPLL",
    "gn:name":"Canum\u00e3",
    "gn:population":0,
    "gn:timezone":"America/Manaus",
    "iso:country":"BR",
    "name:und_x_variant":[
        "Cunuman",
        "Canum\u00e3"
    ],
    "wof:name":"Canuma",
    "wof:placetype":"locality"
},
  "geometry": {"coordinates":[-60.18949,-6.11793],"type":"Point"}
}