{
  "type": "Feature",
  "properties": {
    "gn:admin1_code":"18",
    "gn:admin2_code":"4109401.0",
    "gn:asciiname":"Gois Artigas",
    "gn:country_code":"BR",
    "gn:dem":1170,
    "gn:feature_class":"P",
    "gn:feature_code":"PPL",
    "gn:name":"G\u00f3is Artigas",
    "gn:population":0,
    "gn:timezone":"America/Sao_Paulo",
    "iso:country":"BR",
    "wof:name":"Gois Artigas",
    "wof:placetype":"locality"
},
  "geometry": {"coordinates":[-51.25,-25.45],"type":"Point"}
}