{
  "type": "Feature",
  "properties": {
    "gn:admin1_code":"18.0",
    "gn:admin2_code":"4125555.0",
    "gn:asciiname":"Sao Manoel",
    "gn:country_code":"BR",
    "gn:dem":409,
    "gn:feature_class":"P",
    "gn:feature_code":"PPL",
    "gn:name":"S\u00e3o Manoel",
    "gn:population":0,
    "gn:timezone":"America/Sao_Paulo",
    "iso:country":"BR",
    "name:por_x_preferred":[
        "S\u00e3o Manoel"
    ],
    "wof:name":"Sao Manoel",
    "wof:placetype":"locality"
},
  "geometry": {"coordinates":[-52.64444,-23.39551],"type":"Point"}
}