{
  "type": "Feature",
  "properties": {
    "gn:admin1_code":"16",
    "gn:admin2_code":"1500503.0",
    "gn:asciiname":"Caicara",
    "gn:country_code":"BR",
    "gn:dem":10,
    "gn:feature_class":"P",
    "gn:feature_code":"PPL",
    "gn:name":"Cai\u00e7ara",
    "gn:population":0,
    "gn:timezone":"America/Belem",
    "iso:country":"BR",
    "name:ceb_x_preferred":[
        "Caicara"
    ],
    "name:deu_x_preferred":[
        "Caicara"
    ],
    "name:fra_x_preferred":[
        "Caicara"
    ],
    "name:ita_x_preferred":[
        "Caicara"
    ],
    "name:nld_x_preferred":[
        "Caicara"
    ],
    "name:spa_x_preferred":[
        "Caicara"
    ],
    "name:swe_x_preferred":[
        "Caicara"
    ],
    "wof:name":"Caicara",
    "wof:placetype":"locality"
},
  "geometry": {"coordinates":[-51.92248,-1.14391],"type":"Point"}
}