{
  "type": "Feature",
  "properties": {
    "iso:country":"BR",
    "name:bpy_x_preferred":[
        "\u0995\u09cb\u09b0\u09cd\u09a1\u09c7\u0987\u09b0\u09cb\u09b8"
    ],
    "name:epo_x_preferred":[
        "Cordeiros"
    ],
    "name:eus_x_preferred":[
        "Cordeiros"
    ],
    "name:fra_x_preferred":[
        "Cordeiros"
    ],
    "name:hye_x_preferred":[
        "\u053f\u0578\u0580\u0564\u0565\u0575\u0580\u0578\u0582\u057d"
    ],
    "name:ita_x_preferred":[
        "Cordeiros"
    ],
    "name:kat_x_preferred":[
        "\u10d9\u10dd\u10e0\u10d4\u10d8\u10d3\u10e3\u10e1\u10d8"
    ],
    "name:kaz_x_preferred":[
        "\u041a\u043e\u0440\u0434\u0435\u0439\u0440\u0443\u0441"
    ],
    "name:mlg_x_preferred":[
        "Cordeiros"
    ],
    "name:nld_x_preferred":[
        "Cordeiros"
    ],
    "name:nor_x_preferred":[
        "Cordeiros"
    ],
    "name:pol_x_preferred":[
        "Cordeiros"
    ],
    "name:por_x_preferred":[
        "Cordeiros"
    ],
    "name:ron_x_preferred":[
        "Cordeiros"
    ],
    "name:rus_x_preferred":[
        "\u041a\u043e\u0440\u0434\u0435\u0439\u0440\u0443\u0441"
    ],
    "name:unk_x_variant":[
        "Cordeiros"
    ],
    "name:vie_x_preferred":[
        "Cordeiros"
    ],
    "name:vol_x_preferred":[
        "Cordeiros"
    ],
    "name:war_x_preferred":[
        "Cordeiros"
    ],
    "name:zho_x_preferred":[
        "\u79d1\u5c14\u4ee3\u9c81\u65af"
    ],
    "qs:gn_adm0_cc":"BR",
    "qs:gn_local":3460845,
    "qs:gn_nam_loc":"Itaja\u00ed, Itaja\u00ed, Santa Catarina, BR",
    "qs:gn_namadm1":"26",
    "qs:local_max":702,
    "qs:local_sum":1194,
    "qs:localhoods":4,
    "qs:name":"Cordeiros",
    "qs:name_adm0":"Brasil",
    "qs:name_adm1":"Santa Catarina",
    "qs:name_adm2":"Itaja\u00ed",
    "qs:name_local":"Itaja\u00ed",
    "qs:photo_max":14,
    "qs:photo_sum":19,
    "qs:placetype":"Suburb",
    "qs:quad_count":5,
    "qs:woe_adm0":23424768,
    "qs:woe_adm1":2344867,
    "qs:woe_adm2":12581685,
    "qs:woe_lau":0,
    "qs:woe_local":455870,
    "qs:woe_ver":"7.10.0",
    "wof:lang":[
        "por"
    ],
    "wof:name":"Cordeiros",
    "wof:placetype":"neighbourhood"
},
  "geometry": {"coordinates":[-48.706006,-26.89745],"type":"Point"}
}