{
  "type": "Feature",
  "properties": {
    "gn:admin1_code":"18.0",
    "gn:admin2_code":"4124707.0",
    "gn:asciiname":"Sitio da Igrejinha",
    "gn:country_code":"BR",
    "gn:dem":692,
    "gn:feature_class":"P",
    "gn:feature_code":"PPL",
    "gn:name":"S\u00edtio da Igrejinha",
    "gn:population":0,
    "gn:timezone":"America/Sao_Paulo",
    "iso:country":"BR",
    "name:por_x_preferred":[
        "S\u00edtio da Igrejinha"
    ],
    "wof:name":"Sitio da Igrejinha",
    "wof:placetype":"locality"
},
  "geometry": {"coordinates":[-50.8626,-23.8395],"type":"Point"}
}