{
  "type": "Feature",
  "properties": {
    "gn:admin1_code":"8",
    "gn:admin2_code":"3200201.0",
    "gn:asciiname":"Fazenda da Mata",
    "gn:country_code":"BR",
    "gn:dem":834,
    "gn:feature_class":"P",
    "gn:feature_code":"PPL",
    "gn:name":"Fazenda da Mata",
    "gn:population":0,
    "gn:timezone":"America/Sao_Paulo",
    "iso:country":"BR",
    "name:por_x_preferred":[
        "Fazenda da Mata"
    ],
    "wof:name":"Fazenda da Mata",
    "wof:placetype":"locality"
},
  "geometry": {"coordinates":[-41.38333,-20.63333],"type":"Point"}
}