{
  "type": "Feature",
  "properties": {
    "gn:admin1_code":"23",
    "gn:admin2_code":"4305108.0",
    "gn:asciiname":"Nossa Senhora Das Gracas",
    "gn:country_code":"BR",
    "gn:dem":764,
    "gn:feature_class":"P",
    "gn:feature_code":"PPLL",
    "gn:name":"Nossa Senhora Das Gra\u00e7as",
    "gn:population":0,
    "gn:timezone":"America/Sao_Paulo",
    "iso:country":"BR",
    "name:por_x_preferred":[
        "Nossa Senhora Das Gra\u00e7as"
    ],
    "wof:name":"Nossa Senhora Das Gracas",
    "wof:placetype":"locality"
},
  "geometry": {"coordinates":[-51.0949,-29.1544],"type":"Point"}
}