{
  "type": "Feature",
  "properties": {
    "gn:admin1_code":"18",
    "gn:admin2_code":"4104105.0",
    "gn:asciiname":"Sitio Hamilton Moreira",
    "gn:country_code":"BR",
    "gn:dem":815,
    "gn:feature_class":"P",
    "gn:feature_code":"PPL",
    "gn:name":"S\u00edtio Hamilton Moreira",
    "gn:population":0,
    "gn:timezone":"America/Sao_Paulo",
    "iso:country":"BR",
    "name:por_x_preferred":[
        "S\u00edtio Hamilton Moreira"
    ],
    "wof:name":"Sitio Hamilton Moreira",
    "wof:placetype":"locality"
},
  "geometry": {"coordinates":[-49.55944,-25.95944],"type":"Point"}
}