{
  "type": "Feature",
  "properties": {
    "gn:admin1_code":"6",
    "gn:admin2_code":"2304350.0",
    "gn:asciiname":"Cachoeira da Moca",
    "gn:country_code":"BR",
    "gn:dem":130,
    "gn:feature_class":"P",
    "gn:feature_code":"PPL",
    "gn:name":"Cachoeira da Mo\u00e7a",
    "gn:population":0,
    "gn:timezone":"America/Fortaleza",
    "iso:country":"BR",
    "wof:name":"Cachoeira da Moca",
    "wof:placetype":"locality"
},
  "geometry": {"coordinates":[-40.15,-3.76667],"type":"Point"}
}