{
  "type": "Feature",
  "properties": {
    "gn:admin1_code":"15",
    "gn:admin2_code":"3141306.0",
    "gn:asciiname":"Ponte Nova",
    "gn:cc2":"BR",
    "gn:country_code":"BR",
    "gn:dem":772,
    "gn:feature_class":"P",
    "gn:feature_code":"PPL",
    "gn:name":"Ponte Nova",
    "gn:population":0,
    "gn:timezone":"America/Sao_Paulo",
    "iso:country":"BR",
    "name:und_x_variant":[
        "Fazenda Ponte Novo",
        "Ponte Nova"
    ],
    "wof:name":"Ponte Nova",
    "wof:placetype":"locality"
},
  "geometry": {"coordinates":[-46.13333,-20.05],"type":"Point"}
}