{
  "type": "Feature",
  "properties": {
    "gn:admin1_code":"06",
    "gn:admin2_code":"2305209.0",
    "gn:asciiname":"Fazenda Carima",
    "gn:country_code":"BR",
    "gn:dem":204,
    "gn:feature_class":"P",
    "gn:feature_code":"PPL",
    "gn:name":"Fazenda Carima",
    "gn:population":0,
    "gn:timezone":"America/Fortaleza",
    "iso:country":"BR",
    "wof:name":"Fazenda Carima",
    "wof:placetype":"locality"
},
  "geometry": {"coordinates":[-40.43333,-4.48333],"type":"Point"}
}