{
  "type": "Feature",
  "properties": {
    "gn:admin1_code":"18",
    "gn:admin2_code":"4103156.0",
    "gn:asciiname":"Sao Sebastiao",
    "gn:country_code":"BR",
    "gn:dem":562,
    "gn:feature_class":"P",
    "gn:feature_code":"PPL",
    "gn:name":"S\u00e3o Sebasti\u00e3o",
    "gn:population":0,
    "gn:timezone":"America/Sao_Paulo",
    "iso:country":"BR",
    "wof:name":"Sao Sebastiao",
    "wof:placetype":"locality"
},
  "geometry": {"coordinates":[-53.58444,-26.18944],"type":"Point"}
}