{
  "type": "Feature",
  "properties": {
    "gn:admin1_code":"15",
    "gn:admin2_code":"3125606.0",
    "gn:asciiname":"Forquilha",
    "gn:country_code":"BR",
    "gn:dem":744,
    "gn:feature_class":"P",
    "gn:feature_code":"PPL",
    "gn:name":"Forquilha",
    "gn:population":0,
    "gn:timezone":"America/Sao_Paulo",
    "iso:country":"BR",
    "name:por_x_preferred":[
        "Forquilha"
    ],
    "wof:name":"Forquilha",
    "wof:placetype":"locality"
},
  "geometry": {"coordinates":[-40.81667,-16.58333],"type":"Point"}
}