{
  "type": "Feature",
  "properties": {
    "gn:admin1_code":"15",
    "gn:admin2_code":"3125606.0",
    "gn:asciiname":"Forquilha",
    "gn:country_code":"BR",
    "gn:dem":744,
    "gn:feature_class":"P",
    "gn:feature_code":"PPL",
    "gn:name":"Forquilha",
    "gn:population":0,
    "gn:timezone":"America/Sao_Paulo",
    "iso:country":"BR",
    "name:bpy_x_preferred":[
        "\u09ab\u09cb\u09b0\u09cd\u0995\u09c1\u0987\u09b2\u09b9\u09be"
    ],
    "name:ceb_x_preferred":[
        "Forquilha"
    ],
    "name:eus_x_preferred":[
        "Forquilha"
    ],
    "name:fra_x_preferred":[
        "Forquilha"
    ],
    "name:ita_x_preferred":[
        "Forquilha"
    ],
    "name:kat_x_preferred":[
        "\u10e4\u10dd\u10e0\u10d9\u10d8\u10da\u10d8\u10d0"
    ],
    "name:kaz_x_preferred":[
        "\u0424\u043e\u0440\u043a\u0438\u043b\u044c\u044f"
    ],
    "name:nld_x_preferred":[
        "Forquilha"
    ],
    "name:nor_x_preferred":[
        "Forquilha"
    ],
    "name:por_x_preferred":[
        "Forquilha"
    ],
    "name:ron_x_preferred":[
        "Forquilha"
    ],
    "name:rus_x_preferred":[
        "\u0424\u043e\u0440\u043a\u0438\u043b\u044c\u044f"
    ],
    "name:swe_x_preferred":[
        "Forquilha"
    ],
    "name:vie_x_preferred":[
        "Forquilha"
    ],
    "name:vol_x_preferred":[
        "Forquilha"
    ],
    "name:war_x_preferred":[
        "Forquilha"
    ],
    "name:zho_x_preferred":[
        "\u798f\u57fa\u5229\u4e9a"
    ],
    "wof:name":"Forquilha",
    "wof:placetype":"locality"
},
  "geometry": {"coordinates":[-40.81667,-16.58333],"type":"Point"}
}