{
  "type": "Feature",
  "properties": {
    "gn:admin1_code":"25",
    "gn:admin2_code":"1400472.0",
    "gn:asciiname":"Catrimani",
    "gn:cc2":"BR",
    "gn:country_code":"BR",
    "gn:dem":44,
    "gn:feature_class":"P",
    "gn:feature_code":"PPL",
    "gn:name":"Catrimani",
    "gn:population":0,
    "gn:timezone":"America/Boa_Vista",
    "iso:country":"BR",
    "name:und_x_variant":[
        "Ilha do Catrimani",
        "Catrimany",
        "Ilha Caratirimani",
        "Catrimani"
    ],
    "wof:name":"Catrimani",
    "wof:placetype":"locality"
},
  "geometry": {"coordinates":[-61.68995,0.434],"type":"Point"}
}