{
  "type": "Feature",
  "properties": {
    "gn:admin1_code":"06",
    "gn:admin2_code":"2311900.0",
    "gn:asciiname":"Santa Clara",
    "gn:country_code":"BR",
    "gn:dem":461,
    "gn:feature_class":"P",
    "gn:feature_code":"PPL",
    "gn:name":"Santa Clara",
    "gn:population":0,
    "gn:timezone":"America/Fortaleza",
    "iso:country":"BR",
    "wof:name":"Santa Clara",
    "wof:placetype":"locality"
},
  "geometry": {"coordinates":[-39.78333,-6.46667],"type":"Point"}
}