{
  "type": "Feature",
  "properties": {
    "gn:admin1_code":"27.0",
    "gn:admin2_code":"3550308.0",
    "gn:asciiname":"Parque Manaca",
    "gn:country_code":"BR",
    "gn:dem":784,
    "gn:feature_class":"P",
    "gn:feature_code":"PPLL",
    "gn:name":"Parque Manaca",
    "gn:population":0,
    "gn:timezone":"America/Sao_Paulo",
    "iso:country":"BR",
    "name:por_x_preferred":[
        "Parque Manaca"
    ],
    "wof:name":"Parque Manaca",
    "wof:placetype":"locality"
},
  "geometry": {"coordinates":[-46.6372,-23.7866],"type":"Point"}
}