{
  "type": "Feature",
  "properties": {
    "gn:admin1_code":"11",
    "gn:admin2_code":"5008008.0",
    "gn:asciiname":"Pedro Celestino",
    "gn:country_code":"BR",
    "gn:dem":281,
    "gn:feature_class":"P",
    "gn:feature_code":"PPL",
    "gn:name":"Pedro Celestino",
    "gn:population":0,
    "gn:timezone":"America/Campo_Grande",
    "iso:country":"BR",
    "wof:name":"Pedro Celestino",
    "wof:placetype":"locality"
},
  "geometry": {"coordinates":[-55.03333000000001,-20.38333],"type":"Point"}
}