{
  "type": "Feature",
  "properties": {
    "gn:admin1_code":"18.0",
    "gn:admin2_code":"4109609.0",
    "gn:asciiname":"Sitio Pedro Grocha",
    "gn:country_code":"BR",
    "gn:dem":241,
    "gn:feature_class":"P",
    "gn:feature_code":"PPL",
    "gn:name":"S\u00edtio Pedro Grocha",
    "gn:population":0,
    "gn:timezone":"America/Sao_Paulo",
    "iso:country":"BR",
    "name:por_x_preferred":[
        "S\u00edtio Pedro Grocha"
    ],
    "wof:name":"Sitio Pedro Grocha",
    "wof:placetype":"locality"
},
  "geometry": {"coordinates":[-48.88499,-25.81107],"type":"Point"}
}