{
  "type": "Feature",
  "properties": {
    "gn:admin1_code":"18.0",
    "gn:admin2_code":"4120705.0",
    "gn:asciiname":"Sitio Ricardo Azzoline",
    "gn:country_code":"BR",
    "gn:dem":706,
    "gn:feature_class":"P",
    "gn:feature_code":"PPL",
    "gn:name":"S\u00edtio Ricardo Azzoline",
    "gn:population":0,
    "gn:timezone":"America/Sao_Paulo",
    "iso:country":"BR",
    "name:por_x_preferred":[
        "S\u00edtio Ricardo Azzoline"
    ],
    "wof:name":"Sitio Ricardo Azzoline",
    "wof:placetype":"locality"
},
  "geometry": {"coordinates":[-49.922,-23.5566],"type":"Point"}
}