{
  "type": "Feature",
  "properties": {
    "gn:admin1_code":"13",
    "gn:admin2_code":"2113009.0",
    "gn:asciiname":"Sao Felix",
    "gn:country_code":"BR",
    "gn:dem":32,
    "gn:feature_class":"P",
    "gn:feature_code":"PPL",
    "gn:name":"S\u00e3o F\u00e9lix",
    "gn:population":0,
    "gn:timezone":"America/Fortaleza",
    "iso:country":"BR",
    "wof:name":"Sao Felix",
    "wof:placetype":"locality"
},
  "geometry": {"coordinates":[-45.36667,-4.25],"type":"Point"}
}