{
  "type": "Feature",
  "properties": {
    "gn:admin1_code":"06",
    "gn:admin2_code":"2300408.0",
    "gn:asciiname":"Cacimbinha",
    "gn:country_code":"BR",
    "gn:dem":551,
    "gn:feature_class":"P",
    "gn:feature_code":"PPL",
    "gn:name":"Cacimbinha",
    "gn:population":0,
    "gn:timezone":"America/Fortaleza",
    "iso:country":"BR",
    "wof:name":"Cacimbinha",
    "wof:placetype":"locality"
},
  "geometry": {"coordinates":[-40.51667,-6.58333],"type":"Point"}
}