{
  "type": "Feature",
  "properties": {
    "gn:admin1_code":"23",
    "gn:admin2_code":"4302709.0",
    "gn:asciiname":"Roque",
    "gn:cc2":"BR",
    "gn:country_code":"BR",
    "gn:dem":244,
    "gn:feature_class":"P",
    "gn:feature_code":"PPL",
    "gn:name":"Roque",
    "gn:population":0,
    "gn:timezone":"America/Sao_Paulo",
    "iso:country":"BR",
    "name:cat_x_preferred":[
        "Roque"
    ],
    "name:ces_x_preferred":[
        "Roque"
    ],
    "name:dan_x_preferred":[
        "Roque"
    ],
    "name:deu_x_preferred":[
        "Roque"
    ],
    "name:fas_x_preferred":[
        "\u0631\u0648\u06a9\u0647"
    ],
    "name:fin_x_preferred":[
        "Roque"
    ],
    "name:fra_x_preferred":[
        "Roque"
    ],
    "name:ita_x_preferred":[
        "Roque"
    ],
    "name:kor_x_preferred":[
        "\ub85c\ud06c"
    ],
    "name:nld_x_preferred":[
        "Roque"
    ],
    "name:nor_x_preferred":[
        "Roque"
    ],
    "name:pol_x_preferred":[
        "Roque"
    ],
    "name:por_x_preferred":[
        "Roque"
    ],
    "name:rus_x_preferred":[
        "\u0420\u043e\u043a\u0435"
    ],
    "name:spa_x_preferred":[
        "Roque"
    ],
    "name:swe_x_preferred":[
        "Krocket#Beskrivning"
    ],
    "name:ukr_x_preferred":[
        "\u0420\u043e\u043a\u043a\u0456"
    ],
    "name:und_x_variant":[
        "S\u00e3o Roque"
    ],
    "wof:name":"Roque",
    "wof:placetype":"locality"
},
  "geometry": {"coordinates":[-52.08333,-30.21667],"type":"Point"}
}