{
  "type": "Feature",
  "properties": {
    "gn:admin1_code":"18",
    "gn:admin2_code":"4119103.0",
    "gn:asciiname":"Sitio Eurides H. dos Santos",
    "gn:country_code":"BR",
    "gn:dem":874,
    "gn:feature_class":"P",
    "gn:feature_code":"PPL",
    "gn:name":"S\u00edtio Eurides H. dos Santos",
    "gn:population":0,
    "gn:timezone":"America/Sao_Paulo",
    "iso:country":"BR",
    "name:por_x_preferred":[
        "S\u00edtio Eurides H. dos Santos"
    ],
    "wof:name":"Sitio Eurides H. dos Santos",
    "wof:placetype":"locality"
},
  "geometry": {"coordinates":[-49.40600000000001,-26.0439],"type":"Point"}
}