{
  "type": "Feature",
  "properties": {
    "gn:admin1_code":"27.0",
    "gn:admin2_code":"3551108.0",
    "gn:asciiname":"Ilha",
    "gn:country_code":"BR",
    "gn:dem":599,
    "gn:feature_class":"P",
    "gn:feature_code":"PPLL",
    "gn:name":"Ilha",
    "gn:population":0,
    "gn:timezone":"America/Sao_Paulo",
    "iso:country":"BR",
    "name:ceb_x_preferred":[
        "Ilha"
    ],
    "name:deu_x_preferred":[
        "Ilha"
    ],
    "name:fra_x_preferred":[
        "Ilha"
    ],
    "name:por_x_preferred":[
        "Ilha"
    ],
    "wof:name":"Ilha",
    "wof:placetype":"locality"
},
  "geometry": {"coordinates":[-47.66114,-23.68826],"type":"Point"}
}