{
  "type": "Feature",
  "properties": {
    "gn:admin1_code":"03",
    "gn:admin2_code":"1600105.0",
    "gn:asciiname":"Porto Franco",
    "gn:country_code":"BR",
    "gn:dem":6,
    "gn:feature_class":"P",
    "gn:feature_code":"PPL",
    "gn:name":"P\u00f4rto Franco",
    "gn:population":0,
    "gn:timezone":"America/Belem",
    "iso:country":"BR",
    "name:bpy_x_preferred":[
        "\u09aa\u09b0\u09cd\u099f\u09cb \u09ab\u09cd\u09b0\u09be\u09a8\u0995\u09cb"
    ],
    "name:ceb_x_preferred":[
        "Porto Franco"
    ],
    "name:eus_x_preferred":[
        "Porto Franco"
    ],
    "name:fra_x_preferred":[
        "Porto Franco"
    ],
    "name:hye_x_preferred":[
        "\u054a\u0578\u0580\u057f\u0578\u0582 \u0556\u0580\u0561\u0576\u056f\u0578\u0582"
    ],
    "name:ita_x_preferred":[
        "Porto Franco"
    ],
    "name:kat_x_preferred":[
        "\u10de\u10dd\u10e0\u10e2\u10e3-\u10e4\u10e0\u10d0\u10dc\u10d9\u10e3"
    ],
    "name:kaz_x_preferred":[
        "\u041f\u043e\u0440\u0442\u0443-\u0424\u0440\u0430\u043d\u043a\u0443"
    ],
    "name:nld_x_preferred":[
        "Porto Franco"
    ],
    "name:nor_x_preferred":[
        "Porto Franco"
    ],
    "name:por_x_preferred":[
        "Porto Franco"
    ],
    "name:ron_x_preferred":[
        "Porto Franco"
    ],
    "name:rus_x_preferred":[
        "\u041f\u043e\u0440\u0442\u0443-\u0424\u0440\u0430\u043d\u043a\u0443"
    ],
    "name:swe_x_preferred":[
        "Porto Franco"
    ],
    "name:vie_x_preferred":[
        "Porto Franco"
    ],
    "name:vol_x_preferred":[
        "Porto Franco"
    ],
    "name:war_x_preferred":[
        "Porto Franco"
    ],
    "name:zho_x_preferred":[
        "\u4f5b\u6717\u54e5\u6e2f"
    ],
    "wof:name":"Porto Franco",
    "wof:placetype":"locality"
},
  "geometry": {"coordinates":[-50.78333,1.88333],"type":"Point"}
}