{
  "type": "Feature",
  "properties": {
    "gn:admin1_code":"27",
    "gn:admin2_code":"3546702.0",
    "gn:asciiname":"Pascom",
    "gn:country_code":"BR",
    "gn:dem":587,
    "gn:feature_class":"P",
    "gn:feature_code":"PPL",
    "gn:name":"Pascom",
    "gn:population":0,
    "gn:timezone":"America/Sao_Paulo",
    "iso:country":"BR",
    "name:por_x_preferred":[
        "Pascom"
    ],
    "wof:name":"Pascom",
    "wof:placetype":"locality"
},
  "geometry": {"coordinates":[-47.55,-22.45],"type":"Point"}
}