{
  "type": "Feature",
  "properties": {
    "gn:admin1_code":"27.0",
    "gn:admin2_code":"3509254.0",
    "gn:asciiname":"Rio Azeite",
    "gn:country_code":"BR",
    "gn:dem":62,
    "gn:feature_class":"P",
    "gn:feature_code":"PPL",
    "gn:name":"Rio Azeite",
    "gn:population":0,
    "gn:timezone":"America/Sao_Paulo",
    "iso:country":"BR",
    "name:por_x_preferred":[
        "Rio Azeite"
    ],
    "wof:name":"Rio Azeite",
    "wof:placetype":"locality"
},
  "geometry": {"coordinates":[-48.1743,-24.7865],"type":"Point"}
}