{
  "type": "Feature",
  "properties": {
    "gn:admin1_code":"5",
    "gn:admin2_code":"2907103.0",
    "gn:asciiname":"Toca",
    "gn:country_code":"BR",
    "gn:dem":458,
    "gn:feature_class":"P",
    "gn:feature_code":"PPL",
    "gn:name":"Toca",
    "gn:population":0,
    "gn:timezone":"America/Bahia",
    "iso:country":"BR",
    "name:ceb_x_preferred":[
        "Toca"
    ],
    "name:fra_x_preferred":[
        "Toca"
    ],
    "name:por_x_preferred":[
        "Toca"
    ],
    "name:spa_x_preferred":[
        "Toca"
    ],
    "name:swe_x_preferred":[
        "Toca"
    ],
    "wof:name":"Toca",
    "wof:placetype":"locality"
},
  "geometry": {"coordinates":[-43.66667,-13.98333],"type":"Point"}
}