{
  "type": "Feature",
  "properties": {
    "gn:admin1_code":"5",
    "gn:admin2_code":"2919504.0",
    "gn:asciiname":"Lagoa da Pedra",
    "gn:country_code":"BR",
    "gn:dem":452,
    "gn:feature_class":"P",
    "gn:feature_code":"PPL",
    "gn:name":"Lagoa da Pedra",
    "gn:population":0,
    "gn:timezone":"America/Bahia",
    "iso:country":"BR",
    "wof:name":"Lagoa da Pedra",
    "wof:placetype":"locality"
},
  "geometry": {"coordinates":[-41.85,-13.96667],"type":"Point"}
}