{
  "type": "Feature",
  "properties": {
    "gn:admin1_code":"5",
    "gn:admin2_code":"2904506.0",
    "gn:asciiname":"Santana do Ouro",
    "gn:country_code":"BR",
    "gn:dem":801,
    "gn:feature_class":"P",
    "gn:feature_code":"PPL",
    "gn:name":"Santana do Ouro",
    "gn:population":0,
    "gn:timezone":"America/Bahia",
    "iso:country":"BR",
    "wof:name":"Santana do Ouro",
    "wof:placetype":"locality"
},
  "geometry": {"coordinates":[-42.48333,-12.01667],"type":"Point"}
}