{
  "type": "Feature",
  "properties": {
    "gn:admin1_code":"27",
    "gn:admin2_code":"3541307.0",
    "gn:asciiname":"Porto Velho",
    "gn:country_code":"BR",
    "gn:dem":276,
    "gn:feature_class":"P",
    "gn:feature_code":"PPL",
    "gn:name":"P\u00f4rto Velho",
    "gn:population":0,
    "gn:timezone":"America/Sao_Paulo",
    "iso:country":"BR",
    "wof:name":"Porto Velho",
    "wof:placetype":"locality"
},
  "geometry": {"coordinates":[-52.16667,-21.83333],"type":"Point"}
}