{
  "type": "Feature",
  "properties": {
    "gn:gn_country":"BR",
    "gn:gn_fcode":"PPL",
    "gn:gn_pop":0,
    "iso:country":"BR",
    "qs_pg:aaroncc":"BR",
    "qs_pg:gn_country":"BR",
    "qs_pg:gn_fcode":"PPL",
    "qs_pg:gn_pop":0,
    "qs_pg:name":"Bom Jardim",
    "qs_pg:name_adm0":"Brasil",
    "qs_pg:name_adm1":"Rio Grande do Norte",
    "qs_pg:photos":3,
    "qs_pg:photos_1k":1,
    "qs_pg:photos_9k":1,
    "qs_pg:photos_9r":1,
    "qs_pg:photos_all":3,
    "qs_pg:photos_sr":1,
    "qs_pg:pop_sr":0,
    "qs_pg:qs_pg_placetype":"neighbourhood",
    "qs_pg:qs_pg_placetype_gp":"Suburb",
    "qs_pg:woe_adm0":23424768,
    "woe:adm0_id":23424768,
    "woe:name_adm0":"Brasil",
    "woe:name_adm1":"Rio Grande do Norte",
    "woe:placetype":"Suburb",
    "wof:name":"Bom Jardim",
    "wof:placetype":"neighbourhood"
},
  "geometry": {"coordinates":[-38.15611,-5.72389],"type":"Point"}
}