{
  "type": "Feature",
  "properties": {
    "gn:admin1_code":"26",
    "gn:admin2_code":"4210100.0",
    "gn:asciiname":"Sitio Anisio Carvalho",
    "gn:country_code":"BR",
    "gn:dem":918,
    "gn:feature_class":"P",
    "gn:feature_code":"PPL",
    "gn:name":"S\u00edtio An\u00edsio Carvalho",
    "gn:population":0,
    "gn:timezone":"America/Sao_Paulo",
    "iso:country":"BR",
    "name:por_x_preferred":[
        "S\u00edtio An\u00edsio Carvalho"
    ],
    "wof:name":"Sitio Anisio Carvalho",
    "wof:placetype":"locality"
},
  "geometry": {"coordinates":[-49.9304,-26.237],"type":"Point"}
}