{
  "type": "Feature",
  "properties": {
    "gn:admin1_code":"28",
    "gn:admin2_code":"2801207.0",
    "gn:asciiname":"Pedra Preta",
    "gn:country_code":"BR",
    "gn:dem":140,
    "gn:feature_class":"P",
    "gn:feature_code":"PPL",
    "gn:name":"Pedra Preta",
    "gn:population":0,
    "gn:timezone":"America/Maceio",
    "iso:country":"BR",
    "wof:name":"Pedra Preta",
    "wof:placetype":"locality"
},
  "geometry": {"coordinates":[-37.83333,-9.61667],"type":"Point"}
}