{
  "type": "Feature",
  "properties": {
    "gn:admin1_code":"28",
    "gn:admin2_code":"2801207.0",
    "gn:asciiname":"Pedra Preta",
    "gn:country_code":"BR",
    "gn:dem":140,
    "gn:feature_class":"P",
    "gn:feature_code":"PPL",
    "gn:name":"Pedra Preta",
    "gn:population":0,
    "gn:timezone":"America/Maceio",
    "iso:country":"BR",
    "name:bpy_x_preferred":[
        "\u09aa\u09c7\u09a1\u09cd\u09b0\u09be \u09aa\u09cd\u09b0\u09c7\u099f\u09be"
    ],
    "name:eus_x_preferred":[
        "Pedra Preta"
    ],
    "name:fra_x_preferred":[
        "Pedra Preta"
    ],
    "name:hye_x_preferred":[
        "\u054a\u0565\u0564\u0580\u0561 \u054a\u0580\u0565\u057f\u0561"
    ],
    "name:ita_x_preferred":[
        "Pedra Preta"
    ],
    "name:kat_x_preferred":[
        "\u10de\u10d4\u10d3\u10e0\u10d0-\u10de\u10e0\u10d4\u10e2\u10d0"
    ],
    "name:nld_x_preferred":[
        "Pedra Preta"
    ],
    "name:nor_x_preferred":[
        "Pedra Preta"
    ],
    "name:pol_x_preferred":[
        "Pedra Preta"
    ],
    "name:por_x_preferred":[
        "Pedra Preta"
    ],
    "name:ron_x_preferred":[
        "Pedra Preta"
    ],
    "name:rus_x_preferred":[
        "\u041f\u0435\u0434\u0440\u0430-\u041f\u0440\u0435\u0442\u0430"
    ],
    "name:spa_x_preferred":[
        "Pedra Preta"
    ],
    "name:vie_x_preferred":[
        "Pedra Preta"
    ],
    "name:vol_x_preferred":[
        "Pedra Preta"
    ],
    "name:war_x_preferred":[
        "Pedra Preta"
    ],
    "name:zho_x_preferred":[
        "\u4f69\u5fb7\u62c9\u666e\u96f7\u5854"
    ],
    "wof:name":"Pedra Preta",
    "wof:placetype":"locality"
},
  "geometry": {"coordinates":[-37.83333,-9.61667],"type":"Point"}
}