{
  "type": "Feature",
  "properties": {
    "gn:admin1_code":"2",
    "gn:admin2_code":"2708006.0",
    "gn:asciiname":"Barroso",
    "gn:country_code":"BR",
    "gn:dem":271,
    "gn:feature_class":"P",
    "gn:feature_code":"PPL",
    "gn:name":"Barroso",
    "gn:population":0,
    "gn:timezone":"America/Maceio",
    "iso:country":"BR",
    "name:ceb_x_preferred":[
        "Barroso"
    ],
    "name:ces_x_preferred":[
        "Barroso"
    ],
    "name:deu_x_preferred":[
        "Barroso"
    ],
    "name:epo_x_preferred":[
        "Barroso"
    ],
    "name:fra_x_preferred":[
        "Barroso"
    ],
    "name:glg_x_preferred":[
        "Barroso"
    ],
    "name:ita_x_preferred":[
        "Barroso"
    ],
    "name:kaz_x_preferred":[
        "\u0411\u0430\u0440\u0440\u043e\u0437\u0443"
    ],
    "name:nld_x_preferred":[
        "Barroso"
    ],
    "name:por_x_preferred":[
        "Barroso"
    ],
    "name:ron_x_preferred":[
        "Barroso"
    ],
    "name:rus_x_preferred":[
        "\u0411\u0430\u0440\u0440\u043e\u0437\u0443"
    ],
    "name:slv_x_preferred":[
        "Barroso"
    ],
    "name:swe_x_preferred":[
        "Barroso"
    ],
    "wof:name":"Barroso",
    "wof:placetype":"locality"
},
  "geometry": {"coordinates":[-37.23333,-9.36667],"type":"Point"}
}