{
  "type": "Feature",
  "properties": {
    "gn:admin1_code":"27",
    "gn:admin2_code":"3527207.0",
    "gn:asciiname":"Cocho",
    "gn:country_code":"BR",
    "gn:dem":956,
    "gn:elevation":"0.0",
    "gn:feature_class":"P",
    "gn:feature_code":"PPLL",
    "gn:name":"Cocho",
    "gn:population":0,
    "gn:timezone":"America/Sao_Paulo",
    "iso:country":"BR",
    "name:por_x_preferred":[
        "Cocho"
    ],
    "wof:name":"Cocho",
    "wof:placetype":"locality"
},
  "geometry": {"coordinates":[-45.00611,-22.91295],"type":"Point"}
}