{
  "type": "Feature",
  "properties": {
    "gn:admin1_code":"18.0",
    "gn:admin2_code":"4113205.0",
    "gn:asciiname":"Sitio Faxinal dos Correas",
    "gn:country_code":"BR",
    "gn:dem":997,
    "gn:feature_class":"P",
    "gn:feature_code":"PPL",
    "gn:name":"S\u00edtio Faxinal dos Corr\u00eaas",
    "gn:population":0,
    "gn:timezone":"America/Sao_Paulo",
    "iso:country":"BR",
    "name:por_x_preferred":[
        "S\u00edtio Faxinal dos Corr\u00eaas"
    ],
    "wof:name":"Sitio Faxinal dos Correas",
    "wof:placetype":"locality"
},
  "geometry": {"coordinates":[-49.8991,-25.7088],"type":"Point"}
}