{
  "type": "Feature",
  "properties": {
    "gn:admin1_code":"25",
    "gn:admin2_code":"1400050.0",
    "gn:asciiname":"Mel",
    "gn:country_code":"BR",
    "gn:dem":92,
    "gn:feature_class":"P",
    "gn:feature_code":"PPL",
    "gn:name":"Mel",
    "gn:population":0,
    "gn:timezone":"America/Boa_Vista",
    "iso:country":"BR",
    "wof:name":"Mel",
    "wof:placetype":"locality"
},
  "geometry": {"coordinates":[-61.06667,3.01667],"type":"Point"}
}