{
  "type": "Feature",
  "properties": {
    "gn:admin1_code":"27",
    "gn:admin2_code":"3554508.0",
    "gn:asciiname":"Sao Roque",
    "gn:country_code":"BR",
    "gn:dem":523,
    "gn:feature_class":"P",
    "gn:feature_code":"PPLL",
    "gn:name":"S\u00e3o Roque",
    "gn:population":0,
    "gn:timezone":"America/Sao_Paulo",
    "iso:country":"BR",
    "name:por_x_preferred":[
        "S\u00e3o Roque"
    ],
    "wof:name":"Sao Roque",
    "wof:placetype":"locality"
},
  "geometry": {"coordinates":[-47.71866,-23.12219],"type":"Point"}
}