{
  "type": "Feature",
  "properties": {
    "gn:admin1_code":"13",
    "gn:admin2_code":"2100956.0",
    "gn:asciiname":"Buriti Torto",
    "gn:country_code":"BR",
    "gn:dem":155,
    "gn:feature_class":"P",
    "gn:feature_code":"PPL",
    "gn:name":"Buriti Torto",
    "gn:population":0,
    "gn:timezone":"America/Fortaleza",
    "iso:country":"BR",
    "wof:name":"Buriti Torto",
    "wof:placetype":"locality"
},
  "geometry": {"coordinates":[-46.01667,-5.28333],"type":"Point"}
}