{
  "type": "Feature",
  "properties": {
    "gn:admin1_code":"27.0",
    "gn:admin2_code":"3516408.0",
    "gn:asciiname":"Bairro Jardim Casa Grande",
    "gn:country_code":"BR",
    "gn:dem":783,
    "gn:feature_class":"P",
    "gn:feature_code":"PPL",
    "gn:name":"Bairro Jardim Casa Grande",
    "gn:population":0,
    "gn:timezone":"America/Sao_Paulo",
    "iso:country":"BR",
    "name:por_x_preferred":[
        "Bairro Jardim Casa Grande"
    ],
    "wof:name":"Bairro Jardim Casa Grande",
    "wof:placetype":"locality"
},
  "geometry": {"coordinates":[-46.74703,-23.30339],"type":"Point"}
}