{
  "type": "Feature",
  "properties": {
    "gn:admin1_code":"27.0",
    "gn:admin2_code":"3500758.0",
    "gn:asciiname":"Barra",
    "gn:country_code":"BR",
    "gn:dem":574,
    "gn:feature_class":"P",
    "gn:feature_code":"PPLL",
    "gn:name":"Barra",
    "gn:population":0,
    "gn:timezone":"America/Sao_Paulo",
    "iso:country":"BR",
    "name:bre_x_preferred":[
        "Barraigh"
    ],
    "name:ces_x_preferred":[
        "Barra"
    ],
    "name:cym_x_preferred":[
        "Barraigh"
    ],
    "name:deu_x_preferred":[
        "Barra"
    ],
    "name:ell_x_preferred":[
        "\u039c\u03c0\u03ac\u03c1\u03b1"
    ],
    "name:epo_x_preferred":[
        "Barra"
    ],
    "name:eus_x_preferred":[
        "Barra"
    ],
    "name:fin_x_preferred":[
        "Barra"
    ],
    "name:fra_x_preferred":[
        "Barra"
    ],
    "name:gla_x_preferred":[
        "Barraigh"
    ],
    "name:gle_x_preferred":[
        "Barraigh"
    ],
    "name:hun_x_preferred":[
        "Barra"
    ],
    "name:isl_x_preferred":[
        "Barrey"
    ],
    "name:jpn_x_preferred":[
        "\u30d0\u30e9\u5cf6"
    ],
    "name:lit_x_preferred":[
        "Bara"
    ],
    "name:nld_x_preferred":[
        "Barra"
    ],
    "name:nno_x_preferred":[
        "Barra"
    ],
    "name:nor_x_preferred":[
        "Barra"
    ],
    "name:pol_x_preferred":[
        "Barra"
    ],
    "name:por_x_preferred":[
        "Barra"
    ],
    "name:rus_x_preferred":[
        "\u0411\u0430\u0440\u0440\u0430"
    ],
    "name:spa_x_preferred":[
        "Barra"
    ],
    "name:srp_x_preferred":[
        "\u0411\u0430\u0440\u0430"
    ],
    "name:swe_x_preferred":[
        "Barra"
    ],
    "name:vie_x_preferred":[
        "Barra"
    ],
    "name:zho_x_preferred":[
        "\u5df4\u62c9\u5c9b"
    ],
    "wof:name":"Barra",
    "wof:placetype":"locality"
},
  "geometry": {"coordinates":[-47.81509000000001,-23.49871],"type":"Point"}
}