{
  "type": "Feature",
  "properties": {
    "gn:admin1_code":"27.0",
    "gn:admin2_code":"3550308.0",
    "gn:asciiname":"Vila Ede",
    "gn:country_code":"BR",
    "gn:dem":783,
    "gn:feature_class":"P",
    "gn:feature_code":"PPL",
    "gn:name":"Vila Ede",
    "gn:population":0,
    "gn:timezone":"America/Sao_Paulo",
    "iso:country":"BR",
    "name:por_x_preferred":[
        "Vila Ede"
    ],
    "wof:name":"Vila Ede",
    "wof:placetype":"locality"
},
  "geometry": {"coordinates":[-46.5934,-23.49119],"type":"Point"}
}