{
  "type": "Feature",
  "properties": {
    "gn:admin1_code":"22",
    "gn:admin2_code":"2404606.0",
    "gn:asciiname":"Riacho da Telha",
    "gn:country_code":"BR",
    "gn:dem":85,
    "gn:feature_class":"P",
    "gn:feature_code":"PPL",
    "gn:name":"Riacho da Telha",
    "gn:population":0,
    "gn:timezone":"America/Fortaleza",
    "iso:country":"BR",
    "wof:name":"Riacho da Telha",
    "wof:placetype":"locality"
},
  "geometry": {"coordinates":[-35.61667,-5.81667],"type":"Point"}
}