{
  "type": "Feature",
  "properties": {
    "gn:admin1_code":"30",
    "gn:admin2_code":"2614105.0",
    "gn:asciiname":"Feliciano",
    "gn:country_code":"BR",
    "gn:dem":606,
    "gn:feature_class":"P",
    "gn:feature_code":"PPL",
    "gn:name":"Feliciano",
    "gn:population":0,
    "gn:timezone":"America/Recife",
    "iso:country":"BR",
    "name:ceb_x_preferred":[
        "Feliciano"
    ],
    "name:deu_x_preferred":[
        "Feliciano"
    ],
    "name:fra_x_preferred":[
        "Feliciano"
    ],
    "name:jpn_x_preferred":[
        "\u30d5\u30a7\u30ea\u30b7\u30a2\u30fc\u30ce"
    ],
    "name:rus_x_preferred":[
        "\u0424\u0435\u043b\u0438\u0441\u0438\u0430\u043d\u043e"
    ],
    "name:spa_x_preferred":[
        "Feliciano"
    ],
    "name:swe_x_preferred":[
        "Feliciano"
    ],
    "wof:name":"Feliciano",
    "wof:placetype":"locality"
},
  "geometry": {"coordinates":[-37.25,-8.16667],"type":"Point"}
}