{
  "type": "Feature",
  "properties": {
    "gn:admin1_code":"30",
    "gn:admin2_code":"2614105.0",
    "gn:asciiname":"Feliciano",
    "gn:country_code":"BR",
    "gn:dem":606,
    "gn:feature_class":"P",
    "gn:feature_code":"PPL",
    "gn:name":"Feliciano",
    "gn:population":0,
    "gn:timezone":"America/Recife",
    "iso:country":"BR",
    "wof:name":"Feliciano",
    "wof:placetype":"locality"
},
  "geometry": {"coordinates":[-37.25,-8.16667],"type":"Point"}
}