{
  "type": "Feature",
  "properties": {
    "gn:admin1_code":"06",
    "gn:admin2_code":"2304350.0",
    "gn:asciiname":"Martinica",
    "gn:country_code":"BR",
    "gn:dem":109,
    "gn:feature_class":"P",
    "gn:feature_code":"PPL",
    "gn:name":"Martinica",
    "gn:population":0,
    "gn:timezone":"America/Fortaleza",
    "iso:country":"BR",
    "wof:name":"Martinica",
    "wof:placetype":"locality"
},
  "geometry": {"coordinates":[-40.23333,-3.83333],"type":"Point"}
}