{
  "type": "Feature",
  "properties": {
    "gn:admin1_code":"06",
    "gn:admin2_code":"2313302.0",
    "gn:asciiname":"Sao Joao (3)",
    "gn:country_code":"BR",
    "gn:dem":463,
    "gn:feature_class":"P",
    "gn:feature_code":"PPL",
    "gn:name":"S\u00e3o Jo\u00e3o (3)",
    "gn:population":0,
    "gn:timezone":"America/Fortaleza",
    "iso:country":"BR",
    "wof:name":"Sao Joao (3)",
    "wof:placetype":"locality"
},
  "geometry": {"coordinates":[-40.46667,-5.88333],"type":"Point"}
}