{
  "type": "Feature",
  "properties": {
    "gn:admin1_code":"20",
    "gn:admin2_code":"2211308.0",
    "gn:asciiname":"Pau d'Arco",
    "gn:country_code":"BR",
    "gn:dem":207,
    "gn:feature_class":"P",
    "gn:feature_code":"PPL",
    "gn:name":"Pau d\u2019Arco",
    "gn:population":0,
    "gn:timezone":"America/Fortaleza",
    "iso:country":"BR",
    "name:ceb_x_preferred":[
        "Pau d'Arco"
    ],
    "name:fra_x_preferred":[
        "Pau d'Arco"
    ],
    "name:ita_x_preferred":[
        "Pau d'Arco"
    ],
    "name:kaz_x_preferred":[
        "\u041f\u0430\u0443-\u0434\u2019\u0410\u0440\u043a\u0443"
    ],
    "name:nld_x_preferred":[
        "Pau-d'Arco"
    ],
    "name:nor_x_preferred":[
        "Pau d'Arco"
    ],
    "name:por_x_preferred":[
        "Pau-d'Arco"
    ],
    "name:rus_x_preferred":[
        "\u041f\u0430\u0443-\u0434\u2019\u0410\u0440\u043a\u0443"
    ],
    "name:spa_x_preferred":[
        "Pau d'Arco"
    ],
    "name:swe_x_preferred":[
        "Pau d'Arco"
    ],
    "name:vie_x_preferred":[
        "Pau d'Arco"
    ],
    "name:vol_x_preferred":[
        "Pau d'Arco"
    ],
    "name:war_x_preferred":[
        "Pau d'Arco"
    ],
    "wof:name":"Pau d'Arco",
    "wof:placetype":"locality"
},
  "geometry": {"coordinates":[-41.86667,-6.25],"type":"Point"}
}