{
  "type": "Feature",
  "properties": {
    "gn:admin1_code":"26.0",
    "gn:admin2_code":"4210100.0",
    "gn:asciiname":"Sitio Nicolau Peichisis",
    "gn:country_code":"BR",
    "gn:dem":841,
    "gn:feature_class":"P",
    "gn:feature_code":"PPL",
    "gn:name":"S\u00edtio Nicolau Peichisis",
    "gn:population":0,
    "gn:timezone":"America/Sao_Paulo",
    "iso:country":"BR",
    "name:por_x_preferred":[
        "S\u00edtio Nicolau Peichisis"
    ],
    "wof:name":"Sitio Nicolau Peichisis",
    "wof:placetype":"locality"
},
  "geometry": {"coordinates":[-49.9699,-26.0939],"type":"Point"}
}