{
  "type": "Feature",
  "properties": {
    "gn:admin1_code":"18.0",
    "gn:admin2_code":"4109708.0",
    "gn:asciiname":"Sitio Benedito Onesio e Noel",
    "gn:country_code":"BR",
    "gn:dem":647,
    "gn:feature_class":"P",
    "gn:feature_code":"PPL",
    "gn:name":"S\u00edtio Benedito On\u00e9sio e Noel",
    "gn:population":0,
    "gn:timezone":"America/Sao_Paulo",
    "iso:country":"BR",
    "name:por_x_preferred":[
        "S\u00edtio Benedito On\u00e9sio e Noel"
    ],
    "wof:name":"Sitio Benedito Onesio e Noel",
    "wof:placetype":"locality"
},
  "geometry": {"coordinates":[-50.27704,-23.88309],"type":"Point"}
}