{
  "type": "Feature",
  "properties": {
    "gn:admin1_code":"13",
    "gn:admin2_code":"2110237.0",
    "gn:asciiname":"Canto Sujo",
    "gn:country_code":"BR",
    "gn:dem":47,
    "gn:feature_class":"P",
    "gn:feature_code":"PPL",
    "gn:name":"Canto Sujo",
    "gn:population":0,
    "gn:timezone":"America/Fortaleza",
    "iso:country":"BR",
    "wof:name":"Canto Sujo",
    "wof:placetype":"locality"
},
  "geometry": {"coordinates":[-42.54472,-3.16056],"type":"Point"}
}