{
  "type": "Feature",
  "properties": {
    "gn:admin1_code":"26",
    "gn:admin2_code":"4218707.0",
    "gn:asciiname":"Guarda",
    "gn:country_code":"BR",
    "gn:dem":28,
    "gn:feature_class":"P",
    "gn:feature_code":"PPL",
    "gn:name":"Guarda",
    "gn:population":0,
    "gn:timezone":"America/Sao_Paulo",
    "iso:country":"BR",
    "name:arg_x_preferred":[
        "Guarda"
    ],
    "name:ben_x_preferred":[
        "\u0997\u09c1\u09df\u09be\u09b0\u09cd\u09a6\u09be"
    ],
    "name:bre_x_preferred":[
        "Guarda"
    ],
    "name:cat_x_preferred":[
        "Guarda"
    ],
    "name:ceb_x_preferred":[
        "Guarda"
    ],
    "name:deu_x_preferred":[
        "Guarda"
    ],
    "name:ell_x_preferred":[
        "\u0393\u03ba\u03bf\u03c5\u03ac\u03c1\u03bd\u03c4\u03b1"
    ],
    "name:epo_x_preferred":[
        "Guarda"
    ],
    "name:fra_x_preferred":[
        "Guarda"
    ],
    "name:glg_x_preferred":[
        "Guarda"
    ],
    "name:heb_x_preferred":[
        "\u05d2\u05d0\u05e8\u05d3\u05d4"
    ],
    "name:hin_x_preferred":[
        "\u0917\u0941\u0906\u0930\u094d\u0921\u093e"
    ],
    "name:hun_x_preferred":[
        "Guarda"
    ],
    "name:ind_x_preferred":[
        "Guarda"
    ],
    "name:ita_x_preferred":[
        "Guarda"
    ],
    "name:msa_x_preferred":[
        "Guarda"
    ],
    "name:nld_x_preferred":[
        "Guarda"
    ],
    "name:nno_x_preferred":[
        "Guarda"
    ],
    "name:pnb_x_preferred":[
        "\u06af\u0648\u0622\u0631\u062f\u0627"
    ],
    "name:pol_x_preferred":[
        "Guarda"
    ],
    "name:por_x_preferred":[
        "Guarda"
    ],
    "name:sco_x_preferred":[
        "Guarda"
    ],
    "name:slk_x_preferred":[
        "Guarda"
    ],
    "name:spa_x_preferred":[
        "Guarda"
    ],
    "name:srp_x_preferred":[
        "Gvarda"
    ],
    "name:swe_x_preferred":[
        "Guarda"
    ],
    "name:ukr_x_preferred":[
        "\u0413\u0443\u0430\u0440\u0434\u0430"
    ],
    "name:vie_x_preferred":[
        "Guarda"
    ],
    "name:vol_x_preferred":[
        "Guarda"
    ],
    "name:war_x_preferred":[
        "Guarda"
    ],
    "wof:name":"Guarda",
    "wof:placetype":"locality"
},
  "geometry": {"coordinates":[-49.08333,-28.45],"type":"Point"}
}