{
  "type": "Feature",
  "properties": {
    "gn:admin1_code":"4",
    "gn:admin2_code":"1302801.0",
    "gn:asciiname":"Floresta",
    "gn:country_code":"BR",
    "gn:dem":56,
    "gn:feature_class":"P",
    "gn:feature_code":"PPL",
    "gn:name":"Floresta",
    "gn:population":0,
    "gn:timezone":"America/Manaus",
    "iso:country":"BR",
    "name:bel_x_preferred":[
        "\u0424\u043b\u0430\u0440\u044d\u0441\u0442\u0430"
    ],
    "name:cat_x_preferred":[
        "Floresta"
    ],
    "name:ceb_x_preferred":[
        "Floresta"
    ],
    "name:deu_x_preferred":[
        "Floresta"
    ],
    "name:fra_x_preferred":[
        "Floresta"
    ],
    "name:ita_x_preferred":[
        "Floresta"
    ],
    "name:jpn_x_preferred":[
        "\u30d5\u30ed\u30ec\u30b9\u30bf"
    ],
    "name:nld_x_preferred":[
        "Floresta"
    ],
    "name:nor_x_preferred":[
        "Floresta"
    ],
    "name:por_x_preferred":[
        "Floresta"
    ],
    "name:ron_x_preferred":[
        "Floresta"
    ],
    "name:rus_x_preferred":[
        "\u0424\u043b\u043e\u0440\u0435\u0441\u0442\u0430"
    ],
    "name:spa_x_preferred":[
        "Floresta"
    ],
    "name:srp_x_preferred":[
        "\u0424\u043b\u043e\u0440\u0435\u0441\u0442\u0430"
    ],
    "name:swe_x_preferred":[
        "Floresta"
    ],
    "name:vol_x_preferred":[
        "Floresta"
    ],
    "name:war_x_preferred":[
        "Floresta"
    ],
    "wof:name":"Floresta",
    "wof:placetype":"locality"
},
  "geometry": {"coordinates":[-65.95953,-1.75009],"type":"Point"}
}