{
  "type": "Feature",
  "properties": {
    "gn:admin1_code":"13",
    "gn:admin2_code":"2112001.0",
    "gn:asciiname":"Zelandia",
    "gn:country_code":"BR",
    "gn:dem":254,
    "gn:feature_class":"P",
    "gn:feature_code":"PPL",
    "gn:name":"Zel\u00e2ndia",
    "gn:population":0,
    "gn:timezone":"America/Fortaleza",
    "iso:country":"BR",
    "name:und_x_variant":[
        "Porto de Zelandia",
        "Zel\u00e2ndia"
    ],
    "wof:name":"Zelandia",
    "wof:placetype":"locality"
},
  "geometry": {"coordinates":[-45.7643,-8.54858],"type":"Point"}
}