{
  "type": "Feature",
  "properties": {
    "gn:admin1_code":"6",
    "gn:admin2_code":"2313302.0",
    "gn:asciiname":"Araca",
    "gn:country_code":"BR",
    "gn:dem":463,
    "gn:feature_class":"P",
    "gn:feature_code":"PPL",
    "gn:name":"Ara\u00e7a",
    "gn:population":0,
    "gn:timezone":"America/Fortaleza",
    "iso:country":"BR",
    "wof:name":"Araca",
    "wof:placetype":"locality"
},
  "geometry": {"coordinates":[-40.56667,-5.86667],"type":"Point"}
}