{
  "type": "Feature",
  "properties": {
    "gn:admin1_code":"13",
    "gn:admin2_code":"2106409.0",
    "gn:asciiname":"Santa Elvira",
    "gn:country_code":"BR",
    "gn:dem":64,
    "gn:feature_class":"P",
    "gn:feature_code":"PPL",
    "gn:name":"Santa Elvira",
    "gn:population":0,
    "gn:timezone":"America/Fortaleza",
    "iso:country":"BR",
    "wof:name":"Santa Elvira",
    "wof:placetype":"locality"
},
  "geometry": {"coordinates":[-43.32,-3.63167],"type":"Point"}
}