{
  "type": "Feature",
  "properties": {
    "gn:admin1_code":"27.0",
    "gn:admin2_code":"3545308.0",
    "gn:asciiname":"Barros",
    "gn:country_code":"BR",
    "gn:dem":695,
    "gn:feature_class":"P",
    "gn:feature_code":"PPLL",
    "gn:name":"Barros",
    "gn:population":0,
    "gn:timezone":"America/Sao_Paulo",
    "iso:country":"BR",
    "name:por_x_preferred":[
        "Barros"
    ],
    "wof:name":"Barros",
    "wof:placetype":"locality"
},
  "geometry": {"coordinates":[-47.6138,-23.7378],"type":"Point"}
}