{
  "type": "Feature",
  "properties": {
    "gn:admin1_code":"18.0",
    "gn:admin2_code":"4114302.0",
    "gn:asciiname":"Sitio Angelino A. de Lima",
    "gn:country_code":"BR",
    "gn:dem":919,
    "gn:feature_class":"P",
    "gn:feature_code":"PPL",
    "gn:name":"S\u00edtio Angelino A. de Lima",
    "gn:population":0,
    "gn:timezone":"America/Sao_Paulo",
    "iso:country":"BR",
    "name:por_x_preferred":[
        "S\u00edtio Angelino A. de Lima"
    ],
    "wof:name":"Sitio Angelino A. de Lima",
    "wof:placetype":"locality"
},
  "geometry": {"coordinates":[-49.2712,-25.9159],"type":"Point"}
}