{
  "type": "Feature",
  "properties": {
    "gn:admin1_code":"13",
    "gn:admin2_code":"2102101.0",
    "gn:asciiname":"Cruz",
    "gn:country_code":"BR",
    "gn:dem":88,
    "gn:feature_class":"P",
    "gn:feature_code":"PPL",
    "gn:name":"Cruz",
    "gn:population":0,
    "gn:timezone":"America/Fortaleza",
    "iso:country":"BR",
    "wof:name":"Cruz",
    "wof:placetype":"locality"
},
  "geometry": {"coordinates":[-42.97694,-3.69667],"type":"Point"}
}