{
  "type": "Feature",
  "properties": {
    "gn:admin1_code":"18",
    "gn:admin2_code":"4104105.0",
    "gn:asciiname":"Sitio Joao Lopes",
    "gn:country_code":"BR",
    "gn:dem":845,
    "gn:feature_class":"P",
    "gn:feature_code":"PPL",
    "gn:name":"S\u00edtio Jo\u00e3o Lopes",
    "gn:population":0,
    "gn:timezone":"America/Sao_Paulo",
    "iso:country":"BR",
    "name:por_x_preferred":[
        "S\u00edtio Jo\u00e3o Lopes"
    ],
    "wof:name":"Sitio Joao Lopes",
    "wof:placetype":"locality"
},
  "geometry": {"coordinates":[-49.62394000000001,-26.03641],"type":"Point"}
}