{
  "type": "Feature",
  "properties": {
    "gn:admin1_code":"18",
    "gn:admin2_code":"4110102.0",
    "gn:asciiname":"Colonia Bela Vista",
    "gn:country_code":"BR",
    "gn:dem":850,
    "gn:feature_class":"P",
    "gn:feature_code":"PPLL",
    "gn:name":"Col\u00f4nia Bela Vista",
    "gn:population":0,
    "gn:timezone":"America/Sao_Paulo",
    "iso:country":"BR",
    "name:por_x_preferred":[
        "Col\u00f4nia Bela Vista"
    ],
    "wof:name":"Colonia Bela Vista",
    "wof:placetype":"locality"
},
  "geometry": {"coordinates":[-50.7042,-25.2595],"type":"Point"}
}