{
  "type": "Feature",
  "properties": {
    "gn:admin1_code":"6",
    "gn:admin2_code":"2313500.0",
    "gn:asciiname":"Agua Boa (2)",
    "gn:country_code":"BR",
    "gn:dem":44,
    "gn:feature_class":"P",
    "gn:feature_code":"PPL",
    "gn:name":"\u00c1gua Boa (2)",
    "gn:population":0,
    "gn:timezone":"America/Fortaleza",
    "iso:country":"BR",
    "wof:name":"Agua Boa (2)",
    "wof:placetype":"locality"
},
  "geometry": {"coordinates":[-39.31667,-3.41667],"type":"Point"}
}