{
  "type": "Feature",
  "properties": {
    "gn:admin1_code":"27.0",
    "gn:admin2_code":"3528502.0",
    "gn:asciiname":"Sitio Joao-de-Barro",
    "gn:country_code":"BR",
    "gn:dem":934,
    "gn:feature_class":"P",
    "gn:feature_code":"PPL",
    "gn:name":"S\u00edtio Jo\u00e3o-de-Barro",
    "gn:population":0,
    "gn:timezone":"America/Sao_Paulo",
    "iso:country":"BR",
    "name:por_x_preferred":[
        "S\u00edtio Jo\u00e3o-de-Barro"
    ],
    "wof:name":"Sitio Joao-de-Barro",
    "wof:placetype":"locality"
},
  "geometry": {"coordinates":[-46.54674,-23.27247],"type":"Point"}
}