{
  "type": "Feature",
  "properties": {
    "gn:admin1_code":"26",
    "gn:admin2_code":"4214706.0",
    "gn:asciiname":"Pameranos",
    "gn:country_code":"BR",
    "gn:dem":95,
    "gn:feature_class":"P",
    "gn:feature_code":"PPL",
    "gn:name":"Pameranos",
    "gn:population":0,
    "gn:timezone":"America/Sao_Paulo",
    "iso:country":"BR",
    "wof:name":"Pameranos",
    "wof:placetype":"locality"
},
  "geometry": {"coordinates":[-49.25,-26.68333],"type":"Point"}
}