{
  "type": "Feature",
  "properties": {
    "gn:admin1_code":"31",
    "gn:admin2_code":"1717909.0",
    "gn:asciiname":"Cambauba",
    "gn:cc2":"BR",
    "gn:country_code":"BR",
    "gn:dem":388,
    "gn:feature_class":"P",
    "gn:feature_code":"PPL",
    "gn:name":"Camba\u00faba",
    "gn:population":0,
    "gn:timezone":"America/Araguaina",
    "iso:country":"BR",
    "name:und_x_variant":[
        "Camba\u00fabas",
        "Camba\u00faba"
    ],
    "wof:name":"Cambauba",
    "wof:placetype":"locality"
},
  "geometry": {"coordinates":[-47.51667,-10.83333],"type":"Point"}
}