{
  "type": "Feature",
  "properties": {
    "gn:admin1_code":"20",
    "gn:admin2_code":"2200251.0",
    "gn:asciiname":"Vaquejador",
    "gn:country_code":"BR",
    "gn:dem":419,
    "gn:feature_class":"P",
    "gn:feature_code":"PPL",
    "gn:name":"Vaquejador",
    "gn:population":0,
    "gn:timezone":"America/Fortaleza",
    "iso:country":"BR",
    "wof:name":"Vaquejador",
    "wof:placetype":"locality"
},
  "geometry": {"coordinates":[-40.85,-6.95],"type":"Point"}
}