{
  "type": "Feature",
  "properties": {
    "gn:admin1_code":"02",
    "gn:admin2_code":"2705408.0",
    "gn:asciiname":"Riacho d'Agua",
    "gn:country_code":"BR",
    "gn:dem":230,
    "gn:feature_class":"P",
    "gn:feature_code":"PPL",
    "gn:name":"Riacho d\u2019\u00c1gua",
    "gn:population":0,
    "gn:timezone":"America/Maceio",
    "iso:country":"BR",
    "wof:name":"Riacho d'Agua",
    "wof:placetype":"locality"
},
  "geometry": {"coordinates":[-37.26667,-9.58333],"type":"Point"}
}