{
  "type": "Feature",
  "properties": {
    "gn:admin1_code":"8",
    "gn:admin2_code":"3203320.0",
    "gn:asciiname":"Boa Esperanca",
    "gn:country_code":"BR",
    "gn:dem":6,
    "gn:feature_class":"P",
    "gn:feature_code":"PPL",
    "gn:name":"Boa Esperan\u00e7a",
    "gn:population":0,
    "gn:timezone":"America/Sao_Paulo",
    "iso:country":"BR",
    "name:por_x_preferred":[
        "Boa Esperan\u00e7a"
    ],
    "wof:name":"Boa Esperanca",
    "wof:placetype":"locality"
},
  "geometry": {"coordinates":[-40.95,-21.13333],"type":"Point"}
}