{
  "type": "Feature",
  "properties": {
    "gn:admin1_code":"5",
    "gn:admin2_code":"2911907.0",
    "gn:asciiname":"Piedade",
    "gn:country_code":"BR",
    "gn:dem":291,
    "gn:feature_class":"P",
    "gn:feature_code":"PPL",
    "gn:name":"Piedade",
    "gn:population":0,
    "gn:timezone":"America/Bahia",
    "iso:country":"BR",
    "wof:name":"Piedade",
    "wof:placetype":"locality"
},
  "geometry": {"coordinates":[-39.98333,-12.78333],"type":"Point"}
}