{
  "type": "Feature",
  "properties": {
    "gn:admin1_code":"24.0",
    "gn:admin2_code":"1101492.0",
    "gn:asciiname":"Fazenda Fortaleza",
    "gn:country_code":"BR",
    "gn:dem":152,
    "gn:feature_class":"P",
    "gn:feature_code":"PPLL",
    "gn:name":"Fazenda Fortaleza",
    "gn:population":0,
    "gn:timezone":"America/Porto_Velho",
    "iso:country":"BR",
    "wof:name":"Fazenda Fortaleza",
    "wof:placetype":"locality"
},
  "geometry": {"coordinates":[-63.19105,-12.24012],"type":"Point"}
}