{
  "type": "Feature",
  "properties": {
    "gn:admin1_code":"27",
    "gn:admin2_code":"3518206.0",
    "gn:asciiname":"Jangada",
    "gn:country_code":"BR",
    "gn:dem":453,
    "gn:feature_class":"P",
    "gn:feature_code":"PPL",
    "gn:name":"Jangada",
    "gn:population":0,
    "gn:timezone":"America/Sao_Paulo",
    "iso:country":"BR",
    "name:cat_x_preferred":[
        "Jangada"
    ],
    "name:deu_x_preferred":[
        "Jangada"
    ],
    "name:fra_x_preferred":[
        "Jangada"
    ],
    "name:kaz_x_preferred":[
        "\u0416\u0430\u043d\u0433\u0430\u0434\u0430"
    ],
    "name:por_x_preferred":[
        "Jangada"
    ],
    "name:rus_x_preferred":[
        "\u0416\u0430\u043d\u0433\u0430\u0434\u0430"
    ],
    "name:spa_x_preferred":[
        "Jangada"
    ],
    "wof:name":"Jangada",
    "wof:placetype":"locality"
},
  "geometry": {"coordinates":[-50.68333,-21.41667],"type":"Point"}
}