{
  "type": "Feature",
  "properties": {
    "gn:admin1_code":"02",
    "gn:admin2_code":"2702504.0",
    "gn:asciiname":"Fazenda de Baixo",
    "gn:country_code":"BR",
    "gn:dem":237,
    "gn:feature_class":"P",
    "gn:feature_code":"PPL",
    "gn:name":"Fazenda de Baixo",
    "gn:population":0,
    "gn:timezone":"America/Maceio",
    "iso:country":"BR",
    "wof:name":"Fazenda de Baixo",
    "wof:placetype":"locality"
},
  "geometry": {"coordinates":[-37.06667,-9.35],"type":"Point"}
}