{
  "type": "Feature",
  "properties": {
    "gn:admin1_code":"20",
    "gn:admin2_code":"2200103.0",
    "gn:asciiname":"Agricolandia",
    "gn:country_code":"BR",
    "gn:dem":256,
    "gn:feature_class":"P",
    "gn:feature_code":"PPL",
    "gn:name":"Agricol\u00e2ndia",
    "gn:population":0,
    "gn:timezone":"America/Fortaleza",
    "iso:country":"BR",
    "name:por_x_preferred":[
        "Agricol\u00e2ndia"
    ],
    "wof:name":"Agricolandia",
    "wof:placetype":"locality"
},
  "geometry": {"coordinates":[-42.66446,-5.79782],"type":"Point"}
}