{
  "type": "Feature",
  "properties": {
    "gn:admin1_code":"15",
    "gn:admin2_code":"3126109.0",
    "gn:asciiname":"Carolina Belo",
    "gn:country_code":"BR",
    "gn:dem":784,
    "gn:feature_class":"P",
    "gn:feature_code":"PPL",
    "gn:name":"Carolina Belo",
    "gn:population":0,
    "gn:timezone":"America/Sao_Paulo",
    "iso:country":"BR",
    "name:por_x_preferred":[
        "Carolina Belo"
    ],
    "wof:name":"Carolina Belo",
    "wof:placetype":"locality"
},
  "geometry": {"coordinates":[-45.61667,-20.53333],"type":"Point"}
}