{
  "type": "Feature",
  "properties": {
    "gn:admin1_code":"06",
    "gn:admin2_code":"2310308.0",
    "gn:asciiname":"Sitio",
    "gn:country_code":"BR",
    "gn:dem":614,
    "gn:feature_class":"P",
    "gn:feature_code":"PPL",
    "gn:name":"S\u00edtio",
    "gn:population":0,
    "gn:timezone":"America/Fortaleza",
    "iso:country":"BR",
    "name:deu_x_preferred":[
        "Sitio"
    ],
    "name:ilo_x_preferred":[
        "Sitio"
    ],
    "wof:name":"Sitio",
    "wof:placetype":"locality"
},
  "geometry": {"coordinates":[-40.71667,-6.13333],"type":"Point"}
}