{
  "type": "Feature",
  "properties": {
    "gn:admin1_code":"15",
    "gn:admin2_code":"3127602.0",
    "gn:asciiname":"Cuiaba",
    "gn:country_code":"BR",
    "gn:dem":1207,
    "gn:feature_class":"P",
    "gn:feature_code":"PPL",
    "gn:name":"Cuiab\u00e1",
    "gn:population":0,
    "gn:timezone":"America/Sao_Paulo",
    "iso:country":"BR",
    "name:por_x_preferred":[
        "Cuiab\u00e1"
    ],
    "wof:name":"Cuiaba",
    "wof:placetype":"locality"
},
  "geometry": {"coordinates":[-43.81667,-18.41667],"type":"Point"}
}