{
  "type": "Feature",
  "properties": {
    "gn:admin1_code":"31",
    "gn:admin2_code":"1703883.0",
    "gn:asciiname":"Alfredo Dantas",
    "gn:country_code":"BR",
    "gn:dem":212,
    "gn:feature_class":"P",
    "gn:feature_code":"PPL",
    "gn:name":"Alfredo Dantas",
    "gn:population":0,
    "gn:timezone":"America/Araguaina",
    "iso:country":"BR",
    "wof:name":"Alfredo Dantas",
    "wof:placetype":"locality"
},
  "geometry": {"coordinates":[-48.35,-7.11667],"type":"Point"}
}