{
  "type": "Feature",
  "properties": {
    "gn:admin1_code":"18.0",
    "gn:admin2_code":"4122305.0",
    "gn:asciiname":"Sitio Osmar Ficher",
    "gn:country_code":"BR",
    "gn:dem":798,
    "gn:feature_class":"P",
    "gn:feature_code":"PPL",
    "gn:name":"S\u00edtio Osmar Ficher",
    "gn:population":0,
    "gn:timezone":"America/Sao_Paulo",
    "iso:country":"BR",
    "name:por_x_preferred":[
        "S\u00edtio Osmar Ficher"
    ],
    "wof:name":"Sitio Osmar Ficher",
    "wof:placetype":"locality"
},
  "geometry": {"coordinates":[-49.8041,-26.0559],"type":"Point"}
}