{
  "type": "Feature",
  "properties": {
    "gn:admin1_code":"16",
    "gn:admin2_code":"1503754.0",
    "gn:asciiname":"Pereirinha",
    "gn:cc2":"BR",
    "gn:country_code":"BR",
    "gn:dem":175,
    "gn:feature_class":"P",
    "gn:feature_code":"PPL",
    "gn:name":"Pereirinha",
    "gn:population":0,
    "gn:timezone":"America/Santarem",
    "iso:country":"BR",
    "name:und_x_variant":[
        "Barraca Pereirinha",
        "Pereirinha"
    ],
    "wof:name":"Pereirinha",
    "wof:placetype":"locality"
},
  "geometry": {"coordinates":[-57.58333,-8.15],"type":"Point"}
}