{
  "type": "Feature",
  "properties": {
    "gn:admin1_code":"18.0",
    "gn:admin2_code":"4109500.0",
    "gn:asciiname":"Vila Fatima",
    "gn:country_code":"BR",
    "gn:dem":5,
    "gn:feature_class":"P",
    "gn:feature_code":"PPL",
    "gn:name":"Vila F\u00e1tima",
    "gn:population":0,
    "gn:timezone":"America/Sao_Paulo",
    "iso:country":"BR",
    "name:por_x_preferred":[
        "Vila F\u00e1tima"
    ],
    "wof:name":"Vila Fatima",
    "wof:placetype":"locality"
},
  "geometry": {"coordinates":[-48.15472000000001,-25.29188],"type":"Point"}
}