{
  "type": "Feature",
  "properties": {
    "gn:admin1_code":"18",
    "gn:admin2_code":"4106308.0",
    "gn:asciiname":"Santa Luzia",
    "gn:country_code":"BR",
    "gn:dem":551,
    "gn:feature_class":"P",
    "gn:feature_code":"PPL",
    "gn:name":"Santa Luzia",
    "gn:population":0,
    "gn:timezone":"America/Sao_Paulo",
    "iso:country":"BR",
    "name:bpy_x_preferred":[
        "\u09b8\u09be\u09a8\u09cd\u099f\u09be \u09b2\u09c1\u099c\u09bf\u09af\u09bc\u09be"
    ],
    "name:bre_x_preferred":[
        "Santa Luzia"
    ],
    "name:ceb_x_preferred":[
        "Santa Luzia"
    ],
    "name:deu_x_preferred":[
        "Santa Luzia"
    ],
    "name:eus_x_preferred":[
        "Santa Luzia"
    ],
    "name:fra_x_preferred":[
        "Santa Luzia"
    ],
    "name:hye_x_preferred":[
        "\u054d\u0561\u0576\u057f\u0561 \u053c\u0578\u0582\u0566\u056b\u0561"
    ],
    "name:ita_x_preferred":[
        "Santa Luzia"
    ],
    "name:lit_x_preferred":[
        "Santa Luzija"
    ],
    "name:mlg_x_preferred":[
        "Santa Luzia"
    ],
    "name:nds_x_preferred":[
        "Santa Luzia"
    ],
    "name:nld_x_preferred":[
        "Santa Luzia"
    ],
    "name:nor_x_preferred":[
        "Santa Luzia"
    ],
    "name:pol_x_preferred":[
        "Santa Luzia"
    ],
    "name:por_x_preferred":[
        "Santa Luzia"
    ],
    "name:ron_x_preferred":[
        "Santa Luzia"
    ],
    "name:rus_x_preferred":[
        "\u0421\u0430\u043d\u0442\u0430-\u041b\u0443\u0437\u0438\u044f"
    ],
    "name:sco_x_preferred":[
        "Santa Luzia"
    ],
    "name:swe_x_preferred":[
        "Santa Luzia"
    ],
    "name:tur_x_preferred":[
        "Santa Luzia"
    ],
    "name:ukr_x_preferred":[
        "\u0421\u0430\u043d\u0442\u0430-\u041b\u0443\u0437\u0456\u044f"
    ],
    "name:vie_x_preferred":[
        "Santa Luzia"
    ],
    "name:vol_x_preferred":[
        "Santa Luzia"
    ],
    "wof:name":"Santa Luzia",
    "wof:placetype":"locality"
},
  "geometry": {"coordinates":[-53.23333,-24.71667],"type":"Point"}
}