{
  "type": "Feature",
  "properties": {
    "gn:admin1_code":"18",
    "gn:admin2_code":"4106308.0",
    "gn:asciiname":"Santa Luzia",
    "gn:country_code":"BR",
    "gn:dem":551,
    "gn:feature_class":"P",
    "gn:feature_code":"PPL",
    "gn:name":"Santa Luzia",
    "gn:population":0,
    "gn:timezone":"America/Sao_Paulo",
    "iso:country":"BR",
    "wof:name":"Santa Luzia",
    "wof:placetype":"locality"
},
  "geometry": {"coordinates":[-53.23333,-24.71667],"type":"Point"}
}