{
  "type": "Feature",
  "properties": {
    "gn:admin1_code":"15",
    "gn:admin2_code":"3141405.0",
    "gn:asciiname":"Agua Branca",
    "gn:cc2":"BR",
    "gn:country_code":"BR",
    "gn:dem":614,
    "gn:feature_class":"P",
    "gn:feature_code":"PPL",
    "gn:name":"\u00c1gua Branca",
    "gn:population":0,
    "gn:timezone":"America/Sao_Paulo",
    "iso:country":"BR",
    "name:und_x_variant":[
        "Fazenda \u00c1gua Branca",
        "\u00c1gua Branca"
    ],
    "wof:name":"Agua Branca",
    "wof:placetype":"locality"
},
  "geometry": {"coordinates":[-41.46667,-16.18333],"type":"Point"}
}