{
  "type": "Feature",
  "properties": {
    "gn:admin1_code":"18",
    "gn:admin2_code":"4121208.0",
    "gn:asciiname":"Sitio Antonio F. Barbosa",
    "gn:country_code":"BR",
    "gn:dem":821,
    "gn:feature_class":"P",
    "gn:feature_code":"PPL",
    "gn:name":"S\u00edtio Ant\u00f4nio F. Barbosa",
    "gn:population":0,
    "gn:timezone":"America/Sao_Paulo",
    "iso:country":"BR",
    "name:por_x_preferred":[
        "S\u00edtio Ant\u00f4nio F. Barbosa"
    ],
    "wof:name":"Sitio Antonio F. Barbosa",
    "wof:placetype":"locality"
},
  "geometry": {"coordinates":[-49.5229,-25.998],"type":"Point"}
}