{
  "type": "Feature",
  "properties": {
    "gn:admin1_code":"11",
    "gn:admin2_code":"5003108.0",
    "gn:asciiname":"Santana",
    "gn:cc2":"BR",
    "gn:country_code":"BR",
    "gn:dem":551,
    "gn:feature_class":"P",
    "gn:feature_code":"PPL",
    "gn:name":"Santana",
    "gn:population":0,
    "gn:timezone":"America/Campo_Grande",
    "iso:country":"BR",
    "name:und_x_variant":[
        "Sant\u2019Anna",
        "Santana"
    ],
    "wof:name":"Santana",
    "wof:placetype":"locality"
},
  "geometry": {"coordinates":[-55.33333,-19.75],"type":"Point"}
}