{
  "type": "Feature",
  "properties": {
    "gn:admin1_code":"16",
    "gn:admin2_code":"1504208.0",
    "gn:asciiname":"Tortinho",
    "gn:country_code":"BR",
    "gn:dem":143,
    "gn:feature_class":"P",
    "gn:feature_code":"PPL",
    "gn:name":"Tortinho",
    "gn:population":0,
    "gn:timezone":"America/Belem",
    "iso:country":"BR",
    "wof:name":"Tortinho",
    "wof:placetype":"locality"
},
  "geometry": {"coordinates":[-49.95,-5.56667],"type":"Point"}
}