{
  "type": "Feature",
  "properties": {
    "gn:admin1_code":"18.0",
    "gn:admin2_code":"4101606.0",
    "gn:asciiname":"Sitio Sebastiao B. Anhaia",
    "gn:country_code":"BR",
    "gn:dem":616,
    "gn:feature_class":"P",
    "gn:feature_code":"PPL",
    "gn:name":"S\u00edtio Sebasti\u00e3o B. Anhaia",
    "gn:population":0,
    "gn:timezone":"America/Sao_Paulo",
    "iso:country":"BR",
    "name:por_x_preferred":[
        "S\u00edtio Sebasti\u00e3o B. Anhaia"
    ],
    "wof:name":"Sitio Sebastiao B. Anhaia",
    "wof:placetype":"locality"
},
  "geometry": {"coordinates":[-50.00842,-23.99657],"type":"Point"}
}