{
  "type": "Feature",
  "properties": {
    "gn:admin1_code":"30",
    "gn:admin2_code":"2607208.0",
    "gn:asciiname":"Cupe",
    "gn:country_code":"BR",
    "gn:dem":1,
    "gn:feature_class":"P",
    "gn:feature_code":"PPL",
    "gn:name":"Cupe",
    "gn:population":0,
    "gn:timezone":"America/Recife",
    "iso:country":"BR",
    "wof:name":"Cupe",
    "wof:placetype":"locality"
},
  "geometry": {"coordinates":[-34.99217,-8.46404],"type":"Point"}
}