{
  "type": "Feature",
  "properties": {
    "gn:admin1_code":"25",
    "gn:admin2_code":"1400100.0",
    "gn:asciiname":"Cacada Real",
    "gn:country_code":"BR",
    "gn:dem":91,
    "gn:feature_class":"P",
    "gn:feature_code":"PPL",
    "gn:name":"Ca\u00e7ada Real",
    "gn:population":0,
    "gn:timezone":"America/Boa_Vista",
    "iso:country":"BR",
    "wof:name":"Cacada Real",
    "wof:placetype":"locality"
},
  "geometry": {"coordinates":[-60.71666999999999,3.13333],"type":"Point"}
}