{
  "type": "Feature",
  "properties": {
    "gn:admin1_code":"5",
    "gn:admin2_code":"2910800.0",
    "gn:asciiname":"Malhada Nova",
    "gn:country_code":"BR",
    "gn:dem":257,
    "gn:feature_class":"P",
    "gn:feature_code":"PPL",
    "gn:name":"Malhada Nova",
    "gn:population":0,
    "gn:timezone":"America/Bahia",
    "iso:country":"BR",
    "wof:name":"Malhada Nova",
    "wof:placetype":"locality"
},
  "geometry": {"coordinates":[-38.93333,-12.06667],"type":"Point"}
}