{
  "type": "Feature",
  "properties": {
    "gn:admin1_code":"22",
    "gn:admin2_code":"2408102.0",
    "gn:asciiname":"Redinha",
    "gn:country_code":"BR",
    "gn:dem":5,
    "gn:feature_class":"P",
    "gn:feature_code":"PPL",
    "gn:name":"Redinha",
    "gn:population":0,
    "gn:timezone":"America/Fortaleza",
    "iso:country":"BR",
    "wof:name":"Redinha",
    "wof:placetype":"locality"
},
  "geometry": {"coordinates":[-35.20333,-5.75333],"type":"Point"}
}