{
  "type": "Feature",
  "properties": {
    "gn:admin1_code":"14",
    "gn:admin2_code":"5103304.0",
    "gn:asciiname":"Colonia dos Mineiros",
    "gn:country_code":"BR",
    "gn:dem":574,
    "gn:feature_class":"P",
    "gn:feature_code":"PPL",
    "gn:name":"Col\u00f4nia dos Mineiros",
    "gn:population":0,
    "gn:timezone":"America/Cuiaba",
    "iso:country":"BR",
    "wof:name":"Colonia dos Mineiros",
    "wof:placetype":"locality"
},
  "geometry": {"coordinates":[-59.75556,-13.90139],"type":"Point"}
}