{
  "type": "Feature",
  "properties": {
    "gn:admin1_code":"11",
    "gn:admin2_code":"5003108.0",
    "gn:asciiname":"Indaia",
    "gn:country_code":"BR",
    "gn:dem":274,
    "gn:feature_class":"P",
    "gn:feature_code":"PPL",
    "gn:name":"Indai\u00e1",
    "gn:population":0,
    "gn:timezone":"America/Campo_Grande",
    "iso:country":"BR",
    "name:por_x_preferred":[
        "Indai\u00e1"
    ],
    "wof:name":"Indaia",
    "wof:placetype":"locality"
},
  "geometry": {"coordinates":[-55.03333000000001,-20.03333],"type":"Point"}
}