{
  "type": "Feature",
  "properties": {
    "gn:admin1_code":"18.0",
    "gn:admin2_code":"4113205.0",
    "gn:asciiname":"Sitio Benedito M. de Souza",
    "gn:country_code":"BR",
    "gn:dem":812,
    "gn:feature_class":"P",
    "gn:feature_code":"PPL",
    "gn:name":"S\u00edtio Benedito M. de Souza",
    "gn:population":0,
    "gn:timezone":"America/Sao_Paulo",
    "iso:country":"BR",
    "name:por_x_preferred":[
        "S\u00edtio Benedito M. de Souza"
    ],
    "wof:name":"Sitio Benedito M. de Souza",
    "wof:placetype":"locality"
},
  "geometry": {"coordinates":[-49.5787,-25.8178],"type":"Point"}
}