{
  "type": "Feature",
  "properties": {
    "gn:admin1_code":"18.0",
    "gn:admin2_code":"4109708.0",
    "gn:asciiname":"Sitio Manoel de Moura",
    "gn:country_code":"BR",
    "gn:dem":733,
    "gn:feature_class":"P",
    "gn:feature_code":"PPL",
    "gn:name":"S\u00edtio Manoel de Moura",
    "gn:population":0,
    "gn:timezone":"America/Sao_Paulo",
    "iso:country":"BR",
    "name:por_x_preferred":[
        "S\u00edtio Manoel de Moura"
    ],
    "wof:name":"Sitio Manoel de Moura",
    "wof:placetype":"locality"
},
  "geometry": {"coordinates":[-50.20947,-23.83857],"type":"Point"}
}