{
  "type": "Feature",
  "properties": {
    "gn:admin1_code":"18.0",
    "gn:admin2_code":"4121208.0",
    "gn:asciiname":"Sitio Benedito Mendes",
    "gn:country_code":"BR",
    "gn:dem":807,
    "gn:feature_class":"P",
    "gn:feature_code":"PPL",
    "gn:name":"S\u00edtio Benedito Mendes",
    "gn:population":0,
    "gn:timezone":"America/Sao_Paulo",
    "iso:country":"BR",
    "name:por_x_preferred":[
        "S\u00edtio Benedito Mendes"
    ],
    "wof:name":"Sitio Benedito Mendes",
    "wof:placetype":"locality"
},
  "geometry": {"coordinates":[-49.5055,-25.884],"type":"Point"}
}