{
  "type": "Feature",
  "properties": {
    "gn:admin1_code":"4",
    "gn:admin2_code":"1302306.0",
    "gn:asciiname":"Copatana",
    "gn:country_code":"BR",
    "gn:dem":53,
    "gn:feature_class":"P",
    "gn:feature_code":"PPL",
    "gn:name":"Copatana",
    "gn:population":0,
    "gn:timezone":"America/Manaus",
    "iso:country":"BR",
    "name:und_x_variant":[
        "Capatana",
        "Cupatana",
        "Copatana"
    ],
    "wof:name":"Copatana",
    "wof:placetype":"locality"
},
  "geometry": {"coordinates":[-66.99035000000001,-2.89328],"type":"Point"}
}