{
  "type": "Feature",
  "properties": {
    "gn:admin1_code":"20",
    "gn:admin2_code":"2209906.0",
    "gn:asciiname":"Fazenda Calumbi",
    "gn:country_code":"BR",
    "gn:dem":140,
    "gn:feature_class":"P",
    "gn:feature_code":"PPL",
    "gn:name":"Fazenda Calumbi",
    "gn:population":0,
    "gn:timezone":"America/Fortaleza",
    "iso:country":"BR",
    "wof:name":"Fazenda Calumbi",
    "wof:placetype":"locality"
},
  "geometry": {"coordinates":[-41.91667,-5.43333],"type":"Point"}
}