{
  "type": "Feature",
  "properties": {
    "gn:admin1_code":"20",
    "gn:admin2_code":"2203420.0",
    "gn:asciiname":"Olho d'Agua Grande",
    "gn:country_code":"BR",
    "gn:dem":132,
    "gn:feature_class":"P",
    "gn:feature_code":"PPL",
    "gn:name":"\u00d4lho d\u2019\u00c1gua Grande",
    "gn:population":0,
    "gn:timezone":"America/Fortaleza",
    "iso:country":"BR",
    "wof:name":"Olho d'Agua Grande",
    "wof:placetype":"locality"
},
  "geometry": {"coordinates":[-41.28333,-4.25],"type":"Point"}
}