{
  "type": "Feature",
  "properties": {
    "gn:admin1_code":"6",
    "gn:admin2_code":"2306553.0",
    "gn:asciiname":"Almfala",
    "gn:country_code":"BR",
    "gn:dem":-9999,
    "gn:feature_class":"P",
    "gn:feature_code":"PPL",
    "gn:name":"Almfala",
    "gn:population":0,
    "gn:timezone":"America/Fortaleza",
    "iso:country":"BR",
    "wof:name":"Almfala",
    "wof:placetype":"locality"
},
  "geometry": {"coordinates":[-39.81667,-2.93333],"type":"Point"}
}