{
  "type": "Feature",
  "properties": {
    "gn:admin1_code":"22",
    "gn:admin2_code":"2409704.0",
    "gn:asciiname":"Santa Penha",
    "gn:country_code":"BR",
    "gn:dem":109,
    "gn:feature_class":"P",
    "gn:feature_code":"PPL",
    "gn:name":"Santa Penha",
    "gn:population":0,
    "gn:timezone":"America/Fortaleza",
    "iso:country":"BR",
    "wof:name":"Santa Penha",
    "wof:placetype":"locality"
},
  "geometry": {"coordinates":[-36.36056,-5.47694],"type":"Point"}
}