{
  "type": "Feature",
  "properties": {
    "gn:admin1_code":"22",
    "gn:admin2_code":"2412708.0",
    "gn:asciiname":"Lagoa Grande",
    "gn:country_code":"BR",
    "gn:dem":88,
    "gn:feature_class":"P",
    "gn:feature_code":"PPL",
    "gn:name":"Lagoa Grande",
    "gn:population":0,
    "gn:timezone":"America/Fortaleza",
    "iso:country":"BR",
    "wof:name":"Lagoa Grande",
    "wof:placetype":"locality"
},
  "geometry": {"coordinates":[-35.63333,-5.85],"type":"Point"}
}