{
  "type": "Feature",
  "properties": {
    "gn:admin1_code":"22",
    "gn:admin2_code":"2412708.0",
    "gn:asciiname":"Lagoa Grande",
    "gn:country_code":"BR",
    "gn:dem":88,
    "gn:feature_class":"P",
    "gn:feature_code":"PPL",
    "gn:name":"Lagoa Grande",
    "gn:population":0,
    "gn:timezone":"America/Fortaleza",
    "iso:country":"BR",
    "name:bpy_x_preferred":[
        "\u09b2\u09be\u0997\u09cb\u09af\u09bc\u09be \u0997\u09cd\u09b0\u09be\u09a8\u09cd\u09a1\u09c7"
    ],
    "name:ceb_x_preferred":[
        "Lagoa Grande"
    ],
    "name:epo_x_preferred":[
        "Lagoa Grande"
    ],
    "name:ita_x_preferred":[
        "Lagoa Grande"
    ],
    "name:nld_x_preferred":[
        "Lagoa Grande"
    ],
    "name:nor_x_preferred":[
        "Lagoa Grande"
    ],
    "name:por_x_preferred":[
        "Lagoa Grande"
    ],
    "name:rus_x_preferred":[
        "\u041b\u0430\u0433\u043e\u0430-\u0413\u0440\u0430\u043d\u0434\u0438"
    ],
    "name:swe_x_preferred":[
        "Lagoa Grande"
    ],
    "name:vie_x_preferred":[
        "Lagoa Grande"
    ],
    "name:vol_x_preferred":[
        "Lagoa Grande"
    ],
    "wof:name":"Lagoa Grande",
    "wof:placetype":"locality"
},
  "geometry": {"coordinates":[-35.63333,-5.85],"type":"Point"}
}