{
  "type": "Feature",
  "properties": {
    "gn:admin1_code":"14",
    "gn:admin2_code":"5106505.0",
    "gn:asciiname":"Capinzal",
    "gn:country_code":"BR",
    "gn:dem":117,
    "gn:feature_class":"P",
    "gn:feature_code":"PPL",
    "gn:name":"Capinzal",
    "gn:population":0,
    "gn:timezone":"America/Cuiaba",
    "iso:country":"BR",
    "name:bpy_x_preferred":[
        "\u0995\u09be\u09aa\u09bf\u09a8\u099c\u09be\u09b2"
    ],
    "name:eus_x_preferred":[
        "Capinzal"
    ],
    "name:fra_x_preferred":[
        "Capinzal"
    ],
    "name:ina_x_preferred":[
        "Capinzal"
    ],
    "name:ita_x_preferred":[
        "Capinzal"
    ],
    "name:kat_x_preferred":[
        "\u10d9\u10d0\u10de\u10d8\u10dc\u10d6\u10d0\u10da\u10d8"
    ],
    "name:mlg_x_preferred":[
        "Capinzal"
    ],
    "name:nld_x_preferred":[
        "Capinzal"
    ],
    "name:nor_x_preferred":[
        "Capinzal"
    ],
    "name:oci_x_preferred":[
        "Capinzal"
    ],
    "name:pol_x_preferred":[
        "Capinzal"
    ],
    "name:por_x_preferred":[
        "Capinzal"
    ],
    "name:ron_x_preferred":[
        "Capinzal"
    ],
    "name:rus_x_preferred":[
        "\u041a\u0430\u043f\u0438\u043d\u0437\u0430\u043b"
    ],
    "name:vie_x_preferred":[
        "Capinzal"
    ],
    "name:vol_x_preferred":[
        "Capinzal"
    ],
    "name:war_x_preferred":[
        "Capinzal"
    ],
    "name:zho_x_preferred":[
        "\u5361\u5e73\u624e\u5c14"
    ],
    "wof:name":"Capinzal",
    "wof:placetype":"locality"
},
  "geometry": {"coordinates":[-56.58333,-16.38332999999999],"type":"Point"}
}