{
  "type": "Feature",
  "properties": {
    "gn:admin1_code":"27.0",
    "gn:admin2_code":"3550308.0",
    "gn:asciiname":"Bairro Borore",
    "gn:country_code":"BR",
    "gn:dem":751,
    "gn:feature_class":"P",
    "gn:feature_code":"PPL",
    "gn:name":"Bairro Boror\u00e9",
    "gn:population":0,
    "gn:timezone":"America/Sao_Paulo",
    "iso:country":"BR",
    "name:por_x_preferred":[
        "Bairro Boror\u00e9"
    ],
    "wof:name":"Bairro Borore",
    "wof:placetype":"locality"
},
  "geometry": {"coordinates":[-46.6428,-23.7712],"type":"Point"}
}