{
  "type": "Feature",
  "properties": {
    "gn:admin1_code":"27.0",
    "gn:admin2_code":"3514809.0",
    "gn:asciiname":"Sitio Nascente do Vale",
    "gn:country_code":"BR",
    "gn:dem":87,
    "gn:feature_class":"P",
    "gn:feature_code":"PPL",
    "gn:name":"S\u00edtio Nascente do Vale",
    "gn:population":0,
    "gn:timezone":"America/Sao_Paulo",
    "iso:country":"BR",
    "name:por_x_preferred":[
        "S\u00edtio Nascente do Vale"
    ],
    "wof:name":"Sitio Nascente do Vale",
    "wof:placetype":"locality"
},
  "geometry": {"coordinates":[-48.1403,-24.60827],"type":"Point"}
}