{
  "type": "Feature",
  "properties": {
    "gn:admin1_code":"06",
    "gn:admin2_code":"2309409.0",
    "gn:asciiname":"Campestre",
    "gn:country_code":"BR",
    "gn:dem":380,
    "gn:feature_class":"P",
    "gn:feature_code":"PPL",
    "gn:name":"Campestre",
    "gn:population":0,
    "gn:timezone":"America/Fortaleza",
    "iso:country":"BR",
    "wof:name":"Campestre",
    "wof:placetype":"locality"
},
  "geometry": {"coordinates":[-40.73333,-5.61667],"type":"Point"}
}