{
  "type": "Feature",
  "properties": {
    "gn:admin1_code":"18",
    "gn:admin2_code":"4125605.0",
    "gn:asciiname":"Faxinal de Sao Pedro",
    "gn:country_code":"BR",
    "gn:dem":787,
    "gn:feature_class":"P",
    "gn:feature_code":"PPL",
    "gn:name":"Faxinal de S\u00e3o Pedro",
    "gn:population":0,
    "gn:timezone":"America/Sao_Paulo",
    "iso:country":"BR",
    "wof:name":"Faxinal de Sao Pedro",
    "wof:placetype":"locality"
},
  "geometry": {"coordinates":[-50.53333,-25.85],"type":"Point"}
}