{
  "type": "Feature",
  "properties": {
    "gn:admin1_code":"06",
    "gn:admin2_code":"2305332.0",
    "gn:asciiname":"Doris Irmaos",
    "gn:country_code":"BR",
    "gn:dem":99,
    "gn:feature_class":"P",
    "gn:feature_code":"PPL",
    "gn:name":"Doris Irm\u00e3os",
    "gn:population":0,
    "gn:timezone":"America/Fortaleza",
    "iso:country":"BR",
    "wof:name":"Doris Irmaos",
    "wof:placetype":"locality"
},
  "geometry": {"coordinates":[-38.46667,-4.88333],"type":"Point"}
}