{
  "type": "Feature",
  "properties": {
    "gn:admin1_code":"06",
    "gn:admin2_code":"2302404.0",
    "gn:asciiname":"Fazenda Santa Maria",
    "gn:country_code":"BR",
    "gn:dem":423,
    "gn:feature_class":"P",
    "gn:feature_code":"PPL",
    "gn:name":"Fazenda Santa Maria",
    "gn:population":0,
    "gn:timezone":"America/Fortaleza",
    "iso:country":"BR",
    "wof:name":"Fazenda Santa Maria",
    "wof:placetype":"locality"
},
  "geometry": {"coordinates":[-39.76667,-4.71667],"type":"Point"}
}