{
  "type": "Feature",
  "properties": {
    "gn:admin1_code":"11",
    "gn:admin2_code":"5005806.0",
    "gn:asciiname":"Urumbeba",
    "gn:cc2":"BR",
    "gn:country_code":"BR",
    "gn:dem":303,
    "gn:feature_class":"P",
    "gn:feature_code":"PPL",
    "gn:name":"Urumbeba",
    "gn:population":0,
    "gn:timezone":"America/Campo_Grande",
    "iso:country":"BR",
    "name:und_x_variant":[
        "S\u00e3o Miguel",
        "Urumbeba"
    ],
    "wof:name":"Urumbeba",
    "wof:placetype":"locality"
},
  "geometry": {"coordinates":[-55.68333000000001,-21.18333],"type":"Point"}
}