{
  "type": "Feature",
  "properties": {
    "gn:admin1_code":"06",
    "gn:admin2_code":"2302800.0",
    "gn:asciiname":"Esse",
    "gn:country_code":"BR",
    "gn:dem":183,
    "gn:feature_class":"P",
    "gn:feature_code":"PPL",
    "gn:name":"Esse",
    "gn:population":0,
    "gn:timezone":"America/Fortaleza",
    "iso:country":"BR",
    "name:ceb_x_preferred":[
        "Esse"
    ],
    "name:deu_x_preferred":[
        "Esse"
    ],
    "name:fra_x_preferred":[
        "Esse"
    ],
    "name:ita_x_preferred":[
        "Esse"
    ],
    "name:nld_x_preferred":[
        "Esse"
    ],
    "name:por_x_preferred":[
        "Esse"
    ],
    "name:slk_x_preferred":[
        "Esse"
    ],
    "name:spa_x_preferred":[
        "Esse"
    ],
    "name:swe_x_preferred":[
        "Esse"
    ],
    "name:uzb_x_preferred":[
        "Esse"
    ],
    "wof:name":"Esse",
    "wof:placetype":"locality"
},
  "geometry": {"coordinates":[-39.33333,-4.35],"type":"Point"}
}