{
  "type": "Feature",
  "properties": {
    "gn:admin1_code":"15",
    "gn:admin2_code":"3170529.0",
    "gn:asciiname":"Ramalho",
    "gn:country_code":"BR",
    "gn:dem":643,
    "gn:feature_class":"P",
    "gn:feature_code":"PPL",
    "gn:name":"Ramalho",
    "gn:population":0,
    "gn:timezone":"America/Sao_Paulo",
    "iso:country":"BR",
    "wof:name":"Ramalho",
    "wof:placetype":"locality"
},
  "geometry": {"coordinates":[-45.63333,-15.78333],"type":"Point"}
}