{
  "type": "Feature",
  "properties": {
    "gn:admin1_code":"5",
    "gn:admin2_code":"2913606.0",
    "gn:asciiname":"Itaipe",
    "gn:country_code":"BR",
    "gn:dem":6,
    "gn:feature_class":"P",
    "gn:feature_code":"PPL",
    "gn:name":"Ita\u00edpe",
    "gn:population":0,
    "gn:timezone":"America/Bahia",
    "iso:country":"BR",
    "wof:name":"Itaipe",
    "wof:placetype":"locality"
},
  "geometry": {"coordinates":[-39.05438,-14.77202],"type":"Point"}
}