{
  "type": "Feature",
  "properties": {
    "gn:admin1_code":"4",
    "gn:admin2_code":"1302702.0",
    "gn:asciiname":"Ilha de Monte Cristo",
    "gn:country_code":"BR",
    "gn:dem":41,
    "gn:feature_class":"P",
    "gn:feature_code":"PPL",
    "gn:name":"Ilha de Monte Cristo",
    "gn:population":0,
    "gn:timezone":"America/Manaus",
    "iso:country":"BR",
    "wof:name":"Ilha de Monte Cristo",
    "wof:placetype":"locality"
},
  "geometry": {"coordinates":[-61.12444,-5.58722],"type":"Point"}
}