{
  "type": "Feature",
  "properties": {
    "gn:admin1_code":"18.0",
    "gn:admin2_code":"4103107.0",
    "gn:asciiname":"Pombas",
    "gn:country_code":"BR",
    "gn:dem":882,
    "gn:feature_class":"P",
    "gn:feature_code":"PPLL",
    "gn:name":"Pombas",
    "gn:population":0,
    "gn:timezone":"America/Sao_Paulo",
    "iso:country":"BR",
    "name:por_x_preferred":[
        "Pombas"
    ],
    "wof:name":"Pombas",
    "wof:placetype":"locality"
},
  "geometry": {"coordinates":[-48.96215,-25.18092],"type":"Point"}
}