{
  "type": "Feature",
  "properties": {
    "gn:admin1_code":"26",
    "gn:admin2_code":"4210100.0",
    "gn:asciiname":"Sitio Alfredo S. Wochl",
    "gn:country_code":"BR",
    "gn:dem":796,
    "gn:feature_class":"P",
    "gn:feature_code":"PPL",
    "gn:name":"S\u00edtio Alfredo S. Wochl",
    "gn:population":0,
    "gn:timezone":"America/Sao_Paulo",
    "iso:country":"BR",
    "name:por_x_preferred":[
        "S\u00edtio Alfredo S. Wochl"
    ],
    "wof:name":"Sitio Alfredo S. Wochl",
    "wof:placetype":"locality"
},
  "geometry": {"coordinates":[-49.71824,-26.21398],"type":"Point"}
}