{
  "type": "Feature",
  "properties": {
    "gn:admin1_code":"23",
    "gn:admin2_code":"4305108.0",
    "gn:asciiname":"Sao Valentim",
    "gn:country_code":"BR",
    "gn:dem":670,
    "gn:feature_class":"P",
    "gn:feature_code":"PPLL",
    "gn:name":"S\u00e3o Valentim",
    "gn:population":0,
    "gn:timezone":"America/Sao_Paulo",
    "iso:country":"BR",
    "name:por_x_preferred":[
        "S\u00e3o Valentim"
    ],
    "wof:name":"Sao Valentim",
    "wof:placetype":"locality"
},
  "geometry": {"coordinates":[-51.1097,-29.1944],"type":"Point"}
}