{
  "type": "Feature",
  "properties": {
    "gn:admin1_code":"16",
    "gn:admin2_code":"1503200.0",
    "gn:asciiname":"Santo Cristo",
    "gn:country_code":"BR",
    "gn:dem":42,
    "gn:feature_class":"P",
    "gn:feature_code":"PPL",
    "gn:name":"Santo Cristo",
    "gn:population":0,
    "gn:timezone":"America/Belem",
    "iso:country":"BR",
    "wof:name":"Santo Cristo",
    "wof:placetype":"locality"
},
  "geometry": {"coordinates":[-47.66281,-1.21312],"type":"Point"}
}