{
  "type": "Feature",
  "properties": {
    "gn:admin1_code":"20",
    "gn:admin2_code":"2207504.0",
    "gn:asciiname":"Prata",
    "gn:country_code":"BR",
    "gn:dem":168,
    "gn:feature_class":"P",
    "gn:feature_code":"PPL",
    "gn:name":"Prata",
    "gn:population":0,
    "gn:timezone":"America/Fortaleza",
    "iso:country":"BR",
    "name:ceb_x_preferred":[
        "Prata"
    ],
    "name:deu_x_preferred":[
        "Prata"
    ],
    "name:fra_x_preferred":[
        "Prata"
    ],
    "name:ita_x_preferred":[
        "Prata"
    ],
    "name:lat_x_preferred":[
        "Prata"
    ],
    "name:nld_x_preferred":[
        "Prata"
    ],
    "name:nor_x_preferred":[
        "Prata"
    ],
    "name:por_x_preferred":[
        "Prata"
    ],
    "name:rus_x_preferred":[
        "\u041f\u0440\u0430\u0442\u0430"
    ],
    "name:srp_x_preferred":[
        "\u041f\u0440\u0430\u0442\u0430"
    ],
    "name:swe_x_preferred":[
        "Prata"
    ],
    "name:vie_x_preferred":[
        "Prata"
    ],
    "name:vol_x_preferred":[
        "Prata"
    ],
    "wof:name":"Prata",
    "wof:placetype":"locality"
},
  "geometry": {"coordinates":[-42.96667,-5.61667],"type":"Point"}
}