{
  "type": "Feature",
  "properties": {
    "gn:admin1_code":"27",
    "gn:admin2_code":"3545209.0",
    "gn:asciiname":"Ajudante",
    "gn:country_code":"BR",
    "gn:dem":542,
    "gn:feature_class":"P",
    "gn:feature_code":"PPL",
    "gn:name":"Ajudante",
    "gn:population":0,
    "gn:timezone":"America/Sao_Paulo",
    "iso:country":"BR",
    "name:por_x_preferred":[
        "Ajudante"
    ],
    "wof:name":"Ajudante",
    "wof:placetype":"locality"
},
  "geometry": {"coordinates":[-47.31667,-23.16667],"type":"Point"}
}