{
  "type": "Feature",
  "properties": {
    "gn:admin1_code":"4",
    "gn:admin2_code":"1303536.0",
    "gn:asciiname":"Sitio Ararau",
    "gn:country_code":"BR",
    "gn:dem":72,
    "gn:feature_class":"P",
    "gn:feature_code":"PPL",
    "gn:name":"S\u00edtio Ararau",
    "gn:population":0,
    "gn:timezone":"America/Manaus",
    "iso:country":"BR",
    "wof:name":"Sitio Ararau",
    "wof:placetype":"locality"
},
  "geometry": {"coordinates":[-60.16278000000001,-1.68306],"type":"Point"}
}