{
  "type": "Feature",
  "properties": {
    "gn:admin1_code":"17",
    "gn:admin2_code":"2510204.0",
    "gn:asciiname":"Manguenza Caboclo",
    "gn:country_code":"BR",
    "gn:dem":344,
    "gn:feature_class":"P",
    "gn:feature_code":"PPL",
    "gn:name":"Manguenza Cab\u00f4clo",
    "gn:population":0,
    "gn:timezone":"America/Fortaleza",
    "iso:country":"BR",
    "wof:name":"Manguenza Caboclo",
    "wof:placetype":"locality"
},
  "geometry": {"coordinates":[-37.98333,-7.48333],"type":"Point"}
}