{
  "type": "Feature",
  "properties": {
    "gn:admin1_code":"1",
    "gn:admin2_code":"1200807.0",
    "gn:asciiname":"Colocacao Santo Antonio",
    "gn:country_code":"BR",
    "gn:dem":192,
    "gn:feature_class":"P",
    "gn:feature_code":"PPL",
    "gn:name":"Coloca\u00e7\u00e3o Santo Ant\u00f4nio",
    "gn:population":0,
    "gn:timezone":"America/Rio_Branco",
    "iso:country":"BR",
    "wof:name":"Colocacao Santo Antonio",
    "wof:placetype":"locality"
},
  "geometry": {"coordinates":[-67.41667,-9.81667],"type":"Point"}
}