{
  "type": "Feature",
  "properties": {
    "gn:admin1_code":"24.0",
    "gn:admin2_code":"1100106.0",
    "gn:asciiname":"Pocao",
    "gn:country_code":"BR",
    "gn:dem":137,
    "gn:feature_class":"P",
    "gn:feature_code":"PPL",
    "gn:name":"Pocao",
    "gn:population":0,
    "gn:timezone":"America/Porto_Velho",
    "iso:country":"BR",
    "wof:name":"Pocao",
    "wof:placetype":"locality"
},
  "geometry": {"coordinates":[-65.22583,-10.98931],"type":"Point"}
}