{
  "type": "Feature",
  "properties": {
    "gn:admin1_code":"06",
    "gn:admin2_code":"2312700.0",
    "gn:asciiname":"Passagem do Meio",
    "gn:country_code":"BR",
    "gn:dem":251,
    "gn:feature_class":"P",
    "gn:feature_code":"PPL",
    "gn:name":"Passagem do Meio",
    "gn:population":0,
    "gn:timezone":"America/Fortaleza",
    "iso:country":"BR",
    "wof:name":"Passagem do Meio",
    "wof:placetype":"locality"
},
  "geometry": {"coordinates":[-39.53333,-5.51667],"type":"Point"}
}