{
  "type": "Feature",
  "properties": {
    "gn:admin1_code":"15",
    "gn:admin2_code":"3104908.0",
    "gn:asciiname":"Vargem do Laje",
    "gn:country_code":"BR",
    "gn:dem":1193,
    "gn:feature_class":"P",
    "gn:feature_code":"PPL",
    "gn:name":"Vargem do Laje",
    "gn:population":0,
    "gn:timezone":"America/Sao_Paulo",
    "iso:country":"BR",
    "name:und_x_variant":[
        "Vargem do Lage",
        "Vargem do Laje"
    ],
    "wof:name":"Vargem do Laje",
    "wof:placetype":"locality"
},
  "geometry": {"coordinates":[-44.81293,-22.13055],"type":"Point"}
}