{
  "type": "Feature",
  "properties": {
    "gn:admin1_code":"20",
    "gn:admin2_code":"2207553.0",
    "gn:asciiname":"Pai Amaro",
    "gn:country_code":"BR",
    "gn:dem":438,
    "gn:feature_class":"P",
    "gn:feature_code":"PPL",
    "gn:name":"Pai Amaro",
    "gn:population":0,
    "gn:timezone":"America/Fortaleza",
    "iso:country":"BR",
    "wof:name":"Pai Amaro",
    "wof:placetype":"locality"
},
  "geometry": {"coordinates":[-41.61667,-7.06667],"type":"Point"}
}