{
  "type": "Feature",
  "properties": {
    "gn:admin1_code":"17",
    "gn:admin2_code":"2504405.0",
    "gn:asciiname":"Chorao",
    "gn:country_code":"BR",
    "gn:dem":426,
    "gn:feature_class":"P",
    "gn:feature_code":"PPL",
    "gn:name":"Chor\u00e3o",
    "gn:population":0,
    "gn:timezone":"America/Fortaleza",
    "iso:country":"BR",
    "wof:name":"Chorao",
    "wof:placetype":"locality"
},
  "geometry": {"coordinates":[-38.43333,-7.56667],"type":"Point"}
}