{
  "type": "Feature",
  "properties": {
    "gn:admin1_code":"06",
    "gn:admin2_code":"2313104.0",
    "gn:asciiname":"Saco Verde",
    "gn:country_code":"BR",
    "gn:dem":133,
    "gn:feature_class":"P",
    "gn:feature_code":"PPL",
    "gn:name":"Saco Verde",
    "gn:population":0,
    "gn:timezone":"America/Fortaleza",
    "iso:country":"BR",
    "wof:name":"Saco Verde",
    "wof:placetype":"locality"
},
  "geometry": {"coordinates":[-38.03333,-5.23333],"type":"Point"}
}