{
  "type": "Feature",
  "properties": {
    "gn:admin1_code":"17",
    "gn:admin2_code":"2502409.0",
    "gn:asciiname":"Chapeu",
    "gn:country_code":"BR",
    "gn:dem":586,
    "gn:feature_class":"P",
    "gn:feature_code":"PPL",
    "gn:name":"Chap\u00e9u",
    "gn:population":0,
    "gn:timezone":"America/Fortaleza",
    "iso:country":"BR",
    "wof:name":"Chapeu",
    "wof:placetype":"locality"
},
  "geometry": {"coordinates":[-38.51667,-7.25],"type":"Point"}
}