{
  "type": "Feature",
  "properties": {
    "gn:admin1_code":"26",
    "gn:admin2_code":"4210407.0",
    "gn:asciiname":"Caraiuva",
    "gn:cc2":"BR",
    "gn:country_code":"BR",
    "gn:dem":2,
    "gn:feature_class":"P",
    "gn:feature_code":"PPL",
    "gn:name":"Caraiuva",
    "gn:population":0,
    "gn:timezone":"America/Sao_Paulo",
    "iso:country":"BR",
    "name:und_x_variant":[
        "Garajuva",
        "Caraiuva"
    ],
    "wof:name":"Caraiuva",
    "wof:placetype":"locality"
},
  "geometry": {"coordinates":[-49.48483,-28.88305],"type":"Point"}
}