{
  "type": "Feature",
  "properties": {
    "gn:admin1_code":"18",
    "gn:admin2_code":"4121208.0",
    "gn:asciiname":"Sitio Helena Gavlak",
    "gn:country_code":"BR",
    "gn:dem":829,
    "gn:feature_class":"P",
    "gn:feature_code":"PPL",
    "gn:name":"S\u00edtio Helena Gavlak",
    "gn:population":0,
    "gn:timezone":"America/Sao_Paulo",
    "iso:country":"BR",
    "name:por_x_preferred":[
        "S\u00edtio Helena Gavlak"
    ],
    "wof:name":"Sitio Helena Gavlak",
    "wof:placetype":"locality"
},
  "geometry": {"coordinates":[-49.59417,-25.91111],"type":"Point"}
}