{
  "type": "Feature",
  "properties": {
    "gn:admin1_code":"26",
    "gn:admin2_code":"4210100.0",
    "gn:asciiname":"Sitio Aglaeia Bastos",
    "gn:country_code":"BR",
    "gn:dem":822,
    "gn:feature_class":"P",
    "gn:feature_code":"PPL",
    "gn:name":"S\u00edtio Agla\u00e9ia Bastos",
    "gn:population":0,
    "gn:timezone":"America/Sao_Paulo",
    "iso:country":"BR",
    "name:por_x_preferred":[
        "S\u00edtio Agla\u00e9ia Bastos"
    ],
    "wof:name":"Sitio Aglaeia Bastos",
    "wof:placetype":"locality"
},
  "geometry": {"coordinates":[-49.8287,-26.1944],"type":"Point"}
}