{
  "type": "Feature",
  "properties": {
    "gn:admin1_code":"14",
    "gn:admin2_code":"5103601.0",
    "gn:asciiname":"Sao Pedro da Cipa",
    "gn:cc2":"BR",
    "gn:country_code":"BR",
    "gn:dem":397,
    "gn:feature_class":"P",
    "gn:feature_code":"PPL",
    "gn:name":"S\u00e3o Pedro da Cipa",
    "gn:population":0,
    "gn:timezone":"America/Cuiaba",
    "iso:country":"BR",
    "name:und_x_variant":[
        "S\u00e3o Pedro",
        "S\u00e3o Pedro da Cipa"
    ],
    "wof:name":"Sao Pedro da Cipa",
    "wof:placetype":"locality"
},
  "geometry": {"coordinates":[-54.66667,-15.86667],"type":"Point"}
}