{
  "type": "Feature",
  "properties": {
    "gn:admin1_code":"18.0",
    "gn:admin2_code":"4126207.0",
    "gn:asciiname":"Sitio Joao Roberto Pires",
    "gn:country_code":"BR",
    "gn:dem":865,
    "gn:feature_class":"P",
    "gn:feature_code":"PPL",
    "gn:name":"S\u00edtio Jo\u00e3o Roberto Pires",
    "gn:population":0,
    "gn:timezone":"America/Sao_Paulo",
    "iso:country":"BR",
    "name:por_x_preferred":[
        "S\u00edtio Jo\u00e3o Roberto Pires"
    ],
    "wof:name":"Sitio Joao Roberto Pires",
    "wof:placetype":"locality"
},
  "geometry": {"coordinates":[-50.59908,-23.83266],"type":"Point"}
}