{
  "type": "Feature",
  "properties": {
    "gn:admin1_code":"13",
    "gn:admin2_code":"2101707.0",
    "gn:asciiname":"Pacas",
    "gn:country_code":"BR",
    "gn:dem":31,
    "gn:feature_class":"P",
    "gn:feature_code":"PPL",
    "gn:name":"Pacas",
    "gn:population":0,
    "gn:timezone":"America/Fortaleza",
    "iso:country":"BR",
    "wof:name":"Pacas",
    "wof:placetype":"locality"
},
  "geometry": {"coordinates":[-43.08889,-3.08056],"type":"Point"}
}