{
  "type": "Feature",
  "properties": {
    "gn:gn_country":"BR",
    "gn:gn_fcode":"PPL",
    "gn:gn_pop":22933,
    "gn:population":22933,
    "iso:country":"BR",
    "name:arm_x_preferred":[
        "\u054a\u056b\u0576\u0564\u0561\u0580\u0565 \u0544\u056b\u0580\u056b\u0576"
    ],
    "name:baq_x_preferred":[
        "Pindar\u00e9-Mirim"
    ],
    "name:bpy_x_preferred":[
        "\u09aa\u09bf\u09a8\u09cd\u09a1\u09be\u09b0\u09c7-\u09ae\u09bf\u09b0\u09bf\u09ae"
    ],
    "name:chi_x_preferred":[
        "\u5e73\u8fbe\u96f7\u7c73\u6797"
    ],
    "name:dut_x_preferred":[
        "Pindar\u00e9-Mirim"
    ],
    "name:eng_x_preferred":[
        "Pindar\u00e9-Mirim"
    ],
    "name:fre_x_preferred":[
        "Pindar\u00e9-Mirim"
    ],
    "name:geo_x_preferred":[
        "\u10de\u10d8\u10dc\u10d3\u10d0\u10e0\u10d4-\u10db\u10d8\u10e0\u10d8\u10dc\u10d8"
    ],
    "name:ger_x_preferred":[
        "Pindar\u00e9-Mirim"
    ],
    "name:hun_x_preferred":[
        "Pindar\u00e9-Mirim"
    ],
    "name:ita_x_preferred":[
        "Pindar\u00e9-Mirim"
    ],
    "name:kaz_x_preferred":[
        "\u041f\u0438\u043d\u0434\u0430\u0440\u0435-\u041c\u0438\u0440\u0438\u043d"
    ],
    "name:nan_x_preferred":[
        "Pindar\u00e9-Mirim"
    ],
    "name:nob_x_preferred":[
        "Pindar\u00e9-Mirim"
    ],
    "name:por_x_preferred":[
        "Pindar\u00e9-Mirim"
    ],
    "name:rum_x_preferred":[
        "Pindar\u00e9 Mirim"
    ],
    "name:rus_x_preferred":[
        "\u041f\u0438\u043d\u0434\u0430\u0440\u0435-\u041c\u0438\u0440\u0438\u043d"
    ],
    "name:swe_x_preferred":[
        "Pindar\u00e9-Mirim"
    ],
    "name:unk_x_variant":[
        "Engenho Central"
    ],
    "name:vie_x_preferred":[
        "Pindar\u00e9-Mirim"
    ],
    "name:vol_x_preferred":[
        "Pindar\u00e9-Mirim"
    ],
    "name:war_x_preferred":[
        "Pindar\u00e9-Mirim"
    ],
    "qs_pg:aaroncc":"BR",
    "qs_pg:gn_country":"BR",
    "qs_pg:gn_fcode":"PPL",
    "qs_pg:gn_pop":22933,
    "qs_pg:name":"Pindar\u00e9 Mirim",
    "qs_pg:photos_9r":0,
    "qs_pg:photos_sr":0,
    "qs_pg:pop_sr":7,
    "qs_pg:qs_pg_placetype":"locality",
    "wof:name":"Pindar\u00e9 Mirim",
    "wof:placetype":"locality",
    "wof:population":22933
},
  "geometry": {"coordinates":[-45.34333,-3.60833],"type":"Point"}
}