{
  "type": "Feature",
  "properties": {
    "gn:admin1_code":"22",
    "gn:admin2_code":"2400208.0",
    "gn:asciiname":"Angico",
    "gn:country_code":"BR",
    "gn:dem":116,
    "gn:feature_class":"P",
    "gn:feature_code":"PPL",
    "gn:name":"Angico",
    "gn:population":0,
    "gn:timezone":"America/Fortaleza",
    "iso:country":"BR",
    "name:ceb_x_preferred":[
        "Angico"
    ],
    "name:epo_x_preferred":[
        "Angico"
    ],
    "name:eus_x_preferred":[
        "Angico"
    ],
    "name:fra_x_preferred":[
        "Angico"
    ],
    "name:hye_x_preferred":[
        "\u0531\u0576\u056a\u056b\u056f\u0578\u0582"
    ],
    "name:ita_x_preferred":[
        "Angico"
    ],
    "name:kaz_x_preferred":[
        "\u0410\u043d\u0436\u0438\u043a\u0443"
    ],
    "name:nld_x_preferred":[
        "Angico"
    ],
    "name:nor_x_preferred":[
        "Angico"
    ],
    "name:por_x_preferred":[
        "Angico"
    ],
    "name:ron_x_preferred":[
        "Angico"
    ],
    "name:rus_x_preferred":[
        "\u0410\u043d\u0436\u0438\u043a\u0443"
    ],
    "name:spa_x_preferred":[
        "Angico"
    ],
    "name:swe_x_preferred":[
        "Angico"
    ],
    "name:vie_x_preferred":[
        "Angico"
    ],
    "name:vol_x_preferred":[
        "Angico"
    ],
    "name:war_x_preferred":[
        "Angico"
    ],
    "name:zho_x_preferred":[
        "\u5b89\u5409\u79d1"
    ],
    "wof:name":"Angico",
    "wof:placetype":"locality"
},
  "geometry": {"coordinates":[-37.06056,-5.40556],"type":"Point"}
}