{
  "type": "Feature",
  "properties": {
    "gn:admin1_code":"18",
    "gn:admin2_code":"4127601.0",
    "gn:asciiname":"Sitio Marcos",
    "gn:country_code":"BR",
    "gn:dem":904,
    "gn:feature_class":"P",
    "gn:feature_code":"PPL",
    "gn:name":"S\u00edtio Marcos",
    "gn:population":0,
    "gn:timezone":"America/Sao_Paulo",
    "iso:country":"BR",
    "name:por_x_preferred":[
        "S\u00edtio Marcos"
    ],
    "wof:name":"Sitio Marcos",
    "wof:placetype":"locality"
},
  "geometry": {"coordinates":[-49.2359,-25.9155],"type":"Point"}
}