{
  "type": "Feature",
  "properties": {
    "gn:admin1_code":"18.0",
    "gn:admin2_code":"4126678.0",
    "gn:asciiname":"Sitio Natalina Jose Eugenio",
    "gn:country_code":"BR",
    "gn:dem":732,
    "gn:feature_class":"P",
    "gn:feature_code":"PPL",
    "gn:name":"S\u00edtio Natalina Jos\u00e9 Eug\u00eanio",
    "gn:population":0,
    "gn:timezone":"America/Sao_Paulo",
    "iso:country":"BR",
    "name:por_x_preferred":[
        "S\u00edtio Natalina Jos\u00e9 Eug\u00eanio"
    ],
    "wof:name":"Sitio Natalina Jose Eugenio",
    "wof:placetype":"locality"
},
  "geometry": {"coordinates":[-50.9898,-23.8749],"type":"Point"}
}