{
  "type": "Feature",
  "properties": {
    "gn:admin1_code":"18.0",
    "gn:admin2_code":"4109500.0",
    "gn:asciiname":"Sitio Romildo Mendes",
    "gn:country_code":"BR",
    "gn:dem":17,
    "gn:feature_class":"P",
    "gn:feature_code":"PPL",
    "gn:name":"S\u00edtio Romildo Mendes",
    "gn:population":0,
    "gn:timezone":"America/Sao_Paulo",
    "iso:country":"BR",
    "name:por_x_preferred":[
        "S\u00edtio Romildo Mendes"
    ],
    "wof:name":"Sitio Romildo Mendes",
    "wof:placetype":"locality"
},
  "geometry": {"coordinates":[-48.53409,-25.23363],"type":"Point"}
}