{
  "type": "Feature",
  "properties": {
    "gn:admin1_code":"26",
    "gn:admin2_code":"4216206.0",
    "gn:asciiname":"Marechal Luz",
    "gn:cc2":"BR",
    "gn:country_code":"BR",
    "gn:dem":-9999,
    "gn:feature_class":"P",
    "gn:feature_code":"PPL",
    "gn:name":"Marechal Luz",
    "gn:population":0,
    "gn:timezone":"America/Sao_Paulo",
    "iso:country":"BR",
    "name:und_x_variant":[
        "M\u00e1 Luz",
        "Marechal Luz"
    ],
    "wof:name":"Marechal Luz",
    "wof:placetype":"locality"
},
  "geometry": {"coordinates":[-48.53333,-26.16667],"type":"Point"}
}