{
  "type": "Feature",
  "properties": {
    "gn:country":"BR",
    "gn:fcode":"PPL",
    "gn:population":0,
    "iso:country":"BR",
    "name:ceb_x_preferred":[
        "Atenas"
    ],
    "name:ell_x_preferred":[
        "\u0391\u03b8\u03ae\u03bd\u03b1"
    ],
    "name:fas_x_preferred":[
        "\u0622\u062a\u0646\u0627\u0633"
    ],
    "name:fra_x_preferred":[
        "Atenas"
    ],
    "name:ita_x_preferred":[
        "Atenas"
    ],
    "name:lit_x_preferred":[
        "Atenasas"
    ],
    "name:nld_x_preferred":[
        "Atenas"
    ],
    "name:nor_x_preferred":[
        "Atenas"
    ],
    "name:spa_x_preferred":[
        "Atenas"
    ],
    "name:swe_x_preferred":[
        "Atenas"
    ],
    "name:und_x_variant":[
        "Athenas"
    ],
    "name:zho_x_preferred":[
        "\u963f\u7279\u7d0d\u65af\u5340"
    ],
    "qs_pg:aaroncc":"BR",
    "qs_pg:gn_country":"BR",
    "qs_pg:gn_fcode":"PPL",
    "qs_pg:gn_pop":0,
    "qs_pg:name":"Atenas",
    "qs_pg:name_adm0":"Brasil",
    "qs_pg:name_adm1":"Acre",
    "qs_pg:photos_9k":1,
    "qs_pg:photos_9r":1,
    "qs_pg:photos_all":1,
    "qs_pg:photos_sr":0,
    "qs_pg:pop_sr":3,
    "qs_pg:qs_pg_placetype":"locality",
    "qs_pg:qs_pg_placetype_gp":"Town",
    "qs_pg:woe_adm0":23424768,
    "woe:adm0_id":23424768,
    "woe:name_adm0":"Brasil",
    "woe:name_adm1":"Acre",
    "woe:placetype":"Town",
    "wof:name":"Atenas",
    "wof:placetype":"locality"
},
  "geometry": {"coordinates":[-71.48333,-8.86667],"type":"Point"}
}