{
  "type": "Feature",
  "properties": {
    "gn:admin1_code":"20",
    "gn:admin2_code":"2211308.0",
    "gn:asciiname":"Sao Luis (2)",
    "gn:country_code":"BR",
    "gn:dem":286,
    "gn:feature_class":"P",
    "gn:feature_code":"PPL",
    "gn:name":"S\u00e3o Lu\u00eds (2)",
    "gn:population":0,
    "gn:timezone":"America/Fortaleza",
    "iso:country":"BR",
    "wof:name":"Sao Luis (2)",
    "wof:placetype":"locality"
},
  "geometry": {"coordinates":[-41.73333,-6.38333],"type":"Point"}
}