{
  "type": "Feature",
  "properties": {
    "gn:admin1_code":"27",
    "gn:admin2_code":"3526209.0",
    "gn:asciiname":"Sitio do Teimoso",
    "gn:country_code":"BR",
    "gn:dem":778,
    "gn:feature_class":"P",
    "gn:feature_code":"PPL",
    "gn:name":"S\u00edtio do Teimoso",
    "gn:population":0,
    "gn:timezone":"America/Sao_Paulo",
    "iso:country":"BR",
    "name:por_x_preferred":[
        "S\u00edtio do Teimoso"
    ],
    "wof:name":"Sitio do Teimoso",
    "wof:placetype":"locality"
},
  "geometry": {"coordinates":[-47.0099,-23.9077],"type":"Point"}
}