{
  "type": "Feature",
  "properties": {
    "gn:admin1_code":"18.0",
    "gn:admin2_code":"4113205.0",
    "gn:asciiname":"Sitio Romoaldo Vidal",
    "gn:country_code":"BR",
    "gn:dem":886,
    "gn:feature_class":"P",
    "gn:feature_code":"PPL",
    "gn:name":"S\u00edtio Romoaldo Vidal",
    "gn:population":0,
    "gn:timezone":"America/Sao_Paulo",
    "iso:country":"BR",
    "name:por_x_preferred":[
        "S\u00edtio Romoaldo Vidal"
    ],
    "wof:name":"Sitio Romoaldo Vidal",
    "wof:placetype":"locality"
},
  "geometry": {"coordinates":[-49.657,-25.8189],"type":"Point"}
}