{
  "type": "Feature",
  "properties": {
    "gn:admin1_code":"27.0",
    "gn:admin2_code":"3522307.0",
    "gn:asciiname":"Sitio Bom Jesus",
    "gn:country_code":"BR",
    "gn:dem":713,
    "gn:feature_class":"P",
    "gn:feature_code":"PPL",
    "gn:name":"S\u00edtio Bom Jesus",
    "gn:population":0,
    "gn:timezone":"America/Sao_Paulo",
    "iso:country":"BR",
    "name:por_x_preferred":[
        "S\u00edtio Bom Jesus"
    ],
    "wof:name":"Sitio Bom Jesus",
    "wof:placetype":"locality"
},
  "geometry": {"coordinates":[-47.9748,-23.7244],"type":"Point"}
}