{
  "type": "Feature",
  "properties": {
    "gn:admin1_code":"06",
    "gn:admin2_code":"2306108.0",
    "gn:asciiname":"Fazenda Caminhadeira",
    "gn:country_code":"BR",
    "gn:dem":198,
    "gn:feature_class":"P",
    "gn:feature_code":"PPL",
    "gn:name":"Fazenda Caminhadeira",
    "gn:population":0,
    "gn:timezone":"America/Fortaleza",
    "iso:country":"BR",
    "wof:name":"Fazenda Caminhadeira",
    "wof:placetype":"locality"
},
  "geometry": {"coordinates":[-39.88333,-3.98333],"type":"Point"}
}