{
  "type": "Feature",
  "properties": {
    "gn:admin1_code":"27",
    "gn:admin2_code":"3550605.0",
    "gn:asciiname":"Sito Vila Pauliceia",
    "gn:country_code":"BR",
    "gn:dem":911,
    "gn:feature_class":"P",
    "gn:feature_code":"PPL",
    "gn:name":"Sito Vila Paulic\u00e9ia",
    "gn:population":0,
    "gn:timezone":"America/Sao_Paulo",
    "iso:country":"BR",
    "name:por_x_preferred":[
        "Sito Vila Paulic\u00e9ia"
    ],
    "wof:name":"Sito Vila Pauliceia",
    "wof:placetype":"locality"
},
  "geometry": {"coordinates":[-47.11887,-23.52354],"type":"Point"}
}