{
  "type": "Feature",
  "properties": {
    "gn:admin1_code":"18.0",
    "gn:admin2_code":"4122305.0",
    "gn:asciiname":"Sitio Ana Muskuvicz",
    "gn:country_code":"BR",
    "gn:dem":784,
    "gn:feature_class":"P",
    "gn:feature_code":"PPL",
    "gn:name":"S\u00edtio Ana Muskuvicz",
    "gn:population":0,
    "gn:timezone":"America/Sao_Paulo",
    "iso:country":"BR",
    "name:por_x_preferred":[
        "S\u00edtio Ana Muskuvicz"
    ],
    "wof:name":"Sitio Ana Muskuvicz",
    "wof:placetype":"locality"
},
  "geometry": {"coordinates":[-49.8477,-26.0335],"type":"Point"}
}