{
  "type": "Feature",
  "properties": {
    "gn:admin1_code":"28.0",
    "gn:admin2_code":"2806701.0",
    "gn:asciiname":"Sobrado",
    "gn:country_code":"BR",
    "gn:dem":2,
    "gn:feature_class":"P",
    "gn:feature_code":"PPL",
    "gn:name":"Sobrado",
    "gn:population":0,
    "gn:timezone":"America/Maceio",
    "iso:country":"BR",
    "name:por_x_preferred":[
        "Sobrado"
    ],
    "wof:name":"Sobrado",
    "wof:placetype":"locality"
},
  "geometry": {"coordinates":[-37.12218,-10.92163],"type":"Point"}
}