{
  "type": "Feature",
  "properties": {
    "gn:admin1_code":"26",
    "gn:admin2_code":"4209102.0",
    "gn:asciiname":"Cares",
    "gn:cc2":"BR",
    "gn:country_code":"BR",
    "gn:dem":39,
    "gn:feature_class":"P",
    "gn:feature_code":"PPL",
    "gn:name":"Cares",
    "gn:population":0,
    "gn:timezone":"America/Sao_Paulo",
    "iso:country":"BR",
    "name:und_x_variant":[
        "Soares",
        "Cares"
    ],
    "wof:name":"Cares",
    "wof:placetype":"locality"
},
  "geometry": {"coordinates":[-48.85,-26.35],"type":"Point"}
}