{
  "type": "Feature",
  "properties": {
    "gn:admin1_code":"26",
    "gn:admin2_code":"4209102.0",
    "gn:asciiname":"Cares",
    "gn:cc2":"BR",
    "gn:country_code":"BR",
    "gn:dem":39,
    "gn:feature_class":"P",
    "gn:feature_code":"PPL",
    "gn:name":"Cares",
    "gn:population":0,
    "gn:timezone":"America/Sao_Paulo",
    "iso:country":"BR",
    "name:ara_x_preferred":[
        "\u0643\u0627\u0631\u064a\u0633"
    ],
    "name:ast_x_preferred":[
        "R\u00edu Cares"
    ],
    "name:cat_x_preferred":[
        "Riu Cares"
    ],
    "name:ceb_x_preferred":[
        "R\u00edo Cares"
    ],
    "name:deu_x_preferred":[
        "R\u00edo Cares"
    ],
    "name:eus_x_preferred":[
        "Cares ibaia"
    ],
    "name:fin_x_preferred":[
        "Cares"
    ],
    "name:fra_x_preferred":[
        "Cares"
    ],
    "name:glg_x_preferred":[
        "R\u00edo Cares"
    ],
    "name:nno_x_preferred":[
        "Cares"
    ],
    "name:por_x_preferred":[
        "Rio Cares"
    ],
    "name:rus_x_preferred":[
        "\u041a\u0430\u0440\u0435\u0441"
    ],
    "name:spa_x_preferred":[
        "R\u00edo Cares"
    ],
    "name:swe_x_preferred":[
        "R\u00edo Cares"
    ],
    "name:und_x_variant":[
        "Soares",
        "Cares"
    ],
    "name:zho_x_preferred":[
        "\u5361\u96f7\u65af\u6cb3"
    ],
    "wof:name":"Cares",
    "wof:placetype":"locality"
},
  "geometry": {"coordinates":[-48.85,-26.35],"type":"Point"}
}