{
  "type": "Feature",
  "properties": {
    "gn:admin1_code":"22",
    "gn:admin2_code":"2406809.0",
    "gn:asciiname":"Olho-d'Agua",
    "gn:country_code":"BR",
    "gn:dem":325,
    "gn:feature_class":"P",
    "gn:feature_code":"PPL",
    "gn:name":"\u00d4lho-d\u2019\u00c1gua",
    "gn:population":0,
    "gn:timezone":"America/Fortaleza",
    "iso:country":"BR",
    "name:und_x_variant":[
        "Olho-d\u2019Agua-do-Borges",
        "\u00d4lho-d\u2019\u00c1gua"
    ],
    "wof:name":"Olho-d'Agua",
    "wof:placetype":"locality"
},
  "geometry": {"coordinates":[-36.15,-6.16667],"type":"Point"}
}