{
  "type": "Feature",
  "properties": {
    "gn:admin1_code":"20",
    "gn:admin2_code":"2200459.0",
    "gn:asciiname":"Sao Lourenco",
    "gn:country_code":"BR",
    "gn:dem":296,
    "gn:feature_class":"P",
    "gn:feature_code":"PPL",
    "gn:name":"S\u00e3o Louren\u00e7o",
    "gn:population":0,
    "gn:timezone":"America/Fortaleza",
    "iso:country":"BR",
    "wof:name":"Sao Lourenco",
    "wof:placetype":"locality"
},
  "geometry": {"coordinates":[-43.69095,-8.48754],"type":"Point"}
}