{
  "type": "Feature",
  "properties": {
    "gn:admin1_code":"18",
    "gn:admin2_code":"4122305.0",
    "gn:asciiname":"Sitio Jose K. Taborda",
    "gn:country_code":"BR",
    "gn:dem":831,
    "gn:feature_class":"P",
    "gn:feature_code":"PPL",
    "gn:name":"S\u00edtio Jos\u00e9 K. Taborda",
    "gn:population":0,
    "gn:timezone":"America/Sao_Paulo",
    "iso:country":"BR",
    "name:por_x_preferred":[
        "S\u00edtio Jos\u00e9 K. Taborda"
    ],
    "wof:name":"Sitio Jose K. Taborda",
    "wof:placetype":"locality"
},
  "geometry": {"coordinates":[-49.56211,-26.19192],"type":"Point"}
}