{
  "type": "Feature",
  "properties": {
    "gn:admin1_code":"27.0",
    "gn:admin2_code":"3548708.0",
    "gn:asciiname":"Curucutu",
    "gn:country_code":"BR",
    "gn:dem":796,
    "gn:feature_class":"P",
    "gn:feature_code":"PPLL",
    "gn:name":"Curucutu",
    "gn:population":0,
    "gn:timezone":"America/Sao_Paulo",
    "iso:country":"BR",
    "name:por_x_preferred":[
        "Curucutu"
    ],
    "wof:name":"Curucutu",
    "wof:placetype":"locality"
},
  "geometry": {"coordinates":[-46.6125,-23.8892],"type":"Point"}
}