{
  "type": "Feature",
  "properties": {
    "gn:admin1_code":"21",
    "gn:admin2_code":"3304003.0",
    "gn:asciiname":"Quilometro Oitenta e Quatro",
    "gn:country_code":"BR",
    "gn:dem":444,
    "gn:feature_class":"P",
    "gn:feature_code":"PPL",
    "gn:name":"Quil\u00f4metro Oitenta e Quatro",
    "gn:population":0,
    "gn:timezone":"America/Sao_Paulo",
    "iso:country":"BR",
    "name:por_x_preferred":[
        "Quil\u00f4metro Oitenta e Quatro"
    ],
    "wof:name":"Quilometro Oitenta e Quatro",
    "wof:placetype":"locality"
},
  "geometry": {"coordinates":[-43.97333,-22.57917],"type":"Point"}
}