{
  "type": "Feature",
  "properties": {
    "gn:admin1_code":"06",
    "gn:admin2_code":"2307403.0",
    "gn:asciiname":"Santo Agostinho",
    "gn:country_code":"BR",
    "gn:dem":327,
    "gn:feature_class":"P",
    "gn:feature_code":"PPL",
    "gn:name":"Santo Agostinho",
    "gn:population":0,
    "gn:timezone":"America/Fortaleza",
    "iso:country":"BR",
    "wof:name":"Santo Agostinho",
    "wof:placetype":"locality"
},
  "geometry": {"coordinates":[-39.61667,-6.41667],"type":"Point"}
}