{
  "type": "Feature",
  "properties": {
    "gn:admin1_code":"17",
    "gn:admin2_code":"2516102.0",
    "gn:asciiname":"Barroca",
    "gn:country_code":"BR",
    "gn:dem":499,
    "gn:feature_class":"P",
    "gn:feature_code":"PPL",
    "gn:name":"Barroca",
    "gn:population":0,
    "gn:timezone":"America/Fortaleza",
    "iso:country":"BR",
    "wof:name":"Barroca",
    "wof:placetype":"locality"
},
  "geometry": {"coordinates":[-36.43333,-7.16667],"type":"Point"}
}