{
  "type": "Feature",
  "properties": {
    "gn:admin1_code":"30",
    "gn:admin2_code":"2614303.0",
    "gn:asciiname":"Ingazeiras",
    "gn:country_code":"BR",
    "gn:dem":472,
    "gn:feature_class":"P",
    "gn:feature_code":"PPL",
    "gn:name":"Ing\u00e0zeiras",
    "gn:population":0,
    "gn:timezone":"America/Recife",
    "iso:country":"BR",
    "wof:name":"Ingazeiras",
    "wof:placetype":"locality"
},
  "geometry": {"coordinates":[-39.53333,-7.73333],"type":"Point"}
}