{
  "type": "Feature",
  "properties": {
    "gn:admin1_code":"18",
    "gn:admin2_code":"4103156.0",
    "gn:asciiname":"Nossa Senhora de Fatima",
    "gn:country_code":"BR",
    "gn:dem":579,
    "gn:feature_class":"P",
    "gn:feature_code":"PPL",
    "gn:name":"Nossa Senhora de F\u00e1tima",
    "gn:population":0,
    "gn:timezone":"America/Sao_Paulo",
    "iso:country":"BR",
    "wof:name":"Nossa Senhora de Fatima",
    "wof:placetype":"locality"
},
  "geometry": {"coordinates":[-53.60611,-26.17528],"type":"Point"}
}