{
  "type": "Feature",
  "properties": {
    "gn:admin1_code":"21",
    "gn:admin2_code":"3304755.0",
    "gn:asciiname":"Convivencia",
    "gn:country_code":"BR",
    "gn:dem":1,
    "gn:feature_class":"P",
    "gn:feature_code":"PPL",
    "gn:name":"Conviv\u00eancia",
    "gn:population":0,
    "gn:timezone":"America/Sao_Paulo",
    "iso:country":"BR",
    "name:por_x_preferred":[
        "Conviv\u00eancia"
    ],
    "wof:name":"Convivencia",
    "wof:placetype":"locality"
},
  "geometry": {"coordinates":[-41.03448,-21.6097],"type":"Point"}
}