{
  "type": "Feature",
  "properties": {
    "gn:admin1_code":"18.0",
    "gn:admin2_code":"4121208.0",
    "gn:asciiname":"Sitio Paulo Klisievicz",
    "gn:country_code":"BR",
    "gn:dem":850,
    "gn:feature_class":"P",
    "gn:feature_code":"PPL",
    "gn:name":"S\u00edtio Paulo Klisievicz",
    "gn:population":0,
    "gn:timezone":"America/Sao_Paulo",
    "iso:country":"BR",
    "name:por_x_preferred":[
        "S\u00edtio Paulo Klisievicz"
    ],
    "wof:name":"Sitio Paulo Klisievicz",
    "wof:placetype":"locality"
},
  "geometry": {"coordinates":[-49.48081,-25.81287],"type":"Point"}
}