{
  "type": "Feature",
  "properties": {
    "gn:admin1_code":"18.0",
    "gn:admin2_code":"4106209.0",
    "gn:asciiname":"Sitio Francisca Brunha",
    "gn:country_code":"BR",
    "gn:dem":874,
    "gn:feature_class":"P",
    "gn:feature_code":"PPL",
    "gn:name":"S\u00edtio Francisca Brunha",
    "gn:population":0,
    "gn:timezone":"America/Sao_Paulo",
    "iso:country":"BR",
    "name:por_x_preferred":[
        "S\u00edtio Francisca Brunha"
    ],
    "wof:name":"Sitio Francisca Brunha",
    "wof:placetype":"locality"
},
  "geometry": {"coordinates":[-49.4759,-25.768],"type":"Point"}
}