{
  "type": "Feature",
  "properties": {
    "gn:admin1_code":"06",
    "gn:admin2_code":"2302404.0",
    "gn:asciiname":"Trapizeiro",
    "gn:country_code":"BR",
    "gn:dem":327,
    "gn:feature_class":"P",
    "gn:feature_code":"PPL",
    "gn:name":"Trapizeiro",
    "gn:population":0,
    "gn:timezone":"America/Fortaleza",
    "iso:country":"BR",
    "wof:name":"Trapizeiro",
    "wof:placetype":"locality"
},
  "geometry": {"coordinates":[-39.86667,-5.15],"type":"Point"}
}