{
  "type": "Feature",
  "properties": {
    "gn:admin1_code":"27",
    "gn:admin2_code":"3518404.0",
    "gn:asciiname":"Sitio Belem",
    "gn:country_code":"BR",
    "gn:dem":982,
    "gn:elevation":"0.0",
    "gn:feature_class":"P",
    "gn:feature_code":"PPL",
    "gn:name":"S\u00edtio Bel\u00e9m",
    "gn:population":0,
    "gn:timezone":"America/Sao_Paulo",
    "iso:country":"BR",
    "name:por_x_preferred":[
        "S\u00edtio Bel\u00e9m"
    ],
    "wof:name":"Sitio Belem",
    "wof:placetype":"locality"
},
  "geometry": {"coordinates":[-45.157,-22.9984],"type":"Point"}
}