{
  "type": "Feature",
  "properties": {
    "gn:admin1_code":"16.0",
    "gn:admin2_code":"1508100.0",
    "gn:asciiname":"Vila Permanente",
    "gn:country_code":"BR",
    "gn:dem":172,
    "gn:feature_class":"P",
    "gn:feature_code":"PPL",
    "gn:name":"Vila Permanente",
    "gn:population":0,
    "gn:timezone":"America/Belem",
    "iso:country":"BR",
    "wof:name":"Vila Permanente",
    "wof:placetype":"locality"
},
  "geometry": {"coordinates":[-49.68438,-3.83244],"type":"Point"}
}