{
  "type": "Feature",
  "properties": {
    "gn:admin1_code":"20",
    "gn:admin2_code":"2211308.0",
    "gn:asciiname":"Diamantina",
    "gn:country_code":"BR",
    "gn:dem":156,
    "gn:feature_class":"P",
    "gn:feature_code":"PPL",
    "gn:name":"Diamantina",
    "gn:population":0,
    "gn:timezone":"America/Fortaleza",
    "iso:country":"BR",
    "name:ceb_x_preferred":[
        "Diamantina"
    ],
    "name:nld_x_preferred":[
        "Diamantina"
    ],
    "name:pol_x_preferred":[
        "Diamantina"
    ],
    "name:slk_x_preferred":[
        "Diamantina"
    ],
    "name:swe_x_preferred":[
        "Diamantina"
    ],
    "wof:name":"Diamantina",
    "wof:placetype":"locality"
},
  "geometry": {"coordinates":[-41.95,-6.18333],"type":"Point"}
}