{
  "type": "Feature",
  "properties": {
    "gn:admin1_code":"5",
    "gn:admin2_code":"2912905.0",
    "gn:asciiname":"Baixa Alegre",
    "gn:country_code":"BR",
    "gn:dem":185,
    "gn:feature_class":"P",
    "gn:feature_code":"PPL",
    "gn:name":"Baixa Alegre",
    "gn:population":0,
    "gn:timezone":"America/Bahia",
    "iso:country":"BR",
    "wof:name":"Baixa Alegre",
    "wof:placetype":"locality"
},
  "geometry": {"coordinates":[-39.63333,-13.95],"type":"Point"}
}