{
  "type": "Feature",
  "properties": {
    "gn:admin1_code":"4",
    "gn:admin2_code":"1302553.0",
    "gn:asciiname":"Tres Poderes",
    "gn:country_code":"BR",
    "gn:dem":37,
    "gn:feature_class":"P",
    "gn:feature_code":"PPL",
    "gn:name":"Tr\u00eas Poderes",
    "gn:population":0,
    "gn:timezone":"America/Manaus",
    "iso:country":"BR",
    "wof:name":"Tres Poderes",
    "wof:placetype":"locality"
},
  "geometry": {"coordinates":[-60.93639,-4.12444],"type":"Point"}
}