{
  "type": "Feature",
  "properties": {
    "gn:admin1_code":"4.0",
    "gn:admin2_code":"1302405.0",
    "gn:asciiname":"Aruda",
    "gn:country_code":"BR",
    "gn:dem":90,
    "gn:feature_class":"P",
    "gn:feature_code":"PPL",
    "gn:name":"Arud\u00e1",
    "gn:population":0,
    "gn:timezone":"America/Manaus",
    "iso:country":"BR",
    "wof:name":"Aruda",
    "wof:placetype":"locality"
},
  "geometry": {"coordinates":[-66.05195000000001,-7.72046],"type":"Point"}
}