{
  "type": "Feature",
  "properties": {
    "gn:admin1_code":"27.0",
    "gn:admin2_code":"3505401.0",
    "gn:asciiname":"Sitio Ribeirao do Meio",
    "gn:country_code":"BR",
    "gn:dem":224,
    "gn:feature_class":"P",
    "gn:feature_code":"PPL",
    "gn:name":"S\u00edtio Ribeir\u00e3o do Meio",
    "gn:population":0,
    "gn:timezone":"America/Sao_Paulo",
    "iso:country":"BR",
    "name:por_x_preferred":[
        "S\u00edtio Ribeir\u00e3o do Meio"
    ],
    "wof:name":"Sitio Ribeirao do Meio",
    "wof:placetype":"locality"
},
  "geometry": {"coordinates":[-48.4335,-24.7673],"type":"Point"}
}