{
  "type": "Feature",
  "properties": {
    "gn:admin1_code":"27",
    "gn:admin2_code":"3554508.0",
    "gn:asciiname":"Serra",
    "gn:country_code":"BR",
    "gn:dem":537,
    "gn:feature_class":"P",
    "gn:feature_code":"PPLL",
    "gn:name":"Serra",
    "gn:population":0,
    "gn:timezone":"America/Sao_Paulo",
    "iso:country":"BR",
    "name:por_x_preferred":[
        "Serra"
    ],
    "wof:name":"Serra",
    "wof:placetype":"locality"
},
  "geometry": {"coordinates":[-47.67727,-23.10997],"type":"Point"}
}