{
  "type": "Feature",
  "properties": {
    "gn:admin1_code":"8",
    "gn:admin2_code":"3203809.0",
    "gn:asciiname":"Andes",
    "gn:country_code":"BR",
    "gn:dem":421,
    "gn:feature_class":"P",
    "gn:feature_code":"PPL",
    "gn:name":"Andes",
    "gn:population":0,
    "gn:timezone":"America/Sao_Paulo",
    "iso:country":"BR",
    "name:por_x_preferred":[
        "Andes"
    ],
    "wof:name":"Andes",
    "wof:placetype":"locality"
},
  "geometry": {"coordinates":[-41.28333,-20.98333],"type":"Point"}
}