{
  "type": "Feature",
  "properties": {
    "gn:admin1_code":"18.0",
    "gn:admin2_code":"4126009.0",
    "gn:asciiname":"Sitio Antonio I. Sobrinho",
    "gn:country_code":"BR",
    "gn:dem":665,
    "gn:feature_class":"P",
    "gn:feature_code":"PPL",
    "gn:name":"S\u00edtio Ant\u00f4nio I. Sobrinho",
    "gn:population":0,
    "gn:timezone":"America/Sao_Paulo",
    "iso:country":"BR",
    "name:por_x_preferred":[
        "S\u00edtio Ant\u00f4nio I. Sobrinho"
    ],
    "wof:name":"Sitio Antonio I. Sobrinho",
    "wof:placetype":"locality"
},
  "geometry": {"coordinates":[-50.71661,-23.51975],"type":"Point"}
}