{
  "type": "Feature",
  "properties": {
    "gn:admin1_code":"27",
    "gn:admin2_code":"3546801.0",
    "gn:asciiname":"Stio Cachoeira",
    "gn:country_code":"BR",
    "gn:dem":685,
    "gn:feature_class":"P",
    "gn:feature_code":"PPL",
    "gn:name":"Stio Cachoeira",
    "gn:population":0,
    "gn:timezone":"America/Sao_Paulo",
    "iso:country":"BR",
    "name:por_x_preferred":[
        "Stio Cachoeira"
    ],
    "wof:name":"Stio Cachoeira",
    "wof:placetype":"locality"
},
  "geometry": {"coordinates":[-46.1821,-23.2779],"type":"Point"}
}