{
  "type": "Feature",
  "properties": {
    "gn:admin1_code":"5",
    "gn:admin2_code":"2922250.0",
    "gn:asciiname":"Pernambuco",
    "gn:country_code":"BR",
    "gn:dem":426,
    "gn:feature_class":"P",
    "gn:feature_code":"PPL",
    "gn:name":"Pernambuco",
    "gn:population":0,
    "gn:timezone":"America/Bahia",
    "iso:country":"BR",
    "wof:name":"Pernambuco",
    "wof:placetype":"locality"
},
  "geometry": {"coordinates":[-43.21667,-12.68333],"type":"Point"}
}