{
  "type": "Feature",
  "properties": {
    "gn:admin1_code":"20.0",
    "gn:admin2_code":"2203230.0",
    "gn:asciiname":"Riachao",
    "gn:country_code":"BR",
    "gn:dem":375,
    "gn:feature_class":"P",
    "gn:feature_code":"PPL",
    "gn:name":"Riach\u00e3o",
    "gn:population":0,
    "gn:timezone":"America/Fortaleza",
    "iso:country":"BR",
    "name:por_x_preferred":[
        "Riach\u00e3o"
    ],
    "wof:name":"Riachao",
    "wof:placetype":"locality"
},
  "geometry": {"coordinates":[-44.83587,-8.87972],"type":"Point"}
}