{
  "type": "Feature",
  "properties": {
    "gn:admin1_code":"30",
    "gn:admin2_code":"2607406.0",
    "gn:asciiname":"Poco da Roca",
    "gn:country_code":"BR",
    "gn:dem":306,
    "gn:feature_class":"P",
    "gn:feature_code":"PPL",
    "gn:name":"Po\u00e7o da Ro\u00e7a",
    "gn:population":0,
    "gn:timezone":"America/Recife",
    "iso:country":"BR",
    "wof:name":"Poco da Roca",
    "wof:placetype":"locality"
},
  "geometry": {"coordinates":[-38.66667,-8.81667],"type":"Point"}
}