{
  "type": "Feature",
  "properties": {
    "gn:admin1_code":"18.0",
    "gn:admin2_code":"4127882.0",
    "gn:asciiname":"Antinha",
    "gn:country_code":"BR",
    "gn:dem":858,
    "gn:feature_class":"P",
    "gn:feature_code":"PPLL",
    "gn:name":"Antinha",
    "gn:population":0,
    "gn:timezone":"America/Sao_Paulo",
    "iso:country":"BR",
    "name:por_x_preferred":[
        "Antinha"
    ],
    "wof:name":"Antinha",
    "wof:placetype":"locality"
},
  "geometry": {"coordinates":[-48.99394,-24.98026],"type":"Point"}
}