{
  "type": "Feature",
  "properties": {
    "gn:admin1_code":"18.0",
    "gn:admin2_code":"4127882.0",
    "gn:asciiname":"Fundacao",
    "gn:country_code":"BR",
    "gn:dem":888,
    "gn:feature_class":"P",
    "gn:feature_code":"PPLL",
    "gn:name":"Funda\u00e7\u00e3o",
    "gn:population":0,
    "gn:timezone":"America/Sao_Paulo",
    "iso:country":"BR",
    "name:por_x_preferred":[
        "Funda\u00e7\u00e3o"
    ],
    "wof:name":"Fundacao",
    "wof:placetype":"locality"
},
  "geometry": {"coordinates":[-48.81687,-24.99762],"type":"Point"}
}