{
  "type": "Feature",
  "properties": {
    "gn:admin1_code":"11",
    "gn:admin2_code":"5001102.0",
    "gn:asciiname":"Leblon",
    "gn:country_code":"BR",
    "gn:dem":128,
    "gn:feature_class":"P",
    "gn:feature_code":"PPL",
    "gn:name":"Leblon",
    "gn:population":0,
    "gn:timezone":"America/Campo_Grande",
    "iso:country":"BR",
    "name:aze_x_preferred":[
        "Lablon"
    ],
    "name:bel_x_preferred":[
        "\u041b\u0435\u0431\u043b\u043e\u043d"
    ],
    "name:bos_x_preferred":[
        "Leblon"
    ],
    "name:cat_x_preferred":[
        "Leblon"
    ],
    "name:dan_x_preferred":[
        "Leblon"
    ],
    "name:deu_x_preferred":[
        "Leblon"
    ],
    "name:ell_x_preferred":[
        "\u039b\u03b5\u03bc\u03c0\u03bb\u03cc\u03bd"
    ],
    "name:fra_x_preferred":[
        "Leblon"
    ],
    "name:heb_x_preferred":[
        "\u05dc\u05d1\u05dc\u05d5\u05df"
    ],
    "name:hrv_x_preferred":[
        "Leblon"
    ],
    "name:ita_x_preferred":[
        "Leblon"
    ],
    "name:nld_x_preferred":[
        "Leblon"
    ],
    "name:nor_x_preferred":[
        "Leblon"
    ],
    "name:por_x_preferred":[
        "Leblon"
    ],
    "name:ron_x_preferred":[
        "Leblon"
    ],
    "name:rus_x_preferred":[
        "\u041b\u0435\u0431\u043b\u043e\u043d"
    ],
    "name:spa_x_preferred":[
        "Leblon"
    ],
    "name:srp_x_preferred":[
        "\u041b\u0435\u0431\u043b\u043e\u043d"
    ],
    "name:tur_x_preferred":[
        "Leblon"
    ],
    "name:zho_x_preferred":[
        "\u83b1\u4f2f\u4f26"
    ],
    "wof:name":"Leblon",
    "wof:placetype":"locality"
},
  "geometry": {"coordinates":[-56.01667,-19.98333],"type":"Point"}
}