{
  "type": "Feature",
  "properties": {
    "gn:admin1_code":"11",
    "gn:admin2_code":"5001102.0",
    "gn:asciiname":"Leblon",
    "gn:country_code":"BR",
    "gn:dem":128,
    "gn:feature_class":"P",
    "gn:feature_code":"PPL",
    "gn:name":"Leblon",
    "gn:population":0,
    "gn:timezone":"America/Campo_Grande",
    "iso:country":"BR",
    "name:por_x_preferred":[
        "Leblon"
    ],
    "wof:name":"Leblon",
    "wof:placetype":"locality"
},
  "geometry": {"coordinates":[-56.01667,-19.98333],"type":"Point"}
}