{
  "type": "Feature",
  "properties": {
    "gn:admin1_code":"20",
    "gn:admin2_code":"2208502.0",
    "gn:asciiname":"Brasilia",
    "gn:country_code":"BR",
    "gn:dem":51,
    "gn:feature_class":"P",
    "gn:feature_code":"PPL",
    "gn:name":"Bras\u00edlia",
    "gn:population":0,
    "gn:timezone":"America/Fortaleza",
    "iso:country":"BR",
    "wof:name":"Brasilia",
    "wof:placetype":"locality"
},
  "geometry": {"coordinates":[-42.69417,-3.89472],"type":"Point"}
}