{
  "type": "Feature",
  "properties": {
    "gn:admin1_code":"22",
    "gn:admin2_code":"2414456.0",
    "gn:asciiname":"Poco Redondo",
    "gn:country_code":"BR",
    "gn:dem":152,
    "gn:feature_class":"P",
    "gn:feature_code":"PPL",
    "gn:name":"Po\u00e7o Redondo",
    "gn:population":0,
    "gn:timezone":"America/Fortaleza",
    "iso:country":"BR",
    "wof:name":"Poco Redondo",
    "wof:placetype":"locality"
},
  "geometry": {"coordinates":[-37.18972,-5.96667],"type":"Point"}
}