{
  "type": "Feature",
  "properties": {
    "gn:admin1_code":"02",
    "gn:admin2_code":"2704302.0",
    "gn:asciiname":"Saude",
    "gn:cc2":"BR",
    "gn:country_code":"BR",
    "gn:dem":41,
    "gn:feature_class":"P",
    "gn:feature_code":"PPL",
    "gn:name":"Sa\u00fade",
    "gn:population":0,
    "gn:timezone":"America/Maceio",
    "iso:country":"BR",
    "name:und_x_variant":[
        "Meirim",
        "Mirim",
        "Sa\u00fade"
    ],
    "wof:name":"Saude",
    "wof:placetype":"locality"
},
  "geometry": {"coordinates":[-35.61667,-9.51667],"type":"Point"}
}