{
  "type": "Feature",
  "properties": {
    "gn:admin1_code":"18",
    "gn:admin2_code":"4122305.0",
    "gn:asciiname":"Sitio Tereza Silva",
    "gn:country_code":"BR",
    "gn:dem":870,
    "gn:feature_class":"P",
    "gn:feature_code":"PPL",
    "gn:name":"S\u00edtio Tereza Silva",
    "gn:population":0,
    "gn:timezone":"America/Sao_Paulo",
    "iso:country":"BR",
    "name:por_x_preferred":[
        "S\u00edtio Tereza Silva"
    ],
    "wof:name":"Sitio Tereza Silva",
    "wof:placetype":"locality"
},
  "geometry": {"coordinates":[-49.62481,-26.0854],"type":"Point"}
}