{
  "type": "Feature",
  "properties": {
    "gn:admin1_code":"4",
    "gn:admin2_code":"1301407.0",
    "gn:asciiname":"Daiva",
    "gn:country_code":"BR",
    "gn:dem":153,
    "gn:feature_class":"P",
    "gn:feature_code":"PPL",
    "gn:name":"Daiva",
    "gn:population":0,
    "gn:timezone":"America/Eirunepe",
    "iso:country":"BR",
    "wof:name":"Daiva",
    "wof:placetype":"locality"
},
  "geometry": {"coordinates":[-71.02221999999998,-7.34333],"type":"Point"}
}