{
  "type": "Feature",
  "properties": {
    "gn:admin1_code":"20",
    "gn:admin2_code":"2201903.0",
    "gn:asciiname":"Boa Esperanca",
    "gn:cc2":"BR",
    "gn:country_code":"BR",
    "gn:dem":564,
    "gn:feature_class":"P",
    "gn:feature_code":"PPL",
    "gn:name":"Boa Esperan\u00e7a",
    "gn:population":0,
    "gn:timezone":"America/Fortaleza",
    "iso:country":"BR",
    "name:und_x_variant":[
        "Boa Esperaran\u00e7a",
        "Boa Esperan\u00e7a"
    ],
    "wof:name":"Boa Esperanca",
    "wof:placetype":"locality"
},
  "geometry": {"coordinates":[-44.08333,-9.25],"type":"Point"}
}