{
  "type": "Feature",
  "properties": {
    "gn:admin1_code":"18.0",
    "gn:admin2_code":"4109609.0",
    "gn:asciiname":"Sitio Henrique Nigel",
    "gn:country_code":"BR",
    "gn:dem":12,
    "gn:feature_class":"P",
    "gn:feature_code":"PPL",
    "gn:name":"S\u00edtio Henrique Nigel",
    "gn:population":0,
    "gn:timezone":"America/Sao_Paulo",
    "iso:country":"BR",
    "name:por_x_preferred":[
        "S\u00edtio Henrique Nigel"
    ],
    "wof:name":"Sitio Henrique Nigel",
    "wof:placetype":"locality"
},
  "geometry": {"coordinates":[-48.83631,-25.98015],"type":"Point"}
}