{
  "type": "Feature",
  "properties": {
    "gn:admin1_code":"18.0",
    "gn:admin2_code":"4121208.0",
    "gn:asciiname":"Sitio Pedro Barao",
    "gn:country_code":"BR",
    "gn:dem":895,
    "gn:feature_class":"P",
    "gn:feature_code":"PPL",
    "gn:name":"S\u00edtio Pedro Bar\u00e3o",
    "gn:population":0,
    "gn:timezone":"America/Sao_Paulo",
    "iso:country":"BR",
    "name:por_x_preferred":[
        "S\u00edtio Pedro Bar\u00e3o"
    ],
    "wof:name":"Sitio Pedro Barao",
    "wof:placetype":"locality"
},
  "geometry": {"coordinates":[-49.4394,-25.8085],"type":"Point"}
}