{
  "type": "Feature",
  "properties": {
    "gn:admin1_code":"13",
    "gn:admin2_code":"2108256.0",
    "gn:asciiname":"Alto Turi",
    "gn:country_code":"BR",
    "gn:dem":20,
    "gn:feature_class":"P",
    "gn:feature_code":"PPL",
    "gn:name":"Alto Turi",
    "gn:population":0,
    "gn:timezone":"America/Fortaleza",
    "iso:country":"BR",
    "wof:name":"Alto Turi",
    "wof:placetype":"locality"
},
  "geometry": {"coordinates":[-45.63669,-2.89645],"type":"Point"}
}