{
  "type": "Feature",
  "properties": {
    "gn:admin1_code":"22",
    "gn:admin2_code":"2411809.0",
    "gn:asciiname":"Ponta da Serra (2)",
    "gn:country_code":"BR",
    "gn:dem":163,
    "gn:feature_class":"P",
    "gn:feature_code":"PPL",
    "gn:name":"Ponta da Serra (2)",
    "gn:population":0,
    "gn:timezone":"America/Fortaleza",
    "iso:country":"BR",
    "wof:name":"Ponta da Serra (2)",
    "wof:placetype":"locality"
},
  "geometry": {"coordinates":[-37.18333,-6.43333],"type":"Point"}
}