{
  "type": "Feature",
  "properties": {
    "gn:admin1_code":"18.0",
    "gn:admin2_code":"4128534.0",
    "gn:asciiname":"Sitio Aristides A. de Souza",
    "gn:country_code":"BR",
    "gn:dem":599,
    "gn:feature_class":"P",
    "gn:feature_code":"PPL",
    "gn:name":"S\u00edtio Aristides A. de Souza",
    "gn:population":0,
    "gn:timezone":"America/Sao_Paulo",
    "iso:country":"BR",
    "name:por_x_preferred":[
        "S\u00edtio Aristides A. de Souza"
    ],
    "wof:name":"Sitio Aristides A. de Souza",
    "wof:placetype":"locality"
},
  "geometry": {"coordinates":[-50.28388,-23.99226],"type":"Point"}
}