{
  "type": "Feature",
  "properties": {
    "gn:admin1_code":"06",
    "gn:admin2_code":"2303501.0",
    "gn:asciiname":"Mataquiri",
    "gn:country_code":"BR",
    "gn:dem":40,
    "gn:feature_class":"P",
    "gn:feature_code":"PPL",
    "gn:name":"Mataquir\u00ed",
    "gn:population":0,
    "gn:timezone":"America/Fortaleza",
    "iso:country":"BR",
    "wof:name":"Mataquiri",
    "wof:placetype":"locality"
},
  "geometry": {"coordinates":[-38.26667,-4.11667],"type":"Point"}
}