{
  "type": "Feature",
  "properties": {
    "gn:admin1_code":"27.0",
    "gn:admin2_code":"3502705.0",
    "gn:asciiname":"Sitio Takigushi",
    "gn:country_code":"BR",
    "gn:dem":830,
    "gn:feature_class":"P",
    "gn:feature_code":"PPL",
    "gn:name":"S\u00edtio Takigushi",
    "gn:population":0,
    "gn:timezone":"America/Sao_Paulo",
    "iso:country":"BR",
    "name:por_x_preferred":[
        "S\u00edtio Takigushi"
    ],
    "wof:name":"Sitio Takigushi",
    "wof:placetype":"locality"
},
  "geometry": {"coordinates":[-48.80741,-24.53115],"type":"Point"}
}