{
  "type": "Feature",
  "properties": {
    "gn:admin1_code":"27",
    "gn:admin2_code":"3524402.0",
    "gn:asciiname":"Stio Ana Maria Conceio",
    "gn:country_code":"BR",
    "gn:dem":604,
    "gn:feature_class":"P",
    "gn:feature_code":"PPL",
    "gn:name":"Stio Ana Maria Conceio",
    "gn:population":0,
    "gn:timezone":"America/Sao_Paulo",
    "iso:country":"BR",
    "name:por_x_preferred":[
        "Stio Ana Maria Conceio"
    ],
    "wof:name":"Stio Ana Maria Conceio",
    "wof:placetype":"locality"
},
  "geometry": {"coordinates":[-46.0405,-23.3633],"type":"Point"}
}