{
  "type": "Feature",
  "properties": {
    "gn:admin1_code":"27",
    "gn:admin2_code":"3530805.0",
    "gn:asciiname":"Tujucue",
    "gn:cc2":"BR",
    "gn:country_code":"BR",
    "gn:dem":646,
    "gn:feature_class":"P",
    "gn:feature_code":"PPL",
    "gn:name":"Tujucu\u00e9",
    "gn:population":0,
    "gn:timezone":"America/Sao_Paulo",
    "iso:country":"BR",
    "name:und_x_variant":[
        "Benfica",
        "Tujucu\u00e9"
    ],
    "wof:name":"Tujucue",
    "wof:placetype":"locality"
},
  "geometry": {"coordinates":[-46.93333,-22.48333],"type":"Point"}
}