{
  "type": "Feature",
  "properties": {
    "gn:admin1_code":"06",
    "gn:admin2_code":"2306603.0",
    "gn:asciiname":"Lagoa do Mato",
    "gn:country_code":"BR",
    "gn:dem":410,
    "gn:feature_class":"P",
    "gn:feature_code":"PPLL",
    "gn:name":"Lagoa do Mato",
    "gn:population":0,
    "gn:timezone":"America/Fortaleza",
    "iso:country":"BR",
    "wof:name":"Lagoa do Mato",
    "wof:placetype":"locality"
},
  "geometry": {"coordinates":[-39.675,-4.64556],"type":"Point"}
}