{
  "type": "Feature",
  "properties": {
    "gn:admin1_code":"06",
    "gn:admin2_code":"2311801.0",
    "gn:asciiname":"Timbauba (2)",
    "gn:country_code":"BR",
    "gn:dem":24,
    "gn:feature_class":"P",
    "gn:feature_code":"PPL",
    "gn:name":"Timba\u00faba (2)",
    "gn:population":0,
    "gn:timezone":"America/Fortaleza",
    "iso:country":"BR",
    "wof:name":"Timbauba (2)",
    "wof:placetype":"locality"
},
  "geometry": {"coordinates":[-37.96667,-4.98333],"type":"Point"}
}