{
  "type": "Feature",
  "properties": {
    "gn:admin1_code":"15",
    "gn:admin2_code":"3111200.0",
    "gn:asciiname":"Jacutinga",
    "gn:country_code":"BR",
    "gn:dem":982,
    "gn:feature_class":"P",
    "gn:feature_code":"PPL",
    "gn:name":"Jacutinga",
    "gn:population":0,
    "gn:timezone":"America/Sao_Paulo",
    "iso:country":"BR",
    "name:por_x_preferred":[
        "Jacutinga"
    ],
    "wof:name":"Jacutinga",
    "wof:placetype":"locality"
},
  "geometry": {"coordinates":[-45.28333,-20.85],"type":"Point"}
}