{
  "type": "Feature",
  "properties": {
    "gn:admin1_code":"13",
    "gn:admin2_code":"2100600.0",
    "gn:asciiname":"Vargem Limpa",
    "gn:country_code":"BR",
    "gn:dem":294,
    "gn:feature_class":"P",
    "gn:feature_code":"PPL",
    "gn:name":"Vargem Limpa",
    "gn:population":0,
    "gn:timezone":"America/Fortaleza",
    "iso:country":"BR",
    "wof:name":"Vargem Limpa",
    "wof:placetype":"locality"
},
  "geometry": {"coordinates":[-46.13333,-4.96667],"type":"Point"}
}