{
  "type": "Feature",
  "properties": {
    "gn:admin1_code":"18.0",
    "gn:admin2_code":"4103602.0",
    "gn:asciiname":"Sitio Antonio Cortes",
    "gn:country_code":"BR",
    "gn:dem":546,
    "gn:feature_class":"P",
    "gn:feature_code":"PPL",
    "gn:name":"S\u00edtio Ant\u00f4nio Cort\u00eas",
    "gn:population":0,
    "gn:timezone":"America/Sao_Paulo",
    "iso:country":"BR",
    "name:por_x_preferred":[
        "S\u00edtio Ant\u00f4nio Cort\u00eas"
    ],
    "wof:name":"Sitio Antonio Cortes",
    "wof:placetype":"locality"
},
  "geometry": {"coordinates":[-50.1254,-23.07],"type":"Point"}
}