{
  "type": "Feature",
  "properties": {
    "gn:admin1_code":"23",
    "gn:admin2_code":"4301503.0",
    "gn:asciiname":"Doutor Pestana",
    "gn:country_code":"BR",
    "gn:dem":369,
    "gn:feature_class":"P",
    "gn:feature_code":"PPL",
    "gn:name":"Doutor Pestana",
    "gn:population":0,
    "gn:timezone":"America/Sao_Paulo",
    "iso:country":"BR",
    "wof:name":"Doutor Pestana",
    "wof:placetype":"locality"
},
  "geometry": {"coordinates":[-53.98333,-28.51667],"type":"Point"}
}