{
  "type": "Feature",
  "properties": {
    "gn:admin1_code":"26",
    "gn:admin2_code":"4200754.0",
    "gn:asciiname":"Volta Grande",
    "gn:country_code":"BR",
    "gn:dem":408,
    "gn:feature_class":"P",
    "gn:feature_code":"PPL",
    "gn:name":"Volta Grande",
    "gn:population":0,
    "gn:timezone":"America/Sao_Paulo",
    "iso:country":"BR",
    "name:bpy_x_preferred":[
        "\u09ad\u09cb\u09b2\u099f\u09be \u0997\u09cd\u09b0\u09be\u09a8\u09cd\u09a1\u09c7"
    ],
    "name:ceb_x_preferred":[
        "Volta Grande"
    ],
    "name:epo_x_preferred":[
        "Volta Grande"
    ],
    "name:eus_x_preferred":[
        "Volta Grande"
    ],
    "name:fra_x_preferred":[
        "Volta Grande"
    ],
    "name:hye_x_preferred":[
        "\u054e\u0578\u056c\u057f\u0561 \u0533\u0580\u0561\u0576\u0564\u056b"
    ],
    "name:ita_x_preferred":[
        "Volta Grande"
    ],
    "name:kat_x_preferred":[
        "\u10d5\u10dd\u10da\u10e2\u10d0-\u10d2\u10e0\u10d0\u10dc\u10d3\u10d8"
    ],
    "name:kaz_x_preferred":[
        "\u0412\u043e\u043b\u0442\u0430-\u0413\u0440\u0430\u043d\u0434\u0438"
    ],
    "name:mlg_x_preferred":[
        "Volta Grande"
    ],
    "name:nld_x_preferred":[
        "Volta Grande"
    ],
    "name:nor_x_preferred":[
        "Volta Grande"
    ],
    "name:pol_x_preferred":[
        "Volta Grande"
    ],
    "name:por_x_preferred":[
        "Volta Grande"
    ],
    "name:ron_x_preferred":[
        "Volta Grande"
    ],
    "name:rus_x_preferred":[
        "\u0412\u043e\u043b\u0442\u0430-\u0413\u0440\u0430\u043d\u0434\u0438"
    ],
    "name:spa_x_preferred":[
        "Volta Grande"
    ],
    "name:swe_x_preferred":[
        "Volta Grande"
    ],
    "name:vie_x_preferred":[
        "Volta Grande"
    ],
    "name:vol_x_preferred":[
        "Volta Grande"
    ],
    "name:war_x_preferred":[
        "Volta Grande"
    ],
    "name:zho_x_preferred":[
        "\u5927\u6c83\u5c14\u5854"
    ],
    "wof:name":"Volta Grande",
    "wof:placetype":"locality"
},
  "geometry": {"coordinates":[-51.88333,-27.45],"type":"Point"}
}