{
  "type": "Feature",
  "properties": {
    "gn:admin1_code":"26",
    "gn:admin2_code":"4200754.0",
    "gn:asciiname":"Volta Grande",
    "gn:country_code":"BR",
    "gn:dem":408,
    "gn:feature_class":"P",
    "gn:feature_code":"PPL",
    "gn:name":"Volta Grande",
    "gn:population":0,
    "gn:timezone":"America/Sao_Paulo",
    "iso:country":"BR",
    "wof:name":"Volta Grande",
    "wof:placetype":"locality"
},
  "geometry": {"coordinates":[-51.88333,-27.45],"type":"Point"}
}