{
  "type": "Feature",
  "properties": {
    "gn:admin1_code":"5",
    "gn:admin2_code":"2901304.0",
    "gn:asciiname":"Poco d'Agua",
    "gn:country_code":"BR",
    "gn:dem":442,
    "gn:feature_class":"P",
    "gn:feature_code":"PPL",
    "gn:name":"Po\u00e7o d\u2019\u00c1gua",
    "gn:population":0,
    "gn:timezone":"America/Bahia",
    "iso:country":"BR",
    "name:und_x_variant":[
        "Po\u00e7o da \u00c1gua",
        "Po\u00e7o d\u2019\u00c1gua"
    ],
    "wof:name":"Poco d'Agua",
    "wof:placetype":"locality"
},
  "geometry": {"coordinates":[-41.25,-12.86667],"type":"Point"}
}