{
  "type": "Feature",
  "properties": {
    "gn:admin1_code":"27.0",
    "gn:admin2_code":"3505401.0",
    "gn:asciiname":"Sitio Jose Pedro Ramos",
    "gn:country_code":"BR",
    "gn:dem":630,
    "gn:feature_class":"P",
    "gn:feature_code":"PPL",
    "gn:name":"S\u00edtio Jos\u00e9 Pedro Ramos",
    "gn:population":0,
    "gn:timezone":"America/Sao_Paulo",
    "iso:country":"BR",
    "name:por_x_preferred":[
        "S\u00edtio Jos\u00e9 Pedro Ramos"
    ],
    "wof:name":"Sitio Jose Pedro Ramos",
    "wof:placetype":"locality"
},
  "geometry": {"coordinates":[-48.56319000000001,-25.04489],"type":"Point"}
}