{
  "type": "Feature",
  "properties": {
    "gn:admin1_code":"20",
    "gn:admin2_code":"2206951.0",
    "gn:asciiname":"Goiaberira",
    "gn:country_code":"BR",
    "gn:dem":117,
    "gn:feature_class":"P",
    "gn:feature_code":"PPL",
    "gn:name":"Goiaberira",
    "gn:population":0,
    "gn:timezone":"America/Fortaleza",
    "iso:country":"BR",
    "wof:name":"Goiaberira",
    "wof:placetype":"locality"
},
  "geometry": {"coordinates":[-41.86667,-5.35],"type":"Point"}
}