{
  "type": "Feature",
  "properties": {
    "gn:admin1_code":"31",
    "gn:admin2_code":"1709500.0",
    "gn:asciiname":"Retiro",
    "gn:country_code":"BR",
    "gn:dem":268,
    "gn:feature_class":"P",
    "gn:feature_code":"PPL",
    "gn:name":"Retiro",
    "gn:population":0,
    "gn:timezone":"America/Araguaina",
    "iso:country":"BR",
    "wof:name":"Retiro",
    "wof:placetype":"locality"
},
  "geometry": {"coordinates":[-48.81861,-11.71667],"type":"Point"}
}