{
  "type": "Feature",
  "properties": {
    "gn:admin1_code":"23",
    "gn:admin2_code":"4313466.0",
    "gn:asciiname":"Xingu",
    "gn:country_code":"BR",
    "gn:dem":379,
    "gn:feature_class":"P",
    "gn:feature_code":"PPLL",
    "gn:name":"Xingu",
    "gn:population":0,
    "gn:timezone":"America/Sao_Paulo",
    "iso:country":"BR",
    "name:dan_x_preferred":[
        "Xingu"
    ],
    "name:deu_x_preferred":[
        "Xingu"
    ],
    "name:fra_x_preferred":[
        "Xingu"
    ],
    "name:nld_x_preferred":[
        "Xingu"
    ],
    "name:por_x_preferred":[
        "Xingu"
    ],
    "name:rus_x_preferred":[
        "\u0428\u0438\u043d\u0433\u0443"
    ],
    "name:slk_x_preferred":[
        "Xingu"
    ],
    "name:swe_x_preferred":[
        "Xingu"
    ],
    "wof:name":"Xingu",
    "wof:placetype":"locality"
},
  "geometry": {"coordinates":[-53.05722,-27.74667],"type":"Point"}
}