{
  "type": "Feature",
  "properties": {
    "gn:admin1_code":"06",
    "gn:admin2_code":"2301703.0",
    "gn:asciiname":"Calumbi",
    "gn:country_code":"BR",
    "gn:dem":252,
    "gn:feature_class":"P",
    "gn:feature_code":"PPL",
    "gn:name":"Calumbi",
    "gn:population":0,
    "gn:timezone":"America/Fortaleza",
    "iso:country":"BR",
    "name:bpy_x_preferred":[
        "\u0995\u09be\u09b2\u09c1\u09ae\u09ac\u09bf"
    ],
    "name:eus_x_preferred":[
        "Calumbi"
    ],
    "name:fra_x_preferred":[
        "Calumbi"
    ],
    "name:ita_x_preferred":[
        "Calumbi"
    ],
    "name:kat_x_preferred":[
        "\u10d9\u10d0\u10da\u10e3\u10db\u10d1\u10d8"
    ],
    "name:kaz_x_preferred":[
        "\u041a\u0430\u043b\u0443\u043c\u0431\u0438"
    ],
    "name:mlg_x_preferred":[
        "Calumbi"
    ],
    "name:nld_x_preferred":[
        "Calumbi"
    ],
    "name:nor_x_preferred":[
        "Calumbi"
    ],
    "name:pol_x_preferred":[
        "Calumbi"
    ],
    "name:por_x_preferred":[
        "Calumbi"
    ],
    "name:ron_x_preferred":[
        "Calumbi"
    ],
    "name:rus_x_preferred":[
        "\u041a\u0430\u043b\u0443\u043c\u0431\u0438"
    ],
    "name:vie_x_preferred":[
        "Calumbi"
    ],
    "name:vol_x_preferred":[
        "Calumbi"
    ],
    "name:war_x_preferred":[
        "Calumbi"
    ],
    "name:zho_x_preferred":[
        "\u5361\u4f26\u6bd4"
    ],
    "wof:name":"Calumbi",
    "wof:placetype":"locality"
},
  "geometry": {"coordinates":[-38.96667,-6.88333],"type":"Point"}
}