{
  "type": "Feature",
  "properties": {
    "gn:admin1_code":"06",
    "gn:admin2_code":"2301703.0",
    "gn:asciiname":"Calumbi",
    "gn:country_code":"BR",
    "gn:dem":252,
    "gn:feature_class":"P",
    "gn:feature_code":"PPL",
    "gn:name":"Calumbi",
    "gn:population":0,
    "gn:timezone":"America/Fortaleza",
    "iso:country":"BR",
    "wof:name":"Calumbi",
    "wof:placetype":"locality"
},
  "geometry": {"coordinates":[-38.96667,-6.88333],"type":"Point"}
}