{
  "type": "Feature",
  "properties": {
    "gn:admin1_code":"17",
    "gn:admin2_code":"2505105.0",
    "gn:asciiname":"Angico Torto",
    "gn:country_code":"BR",
    "gn:dem":293,
    "gn:feature_class":"P",
    "gn:feature_code":"PPL",
    "gn:name":"Angico Torto",
    "gn:population":0,
    "gn:timezone":"America/Fortaleza",
    "iso:country":"BR",
    "wof:name":"Angico Torto",
    "wof:placetype":"locality"
},
  "geometry": {"coordinates":[-36.08333,-6.41667],"type":"Point"}
}