{
  "type": "Feature",
  "properties": {
    "gn:admin1_code":"15",
    "gn:admin2_code":"3135803.0",
    "gn:asciiname":"Afonso Martins",
    "gn:country_code":"BR",
    "gn:dem":662,
    "gn:feature_class":"P",
    "gn:feature_code":"PPL",
    "gn:name":"Afonso Martins",
    "gn:population":0,
    "gn:timezone":"America/Sao_Paulo",
    "iso:country":"BR",
    "name:ara_x_preferred":[
        "\u0623\u0641\u0648\u0646\u0633\u0648 \u0645\u0627\u0631\u062a\u064a\u0646\u0632"
    ],
    "name:fra_x_preferred":[
        "Afonso Martins"
    ],
    "name:ita_x_preferred":[
        "Afonso Martins"
    ],
    "name:por_x_preferred":[
        "Afonso Martins"
    ],
    "name:rus_x_preferred":[
        "\u041c\u0430\u0440\u0442\u0438\u043d\u0448"
    ],
    "wof:name":"Afonso Martins",
    "wof:placetype":"locality"
},
  "geometry": {"coordinates":[-40.91667,-16.48333],"type":"Point"}
}