{
  "type": "Feature",
  "properties": {
    "gn:admin1_code":"15",
    "gn:admin2_code":"3162450.0",
    "gn:asciiname":"Missoes",
    "gn:country_code":"BR",
    "gn:dem":480,
    "gn:feature_class":"P",
    "gn:feature_code":"PPL",
    "gn:name":"Miss\u00f5es",
    "gn:population":0,
    "gn:timezone":"America/Sao_Paulo",
    "iso:country":"BR",
    "name:und_x_variant":[
        "Niss\u00f5es",
        "S\u00e3o Jo\u00e3o dos Miss\u00f5es",
        "Miss\u00f5es"
    ],
    "wof:name":"Missoes",
    "wof:placetype":"locality"
},
  "geometry": {"coordinates":[-44.07994,-14.88244],"type":"Point"}
}