{
  "type": "Feature",
  "properties": {
    "gn:admin1_code":"20",
    "gn:admin2_code":"2201101.0",
    "gn:asciiname":"Ruinas",
    "gn:country_code":"BR",
    "gn:dem":363,
    "gn:feature_class":"P",
    "gn:feature_code":"PPL",
    "gn:name":"Ru\u00ednas",
    "gn:population":0,
    "gn:timezone":"America/Fortaleza",
    "iso:country":"BR",
    "wof:name":"Ruinas",
    "wof:placetype":"locality"
},
  "geometry": {"coordinates":[-44.11667,-10.03333],"type":"Point"}
}