{
  "type": "Feature",
  "properties": {
    "gn:admin1_code":"20",
    "gn:admin2_code":"2201101.0",
    "gn:asciiname":"Ruinas",
    "gn:country_code":"BR",
    "gn:dem":363,
    "gn:feature_class":"P",
    "gn:feature_code":"PPL",
    "gn:name":"Ru\u00ednas",
    "gn:population":0,
    "gn:timezone":"America/Fortaleza",
    "iso:country":"BR",
    "name:arg_x_preferred":[
        "Arruinas"
    ],
    "name:azb_x_preferred":[
        "\u0631\u0648\u06cc\u0646\u0627\u0633"
    ],
    "name:bel_x_preferred":[
        "\u0420\u0443\u0439\u043d\u0430\u0441"
    ],
    "name:bul_x_preferred":[
        "\u0420\u0443\u0438\u043d\u0430\u0441"
    ],
    "name:cat_x_preferred":[
        "Ruinas"
    ],
    "name:ceb_x_preferred":[
        "Ruinas"
    ],
    "name:ces_x_preferred":[
        "Ruinas"
    ],
    "name:dan_x_preferred":[
        "Ruinas"
    ],
    "name:deu_x_preferred":[
        "Ruinas"
    ],
    "name:epo_x_preferred":[
        "Ruinas"
    ],
    "name:eus_x_preferred":[
        "Ruinas"
    ],
    "name:fas_x_preferred":[
        "\u0631\u0648\u06cc\u0646\u0627\u0633"
    ],
    "name:fin_x_preferred":[
        "Ruinas"
    ],
    "name:fra_x_preferred":[
        "Ruinas"
    ],
    "name:hrv_x_preferred":[
        "Ruinas"
    ],
    "name:hun_x_preferred":[
        "Ruinas"
    ],
    "name:hye_x_preferred":[
        "\u054c\u0578\u0582\u056b\u0576\u0561\u057d"
    ],
    "name:ind_x_preferred":[
        "Ruinas"
    ],
    "name:ita_x_preferred":[
        "Ruinas"
    ],
    "name:jpn_x_preferred":[
        "\u30eb\u30a4\u30fc\u30ca\u30b9"
    ],
    "name:kaz_x_preferred":[
        "\u0420\u0443\u0439\u043d\u0430\u0441"
    ],
    "name:lat_x_preferred":[
        "Ruina"
    ],
    "name:lmo_x_preferred":[
        "Ruinas"
    ],
    "name:msa_x_preferred":[
        "Ruinas"
    ],
    "name:nap_x_preferred":[
        "Ruinas"
    ],
    "name:nld_x_preferred":[
        "Ruinas"
    ],
    "name:nno_x_preferred":[
        "Ruinas"
    ],
    "name:nor_x_preferred":[
        "Ruinas"
    ],
    "name:pms_x_preferred":[
        "Ruinas"
    ],
    "name:pol_x_preferred":[
        "Ruinas"
    ],
    "name:por_x_preferred":[
        "Ruinas"
    ],
    "name:ron_x_preferred":[
        "Ruinas"
    ],
    "name:rus_x_preferred":[
        "\u0420\u0443\u0438\u043d\u0430\u0441"
    ],
    "name:scn_x_preferred":[
        "Ruinas"
    ],
    "name:spa_x_preferred":[
        "Ruinas"
    ],
    "name:sqi_x_preferred":[
        "Ruinas"
    ],
    "name:srd_x_preferred":[
        "Arruinas"
    ],
    "name:srp_x_preferred":[
        "\u0420\u0443\u0438\u043d\u0430\u0441"
    ],
    "name:tgl_x_preferred":[
        "Ruinas"
    ],
    "name:tur_x_preferred":[
        "Ruinas"
    ],
    "name:ukr_x_preferred":[
        "\u0420\u0443\u0457\u043d\u0430\u0441"
    ],
    "name:uzb_x_preferred":[
        "Ruinas"
    ],
    "name:vec_x_preferred":[
        "Ruinas"
    ],
    "name:vie_x_preferred":[
        "Ruinas"
    ],
    "name:vol_x_preferred":[
        "Ruinas"
    ],
    "name:war_x_preferred":[
        "Ruinas"
    ],
    "name:zho_x_preferred":[
        "\u9c81\u4f0a\u7eb3\u65af"
    ],
    "wof:name":"Ruinas",
    "wof:placetype":"locality"
},
  "geometry": {"coordinates":[-44.11667,-10.03333],"type":"Point"}
}