{
  "type": "Feature",
  "properties": {
    "gn:admin1_code":"15",
    "gn:admin2_code":"3168606.0",
    "gn:asciiname":"Francisco Ferreira",
    "gn:country_code":"BR",
    "gn:dem":638,
    "gn:feature_class":"P",
    "gn:feature_code":"PPL",
    "gn:name":"Francisco Ferreira",
    "gn:population":0,
    "gn:timezone":"America/Sao_Paulo",
    "iso:country":"BR",
    "name:por_x_preferred":[
        "Francisco Ferreira"
    ],
    "wof:name":"Francisco Ferreira",
    "wof:placetype":"locality"
},
  "geometry": {"coordinates":[-41.35,-17.55],"type":"Point"}
}