{
  "type": "Feature",
  "properties": {
    "gn:admin1_code":"20",
    "gn:admin2_code":"2210706.0",
    "gn:asciiname":"Residencia",
    "gn:country_code":"BR",
    "gn:dem":363,
    "gn:feature_class":"P",
    "gn:feature_code":"PPL",
    "gn:name":"Resid\u00eancia",
    "gn:population":0,
    "gn:timezone":"America/Fortaleza",
    "iso:country":"BR",
    "wof:name":"Residencia",
    "wof:placetype":"locality"
},
  "geometry": {"coordinates":[-40.95,-7.55],"type":"Point"}
}