{
  "type": "Feature",
  "properties": {
    "gn:admin1_code":"2",
    "gn:admin2_code":"2703601.0",
    "gn:asciiname":"Barreiras",
    "gn:country_code":"BR",
    "gn:dem":-9999,
    "gn:feature_class":"P",
    "gn:feature_code":"PPL",
    "gn:name":"Barreiras",
    "gn:population":0,
    "gn:timezone":"America/Maceio",
    "iso:country":"BR",
    "wof:name":"Barreiras",
    "wof:placetype":"locality"
},
  "geometry": {"coordinates":[-35.26667,-9.11667],"type":"Point"}
}