{
  "type": "Feature",
  "properties": {
    "gn:admin1_code":"13",
    "gn:admin2_code":"2111300.0",
    "gn:asciiname":"Tirirical",
    "gn:country_code":"BR",
    "gn:dem":41,
    "gn:feature_class":"P",
    "gn:feature_code":"PPL",
    "gn:name":"Tirirical",
    "gn:population":0,
    "gn:timezone":"America/Fortaleza",
    "iso:country":"BR",
    "wof:name":"Tirirical",
    "wof:placetype":"locality"
},
  "geometry": {"coordinates":[-44.23333,-2.56667],"type":"Point"}
}