{
  "type": "Feature",
  "properties": {
    "gn:country":"BR",
    "gn:fcode":"PPLL",
    "gn:population":0,
    "iso:country":"BR",
    "qs_pg:aaroncc":"BR",
    "qs_pg:gn_country":"BR",
    "qs_pg:gn_fcode":"PPLL",
    "qs_pg:gn_pop":0,
    "qs_pg:name":"P\u00f4rto Batista",
    "qs_pg:name_adm0":"Brasil",
    "qs_pg:name_adm1":"Rio Grande do Sul",
    "qs_pg:photos_9k":1,
    "qs_pg:photos_9r":1,
    "qs_pg:photos_all":9,
    "qs_pg:photos_sr":0,
    "qs_pg:pop_sr":0,
    "qs_pg:qs_pg_placetype":"locality",
    "qs_pg:qs_pg_placetype_gp":"Town",
    "qs_pg:woe_adm0":23424768,
    "woe:adm0_id":23424768,
    "woe:name_adm0":"Brasil",
    "woe:name_adm1":"Rio Grande do Sul",
    "woe:placetype":"Town",
    "wof:name":"P\u00f4rto Batista",
    "wof:placetype":"locality"
},
  "geometry": {"coordinates":[-51.51806,-29.91194],"type":"Point"}
}