{
  "type": "Feature",
  "properties": {
    "gn:admin1_code":"18.0",
    "gn:admin2_code":"4126603.0",
    "gn:asciiname":"Sitio Joaquim Inacio",
    "gn:country_code":"BR",
    "gn:dem":585,
    "gn:feature_class":"P",
    "gn:feature_code":"PPL",
    "gn:name":"S\u00edtio Joaquim In\u00e1cio",
    "gn:population":0,
    "gn:timezone":"America/Sao_Paulo",
    "iso:country":"BR",
    "name:por_x_preferred":[
        "S\u00edtio Joaquim In\u00e1cio"
    ],
    "wof:name":"Sitio Joaquim Inacio",
    "wof:placetype":"locality"
},
  "geometry": {"coordinates":[-49.813,-23.7082],"type":"Point"}
}