{
  "type": "Feature",
  "properties": {
    "gn:admin1_code":"17",
    "gn:admin2_code":"2508802.0",
    "gn:asciiname":"Monte Fernandes",
    "gn:country_code":"BR",
    "gn:dem":287,
    "gn:feature_class":"P",
    "gn:feature_code":"PPL",
    "gn:name":"Monte Fernandes",
    "gn:population":0,
    "gn:timezone":"America/Fortaleza",
    "iso:country":"BR",
    "wof:name":"Monte Fernandes",
    "wof:placetype":"locality"
},
  "geometry": {"coordinates":[-37.53333,-6.95],"type":"Point"}
}