{
  "type": "Feature",
  "properties": {
    "gn:admin1_code":"18.0",
    "gn:admin2_code":"4127601.0",
    "gn:asciiname":"Sitio Francisco B. Lemos",
    "gn:country_code":"BR",
    "gn:dem":915,
    "gn:feature_class":"P",
    "gn:feature_code":"PPL",
    "gn:name":"S\u00edtio Francisco B. Lemos",
    "gn:population":0,
    "gn:timezone":"America/Sao_Paulo",
    "iso:country":"BR",
    "name:por_x_preferred":[
        "S\u00edtio Francisco B. Lemos"
    ],
    "wof:name":"Sitio Francisco B. Lemos",
    "wof:placetype":"locality"
},
  "geometry": {"coordinates":[-49.03468,-25.91432],"type":"Point"}
}