{
  "type": "Feature",
  "properties": {
    "gn:admin1_code":"18.0",
    "gn:admin2_code":"4116208.0",
    "gn:asciiname":"Sitio Daninho",
    "gn:country_code":"BR",
    "gn:dem":185,
    "gn:feature_class":"P",
    "gn:feature_code":"PPL",
    "gn:name":"S\u00edtio Daninho",
    "gn:population":0,
    "gn:timezone":"America/Sao_Paulo",
    "iso:country":"BR",
    "name:por_x_preferred":[
        "S\u00edtio Daninho"
    ],
    "wof:name":"Sitio Daninho",
    "wof:placetype":"locality"
},
  "geometry": {"coordinates":[-48.8116,-25.5864],"type":"Point"}
}