{
  "type": "Feature",
  "properties": {
    "gn:admin1_code":"05",
    "gn:admin2_code":"2907202.0",
    "gn:asciiname":"Joao Soares",
    "gn:country_code":"BR",
    "gn:dem":490,
    "gn:feature_class":"P",
    "gn:feature_code":"PPL",
    "gn:name":"Jo\u00e3o Soares",
    "gn:population":0,
    "gn:timezone":"America/Bahia",
    "iso:country":"BR",
    "wof:name":"Joao Soares",
    "wof:placetype":"locality"
},
  "geometry": {"coordinates":[-41.65,-9.28333],"type":"Point"}
}