{
  "type": "Feature",
  "properties": {
    "gn:admin1_code":"15",
    "gn:admin2_code":"3134806.0",
    "gn:asciiname":"Lazarino Vieira",
    "gn:country_code":"BR",
    "gn:dem":1008,
    "gn:feature_class":"P",
    "gn:feature_code":"PPL",
    "gn:name":"Lazarino Vieira",
    "gn:population":0,
    "gn:timezone":"America/Sao_Paulo",
    "iso:country":"BR",
    "name:por_x_preferred":[
        "Lazarino Vieira"
    ],
    "wof:name":"Lazarino Vieira",
    "wof:placetype":"locality"
},
  "geometry": {"coordinates":[-46.83333,-21.06667],"type":"Point"}
}