{
  "type": "Feature",
  "properties": {
    "gn:admin1_code":"8",
    "gn:admin2_code":"3205309.0",
    "gn:asciiname":"Camburi",
    "gn:country_code":"BR",
    "gn:dem":0,
    "gn:feature_class":"P",
    "gn:feature_code":"PPL",
    "gn:name":"Camburi",
    "gn:population":0,
    "gn:timezone":"America/Sao_Paulo",
    "iso:country":"BR",
    "name:por_x_preferred":[
        "Camburi"
    ],
    "wof:name":"Camburi",
    "wof:placetype":"locality"
},
  "geometry": {"coordinates":[-40.26667,-20.26667],"type":"Point"}
}