{
  "type": "Feature",
  "properties": {
    "gn:admin1_code":"27.0",
    "gn:admin2_code":"3509254.0",
    "gn:asciiname":"Sitio Pouso Alto",
    "gn:country_code":"BR",
    "gn:dem":49,
    "gn:feature_class":"P",
    "gn:feature_code":"PPL",
    "gn:name":"S\u00edtio Pouso Alto",
    "gn:population":0,
    "gn:timezone":"America/Sao_Paulo",
    "iso:country":"BR",
    "name:por_x_preferred":[
        "S\u00edtio Pouso Alto"
    ],
    "wof:name":"Sitio Pouso Alto",
    "wof:placetype":"locality"
},
  "geometry": {"coordinates":[-48.14907,-24.73696],"type":"Point"}
}