{
  "type": "Feature",
  "properties": {
    "gn:admin1_code":"27",
    "gn:admin2_code":"3546801.0",
    "gn:asciiname":"Stio So Roque",
    "gn:country_code":"BR",
    "gn:dem":642,
    "gn:feature_class":"P",
    "gn:feature_code":"PPL",
    "gn:name":"Stio So Roque",
    "gn:population":0,
    "gn:timezone":"America/Sao_Paulo",
    "iso:country":"BR",
    "name:por_x_preferred":[
        "Stio So Roque"
    ],
    "wof:name":"Stio So Roque",
    "wof:placetype":"locality"
},
  "geometry": {"coordinates":[-46.19,-23.25800000000001],"type":"Point"}
}