{
  "type": "Feature",
  "properties": {
    "gn:admin1_code":"30",
    "gn:admin2_code":"2602803.0",
    "gn:asciiname":"Mulungu",
    "gn:country_code":"BR",
    "gn:dem":744,
    "gn:feature_class":"P",
    "gn:feature_code":"PPL",
    "gn:name":"Mulungu",
    "gn:population":0,
    "gn:timezone":"America/Recife",
    "iso:country":"BR",
    "name:ita_x_preferred":[
        "Mulungu"
    ],
    "name:lit_x_preferred":[
        "Mulungu"
    ],
    "name:swe_x_preferred":[
        "Mulungu"
    ],
    "wof:name":"Mulungu",
    "wof:placetype":"locality"
},
  "geometry": {"coordinates":[-37.13333,-8.63333],"type":"Point"}
}