{
  "type": "Feature",
  "properties": {
    "gn:admin1_code":"13",
    "gn:admin2_code":"2103000.0",
    "gn:asciiname":"Carolina",
    "gn:country_code":"BR",
    "gn:dem":135,
    "gn:feature_class":"P",
    "gn:feature_code":"PPL",
    "gn:name":"Carolina",
    "gn:population":0,
    "gn:timezone":"America/Fortaleza",
    "iso:country":"BR",
    "wof:name":"Carolina",
    "wof:placetype":"locality"
},
  "geometry": {"coordinates":[-43.21667,-5.15],"type":"Point"}
}