{
  "type": "Feature",
  "properties": {
    "gn:admin1_code":"15",
    "gn:admin2_code":"3142809.0",
    "gn:asciiname":"Joao Anacleto Diniz",
    "gn:country_code":"BR",
    "gn:dem":755,
    "gn:feature_class":"P",
    "gn:feature_code":"PPL",
    "gn:name":"Jo\u00e3o Anacleto Diniz",
    "gn:population":0,
    "gn:timezone":"America/Sao_Paulo",
    "iso:country":"BR",
    "name:por_x_preferred":[
        "Jo\u00e3o Anacleto Diniz"
    ],
    "wof:name":"Joao Anacleto Diniz",
    "wof:placetype":"locality"
},
  "geometry": {"coordinates":[-48.96667,-18.55],"type":"Point"}
}