{
  "type": "Feature",
  "properties": {
    "gn:admin1_code":"20",
    "gn:admin2_code":"2207850.0",
    "gn:asciiname":"Malhadinha (1)",
    "gn:country_code":"BR",
    "gn:dem":364,
    "gn:feature_class":"P",
    "gn:feature_code":"PPL",
    "gn:name":"Malhadinha (1)",
    "gn:population":0,
    "gn:timezone":"America/Fortaleza",
    "iso:country":"BR",
    "wof:name":"Malhadinha (1)",
    "wof:placetype":"locality"
},
  "geometry": {"coordinates":[-43.23333,-7.93333],"type":"Point"}
}