{
  "type": "Feature",
  "properties": {
    "gn:admin1_code":"02",
    "gn:admin2_code":"2703304.0",
    "gn:asciiname":"Pau Seco",
    "gn:country_code":"BR",
    "gn:dem":332,
    "gn:feature_class":"P",
    "gn:feature_code":"PPL",
    "gn:name":"Pau S\u00eaco",
    "gn:population":0,
    "gn:timezone":"America/Maceio",
    "iso:country":"BR",
    "wof:name":"Pau Seco",
    "wof:placetype":"locality"
},
  "geometry": {"coordinates":[-37.76667,-9.28333],"type":"Point"}
}