{
  "type": "Feature",
  "properties": {
    "gn:admin1_code":"22",
    "gn:admin2_code":"2412906.0",
    "gn:asciiname":"Malhada do Rio",
    "gn:country_code":"BR",
    "gn:dem":151,
    "gn:feature_class":"P",
    "gn:feature_code":"PPL",
    "gn:name":"Malhada do Rio",
    "gn:population":0,
    "gn:timezone":"America/Fortaleza",
    "iso:country":"BR",
    "wof:name":"Malhada do Rio",
    "wof:placetype":"locality"
},
  "geometry": {"coordinates":[-36.00917000000001,-5.97444],"type":"Point"}
}