{
  "type": "Feature",
  "properties": {
    "gn:admin1_code":"11",
    "gn:admin2_code":"5003207.0",
    "gn:asciiname":"Chicao",
    "gn:country_code":"BR",
    "gn:dem":125,
    "gn:feature_class":"P",
    "gn:feature_code":"PPL",
    "gn:name":"Chic\u00e3o",
    "gn:population":0,
    "gn:timezone":"America/Campo_Grande",
    "iso:country":"BR",
    "wof:name":"Chicao",
    "wof:placetype":"locality"
},
  "geometry": {"coordinates":[-56.28333000000001,-18.43333],"type":"Point"}
}