{
  "type": "Feature",
  "properties": {
    "gn:admin1_code":"16.0",
    "gn:admin2_code":"1500404.0",
    "gn:asciiname":"Sao Miguel",
    "gn:country_code":"BR",
    "gn:dem":23,
    "gn:feature_class":"P",
    "gn:feature_code":"PPL",
    "gn:name":"S\u00e3o Miguel",
    "gn:population":0,
    "gn:timezone":"America/Santarem",
    "iso:country":"BR",
    "name:por_x_preferred":[
        "S\u00e3o Miguel"
    ],
    "wof:name":"Sao Miguel",
    "wof:placetype":"locality"
},
  "geometry": {"coordinates":[-54.79662,-1.74491],"type":"Point"}
}