{
  "type": "Feature",
  "properties": {
    "gn:admin1_code":"18.0",
    "gn:admin2_code":"4117214.0",
    "gn:asciiname":"Sitio Tadashi",
    "gn:country_code":"BR",
    "gn:dem":743,
    "gn:feature_class":"P",
    "gn:feature_code":"PPL",
    "gn:name":"S\u00edtio Tadashi",
    "gn:population":0,
    "gn:timezone":"America/Sao_Paulo",
    "iso:country":"BR",
    "name:por_x_preferred":[
        "S\u00edtio Tadashi"
    ],
    "wof:name":"Sitio Tadashi",
    "wof:placetype":"locality"
},
  "geometry": {"coordinates":[-50.72769,-23.56978],"type":"Point"}
}