{
  "type": "Feature",
  "properties": {
    "gn:admin1_code":"13",
    "gn:admin2_code":"2104800.0",
    "gn:asciiname":"Jucaral",
    "gn:cc2":"BR",
    "gn:country_code":"BR",
    "gn:dem":311,
    "gn:feature_class":"P",
    "gn:feature_code":"PPL",
    "gn:name":"Ju\u00e7aral",
    "gn:population":0,
    "gn:timezone":"America/Fortaleza",
    "iso:country":"BR",
    "name:und_x_variant":[
        "Juissara",
        "Ju\u00e7aral"
    ],
    "wof:name":"Jucaral",
    "wof:placetype":"locality"
},
  "geometry": {"coordinates":[-46.25,-5.93333],"type":"Point"}
}