{
  "type": "Feature",
  "properties": {
    "gn:admin1_code":"17",
    "gn:admin2_code":"2514107.0",
    "gn:asciiname":"Monteirinho",
    "gn:country_code":"BR",
    "gn:dem":1048,
    "gn:feature_class":"P",
    "gn:feature_code":"PPL",
    "gn:name":"Monteirinho",
    "gn:population":0,
    "gn:timezone":"America/Fortaleza",
    "iso:country":"BR",
    "wof:name":"Monteirinho",
    "wof:placetype":"locality"
},
  "geometry": {"coordinates":[-36.75,-8.16667],"type":"Point"}
}