{
  "type": "Feature",
  "properties": {
    "gn:admin1_code":"18.0",
    "gn:admin2_code":"4113205.0",
    "gn:asciiname":"Paiquere",
    "gn:country_code":"BR",
    "gn:dem":817,
    "gn:feature_class":"P",
    "gn:feature_code":"PPLL",
    "gn:name":"Paiquere",
    "gn:population":0,
    "gn:timezone":"America/Sao_Paulo",
    "iso:country":"BR",
    "name:por_x_preferred":[
        "Paiquere"
    ],
    "wof:name":"Paiquere",
    "wof:placetype":"locality"
},
  "geometry": {"coordinates":[-50.03367,-25.67886],"type":"Point"}
}