{
  "type": "Feature",
  "properties": {
    "gn:admin1_code":"02",
    "gn:admin2_code":"2706406.0",
    "gn:asciiname":"Coite",
    "gn:country_code":"BR",
    "gn:dem":136,
    "gn:feature_class":"P",
    "gn:feature_code":"PPL",
    "gn:name":"Coit\u00e9",
    "gn:population":0,
    "gn:timezone":"America/Maceio",
    "iso:country":"BR",
    "wof:name":"Coite",
    "wof:placetype":"locality"
},
  "geometry": {"coordinates":[-37.45,-9.68333],"type":"Point"}
}