{
  "type": "Feature",
  "properties": {
    "gn:admin1_code":"18.0",
    "gn:admin2_code":"4117214.0",
    "gn:asciiname":"Sitio Bom Jesus",
    "gn:country_code":"BR",
    "gn:dem":780,
    "gn:feature_class":"P",
    "gn:feature_code":"PPL",
    "gn:name":"S\u00edtio Bom Jesus",
    "gn:population":0,
    "gn:timezone":"America/Sao_Paulo",
    "iso:country":"BR",
    "name:por_x_preferred":[
        "S\u00edtio Bom Jesus"
    ],
    "wof:name":"Sitio Bom Jesus",
    "wof:placetype":"locality"
},
  "geometry": {"coordinates":[-50.67052,-23.61344],"type":"Point"}
}