{
  "type": "Feature",
  "properties": {
    "gn:admin1_code":"18",
    "gn:admin2_code":"4122305.0",
    "gn:asciiname":"Sitio Joao R. de Lima",
    "gn:country_code":"BR",
    "gn:dem":794,
    "gn:feature_class":"P",
    "gn:feature_code":"PPL",
    "gn:name":"S\u00edtio Jo\u00e3o R. de Lima",
    "gn:population":0,
    "gn:timezone":"America/Sao_Paulo",
    "iso:country":"BR",
    "name:por_x_preferred":[
        "S\u00edtio Jo\u00e3o R. de Lima"
    ],
    "wof:name":"Sitio Joao R. de Lima",
    "wof:placetype":"locality"
},
  "geometry": {"coordinates":[-49.7062,-26.13825],"type":"Point"}
}