{
  "type": "Feature",
  "properties": {
    "gn:admin1_code":"18",
    "gn:admin2_code":"4114302.0",
    "gn:asciiname":"Sitio Lima Cordeiro",
    "gn:country_code":"BR",
    "gn:dem":931,
    "gn:feature_class":"P",
    "gn:feature_code":"PPL",
    "gn:name":"S\u00edtio Lima Cordeiro",
    "gn:population":0,
    "gn:timezone":"America/Sao_Paulo",
    "iso:country":"BR",
    "name:por_x_preferred":[
        "S\u00edtio Lima Cordeiro"
    ],
    "wof:name":"Sitio Lima Cordeiro",
    "wof:placetype":"locality"
},
  "geometry": {"coordinates":[-49.24951,-25.76063],"type":"Point"}
}