{
  "type": "Feature",
  "properties": {
    "iso:country":"BR",
    "name:por_x_preferred":[
        "Subsetor Sul-5"
    ],
    "name:unk_x_variant":[
        "Subsetor Sul-5"
    ],
    "qs:gn_adm0_cc":"BR",
    "qs:gn_local":3451328,
    "qs:local_max":1109,
    "qs:local_sum":2488,
    "qs:localhoods":7,
    "qs:name":"Subsetor Sul-5",
    "qs:name_adm0":"Brasil",
    "qs:name_adm1":"S\u00e3o Paulo",
    "qs:name_adm2":"Ribeir\u00e3o Preto",
    "qs:name_local":"Ribeir\u00e3o Preto",
    "qs:photo_max":586,
    "qs:photo_sum":1069,
    "qs:placetype":"Suburb",
    "qs:quad_count":18,
    "qs:woe_adm0":23424768,
    "qs:woe_adm1":2344868,
    "qs:woe_adm2":12582246,
    "qs:woe_lau":0,
    "qs:woe_local":455903,
    "qs:woe_ver":"7.10.0",
    "wof:lang":[
        "por"
    ],
    "wof:name":"Subsetor Sul-5",
    "wof:placetype":"neighbourhood"
},
  "geometry": {"coordinates":[-47.820485,-21.213531],"type":"Point"}
}