{
  "type": "Feature",
  "properties": {
    "gn:admin1_code":"20",
    "gn:admin2_code":"2201903.0",
    "gn:asciiname":"Sumidouro",
    "gn:country_code":"BR",
    "gn:dem":363,
    "gn:feature_class":"P",
    "gn:feature_code":"PPL",
    "gn:name":"Sumidouro",
    "gn:population":0,
    "gn:timezone":"America/Fortaleza",
    "iso:country":"BR",
    "wof:name":"Sumidouro",
    "wof:placetype":"locality"
},
  "geometry": {"coordinates":[-45.28389,-9.22389],"type":"Point"}
}