{
  "type": "Feature",
  "properties": {
    "gn:admin1_code":"20",
    "gn:admin2_code":"2201903.0",
    "gn:asciiname":"Sumidouro",
    "gn:country_code":"BR",
    "gn:dem":363,
    "gn:feature_class":"P",
    "gn:feature_code":"PPL",
    "gn:name":"Sumidouro",
    "gn:population":0,
    "gn:timezone":"America/Fortaleza",
    "iso:country":"BR",
    "name:bpy_x_preferred":[
        "\u09b8\u09c1\u09ae\u09bf\u09a1\u09cb\u0989\u09b0\u09cb"
    ],
    "name:ceb_x_preferred":[
        "Sumidouro"
    ],
    "name:epo_x_preferred":[
        "Sumidouro"
    ],
    "name:fra_x_preferred":[
        "Sumidouro"
    ],
    "name:ita_x_preferred":[
        "Sumidouro"
    ],
    "name:kat_x_preferred":[
        "\u10e1\u10e3\u10db\u10d8\u10d3\u10dd\u10e0\u10e3"
    ],
    "name:kaz_x_preferred":[
        "\u0421\u0443\u043c\u0438\u0434\u043e\u0440\u0443"
    ],
    "name:nld_x_preferred":[
        "Sumidouro"
    ],
    "name:nor_x_preferred":[
        "Sumidouro"
    ],
    "name:pol_x_preferred":[
        "Sumidouro"
    ],
    "name:ron_x_preferred":[
        "Sumidouro"
    ],
    "name:rus_x_preferred":[
        "\u0421\u0443\u043c\u0438\u0434\u043e\u0440\u0443"
    ],
    "name:spa_x_preferred":[
        "Sumidouro"
    ],
    "name:swe_x_preferred":[
        "Sumidouro"
    ],
    "name:vie_x_preferred":[
        "Sumidouro"
    ],
    "name:vol_x_preferred":[
        "Sumidouro"
    ],
    "name:war_x_preferred":[
        "Sumidouro"
    ],
    "name:zho_x_preferred":[
        "\u82cf\u7c73\u591a\u9c81"
    ],
    "wof:name":"Sumidouro",
    "wof:placetype":"locality"
},
  "geometry": {"coordinates":[-45.28389,-9.22389],"type":"Point"}
}