{
  "type": "Feature",
  "properties": {
    "gn:admin1_code":"4",
    "gn:admin2_code":"1303601.0",
    "gn:asciiname":"Iaunari",
    "gn:country_code":"BR",
    "gn:dem":41,
    "gn:feature_class":"P",
    "gn:feature_code":"PPL",
    "gn:name":"Iaunari",
    "gn:population":0,
    "gn:timezone":"America/Manaus",
    "iso:country":"BR",
    "wof:name":"Iaunari",
    "wof:placetype":"locality"
},
  "geometry": {"coordinates":[-64.83333,-0.51667],"type":"Point"}
}