{
  "type": "Feature",
  "properties": {
    "gn:admin1_code":"04",
    "gn:admin2_code":"1302900.0",
    "gn:asciiname":"Macauari",
    "gn:cc2":"BR",
    "gn:country_code":"BR",
    "gn:dem":18,
    "gn:feature_class":"P",
    "gn:feature_code":"PPL",
    "gn:name":"Macauari",
    "gn:population":0,
    "gn:timezone":"America/Manaus",
    "iso:country":"BR",
    "name:und_x_variant":[
        "Macuari",
        "Macauary",
        "Macavari",
        "Macauari"
    ],
    "wof:name":"Macauari",
    "wof:placetype":"locality"
},
  "geometry": {"coordinates":[-57.58333,-4.13333],"type":"Point"}
}