{
  "type": "Feature",
  "properties": {
    "gn:admin1_code":"27",
    "gn:admin2_code":"3504107.0",
    "gn:asciiname":"Jardim Brogota",
    "gn:country_code":"BR",
    "gn:dem":809,
    "gn:feature_class":"P",
    "gn:feature_code":"PPL",
    "gn:name":"Jardim Brogot\u00e1",
    "gn:population":0,
    "gn:timezone":"America/Sao_Paulo",
    "iso:country":"BR",
    "name:por_x_preferred":[
        "Jardim Brogot\u00e1"
    ],
    "wof:name":"Jardim Brogota",
    "wof:placetype":"locality"
},
  "geometry": {"coordinates":[-46.54028,-23.09333],"type":"Point"}
}