{
  "type": "Feature",
  "properties": {
    "gn:admin1_code":"18.0",
    "gn:admin2_code":"4124707.0",
    "gn:asciiname":"Sitio Santa Teresinha",
    "gn:country_code":"BR",
    "gn:dem":1024,
    "gn:feature_class":"P",
    "gn:feature_code":"PPL",
    "gn:name":"S\u00edtio Santa Teresinha",
    "gn:population":0,
    "gn:timezone":"America/Sao_Paulo",
    "iso:country":"BR",
    "name:por_x_preferred":[
        "S\u00edtio Santa Teresinha"
    ],
    "wof:name":"Sitio Santa Teresinha",
    "wof:placetype":"locality"
},
  "geometry": {"coordinates":[-50.79652,-23.79392],"type":"Point"}
}