{
  "type": "Feature",
  "properties": {
    "gn:admin1_code":"22",
    "gn:admin2_code":"2400307.0",
    "gn:asciiname":"Santa Luiza",
    "gn:country_code":"BR",
    "gn:dem":63,
    "gn:feature_class":"P",
    "gn:feature_code":"PPL",
    "gn:name":"Santa Luiza",
    "gn:population":0,
    "gn:timezone":"America/Fortaleza",
    "iso:country":"BR",
    "wof:name":"Santa Luiza",
    "wof:placetype":"locality"
},
  "geometry": {"coordinates":[-36.7425,-5.4475],"type":"Point"}
}