{
  "type": "Feature",
  "properties": {
    "gn:admin1_code":"18.0",
    "gn:admin2_code":"4124301.0",
    "gn:asciiname":"Sitio Sao Paulo",
    "gn:country_code":"BR",
    "gn:dem":753,
    "gn:feature_class":"P",
    "gn:feature_code":"PPL",
    "gn:name":"S\u00edtio S\u00e3o Paulo",
    "gn:population":0,
    "gn:timezone":"America/Sao_Paulo",
    "iso:country":"BR",
    "name:por_x_preferred":[
        "S\u00edtio S\u00e3o Paulo"
    ],
    "wof:name":"Sitio Sao Paulo",
    "wof:placetype":"locality"
},
  "geometry": {"coordinates":[-50.67232,-23.5557],"type":"Point"}
}