{
  "type": "Feature",
  "properties": {
    "gn:admin1_code":"15",
    "gn:admin2_code":"3126703.0",
    "gn:asciiname":"Vaca Brava",
    "gn:country_code":"BR",
    "gn:dem":621,
    "gn:feature_class":"P",
    "gn:feature_code":"PPL",
    "gn:name":"Vaca Brava",
    "gn:population":0,
    "gn:timezone":"America/Sao_Paulo",
    "iso:country":"BR",
    "name:por_x_preferred":[
        "Vaca Brava"
    ],
    "wof:name":"Vaca Brava",
    "wof:placetype":"locality"
},
  "geometry": {"coordinates":[-43.65,-16.56667],"type":"Point"}
}