{
  "type": "Feature",
  "properties": {
    "gn:admin1_code":"18.0",
    "gn:admin2_code":"4116208.0",
    "gn:asciiname":"Sitio Luis C. de Franca",
    "gn:country_code":"BR",
    "gn:dem":100,
    "gn:feature_class":"P",
    "gn:feature_code":"PPL",
    "gn:name":"S\u00edtio Luis C. de Fran\u00e7a",
    "gn:population":0,
    "gn:timezone":"America/Sao_Paulo",
    "iso:country":"BR",
    "name:por_x_preferred":[
        "S\u00edtio Luis C. de Fran\u00e7a"
    ],
    "wof:name":"Sitio Luis C. de Franca",
    "wof:placetype":"locality"
},
  "geometry": {"coordinates":[-48.8983,-25.5273],"type":"Point"}
}