{
  "type": "Feature",
  "properties": {
    "gn:admin1_code":"18",
    "gn:admin2_code":"4110706.0",
    "gn:asciiname":"Vila Raquel",
    "gn:country_code":"BR",
    "gn:dem":848,
    "gn:feature_class":"P",
    "gn:feature_code":"PPL",
    "gn:name":"Vila Raquel",
    "gn:population":0,
    "gn:timezone":"America/Sao_Paulo",
    "iso:country":"BR",
    "name:por_x_preferred":[
        "Vila Raquel"
    ],
    "wof:name":"Vila Raquel",
    "wof:placetype":"locality"
},
  "geometry": {"coordinates":[-50.66112,-25.50769],"type":"Point"}
}