{
  "type": "Feature",
  "properties": {
    "gn:admin1_code":"6",
    "gn:admin2_code":"2301950.0",
    "gn:asciiname":"Arua",
    "gn:country_code":"BR",
    "gn:dem":97,
    "gn:feature_class":"P",
    "gn:feature_code":"PPL",
    "gn:name":"Aru\u00e1",
    "gn:population":0,
    "gn:timezone":"America/Fortaleza",
    "iso:country":"BR",
    "wof:name":"Arua",
    "wof:placetype":"locality"
},
  "geometry": {"coordinates":[-38.58333,-4.33333],"type":"Point"}
}