{
  "type": "Feature",
  "properties": {
    "gn:admin1_code":"4",
    "gn:admin2_code":"1301209.0",
    "gn:asciiname":"Camara",
    "gn:country_code":"BR",
    "gn:dem":33,
    "gn:feature_class":"P",
    "gn:feature_code":"PPL",
    "gn:name":"Camar\u00e1",
    "gn:population":0,
    "gn:timezone":"America/Manaus",
    "iso:country":"BR",
    "name:cat_x_preferred":[
        "Cambra"
    ],
    "name:deu_x_preferred":[
        "Camara"
    ],
    "name:epo_x_preferred":[
        "Camara"
    ],
    "name:fra_x_preferred":[
        "Camara"
    ],
    "name:ita_x_preferred":[
        "Camara"
    ],
    "name:jpn_x_preferred":[
        "\u30ab\u30de\u30e9"
    ],
    "name:lit_x_preferred":[
        "Camara"
    ],
    "name:nld_x_preferred":[
        "Camara"
    ],
    "name:scn_x_preferred":[
        "C\u00e0mmara"
    ],
    "name:spa_x_preferred":[
        "C\u00e1mara"
    ],
    "name:ukr_x_preferred":[
        "\u041a\u0430\u043c\u0430\u0440\u0430"
    ],
    "name:und_x_variant":[
        "Camar\u00e1",
        "Vila Camar\u00e1"
    ],
    "name:vec_x_preferred":[
        "C\u00e0mara"
    ],
    "wof:name":"Camara",
    "wof:placetype":"locality"
},
  "geometry": {"coordinates":[-62.61615,-3.92615],"type":"Point"}
}