{
  "type": "Feature",
  "properties": {
    "gn:admin1_code":"27",
    "gn:admin2_code":"3540606.0",
    "gn:asciiname":"Sitio Itaguacu",
    "gn:country_code":"BR",
    "gn:dem":567,
    "gn:feature_class":"P",
    "gn:feature_code":"PPL",
    "gn:name":"S\u00edtio Itagua\u00e7u",
    "gn:population":0,
    "gn:timezone":"America/Sao_Paulo",
    "iso:country":"BR",
    "name:por_x_preferred":[
        "S\u00edtio Itagua\u00e7u"
    ],
    "wof:name":"Sitio Itaguacu",
    "wof:placetype":"locality"
},
  "geometry": {"coordinates":[-47.57444,-23.12806],"type":"Point"}
}