{
  "type": "Feature",
  "properties": {
    "gn:admin1_code":"06",
    "gn:admin2_code":"2302800.0",
    "gn:asciiname":"Fazenda Veneza",
    "gn:country_code":"BR",
    "gn:dem":211,
    "gn:feature_class":"P",
    "gn:feature_code":"PPL",
    "gn:name":"Fazenda Veneza",
    "gn:population":0,
    "gn:timezone":"America/Fortaleza",
    "iso:country":"BR",
    "wof:name":"Fazenda Veneza",
    "wof:placetype":"locality"
},
  "geometry": {"coordinates":[-39.16667,-4.56667],"type":"Point"}
}