{
  "type": "Feature",
  "properties": {
    "gn:admin1_code":"27.0",
    "gn:admin2_code":"3505401.0",
    "gn:asciiname":"Abertinha",
    "gn:country_code":"BR",
    "gn:dem":218,
    "gn:feature_class":"P",
    "gn:feature_code":"PPLL",
    "gn:name":"Abertinha",
    "gn:population":0,
    "gn:timezone":"America/Sao_Paulo",
    "iso:country":"BR",
    "name:por_x_preferred":[
        "Abertinha"
    ],
    "wof:name":"Abertinha",
    "wof:placetype":"locality"
},
  "geometry": {"coordinates":[-48.5365,-24.8867],"type":"Point"}
}