{
  "type": "Feature",
  "properties": {
    "gn:admin1_code":"20",
    "gn:admin2_code":"2206050.0",
    "gn:asciiname":"Fazenda Malhadinha",
    "gn:country_code":"BR",
    "gn:dem":241,
    "gn:feature_class":"P",
    "gn:feature_code":"PPL",
    "gn:name":"Fazenda Malhadinha",
    "gn:population":0,
    "gn:timezone":"America/Fortaleza",
    "iso:country":"BR",
    "wof:name":"Fazenda Malhadinha",
    "wof:placetype":"locality"
},
  "geometry": {"coordinates":[-41.11667,-7.53333],"type":"Point"}
}