{
  "type": "Feature",
  "properties": {
    "gn:admin1_code":"4.0",
    "gn:admin2_code":"1302405.0",
    "gn:asciiname":"Seringal Morongaba",
    "gn:country_code":"BR",
    "gn:dem":100,
    "gn:feature_class":"P",
    "gn:feature_code":"PPL",
    "gn:name":"Seringal Morongaba",
    "gn:population":0,
    "gn:timezone":"America/Manaus",
    "iso:country":"BR",
    "wof:name":"Seringal Morongaba",
    "wof:placetype":"locality"
},
  "geometry": {"coordinates":[-66.32254,-7.60752],"type":"Point"}
}