{
  "type": "Feature",
  "properties": {
    "gn:admin1_code":"18",
    "gn:admin2_code":"4127601.0",
    "gn:asciiname":"Sitio Ramelo",
    "gn:country_code":"BR",
    "gn:dem":923,
    "gn:feature_class":"P",
    "gn:feature_code":"PPL",
    "gn:name":"S\u00edtio Ramelo",
    "gn:population":0,
    "gn:timezone":"America/Sao_Paulo",
    "iso:country":"BR",
    "name:por_x_preferred":[
        "S\u00edtio Ramelo"
    ],
    "wof:name":"Sitio Ramelo",
    "wof:placetype":"locality"
},
  "geometry": {"coordinates":[-49.1048,-25.8626],"type":"Point"}
}