{
  "type": "Feature",
  "properties": {
    "gn:admin1_code":"16.0",
    "gn:admin2_code":"1505304.0",
    "gn:asciiname":"Aldeia Mapuera",
    "gn:country_code":"BR",
    "gn:dem":94,
    "gn:feature_class":"P",
    "gn:feature_code":"PPL",
    "gn:name":"Aldeia Mapuera",
    "gn:population":0,
    "gn:timezone":"America/Santarem",
    "iso:country":"BR",
    "name:por_x_preferred":[
        "Aldeia Mapuera"
    ],
    "wof:name":"Aldeia Mapuera",
    "wof:placetype":"locality"
},
  "geometry": {"coordinates":[-58.09345,-0.5556],"type":"Point"}
}