{
  "type": "Feature",
  "properties": {
    "gn:admin1_code":"18",
    "gn:admin2_code":"4114609.0",
    "gn:asciiname":"Porto Artaza",
    "gn:cc2":"BR",
    "gn:country_code":"BR",
    "gn:dem":251,
    "gn:feature_class":"P",
    "gn:feature_code":"PPL",
    "gn:name":"P\u00f4rto Artaza",
    "gn:population":0,
    "gn:timezone":"America/Sao_Paulo",
    "iso:country":"BR",
    "name:und_x_variant":[
        "Porto Alica",
        "P\u00f4rto Artaza"
    ],
    "wof:name":"Porto Artaza",
    "wof:placetype":"locality"
},
  "geometry": {"coordinates":[-54.29018000000001,-24.52647],"type":"Point"}
}