{
  "type": "Feature",
  "properties": {
    "gn:admin1_code":"18.0",
    "gn:admin2_code":"4119202.0",
    "gn:asciiname":"Sitio Sergio I. Rodrigues",
    "gn:country_code":"BR",
    "gn:dem":849,
    "gn:feature_class":"P",
    "gn:feature_code":"PPL",
    "gn:name":"S\u00edtio S\u00e9rgio I. Rodrigues",
    "gn:population":0,
    "gn:timezone":"America/Sao_Paulo",
    "iso:country":"BR",
    "name:por_x_preferred":[
        "S\u00edtio S\u00e9rgio I. Rodrigues"
    ],
    "wof:name":"Sitio Sergio I. Rodrigues",
    "wof:placetype":"locality"
},
  "geometry": {"coordinates":[-50.07029,-23.89694],"type":"Point"}
}