{
  "type": "Feature",
  "properties": {
    "gn:admin1_code":"25",
    "gn:admin2_code":"1400100.0",
    "gn:asciiname":"Noe",
    "gn:cc2":"BR",
    "gn:country_code":"BR",
    "gn:dem":76,
    "gn:feature_class":"P",
    "gn:feature_code":"PPL",
    "gn:name":"No\u00ea",
    "gn:population":0,
    "gn:timezone":"America/Boa_Vista",
    "iso:country":"BR",
    "name:und_x_variant":[
        "Nova Olinda",
        "No\u00ea"
    ],
    "wof:name":"Noe",
    "wof:placetype":"locality"
},
  "geometry": {"coordinates":[-60.75,2.86667],"type":"Point"}
}