{
  "type": "Feature",
  "properties": {
    "gn:admin1_code":"14",
    "gn:admin2_code":"5103502.0",
    "gn:asciiname":"Nova",
    "gn:country_code":"BR",
    "gn:dem":376,
    "gn:feature_class":"P",
    "gn:feature_code":"PPL",
    "gn:name":"Nova",
    "gn:population":0,
    "gn:timezone":"America/Cuiaba",
    "iso:country":"BR",
    "name:por_x_preferred":[
        "Nova"
    ],
    "wof:name":"Nova",
    "wof:placetype":"locality"
},
  "geometry": {"coordinates":[-56.28333000000001,-14.15],"type":"Point"}
}