{
  "type": "Feature",
  "properties": {
    "gn:admin1_code":"27.0",
    "gn:admin2_code":"3550605.0",
    "gn:asciiname":"Soroca Mirim",
    "gn:country_code":"BR",
    "gn:dem":913,
    "gn:feature_class":"P",
    "gn:feature_code":"PPLL",
    "gn:name":"Soroca Mirim",
    "gn:population":0,
    "gn:timezone":"America/Sao_Paulo",
    "iso:country":"BR",
    "name:por_x_preferred":[
        "Soroca Mirim"
    ],
    "wof:name":"Soroca Mirim",
    "wof:placetype":"locality"
},
  "geometry": {"coordinates":[-47.15386,-23.57742],"type":"Point"}
}