{
  "type": "Feature",
  "properties": {
    "gn:admin1_code":"15",
    "gn:admin2_code":"3165404.0",
    "gn:asciiname":"Rodeio",
    "gn:country_code":"BR",
    "gn:dem":968,
    "gn:feature_class":"P",
    "gn:feature_code":"PPLL",
    "gn:name":"Rodeio",
    "gn:population":0,
    "gn:timezone":"America/Sao_Paulo",
    "iso:country":"BR",
    "name:por_x_preferred":[
        "Rodeio"
    ],
    "wof:name":"Rodeio",
    "wof:placetype":"locality"
},
  "geometry": {"coordinates":[-45.72009,-22.7485],"type":"Point"}
}