{
  "type": "Feature",
  "properties": {
    "gn:admin1_code":"15",
    "gn:admin2_code":"3165404.0",
    "gn:asciiname":"Rodeio",
    "gn:country_code":"BR",
    "gn:dem":968,
    "gn:feature_class":"P",
    "gn:feature_code":"PPLL",
    "gn:name":"Rodeio",
    "gn:population":0,
    "gn:timezone":"America/Sao_Paulo",
    "iso:country":"BR",
    "name:bpy_x_preferred":[
        "\u09b0\u09cb\u09a1\u09c7\u0987\u0993"
    ],
    "name:ceb_x_preferred":[
        "Rodeio"
    ],
    "name:eus_x_preferred":[
        "Rodeio"
    ],
    "name:fra_x_preferred":[
        "Rodeio"
    ],
    "name:ina_x_preferred":[
        "Rodeio"
    ],
    "name:ita_x_preferred":[
        "Rodeio"
    ],
    "name:nld_x_preferred":[
        "Rodeio"
    ],
    "name:nor_x_preferred":[
        "Rodeio"
    ],
    "name:oci_x_preferred":[
        "Rodeio"
    ],
    "name:pol_x_preferred":[
        "Rodeio"
    ],
    "name:por_x_preferred":[
        "Rodeio"
    ],
    "name:ron_x_preferred":[
        "Rodeio"
    ],
    "name:rus_x_preferred":[
        "\u0420\u043e\u0434\u0435\u044e"
    ],
    "name:swe_x_preferred":[
        "Rodeio"
    ],
    "name:vie_x_preferred":[
        "Rodeio"
    ],
    "name:vol_x_preferred":[
        "Rodeio"
    ],
    "name:war_x_preferred":[
        "Rodeio"
    ],
    "name:zho_x_preferred":[
        "\u7f57\u5fb7\u5c24"
    ],
    "wof:name":"Rodeio",
    "wof:placetype":"locality"
},
  "geometry": {"coordinates":[-45.72009,-22.7485],"type":"Point"}
}