{
  "type": "Feature",
  "properties": {
    "iso:country":"BR",
    "name:por_x_preferred":[
        "Centro"
    ],
    "name:unk_x_variant":[
        "Centro"
    ],
    "qs:gn_adm0_cc":"BR",
    "qs:gn_local":3450269,
    "qs:gn_nam_loc":"Santa Cruz do Sul, Rio Grande do Sul, BR",
    "qs:gn_namadm1":"23",
    "qs:local_max":129,
    "qs:local_sum":130,
    "qs:localhoods":2,
    "qs:name":"Centro",
    "qs:name_adm0":"Brasil",
    "qs:name_adm1":"Rio Grande do Sul",
    "qs:name_adm2":"Santa Cruz do Sul",
    "qs:name_local":"Santa Cruz do Sul",
    "qs:photo_max":28,
    "qs:photo_sum":129,
    "qs:placetype":"Suburb",
    "qs:quad_count":14,
    "qs:woe_adm0":23424768,
    "qs:woe_adm1":2344864,
    "qs:woe_adm2":12581473,
    "qs:woe_lau":0,
    "qs:woe_local":455988,
    "qs:woe_ver":"7.10.0",
    "wof:lang":[
        "por"
    ],
    "wof:name":"Centro",
    "wof:placetype":"neighbourhood"
},
  "geometry": {"coordinates":[-52.429442,-29.713934],"type":"Point"}
}