{
  "type": "Feature",
  "properties": {
    "gn:admin1_code":"13",
    "gn:admin2_code":"2101251.0",
    "gn:asciiname":"Perises",
    "gn:cc2":"BR",
    "gn:country_code":"BR",
    "gn:dem":12,
    "gn:feature_class":"P",
    "gn:feature_code":"PPL",
    "gn:name":"Perises",
    "gn:population":0,
    "gn:timezone":"America/Fortaleza",
    "iso:country":"BR",
    "name:und_x_variant":[
        "Perizes",
        "Perises"
    ],
    "wof:name":"Perises",
    "wof:placetype":"locality"
},
  "geometry": {"coordinates":[-44.35,-2.91667],"type":"Point"}
}