{
  "type": "Feature",
  "properties": {
    "gn:admin1_code":"26.0",
    "gn:admin2_code":"4205407.0",
    "gn:asciiname":"Praia de Mocambique",
    "gn:country_code":"BR",
    "gn:dem":3,
    "gn:elevation":"2.0",
    "gn:feature_class":"P",
    "gn:feature_code":"PPLL",
    "gn:name":"Praia de Mocambique",
    "gn:population":0,
    "gn:timezone":"America/Sao_Paulo",
    "iso:country":"BR",
    "wof:name":"Praia de Mocambique",
    "wof:placetype":"locality"
},
  "geometry": {"coordinates":[-48.41589000000001,-27.52076],"type":"Point"}
}