{
  "type": "Feature",
  "properties": {
    "gn:admin1_code":"13",
    "gn:admin2_code":"2100907.0",
    "gn:asciiname":"Lagoa do Barro",
    "gn:country_code":"BR",
    "gn:dem":23,
    "gn:feature_class":"P",
    "gn:feature_code":"PPL",
    "gn:name":"Lagoa do Barro",
    "gn:population":0,
    "gn:timezone":"America/Fortaleza",
    "iso:country":"BR",
    "wof:name":"Lagoa do Barro",
    "wof:placetype":"locality"
},
  "geometry": {"coordinates":[-42.28861,-3.08889],"type":"Point"}
}