{
  "type": "Feature",
  "properties": {
    "gn:admin1_code":"18.0",
    "gn:admin2_code":"4122305.0",
    "gn:asciiname":"Sitio Benedito Correia",
    "gn:country_code":"BR",
    "gn:dem":853,
    "gn:feature_class":"P",
    "gn:feature_code":"PPL",
    "gn:name":"S\u00edtio Benedito Correia",
    "gn:population":0,
    "gn:timezone":"America/Sao_Paulo",
    "iso:country":"BR",
    "name:por_x_preferred":[
        "S\u00edtio Benedito Correia"
    ],
    "wof:name":"Sitio Benedito Correia",
    "wof:placetype":"locality"
},
  "geometry": {"coordinates":[-49.8431,-26.0436],"type":"Point"}
}