{
  "type": "Feature",
  "properties": {
    "gn:admin1_code":"15",
    "gn:admin2_code":"3121209.0",
    "gn:asciiname":"Iacaia",
    "gn:country_code":"BR",
    "gn:dem":718,
    "gn:feature_class":"P",
    "gn:feature_code":"PPL",
    "gn:name":"Iacai\u00e1",
    "gn:population":0,
    "gn:timezone":"America/Sao_Paulo",
    "iso:country":"BR",
    "name:por_x_preferred":[
        "Iacai\u00e1"
    ],
    "wof:name":"Iacaia",
    "wof:placetype":"locality"
},
  "geometry": {"coordinates":[-46.73333,-20.43333],"type":"Point"}
}