{
  "type": "Feature",
  "properties": {
    "gn:admin1_code":"18",
    "gn:admin2_code":"4125506.0",
    "gn:asciiname":"Sitio Jose Moura",
    "gn:country_code":"BR",
    "gn:dem":941,
    "gn:feature_class":"P",
    "gn:feature_code":"PPL",
    "gn:name":"S\u00edtio Jos\u00e9 Moura",
    "gn:population":0,
    "gn:timezone":"America/Sao_Paulo",
    "iso:country":"BR",
    "name:por_x_preferred":[
        "S\u00edtio Jos\u00e9 Moura"
    ],
    "wof:name":"Sitio Jose Moura",
    "wof:placetype":"locality"
},
  "geometry": {"coordinates":[-49.2219,-25.7515],"type":"Point"}
}