{
  "type": "Feature",
  "properties": {
    "gn:admin1_code":"18",
    "gn:admin2_code":"4107751.0",
    "gn:asciiname":"Bairro Cambui",
    "gn:country_code":"BR",
    "gn:dem":605,
    "gn:feature_class":"P",
    "gn:feature_code":"PPL",
    "gn:name":"Bairro Cambu\u00ed",
    "gn:population":0,
    "gn:timezone":"America/Sao_Paulo",
    "iso:country":"BR",
    "name:por_x_preferred":[
        "Bairro Cambu\u00ed"
    ],
    "name:por_x_variant":[
        "Cambu\u00ed\u00ed",
        "Cambu\u00ed",
        "Cambi\u00fa"
    ],
    "name:und_x_variant":[
        "Cambi\u00fa",
        "Cambu\u00ed\u00ed",
        "Cambu\u00ed"
    ],
    "wof:name":"Bairro Cambui",
    "wof:placetype":"locality"
},
  "geometry": {"coordinates":[-50.41775,-23.86424],"type":"Point"}
}