{
  "type": "Feature",
  "properties": {
    "gn:admin1_code":"27",
    "gn:admin2_code":"3518305.0",
    "gn:asciiname":"Recanto Campestre",
    "gn:country_code":"BR",
    "gn:dem":649,
    "gn:feature_class":"P",
    "gn:feature_code":"PPL",
    "gn:name":"Recanto Campestre",
    "gn:population":0,
    "gn:timezone":"America/Sao_Paulo",
    "iso:country":"BR",
    "name:por_x_preferred":[
        "Recanto Campestre"
    ],
    "wof:name":"Recanto Campestre",
    "wof:placetype":"locality"
},
  "geometry": {"coordinates":[-46.0822,-23.3424],"type":"Point"}
}