{
  "type": "Feature",
  "properties": {
    "gn:admin1_code":"30",
    "gn:admin2_code":"2605707.0",
    "gn:asciiname":"Capim",
    "gn:country_code":"BR",
    "gn:dem":417,
    "gn:feature_class":"P",
    "gn:feature_code":"PPL",
    "gn:name":"Capim",
    "gn:population":0,
    "gn:timezone":"America/Recife",
    "iso:country":"BR",
    "name:bpy_x_preferred":[
        "\u0995\u09be\u09aa\u09bf\u09ae"
    ],
    "name:ceb_x_preferred":[
        "Capim"
    ],
    "name:eus_x_preferred":[
        "Capim"
    ],
    "name:fra_x_preferred":[
        "Capim"
    ],
    "name:hye_x_preferred":[
        "\u053f\u0561\u057a\u056b\u0576"
    ],
    "name:ita_x_preferred":[
        "Capim"
    ],
    "name:kat_x_preferred":[
        "\u10d9\u10d0\u10de\u10d8\u10dc\u10d8"
    ],
    "name:kaz_x_preferred":[
        "\u041a\u0430\u043f\u0438\u043d"
    ],
    "name:mlg_x_preferred":[
        "Capim"
    ],
    "name:nld_x_preferred":[
        "Capim"
    ],
    "name:nor_x_preferred":[
        "Capim"
    ],
    "name:por_x_preferred":[
        "Capim"
    ],
    "name:ron_x_preferred":[
        "Capim"
    ],
    "name:rus_x_preferred":[
        "\u041a\u0430\u043f\u0438\u043d"
    ],
    "name:vie_x_preferred":[
        "Capim"
    ],
    "name:vol_x_preferred":[
        "Capim"
    ],
    "name:war_x_preferred":[
        "Capim"
    ],
    "wof:name":"Capim",
    "wof:placetype":"locality"
},
  "geometry": {"coordinates":[-38.25,-8.46667],"type":"Point"}
}