{
  "type": "Feature",
  "properties": {
    "gn:admin1_code":"06",
    "gn:admin2_code":"2309409.0",
    "gn:asciiname":"Logoa Branca",
    "gn:country_code":"BR",
    "gn:dem":350,
    "gn:feature_class":"P",
    "gn:feature_code":"PPL",
    "gn:name":"Logoa Branca",
    "gn:population":0,
    "gn:timezone":"America/Fortaleza",
    "iso:country":"BR",
    "wof:name":"Logoa Branca",
    "wof:placetype":"locality"
},
  "geometry": {"coordinates":[-40.68333,-5.58333],"type":"Point"}
}