{
  "type": "Feature",
  "properties": {
    "gn:admin1_code":"26",
    "gn:admin2_code":"4202909.0",
    "gn:asciiname":"Limeira",
    "gn:cc2":"BR",
    "gn:country_code":"BR",
    "gn:dem":40,
    "gn:feature_class":"P",
    "gn:feature_code":"PPL",
    "gn:name":"Limeira",
    "gn:population":0,
    "gn:timezone":"America/Sao_Paulo",
    "iso:country":"BR",
    "name:ara_x_preferred":[
        "\u0644\u064a\u0645\u064a\u0631\u0627"
    ],
    "name:bpy_x_preferred":[
        "\u09b2\u09bf\u09ae\u09af\u09bc\u09c7\u0987\u09b0\u09be"
    ],
    "name:ceb_x_preferred":[
        "Limeira"
    ],
    "name:deu_x_preferred":[
        "Limeira"
    ],
    "name:epo_x_preferred":[
        "Limeira"
    ],
    "name:eus_x_preferred":[
        "Limeira"
    ],
    "name:fin_x_preferred":[
        "Limeira"
    ],
    "name:fra_x_preferred":[
        "Limeira"
    ],
    "name:ita_x_preferred":[
        "Limeira"
    ],
    "name:kaz_x_preferred":[
        "\u041b\u0438\u043c\u0435\u0439\u0440\u0430"
    ],
    "name:lit_x_preferred":[
        "Limeira"
    ],
    "name:mlg_x_preferred":[
        "Limeira"
    ],
    "name:nld_x_preferred":[
        "Limeira"
    ],
    "name:nor_x_preferred":[
        "Limeira"
    ],
    "name:pol_x_preferred":[
        "Limeira"
    ],
    "name:por_x_preferred":[
        "Limeira"
    ],
    "name:ron_x_preferred":[
        "Limeira"
    ],
    "name:rus_x_preferred":[
        "\u041b\u0438\u043c\u0435\u0439\u0440\u0430"
    ],
    "name:spa_x_preferred":[
        "Limeira"
    ],
    "name:srp_x_preferred":[
        "\u041b\u0438\u043c\u0435\u0438\u0440\u0430"
    ],
    "name:swe_x_preferred":[
        "Limeira"
    ],
    "name:tat_x_preferred":[
        "\u041b\u0438\u043c\u0435\u0439\u0440\u0430"
    ],
    "name:tha_x_preferred":[
        "\u0e25\u0e35\u0e40\u0e21\u0e22\u0e4c\u0e23\u0e32"
    ],
    "name:und_x_variant":[
        "Limeiro"
    ],
    "name:vie_x_preferred":[
        "Limeira"
    ],
    "name:vol_x_preferred":[
        "Limeira"
    ],
    "name:war_x_preferred":[
        "Limeira"
    ],
    "name:zho_x_preferred":[
        "\u5229\u6885\u62c9"
    ],
    "wof:name":"Limeira",
    "wof:placetype":"locality"
},
  "geometry": {"coordinates":[-48.86667,-27.05],"type":"Point"}
}