{
  "type": "Feature",
  "properties": {
    "gn:admin1_code":"26",
    "gn:admin2_code":"4202909.0",
    "gn:asciiname":"Limeira",
    "gn:cc2":"BR",
    "gn:country_code":"BR",
    "gn:dem":40,
    "gn:feature_class":"P",
    "gn:feature_code":"PPL",
    "gn:name":"Limeira",
    "gn:population":0,
    "gn:timezone":"America/Sao_Paulo",
    "iso:country":"BR",
    "name:und_x_variant":[
        "Limeiro",
        "Limeira"
    ],
    "wof:name":"Limeira",
    "wof:placetype":"locality"
},
  "geometry": {"coordinates":[-48.86667,-27.05],"type":"Point"}
}