{
  "type": "Feature",
  "properties": {
    "gn:admin1_code":"14",
    "gn:admin2_code":"5105259.0",
    "gn:asciiname":"Lucas do Rio Verde",
    "gn:country_code":"BR",
    "gn:dem":395,
    "gn:feature_class":"P",
    "gn:feature_code":"PPL",
    "gn:name":"Lucas do Rio Verde",
    "gn:population":0,
    "gn:timezone":"America/Cuiaba",
    "iso:country":"BR",
    "name:bpy_x_preferred":[
        "\u09b2\u09c1\u0995\u09be\u09b8 \u09a1\u09cb \u09b0\u09bf\u0993 \u09ad\u09c7\u09b0\u09cd\u09a1\u09c7"
    ],
    "name:hye_x_preferred":[
        "\u053c\u0578\u0582\u056f\u0561\u057d \u0564\u0578\u0582 \u054c\u056b\u0578\u0582 \u054e\u0565\u0580\u0564\u056b"
    ],
    "name:por_x_preferred":[
        "Lucas do Rio Verde"
    ],
    "name:und_x_variant":[
        "Lucas",
        "Francisco Lucas"
    ],
    "wof:name":"Lucas do Rio Verde",
    "wof:placetype":"locality"
},
  "geometry": {"coordinates":[-55.92139,-13.06754],"type":"Point"}
}