{
  "type": "Feature",
  "properties": {
    "gn:admin1_code":"14",
    "gn:admin2_code":"5105259.0",
    "gn:asciiname":"Lucas do Rio Verde",
    "gn:country_code":"BR",
    "gn:dem":395,
    "gn:feature_class":"P",
    "gn:feature_code":"PPL",
    "gn:name":"Lucas do Rio Verde",
    "gn:population":0,
    "gn:timezone":"America/Cuiaba",
    "iso:country":"BR",
    "name:por_x_preferred":[
        "Lucas do Rio Verde"
    ],
    "name:und_x_variant":[
        "Lucas",
        "Francisco Lucas"
    ],
    "wof:name":"Lucas do Rio Verde",
    "wof:placetype":"locality"
},
  "geometry": {"coordinates":[-55.92139,-13.06754],"type":"Point"}
}