{
  "type": "Feature",
  "properties": {
    "gn:admin1_code":"18.0",
    "gn:admin2_code":"4109005.0",
    "gn:asciiname":"Sitio Jose Nita",
    "gn:country_code":"BR",
    "gn:dem":515,
    "gn:feature_class":"P",
    "gn:feature_code":"PPL",
    "gn:name":"S\u00edtio Jos\u00e9 Nita",
    "gn:population":0,
    "gn:timezone":"America/Sao_Paulo",
    "iso:country":"BR",
    "name:por_x_preferred":[
        "S\u00edtio Jos\u00e9 Nita"
    ],
    "wof:name":"Sitio Jose Nita",
    "wof:placetype":"locality"
},
  "geometry": {"coordinates":[-50.02707,-23.51647],"type":"Point"}
}