{
  "type": "Feature",
  "properties": {
    "gn:admin1_code":"20",
    "gn:admin2_code":"2204907.0",
    "gn:asciiname":"Tamboril",
    "gn:country_code":"BR",
    "gn:dem":335,
    "gn:feature_class":"P",
    "gn:feature_code":"PPL",
    "gn:name":"Tamboril",
    "gn:population":0,
    "gn:timezone":"America/Fortaleza",
    "iso:country":"BR",
    "name:ceb_x_preferred":[
        "Tamboril"
    ],
    "name:glg_x_preferred":[
        "Tamboril"
    ],
    "name:ita_x_preferred":[
        "Tamboril"
    ],
    "name:por_x_preferred":[
        "Tamboril"
    ],
    "name:swe_x_preferred":[
        "Tamboril"
    ],
    "wof:name":"Tamboril",
    "wof:placetype":"locality"
},
  "geometry": {"coordinates":[-41.58333,-7.68333],"type":"Point"}
}