{
  "type": "Feature",
  "properties": {
    "gn:admin1_code":"18.0",
    "gn:admin2_code":"4126207.0",
    "gn:asciiname":"Sao Roque",
    "gn:country_code":"BR",
    "gn:dem":712,
    "gn:feature_class":"P",
    "gn:feature_code":"PPL",
    "gn:name":"S\u00e3o Roque",
    "gn:population":0,
    "gn:timezone":"America/Sao_Paulo",
    "iso:country":"BR",
    "name:por_x_preferred":[
        "S\u00e3o Roque"
    ],
    "wof:name":"Sao Roque",
    "wof:placetype":"locality"
},
  "geometry": {"coordinates":[-50.4934,-23.9165],"type":"Point"}
}