{
  "type": "Feature",
  "properties": {
    "gn:admin1_code":"13",
    "gn:admin2_code":"2109502.0",
    "gn:asciiname":"Sao Pedro",
    "gn:cc2":"BR",
    "gn:country_code":"BR",
    "gn:dem":315,
    "gn:feature_class":"P",
    "gn:feature_code":"PPL",
    "gn:name":"S\u00e3o Pedro",
    "gn:population":0,
    "gn:timezone":"America/Fortaleza",
    "iso:country":"BR",
    "name:und_x_variant":[
        "Brej\u00e3o",
        "S\u00e3o Pedro"
    ],
    "wof:name":"Sao Pedro",
    "wof:placetype":"locality"
},
  "geometry": {"coordinates":[-46.56667,-7.83333],"type":"Point"}
}