{
  "type": "Feature",
  "properties": {
    "iso:country":"BR",
    "name:por_x_preferred":[
        "Centro"
    ],
    "name:unk_x_variant":[
        "Centro"
    ],
    "qs:gn_adm0_cc":"BR",
    "qs:gn_local":3460845,
    "qs:gn_nam_loc":"Itaja\u00ed, Itaja\u00ed, Santa Catarina, BR",
    "qs:gn_namadm1":"26",
    "qs:local_max":702,
    "qs:local_sum":1194,
    "qs:localhoods":4,
    "qs:name":"Centro",
    "qs:name_adm0":"Brasil",
    "qs:name_adm1":"Santa Catarina",
    "qs:name_adm2":"Itaja\u00ed",
    "qs:name_local":"Itaja\u00ed",
    "qs:photo_max":140,
    "qs:photo_sum":702,
    "qs:placetype":"Suburb",
    "qs:quad_count":33,
    "qs:woe_adm0":23424768,
    "qs:woe_adm1":2344867,
    "qs:woe_adm2":12581685,
    "qs:woe_lau":0,
    "qs:woe_local":455870,
    "qs:woe_ver":"7.10.0",
    "wof:lang":[
        "por"
    ],
    "wof:name":"Centro",
    "wof:placetype":"neighbourhood"
},
  "geometry": {"coordinates":[-48.656111,-26.90718],"type":"Point"}
}