{
  "type": "Feature",
  "properties": {
    "gn:admin1_code":"16",
    "gn:admin2_code":"1507805.0",
    "gn:asciiname":"Alto Bonito",
    "gn:country_code":"BR",
    "gn:dem":164,
    "gn:feature_class":"P",
    "gn:feature_code":"PPL",
    "gn:name":"Alto Bonito",
    "gn:population":0,
    "gn:timezone":"America/Belem",
    "iso:country":"BR",
    "wof:name":"Alto Bonito",
    "wof:placetype":"locality"
},
  "geometry": {"coordinates":[-51.91667,-4.11667],"type":"Point"}
}