{
  "type": "Feature",
  "properties": {
    "gn:admin1_code":"20",
    "gn:admin2_code":"2206100.0",
    "gn:asciiname":"Cajazeiras",
    "gn:country_code":"BR",
    "gn:dem":52,
    "gn:feature_class":"P",
    "gn:feature_code":"PPL",
    "gn:name":"Cajazeiras",
    "gn:population":0,
    "gn:timezone":"America/Fortaleza",
    "iso:country":"BR",
    "wof:name":"Cajazeiras",
    "wof:placetype":"locality"
},
  "geometry": {"coordinates":[-42.58694000000001,-3.66639],"type":"Point"}
}