{
  "type": "Feature",
  "properties": {
    "gn:admin1_code":"20",
    "gn:admin2_code":"2206100.0",
    "gn:asciiname":"Cajazeiras",
    "gn:country_code":"BR",
    "gn:dem":52,
    "gn:feature_class":"P",
    "gn:feature_code":"PPL",
    "gn:name":"Cajazeiras",
    "gn:population":0,
    "gn:timezone":"America/Fortaleza",
    "iso:country":"BR",
    "name:bpy_x_preferred":[
        "\u0995\u09be\u099c\u09be\u099c\u09af\u09bc\u09c7\u0987\u09b0\u09be\u09b8"
    ],
    "name:epo_x_preferred":[
        "Cajazeiras"
    ],
    "name:eus_x_preferred":[
        "Cajazeiras"
    ],
    "name:fra_x_preferred":[
        "Cajazeiras"
    ],
    "name:hye_x_preferred":[
        "\u053f\u0561\u057b\u0561\u0566\u0565\u0575\u0580\u0561\u057d"
    ],
    "name:ita_x_preferred":[
        "Cajazeiras"
    ],
    "name:kat_x_preferred":[
        "\u10d9\u10d0\u10df\u10d0\u10d6\u10d4\u10d8\u10e0\u10d0\u10e1\u10d8"
    ],
    "name:kaz_x_preferred":[
        "\u041a\u0430\u0436\u0430\u0437\u0435\u0439\u0440\u0430\u0441"
    ],
    "name:mlg_x_preferred":[
        "Cajazeiras"
    ],
    "name:nld_x_preferred":[
        "Cajazeiras"
    ],
    "name:nor_x_preferred":[
        "Cajazeiras"
    ],
    "name:pol_x_preferred":[
        "Cajazeiras"
    ],
    "name:por_x_preferred":[
        "Cajazeiras"
    ],
    "name:ron_x_preferred":[
        "Cajazeiras"
    ],
    "name:rus_x_preferred":[
        "\u041a\u0430\u0436\u0430\u0437\u0435\u0439\u0440\u0430\u0441"
    ],
    "name:spa_x_preferred":[
        "Cajazeiras"
    ],
    "name:vie_x_preferred":[
        "Cajazeiras"
    ],
    "name:vol_x_preferred":[
        "Cajazeiras"
    ],
    "name:war_x_preferred":[
        "Cajazeiras"
    ],
    "name:zho_x_preferred":[
        "\u5361\u96c5\u6cfd\u62c9\u65af"
    ],
    "wof:name":"Cajazeiras",
    "wof:placetype":"locality"
},
  "geometry": {"coordinates":[-42.58694000000001,-3.66639],"type":"Point"}
}