{
  "type": "Feature",
  "properties": {
    "gn:admin1_code":"5",
    "gn:admin2_code":"2924678.0",
    "gn:asciiname":"Candeias",
    "gn:country_code":"BR",
    "gn:dem":524,
    "gn:feature_class":"P",
    "gn:feature_code":"PPL",
    "gn:name":"Candeias",
    "gn:population":0,
    "gn:timezone":"America/Bahia",
    "iso:country":"BR",
    "wof:name":"Candeias",
    "wof:placetype":"locality"
},
  "geometry": {"coordinates":[-39.38333,-13.85],"type":"Point"}
}