{
  "type": "Feature",
  "properties": {
    "gn:admin1_code":"18",
    "gn:admin2_code":"4122305.0",
    "gn:asciiname":"Sitio Ricardo Schrueder",
    "gn:country_code":"BR",
    "gn:dem":863,
    "gn:feature_class":"P",
    "gn:feature_code":"PPL",
    "gn:name":"S\u00edtio Ricardo Schrueder",
    "gn:population":0,
    "gn:timezone":"America/Sao_Paulo",
    "iso:country":"BR",
    "name:por_x_preferred":[
        "S\u00edtio Ricardo Schrueder"
    ],
    "wof:name":"Sitio Ricardo Schrueder",
    "wof:placetype":"locality"
},
  "geometry": {"coordinates":[-49.55933,-26.08257],"type":"Point"}
}