{
  "type": "Feature",
  "properties": {
    "iso:country":"BR",
    "name:ceb_x_preferred":[
        "Badu"
    ],
    "name:deu_x_preferred":[
        "Badu"
    ],
    "name:fra_x_preferred":[
        "Badu"
    ],
    "name:por_x_preferred":[
        "Badu"
    ],
    "name:rus_x_preferred":[
        "\u0411\u0430\u0434\u0443"
    ],
    "name:swe_x_preferred":[
        "Badu"
    ],
    "name:unk_x_variant":[
        "Badu"
    ],
    "qs:gn_adm0_cc":"BR",
    "qs:gn_local":3456283,
    "qs:gn_nam_loc":"Niter\u00f3i, Niter\u00f3i, Rio de Janeiro, BR",
    "qs:gn_namadm1":"21",
    "qs:local_max":2228,
    "qs:local_sum":7420,
    "qs:localhoods":12,
    "qs:name":"Badu",
    "qs:name_adm0":"Brasil",
    "qs:name_adm1":"Rio de Janeiro",
    "qs:name_adm2":"Niter\u00f3i",
    "qs:name_local":"Niter\u00f3i",
    "qs:photo_max":12,
    "qs:photo_sum":20,
    "qs:placetype":"Suburb",
    "qs:quad_count":5,
    "qs:woe_adm0":23424768,
    "qs:woe_adm1":2344862,
    "qs:woe_adm2":12581047,
    "qs:woe_lau":0,
    "qs:woe_local":455891,
    "qs:woe_ver":"7.10.0",
    "wd:wordcount":111,
    "wof:lang":[
        "por"
    ],
    "wof:name":"Badu",
    "wof:placetype":"neighbourhood"
},
  "geometry": {"coordinates":[-43.035507,-22.896418],"type":"Point"}
}