{
  "type": "Feature",
  "properties": {
    "gn:admin1_code":"11",
    "gn:admin2_code":"5006606.0",
    "gn:asciiname":"Aquidaba",
    "gn:country_code":"BR",
    "gn:dem":700,
    "gn:feature_class":"P",
    "gn:feature_code":"PPL",
    "gn:name":"Aquidab\u00e3",
    "gn:population":0,
    "gn:timezone":"America/Campo_Grande",
    "iso:country":"BR",
    "wof:name":"Aquidaba",
    "wof:placetype":"locality"
},
  "geometry": {"coordinates":[-55.71666999999999,-22.38333],"type":"Point"}
}