{
  "type": "Feature",
  "properties": {
    "gn:admin1_code":"27.0",
    "gn:admin2_code":"3502705.0",
    "gn:asciiname":"Rio das Pedras",
    "gn:country_code":"BR",
    "gn:dem":802,
    "gn:feature_class":"P",
    "gn:feature_code":"PPLL",
    "gn:name":"Rio das Pedras",
    "gn:population":0,
    "gn:timezone":"America/Sao_Paulo",
    "iso:country":"BR",
    "name:ceb_x_preferred":[
        "Rio das Pedras"
    ],
    "name:fra_x_preferred":[
        "Rio das Pedras"
    ],
    "name:por_x_preferred":[
        "Rio das Pedras"
    ],
    "name:swe_x_preferred":[
        "Rio das Pedras"
    ],
    "wof:name":"Rio das Pedras",
    "wof:placetype":"locality"
},
  "geometry": {"coordinates":[-48.85073,-24.54988],"type":"Point"}
}