{
  "type": "Feature",
  "properties": {
    "gn:admin1_code":"13",
    "gn:admin2_code":"2101707.0",
    "gn:asciiname":"Armazem",
    "gn:country_code":"BR",
    "gn:dem":30,
    "gn:feature_class":"P",
    "gn:feature_code":"PPL",
    "gn:name":"Armaz\u00e9m",
    "gn:population":0,
    "gn:timezone":"America/Fortaleza",
    "iso:country":"BR",
    "wof:name":"Armazem",
    "wof:placetype":"locality"
},
  "geometry": {"coordinates":[-43.11361,-3.08278],"type":"Point"}
}