{
  "type": "Feature",
  "properties": {
    "gn:admin1_code":"18",
    "gn:admin2_code":"4127601.0",
    "gn:asciiname":"Sitio Joao M. Cardoso",
    "gn:country_code":"BR",
    "gn:dem":846,
    "gn:feature_class":"P",
    "gn:feature_code":"PPL",
    "gn:name":"S\u00edtio Jo\u00e3o M. Cardoso",
    "gn:population":0,
    "gn:timezone":"America/Sao_Paulo",
    "iso:country":"BR",
    "name:por_x_preferred":[
        "S\u00edtio Jo\u00e3o M. Cardoso"
    ],
    "wof:name":"Sitio Joao M. Cardoso",
    "wof:placetype":"locality"
},
  "geometry": {"coordinates":[-49.0461,-25.974],"type":"Point"}
}