{
  "type": "Feature",
  "properties": {
    "gn:admin1_code":"15",
    "gn:admin2_code":"3154150.0",
    "gn:asciiname":"Prosperidade",
    "gn:country_code":"BR",
    "gn:dem":620,
    "gn:feature_class":"P",
    "gn:feature_code":"PPL",
    "gn:name":"Prosperidade",
    "gn:population":0,
    "gn:timezone":"America/Sao_Paulo",
    "iso:country":"BR",
    "name:por_x_preferred":[
        "Prosperidade"
    ],
    "wof:name":"Prosperidade",
    "wof:placetype":"locality"
},
  "geometry": {"coordinates":[-41.96667,-20.28333],"type":"Point"}
}