{
  "type": "Feature",
  "properties": {
    "gn:admin1_code":"13",
    "gn:admin2_code":"2110609.0",
    "gn:asciiname":"Ribeiro",
    "gn:country_code":"BR",
    "gn:dem":24,
    "gn:feature_class":"P",
    "gn:feature_code":"PPL",
    "gn:name":"Ribeiro",
    "gn:population":0,
    "gn:timezone":"America/Fortaleza",
    "iso:country":"BR",
    "wof:name":"Ribeiro",
    "wof:placetype":"locality"
},
  "geometry": {"coordinates":[-42.48222,-3.45806],"type":"Point"}
}