{
  "type": "Feature",
  "properties": {
    "gn:admin1_code":"13",
    "gn:admin2_code":"2110609.0",
    "gn:asciiname":"Ribeiro",
    "gn:country_code":"BR",
    "gn:dem":24,
    "gn:feature_class":"P",
    "gn:feature_code":"PPL",
    "gn:name":"Ribeiro",
    "gn:population":0,
    "gn:timezone":"America/Fortaleza",
    "iso:country":"BR",
    "name:bel_x_preferred":[
        "\u0420\u044b\u0431\u0435\u0439\u0440\u0443"
    ],
    "name:ces_x_preferred":[
        "Ribeiro"
    ],
    "name:deu_x_preferred":[
        "Ribeiro"
    ],
    "name:fin_x_preferred":[
        "Ribeiro"
    ],
    "name:fra_x_preferred":[
        "Ribeiro"
    ],
    "name:glg_x_preferred":[
        "Ribeiro"
    ],
    "name:ita_x_preferred":[
        "Ribeiro"
    ],
    "name:kor_x_preferred":[
        "\ud788\ubca0\uc774\ub8e8"
    ],
    "name:lit_x_preferred":[
        "Ribeiro"
    ],
    "name:pol_x_preferred":[
        "Ribeiro"
    ],
    "name:rus_x_preferred":[
        "\u0420\u0438\u0431\u0435\u0439\u0440\u0443"
    ],
    "name:swe_x_preferred":[
        "Ribeiro"
    ],
    "name:ukr_x_preferred":[
        "\u0420\u0456\u0431\u0435\u0439\u0440\u043e"
    ],
    "wof:name":"Ribeiro",
    "wof:placetype":"locality"
},
  "geometry": {"coordinates":[-42.48222,-3.45806],"type":"Point"}
}