{
  "type": "Feature",
  "properties": {
    "gn:admin1_code":"18.0",
    "gn:admin2_code":"4126678.0",
    "gn:asciiname":"Sitio Manoel Guedes Morais",
    "gn:country_code":"BR",
    "gn:dem":697,
    "gn:feature_class":"P",
    "gn:feature_code":"PPL",
    "gn:name":"S\u00edtio Manoel Guedes Morais",
    "gn:population":0,
    "gn:timezone":"America/Sao_Paulo",
    "iso:country":"BR",
    "name:por_x_preferred":[
        "S\u00edtio Manoel Guedes Morais"
    ],
    "wof:name":"Sitio Manoel Guedes Morais",
    "wof:placetype":"locality"
},
  "geometry": {"coordinates":[-50.989,-23.8846],"type":"Point"}
}