{
  "type": "Feature",
  "properties": {
    "gn:admin1_code":"13",
    "gn:admin2_code":"2108454.0",
    "gn:asciiname":"Bacuri",
    "gn:country_code":"BR",
    "gn:dem":90,
    "gn:feature_class":"P",
    "gn:feature_code":"PPL",
    "gn:name":"Bacuri",
    "gn:population":0,
    "gn:timezone":"America/Fortaleza",
    "iso:country":"BR",
    "wof:name":"Bacuri",
    "wof:placetype":"locality"
},
  "geometry": {"coordinates":[-44.34923,-4.5652],"type":"Point"}
}