{
  "type": "Feature",
  "properties": {
    "gn:admin1_code":"20",
    "gn:admin2_code":"2202075.0",
    "gn:asciiname":"Formiga",
    "gn:country_code":"BR",
    "gn:dem":218,
    "gn:feature_class":"P",
    "gn:feature_code":"PPL",
    "gn:name":"Formiga",
    "gn:population":0,
    "gn:timezone":"America/Fortaleza",
    "iso:country":"BR",
    "wof:name":"Formiga",
    "wof:placetype":"locality"
},
  "geometry": {"coordinates":[-42.36667,-6.68333],"type":"Point"}
}