{
  "type": "Feature",
  "properties": {
    "gn:admin1_code":"5",
    "gn:admin2_code":"2930808.0",
    "gn:asciiname":"Vargem",
    "gn:country_code":"BR",
    "gn:dem":1019,
    "gn:feature_class":"P",
    "gn:feature_code":"PPL",
    "gn:name":"Vargem",
    "gn:population":0,
    "gn:timezone":"America/Bahia",
    "iso:country":"BR",
    "wof:name":"Vargem",
    "wof:placetype":"locality"
},
  "geometry": {"coordinates":[-41.86667,-12.08333],"type":"Point"}
}