{
  "type": "Feature",
  "properties": {
    "gn:admin1_code":"5",
    "gn:admin2_code":"2930808.0",
    "gn:asciiname":"Vargem",
    "gn:country_code":"BR",
    "gn:dem":1019,
    "gn:feature_class":"P",
    "gn:feature_code":"PPL",
    "gn:name":"Vargem",
    "gn:population":0,
    "gn:timezone":"America/Bahia",
    "iso:country":"BR",
    "name:bpy_x_preferred":[
        "\u09ad\u09be\u09b0\u09cd\u0997\u09c7\u09ae"
    ],
    "name:ceb_x_preferred":[
        "Vargem"
    ],
    "name:epo_x_preferred":[
        "Vargem"
    ],
    "name:eus_x_preferred":[
        "Vargem"
    ],
    "name:fra_x_preferred":[
        "Vargem"
    ],
    "name:ita_x_preferred":[
        "Vargem"
    ],
    "name:kaz_x_preferred":[
        "\u0412\u0430\u0440\u0436\u0435\u043d"
    ],
    "name:mlg_x_preferred":[
        "Vargem"
    ],
    "name:nld_x_preferred":[
        "Vargem"
    ],
    "name:nor_x_preferred":[
        "Vargem"
    ],
    "name:pol_x_preferred":[
        "Vargem"
    ],
    "name:por_x_preferred":[
        "Vargem"
    ],
    "name:ron_x_preferred":[
        "Vargem"
    ],
    "name:rus_x_preferred":[
        "\u0412\u0430\u0440\u0436\u0435\u043d"
    ],
    "name:vie_x_preferred":[
        "Vargem"
    ],
    "name:vol_x_preferred":[
        "Vargem"
    ],
    "name:war_x_preferred":[
        "Vargem"
    ],
    "name:zho_x_preferred":[
        "\u74e6\u5c14\u4efb"
    ],
    "wof:name":"Vargem",
    "wof:placetype":"locality"
},
  "geometry": {"coordinates":[-41.86667,-12.08333],"type":"Point"}
}