{
  "type": "Feature",
  "properties": {
    "gn:admin1_code":"4",
    "gn:admin2_code":"1300706.0",
    "gn:asciiname":"Colocacao Bela Vista",
    "gn:country_code":"BR",
    "gn:dem":166,
    "gn:feature_class":"P",
    "gn:feature_code":"PPL",
    "gn:name":"Coloca\u00e7\u00e3o Bela Vista",
    "gn:population":0,
    "gn:timezone":"America/Manaus",
    "iso:country":"BR",
    "wof:name":"Colocacao Bela Vista",
    "wof:placetype":"locality"
},
  "geometry": {"coordinates":[-67.31667,-9.56667],"type":"Point"}
}