{
  "type": "Feature",
  "properties": {
    "gn:admin1_code":"18.0",
    "gn:admin2_code":"4126207.0",
    "gn:asciiname":"Sitio Manoel M. Camargo",
    "gn:country_code":"BR",
    "gn:dem":636,
    "gn:feature_class":"P",
    "gn:feature_code":"PPL",
    "gn:name":"S\u00edtio Manoel M. Camargo",
    "gn:population":0,
    "gn:timezone":"America/Sao_Paulo",
    "iso:country":"BR",
    "name:por_x_preferred":[
        "S\u00edtio Manoel M. Camargo"
    ],
    "wof:name":"Sitio Manoel M. Camargo",
    "wof:placetype":"locality"
},
  "geometry": {"coordinates":[-50.50642,-23.92331],"type":"Point"}
}