{
  "type": "Feature",
  "properties": {
    "gn:admin1_code":"30",
    "gn:admin2_code":"2605707.0",
    "gn:asciiname":"Arapua",
    "gn:country_code":"BR",
    "gn:dem":345,
    "gn:feature_class":"P",
    "gn:feature_code":"PPL",
    "gn:name":"Arapu\u00e1",
    "gn:population":0,
    "gn:timezone":"America/Recife",
    "iso:country":"BR",
    "wof:name":"Arapua",
    "wof:placetype":"locality"
},
  "geometry": {"coordinates":[-38.53333,-8.43333],"type":"Point"}
}