{
  "type": "Feature",
  "properties": {
    "gn:admin1_code":"18",
    "gn:admin2_code":"4127601.0",
    "gn:asciiname":"Sitio Demanda",
    "gn:country_code":"BR",
    "gn:dem":922,
    "gn:feature_class":"P",
    "gn:feature_code":"PPL",
    "gn:name":"S\u00edtio Demanda",
    "gn:population":0,
    "gn:timezone":"America/Sao_Paulo",
    "iso:country":"BR",
    "name:por_x_preferred":[
        "S\u00edtio Demanda"
    ],
    "wof:name":"Sitio Demanda",
    "wof:placetype":"locality"
},
  "geometry": {"coordinates":[-49.20242,-25.93713],"type":"Point"}
}