{
  "type": "Feature",
  "properties": {
    "gn:admin1_code":"20",
    "gn:admin2_code":"2207009.0",
    "gn:asciiname":"Fomento",
    "gn:country_code":"BR",
    "gn:dem":166,
    "gn:feature_class":"P",
    "gn:feature_code":"PPL",
    "gn:name":"Fomento",
    "gn:population":0,
    "gn:timezone":"America/Fortaleza",
    "iso:country":"BR",
    "wof:name":"Fomento",
    "wof:placetype":"locality"
},
  "geometry": {"coordinates":[-42.06667,-6.98333],"type":"Point"}
}