{
  "type": "Feature",
  "properties": {
    "gn:admin1_code":"18.0",
    "gn:admin2_code":"4113205.0",
    "gn:asciiname":"Sitio Florentina Berniak",
    "gn:country_code":"BR",
    "gn:dem":830,
    "gn:feature_class":"P",
    "gn:feature_code":"PPL",
    "gn:name":"S\u00edtio Florentina Berniak",
    "gn:population":0,
    "gn:timezone":"America/Sao_Paulo",
    "iso:country":"BR",
    "name:por_x_preferred":[
        "S\u00edtio Florentina Berniak"
    ],
    "wof:name":"Sitio Florentina Berniak",
    "wof:placetype":"locality"
},
  "geometry": {"coordinates":[-49.5447,-25.8383],"type":"Point"}
}