{
  "type": "Feature",
  "properties": {
    "gn:admin1_code":"18.0",
    "gn:admin2_code":"4106001.0",
    "gn:asciiname":"Bairro Pedra Amarela",
    "gn:country_code":"BR",
    "gn:dem":855,
    "gn:feature_class":"P",
    "gn:feature_code":"PPLL",
    "gn:name":"Bairro Pedra Amarela",
    "gn:population":0,
    "gn:timezone":"America/Sao_Paulo",
    "iso:country":"BR",
    "name:por_x_preferred":[
        "Bairro Pedra Amarela"
    ],
    "wof:name":"Bairro Pedra Amarela",
    "wof:placetype":"locality"
},
  "geometry": {"coordinates":[-50.52346,-23.62023],"type":"Point"}
}