{
  "type": "Feature",
  "properties": {
    "gn:admin1_code":"15",
    "gn:admin2_code":"3147006.0",
    "gn:asciiname":"Belamino Dias",
    "gn:country_code":"BR",
    "gn:dem":596,
    "gn:feature_class":"P",
    "gn:feature_code":"PPL",
    "gn:name":"Belamino Dias",
    "gn:population":0,
    "gn:timezone":"America/Sao_Paulo",
    "iso:country":"BR",
    "name:por_x_preferred":[
        "Belamino Dias"
    ],
    "wof:name":"Belamino Dias",
    "wof:placetype":"locality"
},
  "geometry": {"coordinates":[-46.75,-17.01667],"type":"Point"}
}