{
  "type": "Feature",
  "properties": {
    "gn:admin1_code":"18.0",
    "gn:admin2_code":"4102703.0",
    "gn:asciiname":"Sitio Tres Coqueiros",
    "gn:country_code":"BR",
    "gn:dem":412,
    "gn:feature_class":"P",
    "gn:feature_code":"PPL",
    "gn:name":"S\u00edtio Tr\u00eas Coqueiros",
    "gn:population":0,
    "gn:timezone":"America/Sao_Paulo",
    "iso:country":"BR",
    "name:por_x_preferred":[
        "S\u00edtio Tr\u00eas Coqueiros"
    ],
    "wof:name":"Sitio Tres Coqueiros",
    "wof:placetype":"locality"
},
  "geometry": {"coordinates":[-50.1504,-23.1269],"type":"Point"}
}