{
  "type": "Feature",
  "properties": {
    "gn:admin1_code":"5",
    "gn:admin2_code":"2906907.0",
    "gn:asciiname":"Peruipe",
    "gn:country_code":"BR",
    "gn:dem":50,
    "gn:feature_class":"P",
    "gn:feature_code":"PPL",
    "gn:name":"Peru\u00edpe",
    "gn:population":0,
    "gn:timezone":"America/Bahia",
    "iso:country":"BR",
    "name:por_x_preferred":[
        "Peru\u00edpe"
    ],
    "wof:name":"Peruipe",
    "wof:placetype":"locality"
},
  "geometry": {"coordinates":[-39.61667,-17.76667],"type":"Point"}
}