{
  "type": "Feature",
  "properties": {
    "gn:admin1_code":"13",
    "gn:admin2_code":"2112605.0",
    "gn:asciiname":"Guaribas V",
    "gn:country_code":"BR",
    "gn:dem":64,
    "gn:feature_class":"P",
    "gn:feature_code":"PPL",
    "gn:name":"Guaribas V",
    "gn:population":0,
    "gn:timezone":"America/Fortaleza",
    "iso:country":"BR",
    "wof:name":"Guaribas V",
    "wof:placetype":"locality"
},
  "geometry": {"coordinates":[-43.37083,-3.44083],"type":"Point"}
}