{
  "type": "Feature",
  "properties": {
    "gn:admin1_code":"27",
    "gn:admin2_code":"3530607.0",
    "gn:asciiname":"Stio Papa-Vento",
    "gn:country_code":"BR",
    "gn:dem":657,
    "gn:feature_class":"P",
    "gn:feature_code":"PPL",
    "gn:name":"Stio Papa-Vento",
    "gn:population":0,
    "gn:timezone":"America/Sao_Paulo",
    "iso:country":"BR",
    "name:por_x_preferred":[
        "Stio Papa-Vento"
    ],
    "wof:name":"Stio Papa-Vento",
    "wof:placetype":"locality"
},
  "geometry": {"coordinates":[-46.1808,-23.3977],"type":"Point"}
}