{
  "type": "Feature",
  "properties": {
    "gn:admin1_code":"23",
    "gn:admin2_code":"4311304.0",
    "gn:asciiname":"Olinda",
    "gn:cc2":"BR",
    "gn:country_code":"BR",
    "gn:dem":793,
    "gn:feature_class":"P",
    "gn:feature_code":"PPL",
    "gn:name":"Olinda",
    "gn:population":0,
    "gn:timezone":"America/Sao_Paulo",
    "iso:country":"BR",
    "name:rus_x_preferred":[
        "\u041e\u043b\u0438\u043d\u0434\u0430"
    ],
    "name:und_x_variant":[
        "Olinto",
        "Olinda"
    ],
    "wof:name":"Olinda",
    "wof:placetype":"locality"
},
  "geometry": {"coordinates":[-51.46667,-28.35],"type":"Point"}
}