{
  "type": "Feature",
  "properties": {
    "gn:admin1_code":"18.0",
    "gn:admin2_code":"4103602.0",
    "gn:asciiname":"Sitio Ivo Bonanci",
    "gn:country_code":"BR",
    "gn:dem":478,
    "gn:feature_class":"P",
    "gn:feature_code":"PPL",
    "gn:name":"S\u00edtio Ivo Bonanci",
    "gn:population":0,
    "gn:timezone":"America/Sao_Paulo",
    "iso:country":"BR",
    "name:por_x_preferred":[
        "S\u00edtio Ivo Bonanci"
    ],
    "wof:name":"Sitio Ivo Bonanci",
    "wof:placetype":"locality"
},
  "geometry": {"coordinates":[-50.1861,-23.0417],"type":"Point"}
}