{
  "type": "Feature",
  "properties": {
    "iso:country":"BR",
    "name:bre_x_preferred":[
        "S\u00e3o Jos\u00e9"
    ],
    "name:ceb_x_preferred":[
        "S\u00e3o Jos\u00e9"
    ],
    "name:deu_x_preferred":[
        "S\u00e3o Jos\u00e9"
    ],
    "name:epo_x_preferred":[
        "S\u00e3o Jos\u00e9"
    ],
    "name:fra_x_preferred":[
        "S\u00e3o Jos\u00e9"
    ],
    "name:ita_x_preferred":[
        "S\u00e3o Jos\u00e9"
    ],
    "name:jpn_x_preferred":[
        "\u30b5\u30f3\u30fb\u30b8\u30e7\u30bc"
    ],
    "name:lit_x_preferred":[
        "San \u017doz\u0117"
    ],
    "name:mlg_x_preferred":[
        "S\u00e3o Jos\u00e9"
    ],
    "name:nld_x_preferred":[
        "S\u00e3o Jos\u00e9"
    ],
    "name:pol_x_preferred":[
        "S\u00e3o Jos\u00e9"
    ],
    "name:por_x_preferred":[
        "S\u00e3o Jos\u00e9"
    ],
    "name:rus_x_preferred":[
        "\u0421\u0430\u043d-\u0416\u043e\u0437\u0435"
    ],
    "name:sco_x_preferred":[
        "S\u00e3o Jos\u00e9"
    ],
    "name:spa_x_preferred":[
        "S\u00e3o Jos\u00e9"
    ],
    "name:swe_x_preferred":[
        "S\u00e3o Jos\u00e9"
    ],
    "name:vie_x_preferred":[
        "S\u00e3o Jos\u00e9"
    ],
    "name:war_x_preferred":[
        "S\u00e3o Jos\u00e9"
    ],
    "qs_pg:aaroncc":"BR",
    "qs_pg:name":"S\u00e3o Jos\u00e9",
    "qs_pg:name_adm0":"Brasil",
    "qs_pg:name_adm1":"Rio Grande do Sul",
    "qs_pg:photos":1,
    "qs_pg:photos_1k":1,
    "qs_pg:photos_9k":1,
    "qs_pg:photos_9r":1,
    "qs_pg:photos_all":1,
    "qs_pg:photos_sr":1,
    "qs_pg:pop_sr":0,
    "qs_pg:qs_pg_placetype":"neighbourhood",
    "qs_pg:qs_pg_placetype_gp":"Suburb",
    "qs_pg:woe_adm0":23424768,
    "woe:adm0_id":23424768,
    "woe:name_adm0":"Brasil",
    "woe:name_adm1":"Rio Grande do Sul",
    "woe:placetype":"Suburb",
    "wof:name":"S\u00e3o Jos\u00e9",
    "wof:placetype":"neighbourhood"
},
  "geometry": {"coordinates":[-51.186023,-29.173222],"type":"Point"}
}