{
  "type": "Feature",
  "properties": {
    "gn:admin1_code":"21",
    "gn:admin2_code":"3304904.0",
    "gn:asciiname":"Ilha de Itaoca",
    "gn:country_code":"BR",
    "gn:dem":5,
    "gn:feature_class":"P",
    "gn:feature_code":"PPL",
    "gn:name":"Ilha de Itaoca",
    "gn:population":0,
    "gn:timezone":"America/Sao_Paulo",
    "iso:country":"BR",
    "name:por_x_preferred":[
        "Ilha de Itaoca"
    ],
    "wof:name":"Ilha de Itaoca",
    "wof:placetype":"locality"
},
  "geometry": {"coordinates":[-43.06667,-22.78333],"type":"Point"}
}