{
  "type": "Feature",
  "properties": {
    "gn:admin1_code":"18",
    "gn:admin2_code":"4122305.0",
    "gn:asciiname":"Sitio Valdomiro Fagundes",
    "gn:country_code":"BR",
    "gn:dem":936,
    "gn:feature_class":"P",
    "gn:feature_code":"PPL",
    "gn:name":"S\u00edtio Valdomiro Fagundes",
    "gn:population":0,
    "gn:timezone":"America/Sao_Paulo",
    "iso:country":"BR",
    "name:por_x_preferred":[
        "S\u00edtio Valdomiro Fagundes"
    ],
    "wof:name":"Sitio Valdomiro Fagundes",
    "wof:placetype":"locality"
},
  "geometry": {"coordinates":[-49.60444,-26.11416],"type":"Point"}
}