{
  "type": "Feature",
  "properties": {
    "gn:admin1_code":"20",
    "gn:admin2_code":"2207108.0",
    "gn:asciiname":"Chapada",
    "gn:country_code":"BR",
    "gn:dem":231,
    "gn:feature_class":"P",
    "gn:feature_code":"PPL",
    "gn:name":"Chapada",
    "gn:population":0,
    "gn:timezone":"America/Fortaleza",
    "iso:country":"BR",
    "wof:name":"Chapada",
    "wof:placetype":"locality"
},
  "geometry": {"coordinates":[-42.51667,-5.86667],"type":"Point"}
}