{
  "type": "Feature",
  "properties": {
    "gn:admin1_code":"5",
    "gn:admin2_code":"2911105.0",
    "gn:asciiname":"Brejo do Salto",
    "gn:country_code":"BR",
    "gn:dem":558,
    "gn:feature_class":"P",
    "gn:feature_code":"PPL",
    "gn:name":"Brejo do Salto",
    "gn:population":0,
    "gn:timezone":"America/Bahia",
    "iso:country":"BR",
    "wof:name":"Brejo do Salto",
    "wof:placetype":"locality"
},
  "geometry": {"coordinates":[-45.73333,-11.08333],"type":"Point"}
}