{
  "type": "Feature",
  "properties": {
    "gn:admin1_code":"05",
    "gn:admin2_code":"2918407.0",
    "gn:asciiname":"Tanque Velho",
    "gn:country_code":"BR",
    "gn:dem":395,
    "gn:feature_class":"P",
    "gn:feature_code":"PPL",
    "gn:name":"Tanque Velho",
    "gn:population":0,
    "gn:timezone":"America/Bahia",
    "iso:country":"BR",
    "wof:name":"Tanque Velho",
    "wof:placetype":"locality"
},
  "geometry": {"coordinates":[-40.73333,-9.58333],"type":"Point"}
}