{
  "type": "Feature",
  "properties": {
    "gn:admin1_code":"21",
    "gn:admin2_code":"3304557.0",
    "gn:asciiname":"Tijuca",
    "gn:country_code":"BR",
    "gn:dem":27,
    "gn:feature_class":"P",
    "gn:feature_code":"PPL",
    "gn:name":"Tijuca",
    "gn:population":0,
    "gn:timezone":"America/Sao_Paulo",
    "iso:country":"BR",
    "name:por_x_preferred":[
        "Tijuca"
    ],
    "wof:name":"Tijuca",
    "wof:placetype":"locality"
},
  "geometry": {"coordinates":[-43.23058,-22.92712],"type":"Point"}
}