{
  "type": "Feature",
  "properties": {
    "gn:admin1_code":"30",
    "gn:admin2_code":"2605301.0",
    "gn:asciiname":"Sao Goncalo",
    "gn:country_code":"BR",
    "gn:dem":528,
    "gn:feature_class":"P",
    "gn:feature_code":"PPL",
    "gn:name":"S\u00e3o Goncalo",
    "gn:population":0,
    "gn:timezone":"America/Recife",
    "iso:country":"BR",
    "wof:name":"Sao Goncalo",
    "wof:placetype":"locality"
},
  "geometry": {"coordinates":[-39.76667,-7.51667],"type":"Point"}
}