{
  "type": "Feature",
  "properties": {
    "gn:admin1_code":"18.0",
    "gn:admin2_code":"4113205.0",
    "gn:asciiname":"Sitio Francisco Raiz",
    "gn:country_code":"BR",
    "gn:dem":858,
    "gn:feature_class":"P",
    "gn:feature_code":"PPL",
    "gn:name":"S\u00edtio Francisco Raiz",
    "gn:population":0,
    "gn:timezone":"America/Sao_Paulo",
    "iso:country":"BR",
    "name:por_x_preferred":[
        "S\u00edtio Francisco Raiz"
    ],
    "wof:name":"Sitio Francisco Raiz",
    "wof:placetype":"locality"
},
  "geometry": {"coordinates":[-49.95532,-25.95447],"type":"Point"}
}