{
  "type": "Feature",
  "properties": {
    "gn:admin1_code":"18",
    "gn:admin2_code":"4113205.0",
    "gn:asciiname":"Sitio Benedito H. Goncalves",
    "gn:country_code":"BR",
    "gn:dem":932,
    "gn:feature_class":"P",
    "gn:feature_code":"PPL",
    "gn:name":"S\u00edtio Benedito H. Gon\u00e7alves",
    "gn:population":0,
    "gn:timezone":"America/Sao_Paulo",
    "iso:country":"BR",
    "name:por_x_preferred":[
        "S\u00edtio Benedito H. Gon\u00e7alves"
    ],
    "wof:name":"Sitio Benedito H. Goncalves",
    "wof:placetype":"locality"
},
  "geometry": {"coordinates":[-49.74833,-25.78972000000001],"type":"Point"}
}