{
  "type": "Feature",
  "properties": {
    "gn:admin1_code":"26",
    "gn:admin2_code":"4211652.0",
    "gn:asciiname":"Novo Horizonte",
    "gn:country_code":"BR",
    "gn:dem":697,
    "gn:feature_class":"P",
    "gn:feature_code":"PPL",
    "gn:name":"Novo Horizonte",
    "gn:population":0,
    "gn:timezone":"America/Sao_Paulo",
    "iso:country":"BR",
    "wof:name":"Novo Horizonte",
    "wof:placetype":"locality"
},
  "geometry": {"coordinates":[-52.83361,-26.44444],"type":"Point"}
}