{
  "type": "Feature",
  "properties": {
    "gn:admin1_code":"26",
    "gn:admin2_code":"4211652.0",
    "gn:asciiname":"Novo Horizonte",
    "gn:country_code":"BR",
    "gn:dem":697,
    "gn:feature_class":"P",
    "gn:feature_code":"PPL",
    "gn:name":"Novo Horizonte",
    "gn:population":0,
    "gn:timezone":"America/Sao_Paulo",
    "iso:country":"BR",
    "name:eus_x_preferred":[
        "Novo Horizonte"
    ],
    "name:fra_x_preferred":[
        "Novo Horizonte"
    ],
    "name:ina_x_preferred":[
        "Novo Horizonte"
    ],
    "name:ita_x_preferred":[
        "Novo Horizonte"
    ],
    "name:kat_x_preferred":[
        "\u10dc\u10dd\u10d5\u10e3-\u10dd\u10e0\u10d8\u10d6\u10dd\u10dc\u10e2\u10d8"
    ],
    "name:nld_x_preferred":[
        "Novo Horizonte"
    ],
    "name:nor_x_preferred":[
        "Novo Horizonte"
    ],
    "name:oci_x_preferred":[
        "Novo Horizonte"
    ],
    "name:pol_x_preferred":[
        "Novo Horizonte"
    ],
    "name:por_x_preferred":[
        "Novo Horizonte"
    ],
    "name:rus_x_preferred":[
        "\u041d\u043e\u0432\u0443-\u041e\u0440\u0438\u0437\u043e\u043d\u0442\u0438"
    ],
    "name:spa_x_preferred":[
        "Novo Horizonte"
    ],
    "name:vol_x_preferred":[
        "Novo Horizonte"
    ],
    "name:war_x_preferred":[
        "Novo Horizonte"
    ],
    "name:zho_x_preferred":[
        "\u65b0\u5967\u91cc\u85cf\u7279"
    ],
    "wof:name":"Novo Horizonte",
    "wof:placetype":"locality"
},
  "geometry": {"coordinates":[-52.83361,-26.44444],"type":"Point"}
}