{
  "type": "Feature",
  "properties": {
    "gn:admin1_code":"26",
    "gn:admin2_code":"4211652.0",
    "gn:asciiname":"Novo Horizonte",
    "gn:country_code":"BR",
    "gn:dem":697,
    "gn:feature_class":"P",
    "gn:feature_code":"PPL",
    "gn:name":"Novo Horizonte",
    "gn:population":0,
    "gn:timezone":"America/Sao_Paulo",
    "iso:country":"BR",
    "name:ara_x_preferred":[
        "\u0646\u0648\u0641\u0648 \u0647\u0648\u0631\u064a\u0632\u0648\u0646\u062a\u064a"
    ],
    "name:ben_x_preferred":[
        "\u09a8\u09cb\u09ad\u09cb \u09b9\u09b0\u09be\u0987\u099c\u09cb\u09a8\u09cd\u09a4\u09c7"
    ],
    "name:ell_x_preferred":[
        "\u039d\u03cc\u03b2\u03bf \u039f\u03c1\u03b9\u03b6\u03cc\u03bd\u03c4\u03b5"
    ],
    "name:eus_x_preferred":[
        "Novo Horizonte"
    ],
    "name:fas_x_preferred":[
        "\u0646\u0648\u0648 \u0647\u0648\u0631\u06cc\u0632\u0646\u062a\u0647"
    ],
    "name:fra_x_preferred":[
        "Novo Horizonte"
    ],
    "name:heb_x_preferred":[
        "\u05e0\u05d5\u05d1\u05d5 \u05d4\u05d5\u05e8\u05d9\u05d6\u05d5\u05e0\u05d8\u05d4"
    ],
    "name:hin_x_preferred":[
        "\u0928\u094b\u0935\u094b \u0911\u0930\u0949\u091c\u093c\u093e\u0902\u091f\u0947"
    ],
    "name:ina_x_preferred":[
        "Novo Horizonte"
    ],
    "name:ind_x_preferred":[
        "Novo Horizonte"
    ],
    "name:ita_x_preferred":[
        "Novo Horizonte"
    ],
    "name:kat_x_preferred":[
        "\u10dc\u10dd\u10d5\u10e3-\u10dd\u10e0\u10d8\u10d6\u10dd\u10dc\u10e2\u10d8"
    ],
    "name:kor_x_preferred":[
        "\ub178\ubcf4 \uc624\ub9ac\ud3f0\ud14c"
    ],
    "name:nld_x_preferred":[
        "Novo Horizonte"
    ],
    "name:nor_x_preferred":[
        "Novo Horizonte"
    ],
    "name:oci_x_preferred":[
        "Novo Horizonte"
    ],
    "name:pol_x_preferred":[
        "Novo Horizonte"
    ],
    "name:por_x_preferred":[
        "Novo Horizonte"
    ],
    "name:rus_x_preferred":[
        "\u041d\u043e\u0432\u0443-\u041e\u0440\u0438\u0437\u043e\u043d\u0442\u0438"
    ],
    "name:spa_x_preferred":[
        "Novo Horizonte"
    ],
    "name:tur_x_preferred":[
        "Novo Horizonte"
    ],
    "name:ukr_x_preferred":[
        "\u041d\u043e\u0432\u043e-\u0413\u043e\u0440\u0456\u0437\u043e\u043d\u0442\u0435"
    ],
    "name:urd_x_preferred":[
        "\u0646\u0648\u0648 \u06c1\u0648\u0631\u06cc\u0632\u0648\u0646\u0679\u06d2"
    ],
    "name:vol_x_preferred":[
        "Novo Horizonte"
    ],
    "name:war_x_preferred":[
        "Novo Horizonte"
    ],
    "name:zho_x_preferred":[
        "\u65b0\u5967\u91cc\u85cf\u7279"
    ],
    "wof:name":"Novo Horizonte",
    "wof:placetype":"locality"
},
  "geometry": {"coordinates":[-52.83361,-26.44444],"type":"Point"}
}