{
  "type": "Feature",
  "properties": {
    "gn:admin1_code":"18.0",
    "gn:admin2_code":"4126603.0",
    "gn:asciiname":"Sitio Francisca Messias",
    "gn:country_code":"BR",
    "gn:dem":626,
    "gn:feature_class":"P",
    "gn:feature_code":"PPL",
    "gn:name":"S\u00edtio Francisca Messias",
    "gn:population":0,
    "gn:timezone":"America/Sao_Paulo",
    "iso:country":"BR",
    "name:por_x_preferred":[
        "S\u00edtio Francisca Messias"
    ],
    "wof:name":"Sitio Francisca Messias",
    "wof:placetype":"locality"
},
  "geometry": {"coordinates":[-49.7829,-23.6493],"type":"Point"}
}