{
  "type": "Feature",
  "properties": {
    "gn:admin1_code":"27",
    "gn:admin2_code":"3528403.0",
    "gn:asciiname":"Sitio Fujio",
    "gn:country_code":"BR",
    "gn:dem":896,
    "gn:feature_class":"P",
    "gn:feature_code":"PPL",
    "gn:name":"S\u00edtio Fujio",
    "gn:population":0,
    "gn:timezone":"America/Sao_Paulo",
    "iso:country":"BR",
    "name:por_x_preferred":[
        "S\u00edtio Fujio"
    ],
    "wof:name":"Sitio Fujio",
    "wof:placetype":"locality"
},
  "geometry": {"coordinates":[-47.20911,-23.58944],"type":"Point"}
}