{
  "type": "Feature",
  "properties": {
    "gn:admin1_code":"06",
    "gn:admin2_code":"2310902.0",
    "gn:asciiname":"Sao Luis",
    "gn:country_code":"BR",
    "gn:dem":271,
    "gn:feature_class":"P",
    "gn:feature_code":"PPL",
    "gn:name":"S\u00e3o Lu\u00eds",
    "gn:population":0,
    "gn:timezone":"America/Fortaleza",
    "iso:country":"BR",
    "wof:name":"Sao Luis",
    "wof:placetype":"locality"
},
  "geometry": {"coordinates":[-39.35,-5.78333],"type":"Point"}
}