{
  "type": "Feature",
  "properties": {
    "gn:admin1_code":"6",
    "gn:admin2_code":"2304103.0",
    "gn:asciiname":"Cabacas",
    "gn:country_code":"BR",
    "gn:dem":271,
    "gn:feature_class":"P",
    "gn:feature_code":"PPL",
    "gn:name":"Caba\u00e7as",
    "gn:population":0,
    "gn:timezone":"America/Fortaleza",
    "iso:country":"BR",
    "wof:name":"Cabacas",
    "wof:placetype":"locality"
},
  "geometry": {"coordinates":[-40.86667,-5.06667],"type":"Point"}
}