{
  "type": "Feature",
  "properties": {
    "gn:admin1_code":"5",
    "gn:admin2_code":"2929008.0",
    "gn:asciiname":"Cachoeirinha",
    "gn:country_code":"BR",
    "gn:dem":176,
    "gn:feature_class":"P",
    "gn:feature_code":"PPL",
    "gn:name":"Cachoeirinha",
    "gn:population":0,
    "gn:timezone":"America/Bahia",
    "iso:country":"BR",
    "wof:name":"Cachoeirinha",
    "wof:placetype":"locality"
},
  "geometry": {"coordinates":[-38.96667,-12.65],"type":"Point"}
}