{
  "type": "Feature",
  "properties": {
    "gn:admin1_code":"27.0",
    "gn:admin2_code":"3505401.0",
    "gn:asciiname":"Sitio Uniao",
    "gn:country_code":"BR",
    "gn:dem":206,
    "gn:feature_class":"P",
    "gn:feature_code":"PPL",
    "gn:name":"S\u00edtio Uni\u00e3o",
    "gn:population":0,
    "gn:timezone":"America/Sao_Paulo",
    "iso:country":"BR",
    "name:por_x_preferred":[
        "S\u00edtio Uni\u00e3o"
    ],
    "wof:name":"Sitio Uniao",
    "wof:placetype":"locality"
},
  "geometry": {"coordinates":[-48.5385,-24.8842],"type":"Point"}
}