{
  "type": "Feature",
  "properties": {
    "gn:admin1_code":"5",
    "gn:admin2_code":"2910602.0",
    "gn:asciiname":"Mucuge",
    "gn:country_code":"BR",
    "gn:dem":29,
    "gn:feature_class":"P",
    "gn:feature_code":"PPL",
    "gn:name":"Mucug\u00ea",
    "gn:population":0,
    "gn:timezone":"America/Bahia",
    "iso:country":"BR",
    "name:und_x_variant":[
        "Mucuj\u00ea",
        "Mucug\u00ea"
    ],
    "wof:name":"Mucuge",
    "wof:placetype":"locality"
},
  "geometry": {"coordinates":[-37.88543,-12.2141],"type":"Point"}
}