{
  "type": "Feature",
  "properties": {
    "gn:admin1_code":"17",
    "gn:admin2_code":"2516805.0",
    "gn:asciiname":"Triunfo",
    "gn:country_code":"BR",
    "gn:dem":308,
    "gn:feature_class":"P",
    "gn:feature_code":"PPL",
    "gn:name":"Triunfo",
    "gn:population":0,
    "gn:timezone":"America/Fortaleza",
    "iso:country":"BR",
    "name:ceb_x_preferred":[
        "Triunfo"
    ],
    "name:deu_x_preferred":[
        "Triunfo"
    ],
    "name:eus_x_preferred":[
        "Triunfo"
    ],
    "name:fra_x_preferred":[
        "Triunfo"
    ],
    "name:ita_x_preferred":[
        "Triunfo"
    ],
    "name:kaz_x_preferred":[
        "\u0422\u0440\u0438\u0443\u043d\u0444\u0443"
    ],
    "name:nld_x_preferred":[
        "Triunfo"
    ],
    "name:nor_x_preferred":[
        "Triunfo"
    ],
    "name:por_x_preferred":[
        "Triunfo"
    ],
    "name:rus_x_preferred":[
        "\u0422\u0440\u0438\u0443\u043d\u0444\u0443"
    ],
    "name:spa_x_preferred":[
        "Triunfo"
    ],
    "name:swe_x_preferred":[
        "Triunfo"
    ],
    "name:vie_x_preferred":[
        "Triunfo"
    ],
    "name:vol_x_preferred":[
        "Triunfo"
    ],
    "wof:name":"Triunfo",
    "wof:placetype":"locality"
},
  "geometry": {"coordinates":[-38.59694,-6.57861],"type":"Point"}
}