{
  "type": "Feature",
  "properties": {
    "gn:admin1_code":"20",
    "gn:admin2_code":"2206357.0",
    "gn:asciiname":"Sitio Velho",
    "gn:country_code":"BR",
    "gn:dem":314,
    "gn:feature_class":"P",
    "gn:feature_code":"PPL",
    "gn:name":"S\u00edtio Velho",
    "gn:population":0,
    "gn:timezone":"America/Fortaleza",
    "iso:country":"BR",
    "wof:name":"Sitio Velho",
    "wof:placetype":"locality"
},
  "geometry": {"coordinates":[-41.68333,-4.73333],"type":"Point"}
}