{
  "type": "Feature",
  "properties": {
    "gn:admin1_code":"18.0",
    "gn:admin2_code":"4127809.0",
    "gn:asciiname":"Sitio Arlindo Farias",
    "gn:country_code":"BR",
    "gn:dem":554,
    "gn:feature_class":"P",
    "gn:feature_code":"PPL",
    "gn:name":"S\u00edtio Arlindo Farias",
    "gn:population":0,
    "gn:timezone":"America/Sao_Paulo",
    "iso:country":"BR",
    "name:por_x_preferred":[
        "S\u00edtio Arlindo Farias"
    ],
    "wof:name":"Sitio Arlindo Farias",
    "wof:placetype":"locality"
},
  "geometry": {"coordinates":[-49.9424,-23.6948],"type":"Point"}
}