{
  "type": "Feature",
  "properties": {
    "gn:admin1_code":"27",
    "gn:admin2_code":"3530607.0",
    "gn:asciiname":"Stio A. Colossal",
    "gn:country_code":"BR",
    "gn:dem":624,
    "gn:feature_class":"P",
    "gn:feature_code":"PPL",
    "gn:name":"Stio A. Colossal",
    "gn:population":0,
    "gn:timezone":"America/Sao_Paulo",
    "iso:country":"BR",
    "name:por_x_preferred":[
        "Stio A. Colossal"
    ],
    "wof:name":"Stio A. Colossal",
    "wof:placetype":"locality"
},
  "geometry": {"coordinates":[-46.16264,-23.38763],"type":"Point"}
}