{
  "type": "Feature",
  "properties": {
    "gn:admin1_code":"20",
    "gn:admin2_code":"2202851.0",
    "gn:asciiname":"Laje",
    "gn:country_code":"BR",
    "gn:dem":413,
    "gn:feature_class":"P",
    "gn:feature_code":"PPL",
    "gn:name":"Laje",
    "gn:population":0,
    "gn:timezone":"America/Fortaleza",
    "iso:country":"BR",
    "name:und_x_variant":[
        "Laje de Pedra"
    ],
    "wof:name":"Laje",
    "wof:placetype":"locality"
},
  "geometry": {"coordinates":[-42.20248,-9.18917],"type":"Point"}
}