{
  "type": "Feature",
  "properties": {
    "gn:admin1_code":"03",
    "gn:admin2_code":"1600204.0",
    "gn:asciiname":"Pedro de Freitas",
    "gn:country_code":"BR",
    "gn:dem":19,
    "gn:feature_class":"P",
    "gn:feature_code":"PPL",
    "gn:name":"Pedro de Freitas",
    "gn:population":0,
    "gn:timezone":"America/Belem",
    "iso:country":"BR",
    "wof:name":"Pedro de Freitas",
    "wof:placetype":"locality"
},
  "geometry": {"coordinates":[-50.85,2.15],"type":"Point"}
}