{
  "type": "Feature",
  "properties": {
    "gn:admin1_code":"18.0",
    "gn:admin2_code":"4121208.0",
    "gn:asciiname":"Sitio Roberto J. R. Junior",
    "gn:country_code":"BR",
    "gn:dem":865,
    "gn:feature_class":"P",
    "gn:feature_code":"PPL",
    "gn:name":"S\u00edtio Roberto J. R. J\u00fanior",
    "gn:population":0,
    "gn:timezone":"America/Sao_Paulo",
    "iso:country":"BR",
    "name:por_x_preferred":[
        "S\u00edtio Roberto J. R. J\u00fanior"
    ],
    "wof:name":"Sitio Roberto J. R. Junior",
    "wof:placetype":"locality"
},
  "geometry": {"coordinates":[-49.6031,-25.884],"type":"Point"}
}