{
  "type": "Feature",
  "properties": {
    "gn:admin1_code":"23",
    "gn:admin2_code":"4310439.0",
    "gn:asciiname":"Estrada do Campo",
    "gn:cc2":"BR",
    "gn:country_code":"BR",
    "gn:dem":824,
    "gn:feature_class":"P",
    "gn:feature_code":"PPL",
    "gn:name":"Estrada do Campo",
    "gn:population":0,
    "gn:timezone":"America/Sao_Paulo",
    "iso:country":"BR",
    "name:und_x_variant":[
        "Entrada do Campo",
        "Estrada do Campo"
    ],
    "wof:name":"Estrada do Campo",
    "wof:placetype":"locality"
},
  "geometry": {"coordinates":[-51.26667,-28.73333],"type":"Point"}
}