{
  "type": "Feature",
  "properties": {
    "gn:admin1_code":"5",
    "gn:admin2_code":"2932903.0",
    "gn:asciiname":"Parituabe",
    "gn:country_code":"BR",
    "gn:dem":23,
    "gn:feature_class":"P",
    "gn:feature_code":"PPL",
    "gn:name":"Parituabe",
    "gn:population":0,
    "gn:timezone":"America/Bahia",
    "iso:country":"BR",
    "wof:name":"Parituabe",
    "wof:placetype":"locality"
},
  "geometry": {"coordinates":[-39.08333,-13.43333],"type":"Point"}
}