{
  "type": "Feature",
  "properties": {
    "gn:admin1_code":"06",
    "gn:admin2_code":"2304350.0",
    "gn:asciiname":"Lagoa Nova (1)",
    "gn:country_code":"BR",
    "gn:dem":134,
    "gn:feature_class":"P",
    "gn:feature_code":"PPL",
    "gn:name":"Lagoa Nova (1)",
    "gn:population":0,
    "gn:timezone":"America/Fortaleza",
    "iso:country":"BR",
    "wof:name":"Lagoa Nova (1)",
    "wof:placetype":"locality"
},
  "geometry": {"coordinates":[-40.25,-3.86667],"type":"Point"}
}