{
  "type": "Feature",
  "properties": {
    "gn:admin1_code":"20",
    "gn:admin2_code":"2204808.0",
    "gn:asciiname":"Guarani",
    "gn:country_code":"BR",
    "gn:dem":415,
    "gn:feature_class":"P",
    "gn:feature_code":"PPL",
    "gn:name":"Guarani",
    "gn:population":0,
    "gn:timezone":"America/Fortaleza",
    "iso:country":"BR",
    "wof:name":"Guarani",
    "wof:placetype":"locality"
},
  "geometry": {"coordinates":[-41.76667,-6.86667],"type":"Point"}
}