{
  "type": "Feature",
  "properties": {
    "gn:admin1_code":"20",
    "gn:admin2_code":"2205532.0",
    "gn:asciiname":"Cana Brava",
    "gn:country_code":"BR",
    "gn:dem":644,
    "gn:feature_class":"P",
    "gn:feature_code":"PPL",
    "gn:name":"Cana Brava",
    "gn:population":0,
    "gn:timezone":"America/Fortaleza",
    "iso:country":"BR",
    "wof:name":"Cana Brava",
    "wof:placetype":"locality"
},
  "geometry": {"coordinates":[-43.16667,-8.96667],"type":"Point"}
}