{
  "type": "Feature",
  "properties": {
    "gn:admin1_code":"18",
    "gn:admin2_code":"4122305.0",
    "gn:asciiname":"Sitio Vidal Barbosa",
    "gn:country_code":"BR",
    "gn:dem":867,
    "gn:feature_class":"P",
    "gn:feature_code":"PPL",
    "gn:name":"S\u00edtio Vidal Barbosa",
    "gn:population":0,
    "gn:timezone":"America/Sao_Paulo",
    "iso:country":"BR",
    "name:por_x_preferred":[
        "S\u00edtio Vidal Barbosa"
    ],
    "wof:name":"Sitio Vidal Barbosa",
    "wof:placetype":"locality"
},
  "geometry": {"coordinates":[-49.55451,-26.08463],"type":"Point"}
}