{
  "type": "Feature",
  "properties": {
    "gn:admin1_code":"18",
    "gn:admin2_code":"4101200.0",
    "gn:asciiname":"Turvo",
    "gn:country_code":"BR",
    "gn:dem":24,
    "gn:feature_class":"P",
    "gn:feature_code":"PPL",
    "gn:name":"Turvo",
    "gn:population":0,
    "gn:timezone":"America/Sao_Paulo",
    "iso:country":"BR",
    "wof:name":"Turvo",
    "wof:placetype":"locality"
},
  "geometry": {"coordinates":[-48.68333,-25.28333],"type":"Point"}
}