{
  "type": "Feature",
  "properties": {
    "gn:admin1_code":"18.0",
    "gn:admin2_code":"4101101.0",
    "gn:asciiname":"Sitio Angelo Coleti",
    "gn:country_code":"BR",
    "gn:dem":489,
    "gn:feature_class":"P",
    "gn:feature_code":"PPL",
    "gn:name":"S\u00edtio \u00c2ngelo Coleti",
    "gn:population":0,
    "gn:timezone":"America/Sao_Paulo",
    "iso:country":"BR",
    "name:por_x_preferred":[
        "S\u00edtio \u00c2ngelo Coleti"
    ],
    "wof:name":"Sitio Angelo Coleti",
    "wof:placetype":"locality"
},
  "geometry": {"coordinates":[-50.2065,-23.0686],"type":"Point"}
}