{
  "type": "Feature",
  "properties": {
    "gn:admin1_code":"4",
    "gn:admin2_code":"1300805.0",
    "gn:asciiname":"Inveja",
    "gn:country_code":"BR",
    "gn:dem":36,
    "gn:feature_class":"P",
    "gn:feature_code":"PPL",
    "gn:name":"Inveja",
    "gn:population":0,
    "gn:timezone":"America/Manaus",
    "iso:country":"BR",
    "wof:name":"Inveja",
    "wof:placetype":"locality"
},
  "geometry": {"coordinates":[-59.42722,-4.63444],"type":"Point"}
}