{
  "type": "Feature",
  "properties": {
    "gn:admin1_code":"31",
    "gn:admin2_code":"1706001.0",
    "gn:asciiname":"Santa Maria Velha",
    "gn:country_code":"BR",
    "gn:dem":151,
    "gn:feature_class":"P",
    "gn:feature_code":"PPL",
    "gn:name":"Santa Maria Velha",
    "gn:population":0,
    "gn:timezone":"America/Araguaina",
    "iso:country":"BR",
    "wof:name":"Santa Maria Velha",
    "wof:placetype":"locality"
},
  "geometry": {"coordinates":[-49.26833,-8.34028],"type":"Point"}
}