{
  "type": "Feature",
  "properties": {
    "gn:gn_country":"BR",
    "gn:gn_fcode":"PPL",
    "gn:gn_pop":34053,
    "gn:population":34053,
    "iso:country":"BR",
    "name:baq_x_preferred":[
        "Tom\u00e9-A\u00e7u"
    ],
    "name:bpy_x_preferred":[
        "\u099f\u09cb\u09ae\u09c7-\u0986\u0995\u09c1"
    ],
    "name:chi_x_preferred":[
        "\u6258\u59c6\u963f\u8607"
    ],
    "name:dut_x_preferred":[
        "Tom\u00e9-A\u00e7u"
    ],
    "name:eng_x_preferred":[
        "Tom\u00e9-A\u00e7u"
    ],
    "name:fre_x_preferred":[
        "Tom\u00e9-A\u00e7u"
    ],
    "name:ger_x_preferred":[
        "Tom\u00e9-A\u00e7u"
    ],
    "name:hun_x_preferred":[
        "Tom\u00e9-A\u00e7u"
    ],
    "name:ita_x_preferred":[
        "Tom\u00e9-A\u00e7u"
    ],
    "name:jpn_x_preferred":[
        "\u30c8\u30e1\u30a2\u30b9\u30fc"
    ],
    "name:kaz_x_preferred":[
        "\u0422\u043e\u043c\u0435-\u0410\u0441\u0443"
    ],
    "name:nan_x_preferred":[
        "Tom\u00e9-A\u00e7u"
    ],
    "name:nob_x_preferred":[
        "Tom\u00e9-A\u00e7u"
    ],
    "name:pol_x_preferred":[
        "Tom\u00e9-A\u00e7u"
    ],
    "name:por_x_preferred":[
        "Tom\u00e9-A\u00e7u"
    ],
    "name:rum_x_preferred":[
        "Tom\u00e9-A\u00e7u"
    ],
    "name:rus_x_preferred":[
        "\u0422\u043e\u043c\u0435-\u0410\u0441\u0443"
    ],
    "name:swe_x_preferred":[
        "Tom\u00e9-A\u00e7u"
    ],
    "name:vie_x_preferred":[
        "Tom\u00e9-A\u00e7u"
    ],
    "name:vol_x_preferred":[
        "Tom\u00e9-A\u00e7u"
    ],
    "name:war_x_preferred":[
        "Tom\u00e9-A\u00e7u"
    ],
    "qs_pg:aaroncc":"BR",
    "qs_pg:gn_country":"BR",
    "qs_pg:gn_fcode":"PPL",
    "qs_pg:gn_pop":34053,
    "qs_pg:name":"Tom\u00e9 A\u00e7u",
    "qs_pg:photos_9r":0,
    "qs_pg:photos_sr":0,
    "qs_pg:pop_sr":7,
    "qs_pg:qs_pg_placetype":"locality",
    "wof:name":"Tom\u00e9 A\u00e7u",
    "wof:placetype":"locality",
    "wof:population":34053
},
  "geometry": {"coordinates":[-48.15222,-2.41889],"type":"Point"}
}