{
  "type": "Feature",
  "properties": {
    "gn:admin1_code":"30",
    "gn:admin2_code":"2610301.0",
    "gn:asciiname":"Beldroega",
    "gn:country_code":"BR",
    "gn:dem":819,
    "gn:feature_class":"P",
    "gn:feature_code":"PPL",
    "gn:name":"Beldroega",
    "gn:population":0,
    "gn:timezone":"America/Recife",
    "iso:country":"BR",
    "wof:name":"Beldroega",
    "wof:placetype":"locality"
},
  "geometry": {"coordinates":[-36.75,-8.85],"type":"Point"}
}