{
  "type": "Feature",
  "properties": {
    "gn:admin1_code":"18.0",
    "gn:admin2_code":"4109708.0",
    "gn:asciiname":"Sitio Eduardo Carmceiro",
    "gn:country_code":"BR",
    "gn:dem":603,
    "gn:feature_class":"P",
    "gn:feature_code":"PPL",
    "gn:name":"S\u00edtio Eduardo Carmceiro",
    "gn:population":0,
    "gn:timezone":"America/Sao_Paulo",
    "iso:country":"BR",
    "name:por_x_preferred":[
        "S\u00edtio Eduardo Carmceiro"
    ],
    "wof:name":"Sitio Eduardo Carmceiro",
    "wof:placetype":"locality"
},
  "geometry": {"coordinates":[-50.22251,-23.74963],"type":"Point"}
}