{
  "type": "Feature",
  "properties": {
    "gn:admin1_code":"13",
    "gn:admin2_code":"2101202.0",
    "gn:asciiname":"Cachucha",
    "gn:country_code":"BR",
    "gn:dem":60,
    "gn:feature_class":"P",
    "gn:feature_code":"PPL",
    "gn:name":"Cachucha",
    "gn:population":0,
    "gn:timezone":"America/Fortaleza",
    "iso:country":"BR",
    "wof:name":"Cachucha",
    "wof:placetype":"locality"
},
  "geometry": {"coordinates":[-44.46584,-4.19439],"type":"Point"}
}