{
  "type": "Feature",
  "properties": {
    "gn:admin1_code":"30",
    "gn:admin2_code":"2611002.0",
    "gn:asciiname":"Beldroegas",
    "gn:country_code":"BR",
    "gn:dem":472,
    "gn:feature_class":"P",
    "gn:feature_code":"PPL",
    "gn:name":"Beldroegas",
    "gn:population":0,
    "gn:timezone":"America/Recife",
    "iso:country":"BR",
    "wof:name":"Beldroegas",
    "wof:placetype":"locality"
},
  "geometry": {"coordinates":[-38.16667,-8.75],"type":"Point"}
}