{
  "type": "Feature",
  "properties": {
    "gn:admin1_code":"18.0",
    "gn:admin2_code":"4122305.0",
    "gn:asciiname":"Sitio Jose Muller",
    "gn:country_code":"BR",
    "gn:dem":790,
    "gn:feature_class":"P",
    "gn:feature_code":"PPL",
    "gn:name":"S\u00edtio Jos\u00e9 M\u00fcller",
    "gn:population":0,
    "gn:timezone":"America/Sao_Paulo",
    "iso:country":"BR",
    "name:por_x_preferred":[
        "S\u00edtio Jos\u00e9 M\u00fcller"
    ],
    "wof:name":"Sitio Jose Muller",
    "wof:placetype":"locality"
},
  "geometry": {"coordinates":[-49.84376,-25.97449],"type":"Point"}
}