{
  "type": "Feature",
  "properties": {
    "gn:admin1_code":"16.0",
    "gn:admin2_code":"1500206.0",
    "gn:asciiname":"Progresso",
    "gn:country_code":"BR",
    "gn:dem":24,
    "gn:feature_class":"P",
    "gn:feature_code":"PPL",
    "gn:name":"Progresso",
    "gn:population":0,
    "gn:timezone":"America/Belem",
    "iso:country":"BR",
    "wof:name":"Progresso",
    "wof:placetype":"locality"
},
  "geometry": {"coordinates":[-48.44935,-1.87362],"type":"Point"}
}