{
  "type": "Feature",
  "properties": {
    "gn:admin1_code":"16.0",
    "gn:admin2_code":"1500206.0",
    "gn:asciiname":"Progresso",
    "gn:country_code":"BR",
    "gn:dem":24,
    "gn:feature_class":"P",
    "gn:feature_code":"PPL",
    "gn:name":"Progresso",
    "gn:population":0,
    "gn:timezone":"America/Belem",
    "iso:country":"BR",
    "name:bpy_x_preferred":[
        "\u09aa\u09cd\u09b0\u09cb\u0997\u09cd\u09b0\u09c7\u09b8\u09b8\u09cb"
    ],
    "name:ceb_x_preferred":[
        "Progresso"
    ],
    "name:ita_x_preferred":[
        "Progresso"
    ],
    "name:nds_x_preferred":[
        "Progresso"
    ],
    "name:nld_x_preferred":[
        "Progresso"
    ],
    "name:por_x_preferred":[
        "Progresso"
    ],
    "name:spa_x_preferred":[
        "Progresso"
    ],
    "name:swe_x_preferred":[
        "Progresso"
    ],
    "wof:name":"Progresso",
    "wof:placetype":"locality"
},
  "geometry": {"coordinates":[-48.44935,-1.87362],"type":"Point"}
}