{
  "type": "Feature",
  "properties": {
    "gn:admin1_code":"18.0",
    "gn:admin2_code":"4109500.0",
    "gn:asciiname":"Rio dos Canoas",
    "gn:country_code":"BR",
    "gn:dem":9,
    "gn:feature_class":"P",
    "gn:feature_code":"PPLL",
    "gn:name":"Rio dos Canoas",
    "gn:population":0,
    "gn:timezone":"America/Sao_Paulo",
    "iso:country":"BR",
    "name:por_x_preferred":[
        "Rio dos Canoas"
    ],
    "wof:name":"Rio dos Canoas",
    "wof:placetype":"locality"
},
  "geometry": {"coordinates":[-48.35385,-25.22401],"type":"Point"}
}