{
  "type": "Feature",
  "properties": {
    "gn:admin1_code":"5",
    "gn:admin2_code":"2908101.0",
    "gn:asciiname":"Cana Brava",
    "gn:country_code":"BR",
    "gn:dem":712,
    "gn:feature_class":"P",
    "gn:feature_code":"PPL",
    "gn:name":"Cana Brava",
    "gn:population":0,
    "gn:timezone":"America/Bahia",
    "iso:country":"BR",
    "wof:name":"Cana Brava",
    "wof:placetype":"locality"
},
  "geometry": {"coordinates":[-45.81667,-15.11667],"type":"Point"}
}