{
  "type": "Feature",
  "properties": {
    "gn:admin1_code":"18.0",
    "gn:admin2_code":"4100202.0",
    "gn:asciiname":"Tanque",
    "gn:country_code":"BR",
    "gn:dem":691,
    "gn:feature_class":"P",
    "gn:feature_code":"PPLL",
    "gn:name":"Tanque",
    "gn:population":0,
    "gn:timezone":"America/Sao_Paulo",
    "iso:country":"BR",
    "name:ita_x_preferred":[
        "Tanque"
    ],
    "name:por_x_preferred":[
        "Tanque"
    ],
    "wof:name":"Tanque",
    "wof:placetype":"locality"
},
  "geometry": {"coordinates":[-48.79600000000001,-24.86062],"type":"Point"}
}