{
  "type": "Feature",
  "properties": {
    "gn:admin1_code":"11",
    "gn:admin2_code":"5002100.0",
    "gn:asciiname":"Agua Azul",
    "gn:country_code":"BR",
    "gn:dem":310,
    "gn:feature_class":"P",
    "gn:feature_code":"PPL",
    "gn:name":"\u00c1gua Azul",
    "gn:population":0,
    "gn:timezone":"America/Campo_Grande",
    "iso:country":"BR",
    "name:bre_x_preferred":[
        "Agua Azul"
    ],
    "name:lit_x_preferred":[
        "Agua Asulio krioklys"
    ],
    "name:pol_x_preferred":[
        "Wodospady Agua Azul"
    ],
    "name:swe_x_preferred":[
        "Agua Azul"
    ],
    "name:ukr_x_preferred":[
        "\u0410\u0433\u0432\u0430 \u0410\u0441\u0443\u043b\u044c"
    ],
    "wof:name":"Agua Azul",
    "wof:placetype":"locality"
},
  "geometry": {"coordinates":[-56.18333000000001,-21.93333],"type":"Point"}
}