{
  "type": "Feature",
  "properties": {
    "gn:admin1_code":"11",
    "gn:admin2_code":"5002100.0",
    "gn:asciiname":"Agua Azul",
    "gn:country_code":"BR",
    "gn:dem":310,
    "gn:feature_class":"P",
    "gn:feature_code":"PPL",
    "gn:name":"\u00c1gua Azul",
    "gn:population":0,
    "gn:timezone":"America/Campo_Grande",
    "iso:country":"BR",
    "wof:name":"Agua Azul",
    "wof:placetype":"locality"
},
  "geometry": {"coordinates":[-56.18333000000001,-21.93333],"type":"Point"}
}