{
  "type": "Feature",
  "properties": {
    "gn:admin1_code":"02",
    "gn:admin2_code":"2709152.0",
    "gn:asciiname":"Roceira",
    "gn:country_code":"BR",
    "gn:dem":80,
    "gn:feature_class":"P",
    "gn:feature_code":"PPL",
    "gn:name":"Roceira",
    "gn:population":0,
    "gn:timezone":"America/Maceio",
    "iso:country":"BR",
    "wof:name":"Roceira",
    "wof:placetype":"locality"
},
  "geometry": {"coordinates":[-36.35,-9.88333],"type":"Point"}
}