{
  "type": "Feature",
  "properties": {
    "gn:admin1_code":"23",
    "gn:admin2_code":"4302907.0",
    "gn:asciiname":"Entroncamento",
    "gn:cc2":"BR",
    "gn:country_code":"BR",
    "gn:dem":85,
    "gn:feature_class":"P",
    "gn:feature_code":"PPL",
    "gn:name":"Entroncamento",
    "gn:population":0,
    "gn:timezone":"America/Sao_Paulo",
    "iso:country":"BR",
    "name:ara_x_preferred":[
        "\u0627\u0646\u062a\u0631\u0648\u0646\u0643\u0627\u0645\u0646\u062a\u0648"
    ],
    "name:cat_x_preferred":[
        "Entroncamento"
    ],
    "name:ceb_x_preferred":[
        "Entroncamento"
    ],
    "name:deu_x_preferred":[
        "Entroncamento"
    ],
    "name:epo_x_preferred":[
        "Entroncamento"
    ],
    "name:fas_x_preferred":[
        "\u0627\u0646\u062a\u0631\u0648\u0646\u06a9\u0627\u0645\u0646\u062a\u0648"
    ],
    "name:fra_x_preferred":[
        "Entroncamento"
    ],
    "name:ita_x_preferred":[
        "Entroncamento"
    ],
    "name:kat_x_preferred":[
        "\u10d4\u10dc\u10e2\u10e0\u10dd\u10dc\u10d9\u10d0\u10db\u10d4\u10dc\u10e2\u10e3"
    ],
    "name:mzn_x_preferred":[
        "\u0627\u0646\u062a\u0631\u0648\u0646\u06a9\u0627\u0645\u0646\u062a\u0648"
    ],
    "name:nld_x_preferred":[
        "Entroncamento"
    ],
    "name:pol_x_preferred":[
        "Entroncamento"
    ],
    "name:por_x_preferred":[
        "Entroncamento"
    ],
    "name:ron_x_preferred":[
        "Entroncamento"
    ],
    "name:rus_x_preferred":[
        "\u042d\u043d\u0442\u0440\u043e\u043d\u043a\u0430\u043c\u0435\u043d\u0442\u0443"
    ],
    "name:spa_x_preferred":[
        "Entroncamento"
    ],
    "name:srp_x_preferred":[
        "\u0415\u043d\u0442\u0440\u043e\u043d\u043a\u0430\u043c\u0435\u043d\u0442\u043e"
    ],
    "name:tur_x_preferred":[
        "Entroncamento"
    ],
    "name:ukr_x_preferred":[
        "\u0415\u043d\u0442\u0440\u043e\u043d\u043a\u0430\u043c\u0435\u043d\u0442\u0443"
    ],
    "name:und_x_variant":[
        "Est\u00e2ncia Entroncamento",
        "Entroncamento"
    ],
    "name:vie_x_preferred":[
        "Entroncamento"
    ],
    "name:vol_x_preferred":[
        "Entroncamento"
    ],
    "name:war_x_preferred":[
        "Entroncamento"
    ],
    "name:zho_x_preferred":[
        "\u6069\u7279\u9f99\u5361\u95e8\u56fe"
    ],
    "wof:name":"Entroncamento",
    "wof:placetype":"locality"
},
  "geometry": {"coordinates":[-54.93333000000001,-29.85],"type":"Point"}
}