{
  "type": "Feature",
  "properties": {
    "gn:admin1_code":"23",
    "gn:admin2_code":"4302907.0",
    "gn:asciiname":"Entroncamento",
    "gn:cc2":"BR",
    "gn:country_code":"BR",
    "gn:dem":85,
    "gn:feature_class":"P",
    "gn:feature_code":"PPL",
    "gn:name":"Entroncamento",
    "gn:population":0,
    "gn:timezone":"America/Sao_Paulo",
    "iso:country":"BR",
    "name:und_x_variant":[
        "Est\u00e2ncia Entroncamento",
        "Entroncamento"
    ],
    "wof:name":"Entroncamento",
    "wof:placetype":"locality"
},
  "geometry": {"coordinates":[-54.93333000000001,-29.85],"type":"Point"}
}