{
  "type": "Feature",
  "properties": {
    "gn:admin1_code":"5",
    "gn:admin2_code":"2910107.0",
    "gn:asciiname":"Joao Para",
    "gn:country_code":"BR",
    "gn:dem":503,
    "gn:feature_class":"P",
    "gn:feature_code":"PPL",
    "gn:name":"Jo\u00e3o Par\u00e1",
    "gn:population":0,
    "gn:timezone":"America/Bahia",
    "iso:country":"BR",
    "wof:name":"Joao Para",
    "wof:placetype":"locality"
},
  "geometry": {"coordinates":[-41.76667,-13.73333],"type":"Point"}
}