{
  "type": "Feature",
  "properties": {
    "gn:admin1_code":"13",
    "gn:admin2_code":"2104800.0",
    "gn:asciiname":"Canoa Grande",
    "gn:country_code":"BR",
    "gn:dem":109,
    "gn:feature_class":"P",
    "gn:feature_code":"PPL",
    "gn:name":"Canoa Grande",
    "gn:population":0,
    "gn:timezone":"America/Fortaleza",
    "iso:country":"BR",
    "wof:name":"Canoa Grande",
    "wof:placetype":"locality"
},
  "geometry": {"coordinates":[-46.01667,-5.36667],"type":"Point"}
}