{
  "type": "Feature",
  "properties": {
    "gn:admin1_code":"06",
    "gn:admin2_code":"2310407.0",
    "gn:asciiname":"Vargem dos Bois",
    "gn:country_code":"BR",
    "gn:dem":97,
    "gn:feature_class":"P",
    "gn:feature_code":"PPL",
    "gn:name":"Vargem dos Bois",
    "gn:population":0,
    "gn:timezone":"America/Fortaleza",
    "iso:country":"BR",
    "wof:name":"Vargem dos Bois",
    "wof:placetype":"locality"
},
  "geometry": {"coordinates":[-39.25,-4.11667],"type":"Point"}
}