{
  "type": "Feature",
  "properties": {
    "gn:admin1_code":"30.0",
    "gn:admin2_code":"2614204.0",
    "gn:asciiname":"Sao Roque",
    "gn:country_code":"BR",
    "gn:dem":44,
    "gn:feature_class":"P",
    "gn:feature_code":"PPL",
    "gn:name":"S\u00e3o Roque",
    "gn:population":0,
    "gn:timezone":"America/Recife",
    "iso:country":"BR",
    "wof:name":"Sao Roque",
    "wof:placetype":"locality"
},
  "geometry": {"coordinates":[-35.11438,-8.59385],"type":"Point"}
}