{
  "type": "Feature",
  "properties": {
    "gn:admin1_code":"20",
    "gn:admin2_code":"2209104.0",
    "gn:asciiname":"Tamboril (3)",
    "gn:country_code":"BR",
    "gn:dem":272,
    "gn:feature_class":"P",
    "gn:feature_code":"PPL",
    "gn:name":"Tamboril (3)",
    "gn:population":0,
    "gn:timezone":"America/Fortaleza",
    "iso:country":"BR",
    "wof:name":"Tamboril (3)",
    "wof:placetype":"locality"
},
  "geometry": {"coordinates":[-41.68333,-7.33333],"type":"Point"}
}