{
  "type": "Feature",
  "properties": {
    "gn:admin1_code":"24",
    "gn:admin2_code":"1100106.0",
    "gn:asciiname":"Dom Pedrito",
    "gn:country_code":"BR",
    "gn:dem":145,
    "gn:feature_class":"P",
    "gn:feature_code":"PPL",
    "gn:name":"Dom Pedrito",
    "gn:population":0,
    "gn:timezone":"America/Porto_Velho",
    "iso:country":"BR",
    "name:bpy_x_preferred":[
        "\u09a1\u09cb\u09ae \u09aa\u09c7\u09a1\u09cd\u09b0\u09bf\u099f\u09cb"
    ],
    "name:epo_x_preferred":[
        "Dom Pedrito"
    ],
    "name:eus_x_preferred":[
        "Dom Pedrito"
    ],
    "name:fra_x_preferred":[
        "Dom Pedrito"
    ],
    "name:ita_x_preferred":[
        "Dom Pedrito"
    ],
    "name:kaz_x_preferred":[
        "\u0414\u043e\u043d-\u041f\u0435\u0434\u0440\u0438\u0442\u0443"
    ],
    "name:mlg_x_preferred":[
        "Dom Pedrito"
    ],
    "name:nld_x_preferred":[
        "Dom Pedrito"
    ],
    "name:nor_x_preferred":[
        "Dom Pedrito"
    ],
    "name:pol_x_preferred":[
        "Dom Pedrito"
    ],
    "name:por_x_preferred":[
        "Dom Pedrito"
    ],
    "name:ron_x_preferred":[
        "Dom Pedrito"
    ],
    "name:rus_x_preferred":[
        "\u0414\u043e\u043d-\u041f\u0435\u0434\u0440\u0438\u0442\u0443"
    ],
    "name:spa_x_preferred":[
        "Dom Pedrito"
    ],
    "name:vie_x_preferred":[
        "Dom Pedrito"
    ],
    "name:vol_x_preferred":[
        "Dom Pedrito"
    ],
    "name:war_x_preferred":[
        "Dom Pedrito"
    ],
    "name:zho_x_preferred":[
        "\u5510\u4f69\u5fb7\u91cc\u56fe"
    ],
    "wof:name":"Dom Pedrito",
    "wof:placetype":"locality"
},
  "geometry": {"coordinates":[-65.31667,-11.43333],"type":"Point"}
}