{
  "type": "Feature",
  "properties": {
    "gn:admin1_code":"24",
    "gn:admin2_code":"1100106.0",
    "gn:asciiname":"Dom Pedrito",
    "gn:country_code":"BR",
    "gn:dem":145,
    "gn:feature_class":"P",
    "gn:feature_code":"PPL",
    "gn:name":"Dom Pedrito",
    "gn:population":0,
    "gn:timezone":"America/Porto_Velho",
    "iso:country":"BR",
    "wof:name":"Dom Pedrito",
    "wof:placetype":"locality"
},
  "geometry": {"coordinates":[-65.31667,-11.43333],"type":"Point"}
}