{
  "type": "Feature",
  "properties": {
    "gn:admin1_code":"16",
    "gn:admin2_code":"1506807.0",
    "gn:asciiname":"Taperinha",
    "gn:cc2":"BR",
    "gn:country_code":"BR",
    "gn:dem":63,
    "gn:feature_class":"P",
    "gn:feature_code":"PPL",
    "gn:name":"Taperinha",
    "gn:population":0,
    "gn:timezone":"America/Santarem",
    "iso:country":"BR",
    "name:und_x_variant":[
        "Paderinha",
        "Taderinha",
        "Taperinha"
    ],
    "wof:name":"Taperinha",
    "wof:placetype":"locality"
},
  "geometry": {"coordinates":[-54.28333000000001,-2.53333],"type":"Point"}
}