{
  "type": "Feature",
  "properties": {
    "gn:admin1_code":"27",
    "gn:admin2_code":"3553302.0",
    "gn:asciiname":"Morrinhos",
    "gn:country_code":"BR",
    "gn:dem":606,
    "gn:feature_class":"P",
    "gn:feature_code":"PPL",
    "gn:name":"Morrinhos",
    "gn:population":0,
    "gn:timezone":"America/Sao_Paulo",
    "iso:country":"BR",
    "name:por_x_preferred":[
        "Morrinhos"
    ],
    "wof:name":"Morrinhos",
    "wof:placetype":"locality"
},
  "geometry": {"coordinates":[-47.23333,-21.51667],"type":"Point"}
}