{
  "type": "Feature",
  "properties": {
    "gn:admin1_code":"23",
    "gn:admin2_code":"4306908.0",
    "gn:asciiname":"Peral do Sobrado",
    "gn:country_code":"BR",
    "gn:dem":224,
    "gn:feature_class":"P",
    "gn:feature_code":"PPLL",
    "gn:name":"Peral do Sobrado",
    "gn:population":0,
    "gn:timezone":"America/Sao_Paulo",
    "iso:country":"BR",
    "name:por_x_preferred":[
        "Peral do Sobrado"
    ],
    "wof:name":"Peral do Sobrado",
    "wof:placetype":"locality"
},
  "geometry": {"coordinates":[-52.3858,-30.6575],"type":"Point"}
}