{
  "type": "Feature",
  "properties": {
    "gn:admin1_code":"29",
    "gn:admin2_code":"5205513.0",
    "gn:asciiname":"Mombaco",
    "gn:country_code":"BR",
    "gn:dem":1109,
    "gn:feature_class":"P",
    "gn:feature_code":"PPL",
    "gn:name":"Momba\u00e7o",
    "gn:population":0,
    "gn:timezone":"America/Sao_Paulo",
    "iso:country":"BR",
    "wof:name":"Mombaco",
    "wof:placetype":"locality"
},
  "geometry": {"coordinates":[-48.71667,-15.71667],"type":"Point"}
}