{
  "type": "Feature",
  "properties": {
    "gn:admin1_code":"18.0",
    "gn:admin2_code":"4127809.0",
    "gn:asciiname":"Sitio Antonio A. Barbosa",
    "gn:country_code":"BR",
    "gn:dem":482,
    "gn:feature_class":"P",
    "gn:feature_code":"PPL",
    "gn:name":"S\u00edtio Ant\u00f4nio A. Barbosa",
    "gn:population":0,
    "gn:timezone":"America/Sao_Paulo",
    "iso:country":"BR",
    "name:por_x_preferred":[
        "S\u00edtio Ant\u00f4nio A. Barbosa"
    ],
    "wof:name":"Sitio Antonio A. Barbosa",
    "wof:placetype":"locality"
},
  "geometry": {"coordinates":[-49.9873,-23.7431],"type":"Point"}
}