{
  "type": "Feature",
  "properties": {
    "gn:admin1_code":"30",
    "gn:admin2_code":"2613909.0",
    "gn:asciiname":"Prazeres",
    "gn:country_code":"BR",
    "gn:dem":575,
    "gn:feature_class":"P",
    "gn:feature_code":"PPL",
    "gn:name":"Prazeres",
    "gn:population":0,
    "gn:timezone":"America/Recife",
    "iso:country":"BR",
    "name:ceb_x_preferred":[
        "Prazeres"
    ],
    "name:deu_x_preferred":[
        "Prazeres"
    ],
    "name:ita_x_preferred":[
        "Prazeres"
    ],
    "name:nld_x_preferred":[
        "Prazeres"
    ],
    "name:por_x_preferred":[
        "Prazeres"
    ],
    "name:rus_x_preferred":[
        "\u041f\u0440\u0430\u0437\u0435\u0440\u0435\u0448"
    ],
    "name:spa_x_preferred":[
        "Prazeres"
    ],
    "name:swe_x_preferred":[
        "Prazeres"
    ],
    "wof:name":"Prazeres",
    "wof:placetype":"locality"
},
  "geometry": {"coordinates":[-38.46667,-7.81667],"type":"Point"}
}