{
  "type": "Feature",
  "properties": {
    "gn:admin1_code":"18.0",
    "gn:admin2_code":"4124707.0",
    "gn:asciiname":"Sitio Tres Minas",
    "gn:country_code":"BR",
    "gn:dem":1026,
    "gn:feature_class":"P",
    "gn:feature_code":"PPL",
    "gn:name":"S\u00edtio Tr\u00eas Minas",
    "gn:population":0,
    "gn:timezone":"America/Sao_Paulo",
    "iso:country":"BR",
    "name:por_x_preferred":[
        "S\u00edtio Tr\u00eas Minas"
    ],
    "wof:name":"Sitio Tres Minas",
    "wof:placetype":"locality"
},
  "geometry": {"coordinates":[-50.66831,-23.74977],"type":"Point"}
}