{
  "type": "Feature",
  "properties": {
    "gn:admin1_code":"27",
    "gn:admin2_code":"3507753.0",
    "gn:asciiname":"Porto Marcos Pereira",
    "gn:country_code":"BR",
    "gn:dem":374,
    "gn:feature_class":"P",
    "gn:feature_code":"PPL",
    "gn:name":"P\u00f4rto Marcos Pereira",
    "gn:population":0,
    "gn:timezone":"America/Sao_Paulo",
    "iso:country":"BR",
    "wof:name":"Porto Marcos Pereira",
    "wof:placetype":"locality"
},
  "geometry": {"coordinates":[-50.23333,-21.13333],"type":"Point"}
}