{
  "type": "Feature",
  "properties": {
    "gn:admin1_code":"22",
    "gn:admin2_code":"2400802.0",
    "gn:asciiname":"Bonsucesso",
    "gn:country_code":"BR",
    "gn:dem":89,
    "gn:feature_class":"P",
    "gn:feature_code":"PPL",
    "gn:name":"Bonsucesso",
    "gn:population":0,
    "gn:timezone":"America/Fortaleza",
    "iso:country":"BR",
    "name:ita_x_preferred":[
        "Bonsucesso"
    ],
    "name:por_x_preferred":[
        "Bonsucesso"
    ],
    "wof:name":"Bonsucesso",
    "wof:placetype":"locality"
},
  "geometry": {"coordinates":[-36.64556,-5.57861],"type":"Point"}
}