{
  "type": "Feature",
  "properties": {
    "iso:country":"BR",
    "name:cat_x_preferred":[
        "Santa Rosa"
    ],
    "name:ceb_x_preferred":[
        "Santa Rosa"
    ],
    "name:ces_x_preferred":[
        "Santa Rosa"
    ],
    "name:deu_x_preferred":[
        "Santa Rosa"
    ],
    "name:epo_x_preferred":[
        "Santa Rosa"
    ],
    "name:fin_x_preferred":[
        "Santa Rosa"
    ],
    "name:fra_x_preferred":[
        "Santa Rosa"
    ],
    "name:glg_x_preferred":[
        "Santa Rosa"
    ],
    "name:heb_x_preferred":[
        "\u05e1\u05e0\u05d8\u05d4 \u05e8\u05d5\u05e1\u05d4"
    ],
    "name:hun_x_preferred":[
        "Santa Rosa"
    ],
    "name:ilo_x_preferred":[
        "Santa Rosa"
    ],
    "name:ind_x_preferred":[
        "Santa Rosa"
    ],
    "name:ita_x_preferred":[
        "Santa Rosa"
    ],
    "name:jpn_x_preferred":[
        "\u30b5\u30f3\u30bf\u30ed\u30fc\u30b6"
    ],
    "name:kor_x_preferred":[
        "\uc0b0\ud0c0\ub85c\uc0ac"
    ],
    "name:lit_x_preferred":[
        "Santa Rosa"
    ],
    "name:mlg_x_preferred":[
        "Santa Rosa"
    ],
    "name:nds_x_preferred":[
        "Santa Rosa"
    ],
    "name:nld_x_preferred":[
        "Santa Rosa"
    ],
    "name:nor_x_preferred":[
        "Santa Rosa"
    ],
    "name:pol_x_preferred":[
        "Santa Rosa"
    ],
    "name:por_x_preferred":[
        "Santa Rosa"
    ],
    "name:rus_x_preferred":[
        "\u0421\u0430\u043d\u0442\u0430-\u0420\u043e\u0437\u0430"
    ],
    "name:sco_x_preferred":[
        "Santa Rosa"
    ],
    "name:slk_x_preferred":[
        "Santa Rosa"
    ],
    "name:spa_x_preferred":[
        "Santa Rosa"
    ],
    "name:srp_x_preferred":[
        "\u0421\u0430\u043d\u0442\u0430 \u0420\u043e\u0441\u0430"
    ],
    "name:swa_x_preferred":[
        "Santa Rosa"
    ],
    "name:swe_x_preferred":[
        "Santa Rosa"
    ],
    "name:vol_x_preferred":[
        "Santa Rosa"
    ],
    "name:war_x_preferred":[
        "Santa Rosa"
    ],
    "qs:gn_adm0_cc":"BR",
    "qs:gn_fcode":"PPL",
    "qs:gn_local":3456283,
    "qs:gn_nam_loc":"Niter\u00f3i, Niter\u00f3i, Rio de Janeiro, BR",
    "qs:gn_namadm1":"21",
    "qs:gn_name":"Santa Rosa",
    "qs:local_max":2228,
    "qs:local_sum":7420,
    "qs:localhoods":12,
    "qs:name":"Santa Rosa",
    "qs:name_adm0":"Brasil",
    "qs:name_adm1":"Rio de Janeiro",
    "qs:name_adm2":"Niter\u00f3i",
    "qs:name_local":"Niter\u00f3i",
    "qs:photo_max":115,
    "qs:photo_sum":223,
    "qs:placetype":"Suburb",
    "qs:quad_count":12,
    "qs:woe_adm0":23424768,
    "qs:woe_adm1":2344862,
    "qs:woe_adm2":12581047,
    "qs:woe_lau":0,
    "qs:woe_local":455891,
    "qs:woe_ver":"7.10.0",
    "wof:lang":[
        "por"
    ],
    "wof:name":"Santa Rosa",
    "wof:placetype":"neighbourhood"
},
  "geometry": {"coordinates":[-43.095838,-22.900727],"type":"Point"}
}