{
  "type": "Feature",
  "properties": {
    "gn:admin1_code":"27",
    "gn:admin2_code":"3540606.0",
    "gn:asciiname":"Tanquinho",
    "gn:country_code":"BR",
    "gn:dem":589,
    "gn:feature_class":"P",
    "gn:feature_code":"PPL",
    "gn:name":"Tanquinho",
    "gn:population":0,
    "gn:timezone":"America/Sao_Paulo",
    "iso:country":"BR",
    "name:por_x_preferred":[
        "Tanquinho"
    ],
    "wof:name":"Tanquinho",
    "wof:placetype":"locality"
},
  "geometry": {"coordinates":[-47.53846,-23.11641],"type":"Point"}
}