{
  "type": "Feature",
  "properties": {
    "gn:admin1_code":"15",
    "gn:admin2_code":"3112109.0",
    "gn:asciiname":"Marmota",
    "gn:country_code":"BR",
    "gn:dem":865,
    "gn:feature_class":"P",
    "gn:feature_code":"PPL",
    "gn:name":"Marmota",
    "gn:population":0,
    "gn:timezone":"America/Sao_Paulo",
    "iso:country":"BR",
    "name:por_x_preferred":[
        "Marmota"
    ],
    "wof:name":"Marmota",
    "wof:placetype":"locality"
},
  "geometry": {"coordinates":[-41.98333,-20.56667],"type":"Point"}
}