{
  "type": "Feature",
  "properties": {
    "gn:admin1_code":"6",
    "gn:admin2_code":"2305266.0",
    "gn:asciiname":"Bastioes",
    "gn:country_code":"BR",
    "gn:dem":136,
    "gn:feature_class":"P",
    "gn:feature_code":"PPL",
    "gn:name":"Basti\u00f5es",
    "gn:population":0,
    "gn:timezone":"America/Fortaleza",
    "iso:country":"BR",
    "wof:name":"Bastioes",
    "wof:placetype":"locality"
},
  "geometry": {"coordinates":[-38.71667,-4.61667],"type":"Point"}
}