{
  "type": "Feature",
  "properties": {
    "gn:admin1_code":"27.0",
    "gn:admin2_code":"3528502.0",
    "gn:asciiname":"Sitio Santa Maria",
    "gn:country_code":"BR",
    "gn:dem":1049,
    "gn:feature_class":"P",
    "gn:feature_code":"PPL",
    "gn:name":"S\u00edtio Santa Maria",
    "gn:population":0,
    "gn:timezone":"America/Sao_Paulo",
    "iso:country":"BR",
    "name:por_x_preferred":[
        "S\u00edtio Santa Maria"
    ],
    "wof:name":"Sitio Santa Maria",
    "wof:placetype":"locality"
},
  "geometry": {"coordinates":[-46.54,-23.26242],"type":"Point"}
}