{
  "type": "Feature",
  "properties": {
    "gn:admin1_code":"18.0",
    "gn:admin2_code":"4109609.0",
    "gn:asciiname":"Sitio Serra Verde",
    "gn:country_code":"BR",
    "gn:dem":11,
    "gn:feature_class":"P",
    "gn:feature_code":"PPL",
    "gn:name":"S\u00edtio Serra Verde",
    "gn:population":0,
    "gn:timezone":"America/Sao_Paulo",
    "iso:country":"BR",
    "name:por_x_preferred":[
        "S\u00edtio Serra Verde"
    ],
    "wof:name":"Sitio Serra Verde",
    "wof:placetype":"locality"
},
  "geometry": {"coordinates":[-48.8048,-25.92593],"type":"Point"}
}