{
  "type": "Feature",
  "properties": {
    "gn:admin1_code":"11",
    "gn:admin2_code":"5003108.0",
    "gn:asciiname":"Oliveira",
    "gn:cc2":"BR",
    "gn:country_code":"BR",
    "gn:dem":387,
    "gn:feature_class":"P",
    "gn:feature_code":"PPL",
    "gn:name":"Oliveira",
    "gn:population":0,
    "gn:timezone":"America/Campo_Grande",
    "iso:country":"BR",
    "name:und_x_variant":[
        "A. Oliveira",
        "Oliveira"
    ],
    "wof:name":"Oliveira",
    "wof:placetype":"locality"
},
  "geometry": {"coordinates":[-55.18333000000001,-19.68333],"type":"Point"}
}