{
  "type": "Feature",
  "properties": {
    "gn:admin1_code":"18.0",
    "gn:admin2_code":"4122909.0",
    "gn:asciiname":"Sitio Jair O. da Silva",
    "gn:country_code":"BR",
    "gn:dem":720,
    "gn:feature_class":"P",
    "gn:feature_code":"PPL",
    "gn:name":"S\u00edtio Jair O. da Silva",
    "gn:population":0,
    "gn:timezone":"America/Sao_Paulo",
    "iso:country":"BR",
    "name:por_x_preferred":[
        "S\u00edtio Jair O. da Silva"
    ],
    "wof:name":"Sitio Jair O. da Silva",
    "wof:placetype":"locality"
},
  "geometry": {"coordinates":[-49.7989,-23.6165],"type":"Point"}
}