{
  "type": "Feature",
  "properties": {
    "gn:admin1_code":"06",
    "gn:admin2_code":"2313005.0",
    "gn:asciiname":"Jenipapeiro",
    "gn:country_code":"BR",
    "gn:dem":210,
    "gn:feature_class":"P",
    "gn:feature_code":"PPL",
    "gn:name":"Jenipapeiro",
    "gn:population":0,
    "gn:timezone":"America/Fortaleza",
    "iso:country":"BR",
    "wof:name":"Jenipapeiro",
    "wof:placetype":"locality"
},
  "geometry": {"coordinates":[-39.08333,-5.91667],"type":"Point"}
}