{
  "type": "Feature",
  "properties": {
    "gn:admin1_code":"06",
    "gn:admin2_code":"2310100.0",
    "gn:asciiname":"Sitio Boqueirao",
    "gn:country_code":"BR",
    "gn:dem":442,
    "gn:feature_class":"P",
    "gn:feature_code":"PPL",
    "gn:name":"S\u00edtio Boqueirao",
    "gn:population":0,
    "gn:timezone":"America/Fortaleza",
    "iso:country":"BR",
    "wof:name":"Sitio Boqueirao",
    "wof:placetype":"locality"
},
  "geometry": {"coordinates":[-38.83333,-4.16667],"type":"Point"}
}