{
  "type": "Feature",
  "properties": {
    "gn:admin1_code":"30",
    "gn:admin2_code":"2614303.0",
    "gn:asciiname":"Queimadas",
    "gn:country_code":"BR",
    "gn:dem":534,
    "gn:feature_class":"P",
    "gn:feature_code":"PPL",
    "gn:name":"Queimadas",
    "gn:population":0,
    "gn:timezone":"America/Recife",
    "iso:country":"BR",
    "name:ceb_x_preferred":[
        "Queimadas"
    ],
    "name:fra_x_preferred":[
        "Queimadas"
    ],
    "name:hye_x_preferred":[
        "\u053f\u0565\u0575\u0574\u0561\u0564\u0561\u057d"
    ],
    "name:ita_x_preferred":[
        "Queimadas"
    ],
    "name:kaz_x_preferred":[
        "\u041a\u0435\u0439\u043c\u0430\u0434\u0430\u0441"
    ],
    "name:nld_x_preferred":[
        "Queimadas"
    ],
    "name:nor_x_preferred":[
        "Queimadas"
    ],
    "name:ron_x_preferred":[
        "Queimadas"
    ],
    "name:rus_x_preferred":[
        "\u041a\u0435\u0439\u043c\u0430\u0434\u0430\u0441"
    ],
    "name:swe_x_preferred":[
        "Queimadas"
    ],
    "name:vol_x_preferred":[
        "Queimadas"
    ],
    "wof:name":"Queimadas",
    "wof:placetype":"locality"
},
  "geometry": {"coordinates":[-39.46667,-7.65],"type":"Point"}
}