{
  "type": "Feature",
  "properties": {
    "gn:admin1_code":"1",
    "gn:admin2_code":"1200203.0",
    "gn:asciiname":"Botafogo",
    "gn:country_code":"BR",
    "gn:dem":222,
    "gn:feature_class":"P",
    "gn:feature_code":"PPL",
    "gn:name":"Botafogo",
    "gn:population":0,
    "gn:timezone":"America/Rio_Branco",
    "iso:country":"BR",
    "wof:name":"Botafogo",
    "wof:placetype":"locality"
},
  "geometry": {"coordinates":[-73.16667,-8.25],"type":"Point"}
}