{
  "type": "Feature",
  "properties": {
    "gn:admin1_code":"1",
    "gn:admin2_code":"1200203.0",
    "gn:asciiname":"Botafogo",
    "gn:country_code":"BR",
    "gn:dem":222,
    "gn:feature_class":"P",
    "gn:feature_code":"PPL",
    "gn:name":"Botafogo",
    "gn:population":0,
    "gn:timezone":"America/Rio_Branco",
    "iso:country":"BR",
    "name:bul_x_preferred":[
        "\u0411\u043e\u0442\u0430\u0444\u043e\u0433\u043e"
    ],
    "name:dan_x_preferred":[
        "Botafogo"
    ],
    "name:deu_x_preferred":[
        "Botafogo"
    ],
    "name:est_x_preferred":[
        "Botafogo"
    ],
    "name:kat_x_preferred":[
        "\u10d1\u10dd\u10e2\u10d0\u10e4\u10dd\u10d2\u10dd"
    ],
    "name:kor_x_preferred":[
        "\ubcf4\ud0c0\ud3ec\uad6c"
    ],
    "name:mkd_x_preferred":[
        "\u0411\u043e\u0442\u0430\u0444\u043e\u0433\u043e"
    ],
    "name:nor_x_preferred":[
        "Botafogo"
    ],
    "name:ron_x_preferred":[
        "Botafogo"
    ],
    "name:rus_x_preferred":[
        "\u0411\u043e\u0442\u0430\u0444\u043e\u0433\u0443"
    ],
    "name:sco_x_preferred":[
        "Botafogo"
    ],
    "name:spa_x_preferred":[
        "Botafogo"
    ],
    "name:srp_x_preferred":[
        "\u0411\u043e\u0442\u0430\u0444\u043e\u0433\u043e"
    ],
    "name:swe_x_preferred":[
        "Botafogo"
    ],
    "name:tur_x_preferred":[
        "Botafogo"
    ],
    "name:ukr_x_preferred":[
        "\u0411\u043e\u0442\u0430\u0444\u043e\u0433\u0443"
    ],
    "name:zho_x_preferred":[
        "\u535a\u5854\u5f17\u6208"
    ],
    "wof:name":"Botafogo",
    "wof:placetype":"locality"
},
  "geometry": {"coordinates":[-73.16667,-8.25],"type":"Point"}
}