{
  "type": "Feature",
  "properties": {
    "gn:admin1_code":"5",
    "gn:admin2_code":"2907202.0",
    "gn:asciiname":"Barra da Cruz",
    "gn:country_code":"BR",
    "gn:dem":391,
    "gn:feature_class":"P",
    "gn:feature_code":"PPL",
    "gn:name":"Barra da Cruz",
    "gn:population":0,
    "gn:timezone":"America/Bahia",
    "iso:country":"BR",
    "wof:name":"Barra da Cruz",
    "wof:placetype":"locality"
},
  "geometry": {"coordinates":[-41.53333,-9.65],"type":"Point"}
}