{
  "type": "Feature",
  "properties": {
    "gn:admin1_code":"17",
    "gn:admin2_code":"2510907.0",
    "gn:asciiname":"Fechadinho",
    "gn:country_code":"BR",
    "gn:dem":205,
    "gn:feature_class":"P",
    "gn:feature_code":"PPL",
    "gn:name":"Fechadinho",
    "gn:population":0,
    "gn:timezone":"America/Fortaleza",
    "iso:country":"BR",
    "wof:name":"Fechadinho",
    "wof:placetype":"locality"
},
  "geometry": {"coordinates":[-37.58333,-6.63333],"type":"Point"}
}