{
  "type": "Feature",
  "properties": {
    "gn:admin1_code":"21",
    "gn:admin2_code":"3304151.0",
    "gn:asciiname":"Piedade",
    "gn:country_code":"BR",
    "gn:dem":32,
    "gn:feature_class":"P",
    "gn:feature_code":"PPL",
    "gn:name":"Piedade",
    "gn:population":0,
    "gn:timezone":"America/Sao_Paulo",
    "iso:country":"BR",
    "name:bpy_x_preferred":[
        "\u09aa\u09bf\u09af\u09bc\u09c7\u09a1\u09be\u09a1\u09c7"
    ],
    "name:ceb_x_preferred":[
        "Piedade"
    ],
    "name:deu_x_preferred":[
        "Piedade"
    ],
    "name:fra_x_preferred":[
        "Piedade"
    ],
    "name:ita_x_preferred":[
        "Piedade"
    ],
    "name:nld_x_preferred":[
        "Piedade"
    ],
    "name:por_x_preferred":[
        "Piedade"
    ],
    "name:rus_x_preferred":[
        "\u041f\u044c\u0435\u0434\u0430\u0434\u0438"
    ],
    "name:swe_x_preferred":[
        "Piedade"
    ],
    "wof:name":"Piedade",
    "wof:placetype":"locality"
},
  "geometry": {"coordinates":[-41.61667,-22.11667000000001],"type":"Point"}
}