{
  "type": "Feature",
  "properties": {
    "gn:admin1_code":"21",
    "gn:admin2_code":"3304151.0",
    "gn:asciiname":"Piedade",
    "gn:country_code":"BR",
    "gn:dem":32,
    "gn:feature_class":"P",
    "gn:feature_code":"PPL",
    "gn:name":"Piedade",
    "gn:population":0,
    "gn:timezone":"America/Sao_Paulo",
    "iso:country":"BR",
    "name:por_x_preferred":[
        "Piedade"
    ],
    "wof:name":"Piedade",
    "wof:placetype":"locality"
},
  "geometry": {"coordinates":[-41.61667,-22.11667000000001],"type":"Point"}
}