{
  "type": "Feature",
  "properties": {
    "gn:admin1_code":"20",
    "gn:admin2_code":"2209153.0",
    "gn:asciiname":"Cacimba Grande",
    "gn:country_code":"BR",
    "gn:dem":185,
    "gn:feature_class":"P",
    "gn:feature_code":"PPL",
    "gn:name":"Cacimba Grande",
    "gn:population":0,
    "gn:timezone":"America/Fortaleza",
    "iso:country":"BR",
    "wof:name":"Cacimba Grande",
    "wof:placetype":"locality"
},
  "geometry": {"coordinates":[-41.85,-5.85],"type":"Point"}
}