{
  "type": "Feature",
  "properties": {
    "gn:admin1_code":"26.0",
    "gn:admin2_code":"4202107.0",
    "gn:asciiname":"Sao Joao do Itaperiu",
    "gn:country_code":"BR",
    "gn:dem":16,
    "gn:feature_class":"P",
    "gn:feature_code":"PPLL",
    "gn:name":"S\u00e3o Jo\u00e3o do Itaperi\u00fa",
    "gn:population":0,
    "gn:timezone":"America/Sao_Paulo",
    "iso:country":"BR",
    "name:por_x_preferred":[
        "S\u00e3o Jo\u00e3o do Itaperi\u00fa"
    ],
    "wof:name":"Sao Joao do Itaperiu",
    "wof:placetype":"locality"
},
  "geometry": {"coordinates":[-48.737,-26.6058],"type":"Point"}
}