{
  "type": "Feature",
  "properties": {
    "gn:admin1_code":"27",
    "gn:admin2_code":"3518305.0",
    "gn:asciiname":"Stio Nossa Senhora Aparecida",
    "gn:country_code":"BR",
    "gn:dem":635,
    "gn:feature_class":"P",
    "gn:feature_code":"PPL",
    "gn:name":"Stio Nossa Senhora Aparecida",
    "gn:population":0,
    "gn:timezone":"America/Sao_Paulo",
    "iso:country":"BR",
    "name:por_x_preferred":[
        "Stio Nossa Senhora Aparecida"
    ],
    "wof:name":"Stio Nossa Senhora Aparecida",
    "wof:placetype":"locality"
},
  "geometry": {"coordinates":[-46.1408,-23.3696],"type":"Point"}
}