{
  "type": "Feature",
  "properties": {
    "gn:admin1_code":"4",
    "gn:admin2_code":"1300201.0",
    "gn:asciiname":"Caxias",
    "gn:country_code":"BR",
    "gn:dem":94,
    "gn:feature_class":"P",
    "gn:feature_code":"PPL",
    "gn:name":"Caxias",
    "gn:population":0,
    "gn:timezone":"America/Eirunepe",
    "iso:country":"BR",
    "name:bpy_x_preferred":[
        "\u0995\u09be\u0995\u09cd\u09b8\u0987\u09af\u09bc\u09be\u09b8"
    ],
    "name:ceb_x_preferred":[
        "Caxias"
    ],
    "name:deu_x_preferred":[
        "Caxias"
    ],
    "name:fra_x_preferred":[
        "Caxias"
    ],
    "name:ita_x_preferred":[
        "Caxias"
    ],
    "name:jpn_x_preferred":[
        "\u30ab\u30b7\u30a2\u30b9"
    ],
    "name:mlg_x_preferred":[
        "Caxias"
    ],
    "name:nld_x_preferred":[
        "Caxias"
    ],
    "name:nor_x_preferred":[
        "Caxias"
    ],
    "name:por_x_preferred":[
        "Caxias"
    ],
    "name:rus_x_preferred":[
        "\u041a\u0430\u0448\u0438\u0430\u0441"
    ],
    "name:slk_x_preferred":[
        "Caxias"
    ],
    "name:spa_x_preferred":[
        "Caxias"
    ],
    "name:swe_x_preferred":[
        "Caxias"
    ],
    "name:vie_x_preferred":[
        "Caxias"
    ],
    "wof:name":"Caxias",
    "wof:placetype":"locality"
},
  "geometry": {"coordinates":[-71.43556,-4.4825],"type":"Point"}
}