{
  "type": "Feature",
  "properties": {
    "gn:admin1_code":"4",
    "gn:admin2_code":"1300201.0",
    "gn:asciiname":"Caxias",
    "gn:country_code":"BR",
    "gn:dem":94,
    "gn:feature_class":"P",
    "gn:feature_code":"PPL",
    "gn:name":"Caxias",
    "gn:population":0,
    "gn:timezone":"America/Eirunepe",
    "iso:country":"BR",
    "wof:name":"Caxias",
    "wof:placetype":"locality"
},
  "geometry": {"coordinates":[-71.43556,-4.4825],"type":"Point"}
}