{
  "type": "Feature",
  "properties": {
    "gn:admin1_code":"5",
    "gn:admin2_code":"2917805.0",
    "gn:asciiname":"Bernardo",
    "gn:country_code":"BR",
    "gn:dem":60,
    "gn:feature_class":"P",
    "gn:feature_code":"PPL",
    "gn:name":"Bernardo",
    "gn:population":0,
    "gn:timezone":"America/Bahia",
    "iso:country":"BR",
    "name:bel_x_preferred":[
        "\u0411\u0435\u0440\u043d\u0430\u0440\u0434\u0443"
    ],
    "name:deu_x_preferred":[
        "Bernardo"
    ],
    "name:ita_x_preferred":[
        "Bernardo"
    ],
    "name:slv_x_preferred":[
        "Bernardo"
    ],
    "name:spa_x_preferred":[
        "Bernardo"
    ],
    "wof:name":"Bernardo",
    "wof:placetype":"locality"
},
  "geometry": {"coordinates":[-39.01667,-13.13333],"type":"Point"}
}