{
  "type": "Feature",
  "properties": {
    "gn:admin1_code":"5",
    "gn:admin2_code":"2920502.0",
    "gn:asciiname":"Mumbuca",
    "gn:country_code":"BR",
    "gn:dem":419,
    "gn:feature_class":"P",
    "gn:feature_code":"PPL",
    "gn:name":"Mumbuca",
    "gn:population":0,
    "gn:timezone":"America/Bahia",
    "iso:country":"BR",
    "wof:name":"Mumbuca",
    "wof:placetype":"locality"
},
  "geometry": {"coordinates":[-40.58333,-13.25],"type":"Point"}
}