{
  "type": "Feature",
  "properties": {
    "iso:country":"BR",
    "name:deu_x_preferred":[
        "Flughafen Tabatinga"
    ],
    "name:fas_x_preferred":[
        "\u0641\u0631\u0648\u062f\u06af\u0627\u0647 \u0628\u06cc\u0646\u200c\u0627\u0644\u0645\u0644\u0644\u06cc \u062a\u0627\u0628\u0627\u062a\u06cc\u0646\u06af\u0627"
    ],
    "name:jpn_x_preferred":[
        "\u30bf\u30d0\u30c1\u30f3\u30ac\u56fd\u969b\u7a7a\u6e2f"
    ],
    "name:msa_x_preferred":[
        "Lapangan Terbang Antarabangsa Tabatinga"
    ],
    "name:ron_x_preferred":[
        "Aeroportul Tabatinga"
    ],
    "name:rus_x_preferred":[
        "\u0422\u0430\u0431\u0430\u0442\u0438\u043d\u0433\u0430"
    ],
    "name:tgk_x_preferred":[
        "\u0424\u0443\u0440\u0443\u0434\u0433\u043e\u04b3\u0438 \u0431\u0438\u043d\u200c\u0430\u043b\u043c\u0438\u043b\u0430\u043b\u04e3 \u0442\u043e\u0431\u043e\u0442\u0438\u043d\u0433\u043e"
    ],
    "name:zho_x_preferred":[
        "\u5854\u5df4\u5ef7\u52a0\u570b\u969b\u6a5f\u5834"
    ],
    "oa:elevation_ft":"279",
    "oa:type":"medium_airport",
    "woe:hierarchy":{
        "country_id":23424768,
        "county_id":12578224,
        "planet_id":1,
        "state_id":2344847
    },
    "wof:name":"Aeroporto Internacional Tabatinga",
    "wof:placetype":"campus"
},
  "geometry": {"coordinates":[-69.937777777778,-4.2569444444444],"type":"Point"}
}