{
  "type": "Feature",
  "properties": {
    "iso:country":"BR",
    "oa:elevation_ft":"279",
    "oa:type":"medium_airport",
    "woe:hierarchy":{
        "country_id":23424768,
        "county_id":12578224,
        "planet_id":1,
        "state_id":2344847
    },
    "wof:name":"Aeroporto Internacional Tabatinga",
    "wof:placetype":"campus"
},
  "geometry": {"coordinates":[-69.937777777778,-4.2569444444444],"type":"Point"}
}