{
  "type": "Feature",
  "properties": {
    "gn:admin1_code":"30",
    "gn:admin2_code":"2608008.0",
    "gn:asciiname":"Jerimum",
    "gn:country_code":"BR",
    "gn:dem":564,
    "gn:feature_class":"P",
    "gn:feature_code":"PPL",
    "gn:name":"Jerimum",
    "gn:population":0,
    "gn:timezone":"America/Recife",
    "iso:country":"BR",
    "wof:name":"Jerimum",
    "wof:placetype":"locality"
},
  "geometry": {"coordinates":[-36.56667,-7.93333],"type":"Point"}
}