{
  "type": "Feature",
  "properties": {
    "gn:admin1_code":"16",
    "gn:admin2_code":"1500503.0",
    "gn:asciiname":"Segredo",
    "gn:country_code":"BR",
    "gn:dem":210,
    "gn:feature_class":"P",
    "gn:feature_code":"PPL",
    "gn:name":"Segr\u00eado",
    "gn:population":0,
    "gn:timezone":"America/Santarem",
    "iso:country":"BR",
    "wof:name":"Segredo",
    "wof:placetype":"locality"
},
  "geometry": {"coordinates":[-53.18333000000001,0.33333],"type":"Point"}
}