{
  "type": "Feature",
  "properties": {
    "gn:admin1_code":"5.0",
    "gn:admin2_code":"2929255.0",
    "gn:asciiname":"Gameleira",
    "gn:country_code":"BR",
    "gn:dem":806,
    "gn:feature_class":"P",
    "gn:feature_code":"PPL",
    "gn:name":"Gameleira",
    "gn:population":0,
    "gn:timezone":"America/Bahia",
    "iso:country":"BR",
    "name:por_x_preferred":[
        "Gameleira"
    ],
    "wof:name":"Gameleira",
    "wof:placetype":"locality"
},
  "geometry": {"coordinates":[-41.68713,-11.06857],"type":"Point"}
}