{
  "type": "Feature",
  "properties": {
    "gn:admin1_code":"18.0",
    "gn:admin2_code":"4111704.0",
    "gn:asciiname":"Sitio Benedito Siqueira",
    "gn:country_code":"BR",
    "gn:dem":521,
    "gn:feature_class":"P",
    "gn:feature_code":"PPL",
    "gn:name":"S\u00edtio Benedito Siqueira",
    "gn:population":0,
    "gn:timezone":"America/Sao_Paulo",
    "iso:country":"BR",
    "name:por_x_preferred":[
        "S\u00edtio Benedito Siqueira"
    ],
    "wof:name":"Sitio Benedito Siqueira",
    "wof:placetype":"locality"
},
  "geometry": {"coordinates":[-50.06257,-23.68897],"type":"Point"}
}