{
  "type": "Feature",
  "properties": {
    "gn:admin1_code":"27.0",
    "gn:admin2_code":"3505401.0",
    "gn:asciiname":"Sitio Sebastiao Carvalho Justino dos Santos",
    "gn:country_code":"BR",
    "gn:dem":619,
    "gn:feature_class":"P",
    "gn:feature_code":"PPL",
    "gn:name":"S\u00edtio Sebasti\u00e3o Carvalho Justino dos Santos",
    "gn:population":0,
    "gn:timezone":"America/Sao_Paulo",
    "iso:country":"BR",
    "name:por_x_preferred":[
        "S\u00edtio Sebasti\u00e3o Carvalho Justino dos Santos"
    ],
    "wof:name":"Sitio Sebastiao Carvalho Justino dos Santos",
    "wof:placetype":"locality"
},
  "geometry": {"coordinates":[-48.55288,-25.0562],"type":"Point"}
}