{
  "type": "Feature",
  "properties": {
    "gn:admin1_code":"5",
    "gn:admin2_code":"2922300.0",
    "gn:asciiname":"Cocao",
    "gn:country_code":"BR",
    "gn:dem":183,
    "gn:feature_class":"P",
    "gn:feature_code":"PPL",
    "gn:name":"Coc\u00e3o",
    "gn:population":0,
    "gn:timezone":"America/Bahia",
    "iso:country":"BR",
    "wof:name":"Cocao",
    "wof:placetype":"locality"
},
  "geometry": {"coordinates":[-39.06667,-12.65],"type":"Point"}
}