{
  "type": "Feature",
  "properties": {
    "gn:admin1_code":"18.0",
    "gn:admin2_code":"4109609.0",
    "gn:asciiname":"Sitio Quiriri",
    "gn:country_code":"BR",
    "gn:dem":96,
    "gn:feature_class":"P",
    "gn:feature_code":"PPL",
    "gn:name":"S\u00edtio Quiriri",
    "gn:population":0,
    "gn:timezone":"America/Sao_Paulo",
    "iso:country":"BR",
    "name:por_x_preferred":[
        "S\u00edtio Quiriri"
    ],
    "wof:name":"Sitio Quiriri",
    "wof:placetype":"locality"
},
  "geometry": {"coordinates":[-48.8964,-25.9666],"type":"Point"}
}