{
  "type": "Feature",
  "properties": {
    "gn:admin1_code":"18.0",
    "gn:admin2_code":"4100202.0",
    "gn:asciiname":"Bairro Tatupeba",
    "gn:country_code":"BR",
    "gn:dem":106,
    "gn:feature_class":"P",
    "gn:feature_code":"PPLL",
    "gn:name":"Bairro Tatupeba",
    "gn:population":0,
    "gn:timezone":"America/Sao_Paulo",
    "iso:country":"BR",
    "name:por_x_preferred":[
        "Bairro Tatupeba"
    ],
    "wof:name":"Bairro Tatupeba",
    "wof:placetype":"locality"
},
  "geometry": {"coordinates":[-48.7555,-24.70358],"type":"Point"}
}