{
  "type": "Feature",
  "properties": {
    "gn:admin1_code":"29",
    "gn:admin2_code":"5213103.0",
    "gn:asciiname":"Jose",
    "gn:country_code":"BR",
    "gn:dem":811,
    "gn:feature_class":"P",
    "gn:feature_code":"PPL",
    "gn:name":"Jos\u00e9",
    "gn:population":0,
    "gn:timezone":"America/Sao_Paulo",
    "iso:country":"BR",
    "name:por_x_preferred":[
        "Jos\u00e9"
    ],
    "wof:name":"Jose",
    "wof:placetype":"locality"
},
  "geometry": {"coordinates":[-52.85,-17.58333],"type":"Point"}
}