{
  "type": "Feature",
  "properties": {
    "gn:admin1_code":"17",
    "gn:admin2_code":"2514503.0",
    "gn:asciiname":"Picada",
    "gn:country_code":"BR",
    "gn:dem":344,
    "gn:feature_class":"P",
    "gn:feature_code":"PPL",
    "gn:name":"Picada",
    "gn:population":0,
    "gn:timezone":"America/Fortaleza",
    "iso:country":"BR",
    "name:cat_x_preferred":[
        "Picada"
    ],
    "name:ces_x_preferred":[
        "Picada"
    ],
    "name:fra_x_preferred":[
        "Picada"
    ],
    "name:ita_x_preferred":[
        "Picada"
    ],
    "name:spa_x_preferred":[
        "Picada"
    ],
    "wof:name":"Picada",
    "wof:placetype":"locality"
},
  "geometry": {"coordinates":[-38.55,-7.08333],"type":"Point"}
}