{
  "type": "Feature",
  "properties": {
    "gn:admin1_code":"15",
    "gn:admin2_code":"3150901.0",
    "gn:asciiname":"Sitio Sao Jorge",
    "gn:country_code":"BR",
    "gn:dem":1534,
    "gn:feature_class":"P",
    "gn:feature_code":"PPL",
    "gn:name":"S\u00edtio S\u00e3o Jorge",
    "gn:population":0,
    "gn:timezone":"America/Sao_Paulo",
    "iso:country":"BR",
    "name:por_x_preferred":[
        "S\u00edtio S\u00e3o Jorge"
    ],
    "wof:name":"Sitio Sao Jorge",
    "wof:placetype":"locality"
},
  "geometry": {"coordinates":[-45.5611,-22.652],"type":"Point"}
}