{
  "type": "Feature",
  "properties": {
    "gn:admin1_code":"5",
    "gn:admin2_code":"2920403.0",
    "gn:asciiname":"Recreio",
    "gn:country_code":"BR",
    "gn:dem":561,
    "gn:feature_class":"P",
    "gn:feature_code":"PPL",
    "gn:name":"Recreio",
    "gn:population":0,
    "gn:timezone":"America/Bahia",
    "iso:country":"BR",
    "name:bpy_x_preferred":[
        "\u09b0\u09c7\u0995\u09cd\u09b0\u09c7\u0987\u0993"
    ],
    "name:ceb_x_preferred":[
        "Recreio"
    ],
    "name:epo_x_preferred":[
        "Recreio"
    ],
    "name:eus_x_preferred":[
        "Recreio"
    ],
    "name:fra_x_preferred":[
        "Recreio"
    ],
    "name:ita_x_preferred":[
        "Recreio"
    ],
    "name:kat_x_preferred":[
        "\u10e0\u10d4\u10d9\u10e0\u10d4\u10d8\u10e3"
    ],
    "name:kaz_x_preferred":[
        "\u0420\u0435\u043a\u0440\u0435\u044e"
    ],
    "name:mlg_x_preferred":[
        "Recreio"
    ],
    "name:nld_x_preferred":[
        "Recreio"
    ],
    "name:nor_x_preferred":[
        "Recreio"
    ],
    "name:pol_x_preferred":[
        "Recreio"
    ],
    "name:por_x_preferred":[
        "Recreio"
    ],
    "name:ron_x_preferred":[
        "Recreio"
    ],
    "name:rus_x_preferred":[
        "\u0420\u0435\u043a\u0440\u0435\u044e"
    ],
    "name:swe_x_preferred":[
        "Recreio"
    ],
    "name:vie_x_preferred":[
        "Recreio"
    ],
    "name:vol_x_preferred":[
        "Recreio"
    ],
    "name:war_x_preferred":[
        "Recreio"
    ],
    "name:zho_x_preferred":[
        "\u96f7\u514b\u96f7\u5c24"
    ],
    "wof:name":"Recreio",
    "wof:placetype":"locality"
},
  "geometry": {"coordinates":[-40.41667,-14.21667],"type":"Point"}
}