{
  "type": "Feature",
  "properties": {
    "gn:admin1_code":"4",
    "gn:admin2_code":"1304260.0",
    "gn:asciiname":"Boa Vista do Jauato",
    "gn:cc2":"BR",
    "gn:country_code":"BR",
    "gn:dem":30,
    "gn:feature_class":"P",
    "gn:feature_code":"PPL",
    "gn:name":"Boa Vista do Jauat\u00f3",
    "gn:population":0,
    "gn:timezone":"America/Manaus",
    "iso:country":"BR",
    "name:und_x_variant":[
        "Boa Vista",
        "Boa Vista do Jauat\u00f3"
    ],
    "wof:name":"Boa Vista do Jauato",
    "wof:placetype":"locality"
},
  "geometry": {"coordinates":[-65.28333000000001,-2.76667],"type":"Point"}
}