{
  "type": "Feature",
  "properties": {
    "gn:admin1_code":"16",
    "gn:admin2_code":"1508084.0",
    "gn:asciiname":"Tucuma",
    "gn:country_code":"BR",
    "gn:dem":302,
    "gn:feature_class":"P",
    "gn:feature_code":"PPL",
    "gn:name":"Tucum\u00e3",
    "gn:population":0,
    "gn:timezone":"America/Belem",
    "iso:country":"BR",
    "wof:name":"Tucuma",
    "wof:placetype":"locality"
},
  "geometry": {"coordinates":[-51.16111,-6.7475],"type":"Point"}
}