{
  "type": "Feature",
  "properties": {
    "gn:admin1_code":"16",
    "gn:admin2_code":"1508084.0",
    "gn:asciiname":"Tucuma",
    "gn:country_code":"BR",
    "gn:dem":302,
    "gn:feature_class":"P",
    "gn:feature_code":"PPL",
    "gn:name":"Tucum\u00e3",
    "gn:population":0,
    "gn:timezone":"America/Belem",
    "iso:country":"BR",
    "name:ceb_x_preferred":[
        "Tucum\u00e3"
    ],
    "name:eus_x_preferred":[
        "Tucum\u00e3"
    ],
    "name:fra_x_preferred":[
        "Tucum\u00e3"
    ],
    "name:ita_x_preferred":[
        "Tucum\u00e3"
    ],
    "name:nld_x_preferred":[
        "Tucum\u00e3"
    ],
    "name:nor_x_preferred":[
        "Tucum\u00e3"
    ],
    "name:pol_x_preferred":[
        "Tucum\u00e3"
    ],
    "name:por_x_preferred":[
        "Tucum\u00e3"
    ],
    "name:ron_x_preferred":[
        "Tucum\u00e3"
    ],
    "name:swe_x_preferred":[
        "Tucum\u00e3"
    ],
    "name:vie_x_preferred":[
        "Tucum\u00e3"
    ],
    "name:vol_x_preferred":[
        "Tucum\u00e3"
    ],
    "name:war_x_preferred":[
        "Tucum\u00e3"
    ],
    "name:zho_x_preferred":[
        "\u5716\u5eab\u8292"
    ],
    "wof:name":"Tucuma",
    "wof:placetype":"locality"
},
  "geometry": {"coordinates":[-51.16111,-6.7475],"type":"Point"}
}