{
  "type": "Feature",
  "properties": {
    "gn:admin1_code":"30",
    "gn:admin2_code":"2610905.0",
    "gn:asciiname":"Lagoa Pedro Borges",
    "gn:country_code":"BR",
    "gn:dem":940,
    "gn:feature_class":"P",
    "gn:feature_code":"PPL",
    "gn:name":"Lagoa Pedro Borges",
    "gn:population":0,
    "gn:timezone":"America/Recife",
    "iso:country":"BR",
    "wof:name":"Lagoa Pedro Borges",
    "wof:placetype":"locality"
},
  "geometry": {"coordinates":[-36.73333,-8.33333],"type":"Point"}
}