{
  "type": "Feature",
  "properties": {
    "gn:admin1_code":"18",
    "gn:admin2_code":"4104105.0",
    "gn:asciiname":"Sitio Leocadia M. Nazachuki",
    "gn:country_code":"BR",
    "gn:dem":840,
    "gn:feature_class":"P",
    "gn:feature_code":"PPL",
    "gn:name":"S\u00edtio Leoc\u00e1dia M. Nazachuki",
    "gn:population":0,
    "gn:timezone":"America/Sao_Paulo",
    "iso:country":"BR",
    "name:por_x_preferred":[
        "S\u00edtio Leoc\u00e1dia M. Nazachuki"
    ],
    "wof:name":"Sitio Leocadia M. Nazachuki",
    "wof:placetype":"locality"
},
  "geometry": {"coordinates":[-49.69222,-25.99556],"type":"Point"}
}