{
  "type": "Feature",
  "properties": {
    "gn:admin1_code":"29.0",
    "gn:admin2_code":"5221700.0",
    "gn:asciiname":"Ranchao",
    "gn:country_code":"BR",
    "gn:dem":638,
    "gn:feature_class":"P",
    "gn:feature_code":"PPL",
    "gn:name":"Ranchao",
    "gn:population":0,
    "gn:timezone":"America/Sao_Paulo",
    "iso:country":"BR",
    "wof:name":"Ranchao",
    "wof:placetype":"locality"
},
  "geometry": {"coordinates":[-49.62911,-15.57567],"type":"Point"}
}