{
  "type": "Feature",
  "properties": {
    "gn:admin1_code":"31",
    "gn:admin2_code":"1712702.0",
    "gn:asciiname":"Buriti-So",
    "gn:country_code":"BR",
    "gn:dem":683,
    "gn:feature_class":"P",
    "gn:feature_code":"PPL",
    "gn:name":"Buriti-S\u00f3",
    "gn:population":0,
    "gn:timezone":"America/Araguaina",
    "iso:country":"BR",
    "wof:name":"Buriti-So",
    "wof:placetype":"locality"
},
  "geometry": {"coordinates":[-46.03333,-10.48333],"type":"Point"}
}