{
  "type": "Feature",
  "properties": {
    "gn:admin1_code":"31",
    "gn:admin2_code":"1715507.0",
    "gn:asciiname":"Manuel Botelho",
    "gn:country_code":"BR",
    "gn:dem":330,
    "gn:feature_class":"P",
    "gn:feature_code":"PPL",
    "gn:name":"Manuel Botelho",
    "gn:population":0,
    "gn:timezone":"America/Araguaina",
    "iso:country":"BR",
    "name:por_x_preferred":[
        "Manuel Botelho"
    ],
    "wof:name":"Manuel Botelho",
    "wof:placetype":"locality"
},
  "geometry": {"coordinates":[-48.95,-10.73333],"type":"Point"}
}