{
  "type": "Feature",
  "properties": {
    "gn:admin1_code":"18.0",
    "gn:admin2_code":"4126603.0",
    "gn:asciiname":"Sitio Paulo Lopes",
    "gn:country_code":"BR",
    "gn:dem":671,
    "gn:feature_class":"P",
    "gn:feature_code":"PPL",
    "gn:name":"S\u00edtio Paulo Lopes",
    "gn:population":0,
    "gn:timezone":"America/Sao_Paulo",
    "iso:country":"BR",
    "name:por_x_preferred":[
        "S\u00edtio Paulo Lopes"
    ],
    "wof:name":"Sitio Paulo Lopes",
    "wof:placetype":"locality"
},
  "geometry": {"coordinates":[-49.8558,-23.6713],"type":"Point"}
}