{
  "type": "Feature",
  "properties": {
    "gn:admin1_code":"14",
    "gn:admin2_code":"5107701.0",
    "gn:asciiname":"Mato Novo",
    "gn:country_code":"BR",
    "gn:dem":379,
    "gn:feature_class":"P",
    "gn:feature_code":"PPL",
    "gn:name":"Mato Novo",
    "gn:population":0,
    "gn:timezone":"America/Cuiaba",
    "iso:country":"BR",
    "wof:name":"Mato Novo",
    "wof:placetype":"locality"
},
  "geometry": {"coordinates":[-55.98333,-15.06667],"type":"Point"}
}