{
  "type": "Feature",
  "properties": {
    "gn:admin1_code":"27.0",
    "gn:admin2_code":"3509254.0",
    "gn:asciiname":"Sitio Tres Marias",
    "gn:country_code":"BR",
    "gn:dem":60,
    "gn:feature_class":"P",
    "gn:feature_code":"PPL",
    "gn:name":"S\u00edtio Tr\u00eas Marias",
    "gn:population":0,
    "gn:timezone":"America/Sao_Paulo",
    "iso:country":"BR",
    "name:por_x_preferred":[
        "S\u00edtio Tr\u00eas Marias"
    ],
    "wof:name":"Sitio Tres Marias",
    "wof:placetype":"locality"
},
  "geometry": {"coordinates":[-48.16472,-24.69888],"type":"Point"}
}