{
  "type": "Feature",
  "properties": {
    "gn:admin1_code":"27",
    "gn:admin2_code":"3528502.0",
    "gn:asciiname":"Sitio Santa Amelia",
    "gn:country_code":"BR",
    "gn:dem":954,
    "gn:feature_class":"P",
    "gn:feature_code":"PPL",
    "gn:name":"S\u00edtio Santa Am\u00e9lia",
    "gn:population":0,
    "gn:timezone":"America/Sao_Paulo",
    "iso:country":"BR",
    "name:por_x_preferred":[
        "S\u00edtio Santa Am\u00e9lia"
    ],
    "wof:name":"Sitio Santa Amelia",
    "wof:placetype":"locality"
},
  "geometry": {"coordinates":[-46.57083,-23.23694],"type":"Point"}
}