{
  "type": "Feature",
  "properties": {
    "gn:admin1_code":"27",
    "gn:admin2_code":"3518305.0",
    "gn:asciiname":"Bairro Maracatu",
    "gn:country_code":"BR",
    "gn:dem":617,
    "gn:feature_class":"P",
    "gn:feature_code":"PPL",
    "gn:name":"Bairro Maracatu",
    "gn:population":0,
    "gn:timezone":"America/Sao_Paulo",
    "iso:country":"BR",
    "name:por_x_preferred":[
        "Bairro Maracatu"
    ],
    "wof:name":"Bairro Maracatu",
    "wof:placetype":"locality"
},
  "geometry": {"coordinates":[-46.1202,-23.3574],"type":"Point"}
}