{
  "type": "Feature",
  "properties": {
    "gn:admin1_code":"15",
    "gn:admin2_code":"3162203.0",
    "gn:asciiname":"Joao Fabricio",
    "gn:country_code":"BR",
    "gn:dem":743,
    "gn:feature_class":"P",
    "gn:feature_code":"PPL",
    "gn:name":"Jo\u00e3o Fabr\u00edcio",
    "gn:population":0,
    "gn:timezone":"America/Sao_Paulo",
    "iso:country":"BR",
    "name:por_x_preferred":[
        "Jo\u00e3o Fabr\u00edcio"
    ],
    "wof:name":"Joao Fabricio",
    "wof:placetype":"locality"
},
  "geometry": {"coordinates":[-46.51667,-20.56667],"type":"Point"}
}