{
  "type": "Feature",
  "properties": {
    "gn:admin1_code":"27.0",
    "gn:admin2_code":"3505401.0",
    "gn:asciiname":"Bairro Rio Vermelho",
    "gn:country_code":"BR",
    "gn:dem":705,
    "gn:feature_class":"P",
    "gn:feature_code":"PPLL",
    "gn:name":"Bairro Rio Vermelho",
    "gn:population":0,
    "gn:timezone":"America/Sao_Paulo",
    "iso:country":"BR",
    "name:por_x_preferred":[
        "Bairro Rio Vermelho"
    ],
    "wof:name":"Bairro Rio Vermelho",
    "wof:placetype":"locality"
},
  "geometry": {"coordinates":[-48.5098,-24.9848],"type":"Point"}
}