{
  "type": "Feature",
  "properties": {
    "gn:admin1_code":"17",
    "gn:admin2_code":"2502904.0",
    "gn:asciiname":"Salgidinho",
    "gn:country_code":"BR",
    "gn:dem":352,
    "gn:feature_class":"P",
    "gn:feature_code":"PPL",
    "gn:name":"Salgidinho",
    "gn:population":0,
    "gn:timezone":"America/Fortaleza",
    "iso:country":"BR",
    "wof:name":"Salgidinho",
    "wof:placetype":"locality"
},
  "geometry": {"coordinates":[-37.83333,-6.38333],"type":"Point"}
}