{
  "type": "Feature",
  "properties": {
    "gn:admin1_code":"17",
    "gn:admin2_code":"2512788.0",
    "gn:asciiname":"Tarrafa",
    "gn:country_code":"BR",
    "gn:dem":413,
    "gn:feature_class":"P",
    "gn:feature_code":"PPL",
    "gn:name":"Tarrafa",
    "gn:population":0,
    "gn:timezone":"America/Fortaleza",
    "iso:country":"BR",
    "wof:name":"Tarrafa",
    "wof:placetype":"locality"
},
  "geometry": {"coordinates":[-36.13333,-7.66667],"type":"Point"}
}