{
  "type": "Feature",
  "properties": {
    "gn:admin1_code":"20",
    "gn:admin2_code":"2206803.0",
    "gn:asciiname":"Campinho dos Cavalos",
    "gn:country_code":"BR",
    "gn:dem":85,
    "gn:feature_class":"P",
    "gn:feature_code":"PPL",
    "gn:name":"Campinho dos Cavalos",
    "gn:population":0,
    "gn:timezone":"America/Fortaleza",
    "iso:country":"BR",
    "wof:name":"Campinho dos Cavalos",
    "wof:placetype":"locality"
},
  "geometry": {"coordinates":[-42.57639,-3.95111],"type":"Point"}
}