{
  "type": "Feature",
  "properties": {
    "gn:admin1_code":"06",
    "gn:admin2_code":"2307601.0",
    "gn:asciiname":"Varzea do Corre",
    "gn:country_code":"BR",
    "gn:dem":31,
    "gn:feature_class":"P",
    "gn:feature_code":"PPL",
    "gn:name":"Varzea do Corre",
    "gn:population":0,
    "gn:timezone":"America/Fortaleza",
    "iso:country":"BR",
    "wof:name":"Varzea do Corre",
    "wof:placetype":"locality"
},
  "geometry": {"coordinates":[-38.05,-5.13333],"type":"Point"}
}