{
  "type": "Feature",
  "properties": {
    "gn:admin1_code":"16",
    "gn:admin2_code":"1501006.0",
    "gn:asciiname":"Catauara",
    "gn:country_code":"BR",
    "gn:dem":85,
    "gn:feature_class":"P",
    "gn:feature_code":"PPL",
    "gn:name":"Catauara",
    "gn:population":0,
    "gn:timezone":"America/Santarem",
    "iso:country":"BR",
    "wof:name":"Catauara",
    "wof:placetype":"locality"
},
  "geometry": {"coordinates":[-56.38333000000001,-3.35],"type":"Point"}
}