{
  "type": "Feature",
  "properties": {
    "gn:admin1_code":"20",
    "gn:admin2_code":"2201988.0",
    "gn:asciiname":"Caicara",
    "gn:country_code":"BR",
    "gn:dem":263,
    "gn:feature_class":"P",
    "gn:feature_code":"PPL",
    "gn:name":"Cai\u00e7ara",
    "gn:population":0,
    "gn:timezone":"America/Fortaleza",
    "iso:country":"BR",
    "wof:name":"Caicara",
    "wof:placetype":"locality"
},
  "geometry": {"coordinates":[-42.86667,-8.13333],"type":"Point"}
}