{
  "type": "Feature",
  "properties": {
    "gn:admin1_code":"11",
    "gn:admin2_code":"5006002.0",
    "gn:asciiname":"Santa Sofia",
    "gn:cc2":"BR",
    "gn:country_code":"BR",
    "gn:dem":306,
    "gn:feature_class":"P",
    "gn:feature_code":"PPL",
    "gn:name":"Santa Sofia",
    "gn:population":0,
    "gn:timezone":"America/Campo_Grande",
    "iso:country":"BR",
    "name:und_x_variant":[
        "Fazenda Santa Sophia",
        "Sofia",
        "Fazenda Santa Sofia",
        "Santa Sofia"
    ],
    "wof:name":"Santa Sofia",
    "wof:placetype":"locality"
},
  "geometry": {"coordinates":[-53.73333,-21.58333],"type":"Point"}
}