{
  "type": "Feature",
  "properties": {
    "gn:admin1_code":"27",
    "gn:admin2_code":"3526902.0",
    "gn:asciiname":"Jardim Nova Europa",
    "gn:country_code":"BR",
    "gn:dem":623,
    "gn:feature_class":"P",
    "gn:feature_code":"PPL",
    "gn:name":"Jardim Nova Europa",
    "gn:population":0,
    "gn:timezone":"America/Sao_Paulo",
    "iso:country":"BR",
    "name:por_x_preferred":[
        "Jardim Nova Europa"
    ],
    "wof:name":"Jardim Nova Europa",
    "wof:placetype":"locality"
},
  "geometry": {"coordinates":[-47.41778,-22.58111],"type":"Point"}
}