{
  "type": "Feature",
  "properties": {
    "gn:admin1_code":"11",
    "gn:admin2_code":"5003207.0",
    "gn:asciiname":"Dona Carlota",
    "gn:cc2":"BR",
    "gn:country_code":"BR",
    "gn:dem":83,
    "gn:feature_class":"P",
    "gn:feature_code":"PPL",
    "gn:name":"Dona Carlota",
    "gn:population":0,
    "gn:timezone":"America/Campo_Grande",
    "iso:country":"BR",
    "name:und_x_variant":[
        "Carlota",
        "Dona Carlota"
    ],
    "wof:name":"Dona Carlota",
    "wof:placetype":"locality"
},
  "geometry": {"coordinates":[-57.65,-19.78333],"type":"Point"}
}