{
  "type": "Feature",
  "properties": {
    "gn:admin1_code":"18",
    "gn:admin2_code":"4125605.0",
    "gn:asciiname":"Olho d'Agua",
    "gn:country_code":"BR",
    "gn:dem":803,
    "gn:feature_class":"P",
    "gn:feature_code":"PPL",
    "gn:name":"\u00d4lho d\u2019\u00c1gua",
    "gn:population":0,
    "gn:timezone":"America/Sao_Paulo",
    "iso:country":"BR",
    "wof:name":"Olho d'Agua",
    "wof:placetype":"locality"
},
  "geometry": {"coordinates":[-50.33333,-25.78333],"type":"Point"}
}