{
  "type": "Feature",
  "properties": {
    "gn:admin1_code":"26",
    "gn:admin2_code":"4217402.0",
    "gn:asciiname":"Grota Funda",
    "gn:country_code":"BR",
    "gn:dem":318,
    "gn:feature_class":"P",
    "gn:feature_code":"PPL",
    "gn:name":"Grota Funda",
    "gn:population":0,
    "gn:timezone":"America/Sao_Paulo",
    "iso:country":"BR",
    "wof:name":"Grota Funda",
    "wof:placetype":"locality"
},
  "geometry": {"coordinates":[-49.13333,-26.33333],"type":"Point"}
}