{
  "type": "Feature",
  "properties": {
    "gn:admin1_code":"22",
    "gn:admin2_code":"2407104.0",
    "gn:asciiname":"Lagoa dos Currais",
    "gn:country_code":"BR",
    "gn:dem":101,
    "gn:feature_class":"P",
    "gn:feature_code":"PPL",
    "gn:name":"Lagoa dos Currais",
    "gn:population":0,
    "gn:timezone":"America/Fortaleza",
    "iso:country":"BR",
    "wof:name":"Lagoa dos Currais",
    "wof:placetype":"locality"
},
  "geometry": {"coordinates":[-35.51667,-5.88333],"type":"Point"}
}