{
  "type": "Feature",
  "properties": {
    "gn:admin1_code":"5",
    "gn:admin2_code":"2921708.0",
    "gn:asciiname":"Boqueirao",
    "gn:country_code":"BR",
    "gn:dem":1109,
    "gn:feature_class":"P",
    "gn:feature_code":"PPL",
    "gn:name":"Boqueir\u00e3o",
    "gn:population":0,
    "gn:timezone":"America/Bahia",
    "iso:country":"BR",
    "wof:name":"Boqueirao",
    "wof:placetype":"locality"
},
  "geometry": {"coordinates":[-41.25,-11.51667],"type":"Point"}
}