{
  "type": "Feature",
  "properties": {
    "gn:admin1_code":"18.0",
    "gn:admin2_code":"4124707.0",
    "gn:asciiname":"Sitio Hugo",
    "gn:country_code":"BR",
    "gn:dem":961,
    "gn:feature_class":"P",
    "gn:feature_code":"PPL",
    "gn:name":"S\u00edtio Hugo",
    "gn:population":0,
    "gn:timezone":"America/Sao_Paulo",
    "iso:country":"BR",
    "name:por_x_preferred":[
        "S\u00edtio Hugo"
    ],
    "wof:name":"Sitio Hugo",
    "wof:placetype":"locality"
},
  "geometry": {"coordinates":[-50.7405,-23.80467],"type":"Point"}
}