{
  "type": "Feature",
  "properties": {
    "gn:admin1_code":"26",
    "gn:admin2_code":"4208104.0",
    "gn:asciiname":"Sitio Lered Schubauer",
    "gn:country_code":"BR",
    "gn:dem":829,
    "gn:feature_class":"P",
    "gn:feature_code":"PPL",
    "gn:name":"S\u00edtio Lered Schubauer",
    "gn:population":0,
    "gn:timezone":"America/Sao_Paulo",
    "iso:country":"BR",
    "name:por_x_preferred":[
        "S\u00edtio Lered Schubauer"
    ],
    "wof:name":"Sitio Lered Schubauer",
    "wof:placetype":"locality"
},
  "geometry": {"coordinates":[-49.849,-26.2478],"type":"Point"}
}