{
  "type": "Feature",
  "properties": {
    "gn:admin1_code":"22",
    "gn:admin2_code":"2409308.0",
    "gn:asciiname":"Picos",
    "gn:country_code":"BR",
    "gn:dem":193,
    "gn:feature_class":"P",
    "gn:feature_code":"PPL",
    "gn:name":"Picos",
    "gn:population":0,
    "gn:timezone":"America/Fortaleza",
    "iso:country":"BR",
    "name:ceb_x_preferred":[
        "Picos"
    ],
    "name:eml_x_preferred":[
        "Picos"
    ],
    "name:eus_x_preferred":[
        "Picos"
    ],
    "name:fra_x_preferred":[
        "Picos"
    ],
    "name:ita_x_preferred":[
        "Picos"
    ],
    "name:jpn_x_preferred":[
        "\u30d4\u30fc\u30af\u30b9"
    ],
    "name:kat_x_preferred":[
        "\u10de\u10d8\u10d9\u10e3\u10e1\u10d8"
    ],
    "name:kor_x_preferred":[
        "\ud53c\ucfe0\uc2a4"
    ],
    "name:mlg_x_preferred":[
        "Picos"
    ],
    "name:nld_x_preferred":[
        "Picos"
    ],
    "name:nor_x_preferred":[
        "Picos"
    ],
    "name:por_x_preferred":[
        "Picos"
    ],
    "name:ron_x_preferred":[
        "Picos"
    ],
    "name:rus_x_preferred":[
        "\u041f\u0438\u043a\u0443\u0441"
    ],
    "name:spa_x_preferred":[
        "Picos"
    ],
    "name:swe_x_preferred":[
        "Picos"
    ],
    "name:vie_x_preferred":[
        "Picos"
    ],
    "name:war_x_preferred":[
        "Picos"
    ],
    "name:zho_x_preferred":[
        "\u76ae\u79d1\u65af"
    ],
    "wof:name":"Picos",
    "wof:placetype":"locality"
},
  "geometry": {"coordinates":[-37.58333,-6.03333],"type":"Point"}
}