{
  "type": "Feature",
  "properties": {
    "gn:admin1_code":"22",
    "gn:admin2_code":"2409308.0",
    "gn:asciiname":"Picos",
    "gn:country_code":"BR",
    "gn:dem":193,
    "gn:feature_class":"P",
    "gn:feature_code":"PPL",
    "gn:name":"Picos",
    "gn:population":0,
    "gn:timezone":"America/Fortaleza",
    "iso:country":"BR",
    "wof:name":"Picos",
    "wof:placetype":"locality"
},
  "geometry": {"coordinates":[-37.58333,-6.03333],"type":"Point"}
}