{
  "type": "Feature",
  "properties": {
    "gn:admin1_code":"15",
    "gn:admin2_code":"3124302.0",
    "gn:asciiname":"Espigao",
    "gn:country_code":"BR",
    "gn:dem":933,
    "gn:feature_class":"P",
    "gn:feature_code":"PPL",
    "gn:name":"Espig\u00e3o",
    "gn:population":0,
    "gn:timezone":"America/Sao_Paulo",
    "iso:country":"BR",
    "wof:name":"Espigao",
    "wof:placetype":"locality"
},
  "geometry": {"coordinates":[-42.58333,-14.98333],"type":"Point"}
}