{
  "type": "Feature",
  "properties": {
    "gn:admin1_code":"26.0",
    "gn:admin2_code":"4209102.0",
    "gn:asciiname":"Rio de Julio",
    "gn:country_code":"BR",
    "gn:dem":645,
    "gn:feature_class":"P",
    "gn:feature_code":"PPL",
    "gn:name":"Rio de Julio",
    "gn:population":0,
    "gn:timezone":"America/Sao_Paulo",
    "iso:country":"BR",
    "wof:name":"Rio de Julio",
    "wof:placetype":"locality"
},
  "geometry": {"coordinates":[-49.0955,-26.24567],"type":"Point"}
}