{
  "type": "Feature",
  "properties": {
    "gn:admin1_code":"15",
    "gn:admin2_code":"3144300.0",
    "gn:asciiname":"Vitoria",
    "gn:country_code":"BR",
    "gn:dem":171,
    "gn:feature_class":"P",
    "gn:feature_code":"PPL",
    "gn:name":"Vit\u00f3ria",
    "gn:population":0,
    "gn:timezone":"America/Sao_Paulo",
    "iso:country":"BR",
    "name:por_x_preferred":[
        "Vit\u00f3ria"
    ],
    "wof:name":"Vitoria",
    "wof:placetype":"locality"
},
  "geometry": {"coordinates":[-40.28333,-17.93332999999999],"type":"Point"}
}