{
  "type": "Feature",
  "properties": {
    "gn:admin1_code":"18.0",
    "gn:admin2_code":"4127809.0",
    "gn:asciiname":"Sitio Miguel Osorio",
    "gn:country_code":"BR",
    "gn:dem":547,
    "gn:feature_class":"P",
    "gn:feature_code":"PPL",
    "gn:name":"S\u00edtio Miguel Os\u00f3rio",
    "gn:population":0,
    "gn:timezone":"America/Sao_Paulo",
    "iso:country":"BR",
    "name:por_x_preferred":[
        "S\u00edtio Miguel Os\u00f3rio"
    ],
    "wof:name":"Sitio Miguel Osorio",
    "wof:placetype":"locality"
},
  "geometry": {"coordinates":[-50.01669,-23.73656],"type":"Point"}
}