{
  "type": "Feature",
  "properties": {
    "gn:admin1_code":"16",
    "gn:admin2_code":"1500503.0",
    "gn:asciiname":"Vida Nova",
    "gn:country_code":"BR",
    "gn:dem":23,
    "gn:feature_class":"P",
    "gn:feature_code":"PPL",
    "gn:name":"Vida Nova",
    "gn:population":0,
    "gn:timezone":"America/Belem",
    "iso:country":"BR",
    "name:und_x_variant":[
        "Villa Nova",
        "Vila Nova",
        "Vida Nova"
    ],
    "wof:name":"Vida Nova",
    "wof:placetype":"locality"
},
  "geometry": {"coordinates":[-51.96892,-1.14523],"type":"Point"}
}