{
  "type": "Feature",
  "properties": {
    "gn:admin1_code":"15",
    "gn:admin2_code":"3170206.0",
    "gn:asciiname":"Agua Limpa",
    "gn:country_code":"BR",
    "gn:dem":857,
    "gn:feature_class":"P",
    "gn:feature_code":"PPL",
    "gn:name":"\u00c1gua Limpa",
    "gn:population":0,
    "gn:timezone":"America/Sao_Paulo",
    "iso:country":"BR",
    "name:por_x_preferred":[
        "\u00c1gua Limpa"
    ],
    "wof:name":"Agua Limpa",
    "wof:placetype":"locality"
},
  "geometry": {"coordinates":[-48.26667,-19.21667],"type":"Point"}
}