{
  "type": "Feature",
  "properties": {
    "gn:admin1_code":"16",
    "gn:admin2_code":"1505494.0",
    "gn:asciiname":"Campina",
    "gn:cc2":"BR",
    "gn:country_code":"BR",
    "gn:dem":113,
    "gn:feature_class":"P",
    "gn:feature_code":"PPL",
    "gn:name":"Campina",
    "gn:population":0,
    "gn:timezone":"America/Belem",
    "iso:country":"BR",
    "name:ceb_x_preferred":[
        "Campina"
    ],
    "name:deu_x_preferred":[
        "Campina"
    ],
    "name:fra_x_preferred":[
        "Campina"
    ],
    "name:ita_x_preferred":[
        "Campina"
    ],
    "name:nld_x_preferred":[
        "Campina"
    ],
    "name:por_x_preferred":[
        "Campina"
    ],
    "name:swe_x_preferred":[
        "Campina"
    ],
    "name:und_x_variant":[
        "Compina",
        "Campinas"
    ],
    "wof:name":"Campina",
    "wof:placetype":"locality"
},
  "geometry": {"coordinates":[-48.32271,-5.78608],"type":"Point"}
}