{
  "type": "Feature",
  "properties": {
    "gn:admin1_code":"18.0",
    "gn:admin2_code":"4109609.0",
    "gn:asciiname":"Sitio Floriano Soares",
    "gn:country_code":"BR",
    "gn:dem":12,
    "gn:feature_class":"P",
    "gn:feature_code":"PPL",
    "gn:name":"S\u00edtio Floriano Soares",
    "gn:population":0,
    "gn:timezone":"America/Sao_Paulo",
    "iso:country":"BR",
    "name:por_x_preferred":[
        "S\u00edtio Floriano Soares"
    ],
    "wof:name":"Sitio Floriano Soares",
    "wof:placetype":"locality"
},
  "geometry": {"coordinates":[-48.7285,-25.9285],"type":"Point"}
}