{
  "type": "Feature",
  "properties": {
    "gn:admin1_code":"18.0",
    "gn:admin2_code":"4100202.0",
    "gn:asciiname":"Sitio Pica-Pau",
    "gn:country_code":"BR",
    "gn:dem":139,
    "gn:feature_class":"P",
    "gn:feature_code":"PPL",
    "gn:name":"S\u00edtio Pica-Pau",
    "gn:population":0,
    "gn:timezone":"America/Sao_Paulo",
    "iso:country":"BR",
    "name:por_x_preferred":[
        "S\u00edtio Pica-Pau"
    ],
    "wof:name":"Sitio Pica-Pau",
    "wof:placetype":"locality"
},
  "geometry": {"coordinates":[-48.82589,-24.71375],"type":"Point"}
}