{
  "type": "Feature",
  "properties": {
    "gn:admin1_code":"18.0",
    "gn:admin2_code":"4116208.0",
    "gn:asciiname":"Sitio Joao da S. Passos",
    "gn:country_code":"BR",
    "gn:dem":31,
    "gn:feature_class":"P",
    "gn:feature_code":"PPL",
    "gn:name":"S\u00edtio Jo\u00e3o da S. Passos",
    "gn:population":0,
    "gn:timezone":"America/Sao_Paulo",
    "iso:country":"BR",
    "name:por_x_preferred":[
        "S\u00edtio Jo\u00e3o da S. Passos"
    ],
    "wof:name":"Sitio Joao da S. Passos",
    "wof:placetype":"locality"
},
  "geometry": {"coordinates":[-48.81643,-25.46546],"type":"Point"}
}