{
  "type": "Feature",
  "properties": {
    "gn:admin1_code":"14.0",
    "gn:admin2_code":"5108600.0",
    "gn:asciiname":"Sao Jose",
    "gn:country_code":"BR",
    "gn:dem":236,
    "gn:feature_class":"P",
    "gn:feature_code":"PPL",
    "gn:name":"Sao Jose",
    "gn:population":0,
    "gn:timezone":"America/Cuiaba",
    "iso:country":"BR",
    "wof:name":"Sao Jose",
    "wof:placetype":"locality"
},
  "geometry": {"coordinates":[-51.08793,-10.18662],"type":"Point"}
}