{
  "type": "Feature",
  "properties": {
    "gn:admin1_code":"27",
    "gn:admin2_code":"3528403.0",
    "gn:asciiname":"Sitio Tibirica",
    "gn:country_code":"BR",
    "gn:dem":881,
    "gn:feature_class":"P",
    "gn:feature_code":"PPL",
    "gn:name":"S\u00edtio Tibiri\u00e7\u00e1",
    "gn:population":0,
    "gn:timezone":"America/Sao_Paulo",
    "iso:country":"BR",
    "name:por_x_preferred":[
        "S\u00edtio Tibiri\u00e7\u00e1"
    ],
    "wof:name":"Sitio Tibirica",
    "wof:placetype":"locality"
},
  "geometry": {"coordinates":[-47.20915,-23.57218],"type":"Point"}
}