{
  "type": "Feature",
  "properties": {
    "gn:admin1_code":"27.0",
    "gn:admin2_code":"3550308.0",
    "gn:asciiname":"Tapera da Lagoa",
    "gn:country_code":"BR",
    "gn:dem":789,
    "gn:feature_class":"P",
    "gn:feature_code":"PPLL",
    "gn:name":"Tapera da Lagoa",
    "gn:population":0,
    "gn:timezone":"America/Sao_Paulo",
    "iso:country":"BR",
    "name:por_x_preferred":[
        "Tapera da Lagoa"
    ],
    "wof:name":"Tapera da Lagoa",
    "wof:placetype":"locality"
},
  "geometry": {"coordinates":[-46.7444,-23.8224],"type":"Point"}
}