{
  "type": "Feature",
  "properties": {
    "gn:admin1_code":"27.0",
    "gn:admin2_code":"3554003.0",
    "gn:asciiname":"Congonhal de Baixo",
    "gn:country_code":"BR",
    "gn:dem":555,
    "gn:feature_class":"P",
    "gn:feature_code":"PPLL",
    "gn:name":"Congonhal de Baixo",
    "gn:population":0,
    "gn:timezone":"America/Sao_Paulo",
    "iso:country":"BR",
    "name:por_x_preferred":[
        "Congonhal de Baixo"
    ],
    "wof:name":"Congonhal de Baixo",
    "wof:placetype":"locality"
},
  "geometry": {"coordinates":[-47.81096,-23.42117],"type":"Point"}
}