{
  "type": "Feature",
  "properties": {
    "gn:admin1_code":"5",
    "gn:admin2_code":"2921708.0",
    "gn:asciiname":"Sonhem",
    "gn:country_code":"BR",
    "gn:dem":672,
    "gn:feature_class":"P",
    "gn:feature_code":"PPL",
    "gn:name":"Sonh\u00e9m",
    "gn:population":0,
    "gn:timezone":"America/Bahia",
    "iso:country":"BR",
    "wof:name":"Sonhem",
    "wof:placetype":"locality"
},
  "geometry": {"coordinates":[-40.83333,-11.63333],"type":"Point"}
}