{
  "type": "Feature",
  "properties": {
    "gn:admin1_code":"2",
    "gn:admin2_code":"2700102.0",
    "gn:asciiname":"Boqueirao",
    "gn:country_code":"BR",
    "gn:dem":336,
    "gn:feature_class":"P",
    "gn:feature_code":"PPL",
    "gn:name":"Boqueir\u00e3o",
    "gn:population":0,
    "gn:timezone":"America/Maceio",
    "iso:country":"BR",
    "wof:name":"Boqueirao",
    "wof:placetype":"locality"
},
  "geometry": {"coordinates":[-37.86667,-9.25],"type":"Point"}
}