{
  "type": "Feature",
  "properties": {
    "gn:admin1_code":"18.0",
    "gn:admin2_code":"4101200.0",
    "gn:asciiname":"Sitio Irma Muller",
    "gn:country_code":"BR",
    "gn:dem":22,
    "gn:feature_class":"P",
    "gn:feature_code":"PPL",
    "gn:name":"S\u00edtio Irm\u00e3 M\u00fcller",
    "gn:population":0,
    "gn:timezone":"America/Sao_Paulo",
    "iso:country":"BR",
    "name:por_x_preferred":[
        "S\u00edtio Irm\u00e3 M\u00fcller"
    ],
    "wof:name":"Sitio Irma Muller",
    "wof:placetype":"locality"
},
  "geometry": {"coordinates":[-48.7489,-25.4648],"type":"Point"}
}