{
  "type": "Feature",
  "properties": {
    "gn:admin1_code":"31",
    "gn:admin2_code":"1710706.0",
    "gn:asciiname":"Pontal",
    "gn:country_code":"BR",
    "gn:dem":305,
    "gn:feature_class":"P",
    "gn:feature_code":"PPL",
    "gn:name":"Pontal",
    "gn:population":0,
    "gn:timezone":"America/Araguaina",
    "iso:country":"BR",
    "wof:name":"Pontal",
    "wof:placetype":"locality"
},
  "geometry": {"coordinates":[-47.68333,-5.93333],"type":"Point"}
}