{
  "type": "Feature",
  "properties": {
    "gn:admin1_code":"22",
    "gn:admin2_code":"2401909.0",
    "gn:asciiname":"Rio Novo",
    "gn:country_code":"BR",
    "gn:dem":210,
    "gn:feature_class":"P",
    "gn:feature_code":"PPL",
    "gn:name":"Rio N\u00f4vo",
    "gn:population":0,
    "gn:timezone":"America/Fortaleza",
    "iso:country":"BR",
    "name:ceb_x_preferred":[
        "Rio Novo"
    ],
    "name:deu_x_preferred":[
        "Rio Novo"
    ],
    "name:fra_x_preferred":[
        "Rio Novo"
    ],
    "name:nds_x_preferred":[
        "Rio Novo"
    ],
    "name:por_x_preferred":[
        "Rio Novo"
    ],
    "name:spa_x_preferred":[
        "Rio Novo"
    ],
    "name:swe_x_preferred":[
        "Rio Novo"
    ],
    "wof:name":"Rio Novo",
    "wof:placetype":"locality"
},
  "geometry": {"coordinates":[-36.04056,-5.825],"type":"Point"}
}