{
  "type": "Feature",
  "properties": {
    "gn:admin1_code":"17",
    "gn:admin2_code":"2514404.0",
    "gn:asciiname":"Maria Paes",
    "gn:country_code":"BR",
    "gn:dem":220,
    "gn:feature_class":"P",
    "gn:feature_code":"PPL",
    "gn:name":"Maria Paes",
    "gn:population":0,
    "gn:timezone":"America/Fortaleza",
    "iso:country":"BR",
    "wof:name":"Maria Paes",
    "wof:placetype":"locality"
},
  "geometry": {"coordinates":[-37.31667,-6.73333],"type":"Point"}
}