{
  "type": "Feature",
  "properties": {
    "gn:admin1_code":"27.0",
    "gn:admin2_code":"3502903.0",
    "gn:asciiname":"Sitio Fernandes",
    "gn:country_code":"BR",
    "gn:dem":622,
    "gn:feature_class":"P",
    "gn:feature_code":"PPL",
    "gn:name":"S\u00edtio Fernandes",
    "gn:population":0,
    "gn:timezone":"America/Sao_Paulo",
    "iso:country":"BR",
    "name:por_x_preferred":[
        "S\u00edtio Fernandes"
    ],
    "wof:name":"Sitio Fernandes",
    "wof:placetype":"locality"
},
  "geometry": {"coordinates":[-47.57044000000001,-23.55201],"type":"Point"}
}