{
  "type": "Feature",
  "properties": {
    "gn:admin1_code":"4",
    "gn:admin2_code":"1300409.0",
    "gn:asciiname":"Lagoa da Vila",
    "gn:country_code":"BR",
    "gn:dem":60,
    "gn:feature_class":"P",
    "gn:feature_code":"PPL",
    "gn:name":"Lagoa da Vila",
    "gn:population":0,
    "gn:timezone":"America/Manaus",
    "iso:country":"BR",
    "wof:name":"Lagoa da Vila",
    "wof:placetype":"locality"
},
  "geometry": {"coordinates":[-63.95,-0.11667],"type":"Point"}
}