{
  "type": "Feature",
  "properties": {
    "gn:gn_country":"BR",
    "gn:gn_fcode":"PPL",
    "gn:gn_pop":26837,
    "gn:population":26837,
    "iso:country":"BR",
    "name:unk_x_variant":[
        "Igarap\u00e9-Mirim"
    ],
    "qs_pg:aaroncc":"BR",
    "qs_pg:gn_country":"BR",
    "qs_pg:gn_fcode":"PPL",
    "qs_pg:gn_pop":26837,
    "qs_pg:name":"Igarap\u00e9 Miry",
    "qs_pg:name_adm0":"Brasil",
    "qs_pg:name_adm1":"Par\u00e1",
    "qs_pg:photos_9r":0,
    "qs_pg:photos_sr":0,
    "qs_pg:pop_sr":7,
    "qs_pg:qs_pg_placetype":"locality",
    "qs_pg:qs_pg_placetype_gp":"Town",
    "qs_pg:woe_adm0":23424768,
    "woe:adm0_id":23424768,
    "woe:name_adm0":"Brasil",
    "woe:name_adm1":"Par\u00e1",
    "woe:placetype":"Town",
    "wof:name":"Igarap\u00e9 Miry",
    "wof:placetype":"locality",
    "wof:population":26837
},
  "geometry": {"coordinates":[-48.95972,-1.975],"type":"Point"}
}