{
  "type": "Feature",
  "properties": {
    "gn:admin1_code":"18.0",
    "gn:admin2_code":"4116208.0",
    "gn:asciiname":"Fortaleza",
    "gn:country_code":"BR",
    "gn:dem":27,
    "gn:feature_class":"P",
    "gn:feature_code":"PPLL",
    "gn:name":"Fortaleza",
    "gn:population":0,
    "gn:timezone":"America/Sao_Paulo",
    "iso:country":"BR",
    "name:por_x_preferred":[
        "Fortaleza"
    ],
    "wof:name":"Fortaleza",
    "wof:placetype":"locality"
},
  "geometry": {"coordinates":[-48.84359,-25.49676],"type":"Point"}
}