{
  "type": "Feature",
  "properties": {
    "gn:admin1_code":"22",
    "gn:admin2_code":"2401503.0",
    "gn:asciiname":"Lagoa Seca",
    "gn:country_code":"BR",
    "gn:dem":154,
    "gn:feature_class":"P",
    "gn:feature_code":"PPL",
    "gn:name":"Lagoa S\u00eaca",
    "gn:population":0,
    "gn:timezone":"America/Fortaleza",
    "iso:country":"BR",
    "wof:name":"Lagoa Seca",
    "wof:placetype":"locality"
},
  "geometry": {"coordinates":[-35.91667,-5.91667],"type":"Point"}
}