{
  "type": "Feature",
  "properties": {
    "gn:admin1_code":"15",
    "gn:admin2_code":"3164431.0",
    "gn:asciiname":"Catinga",
    "gn:country_code":"BR",
    "gn:dem":762,
    "gn:feature_class":"P",
    "gn:feature_code":"PPL",
    "gn:name":"Catinga",
    "gn:population":0,
    "gn:timezone":"America/Sao_Paulo",
    "iso:country":"BR",
    "name:por_x_preferred":[
        "Catinga"
    ],
    "wof:name":"Catinga",
    "wof:placetype":"locality"
},
  "geometry": {"coordinates":[-42.63333,-21.06667],"type":"Point"}
}