{
  "type": "Feature",
  "properties": {
    "gn:admin1_code":"8",
    "gn:admin2_code":"3200409.0",
    "gn:asciiname":"Sao Miguel",
    "gn:country_code":"BR",
    "gn:dem":53,
    "gn:feature_class":"P",
    "gn:feature_code":"PPL",
    "gn:name":"S\u00e3o Miguel",
    "gn:population":0,
    "gn:timezone":"America/Sao_Paulo",
    "iso:country":"BR",
    "name:por_x_preferred":[
        "S\u00e3o Miguel"
    ],
    "wof:name":"Sao Miguel",
    "wof:placetype":"locality"
},
  "geometry": {"coordinates":[-40.64141,-20.58876],"type":"Point"}
}