{
  "type": "Feature",
  "properties": {
    "gn:admin1_code":"24",
    "gn:admin2_code":"1100106.0",
    "gn:asciiname":"Barracao Belo Horizonte",
    "gn:cc2":"BR",
    "gn:country_code":"BR",
    "gn:dem":153,
    "gn:feature_class":"P",
    "gn:feature_code":"PPL",
    "gn:name":"Barrac\u00e3o Belo Horizonte",
    "gn:population":0,
    "gn:timezone":"America/Porto_Velho",
    "iso:country":"BR",
    "name:und_x_variant":[
        "Bello Horizonte",
        "Barrac\u00e3o Bello Horisonte",
        "Belo Horizonte",
        "Barrac\u00e3o Belo Horizonte"
    ],
    "wof:name":"Barracao Belo Horizonte",
    "wof:placetype":"locality"
},
  "geometry": {"coordinates":[-64.16667,-11.88333],"type":"Point"}
}