{
  "type": "Feature",
  "properties": {
    "gn:admin1_code":"26.0",
    "gn:admin2_code":"4219408.0",
    "gn:asciiname":"Cambara",
    "gn:country_code":"BR",
    "gn:dem":431,
    "gn:feature_class":"P",
    "gn:feature_code":"PPLL",
    "gn:name":"Cambar\u00e1",
    "gn:population":0,
    "gn:timezone":"America/Sao_Paulo",
    "iso:country":"BR",
    "name:por_x_preferred":[
        "Cambar\u00e1"
    ],
    "wof:name":"Cambara",
    "wof:placetype":"locality"
},
  "geometry": {"coordinates":[-49.80513,-26.91007],"type":"Point"}
}