{
  "type": "Feature",
  "properties": {
    "gn:admin1_code":"8",
    "gn:admin2_code":"3200300.0",
    "gn:asciiname":"Nova Estrela",
    "gn:country_code":"BR",
    "gn:dem":641,
    "gn:feature_class":"P",
    "gn:feature_code":"PPL",
    "gn:name":"Nova Estr\u00eala",
    "gn:population":0,
    "gn:timezone":"America/Sao_Paulo",
    "iso:country":"BR",
    "name:cat_x_preferred":[
        "Novo Estrela"
    ],
    "name:fra_x_preferred":[
        "Nova Estrela"
    ],
    "name:por_x_preferred":[
        "Nova Estr\u00eala"
    ],
    "wof:name":"Nova Estrela",
    "wof:placetype":"locality"
},
  "geometry": {"coordinates":[-40.83333,-20.66667],"type":"Point"}
}