{
  "type": "Feature",
  "properties": {
    "gn:admin1_code":"13",
    "gn:admin2_code":"2101707.0",
    "gn:asciiname":"Goncalo",
    "gn:country_code":"BR",
    "gn:dem":62,
    "gn:feature_class":"P",
    "gn:feature_code":"PPL",
    "gn:name":"Gon\u00e7alo",
    "gn:population":0,
    "gn:timezone":"America/Fortaleza",
    "iso:country":"BR",
    "wof:name":"Goncalo",
    "wof:placetype":"locality"
},
  "geometry": {"coordinates":[-43.23167,-3.04417],"type":"Point"}
}