{
  "type": "Feature",
  "properties": {
    "gn:admin1_code":"5",
    "gn:admin2_code":"2907509.0",
    "gn:asciiname":"Gomaticum",
    "gn:country_code":"BR",
    "gn:dem":142,
    "gn:feature_class":"P",
    "gn:feature_code":"PPL",
    "gn:name":"Gomaticum",
    "gn:population":0,
    "gn:timezone":"America/Bahia",
    "iso:country":"BR",
    "wof:name":"Gomaticum",
    "wof:placetype":"locality"
},
  "geometry": {"coordinates":[-38.51667,-12.36667],"type":"Point"}
}