{
  "type": "Feature",
  "properties": {
    "gn:admin1_code":"27",
    "gn:admin2_code":"3524402.0",
    "gn:asciiname":"Stio Joo Vayne",
    "gn:country_code":"BR",
    "gn:dem":600,
    "gn:feature_class":"P",
    "gn:feature_code":"PPL",
    "gn:name":"Stio Joo Vayne",
    "gn:population":0,
    "gn:timezone":"America/Sao_Paulo",
    "iso:country":"BR",
    "name:por_x_preferred":[
        "Stio Joo Vayne"
    ],
    "wof:name":"Stio Joo Vayne",
    "wof:placetype":"locality"
},
  "geometry": {"coordinates":[-46.0196,-23.2926],"type":"Point"}
}