{
  "type": "Feature",
  "properties": {
    "gn:admin1_code":"18",
    "gn:admin2_code":"4125605.0",
    "gn:asciiname":"Tesoura",
    "gn:country_code":"BR",
    "gn:dem":802,
    "gn:feature_class":"P",
    "gn:feature_code":"PPL",
    "gn:name":"Tesoura",
    "gn:population":0,
    "gn:timezone":"America/Sao_Paulo",
    "iso:country":"BR",
    "wof:name":"Tesoura",
    "wof:placetype":"locality"
},
  "geometry": {"coordinates":[-50.26667,-25.88333],"type":"Point"}
}