{
  "type": "Feature",
  "properties": {
    "gn:admin1_code":"18.0",
    "gn:admin2_code":"4112306.0",
    "gn:asciiname":"Sitio Pagani",
    "gn:country_code":"BR",
    "gn:dem":595,
    "gn:feature_class":"P",
    "gn:feature_code":"PPL",
    "gn:name":"S\u00edtio Pagani",
    "gn:population":0,
    "gn:timezone":"America/Sao_Paulo",
    "iso:country":"BR",
    "name:por_x_preferred":[
        "S\u00edtio Pagani"
    ],
    "wof:name":"Sitio Pagani",
    "wof:placetype":"locality"
},
  "geometry": {"coordinates":[-50.1799,-23.74886],"type":"Point"}
}