{
  "type": "Feature",
  "properties": {
    "gn:admin1_code":"18.0",
    "gn:admin2_code":"4122305.0",
    "gn:asciiname":"Sitio Anivaldo de Lima",
    "gn:country_code":"BR",
    "gn:dem":861,
    "gn:feature_class":"P",
    "gn:feature_code":"PPL",
    "gn:name":"S\u00edtio Anivaldo de Lima",
    "gn:population":0,
    "gn:timezone":"America/Sao_Paulo",
    "iso:country":"BR",
    "name:por_x_preferred":[
        "S\u00edtio Anivaldo de Lima"
    ],
    "wof:name":"Sitio Anivaldo de Lima",
    "wof:placetype":"locality"
},
  "geometry": {"coordinates":[-49.7944,-26.0169],"type":"Point"}
}