{
  "type": "Feature",
  "properties": {
    "gn:admin1_code":"06",
    "gn:admin2_code":"2302305.0",
    "gn:asciiname":"Pizunha",
    "gn:country_code":"BR",
    "gn:dem":37,
    "gn:feature_class":"P",
    "gn:feature_code":"PPL",
    "gn:name":"Pizunha",
    "gn:population":0,
    "gn:timezone":"America/Fortaleza",
    "iso:country":"BR",
    "wof:name":"Pizunha",
    "wof:placetype":"locality"
},
  "geometry": {"coordinates":[-40.21667,-2.95],"type":"Point"}
}