{
  "type": "Feature",
  "properties": {
    "gn:admin1_code":"25",
    "gn:admin2_code":"1400209.0",
    "gn:asciiname":"Parente",
    "gn:country_code":"BR",
    "gn:dem":43,
    "gn:feature_class":"P",
    "gn:feature_code":"PPL",
    "gn:name":"Parente",
    "gn:population":0,
    "gn:timezone":"America/Boa_Vista",
    "iso:country":"BR",
    "wof:name":"Parente",
    "wof:placetype":"locality"
},
  "geometry": {"coordinates":[-61.67167,0.91167],"type":"Point"}
}