{
  "type": "Feature",
  "properties": {
    "gn:admin1_code":"26",
    "gn:admin2_code":"4203808.0",
    "gn:asciiname":"Rio dos Pardos",
    "gn:cc2":"BR",
    "gn:country_code":"BR",
    "gn:dem":815,
    "gn:feature_class":"P",
    "gn:feature_code":"PPL",
    "gn:name":"Rio dos Pardos",
    "gn:population":0,
    "gn:timezone":"America/Sao_Paulo",
    "iso:country":"BR",
    "name:und_x_variant":[
        "Reichart",
        "Rio dos Pardos"
    ],
    "wof:name":"Rio dos Pardos",
    "wof:placetype":"locality"
},
  "geometry": {"coordinates":[-50.61667,-26.33333],"type":"Point"}
}