{
  "type": "Feature",
  "properties": {
    "gn:admin1_code":"18.0",
    "gn:admin2_code":"4113205.0",
    "gn:asciiname":"Sitio Domingos Borges",
    "gn:country_code":"BR",
    "gn:dem":922,
    "gn:feature_class":"P",
    "gn:feature_code":"PPL",
    "gn:name":"S\u00edtio Domingos Borges",
    "gn:population":0,
    "gn:timezone":"America/Sao_Paulo",
    "iso:country":"BR",
    "name:por_x_preferred":[
        "S\u00edtio Domingos Borges"
    ],
    "wof:name":"Sitio Domingos Borges",
    "wof:placetype":"locality"
},
  "geometry": {"coordinates":[-49.75439,-25.80421],"type":"Point"}
}