{
  "type": "Feature",
  "properties": {
    "gn:admin1_code":"14",
    "gn:admin2_code":"5104609.0",
    "gn:asciiname":"Jaragua",
    "gn:country_code":"BR",
    "gn:dem":152,
    "gn:feature_class":"P",
    "gn:feature_code":"PPL",
    "gn:name":"Jaragu\u00e1",
    "gn:population":0,
    "gn:timezone":"America/Cuiaba",
    "iso:country":"BR",
    "name:por_x_preferred":[
        "Jaragu\u00e1"
    ],
    "wof:name":"Jaragua",
    "wof:placetype":"locality"
},
  "geometry": {"coordinates":[-55.08333,-17.15],"type":"Point"}
}