{
  "type": "Feature",
  "properties": {
    "gn:admin1_code":"18",
    "gn:admin2_code":"4127601.0",
    "gn:asciiname":"Sitio Arold Pozoski",
    "gn:country_code":"BR",
    "gn:dem":873,
    "gn:feature_class":"P",
    "gn:feature_code":"PPL",
    "gn:name":"S\u00edtio Arold Pozoski",
    "gn:population":0,
    "gn:timezone":"America/Sao_Paulo",
    "iso:country":"BR",
    "name:por_x_preferred":[
        "S\u00edtio Arold Pozoski"
    ],
    "wof:name":"Sitio Arold Pozoski",
    "wof:placetype":"locality"
},
  "geometry": {"coordinates":[-49.0429,-25.8326],"type":"Point"}
}