{
  "type": "Feature",
  "properties": {
    "iso:country":"BR",
    "qs_pg:aaroncc":"BR",
    "qs_pg:name":"Quart\u00e9is",
    "qs_pg:name_adm0":"Brasil",
    "qs_pg:name_adm1":"Rio de Janeiro",
    "qs_pg:photos":133,
    "qs_pg:photos_1k":27,
    "qs_pg:photos_9k":1,
    "qs_pg:photos_9r":3,
    "qs_pg:photos_all":133,
    "qs_pg:photos_sr":3,
    "qs_pg:pop_sr":0,
    "qs_pg:qs_pg_placetype":"locality",
    "qs_pg:qs_pg_placetype_gp":"Town",
    "qs_pg:woe_adm0":23424768,
    "woe:adm0_id":23424768,
    "woe:name_adm0":"Brasil",
    "woe:name_adm1":"Rio de Janeiro",
    "woe:placetype":"Town",
    "wof:name":"Quart\u00e9is",
    "wof:placetype":"locality"
},
  "geometry": {"coordinates":[-42.250285,-22.442169],"type":"Point"}
}