{
  "type": "Feature",
  "properties": {
    "gn:admin1_code":"20",
    "gn:admin2_code":"2202091.0",
    "gn:asciiname":"Barriguda",
    "gn:country_code":"BR",
    "gn:dem":618,
    "gn:feature_class":"P",
    "gn:feature_code":"PPL",
    "gn:name":"Barriguda",
    "gn:population":0,
    "gn:timezone":"America/Fortaleza",
    "iso:country":"BR",
    "wof:name":"Barriguda",
    "wof:placetype":"locality"
},
  "geometry": {"coordinates":[-40.53333,-7.21667],"type":"Point"}
}