{
  "type": "Feature",
  "properties": {
    "gn:admin1_code":"18.0",
    "gn:admin2_code":"4120705.0",
    "gn:asciiname":"Sitio Monte Alto",
    "gn:country_code":"BR",
    "gn:dem":611,
    "gn:feature_class":"P",
    "gn:feature_code":"PPL",
    "gn:name":"S\u00edtio Monte Alto",
    "gn:population":0,
    "gn:timezone":"America/Sao_Paulo",
    "iso:country":"BR",
    "name:por_x_preferred":[
        "S\u00edtio Monte Alto"
    ],
    "wof:name":"Sitio Monte Alto",
    "wof:placetype":"locality"
},
  "geometry": {"coordinates":[-49.8907,-23.5469],"type":"Point"}
}