{
  "type": "Feature",
  "properties": {
    "gn:admin1_code":"26.0",
    "gn:admin2_code":"4211900.0",
    "gn:asciiname":"Ponte do Imaruim",
    "gn:country_code":"BR",
    "gn:dem":4,
    "gn:feature_class":"P",
    "gn:feature_code":"PPLL",
    "gn:name":"Ponte do Imaruim",
    "gn:population":0,
    "gn:timezone":"America/Sao_Paulo",
    "iso:country":"BR",
    "wof:name":"Ponte do Imaruim",
    "wof:placetype":"locality"
},
  "geometry": {"coordinates":[-48.65261,-27.63411],"type":"Point"}
}