{
  "type": "Feature",
  "properties": {
    "gn:admin1_code":"16",
    "gn:admin2_code":"1500602.0",
    "gn:asciiname":"Relogio do Sol",
    "gn:country_code":"BR",
    "gn:dem":217,
    "gn:feature_class":"P",
    "gn:feature_code":"PPL",
    "gn:name":"Rel\u00f3gio do Sol",
    "gn:population":0,
    "gn:timezone":"America/Santarem",
    "iso:country":"BR",
    "wof:name":"Relogio do Sol",
    "wof:placetype":"locality"
},
  "geometry": {"coordinates":[-54.13333000000001,-6.25],"type":"Point"}
}