{
  "type": "Feature",
  "properties": {
    "gn:admin1_code":"18.0",
    "gn:admin2_code":"4109609.0",
    "gn:asciiname":"Sitio Francisco Alves Cordeiro",
    "gn:country_code":"BR",
    "gn:dem":24,
    "gn:feature_class":"P",
    "gn:feature_code":"PPL",
    "gn:name":"S\u00edtio Francisco Alves Cordeiro",
    "gn:population":0,
    "gn:timezone":"America/Sao_Paulo",
    "iso:country":"BR",
    "name:por_x_preferred":[
        "S\u00edtio Francisco Alves Cordeiro"
    ],
    "wof:name":"Sitio Francisco Alves Cordeiro",
    "wof:placetype":"locality"
},
  "geometry": {"coordinates":[-48.7681,-25.7081],"type":"Point"}
}