{
  "type": "Feature",
  "properties": {
    "gn:admin1_code":"17",
    "gn:admin2_code":"2502151.0",
    "gn:asciiname":"Jua",
    "gn:country_code":"BR",
    "gn:dem":460,
    "gn:feature_class":"P",
    "gn:feature_code":"PPL",
    "gn:name":"Ju\u00e1",
    "gn:population":0,
    "gn:timezone":"America/Fortaleza",
    "iso:country":"BR",
    "wof:name":"Jua",
    "wof:placetype":"locality"
},
  "geometry": {"coordinates":[-36.13333,-7.28333],"type":"Point"}
}