{
  "type": "Feature",
  "properties": {
    "gn:admin1_code":"5",
    "gn:admin2_code":"2917359.0",
    "gn:asciiname":"Santa Clara",
    "gn:country_code":"BR",
    "gn:dem":460,
    "gn:feature_class":"P",
    "gn:feature_code":"PPL",
    "gn:name":"Santa Clara",
    "gn:population":0,
    "gn:timezone":"America/Bahia",
    "iso:country":"BR",
    "wof:name":"Santa Clara",
    "wof:placetype":"locality"
},
  "geometry": {"coordinates":[-44.26667,-13.41667],"type":"Point"}
}