{
  "type": "Feature",
  "properties": {
    "gn:admin1_code":"02",
    "gn:admin2_code":"2704302.0",
    "gn:asciiname":"Riacho Doce",
    "gn:country_code":"BR",
    "gn:dem":6,
    "gn:feature_class":"P",
    "gn:feature_code":"PPL",
    "gn:name":"Riacho Doce",
    "gn:population":0,
    "gn:timezone":"America/Maceio",
    "iso:country":"BR",
    "wof:name":"Riacho Doce",
    "wof:placetype":"locality"
},
  "geometry": {"coordinates":[-35.65,-9.56667],"type":"Point"}
}