{
  "type": "Feature",
  "properties": {
    "gn:admin1_code":"02",
    "gn:admin2_code":"2707107.0",
    "gn:asciiname":"Panelas",
    "gn:country_code":"BR",
    "gn:dem":237,
    "gn:feature_class":"P",
    "gn:feature_code":"PPL",
    "gn:name":"Panelas",
    "gn:population":0,
    "gn:timezone":"America/Maceio",
    "iso:country":"BR",
    "wof:name":"Panelas",
    "wof:placetype":"locality"
},
  "geometry": {"coordinates":[-37.71667,-9.46667],"type":"Point"}
}