{
  "type": "Feature",
  "properties": {
    "iso:country":"BR",
    "name:arg_x_preferred":[
        "Centro"
    ],
    "name:cat_x_preferred":[
        "Centro"
    ],
    "name:ceb_x_preferred":[
        "Centro"
    ],
    "name:ces_x_preferred":[
        "Centro"
    ],
    "name:deu_x_preferred":[
        "Centro"
    ],
    "name:ell_x_preferred":[
        "\u039a\u03ad\u03bd\u03c4\u03c1\u03bf"
    ],
    "name:epo_x_preferred":[
        "Centro"
    ],
    "name:eus_x_preferred":[
        "Centro"
    ],
    "name:fra_x_preferred":[
        "Centro"
    ],
    "name:glg_x_preferred":[
        "Centro"
    ],
    "name:ido_x_preferred":[
        "Centro"
    ],
    "name:ita_x_preferred":[
        "Centro"
    ],
    "name:jpn_x_preferred":[
        "\u30bb\u30f3\u30c8\u30ed"
    ],
    "name:kor_x_preferred":[
        "\uc13c\ud2b8\ub85c"
    ],
    "name:nld_x_preferred":[
        "Centro"
    ],
    "name:pol_x_preferred":[
        "Centro"
    ],
    "name:por_x_preferred":[
        "Centro"
    ],
    "name:rus_x_preferred":[
        "\u0421\u0435\u043d\u0442\u0440\u043e"
    ],
    "name:sco_x_preferred":[
        "Centro"
    ],
    "name:slk_x_preferred":[
        "Centro"
    ],
    "name:spa_x_preferred":[
        "Centro"
    ],
    "name:srp_x_preferred":[
        "Centro"
    ],
    "name:swe_x_preferred":[
        "Centro"
    ],
    "name:vie_x_preferred":[
        "Centro"
    ],
    "qs:gn_adm0_cc":"BR",
    "qs:gn_fcode":"PPLL",
    "qs:gn_local":3449112,
    "qs:gn_nam_loc":"S\u00e3o Francisco do Sul, Santa Catarina, BR",
    "qs:gn_namadm1":"26",
    "qs:gn_name":"Centro",
    "qs:local_max":302,
    "qs:local_sum":302,
    "qs:localhoods":1,
    "qs:name":"Centro",
    "qs:name_adm0":"Brasil",
    "qs:name_adm1":"Santa Catarina",
    "qs:name_adm2":"S\u00e3o Francisco do Sul",
    "qs:name_local":"S\u00e3o Francisco do Sul",
    "qs:photo_max":82,
    "qs:photo_sum":302,
    "qs:placetype":"Suburb",
    "qs:quad_count":20,
    "qs:woe_adm0":23424768,
    "qs:woe_adm1":2344867,
    "qs:woe_adm2":12581771,
    "qs:woe_lau":0,
    "qs:woe_local":456516,
    "qs:woe_ver":"7.10.0",
    "wof:lang":[
        "por"
    ],
    "wof:name":"Centro",
    "wof:placetype":"neighbourhood"
},
  "geometry": {"coordinates":[-48.639968,-26.243381],"type":"Point"}
}