{
  "type": "Feature",
  "properties": {
    "gn:admin1_code":"8",
    "gn:admin2_code":"3205150.0",
    "gn:asciiname":"Corrego Grande",
    "gn:country_code":"BR",
    "gn:dem":188,
    "gn:feature_class":"P",
    "gn:feature_code":"PPL",
    "gn:name":"C\u00f3rrego Grande",
    "gn:population":0,
    "gn:timezone":"America/Sao_Paulo",
    "iso:country":"BR",
    "name:por_x_preferred":[
        "C\u00f3rrego Grande"
    ],
    "name:por_x_variant":[
        "Corrego Grande"
    ],
    "wof:name":"Corrego Grande",
    "wof:placetype":"locality"
},
  "geometry": {"coordinates":[-40.60203,-18.62125],"type":"Point"}
}