{
  "type": "Feature",
  "properties": {
    "gn:admin1_code":"27",
    "gn:admin2_code":"3540002.0",
    "gn:asciiname":"Vila Audenia",
    "gn:country_code":"BR",
    "gn:dem":399,
    "gn:feature_class":"P",
    "gn:feature_code":"PPL",
    "gn:name":"Vila Aud\u00eania",
    "gn:population":0,
    "gn:timezone":"America/Sao_Paulo",
    "iso:country":"BR",
    "wof:name":"Vila Audenia",
    "wof:placetype":"locality"
},
  "geometry": {"coordinates":[-50.23333,-22.21667],"type":"Point"}
}