{
  "type": "Feature",
  "properties": {
    "gn:admin1_code":"20",
    "gn:admin2_code":"2208809.0",
    "gn:asciiname":"Carrapato",
    "gn:country_code":"BR",
    "gn:dem":376,
    "gn:feature_class":"P",
    "gn:feature_code":"PPL",
    "gn:name":"Carrapato",
    "gn:population":0,
    "gn:timezone":"America/Fortaleza",
    "iso:country":"BR",
    "wof:name":"Carrapato",
    "wof:placetype":"locality"
},
  "geometry": {"coordinates":[-42.41667,-6.36667],"type":"Point"}
}