{
  "type": "Feature",
  "properties": {
    "gn:admin1_code":"15",
    "gn:admin2_code":"3156106.0",
    "gn:asciiname":"Gloria",
    "gn:country_code":"BR",
    "gn:dem":919,
    "gn:feature_class":"P",
    "gn:feature_code":"PPL",
    "gn:name":"Gl\u00f3ria",
    "gn:population":0,
    "gn:timezone":"America/Sao_Paulo",
    "iso:country":"BR",
    "name:bre_x_preferred":[
        "Gloria"
    ],
    "name:ceb_x_preferred":[
        "Gloria"
    ],
    "name:ces_x_preferred":[
        "Gloria"
    ],
    "name:dan_x_preferred":[
        "Gloria"
    ],
    "name:deu_x_preferred":[
        "Gloria"
    ],
    "name:est_x_preferred":[
        "Gloria"
    ],
    "name:fas_x_preferred":[
        "\u06af\u0644\u0648\u0631\u06cc\u0627"
    ],
    "name:fin_x_preferred":[
        "Gloria"
    ],
    "name:fra_x_preferred":[
        "Gloria"
    ],
    "name:glg_x_preferred":[
        "Gloria"
    ],
    "name:heb_x_preferred":[
        "\u05d2\u05dc\u05d5\u05e8\u05d9\u05d4"
    ],
    "name:ita_x_preferred":[
        "Gloria"
    ],
    "name:jpn_x_preferred":[
        "\u30b0\u30ed\u30ea\u30a2"
    ],
    "name:kor_x_preferred":[
        "\uae00\ub85c\ub9ac\uc544"
    ],
    "name:lat_x_preferred":[
        "Gloria"
    ],
    "name:nld_x_preferred":[
        "Gloria"
    ],
    "name:pol_x_preferred":[
        "Gloria"
    ],
    "name:por_x_preferred":[
        "Gl\u00f3ria"
    ],
    "name:rus_x_preferred":[
        "\u0413\u043b\u043e\u0440\u0438\u044f"
    ],
    "name:spa_x_preferred":[
        "Gloria"
    ],
    "name:swe_x_preferred":[
        "Gloria"
    ],
    "name:tur_x_preferred":[
        "Gloria"
    ],
    "name:ukr_x_preferred":[
        "\u0413\u043b\u043e\u0440\u0456\u044f"
    ],
    "name:war_x_preferred":[
        "Gloria"
    ],
    "wof:name":"Gloria",
    "wof:placetype":"locality"
},
  "geometry": {"coordinates":[-44.28333,-21.01667],"type":"Point"}
}