{
  "type": "Feature",
  "properties": {
    "gn:admin1_code":"11",
    "gn:admin2_code":"5002209.0",
    "gn:asciiname":"Piraputanga",
    "gn:cc2":"BR",
    "gn:country_code":"BR",
    "gn:dem":159,
    "gn:feature_class":"P",
    "gn:feature_code":"PPL",
    "gn:name":"Piraputanga",
    "gn:population":0,
    "gn:timezone":"America/Campo_Grande",
    "iso:country":"BR",
    "name:und_x_variant":[
        "Piraputangas",
        "Piraputanga"
    ],
    "wof:name":"Piraputanga",
    "wof:placetype":"locality"
},
  "geometry": {"coordinates":[-56.11666999999999,-20.81667],"type":"Point"}
}