{
  "type": "Feature",
  "properties": {
    "gn:admin1_code":"24.0",
    "gn:admin2_code":"1101203.0",
    "gn:asciiname":"Nova Brasilia",
    "gn:country_code":"BR",
    "gn:dem":263,
    "gn:feature_class":"P",
    "gn:feature_code":"PPL",
    "gn:name":"Nova Brasilia",
    "gn:population":0,
    "gn:timezone":"America/Porto_Velho",
    "iso:country":"BR",
    "name:por_x_preferred":[
        "Nova Brasilia"
    ],
    "wof:name":"Nova Brasilia",
    "wof:placetype":"locality"
},
  "geometry": {"coordinates":[-61.51709,-11.19792],"type":"Point"}
}