{
  "type": "Feature",
  "properties": {
    "gn:admin1_code":"06",
    "gn:admin2_code":"2306702.0",
    "gn:asciiname":"Caruauba",
    "gn:country_code":"BR",
    "gn:dem":163,
    "gn:feature_class":"P",
    "gn:feature_code":"PPL",
    "gn:name":"Caruauba",
    "gn:population":0,
    "gn:timezone":"America/Fortaleza",
    "iso:country":"BR",
    "wof:name":"Caruauba",
    "wof:placetype":"locality"
},
  "geometry": {"coordinates":[-38.73333,-5.48333],"type":"Point"}
}