{
  "type": "Feature",
  "properties": {
    "gn:admin1_code":"13.0",
    "gn:admin2_code":"2104404.0",
    "gn:asciiname":"Casa Nova",
    "gn:country_code":"BR",
    "gn:dem":115,
    "gn:feature_class":"P",
    "gn:feature_code":"PPL",
    "gn:name":"Casa Nova",
    "gn:population":0,
    "gn:timezone":"America/Fortaleza",
    "iso:country":"BR",
    "name:ara_x_preferred":[
        "\u0643\u0627\u0632\u0627\u0646\u0648\u0641\u0627"
    ],
    "name:bpy_x_preferred":[
        "\u0995\u09be\u09b8\u09be \u09a8\u09cb\u09ad\u09be"
    ],
    "name:bul_x_preferred":[
        "\u041a\u0430\u0437\u0430 \u041d\u043e\u0432\u0430"
    ],
    "name:epo_x_preferred":[
        "Casa Nova"
    ],
    "name:eus_x_preferred":[
        "Casa Nova"
    ],
    "name:fra_x_preferred":[
        "Casa Nova"
    ],
    "name:hye_x_preferred":[
        "\u053f\u0561\u0566\u0561 \u0546\u0578\u057e\u0561"
    ],
    "name:ita_x_preferred":[
        "Casa Nova"
    ],
    "name:kat_x_preferred":[
        "\u10d9\u10d0\u10d6\u10d0-\u10dc\u10dd\u10d5\u10d0"
    ],
    "name:kaz_x_preferred":[
        "\u041a\u0430\u0437\u0430-\u041d\u043e\u0432\u0430"
    ],
    "name:mlg_x_preferred":[
        "Casa Nova"
    ],
    "name:nld_x_preferred":[
        "Casa Nova"
    ],
    "name:nor_x_preferred":[
        "Casa Nova"
    ],
    "name:pol_x_preferred":[
        "Casa Nova"
    ],
    "name:por_x_preferred":[
        "Casa Nova"
    ],
    "name:ron_x_preferred":[
        "Casa Nova"
    ],
    "name:rus_x_preferred":[
        "\u041a\u0430\u0437\u0430-\u041d\u043e\u0432\u0430"
    ],
    "name:vie_x_preferred":[
        "Casa Nova"
    ],
    "name:vol_x_preferred":[
        "Casa Nova"
    ],
    "name:war_x_preferred":[
        "Casa Nova"
    ],
    "name:zho_x_preferred":[
        "\u5361\u8428\u8bfa\u74e6"
    ],
    "wof:name":"Casa Nova",
    "wof:placetype":"locality"
},
  "geometry": {"coordinates":[-44.11278,-5.20582],"type":"Point"}
}