{
  "type": "Feature",
  "properties": {
    "gn:admin1_code":"13.0",
    "gn:admin2_code":"2104404.0",
    "gn:asciiname":"Casa Nova",
    "gn:country_code":"BR",
    "gn:dem":115,
    "gn:feature_class":"P",
    "gn:feature_code":"PPL",
    "gn:name":"Casa Nova",
    "gn:population":0,
    "gn:timezone":"America/Fortaleza",
    "iso:country":"BR",
    "name:por_x_preferred":[
        "Casa Nova"
    ],
    "wof:name":"Casa Nova",
    "wof:placetype":"locality"
},
  "geometry": {"coordinates":[-44.11278,-5.20582],"type":"Point"}
}