{
  "type": "Feature",
  "properties": {
    "gn:admin1_code":"27",
    "gn:admin2_code":"3548609.0",
    "gn:asciiname":"Bau de Cima",
    "gn:country_code":"BR",
    "gn:dem":1398,
    "gn:feature_class":"P",
    "gn:feature_code":"PPLL",
    "gn:name":"Ba\u00fa de Cima",
    "gn:population":0,
    "gn:timezone":"America/Sao_Paulo",
    "iso:country":"BR",
    "name:por_x_preferred":[
        "Ba\u00fa de Cima"
    ],
    "wof:name":"Bau de Cima",
    "wof:placetype":"locality"
},
  "geometry": {"coordinates":[-45.6205,-22.6952],"type":"Point"}
}