{
  "type": "Feature",
  "properties": {
    "gn:admin1_code":"22",
    "gn:admin2_code":"2408003.0",
    "gn:asciiname":"Sao Carlos",
    "gn:country_code":"BR",
    "gn:dem":17,
    "gn:feature_class":"P",
    "gn:feature_code":"PPL",
    "gn:name":"S\u00e3o Carlos",
    "gn:population":0,
    "gn:timezone":"America/Fortaleza",
    "iso:country":"BR",
    "wof:name":"Sao Carlos",
    "wof:placetype":"locality"
},
  "geometry": {"coordinates":[-37.37667,-5.2375],"type":"Point"}
}