{
  "type": "Feature",
  "properties": {
    "gn:admin1_code":"14",
    "gn:admin2_code":"5102637.0",
    "gn:asciiname":"Boa Nova",
    "gn:country_code":"BR",
    "gn:dem":492,
    "gn:feature_class":"P",
    "gn:feature_code":"PPL",
    "gn:name":"Boa Nova",
    "gn:population":0,
    "gn:timezone":"America/Cuiaba",
    "iso:country":"BR",
    "wof:name":"Boa Nova",
    "wof:placetype":"locality"
},
  "geometry": {"coordinates":[-57.91667,-13.41667],"type":"Point"}
}