{
  "type": "Feature",
  "properties": {
    "gn:admin1_code":"14",
    "gn:admin2_code":"5102637.0",
    "gn:asciiname":"Boa Nova",
    "gn:country_code":"BR",
    "gn:dem":492,
    "gn:feature_class":"P",
    "gn:feature_code":"PPL",
    "gn:name":"Boa Nova",
    "gn:population":0,
    "gn:timezone":"America/Cuiaba",
    "iso:country":"BR",
    "name:bpy_x_preferred":[
        "\u09ac\u09cb\u09f1\u09be \u09a8\u09cb\u09ad\u09be"
    ],
    "name:ceb_x_preferred":[
        "Boa Nova"
    ],
    "name:epo_x_preferred":[
        "Boa Nova"
    ],
    "name:eus_x_preferred":[
        "Boa Nova"
    ],
    "name:fra_x_preferred":[
        "Boa Nova"
    ],
    "name:hye_x_preferred":[
        "\u0532\u0578\u0561 \u0546\u0578\u057e\u0561"
    ],
    "name:ita_x_preferred":[
        "Boa Nova"
    ],
    "name:kat_x_preferred":[
        "\u10d1\u10dd\u10d0-\u10dc\u10dd\u10d5\u10d0"
    ],
    "name:kaz_x_preferred":[
        "\u0411\u043e\u0430-\u041d\u043e\u0432\u0430"
    ],
    "name:mlg_x_preferred":[
        "Boa Nova"
    ],
    "name:nld_x_preferred":[
        "Boa Nova"
    ],
    "name:nor_x_preferred":[
        "Boa Nova"
    ],
    "name:pol_x_preferred":[
        "Boa Nova"
    ],
    "name:por_x_preferred":[
        "Boa Nova"
    ],
    "name:ron_x_preferred":[
        "Boa Nova"
    ],
    "name:rus_x_preferred":[
        "\u0411\u043e\u0430-\u041d\u043e\u0432\u0430"
    ],
    "name:spa_x_preferred":[
        "Boa Nova"
    ],
    "name:swe_x_preferred":[
        "Boa Nova"
    ],
    "name:vie_x_preferred":[
        "Boa Nova"
    ],
    "name:vol_x_preferred":[
        "Boa Nova"
    ],
    "name:war_x_preferred":[
        "Boa Nova"
    ],
    "name:zho_x_preferred":[
        "\u535a\u963f\u8bfa\u74e6"
    ],
    "wof:name":"Boa Nova",
    "wof:placetype":"locality"
},
  "geometry": {"coordinates":[-57.91667,-13.41667],"type":"Point"}
}