{
  "type": "Feature",
  "properties": {
    "gn:admin1_code":"06",
    "gn:admin2_code":"2304350.0",
    "gn:asciiname":"Fazenda Cajazeiras",
    "gn:country_code":"BR",
    "gn:dem":115,
    "gn:feature_class":"P",
    "gn:feature_code":"PPL",
    "gn:name":"Fazenda Cajazeiras",
    "gn:population":0,
    "gn:timezone":"America/Fortaleza",
    "iso:country":"BR",
    "wof:name":"Fazenda Cajazeiras",
    "wof:placetype":"locality"
},
  "geometry": {"coordinates":[-40.18333,-3.73333],"type":"Point"}
}