{
  "type": "Feature",
  "properties": {
    "gn:admin1_code":"18",
    "gn:admin2_code":"4114302.0",
    "gn:asciiname":"Sitio Everaldo",
    "gn:country_code":"BR",
    "gn:dem":896,
    "gn:feature_class":"P",
    "gn:feature_code":"PPL",
    "gn:name":"S\u00edtio Everaldo",
    "gn:population":0,
    "gn:timezone":"America/Sao_Paulo",
    "iso:country":"BR",
    "name:por_x_preferred":[
        "S\u00edtio Everaldo"
    ],
    "wof:name":"Sitio Everaldo",
    "wof:placetype":"locality"
},
  "geometry": {"coordinates":[-49.2261,-25.87851],"type":"Point"}
}