{
  "type": "Feature",
  "properties": {
    "gn:admin1_code":"16.0",
    "gn:admin2_code":"1501808.0",
    "gn:asciiname":"Santa Cruz",
    "gn:country_code":"BR",
    "gn:dem":15,
    "gn:feature_class":"P",
    "gn:feature_code":"PPL",
    "gn:name":"Santa Cruz",
    "gn:population":0,
    "gn:timezone":"America/Belem",
    "iso:country":"BR",
    "name:por_x_preferred":[
        "Santa Cruz"
    ],
    "wof:name":"Santa Cruz",
    "wof:placetype":"locality"
},
  "geometry": {"coordinates":[-50.77148,-1.46898],"type":"Point"}
}