{
  "type": "Feature",
  "properties": {
    "gn:admin1_code":"18.0",
    "gn:admin2_code":"4126603.0",
    "gn:asciiname":"Sitio Pedro Lopes",
    "gn:country_code":"BR",
    "gn:dem":650,
    "gn:feature_class":"P",
    "gn:feature_code":"PPL",
    "gn:name":"S\u00edtio Pedro Lopes",
    "gn:population":0,
    "gn:timezone":"America/Sao_Paulo",
    "iso:country":"BR",
    "name:por_x_preferred":[
        "S\u00edtio Pedro Lopes"
    ],
    "wof:name":"Sitio Pedro Lopes",
    "wof:placetype":"locality"
},
  "geometry": {"coordinates":[-49.8499,-23.6831],"type":"Point"}
}