{
  "type": "Feature",
  "properties": {
    "gn:admin1_code":"27.0",
    "gn:admin2_code":"3522158.0",
    "gn:asciiname":"Barrio do Pavao",
    "gn:country_code":"BR",
    "gn:dem":157,
    "gn:feature_class":"P",
    "gn:feature_code":"PPLL",
    "gn:name":"Barrio do Pav\u00e3o",
    "gn:population":0,
    "gn:timezone":"America/Sao_Paulo",
    "iso:country":"BR",
    "name:por_x_preferred":[
        "Barrio do Pav\u00e3o"
    ],
    "wof:name":"Barrio do Pavao",
    "wof:placetype":"locality"
},
  "geometry": {"coordinates":[-48.79004000000001,-24.64394],"type":"Point"}
}