{
  "type": "Feature",
  "properties": {
    "gn:admin1_code":"16",
    "gn:admin2_code":"1501204.0",
    "gn:asciiname":"Sao Joaquim",
    "gn:country_code":"BR",
    "gn:dem":58,
    "gn:feature_class":"P",
    "gn:feature_code":"PPL",
    "gn:name":"S\u00e3o Joaquim",
    "gn:population":0,
    "gn:timezone":"America/Belem",
    "iso:country":"BR",
    "wof:name":"Sao Joaquim",
    "wof:placetype":"locality"
},
  "geometry": {"coordinates":[-49.66456,-2.86778],"type":"Point"}
}