{
  "type": "Feature",
  "properties": {
    "gn:admin1_code":"20",
    "gn:admin2_code":"2201903.0",
    "gn:asciiname":"Tapera",
    "gn:country_code":"BR",
    "gn:dem":627,
    "gn:feature_class":"P",
    "gn:feature_code":"PPL",
    "gn:name":"Tapera",
    "gn:population":0,
    "gn:timezone":"America/Fortaleza",
    "iso:country":"BR",
    "wof:name":"Tapera",
    "wof:placetype":"locality"
},
  "geometry": {"coordinates":[-43.91667,-9.36667],"type":"Point"}
}