{
  "type": "Feature",
  "properties": {
    "gn:admin1_code":"27",
    "gn:admin2_code":"3504107.0",
    "gn:asciiname":"Sitio Palmares",
    "gn:country_code":"BR",
    "gn:dem":769,
    "gn:feature_class":"P",
    "gn:feature_code":"PPL",
    "gn:name":"S\u00edtio Palmares",
    "gn:population":0,
    "gn:timezone":"America/Sao_Paulo",
    "iso:country":"BR",
    "name:por_x_preferred":[
        "S\u00edtio Palmares"
    ],
    "wof:name":"Sitio Palmares",
    "wof:placetype":"locality"
},
  "geometry": {"coordinates":[-46.56639000000001,-23.15833],"type":"Point"}
}