{
  "type": "Feature",
  "properties": {
    "gn:admin1_code":"20",
    "gn:admin2_code":"2202026.0",
    "gn:asciiname":"Mundo Novo",
    "gn:country_code":"BR",
    "gn:dem":609,
    "gn:feature_class":"P",
    "gn:feature_code":"PPL",
    "gn:name":"Mundo N\u00f4vo",
    "gn:population":0,
    "gn:timezone":"America/Fortaleza",
    "iso:country":"BR",
    "name:ceb_x_preferred":[
        "Mundo Novo"
    ],
    "name:deu_x_preferred":[
        "Mundo Novo"
    ],
    "name:ita_x_preferred":[
        "Mundo Novo"
    ],
    "name:nld_x_preferred":[
        "Mundo Novo"
    ],
    "name:nor_x_preferred":[
        "Mundo Novo"
    ],
    "name:pol_x_preferred":[
        "Mundo Novo"
    ],
    "name:por_x_preferred":[
        "Mundo Novo"
    ],
    "name:spa_x_preferred":[
        "Mundo Novo"
    ],
    "name:swe_x_preferred":[
        "Mundo Novo"
    ],
    "name:vie_x_preferred":[
        "Mundo Novo"
    ],
    "name:vol_x_preferred":[
        "Mundo Novo"
    ],
    "wof:name":"Mundo Novo",
    "wof:placetype":"locality"
},
  "geometry": {"coordinates":[-40.98333,-5.26667],"type":"Point"}
}