{
  "type": "Feature",
  "properties": {
    "gn:admin1_code":"17",
    "gn:admin2_code":"2509701.0",
    "gn:asciiname":"Rancho dos Negros",
    "gn:country_code":"BR",
    "gn:dem":591,
    "gn:feature_class":"P",
    "gn:feature_code":"PPL",
    "gn:name":"Rancho dos Negros",
    "gn:population":0,
    "gn:timezone":"America/Fortaleza",
    "iso:country":"BR",
    "wof:name":"Rancho dos Negros",
    "wof:placetype":"locality"
},
  "geometry": {"coordinates":[-37.03333,-7.75],"type":"Point"}
}