{
  "type": "Feature",
  "properties": {
    "gn:admin1_code":"27.0",
    "gn:admin2_code":"3516408.0",
    "gn:asciiname":"Rio Abaixo",
    "gn:country_code":"BR",
    "gn:dem":830,
    "gn:feature_class":"P",
    "gn:feature_code":"PPLL",
    "gn:name":"Rio Abaixo",
    "gn:population":0,
    "gn:timezone":"America/Sao_Paulo",
    "iso:country":"BR",
    "name:por_x_preferred":[
        "Rio Abaixo"
    ],
    "wof:name":"Rio Abaixo",
    "wof:placetype":"locality"
},
  "geometry": {"coordinates":[-46.68452,-23.32289],"type":"Point"}
}