{
  "type": "Feature",
  "properties": {
    "gn:admin1_code":"5.0",
    "gn:admin2_code":"2924405.0",
    "gn:asciiname":"Mandarim",
    "gn:country_code":"BR",
    "gn:dem":431,
    "gn:feature_class":"P",
    "gn:feature_code":"PPL",
    "gn:name":"Mandarim",
    "gn:population":0,
    "gn:timezone":"America/Bahia",
    "iso:country":"BR",
    "name:por_x_preferred":[
        "Mandarim"
    ],
    "wof:name":"Mandarim",
    "wof:placetype":"locality"
},
  "geometry": {"coordinates":[-43.28606,-9.83124],"type":"Point"}
}