{
  "type": "Feature",
  "properties": {
    "gn:admin1_code":"06",
    "gn:admin2_code":"2312809.0",
    "gn:asciiname":"Fazenda Esperantina",
    "gn:country_code":"BR",
    "gn:dem":69,
    "gn:feature_class":"P",
    "gn:feature_code":"PPL",
    "gn:name":"Fazenda Esperantina",
    "gn:population":0,
    "gn:timezone":"America/Fortaleza",
    "iso:country":"BR",
    "wof:name":"Fazenda Esperantina",
    "wof:placetype":"locality"
},
  "geometry": {"coordinates":[-40.46667,-3.23333],"type":"Point"}
}