{
  "type": "Feature",
  "properties": {
    "gn:admin1_code":"16",
    "gn:admin2_code":"1500503.0",
    "gn:asciiname":"Bom Lugar",
    "gn:country_code":"BR",
    "gn:dem":34,
    "gn:feature_class":"P",
    "gn:feature_code":"PPL",
    "gn:name":"Bom Lugar",
    "gn:population":0,
    "gn:timezone":"America/Santarem",
    "iso:country":"BR",
    "wof:name":"Bom Lugar",
    "wof:placetype":"locality"
},
  "geometry": {"coordinates":[-52.81191999999999,-1.54983],"type":"Point"}
}