{
  "type": "Feature",
  "properties": {
    "gn:admin1_code":"16",
    "gn:admin2_code":"1500503.0",
    "gn:asciiname":"Bom Lugar",
    "gn:country_code":"BR",
    "gn:dem":34,
    "gn:feature_class":"P",
    "gn:feature_code":"PPL",
    "gn:name":"Bom Lugar",
    "gn:population":0,
    "gn:timezone":"America/Santarem",
    "iso:country":"BR",
    "name:bpy_x_preferred":[
        "\u09ac\u09cb\u09ae \u09b2\u09c1\u0997\u09be\u09b0\u09cd"
    ],
    "name:ceb_x_preferred":[
        "Bom Lugar"
    ],
    "name:eus_x_preferred":[
        "Bom Lugar"
    ],
    "name:fra_x_preferred":[
        "Bom Lugar"
    ],
    "name:hye_x_preferred":[
        "\u0532\u0578\u0576 \u053c\u0578\u0582\u0563\u0561\u0580"
    ],
    "name:ita_x_preferred":[
        "Bom Lugar"
    ],
    "name:kat_x_preferred":[
        "\u10d1\u10dd\u10dc-\u10da\u10e3\u10d2\u10d0\u10e0\u10d8"
    ],
    "name:kaz_x_preferred":[
        "\u0411\u043e\u043d-\u041b\u0443\u0433\u0430\u0440"
    ],
    "name:nld_x_preferred":[
        "Bom Lugar"
    ],
    "name:nor_x_preferred":[
        "Bom Lugar"
    ],
    "name:por_x_preferred":[
        "Bom Lugar"
    ],
    "name:ron_x_preferred":[
        "Bom Lugar"
    ],
    "name:rus_x_preferred":[
        "\u0411\u043e\u043d-\u041b\u0443\u0433\u0430\u0440"
    ],
    "name:swe_x_preferred":[
        "Bom Lugar"
    ],
    "name:vie_x_preferred":[
        "Bom Lugar"
    ],
    "name:vol_x_preferred":[
        "Bom Lugar"
    ],
    "name:war_x_preferred":[
        "Bom Lugar"
    ],
    "name:zho_x_preferred":[
        "\u90a6\u5362\u52a0\u5c14"
    ],
    "wof:name":"Bom Lugar",
    "wof:placetype":"locality"
},
  "geometry": {"coordinates":[-52.81191999999999,-1.54983],"type":"Point"}
}