{
  "type": "Feature",
  "properties": {
    "gn:admin1_code":"26",
    "gn:admin2_code":"4207908.0",
    "gn:asciiname":"Quilometro Quinze",
    "gn:country_code":"BR",
    "gn:dem":807,
    "gn:feature_class":"P",
    "gn:feature_code":"PPL",
    "gn:name":"Quil\u00f4metro Quinze",
    "gn:population":0,
    "gn:timezone":"America/Sao_Paulo",
    "iso:country":"BR",
    "wof:name":"Quilometro Quinze",
    "wof:placetype":"locality"
},
  "geometry": {"coordinates":[-50.71667,-26.33333],"type":"Point"}
}