{
  "type": "Feature",
  "properties": {
    "gn:admin1_code":"27",
    "gn:admin2_code":"3530607.0",
    "gn:asciiname":"Tabuo",
    "gn:country_code":"BR",
    "gn:dem":701,
    "gn:feature_class":"P",
    "gn:feature_code":"PPLL",
    "gn:name":"Tabuo",
    "gn:population":0,
    "gn:timezone":"America/Sao_Paulo",
    "iso:country":"BR",
    "name:por_x_preferred":[
        "Tabuo"
    ],
    "wof:name":"Tabuo",
    "wof:placetype":"locality"
},
  "geometry": {"coordinates":[-46.2398,-23.4212],"type":"Point"}
}