{
  "type": "Feature",
  "properties": {
    "gn:country":"BR",
    "gn:fcode":"PPL",
    "gn:population":0,
    "iso:country":"BR",
    "name:bpy_x_preferred":[
        "\u09b8\u09be\u09a8\u09cd\u099f\u09be \u09b8\u09c7\u0995\u0987\u09b2\u09bf\u09af\u09bc\u09be"
    ],
    "name:eus_x_preferred":[
        "Santa Cec\u00edlia"
    ],
    "name:fra_x_preferred":[
        "Santa Cec\u00edlia"
    ],
    "name:ina_x_preferred":[
        "Santa Cec\u00edlia"
    ],
    "name:ita_x_preferred":[
        "Santa Cec\u00edlia"
    ],
    "name:kat_x_preferred":[
        "\u10e1\u10d0\u10dc\u10e2\u10d0-\u10e1\u10d4\u10e1\u10d8\u10da\u10d8\u10d0"
    ],
    "name:mlg_x_preferred":[
        "Santa Cec\u00edlia"
    ],
    "name:nld_x_preferred":[
        "Santa Cec\u00edlia"
    ],
    "name:nor_x_preferred":[
        "Santa Cec\u00edlia"
    ],
    "name:oci_x_preferred":[
        "Santa Cec\u00edlia"
    ],
    "name:pol_x_preferred":[
        "Santa Cec\u00edlia"
    ],
    "name:por_x_preferred":[
        "Santa Cec\u00edlia"
    ],
    "name:ron_x_preferred":[
        "Santa Cec\u00edlia"
    ],
    "name:rus_x_preferred":[
        "\u0421\u0430\u043d\u0442\u0430-\u0421\u0435\u0441\u0438\u043b\u0438\u044f"
    ],
    "name:vol_x_preferred":[
        "Santa Cec\u00edlia"
    ],
    "name:war_x_preferred":[
        "Santa Cec\u00edlia"
    ],
    "name:zho_x_preferred":[
        "\u8056\u585e\u897f\u5229\u4e9e"
    ],
    "qs_pg:aaroncc":"BR",
    "qs_pg:gn_country":"BR",
    "qs_pg:gn_fcode":"PPL",
    "qs_pg:gn_pop":0,
    "qs_pg:name":"Santa Cec\u00edlia",
    "qs_pg:name_adm0":"Brasil",
    "qs_pg:name_adm1":"Minas Gerais",
    "qs_pg:photos":13,
    "qs_pg:photos_1k":3,
    "qs_pg:photos_9k":1,
    "qs_pg:photos_9r":1,
    "qs_pg:photos_all":13,
    "qs_pg:photos_sr":1,
    "qs_pg:pop_sr":0,
    "qs_pg:qs_pg_placetype":"neighbourhood",
    "qs_pg:qs_pg_placetype_gp":"Suburb",
    "qs_pg:woe_adm0":23424768,
    "woe:adm0_id":23424768,
    "woe:name_adm0":"Brasil",
    "woe:name_adm1":"Minas Gerais",
    "woe:placetype":"Suburb",
    "wof:name":"Santa Cec\u00edlia",
    "wof:placetype":"neighbourhood"
},
  "geometry": {"coordinates":[-43.86667,-22.46667],"type":"Point"}
}