{
  "type": "Feature",
  "properties": {
    "gn:admin1_code":"5",
    "gn:admin2_code":"2929206.0",
    "gn:asciiname":"Vera Cruz",
    "gn:country_code":"BR",
    "gn:dem":76,
    "gn:feature_class":"P",
    "gn:feature_code":"PPL",
    "gn:name":"Vera Cruz",
    "gn:population":0,
    "gn:timezone":"America/Bahia",
    "iso:country":"BR",
    "wof:name":"Vera Cruz",
    "wof:placetype":"locality"
},
  "geometry": {"coordinates":[-38.61667,-12.56667],"type":"Point"}
}