{
  "type": "Feature",
  "properties": {
    "gn:admin1_code":"27",
    "gn:admin2_code":"3528502.0",
    "gn:asciiname":"Jardim Sun Valley",
    "gn:country_code":"BR",
    "gn:dem":944,
    "gn:feature_class":"P",
    "gn:feature_code":"PPL",
    "gn:name":"Jardim Sun Valley",
    "gn:population":0,
    "gn:timezone":"America/Sao_Paulo",
    "iso:country":"BR",
    "name:por_x_preferred":[
        "Jardim Sun Valley"
    ],
    "wof:name":"Jardim Sun Valley",
    "wof:placetype":"locality"
},
  "geometry": {"coordinates":[-46.56333,-23.24667],"type":"Point"}
}