{
  "type": "Feature",
  "properties": {
    "gn:admin1_code":"18.0",
    "gn:admin2_code":"4100202.0",
    "gn:asciiname":"Ribeirao das Pedras",
    "gn:country_code":"BR",
    "gn:dem":719,
    "gn:feature_class":"P",
    "gn:feature_code":"PPLL",
    "gn:name":"Ribeir\u00e3o das Pedras",
    "gn:population":0,
    "gn:timezone":"America/Sao_Paulo",
    "iso:country":"BR",
    "name:por_x_preferred":[
        "Ribeir\u00e3o das Pedras"
    ],
    "wof:name":"Ribeirao das Pedras",
    "wof:placetype":"locality"
},
  "geometry": {"coordinates":[-48.95458,-24.89745],"type":"Point"}
}