{
  "type": "Feature",
  "properties": {
    "gn:admin1_code":"1",
    "gn:admin2_code":"1200054.0",
    "gn:asciiname":"Seringal Paraguacu",
    "gn:country_code":"BR",
    "gn:dem":268,
    "gn:feature_class":"P",
    "gn:feature_code":"PPL",
    "gn:name":"Seringal Paragua\u00e7u",
    "gn:population":0,
    "gn:timezone":"America/Rio_Branco",
    "iso:country":"BR",
    "wof:name":"Seringal Paraguacu",
    "wof:placetype":"locality"
},
  "geometry": {"coordinates":[-69.56667,-10.93333],"type":"Point"}
}