{
  "type": "Feature",
  "properties": {
    "gn:admin1_code":"22",
    "gn:admin2_code":"2402303.0",
    "gn:asciiname":"Baixa Grande",
    "gn:country_code":"BR",
    "gn:dem":143,
    "gn:feature_class":"P",
    "gn:feature_code":"PPL",
    "gn:name":"Baixa Grande",
    "gn:population":0,
    "gn:timezone":"America/Fortaleza",
    "iso:country":"BR",
    "wof:name":"Baixa Grande",
    "wof:placetype":"locality"
},
  "geometry": {"coordinates":[-37.48583,-5.71],"type":"Point"}
}