{
  "type": "Feature",
  "properties": {
    "gn:admin1_code":"18.0",
    "gn:admin2_code":"4101200.0",
    "gn:asciiname":"Sitio Luiz Carlos",
    "gn:country_code":"BR",
    "gn:dem":16,
    "gn:feature_class":"P",
    "gn:feature_code":"PPL",
    "gn:name":"S\u00edtio Luiz Carlos",
    "gn:population":0,
    "gn:timezone":"America/Sao_Paulo",
    "iso:country":"BR",
    "name:por_x_preferred":[
        "S\u00edtio Luiz Carlos"
    ],
    "wof:name":"Sitio Luiz Carlos",
    "wof:placetype":"locality"
},
  "geometry": {"coordinates":[-48.76283,-25.32329],"type":"Point"}
}