{
  "type": "Feature",
  "properties": {
    "gn:admin1_code":"26.0",
    "gn:admin2_code":"4208104.0",
    "gn:asciiname":"Sitio Pomar das Chacaras",
    "gn:country_code":"BR",
    "gn:dem":982,
    "gn:feature_class":"P",
    "gn:feature_code":"PPL",
    "gn:name":"S\u00edtio Pomar das Ch\u00e1caras",
    "gn:population":0,
    "gn:timezone":"America/Sao_Paulo",
    "iso:country":"BR",
    "name:por_x_preferred":[
        "S\u00edtio Pomar das Ch\u00e1caras"
    ],
    "wof:name":"Sitio Pomar das Chacaras",
    "wof:placetype":"locality"
},
  "geometry": {"coordinates":[-49.73487,-26.6282],"type":"Point"}
}