{
  "type": "Feature",
  "properties": {
    "gn:admin1_code":"18",
    "gn:admin2_code":"4119103.0",
    "gn:asciiname":"Sitio Alcides P. Giese",
    "gn:country_code":"BR",
    "gn:dem":840,
    "gn:feature_class":"P",
    "gn:feature_code":"PPL",
    "gn:name":"S\u00edtio Alcides P. Giese",
    "gn:population":0,
    "gn:timezone":"America/Sao_Paulo",
    "iso:country":"BR",
    "name:por_x_preferred":[
        "S\u00edtio Alcides P. Giese"
    ],
    "wof:name":"Sitio Alcides P. Giese",
    "wof:placetype":"locality"
},
  "geometry": {"coordinates":[-49.4057,-26.1274],"type":"Point"}
}