{
  "type": "Feature",
  "properties": {
    "gn:admin1_code":"31",
    "gn:admin2_code":"1711902.0",
    "gn:asciiname":"Fontoura",
    "gn:country_code":"BR",
    "gn:dem":186,
    "gn:feature_class":"P",
    "gn:feature_code":"PPL",
    "gn:name":"Fontoura",
    "gn:population":0,
    "gn:timezone":"America/Araguaina",
    "iso:country":"BR",
    "wof:name":"Fontoura",
    "wof:placetype":"locality"
},
  "geometry": {"coordinates":[-50.60556,-11.30083],"type":"Point"}
}