{
  "type": "Feature",
  "properties": {
    "gn:admin1_code":"31",
    "gn:admin2_code":"1711902.0",
    "gn:asciiname":"Fontoura",
    "gn:country_code":"BR",
    "gn:dem":186,
    "gn:feature_class":"P",
    "gn:feature_code":"PPL",
    "gn:name":"Fontoura",
    "gn:population":0,
    "gn:timezone":"America/Araguaina",
    "iso:country":"BR",
    "name:ceb_x_preferred":[
        "Fontoura"
    ],
    "name:deu_x_preferred":[
        "Fontoura"
    ],
    "name:kaz_x_preferred":[
        "\u0424\u043e\u043d\u0442\u043e\u0440\u0430"
    ],
    "name:nld_x_preferred":[
        "Fontoura"
    ],
    "name:por_x_preferred":[
        "Fontoura"
    ],
    "name:rus_x_preferred":[
        "\u0424\u043e\u043d\u0442\u043e\u0440\u0430"
    ],
    "name:spa_x_preferred":[
        "Fontoura"
    ],
    "name:tur_x_preferred":[
        "Fontoura"
    ],
    "wof:name":"Fontoura",
    "wof:placetype":"locality"
},
  "geometry": {"coordinates":[-50.60556,-11.30083],"type":"Point"}
}