{
  "type": "Feature",
  "properties": {
    "gn:admin1_code":"20",
    "gn:admin2_code":"2203701.0",
    "gn:asciiname":"Boa Vista dos Cariocas",
    "gn:country_code":"BR",
    "gn:dem":78,
    "gn:feature_class":"P",
    "gn:feature_code":"PPL",
    "gn:name":"Boa Vista dos Cariocas",
    "gn:population":0,
    "gn:timezone":"America/Fortaleza",
    "iso:country":"BR",
    "wof:name":"Boa Vista dos Cariocas",
    "wof:placetype":"locality"
},
  "geometry": {"coordinates":[-42.15,-3.65],"type":"Point"}
}