{
  "type": "Feature",
  "properties": {
    "gn:admin1_code":"27.0",
    "gn:admin2_code":"3518800.0",
    "gn:asciiname":"Cabucu",
    "gn:country_code":"BR",
    "gn:dem":792,
    "gn:feature_class":"P",
    "gn:feature_code":"PPLL",
    "gn:name":"Cabu\u00e7u",
    "gn:population":0,
    "gn:timezone":"America/Sao_Paulo",
    "iso:country":"BR",
    "name:por_x_preferred":[
        "Cabu\u00e7u"
    ],
    "wof:name":"Cabucu",
    "wof:placetype":"locality"
},
  "geometry": {"coordinates":[-46.53823,-23.40633],"type":"Point"}
}