{
  "type": "Feature",
  "properties": {
    "gn:admin1_code":"4.0",
    "gn:admin2_code":"1300839.0",
    "gn:asciiname":"Vila Uniao",
    "gn:country_code":"BR",
    "gn:dem":45,
    "gn:feature_class":"P",
    "gn:feature_code":"PPLL",
    "gn:name":"Vila Uni\u00e3o",
    "gn:population":0,
    "gn:timezone":"America/Manaus",
    "iso:country":"BR",
    "name:por_x_preferred":[
        "Vila Uni\u00e3o"
    ],
    "wof:name":"Vila Uniao",
    "wof:placetype":"locality"
},
  "geometry": {"coordinates":[-61.73019,-2.98864],"type":"Point"}
}