{
  "type": "Feature",
  "properties": {
    "gn:admin1_code":"5",
    "gn:admin2_code":"2918506.0",
    "gn:asciiname":"Jussara",
    "gn:country_code":"BR",
    "gn:dem":619,
    "gn:feature_class":"P",
    "gn:feature_code":"PPL",
    "gn:name":"Jussara",
    "gn:population":0,
    "gn:timezone":"America/Bahia",
    "iso:country":"BR",
    "wof:name":"Jussara",
    "wof:placetype":"locality"
},
  "geometry": {"coordinates":[-41.96944000000001,-11.04694],"type":"Point"}
}