{
  "type": "Feature",
  "properties": {
    "gn:admin1_code":"5",
    "gn:admin2_code":"2918506.0",
    "gn:asciiname":"Jussara",
    "gn:country_code":"BR",
    "gn:dem":619,
    "gn:feature_class":"P",
    "gn:feature_code":"PPL",
    "gn:name":"Jussara",
    "gn:population":0,
    "gn:timezone":"America/Bahia",
    "iso:country":"BR",
    "name:deu_x_preferred":[
        "Jussara"
    ],
    "name:epo_x_preferred":[
        "Jussara"
    ],
    "name:eus_x_preferred":[
        "Jussara"
    ],
    "name:fra_x_preferred":[
        "Jussara"
    ],
    "name:hye_x_preferred":[
        "\u053a\u0578\u0582\u057d\u0561\u0580\u0561"
    ],
    "name:ita_x_preferred":[
        "Jussara"
    ],
    "name:kat_x_preferred":[
        "\u10df\u10e3\u10e1\u10d0\u10e0\u10d0"
    ],
    "name:kaz_x_preferred":[
        "\u0416\u0443\u0441\u0430\u0440\u0430"
    ],
    "name:mlg_x_preferred":[
        "Jussara"
    ],
    "name:nld_x_preferred":[
        "Jussara"
    ],
    "name:nor_x_preferred":[
        "Jussara"
    ],
    "name:pol_x_preferred":[
        "Jussara"
    ],
    "name:por_x_preferred":[
        "Jussara"
    ],
    "name:rus_x_preferred":[
        "\u0416\u0443\u0441\u0430\u0440\u0430"
    ],
    "name:vol_x_preferred":[
        "Jussara"
    ],
    "name:war_x_preferred":[
        "Jussara"
    ],
    "name:zho_x_preferred":[
        "\u8339\u8428\u62c9"
    ],
    "wof:name":"Jussara",
    "wof:placetype":"locality"
},
  "geometry": {"coordinates":[-41.96944000000001,-11.04694],"type":"Point"}
}