{
  "type": "Feature",
  "properties": {
    "gn:admin1_code":"27.0",
    "gn:admin2_code":"3505401.0",
    "gn:asciiname":"Sitio Diogo",
    "gn:country_code":"BR",
    "gn:dem":626,
    "gn:feature_class":"P",
    "gn:feature_code":"PPL",
    "gn:name":"S\u00edtio Diogo",
    "gn:population":0,
    "gn:timezone":"America/Sao_Paulo",
    "iso:country":"BR",
    "name:por_x_preferred":[
        "S\u00edtio Diogo"
    ],
    "wof:name":"Sitio Diogo",
    "wof:placetype":"locality"
},
  "geometry": {"coordinates":[-48.54937,-25.06611],"type":"Point"}
}