{
  "type": "Feature",
  "properties": {
    "gn:admin1_code":"22",
    "gn:admin2_code":"2401909.0",
    "gn:asciiname":"Bandeira",
    "gn:country_code":"BR",
    "gn:dem":320,
    "gn:feature_class":"P",
    "gn:feature_code":"PPL",
    "gn:name":"Bandeira",
    "gn:population":0,
    "gn:timezone":"America/Fortaleza",
    "iso:country":"BR",
    "wof:name":"Bandeira",
    "wof:placetype":"locality"
},
  "geometry": {"coordinates":[-35.96667,-5.78333],"type":"Point"}
}