{
  "type": "Feature",
  "properties": {
    "gn:admin1_code":"22",
    "gn:admin2_code":"2401909.0",
    "gn:asciiname":"Bandeira",
    "gn:country_code":"BR",
    "gn:dem":320,
    "gn:feature_class":"P",
    "gn:feature_code":"PPL",
    "gn:name":"Bandeira",
    "gn:population":0,
    "gn:timezone":"America/Fortaleza",
    "iso:country":"BR",
    "name:ceb_x_preferred":[
        "Bandeira"
    ],
    "name:deu_x_preferred":[
        "Bandeira"
    ],
    "name:fra_x_preferred":[
        "Bandeira"
    ],
    "name:glg_x_preferred":[
        "Bandeira"
    ],
    "name:hye_x_preferred":[
        "\u0532\u0561\u0576\u0564\u0565\u0575\u0580\u0561"
    ],
    "name:nld_x_preferred":[
        "Bandeira"
    ],
    "name:pol_x_preferred":[
        "Bandeira"
    ],
    "name:por_x_preferred":[
        "Bandeira"
    ],
    "name:rus_x_preferred":[
        "\u0411\u0430\u043d\u0434\u0435\u0439\u0440\u0430"
    ],
    "name:swe_x_preferred":[
        "Bandeira"
    ],
    "wof:name":"Bandeira",
    "wof:placetype":"locality"
},
  "geometry": {"coordinates":[-35.96667,-5.78333],"type":"Point"}
}