{
  "type": "Feature",
  "properties": {
    "gn:admin1_code":"4",
    "gn:admin2_code":"1302504.0",
    "gn:asciiname":"Cajual",
    "gn:country_code":"BR",
    "gn:dem":21,
    "gn:feature_class":"P",
    "gn:feature_code":"PPL",
    "gn:name":"Cajual",
    "gn:population":0,
    "gn:timezone":"America/Manaus",
    "iso:country":"BR",
    "wof:name":"Cajual",
    "wof:placetype":"locality"
},
  "geometry": {"coordinates":[-60.55,-3.13333],"type":"Point"}
}