{
  "type": "Feature",
  "properties": {
    "gn:admin1_code":"20",
    "gn:admin2_code":"2209971.0",
    "gn:asciiname":"Chapada da Sinda",
    "gn:country_code":"BR",
    "gn:dem":101,
    "gn:feature_class":"P",
    "gn:feature_code":"PPL",
    "gn:name":"Chapada da Sind\u00e1",
    "gn:population":0,
    "gn:timezone":"America/Fortaleza",
    "iso:country":"BR",
    "wof:name":"Chapada da Sinda",
    "wof:placetype":"locality"
},
  "geometry": {"coordinates":[-42.43361,-3.86583],"type":"Point"}
}