{
  "type": "Feature",
  "properties": {
    "gn:admin1_code":"26",
    "gn:admin2_code":"4210100.0",
    "gn:asciiname":"Sitio Erico Muller",
    "gn:country_code":"BR",
    "gn:dem":816,
    "gn:feature_class":"P",
    "gn:feature_code":"PPL",
    "gn:name":"S\u00edtio \u00c9rico M\u00fcller",
    "gn:population":0,
    "gn:timezone":"America/Sao_Paulo",
    "iso:country":"BR",
    "name:por_x_preferred":[
        "S\u00edtio \u00c9rico M\u00fcller"
    ],
    "wof:name":"Sitio Erico Muller",
    "wof:placetype":"locality"
},
  "geometry": {"coordinates":[-49.7544,-26.2379],"type":"Point"}
}