{
  "type": "Feature",
  "properties": {
    "iso:country":"BR",
    "oa:elevation_ft":"397",
    "oa:type":"small_airport",
    "woe:hierarchy":{
        "country_id":23424768,
        "county_id":12578215,
        "planet_id":1,
        "state_id":2344847
    },
    "wof:name":"Aeroporto Pauini",
    "wof:placetype":"campus"
},
  "geometry": {"coordinates":[-67.028333,-7.7225],"type":"Point"}
}