{
  "type": "Feature",
  "properties": {
    "iso:country":"BR",
    "name:deu_x_preferred":[
        "Flughafen Pauini"
    ],
    "name:eng_x_preferred":[
        "Pauini Airport"
    ],
    "name:msa_x_preferred":[
        "Lapangan Terbang Pauini"
    ],
    "name:por_x_preferred":[
        "Aer\u00f3dromo Pauini"
    ],
    "name:ron_x_preferred":[
        "Aeroportul Pauini"
    ],
    "oa:elevation_ft":"397",
    "oa:type":"small_airport",
    "woe:hierarchy":{
        "country_id":23424768,
        "county_id":12578215,
        "planet_id":1,
        "state_id":2344847
    },
    "wof:name":"Aeroporto Pauini",
    "wof:placetype":"campus"
},
  "geometry": {"coordinates":[-67.028333,-7.7225],"type":"Point"}
}