{
  "type": "Feature",
  "properties": {
    "gn:admin1_code":"15",
    "gn:admin2_code":"3165305.0",
    "gn:asciiname":"Porteirinhas",
    "gn:country_code":"BR",
    "gn:dem":965,
    "gn:feature_class":"P",
    "gn:feature_code":"PPL",
    "gn:name":"Porteirinhas",
    "gn:population":0,
    "gn:timezone":"America/Sao_Paulo",
    "iso:country":"BR",
    "name:por_x_preferred":[
        "Porteirinhas"
    ],
    "wof:name":"Porteirinhas",
    "wof:placetype":"locality"
},
  "geometry": {"coordinates":[-44.46667,-21.71667],"type":"Point"}
}