{
  "type": "Feature",
  "properties": {
    "gn:admin1_code":"27",
    "gn:admin2_code":"3550605.0",
    "gn:asciiname":"Sitio Barracao",
    "gn:country_code":"BR",
    "gn:dem":881,
    "gn:feature_class":"P",
    "gn:feature_code":"PPL",
    "gn:name":"S\u00edtio Barrac\u00e3o",
    "gn:population":0,
    "gn:timezone":"America/Sao_Paulo",
    "iso:country":"BR",
    "name:por_x_preferred":[
        "S\u00edtio Barrac\u00e3o"
    ],
    "wof:name":"Sitio Barracao",
    "wof:placetype":"locality"
},
  "geometry": {"coordinates":[-47.17372,-23.62734],"type":"Point"}
}