{
  "type": "Feature",
  "properties": {
    "gn:admin1_code":"20",
    "gn:admin2_code":"2207207.0",
    "gn:asciiname":"Malhada de Cima",
    "gn:country_code":"BR",
    "gn:dem":488,
    "gn:feature_class":"P",
    "gn:feature_code":"PPL",
    "gn:name":"Malhada de Cima",
    "gn:population":0,
    "gn:timezone":"America/Fortaleza",
    "iso:country":"BR",
    "wof:name":"Malhada de Cima",
    "wof:placetype":"locality"
},
  "geometry": {"coordinates":[-40.81667,-7.43333],"type":"Point"}
}