{
  "type": "Feature",
  "properties": {
    "gn:admin1_code":"5.0",
    "gn:admin2_code":"2920205.0",
    "gn:asciiname":"Mandacaru",
    "gn:country_code":"BR",
    "gn:dem":480,
    "gn:feature_class":"P",
    "gn:feature_code":"PPL",
    "gn:name":"Mandacaru",
    "gn:population":0,
    "gn:timezone":"America/Bahia",
    "iso:country":"BR",
    "name:por_x_preferred":[
        "Mandacaru"
    ],
    "wof:name":"Mandacaru",
    "wof:placetype":"locality"
},
  "geometry": {"coordinates":[-43.76344,-14.554],"type":"Point"}
}