{
  "type": "Feature",
  "properties": {
    "gn:admin1_code":"23",
    "gn:admin2_code":"4305108.0",
    "gn:asciiname":"Sao Victor",
    "gn:country_code":"BR",
    "gn:dem":467,
    "gn:feature_class":"P",
    "gn:feature_code":"PPLL",
    "gn:name":"S\u00e3o Victor",
    "gn:population":0,
    "gn:timezone":"America/Sao_Paulo",
    "iso:country":"BR",
    "name:por_x_preferred":[
        "S\u00e3o Victor"
    ],
    "wof:name":"Sao Victor",
    "wof:placetype":"locality"
},
  "geometry": {"coordinates":[-51.1101,-29.2388],"type":"Point"}
}