{
  "type": "Feature",
  "properties": {
    "gn:admin1_code":"27",
    "gn:admin2_code":"3513009.0",
    "gn:asciiname":"Sitio Maca Oda",
    "gn:country_code":"BR",
    "gn:dem":915,
    "gn:feature_class":"P",
    "gn:feature_code":"PPL",
    "gn:name":"S\u00edtio Ma\u00e7a Oda",
    "gn:population":0,
    "gn:timezone":"America/Sao_Paulo",
    "iso:country":"BR",
    "name:por_x_preferred":[
        "S\u00edtio Ma\u00e7a Oda"
    ],
    "wof:name":"Sitio Maca Oda",
    "wof:placetype":"locality"
},
  "geometry": {"coordinates":[-47.05389,-23.69101],"type":"Point"}
}