{
  "type": "Feature",
  "properties": {
    "gn:admin1_code":"5",
    "gn:admin2_code":"2933406.0",
    "gn:asciiname":"Buriti",
    "gn:country_code":"BR",
    "gn:dem":561,
    "gn:feature_class":"P",
    "gn:feature_code":"PPL",
    "gn:name":"Buriti",
    "gn:population":0,
    "gn:timezone":"America/Bahia",
    "iso:country":"BR",
    "wof:name":"Buriti",
    "wof:placetype":"locality"
},
  "geometry": {"coordinates":[-41.13333,-12.11667],"type":"Point"}
}