{
  "type": "Feature",
  "properties": {
    "gn:admin1_code":"18.0",
    "gn:admin2_code":"4119202.0",
    "gn:asciiname":"Sitio Mococa",
    "gn:country_code":"BR",
    "gn:dem":811,
    "gn:feature_class":"P",
    "gn:feature_code":"PPL",
    "gn:name":"S\u00edtio Mococa",
    "gn:population":0,
    "gn:timezone":"America/Sao_Paulo",
    "iso:country":"BR",
    "name:por_x_preferred":[
        "S\u00edtio Mococa"
    ],
    "wof:name":"Sitio Mococa",
    "wof:placetype":"locality"
},
  "geometry": {"coordinates":[-50.0808,-23.89058],"type":"Point"}
}