{
  "type": "Feature",
  "properties": {
    "gn:admin1_code":"13",
    "gn:admin2_code":"2101707.0",
    "gn:asciiname":"Mangueira",
    "gn:country_code":"BR",
    "gn:dem":53,
    "gn:feature_class":"P",
    "gn:feature_code":"PPL",
    "gn:name":"Mangueira",
    "gn:population":0,
    "gn:timezone":"America/Fortaleza",
    "iso:country":"BR",
    "name:ita_x_preferred":[
        "Mangueira"
    ],
    "wof:name":"Mangueira",
    "wof:placetype":"locality"
},
  "geometry": {"coordinates":[-42.76528,-3.10917],"type":"Point"}
}