{
  "type": "Feature",
  "properties": {
    "gn:admin1_code":"18.0",
    "gn:admin2_code":"4111803.0",
    "gn:asciiname":"Sitio Jose Oliveira Campos",
    "gn:country_code":"BR",
    "gn:dem":459,
    "gn:feature_class":"P",
    "gn:feature_code":"PPL",
    "gn:name":"S\u00edtio Jos\u00e9 Oliveira Campos",
    "gn:population":0,
    "gn:timezone":"America/Sao_Paulo",
    "iso:country":"BR",
    "name:por_x_preferred":[
        "S\u00edtio Jos\u00e9 Oliveira Campos"
    ],
    "wof:name":"Sitio Jose Oliveira Campos",
    "wof:placetype":"locality"
},
  "geometry": {"coordinates":[-49.87649,-23.14665],"type":"Point"}
}