{
  "type": "Feature",
  "properties": {
    "gn:admin1_code":"18.0",
    "gn:admin2_code":"4101200.0",
    "gn:asciiname":"Sitio Cachoeira",
    "gn:country_code":"BR",
    "gn:dem":15,
    "gn:feature_class":"P",
    "gn:feature_code":"PPL",
    "gn:name":"S\u00edtio Cachoeira",
    "gn:population":0,
    "gn:timezone":"America/Sao_Paulo",
    "iso:country":"BR",
    "name:por_x_preferred":[
        "S\u00edtio Cachoeira"
    ],
    "wof:name":"Sitio Cachoeira",
    "wof:placetype":"locality"
},
  "geometry": {"coordinates":[-48.7402,-25.2653],"type":"Point"}
}