{
  "type": "Feature",
  "properties": {
    "gn:admin1_code":"18.0",
    "gn:admin2_code":"4116208.0",
    "gn:asciiname":"Sitio Rio Mata",
    "gn:country_code":"BR",
    "gn:dem":16,
    "gn:feature_class":"P",
    "gn:feature_code":"PPL",
    "gn:name":"S\u00edtio Rio Mata",
    "gn:population":0,
    "gn:timezone":"America/Sao_Paulo",
    "iso:country":"BR",
    "name:por_x_preferred":[
        "S\u00edtio Rio Mata"
    ],
    "wof:name":"Sitio Rio Mata",
    "wof:placetype":"locality"
},
  "geometry": {"coordinates":[-48.8107,-25.5106],"type":"Point"}
}