{
  "type": "Feature",
  "properties": {
    "gn:admin1_code":"06",
    "gn:admin2_code":"2301109.0",
    "gn:asciiname":"Tanque do Lima",
    "gn:country_code":"BR",
    "gn:dem":18,
    "gn:feature_class":"P",
    "gn:feature_code":"PPL",
    "gn:name":"Tanque do Lima",
    "gn:population":0,
    "gn:timezone":"America/Fortaleza",
    "iso:country":"BR",
    "wof:name":"Tanque do Lima",
    "wof:placetype":"locality"
},
  "geometry": {"coordinates":[-37.39417,-4.80639],"type":"Point"}
}