{
  "type": "Feature",
  "properties": {
    "gn:admin1_code":"4",
    "gn:admin2_code":"1300409.0",
    "gn:asciiname":"Carvoeiro",
    "gn:country_code":"BR",
    "gn:dem":30,
    "gn:feature_class":"P",
    "gn:feature_code":"PPL",
    "gn:name":"Carvoeiro",
    "gn:population":0,
    "gn:timezone":"America/Manaus",
    "iso:country":"BR",
    "name:ceb_x_preferred":[
        "Carvoeiro"
    ],
    "name:deu_x_preferred":[
        "Carvoeiro"
    ],
    "name:nld_x_preferred":[
        "Carvoeiro"
    ],
    "name:por_x_preferred":[
        "Carvoeiro"
    ],
    "name:rus_x_preferred":[
        "\u041a\u0430\u0440\u0432\u043e\u044d\u0439\u0440\u0430"
    ],
    "name:tur_x_preferred":[
        "Carvoeiro"
    ],
    "name:und_x_variant":[
        "Carvoeira"
    ],
    "wof:name":"Carvoeiro",
    "wof:placetype":"locality"
},
  "geometry": {"coordinates":[-61.97493000000001,-1.39881],"type":"Point"}
}