{
  "type": "Feature",
  "properties": {
    "gn:admin1_code":"4",
    "gn:admin2_code":"1300409.0",
    "gn:asciiname":"Carvoeiro",
    "gn:country_code":"BR",
    "gn:dem":30,
    "gn:feature_class":"P",
    "gn:feature_code":"PPL",
    "gn:name":"Carvoeiro",
    "gn:population":0,
    "gn:timezone":"America/Manaus",
    "iso:country":"BR",
    "name:und_x_variant":[
        "Carvoeira",
        "Carvoeiro"
    ],
    "wof:name":"Carvoeiro",
    "wof:placetype":"locality"
},
  "geometry": {"coordinates":[-61.97493000000001,-1.39881],"type":"Point"}
}