{
  "type": "Feature",
  "properties": {
    "gn:admin1_code":"27",
    "gn:admin2_code":"3504206.0",
    "gn:asciiname":"Antonina",
    "gn:cc2":"BR",
    "gn:country_code":"BR",
    "gn:dem":433,
    "gn:feature_class":"P",
    "gn:feature_code":"PPL",
    "gn:name":"Antonina",
    "gn:population":0,
    "gn:timezone":"America/Sao_Paulo",
    "iso:country":"BR",
    "name:und_x_variant":[
        "Arouca",
        "Villa Antonina",
        "Antonina"
    ],
    "wof:name":"Antonina",
    "wof:placetype":"locality"
},
  "geometry": {"coordinates":[-50.61667,-20.56667],"type":"Point"}
}