{
  "type": "Feature",
  "properties": {
    "gn:admin1_code":"27",
    "gn:admin2_code":"3504206.0",
    "gn:asciiname":"Antonina",
    "gn:cc2":"BR",
    "gn:country_code":"BR",
    "gn:dem":433,
    "gn:feature_class":"P",
    "gn:feature_code":"PPL",
    "gn:name":"Antonina",
    "gn:population":0,
    "gn:timezone":"America/Sao_Paulo",
    "iso:country":"BR",
    "name:bre_x_preferred":[
        "Antonina"
    ],
    "name:cat_x_preferred":[
        "Antonina"
    ],
    "name:ceb_x_preferred":[
        "Antonina"
    ],
    "name:deu_x_preferred":[
        "Antonina"
    ],
    "name:fra_x_preferred":[
        "Antonina"
    ],
    "name:ita_x_preferred":[
        "Antonina"
    ],
    "name:pol_x_preferred":[
        "Antonina"
    ],
    "name:por_x_preferred":[
        "Antonina"
    ],
    "name:rus_x_preferred":[
        "\u0410\u043d\u0442\u043e\u043d\u0438\u043d\u0430"
    ],
    "name:spa_x_preferred":[
        "Antonina"
    ],
    "name:swe_x_preferred":[
        "Antonina"
    ],
    "name:und_x_variant":[
        "Arouca",
        "Villa Antonina"
    ],
    "wof:name":"Antonina",
    "wof:placetype":"locality"
},
  "geometry": {"coordinates":[-50.61667,-20.56667],"type":"Point"}
}