{
  "type": "Feature",
  "properties": {
    "gn:admin1_code":"18.0",
    "gn:admin2_code":"4104006.0",
    "gn:asciiname":"Sitio Julio Ribeiro dos Santos",
    "gn:country_code":"BR",
    "gn:dem":702,
    "gn:feature_class":"P",
    "gn:feature_code":"PPL",
    "gn:name":"S\u00edtio J\u00falio Ribeiro dos Santos",
    "gn:population":0,
    "gn:timezone":"America/Sao_Paulo",
    "iso:country":"BR",
    "name:por_x_preferred":[
        "S\u00edtio J\u00falio Ribeiro dos Santos"
    ],
    "wof:name":"Sitio Julio Ribeiro dos Santos",
    "wof:placetype":"locality"
},
  "geometry": {"coordinates":[-48.8295,-25.10076],"type":"Point"}
}