{
  "type": "Feature",
  "properties": {
    "gn:admin1_code":"20",
    "gn:admin2_code":"2205599.0",
    "gn:asciiname":"Urucu",
    "gn:country_code":"BR",
    "gn:dem":542,
    "gn:feature_class":"P",
    "gn:feature_code":"PPL",
    "gn:name":"Uru\u00e7u",
    "gn:population":0,
    "gn:timezone":"America/Fortaleza",
    "iso:country":"BR",
    "wof:name":"Urucu",
    "wof:placetype":"locality"
},
  "geometry": {"coordinates":[-41.46667,-6.51667],"type":"Point"}
}