{
  "type": "Feature",
  "properties": {
    "gn:admin1_code":"27",
    "gn:admin2_code":"3504107.0",
    "gn:asciiname":"Sitio Tres Pontes",
    "gn:country_code":"BR",
    "gn:dem":823,
    "gn:feature_class":"P",
    "gn:feature_code":"PPL",
    "gn:name":"S\u00edtio Tr\u00eas Pontes",
    "gn:population":0,
    "gn:timezone":"America/Sao_Paulo",
    "iso:country":"BR",
    "name:por_x_preferred":[
        "S\u00edtio Tr\u00eas Pontes"
    ],
    "wof:name":"Sitio Tres Pontes",
    "wof:placetype":"locality"
},
  "geometry": {"coordinates":[-46.57083,-23.17944],"type":"Point"}
}