{
  "type": "Feature",
  "properties": {
    "gn:admin1_code":"14",
    "gn:admin2_code":"5103452.0",
    "gn:asciiname":"Palmital Grande",
    "gn:country_code":"BR",
    "gn:dem":178,
    "gn:feature_class":"P",
    "gn:feature_code":"PPL",
    "gn:name":"Palmital Grande",
    "gn:population":0,
    "gn:timezone":"America/Cuiaba",
    "iso:country":"BR",
    "wof:name":"Palmital Grande",
    "wof:placetype":"locality"
},
  "geometry": {"coordinates":[-57.03333000000001,-14.85],"type":"Point"}
}