{
  "type": "Feature",
  "properties": {
    "gn:admin1_code":"4",
    "gn:admin2_code":"1301704.0",
    "gn:asciiname":"Trapiche",
    "gn:country_code":"BR",
    "gn:dem":57,
    "gn:feature_class":"P",
    "gn:feature_code":"PPL",
    "gn:name":"Trapiche",
    "gn:population":0,
    "gn:timezone":"America/Manaus",
    "iso:country":"BR",
    "name:cat_x_preferred":[
        "Trapig"
    ],
    "name:fra_x_preferred":[
        "Trapiche"
    ],
    "name:por_x_preferred":[
        "Trapiche"
    ],
    "name:spa_x_preferred":[
        "Trapiche"
    ],
    "wof:name":"Trapiche",
    "wof:placetype":"locality"
},
  "geometry": {"coordinates":[-62.98333,-7.51667],"type":"Point"}
}