{
  "type": "Feature",
  "properties": {
    "gn:admin1_code":"21",
    "gn:admin2_code":"3300308.0",
    "gn:asciiname":"Santana da Barra",
    "gn:country_code":"BR",
    "gn:dem":387,
    "gn:feature_class":"P",
    "gn:feature_code":"PPL",
    "gn:name":"Santana da Barra",
    "gn:population":0,
    "gn:timezone":"America/Sao_Paulo",
    "iso:country":"BR",
    "name:por_x_preferred":[
        "Santana da Barra"
    ],
    "wof:name":"Santana da Barra",
    "wof:placetype":"locality"
},
  "geometry": {"coordinates":[-43.805,-22.51611],"type":"Point"}
}