{
  "type": "Feature",
  "properties": {
    "gn:admin1_code":"18.0",
    "gn:admin2_code":"4102703.0",
    "gn:asciiname":"Sitio Santo Andre",
    "gn:country_code":"BR",
    "gn:dem":456,
    "gn:feature_class":"P",
    "gn:feature_code":"PPL",
    "gn:name":"S\u00edtio Santo Andr\u00e9",
    "gn:population":0,
    "gn:timezone":"America/Sao_Paulo",
    "iso:country":"BR",
    "name:por_x_preferred":[
        "S\u00edtio Santo Andr\u00e9"
    ],
    "wof:name":"Sitio Santo Andre",
    "wof:placetype":"locality"
},
  "geometry": {"coordinates":[-50.1207,-23.1065],"type":"Point"}
}