{
  "type": "Feature",
  "properties": {
    "gn:admin1_code":"06",
    "gn:admin2_code":"2311900.0",
    "gn:asciiname":"Tapera",
    "gn:country_code":"BR",
    "gn:dem":333,
    "gn:feature_class":"P",
    "gn:feature_code":"PPL",
    "gn:name":"Tapera",
    "gn:population":0,
    "gn:timezone":"America/Fortaleza",
    "iso:country":"BR",
    "wof:name":"Tapera",
    "wof:placetype":"locality"
},
  "geometry": {"coordinates":[-39.95,-6.48333],"type":"Point"}
}