{
  "type": "Feature",
  "properties": {
    "gn:admin1_code":"14.0",
    "gn:admin2_code":"5106182.0",
    "gn:asciiname":"Areia Branca",
    "gn:country_code":"BR",
    "gn:dem":618,
    "gn:feature_class":"P",
    "gn:feature_code":"PPL",
    "gn:name":"Areia Branca",
    "gn:population":0,
    "gn:timezone":"America/Cuiaba",
    "iso:country":"BR",
    "wof:name":"Areia Branca",
    "wof:placetype":"locality"
},
  "geometry": {"coordinates":[-59.45278,-14.20727],"type":"Point"}
}