{
  "type": "Feature",
  "properties": {
    "gn:admin1_code":"14.0",
    "gn:admin2_code":"5106182.0",
    "gn:asciiname":"Areia Branca",
    "gn:country_code":"BR",
    "gn:dem":618,
    "gn:feature_class":"P",
    "gn:feature_code":"PPL",
    "gn:name":"Areia Branca",
    "gn:population":0,
    "gn:timezone":"America/Cuiaba",
    "iso:country":"BR",
    "name:ceb_x_preferred":[
        "Areia Branca"
    ],
    "name:deu_x_preferred":[
        "Areia Branca"
    ],
    "name:fra_x_preferred":[
        "Areia Branca"
    ],
    "name:ita_x_preferred":[
        "Areia Branca"
    ],
    "name:nld_x_preferred":[
        "Areia Branca"
    ],
    "name:nor_x_preferred":[
        "Areia Branca"
    ],
    "name:por_x_preferred":[
        "Areia Branca"
    ],
    "name:rus_x_preferred":[
        "\u0410\u0440\u0435\u044f-\u0411\u0440\u0430\u043d\u043a\u0430"
    ],
    "name:spa_x_preferred":[
        "Areia Branca"
    ],
    "name:swe_x_preferred":[
        "Areia Branca"
    ],
    "name:vol_x_preferred":[
        "Areia Branca"
    ],
    "wof:name":"Areia Branca",
    "wof:placetype":"locality"
},
  "geometry": {"coordinates":[-59.45278,-14.20727],"type":"Point"}
}