{
  "type": "Feature",
  "properties": {
    "gn:admin1_code":"15",
    "gn:admin2_code":"3136801.0",
    "gn:asciiname":"Ribeirao",
    "gn:country_code":"BR",
    "gn:dem":661,
    "gn:feature_class":"P",
    "gn:feature_code":"PPL",
    "gn:name":"Ribeir\u00e3o",
    "gn:population":0,
    "gn:timezone":"America/Sao_Paulo",
    "iso:country":"BR",
    "name:por_x_preferred":[
        "Ribeir\u00e3o"
    ],
    "wof:name":"Ribeirao",
    "wof:placetype":"locality"
},
  "geometry": {"coordinates":[-43.65,-16.78333],"type":"Point"}
}