{
  "type": "Feature",
  "properties": {
    "gn:admin1_code":"11",
    "gn:admin2_code":"5007109.0",
    "gn:asciiname":"Retiro dos Cochos",
    "gn:country_code":"BR",
    "gn:dem":434,
    "gn:feature_class":"P",
    "gn:feature_code":"PPL",
    "gn:name":"Retiro dos Cochos",
    "gn:population":0,
    "gn:timezone":"America/Campo_Grande",
    "iso:country":"BR",
    "wof:name":"Retiro dos Cochos",
    "wof:placetype":"locality"
},
  "geometry": {"coordinates":[-53.25,-20.81667],"type":"Point"}
}