{
  "type": "Feature",
  "properties": {
    "gn:admin1_code":"18.0",
    "gn:admin2_code":"4112306.0",
    "gn:asciiname":"Sitio Miguel Nalevaiko",
    "gn:country_code":"BR",
    "gn:dem":606,
    "gn:feature_class":"P",
    "gn:feature_code":"PPL",
    "gn:name":"S\u00edtio Miguel Nalevaiko",
    "gn:population":0,
    "gn:timezone":"America/Sao_Paulo",
    "iso:country":"BR",
    "name:por_x_preferred":[
        "S\u00edtio Miguel Nalevaiko"
    ],
    "wof:name":"Sitio Miguel Nalevaiko",
    "wof:placetype":"locality"
},
  "geometry": {"coordinates":[-50.12315,-23.7828],"type":"Point"}
}