{
  "type": "Feature",
  "properties": {
    "gn:admin1_code":"20",
    "gn:admin2_code":"2204204.0",
    "gn:asciiname":"Pereiros",
    "gn:cc2":"BR",
    "gn:country_code":"BR",
    "gn:dem":363,
    "gn:feature_class":"P",
    "gn:feature_code":"PPL",
    "gn:name":"Pereiros",
    "gn:population":0,
    "gn:timezone":"America/Fortaleza",
    "iso:country":"BR",
    "name:und_x_variant":[
        "Poreiros",
        "Pereiros"
    ],
    "wof:name":"Pereiros",
    "wof:placetype":"locality"
},
  "geometry": {"coordinates":[-41.11667,-6.96667],"type":"Point"}
}