{
  "type": "Feature",
  "properties": {
    "gn:admin1_code":"18.0",
    "gn:admin2_code":"4113205.0",
    "gn:asciiname":"Sitio Juvencio Kolasso",
    "gn:country_code":"BR",
    "gn:dem":882,
    "gn:feature_class":"P",
    "gn:feature_code":"PPL",
    "gn:name":"S\u00edtio Juv\u00eancio Kolasso",
    "gn:population":0,
    "gn:timezone":"America/Sao_Paulo",
    "iso:country":"BR",
    "name:por_x_preferred":[
        "S\u00edtio Juv\u00eancio Kolasso"
    ],
    "wof:name":"Sitio Juvencio Kolasso",
    "wof:placetype":"locality"
},
  "geometry": {"coordinates":[-49.91653,-25.82985],"type":"Point"}
}