{
  "type": "Feature",
  "properties": {
    "gn:admin1_code":"4",
    "gn:admin2_code":"1302702.0",
    "gn:asciiname":"Pau Queimado",
    "gn:country_code":"BR",
    "gn:dem":75,
    "gn:feature_class":"P",
    "gn:feature_code":"PPL",
    "gn:name":"Pau Queimado",
    "gn:population":0,
    "gn:timezone":"America/Manaus",
    "iso:country":"BR",
    "wof:name":"Pau Queimado",
    "wof:placetype":"locality"
},
  "geometry": {"coordinates":[-61.76667,-6.36667],"type":"Point"}
}