{
  "type": "Feature",
  "properties": {
    "gn:admin1_code":"14",
    "gn:admin2_code":"5106224.0",
    "gn:asciiname":"Jaudilandia",
    "gn:country_code":"BR",
    "gn:dem":441,
    "gn:feature_class":"P",
    "gn:feature_code":"PPL",
    "gn:name":"Jaudil\u00e2ndia",
    "gn:population":0,
    "gn:timezone":"America/Cuiaba",
    "iso:country":"BR",
    "wof:name":"Jaudilandia",
    "wof:placetype":"locality"
},
  "geometry": {"coordinates":[-56.06667,-13.98333],"type":"Point"}
}