{
  "type": "Feature",
  "properties": {
    "gn:admin1_code":"23.0",
    "gn:admin2_code":"4302303.0",
    "gn:asciiname":"Rincao Bela Vista",
    "gn:country_code":"BR",
    "gn:dem":1129,
    "gn:feature_class":"P",
    "gn:feature_code":"PPL",
    "gn:name":"Rinc\u00e3o Bela Vista",
    "gn:population":0,
    "gn:timezone":"America/Sao_Paulo",
    "iso:country":"BR",
    "wof:name":"Rincao Bela Vista",
    "wof:placetype":"locality"
},
  "geometry": {"coordinates":[-50.22054,-28.7428],"type":"Point"}
}