{
  "type": "Feature",
  "properties": {
    "gn:admin1_code":"11",
    "gn:admin2_code":"5003207.0",
    "gn:asciiname":"Sao Vicente",
    "gn:cc2":"BR",
    "gn:country_code":"BR",
    "gn:dem":152,
    "gn:feature_class":"P",
    "gn:feature_code":"PPL",
    "gn:name":"S\u00e3o Vicente",
    "gn:population":0,
    "gn:timezone":"America/Campo_Grande",
    "iso:country":"BR",
    "name:und_x_variant":[
        "Tapera do Vicente",
        "S\u00e3o Vicente"
    ],
    "wof:name":"Sao Vicente",
    "wof:placetype":"locality"
},
  "geometry": {"coordinates":[-55.66667,-18.31667],"type":"Point"}
}