{
  "type": "Feature",
  "properties": {
    "gn:admin1_code":"03",
    "gn:admin2_code":"1600501.0",
    "gn:asciiname":"Jenipapo",
    "gn:country_code":"BR",
    "gn:dem":16,
    "gn:feature_class":"P",
    "gn:feature_code":"PPL",
    "gn:name":"Jenipapo",
    "gn:population":0,
    "gn:timezone":"America/Belem",
    "iso:country":"BR",
    "wof:name":"Jenipapo",
    "wof:placetype":"locality"
},
  "geometry": {"coordinates":[-51.192,3.79949],"type":"Point"}
}