{
  "type": "Feature",
  "properties": {
    "gn:admin1_code":"23",
    "gn:admin2_code":"4309308.0",
    "gn:asciiname":"Vila Elza",
    "gn:cc2":"BR",
    "gn:country_code":"BR",
    "gn:dem":8,
    "gn:feature_class":"P",
    "gn:feature_code":"PPL",
    "gn:name":"Vila Elza",
    "gn:population":0,
    "gn:timezone":"America/Sao_Paulo",
    "iso:country":"BR",
    "name:und_x_variant":[
        "Vila Elsa",
        "Vila Elza"
    ],
    "wof:name":"Vila Elza",
    "wof:placetype":"locality"
},
  "geometry": {"coordinates":[-51.31667,-30.13333],"type":"Point"}
}