{
  "type": "Feature",
  "properties": {
    "gn:admin1_code":"14",
    "gn:admin2_code":"5105903.0",
    "gn:asciiname":"Sao Jose",
    "gn:country_code":"BR",
    "gn:dem":253,
    "gn:feature_class":"P",
    "gn:feature_code":"PPL",
    "gn:name":"S\u00e3o Jos\u00e9",
    "gn:population":0,
    "gn:timezone":"America/Cuiaba",
    "iso:country":"BR",
    "wof:name":"Sao Jose",
    "wof:placetype":"locality"
},
  "geometry": {"coordinates":[-55.66667,-14.45],"type":"Point"}
}