{
  "type": "Feature",
  "properties": {
    "gn:admin1_code":"27",
    "gn:admin2_code":"3518305.0",
    "gn:asciiname":"Stio Brejo Seco",
    "gn:country_code":"BR",
    "gn:dem":575,
    "gn:feature_class":"P",
    "gn:feature_code":"PPL",
    "gn:name":"Stio Brejo Seco",
    "gn:population":0,
    "gn:timezone":"America/Sao_Paulo",
    "iso:country":"BR",
    "name:por_x_preferred":[
        "Stio Brejo Seco"
    ],
    "wof:name":"Stio Brejo Seco",
    "wof:placetype":"locality"
},
  "geometry": {"coordinates":[-46.0485,-23.3973],"type":"Point"}
}