{
  "type": "Feature",
  "properties": {
    "gn:admin1_code":"11",
    "gn:admin2_code":"5001102.0",
    "gn:asciiname":"Retiro Novo",
    "gn:country_code":"BR",
    "gn:dem":115,
    "gn:feature_class":"P",
    "gn:feature_code":"PPL",
    "gn:name":"Retiro Novo",
    "gn:population":0,
    "gn:timezone":"America/Campo_Grande",
    "iso:country":"BR",
    "wof:name":"Retiro Novo",
    "wof:placetype":"locality"
},
  "geometry": {"coordinates":[-56.26667,-19.83333],"type":"Point"}
}