{
  "type": "Feature",
  "properties": {
    "gn:admin1_code":"26",
    "gn:admin2_code":"4210100.0",
    "gn:asciiname":"Sitio Jose R. Ianoski",
    "gn:country_code":"BR",
    "gn:dem":855,
    "gn:feature_class":"P",
    "gn:feature_code":"PPL",
    "gn:name":"S\u00edtio Jos\u00e9 R. Ianoski",
    "gn:population":0,
    "gn:timezone":"America/Sao_Paulo",
    "iso:country":"BR",
    "name:por_x_preferred":[
        "S\u00edtio Jos\u00e9 R. Ianoski"
    ],
    "wof:name":"Sitio Jose R. Ianoski",
    "wof:placetype":"locality"
},
  "geometry": {"coordinates":[-49.9557,-26.1987],"type":"Point"}
}