{
  "type": "Feature",
  "properties": {
    "gn:admin1_code":"8",
    "gn:admin2_code":"3205176.0",
    "gn:asciiname":"Valerio",
    "gn:country_code":"BR",
    "gn:dem":188,
    "gn:feature_class":"P",
    "gn:feature_code":"PPL",
    "gn:name":"Val\u00e9rio",
    "gn:population":0,
    "gn:timezone":"America/Sao_Paulo",
    "iso:country":"BR",
    "name:deu_x_preferred":[
        "Valerio"
    ],
    "name:ita_x_preferred":[
        "Valerio"
    ],
    "name:por_x_preferred":[
        "Val\u00e9rio"
    ],
    "name:rus_x_preferred":[
        "\u0412\u0430\u043b\u0435\u0440\u0438\u043e"
    ],
    "name:spa_x_preferred":[
        "Valerio"
    ],
    "name:srp_x_preferred":[
        "Valerio"
    ],
    "wof:name":"Valerio",
    "wof:placetype":"locality"
},
  "geometry": {"coordinates":[-40.36667,-18.98333],"type":"Point"}
}