{
  "type": "Feature",
  "properties": {
    "gn:admin1_code":"1",
    "gn:admin2_code":"1200054.0",
    "gn:asciiname":"Reserva Extrema",
    "gn:cc2":"BR",
    "gn:country_code":"BR",
    "gn:dem":257,
    "gn:feature_class":"P",
    "gn:feature_code":"PPL",
    "gn:name":"Reserva Extrema",
    "gn:population":0,
    "gn:timezone":"America/Rio_Branco",
    "iso:country":"BR",
    "name:und_x_variant":[
        "Extrema",
        "Guanabara",
        "Reserva Estrema",
        "Estrema",
        "Reserva Extrema"
    ],
    "wof:name":"Reserva Extrema",
    "wof:placetype":"locality"
},
  "geometry": {"coordinates":[-70.09999999999999,-10.66667],"type":"Point"}
}