{
  "type": "Feature",
  "properties": {
    "gn:admin1_code":"18",
    "gn:admin2_code":"4119103.0",
    "gn:asciiname":"Sitio Leopoldo Filho",
    "gn:country_code":"BR",
    "gn:dem":915,
    "gn:feature_class":"P",
    "gn:feature_code":"PPL",
    "gn:name":"S\u00edtio Leopoldo Filho",
    "gn:population":0,
    "gn:timezone":"America/Sao_Paulo",
    "iso:country":"BR",
    "name:por_x_preferred":[
        "S\u00edtio Leopoldo Filho"
    ],
    "wof:name":"Sitio Leopoldo Filho",
    "wof:placetype":"locality"
},
  "geometry": {"coordinates":[-49.50324000000001,-26.09676],"type":"Point"}
}