{
  "type": "Feature",
  "properties": {
    "gn:admin1_code":"21",
    "gn:admin2_code":"3304557.0",
    "gn:asciiname":"Vardem Pequena",
    "gn:country_code":"BR",
    "gn:dem":5,
    "gn:feature_class":"P",
    "gn:feature_code":"PPL",
    "gn:name":"Vardem Pequena",
    "gn:population":0,
    "gn:timezone":"America/Sao_Paulo",
    "iso:country":"BR",
    "name:por_x_preferred":[
        "Vardem Pequena"
    ],
    "wof:name":"Vardem Pequena",
    "wof:placetype":"locality"
},
  "geometry": {"coordinates":[-43.4618,-22.98941],"type":"Point"}
}