{
  "type": "Feature",
  "properties": {
    "gn:admin1_code":"20",
    "gn:admin2_code":"2200509.0",
    "gn:asciiname":"Carao",
    "gn:country_code":"BR",
    "gn:dem":107,
    "gn:feature_class":"P",
    "gn:feature_code":"PPL",
    "gn:name":"Carao",
    "gn:population":0,
    "gn:timezone":"America/Fortaleza",
    "iso:country":"BR",
    "wof:name":"Carao",
    "wof:placetype":"locality"
},
  "geometry": {"coordinates":[-42.86667,-6.45],"type":"Point"}
}