{
  "type": "Feature",
  "properties": {
    "gn:admin1_code":"27.0",
    "gn:admin2_code":"3518800.0",
    "gn:asciiname":"Jardim Acacio",
    "gn:country_code":"BR",
    "gn:dem":795,
    "gn:feature_class":"P",
    "gn:feature_code":"PPL",
    "gn:name":"Jardim Ac\u00e1cio",
    "gn:population":0,
    "gn:timezone":"America/Sao_Paulo",
    "iso:country":"BR",
    "name:por_x_preferred":[
        "Jardim Ac\u00e1cio"
    ],
    "wof:name":"Jardim Acacio",
    "wof:placetype":"locality"
},
  "geometry": {"coordinates":[-46.51078,-23.41387000000001],"type":"Point"}
}