{
  "type": "Feature",
  "properties": {
    "gn:admin1_code":"26",
    "gn:admin2_code":"4211850.0",
    "gn:asciiname":"Ouro Verde",
    "gn:country_code":"BR",
    "gn:dem":757,
    "gn:feature_class":"P",
    "gn:feature_code":"PPL",
    "gn:name":"Ouro Verde",
    "gn:population":0,
    "gn:timezone":"America/Sao_Paulo",
    "iso:country":"BR",
    "wof:name":"Ouro Verde",
    "wof:placetype":"locality"
},
  "geometry": {"coordinates":[-52.31194,-26.69444],"type":"Point"}
}