{
  "type": "Feature",
  "properties": {
    "gn:gn_country":"BR",
    "gn:gn_fcode":"PPLL",
    "gn:gn_pop":0,
    "iso:country":"BR",
    "qs_pg:aaroncc":"BR",
    "qs_pg:gn_country":"BR",
    "qs_pg:gn_fcode":"PPLL",
    "qs_pg:gn_pop":0,
    "qs_pg:name":"Parque Meia Lua",
    "qs_pg:name_adm0":"Brasil",
    "qs_pg:name_adm1":"S\u00e3o Paulo",
    "qs_pg:photos":6,
    "qs_pg:photos_1k":1,
    "qs_pg:photos_9k":1,
    "qs_pg:photos_9r":1,
    "qs_pg:photos_all":6,
    "qs_pg:photos_sr":1,
    "qs_pg:pop_sr":0,
    "qs_pg:qs_pg_placetype":"neighbourhood",
    "qs_pg:qs_pg_placetype_gp":"Suburb",
    "qs_pg:woe_adm0":23424768,
    "woe:adm0_id":23424768,
    "woe:name_adm0":"Brasil",
    "woe:name_adm1":"S\u00e3o Paulo",
    "woe:placetype":"Suburb",
    "wof:name":"Parque Meia Lua",
    "wof:placetype":"neighbourhood"
},
  "geometry": {"coordinates":[-45.96222,-23.26167],"type":"Point"}
}