{
  "type": "Feature",
  "properties": {
    "gn:admin1_code":"15",
    "gn:admin2_code":"3135803.0",
    "gn:asciiname":"Guarani",
    "gn:country_code":"BR",
    "gn:dem":195,
    "gn:feature_class":"P",
    "gn:feature_code":"PPL",
    "gn:name":"Guarani",
    "gn:population":0,
    "gn:timezone":"America/Sao_Paulo",
    "iso:country":"BR",
    "name:bel_x_preferred":[
        "\u0413\u0443\u0430\u0440\u0430\u043d\u0456"
    ],
    "name:ceb_x_preferred":[
        "Guarani"
    ],
    "name:deu_x_preferred":[
        "Guarani"
    ],
    "name:eus_x_preferred":[
        "Guarani"
    ],
    "name:fra_x_preferred":[
        "Guarani"
    ],
    "name:heb_x_preferred":[
        "\u05d2\u05d5\u05d0\u05e8\u05e0\u05d9"
    ],
    "name:hun_x_preferred":[
        "Guarani"
    ],
    "name:ita_x_preferred":[
        "Guarani"
    ],
    "name:jpn_x_preferred":[
        "\u30b0\u30a2\u30e9\u30cb\u30fc"
    ],
    "name:kat_x_preferred":[
        "\u10d2\u10e3\u10d0\u10e0\u10d0\u10dc\u10d8"
    ],
    "name:kor_x_preferred":[
        "\uacfc\ub77c\ub2c8"
    ],
    "name:nor_x_preferred":[
        "Guarani"
    ],
    "name:oss_x_preferred":[
        "\u0413\u0443\u0430\u0440\u0430\u043d\u0438"
    ],
    "name:por_x_preferred":[
        "Guarani"
    ],
    "name:ron_x_preferred":[
        "Guarani"
    ],
    "name:rus_x_preferred":[
        "\u0413\u0443\u0430\u0440\u0430\u043d\u0438"
    ],
    "name:sco_x_preferred":[
        "Guarani"
    ],
    "name:srp_x_preferred":[
        "\u0413\u0432\u0430\u0440\u0430\u043d\u0438"
    ],
    "name:swe_x_preferred":[
        "Guarani"
    ],
    "name:ukr_x_preferred":[
        "\u0413\u0443\u0430\u0440\u0430\u043d\u0456"
    ],
    "name:vie_x_preferred":[
        "Guarani"
    ],
    "name:zho_x_preferred":[
        "\u74dc\u62c9\u5c3c"
    ],
    "wof:name":"Guarani",
    "wof:placetype":"locality"
},
  "geometry": {"coordinates":[-40.80653,-16.30138],"type":"Point"}
}