{
  "type": "Feature",
  "properties": {
    "gn:admin1_code":"18.0",
    "gn:admin2_code":"4117214.0",
    "gn:asciiname":"Sitio Luiz B. da Silva",
    "gn:country_code":"BR",
    "gn:dem":765,
    "gn:feature_class":"P",
    "gn:feature_code":"PPL",
    "gn:name":"S\u00edtio Luiz B. da Silva",
    "gn:population":0,
    "gn:timezone":"America/Sao_Paulo",
    "iso:country":"BR",
    "name:por_x_preferred":[
        "S\u00edtio Luiz B. da Silva"
    ],
    "wof:name":"Sitio Luiz B. da Silva",
    "wof:placetype":"locality"
},
  "geometry": {"coordinates":[-50.69708,-23.58937],"type":"Point"}
}