{
  "type": "Feature",
  "properties": {
    "gn:admin1_code":"15",
    "gn:admin2_code":"3112000.0",
    "gn:asciiname":"Urias Alvarenga",
    "gn:country_code":"BR",
    "gn:dem":873,
    "gn:feature_class":"P",
    "gn:feature_code":"PPL",
    "gn:name":"Urias Alvarenga",
    "gn:population":0,
    "gn:timezone":"America/Sao_Paulo",
    "iso:country":"BR",
    "name:por_x_preferred":[
        "Urias Alvarenga"
    ],
    "wof:name":"Urias Alvarenga",
    "wof:placetype":"locality"
},
  "geometry": {"coordinates":[-45.38333,-20.83333],"type":"Point"}
}