{
  "type": "Feature",
  "properties": {
    "gn:admin1_code":"15",
    "gn:admin2_code":"3170206.0",
    "gn:asciiname":"Bom Jardim",
    "gn:country_code":"BR",
    "gn:dem":809,
    "gn:feature_class":"P",
    "gn:feature_code":"PPL",
    "gn:name":"Bom Jardim",
    "gn:population":0,
    "gn:timezone":"America/Sao_Paulo",
    "iso:country":"BR",
    "name:ceb_x_preferred":[
        "Bom Jardim"
    ],
    "name:deu_x_preferred":[
        "Bom Jardim"
    ],
    "name:fra_x_preferred":[
        "Bom Jardim"
    ],
    "name:ita_x_preferred":[
        "Bom Jardim"
    ],
    "name:nld_x_preferred":[
        "Bom Jardim"
    ],
    "name:nor_x_preferred":[
        "Bom Jardim"
    ],
    "name:por_x_preferred":[
        "Bom Jardim"
    ],
    "name:swe_x_preferred":[
        "Bom Jardim"
    ],
    "name:vol_x_preferred":[
        "Bom Jardim"
    ],
    "wof:name":"Bom Jardim",
    "wof:placetype":"locality"
},
  "geometry": {"coordinates":[-48.26667,-19.01667],"type":"Point"}
}