{
  "type": "Feature",
  "properties": {
    "gn:admin1_code":"17",
    "gn:admin2_code":"2510402.0",
    "gn:asciiname":"Cabeca de Boi",
    "gn:country_code":"BR",
    "gn:dem":275,
    "gn:feature_class":"P",
    "gn:feature_code":"PPL",
    "gn:name":"Cabe\u00e7a de Boi",
    "gn:population":0,
    "gn:timezone":"America/Fortaleza",
    "iso:country":"BR",
    "wof:name":"Cabeca de Boi",
    "wof:placetype":"locality"
},
  "geometry": {"coordinates":[-37.78333,-7.26667],"type":"Point"}
}