{
  "type": "Feature",
  "properties": {
    "gn:admin1_code":"29",
    "gn:admin2_code":"5202353.0",
    "gn:asciiname":"Cabo Joao",
    "gn:country_code":"BR",
    "gn:dem":365,
    "gn:feature_class":"P",
    "gn:feature_code":"PPL",
    "gn:name":"Cabo Jo\u00e3o",
    "gn:population":0,
    "gn:timezone":"America/Sao_Paulo",
    "iso:country":"BR",
    "name:por_x_preferred":[
        "Cabo Jo\u00e3o"
    ],
    "wof:name":"Cabo Joao",
    "wof:placetype":"locality"
},
  "geometry": {"coordinates":[-51.66667,-16.26667],"type":"Point"}
}