{
  "type": "Feature",
  "properties": {
    "gn:admin1_code":"5",
    "gn:admin2_code":"2914901.0",
    "gn:asciiname":"Itati",
    "gn:country_code":"BR",
    "gn:dem":110,
    "gn:feature_class":"P",
    "gn:feature_code":"PPL",
    "gn:name":"Itati",
    "gn:population":0,
    "gn:timezone":"America/Bahia",
    "iso:country":"BR",
    "name:epo_x_preferred":[
        "Itati"
    ],
    "name:eus_x_preferred":[
        "Itati"
    ],
    "name:fra_x_preferred":[
        "Itati"
    ],
    "name:ita_x_preferred":[
        "Itati"
    ],
    "name:kaz_x_preferred":[
        "\u0418\u0442\u0430\u0442\u0438"
    ],
    "name:mlg_x_preferred":[
        "Itati"
    ],
    "name:nld_x_preferred":[
        "Itati"
    ],
    "name:nor_x_preferred":[
        "Itati"
    ],
    "name:pol_x_preferred":[
        "Itati"
    ],
    "name:por_x_preferred":[
        "Itati"
    ],
    "name:ron_x_preferred":[
        "Itati"
    ],
    "name:rus_x_preferred":[
        "\u0418\u0442\u0430\u0442\u0438"
    ],
    "name:vie_x_preferred":[
        "Itati"
    ],
    "name:vol_x_preferred":[
        "Itati"
    ],
    "name:war_x_preferred":[
        "Itati"
    ],
    "name:zho_x_preferred":[
        "\u4f0a\u5854\u8482"
    ],
    "wof:name":"Itati",
    "wof:placetype":"locality"
},
  "geometry": {"coordinates":[-39.28333,-14.31667],"type":"Point"}
}