{
  "type": "Feature",
  "properties": {
    "gn:admin1_code":"5",
    "gn:admin2_code":"2914901.0",
    "gn:asciiname":"Itati",
    "gn:country_code":"BR",
    "gn:dem":110,
    "gn:feature_class":"P",
    "gn:feature_code":"PPL",
    "gn:name":"Itati",
    "gn:population":0,
    "gn:timezone":"America/Bahia",
    "iso:country":"BR",
    "wof:name":"Itati",
    "wof:placetype":"locality"
},
  "geometry": {"coordinates":[-39.28333,-14.31667],"type":"Point"}
}