{
  "type": "Feature",
  "properties": {
    "iso:country":"BR",
    "name:por_x_colloquial":[
        "Braunas"
    ],
    "name:por_x_preferred":[
        "Bra\u00fanas"
    ],
    "name:unk_x_variant":[
        "Bra\u00fanas"
    ],
    "qs:gn_adm0_cc":"BR",
    "qs:gn_local":3470127,
    "qs:gn_nam_loc":"Belo Horizonte, Belo Horizonte, Minas Gerais, BR",
    "qs:gn_namadm1":"15",
    "qs:local_max":8946,
    "qs:local_sum":53157,
    "qs:localhoods":65,
    "qs:name":"Bra\u00fanas",
    "qs:name_adm0":"Brasil",
    "qs:name_adm1":"Minas Gerais",
    "qs:name_adm2":"Belo Horizonte",
    "qs:name_local":"Belo Horizonte",
    "qs:photo_max":196,
    "qs:photo_sum":603,
    "qs:placetype":"Suburb",
    "qs:quad_count":13,
    "qs:woe_adm0":23424768,
    "qs:woe_adm1":2344856,
    "qs:woe_adm2":12579464,
    "qs:woe_lau":0,
    "qs:woe_local":455821,
    "qs:woe_ver":"7.10.0",
    "wof:lang":[
        "por"
    ],
    "wof:name":"Bra\u00fanas",
    "wof:placetype":"neighbourhood"
},
  "geometry": {"coordinates":[-44.007549,-19.858331],"type":"Point"}
}