{
  "type": "Feature",
  "properties": {
    "iso:country":"BR",
    "name:bpy_x_preferred":[
        "\u09ac\u09cd\u09b0\u09be\u0989\u09a8\u09be\u09b8"
    ],
    "name:ceb_x_preferred":[
        "Bra\u00fanas"
    ],
    "name:epo_x_preferred":[
        "Bra\u00fanas"
    ],
    "name:eus_x_preferred":[
        "Bra\u00fanas"
    ],
    "name:fra_x_preferred":[
        "Bra\u00fanas"
    ],
    "name:hye_x_preferred":[
        "\u0532\u0580\u0561\u0578\u0582\u0576\u0561\u057d"
    ],
    "name:ita_x_preferred":[
        "Bra\u00fanas"
    ],
    "name:kat_x_preferred":[
        "\u10d1\u10e0\u10d0\u10e3\u10dc\u10d0\u10e1\u10d8"
    ],
    "name:kaz_x_preferred":[
        "\u0411\u0440\u0430\u0443\u043d\u0430\u0441"
    ],
    "name:mlg_x_preferred":[
        "Bra\u00fanas"
    ],
    "name:nld_x_preferred":[
        "Bra\u00fanas"
    ],
    "name:nor_x_preferred":[
        "Bra\u00fanas"
    ],
    "name:pol_x_preferred":[
        "Bra\u00fanas"
    ],
    "name:por_x_colloquial":[
        "Braunas"
    ],
    "name:por_x_preferred":[
        "Bra\u00fanas"
    ],
    "name:ron_x_preferred":[
        "Bra\u00fanas"
    ],
    "name:rus_x_preferred":[
        "\u0411\u0440\u0430\u0443\u043d\u0430\u0441"
    ],
    "name:swe_x_preferred":[
        "Bra\u00fanas"
    ],
    "name:vie_x_preferred":[
        "Bra\u00fanas"
    ],
    "name:vol_x_preferred":[
        "Bra\u00fanas"
    ],
    "name:war_x_preferred":[
        "Bra\u00fanas"
    ],
    "name:zho_x_preferred":[
        "\u5e03\u52b3\u7eb3\u65af"
    ],
    "qs:gn_adm0_cc":"BR",
    "qs:gn_local":3470127,
    "qs:gn_nam_loc":"Belo Horizonte, Belo Horizonte, Minas Gerais, BR",
    "qs:gn_namadm1":"15",
    "qs:local_max":8946,
    "qs:local_sum":53157,
    "qs:localhoods":65,
    "qs:name":"Bra\u00fanas",
    "qs:name_adm0":"Brasil",
    "qs:name_adm1":"Minas Gerais",
    "qs:name_adm2":"Belo Horizonte",
    "qs:name_local":"Belo Horizonte",
    "qs:photo_max":196,
    "qs:photo_sum":603,
    "qs:placetype":"Suburb",
    "qs:quad_count":13,
    "qs:woe_adm0":23424768,
    "qs:woe_adm1":2344856,
    "qs:woe_adm2":12579464,
    "qs:woe_lau":0,
    "qs:woe_local":455821,
    "qs:woe_ver":"7.10.0",
    "wof:lang":[
        "por"
    ],
    "wof:name":"Bra\u00fanas",
    "wof:placetype":"neighbourhood"
},
  "geometry": {"coordinates":[-44.007549,-19.858331],"type":"Point"}
}