{
  "type": "Feature",
  "properties": {
    "gn:admin1_code":"16",
    "gn:admin2_code":"1500909.0",
    "gn:asciiname":"Juvencio",
    "gn:country_code":"BR",
    "gn:dem":1,
    "gn:feature_class":"P",
    "gn:feature_code":"PPL",
    "gn:name":"Juv\u00eancio",
    "gn:population":0,
    "gn:timezone":"America/Belem",
    "iso:country":"BR",
    "wof:name":"Juvencio",
    "wof:placetype":"locality"
},
  "geometry": {"coordinates":[-46.64194000000001,-0.96894],"type":"Point"}
}