{
  "type": "Feature",
  "properties": {
    "gn:admin1_code":"30.0",
    "gn:admin2_code":"2614204.0",
    "gn:asciiname":"Boca da Mata",
    "gn:country_code":"BR",
    "gn:dem":16,
    "gn:feature_class":"P",
    "gn:feature_code":"PPL",
    "gn:name":"Boca da Mata",
    "gn:population":0,
    "gn:timezone":"America/Recife",
    "iso:country":"BR",
    "wof:name":"Boca da Mata",
    "wof:placetype":"locality"
},
  "geometry": {"coordinates":[-35.10164,-8.56033],"type":"Point"}
}