{
  "type": "Feature",
  "properties": {
    "gn:admin1_code":"30.0",
    "gn:admin2_code":"2614204.0",
    "gn:asciiname":"Boca da Mata",
    "gn:country_code":"BR",
    "gn:dem":16,
    "gn:feature_class":"P",
    "gn:feature_code":"PPL",
    "gn:name":"Boca da Mata",
    "gn:population":0,
    "gn:timezone":"America/Recife",
    "iso:country":"BR",
    "name:bpy_x_preferred":[
        "\u09ac\u09cb\u0995\u09be \u09a1\u09be \u09ae\u09be\u099f\u09be"
    ],
    "name:ceb_x_preferred":[
        "Boca da Mata"
    ],
    "name:epo_x_preferred":[
        "Boca da Mata"
    ],
    "name:eus_x_preferred":[
        "Boca da Mata"
    ],
    "name:fra_x_preferred":[
        "Boca da Mata"
    ],
    "name:hye_x_preferred":[
        "\u0532\u0578\u056f\u0561 \u0564\u0561 \u0544\u0561\u057f\u0561"
    ],
    "name:ind_x_preferred":[
        "Boca da Mata"
    ],
    "name:ita_x_preferred":[
        "Boca da Mata"
    ],
    "name:kat_x_preferred":[
        "\u10d1\u10dd\u10d9\u10d0-\u10d3\u10d0-\u10db\u10d0\u10e2\u10d0"
    ],
    "name:kaz_x_preferred":[
        "\u0411\u043e\u043a\u0430-\u0434\u0430-\u041c\u0430\u0442\u0430"
    ],
    "name:mlg_x_preferred":[
        "Boca da Mata"
    ],
    "name:nld_x_preferred":[
        "Boca da Mata"
    ],
    "name:nno_x_preferred":[
        "Boca da Mata"
    ],
    "name:nor_x_preferred":[
        "Boca da Mata"
    ],
    "name:por_x_preferred":[
        "Boca da Mata"
    ],
    "name:ron_x_preferred":[
        "Boca da Mata"
    ],
    "name:rus_x_preferred":[
        "\u0411\u043e\u043a\u0430-\u0434\u0430-\u041c\u0430\u0442\u0430"
    ],
    "name:spa_x_preferred":[
        "Boca da Mata"
    ],
    "name:swe_x_preferred":[
        "Boca da Mata"
    ],
    "name:vie_x_preferred":[
        "Boca da Mata"
    ],
    "name:vol_x_preferred":[
        "Boca da Mata"
    ],
    "name:war_x_preferred":[
        "Boca da Mata"
    ],
    "name:zho_x_preferred":[
        "\u535a\u5361\u8fbe\u9a6c\u5854"
    ],
    "wof:name":"Boca da Mata",
    "wof:placetype":"locality"
},
  "geometry": {"coordinates":[-35.10164,-8.56033],"type":"Point"}
}