{
  "type": "Feature",
  "properties": {
    "gn:admin1_code":"27",
    "gn:admin2_code":"3526209.0",
    "gn:asciiname":"Sitio Guaramiama",
    "gn:country_code":"BR",
    "gn:dem":712,
    "gn:feature_class":"P",
    "gn:feature_code":"PPL",
    "gn:name":"S\u00edtio Guaramiama",
    "gn:population":0,
    "gn:timezone":"America/Sao_Paulo",
    "iso:country":"BR",
    "name:por_x_preferred":[
        "S\u00edtio Guaramiama"
    ],
    "wof:name":"Sitio Guaramiama",
    "wof:placetype":"locality"
},
  "geometry": {"coordinates":[-47.0061,-23.9175],"type":"Point"}
}