{
  "type": "Feature",
  "properties": {
    "gn:admin1_code":"23",
    "gn:admin2_code":"4314506.0",
    "gn:asciiname":"Alegrias",
    "gn:country_code":"BR",
    "gn:dem":134,
    "gn:feature_class":"P",
    "gn:feature_code":"PPL",
    "gn:name":"Alegrias",
    "gn:population":0,
    "gn:timezone":"America/Sao_Paulo",
    "iso:country":"BR",
    "wof:name":"Alegrias",
    "wof:placetype":"locality"
},
  "geometry": {"coordinates":[-53.41667,-31.83333],"type":"Point"}
}