{
  "type": "Feature",
  "properties": {
    "gn:admin1_code":"15",
    "gn:admin2_code":"3160306.0",
    "gn:asciiname":"Altino",
    "gn:country_code":"BR",
    "gn:dem":572,
    "gn:feature_class":"P",
    "gn:feature_code":"PPL",
    "gn:name":"Altino",
    "gn:population":0,
    "gn:timezone":"America/Sao_Paulo",
    "iso:country":"BR",
    "name:por_x_preferred":[
        "Altino"
    ],
    "wof:name":"Altino",
    "wof:placetype":"locality"
},
  "geometry": {"coordinates":[-40.33333,-16.41667],"type":"Point"}
}