{
  "type": "Feature",
  "properties": {
    "gn:admin1_code":"15",
    "gn:admin2_code":"3120201.0",
    "gn:asciiname":"Fernandes",
    "gn:country_code":"BR",
    "gn:dem":770,
    "gn:feature_class":"P",
    "gn:feature_code":"PPL",
    "gn:name":"Fernandes",
    "gn:population":0,
    "gn:timezone":"America/Sao_Paulo",
    "iso:country":"BR",
    "name:por_x_preferred":[
        "Fernandes"
    ],
    "wof:name":"Fernandes",
    "wof:placetype":"locality"
},
  "geometry": {"coordinates":[-45.64975,-20.79557],"type":"Point"}
}