{
  "type": "Feature",
  "properties": {
    "gn:admin1_code":"18.0",
    "gn:admin2_code":"4111803.0",
    "gn:asciiname":"Sitio Manoel Gomes",
    "gn:country_code":"BR",
    "gn:dem":553,
    "gn:feature_class":"P",
    "gn:feature_code":"PPL",
    "gn:name":"S\u00edtio Manoel Gomes",
    "gn:population":0,
    "gn:timezone":"America/Sao_Paulo",
    "iso:country":"BR",
    "name:por_x_preferred":[
        "S\u00edtio Manoel Gomes"
    ],
    "wof:name":"Sitio Manoel Gomes",
    "wof:placetype":"locality"
},
  "geometry": {"coordinates":[-49.94897,-23.19309],"type":"Point"}
}