{
  "type": "Feature",
  "properties": {
    "gn:admin1_code":"04",
    "gn:admin2_code":"1302900.0",
    "gn:asciiname":"Pedra do Barco",
    "gn:cc2":"BR",
    "gn:country_code":"BR",
    "gn:dem":28,
    "gn:feature_class":"P",
    "gn:feature_code":"PPL",
    "gn:name":"Pedra do Barco",
    "gn:population":0,
    "gn:timezone":"America/Manaus",
    "iso:country":"BR",
    "name:und_x_variant":[
        "Pedra do Buraco",
        "Pedra do Barco"
    ],
    "wof:name":"Pedra do Barco",
    "wof:placetype":"locality"
},
  "geometry": {"coordinates":[-58.03333000000001,-4.91667],"type":"Point"}
}