{
  "type": "Feature",
  "properties": {
    "gn:admin1_code":"06",
    "gn:admin2_code":"2307502.0",
    "gn:asciiname":"Cipriano",
    "gn:country_code":"BR",
    "gn:dem":281,
    "gn:feature_class":"P",
    "gn:feature_code":"PPL",
    "gn:name":"Cipriano",
    "gn:population":0,
    "gn:timezone":"America/Fortaleza",
    "iso:country":"BR",
    "wof:name":"Cipriano",
    "wof:placetype":"locality"
},
  "geometry": {"coordinates":[-38.88333,-6.71667],"type":"Point"}
}