{
  "type": "Feature",
  "properties": {
    "gn:admin1_code":"24.0",
    "gn:admin2_code":"1100189.0",
    "gn:asciiname":"Posto Indigena Roosevelt",
    "gn:country_code":"BR",
    "gn:dem":253,
    "gn:feature_class":"P",
    "gn:feature_code":"PPL",
    "gn:name":"Posto Ind\u00edgena Roosevelt",
    "gn:population":0,
    "gn:timezone":"America/Porto_Velho",
    "iso:country":"BR",
    "name:por_x_preferred":[
        "Posto Ind\u00edgena Roosevelt"
    ],
    "wof:name":"Posto Indigena Roosevelt",
    "wof:placetype":"locality"
},
  "geometry": {"coordinates":[-60.46824,-11.48801],"type":"Point"}
}