{
  "type": "Feature",
  "properties": {
    "gn:admin1_code":"18.0",
    "gn:admin2_code":"4124103.0",
    "gn:asciiname":"Sitio Dengo",
    "gn:country_code":"BR",
    "gn:dem":490,
    "gn:feature_class":"P",
    "gn:feature_code":"PPL",
    "gn:name":"S\u00edtio Dengo",
    "gn:population":0,
    "gn:timezone":"America/Sao_Paulo",
    "iso:country":"BR",
    "name:por_x_preferred":[
        "S\u00edtio Dengo"
    ],
    "wof:name":"Sitio Dengo",
    "wof:placetype":"locality"
},
  "geometry": {"coordinates":[-50.02546,-23.37797],"type":"Point"}
}