{
  "type": "Feature",
  "properties": {
    "gn:admin1_code":"06",
    "gn:admin2_code":"2307254.0",
    "gn:asciiname":"Corrego da Forquiha",
    "gn:country_code":"BR",
    "gn:dem":26,
    "gn:feature_class":"P",
    "gn:feature_code":"PPL",
    "gn:name":"C\u00f3rrego da Forquiha",
    "gn:population":0,
    "gn:timezone":"America/Fortaleza",
    "iso:country":"BR",
    "wof:name":"Corrego da Forquiha",
    "wof:placetype":"locality"
},
  "geometry": {"coordinates":[-40.48333,-2.88333],"type":"Point"}
}