{
  "type": "Feature",
  "properties": {
    "gn:admin1_code":"5",
    "gn:admin2_code":"2925402.0",
    "gn:asciiname":"Coroa",
    "gn:country_code":"BR",
    "gn:dem":290,
    "gn:feature_class":"P",
    "gn:feature_code":"PPL",
    "gn:name":"Coroa",
    "gn:population":0,
    "gn:timezone":"America/Bahia",
    "iso:country":"BR",
    "wof:name":"Coroa",
    "wof:placetype":"locality"
},
  "geometry": {"coordinates":[-39.88333,-15.65],"type":"Point"}
}