{
  "type": "Feature",
  "properties": {
    "gn:admin1_code":"13",
    "gn:admin2_code":"2106300.0",
    "gn:asciiname":"Santo Inacio",
    "gn:country_code":"BR",
    "gn:dem":23,
    "gn:feature_class":"P",
    "gn:feature_code":"PPL",
    "gn:name":"Santo In\u00e1cio",
    "gn:population":0,
    "gn:timezone":"America/Fortaleza",
    "iso:country":"BR",
    "wof:name":"Santo Inacio",
    "wof:placetype":"locality"
},
  "geometry": {"coordinates":[-42.16,-3.25194],"type":"Point"}
}