{
  "type": "Feature",
  "properties": {
    "gn:admin1_code":"5",
    "gn:admin2_code":"2923209.0",
    "gn:asciiname":"Caxingo",
    "gn:country_code":"BR",
    "gn:dem":442,
    "gn:feature_class":"P",
    "gn:feature_code":"PPL",
    "gn:name":"Caxing\u00f3",
    "gn:population":0,
    "gn:timezone":"America/Bahia",
    "iso:country":"BR",
    "wof:name":"Caxingo",
    "wof:placetype":"locality"
},
  "geometry": {"coordinates":[-42.76667,-12.25],"type":"Point"}
}