{
  "type": "Feature",
  "properties": {
    "gn:admin1_code":"18",
    "gn:admin2_code":"4110706.0",
    "gn:asciiname":"Caratuva",
    "gn:country_code":"BR",
    "gn:dem":896,
    "gn:feature_class":"P",
    "gn:feature_code":"PPL",
    "gn:name":"Caratuva",
    "gn:population":0,
    "gn:timezone":"America/Sao_Paulo",
    "iso:country":"BR",
    "name:por_x_preferred":[
        "Caratuva"
    ],
    "wof:name":"Caratuva",
    "wof:placetype":"locality"
},
  "geometry": {"coordinates":[-50.7117,-25.4167],"type":"Point"}
}