{
  "type": "Feature",
  "properties": {
    "gn:admin1_code":"18.0",
    "gn:admin2_code":"4126603.0",
    "gn:asciiname":"Sitio Roberto Godoy",
    "gn:country_code":"BR",
    "gn:dem":653,
    "gn:feature_class":"P",
    "gn:feature_code":"PPL",
    "gn:name":"S\u00edtio Roberto Godoy",
    "gn:population":0,
    "gn:timezone":"America/Sao_Paulo",
    "iso:country":"BR",
    "name:por_x_preferred":[
        "S\u00edtio Roberto Godoy"
    ],
    "wof:name":"Sitio Roberto Godoy",
    "wof:placetype":"locality"
},
  "geometry": {"coordinates":[-49.8166,-23.7164],"type":"Point"}
}