{
  "type": "Feature",
  "properties": {
    "gn:admin1_code":"27",
    "gn:admin2_code":"3523909.0",
    "gn:asciiname":"Porto Gois",
    "gn:country_code":"BR",
    "gn:dem":636,
    "gn:feature_class":"P",
    "gn:feature_code":"PPL",
    "gn:name":"P\u00f4rto G\u00f3is",
    "gn:population":0,
    "gn:timezone":"America/Sao_Paulo",
    "iso:country":"BR",
    "name:por_x_preferred":[
        "P\u00f4rto G\u00f3is"
    ],
    "wof:name":"Porto Gois",
    "wof:placetype":"locality"
},
  "geometry": {"coordinates":[-47.23333,-23.21667],"type":"Point"}
}