{
  "type": "Feature",
  "properties": {
    "gn:admin1_code":"03",
    "gn:admin2_code":"1600154.0",
    "gn:asciiname":"Mongaba",
    "gn:country_code":"BR",
    "gn:dem":81,
    "gn:feature_class":"P",
    "gn:feature_code":"PPL",
    "gn:name":"Mongaba",
    "gn:population":0,
    "gn:timezone":"America/Belem",
    "iso:country":"BR",
    "name:und_x_variant":[
        "Mongubas"
    ],
    "wof:name":"Mongaba",
    "wof:placetype":"locality"
},
  "geometry": {"coordinates":[-51.86293,0.66268],"type":"Point"}
}