{
  "type": "Feature",
  "properties": {
    "gn:admin1_code":"18.0",
    "gn:admin2_code":"4124103.0",
    "gn:asciiname":"Sitio Jose Zava",
    "gn:country_code":"BR",
    "gn:dem":457,
    "gn:feature_class":"P",
    "gn:feature_code":"PPL",
    "gn:name":"S\u00edtio Jos\u00e9 Zava",
    "gn:population":0,
    "gn:timezone":"America/Sao_Paulo",
    "iso:country":"BR",
    "name:por_x_preferred":[
        "S\u00edtio Jos\u00e9 Zava"
    ],
    "wof:name":"Sitio Jose Zava",
    "wof:placetype":"locality"
},
  "geometry": {"coordinates":[-50.1556,-23.1812],"type":"Point"}
}