{
  "type": "Feature",
  "properties": {
    "gn:admin1_code":"8",
    "gn:admin2_code":"3203809.0",
    "gn:asciiname":"Girando",
    "gn:country_code":"BR",
    "gn:dem":214,
    "gn:feature_class":"P",
    "gn:feature_code":"PPL",
    "gn:name":"Girando",
    "gn:population":0,
    "gn:timezone":"America/Sao_Paulo",
    "iso:country":"BR",
    "name:por_x_preferred":[
        "Girando"
    ],
    "wof:name":"Girando",
    "wof:placetype":"locality"
},
  "geometry": {"coordinates":[-41.41667,-20.86667000000001],"type":"Point"}
}