{
  "type": "Feature",
  "properties": {
    "gn:admin1_code":"18.0",
    "gn:admin2_code":"4126009.0",
    "gn:asciiname":"Sitio Bras S. de Souza",
    "gn:country_code":"BR",
    "gn:dem":637,
    "gn:feature_class":"P",
    "gn:feature_code":"PPL",
    "gn:name":"S\u00edtio Br\u00e1s S. de Souza",
    "gn:population":0,
    "gn:timezone":"America/Sao_Paulo",
    "iso:country":"BR",
    "name:por_x_preferred":[
        "S\u00edtio Br\u00e1s S. de Souza"
    ],
    "wof:name":"Sitio Bras S. de Souza",
    "wof:placetype":"locality"
},
  "geometry": {"coordinates":[-50.7288,-23.5159],"type":"Point"}
}