{
  "type": "Feature",
  "properties": {
    "gn:admin1_code":"04",
    "gn:admin2_code":"1303106.0",
    "gn:asciiname":"Quem Diria",
    "gn:cc2":"BR",
    "gn:country_code":"BR",
    "gn:dem":21,
    "gn:feature_class":"P",
    "gn:feature_code":"PPL",
    "gn:name":"Quem Diria",
    "gn:population":0,
    "gn:timezone":"America/Manaus",
    "iso:country":"BR",
    "name:und_x_variant":[
        "Gerinaldo",
        "Quem Diria"
    ],
    "wof:name":"Quem Diria",
    "wof:placetype":"locality"
},
  "geometry": {"coordinates":[-58.38333000000001,-3.78333],"type":"Point"}
}