{
  "type": "Feature",
  "properties": {
    "gn:admin1_code":"23",
    "gn:admin2_code":"4313102.0",
    "gn:asciiname":"Comercio",
    "gn:country_code":"BR",
    "gn:dem":396,
    "gn:feature_class":"P",
    "gn:feature_code":"PPL",
    "gn:name":"Com\u00e9rcio",
    "gn:population":0,
    "gn:timezone":"America/Sao_Paulo",
    "iso:country":"BR",
    "wof:name":"Comercio",
    "wof:placetype":"locality"
},
  "geometry": {"coordinates":[-53.36666999999999,-29.36667000000001],"type":"Point"}
}