{
  "type": "Feature",
  "properties": {
    "gn:admin1_code":"30",
    "gn:admin2_code":"2605707.0",
    "gn:asciiname":"Salina Grande",
    "gn:country_code":"BR",
    "gn:dem":373,
    "gn:feature_class":"P",
    "gn:feature_code":"PPL",
    "gn:name":"Salina Grande",
    "gn:population":0,
    "gn:timezone":"America/Recife",
    "iso:country":"BR",
    "wof:name":"Salina Grande",
    "wof:placetype":"locality"
},
  "geometry": {"coordinates":[-38.38333,-8.68333],"type":"Point"}
}