{
  "type": "Feature",
  "properties": {
    "gn:admin1_code":"15",
    "gn:admin2_code":"3139300.0",
    "gn:asciiname":"Brejo de Sao Caetano",
    "gn:country_code":"BR",
    "gn:dem":470,
    "gn:feature_class":"P",
    "gn:feature_code":"PPL",
    "gn:name":"Brejo de S\u00e3o Caetano",
    "gn:population":0,
    "gn:timezone":"America/Sao_Paulo",
    "iso:country":"BR",
    "wof:name":"Brejo de Sao Caetano",
    "wof:placetype":"locality"
},
  "geometry": {"coordinates":[-44.03333,-14.65],"type":"Point"}
}