{
  "type": "Feature",
  "properties": {
    "gn:admin1_code":"27",
    "gn:admin2_code":"3504107.0",
    "gn:asciiname":"Sitio Parracinha",
    "gn:country_code":"BR",
    "gn:dem":828,
    "gn:feature_class":"P",
    "gn:feature_code":"PPL",
    "gn:name":"S\u00edtio Parracinha",
    "gn:population":0,
    "gn:timezone":"America/Sao_Paulo",
    "iso:country":"BR",
    "name:por_x_preferred":[
        "S\u00edtio Parracinha"
    ],
    "wof:name":"Sitio Parracinha",
    "wof:placetype":"locality"
},
  "geometry": {"coordinates":[-46.59944,-23.20611],"type":"Point"}
}