{
  "type": "Feature",
  "properties": {
    "gn:admin1_code":"27",
    "gn:admin2_code":"3526209.0",
    "gn:asciiname":"Bairro das Rosas",
    "gn:country_code":"BR",
    "gn:dem":678,
    "gn:feature_class":"P",
    "gn:feature_code":"PPL",
    "gn:name":"Bairro das Rosas",
    "gn:population":0,
    "gn:timezone":"America/Sao_Paulo",
    "iso:country":"BR",
    "name:por_x_preferred":[
        "Bairro das Rosas"
    ],
    "wof:name":"Bairro das Rosas",
    "wof:placetype":"locality"
},
  "geometry": {"coordinates":[-47.1078,-23.971],"type":"Point"}
}