{
  "type": "Feature",
  "properties": {
    "gn:admin1_code":"4",
    "gn:admin2_code":"1303304.0",
    "gn:asciiname":"America",
    "gn:country_code":"BR",
    "gn:dem":15,
    "gn:feature_class":"P",
    "gn:feature_code":"PPL",
    "gn:name":"Am\u00e9rica",
    "gn:population":0,
    "gn:timezone":"America/Manaus",
    "iso:country":"BR",
    "wof:name":"America",
    "wof:placetype":"locality"
},
  "geometry": {"coordinates":[-60.43333000000001,-5.16667],"type":"Point"}
}