{
  "type": "Feature",
  "properties": {
    "gn:admin1_code":"15",
    "gn:admin2_code":"3139508.0",
    "gn:asciiname":"Ponte Nova",
    "gn:country_code":"BR",
    "gn:dem":665,
    "gn:feature_class":"P",
    "gn:feature_code":"PPL",
    "gn:name":"Ponte Nova",
    "gn:population":0,
    "gn:timezone":"America/Sao_Paulo",
    "iso:country":"BR",
    "name:por_x_preferred":[
        "Ponte Nova"
    ],
    "wof:name":"Ponte Nova",
    "wof:placetype":"locality"
},
  "geometry": {"coordinates":[-41.95,-20.33333],"type":"Point"}
}