{
  "type": "Feature",
  "properties": {
    "gn:gn_country":"BR",
    "gn:gn_fcode":"PPL",
    "gn:gn_pop":0,
    "iso:country":"BR",
    "qs_pg:aaroncc":"BR",
    "qs_pg:gn_country":"BR",
    "qs_pg:gn_fcode":"PPL",
    "qs_pg:gn_pop":0,
    "qs_pg:name":"Primavera",
    "qs_pg:name_adm0":"Brasil",
    "qs_pg:name_adm1":"Mato Grosso",
    "qs_pg:photos_9k":1,
    "qs_pg:photos_9r":1,
    "qs_pg:photos_all":1,
    "qs_pg:photos_sr":0,
    "qs_pg:pop_sr":4,
    "qs_pg:qs_pg_placetype":"locality",
    "qs_pg:qs_pg_placetype_gp":"Town",
    "qs_pg:woe_adm0":23424768,
    "woe:adm0_id":23424768,
    "woe:name_adm0":"Brasil",
    "woe:name_adm1":"Mato Grosso",
    "woe:placetype":"Town",
    "wof:name":"Primavera",
    "wof:placetype":"locality"
},
  "geometry": {"coordinates":[-54.36667,-15.68333],"type":"Point"}
}