{
  "type": "Feature",
  "properties": {
    "gn:country":"BR",
    "gn:fcode":"PPL",
    "gn:population":0,
    "iso:country":"BR",
    "name:bel_x_preferred":[
        "\u0412\u044f\u0441\u043d\u0430"
    ],
    "name:bre_x_preferred":[
        "Primavera"
    ],
    "name:cat_x_preferred":[
        "Primavera"
    ],
    "name:ceb_x_preferred":[
        "Primavera"
    ],
    "name:deu_x_preferred":[
        "Primavera"
    ],
    "name:fas_x_preferred":[
        "\u067e\u0631\u06cc\u0645\u0627\u0648\u0631\u0627"
    ],
    "name:fin_x_preferred":[
        "Primavera"
    ],
    "name:fra_x_preferred":[
        "Primavera"
    ],
    "name:ita_x_preferred":[
        "Primavera"
    ],
    "name:jpn_x_preferred":[
        "\u30d7\u30ea\u30de\u30f4\u30a7\u30fc\u30e9"
    ],
    "name:kor_x_preferred":[
        "\ud504\ub9ac\ub9c8\ubca0\ub77c"
    ],
    "name:nld_x_preferred":[
        "Primavera"
    ],
    "name:nor_x_preferred":[
        "Primavera"
    ],
    "name:por_x_preferred":[
        "Primavera"
    ],
    "name:rus_x_preferred":[
        "\u0412\u0435\u0441\u043d\u0430"
    ],
    "name:slk_x_preferred":[
        "Primavera"
    ],
    "name:spa_x_preferred":[
        "Primavera"
    ],
    "name:srp_x_preferred":[
        "\u041f\u0440\u0438\u043c\u0430\u0432\u0435\u0440\u0430"
    ],
    "name:swe_x_preferred":[
        "Primavera"
    ],
    "name:ukr_x_preferred":[
        "\u0412\u0435\u0441\u043d\u0430"
    ],
    "name:vol_x_preferred":[
        "Primavera"
    ],
    "qs_pg:aaroncc":"BR",
    "qs_pg:gn_country":"BR",
    "qs_pg:gn_fcode":"PPL",
    "qs_pg:gn_pop":0,
    "qs_pg:name":"Primavera",
    "qs_pg:name_adm0":"Brasil",
    "qs_pg:name_adm1":"Mato Grosso",
    "qs_pg:photos_9k":1,
    "qs_pg:photos_9r":1,
    "qs_pg:photos_all":1,
    "qs_pg:photos_sr":0,
    "qs_pg:pop_sr":4,
    "qs_pg:qs_pg_placetype":"locality",
    "qs_pg:qs_pg_placetype_gp":"Town",
    "qs_pg:woe_adm0":23424768,
    "woe:adm0_id":23424768,
    "woe:name_adm0":"Brasil",
    "woe:name_adm1":"Mato Grosso",
    "woe:placetype":"Town",
    "wof:name":"Primavera",
    "wof:placetype":"locality"
},
  "geometry": {"coordinates":[-54.36667,-15.68333],"type":"Point"}
}