{
  "type": "Feature",
  "properties": {
    "gn:admin1_code":"22",
    "gn:admin2_code":"2409704.0",
    "gn:asciiname":"Bonito",
    "gn:country_code":"BR",
    "gn:dem":111,
    "gn:feature_class":"P",
    "gn:feature_code":"PPL",
    "gn:name":"Bonito",
    "gn:population":0,
    "gn:timezone":"America/Fortaleza",
    "iso:country":"BR",
    "wof:name":"Bonito",
    "wof:placetype":"locality"
},
  "geometry": {"coordinates":[-36.35278,-5.38278],"type":"Point"}
}