{
  "type": "Feature",
  "properties": {
    "gn:admin1_code":"22",
    "gn:admin2_code":"2409704.0",
    "gn:asciiname":"Bonito",
    "gn:country_code":"BR",
    "gn:dem":111,
    "gn:feature_class":"P",
    "gn:feature_code":"PPL",
    "gn:name":"Bonito",
    "gn:population":0,
    "gn:timezone":"America/Fortaleza",
    "iso:country":"BR",
    "name:fas_x_preferred":[
        "\u0644\u0630\u06cc\u0630\u0645\u0627\u0647\u06cc"
    ],
    "name:fra_x_preferred":[
        "Sardini"
    ],
    "name:glg_x_preferred":[
        "Sardinos"
    ],
    "name:lav_x_preferred":[
        "Pelam\u012bdu cilts"
    ],
    "name:por_x_preferred":[
        "Sardini"
    ],
    "wof:name":"Bonito",
    "wof:placetype":"locality"
},
  "geometry": {"coordinates":[-36.35278,-5.38278],"type":"Point"}
}