{
  "type": "Feature",
  "properties": {
    "gn:admin1_code":"22",
    "gn:admin2_code":"2408003.0",
    "gn:asciiname":"Rio Morto",
    "gn:country_code":"BR",
    "gn:dem":8,
    "gn:feature_class":"P",
    "gn:feature_code":"PPL",
    "gn:name":"Rio Morto",
    "gn:population":0,
    "gn:timezone":"America/Fortaleza",
    "iso:country":"BR",
    "wof:name":"Rio Morto",
    "wof:placetype":"locality"
},
  "geometry": {"coordinates":[-37.3075,-5.17861],"type":"Point"}
}