{
  "type": "Feature",
  "properties": {
    "gn:admin1_code":"26",
    "gn:admin2_code":"4210100.0",
    "gn:asciiname":"Campo da Lanca",
    "gn:country_code":"BR",
    "gn:dem":812,
    "gn:feature_class":"P",
    "gn:feature_code":"PPLL",
    "gn:name":"Campo da Lan\u00e7a",
    "gn:population":0,
    "gn:timezone":"America/Sao_Paulo",
    "iso:country":"BR",
    "name:por_x_preferred":[
        "Campo da Lan\u00e7a"
    ],
    "wof:name":"Campo da Lanca",
    "wof:placetype":"locality"
},
  "geometry": {"coordinates":[-49.8292,-26.1931],"type":"Point"}
}