{
  "type": "Feature",
  "properties": {
    "gn:admin1_code":"24",
    "gn:admin2_code":"1100106.0",
    "gn:asciiname":"Renascenca",
    "gn:cc2":"BR",
    "gn:country_code":"BR",
    "gn:dem":165,
    "gn:feature_class":"P",
    "gn:feature_code":"PPL",
    "gn:name":"Renascen\u00e7a",
    "gn:population":0,
    "gn:timezone":"America/Porto_Velho",
    "iso:country":"BR",
    "name:und_x_variant":[
        "Renescen\u00e7a",
        "Renascen\u00e7a"
    ],
    "wof:name":"Renascenca",
    "wof:placetype":"locality"
},
  "geometry": {"coordinates":[-64.53333000000001,-12.16667],"type":"Point"}
}