{
  "type": "Feature",
  "properties": {
    "gn:admin1_code":"13",
    "gn:admin2_code":"2110609.0",
    "gn:asciiname":"Paraiso",
    "gn:country_code":"BR",
    "gn:dem":45,
    "gn:feature_class":"P",
    "gn:feature_code":"PPL",
    "gn:name":"Para\u00edso",
    "gn:population":0,
    "gn:timezone":"America/Fortaleza",
    "iso:country":"BR",
    "wof:name":"Paraiso",
    "wof:placetype":"locality"
},
  "geometry": {"coordinates":[-42.40028,-3.30083],"type":"Point"}
}