{
  "type": "Feature",
  "properties": {
    "gn:admin1_code":"4",
    "gn:admin2_code":"1302801.0",
    "gn:asciiname":"Taboca",
    "gn:country_code":"BR",
    "gn:dem":58,
    "gn:feature_class":"P",
    "gn:feature_code":"PPL",
    "gn:name":"Taboca",
    "gn:population":0,
    "gn:timezone":"America/Manaus",
    "iso:country":"BR",
    "wof:name":"Taboca",
    "wof:placetype":"locality"
},
  "geometry": {"coordinates":[-65.80948000000001,-1.7542],"type":"Point"}
}