{
  "type": "Feature",
  "properties": {
    "gn:admin1_code":"17",
    "gn:admin2_code":"2510808.0",
    "gn:asciiname":"Mocambo",
    "gn:country_code":"BR",
    "gn:dem":247,
    "gn:feature_class":"P",
    "gn:feature_code":"PPL",
    "gn:name":"Mocambo",
    "gn:population":0,
    "gn:timezone":"America/Fortaleza",
    "iso:country":"BR",
    "wof:name":"Mocambo",
    "wof:placetype":"locality"
},
  "geometry": {"coordinates":[-37.25,-6.95],"type":"Point"}
}