{
  "type": "Feature",
  "properties": {
    "gn:admin1_code":"18.0",
    "gn:admin2_code":"4100202.0",
    "gn:asciiname":"Colonia Sete Barras",
    "gn:country_code":"BR",
    "gn:dem":153,
    "gn:feature_class":"P",
    "gn:feature_code":"PPL",
    "gn:name":"Col\u00f4nia Sete Barras",
    "gn:population":0,
    "gn:timezone":"America/Sao_Paulo",
    "iso:country":"BR",
    "name:por_x_preferred":[
        "Col\u00f4nia Sete Barras"
    ],
    "wof:name":"Colonia Sete Barras",
    "wof:placetype":"locality"
},
  "geometry": {"coordinates":[-48.80995,-24.6789],"type":"Point"}
}