{
  "type": "Feature",
  "properties": {
    "gn:admin1_code":"14",
    "gn:admin2_code":"5105507.0",
    "gn:asciiname":"Boa Sorte",
    "gn:cc2":"BR",
    "gn:country_code":"BR",
    "gn:dem":199,
    "gn:feature_class":"P",
    "gn:feature_code":"PPL",
    "gn:name":"Boa Sorte",
    "gn:population":0,
    "gn:timezone":"America/Cuiaba",
    "iso:country":"BR",
    "name:und_x_variant":[
        "Fazenda Boa Sorte",
        "Boa Sorte"
    ],
    "wof:name":"Boa Sorte",
    "wof:placetype":"locality"
},
  "geometry": {"coordinates":[-59.87472,-15.07778],"type":"Point"}
}