{
  "type": "Feature",
  "properties": {
    "gn:admin1_code":"18.0",
    "gn:admin2_code":"4126207.0",
    "gn:asciiname":"Sitio Oswaldo F. Minardi",
    "gn:country_code":"BR",
    "gn:dem":698,
    "gn:feature_class":"P",
    "gn:feature_code":"PPL",
    "gn:name":"S\u00edtio Oswaldo F. Minardi",
    "gn:population":0,
    "gn:timezone":"America/Sao_Paulo",
    "iso:country":"BR",
    "name:por_x_preferred":[
        "S\u00edtio Oswaldo F. Minardi"
    ],
    "wof:name":"Sitio Oswaldo F. Minardi",
    "wof:placetype":"locality"
},
  "geometry": {"coordinates":[-50.54394,-23.88808],"type":"Point"}
}