{
  "type": "Feature",
  "properties": {
    "gn:admin1_code":"4",
    "gn:admin2_code":"1300706.0",
    "gn:asciiname":"Floriano Peixoto",
    "gn:cc2":"BR",
    "gn:country_code":"BR",
    "gn:dem":142,
    "gn:feature_class":"P",
    "gn:feature_code":"PPL",
    "gn:name":"Floriano Peixoto",
    "gn:population":0,
    "gn:timezone":"America/Manaus",
    "iso:country":"BR",
    "name:und_x_variant":[
        "Vila de Floriano Peixoto",
        "Antimari",
        "Floriano Peixoto"
    ],
    "wof:name":"Floriano Peixoto",
    "wof:placetype":"locality"
},
  "geometry": {"coordinates":[-67.40000000000001,-9.05],"type":"Point"}
}