{
  "type": "Feature",
  "properties": {
    "gn:admin1_code":"14",
    "gn:admin2_code":"5106505.0",
    "gn:asciiname":"Araras",
    "gn:country_code":"BR",
    "gn:dem":120,
    "gn:feature_class":"P",
    "gn:feature_code":"PPL",
    "gn:name":"Araras",
    "gn:population":0,
    "gn:timezone":"America/Cuiaba",
    "iso:country":"BR",
    "name:ara_x_preferred":[
        "\u0623\u0631\u0627\u0631\u0627\u0633"
    ],
    "name:bpy_x_preferred":[
        "\u09f1\u09be\u09b0\u09be\u09b0\u09be\u09b8"
    ],
    "name:ceb_x_preferred":[
        "Araras"
    ],
    "name:deu_x_preferred":[
        "Araras"
    ],
    "name:epo_x_preferred":[
        "Araras"
    ],
    "name:eus_x_preferred":[
        "Araras"
    ],
    "name:fra_x_preferred":[
        "Araras"
    ],
    "name:ita_x_preferred":[
        "Araras"
    ],
    "name:kaz_x_preferred":[
        "\u0410\u0440\u0430\u0440\u0430\u0441"
    ],
    "name:lit_x_preferred":[
        "Ararasas"
    ],
    "name:mlg_x_preferred":[
        "Araras"
    ],
    "name:nld_x_preferred":[
        "Araras"
    ],
    "name:nor_x_preferred":[
        "Araras"
    ],
    "name:pol_x_preferred":[
        "Araras"
    ],
    "name:por_x_preferred":[
        "Araras"
    ],
    "name:ron_x_preferred":[
        "Araras"
    ],
    "name:rus_x_preferred":[
        "\u0410\u0440\u0430\u0440\u0430\u0441"
    ],
    "name:spa_x_preferred":[
        "Araras"
    ],
    "name:swe_x_preferred":[
        "Araras"
    ],
    "name:tat_x_preferred":[
        "\u0410\u0440\u0430\u0440\u0430\u0441"
    ],
    "name:vie_x_preferred":[
        "Araras"
    ],
    "name:vol_x_preferred":[
        "Araras"
    ],
    "name:war_x_preferred":[
        "Araras"
    ],
    "name:zho_x_preferred":[
        "\u963f\u62c9\u62c9\u65af"
    ],
    "wof:name":"Araras",
    "wof:placetype":"locality"
},
  "geometry": {"coordinates":[-56.63333000000001,-16.43333],"type":"Point"}
}