{
  "type": "Feature",
  "properties": {
    "gn:admin1_code":"14",
    "gn:admin2_code":"5106505.0",
    "gn:asciiname":"Araras",
    "gn:country_code":"BR",
    "gn:dem":120,
    "gn:feature_class":"P",
    "gn:feature_code":"PPL",
    "gn:name":"Araras",
    "gn:population":0,
    "gn:timezone":"America/Cuiaba",
    "iso:country":"BR",
    "wof:name":"Araras",
    "wof:placetype":"locality"
},
  "geometry": {"coordinates":[-56.63333000000001,-16.43333],"type":"Point"}
}