{
  "type": "Feature",
  "properties": {
    "gn:admin1_code":"27",
    "gn:admin2_code":"3550605.0",
    "gn:asciiname":"Sitio Ben-Te-Vi",
    "gn:country_code":"BR",
    "gn:dem":963,
    "gn:feature_class":"P",
    "gn:feature_code":"PPL",
    "gn:name":"S\u00edtio Ben-Te-Vi",
    "gn:population":0,
    "gn:timezone":"America/Sao_Paulo",
    "iso:country":"BR",
    "name:por_x_preferred":[
        "S\u00edtio Ben-Te-Vi"
    ],
    "wof:name":"Sitio Ben-Te-Vi",
    "wof:placetype":"locality"
},
  "geometry": {"coordinates":[-47.12107,-23.50066],"type":"Point"}
}