{
  "type": "Feature",
  "properties": {
    "gn:admin1_code":"13",
    "gn:admin2_code":"2106300.0",
    "gn:asciiname":"Surubim",
    "gn:country_code":"BR",
    "gn:dem":9,
    "gn:feature_class":"P",
    "gn:feature_code":"PPL",
    "gn:name":"Surubim",
    "gn:population":0,
    "gn:timezone":"America/Fortaleza",
    "iso:country":"BR",
    "name:bpy_x_preferred":[
        "\u09b8\u09c1\u09b0\u09c1\u09ac\u09bf\u09ae"
    ],
    "name:eus_x_preferred":[
        "Surubim"
    ],
    "name:fra_x_preferred":[
        "Surubim"
    ],
    "name:ita_x_preferred":[
        "Surubim"
    ],
    "name:kat_x_preferred":[
        "\u10e1\u10e3\u10e0\u10e3\u10d1\u10d8\u10dc\u10d8"
    ],
    "name:kaz_x_preferred":[
        "\u0421\u0443\u0440\u0443\u0431\u0438\u043d"
    ],
    "name:mlg_x_preferred":[
        "Surubim"
    ],
    "name:nld_x_preferred":[
        "Surubim"
    ],
    "name:nor_x_preferred":[
        "Surubim"
    ],
    "name:por_x_preferred":[
        "Surubim"
    ],
    "name:ron_x_preferred":[
        "Surubim"
    ],
    "name:rus_x_preferred":[
        "\u0421\u0443\u0440\u0443\u0431\u0438\u043d"
    ],
    "name:vie_x_preferred":[
        "Surubim"
    ],
    "name:vol_x_preferred":[
        "Surubim"
    ],
    "name:war_x_preferred":[
        "Surubim"
    ],
    "name:zho_x_preferred":[
        "\u82cf\u9c81\u5bbe"
    ],
    "wof:name":"Surubim",
    "wof:placetype":"locality"
},
  "geometry": {"coordinates":[-42.05306,-3.24472],"type":"Point"}
}