{
  "type": "Feature",
  "properties": {
    "gn:admin1_code":"13",
    "gn:admin2_code":"2106300.0",
    "gn:asciiname":"Surubim",
    "gn:country_code":"BR",
    "gn:dem":9,
    "gn:feature_class":"P",
    "gn:feature_code":"PPL",
    "gn:name":"Surubim",
    "gn:population":0,
    "gn:timezone":"America/Fortaleza",
    "iso:country":"BR",
    "wof:name":"Surubim",
    "wof:placetype":"locality"
},
  "geometry": {"coordinates":[-42.05306,-3.24472],"type":"Point"}
}