{
  "type": "Feature",
  "properties": {
    "gn:admin1_code":"15",
    "gn:admin2_code":"3130507.0",
    "gn:asciiname":"Duas Barras",
    "gn:country_code":"BR",
    "gn:dem":853,
    "gn:feature_class":"P",
    "gn:feature_code":"PPL",
    "gn:name":"Duas Barras",
    "gn:population":0,
    "gn:timezone":"America/Sao_Paulo",
    "iso:country":"BR",
    "name:bpy_x_preferred":[
        "\u09a1\u09c1\u0986\u09b8 \u09ac\u09be\u09b0\u09cd\u09b0\u09be\u09b8"
    ],
    "name:ceb_x_preferred":[
        "Duas Barras"
    ],
    "name:epo_x_preferred":[
        "Duas Barras"
    ],
    "name:eus_x_preferred":[
        "Duas Barras"
    ],
    "name:fra_x_preferred":[
        "Duas Barras"
    ],
    "name:hye_x_preferred":[
        "\u0534\u0578\u0582\u0561\u057d \u0532\u0561\u0580\u0580\u0561\u057d"
    ],
    "name:ita_x_preferred":[
        "Duas Barras"
    ],
    "name:kat_x_preferred":[
        "\u10d3\u10e3\u10d0\u10e1-\u10d1\u10d0\u10e0\u10d0\u10e1\u10d8"
    ],
    "name:kaz_x_preferred":[
        "\u0414\u0443\u0430\u0441-\u0411\u0430\u0440\u0440\u0430\u0441"
    ],
    "name:nld_x_preferred":[
        "Duas Barras"
    ],
    "name:nor_x_preferred":[
        "Duas Barras"
    ],
    "name:pol_x_preferred":[
        "Duas Barras"
    ],
    "name:por_x_preferred":[
        "Duas Barras"
    ],
    "name:ron_x_preferred":[
        "Duas Barras"
    ],
    "name:rus_x_preferred":[
        "\u0414\u0443\u0430\u0441-\u0411\u0430\u0440\u0440\u0430\u0441"
    ],
    "name:swe_x_preferred":[
        "Duas Barras"
    ],
    "name:vie_x_preferred":[
        "Duas Barras"
    ],
    "name:vol_x_preferred":[
        "Duas Barras"
    ],
    "name:war_x_preferred":[
        "Duas Barras"
    ],
    "name:zho_x_preferred":[
        "\u675c\u963f\u65af\u5df4\u62c9\u65af"
    ],
    "wof:name":"Duas Barras",
    "wof:placetype":"locality"
},
  "geometry": {"coordinates":[-45.88333,-20.91667],"type":"Point"}
}