{
  "type": "Feature",
  "properties": {
    "gn:admin1_code":"15",
    "gn:admin2_code":"3130507.0",
    "gn:asciiname":"Duas Barras",
    "gn:country_code":"BR",
    "gn:dem":853,
    "gn:feature_class":"P",
    "gn:feature_code":"PPL",
    "gn:name":"Duas Barras",
    "gn:population":0,
    "gn:timezone":"America/Sao_Paulo",
    "iso:country":"BR",
    "name:por_x_preferred":[
        "Duas Barras"
    ],
    "wof:name":"Duas Barras",
    "wof:placetype":"locality"
},
  "geometry": {"coordinates":[-45.88333,-20.91667],"type":"Point"}
}