{
  "type": "Feature",
  "properties": {
    "gn:admin1_code":"23",
    "gn:admin2_code":"4304622.0",
    "gn:asciiname":"Capao Bonito",
    "gn:country_code":"BR",
    "gn:dem":882,
    "gn:feature_class":"P",
    "gn:feature_code":"PPLL",
    "gn:name":"Cap\u00e3o Bonito",
    "gn:population":0,
    "gn:timezone":"America/Sao_Paulo",
    "iso:country":"BR",
    "wof:name":"Capao Bonito",
    "wof:placetype":"locality"
},
  "geometry": {"coordinates":[-51.39389,-28.12667],"type":"Point"}
}