{
  "type": "Feature",
  "properties": {
    "gn:admin1_code":"18.0",
    "gn:admin2_code":"4117701.0",
    "gn:asciiname":"Sitio Jose Kovausque",
    "gn:country_code":"BR",
    "gn:dem":840,
    "gn:feature_class":"P",
    "gn:feature_code":"PPL",
    "gn:name":"S\u00edtio Jos\u00e9 Kovausque",
    "gn:population":0,
    "gn:timezone":"America/Sao_Paulo",
    "iso:country":"BR",
    "name:por_x_preferred":[
        "S\u00edtio Jos\u00e9 Kovausque"
    ],
    "wof:name":"Sitio Jose Kovausque",
    "wof:placetype":"locality"
},
  "geometry": {"coordinates":[-49.9982,-25.5774],"type":"Point"}
}