{
  "type": "Feature",
  "properties": {
    "gn:admin1_code":"25",
    "gn:admin2_code":"1400308.0",
    "gn:asciiname":"Serrinha",
    "gn:country_code":"BR",
    "gn:dem":139,
    "gn:feature_class":"P",
    "gn:feature_code":"PPL",
    "gn:name":"Serrinha",
    "gn:population":0,
    "gn:timezone":"America/Boa_Vista",
    "iso:country":"BR",
    "wof:name":"Serrinha",
    "wof:placetype":"locality"
},
  "geometry": {"coordinates":[-61.11666999999999,2.63333],"type":"Point"}
}