{
  "type": "Feature",
  "properties": {
    "gn:admin1_code":"18.0",
    "gn:admin2_code":"4101101.0",
    "gn:asciiname":"Sitio Sebastiao Laurindo",
    "gn:country_code":"BR",
    "gn:dem":493,
    "gn:feature_class":"P",
    "gn:feature_code":"PPL",
    "gn:name":"S\u00edtio Sebasti\u00e3o Laurindo",
    "gn:population":0,
    "gn:timezone":"America/Sao_Paulo",
    "iso:country":"BR",
    "name:por_x_preferred":[
        "S\u00edtio Sebasti\u00e3o Laurindo"
    ],
    "wof:name":"Sitio Sebastiao Laurindo",
    "wof:placetype":"locality"
},
  "geometry": {"coordinates":[-50.2082,-23.0651],"type":"Point"}
}