{
  "type": "Feature",
  "properties": {
    "gn:admin1_code":"1",
    "gn:admin2_code":"1200609.0",
    "gn:asciiname":"Friburgo",
    "gn:country_code":"BR",
    "gn:dem":219,
    "gn:feature_class":"P",
    "gn:feature_code":"PPL",
    "gn:name":"Friburgo",
    "gn:population":0,
    "gn:timezone":"America/Eirunepe",
    "iso:country":"BR",
    "wof:name":"Friburgo",
    "wof:placetype":"locality"
},
  "geometry": {"coordinates":[-70.98333000000002,-7.78333],"type":"Point"}
}