{
  "type": "Feature",
  "properties": {
    "gn:admin1_code":"06",
    "gn:admin2_code":"2312205.0",
    "gn:asciiname":"Cipo",
    "gn:cc2":"BR",
    "gn:country_code":"BR",
    "gn:dem":378,
    "gn:feature_class":"P",
    "gn:feature_code":"PPL",
    "gn:name":"Cip\u00f3",
    "gn:population":0,
    "gn:timezone":"America/Fortaleza",
    "iso:country":"BR",
    "name:und_x_variant":[
        "Fazenda Cip\u00f3",
        "Cip\u00f3"
    ],
    "wof:name":"Cipo",
    "wof:placetype":"locality"
},
  "geometry": {"coordinates":[-39.88333,-4.65],"type":"Point"}
}