{
  "type": "Feature",
  "properties": {
    "gn:admin1_code":"18.0",
    "gn:admin2_code":"4113205.0",
    "gn:asciiname":"Sitio Paulo Figura",
    "gn:country_code":"BR",
    "gn:dem":889,
    "gn:feature_class":"P",
    "gn:feature_code":"PPL",
    "gn:name":"S\u00edtio Paulo Figura",
    "gn:population":0,
    "gn:timezone":"America/Sao_Paulo",
    "iso:country":"BR",
    "name:por_x_preferred":[
        "S\u00edtio Paulo Figura"
    ],
    "wof:name":"Sitio Paulo Figura",
    "wof:placetype":"locality"
},
  "geometry": {"coordinates":[-49.99117,-25.85219],"type":"Point"}
}