{
  "type": "Feature",
  "properties": {
    "gn:admin1_code":"31",
    "gn:admin2_code":"1717206.0",
    "gn:asciiname":"Corda",
    "gn:country_code":"BR",
    "gn:dem":149,
    "gn:feature_class":"P",
    "gn:feature_code":"PPL",
    "gn:name":"Corda",
    "gn:population":0,
    "gn:timezone":"America/Araguaina",
    "iso:country":"BR",
    "name:cat_x_preferred":[
        "Corda"
    ],
    "name:deu_x_preferred":[
        "Corda"
    ],
    "name:fra_x_preferred":[
        "Corda"
    ],
    "name:gle_x_preferred":[
        "Corda"
    ],
    "name:glg_x_preferred":[
        "Corda"
    ],
    "name:ita_x_preferred":[
        "Corda"
    ],
    "name:nld_x_preferred":[
        "Corda"
    ],
    "name:por_x_preferred":[
        "Corda"
    ],
    "wof:name":"Corda",
    "wof:placetype":"locality"
},
  "geometry": {"coordinates":[-48.21667,-6.46667],"type":"Point"}
}