{
  "type": "Feature",
  "properties": {
    "gn:admin1_code":"11",
    "gn:admin2_code":"5001102.0",
    "gn:asciiname":"Cutape",
    "gn:cc2":"BR",
    "gn:country_code":"BR",
    "gn:dem":125,
    "gn:feature_class":"P",
    "gn:feature_code":"PPL",
    "gn:name":"Cutape",
    "gn:population":0,
    "gn:timezone":"America/Campo_Grande",
    "iso:country":"BR",
    "name:und_x_variant":[
        "Catude",
        "Cutade",
        "Cutape"
    ],
    "wof:name":"Cutape",
    "wof:placetype":"locality"
},
  "geometry": {"coordinates":[-56.08333,-20.13333],"type":"Point"}
}