{
  "type": "Feature",
  "properties": {
    "gn:admin1_code":"4",
    "gn:admin2_code":"1303809.0",
    "gn:asciiname":"Iauacana",
    "gn:country_code":"BR",
    "gn:dem":87,
    "gn:feature_class":"P",
    "gn:feature_code":"PPL",
    "gn:name":"Iauacan\u00e1",
    "gn:population":0,
    "gn:timezone":"America/Manaus",
    "iso:country":"BR",
    "name:und_x_variant":[
        "Taua-cana",
        "Yauacan\u00e1",
        "Iauacan\u00e1"
    ],
    "wof:name":"Iauacana",
    "wof:placetype":"locality"
},
  "geometry": {"coordinates":[-67.39704999999999,0.55369],"type":"Point"}
}