{
  "type": "Feature",
  "properties": {
    "gn:admin1_code":"27",
    "gn:admin2_code":"3502804.0",
    "gn:asciiname":"Porto Pio Prado",
    "gn:country_code":"BR",
    "gn:dem":334,
    "gn:feature_class":"P",
    "gn:feature_code":"PPL",
    "gn:name":"P\u00f4rto Pio Prado",
    "gn:population":0,
    "gn:timezone":"America/Sao_Paulo",
    "iso:country":"BR",
    "wof:name":"Porto Pio Prado",
    "wof:placetype":"locality"
},
  "geometry": {"coordinates":[-50.46667,-21.05],"type":"Point"}
}