{
  "type": "Feature",
  "properties": {
    "gn:admin1_code":"18",
    "gn:admin2_code":"4105805.0",
    "gn:asciiname":"Guraituba",
    "gn:cc2":"BR",
    "gn:country_code":"BR",
    "gn:dem":926,
    "gn:feature_class":"P",
    "gn:feature_code":"PPL",
    "gn:name":"Guraituba",
    "gn:population":0,
    "gn:timezone":"America/Sao_Paulo",
    "iso:country":"BR",
    "name:und_x_variant":[
        "Garatuba",
        "Guraituba"
    ],
    "wof:name":"Guraituba",
    "wof:placetype":"locality"
},
  "geometry": {"coordinates":[-49.15,-25.35],"type":"Point"}
}