{
  "type": "Feature",
  "properties": {
    "gn:admin1_code":"4",
    "gn:admin2_code":"1302306.0",
    "gn:asciiname":"Foz do Mamoria",
    "gn:country_code":"BR",
    "gn:dem":62,
    "gn:feature_class":"P",
    "gn:feature_code":"PPL",
    "gn:name":"Foz do Mamori\u00e1",
    "gn:population":0,
    "gn:timezone":"America/Manaus",
    "iso:country":"BR",
    "wof:name":"Foz do Mamoria",
    "wof:placetype":"locality"
},
  "geometry": {"coordinates":[-66.45180000000001,-2.36065],"type":"Point"}
}