{
  "type": "Feature",
  "properties": {
    "iso:country":"BR",
    "name:por_x_preferred":[
        "Czerniewicz"
    ],
    "qs:gn_adm0_cc":"BR",
    "qs:gn_local":3460102,
    "qs:gn_nam_loc":"Jaragu\u00e1 do Sul, Jaragu\u00e1 do Sul, Santa Catarina, BR",
    "qs:gn_namadm1":"26",
    "qs:local_max":188,
    "qs:local_sum":326,
    "qs:localhoods":4,
    "qs:name":"Czerniewicz",
    "qs:name_adm0":"Brasil",
    "qs:name_adm1":"Santa Catarina",
    "qs:name_adm2":"Jaragu\u00e1 do Sul",
    "qs:name_local":"Jaragu\u00e1 do Sul",
    "qs:photo_max":3,
    "qs:photo_sum":13,
    "qs:placetype":"Suburb",
    "qs:quad_count":8,
    "qs:woe_adm0":23424768,
    "qs:woe_adm1":2344867,
    "qs:woe_adm2":12581693,
    "qs:woe_lau":0,
    "qs:woe_local":456283,
    "qs:woe_ver":"7.10.0",
    "wof:lang":[
        "por"
    ],
    "wof:name":"Czerniewicz",
    "wof:placetype":"neighbourhood"
},
  "geometry": {"coordinates":[-49.092799,-26.47268],"type":"Point"}
}