{
  "type": "Feature",
  "properties": {
    "gn:admin1_code":"06",
    "gn:admin2_code":"2303931.0",
    "gn:asciiname":"Pocinhos",
    "gn:country_code":"BR",
    "gn:dem":155,
    "gn:feature_class":"P",
    "gn:feature_code":"PPL",
    "gn:name":"Pocinhos",
    "gn:population":0,
    "gn:timezone":"America/Fortaleza",
    "iso:country":"BR",
    "wof:name":"Pocinhos",
    "wof:placetype":"locality"
},
  "geometry": {"coordinates":[-39.05,-4.78333],"type":"Point"}
}