{
  "type": "Feature",
  "properties": {
    "gn:admin1_code":"20",
    "gn:admin2_code":"2200301.0",
    "gn:asciiname":"Retiro",
    "gn:country_code":"BR",
    "gn:dem":111,
    "gn:feature_class":"P",
    "gn:feature_code":"PPL",
    "gn:name":"Retiro",
    "gn:population":0,
    "gn:timezone":"America/Fortaleza",
    "iso:country":"BR",
    "wof:name":"Retiro",
    "wof:placetype":"locality"
},
  "geometry": {"coordinates":[-41.95,-5.41667],"type":"Point"}
}