{
  "type": "Feature",
  "properties": {
    "gn:admin1_code":"18.0",
    "gn:admin2_code":"4101200.0",
    "gn:asciiname":"Morro Grande",
    "gn:country_code":"BR",
    "gn:dem":6,
    "gn:feature_class":"P",
    "gn:feature_code":"PPLL",
    "gn:name":"Morro Grande",
    "gn:population":0,
    "gn:timezone":"America/Sao_Paulo",
    "iso:country":"BR",
    "name:por_x_preferred":[
        "Morro Grande"
    ],
    "wof:name":"Morro Grande",
    "wof:placetype":"locality"
},
  "geometry": {"coordinates":[-48.77399000000001,-25.36238],"type":"Point"}
}