{
  "type": "Feature",
  "properties": {
    "gn:admin1_code":"18.0",
    "gn:admin2_code":"4101200.0",
    "gn:asciiname":"Morro Grande",
    "gn:country_code":"BR",
    "gn:dem":6,
    "gn:feature_class":"P",
    "gn:feature_code":"PPLL",
    "gn:name":"Morro Grande",
    "gn:population":0,
    "gn:timezone":"America/Sao_Paulo",
    "iso:country":"BR",
    "name:bpy_x_preferred":[
        "\u09ae\u09cb\u09b0\u09cd\u09b0\u09cb \u0997\u09cd\u09b0\u09be\u09a8\u09cd\u09a1\u09c7"
    ],
    "name:eus_x_preferred":[
        "Morro Grande"
    ],
    "name:fra_x_preferred":[
        "Morro Grande"
    ],
    "name:ina_x_preferred":[
        "Morro Grande"
    ],
    "name:ita_x_preferred":[
        "Morro Grande"
    ],
    "name:kat_x_preferred":[
        "\u10db\u10dd\u10e0\u10e3-\u10d2\u10e0\u10d0\u10dc\u10d3\u10d8"
    ],
    "name:nld_x_preferred":[
        "Morro Grande"
    ],
    "name:nor_x_preferred":[
        "Morro Grande"
    ],
    "name:oci_x_preferred":[
        "Morro Grande"
    ],
    "name:pol_x_preferred":[
        "Morro Grande"
    ],
    "name:por_x_preferred":[
        "Morro Grande"
    ],
    "name:ron_x_preferred":[
        "Morro Grande"
    ],
    "name:rus_x_preferred":[
        "\u041c\u043e\u0440\u0440\u0443-\u0413\u0440\u0430\u043d\u0434\u0438"
    ],
    "name:vie_x_preferred":[
        "Morro Grande"
    ],
    "name:vol_x_preferred":[
        "Morro Grande"
    ],
    "name:war_x_preferred":[
        "Morro Grande"
    ],
    "name:zho_x_preferred":[
        "\u5927\u83ab\u9c81"
    ],
    "wof:name":"Morro Grande",
    "wof:placetype":"locality"
},
  "geometry": {"coordinates":[-48.77399000000001,-25.36238],"type":"Point"}
}