{
  "type": "Feature",
  "properties": {
    "gn:admin1_code":"20",
    "gn:admin2_code":"2210979.0",
    "gn:asciiname":"Xique-Xique",
    "gn:country_code":"BR",
    "gn:dem":442,
    "gn:feature_class":"P",
    "gn:feature_code":"PPL",
    "gn:name":"Xique-Xique",
    "gn:population":0,
    "gn:timezone":"America/Fortaleza",
    "iso:country":"BR",
    "name:ara_x_preferred":[
        "\u062a\u0634\u064a\u0643\u064a-\u062a\u0634\u064a\u0643\u064a"
    ],
    "name:ben_x_preferred":[
        "\u09b6\u09bf\u0995\u09c7-\u09b6\u09bf\u0995\u09c7"
    ],
    "name:bpy_x_preferred":[
        "\u0995\u09cd\u09b8\u09bf\u0995\u09c1\u09af\u09bc\u09c7-\u0995\u09cd\u09b8\u09bf\u0995\u09c1\u09af\u09bc\u09c7"
    ],
    "name:bul_x_preferred":[
        "\u0428\u0438\u043a\u0438-\u0428\u0438\u043a\u0438"
    ],
    "name:ceb_x_preferred":[
        "Xique-Xique"
    ],
    "name:ell_x_preferred":[
        "\u03a3\u03af\u03ba\u03b5-\u03a3\u03af\u03ba\u03b5"
    ],
    "name:epo_x_preferred":[
        "Xique-Xique"
    ],
    "name:eus_x_preferred":[
        "Xique-Xique"
    ],
    "name:fas_x_preferred":[
        "\u0633\u06cc\u06a9 \u0633\u06cc\u06a9"
    ],
    "name:fra_x_preferred":[
        "Xique-Xique"
    ],
    "name:heb_x_preferred":[
        "\u05e7\u05e1\u05d9\u05e7\u05d4-\u05e7\u05e1\u05d9\u05e7\u05d4"
    ],
    "name:hin_x_preferred":[
        "\u091c\u093c\u093f\u0915\u0940-\u091c\u093c\u093f\u0915\u0940"
    ],
    "name:hye_x_preferred":[
        "\u0547\u056b\u056f\u056b-\u0547\u056b\u056f\u056b"
    ],
    "name:ind_x_preferred":[
        "Xique-Xique"
    ],
    "name:ita_x_preferred":[
        "Xique-Xique"
    ],
    "name:jpn_x_preferred":[
        "\u30b7\u30b1\u30fb\u30b7\u30b1"
    ],
    "name:kat_x_preferred":[
        "\u10e8\u10d8\u10d9\u10d8-\u10e8\u10d8\u10d9\u10d8"
    ],
    "name:kaz_x_preferred":[
        "\u0428\u0438\u043a\u0438-\u0428\u0438\u043a\u0438"
    ],
    "name:kor_x_preferred":[
        "\uc2dc\ud06c-\uc2dc\ud06c"
    ],
    "name:mlg_x_preferred":[
        "Xique-Xique"
    ],
    "name:nld_x_preferred":[
        "Xique-Xique"
    ],
    "name:nor_x_preferred":[
        "Xique-Xique"
    ],
    "name:pol_x_preferred":[
        "Xique-Xique"
    ],
    "name:por_x_preferred":[
        "Xique-Xique"
    ],
    "name:ron_x_preferred":[
        "Xique-Xique"
    ],
    "name:rus_x_preferred":[
        "\u0428\u0438\u043a\u0438-\u0428\u0438\u043a\u0438"
    ],
    "name:spa_x_preferred":[
        "Xique-Xique"
    ],
    "name:swe_x_preferred":[
        "Xique-Xique"
    ],
    "name:tur_x_preferred":[
        "Xique-Xique"
    ],
    "name:ukr_x_preferred":[
        "\u0428\u0438\u043a\u0456-\u0428\u0438\u043a\u0456"
    ],
    "name:urd_x_preferred":[
        "\u0632\u06cc\u06a9\u06d2 \u0632\u06cc\u06a9\u06d2"
    ],
    "name:vie_x_preferred":[
        "Xique-Xique"
    ],
    "name:vol_x_preferred":[
        "Xique-Xique"
    ],
    "name:war_x_preferred":[
        "Xique-Xique"
    ],
    "name:zho_x_preferred":[
        "\u5e0c\u514b\u5e0c\u514b"
    ],
    "wof:name":"Xique-Xique",
    "wof:placetype":"locality"
},
  "geometry": {"coordinates":[-42.15,-6.68333],"type":"Point"}
}