{
  "type": "Feature",
  "properties": {
    "gn:admin1_code":"20",
    "gn:admin2_code":"2210979.0",
    "gn:asciiname":"Xique-Xique",
    "gn:country_code":"BR",
    "gn:dem":442,
    "gn:feature_class":"P",
    "gn:feature_code":"PPL",
    "gn:name":"Xique-Xique",
    "gn:population":0,
    "gn:timezone":"America/Fortaleza",
    "iso:country":"BR",
    "name:bpy_x_preferred":[
        "\u0995\u09cd\u09b8\u09bf\u0995\u09c1\u09af\u09bc\u09c7-\u0995\u09cd\u09b8\u09bf\u0995\u09c1\u09af\u09bc\u09c7"
    ],
    "name:bul_x_preferred":[
        "\u0428\u0438\u043a\u0438-\u0428\u0438\u043a\u0438"
    ],
    "name:ceb_x_preferred":[
        "Xique-Xique"
    ],
    "name:epo_x_preferred":[
        "Xique-Xique"
    ],
    "name:eus_x_preferred":[
        "Xique-Xique"
    ],
    "name:fra_x_preferred":[
        "Xique-Xique"
    ],
    "name:hye_x_preferred":[
        "\u0547\u056b\u056f\u056b-\u0547\u056b\u056f\u056b"
    ],
    "name:ita_x_preferred":[
        "Xique-Xique"
    ],
    "name:kat_x_preferred":[
        "\u10e8\u10d8\u10d9\u10d8-\u10e8\u10d8\u10d9\u10d8"
    ],
    "name:kaz_x_preferred":[
        "\u0428\u0438\u043a\u0438-\u0428\u0438\u043a\u0438"
    ],
    "name:mlg_x_preferred":[
        "Xique-Xique"
    ],
    "name:nld_x_preferred":[
        "Xique-Xique"
    ],
    "name:nor_x_preferred":[
        "Xique-Xique"
    ],
    "name:pol_x_preferred":[
        "Xique-Xique"
    ],
    "name:por_x_preferred":[
        "Xique-Xique"
    ],
    "name:ron_x_preferred":[
        "Xique-Xique"
    ],
    "name:rus_x_preferred":[
        "\u0428\u0438\u043a\u0438-\u0428\u0438\u043a\u0438"
    ],
    "name:spa_x_preferred":[
        "Xique-Xique"
    ],
    "name:swe_x_preferred":[
        "Xique-Xique"
    ],
    "name:vie_x_preferred":[
        "Xique-Xique"
    ],
    "name:vol_x_preferred":[
        "Xique-Xique"
    ],
    "name:war_x_preferred":[
        "Xique-Xique"
    ],
    "name:zho_x_preferred":[
        "\u5e0c\u514b\u5e0c\u514b"
    ],
    "wof:name":"Xique-Xique",
    "wof:placetype":"locality"
},
  "geometry": {"coordinates":[-42.15,-6.68333],"type":"Point"}
}