{
  "type": "Feature",
  "properties": {
    "gn:admin1_code":"18.0",
    "gn:admin2_code":"4111803.0",
    "gn:asciiname":"Sitio Cinco Irmaos",
    "gn:country_code":"BR",
    "gn:dem":512,
    "gn:feature_class":"P",
    "gn:feature_code":"PPL",
    "gn:name":"S\u00edtio Cinco Irm\u00e3os",
    "gn:population":0,
    "gn:timezone":"America/Sao_Paulo",
    "iso:country":"BR",
    "name:por_x_preferred":[
        "S\u00edtio Cinco Irm\u00e3os"
    ],
    "wof:name":"Sitio Cinco Irmaos",
    "wof:placetype":"locality"
},
  "geometry": {"coordinates":[-49.9425,-23.16525],"type":"Point"}
}