{
  "type": "Feature",
  "properties": {
    "gn:admin1_code":"13",
    "gn:admin2_code":"2106706.0",
    "gn:asciiname":"Estiro",
    "gn:cc2":"BR",
    "gn:country_code":"BR",
    "gn:dem":303,
    "gn:feature_class":"P",
    "gn:feature_code":"PPL",
    "gn:name":"Estiro",
    "gn:population":0,
    "gn:timezone":"America/Fortaleza",
    "iso:country":"BR",
    "name:und_x_variant":[
        "Campo Largo",
        "Estiro"
    ],
    "wof:name":"Estiro",
    "wof:placetype":"locality"
},
  "geometry": {"coordinates":[-44.98333,-6.38333],"type":"Point"}
}