{
  "type": "Feature",
  "properties": {
    "gn:admin1_code":"27",
    "gn:admin2_code":"3503307.0",
    "gn:asciiname":"Conceicao",
    "gn:country_code":"BR",
    "gn:dem":640,
    "gn:feature_class":"P",
    "gn:feature_code":"PPL",
    "gn:name":"Concei\u00e7\u00e3o",
    "gn:population":0,
    "gn:timezone":"America/Sao_Paulo",
    "iso:country":"BR",
    "name:por_x_preferred":[
        "Concei\u00e7\u00e3o"
    ],
    "wof:name":"Conceicao",
    "wof:placetype":"locality"
},
  "geometry": {"coordinates":[-47.18333,-22.41667],"type":"Point"}
}