{
  "type": "Feature",
  "properties": {
    "gn:admin1_code":"17",
    "gn:admin2_code":"2505907.0",
    "gn:asciiname":"Pedre d'Agua",
    "gn:country_code":"BR",
    "gn:dem":276,
    "gn:feature_class":"P",
    "gn:feature_code":"PPL",
    "gn:name":"Pedre d\u2019Agua",
    "gn:population":0,
    "gn:timezone":"America/Fortaleza",
    "iso:country":"BR",
    "wof:name":"Pedre d'Agua",
    "wof:placetype":"locality"
},
  "geometry": {"coordinates":[-37.81667,-7.05],"type":"Point"}
}