{
  "type": "Feature",
  "properties": {
    "gn:admin1_code":"26.0",
    "gn:admin2_code":"4210100.0",
    "gn:asciiname":"Sitio Paulino Benech",
    "gn:country_code":"BR",
    "gn:dem":817,
    "gn:feature_class":"P",
    "gn:feature_code":"PPL",
    "gn:name":"S\u00edtio Paulino Benech",
    "gn:population":0,
    "gn:timezone":"America/Sao_Paulo",
    "iso:country":"BR",
    "name:por_x_preferred":[
        "S\u00edtio Paulino Benech"
    ],
    "wof:name":"Sitio Paulino Benech",
    "wof:placetype":"locality"
},
  "geometry": {"coordinates":[-49.8692,-26.1433],"type":"Point"}
}