{
  "type": "Feature",
  "properties": {
    "gn:admin1_code":"13",
    "gn:admin2_code":"2102606.0",
    "gn:asciiname":"Sete Voltas",
    "gn:country_code":"BR",
    "gn:dem":18,
    "gn:feature_class":"P",
    "gn:feature_code":"PPL",
    "gn:name":"Sete Voltas",
    "gn:population":0,
    "gn:timezone":"America/Fortaleza",
    "iso:country":"BR",
    "wof:name":"Sete Voltas",
    "wof:placetype":"locality"
},
  "geometry": {"coordinates":[-45.73333,-1.53333],"type":"Point"}
}