{
  "type": "Feature",
  "properties": {
    "gn:admin1_code":"4.0",
    "gn:admin2_code":"1301951.0",
    "gn:asciiname":"Menino Deus",
    "gn:country_code":"BR",
    "gn:dem":120,
    "gn:feature_class":"P",
    "gn:feature_code":"PPL",
    "gn:name":"Menino Deus",
    "gn:population":0,
    "gn:timezone":"America/Manaus",
    "iso:country":"BR",
    "wof:name":"Menino Deus",
    "wof:placetype":"locality"
},
  "geometry": {"coordinates":[-68.88485,-6.53341],"type":"Point"}
}