{
  "type": "Feature",
  "properties": {
    "gn:admin1_code":"14",
    "gn:admin2_code":"5106232.0",
    "gn:asciiname":"Pascoal",
    "gn:cc2":"BR",
    "gn:country_code":"BR",
    "gn:dem":192,
    "gn:feature_class":"P",
    "gn:feature_code":"PPL",
    "gn:name":"Pascoal",
    "gn:population":0,
    "gn:timezone":"America/Cuiaba",
    "iso:country":"BR",
    "name:deu_x_preferred":[
        "Pascoal"
    ],
    "name:ita_x_preferred":[
        "Pascoal"
    ],
    "name:por_x_preferred":[
        "Pascoal"
    ],
    "name:und_x_variant":[
        "Sitio do Paschoal",
        "Paschoal",
        "Pascoal"
    ],
    "wof:name":"Pascoal",
    "wof:placetype":"locality"
},
  "geometry": {"coordinates":[-57.43333000000001,-14.76667],"type":"Point"}
}