{
  "type": "Feature",
  "properties": {
    "gn:admin1_code":"23",
    "gn:admin2_code":"4307807.0",
    "gn:asciiname":"Posses",
    "gn:country_code":"BR",
    "gn:dem":51,
    "gn:feature_class":"P",
    "gn:feature_code":"PPL",
    "gn:name":"Posses",
    "gn:population":0,
    "gn:timezone":"America/Sao_Paulo",
    "iso:country":"BR",
    "wof:name":"Posses",
    "wof:placetype":"locality"
},
  "geometry": {"coordinates":[-51.86667,-29.48333],"type":"Point"}
}