{
  "type": "Feature",
  "properties": {
    "gn:admin1_code":"03",
    "gn:admin2_code":"1600402.0",
    "gn:asciiname":"Gaivota",
    "gn:country_code":"BR",
    "gn:dem":88,
    "gn:feature_class":"P",
    "gn:feature_code":"PPL",
    "gn:name":"Gaivota",
    "gn:population":0,
    "gn:timezone":"America/Belem",
    "iso:country":"BR",
    "wof:name":"Gaivota",
    "wof:placetype":"locality"
},
  "geometry": {"coordinates":[-51.84493,0.44319],"type":"Point"}
}