{
  "type": "Feature",
  "properties": {
    "gn:admin1_code":"20",
    "gn:admin2_code":"2201507.0",
    "gn:asciiname":"Bem-Te-Vi",
    "gn:country_code":"BR",
    "gn:dem":38,
    "gn:feature_class":"P",
    "gn:feature_code":"PPL",
    "gn:name":"Bem-Te-Vi",
    "gn:population":0,
    "gn:timezone":"America/Fortaleza",
    "iso:country":"BR",
    "wof:name":"Bem-Te-Vi",
    "wof:placetype":"locality"
},
  "geometry": {"coordinates":[-42.01778,-3.78889],"type":"Point"}
}