{
  "type": "Feature",
  "properties": {
    "gn:admin1_code":"18",
    "gn:admin2_code":"4119103.0",
    "gn:asciiname":"Sitio Heidl",
    "gn:country_code":"BR",
    "gn:dem":906,
    "gn:feature_class":"P",
    "gn:feature_code":"PPL",
    "gn:name":"S\u00edtio Heidl",
    "gn:population":0,
    "gn:timezone":"America/Sao_Paulo",
    "iso:country":"BR",
    "name:por_x_preferred":[
        "S\u00edtio Heidl"
    ],
    "wof:name":"Sitio Heidl",
    "wof:placetype":"locality"
},
  "geometry": {"coordinates":[-49.3993,-26.0896],"type":"Point"}
}