{
  "type": "Feature",
  "properties": {
    "gn:admin1_code":"27.0",
    "gn:admin2_code":"3550308.0",
    "gn:asciiname":"Educandario",
    "gn:country_code":"BR",
    "gn:dem":792,
    "gn:feature_class":"P",
    "gn:feature_code":"PPLL",
    "gn:name":"Educand\u00e1rio",
    "gn:population":0,
    "gn:timezone":"America/Sao_Paulo",
    "iso:country":"BR",
    "name:por_x_preferred":[
        "Educand\u00e1rio"
    ],
    "wof:name":"Educandario",
    "wof:placetype":"locality"
},
  "geometry": {"coordinates":[-46.7359,-23.9205],"type":"Point"}
}