{
  "type": "Feature",
  "properties": {
    "gn:admin1_code":"23",
    "gn:admin2_code":"4311155.0",
    "gn:asciiname":"Sao Pedro",
    "gn:country_code":"BR",
    "gn:dem":353,
    "gn:feature_class":"P",
    "gn:feature_code":"PPL",
    "gn:name":"S\u00e3o Pedro",
    "gn:population":0,
    "gn:timezone":"America/Sao_Paulo",
    "iso:country":"BR",
    "wof:name":"Sao Pedro",
    "wof:placetype":"locality"
},
  "geometry": {"coordinates":[-54.08333,-28.61667000000001],"type":"Point"}
}