{
  "type": "Feature",
  "properties": {
    "gn:admin1_code":"06",
    "gn:admin2_code":"2303659.0",
    "gn:asciiname":"Sao Jeronimo",
    "gn:country_code":"BR",
    "gn:dem":444,
    "gn:feature_class":"P",
    "gn:feature_code":"PPL",
    "gn:name":"S\u00e3o J\u00earonimo",
    "gn:population":0,
    "gn:timezone":"America/Fortaleza",
    "iso:country":"BR",
    "wof:name":"Sao Jeronimo",
    "wof:placetype":"locality"
},
  "geometry": {"coordinates":[-40.26667,-4.76667],"type":"Point"}
}