{
  "type": "Feature",
  "properties": {
    "gn:admin1_code":"18.0",
    "gn:admin2_code":"4112306.0",
    "gn:asciiname":"Sitio Jose Terra Pinto",
    "gn:country_code":"BR",
    "gn:dem":551,
    "gn:feature_class":"P",
    "gn:feature_code":"PPL",
    "gn:name":"S\u00edtio Jos\u00e9 Terra Pinto",
    "gn:population":0,
    "gn:timezone":"America/Sao_Paulo",
    "iso:country":"BR",
    "name:por_x_preferred":[
        "S\u00edtio Jos\u00e9 Terra Pinto"
    ],
    "wof:name":"Sitio Jose Terra Pinto",
    "wof:placetype":"locality"
},
  "geometry": {"coordinates":[-50.16749,-23.71902],"type":"Point"}
}