{
  "type": "Feature",
  "properties": {
    "gn:admin1_code":"18.0",
    "gn:admin2_code":"4113205.0",
    "gn:asciiname":"Sitio Jorge Halaiko",
    "gn:country_code":"BR",
    "gn:dem":921,
    "gn:feature_class":"P",
    "gn:feature_code":"PPL",
    "gn:name":"S\u00edtio Jorge Halaiko",
    "gn:population":0,
    "gn:timezone":"America/Sao_Paulo",
    "iso:country":"BR",
    "name:por_x_preferred":[
        "S\u00edtio Jorge Halaiko"
    ],
    "wof:name":"Sitio Jorge Halaiko",
    "wof:placetype":"locality"
},
  "geometry": {"coordinates":[-49.8005,-25.7331],"type":"Point"}
}