{
  "type": "Feature",
  "properties": {
    "gn:admin1_code":"16",
    "gn:admin2_code":"1505304.0",
    "gn:asciiname":"Maloca",
    "gn:country_code":"BR",
    "gn:dem":296,
    "gn:feature_class":"P",
    "gn:feature_code":"PPL",
    "gn:name":"Maloca",
    "gn:population":0,
    "gn:timezone":"America/Santarem",
    "iso:country":"BR",
    "name:fra_x_preferred":[
        "Maloca"
    ],
    "name:heb_x_preferred":[
        "\u05de\u05d0\u05dc\u05d5\u05e7\u05d4"
    ],
    "name:lit_x_preferred":[
        "Maloka"
    ],
    "name:pol_x_preferred":[
        "Maloca"
    ],
    "name:por_x_preferred":[
        "Maloca"
    ],
    "name:rus_x_preferred":[
        "\u041c\u0430\u043b\u043e\u043a\u0430"
    ],
    "name:spa_x_preferred":[
        "Maloca"
    ],
    "name:swe_x_preferred":[
        "Maloca"
    ],
    "wof:name":"Maloca",
    "wof:placetype":"locality"
},
  "geometry": {"coordinates":[-55.97229,0.64208],"type":"Point"}
}