{
  "type": "Feature",
  "properties": {
    "gn:admin1_code":"18",
    "gn:admin2_code":"4104204.0",
    "gn:asciiname":"Palmitalzinho",
    "gn:country_code":"BR",
    "gn:dem":895,
    "gn:feature_class":"P",
    "gn:feature_code":"PPL",
    "gn:name":"Palmitalzinho",
    "gn:population":0,
    "gn:timezone":"America/Sao_Paulo",
    "iso:country":"BR",
    "wof:name":"Palmitalzinho",
    "wof:placetype":"locality"
},
  "geometry": {"coordinates":[-49.78333,-25.21667],"type":"Point"}
}