{
  "type": "Feature",
  "properties": {
    "gn:admin1_code":"22",
    "gn:admin2_code":"2407500.0",
    "gn:asciiname":"Ubanheira",
    "gn:country_code":"BR",
    "gn:dem":46,
    "gn:feature_class":"P",
    "gn:feature_code":"PPL",
    "gn:name":"Ubanheira",
    "gn:population":0,
    "gn:timezone":"America/Fortaleza",
    "iso:country":"BR",
    "wof:name":"Ubanheira",
    "wof:placetype":"locality"
},
  "geometry": {"coordinates":[-35.43333,-5.45],"type":"Point"}
}