{
  "type": "Feature",
  "properties": {
    "gn:admin1_code":"23",
    "gn:admin2_code":"4322343.0",
    "gn:asciiname":"Vinte e Tres de Julho",
    "gn:cc2":"BR",
    "gn:country_code":"BR",
    "gn:dem":290,
    "gn:feature_class":"P",
    "gn:feature_code":"PPL",
    "gn:name":"Vinte e Tr\u00eas de Julho",
    "gn:population":0,
    "gn:timezone":"America/Sao_Paulo",
    "iso:country":"BR",
    "name:und_x_variant":[
        "23 de Julho",
        "Vinte e Tr\u00eas de Julho"
    ],
    "wof:name":"Vinte e Tres de Julho",
    "wof:placetype":"locality"
},
  "geometry": {"coordinates":[-54.61666999999999,-27.96667],"type":"Point"}
}