{
  "type": "Feature",
  "properties": {
    "gn:admin1_code":"05",
    "gn:admin2_code":"2907707.0",
    "gn:asciiname":"Mato Verde",
    "gn:country_code":"BR",
    "gn:dem":446,
    "gn:feature_class":"P",
    "gn:feature_code":"PPL",
    "gn:name":"Mato Verde",
    "gn:population":0,
    "gn:timezone":"America/Bahia",
    "iso:country":"BR",
    "name:bpy_x_preferred":[
        "\u09ae\u09be\u099f\u09cb \u09ad\u09c7\u09b0\u09cd\u09a1\u09c7"
    ],
    "name:ceb_x_preferred":[
        "Mato Verde"
    ],
    "name:epo_x_preferred":[
        "Mato Verde"
    ],
    "name:eus_x_preferred":[
        "Mato Verde"
    ],
    "name:fra_x_preferred":[
        "Mato Verde"
    ],
    "name:ita_x_preferred":[
        "Mato Verde"
    ],
    "name:kat_x_preferred":[
        "\u10db\u10d0\u10e2\u10e3-\u10d5\u10d4\u10e0\u10d3\u10d8"
    ],
    "name:kaz_x_preferred":[
        "\u041c\u0430\u0442\u0443-\u0412\u0435\u0440\u0434\u0438"
    ],
    "name:mlg_x_preferred":[
        "Mato Verde"
    ],
    "name:nld_x_preferred":[
        "Mato Verde"
    ],
    "name:nor_x_preferred":[
        "Mato Verde"
    ],
    "name:pol_x_preferred":[
        "Mato Verde"
    ],
    "name:por_x_preferred":[
        "Mato Verde"
    ],
    "name:ron_x_preferred":[
        "Mato Verde"
    ],
    "name:rus_x_preferred":[
        "\u041c\u0430\u0442\u0443-\u0412\u0435\u0440\u0434\u0438"
    ],
    "name:swe_x_preferred":[
        "Mato Verde"
    ],
    "name:vie_x_preferred":[
        "Mato Verde"
    ],
    "name:vol_x_preferred":[
        "Mato Verde"
    ],
    "name:war_x_preferred":[
        "Mato Verde"
    ],
    "name:zho_x_preferred":[
        "\u9a6c\u56fe\u97e6\u5c14\u8fea"
    ],
    "wof:name":"Mato Verde",
    "wof:placetype":"locality"
},
  "geometry": {"coordinates":[-39.35,-9.45],"type":"Point"}
}