{
  "type": "Feature",
  "properties": {
    "gn:admin1_code":"30",
    "gn:admin2_code":"2612802.0",
    "gn:asciiname":"Bandeira",
    "gn:country_code":"BR",
    "gn:dem":792,
    "gn:feature_class":"P",
    "gn:feature_code":"PPL",
    "gn:name":"Bandeira",
    "gn:population":0,
    "gn:timezone":"America/Recife",
    "iso:country":"BR",
    "wof:name":"Bandeira",
    "wof:placetype":"locality"
},
  "geometry": {"coordinates":[-37.38333,-7.38333],"type":"Point"}
}