{
  "type": "Feature",
  "properties": {
    "gn:admin1_code":"18",
    "gn:admin2_code":"4127601.0",
    "gn:asciiname":"Sitio Joaquim M. Alves",
    "gn:country_code":"BR",
    "gn:dem":915,
    "gn:feature_class":"P",
    "gn:feature_code":"PPL",
    "gn:name":"S\u00edtio Joaquim M. Alves",
    "gn:population":0,
    "gn:timezone":"America/Sao_Paulo",
    "iso:country":"BR",
    "name:por_x_preferred":[
        "S\u00edtio Joaquim M. Alves"
    ],
    "wof:name":"Sitio Joaquim M. Alves",
    "wof:placetype":"locality"
},
  "geometry": {"coordinates":[-49.1816,-25.8746],"type":"Point"}
}