{
  "type": "Feature",
  "properties": {
    "gn:country":"BR",
    "gn:fcode":"PPL",
    "gn:population":32791,
    "iso:country":"BR",
    "name:ara_x_preferred":[
        "\u062a\u0648\u0631\u064a\u0633"
    ],
    "name:bpy_x_preferred":[
        "\u099f\u09cb\u09b0\u09cd\u09b0\u09c7\u09b8"
    ],
    "name:ceb_x_preferred":[
        "Torres"
    ],
    "name:deu_x_preferred":[
        "Torres"
    ],
    "name:eng_x_preferred":[
        "Torres"
    ],
    "name:epo_x_preferred":[
        "Torres"
    ],
    "name:eus_x_preferred":[
        "Torres"
    ],
    "name:fra_x_preferred":[
        "Torres"
    ],
    "name:hun_x_preferred":[
        "Torres"
    ],
    "name:ita_x_preferred":[
        "Torres"
    ],
    "name:jpn_x_preferred":[
        "\u30c8\u30fc\u30ec\u30b9"
    ],
    "name:kaz_x_preferred":[
        "\u0422\u043e\u0440\u0440\u0438\u0441"
    ],
    "name:mlg_x_preferred":[
        "Torres"
    ],
    "name:nan_x_preferred":[
        "Torres"
    ],
    "name:nld_x_preferred":[
        "Torres"
    ],
    "name:nob_x_preferred":[
        "Torres"
    ],
    "name:pol_x_preferred":[
        "Torres"
    ],
    "name:por_x_preferred":[
        "Torres"
    ],
    "name:ron_x_preferred":[
        "Torres"
    ],
    "name:rus_x_preferred":[
        "\u0422\u043e\u0440\u0440\u0435\u0441"
    ],
    "name:rus_x_variant":[
        "\u0422\u043e\u0440\u0440\u0438\u0441"
    ],
    "name:spa_x_preferred":[
        "Torres"
    ],
    "name:swe_x_preferred":[
        "Torres"
    ],
    "name:vol_x_preferred":[
        "Torres"
    ],
    "name:war_x_preferred":[
        "Torres"
    ],
    "name:zho_x_preferred":[
        "\u6258\u91cc\u65af"
    ],
    "name:zho_x_variant":[
        "Torres"
    ],
    "qs_pg:aaroncc":"BR",
    "qs_pg:gn_country":"BR",
    "qs_pg:gn_fcode":"PPL",
    "qs_pg:gn_pop":32791,
    "qs_pg:name":"T\u00f4rres",
    "qs_pg:name_adm0":"Brasil",
    "qs_pg:name_adm1":"Rio Grande do Sul",
    "qs_pg:photos":1407,
    "qs_pg:photos_1k":285,
    "qs_pg:photos_9k":6,
    "qs_pg:photos_9r":7,
    "qs_pg:photos_all":1407,
    "qs_pg:photos_sr":12,
    "qs_pg:pop_sr":7,
    "qs_pg:qs_pg_placetype":"locality",
    "qs_pg:qs_pg_placetype_gp":"Town",
    "qs_pg:woe_adm0":23424768,
    "woe:adm0_id":23424768,
    "woe:name_adm0":"Brasil",
    "woe:name_adm1":"Rio Grande do Sul",
    "woe:placetype":"Town",
    "wof:name":"T\u00f4rres",
    "wof:placetype":"locality",
    "wof:population":32791
},
  "geometry": {"coordinates":[-49.72694,-29.33528],"type":"Point"}
}