{
  "type": "Feature",
  "properties": {
    "gn:admin1_code":"06",
    "gn:admin2_code":"2300200.0",
    "gn:asciiname":"Sao Felipe",
    "gn:country_code":"BR",
    "gn:dem":21,
    "gn:feature_class":"P",
    "gn:feature_code":"PPL",
    "gn:name":"S\u00e3o Felipe",
    "gn:population":0,
    "gn:timezone":"America/Fortaleza",
    "iso:country":"BR",
    "wof:name":"Sao Felipe",
    "wof:placetype":"locality"
},
  "geometry": {"coordinates":[-40.08333,-2.86667],"type":"Point"}
}