{
  "type": "Feature",
  "properties": {
    "gn:admin1_code":"18.0",
    "gn:admin2_code":"4116208.0",
    "gn:asciiname":"Sitio Irmaos Kreutzir",
    "gn:country_code":"BR",
    "gn:dem":68,
    "gn:feature_class":"P",
    "gn:feature_code":"PPL",
    "gn:name":"S\u00edtio Irm\u00e3os Kreutzir",
    "gn:population":0,
    "gn:timezone":"America/Sao_Paulo",
    "iso:country":"BR",
    "name:por_x_preferred":[
        "S\u00edtio Irm\u00e3os Kreutzir"
    ],
    "wof:name":"Sitio Irmaos Kreutzir",
    "wof:placetype":"locality"
},
  "geometry": {"coordinates":[-48.8576,-25.5437],"type":"Point"}
}