{
  "type": "Feature",
  "properties": {
    "gn:admin1_code":"20",
    "gn:admin2_code":"2208106.0",
    "gn:asciiname":"Torres",
    "gn:country_code":"BR",
    "gn:dem":421,
    "gn:feature_class":"P",
    "gn:feature_code":"PPL",
    "gn:name":"Torres",
    "gn:population":0,
    "gn:timezone":"America/Fortaleza",
    "iso:country":"BR",
    "name:bel_x_preferred":[
        "\u0422\u043e\u0440\u044d\u0441"
    ],
    "name:bre_x_preferred":[
        "Torres"
    ],
    "name:cat_x_preferred":[
        "Torres"
    ],
    "name:ceb_x_preferred":[
        "Torres"
    ],
    "name:deu_x_preferred":[
        "Torres"
    ],
    "name:eus_x_preferred":[
        "Torres"
    ],
    "name:fin_x_preferred":[
        "Torres"
    ],
    "name:fra_x_preferred":[
        "Torres"
    ],
    "name:glg_x_preferred":[
        "Torres"
    ],
    "name:heb_x_preferred":[
        "\u05d8\u05d5\u05e8\u05e1"
    ],
    "name:ita_x_preferred":[
        "Torres"
    ],
    "name:jpn_x_preferred":[
        "\u30c8\u30fc\u30ec\u30b9"
    ],
    "name:kor_x_preferred":[
        "\ud1a0\ub808\uc2a4"
    ],
    "name:lat_x_preferred":[
        "Torres"
    ],
    "name:lav_x_preferred":[
        "Torres"
    ],
    "name:nld_x_preferred":[
        "Torres"
    ],
    "name:nor_x_preferred":[
        "Torres"
    ],
    "name:pol_x_preferred":[
        "Torres"
    ],
    "name:por_x_preferred":[
        "Torres"
    ],
    "name:rus_x_preferred":[
        "\u0422\u043e\u0440\u0440\u0435\u0441"
    ],
    "name:spa_x_preferred":[
        "Torres"
    ],
    "name:swe_x_preferred":[
        "Torres"
    ],
    "name:tha_x_preferred":[
        "\u0e17\u0e2d\u0e23\u0e4c\u0e40\u0e23\u0e2a"
    ],
    "name:tur_x_preferred":[
        "Torres"
    ],
    "name:ukr_x_preferred":[
        "\u0422\u043e\u0440\u0440\u0435\u0441"
    ],
    "name:vie_x_preferred":[
        "Torres"
    ],
    "name:zho_x_preferred":[
        "\u6258\u5229\u65af"
    ],
    "wof:name":"Torres",
    "wof:placetype":"locality"
},
  "geometry": {"coordinates":[-41.16667,-6.28333],"type":"Point"}
}