{
  "type": "Feature",
  "properties": {
    "gn:admin1_code":"18",
    "gn:admin2_code":"4103156.0",
    "gn:asciiname":"Linha Sertaneja",
    "gn:country_code":"BR",
    "gn:dem":587,
    "gn:feature_class":"P",
    "gn:feature_code":"PPL",
    "gn:name":"Linha Sertaneja",
    "gn:population":0,
    "gn:timezone":"America/Sao_Paulo",
    "iso:country":"BR",
    "wof:name":"Linha Sertaneja",
    "wof:placetype":"locality"
},
  "geometry": {"coordinates":[-53.6125,-26.19833],"type":"Point"}
}