{
  "type": "Feature",
  "properties": {
    "gn:admin1_code":"18",
    "gn:admin2_code":"4116307.0",
    "gn:asciiname":"Granada",
    "gn:country_code":"BR",
    "gn:dem":614,
    "gn:feature_class":"P",
    "gn:feature_code":"PPL",
    "gn:name":"Granada",
    "gn:population":0,
    "gn:timezone":"America/Sao_Paulo",
    "iso:country":"BR",
    "wof:name":"Granada",
    "wof:placetype":"locality"
},
  "geometry": {"coordinates":[-51.73333,-23.21667],"type":"Point"}
}