{
  "type": "Feature",
  "properties": {
    "gn:admin1_code":"20",
    "gn:admin2_code":"2201507.0",
    "gn:asciiname":"Morro do Cachimbo",
    "gn:country_code":"BR",
    "gn:dem":77,
    "gn:feature_class":"P",
    "gn:feature_code":"PPL",
    "gn:name":"Morro do Cachimbo",
    "gn:population":0,
    "gn:timezone":"America/Fortaleza",
    "iso:country":"BR",
    "wof:name":"Morro do Cachimbo",
    "wof:placetype":"locality"
},
  "geometry": {"coordinates":[-42.02778,-3.94472],"type":"Point"}
}