{
  "type": "Feature",
  "properties": {
    "gn:admin1_code":"15",
    "gn:admin2_code":"3134707.0",
    "gn:asciiname":"Firmino",
    "gn:country_code":"BR",
    "gn:dem":361,
    "gn:feature_class":"P",
    "gn:feature_code":"PPL",
    "gn:name":"Firmino",
    "gn:population":0,
    "gn:timezone":"America/Sao_Paulo",
    "iso:country":"BR",
    "name:deu_x_preferred":[
        "Firmino"
    ],
    "name:por_x_preferred":[
        "Firmino"
    ],
    "name:ukr_x_preferred":[
        "\u0424\u0456\u0440\u043c\u0456\u043d\u043e"
    ],
    "wof:name":"Firmino",
    "wof:placetype":"locality"
},
  "geometry": {"coordinates":[-40.36667,-16.06667],"type":"Point"}
}