{
  "type": "Feature",
  "properties": {
    "gn:admin1_code":"18.0",
    "gn:admin2_code":"4109708.0",
    "gn:asciiname":"Sitio Recanto do Sabia",
    "gn:country_code":"BR",
    "gn:dem":759,
    "gn:feature_class":"P",
    "gn:feature_code":"PPL",
    "gn:name":"S\u00edtio Recanto do Sabi\u00e1",
    "gn:population":0,
    "gn:timezone":"America/Sao_Paulo",
    "iso:country":"BR",
    "name:por_x_preferred":[
        "S\u00edtio Recanto do Sabi\u00e1"
    ],
    "wof:name":"Sitio Recanto do Sabia",
    "wof:placetype":"locality"
},
  "geometry": {"coordinates":[-50.16464000000001,-23.90648],"type":"Point"}
}