{
  "type": "Feature",
  "properties": {
    "gn:admin1_code":"18.0",
    "gn:admin2_code":"4121802.0",
    "gn:asciiname":"Sitio Ouro Verde",
    "gn:country_code":"BR",
    "gn:dem":502,
    "gn:feature_class":"P",
    "gn:feature_code":"PPL",
    "gn:name":"S\u00edtio Ouro Verde",
    "gn:population":0,
    "gn:timezone":"America/Sao_Paulo",
    "iso:country":"BR",
    "name:por_x_preferred":[
        "S\u00edtio Ouro Verde"
    ],
    "wof:name":"Sitio Ouro Verde",
    "wof:placetype":"locality"
},
  "geometry": {"coordinates":[-49.79634,-23.1877],"type":"Point"}
}