{
  "type": "Feature",
  "properties": {
    "gn:admin1_code":"22",
    "gn:admin2_code":"2411601.0",
    "gn:asciiname":"Sao Joao",
    "gn:country_code":"BR",
    "gn:dem":38,
    "gn:feature_class":"P",
    "gn:feature_code":"PPL",
    "gn:name":"S\u00e2o Jo\u00e3o",
    "gn:population":0,
    "gn:timezone":"America/Fortaleza",
    "iso:country":"BR",
    "wof:name":"Sao Joao",
    "wof:placetype":"locality"
},
  "geometry": {"coordinates":[-35.96667,-5.16667],"type":"Point"}
}