{
  "type": "Feature",
  "properties": {
    "gn:admin1_code":"26.0",
    "gn:admin2_code":"4209102.0",
    "gn:asciiname":"Vila Nova",
    "gn:country_code":"BR",
    "gn:dem":24,
    "gn:feature_class":"P",
    "gn:feature_code":"PPL",
    "gn:name":"Vila Nova",
    "gn:population":0,
    "gn:timezone":"America/Sao_Paulo",
    "iso:country":"BR",
    "name:ceb_x_preferred":[
        "Vila Nova"
    ],
    "name:deu_x_preferred":[
        "Vila Nova"
    ],
    "name:fas_x_preferred":[
        "\u0648\u06cc\u0644\u0627 \u0646\u0648\u0627"
    ],
    "name:fra_x_preferred":[
        "Vila Nova"
    ],
    "name:jpn_x_preferred":[
        "\u30f4\u30a3\u30e9\u30fb\u30ce\u30f4\u30a1"
    ],
    "name:kaz_x_preferred":[
        "\u0412\u0438\u043b\u0430-\u041d\u043e\u0432\u0430"
    ],
    "name:nld_x_preferred":[
        "Vila Nova"
    ],
    "name:por_x_preferred":[
        "Vila Nova"
    ],
    "name:rus_x_preferred":[
        "\u0412\u0438\u043b\u0430-\u041d\u043e\u0432\u0430"
    ],
    "name:sco_x_preferred":[
        "Vila Nova"
    ],
    "name:swe_x_preferred":[
        "Vila Nova"
    ],
    "name:tur_x_preferred":[
        "Vila Nova"
    ],
    "name:ukr_x_preferred":[
        "\u0412\u0456\u043b\u0430-\u041d\u043e\u0432\u0430"
    ],
    "wof:name":"Vila Nova",
    "wof:placetype":"locality"
},
  "geometry": {"coordinates":[-48.91114,-26.28431],"type":"Point"}
}