{
  "type": "Feature",
  "properties": {
    "gn:admin1_code":"26.0",
    "gn:admin2_code":"4209102.0",
    "gn:asciiname":"Vila Nova",
    "gn:country_code":"BR",
    "gn:dem":24,
    "gn:feature_class":"P",
    "gn:feature_code":"PPL",
    "gn:name":"Vila Nova",
    "gn:population":0,
    "gn:timezone":"America/Sao_Paulo",
    "iso:country":"BR",
    "wof:name":"Vila Nova",
    "wof:placetype":"locality"
},
  "geometry": {"coordinates":[-48.91114,-26.28431],"type":"Point"}
}