{
  "type": "Feature",
  "properties": {
    "gn:admin1_code":"18.0",
    "gn:admin2_code":"4126207.0",
    "gn:asciiname":"Sitio Paixao",
    "gn:country_code":"BR",
    "gn:dem":580,
    "gn:feature_class":"P",
    "gn:feature_code":"PPL",
    "gn:name":"S\u00edtio Paix\u00e3o",
    "gn:population":0,
    "gn:timezone":"America/Sao_Paulo",
    "iso:country":"BR",
    "name:por_x_preferred":[
        "S\u00edtio Paix\u00e3o"
    ],
    "wof:name":"Sitio Paixao",
    "wof:placetype":"locality"
},
  "geometry": {"coordinates":[-50.48732,-23.84421],"type":"Point"}
}