{
  "type": "Feature",
  "properties": {
    "gn:admin1_code":"27.0",
    "gn:admin2_code":"3505708.0",
    "gn:asciiname":"Vila do Conde",
    "gn:country_code":"BR",
    "gn:dem":783,
    "gn:feature_class":"P",
    "gn:feature_code":"PPL",
    "gn:name":"Vila do Conde",
    "gn:population":0,
    "gn:timezone":"America/Sao_Paulo",
    "iso:country":"BR",
    "wof:name":"Vila do Conde",
    "wof:placetype":"locality"
},
  "geometry": {"coordinates":[-46.8681,-23.53155],"type":"Point"}
}