{
  "type": "Feature",
  "properties": {
    "gn:admin1_code":"27.0",
    "gn:admin2_code":"3505708.0",
    "gn:asciiname":"Vila do Conde",
    "gn:country_code":"BR",
    "gn:dem":783,
    "gn:feature_class":"P",
    "gn:feature_code":"PPL",
    "gn:name":"Vila do Conde",
    "gn:population":0,
    "gn:timezone":"America/Sao_Paulo",
    "iso:country":"BR",
    "name:ara_x_preferred":[
        "\u0641\u064a\u0644\u0627 \u062f\u0648 \u0643\u0648\u0646\u062f\u064a"
    ],
    "name:fas_x_preferred":[
        "\u0648\u06cc\u0644\u0627 \u062f\u0648 \u06a9\u0646\u062f\u0647"
    ],
    "name:kat_x_preferred":[
        "\u10d5\u10d8\u10da\u10d0-\u10d3\u10e3-\u10d9\u10dd\u10dc\u10d3\u10d4"
    ],
    "name:kor_x_preferred":[
        "\ube4c\ub77c\ub450\ucf58\ub4dc"
    ],
    "name:mzn_x_preferred":[
        "\u0648\u06cc\u0644\u0627 \u062f\u0648 \u06a9\u0646\u062f\u0647"
    ],
    "name:rus_x_preferred":[
        "\u0412\u0438\u043b\u0430-\u0434\u0443-\u041a\u043e\u043d\u0434\u0438"
    ],
    "name:ukr_x_preferred":[
        "\u0412\u0456\u043b\u0430-\u0434\u0443-\u041a\u043e\u043d\u0434\u0435"
    ],
    "name:zho_x_preferred":[
        "\u5b54\u8fea\u9547"
    ],
    "wof:name":"Vila do Conde",
    "wof:placetype":"locality"
},
  "geometry": {"coordinates":[-46.8681,-23.53155],"type":"Point"}
}