{
  "type": "Feature",
  "properties": {
    "gn:admin1_code":"5",
    "gn:admin2_code":"2906824.0",
    "gn:asciiname":"Angicos",
    "gn:country_code":"BR",
    "gn:dem":518,
    "gn:feature_class":"P",
    "gn:feature_code":"PPL",
    "gn:name":"Angicos",
    "gn:population":0,
    "gn:timezone":"America/Bahia",
    "iso:country":"BR",
    "name:bpy_x_preferred":[
        "\u0986\u0999\u09cd\u0997\u09bf\u0995\u09cb\u09b8"
    ],
    "name:ceb_x_preferred":[
        "Angicos"
    ],
    "name:epo_x_preferred":[
        "Angicos"
    ],
    "name:eus_x_preferred":[
        "Angicos"
    ],
    "name:fas_x_preferred":[
        "\u0622\u0646\u06af\u06cc\u06a9\u0648\u0633"
    ],
    "name:fra_x_preferred":[
        "Angicos"
    ],
    "name:ita_x_preferred":[
        "Angicos"
    ],
    "name:kat_x_preferred":[
        "\u10d0\u10dc\u10df\u10d8\u10d9\u10e3\u10e1\u10d8"
    ],
    "name:kaz_x_preferred":[
        "\u0410\u043d\u0436\u0438\u043a\u0443\u0441"
    ],
    "name:mlg_x_preferred":[
        "Angicos"
    ],
    "name:nld_x_preferred":[
        "Angicos"
    ],
    "name:nor_x_preferred":[
        "Angicos"
    ],
    "name:por_x_preferred":[
        "Angicos"
    ],
    "name:ron_x_preferred":[
        "Angicos"
    ],
    "name:rus_x_preferred":[
        "\u0410\u043d\u0436\u0438\u043a\u0443\u0441"
    ],
    "name:spa_x_preferred":[
        "Angicos"
    ],
    "name:swe_x_preferred":[
        "Angicos"
    ],
    "name:vie_x_preferred":[
        "Angicos"
    ],
    "name:vol_x_preferred":[
        "Angicos"
    ],
    "name:war_x_preferred":[
        "Angicos"
    ],
    "name:zho_x_preferred":[
        "\u5b89\u65e5\u5e93\u65af"
    ],
    "wof:name":"Angicos",
    "wof:placetype":"locality"
},
  "geometry": {"coordinates":[-38.86667,-10.18333],"type":"Point"}
}