{
  "type": "Feature",
  "properties": {
    "gn:admin1_code":"5",
    "gn:admin2_code":"2906824.0",
    "gn:asciiname":"Angicos",
    "gn:country_code":"BR",
    "gn:dem":518,
    "gn:feature_class":"P",
    "gn:feature_code":"PPL",
    "gn:name":"Angicos",
    "gn:population":0,
    "gn:timezone":"America/Bahia",
    "iso:country":"BR",
    "wof:name":"Angicos",
    "wof:placetype":"locality"
},
  "geometry": {"coordinates":[-38.86667,-10.18333],"type":"Point"}
}