{
  "type": "Feature",
  "properties": {
    "gn:admin1_code":"15",
    "gn:admin2_code":"3137700.0",
    "gn:asciiname":"Sao Joaquim",
    "gn:country_code":"BR",
    "gn:dem":636,
    "gn:feature_class":"P",
    "gn:feature_code":"PPL",
    "gn:name":"S\u00e3o Joaquim",
    "gn:population":0,
    "gn:timezone":"America/Sao_Paulo",
    "iso:country":"BR",
    "name:por_x_preferred":[
        "S\u00e3o Joaquim"
    ],
    "wof:name":"Sao Joaquim",
    "wof:placetype":"locality"
},
  "geometry": {"coordinates":[-41.55,-20.05],"type":"Point"}
}