{
  "type": "Feature",
  "properties": {
    "gn:admin1_code":"5",
    "gn:admin2_code":"2913804.0",
    "gn:asciiname":"Sitio Novo",
    "gn:country_code":"BR",
    "gn:dem":187,
    "gn:feature_class":"P",
    "gn:feature_code":"PPL",
    "gn:name":"S\u00edtio Novo",
    "gn:population":0,
    "gn:timezone":"America/Bahia",
    "iso:country":"BR",
    "wof:name":"Sitio Novo",
    "wof:placetype":"locality"
},
  "geometry": {"coordinates":[-39.36667,-12.38333],"type":"Point"}
}