{
  "type": "Feature",
  "properties": {
    "gn:admin1_code":"27",
    "gn:admin2_code":"3504107.0",
    "gn:asciiname":"Sitio Gramado",
    "gn:country_code":"BR",
    "gn:dem":770,
    "gn:feature_class":"P",
    "gn:feature_code":"PPL",
    "gn:name":"S\u00edtio Gramado",
    "gn:population":0,
    "gn:timezone":"America/Sao_Paulo",
    "iso:country":"BR",
    "name:por_x_preferred":[
        "S\u00edtio Gramado"
    ],
    "wof:name":"Sitio Gramado",
    "wof:placetype":"locality"
},
  "geometry": {"coordinates":[-46.64944000000001,-23.06111],"type":"Point"}
}