{
  "type": "Feature",
  "properties": {
    "gn:admin1_code":"28",
    "gn:admin2_code":"2801207.0",
    "gn:asciiname":"Belo Horizonte",
    "gn:country_code":"BR",
    "gn:dem":288,
    "gn:feature_class":"P",
    "gn:feature_code":"PPL",
    "gn:name":"Belo Horizonte",
    "gn:population":0,
    "gn:timezone":"America/Maceio",
    "iso:country":"BR",
    "wof:name":"Belo Horizonte",
    "wof:placetype":"locality"
},
  "geometry": {"coordinates":[-37.86667,-9.78333],"type":"Point"}
}