{
  "type": "Feature",
  "properties": {
    "gn:admin1_code":"5",
    "gn:admin2_code":"2911105.0",
    "gn:asciiname":"Cabeceira Velha",
    "gn:country_code":"BR",
    "gn:dem":728,
    "gn:feature_class":"P",
    "gn:feature_code":"PPL",
    "gn:name":"Cabeceira Velha",
    "gn:population":0,
    "gn:timezone":"America/Bahia",
    "iso:country":"BR",
    "wof:name":"Cabeceira Velha",
    "wof:placetype":"locality"
},
  "geometry": {"coordinates":[-46.33333,-11.31667],"type":"Point"}
}