{
  "type": "Feature",
  "properties": {
    "gn:admin1_code":"06",
    "gn:admin2_code":"2311264.0",
    "gn:asciiname":"Sariema",
    "gn:country_code":"BR",
    "gn:dem":368,
    "gn:feature_class":"P",
    "gn:feature_code":"PPL",
    "gn:name":"Sariema",
    "gn:population":0,
    "gn:timezone":"America/Fortaleza",
    "iso:country":"BR",
    "wof:name":"Sariema",
    "wof:placetype":"locality"
},
  "geometry": {"coordinates":[-40.68333,-5.68333],"type":"Point"}
}