{
  "type": "Feature",
  "properties": {
    "gn:admin1_code":"31",
    "gn:admin2_code":"1707405.0",
    "gn:asciiname":"Pedra de Amolar",
    "gn:country_code":"BR",
    "gn:dem":94,
    "gn:feature_class":"P",
    "gn:feature_code":"PPL",
    "gn:name":"Pedra de Amolar",
    "gn:population":0,
    "gn:timezone":"America/Araguaina",
    "iso:country":"BR",
    "wof:name":"Pedra de Amolar",
    "wof:placetype":"locality"
},
  "geometry": {"coordinates":[-48.65,-5.33333],"type":"Point"}
}