{
  "type": "Feature",
  "properties": {
    "gn:admin1_code":"31",
    "gn:admin2_code":"1703826.0",
    "gn:asciiname":"Cachoeirinha",
    "gn:country_code":"BR",
    "gn:dem":197,
    "gn:feature_class":"P",
    "gn:feature_code":"PPL",
    "gn:name":"Cachoeirinha",
    "gn:population":0,
    "gn:timezone":"America/Araguaina",
    "iso:country":"BR",
    "wof:name":"Cachoeirinha",
    "wof:placetype":"locality"
},
  "geometry": {"coordinates":[-47.91587,-6.11987],"type":"Point"}
}