{
  "type": "Feature",
  "properties": {
    "gn:admin1_code":"17",
    "gn:admin2_code":"2502508.0",
    "gn:asciiname":"Poco Doce",
    "gn:country_code":"BR",
    "gn:dem":373,
    "gn:feature_class":"P",
    "gn:feature_code":"PPL",
    "gn:name":"Poco Doce",
    "gn:population":0,
    "gn:timezone":"America/Fortaleza",
    "iso:country":"BR",
    "wof:name":"Poco Doce",
    "wof:placetype":"locality"
},
  "geometry": {"coordinates":[-36.18333,-7.51667],"type":"Point"}
}