{
  "type": "Feature",
  "properties": {
    "gn:admin1_code":"22",
    "gn:admin2_code":"2409506.0",
    "gn:asciiname":"Carnauba Enterrada",
    "gn:country_code":"BR",
    "gn:dem":1,
    "gn:feature_class":"P",
    "gn:feature_code":"PPL",
    "gn:name":"Carna\u00faba Enterrada",
    "gn:population":0,
    "gn:timezone":"America/Fortaleza",
    "iso:country":"BR",
    "wof:name":"Carnauba Enterrada",
    "wof:placetype":"locality"
},
  "geometry": {"coordinates":[-35.88333,-5.06667],"type":"Point"}
}