{
  "type": "Feature",
  "properties": {
    "gn:admin1_code":"11",
    "gn:admin2_code":"5006309.0",
    "gn:asciiname":"Nova Jales",
    "gn:country_code":"BR",
    "gn:dem":456,
    "gn:feature_class":"P",
    "gn:feature_code":"PPLL",
    "gn:name":"Nova Jales",
    "gn:population":0,
    "gn:timezone":"America/Campo_Grande",
    "iso:country":"BR",
    "wof:name":"Nova Jales",
    "wof:placetype":"locality"
},
  "geometry": {"coordinates":[-51.32,-19.36167],"type":"Point"}
}