{
  "type": "Feature",
  "properties": {
    "gn:admin1_code":"18.0",
    "gn:admin2_code":"4103107.0",
    "gn:asciiname":"Sitio Nilson",
    "gn:country_code":"BR",
    "gn:dem":798,
    "gn:feature_class":"P",
    "gn:feature_code":"PPL",
    "gn:name":"S\u00edtio Nilson",
    "gn:population":0,
    "gn:timezone":"America/Sao_Paulo",
    "iso:country":"BR",
    "name:por_x_preferred":[
        "S\u00edtio Nilson"
    ],
    "wof:name":"Sitio Nilson",
    "wof:placetype":"locality"
},
  "geometry": {"coordinates":[-48.93327,-25.19104],"type":"Point"}
}