{
  "type": "Feature",
  "properties": {
    "gn:admin1_code":"18.0",
    "gn:admin2_code":"4109609.0",
    "gn:asciiname":"Sitio Porteiro",
    "gn:country_code":"BR",
    "gn:dem":493,
    "gn:feature_class":"P",
    "gn:feature_code":"PPL",
    "gn:name":"S\u00edtio Porteiro",
    "gn:population":0,
    "gn:timezone":"America/Sao_Paulo",
    "iso:country":"BR",
    "name:por_x_preferred":[
        "S\u00edtio Porteiro"
    ],
    "wof:name":"Sitio Porteiro",
    "wof:placetype":"locality"
},
  "geometry": {"coordinates":[-48.90107,-25.83133],"type":"Point"}
}