{
  "type": "Feature",
  "properties": {
    "gn:admin1_code":"18",
    "gn:admin2_code":"4127601.0",
    "gn:asciiname":"Sitio Jair",
    "gn:country_code":"BR",
    "gn:dem":911,
    "gn:feature_class":"P",
    "gn:feature_code":"PPL",
    "gn:name":"S\u00edtio Jair",
    "gn:population":0,
    "gn:timezone":"America/Sao_Paulo",
    "iso:country":"BR",
    "name:por_x_preferred":[
        "S\u00edtio Jair"
    ],
    "wof:name":"Sitio Jair",
    "wof:placetype":"locality"
},
  "geometry": {"coordinates":[-49.1468,-25.9199],"type":"Point"}
}