{
  "type": "Feature",
  "properties": {
    "gn:admin1_code":"18",
    "gn:admin2_code":"4127601.0",
    "gn:asciiname":"Sitio Francisco A. Moreira",
    "gn:country_code":"BR",
    "gn:dem":923,
    "gn:feature_class":"P",
    "gn:feature_code":"PPL",
    "gn:name":"S\u00edtio Francisco A. Moreira",
    "gn:population":0,
    "gn:timezone":"America/Sao_Paulo",
    "iso:country":"BR",
    "name:por_x_preferred":[
        "S\u00edtio Francisco A. Moreira"
    ],
    "wof:name":"Sitio Francisco A. Moreira",
    "wof:placetype":"locality"
},
  "geometry": {"coordinates":[-49.23114,-25.9499],"type":"Point"}
}