{
  "type": "Feature",
  "properties": {
    "gn:admin1_code":"5",
    "gn:admin2_code":"2914208.0",
    "gn:asciiname":"Graciosa",
    "gn:country_code":"BR",
    "gn:dem":537,
    "gn:feature_class":"P",
    "gn:feature_code":"PPL",
    "gn:name":"Graciosa",
    "gn:population":0,
    "gn:timezone":"America/Bahia",
    "iso:country":"BR",
    "wof:name":"Graciosa",
    "wof:placetype":"locality"
},
  "geometry": {"coordinates":[-40.01667,-13.26667],"type":"Point"}
}