{
  "type": "Feature",
  "properties": {
    "gn:admin1_code":"30",
    "gn:admin2_code":"2607604.0",
    "gn:asciiname":"Jaguaribe",
    "gn:country_code":"BR",
    "gn:dem":-9999,
    "gn:feature_class":"P",
    "gn:feature_code":"PPL",
    "gn:name":"Jaguaribe",
    "gn:population":0,
    "gn:timezone":"America/Noronha",
    "iso:country":"BR",
    "wof:name":"Jaguaribe",
    "wof:placetype":"locality"
},
  "geometry": {"coordinates":[-34.81667,-7.73333],"type":"Point"}
}