{
  "type": "Feature",
  "properties": {
    "gn:admin1_code":"30",
    "gn:admin2_code":"2607604.0",
    "gn:asciiname":"Jaguaribe",
    "gn:country_code":"BR",
    "gn:dem":-9999,
    "gn:feature_class":"P",
    "gn:feature_code":"PPL",
    "gn:name":"Jaguaribe",
    "gn:population":0,
    "gn:timezone":"America/Noronha",
    "iso:country":"BR",
    "name:bpy_x_preferred":[
        "\u099c\u09be\u0997\u09c1\u09f1\u09be\u09b0\u09bf\u09ac\u09c7"
    ],
    "name:ceb_x_preferred":[
        "Jaguaribe"
    ],
    "name:eus_x_preferred":[
        "Jaguaribe"
    ],
    "name:fra_x_preferred":[
        "Jaguaribe"
    ],
    "name:ita_x_preferred":[
        "Jaguaribe"
    ],
    "name:kat_x_preferred":[
        "\u10df\u10d0\u10d2\u10e3\u10d0\u10e0\u10d8\u10d1\u10d8"
    ],
    "name:kaz_x_preferred":[
        "\u0416\u0430\u0433\u0443\u0430\u0440\u0438\u0431\u0438"
    ],
    "name:nld_x_preferred":[
        "Jaguaribe"
    ],
    "name:nor_x_preferred":[
        "Jaguaribe"
    ],
    "name:por_x_preferred":[
        "Jaguaribe"
    ],
    "name:ron_x_preferred":[
        "Jaguaribe"
    ],
    "name:rus_x_preferred":[
        "\u0416\u0430\u0433\u0443\u0430\u0440\u0438\u0431\u0438"
    ],
    "name:swe_x_preferred":[
        "Jaguaribe"
    ],
    "name:urd_x_preferred":[
        "\u062c\u06af\u0631\u0628\u06d2"
    ],
    "name:vol_x_preferred":[
        "Jaguaribe"
    ],
    "name:war_x_preferred":[
        "Jaguaribe"
    ],
    "name:zho_x_preferred":[
        "\u96c5\u74dc\u91cc\u8c9d"
    ],
    "wof:name":"Jaguaribe",
    "wof:placetype":"locality"
},
  "geometry": {"coordinates":[-34.81667,-7.73333],"type":"Point"}
}