{
  "type": "Feature",
  "properties": {
    "gn:admin1_code":"27.0",
    "gn:admin2_code":"3509254.0",
    "gn:asciiname":"Sitio Nova Esperanca",
    "gn:country_code":"BR",
    "gn:dem":100,
    "gn:feature_class":"P",
    "gn:feature_code":"PPL",
    "gn:name":"S\u00edtio Nova Esperan\u00e7a",
    "gn:population":0,
    "gn:timezone":"America/Sao_Paulo",
    "iso:country":"BR",
    "name:por_x_preferred":[
        "S\u00edtio Nova Esperan\u00e7a"
    ],
    "wof:name":"Sitio Nova Esperanca",
    "wof:placetype":"locality"
},
  "geometry": {"coordinates":[-48.20708,-24.69807],"type":"Point"}
}