{
  "type": "Feature",
  "properties": {
    "gn:admin1_code":"24.0",
    "gn:admin2_code":"1101492.0",
    "gn:asciiname":"Fazenda Monte Castelo",
    "gn:country_code":"BR",
    "gn:dem":157,
    "gn:feature_class":"P",
    "gn:feature_code":"PPLL",
    "gn:name":"Fazenda Monte Castelo",
    "gn:population":0,
    "gn:timezone":"America/Porto_Velho",
    "iso:country":"BR",
    "wof:name":"Fazenda Monte Castelo",
    "wof:placetype":"locality"
},
  "geometry": {"coordinates":[-63.08774,-12.57607],"type":"Point"}
}