{
  "type": "Feature",
  "properties": {
    "gn:admin1_code":"18.0",
    "gn:admin2_code":"4119202.0",
    "gn:asciiname":"Sitio Braulio P. de Melo",
    "gn:country_code":"BR",
    "gn:dem":586,
    "gn:feature_class":"P",
    "gn:feature_code":"PPL",
    "gn:name":"S\u00edtio Br\u00e1ulio P. de Melo",
    "gn:population":0,
    "gn:timezone":"America/Sao_Paulo",
    "iso:country":"BR",
    "name:por_x_preferred":[
        "S\u00edtio Br\u00e1ulio P. de Melo"
    ],
    "wof:name":"Sitio Braulio P. de Melo",
    "wof:placetype":"locality"
},
  "geometry": {"coordinates":[-50.02922,-23.97615],"type":"Point"}
}