{
  "type": "Feature",
  "properties": {
    "gn:admin1_code":"5",
    "gn:admin2_code":"2924405.0",
    "gn:asciiname":"Lagoa dos Veados",
    "gn:country_code":"BR",
    "gn:dem":550,
    "gn:feature_class":"P",
    "gn:feature_code":"PPL",
    "gn:name":"Lagoa dos Veados",
    "gn:population":0,
    "gn:timezone":"America/Bahia",
    "iso:country":"BR",
    "wof:name":"Lagoa dos Veados",
    "wof:placetype":"locality"
},
  "geometry": {"coordinates":[-43.75,-10.31667],"type":"Point"}
}