{
  "type": "Feature",
  "properties": {
    "gn:admin1_code":"06",
    "gn:admin2_code":"2304301.0",
    "gn:asciiname":"Sitio Monteplo",
    "gn:country_code":"BR",
    "gn:dem":438,
    "gn:feature_class":"P",
    "gn:feature_code":"PPL",
    "gn:name":"S\u00edtio Monteplo",
    "gn:population":0,
    "gn:timezone":"America/Fortaleza",
    "iso:country":"BR",
    "wof:name":"Sitio Monteplo",
    "wof:placetype":"locality"
},
  "geometry": {"coordinates":[-39.48333,-6.98333],"type":"Point"}
}