{
  "type": "Feature",
  "properties": {
    "gn:admin1_code":"27",
    "gn:admin2_code":"3526209.0",
    "gn:asciiname":"Bairro dos Ferreiras",
    "gn:country_code":"BR",
    "gn:dem":712,
    "gn:feature_class":"P",
    "gn:feature_code":"PPL",
    "gn:name":"Bairro dos Ferreiras",
    "gn:population":0,
    "gn:timezone":"America/Sao_Paulo",
    "iso:country":"BR",
    "name:por_x_preferred":[
        "Bairro dos Ferreiras"
    ],
    "wof:name":"Bairro dos Ferreiras",
    "wof:placetype":"locality"
},
  "geometry": {"coordinates":[-47.17152,-23.94265],"type":"Point"}
}