{
  "type": "Feature",
  "properties": {
    "gn:admin1_code":"24",
    "gn:admin2_code":"1101104.0",
    "gn:asciiname":"Torno Largo",
    "gn:cc2":"BR",
    "gn:country_code":"BR",
    "gn:dem":105,
    "gn:feature_class":"P",
    "gn:feature_code":"PPL",
    "gn:name":"T\u00f4rno Largo",
    "gn:population":0,
    "gn:timezone":"America/Porto_Velho",
    "iso:country":"BR",
    "name:und_x_variant":[
        "Esta\u00e7\u00e3o Telegr\u00e1fica Torno Largo",
        "Providencia",
        "T\u00f4rno Largo"
    ],
    "wof:name":"Torno Largo",
    "wof:placetype":"locality"
},
  "geometry": {"coordinates":[-63.25,-9.11667],"type":"Point"}
}