{
  "type": "Feature",
  "properties": {
    "gn:admin1_code":"18.0",
    "gn:admin2_code":"4126603.0",
    "gn:asciiname":"Sitio Jose Candido",
    "gn:country_code":"BR",
    "gn:dem":639,
    "gn:feature_class":"P",
    "gn:feature_code":"PPL",
    "gn:name":"S\u00edtio Jos\u00e9 C\u00e2ndido",
    "gn:population":0,
    "gn:timezone":"America/Sao_Paulo",
    "iso:country":"BR",
    "name:por_x_preferred":[
        "S\u00edtio Jos\u00e9 C\u00e2ndido"
    ],
    "wof:name":"Sitio Jose Candido",
    "wof:placetype":"locality"
},
  "geometry": {"coordinates":[-49.8037,-23.6993],"type":"Point"}
}