{
  "type": "Feature",
  "properties": {
    "gn:admin1_code":"03",
    "gn:admin2_code":"1600303.0",
    "gn:asciiname":"Paricas",
    "gn:country_code":"BR",
    "gn:dem":16,
    "gn:feature_class":"P",
    "gn:feature_code":"PPL",
    "gn:name":"Paric\u00e1s",
    "gn:population":0,
    "gn:timezone":"America/Belem",
    "iso:country":"BR",
    "wof:name":"Paricas",
    "wof:placetype":"locality"
},
  "geometry": {"coordinates":[-51.13333,0.16667],"type":"Point"}
}