{
  "type": "Feature",
  "properties": {
    "gn:admin1_code":"18.0",
    "gn:admin2_code":"4111803.0",
    "gn:asciiname":"Sitio Luiz Correa",
    "gn:country_code":"BR",
    "gn:dem":533,
    "gn:feature_class":"P",
    "gn:feature_code":"PPL",
    "gn:name":"S\u00edtio Luiz Corr\u00eaa",
    "gn:population":0,
    "gn:timezone":"America/Sao_Paulo",
    "iso:country":"BR",
    "name:por_x_preferred":[
        "S\u00edtio Luiz Corr\u00eaa"
    ],
    "wof:name":"Sitio Luiz Correa",
    "wof:placetype":"locality"
},
  "geometry": {"coordinates":[-49.9207,-23.2601],"type":"Point"}
}