{
  "type": "Feature",
  "properties": {
    "gn:admin1_code":"30",
    "gn:admin2_code":"2605103.0",
    "gn:asciiname":"Bom Nome",
    "gn:country_code":"BR",
    "gn:dem":541,
    "gn:feature_class":"P",
    "gn:feature_code":"PPL",
    "gn:name":"Bom Nome",
    "gn:population":0,
    "gn:timezone":"America/Recife",
    "iso:country":"BR",
    "wof:name":"Bom Nome",
    "wof:placetype":"locality"
},
  "geometry": {"coordinates":[-37.61667,-8.11667],"type":"Point"}
}