{
  "type": "Feature",
  "properties": {
    "gn:admin1_code":"5",
    "gn:admin2_code":"2907806.0",
    "gn:asciiname":"Lagoa do Ouro",
    "gn:country_code":"BR",
    "gn:dem":422,
    "gn:feature_class":"P",
    "gn:feature_code":"PPL",
    "gn:name":"Lagoa do Ouro",
    "gn:population":0,
    "gn:timezone":"America/Bahia",
    "iso:country":"BR",
    "wof:name":"Lagoa do Ouro",
    "wof:placetype":"locality"
},
  "geometry": {"coordinates":[-38.56667,-10.45],"type":"Point"}
}