{
  "type": "Feature",
  "properties": {
    "gn:admin1_code":"5",
    "gn:admin2_code":"2907806.0",
    "gn:asciiname":"Lagoa do Ouro",
    "gn:country_code":"BR",
    "gn:dem":422,
    "gn:feature_class":"P",
    "gn:feature_code":"PPL",
    "gn:name":"Lagoa do Ouro",
    "gn:population":0,
    "gn:timezone":"America/Bahia",
    "iso:country":"BR",
    "name:bpy_x_preferred":[
        "\u09b2\u09be\u0997\u09cb\u09af\u09bc\u09be \u09a1\u09cb \u0994\u09b0\u09cb"
    ],
    "name:kat_x_preferred":[
        "\u10da\u10d0\u10d2\u10dd\u10d0-\u10d3\u10e3-\u10dd\u10e0\u10e3"
    ],
    "name:kaz_x_preferred":[
        "\u041b\u0430\u0433\u043e\u0430-\u0434\u0443-\u041e\u0440\u0443"
    ],
    "name:rus_x_preferred":[
        "\u041b\u0430\u0433\u043e\u0430-\u0434\u0443-\u041e\u0440\u0443"
    ],
    "name:zho_x_preferred":[
        "\u62c9\u6208\u963f-\u675c\u6b27\u9c81"
    ],
    "wof:name":"Lagoa do Ouro",
    "wof:placetype":"locality"
},
  "geometry": {"coordinates":[-38.56667,-10.45],"type":"Point"}
}