{
  "type": "Feature",
  "properties": {
    "gn:admin1_code":"26.0",
    "gn:admin2_code":"4209508.0",
    "gn:asciiname":"Cacador",
    "gn:country_code":"BR",
    "gn:dem":392,
    "gn:feature_class":"P",
    "gn:feature_code":"PPLL",
    "gn:name":"Ca\u00e7ador",
    "gn:population":0,
    "gn:timezone":"America/Sao_Paulo",
    "iso:country":"BR",
    "name:por_x_preferred":[
        "Ca\u00e7ador"
    ],
    "wof:name":"Cacador",
    "wof:placetype":"locality"
},
  "geometry": {"coordinates":[-49.732,-27.2388],"type":"Point"}
}