{
  "type": "Feature",
  "properties": {
    "gn:admin1_code":"06",
    "gn:admin2_code":"2300200.0",
    "gn:asciiname":"Juliana",
    "gn:country_code":"BR",
    "gn:dem":41,
    "gn:feature_class":"P",
    "gn:feature_code":"PPL",
    "gn:name":"Juliana",
    "gn:population":0,
    "gn:timezone":"America/Fortaleza",
    "iso:country":"BR",
    "wof:name":"Juliana",
    "wof:placetype":"locality"
},
  "geometry": {"coordinates":[-40.11667,-3.01667],"type":"Point"}
}