{
  "type": "Feature",
  "properties": {
    "gn:admin1_code":"1",
    "gn:admin2_code":"1200203.0",
    "gn:asciiname":"Principe Imperial",
    "gn:country_code":"BR",
    "gn:dem":191,
    "gn:feature_class":"P",
    "gn:feature_code":"PPL",
    "gn:name":"Pr\u00edncipe Imperial",
    "gn:population":0,
    "gn:timezone":"America/Eirunepe",
    "iso:country":"BR",
    "wof:name":"Principe Imperial",
    "wof:placetype":"locality"
},
  "geometry": {"coordinates":[-72.56667,-7.56667],"type":"Point"}
}