{
  "type": "Feature",
  "properties": {
    "gn:admin1_code":"27",
    "gn:admin2_code":"3507100.0",
    "gn:asciiname":"Sitio Lecabanom",
    "gn:country_code":"BR",
    "gn:dem":1042,
    "gn:feature_class":"P",
    "gn:feature_code":"PPL",
    "gn:name":"S\u00edtio Lecabanom",
    "gn:population":0,
    "gn:timezone":"America/Sao_Paulo",
    "iso:country":"BR",
    "name:por_x_preferred":[
        "S\u00edtio Lecabanom"
    ],
    "wof:name":"Sitio Lecabanom",
    "wof:placetype":"locality"
},
  "geometry": {"coordinates":[-46.53306,-23.21361],"type":"Point"}
}