{
  "type": "Feature",
  "properties": {
    "gn:admin1_code":"30",
    "gn:admin2_code":"2605301.0",
    "gn:asciiname":"Ouro",
    "gn:country_code":"BR",
    "gn:dem":521,
    "gn:feature_class":"P",
    "gn:feature_code":"PPL",
    "gn:name":"Ouro",
    "gn:population":0,
    "gn:timezone":"America/Recife",
    "iso:country":"BR",
    "name:bpy_x_preferred":[
        "\u0994\u09b0\u09cb"
    ],
    "name:eus_x_preferred":[
        "Ouro"
    ],
    "name:fra_x_preferred":[
        "Ouro"
    ],
    "name:ina_x_preferred":[
        "Ouro"
    ],
    "name:ita_x_preferred":[
        "Ouro"
    ],
    "name:kat_x_preferred":[
        "\u10dd\u10e0\u10e3"
    ],
    "name:nld_x_preferred":[
        "Ouro"
    ],
    "name:nor_x_preferred":[
        "Ouro"
    ],
    "name:oci_x_preferred":[
        "Ouro"
    ],
    "name:pol_x_preferred":[
        "Ouro"
    ],
    "name:por_x_preferred":[
        "Ouro"
    ],
    "name:ron_x_preferred":[
        "Ouro"
    ],
    "name:rus_x_preferred":[
        "\u041e\u0440\u0443"
    ],
    "name:vie_x_preferred":[
        "Ouro"
    ],
    "name:vol_x_preferred":[
        "Ouro"
    ],
    "name:war_x_preferred":[
        "Ouro"
    ],
    "wof:name":"Ouro",
    "wof:placetype":"locality"
},
  "geometry": {"coordinates":[-39.78333,-7.51667],"type":"Point"}
}