{
  "type": "Feature",
  "properties": {
    "gn:admin1_code":"13",
    "gn:admin2_code":"2107803.0",
    "gn:asciiname":"Sape",
    "gn:country_code":"BR",
    "gn:dem":236,
    "gn:feature_class":"P",
    "gn:feature_code":"PPL",
    "gn:name":"Sap\u00e9",
    "gn:population":0,
    "gn:timezone":"America/Fortaleza",
    "iso:country":"BR",
    "wof:name":"Sape",
    "wof:placetype":"locality"
},
  "geometry": {"coordinates":[-43.31667,-5.63333],"type":"Point"}
}