{
  "type": "Feature",
  "properties": {
    "gn:admin1_code":"30",
    "gn:admin2_code":"2615003.0",
    "gn:asciiname":"Algodao (2)",
    "gn:country_code":"BR",
    "gn:dem":474,
    "gn:feature_class":"P",
    "gn:feature_code":"PPL",
    "gn:name":"Algod\u00e3o (2)",
    "gn:population":0,
    "gn:timezone":"America/Recife",
    "iso:country":"BR",
    "wof:name":"Algodao (2)",
    "wof:placetype":"locality"
},
  "geometry": {"coordinates":[-36.16667,-7.88333],"type":"Point"}
}