{
  "type": "Feature",
  "properties": {
    "gn:admin1_code":"1",
    "gn:admin2_code":"1200351.0",
    "gn:asciiname":"Besouro",
    "gn:country_code":"BR",
    "gn:dem":229,
    "gn:feature_class":"P",
    "gn:feature_code":"PPL",
    "gn:name":"Besouro",
    "gn:population":0,
    "gn:timezone":"America/Rio_Branco",
    "iso:country":"BR",
    "wof:name":"Besouro",
    "wof:placetype":"locality"
},
  "geometry": {"coordinates":[-72.72639000000002,-8.9825],"type":"Point"}
}