{
  "type": "Feature",
  "properties": {
    "gn:admin1_code":"18.0",
    "gn:admin2_code":"4111704.0",
    "gn:asciiname":"Sitio Jose Lopes",
    "gn:country_code":"BR",
    "gn:dem":479,
    "gn:feature_class":"P",
    "gn:feature_code":"PPL",
    "gn:name":"S\u00edtio Jos\u00e9 Lopes",
    "gn:population":0,
    "gn:timezone":"America/Sao_Paulo",
    "iso:country":"BR",
    "name:por_x_preferred":[
        "S\u00edtio Jos\u00e9 Lopes"
    ],
    "wof:name":"Sitio Jose Lopes",
    "wof:placetype":"locality"
},
  "geometry": {"coordinates":[-50.06965,-23.69184],"type":"Point"}
}