{
  "type": "Feature",
  "properties": {
    "gn:admin1_code":"5",
    "gn:admin2_code":"2910750.0",
    "gn:asciiname":"Barra do Barao",
    "gn:country_code":"BR",
    "gn:dem":245,
    "gn:feature_class":"P",
    "gn:feature_code":"PPL",
    "gn:name":"Barra do Bar\u00e3o",
    "gn:population":0,
    "gn:timezone":"America/Bahia",
    "iso:country":"BR",
    "wof:name":"Barra do Barao",
    "wof:placetype":"locality"
},
  "geometry": {"coordinates":[-38.15,-10.46667],"type":"Point"}
}