{
  "type": "Feature",
  "properties": {
    "gn:admin1_code":"28",
    "gn:admin2_code":"2805604.0",
    "gn:asciiname":"Baixada do Burgo",
    "gn:country_code":"BR",
    "gn:dem":218,
    "gn:feature_class":"P",
    "gn:feature_code":"PPL",
    "gn:name":"Baixada do Burgo",
    "gn:population":0,
    "gn:timezone":"America/Maceio",
    "iso:country":"BR",
    "wof:name":"Baixada do Burgo",
    "wof:placetype":"locality"
},
  "geometry": {"coordinates":[-37.55,-9.88333],"type":"Point"}
}