{
  "type": "Feature",
  "properties": {
    "gn:admin1_code":"18.0",
    "gn:admin2_code":"4105201.0",
    "gn:asciiname":"Barra Porto do Lajeado Grande",
    "gn:country_code":"BR",
    "gn:dem":347,
    "gn:feature_class":"P",
    "gn:feature_code":"PPL",
    "gn:name":"Barra P\u00f4rto do Lajeado Grande",
    "gn:population":0,
    "gn:timezone":"America/Sao_Paulo",
    "iso:country":"BR",
    "wof:name":"Barra Porto do Lajeado Grande",
    "wof:placetype":"locality"
},
  "geometry": {"coordinates":[-49.35578,-24.81103],"type":"Point"}
}