{
  "type": "Feature",
  "properties": {
    "iso:country":"BR",
    "qs_pg:aaroncc":"BR",
    "qs_pg:name":"Poxoreu",
    "qs_pg:name_adm0":"Brasil",
    "qs_pg:name_adm1":"Mato Grosso",
    "qs_pg:photos":10,
    "qs_pg:photos_1k":2,
    "qs_pg:photos_9k":1,
    "qs_pg:photos_9r":1,
    "qs_pg:photos_all":10,
    "qs_pg:photos_sr":1,
    "qs_pg:pop_sr":0,
    "qs_pg:qs_pg_placetype":"locality",
    "qs_pg:qs_pg_placetype_gp":"Town",
    "qs_pg:woe_adm0":23424768,
    "woe:adm0_id":23424768,
    "woe:name_adm0":"Brasil",
    "woe:name_adm1":"Mato Grosso",
    "woe:placetype":"Town",
    "wof:name":"Poxoreu",
    "wof:placetype":"locality"
},
  "geometry": {"coordinates":[-54.4067,-15.88589],"type":"Point"}
}