{
  "type": "Feature",
  "properties": {
    "gn:admin1_code":"18.0",
    "gn:admin2_code":"4109609.0",
    "gn:asciiname":"Sitio Manuel Alves",
    "gn:country_code":"BR",
    "gn:dem":38,
    "gn:feature_class":"P",
    "gn:feature_code":"PPL",
    "gn:name":"S\u00edtio Manuel Alves",
    "gn:population":0,
    "gn:timezone":"America/Sao_Paulo",
    "iso:country":"BR",
    "name:por_x_preferred":[
        "S\u00edtio Manuel Alves"
    ],
    "wof:name":"Sitio Manuel Alves",
    "wof:placetype":"locality"
},
  "geometry": {"coordinates":[-48.76,-25.7185],"type":"Point"}
}