{
  "type": "Feature",
  "properties": {
    "gn:admin1_code":"06",
    "gn:admin2_code":"2310704.0",
    "gn:asciiname":"Fazenda Lagoa do Felix",
    "gn:country_code":"BR",
    "gn:dem":101,
    "gn:feature_class":"P",
    "gn:feature_code":"PPL",
    "gn:name":"Fazenda Lagoa do F\u00e9lix",
    "gn:population":0,
    "gn:timezone":"America/Fortaleza",
    "iso:country":"BR",
    "wof:name":"Fazenda Lagoa do Felix",
    "wof:placetype":"locality"
},
  "geometry": {"coordinates":[-39.13333,-3.81667],"type":"Point"}
}