{
  "type": "Feature",
  "properties": {
    "gn:admin1_code":"1",
    "gn:admin2_code":"1200500.0",
    "gn:asciiname":"Sao Vicente",
    "gn:country_code":"BR",
    "gn:dem":193,
    "gn:feature_class":"P",
    "gn:feature_code":"PPL",
    "gn:name":"S\u00e3o Vicente",
    "gn:population":0,
    "gn:timezone":"America/Rio_Branco",
    "iso:country":"BR",
    "wof:name":"Sao Vicente",
    "wof:placetype":"locality"
},
  "geometry": {"coordinates":[-69.21666999999999,-9.36667],"type":"Point"}
}