{
  "type": "Feature",
  "properties": {
    "gn:admin1_code":"18.0",
    "gn:admin2_code":"4126603.0",
    "gn:asciiname":"Sitio Isaltino A. da Silva",
    "gn:country_code":"BR",
    "gn:dem":798,
    "gn:feature_class":"P",
    "gn:feature_code":"PPL",
    "gn:name":"S\u00edtio Isaltino A. da Silva",
    "gn:population":0,
    "gn:timezone":"America/Sao_Paulo",
    "iso:country":"BR",
    "name:por_x_preferred":[
        "S\u00edtio Isaltino A. da Silva"
    ],
    "wof:name":"Sitio Isaltino A. da Silva",
    "wof:placetype":"locality"
},
  "geometry": {"coordinates":[-49.8686,-23.6271],"type":"Point"}
}