{
  "type": "Feature",
  "properties": {
    "gn:admin1_code":"4",
    "gn:admin2_code":"1302405.0",
    "gn:asciiname":"Fazenda Parana",
    "gn:country_code":"BR",
    "gn:dem":172,
    "gn:feature_class":"P",
    "gn:feature_code":"PPL",
    "gn:name":"Fazenda Paran\u00e1",
    "gn:population":0,
    "gn:timezone":"America/Manaus",
    "iso:country":"BR",
    "wof:name":"Fazenda Parana",
    "wof:placetype":"locality"
},
  "geometry": {"coordinates":[-67.28333000000001,-9.48333],"type":"Point"}
}