{
  "type": "Feature",
  "properties": {
    "gn:admin1_code":"18.0",
    "gn:admin2_code":"4109005.0",
    "gn:asciiname":"Sitio Fuginaga",
    "gn:country_code":"BR",
    "gn:dem":471,
    "gn:feature_class":"P",
    "gn:feature_code":"PPL",
    "gn:name":"S\u00edtio Fuginaga",
    "gn:population":0,
    "gn:timezone":"America/Sao_Paulo",
    "iso:country":"BR",
    "name:por_x_preferred":[
        "S\u00edtio Fuginaga"
    ],
    "wof:name":"Sitio Fuginaga",
    "wof:placetype":"locality"
},
  "geometry": {"coordinates":[-50.04925,-23.52168],"type":"Point"}
}