{
  "type": "Feature",
  "properties": {
    "gn:admin1_code":"13",
    "gn:admin2_code":"2105922.0",
    "gn:asciiname":"Barreira do Mato",
    "gn:country_code":"BR",
    "gn:dem":212,
    "gn:feature_class":"P",
    "gn:feature_code":"PPL",
    "gn:name":"Barreira do Mato",
    "gn:population":0,
    "gn:timezone":"America/Fortaleza",
    "iso:country":"BR",
    "wof:name":"Barreira do Mato",
    "wof:placetype":"locality"
},
  "geometry": {"coordinates":[-43.45,-5.93333],"type":"Point"}
}