{
  "type": "Feature",
  "properties": {
    "gn:admin1_code":"4",
    "gn:admin2_code":"1302702.0",
    "gn:asciiname":"Sempre-Viva",
    "gn:cc2":"BR",
    "gn:country_code":"BR",
    "gn:dem":23,
    "gn:feature_class":"P",
    "gn:feature_code":"PPL",
    "gn:name":"Sempre-Viva",
    "gn:population":0,
    "gn:timezone":"America/Manaus",
    "iso:country":"BR",
    "name:und_x_variant":[
        "Siempre Viva",
        "Sempre-Viva"
    ],
    "wof:name":"Sempre-Viva",
    "wof:placetype":"locality"
},
  "geometry": {"coordinates":[-61.26667,-5.66667],"type":"Point"}
}