{
  "type": "Feature",
  "properties": {
    "gn:admin1_code":"15.0",
    "gn:admin2_code":"3147303.0",
    "gn:asciiname":"Sitio Sao Benedito",
    "gn:country_code":"BR",
    "gn:dem":937,
    "gn:feature_class":"P",
    "gn:feature_code":"PPL",
    "gn:name":"S\u00edtio S\u00e3o Benedito",
    "gn:population":0,
    "gn:timezone":"America/Sao_Paulo",
    "iso:country":"BR",
    "name:por_x_preferred":[
        "S\u00edtio S\u00e3o Benedito"
    ],
    "wof:name":"Sitio Sao Benedito",
    "wof:placetype":"locality"
},
  "geometry": {"coordinates":[-45.7067,-22.5179],"type":"Point"}
}