{
  "type": "Feature",
  "properties": {
    "gn:admin1_code":"23",
    "gn:admin2_code":"4310603.0",
    "gn:asciiname":"Getulio D. Vargas",
    "gn:country_code":"BR",
    "gn:dem":92,
    "gn:feature_class":"P",
    "gn:feature_code":"PPL",
    "gn:name":"Get\u00falio D. Vargas",
    "gn:population":0,
    "gn:timezone":"America/Sao_Paulo",
    "iso:country":"BR",
    "wof:name":"Getulio D. Vargas",
    "wof:placetype":"locality"
},
  "geometry": {"coordinates":[-55.96666999999999,-29.25],"type":"Point"}
}