{
  "type": "Feature",
  "properties": {
    "gn:admin1_code":"06",
    "gn:admin2_code":"2312106.0",
    "gn:asciiname":"Pimenteira",
    "gn:country_code":"BR",
    "gn:dem":609,
    "gn:feature_class":"P",
    "gn:feature_code":"PPL",
    "gn:name":"Pimenteira",
    "gn:population":0,
    "gn:timezone":"America/Fortaleza",
    "iso:country":"BR",
    "wof:name":"Pimenteira",
    "wof:placetype":"locality"
},
  "geometry": {"coordinates":[-39.88333,-7.15],"type":"Point"}
}