{
  "type": "Feature",
  "properties": {
    "gn:admin1_code":"27",
    "gn:admin2_code":"3504107.0",
    "gn:asciiname":"Jardim Sao Nicolau",
    "gn:country_code":"BR",
    "gn:dem":769,
    "gn:feature_class":"P",
    "gn:feature_code":"PPL",
    "gn:name":"Jardim S\u00e3o Nicolau",
    "gn:population":0,
    "gn:timezone":"America/Sao_Paulo",
    "iso:country":"BR",
    "name:por_x_preferred":[
        "Jardim S\u00e3o Nicolau"
    ],
    "wof:name":"Jardim Sao Nicolau",
    "wof:placetype":"locality"
},
  "geometry": {"coordinates":[-46.54889,-23.125],"type":"Point"}
}