{
  "type": "Feature",
  "properties": {
    "gn:admin1_code":"18",
    "gn:admin2_code":"4119103.0",
    "gn:asciiname":"Sitio Afonso Groskop",
    "gn:country_code":"BR",
    "gn:dem":926,
    "gn:feature_class":"P",
    "gn:feature_code":"PPL",
    "gn:name":"S\u00edtio Afonso Groskop",
    "gn:population":0,
    "gn:timezone":"America/Sao_Paulo",
    "iso:country":"BR",
    "name:por_x_preferred":[
        "S\u00edtio Afonso Groskop"
    ],
    "wof:name":"Sitio Afonso Groskop",
    "wof:placetype":"locality"
},
  "geometry": {"coordinates":[-49.51728,-26.0495],"type":"Point"}
}