{
  "type": "Feature",
  "properties": {
    "gn:admin1_code":"16",
    "gn:admin2_code":"1501956.0",
    "gn:asciiname":"Pousos",
    "gn:country_code":"BR",
    "gn:dem":22,
    "gn:feature_class":"P",
    "gn:feature_code":"PPL",
    "gn:name":"Pousos",
    "gn:population":0,
    "gn:timezone":"America/Belem",
    "iso:country":"BR",
    "wof:name":"Pousos",
    "wof:placetype":"locality"
},
  "geometry": {"coordinates":[-46.31667,-1.86667],"type":"Point"}
}