{
  "type": "Feature",
  "properties": {
    "gn:admin1_code":"18.0",
    "gn:admin2_code":"4103107.0",
    "gn:asciiname":"Sitio Rui F. Pereira",
    "gn:country_code":"BR",
    "gn:dem":795,
    "gn:feature_class":"P",
    "gn:feature_code":"PPL",
    "gn:name":"S\u00edtio Rui F. Pereira",
    "gn:population":0,
    "gn:timezone":"America/Sao_Paulo",
    "iso:country":"BR",
    "name:por_x_preferred":[
        "S\u00edtio Rui F. Pereira"
    ],
    "wof:name":"Sitio Rui F. Pereira",
    "wof:placetype":"locality"
},
  "geometry": {"coordinates":[-48.89883,-25.13755],"type":"Point"}
}