{
  "type": "Feature",
  "properties": {
    "gn:admin1_code":"27.0",
    "gn:admin2_code":"3548708.0",
    "gn:asciiname":"Sitio Galileia",
    "gn:country_code":"BR",
    "gn:dem":787,
    "gn:feature_class":"P",
    "gn:feature_code":"PPL",
    "gn:name":"S\u00edtio Galil\u00e9ia",
    "gn:population":0,
    "gn:timezone":"America/Sao_Paulo",
    "iso:country":"BR",
    "name:por_x_preferred":[
        "S\u00edtio Galil\u00e9ia"
    ],
    "wof:name":"Sitio Galileia",
    "wof:placetype":"locality"
},
  "geometry": {"coordinates":[-46.6112,-23.812],"type":"Point"}
}