{
  "type": "Feature",
  "properties": {
    "gn:admin1_code":"4",
    "gn:admin2_code":"1300805.0",
    "gn:asciiname":"Santa Maria",
    "gn:country_code":"BR",
    "gn:dem":38,
    "gn:feature_class":"P",
    "gn:feature_code":"PPL",
    "gn:name":"Santa Maria",
    "gn:population":0,
    "gn:timezone":"America/Manaus",
    "iso:country":"BR",
    "name:por_x_preferred":[
        "Santa Maria"
    ],
    "wof:name":"Santa Maria",
    "wof:placetype":"locality"
},
  "geometry": {"coordinates":[-60.21972,-4.90167],"type":"Point"}
}