{
  "type": "Feature",
  "properties": {
    "gn:admin1_code":"06",
    "gn:admin2_code":"2313757.0",
    "gn:asciiname":"Fazenda Acudinho",
    "gn:country_code":"BR",
    "gn:dem":103,
    "gn:feature_class":"P",
    "gn:feature_code":"PPL",
    "gn:name":"Fazenda A\u00e7udinho",
    "gn:population":0,
    "gn:timezone":"America/Fortaleza",
    "iso:country":"BR",
    "wof:name":"Fazenda Acudinho",
    "wof:placetype":"locality"
},
  "geometry": {"coordinates":[-39.36667,-3.58333],"type":"Point"}
}