{
  "type": "Feature",
  "properties": {
    "gn:admin1_code":"18.0",
    "gn:admin2_code":"4127809.0",
    "gn:asciiname":"Sitio Jose Reis",
    "gn:country_code":"BR",
    "gn:dem":727,
    "gn:feature_class":"P",
    "gn:feature_code":"PPL",
    "gn:name":"S\u00edtio Jos\u00e9 Reis",
    "gn:population":0,
    "gn:timezone":"America/Sao_Paulo",
    "iso:country":"BR",
    "name:por_x_preferred":[
        "S\u00edtio Jos\u00e9 Reis"
    ],
    "wof:name":"Sitio Jose Reis",
    "wof:placetype":"locality"
},
  "geometry": {"coordinates":[-49.8951,-23.6365],"type":"Point"}
}