{
  "type": "Feature",
  "properties": {
    "gn:admin1_code":"27",
    "gn:admin2_code":"3548609.0",
    "gn:asciiname":"Paiol Grande",
    "gn:country_code":"BR",
    "gn:dem":1006,
    "gn:feature_class":"P",
    "gn:feature_code":"PPLL",
    "gn:name":"Paiol Grande",
    "gn:population":0,
    "gn:timezone":"America/Sao_Paulo",
    "iso:country":"BR",
    "name:por_x_preferred":[
        "Paiol Grande"
    ],
    "wof:name":"Paiol Grande",
    "wof:placetype":"locality"
},
  "geometry": {"coordinates":[-45.70808,-22.6747],"type":"Point"}
}