{
  "type": "Feature",
  "properties": {
    "gn:admin1_code":"06",
    "gn:admin2_code":"2311900.0",
    "gn:asciiname":"Cruzeta",
    "gn:country_code":"BR",
    "gn:dem":288,
    "gn:feature_class":"P",
    "gn:feature_code":"PPL",
    "gn:name":"Cruzeta",
    "gn:population":0,
    "gn:timezone":"America/Fortaleza",
    "iso:country":"BR",
    "name:bpy_x_preferred":[
        "\u0995\u09cd\u09b0\u09c1\u099c\u09c7\u099f\u09be"
    ],
    "name:ceb_x_preferred":[
        "Cruzeta"
    ],
    "name:epo_x_preferred":[
        "Cruzeta"
    ],
    "name:eus_x_preferred":[
        "Cruzeta"
    ],
    "name:fas_x_preferred":[
        "\u06a9\u0631\u0648\u0632\u062a\u0627"
    ],
    "name:fra_x_preferred":[
        "Cruzeta"
    ],
    "name:ita_x_preferred":[
        "Cruzeta"
    ],
    "name:kat_x_preferred":[
        "\u10d9\u10e0\u10e3\u10d6\u10d4\u10e2\u10d0"
    ],
    "name:kaz_x_preferred":[
        "\u041a\u0440\u0443\u0437\u0435\u0442\u0430"
    ],
    "name:mlg_x_preferred":[
        "Cruzeta"
    ],
    "name:nld_x_preferred":[
        "Cruzeta"
    ],
    "name:nor_x_preferred":[
        "Cruzeta"
    ],
    "name:por_x_preferred":[
        "Cruzeta"
    ],
    "name:ron_x_preferred":[
        "Cruzeta"
    ],
    "name:rus_x_preferred":[
        "\u041a\u0440\u0443\u0437\u0435\u0442\u0430"
    ],
    "name:spa_x_preferred":[
        "Cruzeta"
    ],
    "name:swe_x_preferred":[
        "Cruzeta"
    ],
    "name:vie_x_preferred":[
        "Cruzeta"
    ],
    "name:vol_x_preferred":[
        "Cruzeta"
    ],
    "name:war_x_preferred":[
        "Cruzeta"
    ],
    "name:zho_x_preferred":[
        "\u514b\u9c81\u6cfd\u5854"
    ],
    "wof:name":"Cruzeta",
    "wof:placetype":"locality"
},
  "geometry": {"coordinates":[-39.86667,-6.56667],"type":"Point"}
}