{
  "type": "Feature",
  "properties": {
    "gn:admin1_code":"06",
    "gn:admin2_code":"2311900.0",
    "gn:asciiname":"Cruzeta",
    "gn:country_code":"BR",
    "gn:dem":288,
    "gn:feature_class":"P",
    "gn:feature_code":"PPL",
    "gn:name":"Cruzeta",
    "gn:population":0,
    "gn:timezone":"America/Fortaleza",
    "iso:country":"BR",
    "wof:name":"Cruzeta",
    "wof:placetype":"locality"
},
  "geometry": {"coordinates":[-39.86667,-6.56667],"type":"Point"}
}