{
  "type": "Feature",
  "properties": {
    "gn:admin1_code":"18.0",
    "gn:admin2_code":"4113205.0",
    "gn:asciiname":"Sitio Felix Caja",
    "gn:country_code":"BR",
    "gn:dem":855,
    "gn:feature_class":"P",
    "gn:feature_code":"PPL",
    "gn:name":"S\u00edtio F\u00e9lix Caja",
    "gn:population":0,
    "gn:timezone":"America/Sao_Paulo",
    "iso:country":"BR",
    "name:por_x_preferred":[
        "S\u00edtio F\u00e9lix Caja"
    ],
    "wof:name":"Sitio Felix Caja",
    "wof:placetype":"locality"
},
  "geometry": {"coordinates":[-49.6192,-25.7694],"type":"Point"}
}