{
  "type": "Feature",
  "properties": {
    "gn:admin1_code":"21",
    "gn:admin2_code":"3303500.0",
    "gn:asciiname":"Cidade Jardim Montevideo",
    "gn:country_code":"BR",
    "gn:dem":18,
    "gn:feature_class":"P",
    "gn:feature_code":"PPL",
    "gn:name":"Cidade Jardim Montevideo",
    "gn:population":0,
    "gn:timezone":"America/Sao_Paulo",
    "iso:country":"BR",
    "name:por_x_preferred":[
        "Cidade Jardim Montevideo"
    ],
    "wof:name":"Cidade Jardim Montevideo",
    "wof:placetype":"locality"
},
  "geometry": {"coordinates":[-43.3975,-22.61944],"type":"Point"}
}