{
  "type": "Feature",
  "properties": {
    "gn:country":"BR",
    "gn:fcode":"PPL",
    "gn:population":0,
    "iso:country":"BR",
    "name:deu_x_preferred":[
        "Ipiranga"
    ],
    "name:fra_x_preferred":[
        "Ipiranga"
    ],
    "name:ita_x_preferred":[
        "Ipiranga"
    ],
    "name:nld_x_preferred":[
        "Ipiranga"
    ],
    "name:por_x_preferred":[
        "Ipiranga"
    ],
    "name:spa_x_preferred":[
        "Ipiranga"
    ],
    "qs_pg:aaroncc":"BR",
    "qs_pg:gn_country":"BR",
    "qs_pg:gn_fcode":"PPL",
    "qs_pg:gn_pop":0,
    "qs_pg:name":"Ipiranga",
    "qs_pg:name_adm0":"Brasil",
    "qs_pg:name_adm1":"Minas Gerais",
    "qs_pg:photos_9r":0,
    "qs_pg:photos_sr":0,
    "qs_pg:pop_sr":0,
    "qs_pg:qs_pg_placetype":"neighbourhood",
    "qs_pg:qs_pg_placetype_gp":"Suburb",
    "qs_pg:woe_adm0":23424768,
    "woe:adm0_id":23424768,
    "woe:name_adm0":"Brasil",
    "woe:name_adm1":"Minas Gerais",
    "woe:placetype":"Suburb",
    "wof:name":"Ipiranga",
    "wof:placetype":"neighbourhood"
},
  "geometry": {"coordinates":[-43.30028,-20.68472],"type":"Point"}
}