{
  "type": "Feature",
  "properties": {
    "gn:admin1_code":"11",
    "gn:admin2_code":"5003157.0",
    "gn:asciiname":"Taquapiri",
    "gn:cc2":"BR",
    "gn:country_code":"BR",
    "gn:dem":463,
    "gn:feature_class":"P",
    "gn:feature_code":"PPL",
    "gn:name":"Taquapiri",
    "gn:population":0,
    "gn:timezone":"America/Campo_Grande",
    "iso:country":"BR",
    "name:und_x_variant":[
        "Fazenda Taquaperi",
        "Taquapary",
        "Taquaperi",
        "Taguapiri",
        "Taquapery",
        "Tacuapiri",
        "Taquapiri"
    ],
    "wof:name":"Taquapiri",
    "wof:placetype":"locality"
},
  "geometry": {"coordinates":[-55.41667,-23.21667],"type":"Point"}
}