{
  "type": "Feature",
  "properties": {
    "gn:admin1_code":"11",
    "gn:admin2_code":"5002704.0",
    "gn:asciiname":"Braco Forte",
    "gn:country_code":"BR",
    "gn:dem":399,
    "gn:feature_class":"P",
    "gn:feature_code":"PPLL",
    "gn:name":"Bra\u00e7o Forte",
    "gn:population":0,
    "gn:timezone":"America/Campo_Grande",
    "iso:country":"BR",
    "wof:name":"Braco Forte",
    "wof:placetype":"locality"
},
  "geometry": {"coordinates":[-53.76889,-21.28444],"type":"Point"}
}