{
  "type": "Feature",
  "properties": {
    "gn:admin1_code":"22",
    "gn:admin2_code":"2406700.0",
    "gn:asciiname":"Monte Alegre",
    "gn:country_code":"BR",
    "gn:dem":241,
    "gn:feature_class":"P",
    "gn:feature_code":"PPL",
    "gn:name":"Monte Alegre",
    "gn:population":0,
    "gn:timezone":"America/Fortaleza",
    "iso:country":"BR",
    "wof:name":"Monte Alegre",
    "wof:placetype":"locality"
},
  "geometry": {"coordinates":[-36.17528,-5.49194],"type":"Point"}
}