{
  "type": "Feature",
  "properties": {
    "gn:admin1_code":"18.0",
    "gn:admin2_code":"4114302.0",
    "gn:asciiname":"Sitio Cecilia Samila",
    "gn:country_code":"BR",
    "gn:dem":917,
    "gn:feature_class":"P",
    "gn:feature_code":"PPL",
    "gn:name":"S\u00edtio Cec\u00edlia Samila",
    "gn:population":0,
    "gn:timezone":"America/Sao_Paulo",
    "iso:country":"BR",
    "name:por_x_preferred":[
        "S\u00edtio Cec\u00edlia Samila"
    ],
    "wof:name":"Sitio Cecilia Samila",
    "wof:placetype":"locality"
},
  "geometry": {"coordinates":[-49.2922,-25.7575],"type":"Point"}
}