{
  "type": "Feature",
  "properties": {
    "gn:admin1_code":"06",
    "gn:admin2_code":"2312700.0",
    "gn:asciiname":"Riacho da Forquilha",
    "gn:country_code":"BR",
    "gn:dem":265,
    "gn:feature_class":"P",
    "gn:feature_code":"PPL",
    "gn:name":"Riacho da Forquilha",
    "gn:population":0,
    "gn:timezone":"America/Fortaleza",
    "iso:country":"BR",
    "wof:name":"Riacho da Forquilha",
    "wof:placetype":"locality"
},
  "geometry": {"coordinates":[-39.36667,-5.71667],"type":"Point"}
}