{
  "type": "Feature",
  "properties": {
    "gn:admin1_code":"18",
    "gn:admin2_code":"4103040.0",
    "gn:asciiname":"Boa Ventura",
    "gn:country_code":"BR",
    "gn:dem":1004,
    "gn:feature_class":"P",
    "gn:feature_code":"PPL",
    "gn:name":"Boa Ventura",
    "gn:population":0,
    "gn:timezone":"America/Sao_Paulo",
    "iso:country":"BR",
    "name:bpy_x_preferred":[
        "\u09ac\u09cb\u09f1\u09be \u09ad\u09c7\u09a8\u099f\u09c1\u09b0\u09be"
    ],
    "name:ceb_x_preferred":[
        "Boa Ventura"
    ],
    "name:fra_x_preferred":[
        "Boa Ventura"
    ],
    "name:nld_x_preferred":[
        "Boa Ventura"
    ],
    "name:por_x_preferred":[
        "Boa Ventura"
    ],
    "name:swe_x_preferred":[
        "Boa Ventura"
    ],
    "wof:name":"Boa Ventura",
    "wof:placetype":"locality"
},
  "geometry": {"coordinates":[-51.61667,-24.95],"type":"Point"}
}