{
  "type": "Feature",
  "properties": {
    "gn:admin1_code":"18",
    "gn:admin2_code":"4103040.0",
    "gn:asciiname":"Boa Ventura",
    "gn:country_code":"BR",
    "gn:dem":1004,
    "gn:feature_class":"P",
    "gn:feature_code":"PPL",
    "gn:name":"Boa Ventura",
    "gn:population":0,
    "gn:timezone":"America/Sao_Paulo",
    "iso:country":"BR",
    "wof:name":"Boa Ventura",
    "wof:placetype":"locality"
},
  "geometry": {"coordinates":[-51.61667,-24.95],"type":"Point"}
}