{
  "type": "Feature",
  "properties": {
    "gn:admin1_code":"18.0",
    "gn:admin2_code":"4127882.0",
    "gn:asciiname":"Souza",
    "gn:country_code":"BR",
    "gn:dem":791,
    "gn:feature_class":"P",
    "gn:feature_code":"PPLL",
    "gn:name":"Souza",
    "gn:population":0,
    "gn:timezone":"America/Sao_Paulo",
    "iso:country":"BR",
    "name:por_x_preferred":[
        "Souza"
    ],
    "wof:name":"Souza",
    "wof:placetype":"locality"
},
  "geometry": {"coordinates":[-48.7116,-24.94400000000001],"type":"Point"}
}