{
  "type": "Feature",
  "properties": {
    "gn:admin1_code":"18.0",
    "gn:admin2_code":"4113205.0",
    "gn:asciiname":"Sitio Candido R. do Valle",
    "gn:country_code":"BR",
    "gn:dem":851,
    "gn:feature_class":"P",
    "gn:feature_code":"PPL",
    "gn:name":"S\u00edtio C\u00e2ndido R. do Valle",
    "gn:population":0,
    "gn:timezone":"America/Sao_Paulo",
    "iso:country":"BR",
    "name:por_x_preferred":[
        "S\u00edtio C\u00e2ndido R. do Valle"
    ],
    "wof:name":"Sitio Candido R. do Valle",
    "wof:placetype":"locality"
},
  "geometry": {"coordinates":[-49.5889,-25.7945],"type":"Point"}
}