{
  "type": "Feature",
  "properties": {
    "gn:admin1_code":"5",
    "gn:admin2_code":"2922102.0",
    "gn:asciiname":"Poco Longe",
    "gn:country_code":"BR",
    "gn:dem":420,
    "gn:feature_class":"P",
    "gn:feature_code":"PPL",
    "gn:name":"Po\u00e7o Longe",
    "gn:population":0,
    "gn:timezone":"America/Bahia",
    "iso:country":"BR",
    "wof:name":"Poco Longe",
    "wof:placetype":"locality"
},
  "geometry": {"coordinates":[-40.58333,-12.08333],"type":"Point"}
}