{
  "type": "Feature",
  "properties": {
    "gn:admin1_code":"18.0",
    "gn:admin2_code":"4106100.0",
    "gn:asciiname":"Sitio Nossa Senhora do Carmo",
    "gn:country_code":"BR",
    "gn:dem":547,
    "gn:feature_class":"P",
    "gn:feature_code":"PPL",
    "gn:name":"S\u00edtio Nossa Senhora do Carmo",
    "gn:population":0,
    "gn:timezone":"America/Sao_Paulo",
    "iso:country":"BR",
    "name:por_x_preferred":[
        "S\u00edtio Nossa Senhora do Carmo"
    ],
    "wof:name":"Sitio Nossa Senhora do Carmo",
    "wof:placetype":"locality"
},
  "geometry": {"coordinates":[-50.16523,-23.65073],"type":"Point"}
}