{
  "type": "Feature",
  "properties": {
    "gn:admin1_code":"18",
    "gn:admin2_code":"4104105.0",
    "gn:asciiname":"Sitio Luiz Turek",
    "gn:country_code":"BR",
    "gn:dem":845,
    "gn:feature_class":"P",
    "gn:feature_code":"PPL",
    "gn:name":"S\u00edtio Luiz Turek",
    "gn:population":0,
    "gn:timezone":"America/Sao_Paulo",
    "iso:country":"BR",
    "name:por_x_preferred":[
        "S\u00edtio Luiz Turek"
    ],
    "wof:name":"Sitio Luiz Turek",
    "wof:placetype":"locality"
},
  "geometry": {"coordinates":[-49.72879,-26.00589],"type":"Point"}
}