{
  "type": "Feature",
  "properties": {
    "gn:admin1_code":"5",
    "gn:admin2_code":"2922656.0",
    "gn:asciiname":"Tanquinho",
    "gn:country_code":"BR",
    "gn:dem":342,
    "gn:feature_class":"P",
    "gn:feature_code":"PPL",
    "gn:name":"Tanquinho",
    "gn:population":0,
    "gn:timezone":"America/Bahia",
    "iso:country":"BR",
    "wof:name":"Tanquinho",
    "wof:placetype":"locality"
},
  "geometry": {"coordinates":[-39.53333,-10.78333],"type":"Point"}
}