{
  "type": "Feature",
  "properties": {
    "gn:admin1_code":"5",
    "gn:admin2_code":"2922656.0",
    "gn:asciiname":"Tanquinho",
    "gn:country_code":"BR",
    "gn:dem":342,
    "gn:feature_class":"P",
    "gn:feature_code":"PPL",
    "gn:name":"Tanquinho",
    "gn:population":0,
    "gn:timezone":"America/Bahia",
    "iso:country":"BR",
    "name:bpy_x_preferred":[
        "\u099f\u09be\u09a8\u0995\u09c1\u0987\u09a8\u09b9\u09cb"
    ],
    "name:ceb_x_preferred":[
        "Tanquinho"
    ],
    "name:epo_x_preferred":[
        "Tanquinho"
    ],
    "name:eus_x_preferred":[
        "Tanquinho"
    ],
    "name:fra_x_preferred":[
        "Tanquinho"
    ],
    "name:hye_x_preferred":[
        "\u054f\u0561\u0576\u056f\u056b\u0576\u056b\u0578\u0582"
    ],
    "name:ita_x_preferred":[
        "Tanquinho"
    ],
    "name:kat_x_preferred":[
        "\u10e2\u10d0\u10dc\u10d9\u10d8\u10dc\u10d8\u10e3"
    ],
    "name:kaz_x_preferred":[
        "\u0422\u0430\u043d\u043a\u0438\u043d\u044c\u044e"
    ],
    "name:nld_x_preferred":[
        "Tanquinho"
    ],
    "name:nor_x_preferred":[
        "Tanquinho"
    ],
    "name:pol_x_preferred":[
        "Tanquinho"
    ],
    "name:por_x_preferred":[
        "Tanquinho"
    ],
    "name:ron_x_preferred":[
        "Tanquinho"
    ],
    "name:rus_x_preferred":[
        "\u0422\u0430\u043d\u043a\u0438\u043d\u044c\u044e"
    ],
    "name:spa_x_preferred":[
        "Tanquinho"
    ],
    "name:swe_x_preferred":[
        "Tanquinho"
    ],
    "name:vie_x_preferred":[
        "Tanquinho"
    ],
    "name:vol_x_preferred":[
        "Tanquinho"
    ],
    "name:war_x_preferred":[
        "Tanquinho"
    ],
    "name:zho_x_preferred":[
        "\u5766\u57fa\u7ebd"
    ],
    "wof:name":"Tanquinho",
    "wof:placetype":"locality"
},
  "geometry": {"coordinates":[-39.53333,-10.78333],"type":"Point"}
}