{
  "type": "Feature",
  "properties": {
    "gn:admin1_code":"18.0",
    "gn:admin2_code":"4109500.0",
    "gn:asciiname":"Sitio Pedro Rosa",
    "gn:country_code":"BR",
    "gn:dem":30,
    "gn:feature_class":"P",
    "gn:feature_code":"PPL",
    "gn:name":"S\u00edtio Pedro Rosa",
    "gn:population":0,
    "gn:timezone":"America/Sao_Paulo",
    "iso:country":"BR",
    "name:por_x_preferred":[
        "S\u00edtio Pedro Rosa"
    ],
    "wof:name":"Sitio Pedro Rosa",
    "wof:placetype":"locality"
},
  "geometry": {"coordinates":[-48.56044,-25.22883],"type":"Point"}
}