{
  "type": "Feature",
  "properties": {
    "gn:admin1_code":"20",
    "gn:admin2_code":"2205805.0",
    "gn:asciiname":"Grossos",
    "gn:country_code":"BR",
    "gn:dem":86,
    "gn:feature_class":"P",
    "gn:feature_code":"PPL",
    "gn:name":"Grossos",
    "gn:population":0,
    "gn:timezone":"America/Fortaleza",
    "iso:country":"BR",
    "wof:name":"Grossos",
    "wof:placetype":"locality"
},
  "geometry": {"coordinates":[-42.54333,-3.63194],"type":"Point"}
}