{
  "type": "Feature",
  "properties": {
    "gn:admin1_code":"26",
    "gn:admin2_code":"4211306.0",
    "gn:asciiname":"Machados",
    "gn:country_code":"BR",
    "gn:dem":3,
    "gn:feature_class":"P",
    "gn:feature_code":"PPLL",
    "gn:name":"Machados",
    "gn:population":0,
    "gn:timezone":"America/Sao_Paulo",
    "iso:country":"BR",
    "wof:name":"Machados",
    "wof:placetype":"locality"
},
  "geometry": {"coordinates":[-48.68917,-26.85722],"type":"Point"}
}