{
  "type": "Feature",
  "properties": {
    "gn:admin1_code":"18.0",
    "gn:admin2_code":"4103602.0",
    "gn:asciiname":"Sitio Antonio Francisquine",
    "gn:country_code":"BR",
    "gn:dem":475,
    "gn:feature_class":"P",
    "gn:feature_code":"PPL",
    "gn:name":"S\u00edtio Ant\u00f4nio Francisquine",
    "gn:population":0,
    "gn:timezone":"America/Sao_Paulo",
    "iso:country":"BR",
    "name:por_x_preferred":[
        "S\u00edtio Ant\u00f4nio Francisquine"
    ],
    "wof:name":"Sitio Antonio Francisquine",
    "wof:placetype":"locality"
},
  "geometry": {"coordinates":[-50.1217,-23.0607],"type":"Point"}
}