{
  "type": "Feature",
  "properties": {
    "gn:admin1_code":"20",
    "gn:admin2_code":"2205409.0",
    "gn:asciiname":"Chapada I",
    "gn:country_code":"BR",
    "gn:dem":66,
    "gn:feature_class":"P",
    "gn:feature_code":"PPL",
    "gn:name":"Chapada I",
    "gn:population":0,
    "gn:timezone":"America/Fortaleza",
    "iso:country":"BR",
    "wof:name":"Chapada I",
    "wof:placetype":"locality"
},
  "geometry": {"coordinates":[-42.08806,-3.41361],"type":"Point"}
}