{
  "type": "Feature",
  "properties": {
    "gn:admin1_code":"26.0",
    "gn:admin2_code":"4208906.0",
    "gn:asciiname":"Molha",
    "gn:country_code":"BR",
    "gn:dem":408,
    "gn:feature_class":"P",
    "gn:feature_code":"PPL",
    "gn:name":"Molha",
    "gn:population":0,
    "gn:timezone":"America/Sao_Paulo",
    "iso:country":"BR",
    "wof:name":"Molha",
    "wof:placetype":"locality"
},
  "geometry": {"coordinates":[-49.07092,-26.51723],"type":"Point"}
}