{
  "type": "Feature",
  "properties": {
    "gn:admin1_code":"20",
    "gn:admin2_code":"2205904.0",
    "gn:asciiname":"Faveira",
    "gn:country_code":"BR",
    "gn:dem":304,
    "gn:feature_class":"P",
    "gn:feature_code":"PPL",
    "gn:name":"Faveira",
    "gn:population":0,
    "gn:timezone":"America/Fortaleza",
    "iso:country":"BR",
    "wof:name":"Faveira",
    "wof:placetype":"locality"
},
  "geometry": {"coordinates":[-43.96667,-8.01667],"type":"Point"}
}