{
  "type": "Feature",
  "properties": {
    "gn:admin1_code":"15",
    "gn:admin2_code":"3140803.0",
    "gn:asciiname":"Belmont",
    "gn:country_code":"BR",
    "gn:dem":526,
    "gn:feature_class":"P",
    "gn:feature_code":"PPL",
    "gn:name":"Belmont",
    "gn:population":0,
    "gn:timezone":"America/Sao_Paulo",
    "iso:country":"BR",
    "name:por_x_preferred":[
        "Belmont"
    ],
    "wof:name":"Belmont",
    "wof:placetype":"locality"
},
  "geometry": {"coordinates":[-43.27778,-21.82722],"type":"Point"}
}