{
  "type": "Feature",
  "properties": {
    "gn:admin1_code":"18.0",
    "gn:admin2_code":"4126207.0",
    "gn:asciiname":"Sitio Sergio de Dalorti",
    "gn:country_code":"BR",
    "gn:dem":957,
    "gn:feature_class":"P",
    "gn:feature_code":"PPL",
    "gn:name":"S\u00edtio S\u00e9rgio de Dalorti",
    "gn:population":0,
    "gn:timezone":"America/Sao_Paulo",
    "iso:country":"BR",
    "name:por_x_preferred":[
        "S\u00edtio S\u00e9rgio de Dalorti"
    ],
    "wof:name":"Sitio Sergio de Dalorti",
    "wof:placetype":"locality"
},
  "geometry": {"coordinates":[-50.61074,-23.82834],"type":"Point"}
}