{
  "type": "Feature",
  "properties": {
    "gn:admin1_code":"27",
    "gn:admin2_code":"3520442.0",
    "gn:asciiname":"Vitoria",
    "gn:cc2":"BR",
    "gn:country_code":"BR",
    "gn:dem":323,
    "gn:feature_class":"P",
    "gn:feature_code":"PPL",
    "gn:name":"Vit\u00f3ria",
    "gn:population":0,
    "gn:timezone":"America/Sao_Paulo",
    "iso:country":"BR",
    "name:ara_x_preferred":[
        "\u0641\u064a\u062a\u0648\u0631\u064a\u0627"
    ],
    "name:ceb_x_preferred":[
        "Vitoria"
    ],
    "name:deu_x_preferred":[
        "Vitoria"
    ],
    "name:epo_x_preferred":[
        "Vitorio"
    ],
    "name:eus_x_preferred":[
        "Vitoria"
    ],
    "name:fin_x_preferred":[
        "Vitoria"
    ],
    "name:glg_x_preferred":[
        "Vitoria"
    ],
    "name:hye_x_preferred":[
        "\u054e\u056b\u057f\u0578\u0580\u056b\u0561"
    ],
    "name:jpn_x_preferred":[
        "\u30f4\u30a3\u30c8\u30fc\u30ea\u30a2"
    ],
    "name:kor_x_preferred":[
        "\ube44\ud1a0\ub9ac\uc544"
    ],
    "name:lim_x_preferred":[
        "Vitoria"
    ],
    "name:lit_x_preferred":[
        "Vitorija"
    ],
    "name:nld_x_preferred":[
        "Vitoria"
    ],
    "name:pol_x_preferred":[
        "Vit\u00f3ria"
    ],
    "name:rus_x_preferred":[
        "\u0412\u0438\u0442\u043e\u0440\u0438\u044f"
    ],
    "name:sco_x_preferred":[
        "Vitoria"
    ],
    "name:slk_x_preferred":[
        "Vitoria"
    ],
    "name:srp_x_preferred":[
        "\u0412\u0438\u0442\u043e\u0440\u0438\u0458\u0430"
    ],
    "name:swe_x_preferred":[
        "Vitoria"
    ],
    "name:ukr_x_preferred":[
        "\u0412\u0456\u0442\u043e\u0440\u0456\u044f"
    ],
    "name:und_x_variant":[
        "Prado",
        "Vit\u00f3ria"
    ],
    "wof:name":"Vitoria",
    "wof:placetype":"locality"
},
  "geometry": {"coordinates":[-51.15,-20.38333],"type":"Point"}
}