{
  "type": "Feature",
  "properties": {
    "gn:admin1_code":"27",
    "gn:admin2_code":"3520442.0",
    "gn:asciiname":"Vitoria",
    "gn:cc2":"BR",
    "gn:country_code":"BR",
    "gn:dem":323,
    "gn:feature_class":"P",
    "gn:feature_code":"PPL",
    "gn:name":"Vit\u00f3ria",
    "gn:population":0,
    "gn:timezone":"America/Sao_Paulo",
    "iso:country":"BR",
    "name:und_x_variant":[
        "Prado",
        "Vit\u00f3ria"
    ],
    "wof:name":"Vitoria",
    "wof:placetype":"locality"
},
  "geometry": {"coordinates":[-51.15,-20.38333],"type":"Point"}
}