{
  "type": "Feature",
  "properties": {
    "gn:admin1_code":"27",
    "gn:admin2_code":"3504107.0",
    "gn:asciiname":"Sitio Colina Perino",
    "gn:country_code":"BR",
    "gn:dem":876,
    "gn:feature_class":"P",
    "gn:feature_code":"PPL",
    "gn:name":"S\u00edtio Colina Perino",
    "gn:population":0,
    "gn:timezone":"America/Sao_Paulo",
    "iso:country":"BR",
    "name:por_x_preferred":[
        "S\u00edtio Colina Perino"
    ],
    "wof:name":"Sitio Colina Perino",
    "wof:placetype":"locality"
},
  "geometry": {"coordinates":[-46.59944,-23.19472],"type":"Point"}
}