{
  "type": "Feature",
  "properties": {
    "gn:admin1_code":"16",
    "gn:admin2_code":"1506195.0",
    "gn:asciiname":"Pedreiras",
    "gn:country_code":"BR",
    "gn:dem":2,
    "gn:feature_class":"P",
    "gn:feature_code":"PPL",
    "gn:name":"Pedreiras",
    "gn:population":0,
    "gn:timezone":"America/Santarem",
    "iso:country":"BR",
    "name:ara_x_preferred":[
        "\u0628\u064a\u062f\u0631\u0627\u0631\u064a\u0633"
    ],
    "name:ben_x_preferred":[
        "\u09aa\u09c7\u09a6\u09cd\u09b0\u09c7\u0987\u09b0\u09be\u09b8"
    ],
    "name:bpy_x_preferred":[
        "\u09aa\u09c7\u09a1\u09cd\u09b0\u09c7\u0987\u09b0\u09be\u09b8"
    ],
    "name:ceb_x_preferred":[
        "Pedreiras"
    ],
    "name:deu_x_preferred":[
        "Pedreiras"
    ],
    "name:ell_x_preferred":[
        "\u03a0\u03b5\u03b4\u03c1\u03ad\u03b9\u03c1\u03b1\u03c2"
    ],
    "name:fas_x_preferred":[
        "\u067e\u062f\u0631\u06cc\u0631\u0627\u0633"
    ],
    "name:glg_x_preferred":[
        "Pedreiras"
    ],
    "name:heb_x_preferred":[
        "\u05e4\u05d3\u05e8\u05d0\u05d9\u05e8\u05d0\u05e1"
    ],
    "name:hin_x_preferred":[
        "\u092a\u0947\u0921\u094d\u0930\u093f\u0930\u093e\u0938"
    ],
    "name:ind_x_preferred":[
        "Pedreiras"
    ],
    "name:ita_x_preferred":[
        "Pedreiras"
    ],
    "name:jpn_x_preferred":[
        "\u30da\u30c9\u30ec\u30a4\u30e9\u30b9"
    ],
    "name:kor_x_preferred":[
        "\ud398\ub4dc\ub808\uc774\ub77c\uc2a4"
    ],
    "name:nds_x_preferred":[
        "Pedreiras"
    ],
    "name:nld_x_preferred":[
        "Pedreiras"
    ],
    "name:pol_x_preferred":[
        "Pedreiras"
    ],
    "name:por_x_preferred":[
        "Pedreiras"
    ],
    "name:spa_x_preferred":[
        "Pedreiras"
    ],
    "name:swe_x_preferred":[
        "Pedreiras"
    ],
    "name:tur_x_preferred":[
        "Pedreiras"
    ],
    "name:ukr_x_preferred":[
        "\u041f\u0435\u0434\u0440\u0435\u0439\u0440\u0430\u0441"
    ],
    "name:urd_x_preferred":[
        "\u067e\u06cc\u0688\u0631\u06cc\u0631\u0627\u0633"
    ],
    "name:vie_x_preferred":[
        "Pedreiras"
    ],
    "wof:name":"Pedreiras",
    "wof:placetype":"locality"
},
  "geometry": {"coordinates":[-55.61667,-4.05],"type":"Point"}
}