{
  "type": "Feature",
  "properties": {
    "gn:admin1_code":"16",
    "gn:admin2_code":"1506195.0",
    "gn:asciiname":"Pedreiras",
    "gn:country_code":"BR",
    "gn:dem":2,
    "gn:feature_class":"P",
    "gn:feature_code":"PPL",
    "gn:name":"Pedreiras",
    "gn:population":0,
    "gn:timezone":"America/Santarem",
    "iso:country":"BR",
    "wof:name":"Pedreiras",
    "wof:placetype":"locality"
},
  "geometry": {"coordinates":[-55.61666999999999,-4.05],"type":"Point"}
}