{
  "type": "Feature",
  "properties": {
    "gn:admin1_code":"25",
    "gn:admin2_code":"1400175.0",
    "gn:asciiname":"Malacacheta",
    "gn:country_code":"BR",
    "gn:dem":98,
    "gn:feature_class":"P",
    "gn:feature_code":"PPL",
    "gn:name":"Malacacheta",
    "gn:population":0,
    "gn:timezone":"America/Boa_Vista",
    "iso:country":"BR",
    "name:bpy_x_preferred":[
        "\u09ae\u09be\u09b2\u09be\u0995\u09be\u0995\u09b9\u09c7\u099f\u09be"
    ],
    "name:ceb_x_preferred":[
        "Malacacheta"
    ],
    "name:epo_x_preferred":[
        "Malacacheta"
    ],
    "name:eus_x_preferred":[
        "Malacacheta"
    ],
    "name:fra_x_preferred":[
        "Malacacheta"
    ],
    "name:ita_x_preferred":[
        "Malacacheta"
    ],
    "name:kat_x_preferred":[
        "\u10db\u10d0\u10da\u10d0\u10d9\u10d0\u10e8\u10d4\u10e2\u10d0"
    ],
    "name:kaz_x_preferred":[
        "\u041c\u0430\u043b\u0430\u043a\u0430\u0448\u0435\u0442\u0430"
    ],
    "name:mlg_x_preferred":[
        "Malacacheta"
    ],
    "name:nld_x_preferred":[
        "Malacacheta"
    ],
    "name:nor_x_preferred":[
        "Malacacheta"
    ],
    "name:pol_x_preferred":[
        "Malacacheta"
    ],
    "name:por_x_preferred":[
        "Malacacheta"
    ],
    "name:ron_x_preferred":[
        "Malacacheta"
    ],
    "name:rus_x_preferred":[
        "\u041c\u0430\u043b\u0430\u043a\u0430\u0448\u0435\u0442\u0430"
    ],
    "name:spa_x_preferred":[
        "Malacacheta"
    ],
    "name:swe_x_preferred":[
        "Malacacheta"
    ],
    "name:und_x_variant":[
        "Maloca Malacacheta"
    ],
    "name:vie_x_preferred":[
        "Malacacheta"
    ],
    "name:vol_x_preferred":[
        "Malacacheta"
    ],
    "name:war_x_preferred":[
        "Malacacheta"
    ],
    "name:zho_x_preferred":[
        "\u9a6c\u62c9\u5361\u8c22\u5854"
    ],
    "wof:name":"Malacacheta",
    "wof:placetype":"locality"
},
  "geometry": {"coordinates":[-60.45352,2.67026],"type":"Point"}
}