{
  "type": "Feature",
  "properties": {
    "gn:admin1_code":"25",
    "gn:admin2_code":"1400175.0",
    "gn:asciiname":"Malacacheta",
    "gn:country_code":"BR",
    "gn:dem":98,
    "gn:feature_class":"P",
    "gn:feature_code":"PPL",
    "gn:name":"Malacacheta",
    "gn:population":0,
    "gn:timezone":"America/Boa_Vista",
    "iso:country":"BR",
    "name:und_x_variant":[
        "Maloca Malacacheta"
    ],
    "wof:name":"Malacacheta",
    "wof:placetype":"locality"
},
  "geometry": {"coordinates":[-60.45352,2.67026],"type":"Point"}
}