{
  "type": "Feature",
  "properties": {
    "gn:admin1_code":"21",
    "gn:admin2_code":"3304557.0",
    "gn:asciiname":"Mare",
    "gn:country_code":"BR",
    "gn:dem":8,
    "gn:feature_class":"P",
    "gn:feature_code":"PPL",
    "gn:name":"Mar\u00e9",
    "gn:population":0,
    "gn:timezone":"America/Sao_Paulo",
    "iso:country":"BR",
    "name:por_x_preferred":[
        "Mar\u00e9"
    ],
    "wof:name":"Mare",
    "wof:placetype":"locality"
},
  "geometry": {"coordinates":[-43.24348,-22.85604],"type":"Point"}
}