{
  "type": "Feature",
  "properties": {
    "gn:admin1_code":"15",
    "gn:admin2_code":"3168606.0",
    "gn:asciiname":"Julio Laender",
    "gn:country_code":"BR",
    "gn:dem":337,
    "gn:feature_class":"P",
    "gn:feature_code":"PPL",
    "gn:name":"J\u00falio Laender",
    "gn:population":0,
    "gn:timezone":"America/Sao_Paulo",
    "iso:country":"BR",
    "name:por_x_preferred":[
        "J\u00falio Laender"
    ],
    "wof:name":"Julio Laender",
    "wof:placetype":"locality"
},
  "geometry": {"coordinates":[-41.38333,-17.88332999999999],"type":"Point"}
}