{
  "type": "Feature",
  "properties": {
    "gn:admin1_code":"18.0",
    "gn:admin2_code":"4102703.0",
    "gn:asciiname":"Sitio da Jaqueira",
    "gn:country_code":"BR",
    "gn:dem":459,
    "gn:feature_class":"P",
    "gn:feature_code":"PPL",
    "gn:name":"S\u00edtio da Jaqueira",
    "gn:population":0,
    "gn:timezone":"America/Sao_Paulo",
    "iso:country":"BR",
    "name:por_x_preferred":[
        "S\u00edtio da Jaqueira"
    ],
    "wof:name":"Sitio da Jaqueira",
    "wof:placetype":"locality"
},
  "geometry": {"coordinates":[-50.2316,-23.0826],"type":"Point"}
}