{
  "type": "Feature",
  "properties": {
    "gn:admin1_code":"26.0",
    "gn:admin2_code":"4210100.0",
    "gn:asciiname":"Sitio Julio Konkel",
    "gn:country_code":"BR",
    "gn:dem":812,
    "gn:feature_class":"P",
    "gn:feature_code":"PPL",
    "gn:name":"S\u00edtio J\u00falio Konkel",
    "gn:population":0,
    "gn:timezone":"America/Sao_Paulo",
    "iso:country":"BR",
    "name:por_x_preferred":[
        "S\u00edtio J\u00falio Konkel"
    ],
    "wof:name":"Sitio Julio Konkel",
    "wof:placetype":"locality"
},
  "geometry": {"coordinates":[-49.9137,-26.0541],"type":"Point"}
}