{
  "type": "Feature",
  "properties": {
    "gn:admin1_code":"18",
    "gn:admin2_code":"4114302.0",
    "gn:asciiname":"Sitio Sao Antonio",
    "gn:country_code":"BR",
    "gn:dem":895,
    "gn:feature_class":"P",
    "gn:feature_code":"PPL",
    "gn:name":"S\u00edtio S\u00e3o Ant\u00f4nio",
    "gn:population":0,
    "gn:timezone":"America/Sao_Paulo",
    "iso:country":"BR",
    "name:por_x_preferred":[
        "S\u00edtio S\u00e3o Ant\u00f4nio"
    ],
    "wof:name":"Sitio Sao Antonio",
    "wof:placetype":"locality"
},
  "geometry": {"coordinates":[-49.22008,-25.84717],"type":"Point"}
}