{
  "type": "Feature",
  "properties": {
    "gn:admin1_code":"18.0",
    "gn:admin2_code":"4109708.0",
    "gn:asciiname":"Sitio Antenor Jacob",
    "gn:country_code":"BR",
    "gn:dem":840,
    "gn:feature_class":"P",
    "gn:feature_code":"PPL",
    "gn:name":"S\u00edtio Antenor Jacob",
    "gn:population":0,
    "gn:timezone":"America/Sao_Paulo",
    "iso:country":"BR",
    "name:por_x_preferred":[
        "S\u00edtio Antenor Jacob"
    ],
    "wof:name":"Sitio Antenor Jacob",
    "wof:placetype":"locality"
},
  "geometry": {"coordinates":[-50.15913,-23.92673],"type":"Point"}
}