{
  "type": "Feature",
  "properties": {
    "gn:admin1_code":"02",
    "gn:admin2_code":"2709103.0",
    "gn:asciiname":"Passagem do Vigario",
    "gn:country_code":"BR",
    "gn:dem":240,
    "gn:feature_class":"P",
    "gn:feature_code":"PPL",
    "gn:name":"Passagem do Vig\u00e1rio",
    "gn:population":0,
    "gn:timezone":"America/Maceio",
    "iso:country":"BR",
    "wof:name":"Passagem do Vigario",
    "wof:placetype":"locality"
},
  "geometry": {"coordinates":[-36.53333,-9.53333],"type":"Point"}
}