{
  "type": "Feature",
  "properties": {
    "gn:admin1_code":"5",
    "gn:admin2_code":"2922805.0",
    "gn:asciiname":"Bom Jardim",
    "gn:country_code":"BR",
    "gn:dem":637,
    "gn:feature_class":"P",
    "gn:feature_code":"PPL",
    "gn:name":"Bom Jardim",
    "gn:population":0,
    "gn:timezone":"America/Bahia",
    "iso:country":"BR",
    "wof:name":"Bom Jardim",
    "wof:placetype":"locality"
},
  "geometry": {"coordinates":[-39.98333,-13.13333],"type":"Point"}
}