{
  "type": "Feature",
  "properties": {
    "gn:admin1_code":"18.0",
    "gn:admin2_code":"4128500.0",
    "gn:asciiname":"Sitio Alcino V. da Silva",
    "gn:country_code":"BR",
    "gn:dem":632,
    "gn:feature_class":"P",
    "gn:feature_code":"PPL",
    "gn:name":"S\u00edtio Alcino V. da Silva",
    "gn:population":0,
    "gn:timezone":"America/Sao_Paulo",
    "iso:country":"BR",
    "name:por_x_preferred":[
        "S\u00edtio Alcino V. da Silva"
    ],
    "wof:name":"Sitio Alcino V. da Silva",
    "wof:placetype":"locality"
},
  "geometry": {"coordinates":[-49.7677,-23.7484],"type":"Point"}
}