{
  "type": "Feature",
  "properties": {
    "gn:admin1_code":"15",
    "gn:admin2_code":"3104908.0",
    "gn:asciiname":"Bananal",
    "gn:country_code":"BR",
    "gn:dem":910,
    "gn:feature_class":"P",
    "gn:feature_code":"PPL",
    "gn:name":"Bananal",
    "gn:population":0,
    "gn:timezone":"America/Sao_Paulo",
    "iso:country":"BR",
    "name:ceb_x_preferred":[
        "Bananal"
    ],
    "name:deu_x_preferred":[
        "Bananal"
    ],
    "name:ita_x_preferred":[
        "Bananal"
    ],
    "name:nld_x_preferred":[
        "Bananal"
    ],
    "name:por_x_preferred":[
        "Bananal"
    ],
    "name:rus_x_preferred":[
        "\u0411\u0430\u043d\u0430\u043d\u0430\u043b"
    ],
    "name:swe_x_preferred":[
        "Bananal"
    ],
    "wof:name":"Bananal",
    "wof:placetype":"locality"
},
  "geometry": {"coordinates":[-44.81667,-22.01667],"type":"Point"}
}