{
  "type": "Feature",
  "properties": {
    "gn:admin1_code":"17",
    "gn:admin2_code":"2503704.0",
    "gn:asciiname":"Caldeirao",
    "gn:country_code":"BR",
    "gn:dem":360,
    "gn:feature_class":"P",
    "gn:feature_code":"PPL",
    "gn:name":"Caldeir\u00e3o",
    "gn:population":0,
    "gn:timezone":"America/Fortaleza",
    "iso:country":"BR",
    "wof:name":"Caldeirao",
    "wof:placetype":"locality"
},
  "geometry": {"coordinates":[-38.53333,-6.96667],"type":"Point"}
}