{
  "type": "Feature",
  "properties": {
    "gn:admin1_code":"21",
    "gn:admin2_code":"3300704.0",
    "gn:asciiname":"Costa",
    "gn:country_code":"BR",
    "gn:dem":1,
    "gn:feature_class":"P",
    "gn:feature_code":"PPL",
    "gn:name":"Costa",
    "gn:population":0,
    "gn:timezone":"America/Sao_Paulo",
    "iso:country":"BR",
    "name:por_x_preferred":[
        "Costa"
    ],
    "wof:name":"Costa",
    "wof:placetype":"locality"
},
  "geometry": {"coordinates":[-41.98796,-22.72102000000001],"type":"Point"}
}