{
  "type": "Feature",
  "properties": {
    "gn:admin1_code":"5",
    "gn:admin2_code":"2900801.0",
    "gn:asciiname":"Arara",
    "gn:country_code":"BR",
    "gn:dem":42,
    "gn:feature_class":"P",
    "gn:feature_code":"PPL",
    "gn:name":"Arara",
    "gn:population":0,
    "gn:timezone":"America/Bahia",
    "iso:country":"BR",
    "name:ceb_x_preferred":[
        "Arara"
    ],
    "name:ces_x_preferred":[
        "Arara"
    ],
    "name:deu_x_preferred":[
        "Arara"
    ],
    "name:hrv_x_preferred":[
        "Arara"
    ],
    "name:ita_x_preferred":[
        "Arara"
    ],
    "name:kat_x_preferred":[
        "\u10d0\u10e0\u10d0\u10e0\u10d0"
    ],
    "name:por_x_preferred":[
        "Arara"
    ],
    "name:rus_x_preferred":[
        "\u0410\u0440\u0430\u0440\u0430"
    ],
    "name:slk_x_preferred":[
        "Arara"
    ],
    "name:srp_x_preferred":[
        "\u0410\u0440\u0430\u0440\u0430"
    ],
    "name:swe_x_preferred":[
        "Arara"
    ],
    "name:vie_x_preferred":[
        "Arara"
    ],
    "wof:name":"Arara",
    "wof:placetype":"locality"
},
  "geometry": {"coordinates":[-39.58333,-17.53333],"type":"Point"}
}