{
  "type": "Feature",
  "properties": {
    "gn:admin1_code":"14",
    "gn:admin2_code":"5100805.0",
    "gn:asciiname":"Miranda",
    "gn:country_code":"BR",
    "gn:dem":158,
    "gn:feature_class":"P",
    "gn:feature_code":"PPL",
    "gn:name":"Miranda",
    "gn:population":0,
    "gn:timezone":"America/Cuiaba",
    "iso:country":"BR",
    "wof:name":"Miranda",
    "wof:placetype":"locality"
},
  "geometry": {"coordinates":[-57.95,-8.35],"type":"Point"}
}