{
  "type": "Feature",
  "properties": {
    "gn:admin1_code":"18.0",
    "gn:admin2_code":"4127882.0",
    "gn:asciiname":"Bairro Alto",
    "gn:country_code":"BR",
    "gn:dem":835,
    "gn:feature_class":"P",
    "gn:feature_code":"PPLL",
    "gn:name":"Bairro Alto",
    "gn:population":0,
    "gn:timezone":"America/Sao_Paulo",
    "iso:country":"BR",
    "name:cat_x_preferred":[
        "Bairro Alto"
    ],
    "name:deu_x_preferred":[
        "Bairro Alto"
    ],
    "name:eus_x_preferred":[
        "Bairro Alto"
    ],
    "name:fra_x_preferred":[
        "Bairro Alto"
    ],
    "name:ita_x_preferred":[
        "Bairro Alto"
    ],
    "name:jpn_x_preferred":[
        "\u30d0\u30a4\u30ed\u30fb\u30a2\u30eb\u30c8"
    ],
    "name:nld_x_preferred":[
        "Bairro Alto"
    ],
    "name:oci_x_preferred":[
        "Bairro Alto"
    ],
    "name:pol_x_preferred":[
        "Bairro Alto"
    ],
    "name:por_x_preferred":[
        "Bairro Alto"
    ],
    "name:rus_x_preferred":[
        "\u0411\u0430\u0439\u0440\u0440\u0443-\u0410\u043b\u0442\u0443"
    ],
    "name:swe_x_preferred":[
        "Bairro Alto"
    ],
    "name:zho_x_preferred":[
        "\u91cc\u65af\u672c\u4e0a\u57ce"
    ],
    "wof:name":"Bairro Alto",
    "wof:placetype":"locality"
},
  "geometry": {"coordinates":[-48.808,-24.92824],"type":"Point"}
}