{
  "type": "Feature",
  "properties": {
    "gn:admin1_code":"18.0",
    "gn:admin2_code":"4127882.0",
    "gn:asciiname":"Bairro Alto",
    "gn:country_code":"BR",
    "gn:dem":835,
    "gn:feature_class":"P",
    "gn:feature_code":"PPLL",
    "gn:name":"Bairro Alto",
    "gn:population":0,
    "gn:timezone":"America/Sao_Paulo",
    "iso:country":"BR",
    "name:por_x_preferred":[
        "Bairro Alto"
    ],
    "wof:name":"Bairro Alto",
    "wof:placetype":"locality"
},
  "geometry": {"coordinates":[-48.808,-24.92824],"type":"Point"}
}