{
  "type": "Feature",
  "properties": {
    "gn:admin1_code":"11",
    "gn:admin2_code":"5003207.0",
    "gn:asciiname":"Alegre",
    "gn:country_code":"BR",
    "gn:dem":112,
    "gn:feature_class":"P",
    "gn:feature_code":"PPL",
    "gn:name":"Alegre",
    "gn:population":0,
    "gn:timezone":"America/Campo_Grande",
    "iso:country":"BR",
    "wof:name":"Alegre",
    "wof:placetype":"locality"
},
  "geometry": {"coordinates":[-56.51667,-18.96667],"type":"Point"}
}