{
  "type": "Feature",
  "properties": {
    "gn:admin1_code":"17",
    "gn:admin2_code":"2504405.0",
    "gn:asciiname":"Pau Ferrinho",
    "gn:country_code":"BR",
    "gn:dem":441,
    "gn:feature_class":"P",
    "gn:feature_code":"PPL",
    "gn:name":"Pau Ferrinho",
    "gn:population":0,
    "gn:timezone":"America/Fortaleza",
    "iso:country":"BR",
    "wof:name":"Pau Ferrinho",
    "wof:placetype":"locality"
},
  "geometry": {"coordinates":[-38.51667,-7.63333],"type":"Point"}
}