{
  "type": "Feature",
  "properties": {
    "gn:admin1_code":"27.0",
    "gn:admin2_code":"3505401.0",
    "gn:asciiname":"Sanharao",
    "gn:country_code":"BR",
    "gn:dem":278,
    "gn:feature_class":"P",
    "gn:feature_code":"PPLL",
    "gn:name":"Sanhar\u00e3o",
    "gn:population":0,
    "gn:timezone":"America/Sao_Paulo",
    "iso:country":"BR",
    "name:por_x_preferred":[
        "Sanhar\u00e3o"
    ],
    "wof:name":"Sanharao",
    "wof:placetype":"locality"
},
  "geometry": {"coordinates":[-48.5447,-24.8247],"type":"Point"}
}