{
  "type": "Feature",
  "properties": {
    "gn:admin1_code":"26",
    "gn:admin2_code":"4201950.0",
    "gn:asciiname":"Arroio do Silva",
    "gn:country_code":"BR",
    "gn:dem":7,
    "gn:feature_class":"P",
    "gn:feature_code":"PPL",
    "gn:name":"Arroio do Silva",
    "gn:population":0,
    "gn:timezone":"America/Sao_Paulo",
    "iso:country":"BR",
    "wof:name":"Arroio do Silva",
    "wof:placetype":"locality"
},
  "geometry": {"coordinates":[-49.43333,-28.98333],"type":"Point"}
}