{
  "type": "Feature",
  "properties": {
    "gn:admin1_code":"14",
    "gn:admin2_code":"5103304.0",
    "gn:asciiname":"Novo Oeste",
    "gn:cc2":"BR",
    "gn:country_code":"BR",
    "gn:dem":673,
    "gn:feature_class":"P",
    "gn:feature_code":"PPL",
    "gn:name":"Novo Oeste",
    "gn:population":0,
    "gn:timezone":"America/Cuiaba",
    "iso:country":"BR",
    "name:und_x_variant":[
        "Vila Oeste",
        "Novo Oeste"
    ],
    "wof:name":"Novo Oeste",
    "wof:placetype":"locality"
},
  "geometry": {"coordinates":[-59.72917,-13.67917],"type":"Point"}
}