{
  "type": "Feature",
  "properties": {
    "iso:country":"BR",
    "name:por_x_preferred":[
        "Garcia"
    ],
    "qs:gn_adm0_cc":"BR",
    "qs:gn_local":3469968,
    "qs:gn_nam_loc":"Blumenau, Blumenau, Santa Catarina, BR",
    "qs:gn_namadm1":"26",
    "qs:local_max":1317,
    "qs:local_sum":3150,
    "qs:localhoods":9,
    "qs:name":"Garcia",
    "qs:name_adm0":"Brasil",
    "qs:name_adm1":"Santa Catarina",
    "qs:name_adm2":"Blumenau",
    "qs:name_local":"Blumenau",
    "qs:photo_max":2,
    "qs:photo_sum":6,
    "qs:placetype":"Suburb",
    "qs:quad_count":4,
    "qs:woe_adm0":23424768,
    "qs:woe_adm1":2344867,
    "qs:woe_adm2":12581621,
    "qs:woe_lau":0,
    "qs:woe_local":455846,
    "qs:woe_ver":"7.10.0",
    "wof:lang":[
        "por"
    ],
    "wof:name":"Garcia",
    "wof:placetype":"neighbourhood"
},
  "geometry": {"coordinates":[-49.065857,-26.941659],"type":"Point"}
}