{
  "type": "Feature",
  "properties": {
    "gn:admin1_code":"17",
    "gn:admin2_code":"2514503.0",
    "gn:asciiname":"Sao Miguel",
    "gn:country_code":"BR",
    "gn:dem":500,
    "gn:feature_class":"P",
    "gn:feature_code":"PPL",
    "gn:name":"S\u00e3o Miguel",
    "gn:population":0,
    "gn:timezone":"America/Fortaleza",
    "iso:country":"BR",
    "wof:name":"Sao Miguel",
    "wof:placetype":"locality"
},
  "geometry": {"coordinates":[-38.35,-7.15],"type":"Point"}
}