{
  "type": "Feature",
  "properties": {
    "gn:admin1_code":"21",
    "gn:admin2_code":"3304110.0",
    "gn:asciiname":"Acacias",
    "gn:country_code":"BR",
    "gn:dem":413,
    "gn:feature_class":"P",
    "gn:feature_code":"PPLL",
    "gn:name":"Ac\u00e1cias",
    "gn:population":0,
    "gn:timezone":"America/Sao_Paulo",
    "iso:country":"BR",
    "name:por_x_preferred":[
        "Ac\u00e1cias"
    ],
    "wof:name":"Acacias",
    "wof:placetype":"locality"
},
  "geometry": {"coordinates":[-44.3228,-22.44],"type":"Point"}
}