{
  "type": "Feature",
  "properties": {
    "gn:admin1_code":"5",
    "gn:admin2_code":"2908903.0",
    "gn:asciiname":"Pau Pombo",
    "gn:country_code":"BR",
    "gn:dem":220,
    "gn:feature_class":"P",
    "gn:feature_code":"PPL",
    "gn:name":"Pau Pombo",
    "gn:population":0,
    "gn:timezone":"America/Bahia",
    "iso:country":"BR",
    "wof:name":"Pau Pombo",
    "wof:placetype":"locality"
},
  "geometry": {"coordinates":[-38.86667,-12.15],"type":"Point"}
}