{
  "type": "Feature",
  "properties": {
    "gn:admin1_code":"18.0",
    "gn:admin2_code":"4112801.0",
    "gn:asciiname":"Sitio Miguel Junior",
    "gn:country_code":"BR",
    "gn:dem":608,
    "gn:feature_class":"P",
    "gn:feature_code":"PPL",
    "gn:name":"S\u00edtio Miguel J\u00fanior",
    "gn:population":0,
    "gn:timezone":"America/Sao_Paulo",
    "iso:country":"BR",
    "name:por_x_preferred":[
        "S\u00edtio Miguel J\u00fanior"
    ],
    "wof:name":"Sitio Miguel Junior",
    "wof:placetype":"locality"
},
  "geometry": {"coordinates":[-49.8968,-23.502],"type":"Point"}
}