{
  "type": "Feature",
  "properties": {
    "gn:admin1_code":"30",
    "gn:admin2_code":"2613909.0",
    "gn:asciiname":"Gameleira",
    "gn:country_code":"BR",
    "gn:dem":619,
    "gn:feature_class":"P",
    "gn:feature_code":"PPL",
    "gn:name":"Gameleira",
    "gn:population":0,
    "gn:timezone":"America/Recife",
    "iso:country":"BR",
    "wof:name":"Gameleira",
    "wof:placetype":"locality"
},
  "geometry": {"coordinates":[-38.56667,-7.76667],"type":"Point"}
}