{
  "type": "Feature",
  "properties": {
    "gn:admin1_code":"4",
    "gn:admin2_code":"1302702.0",
    "gn:asciiname":"Colares",
    "gn:country_code":"BR",
    "gn:dem":34,
    "gn:feature_class":"P",
    "gn:feature_code":"PPL",
    "gn:name":"Colares",
    "gn:population":0,
    "gn:timezone":"America/Manaus",
    "iso:country":"BR",
    "name:bpy_x_preferred":[
        "\u0995\u09cb\u09b2\u09be\u09b0\u09c7\u09b8"
    ],
    "name:ceb_x_preferred":[
        "Colares"
    ],
    "name:deu_x_preferred":[
        "Colares"
    ],
    "name:fra_x_preferred":[
        "Colares"
    ],
    "name:nld_x_preferred":[
        "Colares"
    ],
    "name:por_x_preferred":[
        "Colar"
    ],
    "name:spa_x_preferred":[
        "Colares"
    ],
    "name:swe_x_preferred":[
        "Colares"
    ],
    "wof:name":"Colares",
    "wof:placetype":"locality"
},
  "geometry": {"coordinates":[-60.83639,-5.51806],"type":"Point"}
}