{
  "type": "Feature",
  "properties": {
    "gn:admin1_code":"18",
    "gn:admin2_code":"4101606.0",
    "gn:asciiname":"Cerrado",
    "gn:country_code":"BR",
    "gn:dem":603,
    "gn:feature_class":"P",
    "gn:feature_code":"PPL",
    "gn:name":"Cerrado",
    "gn:population":0,
    "gn:timezone":"America/Sao_Paulo",
    "iso:country":"BR",
    "wof:name":"Cerrado",
    "wof:placetype":"locality"
},
  "geometry": {"coordinates":[-49.95,-24.08333],"type":"Point"}
}