{
  "type": "Feature",
  "properties": {
    "gn:admin1_code":"18",
    "gn:admin2_code":"4101606.0",
    "gn:asciiname":"Cerrado",
    "gn:country_code":"BR",
    "gn:dem":603,
    "gn:feature_class":"P",
    "gn:feature_code":"PPL",
    "gn:name":"Cerrado",
    "gn:population":0,
    "gn:timezone":"America/Sao_Paulo",
    "iso:country":"BR",
    "name:bul_x_preferred":[
        "\u0421\u0435\u0440\u0430\u0434\u043e"
    ],
    "name:cat_x_preferred":[
        "Cerrado"
    ],
    "name:ces_x_preferred":[
        "Cerrado"
    ],
    "name:dan_x_preferred":[
        "Cerrado"
    ],
    "name:deu_x_preferred":[
        "Cerrado"
    ],
    "name:epo_x_preferred":[
        "Cerado"
    ],
    "name:fas_x_preferred":[
        "\u0633\u0631\u0627\u062f\u0648"
    ],
    "name:fin_x_preferred":[
        "Cerrado"
    ],
    "name:fra_x_preferred":[
        "Cerrado"
    ],
    "name:heb_x_preferred":[
        "\u05e1\u05e8\u05d0\u05d3\u05d5"
    ],
    "name:hrv_x_preferred":[
        "Cerrado"
    ],
    "name:ind_x_preferred":[
        "Cerrado"
    ],
    "name:ita_x_preferred":[
        "Cerrado"
    ],
    "name:jpn_x_preferred":[
        "\u30ab\u30f3\u30dd\u30fb\u30bb\u30cf\u30fc\u30c9"
    ],
    "name:lit_x_preferred":[
        "Seradas"
    ],
    "name:mai_x_preferred":[
        "\u0915\u0947\u0930\u094d\u0930\u093e\u0926\u094b"
    ],
    "name:mal_x_preferred":[
        "\u0d38\u0d46\u0d31\u0d3e\u0d27\u0d4b"
    ],
    "name:nep_x_preferred":[
        "\u0915\u0947\u0930\u094d\u0930\u093e\u0926\u094b"
    ],
    "name:nld_x_preferred":[
        "Cerrado"
    ],
    "name:nor_x_preferred":[
        "Cerrado"
    ],
    "name:pol_x_preferred":[
        "Cerrado"
    ],
    "name:por_x_preferred":[
        "Cerrado"
    ],
    "name:ron_x_preferred":[
        "Cerrado"
    ],
    "name:rus_x_preferred":[
        "\u0421\u0435\u0440\u0440\u0430\u0434\u043e"
    ],
    "name:swe_x_preferred":[
        "Cerradon"
    ],
    "name:ukr_x_preferred":[
        "\u0421\u0435\u0440\u0440\u0430\u0434\u043e"
    ],
    "name:zho_x_preferred":[
        "\u585e\u62c9\u591a"
    ],
    "wof:name":"Cerrado",
    "wof:placetype":"locality"
},
  "geometry": {"coordinates":[-49.95,-24.08333],"type":"Point"}
}