{
  "type": "Feature",
  "properties": {
    "gn:admin1_code":"30",
    "gn:admin2_code":"2615706.0",
    "gn:asciiname":"Sao Crispim",
    "gn:country_code":"BR",
    "gn:dem":853,
    "gn:feature_class":"P",
    "gn:feature_code":"PPL",
    "gn:name":"S\u00e3o Crispim",
    "gn:population":0,
    "gn:timezone":"America/Recife",
    "iso:country":"BR",
    "wof:name":"Sao Crispim",
    "wof:placetype":"locality"
},
  "geometry": {"coordinates":[-38.06667,-7.85],"type":"Point"}
}