{
  "type": "Feature",
  "properties": {
    "gn:admin1_code":"13",
    "gn:admin2_code":"2103307.0",
    "gn:asciiname":"Sao Joaquim",
    "gn:country_code":"BR",
    "gn:dem":63,
    "gn:feature_class":"P",
    "gn:feature_code":"PPL",
    "gn:name":"S\u00e3o Joaquim",
    "gn:population":0,
    "gn:timezone":"America/Fortaleza",
    "iso:country":"BR",
    "wof:name":"Sao Joaquim",
    "wof:placetype":"locality"
},
  "geometry": {"coordinates":[-43.81667,-4.35],"type":"Point"}
}