{
  "type": "Feature",
  "properties": {
    "gn:admin1_code":"27.0",
    "gn:admin2_code":"3528502.0",
    "gn:asciiname":"Jardim das Flores",
    "gn:country_code":"BR",
    "gn:dem":962,
    "gn:feature_class":"P",
    "gn:feature_code":"PPLL",
    "gn:name":"Jardim das Flores",
    "gn:population":0,
    "gn:timezone":"America/Sao_Paulo",
    "iso:country":"BR",
    "name:por_x_preferred":[
        "Jardim das Flores"
    ],
    "wof:name":"Jardim das Flores",
    "wof:placetype":"locality"
},
  "geometry": {"coordinates":[-46.54507,-23.25203],"type":"Point"}
}