{
  "type": "Feature",
  "properties": {
    "gn:admin1_code":"18.0",
    "gn:admin2_code":"4106209.0",
    "gn:asciiname":"Sitio Francisco Centenarovski",
    "gn:country_code":"BR",
    "gn:dem":906,
    "gn:feature_class":"P",
    "gn:feature_code":"PPL",
    "gn:name":"S\u00edtio Francisco Centenarovski",
    "gn:population":0,
    "gn:timezone":"America/Sao_Paulo",
    "iso:country":"BR",
    "name:por_x_preferred":[
        "S\u00edtio Francisco Centenarovski"
    ],
    "wof:name":"Sitio Francisco Centenarovski",
    "wof:placetype":"locality"
},
  "geometry": {"coordinates":[-49.42344,-25.77061],"type":"Point"}
}