{
  "type": "Feature",
  "properties": {
    "gn:admin1_code":"18",
    "gn:admin2_code":"4119103.0",
    "gn:asciiname":"Sitio Olivio Train",
    "gn:country_code":"BR",
    "gn:dem":838,
    "gn:feature_class":"P",
    "gn:feature_code":"PPL",
    "gn:name":"S\u00edtio Ol\u00edvio Train",
    "gn:population":0,
    "gn:timezone":"America/Sao_Paulo",
    "iso:country":"BR",
    "name:por_x_preferred":[
        "S\u00edtio Ol\u00edvio Train"
    ],
    "wof:name":"Sitio Olivio Train",
    "wof:placetype":"locality"
},
  "geometry": {"coordinates":[-49.50362,-26.15498],"type":"Point"}
}