{
  "type": "Feature",
  "properties": {
    "gn:admin1_code":"18.0",
    "gn:admin2_code":"4126207.0",
    "gn:asciiname":"Sitio Romilio L. Moreira",
    "gn:country_code":"BR",
    "gn:dem":741,
    "gn:feature_class":"P",
    "gn:feature_code":"PPL",
    "gn:name":"S\u00edtio Rom\u00edlio L. Moreira",
    "gn:population":0,
    "gn:timezone":"America/Sao_Paulo",
    "iso:country":"BR",
    "name:por_x_preferred":[
        "S\u00edtio Rom\u00edlio L. Moreira"
    ],
    "wof:name":"Sitio Romilio L. Moreira",
    "wof:placetype":"locality"
},
  "geometry": {"coordinates":[-50.64344000000001,-23.89764],"type":"Point"}
}