{
  "type": "Feature",
  "properties": {
    "gn:admin1_code":"27",
    "gn:admin2_code":"3519709.0",
    "gn:asciiname":"Sitio do Capitao",
    "gn:country_code":"BR",
    "gn:dem":940,
    "gn:feature_class":"P",
    "gn:feature_code":"PPL",
    "gn:name":"S\u00edtio do Capit\u00e3o",
    "gn:population":0,
    "gn:timezone":"America/Sao_Paulo",
    "iso:country":"BR",
    "name:por_x_preferred":[
        "S\u00edtio do Capit\u00e3o"
    ],
    "wof:name":"Sitio do Capitao",
    "wof:placetype":"locality"
},
  "geometry": {"coordinates":[-47.13532,-23.70658],"type":"Point"}
}