{
  "type": "Feature",
  "properties": {
    "gn:admin1_code":"5",
    "gn:admin2_code":"2915403.0",
    "gn:asciiname":"Colonia",
    "gn:country_code":"BR",
    "gn:dem":200,
    "gn:feature_class":"P",
    "gn:feature_code":"PPL",
    "gn:name":"Col\u00f4nia",
    "gn:population":0,
    "gn:timezone":"America/Bahia",
    "iso:country":"BR",
    "wof:name":"Colonia",
    "wof:placetype":"locality"
},
  "geometry": {"coordinates":[-39.88333,-15.11667],"type":"Point"}
}