{
  "type": "Feature",
  "properties": {
    "gn:admin1_code":"18.0",
    "gn:admin2_code":"4109708.0",
    "gn:asciiname":"Sitio Sao Domingos",
    "gn:country_code":"BR",
    "gn:dem":596,
    "gn:feature_class":"P",
    "gn:feature_code":"PPL",
    "gn:name":"S\u00edtio S\u00e3o Domingos",
    "gn:population":0,
    "gn:timezone":"America/Sao_Paulo",
    "iso:country":"BR",
    "name:por_x_preferred":[
        "S\u00edtio S\u00e3o Domingos"
    ],
    "wof:name":"Sitio Sao Domingos",
    "wof:placetype":"locality"
},
  "geometry": {"coordinates":[-50.22327,-23.78111],"type":"Point"}
}