{
  "type": "Feature",
  "properties": {
    "gn:admin1_code":"18.0",
    "gn:admin2_code":"4126603.0",
    "gn:asciiname":"Sitio Pedro V. da Silva",
    "gn:country_code":"BR",
    "gn:dem":658,
    "gn:feature_class":"P",
    "gn:feature_code":"PPL",
    "gn:name":"S\u00edtio Pedro V. da Silva",
    "gn:population":0,
    "gn:timezone":"America/Sao_Paulo",
    "iso:country":"BR",
    "name:por_x_preferred":[
        "S\u00edtio Pedro V. da Silva"
    ],
    "wof:name":"Sitio Pedro V. da Silva",
    "wof:placetype":"locality"
},
  "geometry": {"coordinates":[-49.8529,-23.6845],"type":"Point"}
}