{
  "type": "Feature",
  "properties": {
    "gn:admin1_code":"18.0",
    "gn:admin2_code":"4103602.0",
    "gn:asciiname":"Sitio Aristides Estevao",
    "gn:country_code":"BR",
    "gn:dem":460,
    "gn:feature_class":"P",
    "gn:feature_code":"PPL",
    "gn:name":"S\u00edtio Aristides Est\u00eav\u00e3o",
    "gn:population":0,
    "gn:timezone":"America/Sao_Paulo",
    "iso:country":"BR",
    "name:por_x_preferred":[
        "S\u00edtio Aristides Est\u00eav\u00e3o"
    ],
    "wof:name":"Sitio Aristides Estevao",
    "wof:placetype":"locality"
},
  "geometry": {"coordinates":[-50.1905,-23.0455],"type":"Point"}
}