{
  "type": "Feature",
  "properties": {
    "gn:admin1_code":"18",
    "gn:admin2_code":"4103354.0",
    "gn:asciiname":"Colonia Sao Pedro",
    "gn:country_code":"BR",
    "gn:dem":671,
    "gn:feature_class":"P",
    "gn:feature_code":"PPL",
    "gn:name":"Col\u00f4nia S\u00e3o Pedro",
    "gn:population":0,
    "gn:timezone":"America/Sao_Paulo",
    "iso:country":"BR",
    "wof:name":"Colonia Sao Pedro",
    "wof:placetype":"locality"
},
  "geometry": {"coordinates":[-53.18333000000001,-24.93333],"type":"Point"}
}