{
  "type": "Feature",
  "properties": {
    "gn:admin1_code":"30",
    "gn:admin2_code":"2610707.0",
    "gn:asciiname":"Navarro",
    "gn:country_code":"BR",
    "gn:dem":50,
    "gn:feature_class":"P",
    "gn:feature_code":"PPLL",
    "gn:name":"Navarro",
    "gn:population":0,
    "gn:timezone":"America/Recife",
    "iso:country":"BR",
    "wof:name":"Navarro",
    "wof:placetype":"locality"
},
  "geometry": {"coordinates":[-34.89056,-7.96222],"type":"Point"}
}