{
  "type": "Feature",
  "properties": {
    "gn:admin1_code":"13",
    "gn:admin2_code":"2101509.0",
    "gn:asciiname":"Praia",
    "gn:country_code":"BR",
    "gn:dem":129,
    "gn:feature_class":"P",
    "gn:feature_code":"PPL",
    "gn:name":"Praia",
    "gn:population":0,
    "gn:timezone":"America/Fortaleza",
    "iso:country":"BR",
    "wof:name":"Praia",
    "wof:placetype":"locality"
},
  "geometry": {"coordinates":[-43.11667,-6.71667],"type":"Point"}
}