{
  "type": "Feature",
  "properties": {
    "gn:admin1_code":"6.0",
    "gn:admin2_code":"2301000.0",
    "gn:asciiname":"Cajueiro do Ministro",
    "gn:country_code":"BR",
    "gn:dem":33,
    "gn:feature_class":"P",
    "gn:feature_code":"PPL",
    "gn:name":"Cajueiro do Ministro",
    "gn:population":0,
    "gn:timezone":"America/Fortaleza",
    "iso:country":"BR",
    "wof:name":"Cajueiro do Ministro",
    "wof:placetype":"locality"
},
  "geometry": {"coordinates":[-38.32503,-4.00865],"type":"Point"}
}