{
  "type": "Feature",
  "properties": {
    "gn:admin1_code":"8",
    "gn:admin2_code":"3204203.0",
    "gn:asciiname":"Itapitanga",
    "gn:country_code":"BR",
    "gn:dem":3,
    "gn:feature_class":"P",
    "gn:feature_code":"PPL",
    "gn:name":"Itapitanga",
    "gn:population":0,
    "gn:timezone":"America/Sao_Paulo",
    "iso:country":"BR",
    "name:por_x_preferred":[
        "Itapitanga"
    ],
    "wof:name":"Itapitanga",
    "wof:placetype":"locality"
},
  "geometry": {"coordinates":[-40.75,-20.85],"type":"Point"}
}