{
  "type": "Feature",
  "properties": {
    "gn:admin1_code":"8",
    "gn:admin2_code":"3204203.0",
    "gn:asciiname":"Itapitanga",
    "gn:country_code":"BR",
    "gn:dem":3,
    "gn:feature_class":"P",
    "gn:feature_code":"PPL",
    "gn:name":"Itapitanga",
    "gn:population":0,
    "gn:timezone":"America/Sao_Paulo",
    "iso:country":"BR",
    "name:bpy_x_preferred":[
        "\u0987\u099f\u09be\u09aa\u09bf\u099f\u09be\u0999\u09cd\u0997\u09be"
    ],
    "name:ceb_x_preferred":[
        "Itapitanga"
    ],
    "name:epo_x_preferred":[
        "Itapitanga"
    ],
    "name:eus_x_preferred":[
        "Itapitanga"
    ],
    "name:fra_x_preferred":[
        "Itapitanga"
    ],
    "name:hye_x_preferred":[
        "\u053b\u057f\u0561\u057a\u056b\u057f\u0561\u0576\u0563\u0561"
    ],
    "name:ita_x_preferred":[
        "Itapitanga"
    ],
    "name:kat_x_preferred":[
        "\u10d8\u10e2\u10d0\u10de\u10d8\u10e2\u10d0\u10dc\u10d2\u10d0"
    ],
    "name:kaz_x_preferred":[
        "\u0418\u0442\u0430\u043f\u0438\u0442\u0430\u043d\u0433\u0430"
    ],
    "name:mlg_x_preferred":[
        "Itapitanga"
    ],
    "name:nld_x_preferred":[
        "Itapitanga"
    ],
    "name:nor_x_preferred":[
        "Itapitanga"
    ],
    "name:pol_x_preferred":[
        "Itapitanga"
    ],
    "name:por_x_preferred":[
        "Itapitanga"
    ],
    "name:ron_x_preferred":[
        "Itapitanga"
    ],
    "name:rus_x_preferred":[
        "\u0418\u0442\u0430\u043f\u0438\u0442\u0430\u043d\u0433\u0430"
    ],
    "name:spa_x_preferred":[
        "Itapitanga"
    ],
    "name:swe_x_preferred":[
        "Itapitanga"
    ],
    "name:vie_x_preferred":[
        "Itapitanga"
    ],
    "name:vol_x_preferred":[
        "Itapitanga"
    ],
    "name:war_x_preferred":[
        "Itapitanga"
    ],
    "name:zho_x_preferred":[
        "\u4f0a\u5854\u76ae\u5766\u52a0"
    ],
    "wof:name":"Itapitanga",
    "wof:placetype":"locality"
},
  "geometry": {"coordinates":[-40.75,-20.85],"type":"Point"}
}