{
  "type": "Feature",
  "properties": {
    "gn:admin1_code":"5",
    "gn:admin2_code":"2926707.0",
    "gn:asciiname":"Real",
    "gn:country_code":"BR",
    "gn:dem":532,
    "gn:feature_class":"P",
    "gn:feature_code":"PPL",
    "gn:name":"Real",
    "gn:population":0,
    "gn:timezone":"America/Bahia",
    "iso:country":"BR",
    "wof:name":"Real",
    "wof:placetype":"locality"
},
  "geometry": {"coordinates":[-41.53333,-13.86667],"type":"Point"}
}