{
  "type": "Feature",
  "properties": {
    "gn:admin1_code":"18",
    "gn:admin2_code":"4121208.0",
    "gn:asciiname":"Sitio Nelson Kipoviski",
    "gn:country_code":"BR",
    "gn:dem":891,
    "gn:feature_class":"P",
    "gn:feature_code":"PPL",
    "gn:name":"S\u00edtio Nelson Kipoviski",
    "gn:population":0,
    "gn:timezone":"America/Sao_Paulo",
    "iso:country":"BR",
    "name:por_x_preferred":[
        "S\u00edtio Nelson Kipoviski"
    ],
    "wof:name":"Sitio Nelson Kipoviski",
    "wof:placetype":"locality"
},
  "geometry": {"coordinates":[-49.4736,-26.0253],"type":"Point"}
}