{
  "type": "Feature",
  "properties": {
    "gn:admin1_code":"1",
    "gn:admin2_code":"1200351.0",
    "gn:asciiname":"Estirao do Tejo",
    "gn:country_code":"BR",
    "gn:dem":226,
    "gn:feature_class":"P",
    "gn:feature_code":"PPL",
    "gn:name":"Estir\u00e3o do Tejo",
    "gn:population":0,
    "gn:timezone":"America/Rio_Branco",
    "iso:country":"BR",
    "wof:name":"Estirao do Tejo",
    "wof:placetype":"locality"
},
  "geometry": {"coordinates":[-72.73305999999999,-8.98944],"type":"Point"}
}