{
  "type": "Feature",
  "properties": {
    "gn:admin1_code":"18.0",
    "gn:admin2_code":"4106100.0",
    "gn:asciiname":"Sitio Alvorada",
    "gn:country_code":"BR",
    "gn:dem":507,
    "gn:feature_class":"P",
    "gn:feature_code":"PPL",
    "gn:name":"S\u00edtio Alvorada",
    "gn:population":0,
    "gn:timezone":"America/Sao_Paulo",
    "iso:country":"BR",
    "name:por_x_preferred":[
        "S\u00edtio Alvorada"
    ],
    "wof:name":"Sitio Alvorada",
    "wof:placetype":"locality"
},
  "geometry": {"coordinates":[-50.17584,-23.63153],"type":"Point"}
}