{
  "type": "Feature",
  "properties": {
    "gn:admin1_code":"11",
    "gn:admin2_code":"5006606.0",
    "gn:asciiname":"Sipicue",
    "gn:cc2":"BR",
    "gn:country_code":"BR",
    "gn:dem":640,
    "gn:feature_class":"P",
    "gn:feature_code":"PPL",
    "gn:name":"Sipicu\u00ea",
    "gn:population":0,
    "gn:timezone":"America/Campo_Grande",
    "iso:country":"BR",
    "name:und_x_variant":[
        "Santo Thomaz",
        "S\u00e3o Tom\u00e1s",
        "S\u00e3o Tomaz",
        "Sipicu\u00ea"
    ],
    "wof:name":"Sipicue",
    "wof:placetype":"locality"
},
  "geometry": {"coordinates":[-55.68333000000001,-22.55],"type":"Point"}
}