{
  "type": "Feature",
  "properties": {
    "gn:admin1_code":"20",
    "gn:admin2_code":"2201903.0",
    "gn:asciiname":"Lagoa Cercada",
    "gn:country_code":"BR",
    "gn:dem":336,
    "gn:feature_class":"P",
    "gn:feature_code":"PPL",
    "gn:name":"Lagoa Cercada",
    "gn:population":0,
    "gn:timezone":"America/Fortaleza",
    "iso:country":"BR",
    "wof:name":"Lagoa Cercada",
    "wof:placetype":"locality"
},
  "geometry": {"coordinates":[-44.25,-9.13333],"type":"Point"}
}