{
  "type": "Feature",
  "properties": {
    "gn:admin1_code":"5",
    "gn:admin2_code":"2930501.0",
    "gn:asciiname":"Mombaca",
    "gn:country_code":"BR",
    "gn:dem":291,
    "gn:feature_class":"P",
    "gn:feature_code":"PPL",
    "gn:name":"Momba\u00e7a",
    "gn:population":0,
    "gn:timezone":"America/Bahia",
    "iso:country":"BR",
    "wof:name":"Mombaca",
    "wof:placetype":"locality"
},
  "geometry": {"coordinates":[-38.91667,-11.61667],"type":"Point"}
}