{
  "type": "Feature",
  "properties": {
    "gn:admin1_code":"18",
    "gn:admin2_code":"4122305.0",
    "gn:asciiname":"Sitio Jaime Rutheis",
    "gn:country_code":"BR",
    "gn:dem":785,
    "gn:feature_class":"P",
    "gn:feature_code":"PPL",
    "gn:name":"S\u00edtio Jaime Rutheis",
    "gn:population":0,
    "gn:timezone":"America/Sao_Paulo",
    "iso:country":"BR",
    "name:por_x_preferred":[
        "S\u00edtio Jaime Rutheis"
    ],
    "wof:name":"Sitio Jaime Rutheis",
    "wof:placetype":"locality"
},
  "geometry": {"coordinates":[-49.70929,-26.13527],"type":"Point"}
}