{
  "type": "Feature",
  "properties": {
    "gn:admin1_code":"27",
    "gn:admin2_code":"3528403.0",
    "gn:asciiname":"Sitio Santa Teresa",
    "gn:country_code":"BR",
    "gn:dem":818,
    "gn:feature_class":"P",
    "gn:feature_code":"PPL",
    "gn:name":"S\u00edtio Santa Teresa",
    "gn:population":0,
    "gn:timezone":"America/Sao_Paulo",
    "iso:country":"BR",
    "name:por_x_preferred":[
        "S\u00edtio Santa Teresa"
    ],
    "wof:name":"Sitio Santa Teresa",
    "wof:placetype":"locality"
},
  "geometry": {"coordinates":[-47.21172,-23.54324],"type":"Point"}
}