{
  "type": "Feature",
  "properties": {
    "gn:admin1_code":"13",
    "gn:admin2_code":"2102200.0",
    "gn:asciiname":"Lagoa do Exu",
    "gn:cc2":"BR",
    "gn:country_code":"BR",
    "gn:dem":120,
    "gn:feature_class":"P",
    "gn:feature_code":"PPL",
    "gn:name":"Lagoa do Exu",
    "gn:population":0,
    "gn:timezone":"America/Fortaleza",
    "iso:country":"BR",
    "name:und_x_variant":[
        "Lagoa do Enchu",
        "Lagoa do Exu"
    ],
    "wof:name":"Lagoa do Exu",
    "wof:placetype":"locality"
},
  "geometry": {"coordinates":[-43.05,-4.01667],"type":"Point"}
}