{
  "type": "Feature",
  "properties": {
    "gn:admin1_code":"18.0",
    "gn:admin2_code":"4124707.0",
    "gn:asciiname":"Esperanca",
    "gn:country_code":"BR",
    "gn:dem":1068,
    "gn:feature_class":"P",
    "gn:feature_code":"PPLL",
    "gn:name":"Esperan\u00e7a",
    "gn:population":0,
    "gn:timezone":"America/Sao_Paulo",
    "iso:country":"BR",
    "name:por_x_preferred":[
        "Esperan\u00e7a"
    ],
    "wof:name":"Esperanca",
    "wof:placetype":"locality"
},
  "geometry": {"coordinates":[-50.64522,-23.78486],"type":"Point"}
}