{
  "type": "Feature",
  "properties": {
    "gn:admin1_code":"20",
    "gn:admin2_code":"2205805.0",
    "gn:asciiname":"Morrinhos",
    "gn:country_code":"BR",
    "gn:dem":26,
    "gn:feature_class":"P",
    "gn:feature_code":"PPL",
    "gn:name":"Morrinhos",
    "gn:population":0,
    "gn:timezone":"America/Fortaleza",
    "iso:country":"BR",
    "name:bpy_x_preferred":[
        "\u09ae\u09cb\u09b0\u09cd\u09b0\u09bf\u09a8\u09b9\u09cb\u09b8"
    ],
    "name:ceb_x_preferred":[
        "Morrinhos"
    ],
    "name:deu_x_preferred":[
        "Morrinhos"
    ],
    "name:ita_x_preferred":[
        "Morrinhos"
    ],
    "name:mlg_x_preferred":[
        "Morrinhos"
    ],
    "name:nld_x_preferred":[
        "Morrinhos"
    ],
    "name:nor_x_preferred":[
        "Morrinhos"
    ],
    "name:por_x_preferred":[
        "Morrinhos"
    ],
    "name:rus_x_preferred":[
        "\u041c\u043e\u0440\u0440\u0438\u043d\u044c\u044e\u0441"
    ],
    "name:swe_x_preferred":[
        "Morrinhos"
    ],
    "name:vie_x_preferred":[
        "Morrinhos"
    ],
    "name:vol_x_preferred":[
        "Morrinhos"
    ],
    "name:war_x_preferred":[
        "Morrinhos"
    ],
    "wof:name":"Morrinhos",
    "wof:placetype":"locality"
},
  "geometry": {"coordinates":[-42.23583,-3.46278],"type":"Point"}
}