{
  "type": "Feature",
  "properties": {
    "gn:admin1_code":"20",
    "gn:admin2_code":"2205805.0",
    "gn:asciiname":"Morrinhos",
    "gn:country_code":"BR",
    "gn:dem":26,
    "gn:feature_class":"P",
    "gn:feature_code":"PPL",
    "gn:name":"Morrinhos",
    "gn:population":0,
    "gn:timezone":"America/Fortaleza",
    "iso:country":"BR",
    "wof:name":"Morrinhos",
    "wof:placetype":"locality"
},
  "geometry": {"coordinates":[-42.23583,-3.46278],"type":"Point"}
}