{
  "type": "Feature",
  "properties": {
    "gn:admin1_code":"6",
    "gn:admin2_code":"2304954.0",
    "gn:asciiname":"Boa Esperanca",
    "gn:country_code":"BR",
    "gn:dem":99,
    "gn:feature_class":"P",
    "gn:feature_code":"PPL",
    "gn:name":"Boa Esperanca",
    "gn:population":0,
    "gn:timezone":"America/Fortaleza",
    "iso:country":"BR",
    "wof:name":"Boa Esperanca",
    "wof:placetype":"locality"
},
  "geometry": {"coordinates":[-38.75,-4.13333],"type":"Point"}
}