{
  "type": "Feature",
  "properties": {
    "gn:admin1_code":"5",
    "gn:admin2_code":"2918001.0",
    "gn:asciiname":"Jatoba",
    "gn:country_code":"BR",
    "gn:dem":614,
    "gn:feature_class":"P",
    "gn:feature_code":"PPL",
    "gn:name":"Jatob\u00e1",
    "gn:population":0,
    "gn:timezone":"America/Bahia",
    "iso:country":"BR",
    "wof:name":"Jatoba",
    "wof:placetype":"locality"
},
  "geometry": {"coordinates":[-40.18333,-13.78333],"type":"Point"}
}