{
  "type": "Feature",
  "properties": {
    "gn:admin1_code":"4",
    "gn:admin2_code":"1304104.0",
    "gn:asciiname":"Tartaruga",
    "gn:country_code":"BR",
    "gn:dem":46,
    "gn:feature_class":"P",
    "gn:feature_code":"PPL",
    "gn:name":"Tartaruga",
    "gn:population":0,
    "gn:timezone":"America/Manaus",
    "iso:country":"BR",
    "name:glg_x_preferred":[
        "Tartaruga"
    ],
    "name:ita_x_preferred":[
        "Tartaruga"
    ],
    "wof:name":"Tartaruga",
    "wof:placetype":"locality"
},
  "geometry": {"coordinates":[-64.46028000000001,-5.86417],"type":"Point"}
}