{
  "type": "Feature",
  "properties": {
    "gn:admin1_code":"15",
    "gn:admin2_code":"3126950.0",
    "gn:asciiname":"Alves",
    "gn:country_code":"BR",
    "gn:dem":661,
    "gn:feature_class":"P",
    "gn:feature_code":"PPL",
    "gn:name":"Alves",
    "gn:population":0,
    "gn:timezone":"America/Sao_Paulo",
    "iso:country":"BR",
    "name:deu_x_preferred":[
        "Alves"
    ],
    "name:por_x_preferred":[
        "Alves"
    ],
    "wof:name":"Alves",
    "wof:placetype":"locality"
},
  "geometry": {"coordinates":[-42.75,-18.16667],"type":"Point"}
}