{
  "type": "Feature",
  "properties": {
    "gn:admin1_code":"06",
    "gn:admin2_code":"2306108.0",
    "gn:asciiname":"Fazenda Cidade",
    "gn:country_code":"BR",
    "gn:dem":178,
    "gn:feature_class":"P",
    "gn:feature_code":"PPL",
    "gn:name":"Fazenda Cidade",
    "gn:population":0,
    "gn:timezone":"America/Fortaleza",
    "iso:country":"BR",
    "wof:name":"Fazenda Cidade",
    "wof:placetype":"locality"
},
  "geometry": {"coordinates":[-39.86667,-3.91667],"type":"Point"}
}