{
  "type": "Feature",
  "properties": {
    "gn:admin1_code":"6",
    "gn:admin2_code":"2303501.0",
    "gn:asciiname":"Aguas Belas",
    "gn:country_code":"BR",
    "gn:dem":1,
    "gn:feature_class":"P",
    "gn:feature_code":"PPL",
    "gn:name":"\u00c1guas Belas",
    "gn:population":0,
    "gn:timezone":"America/Fortaleza",
    "iso:country":"BR",
    "wof:name":"Aguas Belas",
    "wof:placetype":"locality"
},
  "geometry": {"coordinates":[-38.18333,-4.05],"type":"Point"}
}