{
  "type": "Feature",
  "properties": {
    "gn:admin1_code":"18.0",
    "gn:admin2_code":"4101101.0",
    "gn:asciiname":"Sitio Sao Luis",
    "gn:country_code":"BR",
    "gn:dem":428,
    "gn:feature_class":"P",
    "gn:feature_code":"PPL",
    "gn:name":"S\u00edtio S\u00e3o Lu\u00eds",
    "gn:population":0,
    "gn:timezone":"America/Sao_Paulo",
    "iso:country":"BR",
    "name:por_x_preferred":[
        "S\u00edtio S\u00e3o Lu\u00eds"
    ],
    "wof:name":"Sitio Sao Luis",
    "wof:placetype":"locality"
},
  "geometry": {"coordinates":[-50.2481,-23.0053],"type":"Point"}
}