{
  "type": "Feature",
  "properties": {
    "gn:admin1_code":"17",
    "gn:admin2_code":"2502003.0",
    "gn:asciiname":"Japecanaa",
    "gn:country_code":"BR",
    "gn:dem":167,
    "gn:feature_class":"P",
    "gn:feature_code":"PPL",
    "gn:name":"Japecanaa",
    "gn:population":0,
    "gn:timezone":"America/Fortaleza",
    "iso:country":"BR",
    "wof:name":"Japecanaa",
    "wof:placetype":"locality"
},
  "geometry": {"coordinates":[-37.46667,-6.21667],"type":"Point"}
}