{
  "type": "Feature",
  "properties": {
    "gn:admin1_code":"16",
    "gn:admin2_code":"1501956.0",
    "gn:asciiname":"Anelio",
    "gn:country_code":"BR",
    "gn:dem":72,
    "gn:feature_class":"P",
    "gn:feature_code":"PPL",
    "gn:name":"An\u00e9lio",
    "gn:population":0,
    "gn:timezone":"America/Belem",
    "iso:country":"BR",
    "wof:name":"Anelio",
    "wof:placetype":"locality"
},
  "geometry": {"coordinates":[-46.55,-1.98333],"type":"Point"}
}