{
  "type": "Feature",
  "properties": {
    "gn:admin1_code":"16",
    "gn:admin2_code":"1505502.0",
    "gn:asciiname":"Caninde",
    "gn:country_code":"BR",
    "gn:dem":64,
    "gn:feature_class":"P",
    "gn:feature_code":"PPL",
    "gn:name":"Canind\u00e9",
    "gn:population":0,
    "gn:timezone":"America/Belem",
    "iso:country":"BR",
    "wof:name":"Caninde",
    "wof:placetype":"locality"
},
  "geometry": {"coordinates":[-46.51667,-2.56667],"type":"Point"}
}