{
  "type": "Feature",
  "properties": {
    "gn:admin1_code":"5",
    "gn:admin2_code":"2925808.0",
    "gn:asciiname":"Terra Branca",
    "gn:country_code":"BR",
    "gn:dem":310,
    "gn:feature_class":"P",
    "gn:feature_code":"PPL",
    "gn:name":"Terra Branca",
    "gn:population":0,
    "gn:timezone":"America/Bahia",
    "iso:country":"BR",
    "wof:name":"Terra Branca",
    "wof:placetype":"locality"
},
  "geometry": {"coordinates":[-39.86667,-11.08333],"type":"Point"}
}