{
  "type": "Feature",
  "properties": {
    "gn:admin1_code":"14",
    "gn:admin2_code":"5107909.0",
    "gn:asciiname":"Porto de Indios",
    "gn:country_code":"BR",
    "gn:dem":294,
    "gn:feature_class":"P",
    "gn:feature_code":"PPL",
    "gn:name":"Porto de \u00cdndios",
    "gn:population":0,
    "gn:timezone":"America/Cuiaba",
    "iso:country":"BR",
    "name:por_x_preferred":[
        "Porto de \u00cdndios"
    ],
    "name:und_x_variant":[
        "P\u00f4rto de Indio"
    ],
    "wof:name":"Porto de Indios",
    "wof:placetype":"locality"
},
  "geometry": {"coordinates":[-55.64722,-11.58433],"type":"Point"}
}