{
  "type": "Feature",
  "properties": {
    "gn:admin1_code":"13",
    "gn:admin2_code":"2108009.0",
    "gn:asciiname":"Jucara",
    "gn:cc2":"BR",
    "gn:country_code":"BR",
    "gn:dem":435,
    "gn:feature_class":"P",
    "gn:feature_code":"PPL",
    "gn:name":"Ju\u00e7ara",
    "gn:population":0,
    "gn:timezone":"America/Fortaleza",
    "iso:country":"BR",
    "name:und_x_variant":[
        "Jussara",
        "Ju\u00e7ara"
    ],
    "wof:name":"Jucara",
    "wof:placetype":"locality"
},
  "geometry": {"coordinates":[-44.28333,-6.68333],"type":"Point"}
}