{
  "type": "Feature",
  "properties": {
    "gn:admin1_code":"15",
    "gn:admin2_code":"3107109.0",
    "gn:asciiname":"Lagoa",
    "gn:country_code":"BR",
    "gn:dem":773,
    "gn:feature_class":"P",
    "gn:feature_code":"PPL",
    "gn:name":"Lagoa",
    "gn:population":0,
    "gn:timezone":"America/Sao_Paulo",
    "iso:country":"BR",
    "name:por_x_preferred":[
        "Lagoa"
    ],
    "wof:name":"Lagoa",
    "wof:placetype":"locality"
},
  "geometry": {"coordinates":[-45.88333,-21.01667],"type":"Point"}
}