{
  "type": "Feature",
  "properties": {
    "gn:admin1_code":"27.0",
    "gn:admin2_code":"3514809.0",
    "gn:asciiname":"Sitio Santo Antonio da Posse",
    "gn:country_code":"BR",
    "gn:dem":68,
    "gn:feature_class":"P",
    "gn:feature_code":"PPL",
    "gn:name":"S\u00edtio Santo Ant\u00f4nio da Posse",
    "gn:population":0,
    "gn:timezone":"America/Sao_Paulo",
    "iso:country":"BR",
    "name:por_x_preferred":[
        "S\u00edtio Santo Ant\u00f4nio da Posse"
    ],
    "wof:name":"Sitio Santo Antonio da Posse",
    "wof:placetype":"locality"
},
  "geometry": {"coordinates":[-48.13276,-24.61362],"type":"Point"}
}