{
  "type": "Feature",
  "properties": {
    "gn:admin1_code":"15",
    "gn:admin2_code":"3148004.0",
    "gn:asciiname":"Capelinha do Chumbo",
    "gn:country_code":"BR",
    "gn:dem":803,
    "gn:feature_class":"P",
    "gn:feature_code":"PPL",
    "gn:name":"Capelinha do Chumbo",
    "gn:population":0,
    "gn:timezone":"America/Sao_Paulo",
    "iso:country":"BR",
    "name:por_x_preferred":[
        "Capelinha do Chumbo"
    ],
    "wof:name":"Capelinha do Chumbo",
    "wof:placetype":"locality"
},
  "geometry": {"coordinates":[-46.06667,-18.68333],"type":"Point"}
}