{
  "type": "Feature",
  "properties": {
    "gn:admin1_code":"16",
    "gn:admin2_code":"1507474.0",
    "gn:asciiname":"Porto da Praia",
    "gn:country_code":"BR",
    "gn:dem":1,
    "gn:feature_class":"P",
    "gn:feature_code":"PPL",
    "gn:name":"P\u00f4rto da Praia",
    "gn:population":0,
    "gn:timezone":"America/Belem",
    "iso:country":"BR",
    "name:und_x_variant":[
        "P\u00f4rto da Praia",
        "P\u00f4rtoda Praia"
    ],
    "wof:name":"Porto da Praia",
    "wof:placetype":"locality"
},
  "geometry": {"coordinates":[-47.20334,-0.66902],"type":"Point"}
}