{
  "type": "Feature",
  "properties": {
    "gn:admin1_code":"06",
    "gn:admin2_code":"2313302.0",
    "gn:asciiname":"Olho d'Agua (1)",
    "gn:country_code":"BR",
    "gn:dem":451,
    "gn:feature_class":"P",
    "gn:feature_code":"PPL",
    "gn:name":"\u00d4lho d\u2019\u00c1gua (1)",
    "gn:population":0,
    "gn:timezone":"America/Fortaleza",
    "iso:country":"BR",
    "wof:name":"Olho d'Agua (1)",
    "wof:placetype":"locality"
},
  "geometry": {"coordinates":[-40.33333,-6.06667],"type":"Point"}
}