{
  "type": "Feature",
  "properties": {
    "gn:admin1_code":"06",
    "gn:admin2_code":"2302701.0",
    "gn:asciiname":"Floresta",
    "gn:country_code":"BR",
    "gn:dem":591,
    "gn:feature_class":"P",
    "gn:feature_code":"PPL",
    "gn:name":"Floresta",
    "gn:population":0,
    "gn:timezone":"America/Fortaleza",
    "iso:country":"BR",
    "wof:name":"Floresta",
    "wof:placetype":"locality"
},
  "geometry": {"coordinates":[-40.36667,-7.11667],"type":"Point"}
}