{
  "type": "Feature",
  "properties": {
    "gn:admin1_code":"30",
    "gn:admin2_code":"2601607.0",
    "gn:asciiname":"Barra do Tarrachil",
    "gn:cc2":"BR",
    "gn:country_code":"BR",
    "gn:dem":305,
    "gn:feature_class":"P",
    "gn:feature_code":"PPL",
    "gn:name":"Barra do Tarrachil",
    "gn:population":0,
    "gn:timezone":"America/Bahia",
    "iso:country":"BR",
    "name:und_x_variant":[
        "Rosario",
        "Barra do Tarrachil"
    ],
    "wof:name":"Barra do Tarrachil",
    "wof:placetype":"locality"
},
  "geometry": {"coordinates":[-38.96667,-8.78333],"type":"Point"}
}