{
  "type": "Feature",
  "properties": {
    "gn:admin1_code":"16.0",
    "gn:admin2_code":"1501451.0",
    "gn:asciiname":"Porto Novo",
    "gn:country_code":"BR",
    "gn:dem":28,
    "gn:feature_class":"P",
    "gn:feature_code":"PPL",
    "gn:name":"Porto Novo",
    "gn:population":0,
    "gn:timezone":"America/Santarem",
    "iso:country":"BR",
    "name:por_x_preferred":[
        "Porto Novo"
    ],
    "wof:name":"Porto Novo",
    "wof:placetype":"locality"
},
  "geometry": {"coordinates":[-54.97807,-2.62261],"type":"Point"}
}