{
  "type": "Feature",
  "properties": {
    "gn:admin1_code":"31.0",
    "gn:admin2_code":"1702406.0",
    "gn:asciiname":"Santa Helena",
    "gn:country_code":"BR",
    "gn:dem":515,
    "gn:feature_class":"P",
    "gn:feature_code":"PPL",
    "gn:name":"Santa Helena",
    "gn:population":0,
    "gn:timezone":"America/Araguaina",
    "iso:country":"BR",
    "name:cat_x_preferred":[
        "Santa Helena"
    ],
    "name:ceb_x_preferred":[
        "Santa Helena"
    ],
    "name:deu_x_preferred":[
        "Santa Helena"
    ],
    "name:fra_x_preferred":[
        "Santa Helena"
    ],
    "name:glg_x_preferred":[
        "Santa Helena"
    ],
    "name:ita_x_preferred":[
        "Santa Helena"
    ],
    "name:nld_x_preferred":[
        "Santa Helena"
    ],
    "name:nor_x_preferred":[
        "Santa Helena"
    ],
    "name:por_x_preferred":[
        "Santa Helena"
    ],
    "name:spa_x_preferred":[
        "Santa Helena"
    ],
    "name:swe_x_preferred":[
        "Santa Helena"
    ],
    "name:vol_x_preferred":[
        "Santa Helena"
    ],
    "wof:name":"Santa Helena",
    "wof:placetype":"locality"
},
  "geometry": {"coordinates":[-46.65861,-12.79889],"type":"Point"}
}