{
  "type": "Feature",
  "properties": {
    "gn:admin1_code":"11",
    "gn:admin2_code":"5001102.0",
    "gn:asciiname":"Sao Francisco",
    "gn:country_code":"BR",
    "gn:dem":116,
    "gn:feature_class":"P",
    "gn:feature_code":"PPL",
    "gn:name":"S\u00e3o Francisco",
    "gn:population":0,
    "gn:timezone":"America/Campo_Grande",
    "iso:country":"BR",
    "wof:name":"Sao Francisco",
    "wof:placetype":"locality"
},
  "geometry": {"coordinates":[-56.11666999999999,-19.85],"type":"Point"}
}