{
  "type": "Feature",
  "properties": {
    "gn:admin1_code":"27",
    "gn:admin2_code":"3524600.0",
    "gn:asciiname":"Itapuvucu",
    "gn:country_code":"BR",
    "gn:dem":37,
    "gn:feature_class":"P",
    "gn:feature_code":"PPLL",
    "gn:name":"Itapuvu\u00e7u",
    "gn:population":0,
    "gn:timezone":"America/Sao_Paulo",
    "iso:country":"BR",
    "name:por_x_preferred":[
        "Itapuvu\u00e7u"
    ],
    "wof:name":"Itapuvucu",
    "wof:placetype":"locality"
},
  "geometry": {"coordinates":[-48.04082,-24.70088],"type":"Point"}
}