{
  "type": "Feature",
  "properties": {
    "gn:admin1_code":"18.0",
    "gn:admin2_code":"4126603.0",
    "gn:asciiname":"Sitio Maria de Jesus",
    "gn:country_code":"BR",
    "gn:dem":631,
    "gn:feature_class":"P",
    "gn:feature_code":"PPL",
    "gn:name":"S\u00edtio Maria de Jesus",
    "gn:population":0,
    "gn:timezone":"America/Sao_Paulo",
    "iso:country":"BR",
    "name:por_x_preferred":[
        "S\u00edtio Maria de Jesus"
    ],
    "wof:name":"Sitio Maria de Jesus",
    "wof:placetype":"locality"
},
  "geometry": {"coordinates":[-49.7776,-23.6956],"type":"Point"}
}