{
  "type": "Feature",
  "properties": {
    "gn:admin1_code":"5",
    "gn:admin2_code":"2910305.0",
    "gn:asciiname":"Cercado",
    "gn:country_code":"BR",
    "gn:dem":381,
    "gn:feature_class":"P",
    "gn:feature_code":"PPL",
    "gn:name":"Cercado",
    "gn:population":0,
    "gn:timezone":"America/Bahia",
    "iso:country":"BR",
    "name:ceb_x_preferred":[
        "Cercado"
    ],
    "name:deu_x_preferred":[
        "Cercado"
    ],
    "name:ita_x_preferred":[
        "Cercado"
    ],
    "name:nld_x_preferred":[
        "Cercado"
    ],
    "name:por_x_preferred":[
        "Cercado"
    ],
    "name:que_x_preferred":[
        "Cercado"
    ],
    "name:rus_x_preferred":[
        "\u0421\u0435\u0440\u043a\u0430\u0434\u043e"
    ],
    "name:sco_x_preferred":[
        "Cercado"
    ],
    "name:spa_x_preferred":[
        "Cercado"
    ],
    "name:swe_x_preferred":[
        "Cercado"
    ],
    "wof:name":"Cercado",
    "wof:placetype":"locality"
},
  "geometry": {"coordinates":[-39.53333,-12.88333],"type":"Point"}
}