{
  "type": "Feature",
  "properties": {
    "gn:admin1_code":"23",
    "gn:admin2_code":"4306908.0",
    "gn:asciiname":"Minas",
    "gn:country_code":"BR",
    "gn:dem":375,
    "gn:feature_class":"P",
    "gn:feature_code":"PPL",
    "gn:name":"Minas",
    "gn:population":0,
    "gn:timezone":"America/Sao_Paulo",
    "iso:country":"BR",
    "wof:name":"Minas",
    "wof:placetype":"locality"
},
  "geometry": {"coordinates":[-52.85,-30.66667],"type":"Point"}
}