{
  "type": "Feature",
  "properties": {
    "gn:admin1_code":"15",
    "gn:admin2_code":"3111606.0",
    "gn:asciiname":"Tanque",
    "gn:country_code":"BR",
    "gn:dem":815,
    "gn:feature_class":"P",
    "gn:feature_code":"PPL",
    "gn:name":"Tanque",
    "gn:population":0,
    "gn:timezone":"America/Sao_Paulo",
    "iso:country":"BR",
    "name:ita_x_preferred":[
        "Tanque"
    ],
    "name:por_x_preferred":[
        "Tanque"
    ],
    "wof:name":"Tanque",
    "wof:placetype":"locality"
},
  "geometry": {"coordinates":[-45.85,-21.25],"type":"Point"}
}