{
  "type": "Feature",
  "properties": {
    "gn:admin1_code":"26",
    "gn:admin2_code":"4211801.0",
    "gn:asciiname":"Cadori",
    "gn:country_code":"BR",
    "gn:dem":744,
    "gn:feature_class":"P",
    "gn:feature_code":"PPL",
    "gn:name":"Cadori",
    "gn:population":0,
    "gn:timezone":"America/Sao_Paulo",
    "iso:country":"BR",
    "wof:name":"Cadori",
    "wof:placetype":"locality"
},
  "geometry": {"coordinates":[-51.73333,-27.25],"type":"Point"}
}