{
  "type": "Feature",
  "properties": {
    "gn:admin1_code":"5.0",
    "gn:admin2_code":"2919306.0",
    "gn:asciiname":"Estiva",
    "gn:country_code":"BR",
    "gn:dem":933,
    "gn:feature_class":"P",
    "gn:feature_code":"PPL",
    "gn:name":"Estiva",
    "gn:population":0,
    "gn:timezone":"America/Bahia",
    "iso:country":"BR",
    "name:por_x_preferred":[
        "Estiva"
    ],
    "wof:name":"Estiva",
    "wof:placetype":"locality"
},
  "geometry": {"coordinates":[-41.41768,-12.28823],"type":"Point"}
}