{
  "type": "Feature",
  "properties": {
    "gn:admin1_code":"5.0",
    "gn:admin2_code":"2919306.0",
    "gn:asciiname":"Estiva",
    "gn:country_code":"BR",
    "gn:dem":933,
    "gn:feature_class":"P",
    "gn:feature_code":"PPL",
    "gn:name":"Estiva",
    "gn:population":0,
    "gn:timezone":"America/Bahia",
    "iso:country":"BR",
    "name:bpy_x_preferred":[
        "\u098f\u09b8\u099f\u09bf\u09ad\u09be"
    ],
    "name:ceb_x_preferred":[
        "Estiva"
    ],
    "name:epo_x_preferred":[
        "Estiva"
    ],
    "name:eus_x_preferred":[
        "Estiva"
    ],
    "name:fra_x_preferred":[
        "Estiva"
    ],
    "name:ita_x_preferred":[
        "Estiva"
    ],
    "name:kat_x_preferred":[
        "\u10d4\u10e1\u10e2\u10d8\u10d5\u10d0"
    ],
    "name:kaz_x_preferred":[
        "\u042d\u0441\u0442\u0438\u0432\u0430"
    ],
    "name:mlg_x_preferred":[
        "Estiva"
    ],
    "name:nld_x_preferred":[
        "Estiva"
    ],
    "name:nor_x_preferred":[
        "Estiva"
    ],
    "name:pol_x_preferred":[
        "Estiva"
    ],
    "name:por_x_preferred":[
        "Estiva"
    ],
    "name:ron_x_preferred":[
        "Estiva"
    ],
    "name:rus_x_preferred":[
        "\u042d\u0441\u0442\u0438\u0432\u0430"
    ],
    "name:swe_x_preferred":[
        "Estiva"
    ],
    "name:vie_x_preferred":[
        "Estiva"
    ],
    "name:vol_x_preferred":[
        "Estiva"
    ],
    "name:war_x_preferred":[
        "Estiva"
    ],
    "name:zho_x_preferred":[
        "\u57c3\u65af\u8482\u74e6"
    ],
    "wof:name":"Estiva",
    "wof:placetype":"locality"
},
  "geometry": {"coordinates":[-41.41768,-12.28823],"type":"Point"}
}