{
  "type": "Feature",
  "properties": {
    "gn:admin1_code":"06",
    "gn:admin2_code":"2309508.0",
    "gn:asciiname":"Vila Nova Conceicao",
    "gn:country_code":"BR",
    "gn:dem":200,
    "gn:feature_class":"P",
    "gn:feature_code":"PPL",
    "gn:name":"Vila Nova Concei\u00e7\u00e3o",
    "gn:population":0,
    "gn:timezone":"America/Fortaleza",
    "iso:country":"BR",
    "wof:name":"Vila Nova Conceicao",
    "wof:placetype":"locality"
},
  "geometry": {"coordinates":[-38.96667,-6.33333],"type":"Point"}
}