{
  "type": "Feature",
  "properties": {
    "gn:admin1_code":"18.0",
    "gn:admin2_code":"4126678.0",
    "gn:asciiname":"Sitio Pedralina Souza Miranda",
    "gn:country_code":"BR",
    "gn:dem":714,
    "gn:feature_class":"P",
    "gn:feature_code":"PPL",
    "gn:name":"S\u00edtio Pedralina Souza Miranda",
    "gn:population":0,
    "gn:timezone":"America/Sao_Paulo",
    "iso:country":"BR",
    "name:por_x_preferred":[
        "S\u00edtio Pedralina Souza Miranda"
    ],
    "wof:name":"Sitio Pedralina Souza Miranda",
    "wof:placetype":"locality"
},
  "geometry": {"coordinates":[-50.9996,-23.8836],"type":"Point"}
}