{
  "type": "Feature",
  "properties": {
    "gn:admin1_code":"15",
    "gn:admin2_code":"3113602.0",
    "gn:asciiname":"Bom Retiro",
    "gn:country_code":"BR",
    "gn:dem":945,
    "gn:feature_class":"P",
    "gn:feature_code":"PPL",
    "gn:name":"Bom Retiro",
    "gn:population":0,
    "gn:timezone":"America/Sao_Paulo",
    "iso:country":"BR",
    "name:ceb_x_preferred":[
        "Bom Retiro"
    ],
    "name:deu_x_preferred":[
        "Bom Retiro"
    ],
    "name:por_x_preferred":[
        "Bom Retiro"
    ],
    "name:swe_x_preferred":[
        "Bom Retiro"
    ],
    "wof:name":"Bom Retiro",
    "wof:placetype":"locality"
},
  "geometry": {"coordinates":[-45.66667,-22.16667],"type":"Point"}
}