{
  "type": "Feature",
  "properties": {
    "gn:admin1_code":"27",
    "gn:admin2_code":"3534807.0",
    "gn:asciiname":"Arabela",
    "gn:country_code":"BR",
    "gn:dem":308,
    "gn:feature_class":"P",
    "gn:feature_code":"PPLL",
    "gn:name":"Arabela",
    "gn:population":0,
    "gn:timezone":"America/Sao_Paulo",
    "iso:country":"BR",
    "name:ces_x_preferred":[
        "Arabela"
    ],
    "name:pol_x_preferred":[
        "Arabela"
    ],
    "name:slk_x_preferred":[
        "Arabela"
    ],
    "wof:name":"Arabela",
    "wof:placetype":"locality"
},
  "geometry": {"coordinates":[-51.73,-21.40611],"type":"Point"}
}