{
  "type": "Feature",
  "properties": {
    "gn:admin1_code":"18.0",
    "gn:admin2_code":"4112801.0",
    "gn:asciiname":"Sitio Euripedes Galdencio",
    "gn:country_code":"BR",
    "gn:dem":500,
    "gn:feature_class":"P",
    "gn:feature_code":"PPL",
    "gn:name":"S\u00edtio Eur\u00edpedes Gald\u00eancio",
    "gn:population":0,
    "gn:timezone":"America/Sao_Paulo",
    "iso:country":"BR",
    "name:por_x_preferred":[
        "S\u00edtio Eur\u00edpedes Gald\u00eancio"
    ],
    "wof:name":"Sitio Euripedes Galdencio",
    "wof:placetype":"locality"
},
  "geometry": {"coordinates":[-49.9227,-23.3487],"type":"Point"}
}