{
  "type": "Feature",
  "properties": {
    "gn:admin1_code":"18.0",
    "gn:admin2_code":"4112306.0",
    "gn:asciiname":"Sitio Olho-de Agua",
    "gn:country_code":"BR",
    "gn:dem":708,
    "gn:feature_class":"P",
    "gn:feature_code":"PPL",
    "gn:name":"S\u00edtio Olho-de \u00c1gua",
    "gn:population":0,
    "gn:timezone":"America/Sao_Paulo",
    "iso:country":"BR",
    "name:por_x_preferred":[
        "S\u00edtio Olho-de \u00c1gua"
    ],
    "wof:name":"Sitio Olho-de Agua",
    "wof:placetype":"locality"
},
  "geometry": {"coordinates":[-50.16925,-23.81698],"type":"Point"}
}