{
  "type": "Feature",
  "properties": {
    "gn:admin1_code":"8",
    "gn:admin2_code":"3202405.0",
    "gn:asciiname":"Palmeiras",
    "gn:country_code":"BR",
    "gn:dem":21,
    "gn:feature_class":"P",
    "gn:feature_code":"PPL",
    "gn:name":"Palmeiras",
    "gn:population":0,
    "gn:timezone":"America/Sao_Paulo",
    "iso:country":"BR",
    "name:por_x_preferred":[
        "Palmeiras"
    ],
    "wof:name":"Palmeiras",
    "wof:placetype":"locality"
},
  "geometry": {"coordinates":[-40.43333,-20.53333],"type":"Point"}
}