{
  "type": "Feature",
  "properties": {
    "gn:admin1_code":"29",
    "gn:admin2_code":"5206404.0",
    "gn:asciiname":"Verde",
    "gn:country_code":"BR",
    "gn:dem":466,
    "gn:feature_class":"P",
    "gn:feature_code":"PPL",
    "gn:name":"Verde",
    "gn:population":0,
    "gn:timezone":"America/Sao_Paulo",
    "iso:country":"BR",
    "name:por_x_preferred":[
        "Verde"
    ],
    "wof:name":"Verde",
    "wof:placetype":"locality"
},
  "geometry": {"coordinates":[-50.01667,-14.78333],"type":"Point"}
}