{
  "type": "Feature",
  "properties": {
    "gn:admin1_code":"29",
    "gn:admin2_code":"5206404.0",
    "gn:asciiname":"Verde",
    "gn:country_code":"BR",
    "gn:dem":466,
    "gn:feature_class":"P",
    "gn:feature_code":"PPL",
    "gn:name":"Verde",
    "gn:population":0,
    "gn:timezone":"America/Sao_Paulo",
    "iso:country":"BR",
    "name:bre_x_preferred":[
        "Verde"
    ],
    "name:ceb_x_preferred":[
        "Verde"
    ],
    "name:deu_x_preferred":[
        "Verde"
    ],
    "name:ita_x_preferred":[
        "Verde"
    ],
    "name:kor_x_preferred":[
        "\ubca0\ub974\ub370"
    ],
    "name:por_x_preferred":[
        "Verde"
    ],
    "name:rus_x_preferred":[
        "\u0440\u0435\u043a\u0430 \u0420\u0438\u043e-\u0412\u0435\u0440\u0434\u0435"
    ],
    "name:rus_x_variant":[
        "\u0412\u0435\u0440\u0434\u0435"
    ],
    "name:spa_x_preferred":[
        "Verde"
    ],
    "name:swe_x_preferred":[
        "Rio Verde"
    ],
    "name:swe_x_variant":[
        "Verde"
    ],
    "name:tur_x_preferred":[
        "Verde"
    ],
    "name:ukr_x_preferred":[
        "\u0412\u0435\u0440\u0434\u0435"
    ],
    "name:urd_x_preferred":[
        "\u0648\u0631\u062f\u06d2"
    ],
    "name:vie_x_preferred":[
        "S\u00f4ng Verde"
    ],
    "name:zho_cn_x_preferred":[
        "\u4f5b\u5f97\u89d2\u6cb3"
    ],
    "name:zho_tw_x_preferred":[
        "\u7dad\u5fb7\u6cb3"
    ],
    "wof:name":"Verde",
    "wof:placetype":"locality"
},
  "geometry": {"coordinates":[-50.01667,-14.78333],"type":"Point"}
}