{
  "type": "Feature",
  "properties": {
    "gn:admin1_code":"18.0",
    "gn:admin2_code":"4122305.0",
    "gn:asciiname":"Sitio Tito Zielinscki",
    "gn:country_code":"BR",
    "gn:dem":910,
    "gn:feature_class":"P",
    "gn:feature_code":"PPL",
    "gn:name":"S\u00edtio Tito Zielinscki",
    "gn:population":0,
    "gn:timezone":"America/Sao_Paulo",
    "iso:country":"BR",
    "name:por_x_preferred":[
        "S\u00edtio Tito Zielinscki"
    ],
    "wof:name":"Sitio Tito Zielinscki",
    "wof:placetype":"locality"
},
  "geometry": {"coordinates":[-49.8057,-26.0058],"type":"Point"}
}