{
  "type": "Feature",
  "properties": {
    "gn:admin1_code":"22",
    "gn:admin2_code":"2411403.0",
    "gn:asciiname":"Riacho Fundo",
    "gn:country_code":"BR",
    "gn:dem":85,
    "gn:feature_class":"P",
    "gn:feature_code":"PPL",
    "gn:name":"Riacho Fundo",
    "gn:population":0,
    "gn:timezone":"America/Fortaleza",
    "iso:country":"BR",
    "name:deu_x_preferred":[
        "Riacho Fundo"
    ],
    "name:fra_x_preferred":[
        "Riacho Fundo"
    ],
    "name:ita_x_preferred":[
        "Riacho Fundo"
    ],
    "name:por_x_preferred":[
        "Riacho Fundo"
    ],
    "wof:name":"Riacho Fundo",
    "wof:placetype":"locality"
},
  "geometry": {"coordinates":[-36.70278,-5.89528],"type":"Point"}
}