{
  "type": "Feature",
  "properties": {
    "gn:admin1_code":"18.0",
    "gn:admin2_code":"4114302.0",
    "gn:asciiname":"Sitio Setimo Ceu",
    "gn:country_code":"BR",
    "gn:dem":960,
    "gn:feature_class":"P",
    "gn:feature_code":"PPL",
    "gn:name":"S\u00edtio S\u00e9timo C\u00e9u",
    "gn:population":0,
    "gn:timezone":"America/Sao_Paulo",
    "iso:country":"BR",
    "name:por_x_preferred":[
        "S\u00edtio S\u00e9timo C\u00e9u"
    ],
    "wof:name":"Sitio Setimo Ceu",
    "wof:placetype":"locality"
},
  "geometry": {"coordinates":[-49.2983,-25.7942],"type":"Point"}
}