{
  "type": "Feature",
  "properties": {
    "gn:admin1_code":"18.0",
    "gn:admin2_code":"4117701.0",
    "gn:asciiname":"Sitio Agua Clara",
    "gn:country_code":"BR",
    "gn:dem":812,
    "gn:feature_class":"P",
    "gn:feature_code":"PPL",
    "gn:name":"S\u00edtio \u00c1gua Clara",
    "gn:population":0,
    "gn:timezone":"America/Sao_Paulo",
    "iso:country":"BR",
    "name:por_x_preferred":[
        "S\u00edtio \u00c1gua Clara"
    ],
    "wof:name":"Sitio Agua Clara",
    "wof:placetype":"locality"
},
  "geometry": {"coordinates":[-50.09998,-25.57725],"type":"Point"}
}