{
  "type": "Feature",
  "properties": {
    "gn:admin1_code":"15.0",
    "gn:admin2_code":"3114550.0",
    "gn:asciiname":"Gracilandia",
    "gn:country_code":"BR",
    "gn:dem":419,
    "gn:feature_class":"P",
    "gn:feature_code":"PPL",
    "gn:name":"Gracil\u00e2ndia",
    "gn:population":0,
    "gn:timezone":"America/Sao_Paulo",
    "iso:country":"BR",
    "name:por_x_preferred":[
        "Gracil\u00e2ndia"
    ],
    "wof:name":"Gracilandia",
    "wof:placetype":"locality"
},
  "geometry": {"coordinates":[-50.89034,-19.6816],"type":"Point"}
}