{
  "type": "Feature",
  "properties": {
    "gn:admin1_code":"13",
    "gn:admin2_code":"2102200.0",
    "gn:asciiname":"Portela",
    "gn:country_code":"BR",
    "gn:dem":78,
    "gn:feature_class":"P",
    "gn:feature_code":"PPL",
    "gn:name":"Portela",
    "gn:population":0,
    "gn:timezone":"America/Fortaleza",
    "iso:country":"BR",
    "name:ceb_x_preferred":[
        "Portela"
    ],
    "name:deu_x_preferred":[
        "Portela"
    ],
    "name:fra_x_preferred":[
        "Portela"
    ],
    "name:glg_x_preferred":[
        "Portela"
    ],
    "name:kaz_x_preferred":[
        "\u041f\u043e\u0440\u0442\u0435\u043b\u0430"
    ],
    "name:nld_x_preferred":[
        "Portela"
    ],
    "name:por_x_preferred":[
        "Portela"
    ],
    "name:rus_x_preferred":[
        "\u041f\u043e\u0440\u0442\u0435\u043b\u0430"
    ],
    "name:spa_x_preferred":[
        "Portela"
    ],
    "name:srp_x_preferred":[
        "Portela"
    ],
    "name:ukr_x_preferred":[
        "\u041f\u043e\u0440\u0442\u0435\u043b\u0430"
    ],
    "wof:name":"Portela",
    "wof:placetype":"locality"
},
  "geometry": {"coordinates":[-42.88889,-3.97667],"type":"Point"}
}