{
  "type": "Feature",
  "properties": {
    "gn:admin1_code":"20",
    "gn:admin2_code":"2209302.0",
    "gn:asciiname":"Brejo dos Altos",
    "gn:country_code":"BR",
    "gn:dem":265,
    "gn:feature_class":"P",
    "gn:feature_code":"PPL",
    "gn:name":"Brejo dos Altos",
    "gn:population":0,
    "gn:timezone":"America/Fortaleza",
    "iso:country":"BR",
    "wof:name":"Brejo dos Altos",
    "wof:placetype":"locality"
},
  "geometry": {"coordinates":[-44.28333,-8.93333],"type":"Point"}
}