{
  "type": "Feature",
  "properties": {
    "gn:admin1_code":"20",
    "gn:admin2_code":"2202729.0",
    "gn:asciiname":"Pau-d'Alho",
    "gn:country_code":"BR",
    "gn:dem":214,
    "gn:feature_class":"P",
    "gn:feature_code":"PPL",
    "gn:name":"Pau-d\u2019Alho",
    "gn:population":0,
    "gn:timezone":"America/Fortaleza",
    "iso:country":"BR",
    "wof:name":"Pau-d'Alho",
    "wof:placetype":"locality"
},
  "geometry": {"coordinates":[-41.35,-3.66667],"type":"Point"}
}