{
  "type": "Feature",
  "properties": {
    "gn:admin1_code":"18",
    "gn:admin2_code":"4110706.0",
    "gn:asciiname":"Florestal",
    "gn:country_code":"BR",
    "gn:dem":880,
    "gn:feature_class":"P",
    "gn:feature_code":"PPL",
    "gn:name":"Florestal",
    "gn:population":0,
    "gn:timezone":"America/Sao_Paulo",
    "iso:country":"BR",
    "wof:name":"Florestal",
    "wof:placetype":"locality"
},
  "geometry": {"coordinates":[-50.58333,-25.45],"type":"Point"}
}