{
  "type": "Feature",
  "properties": {
    "gn:admin1_code":"20",
    "gn:admin2_code":"2203255.0",
    "gn:asciiname":"Touro de Cimento",
    "gn:country_code":"BR",
    "gn:dem":186,
    "gn:feature_class":"P",
    "gn:feature_code":"PPL",
    "gn:name":"Touro de Cimento",
    "gn:population":0,
    "gn:timezone":"America/Fortaleza",
    "iso:country":"BR",
    "wof:name":"Touro de Cimento",
    "wof:placetype":"locality"
},
  "geometry": {"coordinates":[-42.86667,-5.61667],"type":"Point"}
}