{
  "type": "Feature",
  "properties": {
    "gn:admin1_code":"5",
    "gn:admin2_code":"2920502.0",
    "gn:asciiname":"Pe do Morro",
    "gn:country_code":"BR",
    "gn:dem":643,
    "gn:feature_class":"P",
    "gn:feature_code":"PPL",
    "gn:name":"P\u00e9 do Morro",
    "gn:population":0,
    "gn:timezone":"America/Bahia",
    "iso:country":"BR",
    "wof:name":"Pe do Morro",
    "wof:placetype":"locality"
},
  "geometry": {"coordinates":[-40.63333,-13.66667],"type":"Point"}
}