{
  "type": "Feature",
  "properties": {
    "gn:admin1_code":"06",
    "gn:admin2_code":"2302404.0",
    "gn:asciiname":"Lagoa dos Filos",
    "gn:country_code":"BR",
    "gn:dem":461,
    "gn:feature_class":"P",
    "gn:feature_code":"PPL",
    "gn:name":"Lagoa dos Filos",
    "gn:population":0,
    "gn:timezone":"America/Fortaleza",
    "iso:country":"BR",
    "name:por_x_preferred":[
        "Lagoa dos Fil\u00f3s"
    ],
    "wof:name":"Lagoa dos Filos",
    "wof:placetype":"locality"
},
  "geometry": {"coordinates":[-39.86481,-4.7814],"type":"Point"}
}