{
  "type": "Feature",
  "properties": {
    "gn:admin1_code":"20",
    "gn:admin2_code":"2204303.0",
    "gn:asciiname":"Barra (6)",
    "gn:country_code":"BR",
    "gn:dem":457,
    "gn:feature_class":"P",
    "gn:feature_code":"PPL",
    "gn:name":"Barra (6)",
    "gn:population":0,
    "gn:timezone":"America/Fortaleza",
    "iso:country":"BR",
    "wof:name":"Barra (6)",
    "wof:placetype":"locality"
},
  "geometry": {"coordinates":[-40.55,-7.05],"type":"Point"}
}