{
  "type": "Feature",
  "properties": {
    "gn:admin1_code":"18.0",
    "gn:admin2_code":"4121802.0",
    "gn:asciiname":"Sitio Atillo Godoy",
    "gn:country_code":"BR",
    "gn:dem":614,
    "gn:feature_class":"P",
    "gn:feature_code":"PPL",
    "gn:name":"S\u00edtio At\u00edllo Godoy",
    "gn:population":0,
    "gn:timezone":"America/Sao_Paulo",
    "iso:country":"BR",
    "name:por_x_preferred":[
        "S\u00edtio At\u00edllo Godoy"
    ],
    "wof:name":"Sitio Atillo Godoy",
    "wof:placetype":"locality"
},
  "geometry": {"coordinates":[-49.84116,-23.42326],"type":"Point"}
}