{
  "type": "Feature",
  "properties": {
    "gn:admin1_code":"18",
    "gn:admin2_code":"4125506.0",
    "gn:asciiname":"Sitio Ivone B. Nery",
    "gn:country_code":"BR",
    "gn:dem":929,
    "gn:feature_class":"P",
    "gn:feature_code":"PPL",
    "gn:name":"S\u00edtio Ivone B. Nery",
    "gn:population":0,
    "gn:timezone":"America/Sao_Paulo",
    "iso:country":"BR",
    "name:por_x_preferred":[
        "S\u00edtio Ivone B. Nery"
    ],
    "wof:name":"Sitio Ivone B. Nery",
    "wof:placetype":"locality"
},
  "geometry": {"coordinates":[-49.2065,-25.7741],"type":"Point"}
}