{
  "type": "Feature",
  "properties": {
    "gn:admin1_code":"06",
    "gn:admin2_code":"2303303.0",
    "gn:asciiname":"Sitio Segredo",
    "gn:country_code":"BR",
    "gn:dem":313,
    "gn:feature_class":"P",
    "gn:feature_code":"PPL",
    "gn:name":"S\u00edtio Segredo",
    "gn:population":0,
    "gn:timezone":"America/Fortaleza",
    "iso:country":"BR",
    "wof:name":"Sitio Segredo",
    "wof:placetype":"locality"
},
  "geometry": {"coordinates":[-39.41667,-6.73333],"type":"Point"}
}