{
  "type": "Feature",
  "properties": {
    "gn:admin1_code":"4",
    "gn:admin2_code":"1302207.0",
    "gn:asciiname":"Breuzinho",
    "gn:country_code":"BR",
    "gn:dem":76,
    "gn:feature_class":"P",
    "gn:feature_code":"PPL",
    "gn:name":"Breuzinho",
    "gn:population":0,
    "gn:timezone":"America/Manaus",
    "iso:country":"BR",
    "name:und_x_variant":[
        "Breozinho",
        "Breuzinho"
    ],
    "wof:name":"Breuzinho",
    "wof:placetype":"locality"
},
  "geometry": {"coordinates":[-66.32576999999999,-3.53915],"type":"Point"}
}