{
  "type": "Feature",
  "properties": {
    "gn:admin1_code":"13",
    "gn:admin2_code":"2106607.0",
    "gn:asciiname":"Bom Jesus",
    "gn:country_code":"BR",
    "gn:dem":117,
    "gn:feature_class":"P",
    "gn:feature_code":"PPL",
    "gn:name":"Bom Jesus",
    "gn:population":0,
    "gn:timezone":"America/Fortaleza",
    "iso:country":"BR",
    "wof:name":"Bom Jesus",
    "wof:placetype":"locality"
},
  "geometry": {"coordinates":[-43.28333,-5.23333],"type":"Point"}
}