{
  "type": "Feature",
  "properties": {
    "gn:admin1_code":"06",
    "gn:admin2_code":"2310704.0",
    "gn:asciiname":"Fazenda Fofa",
    "gn:country_code":"BR",
    "gn:dem":66,
    "gn:feature_class":"P",
    "gn:feature_code":"PPL",
    "gn:name":"Fazenda Fofa",
    "gn:population":0,
    "gn:timezone":"America/Fortaleza",
    "iso:country":"BR",
    "wof:name":"Fazenda Fofa",
    "wof:placetype":"locality"
},
  "geometry": {"coordinates":[-39.26667,-3.85],"type":"Point"}
}