{
  "type": "Feature",
  "properties": {
    "gn:admin1_code":"18.0",
    "gn:admin2_code":"4106209.0",
    "gn:asciiname":"Sitio Esuardo Sueng",
    "gn:country_code":"BR",
    "gn:dem":911,
    "gn:feature_class":"P",
    "gn:feature_code":"PPL",
    "gn:name":"S\u00edtio Esuardo Sueng",
    "gn:population":0,
    "gn:timezone":"America/Sao_Paulo",
    "iso:country":"BR",
    "name:por_x_preferred":[
        "S\u00edtio Esuardo Sueng"
    ],
    "wof:name":"Sitio Esuardo Sueng",
    "wof:placetype":"locality"
},
  "geometry": {"coordinates":[-49.5117,-25.7844],"type":"Point"}
}