{
  "type": "Feature",
  "properties": {
    "gn:gn_country":"BR",
    "gn:gn_fcode":"PPLL",
    "gn:gn_pop":3700,
    "gn:population":3700,
    "iso:country":"BR",
    "qs_pg:aaroncc":"BR",
    "qs_pg:gn_country":"BR",
    "qs_pg:gn_fcode":"PPLL",
    "qs_pg:gn_pop":3700,
    "qs_pg:name":"Carianos",
    "qs_pg:name_adm0":"Brasil",
    "qs_pg:name_adm1":"Santa Catarina",
    "qs_pg:photos":1,
    "qs_pg:photos_1k":1,
    "qs_pg:photos_9k":1,
    "qs_pg:photos_9r":1,
    "qs_pg:photos_all":1,
    "qs_pg:photos_sr":1,
    "qs_pg:pop_sr":4,
    "qs_pg:qs_pg_placetype":"neighbourhood",
    "qs_pg:qs_pg_placetype_gp":"Suburb",
    "qs_pg:woe_adm0":23424768,
    "woe:adm0_id":23424768,
    "woe:name_adm0":"Brasil",
    "woe:name_adm1":"Santa Catarina",
    "woe:placetype":"Suburb",
    "wof:name":"Carianos",
    "wof:placetype":"neighbourhood",
    "wof:population":3700
},
  "geometry": {"coordinates":[-48.54318,-27.66088],"type":"Point"}
}