{
  "type": "Feature",
  "properties": {
    "gn:admin1_code":"23",
    "gn:admin2_code":"4305108.0",
    "gn:asciiname":"Sao Giacomo",
    "gn:country_code":"BR",
    "gn:dem":757,
    "gn:feature_class":"P",
    "gn:feature_code":"PPLL",
    "gn:name":"S\u00e3o Gi\u00e1como",
    "gn:population":0,
    "gn:timezone":"America/Sao_Paulo",
    "iso:country":"BR",
    "name:por_x_preferred":[
        "S\u00e3o Gi\u00e1como"
    ],
    "wof:name":"Sao Giacomo",
    "wof:placetype":"locality"
},
  "geometry": {"coordinates":[-51.2331,-29.1656],"type":"Point"}
}