{
  "type": "Feature",
  "properties": {
    "gn:admin1_code":"5",
    "gn:admin2_code":"2922854.0",
    "gn:asciiname":"Caixa Prego",
    "gn:country_code":"BR",
    "gn:dem":321,
    "gn:feature_class":"P",
    "gn:feature_code":"PPL",
    "gn:name":"Caixa Prego",
    "gn:population":0,
    "gn:timezone":"America/Bahia",
    "iso:country":"BR",
    "wof:name":"Caixa Prego",
    "wof:placetype":"locality"
},
  "geometry": {"coordinates":[-41.23333,-12.81667],"type":"Point"}
}