{
  "type": "Feature",
  "properties": {
    "gn:admin1_code":"4",
    "gn:admin2_code":"1300839.0",
    "gn:asciiname":"Manguari",
    "gn:country_code":"BR",
    "gn:dem":29,
    "gn:feature_class":"P",
    "gn:feature_code":"PPL",
    "gn:name":"Manguari",
    "gn:population":0,
    "gn:timezone":"America/Manaus",
    "iso:country":"BR",
    "wof:name":"Manguari",
    "wof:placetype":"locality"
},
  "geometry": {"coordinates":[-61.635,-3.01194],"type":"Point"}
}