{
  "type": "Feature",
  "properties": {
    "gn:admin1_code":"14",
    "gn:admin2_code":"5107776.0",
    "gn:asciiname":"Chico Roberto",
    "gn:country_code":"BR",
    "gn:dem":202,
    "gn:feature_class":"P",
    "gn:feature_code":"PPL",
    "gn:name":"Chico Roberto",
    "gn:population":0,
    "gn:timezone":"America/Cuiaba",
    "iso:country":"BR",
    "wof:name":"Chico Roberto",
    "wof:placetype":"locality"
},
  "geometry": {"coordinates":[-50.46667,-10.31667],"type":"Point"}
}