{
  "type": "Feature",
  "properties": {
    "gn:admin1_code":"5.0",
    "gn:admin2_code":"2917003.0",
    "gn:asciiname":"Ponta Baixa",
    "gn:country_code":"BR",
    "gn:dem":412,
    "gn:feature_class":"P",
    "gn:feature_code":"PPL",
    "gn:name":"Ponta Baixa",
    "gn:population":0,
    "gn:timezone":"America/Bahia",
    "iso:country":"BR",
    "name:por_x_preferred":[
        "Ponta Baixa"
    ],
    "wof:name":"Ponta Baixa",
    "wof:placetype":"locality"
},
  "geometry": {"coordinates":[-39.89308,-10.50949],"type":"Point"}
}