{
  "type": "Feature",
  "properties": {
    "gn:admin1_code":"20",
    "gn:admin2_code":"2210409.0",
    "gn:asciiname":"Gameleiras",
    "gn:country_code":"BR",
    "gn:dem":359,
    "gn:feature_class":"P",
    "gn:feature_code":"PPL",
    "gn:name":"Gameleiras",
    "gn:population":0,
    "gn:timezone":"America/Fortaleza",
    "iso:country":"BR",
    "wof:name":"Gameleiras",
    "wof:placetype":"locality"
},
  "geometry": {"coordinates":[-41.48333,-6.08333],"type":"Point"}
}