{
  "type": "Feature",
  "properties": {
    "gn:admin1_code":"20",
    "gn:admin2_code":"2210409.0",
    "gn:asciiname":"Gameleiras",
    "gn:country_code":"BR",
    "gn:dem":359,
    "gn:feature_class":"P",
    "gn:feature_code":"PPL",
    "gn:name":"Gameleiras",
    "gn:population":0,
    "gn:timezone":"America/Fortaleza",
    "iso:country":"BR",
    "name:bpy_x_preferred":[
        "\u0997\u09be\u09ae\u09c7\u09b2\u09af\u09bc\u09c7\u0987\u09b0\u09be\u09b8"
    ],
    "name:ceb_x_preferred":[
        "Gameleiras"
    ],
    "name:epo_x_preferred":[
        "Gameleiras"
    ],
    "name:eus_x_preferred":[
        "Gameleiras"
    ],
    "name:fra_x_preferred":[
        "Gameleiras"
    ],
    "name:hye_x_preferred":[
        "\u0533\u0561\u0574\u0565\u056c\u0565\u0575\u0580\u0561\u057d"
    ],
    "name:ita_x_preferred":[
        "Gameleiras"
    ],
    "name:kat_x_preferred":[
        "\u10d2\u10d0\u10db\u10d4\u10da\u10d4\u10d8\u10e0\u10d0\u10e1\u10d8"
    ],
    "name:kaz_x_preferred":[
        "\u0413\u0430\u043c\u0435\u043b\u0435\u0439\u0440\u0430\u0441"
    ],
    "name:mlg_x_preferred":[
        "Gameleiras"
    ],
    "name:nld_x_preferred":[
        "Gameleiras"
    ],
    "name:nor_x_preferred":[
        "Gameleiras"
    ],
    "name:pol_x_preferred":[
        "Gameleiras"
    ],
    "name:por_x_preferred":[
        "Gameleiras"
    ],
    "name:ron_x_preferred":[
        "Gameleiras"
    ],
    "name:rus_x_preferred":[
        "\u0413\u0430\u043c\u0435\u043b\u0435\u0439\u0440\u0430\u0441"
    ],
    "name:spa_x_preferred":[
        "Gameleiras"
    ],
    "name:swe_x_preferred":[
        "Gameleiras"
    ],
    "name:vie_x_preferred":[
        "Gameleiras"
    ],
    "name:vol_x_preferred":[
        "Gameleiras"
    ],
    "name:war_x_preferred":[
        "Gameleiras"
    ],
    "name:zho_x_preferred":[
        "\u52a0\u6885\u83b1\u62c9\u65af"
    ],
    "wof:name":"Gameleiras",
    "wof:placetype":"locality"
},
  "geometry": {"coordinates":[-41.48333,-6.08333],"type":"Point"}
}