{
  "type": "Feature",
  "properties": {
    "gn:admin1_code":"16.0",
    "gn:admin2_code":"1505304.0",
    "gn:asciiname":"Teixeira",
    "gn:country_code":"BR",
    "gn:dem":12,
    "gn:feature_class":"P",
    "gn:feature_code":"PPL",
    "gn:name":"Teixeira",
    "gn:population":0,
    "gn:timezone":"America/Santarem",
    "iso:country":"BR",
    "name:por_x_preferred":[
        "Teixeira"
    ],
    "wof:name":"Teixeira",
    "wof:placetype":"locality"
},
  "geometry": {"coordinates":[-56.27594000000001,-1.91235],"type":"Point"}
}