{
  "type": "Feature",
  "properties": {
    "gn:admin1_code":"16.0",
    "gn:admin2_code":"1505304.0",
    "gn:asciiname":"Teixeira",
    "gn:country_code":"BR",
    "gn:dem":12,
    "gn:feature_class":"P",
    "gn:feature_code":"PPL",
    "gn:name":"Teixeira",
    "gn:population":0,
    "gn:timezone":"America/Santarem",
    "iso:country":"BR",
    "name:bpy_x_preferred":[
        "\u099f\u09c7\u0987\u0995\u09cd\u09b8\u09c7\u0987\u09b0\u09be"
    ],
    "name:ceb_x_preferred":[
        "Teixeira"
    ],
    "name:ces_x_preferred":[
        "Teixeira"
    ],
    "name:deu_x_preferred":[
        "Teixeira"
    ],
    "name:fin_x_preferred":[
        "Teixeira"
    ],
    "name:fra_x_preferred":[
        "Teixeira"
    ],
    "name:glg_x_preferred":[
        "Teixeira"
    ],
    "name:ita_x_preferred":[
        "Teixeira"
    ],
    "name:jpn_x_preferred":[
        "\u30c6\u30a4\u30b7\u30a7\u30a4\u30e9"
    ],
    "name:lit_x_preferred":[
        "Teixeira"
    ],
    "name:nld_x_preferred":[
        "Teixeira"
    ],
    "name:por_x_preferred":[
        "Teixeira"
    ],
    "name:rus_x_preferred":[
        "\u0422\u0435\u0439\u0448\u0435\u0439\u0440\u0430"
    ],
    "name:spa_x_preferred":[
        "Teixeira"
    ],
    "name:swe_x_preferred":[
        "Teixeira"
    ],
    "name:ukr_x_preferred":[
        "\u0422\u0435\u0439\u0448\u0435\u0439\u0440\u0430"
    ],
    "name:zho_x_preferred":[
        "\u7279\u8c22\u62c9"
    ],
    "wof:name":"Teixeira",
    "wof:placetype":"locality"
},
  "geometry": {"coordinates":[-56.27594000000001,-1.91235],"type":"Point"}
}