{
  "type": "Feature",
  "properties": {
    "gn:admin1_code":"18.0",
    "gn:admin2_code":"4119202.0",
    "gn:asciiname":"Sitio Valdemar de Oliveira",
    "gn:country_code":"BR",
    "gn:dem":722,
    "gn:feature_class":"P",
    "gn:feature_code":"PPL",
    "gn:name":"S\u00edtio Valdemar de Oliveira",
    "gn:population":0,
    "gn:timezone":"America/Sao_Paulo",
    "iso:country":"BR",
    "name:por_x_preferred":[
        "S\u00edtio Valdemar de Oliveira"
    ],
    "wof:name":"Sitio Valdemar de Oliveira",
    "wof:placetype":"locality"
},
  "geometry": {"coordinates":[-50.05334000000001,-23.83941],"type":"Point"}
}