{
  "type": "Feature",
  "properties": {
    "gn:admin1_code":"27",
    "gn:admin2_code":"3550605.0",
    "gn:asciiname":"Sitio Katel",
    "gn:country_code":"BR",
    "gn:dem":931,
    "gn:feature_class":"P",
    "gn:feature_code":"PPL",
    "gn:name":"S\u00edtio Katel",
    "gn:population":0,
    "gn:timezone":"America/Sao_Paulo",
    "iso:country":"BR",
    "name:por_x_preferred":[
        "S\u00edtio Katel"
    ],
    "wof:name":"Sitio Katel",
    "wof:placetype":"locality"
},
  "geometry": {"coordinates":[-47.05131,-23.56365],"type":"Point"}
}