{
  "type": "Feature",
  "properties": {
    "gn:admin1_code":"27.0",
    "gn:admin2_code":"3530706.0",
    "gn:asciiname":"Jardim Laranjeiras",
    "gn:country_code":"BR",
    "gn:dem":587,
    "gn:feature_class":"P",
    "gn:feature_code":"PPLL",
    "gn:name":"Jardim Laranjeiras",
    "gn:population":0,
    "gn:timezone":"America/Sao_Paulo",
    "iso:country":"BR",
    "wof:name":"Jardim Laranjeiras",
    "wof:placetype":"locality"
},
  "geometry": {"coordinates":[-47.13903,-22.2864],"type":"Point"}
}