{
  "type": "Feature",
  "properties": {
    "gn:admin1_code":"27",
    "gn:admin2_code":"3519709.0",
    "gn:asciiname":"Sitio do Lago",
    "gn:country_code":"BR",
    "gn:dem":900,
    "gn:feature_class":"P",
    "gn:feature_code":"PPL",
    "gn:name":"S\u00edtio do Lago",
    "gn:population":0,
    "gn:timezone":"America/Sao_Paulo",
    "iso:country":"BR",
    "name:por_x_preferred":[
        "S\u00edtio do Lago"
    ],
    "wof:name":"Sitio do Lago",
    "wof:placetype":"locality"
},
  "geometry": {"coordinates":[-47.06554000000001,-23.71718],"type":"Point"}
}