{
  "type": "Feature",
  "properties": {
    "gn:admin1_code":"5.0",
    "gn:admin2_code":"2904753.0",
    "gn:asciiname":"Mimosa",
    "gn:country_code":"BR",
    "gn:dem":501,
    "gn:feature_class":"P",
    "gn:feature_code":"PPL",
    "gn:name":"Mimosa",
    "gn:population":0,
    "gn:timezone":"America/Bahia",
    "iso:country":"BR",
    "name:por_x_preferred":[
        "Mimosa"
    ],
    "wof:name":"Mimosa",
    "wof:placetype":"locality"
},
  "geometry": {"coordinates":[-43.48736,-10.32215],"type":"Point"}
}