{
  "type": "Feature",
  "properties": {
    "gn:admin1_code":"5.0",
    "gn:admin2_code":"2904753.0",
    "gn:asciiname":"Mimosa",
    "gn:country_code":"BR",
    "gn:dem":501,
    "gn:feature_class":"P",
    "gn:feature_code":"PPL",
    "gn:name":"Mimosa",
    "gn:population":0,
    "gn:timezone":"America/Bahia",
    "iso:country":"BR",
    "name:ara_x_preferred":[
        "\u0645\u064a\u0645\u0648\u0632\u0627"
    ],
    "name:ben_x_preferred":[
        "\u09b2\u099c\u09cd\u099c\u09be\u09ac\u09a4\u09c0"
    ],
    "name:bul_x_preferred":[
        "\u041c\u0438\u043c\u043e\u0437\u0430"
    ],
    "name:cat_x_preferred":[
        "Mimosa"
    ],
    "name:ceb_x_preferred":[
        "Mimosa"
    ],
    "name:ces_x_preferred":[
        "Citlivka"
    ],
    "name:dan_x_preferred":[
        "Mimose"
    ],
    "name:deu_x_preferred":[
        "Mimosen"
    ],
    "name:ell_x_preferred":[
        "\u039c\u03b9\u03bc\u03cc\u03b6\u03b1"
    ],
    "name:eus_x_preferred":[
        "Mimosa"
    ],
    "name:fas_x_preferred":[
        "\u0645\u06cc\u0645\u0648\u0633\u0627"
    ],
    "name:fin_x_preferred":[
        "Mimosat"
    ],
    "name:fra_x_preferred":[
        "Mimosa"
    ],
    "name:glg_x_preferred":[
        "Mimosa"
    ],
    "name:hrv_x_preferred":[
        "Mimoza"
    ],
    "name:hsb_x_preferred":[
        "Mimozy"
    ],
    "name:hun_x_preferred":[
        "Mimosa"
    ],
    "name:hye_x_preferred":[
        "\u0544\u056b\u0574\u0578\u0566\u0561"
    ],
    "name:ido_x_preferred":[
        "Mimoso"
    ],
    "name:ind_x_preferred":[
        "Mimosa"
    ],
    "name:ita_x_preferred":[
        "Mimosa"
    ],
    "name:kat_x_preferred":[
        "\u10db\u10d8\u10db\u10dd\u10d6\u10d0"
    ],
    "name:koi_x_preferred":[
        "\u041c\u0438\u043c\u043e\u0437\u0430"
    ],
    "name:kor_x_preferred":[
        "\ubbf8\ubaa8\uc0ac\uc18d"
    ],
    "name:kur_x_preferred":[
        "Giya\u015f\u00eer\u00een"
    ],
    "name:lit_x_preferred":[
        "Mimoza"
    ],
    "name:mrj_x_preferred":[
        "\u041c\u0438\u043c\u043e\u0437\u0430"
    ],
    "name:nah_x_preferred":[
        "Huixachin"
    ],
    "name:nld_x_preferred":[
        "Mimosa"
    ],
    "name:pnb_x_preferred":[
        "\u0644\u0627\u062c\u0648\u0646\u062a\u06cc"
    ],
    "name:pol_x_preferred":[
        "Mimoza"
    ],
    "name:por_x_preferred":[
        "Mimosa"
    ],
    "name:rus_x_preferred":[
        "\u041c\u0438\u043c\u043e\u0437\u0430"
    ],
    "name:snd_x_preferred":[
        "\u0634\u0631\u0645 \u067b\u0648\u067d\u064a"
    ],
    "name:spa_x_preferred":[
        "Mimosa"
    ],
    "name:sun_x_preferred":[
        "Mimosa"
    ],
    "name:swe_x_preferred":[
        "Sensitivasl\u00e4ktet"
    ],
    "name:tat_x_preferred":[
        "\u041a\u044b\u0440 \u043a\u044b\u043d\u0430\u0441\u044b"
    ],
    "name:ukr_x_preferred":[
        "\u041c\u0456\u043c\u043e\u0437\u0430"
    ],
    "name:uzb_x_preferred":[
        "Mimoza"
    ],
    "name:war_x_preferred":[
        "Mimosa"
    ],
    "name:zho_x_preferred":[
        "\u542b\u7f9e\u8349\u5c6c"
    ],
    "wof:name":"Mimosa",
    "wof:placetype":"locality"
},
  "geometry": {"coordinates":[-43.48736,-10.32215],"type":"Point"}
}