{
  "type": "Feature",
  "properties": {
    "gn:admin1_code":"11",
    "gn:admin2_code":"5006606.0",
    "gn:asciiname":"Lagoinha",
    "gn:country_code":"BR",
    "gn:dem":530,
    "gn:feature_class":"P",
    "gn:feature_code":"PPL",
    "gn:name":"Lagoinha",
    "gn:population":0,
    "gn:timezone":"America/Campo_Grande",
    "iso:country":"BR",
    "wof:name":"Lagoinha",
    "wof:placetype":"locality"
},
  "geometry": {"coordinates":[-55.93333000000001,-21.93333],"type":"Point"}
}