{
  "type": "Feature",
  "properties": {
    "gn:admin1_code":"11",
    "gn:admin2_code":"5006606.0",
    "gn:asciiname":"Lagoinha",
    "gn:country_code":"BR",
    "gn:dem":530,
    "gn:feature_class":"P",
    "gn:feature_code":"PPL",
    "gn:name":"Lagoinha",
    "gn:population":0,
    "gn:timezone":"America/Campo_Grande",
    "iso:country":"BR",
    "name:bpy_x_preferred":[
        "\u09b2\u09be\u0997\u09cb\u0987\u09a8\u09b9\u09be"
    ],
    "name:ceb_x_preferred":[
        "Lagoinha"
    ],
    "name:epo_x_preferred":[
        "Lagoinha"
    ],
    "name:eus_x_preferred":[
        "Lagoinha"
    ],
    "name:fas_x_preferred":[
        "\u0644\u0627\u06af\u0648\u06cc\u0646\u0627"
    ],
    "name:fra_x_preferred":[
        "Lagoinha"
    ],
    "name:ita_x_preferred":[
        "Lagoinha"
    ],
    "name:kaz_x_preferred":[
        "\u041b\u0430\u0433\u043e\u0438\u043d\u044c\u044f"
    ],
    "name:mlg_x_preferred":[
        "Lagoinha"
    ],
    "name:nld_x_preferred":[
        "Lagoinha"
    ],
    "name:nor_x_preferred":[
        "Lagoinha"
    ],
    "name:pol_x_preferred":[
        "Lagoinha"
    ],
    "name:por_x_preferred":[
        "Lagoinha"
    ],
    "name:ron_x_preferred":[
        "Lagoinha"
    ],
    "name:rus_x_preferred":[
        "\u041b\u0430\u0433\u043e\u0438\u043d\u044c\u044f"
    ],
    "name:swe_x_preferred":[
        "Lagoinha"
    ],
    "name:vie_x_preferred":[
        "Lagoinha"
    ],
    "name:vol_x_preferred":[
        "Lagoinha"
    ],
    "name:war_x_preferred":[
        "Lagoinha"
    ],
    "name:zho_x_preferred":[
        "\u62c9\u6208\u4f0a\u5c3c\u4e9a"
    ],
    "wof:name":"Lagoinha",
    "wof:placetype":"locality"
},
  "geometry": {"coordinates":[-55.93333000000001,-21.93333],"type":"Point"}
}