{
  "type": "Feature",
  "properties": {
    "gn:admin1_code":"20.0",
    "gn:admin2_code":"2202455.0",
    "gn:asciiname":"Tombador",
    "gn:country_code":"BR",
    "gn:dem":317,
    "gn:feature_class":"P",
    "gn:feature_code":"PPL",
    "gn:name":"Tombador",
    "gn:population":0,
    "gn:timezone":"America/Fortaleza",
    "iso:country":"BR",
    "name:por_x_preferred":[
        "Tombador"
    ],
    "wof:name":"Tombador",
    "wof:placetype":"locality"
},
  "geometry": {"coordinates":[-41.95457,-8.48785],"type":"Point"}
}