{
  "type": "Feature",
  "properties": {
    "gn:admin1_code":"26.0",
    "gn:admin2_code":"4203303.0",
    "gn:asciiname":"Avenquinha de Santo Antonio",
    "gn:country_code":"BR",
    "gn:dem":812,
    "gn:feature_class":"P",
    "gn:feature_code":"PPL",
    "gn:name":"Avenquinha de Santo Ant\u00f4nio",
    "gn:population":0,
    "gn:timezone":"America/Sao_Paulo",
    "iso:country":"BR",
    "name:por_x_preferred":[
        "Avenquinha de Santo Ant\u00f4nio"
    ],
    "wof:name":"Avenquinha de Santo Antonio",
    "wof:placetype":"locality"
},
  "geometry": {"coordinates":[-49.32634,-26.16159],"type":"Point"}
}