{
  "type": "Feature",
  "properties": {
    "gn:admin1_code":"27",
    "gn:admin2_code":"3519709.0",
    "gn:asciiname":"Sitio das Tres Meninas",
    "gn:country_code":"BR",
    "gn:dem":860,
    "gn:feature_class":"P",
    "gn:feature_code":"PPL",
    "gn:name":"S\u00edtio das Tr\u00eas Meninas",
    "gn:population":0,
    "gn:timezone":"America/Sao_Paulo",
    "iso:country":"BR",
    "name:por_x_preferred":[
        "S\u00edtio das Tr\u00eas Meninas"
    ],
    "wof:name":"Sitio das Tres Meninas",
    "wof:placetype":"locality"
},
  "geometry": {"coordinates":[-47.13198,-23.65939],"type":"Point"}
}