{
  "type": "Feature",
  "properties": {
    "gn:admin1_code":"06",
    "gn:admin2_code":"2302206.0",
    "gn:asciiname":"Fazenda Sao Mateus",
    "gn:country_code":"BR",
    "gn:dem":69,
    "gn:feature_class":"P",
    "gn:feature_code":"PPL",
    "gn:name":"Fazenda S\u00e3o Mateus",
    "gn:population":0,
    "gn:timezone":"America/Fortaleza",
    "iso:country":"BR",
    "wof:name":"Fazenda Sao Mateus",
    "wof:placetype":"locality"
},
  "geometry": {"coordinates":[-38.26667,-4.51667],"type":"Point"}
}