{
  "type": "Feature",
  "properties": {
    "gn:admin1_code":"27",
    "gn:admin2_code":"3514809.0",
    "gn:asciiname":"Ribeirao Grande",
    "gn:country_code":"BR",
    "gn:dem":59,
    "gn:feature_class":"P",
    "gn:feature_code":"PPLL",
    "gn:name":"Ribeir\u00e3o Grande",
    "gn:population":0,
    "gn:timezone":"America/Sao_Paulo",
    "iso:country":"BR",
    "name:por_x_preferred":[
        "Ribeir\u00e3o Grande"
    ],
    "wof:name":"Ribeirao Grande",
    "wof:placetype":"locality"
},
  "geometry": {"coordinates":[-48.12582,-24.63906],"type":"Point"}
}