{
  "type": "Feature",
  "properties": {
    "gn:admin1_code":"18.0",
    "gn:admin2_code":"4112306.0",
    "gn:asciiname":"Sitio Bom Retiro",
    "gn:country_code":"BR",
    "gn:dem":593,
    "gn:feature_class":"P",
    "gn:feature_code":"PPL",
    "gn:name":"S\u00edtio Bom Retiro",
    "gn:population":0,
    "gn:timezone":"America/Sao_Paulo",
    "iso:country":"BR",
    "name:por_x_preferred":[
        "S\u00edtio Bom Retiro"
    ],
    "wof:name":"Sitio Bom Retiro",
    "wof:placetype":"locality"
},
  "geometry": {"coordinates":[-50.10621,-23.82187],"type":"Point"}
}