{
  "type": "Feature",
  "properties": {
    "gn:admin1_code":"26",
    "gn:admin2_code":"4206652.0",
    "gn:asciiname":"Zandavali",
    "gn:country_code":"BR",
    "gn:dem":626,
    "gn:feature_class":"P",
    "gn:feature_code":"PPL",
    "gn:name":"Zandavali",
    "gn:population":0,
    "gn:timezone":"America/Sao_Paulo",
    "iso:country":"BR",
    "wof:name":"Zandavali",
    "wof:placetype":"locality"
},
  "geometry": {"coordinates":[-52.75,-27.06667],"type":"Point"}
}