{
  "type": "Feature",
  "properties": {
    "gn:admin1_code":"06",
    "gn:admin2_code":"2300408.0",
    "gn:asciiname":"Satao",
    "gn:country_code":"BR",
    "gn:dem":523,
    "gn:feature_class":"P",
    "gn:feature_code":"PPL",
    "gn:name":"Sat\u00e3o",
    "gn:population":0,
    "gn:timezone":"America/Fortaleza",
    "iso:country":"BR",
    "wof:name":"Satao",
    "wof:placetype":"locality"
},
  "geometry": {"coordinates":[-40.38333,-6.63333],"type":"Point"}
}