{
  "type": "Feature",
  "properties": {
    "gn:admin1_code":"27.0",
    "gn:admin2_code":"3550308.0",
    "gn:asciiname":"Sitio Boa Vista",
    "gn:country_code":"BR",
    "gn:dem":790,
    "gn:feature_class":"P",
    "gn:feature_code":"PPL",
    "gn:name":"S\u00edtio Boa Vista",
    "gn:population":0,
    "gn:timezone":"America/Sao_Paulo",
    "iso:country":"BR",
    "name:por_x_preferred":[
        "S\u00edtio Boa Vista"
    ],
    "wof:name":"Sitio Boa Vista",
    "wof:placetype":"locality"
},
  "geometry": {"coordinates":[-46.69251,-23.8362],"type":"Point"}
}