{
  "type": "Feature",
  "properties": {
    "gn:admin1_code":"18",
    "gn:admin2_code":"4122305.0",
    "gn:asciiname":"Sitio Ervino Zimer",
    "gn:country_code":"BR",
    "gn:dem":857,
    "gn:feature_class":"P",
    "gn:feature_code":"PPL",
    "gn:name":"S\u00edtio Ervino Zimer",
    "gn:population":0,
    "gn:timezone":"America/Sao_Paulo",
    "iso:country":"BR",
    "name:por_x_preferred":[
        "S\u00edtio Ervino Zimer"
    ],
    "wof:name":"Sitio Ervino Zimer",
    "wof:placetype":"locality"
},
  "geometry": {"coordinates":[-49.54248,-26.11845],"type":"Point"}
}