{
  "type": "Feature",
  "properties": {
    "gn:admin1_code":"27",
    "gn:admin2_code":"3519709.0",
    "gn:asciiname":"Sitio Paiol Velho",
    "gn:country_code":"BR",
    "gn:dem":1033,
    "gn:feature_class":"P",
    "gn:feature_code":"PPL",
    "gn:name":"S\u00edtio Paiol Velho",
    "gn:population":0,
    "gn:timezone":"America/Sao_Paulo",
    "iso:country":"BR",
    "name:por_x_preferred":[
        "S\u00edtio Paiol Velho"
    ],
    "wof:name":"Sitio Paiol Velho",
    "wof:placetype":"locality"
},
  "geometry": {"coordinates":[-47.1483,-23.8009],"type":"Point"}
}