{
  "type": "Feature",
  "properties": {
    "gn:admin1_code":"18.0",
    "gn:admin2_code":"4117214.0",
    "gn:asciiname":"Sitio Sao Pedro",
    "gn:country_code":"BR",
    "gn:dem":758,
    "gn:feature_class":"P",
    "gn:feature_code":"PPL",
    "gn:name":"S\u00edtio S\u00e3o Pedro",
    "gn:population":0,
    "gn:timezone":"America/Sao_Paulo",
    "iso:country":"BR",
    "name:por_x_preferred":[
        "S\u00edtio S\u00e3o Pedro"
    ],
    "wof:name":"Sitio Sao Pedro",
    "wof:placetype":"locality"
},
  "geometry": {"coordinates":[-50.70156,-23.5689],"type":"Point"}
}