{
  "type": "Feature",
  "properties": {
    "gn:admin1_code":"20.0",
    "gn:admin2_code":"2210359.0",
    "gn:asciiname":"Ingazeira",
    "gn:country_code":"BR",
    "gn:dem":336,
    "gn:feature_class":"P",
    "gn:feature_code":"PPL",
    "gn:name":"Ingazeira",
    "gn:population":0,
    "gn:timezone":"America/Fortaleza",
    "iso:country":"BR",
    "name:por_x_preferred":[
        "Ingazeira"
    ],
    "wof:name":"Ingazeira",
    "wof:placetype":"locality"
},
  "geometry": {"coordinates":[-42.37272,-9.06081],"type":"Point"}
}