{
  "type": "Feature",
  "properties": {
    "gn:admin1_code":"20.0",
    "gn:admin2_code":"2210359.0",
    "gn:asciiname":"Ingazeira",
    "gn:country_code":"BR",
    "gn:dem":336,
    "gn:feature_class":"P",
    "gn:feature_code":"PPL",
    "gn:name":"Ingazeira",
    "gn:population":0,
    "gn:timezone":"America/Fortaleza",
    "iso:country":"BR",
    "name:bpy_x_preferred":[
        "\u0987\u0999\u09cd\u0997\u09be\u099c\u09af\u09bc\u09c7\u0987\u09b0\u09be"
    ],
    "name:ceb_x_preferred":[
        "Ingazeira"
    ],
    "name:eus_x_preferred":[
        "Ingazeira"
    ],
    "name:fra_x_preferred":[
        "Ingazeira"
    ],
    "name:ita_x_preferred":[
        "Ingazeira"
    ],
    "name:kat_x_preferred":[
        "\u10d8\u10dc\u10d2\u10d0\u10d6\u10d4\u10d8\u10e0\u10d0"
    ],
    "name:kaz_x_preferred":[
        "\u0418\u043d\u0433\u0430\u0437\u0435\u0439\u0440\u0430"
    ],
    "name:mlg_x_preferred":[
        "Ingazeira"
    ],
    "name:nld_x_preferred":[
        "Ingazeira"
    ],
    "name:nor_x_preferred":[
        "Ingazeira"
    ],
    "name:por_x_preferred":[
        "Ingazeira"
    ],
    "name:ron_x_preferred":[
        "Ingazeira"
    ],
    "name:rus_x_preferred":[
        "\u0418\u043d\u0433\u0430\u0437\u0435\u0439\u0440\u0430"
    ],
    "name:swe_x_preferred":[
        "Ingazeira"
    ],
    "name:vie_x_preferred":[
        "Ingazeira"
    ],
    "name:vol_x_preferred":[
        "Ingazeira"
    ],
    "name:war_x_preferred":[
        "Ingazeira"
    ],
    "name:zho_x_preferred":[
        "\u56e0\u52a0\u6cfd\u62c9"
    ],
    "wof:name":"Ingazeira",
    "wof:placetype":"locality"
},
  "geometry": {"coordinates":[-42.37272,-9.06081],"type":"Point"}
}