{
  "type": "Feature",
  "properties": {
    "gn:admin1_code":"11",
    "gn:admin2_code":"5003207.0",
    "gn:asciiname":"Paiaguas",
    "gn:country_code":"BR",
    "gn:dem":106,
    "gn:feature_class":"P",
    "gn:feature_code":"PPLL",
    "gn:name":"Paiagu\u00e1s",
    "gn:population":0,
    "gn:timezone":"America/Campo_Grande",
    "iso:country":"BR",
    "wof:name":"Paiaguas",
    "wof:placetype":"locality"
},
  "geometry": {"coordinates":[-57.04083000000001,-18.44722],"type":"Point"}
}