{
  "type": "Feature",
  "properties": {
    "gn:admin1_code":"18",
    "gn:admin2_code":"4125506.0",
    "gn:asciiname":"Sitio Victor Louce",
    "gn:country_code":"BR",
    "gn:dem":994,
    "gn:feature_class":"P",
    "gn:feature_code":"PPL",
    "gn:name":"S\u00edtio V\u00edctor Louce",
    "gn:population":0,
    "gn:timezone":"America/Sao_Paulo",
    "iso:country":"BR",
    "name:por_x_preferred":[
        "S\u00edtio V\u00edctor Louce"
    ],
    "wof:name":"Sitio Victor Louce",
    "wof:placetype":"locality"
},
  "geometry": {"coordinates":[-49.21919000000001,-25.76403],"type":"Point"}
}