{
  "type": "Feature",
  "properties": {
    "gn:admin1_code":"27.0",
    "gn:admin2_code":"3550308.0",
    "gn:asciiname":"Jardim de Abril",
    "gn:country_code":"BR",
    "gn:dem":818,
    "gn:feature_class":"P",
    "gn:feature_code":"PPL",
    "gn:name":"Jardim de Abril",
    "gn:population":0,
    "gn:timezone":"America/Sao_Paulo",
    "iso:country":"BR",
    "name:por_x_preferred":[
        "Jardim de Abril"
    ],
    "wof:name":"Jardim de Abril",
    "wof:placetype":"locality"
},
  "geometry": {"coordinates":[-46.74827,-23.44948],"type":"Point"}
}