{
  "type": "Feature",
  "properties": {
    "gn:admin1_code":"25",
    "gn:admin2_code":"1400027.0",
    "gn:asciiname":"Consolacao",
    "gn:country_code":"BR",
    "gn:dem":114,
    "gn:feature_class":"P",
    "gn:feature_code":"PPL",
    "gn:name":"Consola\u00e7\u00e3o",
    "gn:population":0,
    "gn:timezone":"America/Boa_Vista",
    "iso:country":"BR",
    "wof:name":"Consolacao",
    "wof:placetype":"locality"
},
  "geometry": {"coordinates":[-60.98333,3.93333],"type":"Point"}
}