{
  "type": "Feature",
  "properties": {
    "gn:admin1_code":"18.0",
    "gn:admin2_code":"4109609.0",
    "gn:asciiname":"Sitio Bertal",
    "gn:country_code":"BR",
    "gn:dem":148,
    "gn:feature_class":"P",
    "gn:feature_code":"PPL",
    "gn:name":"S\u00edtio Bertal",
    "gn:population":0,
    "gn:timezone":"America/Sao_Paulo",
    "iso:country":"BR",
    "name:por_x_preferred":[
        "S\u00edtio Bertal"
    ],
    "wof:name":"Sitio Bertal",
    "wof:placetype":"locality"
},
  "geometry": {"coordinates":[-48.907,-25.94587000000001],"type":"Point"}
}