{
  "type": "Feature",
  "properties": {
    "gn:admin1_code":"4",
    "gn:admin2_code":"1302801.0",
    "gn:asciiname":"Novo Marapi",
    "gn:country_code":"BR",
    "gn:dem":71,
    "gn:feature_class":"P",
    "gn:feature_code":"PPL",
    "gn:name":"Novo Marapi",
    "gn:population":0,
    "gn:timezone":"America/Manaus",
    "iso:country":"BR",
    "wof:name":"Novo Marapi",
    "wof:placetype":"locality"
},
  "geometry": {"coordinates":[-65.73824,-1.76418],"type":"Point"}
}