{
  "type": "Feature",
  "properties": {
    "gn:admin1_code":"27",
    "gn:admin2_code":"3525201.0",
    "gn:asciiname":"Sitio Recanto dos Neonhos",
    "gn:country_code":"BR",
    "gn:dem":769,
    "gn:feature_class":"P",
    "gn:feature_code":"PPL",
    "gn:name":"S\u00edtio Recanto dos Neonhos",
    "gn:population":0,
    "gn:timezone":"America/Sao_Paulo",
    "iso:country":"BR",
    "name:por_x_preferred":[
        "S\u00edtio Recanto dos Neonhos"
    ],
    "wof:name":"Sitio Recanto dos Neonhos",
    "wof:placetype":"locality"
},
  "geometry": {"coordinates":[-46.71769000000001,-23.0848],"type":"Point"}
}