{
  "type": "Feature",
  "properties": {
    "gn:admin1_code":"30",
    "gn:admin2_code":"2611200.0",
    "gn:asciiname":"Azevem",
    "gn:cc2":"BR",
    "gn:country_code":"BR",
    "gn:dem":905,
    "gn:feature_class":"P",
    "gn:feature_code":"PPL",
    "gn:name":"Azev\u00e9m",
    "gn:population":0,
    "gn:timezone":"America/Recife",
    "iso:country":"BR",
    "name:und_x_variant":[
        "Azeveria",
        "Azev\u00e9m"
    ],
    "wof:name":"Azevem",
    "wof:placetype":"locality"
},
  "geometry": {"coordinates":[-36.66667,-8.23333],"type":"Point"}
}