{
  "type": "Feature",
  "properties": {
    "gn:admin1_code":"18.0",
    "gn:admin2_code":"4124103.0",
    "gn:asciiname":"Sitio Sergio Faeda",
    "gn:country_code":"BR",
    "gn:dem":449,
    "gn:feature_class":"P",
    "gn:feature_code":"PPL",
    "gn:name":"S\u00edtio S\u00e9rgio Faeda",
    "gn:population":0,
    "gn:timezone":"America/Sao_Paulo",
    "iso:country":"BR",
    "name:por_x_preferred":[
        "S\u00edtio S\u00e9rgio Faeda"
    ],
    "wof:name":"Sitio Sergio Faeda",
    "wof:placetype":"locality"
},
  "geometry": {"coordinates":[-50.1654,-23.1554],"type":"Point"}
}