{
  "type": "Feature",
  "properties": {
    "gn:admin1_code":"18.0",
    "gn:admin2_code":"4117701.0",
    "gn:asciiname":"Sitio Uvaranas",
    "gn:country_code":"BR",
    "gn:dem":926,
    "gn:feature_class":"P",
    "gn:feature_code":"PPL",
    "gn:name":"S\u00edtio Uvaranas",
    "gn:population":0,
    "gn:timezone":"America/Sao_Paulo",
    "iso:country":"BR",
    "name:por_x_preferred":[
        "S\u00edtio Uvaranas"
    ],
    "wof:name":"Sitio Uvaranas",
    "wof:placetype":"locality"
},
  "geometry": {"coordinates":[-50.08292,-25.5591],"type":"Point"}
}