{
  "type": "Feature",
  "properties": {
    "gn:admin1_code":"06",
    "gn:admin2_code":"2311900.0",
    "gn:asciiname":"Sitio Mota",
    "gn:country_code":"BR",
    "gn:dem":513,
    "gn:feature_class":"P",
    "gn:feature_code":"PPL",
    "gn:name":"S\u00edtio Mota",
    "gn:population":0,
    "gn:timezone":"America/Fortaleza",
    "iso:country":"BR",
    "wof:name":"Sitio Mota",
    "wof:placetype":"locality"
},
  "geometry": {"coordinates":[-39.75,-6.36667],"type":"Point"}
}