{
  "type": "Feature",
  "properties": {
    "gn:admin1_code":"27",
    "gn:admin2_code":"3550605.0",
    "gn:asciiname":"Sitio Santa Carmem",
    "gn:country_code":"BR",
    "gn:dem":772,
    "gn:feature_class":"P",
    "gn:feature_code":"PPL",
    "gn:name":"S\u00edtio Santa Carmem",
    "gn:population":0,
    "gn:timezone":"America/Sao_Paulo",
    "iso:country":"BR",
    "name:por_x_preferred":[
        "S\u00edtio Santa Carmem"
    ],
    "wof:name":"Sitio Santa Carmem",
    "wof:placetype":"locality"
},
  "geometry": {"coordinates":[-47.14526,-23.51489],"type":"Point"}
}