{
  "type": "Feature",
  "properties": {
    "gn:admin1_code":"5",
    "gn:admin2_code":"2912707.0",
    "gn:asciiname":"Funil",
    "gn:country_code":"BR",
    "gn:dem":98,
    "gn:feature_class":"P",
    "gn:feature_code":"PPL",
    "gn:name":"Funil",
    "gn:population":0,
    "gn:timezone":"America/Bahia",
    "iso:country":"BR",
    "wof:name":"Funil",
    "wof:placetype":"locality"
},
  "geometry": {"coordinates":[-39.48263,-14.2336],"type":"Point"}
}