{
  "type": "Feature",
  "properties": {
    "gn:admin1_code":"16.0",
    "gn:admin2_code":"1507300.0",
    "gn:asciiname":"Quilometro",
    "gn:country_code":"BR",
    "gn:dem":211,
    "gn:feature_class":"P",
    "gn:feature_code":"PPL",
    "gn:name":"Quilometro",
    "gn:population":0,
    "gn:timezone":"America/Belem",
    "iso:country":"BR",
    "name:por_x_preferred":[
        "Quil\u00f4metro 27"
    ],
    "name:por_x_variant":[
        "Quil\u00f4metro Vinte e Sete"
    ],
    "wof:name":"Quilometro",
    "wof:placetype":"locality"
},
  "geometry": {"coordinates":[-51.79372,-6.7625],"type":"Point"}
}