{
  "type": "Feature",
  "properties": {
    "gn:admin1_code":"27",
    "gn:admin2_code":"3543907.0",
    "gn:asciiname":"Quilombo",
    "gn:country_code":"BR",
    "gn:dem":597,
    "gn:feature_class":"P",
    "gn:feature_code":"PPL",
    "gn:name":"Quilombo",
    "gn:population":0,
    "gn:timezone":"America/Sao_Paulo",
    "iso:country":"BR",
    "name:bul_x_preferred":[
        "\u041a\u0438\u043b\u043e\u043c\u0431\u0443"
    ],
    "name:cat_x_preferred":[
        "Quilombo"
    ],
    "name:deu_x_preferred":[
        "Quilombo"
    ],
    "name:epo_x_preferred":[
        "Kilombo"
    ],
    "name:fra_x_preferred":[
        "Quilombo"
    ],
    "name:heb_x_preferred":[
        "\u05e7\u05d9\u05dc\u05d5\u05de\u05d1\u05d5"
    ],
    "name:ita_x_preferred":[
        "Quilombo"
    ],
    "name:nld_x_preferred":[
        "Quilombo"
    ],
    "name:nor_x_preferred":[
        "Quilombo"
    ],
    "name:pol_x_preferred":[
        "Quilombo"
    ],
    "name:por_x_preferred":[
        "Quilombo"
    ],
    "name:rus_x_preferred":[
        "\u041a\u0438\u043b\u043e\u043c\u0431\u0443"
    ],
    "name:spa_x_preferred":[
        "Quilombo"
    ],
    "wof:name":"Quilombo",
    "wof:placetype":"locality"
},
  "geometry": {"coordinates":[-47.63333,-22.46667],"type":"Point"}
}