{
  "type": "Feature",
  "properties": {
    "gn:admin1_code":"27",
    "gn:admin2_code":"3543907.0",
    "gn:asciiname":"Quilombo",
    "gn:country_code":"BR",
    "gn:dem":597,
    "gn:feature_class":"P",
    "gn:feature_code":"PPL",
    "gn:name":"Quilombo",
    "gn:population":0,
    "gn:timezone":"America/Sao_Paulo",
    "iso:country":"BR",
    "name:por_x_preferred":[
        "Quilombo"
    ],
    "wof:name":"Quilombo",
    "wof:placetype":"locality"
},
  "geometry": {"coordinates":[-47.63333,-22.46667],"type":"Point"}
}