{
  "type": "Feature",
  "properties": {
    "gn:admin1_code":"20",
    "gn:admin2_code":"2210409.0",
    "gn:asciiname":"Pau d'Oleo",
    "gn:country_code":"BR",
    "gn:dem":730,
    "gn:feature_class":"P",
    "gn:feature_code":"PPL",
    "gn:name":"Pau d\u2019\u00d3leo",
    "gn:population":0,
    "gn:timezone":"America/Fortaleza",
    "iso:country":"BR",
    "wof:name":"Pau d'Oleo",
    "wof:placetype":"locality"
},
  "geometry": {"coordinates":[-40.93333,-5.38333],"type":"Point"}
}