{
  "type": "Feature",
  "properties": {
    "gn:admin1_code":"13",
    "gn:admin2_code":"2100501.0",
    "gn:asciiname":"Cotia",
    "gn:country_code":"BR",
    "gn:dem":353,
    "gn:feature_class":"P",
    "gn:feature_code":"PPL",
    "gn:name":"Cotia",
    "gn:population":0,
    "gn:timezone":"America/Fortaleza",
    "iso:country":"BR",
    "wof:name":"Cotia",
    "wof:placetype":"locality"
},
  "geometry": {"coordinates":[-46.11667,-9.53333],"type":"Point"}
}