{
  "type": "Feature",
  "properties": {
    "gn:admin1_code":"8",
    "gn:admin2_code":"3205010.0",
    "gn:asciiname":"Lagoa",
    "gn:country_code":"BR",
    "gn:dem":57,
    "gn:feature_class":"P",
    "gn:feature_code":"PPL",
    "gn:name":"Lagoa",
    "gn:population":0,
    "gn:timezone":"America/Sao_Paulo",
    "iso:country":"BR",
    "name:cat_x_preferred":[
        "Lagoa"
    ],
    "name:ceb_x_preferred":[
        "Lagoa"
    ],
    "name:deu_x_preferred":[
        "Lagoa"
    ],
    "name:fra_x_preferred":[
        "Lagoa"
    ],
    "name:glg_x_preferred":[
        "Lagoa"
    ],
    "name:ita_x_preferred":[
        "Lagoa"
    ],
    "name:kor_x_preferred":[
        "\ub77c\uace0\uc544"
    ],
    "name:nld_x_preferred":[
        "Lagoa"
    ],
    "name:nor_x_preferred":[
        "Lagoa"
    ],
    "name:pol_x_preferred":[
        "Lagoa"
    ],
    "name:por_x_preferred":[
        "Lagoa"
    ],
    "name:rus_x_preferred":[
        "\u041b\u0430\u0433\u043e\u0430"
    ],
    "name:spa_x_preferred":[
        "Lagoa"
    ],
    "name:swe_x_preferred":[
        "Lagoa"
    ],
    "name:ukr_x_preferred":[
        "\u041b\u0430\u0433\u043e\u0430"
    ],
    "name:vie_x_preferred":[
        "Lagoa"
    ],
    "name:vol_x_preferred":[
        "Lagoa"
    ],
    "wof:name":"Lagoa",
    "wof:placetype":"locality"
},
  "geometry": {"coordinates":[-40.18333,-19.16667],"type":"Point"}
}