{
  "type": "Feature",
  "properties": {
    "gn:admin1_code":"16",
    "gn:admin2_code":"1505064.0",
    "gn:asciiname":"Vila Bela",
    "gn:country_code":"BR",
    "gn:dem":70,
    "gn:feature_class":"P",
    "gn:feature_code":"PPL",
    "gn:name":"Vila Bela",
    "gn:population":0,
    "gn:timezone":"America/Belem",
    "iso:country":"BR",
    "wof:name":"Vila Bela",
    "wof:placetype":"locality"
},
  "geometry": {"coordinates":[-49.41667,-4.63333],"type":"Point"}
}