{
  "type": "Feature",
  "properties": {
    "gn:admin1_code":"06",
    "gn:admin2_code":"2300200.0",
    "gn:asciiname":"Corguinho dos Agostinho",
    "gn:country_code":"BR",
    "gn:dem":26,
    "gn:feature_class":"P",
    "gn:feature_code":"PPL",
    "gn:name":"Corguinho dos Agostinho",
    "gn:population":0,
    "gn:timezone":"America/Fortaleza",
    "iso:country":"BR",
    "wof:name":"Corguinho dos Agostinho",
    "wof:placetype":"locality"
},
  "geometry": {"coordinates":[-40.05,-2.91667],"type":"Point"}
}