{
  "type": "Feature",
  "properties": {
    "gn:admin1_code":"4",
    "gn:admin2_code":"1300631.0",
    "gn:asciiname":"Bacuri",
    "gn:country_code":"BR",
    "gn:dem":22,
    "gn:feature_class":"P",
    "gn:feature_code":"PPL",
    "gn:name":"Bacuri",
    "gn:population":0,
    "gn:timezone":"America/Manaus",
    "iso:country":"BR",
    "wof:name":"Bacuri",
    "wof:placetype":"locality"
},
  "geometry": {"coordinates":[-62.19333,-4.47639],"type":"Point"}
}