{
  "type": "Feature",
  "properties": {
    "gn:admin1_code":"5",
    "gn:admin2_code":"2931400.0",
    "gn:asciiname":"Rumo",
    "gn:country_code":"BR",
    "gn:dem":179,
    "gn:feature_class":"P",
    "gn:feature_code":"PPL",
    "gn:name":"Rumo",
    "gn:population":0,
    "gn:timezone":"America/Bahia",
    "iso:country":"BR",
    "name:azb_x_preferred":[
        "\u0631\u0648\u0645\u0648"
    ],
    "name:bel_x_preferred":[
        "\u0420\u0443\u043c\u0430"
    ],
    "name:cat_x_preferred":[
        "Rumo"
    ],
    "name:deu_x_preferred":[
        "Rumo"
    ],
    "name:epo_x_preferred":[
        "Rumo"
    ],
    "name:est_x_preferred":[
        "Rumo"
    ],
    "name:eus_x_preferred":[
        "Rumo"
    ],
    "name:fas_x_preferred":[
        "\u0631\u0648\u0645\u0648"
    ],
    "name:fra_x_preferred":[
        "Rumo"
    ],
    "name:hun_x_preferred":[
        "Rumo"
    ],
    "name:hye_x_preferred":[
        "\u054c\u0578\u0582\u0574\u0578"
    ],
    "name:ind_x_preferred":[
        "Rumo"
    ],
    "name:ita_x_preferred":[
        "Rumo"
    ],
    "name:jpn_x_preferred":[
        "\u30eb\u30fc\u30e2"
    ],
    "name:kaz_x_preferred":[
        "\u0420\u0443\u043c\u043e"
    ],
    "name:lat_x_preferred":[
        "Rumum"
    ],
    "name:lmo_x_preferred":[
        "Rumo"
    ],
    "name:msa_x_preferred":[
        "Rumo"
    ],
    "name:nap_x_preferred":[
        "Rumo"
    ],
    "name:nld_x_preferred":[
        "Rumo"
    ],
    "name:pms_x_preferred":[
        "Rumo"
    ],
    "name:pol_x_preferred":[
        "Rumo"
    ],
    "name:por_x_preferred":[
        "Rumo"
    ],
    "name:ron_x_preferred":[
        "Rumo"
    ],
    "name:rus_x_preferred":[
        "\u0420\u0443\u043c\u043e"
    ],
    "name:scn_x_preferred":[
        "Rumo"
    ],
    "name:spa_x_preferred":[
        "Rumo"
    ],
    "name:srp_x_preferred":[
        "\u0420\u0443\u043c\u043e"
    ],
    "name:tgl_x_preferred":[
        "Rumo"
    ],
    "name:tur_x_preferred":[
        "Rumo"
    ],
    "name:ukr_x_preferred":[
        "\u0420\u0443\u043c\u043e"
    ],
    "name:uzb_x_preferred":[
        "Rumo"
    ],
    "name:vie_x_preferred":[
        "Rumo"
    ],
    "name:vol_x_preferred":[
        "Rumo"
    ],
    "name:war_x_preferred":[
        "Rumo"
    ],
    "wof:name":"Rumo",
    "wof:placetype":"locality"
},
  "geometry": {"coordinates":[-38.63333,-12.18333],"type":"Point"}
}