{
  "type": "Feature",
  "properties": {
    "gn:admin1_code":"5",
    "gn:admin2_code":"2931400.0",
    "gn:asciiname":"Rumo",
    "gn:country_code":"BR",
    "gn:dem":179,
    "gn:feature_class":"P",
    "gn:feature_code":"PPL",
    "gn:name":"Rumo",
    "gn:population":0,
    "gn:timezone":"America/Bahia",
    "iso:country":"BR",
    "wof:name":"Rumo",
    "wof:placetype":"locality"
},
  "geometry": {"coordinates":[-38.63333,-12.18333],"type":"Point"}
}