{
  "type": "Feature",
  "properties": {
    "gn:admin1_code":"23",
    "gn:admin2_code":"4313391.0",
    "gn:asciiname":"Cortado",
    "gn:country_code":"BR",
    "gn:dem":64,
    "gn:feature_class":"P",
    "gn:feature_code":"PPL",
    "gn:name":"Cortado",
    "gn:population":0,
    "gn:timezone":"America/Sao_Paulo",
    "iso:country":"BR",
    "wof:name":"Cortado",
    "wof:placetype":"locality"
},
  "geometry": {"coordinates":[-52.96666999999999,-29.75],"type":"Point"}
}