{
  "type": "Feature",
  "properties": {
    "gn:admin1_code":"23",
    "gn:admin2_code":"4313391.0",
    "gn:asciiname":"Cortado",
    "gn:country_code":"BR",
    "gn:dem":64,
    "gn:feature_class":"P",
    "gn:feature_code":"PPL",
    "gn:name":"Cortado",
    "gn:population":0,
    "gn:timezone":"America/Sao_Paulo",
    "iso:country":"BR",
    "name:bel_x_preferred":[
        "\u041a\u0430\u0440\u0442\u0430\u0434\u0430"
    ],
    "name:cat_x_preferred":[
        "Caf\u00e8 tallat"
    ],
    "name:dan_x_preferred":[
        "Cortado"
    ],
    "name:eus_x_preferred":[
        "Kafe ebaki"
    ],
    "name:fra_x_preferred":[
        "Cortado"
    ],
    "name:heb_x_preferred":[
        "\u05e7\u05d5\u05e8\u05d8\u05d3\u05d5"
    ],
    "name:hye_x_preferred":[
        "\u053f\u0578\u0580\u057f\u0561\u0564\u0578"
    ],
    "name:ita_x_preferred":[
        "Cortado"
    ],
    "name:jpn_x_preferred":[
        "\u30b3\u30eb\u30bf\u30fc\u30c9"
    ],
    "name:lit_x_preferred":[
        "Kortadas"
    ],
    "name:nld_x_preferred":[
        "Cortado"
    ],
    "name:nor_x_preferred":[
        "Cortado"
    ],
    "name:rus_x_preferred":[
        "\u041a\u043e\u0440\u0442\u0430\u0434\u043e"
    ],
    "name:spa_x_preferred":[
        "Cortado"
    ],
    "name:swe_x_preferred":[
        "Cortado"
    ],
    "name:tha_x_preferred":[
        "\u0e01\u0e2d\u0e23\u0e4c\u0e15\u0e32\u0e42\u0e14"
    ],
    "name:tur_x_preferred":[
        "Cortado"
    ],
    "name:ukr_x_preferred":[
        "\u041a\u043e\u0440\u0442\u0430\u0434\u043e"
    ],
    "name:zho_x_preferred":[
        "\u544a\u723e\u591a"
    ],
    "wof:name":"Cortado",
    "wof:placetype":"locality"
},
  "geometry": {"coordinates":[-52.96666999999999,-29.75],"type":"Point"}
}