{
  "type": "Feature",
  "properties": {
    "gn:admin1_code":"20",
    "gn:admin2_code":"2206720.0",
    "gn:asciiname":"Pombinhas",
    "gn:country_code":"BR",
    "gn:dem":122,
    "gn:feature_class":"P",
    "gn:feature_code":"PPL",
    "gn:name":"Pombinhas",
    "gn:population":0,
    "gn:timezone":"America/Fortaleza",
    "iso:country":"BR",
    "wof:name":"Pombinhas",
    "wof:placetype":"locality"
},
  "geometry": {"coordinates":[-42.95,-5.53333],"type":"Point"}
}