{
  "type": "Feature",
  "properties": {
    "gn:admin1_code":"18.0",
    "gn:admin2_code":"4109708.0",
    "gn:asciiname":"Sitio Luiz P. da Silva",
    "gn:country_code":"BR",
    "gn:dem":655,
    "gn:feature_class":"P",
    "gn:feature_code":"PPL",
    "gn:name":"S\u00edtio Luiz P. da Silva",
    "gn:population":0,
    "gn:timezone":"America/Sao_Paulo",
    "iso:country":"BR",
    "name:por_x_preferred":[
        "S\u00edtio Luiz P. da Silva"
    ],
    "wof:name":"Sitio Luiz P. da Silva",
    "wof:placetype":"locality"
},
  "geometry": {"coordinates":[-50.29975,-23.87635],"type":"Point"}
}