{
  "type": "Feature",
  "properties": {
    "gn:admin1_code":"13",
    "gn:admin2_code":"2111409.0",
    "gn:asciiname":"Jatoba",
    "gn:country_code":"BR",
    "gn:dem":55,
    "gn:feature_class":"P",
    "gn:feature_code":"PPL",
    "gn:name":"Jatob\u00e1",
    "gn:population":0,
    "gn:timezone":"America/Fortaleza",
    "iso:country":"BR",
    "wof:name":"Jatoba",
    "wof:placetype":"locality"
},
  "geometry": {"coordinates":[-44.65,-4.41667],"type":"Point"}
}