{
  "type": "Feature",
  "properties": {
    "gn:admin1_code":"26",
    "gn:admin2_code":"4208708.0",
    "gn:asciiname":"Pinheirinho Baixo",
    "gn:country_code":"BR",
    "gn:dem":46,
    "gn:feature_class":"P",
    "gn:feature_code":"PPL",
    "gn:name":"Pinheirinho Baixo",
    "gn:population":0,
    "gn:timezone":"America/Sao_Paulo",
    "iso:country":"BR",
    "wof:name":"Pinheirinho Baixo",
    "wof:placetype":"locality"
},
  "geometry": {"coordinates":[-49.78333,-28.95],"type":"Point"}
}