{
  "type": "Feature",
  "properties": {
    "gn:admin1_code":"17",
    "gn:admin2_code":"2502805.0",
    "gn:asciiname":"Condado",
    "gn:country_code":"BR",
    "gn:dem":197,
    "gn:feature_class":"P",
    "gn:feature_code":"PPL",
    "gn:name":"Condado",
    "gn:population":0,
    "gn:timezone":"America/Fortaleza",
    "iso:country":"BR",
    "name:cat_x_preferred":[
        "Condado"
    ],
    "name:ceb_x_preferred":[
        "Condado"
    ],
    "name:deu_x_preferred":[
        "Condado"
    ],
    "name:fra_x_preferred":[
        "Condado"
    ],
    "name:ita_x_preferred":[
        "Condado"
    ],
    "name:nld_x_preferred":[
        "Condado"
    ],
    "name:nor_x_preferred":[
        "Condado"
    ],
    "name:por_x_preferred":[
        "Condado"
    ],
    "name:spa_x_preferred":[
        "Condado"
    ],
    "name:swe_x_preferred":[
        "Condado"
    ],
    "name:vie_x_preferred":[
        "Condado"
    ],
    "name:vol_x_preferred":[
        "Condado"
    ],
    "wof:name":"Condado",
    "wof:placetype":"locality"
},
  "geometry": {"coordinates":[-37.55,-6.35],"type":"Point"}
}