{
  "type": "Feature",
  "properties": {
    "gn:admin1_code":"1",
    "gn:admin2_code":"1200351.0",
    "gn:asciiname":"Sao Francisco",
    "gn:cc2":"BR",
    "gn:country_code":"BR",
    "gn:dem":309,
    "gn:feature_class":"P",
    "gn:feature_code":"PPL",
    "gn:name":"S\u00e3o Francisco",
    "gn:population":0,
    "gn:timezone":"America/Rio_Branco",
    "iso:country":"BR",
    "name:und_x_variant":[
        "Maranguape",
        "Baje",
        "S\u00e3o Francisco"
    ],
    "wof:name":"Sao Francisco",
    "wof:placetype":"locality"
},
  "geometry": {"coordinates":[-72.26666999999998,-9.16667],"type":"Point"}
}