{
  "type": "Feature",
  "properties": {
    "gn:admin1_code":"3",
    "gn:admin2_code":"1600303.0",
    "gn:asciiname":"Ambe",
    "gn:country_code":"BR",
    "gn:dem":14,
    "gn:feature_class":"P",
    "gn:feature_code":"PPL",
    "gn:name":"Amb\u00e9",
    "gn:population":0,
    "gn:timezone":"America/Belem",
    "iso:country":"BR",
    "wof:name":"Ambe",
    "wof:placetype":"locality"
},
  "geometry": {"coordinates":[-50.96527,0.32426],"type":"Point"}
}