{
  "type": "Feature",
  "properties": {
    "gn:admin1_code":"18.0",
    "gn:admin2_code":"4115705.0",
    "gn:asciiname":"Sitio Joao Martins",
    "gn:country_code":"BR",
    "gn:dem":39,
    "gn:feature_class":"P",
    "gn:feature_code":"PPL",
    "gn:name":"S\u00edtio Jo\u00e3o Martins",
    "gn:population":0,
    "gn:timezone":"America/Sao_Paulo",
    "iso:country":"BR",
    "name:por_x_preferred":[
        "S\u00edtio Jo\u00e3o Martins"
    ],
    "wof:name":"Sitio Joao Martins",
    "wof:placetype":"locality"
},
  "geometry": {"coordinates":[-48.5599,-25.8135],"type":"Point"}
}