{
  "type": "Feature",
  "properties": {
    "gn:admin1_code":"5",
    "gn:admin2_code":"2927408.0",
    "gn:asciiname":"Vitoria",
    "gn:country_code":"BR",
    "gn:dem":1,
    "gn:feature_class":"P",
    "gn:feature_code":"PPL",
    "gn:name":"Vit\u00f3ria",
    "gn:population":0,
    "gn:timezone":"America/Bahia",
    "iso:country":"BR",
    "name:por_x_preferred":[
        "Vit\u00f3ria"
    ],
    "wof:name":"Vitoria",
    "wof:placetype":"locality"
},
  "geometry": {"coordinates":[-38.52749,-12.99641],"type":"Point"}
}