{
  "type": "Feature",
  "properties": {
    "gn:admin1_code":"17",
    "gn:admin2_code":"2502003.0",
    "gn:asciiname":"Boa Esperanca",
    "gn:country_code":"BR",
    "gn:dem":174,
    "gn:feature_class":"P",
    "gn:feature_code":"PPL",
    "gn:name":"Boa Esperanca",
    "gn:population":0,
    "gn:timezone":"America/Fortaleza",
    "iso:country":"BR",
    "wof:name":"Boa Esperanca",
    "wof:placetype":"locality"
},
  "geometry": {"coordinates":[-37.48333,-6.23333],"type":"Point"}
}