{
  "type": "Feature",
  "properties": {
    "iso:country":"BR",
    "name:por_x_colloquial":[
        "Canto Dos Aracas"
    ],
    "name:por_x_preferred":[
        "Canto Dos Ara\u00e7\u00e1s"
    ],
    "qs:gn_adm0_cc":"BR",
    "qs:gn_local":3463237,
    "qs:local_max":5086,
    "qs:local_sum":17720,
    "qs:localhoods":35,
    "qs:name":"Canto Dos Ara\u00e7\u00e1s",
    "qs:name_adm0":"Brasil",
    "qs:name_adm1":"Santa Catarina",
    "qs:name_adm2":"Florian\u00f3polis",
    "qs:name_local":"Florian\u00f3polis",
    "qs:photo_max":110,
    "qs:photo_sum":250,
    "qs:placetype":"Suburb",
    "qs:quad_count":23,
    "qs:woe_adm0":23424768,
    "qs:woe_adm1":2344867,
    "qs:woe_adm2":12581654,
    "qs:woe_lau":0,
    "qs:woe_local":455861,
    "qs:woe_ver":"7.10.0",
    "wof:lang":[
        "por"
    ],
    "wof:name":"Canto Dos Ara\u00e7\u00e1s",
    "wof:placetype":"neighbourhood"
},
  "geometry": {"coordinates":[-48.460704,-27.573002],"type":"Point"}
}