{
  "type": "Feature",
  "properties": {
    "gn:admin1_code":"29",
    "gn:admin2_code":"5217203.0",
    "gn:asciiname":"Sucuri",
    "gn:country_code":"BR",
    "gn:dem":414,
    "gn:feature_class":"P",
    "gn:feature_code":"PPL",
    "gn:name":"Sucuri",
    "gn:population":0,
    "gn:timezone":"America/Sao_Paulo",
    "iso:country":"BR",
    "name:por_x_preferred":[
        "Sucuri"
    ],
    "wof:name":"Sucuri",
    "wof:placetype":"locality"
},
  "geometry": {"coordinates":[-51.75,-16.46667],"type":"Point"}
}