{
  "type": "Feature",
  "properties": {
    "gn:admin1_code":"20",
    "gn:admin2_code":"2211605.0",
    "gn:asciiname":"Lagoa (1)",
    "gn:country_code":"BR",
    "gn:dem":412,
    "gn:feature_class":"P",
    "gn:feature_code":"PPL",
    "gn:name":"Lagoa (1)",
    "gn:population":0,
    "gn:timezone":"America/Fortaleza",
    "iso:country":"BR",
    "wof:name":"Lagoa (1)",
    "wof:placetype":"locality"
},
  "geometry": {"coordinates":[-40.93333,-7.18333],"type":"Point"}
}