{
  "type": "Feature",
  "properties": {
    "gn:admin1_code":"27.0",
    "gn:admin2_code":"3550308.0",
    "gn:asciiname":"Sitio Recreio do Canto",
    "gn:country_code":"BR",
    "gn:dem":824,
    "gn:feature_class":"P",
    "gn:feature_code":"PPL",
    "gn:name":"S\u00edtio Recre\u00edo do Canto",
    "gn:population":0,
    "gn:timezone":"America/Sao_Paulo",
    "iso:country":"BR",
    "name:por_x_preferred":[
        "S\u00edtio Recre\u00edo do Canto"
    ],
    "wof:name":"Sitio Recreio do Canto",
    "wof:placetype":"locality"
},
  "geometry": {"coordinates":[-46.7414,-23.8399],"type":"Point"}
}