{
  "type": "Feature",
  "properties": {
    "gn:admin1_code":"16",
    "gn:admin2_code":"1503754.0",
    "gn:asciiname":"Monguba",
    "gn:country_code":"BR",
    "gn:dem":173,
    "gn:feature_class":"P",
    "gn:feature_code":"PPL",
    "gn:name":"Monguba",
    "gn:population":0,
    "gn:timezone":"America/Santarem",
    "iso:country":"BR",
    "wof:name":"Monguba",
    "wof:placetype":"locality"
},
  "geometry": {"coordinates":[-57.63333000000001,-6.43333],"type":"Point"}
}