{
  "type": "Feature",
  "properties": {
    "gn:admin1_code":"23.0",
    "gn:admin2_code":"4309209.0",
    "gn:asciiname":"Vila Natal",
    "gn:country_code":"BR",
    "gn:dem":45,
    "gn:feature_class":"P",
    "gn:feature_code":"PPL",
    "gn:name":"Vila Natal",
    "gn:population":0,
    "gn:timezone":"America/Sao_Paulo",
    "iso:country":"BR",
    "name:por_x_preferred":[
        "Vila Natal"
    ],
    "wof:name":"Vila Natal",
    "wof:placetype":"locality"
},
  "geometry": {"coordinates":[-50.9957,-29.9285],"type":"Point"}
}