{
  "type": "Feature",
  "properties": {
    "gn:admin1_code":"27.0",
    "gn:admin2_code":"3539301.0",
    "gn:asciiname":"Jardim Limoeiro",
    "gn:country_code":"BR",
    "gn:dem":569,
    "gn:feature_class":"P",
    "gn:feature_code":"PPLL",
    "gn:name":"Jardim Limoeiro",
    "gn:population":0,
    "gn:timezone":"America/Sao_Paulo",
    "iso:country":"BR",
    "wof:name":"Jardim Limoeiro",
    "wof:placetype":"locality"
},
  "geometry": {"coordinates":[-47.36193,-21.91976],"type":"Point"}
}