{
  "type": "Feature",
  "properties": {
    "gn:admin1_code":"17",
    "gn:admin2_code":"2500304.0",
    "gn:asciiname":"Bastioes",
    "gn:country_code":"BR",
    "gn:dem":114,
    "gn:feature_class":"P",
    "gn:feature_code":"PPL",
    "gn:name":"Basti\u00f5es",
    "gn:population":0,
    "gn:timezone":"America/Fortaleza",
    "iso:country":"BR",
    "wof:name":"Bastioes",
    "wof:placetype":"locality"
},
  "geometry": {"coordinates":[-35.55,-7.05],"type":"Point"}
}