{
  "type": "Feature",
  "properties": {
    "gn:admin1_code":"27",
    "gn:admin2_code":"3550605.0",
    "gn:asciiname":"Sitio Santa Julieta",
    "gn:country_code":"BR",
    "gn:dem":871,
    "gn:feature_class":"P",
    "gn:feature_code":"PPL",
    "gn:name":"S\u00edtio Santa Julieta",
    "gn:population":0,
    "gn:timezone":"America/Sao_Paulo",
    "iso:country":"BR",
    "name:por_x_preferred":[
        "S\u00edtio Santa Julieta"
    ],
    "wof:name":"Sitio Santa Julieta",
    "wof:placetype":"locality"
},
  "geometry": {"coordinates":[-47.16518,-23.63493],"type":"Point"}
}