{
  "type": "Feature",
  "properties": {
    "gn:admin1_code":"02",
    "gn:admin2_code":"2708402.0",
    "gn:asciiname":"Lagoa do Gaviao",
    "gn:country_code":"BR",
    "gn:dem":220,
    "gn:feature_class":"P",
    "gn:feature_code":"PPL",
    "gn:name":"Lagoa do Gavi\u00e3o",
    "gn:population":0,
    "gn:timezone":"America/Maceio",
    "iso:country":"BR",
    "wof:name":"Lagoa do Gaviao",
    "wof:placetype":"locality"
},
  "geometry": {"coordinates":[-37.63333,-9.46667],"type":"Point"}
}