{
  "type": "Feature",
  "properties": {
    "gn:admin1_code":"27.0",
    "gn:admin2_code":"3510302.0",
    "gn:asciiname":"Cercadinho",
    "gn:country_code":"BR",
    "gn:dem":557,
    "gn:feature_class":"P",
    "gn:feature_code":"PPLL",
    "gn:name":"Cercadinho",
    "gn:population":0,
    "gn:timezone":"America/Sao_Paulo",
    "iso:country":"BR",
    "name:por_x_preferred":[
        "Cercadinho"
    ],
    "wof:name":"Cercadinho",
    "wof:placetype":"locality"
},
  "geometry": {"coordinates":[-47.7617,-23.46894],"type":"Point"}
}