{
  "type": "Feature",
  "properties": {
    "gn:admin1_code":"17",
    "gn:admin2_code":"2516607.0",
    "gn:asciiname":"Minadouro",
    "gn:country_code":"BR",
    "gn:dem":706,
    "gn:feature_class":"P",
    "gn:feature_code":"PPL",
    "gn:name":"Minadouro",
    "gn:population":0,
    "gn:timezone":"America/Fortaleza",
    "iso:country":"BR",
    "wof:name":"Minadouro",
    "wof:placetype":"locality"
},
  "geometry": {"coordinates":[-37.88333,-7.61667],"type":"Point"}
}