{
  "type": "Feature",
  "properties": {
    "gn:admin1_code":"30",
    "gn:admin2_code":"2600609.0",
    "gn:asciiname":"Sao Jose",
    "gn:country_code":"BR",
    "gn:dem":724,
    "gn:feature_class":"P",
    "gn:feature_code":"PPL",
    "gn:name":"S\u00e3o Jos\u00e9",
    "gn:population":0,
    "gn:timezone":"America/Recife",
    "iso:country":"BR",
    "wof:name":"Sao Jose",
    "wof:placetype":"locality"
},
  "geometry": {"coordinates":[-36.78333,-8.46667],"type":"Point"}
}