{
  "type": "Feature",
  "properties": {
    "gn:admin1_code":"5",
    "gn:admin2_code":"2904001.0",
    "gn:asciiname":"Chapada",
    "gn:country_code":"BR",
    "gn:dem":1081,
    "gn:feature_class":"P",
    "gn:feature_code":"PPL",
    "gn:name":"Chapada",
    "gn:population":0,
    "gn:timezone":"America/Bahia",
    "iso:country":"BR",
    "wof:name":"Chapada",
    "wof:placetype":"locality"
},
  "geometry": {"coordinates":[-41.65,-12.73333],"type":"Point"}
}