{
  "type": "Feature",
  "properties": {
    "gn:admin1_code":"27.0",
    "gn:admin2_code":"3524600.0",
    "gn:asciiname":"Sitio Posse",
    "gn:country_code":"BR",
    "gn:dem":96,
    "gn:feature_class":"P",
    "gn:feature_code":"PPL",
    "gn:name":"S\u00edtio Posse",
    "gn:population":0,
    "gn:timezone":"America/Sao_Paulo",
    "iso:country":"BR",
    "name:por_x_preferred":[
        "S\u00edtio Posse"
    ],
    "wof:name":"Sitio Posse",
    "wof:placetype":"locality"
},
  "geometry": {"coordinates":[-48.11737,-24.60066],"type":"Point"}
}