{
  "type": "Feature",
  "properties": {
    "gn:admin1_code":"15",
    "gn:admin2_code":"3170107.0",
    "gn:asciiname":"Peregrino",
    "gn:country_code":"BR",
    "gn:dem":738,
    "gn:feature_class":"P",
    "gn:feature_code":"PPL",
    "gn:name":"Peregrino",
    "gn:population":0,
    "gn:timezone":"America/Sao_Paulo",
    "iso:country":"BR",
    "name:nor_x_preferred":[
        "Peregrino"
    ],
    "name:por_x_preferred":[
        "Peregrino"
    ],
    "wof:name":"Peregrino",
    "wof:placetype":"locality"
},
  "geometry": {"coordinates":[-48.13333,-19.75],"type":"Point"}
}