{
  "type": "Feature",
  "properties": {
    "gn:admin1_code":"20",
    "gn:admin2_code":"2200509.0",
    "gn:asciiname":"Balanco",
    "gn:country_code":"BR",
    "gn:dem":114,
    "gn:feature_class":"P",
    "gn:feature_code":"PPL",
    "gn:name":"Balan\u00e7o",
    "gn:population":0,
    "gn:timezone":"America/Fortaleza",
    "iso:country":"BR",
    "wof:name":"Balanco",
    "wof:placetype":"locality"
},
  "geometry": {"coordinates":[-42.81667,-6.33333],"type":"Point"}
}