{
  "type": "Feature",
  "properties": {
    "gn:admin1_code":"5",
    "gn:admin2_code":"2905206.0",
    "gn:asciiname":"Jatoba",
    "gn:country_code":"BR",
    "gn:dem":863,
    "gn:feature_class":"P",
    "gn:feature_code":"PPL",
    "gn:name":"Jatob\u00e1",
    "gn:population":0,
    "gn:timezone":"America/Bahia",
    "iso:country":"BR",
    "wof:name":"Jatoba",
    "wof:placetype":"locality"
},
  "geometry": {"coordinates":[-42.63333,-13.73333],"type":"Point"}
}