{
  "type": "Feature",
  "properties": {
    "gn:admin1_code":"26.0",
    "gn:admin2_code":"4220000.0",
    "gn:asciiname":"Lombas",
    "gn:country_code":"BR",
    "gn:dem":19,
    "gn:feature_class":"P",
    "gn:feature_code":"PPL",
    "gn:name":"Lombas",
    "gn:population":0,
    "gn:timezone":"America/Sao_Paulo",
    "iso:country":"BR",
    "wof:name":"Lombas",
    "wof:placetype":"locality"
},
  "geometry": {"coordinates":[-49.24543,-28.80402],"type":"Point"}
}