{
  "type": "Feature",
  "properties": {
    "gn:admin1_code":"6",
    "gn:admin2_code":"2313203.0",
    "gn:asciiname":"Barra",
    "gn:country_code":"BR",
    "gn:dem":351,
    "gn:feature_class":"P",
    "gn:feature_code":"PPL",
    "gn:name":"Barra",
    "gn:population":0,
    "gn:timezone":"America/Fortaleza",
    "iso:country":"BR",
    "wof:name":"Barra",
    "wof:placetype":"locality"
},
  "geometry": {"coordinates":[-40.38333,-4.98333],"type":"Point"}
}