{
  "type": "Feature",
  "properties": {
    "gn:admin1_code":"18.0",
    "gn:admin2_code":"4119202.0",
    "gn:asciiname":"Sitio Jose da Silva",
    "gn:country_code":"BR",
    "gn:dem":657,
    "gn:feature_class":"P",
    "gn:feature_code":"PPL",
    "gn:name":"S\u00edtio Jos\u00e9 da Silva",
    "gn:population":0,
    "gn:timezone":"America/Sao_Paulo",
    "iso:country":"BR",
    "name:por_x_preferred":[
        "S\u00edtio Jos\u00e9 da Silva"
    ],
    "wof:name":"Sitio Jose da Silva",
    "wof:placetype":"locality"
},
  "geometry": {"coordinates":[-50.04833,-23.9582],"type":"Point"}
}