{
  "type": "Feature",
  "properties": {
    "gn:admin1_code":"27",
    "gn:admin2_code":"3542107.0",
    "gn:asciiname":"Santana",
    "gn:country_code":"BR",
    "gn:dem":573,
    "gn:feature_class":"P",
    "gn:feature_code":"PPL",
    "gn:name":"Santana",
    "gn:population":0,
    "gn:timezone":"America/Sao_Paulo",
    "iso:country":"BR",
    "name:por_x_preferred":[
        "Santana"
    ],
    "wof:name":"Santana",
    "wof:placetype":"locality"
},
  "geometry": {"coordinates":[-47.52637,-23.08154],"type":"Point"}
}