{
  "type": "Feature",
  "properties": {
    "gn:admin1_code":"4",
    "gn:admin2_code":"1304062.0",
    "gn:asciiname":"Sao Felix",
    "gn:country_code":"BR",
    "gn:dem":80,
    "gn:feature_class":"P",
    "gn:feature_code":"PPL",
    "gn:name":"S\u00e3o F\u00e9lix",
    "gn:population":0,
    "gn:timezone":"America/Manaus",
    "iso:country":"BR",
    "wof:name":"Sao Felix",
    "wof:placetype":"locality"
},
  "geometry": {"coordinates":[-69.48333000000001,-3.75],"type":"Point"}
}