{
  "type": "Feature",
  "properties": {
    "gn:admin1_code":"02",
    "gn:admin2_code":"2702306.0",
    "gn:asciiname":"Santa Luzia",
    "gn:country_code":"BR",
    "gn:dem":119,
    "gn:feature_class":"P",
    "gn:feature_code":"PPL",
    "gn:name":"Santa Luzia",
    "gn:population":0,
    "gn:timezone":"America/Maceio",
    "iso:country":"BR",
    "wof:name":"Santa Luzia",
    "wof:placetype":"locality"
},
  "geometry": {"coordinates":[-36.26667,-9.98333],"type":"Point"}
}