{
  "type": "Feature",
  "properties": {
    "gn:admin1_code":"26",
    "gn:admin2_code":"4218202.0",
    "gn:asciiname":"Mulde Alta",
    "gn:country_code":"BR",
    "gn:dem":247,
    "gn:feature_class":"P",
    "gn:feature_code":"PPL",
    "gn:name":"Mulde Alta",
    "gn:population":0,
    "gn:timezone":"America/Sao_Paulo",
    "iso:country":"BR",
    "name:por_x_preferred":[
        "Mulde Alta"
    ],
    "wof:name":"Mulde Alta",
    "wof:placetype":"locality"
},
  "geometry": {"coordinates":[-49.2126,-26.7922],"type":"Point"}
}