{
  "type": "Feature",
  "properties": {
    "gn:admin1_code":"18",
    "gn:admin2_code":"4121752.0",
    "gn:asciiname":"Rondinha",
    "gn:country_code":"BR",
    "gn:dem":815,
    "gn:feature_class":"P",
    "gn:feature_code":"PPL",
    "gn:name":"Rondinha",
    "gn:population":0,
    "gn:timezone":"America/Sao_Paulo",
    "iso:country":"BR",
    "wof:name":"Rondinha",
    "wof:placetype":"locality"
},
  "geometry": {"coordinates":[-52.08333,-25.88333],"type":"Point"}
}