{
  "type": "Feature",
  "properties": {
    "gn:admin1_code":"11",
    "gn:admin2_code":"5007208.0",
    "gn:asciiname":"Viramao",
    "gn:country_code":"BR",
    "gn:dem":389,
    "gn:feature_class":"P",
    "gn:feature_code":"PPL",
    "gn:name":"Viram\u00e3o",
    "gn:population":0,
    "gn:timezone":"America/Campo_Grande",
    "iso:country":"BR",
    "wof:name":"Viramao",
    "wof:placetype":"locality"
},
  "geometry": {"coordinates":[-54.76667,-21.45],"type":"Point"}
}