{
  "type": "Feature",
  "properties": {
    "gn:admin1_code":"8",
    "gn:admin2_code":"3203320.0",
    "gn:asciiname":"Jacaranda",
    "gn:country_code":"BR",
    "gn:dem":32,
    "gn:feature_class":"P",
    "gn:feature_code":"PPL",
    "gn:name":"Jacarand\u00e1",
    "gn:population":0,
    "gn:timezone":"America/Sao_Paulo",
    "iso:country":"BR",
    "name:ara_x_preferred":[
        "\u062c\u0643\u0631\u0627\u0646\u062f\u0629"
    ],
    "name:bak_x_preferred":[
        "\u0416\u0430\u043a\u0430\u0440\u0430\u043d\u0434\u0430"
    ],
    "name:bar_x_preferred":[
        "Jacaranda"
    ],
    "name:ben_x_preferred":[
        "\u099c\u09cd\u09af\u09be\u0995\u09be\u09b0\u09be\u09a8\u09cd\u09a1\u09be"
    ],
    "name:cat_x_preferred":[
        "Jacaranda"
    ],
    "name:ces_x_preferred":[
        "\u017dakaranda"
    ],
    "name:deu_x_preferred":[
        "Jacaranda"
    ],
    "name:ell_x_preferred":[
        "\u0393\u03b9\u03b1\u03ba\u03b1\u03c1\u03ac\u03bd\u03c4\u03b1"
    ],
    "name:fas_x_preferred":[
        "\u062f\u0631\u062e\u062a \u0646\u0648\u0631\u0627"
    ],
    "name:fin_x_preferred":[
        "Jakarandat"
    ],
    "name:fra_x_preferred":[
        "Jacaranda"
    ],
    "name:hrv_x_preferred":[
        "Jakaranda"
    ],
    "name:hun_x_preferred":[
        "Zsakaranda"
    ],
    "name:ind_x_preferred":[
        "Jacaranda"
    ],
    "name:ita_x_preferred":[
        "Jacaranda"
    ],
    "name:jpn_x_preferred":[
        "\u30ad\u30ea\u30e2\u30c9\u30ad\u5c5e"
    ],
    "name:lit_x_preferred":[
        "Palisandramedis"
    ],
    "name:nep_x_preferred":[
        "\u092d\u0901\u0917\u0947\u0930\u0940 \u092b\u0942\u0932"
    ],
    "name:nor_x_preferred":[
        "Jacaranda"
    ],
    "name:pol_x_preferred":[
        "Jakaranda"
    ],
    "name:por_x_preferred":[
        "Jacarand\u00e1"
    ],
    "name:por_x_variant":[
        "Jacaranda"
    ],
    "name:que_x_preferred":[
        "Qarawichka"
    ],
    "name:rus_x_preferred":[
        "\u0416\u0430\u043a\u0430\u0440\u0430\u043d\u0434\u0430"
    ],
    "name:spa_x_preferred":[
        "Jacaranda"
    ],
    "name:swe_x_preferred":[
        "Jakarandasl\u00e4ktet"
    ],
    "name:tur_x_preferred":[
        "Jakaranda"
    ],
    "name:ukr_x_preferred":[
        "\u0416\u0430\u043a\u0430\u0440\u0430\u043d\u0434\u0430"
    ],
    "name:wln_x_preferred":[
        "Djacaranda"
    ],
    "name:xmf_x_preferred":[
        "\u10df\u10d0\u10d9\u10d0\u10e0\u10d0\u10dc\u10d3\u10d0"
    ],
    "name:zho_x_preferred":[
        "\u85cd\u82b1\u6979\u5c6c"
    ],
    "wof:name":"Jacaranda",
    "wof:placetype":"locality"
},
  "geometry": {"coordinates":[-40.85,-21.06667],"type":"Point"}
}