{
  "type": "Feature",
  "properties": {
    "gn:admin1_code":"22",
    "gn:admin2_code":"2406700.0",
    "gn:asciiname":"Pau de Leite",
    "gn:country_code":"BR",
    "gn:dem":224,
    "gn:feature_class":"P",
    "gn:feature_code":"PPL",
    "gn:name":"Pau de Leite",
    "gn:population":0,
    "gn:timezone":"America/Fortaleza",
    "iso:country":"BR",
    "wof:name":"Pau de Leite",
    "wof:placetype":"locality"
},
  "geometry": {"coordinates":[-36.20278,-5.55222],"type":"Point"}
}