{
  "type": "Feature",
  "properties": {
    "gn:admin1_code":"18.0",
    "gn:admin2_code":"4112801.0",
    "gn:asciiname":"Agua Verde",
    "gn:country_code":"BR",
    "gn:dem":557,
    "gn:feature_class":"P",
    "gn:feature_code":"PPL",
    "gn:name":"\u00c1gua Verde",
    "gn:population":0,
    "gn:timezone":"America/Sao_Paulo",
    "iso:country":"BR",
    "name:por_x_preferred":[
        "\u00c1gua Verde"
    ],
    "wof:name":"Agua Verde",
    "wof:placetype":"locality"
},
  "geometry": {"coordinates":[-49.882,-23.367],"type":"Point"}
}