{
  "type": "Feature",
  "properties": {
    "gn:admin1_code":"5",
    "gn:admin2_code":"2920700.0",
    "gn:asciiname":"Quitungo",
    "gn:country_code":"BR",
    "gn:dem":69,
    "gn:feature_class":"P",
    "gn:feature_code":"PPL",
    "gn:name":"Quitungo",
    "gn:population":0,
    "gn:timezone":"America/Bahia",
    "iso:country":"BR",
    "wof:name":"Quitungo",
    "wof:placetype":"locality"
},
  "geometry": {"coordinates":[-39.08333,-14.18333],"type":"Point"}
}