{
  "type": "Feature",
  "properties": {
    "gn:admin1_code":"4",
    "gn:admin2_code":"1302207.0",
    "gn:asciiname":"Itauna",
    "gn:country_code":"BR",
    "gn:dem":53,
    "gn:feature_class":"P",
    "gn:feature_code":"PPL",
    "gn:name":"Ita\u00fana",
    "gn:population":0,
    "gn:timezone":"America/Manaus",
    "iso:country":"BR",
    "wof:name":"Itauna",
    "wof:placetype":"locality"
},
  "geometry": {"coordinates":[-65.98314000000001,-2.98091],"type":"Point"}
}