{
  "type": "Feature",
  "properties": {
    "gn:admin1_code":"21",
    "gn:admin2_code":"3302700.0",
    "gn:asciiname":"Barra",
    "gn:country_code":"BR",
    "gn:dem":3,
    "gn:feature_class":"P",
    "gn:feature_code":"PPL",
    "gn:name":"Barra",
    "gn:population":0,
    "gn:timezone":"America/Sao_Paulo",
    "iso:country":"BR",
    "name:por_x_preferred":[
        "Barra"
    ],
    "wof:name":"Barra",
    "wof:placetype":"locality"
},
  "geometry": {"coordinates":[-42.81667,-22.95],"type":"Point"}
}