{
  "type": "Feature",
  "properties": {
    "gn:admin1_code":"18.0",
    "gn:admin2_code":"4113205.0",
    "gn:asciiname":"Sitio Antonio Siqueira Mendes",
    "gn:country_code":"BR",
    "gn:dem":812,
    "gn:feature_class":"P",
    "gn:feature_code":"PPL",
    "gn:name":"S\u00edtio Ant\u00f4nio Siqueira Mendes",
    "gn:population":0,
    "gn:timezone":"America/Sao_Paulo",
    "iso:country":"BR",
    "name:por_x_preferred":[
        "S\u00edtio Ant\u00f4nio Siqueira Mendes"
    ],
    "wof:name":"Sitio Antonio Siqueira Mendes",
    "wof:placetype":"locality"
},
  "geometry": {"coordinates":[-49.77577,-25.897],"type":"Point"}
}