{
  "type": "Feature",
  "properties": {
    "gn:admin1_code":"06",
    "gn:admin2_code":"2305902.0",
    "gn:asciiname":"Tapera de Cima",
    "gn:country_code":"BR",
    "gn:dem":614,
    "gn:feature_class":"P",
    "gn:feature_code":"PPL",
    "gn:name":"Tapera de Cima",
    "gn:population":0,
    "gn:timezone":"America/Fortaleza",
    "iso:country":"BR",
    "wof:name":"Tapera de Cima",
    "wof:placetype":"locality"
},
  "geometry": {"coordinates":[-40.88333,-4.53333],"type":"Point"}
}