{
  "type": "Feature",
  "properties": {
    "gn:admin1_code":"18",
    "gn:admin2_code":"4104402.0",
    "gn:asciiname":"Faxinal de Santo Antonio",
    "gn:country_code":"BR",
    "gn:dem":858,
    "gn:feature_class":"P",
    "gn:feature_code":"PPL",
    "gn:name":"Faxinal de Santo Ant\u00f4nio",
    "gn:population":0,
    "gn:timezone":"America/Sao_Paulo",
    "iso:country":"BR",
    "wof:name":"Faxinal de Santo Antonio",
    "wof:placetype":"locality"
},
  "geometry": {"coordinates":[-51.28333,-24.71667],"type":"Point"}
}