{
  "type": "Feature",
  "properties": {
    "gn:admin1_code":"18",
    "gn:admin2_code":"4121208.0",
    "gn:asciiname":"Sitio Leonardo Borene",
    "gn:country_code":"BR",
    "gn:dem":816,
    "gn:feature_class":"P",
    "gn:feature_code":"PPL",
    "gn:name":"S\u00edtio Leonardo Borene",
    "gn:population":0,
    "gn:timezone":"America/Sao_Paulo",
    "iso:country":"BR",
    "name:por_x_preferred":[
        "S\u00edtio Leonardo Borene"
    ],
    "wof:name":"Sitio Leonardo Borene",
    "wof:placetype":"locality"
},
  "geometry": {"coordinates":[-49.55056,-25.91472000000001],"type":"Point"}
}