{
  "type": "Feature",
  "properties": {
    "gn:admin1_code":"13",
    "gn:admin2_code":"2106409.0",
    "gn:asciiname":"Pachequinho",
    "gn:country_code":"BR",
    "gn:dem":56,
    "gn:feature_class":"P",
    "gn:feature_code":"PPL",
    "gn:name":"Pachequinho",
    "gn:population":0,
    "gn:timezone":"America/Fortaleza",
    "iso:country":"BR",
    "name:deu_x_preferred":[
        "Pachequinho"
    ],
    "name:por_x_preferred":[
        "Pachequinho"
    ],
    "name:tgk_x_preferred":[
        "\u041f\u0430\u043a\u0435\u043a\u0438\u043d\u044e"
    ],
    "wof:name":"Pachequinho",
    "wof:placetype":"locality"
},
  "geometry": {"coordinates":[-43.22556,-3.52944],"type":"Point"}
}