{
  "type": "Feature",
  "properties": {
    "gn:admin1_code":"14",
    "gn:admin2_code":"5106505.0",
    "gn:asciiname":"Sitio",
    "gn:country_code":"BR",
    "gn:dem":132,
    "gn:feature_class":"P",
    "gn:feature_code":"PPL",
    "gn:name":"S\u00edtio",
    "gn:population":0,
    "gn:timezone":"America/Cuiaba",
    "iso:country":"BR",
    "name:deu_x_preferred":[
        "Sitio"
    ],
    "name:ilo_x_preferred":[
        "Sitio"
    ],
    "wof:name":"Sitio",
    "wof:placetype":"locality"
},
  "geometry": {"coordinates":[-56.53833,-16.62472],"type":"Point"}
}