{
  "type": "Feature",
  "properties": {
    "gn:admin1_code":"13",
    "gn:admin2_code":"2101400.0",
    "gn:asciiname":"Falha",
    "gn:country_code":"BR",
    "gn:dem":516,
    "gn:feature_class":"P",
    "gn:feature_code":"PPL",
    "gn:name":"Falha",
    "gn:population":0,
    "gn:timezone":"America/Fortaleza",
    "iso:country":"BR",
    "wof:name":"Falha",
    "wof:placetype":"locality"
},
  "geometry": {"coordinates":[-46.80139000000001,-9.28333],"type":"Point"}
}