{
  "type": "Feature",
  "properties": {
    "gn:admin1_code":"18",
    "gn:admin2_code":"4128609.0",
    "gn:asciiname":"Barra do Santana",
    "gn:cc2":"BR",
    "gn:country_code":"BR",
    "gn:dem":504,
    "gn:feature_class":"P",
    "gn:feature_code":"PPL",
    "gn:name":"Barra do Santana",
    "gn:population":0,
    "gn:timezone":"America/Sao_Paulo",
    "iso:country":"BR",
    "name:und_x_variant":[
        "Barra de Santana",
        "Barra do Santana"
    ],
    "wof:name":"Barra do Santana",
    "wof:placetype":"locality"
},
  "geometry": {"coordinates":[-52.86666999999999,-25.91667],"type":"Point"}
}