{
  "type": "Feature",
  "properties": {
    "gn:admin1_code":"23",
    "gn:admin2_code":"4305108.0",
    "gn:asciiname":"Carapai",
    "gn:country_code":"BR",
    "gn:dem":603,
    "gn:feature_class":"P",
    "gn:feature_code":"PPLL",
    "gn:name":"Carapai",
    "gn:population":0,
    "gn:timezone":"America/Sao_Paulo",
    "iso:country":"BR",
    "name:por_x_preferred":[
        "Carapai"
    ],
    "wof:name":"Carapai",
    "wof:placetype":"locality"
},
  "geometry": {"coordinates":[-51.0449,-29.1751],"type":"Point"}
}