{
  "type": "Feature",
  "properties": {
    "gn:admin1_code":"15",
    "gn:admin2_code":"3125507.0",
    "gn:asciiname":"Felisberto Caldeira",
    "gn:country_code":"BR",
    "gn:dem":747,
    "gn:feature_class":"P",
    "gn:feature_code":"PPL",
    "gn:name":"Felisberto Caldeira",
    "gn:population":0,
    "gn:timezone":"America/Sao_Paulo",
    "iso:country":"BR",
    "name:und_x_variant":[
        "Felisberto Caldeiro",
        "Felisberto Caldeira"
    ],
    "wof:name":"Felisberto Caldeira",
    "wof:placetype":"locality"
},
  "geometry": {"coordinates":[-43.38046,-18.00098999999999],"type":"Point"}
}