{
  "type": "Feature",
  "properties": {
    "gn:admin1_code":"18.0",
    "gn:admin2_code":"4126603.0",
    "gn:asciiname":"Sitio Lazinho",
    "gn:country_code":"BR",
    "gn:dem":779,
    "gn:feature_class":"P",
    "gn:feature_code":"PPL",
    "gn:name":"S\u00edtio Lazinho",
    "gn:population":0,
    "gn:timezone":"America/Sao_Paulo",
    "iso:country":"BR",
    "name:por_x_preferred":[
        "S\u00edtio Lazinho"
    ],
    "wof:name":"Sitio Lazinho",
    "wof:placetype":"locality"
},
  "geometry": {"coordinates":[-49.8704,-23.6393],"type":"Point"}
}