{
  "type": "Feature",
  "properties": {
    "gn:admin1_code":"06",
    "gn:admin2_code":"2312205.0",
    "gn:asciiname":"Inta",
    "gn:country_code":"BR",
    "gn:dem":173,
    "gn:feature_class":"P",
    "gn:feature_code":"PPL",
    "gn:name":"Int\u00e3",
    "gn:population":0,
    "gn:timezone":"America/Fortaleza",
    "iso:country":"BR",
    "name:ara_x_preferred":[
        "\u0625\u0646\u062a\u0627"
    ],
    "name:azb_x_preferred":[
        "\u0627\u06cc\u0646\u062a\u0627"
    ],
    "name:aze_x_preferred":[
        "\u0130nta"
    ],
    "name:bel_x_preferred":[
        "\u0406\u043d\u0442\u0430"
    ],
    "name:ben_x_preferred":[
        "\u0987\u09a8\u09cd\u09a4\u09be"
    ],
    "name:bul_x_preferred":[
        "\u0418\u043d\u0442\u0430"
    ],
    "name:cat_x_preferred":[
        "Int\u00e0"
    ],
    "name:ceb_x_preferred":[
        "Inta"
    ],
    "name:ces_x_preferred":[
        "Inta"
    ],
    "name:deu_x_preferred":[
        "Inta"
    ],
    "name:diq_x_preferred":[
        "Inta"
    ],
    "name:ell_x_preferred":[
        "\u038a\u03bd\u03c4\u03b1"
    ],
    "name:epo_x_preferred":[
        "Inta"
    ],
    "name:est_x_preferred":[
        "Inta"
    ],
    "name:eus_x_preferred":[
        "Inta"
    ],
    "name:fas_x_preferred":[
        "\u0627\u06cc\u0646\u062a\u0627"
    ],
    "name:fin_x_preferred":[
        "Inta"
    ],
    "name:fra_x_preferred":[
        "Inta"
    ],
    "name:heb_x_preferred":[
        "\u05d0\u05d9\u05e0\u05d8\u05d4"
    ],
    "name:hin_x_preferred":[
        "\u0907\u0902\u091f\u093e"
    ],
    "name:hsb_x_preferred":[
        "Inta"
    ],
    "name:hun_x_preferred":[
        "Inta"
    ],
    "name:ind_x_preferred":[
        "Inta"
    ],
    "name:ita_x_preferred":[
        "Inta"
    ],
    "name:koi_x_preferred":[
        "\u0418\u043d\u0442\u0430 \u043a\u0430\u0440\u043a\u044b\u0442\u0448"
    ],
    "name:kom_x_preferred":[
        "\u0418\u043d\u0442\u0430"
    ],
    "name:lav_x_preferred":[
        "Inta"
    ],
    "name:lit_x_preferred":[
        "Inta"
    ],
    "name:myv_x_preferred":[
        "\u0418\u043d\u0442\u0430 \u043e\u0448"
    ],
    "name:nld_x_preferred":[
        "Inta"
    ],
    "name:nno_x_preferred":[
        "Inta"
    ],
    "name:nor_x_preferred":[
        "Inta"
    ],
    "name:pol_x_preferred":[
        "Inta"
    ],
    "name:rus_x_preferred":[
        "\u0418\u043d\u0442\u0430"
    ],
    "name:sco_x_preferred":[
        "Inta"
    ],
    "name:spa_x_preferred":[
        "Int\u00e1"
    ],
    "name:srp_x_preferred":[
        "\u0418\u043d\u0442\u0430"
    ],
    "name:tat_x_preferred":[
        "\u0418\u043d\u0442\u0430"
    ],
    "name:tgk_x_preferred":[
        "\u0418\u043d\u0442\u0430"
    ],
    "name:tgl_x_preferred":[
        "Inta"
    ],
    "name:tur_x_preferred":[
        "\u0130nta"
    ],
    "name:ukr_x_preferred":[
        "\u0406\u043d\u0442\u0430"
    ],
    "name:urd_x_preferred":[
        "\u0627\u0646\u0679\u0627"
    ],
    "name:vep_x_preferred":[
        "Int"
    ],
    "name:vie_x_preferred":[
        "Inta"
    ],
    "name:war_x_preferred":[
        "Inta"
    ],
    "name:xal_x_preferred":[
        "\u0418\u043d\u0442\u0430 \u0431\u0430\u043b\u04bb\u0441\u043d"
    ],
    "wof:name":"Inta",
    "wof:placetype":"locality"
},
  "geometry": {"coordinates":[-40.18333,-4.01667],"type":"Point"}
}