{
  "type": "Feature",
  "properties": {
    "gn:admin1_code":"06",
    "gn:admin2_code":"2305605.0",
    "gn:asciiname":"Joaninha",
    "gn:country_code":"BR",
    "gn:dem":510,
    "gn:feature_class":"P",
    "gn:feature_code":"PPL",
    "gn:name":"Joaninha",
    "gn:population":0,
    "gn:timezone":"America/Fortaleza",
    "iso:country":"BR",
    "wof:name":"Joaninha",
    "wof:placetype":"locality"
},
  "geometry": {"coordinates":[-40.43352,-5.82297],"type":"Point"}
}