{
  "type": "Feature",
  "properties": {
    "gn:admin1_code":"4",
    "gn:admin2_code":"1303700.0",
    "gn:asciiname":"Visconde do Rio Branco",
    "gn:country_code":"BR",
    "gn:dem":81,
    "gn:feature_class":"P",
    "gn:feature_code":"PPL",
    "gn:name":"Visconde do Rio Branco",
    "gn:population":0,
    "gn:timezone":"America/Manaus",
    "iso:country":"BR",
    "wof:name":"Visconde do Rio Branco",
    "wof:placetype":"locality"
},
  "geometry": {"coordinates":[-69.65772,-2.86372],"type":"Point"}
}