{
  "type": "Feature",
  "properties": {
    "gn:admin1_code":"1",
    "gn:admin2_code":"1200609.0",
    "gn:asciiname":"Sete Estrelas",
    "gn:cc2":"BR",
    "gn:country_code":"BR",
    "gn:dem":304,
    "gn:feature_class":"P",
    "gn:feature_code":"PPL",
    "gn:name":"Sete Estr\u00ealas",
    "gn:population":0,
    "gn:timezone":"America/Rio_Branco",
    "iso:country":"BR",
    "name:und_x_variant":[
        "Estrellas",
        "Sete Estr\u00ealas"
    ],
    "wof:name":"Sete Estrelas",
    "wof:placetype":"locality"
},
  "geometry": {"coordinates":[-71.68333,-8.45],"type":"Point"}
}