{
  "type": "Feature",
  "properties": {
    "gn:admin1_code":"18",
    "gn:admin2_code":"4121208.0",
    "gn:asciiname":"Sitio Joao B. Cordeiro",
    "gn:country_code":"BR",
    "gn:dem":854,
    "gn:feature_class":"P",
    "gn:feature_code":"PPL",
    "gn:name":"S\u00edtio Jo\u00e3o B. Cordeiro",
    "gn:population":0,
    "gn:timezone":"America/Sao_Paulo",
    "iso:country":"BR",
    "name:por_x_preferred":[
        "S\u00edtio Jo\u00e3o B. Cordeiro"
    ],
    "wof:name":"Sitio Joao B. Cordeiro",
    "wof:placetype":"locality"
},
  "geometry": {"coordinates":[-49.51222,-25.97917],"type":"Point"}
}