{
  "type": "Feature",
  "properties": {
    "gn:admin1_code":"13",
    "gn:admin2_code":"2110237.0",
    "gn:asciiname":"Salvacao",
    "gn:country_code":"BR",
    "gn:dem":75,
    "gn:feature_class":"P",
    "gn:feature_code":"PPL",
    "gn:name":"Salva\u00e7\u00e3o",
    "gn:population":0,
    "gn:timezone":"America/Fortaleza",
    "iso:country":"BR",
    "wof:name":"Salvacao",
    "wof:placetype":"locality"
},
  "geometry": {"coordinates":[-42.68472,-3.25722],"type":"Point"}
}