{
  "type": "Feature",
  "properties": {
    "gn:admin1_code":"1",
    "gn:admin2_code":"1200351.0",
    "gn:asciiname":"Boca do Arara",
    "gn:country_code":"BR",
    "gn:dem":215,
    "gn:feature_class":"P",
    "gn:feature_code":"PPL",
    "gn:name":"Boca do Arar\u00e1",
    "gn:population":0,
    "gn:timezone":"America/Rio_Branco",
    "iso:country":"BR",
    "wof:name":"Boca do Arara",
    "wof:placetype":"locality"
},
  "geometry": {"coordinates":[-72.76167,-8.945],"type":"Point"}
}