{
  "type": "Feature",
  "properties": {
    "gn:admin1_code":"20",
    "gn:admin2_code":"2203701.0",
    "gn:asciiname":"Aroeiras",
    "gn:country_code":"BR",
    "gn:dem":49,
    "gn:feature_class":"P",
    "gn:feature_code":"PPL",
    "gn:name":"Aroeiras",
    "gn:population":0,
    "gn:timezone":"America/Fortaleza",
    "iso:country":"BR",
    "wof:name":"Aroeiras",
    "wof:placetype":"locality"
},
  "geometry": {"coordinates":[-42.03,-3.81694],"type":"Point"}
}