{
  "type": "Feature",
  "properties": {
    "gn:admin1_code":"18.0",
    "gn:admin2_code":"4126207.0",
    "gn:asciiname":"Sitio Pedro Jardim",
    "gn:country_code":"BR",
    "gn:dem":594,
    "gn:feature_class":"P",
    "gn:feature_code":"PPL",
    "gn:name":"S\u00edtio Pedro Jardim",
    "gn:population":0,
    "gn:timezone":"America/Sao_Paulo",
    "iso:country":"BR",
    "name:por_x_preferred":[
        "S\u00edtio Pedro Jardim"
    ],
    "wof:name":"Sitio Pedro Jardim",
    "wof:placetype":"locality"
},
  "geometry": {"coordinates":[-50.51044,-23.84603],"type":"Point"}
}