{
  "type": "Feature",
  "properties": {
    "gn:admin1_code":"27",
    "gn:admin2_code":"3548609.0",
    "gn:asciiname":"Paiol Velho",
    "gn:country_code":"BR",
    "gn:dem":1288,
    "gn:feature_class":"P",
    "gn:feature_code":"PPLL",
    "gn:name":"Paiol Velho",
    "gn:population":0,
    "gn:timezone":"America/Sao_Paulo",
    "iso:country":"BR",
    "name:por_x_preferred":[
        "Paiol Velho"
    ],
    "wof:name":"Paiol Velho",
    "wof:placetype":"locality"
},
  "geometry": {"coordinates":[-45.6766,-22.7462],"type":"Point"}
}