{
  "type": "Feature",
  "properties": {
    "gn:admin1_code":"13",
    "gn:admin2_code":"2106409.0",
    "gn:asciiname":"Barroca",
    "gn:country_code":"BR",
    "gn:dem":101,
    "gn:feature_class":"P",
    "gn:feature_code":"PPL",
    "gn:name":"Barroca",
    "gn:population":0,
    "gn:timezone":"America/Fortaleza",
    "iso:country":"BR",
    "name:ara_x_preferred":[
        "\u0628\u0627\u0631\u0648\u0643\u0627"
    ],
    "name:deu_x_preferred":[
        "Barroca"
    ],
    "name:hun_x_preferred":[
        "Barroca"
    ],
    "name:spa_x_preferred":[
        "Jo\u00e3o Barroca"
    ],
    "name:vie_x_preferred":[
        "Barroca"
    ],
    "wof:name":"Barroca",
    "wof:placetype":"locality"
},
  "geometry": {"coordinates":[-43.18861,-3.71278],"type":"Point"}
}