{
  "type": "Feature",
  "properties": {
    "gn:admin1_code":"27",
    "gn:admin2_code":"3509601.0",
    "gn:asciiname":"Sitio Sabia",
    "gn:country_code":"BR",
    "gn:dem":810,
    "gn:feature_class":"P",
    "gn:feature_code":"PPL",
    "gn:name":"S\u00edtio Sabi\u00e1",
    "gn:population":0,
    "gn:timezone":"America/Sao_Paulo",
    "iso:country":"BR",
    "name:por_x_preferred":[
        "S\u00edtio Sabi\u00e1"
    ],
    "wof:name":"Sitio Sabia",
    "wof:placetype":"locality"
},
  "geometry": {"coordinates":[-46.73944,-23.21583],"type":"Point"}
}