{
  "type": "Feature",
  "properties": {
    "gn:admin1_code":"18",
    "gn:admin2_code":"4122305.0",
    "gn:asciiname":"Sitio Odinir Pinheiro",
    "gn:country_code":"BR",
    "gn:dem":837,
    "gn:feature_class":"P",
    "gn:feature_code":"PPL",
    "gn:name":"S\u00edtio Odinir Pinheiro",
    "gn:population":0,
    "gn:timezone":"America/Sao_Paulo",
    "iso:country":"BR",
    "name:por_x_preferred":[
        "S\u00edtio Odinir Pinheiro"
    ],
    "wof:name":"Sitio Odinir Pinheiro",
    "wof:placetype":"locality"
},
  "geometry": {"coordinates":[-49.72858,-26.0932],"type":"Point"}
}