{
  "type": "Feature",
  "properties": {
    "gn:admin1_code":"18.0",
    "gn:admin2_code":"4124707.0",
    "gn:asciiname":"Sitio Paulo Quadros",
    "gn:country_code":"BR",
    "gn:dem":679,
    "gn:feature_class":"P",
    "gn:feature_code":"PPL",
    "gn:name":"S\u00edtio Paulo Quadros",
    "gn:population":0,
    "gn:timezone":"America/Sao_Paulo",
    "iso:country":"BR",
    "name:por_x_preferred":[
        "S\u00edtio Paulo Quadros"
    ],
    "wof:name":"Sitio Paulo Quadros",
    "wof:placetype":"locality"
},
  "geometry": {"coordinates":[-50.72488,-23.61839],"type":"Point"}
}