{
  "type": "Feature",
  "properties": {
    "gn:admin1_code":"27",
    "gn:admin2_code":"3504107.0",
    "gn:asciiname":"Sitio Alvo e Negro",
    "gn:country_code":"BR",
    "gn:dem":968,
    "gn:feature_class":"P",
    "gn:feature_code":"PPL",
    "gn:name":"S\u00edtio Alvo e Negro",
    "gn:population":0,
    "gn:timezone":"America/Sao_Paulo",
    "iso:country":"BR",
    "name:por_x_preferred":[
        "S\u00edtio Alvo e Negro"
    ],
    "wof:name":"Sitio Alvo e Negro",
    "wof:placetype":"locality"
},
  "geometry": {"coordinates":[-46.555,-23.21667],"type":"Point"}
}