{
  "type": "Feature",
  "properties": {
    "gn:admin1_code":"27.0",
    "gn:admin2_code":"3528502.0",
    "gn:asciiname":"Sitio Matao",
    "gn:country_code":"BR",
    "gn:dem":971,
    "gn:feature_class":"P",
    "gn:feature_code":"PPL",
    "gn:name":"S\u00edtio Mat\u00e3o",
    "gn:population":0,
    "gn:timezone":"America/Sao_Paulo",
    "iso:country":"BR",
    "name:por_x_preferred":[
        "S\u00edtio Mat\u00e3o"
    ],
    "wof:name":"Sitio Matao",
    "wof:placetype":"locality"
},
  "geometry": {"coordinates":[-46.57546,-23.25407],"type":"Point"}
}