{
  "type": "Feature",
  "properties": {
    "gn:admin1_code":"06",
    "gn:admin2_code":"2302800.0",
    "gn:asciiname":"Fazenda Timbauba",
    "gn:country_code":"BR",
    "gn:dem":161,
    "gn:feature_class":"P",
    "gn:feature_code":"PPL",
    "gn:name":"Fazenda Timba\u00faba",
    "gn:population":0,
    "gn:timezone":"America/Fortaleza",
    "iso:country":"BR",
    "wof:name":"Fazenda Timbauba",
    "wof:placetype":"locality"
},
  "geometry": {"coordinates":[-39.56667,-4.15],"type":"Point"}
}