{
  "type": "Feature",
  "properties": {
    "gn:admin1_code":"17",
    "gn:admin2_code":"2510501.0",
    "gn:asciiname":"Palestina",
    "gn:country_code":"BR",
    "gn:dem":550,
    "gn:feature_class":"P",
    "gn:feature_code":"PPL",
    "gn:name":"Palestina",
    "gn:population":0,
    "gn:timezone":"America/Fortaleza",
    "iso:country":"BR",
    "wof:name":"Palestina",
    "wof:placetype":"locality"
},
  "geometry": {"coordinates":[-36.26667,-7.08333],"type":"Point"}
}