{
  "type": "Feature",
  "properties": {
    "gn:admin1_code":"18.0",
    "gn:admin2_code":"4121208.0",
    "gn:asciiname":"Sitio Benvindo Filla",
    "gn:country_code":"BR",
    "gn:dem":921,
    "gn:feature_class":"P",
    "gn:feature_code":"PPL",
    "gn:name":"S\u00edtio Benvindo Filla",
    "gn:population":0,
    "gn:timezone":"America/Sao_Paulo",
    "iso:country":"BR",
    "name:por_x_preferred":[
        "S\u00edtio Benvindo Filla"
    ],
    "wof:name":"Sitio Benvindo Filla",
    "wof:placetype":"locality"
},
  "geometry": {"coordinates":[-49.42529,-25.81521],"type":"Point"}
}