{
  "type": "Feature",
  "properties": {
    "gn:admin1_code":"18.0",
    "gn:admin2_code":"4124707.0",
    "gn:asciiname":"Sitio Oswaldo Romulo",
    "gn:country_code":"BR",
    "gn:dem":872,
    "gn:feature_class":"P",
    "gn:feature_code":"PPL",
    "gn:name":"S\u00edtio Oswaldo R\u00f4mulo",
    "gn:population":0,
    "gn:timezone":"America/Sao_Paulo",
    "iso:country":"BR",
    "name:por_x_preferred":[
        "S\u00edtio Oswaldo R\u00f4mulo"
    ],
    "wof:name":"Sitio Oswaldo Romulo",
    "wof:placetype":"locality"
},
  "geometry": {"coordinates":[-50.58625,-23.72178],"type":"Point"}
}