{
  "type": "Feature",
  "properties": {
    "gn:admin1_code":"22",
    "gn:admin2_code":"2401305.0",
    "gn:asciiname":"Uruguaina",
    "gn:country_code":"BR",
    "gn:dem":156,
    "gn:feature_class":"P",
    "gn:feature_code":"PPL",
    "gn:name":"Uruguaina",
    "gn:population":0,
    "gn:timezone":"America/Fortaleza",
    "iso:country":"BR",
    "wof:name":"Uruguaina",
    "wof:placetype":"locality"
},
  "geometry": {"coordinates":[-37.44028,-5.81222],"type":"Point"}
}