{
  "type": "Feature",
  "properties": {
    "gn:admin1_code":"22",
    "gn:admin2_code":"2406700.0",
    "gn:asciiname":"Bonfim",
    "gn:country_code":"BR",
    "gn:dem":283,
    "gn:feature_class":"P",
    "gn:feature_code":"PPL",
    "gn:name":"Bonfim",
    "gn:population":0,
    "gn:timezone":"America/Fortaleza",
    "iso:country":"BR",
    "wof:name":"Bonfim",
    "wof:placetype":"locality"
},
  "geometry": {"coordinates":[-36.11944,-5.82139],"type":"Point"}
}