{
  "type": "Feature",
  "properties": {
    "gn:admin1_code":"18.0",
    "gn:admin2_code":"4109609.0",
    "gn:asciiname":"Ribeirao Grande",
    "gn:country_code":"BR",
    "gn:dem":15,
    "gn:feature_class":"P",
    "gn:feature_code":"PPL",
    "gn:name":"Ribeir\u00e3o Grande",
    "gn:population":0,
    "gn:timezone":"America/Sao_Paulo",
    "iso:country":"BR",
    "name:por_x_preferred":[
        "Ribeir\u00e3o Grande"
    ],
    "wof:name":"Ribeirao Grande",
    "wof:placetype":"locality"
},
  "geometry": {"coordinates":[-48.7613,-25.707],"type":"Point"}
}