{
  "type": "Feature",
  "properties": {
    "gn:admin1_code":"18.0",
    "gn:admin2_code":"4127809.0",
    "gn:asciiname":"Sitio Jose A. Teixeira",
    "gn:country_code":"BR",
    "gn:dem":483,
    "gn:feature_class":"P",
    "gn:feature_code":"PPL",
    "gn:name":"S\u00edtio Jos\u00e9 A. Teixeira",
    "gn:population":0,
    "gn:timezone":"America/Sao_Paulo",
    "iso:country":"BR",
    "name:por_x_preferred":[
        "S\u00edtio Jos\u00e9 A. Teixeira"
    ],
    "wof:name":"Sitio Jose A. Teixeira",
    "wof:placetype":"locality"
},
  "geometry": {"coordinates":[-49.9352,-23.7446],"type":"Point"}
}