{
  "type": "Feature",
  "properties": {
    "gn:admin1_code":"30",
    "gn:admin2_code":"2609907.0",
    "gn:asciiname":"Sitio Solta",
    "gn:country_code":"BR",
    "gn:dem":443,
    "gn:feature_class":"P",
    "gn:feature_code":"PPL",
    "gn:name":"S\u00edtio Solta",
    "gn:population":0,
    "gn:timezone":"America/Recife",
    "iso:country":"BR",
    "wof:name":"Sitio Solta",
    "wof:placetype":"locality"
},
  "geometry": {"coordinates":[-40.05,-7.91667],"type":"Point"}
}