{
  "type": "Feature",
  "properties": {
    "gn:admin1_code":"27",
    "gn:admin2_code":"3540606.0",
    "gn:asciiname":"Bairro da Ponte",
    "gn:country_code":"BR",
    "gn:dem":502,
    "gn:feature_class":"P",
    "gn:feature_code":"PPL",
    "gn:name":"Bairro da Ponte",
    "gn:population":0,
    "gn:timezone":"America/Sao_Paulo",
    "iso:country":"BR",
    "name:por_x_preferred":[
        "Bairro da Ponte"
    ],
    "wof:name":"Bairro da Ponte",
    "wof:placetype":"locality"
},
  "geometry": {"coordinates":[-47.53391,-23.19073],"type":"Point"}
}