{
  "type": "Feature",
  "properties": {
    "gn:admin1_code":"18.0",
    "gn:admin2_code":"4124707.0",
    "gn:asciiname":"Sitio Tabuao",
    "gn:country_code":"BR",
    "gn:dem":930,
    "gn:feature_class":"P",
    "gn:feature_code":"PPL",
    "gn:name":"S\u00edtio Tabu\u00e1o",
    "gn:population":0,
    "gn:timezone":"America/Sao_Paulo",
    "iso:country":"BR",
    "name:por_x_preferred":[
        "S\u00edtio Tabu\u00e1o"
    ],
    "wof:name":"Sitio Tabuao",
    "wof:placetype":"locality"
},
  "geometry": {"coordinates":[-50.67362,-23.71465],"type":"Point"}
}