{
  "type": "Feature",
  "properties": {
    "gn:admin1_code":"13",
    "gn:admin2_code":"2106409.0",
    "gn:asciiname":"Tataira",
    "gn:country_code":"BR",
    "gn:dem":67,
    "gn:feature_class":"P",
    "gn:feature_code":"PPL",
    "gn:name":"Tata\u00edra",
    "gn:population":0,
    "gn:timezone":"America/Fortaleza",
    "iso:country":"BR",
    "wof:name":"Tataira",
    "wof:placetype":"locality"
},
  "geometry": {"coordinates":[-43.18972,-3.55417],"type":"Point"}
}