{
  "type": "Feature",
  "properties": {
    "gn:admin1_code":"06",
    "gn:admin2_code":"2311009.0",
    "gn:asciiname":"Carnauba",
    "gn:country_code":"BR",
    "gn:dem":546,
    "gn:feature_class":"P",
    "gn:feature_code":"PPL",
    "gn:name":"Carna\u00faba",
    "gn:population":0,
    "gn:timezone":"America/Fortaleza",
    "iso:country":"BR",
    "wof:name":"Carnauba",
    "wof:placetype":"locality"
},
  "geometry": {"coordinates":[-41.01667,-4.85],"type":"Point"}
}