{
  "type": "Feature",
  "properties": {
    "gn:admin1_code":"18.0",
    "gn:admin2_code":"4107009.0",
    "gn:asciiname":"Serra do Caete",
    "gn:country_code":"BR",
    "gn:dem":783,
    "gn:feature_class":"P",
    "gn:feature_code":"PPL",
    "gn:name":"Serra do Caet\u00ea",
    "gn:population":0,
    "gn:timezone":"America/Sao_Paulo",
    "iso:country":"BR",
    "name:por_x_preferred":[
        "Serra do Caet\u00ea"
    ],
    "wof:name":"Serra do Caete",
    "wof:placetype":"locality"
},
  "geometry": {"coordinates":[-50.44852,-23.98113],"type":"Point"}
}