{
  "type": "Feature",
  "properties": {
    "gn:admin1_code":"18",
    "gn:admin2_code":"4119103.0",
    "gn:asciiname":"Sitio Alfredo Zappe",
    "gn:country_code":"BR",
    "gn:dem":844,
    "gn:feature_class":"P",
    "gn:feature_code":"PPL",
    "gn:name":"S\u00edtio Alfredo Zappe",
    "gn:population":0,
    "gn:timezone":"America/Sao_Paulo",
    "iso:country":"BR",
    "name:por_x_preferred":[
        "S\u00edtio Alfredo Zappe"
    ],
    "wof:name":"Sitio Alfredo Zappe",
    "wof:placetype":"locality"
},
  "geometry": {"coordinates":[-49.3668,-26.1199],"type":"Point"}
}