{
  "type": "Feature",
  "properties": {
    "gn:admin1_code":"17",
    "gn:admin2_code":"2516300.0",
    "gn:asciiname":"Amparinho",
    "gn:country_code":"BR",
    "gn:dem":557,
    "gn:feature_class":"P",
    "gn:feature_code":"PPL",
    "gn:name":"Amparinho",
    "gn:population":0,
    "gn:timezone":"America/Fortaleza",
    "iso:country":"BR",
    "wof:name":"Amparinho",
    "wof:placetype":"locality"
},
  "geometry": {"coordinates":[-37.01667,-7.65],"type":"Point"}
}