{
  "type": "Feature",
  "properties": {
    "gn:admin1_code":"18",
    "gn:admin2_code":"4102604.0",
    "gn:asciiname":"Sao Paulo I",
    "gn:country_code":"BR",
    "gn:dem":713,
    "gn:feature_class":"P",
    "gn:feature_code":"PPL",
    "gn:name":"S\u00e3o Paulo I",
    "gn:population":0,
    "gn:timezone":"America/Sao_Paulo",
    "iso:country":"BR",
    "wof:name":"Sao Paulo I",
    "wof:placetype":"locality"
},
  "geometry": {"coordinates":[-53.64111,-26.22583],"type":"Point"}
}