{
  "type": "Feature",
  "properties": {
    "gn:admin1_code":"11",
    "gn:admin2_code":"5002803.0",
    "gn:asciiname":"Alegria",
    "gn:country_code":"BR",
    "gn:dem":220,
    "gn:feature_class":"P",
    "gn:feature_code":"PPL",
    "gn:name":"Alegria",
    "gn:population":0,
    "gn:timezone":"America/Campo_Grande",
    "iso:country":"BR",
    "name:bul_x_preferred":[
        "\u0410\u043b\u0435\u0433\u0440\u0438\u044f"
    ],
    "name:ceb_x_preferred":[
        "Alegria"
    ],
    "name:ita_x_preferred":[
        "Alegria"
    ],
    "name:nld_x_preferred":[
        "Alegria"
    ],
    "name:por_x_preferred":[
        "Alegria"
    ],
    "name:rus_x_preferred":[
        "\u0410\u043b\u0435\u0433\u0440\u0438\u044f"
    ],
    "name:scn_x_preferred":[
        "Alligrizza"
    ],
    "name:swe_x_preferred":[
        "Alegria"
    ],
    "name:war_x_preferred":[
        "Alegria"
    ],
    "wof:name":"Alegria",
    "wof:placetype":"locality"
},
  "geometry": {"coordinates":[-57.11666999999999,-21.95],"type":"Point"}
}