{
  "type": "Feature",
  "properties": {
    "gn:admin1_code":"13",
    "gn:admin2_code":"2110609.0",
    "gn:asciiname":"Anajazinho",
    "gn:country_code":"BR",
    "gn:dem":39,
    "gn:feature_class":"P",
    "gn:feature_code":"PPL",
    "gn:name":"Anajazinho",
    "gn:population":0,
    "gn:timezone":"America/Fortaleza",
    "iso:country":"BR",
    "wof:name":"Anajazinho",
    "wof:placetype":"locality"
},
  "geometry": {"coordinates":[-42.50306,-3.37167],"type":"Point"}
}