{
  "type": "Feature",
  "properties": {
    "gn:admin1_code":"13",
    "gn:admin2_code":"2100154.0",
    "gn:asciiname":"Gaviao",
    "gn:country_code":"BR",
    "gn:dem":23,
    "gn:feature_class":"P",
    "gn:feature_code":"PPL",
    "gn:name":"Gavi\u00e3o",
    "gn:population":0,
    "gn:timezone":"America/Fortaleza",
    "iso:country":"BR",
    "wof:name":"Gaviao",
    "wof:placetype":"locality"
},
  "geometry": {"coordinates":[-42.28722,-3.08083],"type":"Point"}
}