{
  "type": "Feature",
  "properties": {
    "gn:admin1_code":"18",
    "gn:admin2_code":"4127601.0",
    "gn:asciiname":"Sitio Francisco I. Pereira",
    "gn:country_code":"BR",
    "gn:dem":916,
    "gn:feature_class":"P",
    "gn:feature_code":"PPL",
    "gn:name":"S\u00edtio Francisco I. Pereira",
    "gn:population":0,
    "gn:timezone":"America/Sao_Paulo",
    "iso:country":"BR",
    "name:por_x_preferred":[
        "S\u00edtio Francisco I. Pereira"
    ],
    "wof:name":"Sitio Francisco I. Pereira",
    "wof:placetype":"locality"
},
  "geometry": {"coordinates":[-49.2113,-25.9441],"type":"Point"}
}