{
  "type": "Feature",
  "properties": {
    "gn:admin1_code":"18.0",
    "gn:admin2_code":"4101606.0",
    "gn:asciiname":"Sitio Orlando Jorge",
    "gn:country_code":"BR",
    "gn:dem":807,
    "gn:feature_class":"P",
    "gn:feature_code":"PPL",
    "gn:name":"S\u00edtio Orlando Jorge",
    "gn:population":0,
    "gn:timezone":"America/Sao_Paulo",
    "iso:country":"BR",
    "name:por_x_preferred":[
        "S\u00edtio Orlando Jorge"
    ],
    "wof:name":"Sitio Orlando Jorge",
    "wof:placetype":"locality"
},
  "geometry": {"coordinates":[-50.15109,-23.97224],"type":"Point"}
}