{
  "type": "Feature",
  "properties": {
    "gn:admin1_code":"27.0",
    "gn:admin2_code":"3509007.0",
    "gn:asciiname":"Horto Florestal",
    "gn:country_code":"BR",
    "gn:dem":953,
    "gn:feature_class":"P",
    "gn:feature_code":"PPLL",
    "gn:name":"Horto Florestal",
    "gn:population":0,
    "gn:timezone":"America/Sao_Paulo",
    "iso:country":"BR",
    "name:por_x_preferred":[
        "Horto Florestal"
    ],
    "wof:name":"Horto Florestal",
    "wof:placetype":"locality"
},
  "geometry": {"coordinates":[-46.67979,-23.40948],"type":"Point"}
}