{
  "type": "Feature",
  "properties": {
    "gn:admin1_code":"18.0",
    "gn:admin2_code":"4121802.0",
    "gn:asciiname":"Sitio Domingues E. Ferreira",
    "gn:country_code":"BR",
    "gn:dem":549,
    "gn:feature_class":"P",
    "gn:feature_code":"PPL",
    "gn:name":"S\u00edtio Domingues E. Ferreira",
    "gn:population":0,
    "gn:timezone":"America/Sao_Paulo",
    "iso:country":"BR",
    "name:por_x_preferred":[
        "S\u00edtio Domingues E. Ferreira"
    ],
    "wof:name":"Sitio Domingues E. Ferreira",
    "wof:placetype":"locality"
},
  "geometry": {"coordinates":[-49.854,-23.3489],"type":"Point"}
}