{
  "type": "Feature",
  "properties": {
    "gn:admin1_code":"8",
    "gn:admin2_code":"3202108.0",
    "gn:asciiname":"Prata",
    "gn:country_code":"BR",
    "gn:dem":364,
    "gn:feature_class":"P",
    "gn:feature_code":"PPL",
    "gn:name":"Prata",
    "gn:population":0,
    "gn:timezone":"America/Sao_Paulo",
    "iso:country":"BR",
    "name:ceb_x_preferred":[
        "Prata"
    ],
    "name:deu_x_preferred":[
        "Prata"
    ],
    "name:fra_x_preferred":[
        "Prata"
    ],
    "name:ita_x_preferred":[
        "Prata"
    ],
    "name:lat_x_preferred":[
        "Prata"
    ],
    "name:nld_x_preferred":[
        "Prata"
    ],
    "name:nor_x_preferred":[
        "Prata"
    ],
    "name:por_x_preferred":[
        "Prata"
    ],
    "name:rus_x_preferred":[
        "\u041f\u0440\u0430\u0442\u0430"
    ],
    "name:srp_x_preferred":[
        "\u041f\u0440\u0430\u0442\u0430"
    ],
    "name:swe_x_preferred":[
        "Prata"
    ],
    "name:vie_x_preferred":[
        "Prata"
    ],
    "name:vol_x_preferred":[
        "Prata"
    ],
    "wof:name":"Prata",
    "wof:placetype":"locality"
},
  "geometry": {"coordinates":[-40.96667,-18.28333],"type":"Point"}
}