{
  "type": "Feature",
  "properties": {
    "gn:admin1_code":"8",
    "gn:admin2_code":"3202108.0",
    "gn:asciiname":"Prata",
    "gn:country_code":"BR",
    "gn:dem":364,
    "gn:feature_class":"P",
    "gn:feature_code":"PPL",
    "gn:name":"Prata",
    "gn:population":0,
    "gn:timezone":"America/Sao_Paulo",
    "iso:country":"BR",
    "name:por_x_preferred":[
        "Prata"
    ],
    "wof:name":"Prata",
    "wof:placetype":"locality"
},
  "geometry": {"coordinates":[-40.96667,-18.28333],"type":"Point"}
}