{
  "type": "Feature",
  "properties": {
    "gn:admin1_code":"26",
    "gn:admin2_code":"4210100.0",
    "gn:asciiname":"Sitio Gabriel Pillati",
    "gn:country_code":"BR",
    "gn:dem":794,
    "gn:feature_class":"P",
    "gn:feature_code":"PPL",
    "gn:name":"S\u00edtio Gabriel Pillati",
    "gn:population":0,
    "gn:timezone":"America/Sao_Paulo",
    "iso:country":"BR",
    "name:por_x_preferred":[
        "S\u00edtio Gabriel Pillati"
    ],
    "wof:name":"Sitio Gabriel Pillati",
    "wof:placetype":"locality"
},
  "geometry": {"coordinates":[-49.71976,-26.17412],"type":"Point"}
}