{
  "type": "Feature",
  "properties": {
    "gn:admin1_code":"5",
    "gn:admin2_code":"2932804.0",
    "gn:asciiname":"Lagoa dos Porcos",
    "gn:country_code":"BR",
    "gn:dem":670,
    "gn:feature_class":"P",
    "gn:feature_code":"PPL",
    "gn:name":"Lagoa dos Porcos",
    "gn:population":0,
    "gn:timezone":"America/Bahia",
    "iso:country":"BR",
    "wof:name":"Lagoa dos Porcos",
    "wof:placetype":"locality"
},
  "geometry": {"coordinates":[-40.96667,-12.01667],"type":"Point"}
}