{
  "type": "Feature",
  "properties": {
    "gn:admin1_code":"18.0",
    "gn:admin2_code":"4125100.0",
    "gn:asciiname":"Taio",
    "gn:country_code":"BR",
    "gn:dem":814,
    "gn:feature_class":"P",
    "gn:feature_code":"PPL",
    "gn:name":"Tai\u00f3",
    "gn:population":0,
    "gn:timezone":"America/Sao_Paulo",
    "iso:country":"BR",
    "name:azb_x_preferred":[
        "\u062a\u0627\u06cc\u0648"
    ],
    "name:bel_x_preferred":[
        "\u0422\u0430\u0451"
    ],
    "name:cat_x_preferred":[
        "Taio"
    ],
    "name:ceb_x_preferred":[
        "Taio"
    ],
    "name:deu_x_preferred":[
        "Taio"
    ],
    "name:epo_x_preferred":[
        "Taio"
    ],
    "name:eus_x_preferred":[
        "Taio"
    ],
    "name:fas_x_preferred":[
        "\u062a\u0627\u06cc\u0648"
    ],
    "name:fin_x_preferred":[
        "Taio"
    ],
    "name:fra_x_preferred":[
        "Taio"
    ],
    "name:hun_x_preferred":[
        "Taio"
    ],
    "name:hye_x_preferred":[
        "\u054f\u0561\u056b\u0578"
    ],
    "name:ind_x_preferred":[
        "Taio"
    ],
    "name:ita_x_preferred":[
        "Taio"
    ],
    "name:jpn_x_preferred":[
        "\u30bf\u30fc\u30a4\u30aa"
    ],
    "name:lat_x_preferred":[
        "Thaium"
    ],
    "name:lmo_x_preferred":[
        "Taio"
    ],
    "name:msa_x_preferred":[
        "Taio"
    ],
    "name:nap_x_preferred":[
        "Taio"
    ],
    "name:nld_x_preferred":[
        "Taio"
    ],
    "name:pms_x_preferred":[
        "Taio"
    ],
    "name:pol_x_preferred":[
        "Taio"
    ],
    "name:por_x_preferred":[
        "Tai\u00f3"
    ],
    "name:por_x_variant":[
        "Taio"
    ],
    "name:ron_x_preferred":[
        "Taio"
    ],
    "name:rus_x_preferred":[
        "\u0422\u0430\u0439\u043e"
    ],
    "name:scn_x_preferred":[
        "Taio"
    ],
    "name:spa_x_preferred":[
        "Taio"
    ],
    "name:srp_x_preferred":[
        "\u0422\u0430\u0458\u043e"
    ],
    "name:tgl_x_preferred":[
        "Taio"
    ],
    "name:ukr_x_preferred":[
        "\u0422\u0430\u0457\u043e"
    ],
    "name:uzb_x_preferred":[
        "Taio"
    ],
    "name:vie_x_preferred":[
        "Taio"
    ],
    "name:vol_x_preferred":[
        "Taio"
    ],
    "name:war_x_preferred":[
        "Taio"
    ],
    "name:zho_x_preferred":[
        "\u5854\u4f0a\u5965"
    ],
    "wof:name":"Taio",
    "wof:placetype":"locality"
},
  "geometry": {"coordinates":[-50.2931,-25.6294],"type":"Point"}
}