{
  "type": "Feature",
  "properties": {
    "gn:admin1_code":"18.0",
    "gn:admin2_code":"4125100.0",
    "gn:asciiname":"Taio",
    "gn:country_code":"BR",
    "gn:dem":814,
    "gn:feature_class":"P",
    "gn:feature_code":"PPL",
    "gn:name":"Tai\u00f3",
    "gn:population":0,
    "gn:timezone":"America/Sao_Paulo",
    "iso:country":"BR",
    "name:por_x_preferred":[
        "Tai\u00f3"
    ],
    "wof:name":"Taio",
    "wof:placetype":"locality"
},
  "geometry": {"coordinates":[-50.2931,-25.6294],"type":"Point"}
}