{
  "type": "Feature",
  "properties": {
    "gn:admin1_code":"27.0",
    "gn:admin2_code":"3509254.0",
    "gn:asciiname":"Bairro Manuel Gomes",
    "gn:country_code":"BR",
    "gn:dem":58,
    "gn:feature_class":"P",
    "gn:feature_code":"PPLL",
    "gn:name":"Bairro Manuel Gomes",
    "gn:population":0,
    "gn:timezone":"America/Sao_Paulo",
    "iso:country":"BR",
    "name:por_x_preferred":[
        "Bairro Manuel Gomes"
    ],
    "wof:name":"Bairro Manuel Gomes",
    "wof:placetype":"locality"
},
  "geometry": {"coordinates":[-48.17097,-24.74637],"type":"Point"}
}