{
  "type": "Feature",
  "properties": {
    "gn:admin1_code":"30",
    "gn:admin2_code":"2613008.0",
    "gn:asciiname":"Macaranduba",
    "gn:country_code":"BR",
    "gn:dem":646,
    "gn:feature_class":"P",
    "gn:feature_code":"PPL",
    "gn:name":"Ma\u00e7aranduba",
    "gn:population":0,
    "gn:timezone":"America/Recife",
    "iso:country":"BR",
    "wof:name":"Macaranduba",
    "wof:placetype":"locality"
},
  "geometry": {"coordinates":[-36.46667,-8.48333],"type":"Point"}
}