{
  "type": "Feature",
  "properties": {
    "gn:admin1_code":"22",
    "gn:admin2_code":"2401305.0",
    "gn:asciiname":"Aleixo",
    "gn:country_code":"BR",
    "gn:dem":112,
    "gn:feature_class":"P",
    "gn:feature_code":"PPL",
    "gn:name":"Aleixo",
    "gn:population":0,
    "gn:timezone":"America/Fortaleza",
    "iso:country":"BR",
    "wof:name":"Aleixo",
    "wof:placetype":"locality"
},
  "geometry": {"coordinates":[-37.34306,-5.72139],"type":"Point"}
}