{
  "type": "Feature",
  "properties": {
    "gn:admin1_code":"5",
    "gn:admin2_code":"2903805.0",
    "gn:asciiname":"Roca Velha",
    "gn:country_code":"BR",
    "gn:dem":456,
    "gn:feature_class":"P",
    "gn:feature_code":"PPL",
    "gn:name":"Ro\u00e7a Velha",
    "gn:population":0,
    "gn:timezone":"America/Bahia",
    "iso:country":"BR",
    "wof:name":"Roca Velha",
    "wof:placetype":"locality"
},
  "geometry": {"coordinates":[-40.56667,-12.48333],"type":"Point"}
}