{
  "type": "Feature",
  "properties": {
    "gn:admin1_code":"18.0",
    "gn:admin2_code":"4118006.0",
    "gn:asciiname":"Placa Dois",
    "gn:country_code":"BR",
    "gn:dem":375,
    "gn:feature_class":"P",
    "gn:feature_code":"PPLL",
    "gn:name":"Placa Dois",
    "gn:population":0,
    "gn:timezone":"America/Sao_Paulo",
    "iso:country":"BR",
    "name:por_x_preferred":[
        "Placa Dois"
    ],
    "wof:name":"Placa Dois",
    "wof:placetype":"locality"
},
  "geometry": {"coordinates":[-52.59032,-23.25727],"type":"Point"}
}