{
  "type": "Feature",
  "properties": {
    "gn:admin1_code":"18",
    "gn:admin2_code":"4125506.0",
    "gn:asciiname":"Sitio Antonio Wosniaki",
    "gn:country_code":"BR",
    "gn:dem":928,
    "gn:feature_class":"P",
    "gn:feature_code":"PPL",
    "gn:name":"S\u00edtio Ant\u00f4nio Wosniaki",
    "gn:population":0,
    "gn:timezone":"America/Sao_Paulo",
    "iso:country":"BR",
    "name:por_x_preferred":[
        "S\u00edtio Ant\u00f4nio Wosniaki"
    ],
    "wof:name":"Sitio Antonio Wosniaki",
    "wof:placetype":"locality"
},
  "geometry": {"coordinates":[-49.1533,-25.7524],"type":"Point"}
}