{
  "type": "Feature",
  "properties": {
    "gn:admin1_code":"24",
    "gn:admin2_code":"1100205.0",
    "gn:asciiname":"Pedra Canga",
    "gn:country_code":"BR",
    "gn:dem":91,
    "gn:feature_class":"P",
    "gn:feature_code":"PPL",
    "gn:name":"Pedra Canga",
    "gn:population":0,
    "gn:timezone":"America/Porto_Velho",
    "iso:country":"BR",
    "wof:name":"Pedra Canga",
    "wof:placetype":"locality"
},
  "geometry": {"coordinates":[-64.08333,-9.01667],"type":"Point"}
}