{
  "type": "Feature",
  "properties": {
    "gn:admin1_code":"16",
    "gn:admin2_code":"1508357.0",
    "gn:asciiname":"Sumauma",
    "gn:country_code":"BR",
    "gn:dem":30,
    "gn:feature_class":"P",
    "gn:feature_code":"PPL",
    "gn:name":"Suma\u00fama",
    "gn:population":0,
    "gn:timezone":"America/Santarem",
    "iso:country":"BR",
    "wof:name":"Sumauma",
    "wof:placetype":"locality"
},
  "geometry": {"coordinates":[-51.92808,-2.9421],"type":"Point"}
}