{
  "type": "Feature",
  "properties": {
    "gn:admin1_code":"14",
    "gn:admin2_code":"5106307.0",
    "gn:asciiname":"Posto Simoes Lopes",
    "gn:cc2":"BR",
    "gn:country_code":"BR",
    "gn:dem":449,
    "gn:feature_class":"P",
    "gn:feature_code":"PPL",
    "gn:name":"P\u00f4sto Sim\u00f5es Lopes",
    "gn:population":0,
    "gn:timezone":"America/Cuiaba",
    "iso:country":"BR",
    "name:und_x_variant":[
        "Posto Indigena do Cria\u00e7\u00e3o Sim\u00f5es Lopes",
        "P\u00f4sto Sim\u00f5es Lopes"
    ],
    "wof:name":"Posto Simoes Lopes",
    "wof:placetype":"locality"
},
  "geometry": {"coordinates":[-54.68333000000001,-14.23333],"type":"Point"}
}