{
  "type": "Feature",
  "properties": {
    "gn:admin1_code":"15",
    "gn:admin2_code":"3108909.0",
    "gn:asciiname":"Sitio Jose Candido da Silva",
    "gn:country_code":"BR",
    "gn:dem":911,
    "gn:feature_class":"P",
    "gn:feature_code":"PPL",
    "gn:name":"S\u00edtio Jos\u00e9 C\u00e2ndido da Silva",
    "gn:population":0,
    "gn:timezone":"America/Sao_Paulo",
    "iso:country":"BR",
    "name:por_x_preferred":[
        "S\u00edtio Jos\u00e9 C\u00e2ndido da Silva"
    ],
    "wof:name":"Sitio Jose Candido da Silva",
    "wof:placetype":"locality"
},
  "geometry": {"coordinates":[-45.6427,-22.5924],"type":"Point"}
}