{
  "type": "Feature",
  "properties": {
    "gn:admin1_code":"22",
    "gn:admin2_code":"2401008.0",
    "gn:asciiname":"Barra (2)",
    "gn:country_code":"BR",
    "gn:dem":62,
    "gn:feature_class":"P",
    "gn:feature_code":"PPL",
    "gn:name":"Barra (2)",
    "gn:population":0,
    "gn:timezone":"America/Fortaleza",
    "iso:country":"BR",
    "wof:name":"Barra (2)",
    "wof:placetype":"locality"
},
  "geometry": {"coordinates":[-37.83333,-5.65],"type":"Point"}
}