{
  "type": "Feature",
  "properties": {
    "gn:admin1_code":"11",
    "gn:admin2_code":"5000609.0",
    "gn:asciiname":"Lidio Lima",
    "gn:country_code":"BR",
    "gn:dem":418,
    "gn:feature_class":"P",
    "gn:feature_code":"PPL",
    "gn:name":"L\u00eddio Lima",
    "gn:population":0,
    "gn:timezone":"America/Campo_Grande",
    "iso:country":"BR",
    "wof:name":"Lidio Lima",
    "wof:placetype":"locality"
},
  "geometry": {"coordinates":[-54.98333,-23.25],"type":"Point"}
}