{
  "type": "Feature",
  "properties": {
    "gn:admin1_code":"18.0",
    "gn:admin2_code":"4126678.0",
    "gn:asciiname":"Sitio Geraldo Amado",
    "gn:country_code":"BR",
    "gn:dem":724,
    "gn:feature_class":"P",
    "gn:feature_code":"PPL",
    "gn:name":"S\u00edtio Geraldo Amado",
    "gn:population":0,
    "gn:timezone":"America/Sao_Paulo",
    "iso:country":"BR",
    "name:por_x_preferred":[
        "S\u00edtio Geraldo Amado"
    ],
    "wof:name":"Sitio Geraldo Amado",
    "wof:placetype":"locality"
},
  "geometry": {"coordinates":[-50.9639,-23.8058],"type":"Point"}
}