{
  "type": "Feature",
  "properties": {
    "gn:admin1_code":"27.0",
    "gn:admin2_code":"3524600.0",
    "gn:asciiname":"Ribeirao da Batata",
    "gn:country_code":"BR",
    "gn:dem":168,
    "gn:feature_class":"P",
    "gn:feature_code":"PPLL",
    "gn:name":"Ribeir\u00e3o da Batata",
    "gn:population":0,
    "gn:timezone":"America/Sao_Paulo",
    "iso:country":"BR",
    "name:por_x_preferred":[
        "Ribeir\u00e3o da Batata"
    ],
    "wof:name":"Ribeirao da Batata",
    "wof:placetype":"locality"
},
  "geometry": {"coordinates":[-48.09038,-24.9106],"type":"Point"}
}