{
  "type": "Feature",
  "properties": {
    "gn:admin1_code":"16",
    "gn:admin2_code":"1504901.0",
    "gn:asciiname":"Atalaia",
    "gn:country_code":"BR",
    "gn:dem":14,
    "gn:feature_class":"P",
    "gn:feature_code":"PPL",
    "gn:name":"Atalaia",
    "gn:population":0,
    "gn:timezone":"America/Belem",
    "iso:country":"BR",
    "name:ast_x_preferred":[
        "Atalaia"
    ],
    "name:ceb_x_preferred":[
        "Atalaia"
    ],
    "name:deu_x_preferred":[
        "Atalaia"
    ],
    "name:fra_x_preferred":[
        "Atalaia"
    ],
    "name:glg_x_preferred":[
        "Atalaia"
    ],
    "name:ita_x_preferred":[
        "Atalaia"
    ],
    "name:nld_x_preferred":[
        "Atalaia"
    ],
    "name:nor_x_preferred":[
        "Atalaia"
    ],
    "name:por_x_preferred":[
        "Atalaia"
    ],
    "name:spa_x_preferred":[
        "Atalaia"
    ],
    "name:swe_x_preferred":[
        "Atalaia"
    ],
    "name:vol_x_preferred":[
        "Atalaia"
    ],
    "wof:name":"Atalaia",
    "wof:placetype":"locality"
},
  "geometry": {"coordinates":[-49.31667,-0.98333],"type":"Point"}
}