{
  "type": "Feature",
  "properties": {
    "gn:admin1_code":"06",
    "gn:admin2_code":"2303808.0",
    "gn:asciiname":"Ubaldinho",
    "gn:country_code":"BR",
    "gn:dem":303,
    "gn:feature_class":"P",
    "gn:feature_code":"PPL",
    "gn:name":"Ubaldinho",
    "gn:population":0,
    "gn:timezone":"America/Fortaleza",
    "iso:country":"BR",
    "wof:name":"Ubaldinho",
    "wof:placetype":"locality"
},
  "geometry": {"coordinates":[-39.23333,-6.58333],"type":"Point"}
}