{
  "type": "Feature",
  "properties": {
    "gn:admin1_code":"20",
    "gn:admin2_code":"2201606.0",
    "gn:asciiname":"Ponta do Morro",
    "gn:country_code":"BR",
    "gn:dem":158,
    "gn:feature_class":"P",
    "gn:feature_code":"PPL",
    "gn:name":"Ponta do Morro",
    "gn:population":0,
    "gn:timezone":"America/Fortaleza",
    "iso:country":"BR",
    "wof:name":"Ponta do Morro",
    "wof:placetype":"locality"
},
  "geometry": {"coordinates":[-42.41667,-5.36667],"type":"Point"}
}