{
  "type": "Feature",
  "properties": {
    "gn:admin1_code":"6",
    "gn:admin2_code":"2311801.0",
    "gn:asciiname":"Alto do Velame",
    "gn:country_code":"BR",
    "gn:dem":23,
    "gn:feature_class":"P",
    "gn:feature_code":"PPL",
    "gn:name":"Alto do Velame",
    "gn:population":0,
    "gn:timezone":"America/Fortaleza",
    "iso:country":"BR",
    "wof:name":"Alto do Velame",
    "wof:placetype":"locality"
},
  "geometry": {"coordinates":[-37.96667,-4.95],"type":"Point"}
}