{
  "type": "Feature",
  "properties": {
    "gn:admin1_code":"25",
    "gn:admin2_code":"1400050.0",
    "gn:asciiname":"Aningal",
    "gn:country_code":"BR",
    "gn:dem":84,
    "gn:feature_class":"P",
    "gn:feature_code":"PPL",
    "gn:name":"Aningal",
    "gn:population":0,
    "gn:timezone":"America/Boa_Vista",
    "iso:country":"BR",
    "wof:name":"Aningal",
    "wof:placetype":"locality"
},
  "geometry": {"coordinates":[-61.01667,2.83333],"type":"Point"}
}