{
  "type": "Feature",
  "properties": {
    "gn:admin1_code":"15",
    "gn:admin2_code":"3134004.0",
    "gn:asciiname":"Porto Alegre",
    "gn:country_code":"BR",
    "gn:dem":241,
    "gn:feature_class":"P",
    "gn:feature_code":"PPL",
    "gn:name":"P\u00f4rto Alegre",
    "gn:population":0,
    "gn:timezone":"America/Sao_Paulo",
    "iso:country":"BR",
    "name:por_x_preferred":[
        "P\u00f4rto Alegre"
    ],
    "wof:name":"Porto Alegre",
    "wof:placetype":"locality"
},
  "geometry": {"coordinates":[-41.78333,-16.61667000000001],"type":"Point"}
}