{
  "type": "Feature",
  "properties": {
    "gn:admin1_code":"23",
    "gn:admin2_code":"4315602.0",
    "gn:asciiname":"Cassino",
    "gn:cc2":"BR",
    "gn:country_code":"BR",
    "gn:dem":7,
    "gn:feature_class":"P",
    "gn:feature_code":"PPL",
    "gn:name":"Cassino",
    "gn:population":0,
    "gn:timezone":"America/Sao_Paulo",
    "iso:country":"BR",
    "name:und_x_variant":[
        "Mangueira",
        "Casino",
        "Vila Siqueira",
        "Villa Siqueira",
        "Cassino"
    ],
    "wof:name":"Cassino",
    "wof:placetype":"locality"
},
  "geometry": {"coordinates":[-52.16667,-32.18333],"type":"Point"}
}