{
  "type": "Feature",
  "properties": {
    "gn:admin1_code":"23",
    "gn:admin2_code":"4315602.0",
    "gn:asciiname":"Cassino",
    "gn:cc2":"BR",
    "gn:country_code":"BR",
    "gn:dem":7,
    "gn:feature_class":"P",
    "gn:feature_code":"PPL",
    "gn:name":"Cassino",
    "gn:population":0,
    "gn:timezone":"America/Sao_Paulo",
    "iso:country":"BR",
    "name:azb_x_preferred":[
        "\u06a9\u0627\u0633\u06cc\u0646\u0648"
    ],
    "name:bcl_x_preferred":[
        "Cassino"
    ],
    "name:bre_x_preferred":[
        "Cassino"
    ],
    "name:bul_x_preferred":[
        "\u041a\u0430\u0441\u0438\u043d\u043e"
    ],
    "name:cat_x_preferred":[
        "Cassino"
    ],
    "name:ceb_x_preferred":[
        "Cassino"
    ],
    "name:dan_x_preferred":[
        "Cassino"
    ],
    "name:deu_x_preferred":[
        "Cassino"
    ],
    "name:epo_x_preferred":[
        "Cassino"
    ],
    "name:eus_x_preferred":[
        "Cassino"
    ],
    "name:fas_x_preferred":[
        "\u06a9\u0627\u0633\u06cc\u0646\u0648"
    ],
    "name:fin_x_preferred":[
        "Cassino"
    ],
    "name:fra_x_preferred":[
        "Cassino"
    ],
    "name:hun_x_preferred":[
        "Cassino"
    ],
    "name:hye_x_preferred":[
        "\u053f\u0561\u057d\u056b\u0576\u0578"
    ],
    "name:ina_x_preferred":[
        "Cassino"
    ],
    "name:ita_x_preferred":[
        "Cassino"
    ],
    "name:jpn_x_preferred":[
        "\u30ab\u30c3\u30b7\u30fc\u30ce"
    ],
    "name:kat_x_preferred":[
        "\u10d9\u10d0\u10e1\u10d8\u10dc\u10dd"
    ],
    "name:kaz_x_preferred":[
        "\u041a\u0430\u0441\u0441\u0438\u043d\u043e"
    ],
    "name:kor_x_preferred":[
        "\uce74\uc2dc\ub178"
    ],
    "name:lat_x_preferred":[
        "Casinum"
    ],
    "name:lit_x_preferred":[
        "Kasinas"
    ],
    "name:lmo_x_preferred":[
        "Cassino"
    ],
    "name:msa_x_preferred":[
        "Cassino"
    ],
    "name:nap_x_preferred":[
        "Cassino"
    ],
    "name:nld_x_preferred":[
        "Cassino"
    ],
    "name:nno_x_preferred":[
        "Cassino"
    ],
    "name:nor_x_preferred":[
        "Cassino"
    ],
    "name:pms_x_preferred":[
        "Cassino"
    ],
    "name:pol_x_preferred":[
        "Cassino"
    ],
    "name:por_x_preferred":[
        "Cassino"
    ],
    "name:ron_x_preferred":[
        "Cassino"
    ],
    "name:rus_x_preferred":[
        "\u041a\u0430\u0441\u0441\u0438\u043d\u043e"
    ],
    "name:scn_x_preferred":[
        "Cassinu"
    ],
    "name:sco_x_preferred":[
        "Cassino"
    ],
    "name:spa_x_preferred":[
        "Cassino"
    ],
    "name:sqi_x_preferred":[
        "Kasino"
    ],
    "name:srp_x_preferred":[
        "\u041a\u0430\u0441\u0438\u043d\u043e"
    ],
    "name:swe_x_preferred":[
        "Cassino"
    ],
    "name:tur_x_preferred":[
        "Cassino"
    ],
    "name:ukr_x_preferred":[
        "\u041a\u0430\u0441\u0441\u0456\u043d\u043e"
    ],
    "name:und_x_variant":[
        "Mangueira",
        "Casino",
        "Vila Siqueira",
        "Villa Siqueira",
        "Cassino"
    ],
    "name:uzb_x_preferred":[
        "Cassino"
    ],
    "name:vec_x_preferred":[
        "Cassino"
    ],
    "name:vie_x_preferred":[
        "Cassino"
    ],
    "name:vol_x_preferred":[
        "Cassino"
    ],
    "name:war_x_preferred":[
        "Cassino"
    ],
    "name:zho_x_preferred":[
        "\u5361\u897f\u8bfa"
    ],
    "wof:name":"Cassino",
    "wof:placetype":"locality"
},
  "geometry": {"coordinates":[-52.16667,-32.18333],"type":"Point"}
}