{
  "type": "Feature",
  "properties": {
    "gn:admin1_code":"20",
    "gn:admin2_code":"2208809.0",
    "gn:asciiname":"Cabeceiras",
    "gn:country_code":"BR",
    "gn:dem":244,
    "gn:feature_class":"P",
    "gn:feature_code":"PPL",
    "gn:name":"Cabeceiras",
    "gn:population":0,
    "gn:timezone":"America/Fortaleza",
    "iso:country":"BR",
    "wof:name":"Cabeceiras",
    "wof:placetype":"locality"
},
  "geometry": {"coordinates":[-42.43333,-6.41667],"type":"Point"}
}