{
  "type": "Feature",
  "properties": {
    "gn:admin1_code":"20",
    "gn:admin2_code":"2208809.0",
    "gn:asciiname":"Cabeceiras",
    "gn:country_code":"BR",
    "gn:dem":244,
    "gn:feature_class":"P",
    "gn:feature_code":"PPL",
    "gn:name":"Cabeceiras",
    "gn:population":0,
    "gn:timezone":"America/Fortaleza",
    "iso:country":"BR",
    "name:bpy_x_preferred":[
        "\u0995\u09be\u09ac\u09c7\u09b8\u09c7\u0987\u09b0\u09be\u09b8"
    ],
    "name:ceb_x_preferred":[
        "Cabeceiras"
    ],
    "name:deu_x_preferred":[
        "Cabeceiras"
    ],
    "name:epo_x_preferred":[
        "Cabeceiras"
    ],
    "name:eus_x_preferred":[
        "Cabeceiras"
    ],
    "name:fra_x_preferred":[
        "Cabeceiras"
    ],
    "name:hye_x_preferred":[
        "\u053f\u0561\u0562\u0565\u057d\u0565\u0575\u0580\u0561\u057d"
    ],
    "name:ita_x_preferred":[
        "Cabeceiras"
    ],
    "name:kat_x_preferred":[
        "\u10d9\u10d0\u10d1\u10d4\u10e1\u10d4\u10d8\u10e0\u10d0\u10e1\u10d8"
    ],
    "name:kaz_x_preferred":[
        "\u041a\u0430\u0431\u0435\u0441\u0435\u0439\u0440\u0430\u0441"
    ],
    "name:mlg_x_preferred":[
        "Cabeceiras"
    ],
    "name:nld_x_preferred":[
        "Cabeceiras"
    ],
    "name:nor_x_preferred":[
        "Cabeceiras"
    ],
    "name:por_x_preferred":[
        "Cabeceiras"
    ],
    "name:ron_x_preferred":[
        "Cabeceiras"
    ],
    "name:rus_x_preferred":[
        "\u041a\u0430\u0431\u0435\u0441\u0435\u0439\u0440\u0430\u0441"
    ],
    "name:spa_x_preferred":[
        "Cabeceiras"
    ],
    "name:swe_x_preferred":[
        "Cabeceiras"
    ],
    "name:vol_x_preferred":[
        "Cabeceiras"
    ],
    "name:war_x_preferred":[
        "Cabeceiras"
    ],
    "name:zho_x_preferred":[
        "\u5361\u8d1d\u585e\u62c9\u4ec0"
    ],
    "wof:name":"Cabeceiras",
    "wof:placetype":"locality"
},
  "geometry": {"coordinates":[-42.43333,-6.41667],"type":"Point"}
}