{
  "type": "Feature",
  "properties": {
    "gn:admin1_code":"05",
    "gn:admin2_code":"2909901.0",
    "gn:asciiname":"Riacho Grande",
    "gn:cc2":"BR",
    "gn:country_code":"BR",
    "gn:dem":404,
    "gn:feature_class":"P",
    "gn:feature_code":"PPL",
    "gn:name":"Riacho Grande",
    "gn:population":0,
    "gn:timezone":"America/Bahia",
    "iso:country":"BR",
    "name:und_x_variant":[
        "Pinh\u00e3o Grande",
        "Riacho Grande"
    ],
    "wof:name":"Riacho Grande",
    "wof:placetype":"locality"
},
  "geometry": {"coordinates":[-39.85,-9.43333],"type":"Point"}
}