{
  "type": "Feature",
  "properties": {
    "gn:admin1_code":"20",
    "gn:admin2_code":"2203701.0",
    "gn:asciiname":"Angelim",
    "gn:country_code":"BR",
    "gn:dem":94,
    "gn:feature_class":"P",
    "gn:feature_code":"PPL",
    "gn:name":"Angelim",
    "gn:population":0,
    "gn:timezone":"America/Fortaleza",
    "iso:country":"BR",
    "name:bpy_x_preferred":[
        "\u0986\u09a8\u0997\u09c7\u09b2\u09bf\u09ae"
    ],
    "name:ceb_x_preferred":[
        "Angelim"
    ],
    "name:eus_x_preferred":[
        "Angelim"
    ],
    "name:fra_x_preferred":[
        "Angelim"
    ],
    "name:ita_x_preferred":[
        "Angelim"
    ],
    "name:kat_x_preferred":[
        "\u10d0\u10dc\u10df\u10d4\u10da\u10d8\u10dc\u10d8"
    ],
    "name:mlg_x_preferred":[
        "Angelim"
    ],
    "name:nld_x_preferred":[
        "Angelim"
    ],
    "name:nor_x_preferred":[
        "Angelim"
    ],
    "name:por_x_preferred":[
        "Angelim"
    ],
    "name:ron_x_preferred":[
        "Angelim"
    ],
    "name:rus_x_preferred":[
        "\u0410\u043d\u0436\u0435\u043b\u0438\u043d"
    ],
    "name:swe_x_preferred":[
        "Angelim"
    ],
    "name:vie_x_preferred":[
        "Angelim"
    ],
    "name:vol_x_preferred":[
        "Angelim"
    ],
    "name:war_x_preferred":[
        "Angelim"
    ],
    "name:zho_x_preferred":[
        "\u5b89\u70ed\u5229\u59c6"
    ],
    "wof:name":"Angelim",
    "wof:placetype":"locality"
},
  "geometry": {"coordinates":[-42.34083,-3.91806],"type":"Point"}
}