{
  "type": "Feature",
  "properties": {
    "gn:admin1_code":"06",
    "gn:admin2_code":"2306405.0",
    "gn:asciiname":"Varzea do Mandau",
    "gn:country_code":"BR",
    "gn:dem":28,
    "gn:feature_class":"P",
    "gn:feature_code":"PPL",
    "gn:name":"Varzea do Mandau",
    "gn:population":0,
    "gn:timezone":"America/Fortaleza",
    "iso:country":"BR",
    "wof:name":"Varzea do Mandau",
    "wof:placetype":"locality"
},
  "geometry": {"coordinates":[-39.51667,-3.25],"type":"Point"}
}