{
  "type": "Feature",
  "properties": {
    "gn:admin1_code":"06",
    "gn:admin2_code":"2304103.0",
    "gn:asciiname":"Rubim",
    "gn:country_code":"BR",
    "gn:dem":328,
    "gn:feature_class":"P",
    "gn:feature_code":"PPL",
    "gn:name":"Rubim",
    "gn:population":0,
    "gn:timezone":"America/Fortaleza",
    "iso:country":"BR",
    "name:bpy_x_preferred":[
        "\u09b0\u09c1\u09ac\u09bf\u09ae"
    ],
    "name:ceb_x_preferred":[
        "Rubim"
    ],
    "name:epo_x_preferred":[
        "Rubim"
    ],
    "name:eus_x_preferred":[
        "Rubim"
    ],
    "name:fra_x_preferred":[
        "Rubim"
    ],
    "name:ita_x_preferred":[
        "Rubim"
    ],
    "name:kat_x_preferred":[
        "\u10e0\u10e3\u10d1\u10d8\u10dc\u10d8"
    ],
    "name:kaz_x_preferred":[
        "\u0420\u0443\u0431\u0438\u043d"
    ],
    "name:mlg_x_preferred":[
        "Rubim"
    ],
    "name:nld_x_preferred":[
        "Rubim"
    ],
    "name:nor_x_preferred":[
        "Rubim"
    ],
    "name:pol_x_preferred":[
        "Rubim"
    ],
    "name:por_x_preferred":[
        "Rubim"
    ],
    "name:ron_x_preferred":[
        "Rubim"
    ],
    "name:rus_x_preferred":[
        "\u0420\u0443\u0431\u0438\u043d"
    ],
    "name:spa_x_preferred":[
        "Rubim"
    ],
    "name:swe_x_preferred":[
        "Rubim"
    ],
    "name:vie_x_preferred":[
        "Rubim"
    ],
    "name:vol_x_preferred":[
        "Rubim"
    ],
    "name:war_x_preferred":[
        "Rubim"
    ],
    "name:zho_x_preferred":[
        "\u9c81\u5bbe"
    ],
    "wof:name":"Rubim",
    "wof:placetype":"locality"
},
  "geometry": {"coordinates":[-40.73333,-5.33333],"type":"Point"}
}