{
  "type": "Feature",
  "properties": {
    "gn:admin1_code":"06",
    "gn:admin2_code":"2304103.0",
    "gn:asciiname":"Rubim",
    "gn:country_code":"BR",
    "gn:dem":328,
    "gn:feature_class":"P",
    "gn:feature_code":"PPL",
    "gn:name":"Rubim",
    "gn:population":0,
    "gn:timezone":"America/Fortaleza",
    "iso:country":"BR",
    "wof:name":"Rubim",
    "wof:placetype":"locality"
},
  "geometry": {"coordinates":[-40.73333,-5.33333],"type":"Point"}
}