{
  "type": "Feature",
  "properties": {
    "gn:admin1_code":"11",
    "gn:admin2_code":"5002209.0",
    "gn:asciiname":"Lamina",
    "gn:cc2":"BR",
    "gn:country_code":"BR",
    "gn:dem":227,
    "gn:feature_class":"P",
    "gn:feature_code":"PPL",
    "gn:name":"L\u00e2mina",
    "gn:population":0,
    "gn:timezone":"America/Campo_Grande",
    "iso:country":"BR",
    "name:deu_x_preferred":[
        "Lamina"
    ],
    "name:fra_x_preferred":[
        "Lamina"
    ],
    "name:ita_x_preferred":[
        "Lamina"
    ],
    "name:nld_x_preferred":[
        "Lamina"
    ],
    "name:und_x_variant":[
        "Lalima",
        "L\u00e2mina"
    ],
    "wof:name":"Lamina",
    "wof:placetype":"locality"
},
  "geometry": {"coordinates":[-56.36666999999999,-20.68333],"type":"Point"}
}