{
  "type": "Feature",
  "properties": {
    "gn:admin1_code":"15",
    "gn:admin2_code":"3108503.0",
    "gn:asciiname":"Folha Larga",
    "gn:country_code":"BR",
    "gn:dem":875,
    "gn:feature_class":"P",
    "gn:feature_code":"PPL",
    "gn:name":"F\u00f4lha Larga",
    "gn:population":0,
    "gn:timezone":"America/Sao_Paulo",
    "iso:country":"BR",
    "name:por_x_preferred":[
        "F\u00f4lha Larga"
    ],
    "wof:name":"Folha Larga",
    "wof:placetype":"locality"
},
  "geometry": {"coordinates":[-42.98333,-17.06667],"type":"Point"}
}