{
  "type": "Feature",
  "properties": {
    "gn:admin1_code":"27",
    "gn:admin2_code":"3554508.0",
    "gn:asciiname":"Sitio Bom Jesus do Tiete",
    "gn:country_code":"BR",
    "gn:dem":501,
    "gn:feature_class":"P",
    "gn:feature_code":"PPL",
    "gn:name":"S\u00edtio Bom Jesus do Tiet\u00ea",
    "gn:population":0,
    "gn:timezone":"America/Sao_Paulo",
    "iso:country":"BR",
    "name:por_x_preferred":[
        "S\u00edtio Bom Jesus do Tiet\u00ea"
    ],
    "wof:name":"Sitio Bom Jesus do Tiete",
    "wof:placetype":"locality"
},
  "geometry": {"coordinates":[-47.67306,-23.09861],"type":"Point"}
}