{
  "type": "Feature",
  "properties": {
    "gn:admin1_code":"5",
    "gn:admin2_code":"2902054.0",
    "gn:asciiname":"Pati",
    "gn:country_code":"BR",
    "gn:dem":126,
    "gn:feature_class":"P",
    "gn:feature_code":"PPL",
    "gn:name":"Pati",
    "gn:population":0,
    "gn:timezone":"America/Bahia",
    "iso:country":"BR",
    "name:ceb_x_preferred":[
        "Pati"
    ],
    "name:deu_x_preferred":[
        "Pati"
    ],
    "name:fas_x_preferred":[
        "\u067e\u062a\u06cc"
    ],
    "name:fra_x_preferred":[
        "Pati"
    ],
    "name:ind_x_preferred":[
        "Pati"
    ],
    "name:mlg_x_preferred":[
        "Pati"
    ],
    "name:nld_x_preferred":[
        "Pati"
    ],
    "name:swe_x_preferred":[
        "Pati"
    ],
    "wof:name":"Pati",
    "wof:placetype":"locality"
},
  "geometry": {"coordinates":[-38.25,-12.23333],"type":"Point"}
}