{
  "type": "Feature",
  "properties": {
    "gn:admin1_code":"27",
    "gn:admin2_code":"3509254.0",
    "gn:asciiname":"Sitio Elson",
    "gn:country_code":"BR",
    "gn:dem":153,
    "gn:feature_class":"P",
    "gn:feature_code":"PPL",
    "gn:name":"S\u00edtio Elson",
    "gn:population":0,
    "gn:timezone":"America/Sao_Paulo",
    "iso:country":"BR",
    "name:por_x_preferred":[
        "S\u00edtio Elson"
    ],
    "wof:name":"Sitio Elson",
    "wof:placetype":"locality"
},
  "geometry": {"coordinates":[-48.1742,-24.8304],"type":"Point"}
}