{
  "type": "Feature",
  "properties": {
    "gn:admin1_code":"23",
    "gn:admin2_code":"4313359.0",
    "gn:asciiname":"Novo Treviso",
    "gn:cc2":"BR",
    "gn:country_code":"BR",
    "gn:dem":652,
    "gn:feature_class":"P",
    "gn:feature_code":"PPL",
    "gn:name":"Novo Treviso",
    "gn:population":0,
    "gn:timezone":"America/Sao_Paulo",
    "iso:country":"BR",
    "name:und_x_variant":[
        "Ex. Novo Treviso",
        "Novo Treviso"
    ],
    "wof:name":"Novo Treviso",
    "wof:placetype":"locality"
},
  "geometry": {"coordinates":[-51.38333,-28.95],"type":"Point"}
}