{
  "type": "Feature",
  "properties": {
    "gn:admin1_code":"31",
    "gn:admin2_code":"1716604.0",
    "gn:asciiname":"Perdizes",
    "gn:country_code":"BR",
    "gn:dem":234,
    "gn:feature_class":"P",
    "gn:feature_code":"PPL",
    "gn:name":"Perdizes",
    "gn:population":0,
    "gn:timezone":"America/Araguaina",
    "iso:country":"BR",
    "name:ceb_x_preferred":[
        "Perdizes"
    ],
    "name:swe_x_preferred":[
        "Perdizes"
    ],
    "wof:name":"Perdizes",
    "wof:placetype":"locality"
},
  "geometry": {"coordinates":[-48.71694,-11.65028],"type":"Point"}
}