{
  "type": "Feature",
  "properties": {
    "gn:admin1_code":"18",
    "gn:admin2_code":"4108700.0",
    "gn:asciiname":"Sapecada",
    "gn:country_code":"BR",
    "gn:dem":600,
    "gn:feature_class":"P",
    "gn:feature_code":"PPL",
    "gn:name":"Sapecada",
    "gn:population":0,
    "gn:timezone":"America/Sao_Paulo",
    "iso:country":"BR",
    "wof:name":"Sapecada",
    "wof:placetype":"locality"
},
  "geometry": {"coordinates":[-51.53333,-24.16667],"type":"Point"}
}