{
  "type": "Feature",
  "properties": {
    "gn:admin1_code":"16",
    "gn:admin2_code":"1505700.0",
    "gn:asciiname":"Arrozal",
    "gn:country_code":"BR",
    "gn:dem":15,
    "gn:feature_class":"P",
    "gn:feature_code":"PPL",
    "gn:name":"Arrozal",
    "gn:population":0,
    "gn:timezone":"America/Belem",
    "iso:country":"BR",
    "wof:name":"Arrozal",
    "wof:placetype":"locality"
},
  "geometry": {"coordinates":[-48.81667,-1.26667],"type":"Point"}
}