{
  "type": "Feature",
  "properties": {
    "gn:admin1_code":"1",
    "gn:admin2_code":"1200203.0",
    "gn:asciiname":"Aldeola",
    "gn:country_code":"BR",
    "gn:dem":199,
    "gn:feature_class":"P",
    "gn:feature_code":"PPL",
    "gn:name":"Aldeola",
    "gn:population":0,
    "gn:timezone":"America/Rio_Branco",
    "iso:country":"BR",
    "wof:name":"Aldeola",
    "wof:placetype":"locality"
},
  "geometry": {"coordinates":[-72.96666999999999,-8.21667],"type":"Point"}
}