{
  "type": "Feature",
  "properties": {
    "gn:admin1_code":"3",
    "gn:admin2_code":"1600279.0",
    "gn:asciiname":"Barraca da Boca",
    "gn:country_code":"BR",
    "gn:dem":81,
    "gn:feature_class":"P",
    "gn:feature_code":"PPL",
    "gn:name":"Barraca da B\u00f4ca",
    "gn:population":0,
    "gn:timezone":"America/Belem",
    "iso:country":"BR",
    "wof:name":"Barraca da Boca",
    "wof:placetype":"locality"
},
  "geometry": {"coordinates":[-52.56728,-0.55889],"type":"Point"}
}