{
  "type": "Feature",
  "properties": {
    "gn:admin1_code":"18.0",
    "gn:admin2_code":"4113205.0",
    "gn:asciiname":"Sitio Helena Menemberg",
    "gn:country_code":"BR",
    "gn:dem":823,
    "gn:feature_class":"P",
    "gn:feature_code":"PPL",
    "gn:name":"S\u00edtio Helena Menemberg",
    "gn:population":0,
    "gn:timezone":"America/Sao_Paulo",
    "iso:country":"BR",
    "name:por_x_preferred":[
        "S\u00edtio Helena Menemberg"
    ],
    "wof:name":"Sitio Helena Menemberg",
    "wof:placetype":"locality"
},
  "geometry": {"coordinates":[-49.90983,-25.82597],"type":"Point"}
}