{
  "type": "Feature",
  "properties": {
    "gn:admin1_code":"11",
    "gn:admin2_code":"5006903.0",
    "gn:asciiname":"Santo Esidro",
    "gn:country_code":"BR",
    "gn:dem":89,
    "gn:feature_class":"P",
    "gn:feature_code":"PPL",
    "gn:name":"Santo Esidro",
    "gn:population":0,
    "gn:timezone":"America/Campo_Grande",
    "iso:country":"BR",
    "wof:name":"Santo Esidro",
    "wof:placetype":"locality"
},
  "geometry": {"coordinates":[-57.73333,-21.81667],"type":"Point"}
}