{
  "type": "Feature",
  "properties": {
    "gn:admin1_code":"5",
    "gn:admin2_code":"2901700.0",
    "gn:asciiname":"Bom Jesus",
    "gn:country_code":"BR",
    "gn:dem":197,
    "gn:feature_class":"P",
    "gn:feature_code":"PPL",
    "gn:name":"Bom Jesus",
    "gn:population":0,
    "gn:timezone":"America/Bahia",
    "iso:country":"BR",
    "name:bpy_x_preferred":[
        "\u09ac\u09cb\u09ae \u099c\u09c7\u09b8\u0989\u09b8"
    ],
    "name:ceb_x_preferred":[
        "Bom Jesus"
    ],
    "name:deu_x_preferred":[
        "Bom Jesus"
    ],
    "name:fra_x_preferred":[
        "Bom Jesus"
    ],
    "name:ita_x_preferred":[
        "Bom Jesus"
    ],
    "name:nld_x_preferred":[
        "Bom Jesus"
    ],
    "name:nor_x_preferred":[
        "Bom Jesus"
    ],
    "name:pol_x_preferred":[
        "Bom Jesus"
    ],
    "name:por_x_preferred":[
        "Bom Jesus"
    ],
    "name:sco_x_preferred":[
        "Bom Jesus"
    ],
    "name:spa_x_preferred":[
        "Bom Jesus"
    ],
    "name:swe_x_preferred":[
        "Bom Jesus"
    ],
    "name:vie_x_preferred":[
        "Bom Jesus"
    ],
    "name:vol_x_preferred":[
        "Bom Jesus"
    ],
    "name:war_x_preferred":[
        "Bom Jesus"
    ],
    "wof:name":"Bom Jesus",
    "wof:placetype":"locality"
},
  "geometry": {"coordinates":[-39.23333,-12.33333],"type":"Point"}
}