{
  "type": "Feature",
  "properties": {
    "gn:admin1_code":"02",
    "gn:admin2_code":"2704203.0",
    "gn:asciiname":"Eugenio",
    "gn:country_code":"BR",
    "gn:dem":241,
    "gn:feature_class":"P",
    "gn:feature_code":"PPL",
    "gn:name":"Eug\u00eanio",
    "gn:population":0,
    "gn:timezone":"America/Maceio",
    "iso:country":"BR",
    "name:bre_x_preferred":[
        "Eugenio"
    ],
    "name:deu_x_preferred":[
        "Eugenio"
    ],
    "name:ita_x_preferred":[
        "Eugenio"
    ],
    "name:jpn_x_preferred":[
        "\u30a8\u30a6\u30b8\u30a7\u30fc\u30cb\u30aa"
    ],
    "name:tgl_x_preferred":[
        "Eugenio"
    ],
    "wof:name":"Eugenio",
    "wof:placetype":"locality"
},
  "geometry": {"coordinates":[-36.38333,-9.66667],"type":"Point"}
}