{
  "type": "Feature",
  "properties": {
    "gn:admin1_code":"13",
    "gn:admin2_code":"2110609.0",
    "gn:asciiname":"Palmeiras",
    "gn:country_code":"BR",
    "gn:dem":64,
    "gn:feature_class":"P",
    "gn:feature_code":"PPL",
    "gn:name":"Palmeiras",
    "gn:population":0,
    "gn:timezone":"America/Fortaleza",
    "iso:country":"BR",
    "wof:name":"Palmeiras",
    "wof:placetype":"locality"
},
  "geometry": {"coordinates":[-42.42944,-3.21944],"type":"Point"}
}