{
  "type": "Feature",
  "properties": {
    "gn:admin1_code":"18",
    "gn:admin2_code":"4119103.0",
    "gn:asciiname":"Sitio Roberto Drevek",
    "gn:country_code":"BR",
    "gn:dem":798,
    "gn:feature_class":"P",
    "gn:feature_code":"PPL",
    "gn:name":"S\u00edtio Roberto Drevek",
    "gn:population":0,
    "gn:timezone":"America/Sao_Paulo",
    "iso:country":"BR",
    "name:por_x_preferred":[
        "S\u00edtio Roberto Drevek"
    ],
    "wof:name":"Sitio Roberto Drevek",
    "wof:placetype":"locality"
},
  "geometry": {"coordinates":[-49.40099,-26.14933],"type":"Point"}
}