{
  "type": "Feature",
  "properties": {
    "gn:admin1_code":"23",
    "gn:admin2_code":"4317103.0",
    "gn:asciiname":"Manuel Fialho",
    "gn:cc2":"BR",
    "gn:country_code":"BR",
    "gn:dem":325,
    "gn:feature_class":"P",
    "gn:feature_code":"PPL",
    "gn:name":"Manuel Fialho",
    "gn:population":0,
    "gn:timezone":"America/Sao_Paulo",
    "iso:country":"BR",
    "name:und_x_variant":[
        "Est\u00e2ncia Manoel Fialho",
        "Manuel Fialho"
    ],
    "wof:name":"Manuel Fialho",
    "wof:placetype":"locality"
},
  "geometry": {"coordinates":[-55.98333,-31.06667],"type":"Point"}
}