{
  "type": "Feature",
  "properties": {
    "gn:admin1_code":"22",
    "gn:admin2_code":"2413359.0",
    "gn:asciiname":"Rocas",
    "gn:country_code":"BR",
    "gn:dem":139,
    "gn:feature_class":"P",
    "gn:feature_code":"PPL",
    "gn:name":"Ro\u00e7as",
    "gn:population":0,
    "gn:timezone":"America/Fortaleza",
    "iso:country":"BR",
    "wof:name":"Rocas",
    "wof:placetype":"locality"
},
  "geometry": {"coordinates":[-36.91667,-4.98972],"type":"Point"}
}