{
  "type": "Feature",
  "properties": {
    "gn:admin1_code":"21",
    "gn:admin2_code":"3304524.0",
    "gn:asciiname":"Paracampos",
    "gn:country_code":"BR",
    "gn:dem":13,
    "gn:feature_class":"P",
    "gn:feature_code":"PPL",
    "gn:name":"Paracampos",
    "gn:population":0,
    "gn:timezone":"America/Sao_Paulo",
    "iso:country":"BR",
    "name:por_x_preferred":[
        "Paracampos"
    ],
    "wof:name":"Paracampos",
    "wof:placetype":"locality"
},
  "geometry": {"coordinates":[-41.93333,-22.43333],"type":"Point"}
}