{
  "type": "Feature",
  "properties": {
    "gn:admin1_code":"18.0",
    "gn:admin2_code":"4111803.0",
    "gn:asciiname":"Sitio Augustinho Monteiro",
    "gn:country_code":"BR",
    "gn:dem":495,
    "gn:feature_class":"P",
    "gn:feature_code":"PPL",
    "gn:name":"S\u00edtio Augustinho Monteiro",
    "gn:population":0,
    "gn:timezone":"America/Sao_Paulo",
    "iso:country":"BR",
    "name:por_x_preferred":[
        "S\u00edtio Augustinho Monteiro"
    ],
    "wof:name":"Sitio Augustinho Monteiro",
    "wof:placetype":"locality"
},
  "geometry": {"coordinates":[-49.96986,-23.21243],"type":"Point"}
}