{
  "type": "Feature",
  "properties": {
    "gn:admin1_code":"15",
    "gn:admin2_code":"3120201.0",
    "gn:asciiname":"Juca Modesto",
    "gn:country_code":"BR",
    "gn:dem":804,
    "gn:feature_class":"P",
    "gn:feature_code":"PPL",
    "gn:name":"Juca Modesto",
    "gn:population":0,
    "gn:timezone":"America/Sao_Paulo",
    "iso:country":"BR",
    "name:por_x_preferred":[
        "Juca Modesto"
    ],
    "wof:name":"Juca Modesto",
    "wof:placetype":"locality"
},
  "geometry": {"coordinates":[-45.61667,-20.73333],"type":"Point"}
}