{
  "type": "Feature",
  "properties": {
    "gn:admin1_code":"06",
    "gn:admin2_code":"2312205.0",
    "gn:asciiname":"Fazenda Furnas",
    "gn:country_code":"BR",
    "gn:dem":314,
    "gn:feature_class":"P",
    "gn:feature_code":"PPL",
    "gn:name":"Fazenda Furnas",
    "gn:population":0,
    "gn:timezone":"America/Fortaleza",
    "iso:country":"BR",
    "wof:name":"Fazenda Furnas",
    "wof:placetype":"locality"
},
  "geometry": {"coordinates":[-39.78333,-4.33333],"type":"Point"}
}