{
  "type": "Feature",
  "properties": {
    "gn:admin1_code":"18.0",
    "gn:admin2_code":"4114302.0",
    "gn:asciiname":"Sitio Navib Picussa",
    "gn:country_code":"BR",
    "gn:dem":953,
    "gn:feature_class":"P",
    "gn:feature_code":"PPL",
    "gn:name":"S\u00edtio Navib Picussa",
    "gn:population":0,
    "gn:timezone":"America/Sao_Paulo",
    "iso:country":"BR",
    "name:por_x_preferred":[
        "S\u00edtio Navib Picussa"
    ],
    "wof:name":"Sitio Navib Picussa",
    "wof:placetype":"locality"
},
  "geometry": {"coordinates":[-49.2662,-25.7989],"type":"Point"}
}