{
  "type": "Feature",
  "properties": {
    "gn:admin1_code":"18.0",
    "gn:admin2_code":"4120804.0",
    "gn:asciiname":"Sitio Chamine da Serra",
    "gn:country_code":"BR",
    "gn:dem":860,
    "gn:feature_class":"P",
    "gn:feature_code":"PPL",
    "gn:name":"S\u00edtio Chamin\u00e9 da Serra",
    "gn:population":0,
    "gn:timezone":"America/Sao_Paulo",
    "iso:country":"BR",
    "name:por_x_preferred":[
        "S\u00edtio Chamin\u00e9 da Serra"
    ],
    "wof:name":"Sitio Chamine da Serra",
    "wof:placetype":"locality"
},
  "geometry": {"coordinates":[-48.92669,-25.33773],"type":"Point"}
}