{
  "type": "Feature",
  "properties": {
    "gn:admin1_code":"27",
    "gn:admin2_code":"3516200.0",
    "gn:asciiname":"Concordia",
    "gn:cc2":"BR",
    "gn:country_code":"BR",
    "gn:dem":946,
    "gn:feature_class":"P",
    "gn:feature_code":"PPL",
    "gn:name":"Conc\u00f3rdia",
    "gn:population":0,
    "gn:timezone":"America/Sao_Paulo",
    "iso:country":"BR",
    "name:und_x_variant":[
        "Fazenda da Conc\u00f3rdia",
        "Conc\u00f3rdia"
    ],
    "wof:name":"Concordia",
    "wof:placetype":"locality"
},
  "geometry": {"coordinates":[-47.35,-20.48333],"type":"Point"}
}