{
  "type": "Feature",
  "properties": {
    "gn:admin1_code":"18.0",
    "gn:admin2_code":"4100202.0",
    "gn:asciiname":"Corregozinho",
    "gn:country_code":"BR",
    "gn:dem":321,
    "gn:feature_class":"P",
    "gn:feature_code":"PPLL",
    "gn:name":"Corregozinho",
    "gn:population":0,
    "gn:timezone":"America/Sao_Paulo",
    "iso:country":"BR",
    "name:por_x_preferred":[
        "Corregozinho"
    ],
    "name:por_x_variant":[
        "Descampadinho"
    ],
    "wof:name":"Corregozinho",
    "wof:placetype":"locality"
},
  "geometry": {"coordinates":[-48.91613,-24.80495],"type":"Point"}
}