{
  "type": "Feature",
  "properties": {
    "gn:admin1_code":"02",
    "gn:admin2_code":"2702009.0",
    "gn:asciiname":"Rocheira",
    "gn:country_code":"BR",
    "gn:dem":362,
    "gn:feature_class":"P",
    "gn:feature_code":"PPL",
    "gn:name":"Rocheira",
    "gn:population":0,
    "gn:timezone":"America/Maceio",
    "iso:country":"BR",
    "wof:name":"Rocheira",
    "wof:placetype":"locality"
},
  "geometry": {"coordinates":[-36.58333,-9.58333],"type":"Point"}
}