{
  "type": "Feature",
  "properties": {
    "gn:admin1_code":"11",
    "gn:admin2_code":"5002704.0",
    "gn:asciiname":"Anhanduizinho",
    "gn:country_code":"BR",
    "gn:dem":510,
    "gn:feature_class":"P",
    "gn:feature_code":"PPL",
    "gn:name":"Anhandu\u00eczinho",
    "gn:population":0,
    "gn:timezone":"America/Campo_Grande",
    "iso:country":"BR",
    "wof:name":"Anhanduizinho",
    "wof:placetype":"locality"
},
  "geometry": {"coordinates":[-54.38333000000001,-20.75],"type":"Point"}
}