{
  "type": "Feature",
  "properties": {
    "gn:admin1_code":"18.0",
    "gn:admin2_code":"4126603.0",
    "gn:asciiname":"Sitio Jose Calil",
    "gn:country_code":"BR",
    "gn:dem":586,
    "gn:feature_class":"P",
    "gn:feature_code":"PPL",
    "gn:name":"S\u00edtio Jos\u00e9 Calil",
    "gn:population":0,
    "gn:timezone":"America/Sao_Paulo",
    "iso:country":"BR",
    "name:por_x_preferred":[
        "S\u00edtio Jos\u00e9 Calil"
    ],
    "wof:name":"Sitio Jose Calil",
    "wof:placetype":"locality"
},
  "geometry": {"coordinates":[-49.7815,-23.5783],"type":"Point"}
}