{
  "type": "Feature",
  "properties": {
    "gn:admin1_code":"4",
    "gn:admin2_code":"1303502.0",
    "gn:asciiname":"Vera Cruz",
    "gn:country_code":"BR",
    "gn:dem":107,
    "gn:feature_class":"P",
    "gn:feature_code":"PPL",
    "gn:name":"Vera Cruz",
    "gn:population":0,
    "gn:timezone":"America/Manaus",
    "iso:country":"BR",
    "wof:name":"Vera Cruz",
    "wof:placetype":"locality"
},
  "geometry": {"coordinates":[-67.21666999999999,-8.08333],"type":"Point"}
}