{
  "type": "Feature",
  "properties": {
    "gn:admin1_code":"5",
    "gn:admin2_code":"2914703.0",
    "gn:asciiname":"Cajueiro",
    "gn:country_code":"BR",
    "gn:dem":281,
    "gn:feature_class":"P",
    "gn:feature_code":"PPL",
    "gn:name":"Cajueiro",
    "gn:population":0,
    "gn:timezone":"America/Bahia",
    "iso:country":"BR",
    "wof:name":"Cajueiro",
    "wof:placetype":"locality"
},
  "geometry": {"coordinates":[-40.33333,-12.51667],"type":"Point"}
}