{
  "type": "Feature",
  "properties": {
    "gn:admin1_code":"18.0",
    "gn:admin2_code":"4126678.0",
    "gn:asciiname":"Sitio Waldomiro Xavier da Silva",
    "gn:country_code":"BR",
    "gn:dem":731,
    "gn:feature_class":"P",
    "gn:feature_code":"PPL",
    "gn:name":"S\u00edtio Waldomiro Xavier da Silva",
    "gn:population":0,
    "gn:timezone":"America/Sao_Paulo",
    "iso:country":"BR",
    "name:por_x_preferred":[
        "S\u00edtio Waldomiro Xavier da Silva"
    ],
    "wof:name":"Sitio Waldomiro Xavier da Silva",
    "wof:placetype":"locality"
},
  "geometry": {"coordinates":[-50.986,-23.8804],"type":"Point"}
}