{
  "type": "Feature",
  "properties": {
    "gn:admin1_code":"18.0",
    "gn:admin2_code":"4114302.0",
    "gn:asciiname":"Sitio Antonio O. de Lima",
    "gn:country_code":"BR",
    "gn:dem":874,
    "gn:feature_class":"P",
    "gn:feature_code":"PPL",
    "gn:name":"S\u00edtio Ant\u00f4nio O. de Lima",
    "gn:population":0,
    "gn:timezone":"America/Sao_Paulo",
    "iso:country":"BR",
    "name:por_x_preferred":[
        "S\u00edtio Ant\u00f4nio O. de Lima"
    ],
    "wof:name":"Sitio Antonio O. de Lima",
    "wof:placetype":"locality"
},
  "geometry": {"coordinates":[-49.3099,-25.9286],"type":"Point"}
}