{
  "type": "Feature",
  "properties": {
    "gn:admin1_code":"02",
    "gn:admin2_code":"2703809.0",
    "gn:asciiname":"Urucu",
    "gn:country_code":"BR",
    "gn:dem":120,
    "gn:feature_class":"P",
    "gn:feature_code":"PPL",
    "gn:name":"Urucu",
    "gn:population":0,
    "gn:timezone":"America/Maceio",
    "iso:country":"BR",
    "wof:name":"Urucu",
    "wof:placetype":"locality"
},
  "geometry": {"coordinates":[-35.75,-9.11667],"type":"Point"}
}