{
  "type": "Feature",
  "properties": {
    "gn:admin1_code":"18.0",
    "gn:admin2_code":"4127809.0",
    "gn:asciiname":"Sitio Jorge Garanhane",
    "gn:country_code":"BR",
    "gn:dem":699,
    "gn:feature_class":"P",
    "gn:feature_code":"PPL",
    "gn:name":"S\u00edtio Jorge Garanhane",
    "gn:population":0,
    "gn:timezone":"America/Sao_Paulo",
    "iso:country":"BR",
    "name:por_x_preferred":[
        "S\u00edtio Jorge Garanhane"
    ],
    "wof:name":"Sitio Jorge Garanhane",
    "wof:placetype":"locality"
},
  "geometry": {"coordinates":[-49.8981,-23.6614],"type":"Point"}
}