{
  "type": "Feature",
  "properties": {
    "gn:admin1_code":"5",
    "gn:admin2_code":"2917805.0",
    "gn:asciiname":"Outeiro Mata-Fome",
    "gn:cc2":"BR",
    "gn:country_code":"BR",
    "gn:dem":31,
    "gn:feature_class":"P",
    "gn:feature_code":"PPL",
    "gn:name":"Outeiro Mata-Fome",
    "gn:population":0,
    "gn:timezone":"America/Bahia",
    "iso:country":"BR",
    "name:und_x_variant":[
        "Outeiro",
        "Outeiro Mata-Fome"
    ],
    "wof:name":"Outeiro Mata-Fome",
    "wof:placetype":"locality"
},
  "geometry": {"coordinates":[-38.95,-13.08333],"type":"Point"}
}