{
  "type": "Feature",
  "properties": {
    "gn:admin1_code":"27.0",
    "gn:admin2_code":"3524600.0",
    "gn:asciiname":"Sitio das Palmeiras",
    "gn:country_code":"BR",
    "gn:dem":93,
    "gn:feature_class":"P",
    "gn:feature_code":"PPL",
    "gn:name":"S\u00edtio das Palmeiras",
    "gn:population":0,
    "gn:timezone":"America/Sao_Paulo",
    "iso:country":"BR",
    "name:por_x_preferred":[
        "S\u00edtio das Palmeiras"
    ],
    "wof:name":"Sitio das Palmeiras",
    "wof:placetype":"locality"
},
  "geometry": {"coordinates":[-48.10326,-24.58853],"type":"Point"}
}