{
  "type": "Feature",
  "properties": {
    "gn:admin1_code":"20",
    "gn:admin2_code":"2201150.0",
    "gn:asciiname":"Brejao",
    "gn:country_code":"BR",
    "gn:dem":351,
    "gn:feature_class":"P",
    "gn:feature_code":"PPL",
    "gn:name":"Brej\u00e3o",
    "gn:population":0,
    "gn:timezone":"America/Fortaleza",
    "iso:country":"BR",
    "wof:name":"Brejao",
    "wof:placetype":"locality"
},
  "geometry": {"coordinates":[-45.365,-8.69056],"type":"Point"}
}