{
  "type": "Feature",
  "properties": {
    "gn:admin1_code":"17",
    "gn:admin2_code":"2516201.0",
    "gn:asciiname":"Panelas",
    "gn:country_code":"BR",
    "gn:dem":315,
    "gn:feature_class":"P",
    "gn:feature_code":"PPL",
    "gn:name":"Panelas",
    "gn:population":0,
    "gn:timezone":"America/Fortaleza",
    "iso:country":"BR",
    "name:bpy_x_preferred":[
        "\u09aa\u09be\u09a8\u09af\u09bc\u09c7\u09b2\u09be\u09b8"
    ],
    "name:eus_x_preferred":[
        "Panelas"
    ],
    "name:fra_x_preferred":[
        "Panelas"
    ],
    "name:ita_x_preferred":[
        "Panelas"
    ],
    "name:kat_x_preferred":[
        "\u10de\u10d0\u10dc\u10d4\u10da\u10d0\u10e1\u10d8"
    ],
    "name:kaz_x_preferred":[
        "\u041f\u0430\u043d\u0435\u043b\u0430\u0441"
    ],
    "name:mlg_x_preferred":[
        "Panelas"
    ],
    "name:nld_x_preferred":[
        "Panelas"
    ],
    "name:nor_x_preferred":[
        "Panelas"
    ],
    "name:por_x_preferred":[
        "Panelas"
    ],
    "name:ron_x_preferred":[
        "Panelas"
    ],
    "name:rus_x_preferred":[
        "\u041f\u0430\u043d\u0435\u043b\u0430\u0441"
    ],
    "name:vie_x_preferred":[
        "Panelas"
    ],
    "name:vol_x_preferred":[
        "Panelas"
    ],
    "name:war_x_preferred":[
        "Panelas"
    ],
    "name:zho_x_preferred":[
        "\u5e15\u5185\u62c9\u65af"
    ],
    "wof:name":"Panelas",
    "wof:placetype":"locality"
},
  "geometry": {"coordinates":[-38.21667,-6.85],"type":"Point"}
}