{
  "type": "Feature",
  "properties": {
    "gn:admin1_code":"11",
    "gn:admin2_code":"5007406.0",
    "gn:asciiname":"Tres Marias",
    "gn:cc2":"BR",
    "gn:country_code":"BR",
    "gn:dem":136,
    "gn:feature_class":"P",
    "gn:feature_code":"PPL",
    "gn:name":"Tr\u00eas Marias",
    "gn:population":0,
    "gn:timezone":"America/Campo_Grande",
    "iso:country":"BR",
    "name:und_x_variant":[
        "Fazenda Tr\u00eas Marias",
        "Tr\u00eas Marias"
    ],
    "wof:name":"Tres Marias",
    "wof:placetype":"locality"
},
  "geometry": {"coordinates":[-55.35,-19.13333],"type":"Point"}
}