{
  "type": "Feature",
  "properties": {
    "gn:admin1_code":"31",
    "gn:admin2_code":"1715259.0",
    "gn:asciiname":"Goiandira",
    "gn:country_code":"BR",
    "gn:dem":636,
    "gn:feature_class":"P",
    "gn:feature_code":"PPL",
    "gn:name":"Goiandira",
    "gn:population":0,
    "gn:timezone":"America/Araguaina",
    "iso:country":"BR",
    "name:bpy_x_preferred":[
        "\u0997\u09cb\u0987\u0986\u09a8\u09a1\u09bf\u09b0\u09be"
    ],
    "name:ceb_x_preferred":[
        "Goiandira"
    ],
    "name:deu_x_preferred":[
        "Goiandira"
    ],
    "name:epo_x_preferred":[
        "Goiandira"
    ],
    "name:eus_x_preferred":[
        "Goiandira"
    ],
    "name:fra_x_preferred":[
        "Goiandira"
    ],
    "name:hye_x_preferred":[
        "\u0533\u0578\u0575\u0561\u0576\u0564\u056b\u0580\u0561"
    ],
    "name:ita_x_preferred":[
        "Goiandira"
    ],
    "name:kat_x_preferred":[
        "\u10d2\u10dd\u10d8\u10d0\u10dc\u10d3\u10d8\u10e0\u10d0"
    ],
    "name:kaz_x_preferred":[
        "\u0413\u043e\u044f\u043d\u0434\u0438\u0440\u0430"
    ],
    "name:mlg_x_preferred":[
        "Goiandira"
    ],
    "name:nld_x_preferred":[
        "Goiandira"
    ],
    "name:nor_x_preferred":[
        "Goiandira"
    ],
    "name:por_x_preferred":[
        "Goiandira"
    ],
    "name:ron_x_preferred":[
        "Goiandira"
    ],
    "name:rus_x_preferred":[
        "\u0413\u043e\u044f\u043d\u0434\u0438\u0440\u0430"
    ],
    "name:swe_x_preferred":[
        "Goiandira"
    ],
    "name:vie_x_preferred":[
        "Goiandira"
    ],
    "name:vol_x_preferred":[
        "Goiandira"
    ],
    "name:war_x_preferred":[
        "Goiandira"
    ],
    "name:zho_x_preferred":[
        "\u6208\u626c\u8fea\u62c9"
    ],
    "wof:name":"Goiandira",
    "wof:placetype":"locality"
},
  "geometry": {"coordinates":[-46.66667,-11.76667],"type":"Point"}
}