{
  "type": "Feature",
  "properties": {
    "gn:admin1_code":"31",
    "gn:admin2_code":"1715259.0",
    "gn:asciiname":"Goiandira",
    "gn:country_code":"BR",
    "gn:dem":636,
    "gn:feature_class":"P",
    "gn:feature_code":"PPL",
    "gn:name":"Goiandira",
    "gn:population":0,
    "gn:timezone":"America/Araguaina",
    "iso:country":"BR",
    "wof:name":"Goiandira",
    "wof:placetype":"locality"
},
  "geometry": {"coordinates":[-46.66667,-11.76667],"type":"Point"}
}