{
  "type": "Feature",
  "properties": {
    "gn:admin1_code":"26",
    "gn:admin2_code":"4203303.0",
    "gn:asciiname":"Sitio Jaco Pikos",
    "gn:country_code":"BR",
    "gn:dem":822,
    "gn:feature_class":"P",
    "gn:feature_code":"PPL",
    "gn:name":"S\u00edtio Jac\u00f3 Pikos",
    "gn:population":0,
    "gn:timezone":"America/Sao_Paulo",
    "iso:country":"BR",
    "name:por_x_preferred":[
        "S\u00edtio Jac\u00f3 Pikos"
    ],
    "wof:name":"Sitio Jaco Pikos",
    "wof:placetype":"locality"
},
  "geometry": {"coordinates":[-49.40092,-26.17581],"type":"Point"}
}