{
  "type": "Feature",
  "properties": {
    "gn:admin1_code":"18.0",
    "gn:admin2_code":"4121208.0",
    "gn:asciiname":"Sitio Tereza Drevinaki",
    "gn:country_code":"BR",
    "gn:dem":864,
    "gn:feature_class":"P",
    "gn:feature_code":"PPL",
    "gn:name":"S\u00edtio Tereza Drevinaki",
    "gn:population":0,
    "gn:timezone":"America/Sao_Paulo",
    "iso:country":"BR",
    "name:por_x_preferred":[
        "S\u00edtio Tereza Drevinaki"
    ],
    "wof:name":"Sitio Tereza Drevinaki",
    "wof:placetype":"locality"
},
  "geometry": {"coordinates":[-49.5132,-25.8297],"type":"Point"}
}