{
  "type": "Feature",
  "properties": {
    "gn:admin1_code":"27.0",
    "gn:admin2_code":"3548609.0",
    "gn:asciiname":"Areas",
    "gn:country_code":"BR",
    "gn:dem":885,
    "gn:feature_class":"P",
    "gn:feature_code":"PPLL",
    "gn:name":"\u00c1reas",
    "gn:population":0,
    "gn:timezone":"America/Sao_Paulo",
    "iso:country":"BR",
    "name:por_x_preferred":[
        "\u00c1reas"
    ],
    "wof:name":"Areas",
    "wof:placetype":"locality"
},
  "geometry": {"coordinates":[-45.71839,-22.59148],"type":"Point"}
}