{
  "type": "Feature",
  "properties": {
    "gn:admin1_code":"27",
    "gn:admin2_code":"3525201.0",
    "gn:asciiname":"Sitio Ipe-Branco",
    "gn:country_code":"BR",
    "gn:dem":784,
    "gn:feature_class":"P",
    "gn:feature_code":"PPL",
    "gn:name":"S\u00edtio Ip\u00ea-Branco",
    "gn:population":0,
    "gn:timezone":"America/Sao_Paulo",
    "iso:country":"BR",
    "name:por_x_preferred":[
        "S\u00edtio Ip\u00ea-Branco"
    ],
    "wof:name":"Sitio Ipe-Branco",
    "wof:placetype":"locality"
},
  "geometry": {"coordinates":[-46.72589,-23.09382],"type":"Point"}
}