{
  "type": "Feature",
  "properties": {
    "gn:admin1_code":"26",
    "gn:admin2_code":"4210100.0",
    "gn:asciiname":"Sitio Odine M. Teixeira",
    "gn:country_code":"BR",
    "gn:dem":861,
    "gn:feature_class":"P",
    "gn:feature_code":"PPL",
    "gn:name":"S\u00edtio Odine M. Teixeira",
    "gn:population":0,
    "gn:timezone":"America/Sao_Paulo",
    "iso:country":"BR",
    "name:por_x_preferred":[
        "S\u00edtio Odine M. Teixeira"
    ],
    "wof:name":"Sitio Odine M. Teixeira",
    "wof:placetype":"locality"
},
  "geometry": {"coordinates":[-49.7835,-26.2038],"type":"Point"}
}