{
  "type": "Feature",
  "properties": {
    "gn:admin1_code":"11",
    "gn:admin2_code":"5001243.0",
    "gn:asciiname":"Tagi",
    "gn:country_code":"BR",
    "gn:dem":498,
    "gn:feature_class":"P",
    "gn:feature_code":"PPL",
    "gn:name":"Tagi",
    "gn:population":0,
    "gn:timezone":"America/Campo_Grande",
    "iso:country":"BR",
    "wof:name":"Tagi",
    "wof:placetype":"locality"
},
  "geometry": {"coordinates":[-55.38333000000001,-22.78333],"type":"Point"}
}