{
  "type": "Feature",
  "properties": {
    "gn:admin1_code":"13",
    "gn:admin2_code":"2102101.0",
    "gn:asciiname":"Barro Vermelho",
    "gn:country_code":"BR",
    "gn:dem":73,
    "gn:feature_class":"P",
    "gn:feature_code":"PPL",
    "gn:name":"Barro Vermelho",
    "gn:population":0,
    "gn:timezone":"America/Fortaleza",
    "iso:country":"BR",
    "wof:name":"Barro Vermelho",
    "wof:placetype":"locality"
},
  "geometry": {"coordinates":[-42.74389,-3.70111],"type":"Point"}
}