{
  "type": "Feature",
  "properties": {
    "gn:admin1_code":"18.0",
    "gn:admin2_code":"4102703.0",
    "gn:asciiname":"Sitio Douradinho",
    "gn:country_code":"BR",
    "gn:dem":438,
    "gn:feature_class":"P",
    "gn:feature_code":"PPL",
    "gn:name":"S\u00edtio Douradinho",
    "gn:population":0,
    "gn:timezone":"America/Sao_Paulo",
    "iso:country":"BR",
    "name:por_x_preferred":[
        "S\u00edtio Douradinho"
    ],
    "wof:name":"Sitio Douradinho",
    "wof:placetype":"locality"
},
  "geometry": {"coordinates":[-50.1478,-23.1187],"type":"Point"}
}