{
  "type": "Feature",
  "properties": {
    "iso:country":"BR",
    "name:bre_x_preferred":[
        "S\u00e3o Francisco"
    ],
    "name:ceb_x_preferred":[
        "S\u00e3o Francisco"
    ],
    "name:deu_x_preferred":[
        "S\u00e3o Francisco"
    ],
    "name:fra_x_preferred":[
        "S\u00e3o Francisco"
    ],
    "name:hrv_x_preferred":[
        "S\u00e3o Francisco"
    ],
    "name:ita_x_preferred":[
        "S\u00e3o Francisco"
    ],
    "name:mlg_x_preferred":[
        "S\u00e3o Francisco"
    ],
    "name:nld_x_preferred":[
        "S\u00e3o Francisco"
    ],
    "name:nor_x_preferred":[
        "S\u00e3o Francisco"
    ],
    "name:pol_x_preferred":[
        "S\u00e3o Francisco"
    ],
    "name:por_x_colloquial":[
        "Sao Francisco"
    ],
    "name:por_x_preferred":[
        "S\u00e3o Francisco"
    ],
    "name:por_x_variant":[
        "S\u00e3o Franciso"
    ],
    "name:rus_x_preferred":[
        "\u0421\u0430\u043d-\u0424\u0440\u0430\u043d\u0441\u0438\u0441\u043a\u0443"
    ],
    "name:sco_x_preferred":[
        "S\u00e3o Francisco"
    ],
    "name:spa_x_preferred":[
        "S\u00e3o Francisco"
    ],
    "name:swe_x_preferred":[
        "S\u00e3o Francisco"
    ],
    "name:vie_x_preferred":[
        "S\u00e3o Francisco"
    ],
    "name:vol_x_preferred":[
        "S\u00e3o Francisco"
    ],
    "qs:gn_adm0_cc":"BR",
    "qs:gn_fcode":"PPL",
    "qs:gn_local":3456283,
    "qs:gn_nam_loc":"Niter\u00f3i, Niter\u00f3i, Rio de Janeiro, BR",
    "qs:gn_namadm1":"21",
    "qs:gn_name":"S\u00e3o Franciso",
    "qs:local_max":2228,
    "qs:local_sum":7420,
    "qs:localhoods":12,
    "qs:name":"S\u00e3o Francisco",
    "qs:name_adm0":"Brasil",
    "qs:name_adm1":"Rio de Janeiro",
    "qs:name_adm2":"Niter\u00f3i",
    "qs:name_local":"Niter\u00f3i",
    "qs:photo_max":80,
    "qs:photo_sum":242,
    "qs:placetype":"Suburb",
    "qs:quad_count":13,
    "qs:woe_adm0":23424768,
    "qs:woe_adm1":2344862,
    "qs:woe_adm2":12581047,
    "qs:woe_lau":0,
    "qs:woe_local":455891,
    "qs:woe_ver":"7.10.0",
    "wof:lang":[
        "por"
    ],
    "wof:name":"S\u00e3o Francisco",
    "wof:placetype":"neighbourhood"
},
  "geometry": {"coordinates":[-43.093171,-22.91814],"type":"Point"}
}