{
  "type": "Feature",
  "properties": {
    "gn:admin1_code":"27.0",
    "gn:admin2_code":"3545308.0",
    "gn:asciiname":"Lagoao",
    "gn:country_code":"BR",
    "gn:dem":654,
    "gn:feature_class":"P",
    "gn:feature_code":"PPLL",
    "gn:name":"Lago\u00e3o",
    "gn:population":0,
    "gn:timezone":"America/Sao_Paulo",
    "iso:country":"BR",
    "name:por_x_preferred":[
        "Lago\u00e3o"
    ],
    "wof:name":"Lagoao",
    "wof:placetype":"locality"
},
  "geometry": {"coordinates":[-47.594,-23.6734],"type":"Point"}
}