{
  "type": "Feature",
  "properties": {
    "gn:admin1_code":"13.0",
    "gn:admin2_code":"2104206.0",
    "gn:asciiname":"Catumbi",
    "gn:country_code":"BR",
    "gn:dem":175,
    "gn:feature_class":"P",
    "gn:feature_code":"PPL",
    "gn:name":"Catumbi",
    "gn:population":0,
    "gn:timezone":"America/Fortaleza",
    "iso:country":"BR",
    "name:fra_x_preferred":[
        "Catumbi"
    ],
    "name:ita_x_preferred":[
        "Catumbi"
    ],
    "name:por_x_preferred":[
        "Catumbi"
    ],
    "wof:name":"Catumbi",
    "wof:placetype":"locality"
},
  "geometry": {"coordinates":[-44.10565,-5.72758],"type":"Point"}
}