{
  "type": "Feature",
  "properties": {
    "gn:admin1_code":"30",
    "gn:admin2_code":"2600104.0",
    "gn:asciiname":"Curral Velho",
    "gn:country_code":"BR",
    "gn:dem":562,
    "gn:feature_class":"P",
    "gn:feature_code":"PPL",
    "gn:name":"Curral Velho",
    "gn:population":0,
    "gn:timezone":"America/Recife",
    "iso:country":"BR",
    "wof:name":"Curral Velho",
    "wof:placetype":"locality"
},
  "geometry": {"coordinates":[-37.68333,-7.68333],"type":"Point"}
}