{
  "type": "Feature",
  "properties": {
    "gn:admin1_code":"13",
    "gn:admin2_code":"2101731.0",
    "gn:asciiname":"Prata II",
    "gn:country_code":"BR",
    "gn:dem":67,
    "gn:feature_class":"P",
    "gn:feature_code":"PPL",
    "gn:name":"Prata II",
    "gn:population":0,
    "gn:timezone":"America/Fortaleza",
    "iso:country":"BR",
    "wof:name":"Prata II",
    "wof:placetype":"locality"
},
  "geometry": {"coordinates":[-43.35444,-3.08528],"type":"Point"}
}