{
  "type": "Feature",
  "properties": {
    "gn:admin1_code":"20",
    "gn:admin2_code":"2206696.0",
    "gn:asciiname":"Ilha Danta",
    "gn:country_code":"BR",
    "gn:dem":8,
    "gn:feature_class":"P",
    "gn:feature_code":"PPL",
    "gn:name":"Ilha Danta",
    "gn:population":0,
    "gn:timezone":"America/Fortaleza",
    "iso:country":"BR",
    "wof:name":"Ilha Danta",
    "wof:placetype":"locality"
},
  "geometry": {"coordinates":[-42.06222,-3.26667],"type":"Point"}
}