{
  "type": "Feature",
  "properties": {
    "gn:admin1_code":"30",
    "gn:admin2_code":"2605707.0",
    "gn:asciiname":"Serrote do Boi",
    "gn:country_code":"BR",
    "gn:dem":313,
    "gn:feature_class":"P",
    "gn:feature_code":"PPL",
    "gn:name":"Serrote do Boi",
    "gn:population":0,
    "gn:timezone":"America/Recife",
    "iso:country":"BR",
    "wof:name":"Serrote do Boi",
    "wof:placetype":"locality"
},
  "geometry": {"coordinates":[-38.48333,-8.78333],"type":"Point"}
}