{
  "type": "Feature",
  "properties": {
    "gn:admin1_code":"8",
    "gn:admin2_code":"3201209.0",
    "gn:asciiname":"Uniao",
    "gn:country_code":"BR",
    "gn:dem":53,
    "gn:feature_class":"P",
    "gn:feature_code":"PPL",
    "gn:name":"Uni\u00e3o",
    "gn:population":0,
    "gn:timezone":"America/Sao_Paulo",
    "iso:country":"BR",
    "name:por_x_preferred":[
        "Uni\u00e3o"
    ],
    "wof:name":"Uniao",
    "wof:placetype":"locality"
},
  "geometry": {"coordinates":[-41.08333,-20.91667],"type":"Point"}
}