{
  "type": "Feature",
  "properties": {
    "gn:admin1_code":"15",
    "gn:admin2_code":"3145109.0",
    "gn:asciiname":"Caete",
    "gn:cc2":"BR",
    "gn:country_code":"BR",
    "gn:dem":1102,
    "gn:feature_class":"P",
    "gn:feature_code":"PPL",
    "gn:name":"Caet\u00e9",
    "gn:population":0,
    "gn:timezone":"America/Sao_Paulo",
    "iso:country":"BR",
    "name:und_x_variant":[
        "Catete",
        "Caet\u00e9"
    ],
    "wof:name":"Caete",
    "wof:placetype":"locality"
},
  "geometry": {"coordinates":[-46.36667,-21.16667],"type":"Point"}
}