{
  "type": "Feature",
  "properties": {
    "gn:admin1_code":"28",
    "gn:admin2_code":"2800605.0",
    "gn:asciiname":"Porto das Cabras",
    "gn:country_code":"BR",
    "gn:dem":10,
    "gn:feature_class":"P",
    "gn:feature_code":"PPL",
    "gn:name":"P\u00f4rto das Cabras",
    "gn:population":0,
    "gn:timezone":"America/Maceio",
    "iso:country":"BR",
    "wof:name":"Porto das Cabras",
    "wof:placetype":"locality"
},
  "geometry": {"coordinates":[-36.95,-10.83333],"type":"Point"}
}