{
  "type": "Feature",
  "properties": {
    "gn:admin1_code":"18.0",
    "gn:admin2_code":"4112306.0",
    "gn:asciiname":"Sitio Edson Faroto",
    "gn:country_code":"BR",
    "gn:dem":666,
    "gn:feature_class":"P",
    "gn:feature_code":"PPL",
    "gn:name":"S\u00edtio Edson Faroto",
    "gn:population":0,
    "gn:timezone":"America/Sao_Paulo",
    "iso:country":"BR",
    "name:por_x_preferred":[
        "S\u00edtio Edson Faroto"
    ],
    "wof:name":"Sitio Edson Faroto",
    "wof:placetype":"locality"
},
  "geometry": {"coordinates":[-50.20002,-23.74732],"type":"Point"}
}