{
  "type": "Feature",
  "properties": {
    "gn:admin1_code":"23",
    "gn:admin2_code":"4307906.0",
    "gn:asciiname":"Caruara",
    "gn:cc2":"BR",
    "gn:country_code":"BR",
    "gn:dem":617,
    "gn:feature_class":"P",
    "gn:feature_code":"PPL",
    "gn:name":"Caruara",
    "gn:population":0,
    "gn:timezone":"America/Sao_Paulo",
    "iso:country":"BR",
    "name:und_x_variant":[
        "Cajuru",
        "Caruara"
    ],
    "wof:name":"Caruara",
    "wof:placetype":"locality"
},
  "geometry": {"coordinates":[-51.41667,-29.25],"type":"Point"}
}