{
  "type": "Feature",
  "properties": {
    "gn:admin1_code":"18.0",
    "gn:admin2_code":"4113205.0",
    "gn:asciiname":"Sitio Delfino Dalton",
    "gn:country_code":"BR",
    "gn:dem":855,
    "gn:feature_class":"P",
    "gn:feature_code":"PPL",
    "gn:name":"S\u00edtio Delfino Dalton",
    "gn:population":0,
    "gn:timezone":"America/Sao_Paulo",
    "iso:country":"BR",
    "name:por_x_preferred":[
        "S\u00edtio Delfino Dalton"
    ],
    "wof:name":"Sitio Delfino Dalton",
    "wof:placetype":"locality"
},
  "geometry": {"coordinates":[-49.5557,-25.8242],"type":"Point"}
}