{
  "type": "Feature",
  "properties": {
    "gn:admin1_code":"15",
    "gn:admin2_code":"3163904.0",
    "gn:asciiname":"Gabriel Martins",
    "gn:country_code":"BR",
    "gn:dem":1098,
    "gn:feature_class":"P",
    "gn:feature_code":"PPL",
    "gn:name":"Gabriel Martins",
    "gn:population":0,
    "gn:timezone":"America/Sao_Paulo",
    "iso:country":"BR",
    "name:por_x_preferred":[
        "Gabriel Martins"
    ],
    "wof:name":"Gabriel Martins",
    "wof:placetype":"locality"
},
  "geometry": {"coordinates":[-46.58333,-21.15],"type":"Point"}
}