{
  "type": "Feature",
  "properties": {
    "gn:admin1_code":"16.0",
    "gn:admin2_code":"1501907.0",
    "gn:asciiname":"Curucambaba",
    "gn:country_code":"BR",
    "gn:dem":19,
    "gn:feature_class":"P",
    "gn:feature_code":"PPL",
    "gn:name":"Curu\u00e7ambaba",
    "gn:population":0,
    "gn:timezone":"America/Belem",
    "iso:country":"BR",
    "wof:name":"Curucambaba",
    "wof:placetype":"locality"
},
  "geometry": {"coordinates":[-48.19865,-1.53642],"type":"Point"}
}