{
  "type": "Feature",
  "properties": {
    "gn:admin1_code":"18.0",
    "gn:admin2_code":"4124707.0",
    "gn:asciiname":"Sitio Casa Branca",
    "gn:country_code":"BR",
    "gn:dem":746,
    "gn:feature_class":"P",
    "gn:feature_code":"PPL",
    "gn:name":"S\u00edtio Casa Branca",
    "gn:population":0,
    "gn:timezone":"America/Sao_Paulo",
    "iso:country":"BR",
    "name:por_x_preferred":[
        "S\u00edtio Casa Branca"
    ],
    "wof:name":"Sitio Casa Branca",
    "wof:placetype":"locality"
},
  "geometry": {"coordinates":[-50.72477,-23.63641],"type":"Point"}
}