{
  "type": "Feature",
  "properties": {
    "gn:admin1_code":"18.0",
    "gn:admin2_code":"4107751.0",
    "gn:asciiname":"Sitio Jose L. de Oliveira",
    "gn:country_code":"BR",
    "gn:dem":619,
    "gn:feature_class":"P",
    "gn:feature_code":"PPL",
    "gn:name":"S\u00edtio Jos\u00e9 L. de Oliveira",
    "gn:population":0,
    "gn:timezone":"America/Sao_Paulo",
    "iso:country":"BR",
    "name:por_x_preferred":[
        "S\u00edtio Jos\u00e9 L. de Oliveira"
    ],
    "wof:name":"Sitio Jose L. de Oliveira",
    "wof:placetype":"locality"
},
  "geometry": {"coordinates":[-50.40306,-23.91613],"type":"Point"}
}