{
  "type": "Feature",
  "properties": {
    "gn:admin1_code":"18",
    "gn:admin2_code":"4115457.0",
    "gn:asciiname":"Alto do Cobre",
    "gn:country_code":"BR",
    "gn:dem":976,
    "gn:feature_class":"P",
    "gn:feature_code":"PPL",
    "gn:name":"Alto do Cobre",
    "gn:population":0,
    "gn:timezone":"America/Sao_Paulo",
    "iso:country":"BR",
    "wof:name":"Alto do Cobre",
    "wof:placetype":"locality"
},
  "geometry": {"coordinates":[-52.13333,-25.11667000000001],"type":"Point"}
}