{
  "type": "Feature",
  "properties": {
    "gn:admin1_code":"17",
    "gn:admin2_code":"2512101.0",
    "gn:asciiname":"Varzea da Cruz",
    "gn:country_code":"BR",
    "gn:dem":194,
    "gn:feature_class":"P",
    "gn:feature_code":"PPL",
    "gn:name":"V\u00e1rzea da Cruz",
    "gn:population":0,
    "gn:timezone":"America/Fortaleza",
    "iso:country":"BR",
    "wof:name":"Varzea da Cruz",
    "wof:placetype":"locality"
},
  "geometry": {"coordinates":[-37.83333,-6.86667],"type":"Point"}
}