{
  "type": "Feature",
  "properties": {
    "gn:admin1_code":"17",
    "gn:admin2_code":"2514107.0",
    "gn:asciiname":"Jaburu",
    "gn:country_code":"BR",
    "gn:dem":611,
    "gn:feature_class":"P",
    "gn:feature_code":"PPL",
    "gn:name":"Jaburu",
    "gn:population":0,
    "gn:timezone":"America/Fortaleza",
    "iso:country":"BR",
    "wof:name":"Jaburu",
    "wof:placetype":"locality"
},
  "geometry": {"coordinates":[-36.93333,-8.15],"type":"Point"}
}