{
  "type": "Feature",
  "properties": {
    "gn:admin1_code":"18.0",
    "gn:admin2_code":"4113205.0",
    "gn:asciiname":"Sitio Francisco Agular",
    "gn:country_code":"BR",
    "gn:dem":896,
    "gn:feature_class":"P",
    "gn:feature_code":"PPL",
    "gn:name":"S\u00edtio Francisco Agular",
    "gn:population":0,
    "gn:timezone":"America/Sao_Paulo",
    "iso:country":"BR",
    "name:por_x_preferred":[
        "S\u00edtio Francisco Agular"
    ],
    "wof:name":"Sitio Francisco Agular",
    "wof:placetype":"locality"
},
  "geometry": {"coordinates":[-49.9902,-25.83662],"type":"Point"}
}