{
  "type": "Feature",
  "properties": {
    "gn:admin1_code":"22",
    "gn:admin2_code":"2414209.0",
    "gn:asciiname":"Cibauma",
    "gn:country_code":"BR",
    "gn:dem":-9999,
    "gn:feature_class":"P",
    "gn:feature_code":"PPL",
    "gn:name":"Ciba\u00fama",
    "gn:population":0,
    "gn:timezone":"America/Fortaleza",
    "iso:country":"BR",
    "wof:name":"Cibauma",
    "wof:placetype":"locality"
},
  "geometry": {"coordinates":[-35.03333,-6.28333],"type":"Point"}
}