{
  "type": "Feature",
  "properties": {
    "gn:admin1_code":"20",
    "gn:admin2_code":"2202604.0",
    "gn:asciiname":"Fazenda Lagoa do Barro",
    "gn:country_code":"BR",
    "gn:dem":203,
    "gn:feature_class":"P",
    "gn:feature_code":"PPL",
    "gn:name":"Fazenda Lagoa do Barro",
    "gn:population":0,
    "gn:timezone":"America/Fortaleza",
    "iso:country":"BR",
    "wof:name":"Fazenda Lagoa do Barro",
    "wof:placetype":"locality"
},
  "geometry": {"coordinates":[-41.61667,-5.18333],"type":"Point"}
}