{
  "type": "Feature",
  "properties": {
    "gn:admin1_code":"26",
    "gn:admin2_code":"4217709.0",
    "gn:asciiname":"Soares",
    "gn:country_code":"BR",
    "gn:dem":32,
    "gn:feature_class":"P",
    "gn:feature_code":"PPL",
    "gn:name":"Soares",
    "gn:population":0,
    "gn:timezone":"America/Sao_Paulo",
    "iso:country":"BR",
    "name:por_x_preferred":[
        "Soares"
    ],
    "wof:name":"Soares",
    "wof:placetype":"locality"
},
  "geometry": {"coordinates":[-49.61667,-29.03333],"type":"Point"}
}