{
  "type": "Feature",
  "properties": {
    "gn:admin1_code":"02",
    "gn:admin2_code":"2706406.0",
    "gn:asciiname":"Cacimbas",
    "gn:country_code":"BR",
    "gn:dem":234,
    "gn:feature_class":"P",
    "gn:feature_code":"PPL",
    "gn:name":"Cacimbas",
    "gn:population":0,
    "gn:timezone":"America/Maceio",
    "iso:country":"BR",
    "wof:name":"Cacimbas",
    "wof:placetype":"locality"
},
  "geometry": {"coordinates":[-37.61667,-9.51667],"type":"Point"}
}