{
  "type": "Feature",
  "properties": {
    "gn:admin1_code":"02",
    "gn:admin2_code":"2706406.0",
    "gn:asciiname":"Cacimbas",
    "gn:country_code":"BR",
    "gn:dem":234,
    "gn:feature_class":"P",
    "gn:feature_code":"PPL",
    "gn:name":"Cacimbas",
    "gn:population":0,
    "gn:timezone":"America/Maceio",
    "iso:country":"BR",
    "name:bpy_x_preferred":[
        "\u0995\u09be\u09b8\u09bf\u09ae\u09ac\u09be\u09b8"
    ],
    "name:ceb_x_preferred":[
        "Cacimbas"
    ],
    "name:epo_x_preferred":[
        "Cacimbas"
    ],
    "name:eus_x_preferred":[
        "Cacimbas"
    ],
    "name:fra_x_preferred":[
        "Cacimbas"
    ],
    "name:hye_x_preferred":[
        "\u053f\u0561\u057d\u056b\u0574\u0562\u0561\u057d"
    ],
    "name:ita_x_preferred":[
        "Cacimbas"
    ],
    "name:kat_x_preferred":[
        "\u10d9\u10d0\u10e1\u10d8\u10db\u10d1\u10d0\u10e1\u10d8"
    ],
    "name:kaz_x_preferred":[
        "\u041a\u0430\u0441\u0438\u043c\u0431\u0430\u0441"
    ],
    "name:mlg_x_preferred":[
        "Cacimbas"
    ],
    "name:nld_x_preferred":[
        "Cacimbas"
    ],
    "name:nor_x_preferred":[
        "Cacimbas"
    ],
    "name:por_x_preferred":[
        "Cacimbas"
    ],
    "name:ron_x_preferred":[
        "Cacimbas"
    ],
    "name:rus_x_preferred":[
        "\u041a\u0430\u0441\u0438\u043c\u0431\u0430\u0441"
    ],
    "name:swe_x_preferred":[
        "Cacimbas"
    ],
    "name:vie_x_preferred":[
        "Cacimbas"
    ],
    "name:vol_x_preferred":[
        "Cacimbas"
    ],
    "name:war_x_preferred":[
        "Cacimbas"
    ],
    "name:zho_x_preferred":[
        "\u5361\u8f9b\u5df4\u65af"
    ],
    "wof:name":"Cacimbas",
    "wof:placetype":"locality"
},
  "geometry": {"coordinates":[-37.61667,-9.51667],"type":"Point"}
}