{
  "type": "Feature",
  "properties": {
    "gn:admin1_code":"27.0",
    "gn:admin2_code":"3545308.0",
    "gn:asciiname":"Fazendinha",
    "gn:country_code":"BR",
    "gn:dem":772,
    "gn:feature_class":"P",
    "gn:feature_code":"PPLL",
    "gn:name":"Fazendinha",
    "gn:population":0,
    "gn:timezone":"America/Sao_Paulo",
    "iso:country":"BR",
    "name:por_x_preferred":[
        "Fazendinha"
    ],
    "wof:name":"Fazendinha",
    "wof:placetype":"locality"
},
  "geometry": {"coordinates":[-47.53379,-23.6975],"type":"Point"}
}