{
  "type": "Feature",
  "properties": {
    "gn:admin1_code":"26.0",
    "gn:admin2_code":"4210100.0",
    "gn:asciiname":"Sitio Lauro Ulbrich",
    "gn:country_code":"BR",
    "gn:dem":796,
    "gn:feature_class":"P",
    "gn:feature_code":"PPL",
    "gn:name":"S\u00edtio Lauro Ulbrich",
    "gn:population":0,
    "gn:timezone":"America/Sao_Paulo",
    "iso:country":"BR",
    "name:por_x_preferred":[
        "S\u00edtio Lauro Ulbrich"
    ],
    "wof:name":"Sitio Lauro Ulbrich",
    "wof:placetype":"locality"
},
  "geometry": {"coordinates":[-49.9834,-26.0505],"type":"Point"}
}