{
  "type": "Feature",
  "properties": {
    "gn:admin1_code":"30",
    "gn:admin2_code":"2600500.0",
    "gn:asciiname":"Tanquinho de Baixo",
    "gn:country_code":"BR",
    "gn:dem":538,
    "gn:feature_class":"P",
    "gn:feature_code":"PPL",
    "gn:name":"Tanquinho de Baixo",
    "gn:population":0,
    "gn:timezone":"America/Recife",
    "iso:country":"BR",
    "wof:name":"Tanquinho de Baixo",
    "wof:placetype":"locality"
},
  "geometry": {"coordinates":[-37.13333,-9.25],"type":"Point"}
}