{
  "type": "Feature",
  "properties": {
    "gn:admin1_code":"18",
    "gn:admin2_code":"4111407.0",
    "gn:asciiname":"Fojos",
    "gn:country_code":"BR",
    "gn:dem":854,
    "gn:feature_class":"P",
    "gn:feature_code":"PPL",
    "gn:name":"Fojos",
    "gn:population":0,
    "gn:timezone":"America/Sao_Paulo",
    "iso:country":"BR",
    "wof:name":"Fojos",
    "wof:placetype":"locality"
},
  "geometry": {"coordinates":[-50.78333,-24.96667],"type":"Point"}
}