{
  "type": "Feature",
  "properties": {
    "gn:admin1_code":"27",
    "gn:admin2_code":"3502754.0",
    "gn:asciiname":"Sitio Airam",
    "gn:country_code":"BR",
    "gn:dem":897,
    "gn:feature_class":"P",
    "gn:feature_code":"PPL",
    "gn:name":"S\u00edtio Airam",
    "gn:population":0,
    "gn:timezone":"America/Sao_Paulo",
    "iso:country":"BR",
    "name:por_x_preferred":[
        "S\u00edtio Airam"
    ],
    "wof:name":"Sitio Airam",
    "wof:placetype":"locality"
},
  "geometry": {"coordinates":[-47.00549,-23.50186],"type":"Point"}
}