{
  "type": "Feature",
  "properties": {
    "gn:admin1_code":"4.0",
    "gn:admin2_code":"1303957.0",
    "gn:asciiname":"Rancho de Joao Farias",
    "gn:country_code":"BR",
    "gn:dem":39,
    "gn:feature_class":"P",
    "gn:feature_code":"PPLL",
    "gn:name":"Rancho de Jo\u00e3o Farias",
    "gn:population":0,
    "gn:timezone":"America/Manaus",
    "iso:country":"BR",
    "name:por_x_preferred":[
        "Rancho de Jo\u00e3o Farias"
    ],
    "wof:name":"Rancho de Joao Farias",
    "wof:placetype":"locality"
},
  "geometry": {"coordinates":[-58.58639,-1.7696],"type":"Point"}
}