{
  "type": "Feature",
  "properties": {
    "gn:admin1_code":"21",
    "gn:admin2_code":"3302403.0",
    "gn:asciiname":"Imbetiba",
    "gn:country_code":"BR",
    "gn:dem":7,
    "gn:feature_class":"P",
    "gn:feature_code":"PPL",
    "gn:name":"Imbetiba",
    "gn:population":0,
    "gn:timezone":"America/Sao_Paulo",
    "iso:country":"BR",
    "name:por_x_preferred":[
        "Imbetiba"
    ],
    "wof:name":"Imbetiba",
    "wof:placetype":"locality"
},
  "geometry": {"coordinates":[-41.78333,-22.38333],"type":"Point"}
}