{
  "type": "Feature",
  "properties": {
    "gn:admin1_code":"26",
    "gn:admin2_code":"4210100.0",
    "gn:asciiname":"Sitio Romeu Cariolatt",
    "gn:country_code":"BR",
    "gn:dem":938,
    "gn:feature_class":"P",
    "gn:feature_code":"PPL",
    "gn:name":"S\u00edtio Romeu Cariolatt",
    "gn:population":0,
    "gn:timezone":"America/Sao_Paulo",
    "iso:country":"BR",
    "name:por_x_preferred":[
        "S\u00edtio Romeu Cariolatt"
    ],
    "wof:name":"Sitio Romeu Cariolatt",
    "wof:placetype":"locality"
},
  "geometry": {"coordinates":[-49.9021,-26.2173],"type":"Point"}
}