{
  "type": "Feature",
  "properties": {
    "gn:admin1_code":"18.0",
    "gn:admin2_code":"4124103.0",
    "gn:asciiname":"Sitio Sao Jorge",
    "gn:country_code":"BR",
    "gn:dem":439,
    "gn:feature_class":"P",
    "gn:feature_code":"PPL",
    "gn:name":"S\u00edtio S\u00e3o Jorge",
    "gn:population":0,
    "gn:timezone":"America/Sao_Paulo",
    "iso:country":"BR",
    "name:por_x_preferred":[
        "S\u00edtio S\u00e3o Jorge"
    ],
    "wof:name":"Sitio Sao Jorge",
    "wof:placetype":"locality"
},
  "geometry": {"coordinates":[-50.1911,-23.1814],"type":"Point"}
}