{
  "type": "Feature",
  "properties": {
    "gn:gn_country":"BR",
    "gn:gn_fcode":"PPL",
    "gn:gn_pop":0,
    "iso:country":"BR",
    "name:bpy_x_preferred":[
        "\u09b8\u09cb\u09ac\u09cd\u09b0\u09be\u09a1\u09bf\u09a8\u09b9\u09cb"
    ],
    "name:ceb_x_preferred":[
        "Sobradinho"
    ],
    "name:deu_x_preferred":[
        "Sobradinho"
    ],
    "name:fra_x_preferred":[
        "Sobradinho"
    ],
    "name:ita_x_preferred":[
        "Sobradinho"
    ],
    "name:nld_x_preferred":[
        "Sobradinho"
    ],
    "name:nor_x_preferred":[
        "Sobradinho"
    ],
    "name:por_x_preferred":[
        "Sobradinho"
    ],
    "name:rus_x_preferred":[
        "\u0421\u043e\u0431\u0440\u0430\u0434\u0438\u043d\u044c\u044e"
    ],
    "name:sco_x_preferred":[
        "Sobradihno"
    ],
    "name:swe_x_preferred":[
        "Sobradinho"
    ],
    "name:vie_x_preferred":[
        "Sobradinho"
    ],
    "name:vol_x_preferred":[
        "Sobradinho"
    ],
    "name:zho_x_preferred":[
        "\u5c0f\u697c\u9547"
    ],
    "qs_pg:aaroncc":"BR",
    "qs_pg:gn_country":"BR",
    "qs_pg:gn_fcode":"PPL",
    "qs_pg:gn_pop":0,
    "qs_pg:name":"Sobradinho",
    "qs_pg:name_adm0":"Brasil",
    "qs_pg:name_adm1":"Distrito Federal",
    "qs_pg:photos":745,
    "qs_pg:photos_1k":151,
    "qs_pg:photos_9k":3,
    "qs_pg:photos_9r":5,
    "qs_pg:photos_all":745,
    "qs_pg:photos_sr":8,
    "qs_pg:pop_sr":0,
    "qs_pg:qs_pg_placetype":"locality",
    "qs_pg:qs_pg_placetype_gp":"Town",
    "qs_pg:woe_adm0":23424768,
    "woe:adm0_id":23424768,
    "woe:name_adm0":"Brasil",
    "woe:name_adm1":"Distrito Federal",
    "woe:placetype":"Town",
    "wof:name":"Sobradinho",
    "wof:placetype":"locality"
},
  "geometry": {"coordinates":[-47.81667,-15.63333],"type":"Point"}
}