{
  "type": "Feature",
  "properties": {
    "gn:admin1_code":"16",
    "gn:admin2_code":"1505502.0",
    "gn:asciiname":"Araruna",
    "gn:country_code":"BR",
    "gn:dem":74,
    "gn:feature_class":"P",
    "gn:feature_code":"PPL",
    "gn:name":"Araruna",
    "gn:population":0,
    "gn:timezone":"America/Belem",
    "iso:country":"BR",
    "name:ara_x_preferred":[
        "\u0623\u0631\u0627\u0646\u0648\u0646\u0627"
    ],
    "name:bpy_x_preferred":[
        "\u09f1\u09be\u09b0\u09be\u09b0\u09c1\u09a8\u09be"
    ],
    "name:ceb_x_preferred":[
        "Araruna"
    ],
    "name:deu_x_preferred":[
        "Araruna"
    ],
    "name:fra_x_preferred":[
        "Araruna"
    ],
    "name:ita_x_preferred":[
        "Araruna"
    ],
    "name:nld_x_preferred":[
        "Araruna"
    ],
    "name:nor_x_preferred":[
        "Araruna"
    ],
    "name:por_x_preferred":[
        "Araruna"
    ],
    "name:ron_x_preferred":[
        "Araruna"
    ],
    "name:rus_x_preferred":[
        "\u0410\u0440\u0430\u0440\u0443\u043d\u0430"
    ],
    "name:swe_x_preferred":[
        "Araruna"
    ],
    "name:vol_x_preferred":[
        "Araruna"
    ],
    "wof:name":"Araruna",
    "wof:placetype":"locality"
},
  "geometry": {"coordinates":[-46.64091,-2.79143],"type":"Point"}
}