{
  "type": "Feature",
  "properties": {
    "gn:admin1_code":"16",
    "gn:admin2_code":"1505502.0",
    "gn:asciiname":"Araruna",
    "gn:country_code":"BR",
    "gn:dem":74,
    "gn:feature_class":"P",
    "gn:feature_code":"PPL",
    "gn:name":"Araruna",
    "gn:population":0,
    "gn:timezone":"America/Belem",
    "iso:country":"BR",
    "wof:name":"Araruna",
    "wof:placetype":"locality"
},
  "geometry": {"coordinates":[-46.64091,-2.79143],"type":"Point"}
}