{
  "type": "Feature",
  "properties": {
    "gn:admin1_code":"20",
    "gn:admin2_code":"2208403.0",
    "gn:asciiname":"Bebedouro de Cima",
    "gn:country_code":"BR",
    "gn:dem":85,
    "gn:feature_class":"P",
    "gn:feature_code":"PPL",
    "gn:name":"Bebedouro de Cima",
    "gn:population":0,
    "gn:timezone":"America/Fortaleza",
    "iso:country":"BR",
    "wof:name":"Bebedouro de Cima",
    "wof:placetype":"locality"
},
  "geometry": {"coordinates":[-41.53333,-4.16667],"type":"Point"}
}