{
  "type": "Feature",
  "properties": {
    "gn:admin1_code":"30",
    "gn:admin2_code":"2613008.0",
    "gn:asciiname":"Sitio do Meio",
    "gn:country_code":"BR",
    "gn:dem":608,
    "gn:feature_class":"P",
    "gn:feature_code":"PPL",
    "gn:name":"S\u00edtio do Meio",
    "gn:population":0,
    "gn:timezone":"America/Recife",
    "iso:country":"BR",
    "wof:name":"Sitio do Meio",
    "wof:placetype":"locality"
},
  "geometry": {"coordinates":[-36.41667,-8.46667],"type":"Point"}
}