{
  "type": "Feature",
  "properties": {
    "gn:admin1_code":"27.0",
    "gn:admin2_code":"3514809.0",
    "gn:asciiname":"Bairro Nhunguara",
    "gn:country_code":"BR",
    "gn:dem":70,
    "gn:feature_class":"P",
    "gn:feature_code":"PPL",
    "gn:name":"Bairro Nhunguara",
    "gn:population":0,
    "gn:timezone":"America/Sao_Paulo",
    "iso:country":"BR",
    "name:por_x_preferred":[
        "Bairro Nhunguara"
    ],
    "wof:name":"Bairro Nhunguara",
    "wof:placetype":"locality"
},
  "geometry": {"coordinates":[-48.42526,-24.58595],"type":"Point"}
}