{
  "type": "Feature",
  "properties": {
    "gn:admin1_code":"17",
    "gn:admin2_code":"2516508.0",
    "gn:asciiname":"Salgado",
    "gn:country_code":"BR",
    "gn:dem":566,
    "gn:feature_class":"P",
    "gn:feature_code":"PPL",
    "gn:name":"Salgado",
    "gn:population":0,
    "gn:timezone":"America/Fortaleza",
    "iso:country":"BR",
    "wof:name":"Salgado",
    "wof:placetype":"locality"
},
  "geometry": {"coordinates":[-36.86667,-7.28333],"type":"Point"}
}