{
  "type": "Feature",
  "properties": {
    "gn:admin1_code":"17",
    "gn:admin2_code":"2516508.0",
    "gn:asciiname":"Salgado",
    "gn:country_code":"BR",
    "gn:dem":566,
    "gn:feature_class":"P",
    "gn:feature_code":"PPL",
    "gn:name":"Salgado",
    "gn:population":0,
    "gn:timezone":"America/Fortaleza",
    "iso:country":"BR",
    "name:bpy_x_preferred":[
        "\u09b8\u09be\u09b2\u0997\u09be\u09a1\u09cb"
    ],
    "name:epo_x_preferred":[
        "Salgado"
    ],
    "name:eus_x_preferred":[
        "Salgado"
    ],
    "name:fra_x_preferred":[
        "Salgado"
    ],
    "name:ita_x_preferred":[
        "Salgado"
    ],
    "name:nld_x_preferred":[
        "Salgado"
    ],
    "name:nor_x_preferred":[
        "Salgado"
    ],
    "name:por_x_preferred":[
        "Salgado"
    ],
    "name:ron_x_preferred":[
        "Salgado"
    ],
    "name:rus_x_preferred":[
        "\u0421\u0430\u043b\u0433\u0430\u0434\u0443"
    ],
    "name:spa_x_preferred":[
        "Salgado"
    ],
    "name:vie_x_preferred":[
        "Salgado"
    ],
    "name:vol_x_preferred":[
        "Salgado"
    ],
    "name:war_x_preferred":[
        "Salgado"
    ],
    "name:zho_x_preferred":[
        "\u85a9\u723e\u52a0\u675c"
    ],
    "wof:name":"Salgado",
    "wof:placetype":"locality"
},
  "geometry": {"coordinates":[-36.86667,-7.28333],"type":"Point"}
}