{
  "type": "Feature",
  "properties": {
    "gn:admin1_code":"6.0",
    "gn:admin2_code":"2303501.0",
    "gn:asciiname":"Balbino",
    "gn:country_code":"BR",
    "gn:dem":12,
    "gn:feature_class":"P",
    "gn:feature_code":"PPL",
    "gn:name":"Balbino",
    "gn:population":0,
    "gn:timezone":"America/Fortaleza",
    "iso:country":"BR",
    "wof:name":"Balbino",
    "wof:placetype":"locality"
},
  "geometry": {"coordinates":[-38.22123,-4.02192],"type":"Point"}
}