{
  "type": "Feature",
  "properties": {
    "gn:admin1_code":"1",
    "gn:admin2_code":"1200450.0",
    "gn:asciiname":"Fazenda Ipe",
    "gn:country_code":"BR",
    "gn:dem":187,
    "gn:feature_class":"P",
    "gn:feature_code":"PPL",
    "gn:name":"Fazenda Ip\u00ea",
    "gn:population":0,
    "gn:timezone":"America/Rio_Branco",
    "iso:country":"BR",
    "wof:name":"Fazenda Ipe",
    "wof:placetype":"locality"
},
  "geometry": {"coordinates":[-67.43333,-9.83333],"type":"Point"}
}