{
  "type": "Feature",
  "properties": {
    "gn:admin1_code":"30",
    "gn:admin2_code":"2612471.0",
    "gn:asciiname":"Remigio",
    "gn:country_code":"BR",
    "gn:dem":853,
    "gn:feature_class":"P",
    "gn:feature_code":"PPL",
    "gn:name":"Rem\u00edgio",
    "gn:population":0,
    "gn:timezone":"America/Recife",
    "iso:country":"BR",
    "wof:name":"Remigio",
    "wof:placetype":"locality"
},
  "geometry": {"coordinates":[-38.15278,-7.82083],"type":"Point"}
}