{
  "type": "Feature",
  "properties": {
    "gn:admin1_code":"18.0",
    "gn:admin2_code":"4126603.0",
    "gn:asciiname":"Sitio Irmaos Resende",
    "gn:country_code":"BR",
    "gn:dem":651,
    "gn:feature_class":"P",
    "gn:feature_code":"PPL",
    "gn:name":"S\u00edtio Irm\u00e3os Resende",
    "gn:population":0,
    "gn:timezone":"America/Sao_Paulo",
    "iso:country":"BR",
    "name:por_x_preferred":[
        "S\u00edtio Irm\u00e3os Resende"
    ],
    "wof:name":"Sitio Irmaos Resende",
    "wof:placetype":"locality"
},
  "geometry": {"coordinates":[-49.806,-23.7293],"type":"Point"}
}