{
  "type": "Feature",
  "properties": {
    "gn:admin1_code":"5",
    "gn:admin2_code":"2916906.0",
    "gn:asciiname":"Uriporanga",
    "gn:country_code":"BR",
    "gn:dem":659,
    "gn:feature_class":"P",
    "gn:feature_code":"PPL",
    "gn:name":"Uriporanga",
    "gn:population":0,
    "gn:timezone":"America/Bahia",
    "iso:country":"BR",
    "wof:name":"Uriporanga",
    "wof:placetype":"locality"
},
  "geometry": {"coordinates":[-40.18333,-13.36667],"type":"Point"}
}