{
  "type": "Feature",
  "properties": {
    "gn:admin1_code":"14",
    "gn:admin2_code":"5106505.0",
    "gn:asciiname":"Tanque Grande",
    "gn:country_code":"BR",
    "gn:dem":135,
    "gn:feature_class":"P",
    "gn:feature_code":"PPL",
    "gn:name":"Tanque Grande",
    "gn:population":0,
    "gn:timezone":"America/Cuiaba",
    "iso:country":"BR",
    "wof:name":"Tanque Grande",
    "wof:placetype":"locality"
},
  "geometry": {"coordinates":[-56.53333000000001,-16.11667000000001],"type":"Point"}
}