{
  "type": "Feature",
  "properties": {
    "gn:admin1_code":"23",
    "gn:admin2_code":"4306502.0",
    "gn:asciiname":"Herval",
    "gn:country_code":"BR",
    "gn:dem":370,
    "gn:feature_class":"P",
    "gn:feature_code":"PPL",
    "gn:name":"Herval",
    "gn:population":0,
    "gn:timezone":"America/Sao_Paulo",
    "iso:country":"BR",
    "name:bpy_x_preferred":[
        "\u09b9\u09c7\u09b0\u09cd\u09ad\u09be\u09b2"
    ],
    "name:ceb_x_preferred":[
        "Herval"
    ],
    "name:epo_x_preferred":[
        "Herval"
    ],
    "name:eus_x_preferred":[
        "Herval"
    ],
    "name:fra_x_preferred":[
        "Herval"
    ],
    "name:grn_x_preferred":[
        "Herval"
    ],
    "name:ita_x_preferred":[
        "Herval"
    ],
    "name:kaz_x_preferred":[
        "\u042d\u0440\u0432\u0430\u043b"
    ],
    "name:mlg_x_preferred":[
        "Herval"
    ],
    "name:nld_x_preferred":[
        "Herval"
    ],
    "name:nor_x_preferred":[
        "Herval"
    ],
    "name:pol_x_preferred":[
        "Herval"
    ],
    "name:por_x_preferred":[
        "Herval"
    ],
    "name:rus_x_preferred":[
        "\u042d\u0440\u0432\u0430\u043b"
    ],
    "name:spa_x_preferred":[
        "Herval"
    ],
    "name:swe_x_preferred":[
        "Herval"
    ],
    "name:vie_x_preferred":[
        "Herval"
    ],
    "name:vol_x_preferred":[
        "Herval"
    ],
    "name:war_x_preferred":[
        "Herval"
    ],
    "name:zho_x_preferred":[
        "\u57c3\u5c14\u74e6\u5c14"
    ],
    "wof:name":"Herval",
    "wof:placetype":"locality"
},
  "geometry": {"coordinates":[-52.2658,-30.6537],"type":"Point"}
}