{
  "type": "Feature",
  "properties": {
    "gn:admin1_code":"23",
    "gn:admin2_code":"4306502.0",
    "gn:asciiname":"Herval",
    "gn:country_code":"BR",
    "gn:dem":370,
    "gn:feature_class":"P",
    "gn:feature_code":"PPL",
    "gn:name":"Herval",
    "gn:population":0,
    "gn:timezone":"America/Sao_Paulo",
    "iso:country":"BR",
    "name:por_x_preferred":[
        "Herval"
    ],
    "wof:name":"Herval",
    "wof:placetype":"locality"
},
  "geometry": {"coordinates":[-52.2658,-30.6537],"type":"Point"}
}