{
  "type": "Feature",
  "properties": {
    "iso:country":"BR",
    "qs_pg:aaroncc":"BR",
    "qs_pg:name":"Puerto Presidente Franco",
    "qs_pg:name_adm0":"Paraguay",
    "qs_pg:name_adm1":"Alto Paran\u00e1",
    "qs_pg:photos":1659,
    "qs_pg:photos_1k":336,
    "qs_pg:photos_9k":7,
    "qs_pg:photos_9r":8,
    "qs_pg:photos_all":1659,
    "qs_pg:photos_sr":14,
    "qs_pg:pop_sr":0,
    "qs_pg:qs_pg_placetype":"locality",
    "qs_pg:qs_pg_placetype_gp":"Town",
    "qs_pg:woe_adm0":23424917,
    "woe:adm0_id":23424917,
    "woe:name_adm0":"Paraguay",
    "woe:name_adm1":"Alto Paran\u00e1",
    "woe:placetype":"Town",
    "wof:name":"Puerto Presidente Franco",
    "wof:placetype":"locality"
},
  "geometry": {"coordinates":[-54.592609,-25.590445],"type":"Point"}
}