{
  "type": "Feature",
  "properties": {
    "gn:admin1_code":"18.0",
    "gn:admin2_code":"4109005.0",
    "gn:asciiname":"Sitio Pedro de O. Cuba",
    "gn:country_code":"BR",
    "gn:dem":488,
    "gn:feature_class":"P",
    "gn:feature_code":"PPL",
    "gn:name":"S\u00edtio Pedro de O. Cuba",
    "gn:population":0,
    "gn:timezone":"America/Sao_Paulo",
    "iso:country":"BR",
    "name:por_x_preferred":[
        "S\u00edtio Pedro de O. Cuba"
    ],
    "wof:name":"Sitio Pedro de O. Cuba",
    "wof:placetype":"locality"
},
  "geometry": {"coordinates":[-50.05177,-23.42409],"type":"Point"}
}