{
  "type": "Feature",
  "properties": {
    "gn:admin1_code":"14.0",
    "gn:admin2_code":"5104559.0",
    "gn:asciiname":"Aldeia Caiabi",
    "gn:country_code":"BR",
    "gn:dem":313,
    "gn:feature_class":"P",
    "gn:feature_code":"PPL",
    "gn:name":"Aldeia Caiabi",
    "gn:population":0,
    "gn:timezone":"America/Cuiaba",
    "iso:country":"BR",
    "name:por_x_preferred":[
        "Aldeia Caiabi"
    ],
    "wof:name":"Aldeia Caiabi",
    "wof:placetype":"locality"
},
  "geometry": {"coordinates":[-55.49008000000001,-11.29994],"type":"Point"}
}