{
  "type": "Feature",
  "properties": {
    "gn:admin1_code":"18",
    "gn:admin2_code":"4121208.0",
    "gn:asciiname":"Sitio Miguel Carax",
    "gn:country_code":"BR",
    "gn:dem":893,
    "gn:feature_class":"P",
    "gn:feature_code":"PPL",
    "gn:name":"S\u00edtio Miguel Carax",
    "gn:population":0,
    "gn:timezone":"America/Sao_Paulo",
    "iso:country":"BR",
    "name:por_x_preferred":[
        "S\u00edtio Miguel Carax"
    ],
    "wof:name":"Sitio Miguel Carax",
    "wof:placetype":"locality"
},
  "geometry": {"coordinates":[-49.50778,-25.96806],"type":"Point"}
}