{
  "type": "Feature",
  "properties": {
    "gn:admin1_code":"14",
    "gn:admin2_code":"5106505.0",
    "gn:asciiname":"Porto Caracara",
    "gn:country_code":"BR",
    "gn:dem":91,
    "gn:feature_class":"P",
    "gn:feature_code":"PPL",
    "gn:name":"P\u00f4rto Caracar\u00e1",
    "gn:population":0,
    "gn:timezone":"America/Cuiaba",
    "iso:country":"BR",
    "wof:name":"Porto Caracara",
    "wof:placetype":"locality"
},
  "geometry": {"coordinates":[-57.45,-17.86667000000001],"type":"Point"}
}