{
  "type": "Feature",
  "properties": {
    "gn:admin1_code":"15",
    "gn:admin2_code":"3151503.0",
    "gn:asciiname":"Terra",
    "gn:country_code":"BR",
    "gn:dem":865,
    "gn:feature_class":"P",
    "gn:feature_code":"PPL",
    "gn:name":"Terra",
    "gn:population":0,
    "gn:timezone":"America/Sao_Paulo",
    "iso:country":"BR",
    "name:cat_x_preferred":[
        "Terra"
    ],
    "name:deu_x_preferred":[
        "Terra"
    ],
    "name:fin_x_preferred":[
        "Terra"
    ],
    "name:fra_x_preferred":[
        "Terra"
    ],
    "name:glg_x_preferred":[
        "Terra"
    ],
    "name:heb_x_preferred":[
        "\u05d8\u05e8\u05d4"
    ],
    "name:ina_x_preferred":[
        "Terra"
    ],
    "name:ita_x_preferred":[
        "Terra"
    ],
    "name:jpn_x_preferred":[
        "\u30c6\u30e9"
    ],
    "name:kor_x_preferred":[
        "\ud14c\ub77c"
    ],
    "name:lat_x_preferred":[
        "Terra"
    ],
    "name:nld_x_preferred":[
        "Terra"
    ],
    "name:nor_x_preferred":[
        "Terra"
    ],
    "name:oci_x_preferred":[
        "T\u00e8rra"
    ],
    "name:pol_x_preferred":[
        "Terra"
    ],
    "name:por_x_preferred":[
        "Terra"
    ],
    "name:ron_x_preferred":[
        "Terra"
    ],
    "name:rus_x_preferred":[
        "\u0422\u0435\u0440\u0440\u0430"
    ],
    "name:scn_x_preferred":[
        "Terra"
    ],
    "name:spa_x_preferred":[
        "Terra"
    ],
    "name:swe_x_preferred":[
        "Terra"
    ],
    "wof:name":"Terra",
    "wof:placetype":"locality"
},
  "geometry": {"coordinates":[-45.96667,-20.53333],"type":"Point"}
}