{
  "type": "Feature",
  "properties": {
    "gn:admin1_code":"15",
    "gn:admin2_code":"3151503.0",
    "gn:asciiname":"Terra",
    "gn:country_code":"BR",
    "gn:dem":865,
    "gn:feature_class":"P",
    "gn:feature_code":"PPL",
    "gn:name":"Terra",
    "gn:population":0,
    "gn:timezone":"America/Sao_Paulo",
    "iso:country":"BR",
    "name:por_x_preferred":[
        "Terra"
    ],
    "wof:name":"Terra",
    "wof:placetype":"locality"
},
  "geometry": {"coordinates":[-45.96667,-20.53333],"type":"Point"}
}