{
  "type": "Feature",
  "properties": {
    "gn:admin1_code":"18.0",
    "gn:admin2_code":"4109500.0",
    "gn:asciiname":"Medeiros de Baixo",
    "gn:country_code":"BR",
    "gn:dem":0,
    "gn:feature_class":"P",
    "gn:feature_code":"PPLL",
    "gn:name":"Medeiros de Baixo",
    "gn:population":0,
    "gn:timezone":"America/Sao_Paulo",
    "iso:country":"BR",
    "name:por_x_preferred":[
        "Medeiros de Baixo"
    ],
    "wof:name":"Medeiros de Baixo",
    "wof:placetype":"locality"
},
  "geometry": {"coordinates":[-48.45504,-25.37636],"type":"Point"}
}