{
  "type": "Feature",
  "properties": {
    "gn:admin1_code":"18.0",
    "gn:admin2_code":"4116208.0",
    "gn:asciiname":"Candonga",
    "gn:country_code":"BR",
    "gn:dem":133,
    "gn:feature_class":"P",
    "gn:feature_code":"PPL",
    "gn:name":"Candonga",
    "gn:population":0,
    "gn:timezone":"America/Sao_Paulo",
    "iso:country":"BR",
    "name:por_x_preferred":[
        "Candonga"
    ],
    "wof:name":"Candonga",
    "wof:placetype":"locality"
},
  "geometry": {"coordinates":[-48.8042,-25.5855],"type":"Point"}
}