{
  "type": "Feature",
  "properties": {
    "gn:admin1_code":"06",
    "gn:admin2_code":"2308500.0",
    "gn:asciiname":"Quarador",
    "gn:country_code":"BR",
    "gn:dem":335,
    "gn:feature_class":"P",
    "gn:feature_code":"PPL",
    "gn:name":"Quarador",
    "gn:population":0,
    "gn:timezone":"America/Fortaleza",
    "iso:country":"BR",
    "wof:name":"Quarador",
    "wof:placetype":"locality"
},
  "geometry": {"coordinates":[-39.78333,-5.83333],"type":"Point"}
}