{
  "type": "Feature",
  "properties": {
    "gn:admin1_code":"18.0",
    "gn:admin2_code":"4121208.0",
    "gn:asciiname":"Sitio Jose Pestecolask",
    "gn:country_code":"BR",
    "gn:dem":831,
    "gn:feature_class":"P",
    "gn:feature_code":"PPL",
    "gn:name":"S\u00edtio Jos\u00e9 Pestecolask",
    "gn:population":0,
    "gn:timezone":"America/Sao_Paulo",
    "iso:country":"BR",
    "name:por_x_preferred":[
        "S\u00edtio Jos\u00e9 Pestecolask"
    ],
    "wof:name":"Sitio Jose Pestecolask",
    "wof:placetype":"locality"
},
  "geometry": {"coordinates":[-49.4926,-25.8958],"type":"Point"}
}