{
  "type": "Feature",
  "properties": {
    "gn:admin1_code":"27.0",
    "gn:admin2_code":"3550308.0",
    "gn:asciiname":"Sitio Capuava",
    "gn:country_code":"BR",
    "gn:dem":775,
    "gn:feature_class":"P",
    "gn:feature_code":"PPL",
    "gn:name":"S\u00edtio Capuava",
    "gn:population":0,
    "gn:timezone":"America/Sao_Paulo",
    "iso:country":"BR",
    "name:por_x_preferred":[
        "S\u00edtio Capuava"
    ],
    "wof:name":"Sitio Capuava",
    "wof:placetype":"locality"
},
  "geometry": {"coordinates":[-46.6492,-23.82808],"type":"Point"}
}