{
  "type": "Feature",
  "properties": {
    "gn:admin1_code":"16",
    "gn:admin2_code":"1500602.0",
    "gn:asciiname":"Bom Futuro",
    "gn:country_code":"BR",
    "gn:dem":246,
    "gn:feature_class":"P",
    "gn:feature_code":"PPL",
    "gn:name":"Bom Futuro",
    "gn:population":0,
    "gn:timezone":"America/Santarem",
    "iso:country":"BR",
    "wof:name":"Bom Futuro",
    "wof:placetype":"locality"
},
  "geometry": {"coordinates":[-54.78333000000001,-6.41667],"type":"Point"}
}