{
  "type": "Feature",
  "properties": {
    "gn:admin1_code":"27",
    "gn:admin2_code":"3520301.0",
    "gn:asciiname":"Barra do Rio Jacupiranga",
    "gn:cc2":"BR",
    "gn:country_code":"BR",
    "gn:dem":1,
    "gn:feature_class":"P",
    "gn:feature_code":"PPL",
    "gn:name":"Barra do Rio Jacupiranga",
    "gn:population":0,
    "gn:timezone":"America/Sao_Paulo",
    "iso:country":"BR",
    "name:und_x_variant":[
        "Barra do Jacupiranga",
        "Barra do Rio Jacupiranga"
    ],
    "wof:name":"Barra do Rio Jacupiranga",
    "wof:placetype":"locality"
},
  "geometry": {"coordinates":[-47.73333,-24.63333],"type":"Point"}
}