{
  "type": "Feature",
  "properties": {
    "gn:admin1_code":"5",
    "gn:admin2_code":"2914000.0",
    "gn:asciiname":"Candeias",
    "gn:country_code":"BR",
    "gn:dem":374,
    "gn:feature_class":"P",
    "gn:feature_code":"PPL",
    "gn:name":"Candeias",
    "gn:population":0,
    "gn:timezone":"America/Bahia",
    "iso:country":"BR",
    "name:bpy_x_preferred":[
        "\u0995\u09be\u09a8\u09cd\u09a1\u09c7\u0987\u09af\u09bc\u09be\u09b8"
    ],
    "name:ceb_x_preferred":[
        "Candeias"
    ],
    "name:deu_x_preferred":[
        "Candeias"
    ],
    "name:fra_x_preferred":[
        "Candeias"
    ],
    "name:ita_x_preferred":[
        "Candeias"
    ],
    "name:nld_x_preferred":[
        "Candeias"
    ],
    "name:nor_x_preferred":[
        "Candeias"
    ],
    "name:por_x_preferred":[
        "Candeias"
    ],
    "name:rus_x_preferred":[
        "\u041a\u0430\u043d\u0434\u0435\u044f\u0441"
    ],
    "name:sco_x_preferred":[
        "Candeias"
    ],
    "name:swe_x_preferred":[
        "Candeias"
    ],
    "name:vie_x_preferred":[
        "Candeias"
    ],
    "name:vol_x_preferred":[
        "Candeias"
    ],
    "wof:name":"Candeias",
    "wof:placetype":"locality"
},
  "geometry": {"coordinates":[-39.76667,-12.31667],"type":"Point"}
}