{
  "type": "Feature",
  "properties": {
    "gn:gn_country":"BR",
    "gn:gn_fcode":"PPL",
    "gn:gn_pop":6387,
    "gn:population":6387,
    "iso:country":"BR",
    "name:arm_x_preferred":[
        "\u054d\u0561\u0576\u057f\u0578\u0582 \u0531\u0576\u057f\u0578\u0576\u056b\u0578\u0582 \u0564\u0578\u0582 \u053c\u0587\u0565\u0580\u056a\u0565\u0580"
    ],
    "name:baq_x_preferred":[
        "Santo Ant\u00f4nio de Leverger"
    ],
    "name:bpy_x_preferred":[
        "\u09b8\u09be\u09a8\u09cd\u099f\u09cb \u0986\u09a8\u09cd\u099f\u09cb\u09a8\u09bf\u0993 \u09a1\u09cb \u09b2\u09c7\u09ad\u09c7\u09b0\u09cd\u0997\u09af\u09bc\u09c7\u09b0"
    ],
    "name:chi_x_preferred":[
        "\u5723\u5b89\u4e1c\u5c3c\u5965-\u675c\u83b1\u97e6\u70ed"
    ],
    "name:dut_x_preferred":[
        "Santo Ant\u00f4nio do Leverger"
    ],
    "name:eng_x_preferred":[
        "Santo Ant\u00f4nio do Leverger"
    ],
    "name:fre_x_preferred":[
        "Santo Ant\u00f4nio do Leverger"
    ],
    "name:geo_x_preferred":[
        "\u10e1\u10d0\u10dc\u10e2\u10e3-\u10d0\u10dc\u10e2\u10dd\u10dc\u10d8\u10e3-\u10d3\u10e3-\u10da\u10d4\u10d5\u10e0\u10d4\u10df\u10d4\u10e0\u10d8"
    ],
    "name:ger_x_preferred":[
        "Santo Ant\u00f4nio de Leverger"
    ],
    "name:hun_x_preferred":[
        "Santo Ant\u00f4nio do Leverger"
    ],
    "name:ita_x_preferred":[
        "Santo Ant\u00f4nio do Leverger"
    ],
    "name:kaz_x_preferred":[
        "\u0421\u0430\u043d\u0442\u0443-\u0410\u043d\u0442\u043e\u043d\u0438\u0443-\u0434\u0443-\u041b\u0435\u0432\u0435\u0440\u0436\u0435\u0440"
    ],
    "name:nan_x_preferred":[
        "Santo Ant\u00f4nio de Leverger"
    ],
    "name:nob_x_preferred":[
        "Santo Ant\u00f4nio do Leverger"
    ],
    "name:pol_x_preferred":[
        "Santo Ant\u00f4nio do Leverger"
    ],
    "name:por_x_preferred":[
        "Santo Ant\u00f4nio de Leverger"
    ],
    "name:rum_x_preferred":[
        "Santo Ant\u00f4nio do Leverger"
    ],
    "name:rus_x_preferred":[
        "\u0421\u0430\u043d\u0442\u0443-\u0410\u043d\u0442\u043e\u043d\u0438\u0443-\u0434\u0443-\u041b\u0435\u0432\u0435\u0440\u0436\u0435\u0440"
    ],
    "name:swe_x_preferred":[
        "Santo Ant\u00f4nio do Leverger"
    ],
    "name:unk_x_variant":[
        "Leverger"
    ],
    "name:vie_x_preferred":[
        "Santo Ant\u00f4nio do Leverger"
    ],
    "name:vol_x_preferred":[
        "Santo Ant\u00f4nio do Leverger"
    ],
    "name:war_x_preferred":[
        "Santo Ant\u00f4nio do Leverger"
    ],
    "qs_pg:aaroncc":"BR",
    "qs_pg:gn_country":"BR",
    "qs_pg:gn_fcode":"PPL",
    "qs_pg:gn_pop":6387,
    "qs_pg:name":"Santo Antonio",
    "qs_pg:name_adm0":"Brasil",
    "qs_pg:name_adm1":"Mato Grosso",
    "qs_pg:photos_9k":1,
    "qs_pg:photos_9r":1,
    "qs_pg:photos_all":1,
    "qs_pg:photos_sr":0,
    "qs_pg:pop_sr":5,
    "qs_pg:qs_pg_placetype":"locality",
    "qs_pg:qs_pg_placetype_gp":"Town",
    "qs_pg:woe_adm0":23424768,
    "woe:adm0_id":23424768,
    "woe:name_adm0":"Brasil",
    "woe:name_adm1":"Mato Grosso",
    "woe:placetype":"Town",
    "wof:name":"Santo Antonio",
    "wof:placetype":"locality",
    "wof:population":6387
},
  "geometry": {"coordinates":[-56.07667,-15.86556],"type":"Point"}
}