{
  "type": "Feature",
  "properties": {
    "gn:admin1_code":"27",
    "gn:admin2_code":"3504107.0",
    "gn:asciiname":"Sitio Morro Azul",
    "gn:country_code":"BR",
    "gn:dem":827,
    "gn:feature_class":"P",
    "gn:feature_code":"PPL",
    "gn:name":"S\u00edtio Morro Azul",
    "gn:population":0,
    "gn:timezone":"America/Sao_Paulo",
    "iso:country":"BR",
    "name:por_x_preferred":[
        "S\u00edtio Morro Azul"
    ],
    "wof:name":"Sitio Morro Azul",
    "wof:placetype":"locality"
},
  "geometry": {"coordinates":[-46.65611,-23.2225],"type":"Point"}
}