{
  "type": "Feature",
  "properties": {
    "gn:admin1_code":"5",
    "gn:admin2_code":"2927408.0",
    "gn:asciiname":"Flamengo",
    "gn:country_code":"BR",
    "gn:dem":24,
    "gn:feature_class":"P",
    "gn:feature_code":"PPL",
    "gn:name":"Flamengo",
    "gn:population":0,
    "gn:timezone":"America/Bahia",
    "iso:country":"BR",
    "wof:name":"Flamengo",
    "wof:placetype":"locality"
},
  "geometry": {"coordinates":[-38.33333,-12.93333],"type":"Point"}
}