{
  "type": "Feature",
  "properties": {
    "gn:admin1_code":"5",
    "gn:admin2_code":"2911808.0",
    "gn:asciiname":"Pinheiro",
    "gn:country_code":"BR",
    "gn:dem":217,
    "gn:feature_class":"P",
    "gn:feature_code":"PPL",
    "gn:name":"Pinheiro",
    "gn:population":0,
    "gn:timezone":"America/Bahia",
    "iso:country":"BR",
    "name:ceb_x_preferred":[
        "Pinheiro"
    ],
    "name:deu_x_preferred":[
        "Pinheiro"
    ],
    "name:fra_x_preferred":[
        "Pinheiro"
    ],
    "name:jpn_x_preferred":[
        "\u30d4\u30cb\u30a7\u30a4\u30ed"
    ],
    "name:mlg_x_preferred":[
        "Pinheiro"
    ],
    "name:nld_x_preferred":[
        "Pinheiro"
    ],
    "name:por_x_preferred":[
        "Pinheiro"
    ],
    "name:rus_x_preferred":[
        "\u041f\u0438\u043d\u044c\u0435\u0439\u0440\u0443"
    ],
    "name:spa_x_preferred":[
        "Pinheiro"
    ],
    "name:swe_x_preferred":[
        "Pinheiro"
    ],
    "name:ukr_x_preferred":[
        "\u041f\u0456\u043d\u044c\u0454\u0439\u0440\u0443"
    ],
    "wof:name":"Pinheiro",
    "wof:placetype":"locality"
},
  "geometry": {"coordinates":[-39.98663,-16.45381],"type":"Point"}
}