{
  "type": "Feature",
  "properties": {
    "gn:admin1_code":"20",
    "gn:admin2_code":"2205607.0",
    "gn:asciiname":"Roca Nova",
    "gn:country_code":"BR",
    "gn:dem":284,
    "gn:feature_class":"P",
    "gn:feature_code":"PPL",
    "gn:name":"Ro\u00e7a Nova",
    "gn:population":0,
    "gn:timezone":"America/Fortaleza",
    "iso:country":"BR",
    "wof:name":"Roca Nova",
    "wof:placetype":"locality"
},
  "geometry": {"coordinates":[-43.98333,-7.38333],"type":"Point"}
}