{
  "type": "Feature",
  "properties": {
    "gn:admin1_code":"16",
    "gn:admin2_code":"1501303.0",
    "gn:asciiname":"Tauari",
    "gn:country_code":"BR",
    "gn:dem":15,
    "gn:feature_class":"P",
    "gn:feature_code":"PPL",
    "gn:name":"Tauari",
    "gn:population":0,
    "gn:timezone":"America/Belem",
    "iso:country":"BR",
    "wof:name":"Tauari",
    "wof:placetype":"locality"
},
  "geometry": {"coordinates":[-48.56667,-1.46667],"type":"Point"}
}