{
  "type": "Feature",
  "properties": {
    "gn:admin1_code":"11",
    "gn:admin2_code":"5004304.0",
    "gn:asciiname":"Porto Sassoro",
    "gn:cc2":"BR",
    "gn:country_code":"BR",
    "gn:dem":314,
    "gn:feature_class":"P",
    "gn:feature_code":"PPL",
    "gn:name":"P\u00f4rto Sassor\u00f3",
    "gn:population":0,
    "gn:timezone":"America/Campo_Grande",
    "iso:country":"BR",
    "name:und_x_variant":[
        "Sassor\u00f3",
        "P\u00f4rto Sassor\u00e1",
        "P\u00f4rto Sassor\u00f3"
    ],
    "wof:name":"Porto Sassoro",
    "wof:placetype":"locality"
},
  "geometry": {"coordinates":[-54.76667,-23.56667],"type":"Point"}
}