{
  "type": "Feature",
  "properties": {
    "gn:admin1_code":"22",
    "gn:admin2_code":"2401909.0",
    "gn:asciiname":"Sao Domingos",
    "gn:country_code":"BR",
    "gn:dem":143,
    "gn:feature_class":"P",
    "gn:feature_code":"PPL",
    "gn:name":"S\u00e3o Domingos",
    "gn:population":0,
    "gn:timezone":"America/Fortaleza",
    "iso:country":"BR",
    "wof:name":"Sao Domingos",
    "wof:placetype":"locality"
},
  "geometry": {"coordinates":[-36.01917,-5.70083],"type":"Point"}
}