{
  "type": "Feature",
  "properties": {
    "gn:admin1_code":"18.0",
    "gn:admin2_code":"4112306.0",
    "gn:asciiname":"Sitio Luiz Carlos dos Santos",
    "gn:country_code":"BR",
    "gn:dem":609,
    "gn:feature_class":"P",
    "gn:feature_code":"PPL",
    "gn:name":"S\u00edtio Luiz Carlos dos Santos",
    "gn:population":0,
    "gn:timezone":"America/Sao_Paulo",
    "iso:country":"BR",
    "name:por_x_preferred":[
        "S\u00edtio Luiz Carlos dos Santos"
    ],
    "wof:name":"Sitio Luiz Carlos dos Santos",
    "wof:placetype":"locality"
},
  "geometry": {"coordinates":[-50.20339,-23.72918],"type":"Point"}
}