{
  "type": "Feature",
  "properties": {
    "gn:admin1_code":"18.0",
    "gn:admin2_code":"4107751.0",
    "gn:asciiname":"Sitio Joao B. da Silva",
    "gn:country_code":"BR",
    "gn:dem":582,
    "gn:feature_class":"P",
    "gn:feature_code":"PPL",
    "gn:name":"S\u00edtio Jo\u00e3o B. da Silva",
    "gn:population":0,
    "gn:timezone":"America/Sao_Paulo",
    "iso:country":"BR",
    "name:por_x_preferred":[
        "S\u00edtio Jo\u00e3o B. da Silva"
    ],
    "wof:name":"Sitio Joao B. da Silva",
    "wof:placetype":"locality"
},
  "geometry": {"coordinates":[-50.45407,-23.88794],"type":"Point"}
}