{
  "type": "Feature",
  "properties": {
    "gn:admin1_code":"29",
    "gn:admin2_code":"5211909.0",
    "gn:asciiname":"Joao Carmelo",
    "gn:country_code":"BR",
    "gn:dem":693,
    "gn:feature_class":"P",
    "gn:feature_code":"PPL",
    "gn:name":"Jo\u00e3o Carmelo",
    "gn:population":0,
    "gn:timezone":"America/Sao_Paulo",
    "iso:country":"BR",
    "name:por_x_preferred":[
        "Jo\u00e3o Carmelo"
    ],
    "wof:name":"Joao Carmelo",
    "wof:placetype":"locality"
},
  "geometry": {"coordinates":[-51.88333,-17.71667],"type":"Point"}
}