{
  "type": "Feature",
  "properties": {
    "gn:admin1_code":"14",
    "gn:admin2_code":"5107008.0",
    "gn:asciiname":"Sitio Novo",
    "gn:country_code":"BR",
    "gn:dem":347,
    "gn:feature_class":"P",
    "gn:feature_code":"PPL",
    "gn:name":"S\u00edtio Novo",
    "gn:population":0,
    "gn:timezone":"America/Cuiaba",
    "iso:country":"BR",
    "wof:name":"Sitio Novo",
    "wof:placetype":"locality"
},
  "geometry": {"coordinates":[-54.28333000000001,-15.96667],"type":"Point"}
}