{
  "type": "Feature",
  "properties": {
    "gn:admin1_code":"4",
    "gn:admin2_code":"1303502.0",
    "gn:asciiname":"Sao Francisco",
    "gn:country_code":"BR",
    "gn:dem":216,
    "gn:feature_class":"P",
    "gn:feature_code":"PPL",
    "gn:name":"S\u00e3o Francisco",
    "gn:population":0,
    "gn:timezone":"America/Eirunepe",
    "iso:country":"BR",
    "wof:name":"Sao Francisco",
    "wof:placetype":"locality"
},
  "geometry": {"coordinates":[-68.78333000000001,-7.75],"type":"Point"}
}