{
  "type": "Feature",
  "properties": {
    "gn:admin1_code":"5",
    "gn:admin2_code":"2915304.0",
    "gn:asciiname":"Quarto de Onca",
    "gn:country_code":"BR",
    "gn:dem":256,
    "gn:feature_class":"P",
    "gn:feature_code":"PPL",
    "gn:name":"Quarto de On\u00e7a",
    "gn:population":0,
    "gn:timezone":"America/Bahia",
    "iso:country":"BR",
    "name:por_x_preferred":[
        "Quarto de On\u00e7a"
    ],
    "wof:name":"Quarto de Onca",
    "wof:placetype":"locality"
},
  "geometry": {"coordinates":[-39.86667,-16.16667],"type":"Point"}
}