{
  "type": "Feature",
  "properties": {
    "gn:admin1_code":"5.0",
    "gn:admin2_code":"2928109.0",
    "gn:asciiname":"Taboleirinho",
    "gn:country_code":"BR",
    "gn:dem":586,
    "gn:feature_class":"P",
    "gn:feature_code":"PPL",
    "gn:name":"Taboleirinho",
    "gn:population":0,
    "gn:timezone":"America/Bahia",
    "iso:country":"BR",
    "name:por_x_preferred":[
        "Taboleirinho"
    ],
    "wof:name":"Taboleirinho",
    "wof:placetype":"locality"
},
  "geometry": {"coordinates":[-44.60618,-13.15784],"type":"Point"}
}