{
  "type": "Feature",
  "properties": {
    "gn:admin1_code":"27",
    "gn:admin2_code":"3526209.0",
    "gn:asciiname":"Sitio das Cachoeiras",
    "gn:country_code":"BR",
    "gn:dem":691,
    "gn:feature_class":"P",
    "gn:feature_code":"PPL",
    "gn:name":"S\u00edtio das Cachoeiras",
    "gn:population":0,
    "gn:timezone":"America/Sao_Paulo",
    "iso:country":"BR",
    "name:por_x_preferred":[
        "S\u00edtio das Cachoeiras"
    ],
    "wof:name":"Sitio das Cachoeiras",
    "wof:placetype":"locality"
},
  "geometry": {"coordinates":[-47.0966,-23.9634],"type":"Point"}
}