{
  "type": "Feature",
  "properties": {
    "gn:admin1_code":"1",
    "gn:admin2_code":"1200401.0",
    "gn:asciiname":"Taquari",
    "gn:country_code":"BR",
    "gn:dem":190,
    "gn:feature_class":"P",
    "gn:feature_code":"PPL",
    "gn:name":"Taquari",
    "gn:population":0,
    "gn:timezone":"America/Rio_Branco",
    "iso:country":"BR",
    "wof:name":"Taquari",
    "wof:placetype":"locality"
},
  "geometry": {"coordinates":[-67.91028,-9.87361],"type":"Point"}
}