{
  "type": "Feature",
  "properties": {
    "gn:admin1_code":"1",
    "gn:admin2_code":"1200401.0",
    "gn:asciiname":"Taquari",
    "gn:country_code":"BR",
    "gn:dem":190,
    "gn:feature_class":"P",
    "gn:feature_code":"PPL",
    "gn:name":"Taquari",
    "gn:population":0,
    "gn:timezone":"America/Rio_Branco",
    "iso:country":"BR",
    "name:bpy_x_preferred":[
        "\u099f\u09be\u0995\u09c1\u09f1\u09be\u09b0\u09bf"
    ],
    "name:bul_x_preferred":[
        "\u0422\u0430\u043a\u0443\u0430\u0440\u0438"
    ],
    "name:ceb_x_preferred":[
        "Taquari"
    ],
    "name:epo_x_preferred":[
        "Taquari"
    ],
    "name:eus_x_preferred":[
        "Taquari"
    ],
    "name:fra_x_preferred":[
        "Taquari"
    ],
    "name:ita_x_preferred":[
        "Taquari"
    ],
    "name:kaz_x_preferred":[
        "\u0422\u0430\u043a\u0443\u0430\u0440\u0438"
    ],
    "name:mlg_x_preferred":[
        "Taquari"
    ],
    "name:nld_x_preferred":[
        "Taquari"
    ],
    "name:nor_x_preferred":[
        "Taquari"
    ],
    "name:pol_x_preferred":[
        "Taquari"
    ],
    "name:por_x_preferred":[
        "Taquari"
    ],
    "name:ron_x_preferred":[
        "Taquari"
    ],
    "name:rus_x_preferred":[
        "\u0422\u0430\u043a\u0443\u0430\u0440\u0438"
    ],
    "name:spa_x_preferred":[
        "Taquari"
    ],
    "name:swe_x_preferred":[
        "Taquari"
    ],
    "name:ukr_x_preferred":[
        "\u0422\u0430\u043a\u0443\u0430\u0440\u0456"
    ],
    "name:vie_x_preferred":[
        "Taquari"
    ],
    "name:vol_x_preferred":[
        "Taquari"
    ],
    "name:war_x_preferred":[
        "Taquari"
    ],
    "name:zho_x_preferred":[
        "\u5854\u5938\u91cc"
    ],
    "wof:name":"Taquari",
    "wof:placetype":"locality"
},
  "geometry": {"coordinates":[-67.91028,-9.87361],"type":"Point"}
}