{
  "type": "Feature",
  "properties": {
    "gn:admin1_code":"06",
    "gn:admin2_code":"2310308.0",
    "gn:asciiname":"Varzea do Caicara",
    "gn:country_code":"BR",
    "gn:dem":442,
    "gn:feature_class":"P",
    "gn:feature_code":"PPL",
    "gn:name":"V\u00e1rzea do Caicara",
    "gn:population":0,
    "gn:timezone":"America/Fortaleza",
    "iso:country":"BR",
    "wof:name":"Varzea do Caicara",
    "wof:placetype":"locality"
},
  "geometry": {"coordinates":[-40.51667,-6.43333],"type":"Point"}
}