{
  "type": "Feature",
  "properties": {
    "gn:admin1_code":"23",
    "gn:admin2_code":"4306908.0",
    "gn:asciiname":"Figueiras",
    "gn:country_code":"BR",
    "gn:dem":319,
    "gn:feature_class":"P",
    "gn:feature_code":"PPL",
    "gn:name":"Figueiras",
    "gn:population":0,
    "gn:timezone":"America/Sao_Paulo",
    "iso:country":"BR",
    "wof:name":"Figueiras",
    "wof:placetype":"locality"
},
  "geometry": {"coordinates":[-52.91667,-30.85],"type":"Point"}
}