{
  "type": "Feature",
  "properties": {
    "gn:admin1_code":"30",
    "gn:admin2_code":"2615706.0",
    "gn:asciiname":"Retiro",
    "gn:country_code":"BR",
    "gn:dem":1094,
    "gn:feature_class":"P",
    "gn:feature_code":"PPL",
    "gn:name":"Retiro",
    "gn:population":0,
    "gn:timezone":"America/Recife",
    "iso:country":"BR",
    "wof:name":"Retiro",
    "wof:placetype":"locality"
},
  "geometry": {"coordinates":[-38.11667,-7.83333],"type":"Point"}
}