{
  "type": "Feature",
  "properties": {
    "gn:admin1_code":"26",
    "gn:admin2_code":"4203303.0",
    "gn:asciiname":"Sitio Laurentino Hoff",
    "gn:country_code":"BR",
    "gn:dem":886,
    "gn:feature_class":"P",
    "gn:feature_code":"PPL",
    "gn:name":"S\u00edtio Laurentino Hoff",
    "gn:population":0,
    "gn:timezone":"America/Sao_Paulo",
    "iso:country":"BR",
    "name:por_x_preferred":[
        "S\u00edtio Laurentino Hoff"
    ],
    "wof:name":"Sitio Laurentino Hoff",
    "wof:placetype":"locality"
},
  "geometry": {"coordinates":[-49.3089,-26.1914],"type":"Point"}
}