{
  "type": "Feature",
  "properties": {
    "gn:admin1_code":"26",
    "gn:admin2_code":"4205506.0",
    "gn:asciiname":"Butia",
    "gn:country_code":"BR",
    "gn:dem":1015,
    "gn:feature_class":"P",
    "gn:feature_code":"PPL",
    "gn:name":"Buti\u00e1",
    "gn:population":0,
    "gn:timezone":"America/Sao_Paulo",
    "iso:country":"BR",
    "wof:name":"Butia",
    "wof:placetype":"locality"
},
  "geometry": {"coordinates":[-50.83333,-27.11667000000001],"type":"Point"}
}