{
  "type": "Feature",
  "properties": {
    "gn:admin1_code":"26",
    "gn:admin2_code":"4205506.0",
    "gn:asciiname":"Butia",
    "gn:country_code":"BR",
    "gn:dem":1015,
    "gn:feature_class":"P",
    "gn:feature_code":"PPL",
    "gn:name":"Buti\u00e1",
    "gn:population":0,
    "gn:timezone":"America/Sao_Paulo",
    "iso:country":"BR",
    "name:cat_x_preferred":[
        "Butia"
    ],
    "name:ceb_x_preferred":[
        "Butia"
    ],
    "name:deu_x_preferred":[
        "Geleepalmen"
    ],
    "name:fin_x_preferred":[
        "Butiapalmut"
    ],
    "name:fra_x_preferred":[
        "Butia"
    ],
    "name:grn_x_preferred":[
        "Mbotia"
    ],
    "name:ita_x_preferred":[
        "Butia"
    ],
    "name:lit_x_preferred":[
        "Bucija"
    ],
    "name:nld_x_preferred":[
        "Butia"
    ],
    "name:pol_x_preferred":[
        "Butia"
    ],
    "name:por_x_preferred":[
        "Buti\u00e1"
    ],
    "name:rus_x_preferred":[
        "\u0411\u0443\u0442\u0438\u044f"
    ],
    "name:spa_x_preferred":[
        "Butia"
    ],
    "name:swe_x_preferred":[
        "Butia"
    ],
    "name:war_x_preferred":[
        "Butia"
    ],
    "wof:name":"Butia",
    "wof:placetype":"locality"
},
  "geometry": {"coordinates":[-50.83333,-27.11667000000001],"type":"Point"}
}