{
  "type": "Feature",
  "properties": {
    "gn:admin1_code":"18",
    "gn:admin2_code":"4119103.0",
    "gn:asciiname":"Sitio Acir Negrelle",
    "gn:country_code":"BR",
    "gn:dem":811,
    "gn:feature_class":"P",
    "gn:feature_code":"PPL",
    "gn:name":"S\u00edtio Acir Negrelle",
    "gn:population":0,
    "gn:timezone":"America/Sao_Paulo",
    "iso:country":"BR",
    "name:por_x_preferred":[
        "S\u00edtio Acir Negrelle"
    ],
    "wof:name":"Sitio Acir Negrelle",
    "wof:placetype":"locality"
},
  "geometry": {"coordinates":[-49.41999000000001,-26.14138],"type":"Point"}
}