{
  "type": "Feature",
  "properties": {
    "gn:admin1_code":"18.0",
    "gn:admin2_code":"4109708.0",
    "gn:asciiname":"Sitio Marques",
    "gn:country_code":"BR",
    "gn:dem":652,
    "gn:feature_class":"P",
    "gn:feature_code":"PPL",
    "gn:name":"S\u00edtio Marques",
    "gn:population":0,
    "gn:timezone":"America/Sao_Paulo",
    "iso:country":"BR",
    "name:por_x_preferred":[
        "S\u00edtio Marques"
    ],
    "wof:name":"Sitio Marques",
    "wof:placetype":"locality"
},
  "geometry": {"coordinates":[-50.2472,-23.92437],"type":"Point"}
}