{
  "type": "Feature",
  "properties": {
    "gn:admin1_code":"20.0",
    "gn:admin2_code":"2209302.0",
    "gn:asciiname":"Baixao das Ovelhas",
    "gn:country_code":"BR",
    "gn:dem":280,
    "gn:feature_class":"P",
    "gn:feature_code":"PPL",
    "gn:name":"Baix\u00e3o das Ovelhas",
    "gn:population":0,
    "gn:timezone":"America/Fortaleza",
    "iso:country":"BR",
    "name:por_x_preferred":[
        "Baix\u00e3o das Ovelhas"
    ],
    "wof:name":"Baixao das Ovelhas",
    "wof:placetype":"locality"
},
  "geometry": {"coordinates":[-44.23539,-8.97403],"type":"Point"}
}