{
  "type": "Feature",
  "properties": {
    "gn:admin1_code":"27.0",
    "gn:admin2_code":"3550308.0",
    "gn:asciiname":"Parada de Taipas",
    "gn:country_code":"BR",
    "gn:dem":1018,
    "gn:feature_class":"P",
    "gn:feature_code":"PPLL",
    "gn:name":"Parada de Taipas",
    "gn:population":0,
    "gn:timezone":"America/Sao_Paulo",
    "iso:country":"BR",
    "name:por_x_preferred":[
        "Parada de Taipas"
    ],
    "wof:name":"Parada de Taipas",
    "wof:placetype":"locality"
},
  "geometry": {"coordinates":[-46.71077,-23.42411],"type":"Point"}
}