{
  "type": "Feature",
  "properties": {
    "gn:admin1_code":"5",
    "gn:admin2_code":"2930204.0",
    "gn:asciiname":"Mulungu",
    "gn:country_code":"BR",
    "gn:dem":379,
    "gn:feature_class":"P",
    "gn:feature_code":"PPL",
    "gn:name":"Mulungu",
    "gn:population":0,
    "gn:timezone":"America/Bahia",
    "iso:country":"BR",
    "name:ita_x_preferred":[
        "Mulungu"
    ],
    "name:lit_x_preferred":[
        "Mulungu"
    ],
    "name:swe_x_preferred":[
        "Mulungu"
    ],
    "wof:name":"Mulungu",
    "wof:placetype":"locality"
},
  "geometry": {"coordinates":[-40.64942,-9.62345],"type":"Point"}
}