{
  "type": "Feature",
  "properties": {
    "gn:admin1_code":"26.0",
    "gn:admin2_code":"4210100.0",
    "gn:asciiname":"Sitio dos Haid",
    "gn:country_code":"BR",
    "gn:dem":847,
    "gn:feature_class":"P",
    "gn:feature_code":"PPLL",
    "gn:name":"S\u00edtio dos Haid",
    "gn:population":0,
    "gn:timezone":"America/Sao_Paulo",
    "iso:country":"BR",
    "name:por_x_preferred":[
        "S\u00edtio dos Haid"
    ],
    "wof:name":"Sitio dos Haid",
    "wof:placetype":"locality"
},
  "geometry": {"coordinates":[-49.8893,-26.0994],"type":"Point"}
}