{
  "type": "Feature",
  "properties": {
    "gn:admin1_code":"27",
    "gn:admin2_code":"3554508.0",
    "gn:asciiname":"Sitio Estrela",
    "gn:country_code":"BR",
    "gn:dem":555,
    "gn:feature_class":"P",
    "gn:feature_code":"PPL",
    "gn:name":"S\u00edtio Estrela",
    "gn:population":0,
    "gn:timezone":"America/Sao_Paulo",
    "iso:country":"BR",
    "name:por_x_preferred":[
        "S\u00edtio Estrela"
    ],
    "wof:name":"Sitio Estrela",
    "wof:placetype":"locality"
},
  "geometry": {"coordinates":[-47.66167,-23.09806],"type":"Point"}
}