{
  "type": "Feature",
  "properties": {
    "gn:admin1_code":"27.0",
    "gn:admin2_code":"3524600.0",
    "gn:asciiname":"Sitio Jeronimo",
    "gn:country_code":"BR",
    "gn:dem":52,
    "gn:feature_class":"P",
    "gn:feature_code":"PPL",
    "gn:name":"S\u00edtio Jer\u00f4nimo",
    "gn:population":0,
    "gn:timezone":"America/Sao_Paulo",
    "iso:country":"BR",
    "name:por_x_preferred":[
        "S\u00edtio Jer\u00f4nimo"
    ],
    "wof:name":"Sitio Jeronimo",
    "wof:placetype":"locality"
},
  "geometry": {"coordinates":[-48.01749,-24.66032],"type":"Point"}
}