{
  "type": "Feature",
  "properties": {
    "gn:admin1_code":"22",
    "gn:admin2_code":"2400901.0",
    "gn:asciiname":"Corredor",
    "gn:country_code":"BR",
    "gn:dem":295,
    "gn:feature_class":"P",
    "gn:feature_code":"PPL",
    "gn:name":"Corredor",
    "gn:population":0,
    "gn:timezone":"America/Fortaleza",
    "iso:country":"BR",
    "name:cat_x_preferred":[
        "Corredor"
    ],
    "name:ceb_x_preferred":[
        "Corredor"
    ],
    "name:glg_x_preferred":[
        "Corredor"
    ],
    "name:por_x_preferred":[
        "Corredor"
    ],
    "name:spa_x_preferred":[
        "Corredor"
    ],
    "name:swe_x_preferred":[
        "Corredor"
    ],
    "wof:name":"Corredor",
    "wof:placetype":"locality"
},
  "geometry": {"coordinates":[-37.95,-6.18333],"type":"Point"}
}