{
  "type": "Feature",
  "properties": {
    "gn:admin1_code":"18.0",
    "gn:admin2_code":"4107751.0",
    "gn:asciiname":"Sitio Faria",
    "gn:country_code":"BR",
    "gn:dem":611,
    "gn:feature_class":"P",
    "gn:feature_code":"PPL",
    "gn:name":"S\u00edtio Faria",
    "gn:population":0,
    "gn:timezone":"America/Sao_Paulo",
    "iso:country":"BR",
    "name:por_x_preferred":[
        "S\u00edtio Faria"
    ],
    "wof:name":"Sitio Faria",
    "wof:placetype":"locality"
},
  "geometry": {"coordinates":[-50.44896,-23.8956],"type":"Point"}
}