{
  "type": "Feature",
  "properties": {
    "gn:admin1_code":"5",
    "gn:admin2_code":"2919207.0",
    "gn:asciiname":"Portao",
    "gn:country_code":"BR",
    "gn:dem":25,
    "gn:feature_class":"P",
    "gn:feature_code":"PPL",
    "gn:name":"Port\u00e3o",
    "gn:population":0,
    "gn:timezone":"America/Bahia",
    "iso:country":"BR",
    "name:und_x_variant":[
        "Port\u00e3o",
        "Pont\u00e3o"
    ],
    "wof:name":"Portao",
    "wof:placetype":"locality"
},
  "geometry": {"coordinates":[-38.30373,-12.86545],"type":"Point"}
}