{
  "type": "Feature",
  "properties": {
    "gn:admin1_code":"18.0",
    "gn:admin2_code":"4127809.0",
    "gn:asciiname":"Sitio Planalto",
    "gn:country_code":"BR",
    "gn:dem":602,
    "gn:feature_class":"P",
    "gn:feature_code":"PPL",
    "gn:name":"S\u00edtio Planalto",
    "gn:population":0,
    "gn:timezone":"America/Sao_Paulo",
    "iso:country":"BR",
    "name:por_x_preferred":[
        "S\u00edtio Planalto"
    ],
    "wof:name":"Sitio Planalto",
    "wof:placetype":"locality"
},
  "geometry": {"coordinates":[-50.01145,-23.65029],"type":"Point"}
}