{
  "type": "Feature",
  "properties": {
    "gn:admin1_code":"06",
    "gn:admin2_code":"2300408.0",
    "gn:asciiname":"Mulungu",
    "gn:country_code":"BR",
    "gn:dem":594,
    "gn:feature_class":"P",
    "gn:feature_code":"PPL",
    "gn:name":"Mulungu",
    "gn:population":0,
    "gn:timezone":"America/Fortaleza",
    "iso:country":"BR",
    "wof:name":"Mulungu",
    "wof:placetype":"locality"
},
  "geometry": {"coordinates":[-40.45,-6.75],"type":"Point"}
}