{
  "type": "Feature",
  "properties": {
    "gn:admin1_code":"06",
    "gn:admin2_code":"2312403.0",
    "gn:asciiname":"Fazenda Riacho Fundo",
    "gn:country_code":"BR",
    "gn:dem":69,
    "gn:feature_class":"P",
    "gn:feature_code":"PPL",
    "gn:name":"Fazenda Riacho Fundo",
    "gn:population":0,
    "gn:timezone":"America/Fortaleza",
    "iso:country":"BR",
    "wof:name":"Fazenda Riacho Fundo",
    "wof:placetype":"locality"
},
  "geometry": {"coordinates":[-39.26667,-3.55],"type":"Point"}
}