{
  "type": "Feature",
  "properties": {
    "gn:admin1_code":"18",
    "gn:admin2_code":"4100301.0",
    "gn:asciiname":"Sitio Francisco Sarovski",
    "gn:country_code":"BR",
    "gn:dem":879,
    "gn:feature_class":"P",
    "gn:feature_code":"PPL",
    "gn:name":"S\u00edtio Francisco Sarovski",
    "gn:population":0,
    "gn:timezone":"America/Sao_Paulo",
    "iso:country":"BR",
    "name:por_x_preferred":[
        "S\u00edtio Francisco Sarovski"
    ],
    "wof:name":"Sitio Francisco Sarovski",
    "wof:placetype":"locality"
},
  "geometry": {"coordinates":[-49.3658,-26.0357],"type":"Point"}
}