{
  "type": "Feature",
  "properties": {
    "gn:admin1_code":"18.0",
    "gn:admin2_code":"4109708.0",
    "gn:asciiname":"Sitio Lauro Barbosa",
    "gn:country_code":"BR",
    "gn:dem":616,
    "gn:feature_class":"P",
    "gn:feature_code":"PPL",
    "gn:name":"S\u00edtio Lauro Barbosa",
    "gn:population":0,
    "gn:timezone":"America/Sao_Paulo",
    "iso:country":"BR",
    "name:por_x_preferred":[
        "S\u00edtio Lauro Barbosa"
    ],
    "wof:name":"Sitio Lauro Barbosa",
    "wof:placetype":"locality"
},
  "geometry": {"coordinates":[-50.2503,-23.81738],"type":"Point"}
}