{
  "type": "Feature",
  "properties": {
    "gn:admin1_code":"18.0",
    "gn:admin2_code":"4123204.0",
    "gn:asciiname":"Sitio Maeoka",
    "gn:country_code":"BR",
    "gn:dem":726,
    "gn:feature_class":"P",
    "gn:feature_code":"PPL",
    "gn:name":"S\u00edtio Maeoka",
    "gn:population":0,
    "gn:timezone":"America/Sao_Paulo",
    "iso:country":"BR",
    "name:por_x_preferred":[
        "S\u00edtio Maeoka"
    ],
    "wof:name":"Sitio Maeoka",
    "wof:placetype":"locality"
},
  "geometry": {"coordinates":[-50.73325,-23.55154],"type":"Point"}
}