{
  "type": "Feature",
  "properties": {
    "gn:admin1_code":"27.0",
    "gn:admin2_code":"3550308.0",
    "gn:asciiname":"Jardim Itapeva",
    "gn:country_code":"BR",
    "gn:dem":752,
    "gn:feature_class":"P",
    "gn:feature_code":"PPL",
    "gn:name":"Jardim Itapeva",
    "gn:population":0,
    "gn:timezone":"America/Sao_Paulo",
    "iso:country":"BR",
    "name:por_x_preferred":[
        "Jardim Itapeva"
    ],
    "wof:name":"Jardim Itapeva",
    "wof:placetype":"locality"
},
  "geometry": {"coordinates":[-46.745,-23.4791],"type":"Point"}
}