{
  "type": "Feature",
  "properties": {
    "gn:admin1_code":"4.0",
    "gn:admin2_code":"1303536.0",
    "gn:asciiname":"Acampamento Momasa Engenheiro Rio",
    "gn:country_code":"BR",
    "gn:dem":29,
    "gn:feature_class":"P",
    "gn:feature_code":"PPL",
    "gn:name":"Acampamento Momasa Engenheiro Rio",
    "gn:population":0,
    "gn:timezone":"America/Manaus",
    "iso:country":"BR",
    "name:eng_x_preferred":[
        "Momasa River Engineer Camp"
    ],
    "name:por_x_preferred":[
        "Acampamento Momasa Engenheiro Rio"
    ],
    "wof:name":"Acampamento Momasa Engenheiro Rio",
    "wof:placetype":"locality"
},
  "geometry": {"coordinates":[-59.46548000000001,-1.9159],"type":"Point"}
}