{
  "type": "Feature",
  "properties": {
    "gn:admin1_code":"17",
    "gn:admin2_code":"2506707.0",
    "gn:asciiname":"Vertentes",
    "gn:country_code":"BR",
    "gn:dem":784,
    "gn:feature_class":"P",
    "gn:feature_code":"PPL",
    "gn:name":"Vertentes",
    "gn:population":0,
    "gn:timezone":"America/Fortaleza",
    "iso:country":"BR",
    "name:bpy_x_preferred":[
        "\u09ad\u09c7\u09b0\u09cd\u099f\u09c7\u09a8\u099f\u09c7\u09b8"
    ],
    "name:ceb_x_preferred":[
        "Vertentes"
    ],
    "name:eus_x_preferred":[
        "Vertentes"
    ],
    "name:fra_x_preferred":[
        "Vertentes"
    ],
    "name:ita_x_preferred":[
        "Vertentes"
    ],
    "name:kat_x_preferred":[
        "\u10d5\u10d4\u10e0\u10e2\u10d4\u10dc\u10e2\u10d8\u10e1\u10d8"
    ],
    "name:mlg_x_preferred":[
        "Vertentes"
    ],
    "name:nld_x_preferred":[
        "Vertentes"
    ],
    "name:nor_x_preferred":[
        "Vertentes"
    ],
    "name:por_x_preferred":[
        "Vertentes"
    ],
    "name:ron_x_preferred":[
        "Vertentes"
    ],
    "name:rus_x_preferred":[
        "\u0412\u0435\u0440\u0442\u0435\u043d\u0442\u0438\u0441"
    ],
    "name:swe_x_preferred":[
        "Vertentes"
    ],
    "name:vie_x_preferred":[
        "Vertentes"
    ],
    "name:vol_x_preferred":[
        "Vertentes"
    ],
    "name:war_x_preferred":[
        "Vertentes"
    ],
    "name:zho_x_preferred":[
        "\u97e6\u5c14\u6ed5\u8482\u65af"
    ],
    "wof:name":"Vertentes",
    "wof:placetype":"locality"
},
  "geometry": {"coordinates":[-37.48333,-7.33333],"type":"Point"}
}