{
  "type": "Feature",
  "properties": {
    "gn:admin1_code":"17",
    "gn:admin2_code":"2506707.0",
    "gn:asciiname":"Vertentes",
    "gn:country_code":"BR",
    "gn:dem":784,
    "gn:feature_class":"P",
    "gn:feature_code":"PPL",
    "gn:name":"Vertentes",
    "gn:population":0,
    "gn:timezone":"America/Fortaleza",
    "iso:country":"BR",
    "wof:name":"Vertentes",
    "wof:placetype":"locality"
},
  "geometry": {"coordinates":[-37.48333,-7.33333],"type":"Point"}
}