{
  "type": "Feature",
  "properties": {
    "gn:admin1_code":"18.0",
    "gn:admin2_code":"4124707.0",
    "gn:asciiname":"Sitio Viloca",
    "gn:country_code":"BR",
    "gn:dem":749,
    "gn:feature_class":"P",
    "gn:feature_code":"PPL",
    "gn:name":"S\u00edtio Viloca",
    "gn:population":0,
    "gn:timezone":"America/Sao_Paulo",
    "iso:country":"BR",
    "name:por_x_preferred":[
        "S\u00edtio Viloca"
    ],
    "wof:name":"Sitio Viloca",
    "wof:placetype":"locality"
},
  "geometry": {"coordinates":[-50.7243,-23.62612],"type":"Point"}
}