{
  "type": "Feature",
  "properties": {
    "gn:admin1_code":"15.0",
    "gn:admin2_code":"3135209.0",
    "gn:asciiname":"Tijuco",
    "gn:country_code":"BR",
    "gn:dem":518,
    "gn:feature_class":"P",
    "gn:feature_code":"PPL",
    "gn:name":"Tijuco",
    "gn:population":0,
    "gn:timezone":"America/Sao_Paulo",
    "iso:country":"BR",
    "name:por_x_preferred":[
        "Tijuco"
    ],
    "wof:name":"Tijuco",
    "wof:placetype":"locality"
},
  "geometry": {"coordinates":[-44.58365,-15.56182],"type":"Point"}
}