{
  "type": "Feature",
  "properties": {
    "gn:admin1_code":"6",
    "gn:admin2_code":"2308708.0",
    "gn:asciiname":"Bento Pereira",
    "gn:country_code":"BR",
    "gn:dem":49,
    "gn:feature_class":"P",
    "gn:feature_code":"PPL",
    "gn:name":"Bento Pereira",
    "gn:population":0,
    "gn:timezone":"America/Fortaleza",
    "iso:country":"BR",
    "wof:name":"Bento Pereira",
    "wof:placetype":"locality"
},
  "geometry": {"coordinates":[-38.35,-5.11667],"type":"Point"}
}