{
  "type": "Feature",
  "properties": {
    "gn:admin1_code":"23",
    "gn:admin2_code":"4317103.0",
    "gn:asciiname":"Estancia do Cati",
    "gn:country_code":"BR",
    "gn:dem":174,
    "gn:feature_class":"P",
    "gn:feature_code":"PPL",
    "gn:name":"Est\u00e2ncia do Cati",
    "gn:population":0,
    "gn:timezone":"America/Sao_Paulo",
    "iso:country":"BR",
    "wof:name":"Estancia do Cati",
    "wof:placetype":"locality"
},
  "geometry": {"coordinates":[-56.15,-30.48333],"type":"Point"}
}