{
  "type": "Feature",
  "properties": {
    "gn:admin1_code":"26",
    "gn:admin2_code":"4210001.0",
    "gn:asciiname":"Braco Paula Ramos",
    "gn:country_code":"BR",
    "gn:dem":245,
    "gn:feature_class":"P",
    "gn:feature_code":"PPLL",
    "gn:name":"Bra\u00e7o Paula Ramos",
    "gn:population":0,
    "gn:timezone":"America/Sao_Paulo",
    "iso:country":"BR",
    "name:por_x_preferred":[
        "Bra\u00e7o Paula Ramos"
    ],
    "wof:name":"Braco Paula Ramos",
    "wof:placetype":"locality"
},
  "geometry": {"coordinates":[-49.0045,-26.7532],"type":"Point"}
}