{
  "type": "Feature",
  "properties": {
    "gn:admin1_code":"5",
    "gn:admin2_code":"2907202.0",
    "gn:asciiname":"Baixa Grande",
    "gn:country_code":"BR",
    "gn:dem":385,
    "gn:feature_class":"P",
    "gn:feature_code":"PPL",
    "gn:name":"Baixa Grande",
    "gn:population":0,
    "gn:timezone":"America/Bahia",
    "iso:country":"BR",
    "wof:name":"Baixa Grande",
    "wof:placetype":"locality"
},
  "geometry": {"coordinates":[-40.96667,-9.13333],"type":"Point"}
}