{
  "type": "Feature",
  "properties": {
    "gn:admin1_code":"18",
    "gn:admin2_code":"4107124.0",
    "gn:asciiname":"Diamante",
    "gn:country_code":"BR",
    "gn:dem":535,
    "gn:feature_class":"P",
    "gn:feature_code":"PPL",
    "gn:name":"Diamante",
    "gn:population":0,
    "gn:timezone":"America/Sao_Paulo",
    "iso:country":"BR",
    "name:cat_x_preferred":[
        "Diamante"
    ],
    "name:ceb_x_preferred":[
        "Diamante"
    ],
    "name:deu_x_preferred":[
        "Diamante"
    ],
    "name:epo_x_preferred":[
        "Diamante"
    ],
    "name:fra_x_preferred":[
        "Diamante"
    ],
    "name:ita_x_preferred":[
        "Diamante"
    ],
    "name:jpn_x_preferred":[
        "\u30c7\u30a3\u30a2\u30de\u30f3\u30c6"
    ],
    "name:nld_x_preferred":[
        "Diamante"
    ],
    "name:por_x_preferred":[
        "Diamante"
    ],
    "name:ron_x_preferred":[
        "Diamante"
    ],
    "name:rus_x_preferred":[
        "\u0414\u0438\u0430\u043c\u0430\u043d\u0442"
    ],
    "name:slk_x_preferred":[
        "Diamante"
    ],
    "name:spa_x_preferred":[
        "Diamante"
    ],
    "name:swe_x_preferred":[
        "Diamante"
    ],
    "name:ukr_x_preferred":[
        "\u0414\u0456\u0430\u043c\u0430\u043d\u0442"
    ],
    "name:vol_x_preferred":[
        "Diamante"
    ],
    "wof:name":"Diamante",
    "wof:placetype":"locality"
},
  "geometry": {"coordinates":[-52.73333,-24.95],"type":"Point"}
}