{
  "type": "Feature",
  "properties": {
    "gn:admin1_code":"18",
    "gn:admin2_code":"4107124.0",
    "gn:asciiname":"Diamante",
    "gn:country_code":"BR",
    "gn:dem":535,
    "gn:feature_class":"P",
    "gn:feature_code":"PPL",
    "gn:name":"Diamante",
    "gn:population":0,
    "gn:timezone":"America/Sao_Paulo",
    "iso:country":"BR",
    "wof:name":"Diamante",
    "wof:placetype":"locality"
},
  "geometry": {"coordinates":[-52.73333,-24.95],"type":"Point"}
}