{
  "type": "Feature",
  "properties": {
    "gn:admin1_code":"27",
    "gn:admin2_code":"3556453.0",
    "gn:asciiname":"Sitio Belo Horizonte",
    "gn:country_code":"BR",
    "gn:dem":897,
    "gn:feature_class":"P",
    "gn:feature_code":"PPL",
    "gn:name":"S\u00edtio Belo Horizonte",
    "gn:population":0,
    "gn:timezone":"America/Sao_Paulo",
    "iso:country":"BR",
    "name:por_x_preferred":[
        "S\u00edtio Belo Horizonte"
    ],
    "wof:name":"Sitio Belo Horizonte",
    "wof:placetype":"locality"
},
  "geometry": {"coordinates":[-47.03046,-23.59688],"type":"Point"}
}