{
  "type": "Feature",
  "properties": {
    "gn:admin1_code":"5",
    "gn:admin2_code":"2903805.0",
    "gn:asciiname":"Terreiro",
    "gn:country_code":"BR",
    "gn:dem":373,
    "gn:feature_class":"P",
    "gn:feature_code":"PPL",
    "gn:name":"Terreiro",
    "gn:population":0,
    "gn:timezone":"America/Bahia",
    "iso:country":"BR",
    "wof:name":"Terreiro",
    "wof:placetype":"locality"
},
  "geometry": {"coordinates":[-40.95,-12.91667],"type":"Point"}
}