{
  "type": "Feature",
  "properties": {
    "gn:admin1_code":"18.0",
    "gn:admin2_code":"4113205.0",
    "gn:asciiname":"Sitio Teodoro Kanut",
    "gn:country_code":"BR",
    "gn:dem":914,
    "gn:feature_class":"P",
    "gn:feature_code":"PPL",
    "gn:name":"S\u00edtio Teodoro Kanut",
    "gn:population":0,
    "gn:timezone":"America/Sao_Paulo",
    "iso:country":"BR",
    "name:por_x_preferred":[
        "S\u00edtio Teodoro Kanut"
    ],
    "wof:name":"Sitio Teodoro Kanut",
    "wof:placetype":"locality"
},
  "geometry": {"coordinates":[-49.78085,-25.81601],"type":"Point"}
}