{
  "type": "Feature",
  "properties": {
    "gn:admin1_code":"27",
    "gn:admin2_code":"3528502.0",
    "gn:asciiname":"Sitio Regina",
    "gn:country_code":"BR",
    "gn:dem":886,
    "gn:feature_class":"P",
    "gn:feature_code":"PPL",
    "gn:name":"S\u00edtio Regina",
    "gn:population":0,
    "gn:timezone":"America/Sao_Paulo",
    "iso:country":"BR",
    "name:por_x_preferred":[
        "S\u00edtio Regina"
    ],
    "wof:name":"Sitio Regina",
    "wof:placetype":"locality"
},
  "geometry": {"coordinates":[-46.615,-23.2475],"type":"Point"}
}