{
  "type": "Feature",
  "properties": {
    "gn:admin1_code":"18.0",
    "gn:admin2_code":"4107736.0",
    "gn:asciiname":"Avencal",
    "gn:country_code":"BR",
    "gn:dem":882,
    "gn:feature_class":"P",
    "gn:feature_code":"PPL",
    "gn:name":"Avencal",
    "gn:population":0,
    "gn:timezone":"America/Sao_Paulo",
    "iso:country":"BR",
    "name:por_x_preferred":[
        "Avencal"
    ],
    "wof:name":"Avencal",
    "wof:placetype":"locality"
},
  "geometry": {"coordinates":[-50.42894,-25.5538],"type":"Point"}
}