{
  "type": "Feature",
  "properties": {
    "gn:admin1_code":"18",
    "gn:admin2_code":"4104204.0",
    "gn:asciiname":"Dom Rodrigo",
    "gn:cc2":"BR",
    "gn:country_code":"BR",
    "gn:dem":849,
    "gn:feature_class":"P",
    "gn:feature_code":"PPL",
    "gn:name":"Dom Rodrigo",
    "gn:population":0,
    "gn:timezone":"America/Sao_Paulo",
    "iso:country":"BR",
    "name:und_x_variant":[
        "Don Rodrigo",
        "Dom Rodrigo"
    ],
    "wof:name":"Dom Rodrigo",
    "wof:placetype":"locality"
},
  "geometry": {"coordinates":[-49.61667,-25.41667],"type":"Point"}
}