{
  "type": "Feature",
  "properties": {
    "gn:admin1_code":"13",
    "gn:admin2_code":"2100600.0",
    "gn:asciiname":"Nazare",
    "gn:country_code":"BR",
    "gn:dem":198,
    "gn:feature_class":"P",
    "gn:feature_code":"PPL",
    "gn:name":"Nazar\u00e9",
    "gn:population":0,
    "gn:timezone":"America/Fortaleza",
    "iso:country":"BR",
    "wof:name":"Nazare",
    "wof:placetype":"locality"
},
  "geometry": {"coordinates":[-46.56667,-5.65],"type":"Point"}
}