{
  "type": "Feature",
  "properties": {
    "gn:admin1_code":"5",
    "gn:admin2_code":"2913705.0",
    "gn:asciiname":"Jurema",
    "gn:country_code":"BR",
    "gn:dem":281,
    "gn:feature_class":"P",
    "gn:feature_code":"PPL",
    "gn:name":"Jurema",
    "gn:population":0,
    "gn:timezone":"America/Bahia",
    "iso:country":"BR",
    "name:ceb_x_preferred":[
        "Jurema"
    ],
    "name:deu_x_preferred":[
        "Jurema"
    ],
    "name:ita_x_preferred":[
        "Jurema"
    ],
    "name:nld_x_preferred":[
        "Jurema"
    ],
    "name:nor_x_preferred":[
        "Jurema"
    ],
    "name:por_x_preferred":[
        "Jurema"
    ],
    "name:spa_x_preferred":[
        "Jurema"
    ],
    "name:swe_x_preferred":[
        "Jurema"
    ],
    "name:vie_x_preferred":[
        "Jurema"
    ],
    "name:vol_x_preferred":[
        "Jurema"
    ],
    "wof:name":"Jurema",
    "wof:placetype":"locality"
},
  "geometry": {"coordinates":[-38.41667,-11.53333],"type":"Point"}
}