{
  "type": "Feature",
  "properties": {
    "gn:admin1_code":"20",
    "gn:admin2_code":"2201606.0",
    "gn:asciiname":"Calumbi",
    "gn:country_code":"BR",
    "gn:dem":81,
    "gn:feature_class":"P",
    "gn:feature_code":"PPL",
    "gn:name":"Calumbi",
    "gn:population":0,
    "gn:timezone":"America/Fortaleza",
    "iso:country":"BR",
    "wof:name":"Calumbi",
    "wof:placetype":"locality"
},
  "geometry": {"coordinates":[-42.53333,-5.38333],"type":"Point"}
}