{
  "type": "Feature",
  "properties": {
    "gn:admin1_code":"18.0",
    "gn:admin2_code":"4102406.0",
    "gn:asciiname":"Sitio Jose Aparecido Marquiena",
    "gn:country_code":"BR",
    "gn:dem":393,
    "gn:feature_class":"P",
    "gn:feature_code":"PPL",
    "gn:name":"S\u00edtio Jos\u00e9 Aparecido Marquiena",
    "gn:population":0,
    "gn:timezone":"America/Sao_Paulo",
    "iso:country":"BR",
    "name:por_x_preferred":[
        "S\u00edtio Jos\u00e9 Aparecido Marquiena"
    ],
    "wof:name":"Sitio Jose Aparecido Marquiena",
    "wof:placetype":"locality"
},
  "geometry": {"coordinates":[-50.2481,-23.1137],"type":"Point"}
}