{
  "type": "Feature",
  "properties": {
    "gn:admin1_code":"27",
    "gn:admin2_code":"3528809.0",
    "gn:asciiname":"Laranjeiras",
    "gn:country_code":"BR",
    "gn:dem":381,
    "gn:feature_class":"P",
    "gn:feature_code":"PPL",
    "gn:name":"Laranjeiras",
    "gn:population":0,
    "gn:timezone":"America/Sao_Paulo",
    "iso:country":"BR",
    "name:bpy_x_preferred":[
        "\u09b2\u09be\u09b0\u09be\u09a8\u099c\u09c7\u0987\u09b0\u09be\u09b8"
    ],
    "name:heb_x_preferred":[
        "\u05dc\u05e8\u05e0\u05d6'\u05d9\u05d9\u05e8\u05e1"
    ],
    "name:srp_x_preferred":[
        "\u041b\u0430\u0440\u0430\u043d\u0436\u0435\u0438\u0440\u0430\u0441"
    ],
    "name:tur_x_preferred":[
        "Laranjeiras"
    ],
    "name:urd_x_preferred":[
        "\u0644\u0627\u0631\u0627\u0646\u062c\u06cc\u0631\u0627\u0633"
    ],
    "name:zho_x_preferred":[
        "\u62c9\u5170\u70ed\u62c9\u65af"
    ],
    "wof:name":"Laranjeiras",
    "wof:placetype":"locality"
},
  "geometry": {"coordinates":[-50.86667,-22.66667],"type":"Point"}
}