{
  "type": "Feature",
  "properties": {
    "gn:admin1_code":"27",
    "gn:admin2_code":"3528809.0",
    "gn:asciiname":"Laranjeiras",
    "gn:country_code":"BR",
    "gn:dem":381,
    "gn:feature_class":"P",
    "gn:feature_code":"PPL",
    "gn:name":"Laranjeiras",
    "gn:population":0,
    "gn:timezone":"America/Sao_Paulo",
    "iso:country":"BR",
    "wof:name":"Laranjeiras",
    "wof:placetype":"locality"
},
  "geometry": {"coordinates":[-50.86667,-22.66667],"type":"Point"}
}