{
  "type": "Feature",
  "properties": {
    "gn:admin1_code":"13",
    "gn:admin2_code":"2110237.0",
    "gn:asciiname":"Riachao Teixeiras",
    "gn:cc2":"BR",
    "gn:country_code":"BR",
    "gn:dem":40,
    "gn:feature_class":"P",
    "gn:feature_code":"PPL",
    "gn:name":"Riach\u00e3o Teixeiras",
    "gn:population":0,
    "gn:timezone":"America/Fortaleza",
    "iso:country":"BR",
    "name:und_x_variant":[
        "Riach\u00e3o",
        "Riach\u00e3o Teixeiras"
    ],
    "wof:name":"Riachao Teixeiras",
    "wof:placetype":"locality"
},
  "geometry": {"coordinates":[-42.36667,-3.11667],"type":"Point"}
}