{
  "type": "Feature",
  "properties": {
    "gn:admin1_code":"27",
    "gn:admin2_code":"3553302.0",
    "gn:asciiname":"Corrego Fundo",
    "gn:country_code":"BR",
    "gn:dem":767,
    "gn:feature_class":"P",
    "gn:feature_code":"PPL",
    "gn:name":"C\u00f3rrego Fundo",
    "gn:population":0,
    "gn:timezone":"America/Sao_Paulo",
    "iso:country":"BR",
    "name:por_x_preferred":[
        "C\u00f3rrego Fundo"
    ],
    "wof:name":"Corrego Fundo",
    "wof:placetype":"locality"
},
  "geometry": {"coordinates":[-47.35,-21.61667000000001],"type":"Point"}
}