{
  "type": "Feature",
  "properties": {
    "gn:admin1_code":"30",
    "gn:admin2_code":"2607703.0",
    "gn:asciiname":"Cangalha",
    "gn:country_code":"BR",
    "gn:dem":614,
    "gn:feature_class":"P",
    "gn:feature_code":"PPL",
    "gn:name":"Cangalha",
    "gn:population":0,
    "gn:timezone":"America/Recife",
    "iso:country":"BR",
    "wof:name":"Cangalha",
    "wof:placetype":"locality"
},
  "geometry": {"coordinates":[-37.08333,-7.43333],"type":"Point"}
}