{
  "type": "Feature",
  "properties": {
    "gn:admin1_code":"15",
    "gn:admin2_code":"3113008.0",
    "gn:asciiname":"Joaquim Pereira dos Santos",
    "gn:country_code":"BR",
    "gn:dem":758,
    "gn:feature_class":"P",
    "gn:feature_code":"PPL",
    "gn:name":"Joaquim Pereira dos Santos",
    "gn:population":0,
    "gn:timezone":"America/Sao_Paulo",
    "iso:country":"BR",
    "name:por_x_preferred":[
        "Joaquim Pereira dos Santos"
    ],
    "wof:name":"Joaquim Pereira dos Santos",
    "wof:placetype":"locality"
},
  "geometry": {"coordinates":[-41.38333,-17.06667],"type":"Point"}
}