{
  "type": "Feature",
  "properties": {
    "gn:admin1_code":"5",
    "gn:admin2_code":"2905602.0",
    "gn:asciiname":"Secador",
    "gn:country_code":"BR",
    "gn:dem":167,
    "gn:feature_class":"P",
    "gn:feature_code":"PPL",
    "gn:name":"Secador",
    "gn:population":0,
    "gn:timezone":"America/Bahia",
    "iso:country":"BR",
    "wof:name":"Secador",
    "wof:placetype":"locality"
},
  "geometry": {"coordinates":[-39.48333,-15.41667],"type":"Point"}
}