{
  "type": "Feature",
  "properties": {
    "gn:admin1_code":"5",
    "gn:admin2_code":"2904902.0",
    "gn:asciiname":"Engenho Velho",
    "gn:country_code":"BR",
    "gn:dem":149,
    "gn:feature_class":"P",
    "gn:feature_code":"PPL",
    "gn:name":"Engenho Velho",
    "gn:population":0,
    "gn:timezone":"America/Bahia",
    "iso:country":"BR",
    "wof:name":"Engenho Velho",
    "wof:placetype":"locality"
},
  "geometry": {"coordinates":[-38.85,-12.76667],"type":"Point"}
}