{
  "type": "Feature",
  "properties": {
    "gn:admin1_code":"5",
    "gn:admin2_code":"2904902.0",
    "gn:asciiname":"Engenho Velho",
    "gn:country_code":"BR",
    "gn:dem":149,
    "gn:feature_class":"P",
    "gn:feature_code":"PPL",
    "gn:name":"Engenho Velho",
    "gn:population":0,
    "gn:timezone":"America/Bahia",
    "iso:country":"BR",
    "name:bpy_x_preferred":[
        "\u098f\u09a8\u0997\u09c7\u09a8\u09b9\u09cb \u09ad\u09c7\u09b2\u09b9\u09cb"
    ],
    "name:ceb_x_preferred":[
        "Engenho Velho"
    ],
    "name:epo_x_preferred":[
        "Engenho Velho"
    ],
    "name:eus_x_preferred":[
        "Engenho Velho"
    ],
    "name:fra_x_preferred":[
        "Engenho Velho"
    ],
    "name:hye_x_preferred":[
        "\u0537\u0576\u056a\u0565\u0576\u0575\u0578\u0582 \u054e\u0565\u056c\u0575\u0578\u0582"
    ],
    "name:ita_x_preferred":[
        "Engenho Velho"
    ],
    "name:kaz_x_preferred":[
        "\u042d\u043d\u0436\u0435\u043d\u044c\u044e-\u0412\u0435\u043b\u044c\u044e"
    ],
    "name:mlg_x_preferred":[
        "Engenho Velho"
    ],
    "name:nld_x_preferred":[
        "Engenho Velho"
    ],
    "name:nor_x_preferred":[
        "Engenho Velho"
    ],
    "name:pol_x_preferred":[
        "Engenho Velho"
    ],
    "name:por_x_preferred":[
        "Engenho Velho"
    ],
    "name:ron_x_preferred":[
        "Engenho Velho"
    ],
    "name:rus_x_preferred":[
        "\u042d\u043d\u0436\u0435\u043d\u044c\u044e-\u0412\u0435\u043b\u044c\u044e"
    ],
    "name:spa_x_preferred":[
        "Engenho Velho"
    ],
    "name:swe_x_preferred":[
        "Engenho Velho"
    ],
    "name:vie_x_preferred":[
        "Engenho Velho"
    ],
    "name:vol_x_preferred":[
        "Engenho Velho"
    ],
    "name:war_x_preferred":[
        "Engenho Velho"
    ],
    "name:zho_x_preferred":[
        "\u65e7\u6069\u70ed\u7ebd"
    ],
    "wof:name":"Engenho Velho",
    "wof:placetype":"locality"
},
  "geometry": {"coordinates":[-38.85,-12.76667],"type":"Point"}
}