{
  "type": "Feature",
  "properties": {
    "gn:admin1_code":"24",
    "gn:admin2_code":"1100130.0",
    "gn:asciiname":"Milho",
    "gn:cc2":"BR",
    "gn:country_code":"BR",
    "gn:dem":118,
    "gn:feature_class":"P",
    "gn:feature_code":"PPL",
    "gn:name":"Milho",
    "gn:population":0,
    "gn:timezone":"America/Porto_Velho",
    "iso:country":"BR",
    "name:und_x_variant":[
        "Maroins",
        "Milho"
    ],
    "wof:name":"Milho",
    "wof:placetype":"locality"
},
  "geometry": {"coordinates":[-61.93333000000001,-9.01667],"type":"Point"}
}