{
  "type": "Feature",
  "properties": {
    "gn:admin1_code":"5",
    "gn:admin2_code":"2930907.0",
    "gn:asciiname":"Curral Velho",
    "gn:country_code":"BR",
    "gn:dem":766,
    "gn:feature_class":"P",
    "gn:feature_code":"PPL",
    "gn:name":"Curral Velho",
    "gn:population":0,
    "gn:timezone":"America/Bahia",
    "iso:country":"BR",
    "name:por_x_preferred":[
        "Curral Velho"
    ],
    "wof:name":"Curral Velho",
    "wof:placetype":"locality"
},
  "geometry": {"coordinates":[-44.11424,-12.62571],"type":"Point"}
}