{
  "type": "Feature",
  "properties": {
    "gn:admin1_code":"4",
    "gn:admin2_code":"1303304.0",
    "gn:asciiname":"Bela Vista",
    "gn:cc2":"BR",
    "gn:country_code":"BR",
    "gn:dem":119,
    "gn:feature_class":"P",
    "gn:feature_code":"PPL",
    "gn:name":"Bela Vista",
    "gn:population":0,
    "gn:timezone":"America/Manaus",
    "iso:country":"BR",
    "name:ukr_x_preferred":[
        "\u0411\u0435\u043b\u0430-\u0412\u0456\u0441\u0442\u0430"
    ],
    "name:und_x_variant":[
        "Bella Vista",
        "Bela Vista"
    ],
    "wof:name":"Bela Vista",
    "wof:placetype":"locality"
},
  "geometry": {"coordinates":[-60.95,-8.11667],"type":"Point"}
}