{
  "type": "Feature",
  "properties": {
    "gn:admin1_code":"26.0",
    "gn:admin2_code":"4205100.0",
    "gn:asciiname":"Caminho do Posto",
    "gn:country_code":"BR",
    "gn:dem":382,
    "gn:feature_class":"P",
    "gn:feature_code":"PPL",
    "gn:name":"Caminho do Posto",
    "gn:population":0,
    "gn:timezone":"America/Sao_Paulo",
    "iso:country":"BR",
    "name:por_x_preferred":[
        "Caminho do Posto"
    ],
    "wof:name":"Caminho do Posto",
    "wof:placetype":"locality"
},
  "geometry": {"coordinates":[-49.68962,-26.96587],"type":"Point"}
}