{
  "type": "Feature",
  "properties": {
    "gn:admin1_code":"18.0",
    "gn:admin2_code":"4109609.0",
    "gn:asciiname":"Sitio Arno Kretschmer",
    "gn:country_code":"BR",
    "gn:dem":4,
    "gn:feature_class":"P",
    "gn:feature_code":"PPL",
    "gn:name":"S\u00edtio Arno Kretschmer",
    "gn:population":0,
    "gn:timezone":"America/Sao_Paulo",
    "iso:country":"BR",
    "name:por_x_preferred":[
        "S\u00edtio Arno Kretschmer"
    ],
    "wof:name":"Sitio Arno Kretschmer",
    "wof:placetype":"locality"
},
  "geometry": {"coordinates":[-48.78537,-25.86153],"type":"Point"}
}