{
  "type": "Feature",
  "properties": {
    "gn:admin1_code":"11",
    "gn:admin2_code":"5006002.0",
    "gn:asciiname":"Pocao",
    "gn:cc2":"BR",
    "gn:country_code":"BR",
    "gn:dem":328,
    "gn:feature_class":"P",
    "gn:feature_code":"PPL",
    "gn:name":"Po\u00e7\u00e3o",
    "gn:population":0,
    "gn:timezone":"America/Campo_Grande",
    "iso:country":"BR",
    "name:und_x_variant":[
        "Limoeiro",
        "Fazenda Limoeiro",
        "Po\u00e7\u00e3o"
    ],
    "wof:name":"Pocao",
    "wof:placetype":"locality"
},
  "geometry": {"coordinates":[-54.15,-21.66667],"type":"Point"}
}