{
  "type": "Feature",
  "properties": {
    "gn:admin1_code":"18.0",
    "gn:admin2_code":"4127106.0",
    "gn:asciiname":"Estacao Olaria",
    "gn:country_code":"BR",
    "gn:dem":977,
    "gn:feature_class":"P",
    "gn:feature_code":"PPL",
    "gn:name":"Esta\u00e7\u00e3o Olaria",
    "gn:population":0,
    "gn:timezone":"America/Sao_Paulo",
    "iso:country":"BR",
    "wof:name":"Estacao Olaria",
    "wof:placetype":"locality"
},
  "geometry": {"coordinates":[-50.43505,-24.23187],"type":"Point"}
}