{
  "type": "Feature",
  "properties": {
    "gn:admin1_code":"23",
    "gn:admin2_code":"4302808.0",
    "gn:asciiname":"Caraja",
    "gn:country_code":"BR",
    "gn:dem":210,
    "gn:feature_class":"P",
    "gn:feature_code":"PPL",
    "gn:name":"Caraj\u00e1",
    "gn:population":0,
    "gn:timezone":"America/Sao_Paulo",
    "iso:country":"BR",
    "wof:name":"Caraja",
    "wof:placetype":"locality"
},
  "geometry": {"coordinates":[-53.68333000000001,-30.71667],"type":"Point"}
}