{
  "type": "Feature",
  "properties": {
    "gn:admin1_code":"16",
    "gn:admin2_code":"1505551.0",
    "gn:asciiname":"Salobro",
    "gn:cc2":"BR",
    "gn:country_code":"BR",
    "gn:dem":184,
    "gn:feature_class":"P",
    "gn:feature_code":"PPL",
    "gn:name":"Salobro",
    "gn:population":0,
    "gn:timezone":"America/Belem",
    "iso:country":"BR",
    "name:und_x_variant":[
        "Salobre",
        "Salobro"
    ],
    "wof:name":"Salobro",
    "wof:placetype":"locality"
},
  "geometry": {"coordinates":[-49.91667,-7.75],"type":"Point"}
}