{
  "type": "Feature",
  "properties": {
    "gn:admin1_code":"20",
    "gn:admin2_code":"2207777.0",
    "gn:asciiname":"Boqueirao",
    "gn:country_code":"BR",
    "gn:dem":273,
    "gn:feature_class":"P",
    "gn:feature_code":"PPL",
    "gn:name":"Boqueir\u00e3o",
    "gn:population":0,
    "gn:timezone":"America/Fortaleza",
    "iso:country":"BR",
    "wof:name":"Boqueirao",
    "wof:placetype":"locality"
},
  "geometry": {"coordinates":[-41.33333,-7.63333],"type":"Point"}
}