{
  "type": "Feature",
  "properties": {
    "gn:admin1_code":"5",
    "gn:admin2_code":"2904753.0",
    "gn:asciiname":"Jose Goncalo",
    "gn:country_code":"BR",
    "gn:dem":484,
    "gn:feature_class":"P",
    "gn:feature_code":"PPL",
    "gn:name":"Jos\u00e9 Gon\u00e7alo",
    "gn:population":0,
    "gn:timezone":"America/Bahia",
    "iso:country":"BR",
    "wof:name":"Jose Goncalo",
    "wof:placetype":"locality"
},
  "geometry": {"coordinates":[-43.70152,-10.75725],"type":"Point"}
}