{
  "type": "Feature",
  "properties": {
    "gn:admin1_code":"18",
    "gn:admin2_code":"4119103.0",
    "gn:asciiname":"Sitio Ivo Moreno",
    "gn:country_code":"BR",
    "gn:dem":972,
    "gn:feature_class":"P",
    "gn:feature_code":"PPL",
    "gn:name":"S\u00edtio Ivo Moreno",
    "gn:population":0,
    "gn:timezone":"America/Sao_Paulo",
    "iso:country":"BR",
    "name:por_x_preferred":[
        "S\u00edtio Ivo Moreno"
    ],
    "wof:name":"Sitio Ivo Moreno",
    "wof:placetype":"locality"
},
  "geometry": {"coordinates":[-49.4781,-26.0557],"type":"Point"}
}