{
  "type": "Feature",
  "properties": {
    "gn:admin1_code":"31.0",
    "gn:admin2_code":"1722107.0",
    "gn:asciiname":"Remanso dos Botos",
    "gn:country_code":"BR",
    "gn:dem":144,
    "gn:feature_class":"P",
    "gn:feature_code":"PPL",
    "gn:name":"Remanso dos Botos",
    "gn:population":0,
    "gn:timezone":"America/Araguaina",
    "iso:country":"BR",
    "wof:name":"Remanso dos Botos",
    "wof:placetype":"locality"
},
  "geometry": {"coordinates":[-48.37600000000001,-6.38463],"type":"Point"}
}