{
  "type": "Feature",
  "properties": {
    "gn:admin1_code":"20",
    "gn:admin2_code":"2202174.0",
    "gn:asciiname":"Variante",
    "gn:country_code":"BR",
    "gn:dem":42,
    "gn:feature_class":"P",
    "gn:feature_code":"PPL",
    "gn:name":"Variante",
    "gn:population":0,
    "gn:timezone":"America/Fortaleza",
    "iso:country":"BR",
    "wof:name":"Variante",
    "wof:placetype":"locality"
},
  "geometry": {"coordinates":[-42.64111,-3.885],"type":"Point"}
}