{
  "type": "Feature",
  "properties": {
    "gn:admin1_code":"13",
    "gn:admin2_code":"2103208.0",
    "gn:asciiname":"Baixinha I",
    "gn:country_code":"BR",
    "gn:dem":50,
    "gn:feature_class":"P",
    "gn:feature_code":"PPL",
    "gn:name":"Baixinha I",
    "gn:population":0,
    "gn:timezone":"America/Fortaleza",
    "iso:country":"BR",
    "wof:name":"Baixinha I",
    "wof:placetype":"locality"
},
  "geometry": {"coordinates":[-43.49472,-3.41278],"type":"Point"}
}