{
  "type": "Feature",
  "properties": {
    "gn:admin1_code":"4",
    "gn:admin2_code":"1302207.0",
    "gn:asciiname":"Nova Vida",
    "gn:country_code":"BR",
    "gn:dem":63,
    "gn:feature_class":"P",
    "gn:feature_code":"PPL",
    "gn:name":"Nova Vida",
    "gn:population":0,
    "gn:timezone":"America/Manaus",
    "iso:country":"BR",
    "wof:name":"Nova Vida",
    "wof:placetype":"locality"
},
  "geometry": {"coordinates":[-66.42076,-3.95898],"type":"Point"}
}