{
  "type": "Feature",
  "properties": {
    "gn:admin1_code":"27",
    "gn:admin2_code":"3518404.0",
    "gn:asciiname":"Santana dos Piloes",
    "gn:cc2":"BR",
    "gn:country_code":"BR",
    "gn:dem":957,
    "gn:feature_class":"P",
    "gn:feature_code":"PPL",
    "gn:name":"Santana dos Pil\u00f5es",
    "gn:population":0,
    "gn:timezone":"America/Sao_Paulo",
    "iso:country":"BR",
    "name:und_x_variant":[
        "Pil\u00f5es",
        "Santa Ana dos Pil\u00f5es",
        "Santana dos Pil\u00f5es"
    ],
    "wof:name":"Santana dos Piloes",
    "wof:placetype":"locality"
},
  "geometry": {"coordinates":[-45.31667,-22.66667],"type":"Point"}
}