{
  "type": "Feature",
  "properties": {
    "gn:admin1_code":"27",
    "gn:admin2_code":"3507001.0",
    "gn:asciiname":"Quilombo",
    "gn:country_code":"BR",
    "gn:dem":546,
    "gn:feature_class":"P",
    "gn:feature_code":"PPLL",
    "gn:name":"Quilombo",
    "gn:population":0,
    "gn:timezone":"America/Sao_Paulo",
    "iso:country":"BR",
    "name:por_x_preferred":[
        "Quilombo"
    ],
    "wof:name":"Quilombo",
    "wof:placetype":"locality"
},
  "geometry": {"coordinates":[-47.62107,-23.21908],"type":"Point"}
}