{
  "type": "Feature",
  "properties": {
    "gn:admin1_code":"4",
    "gn:admin2_code":"1303304.0",
    "gn:asciiname":"Capitari",
    "gn:country_code":"BR",
    "gn:dem":69,
    "gn:feature_class":"P",
    "gn:feature_code":"PPL",
    "gn:name":"Capitari",
    "gn:population":0,
    "gn:timezone":"America/Manaus",
    "iso:country":"BR",
    "wof:name":"Capitari",
    "wof:placetype":"locality"
},
  "geometry": {"coordinates":[-60.33333,-6.56667],"type":"Point"}
}