{
  "type": "Feature",
  "properties": {
    "gn:admin1_code":"18.0",
    "gn:admin2_code":"4127809.0",
    "gn:asciiname":"Sitio Jovina Custodia",
    "gn:country_code":"BR",
    "gn:dem":675,
    "gn:feature_class":"P",
    "gn:feature_code":"PPL",
    "gn:name":"S\u00edtio Jovina Cust\u00f3dia",
    "gn:population":0,
    "gn:timezone":"America/Sao_Paulo",
    "iso:country":"BR",
    "name:por_x_preferred":[
        "S\u00edtio Jovina Cust\u00f3dia"
    ],
    "wof:name":"Sitio Jovina Custodia",
    "wof:placetype":"locality"
},
  "geometry": {"coordinates":[-49.9228,-23.672],"type":"Point"}
}