{
  "type": "Feature",
  "properties": {
    "gn:admin1_code":"18.0",
    "gn:admin2_code":"4127809.0",
    "gn:asciiname":"Sitio Jose Borges",
    "gn:country_code":"BR",
    "gn:dem":688,
    "gn:feature_class":"P",
    "gn:feature_code":"PPL",
    "gn:name":"S\u00edtio Jos\u00e9 Borges",
    "gn:population":0,
    "gn:timezone":"America/Sao_Paulo",
    "iso:country":"BR",
    "name:por_x_preferred":[
        "S\u00edtio Jos\u00e9 Borges"
    ],
    "wof:name":"Sitio Jose Borges",
    "wof:placetype":"locality"
},
  "geometry": {"coordinates":[-50.01834,-23.80206],"type":"Point"}
}