{
  "type": "Feature",
  "properties": {
    "gn:admin1_code":"30",
    "gn:admin2_code":"2601201.0",
    "gn:asciiname":"Queimada da Onca",
    "gn:country_code":"BR",
    "gn:dem":502,
    "gn:feature_class":"P",
    "gn:feature_code":"PPL",
    "gn:name":"Queimada da On\u00e7a",
    "gn:population":0,
    "gn:timezone":"America/Recife",
    "iso:country":"BR",
    "wof:name":"Queimada da Onca",
    "wof:placetype":"locality"
},
  "geometry": {"coordinates":[-37.14941,-8.7723],"type":"Point"}
}