{
  "type": "Feature",
  "properties": {
    "gn:admin1_code":"5",
    "gn:admin2_code":"2925956.0",
    "gn:asciiname":"Vargem Grande",
    "gn:country_code":"BR",
    "gn:dem":213,
    "gn:feature_class":"P",
    "gn:feature_code":"PPL",
    "gn:name":"Vargem Grande",
    "gn:population":0,
    "gn:timezone":"America/Bahia",
    "iso:country":"BR",
    "wof:name":"Vargem Grande",
    "wof:placetype":"locality"
},
  "geometry": {"coordinates":[-39.46667,-12.53333],"type":"Point"}
}