{
  "type": "Feature",
  "properties": {
    "gn:admin1_code":"5",
    "gn:admin2_code":"2925956.0",
    "gn:asciiname":"Vargem Grande",
    "gn:country_code":"BR",
    "gn:dem":213,
    "gn:feature_class":"P",
    "gn:feature_code":"PPL",
    "gn:name":"Vargem Grande",
    "gn:population":0,
    "gn:timezone":"America/Bahia",
    "iso:country":"BR",
    "name:bpy_x_preferred":[
        "\u09ad\u09be\u09b0\u09cd\u0997\u09c7\u09ae \u0997\u09cd\u09b0\u09be\u09a8\u09cd\u09a1\u09c7"
    ],
    "name:ceb_x_preferred":[
        "Vargem Grande"
    ],
    "name:deu_x_preferred":[
        "Vargem Grande"
    ],
    "name:eus_x_preferred":[
        "Vargem Grande"
    ],
    "name:fra_x_preferred":[
        "Vargem Grande"
    ],
    "name:hye_x_preferred":[
        "\u054e\u0561\u0580\u056a\u0565\u0576 \u0533\u0580\u0561\u0576\u0564\u056b"
    ],
    "name:ita_x_preferred":[
        "Vargem Grande"
    ],
    "name:kaz_x_preferred":[
        "\u0412\u0430\u0440\u0436\u0435\u043d-\u0413\u0440\u0430\u043d\u0434\u0438"
    ],
    "name:nld_x_preferred":[
        "Vargem Grande"
    ],
    "name:nor_x_preferred":[
        "Vargem Grande"
    ],
    "name:pol_x_preferred":[
        "Vargem Grande"
    ],
    "name:por_x_preferred":[
        "Vargem Grande"
    ],
    "name:ron_x_preferred":[
        "Vargem Grande"
    ],
    "name:rus_x_preferred":[
        "\u0412\u0430\u0440\u0436\u0435\u043d-\u0413\u0440\u0430\u043d\u0434\u0438"
    ],
    "name:swe_x_preferred":[
        "Vargem Grande"
    ],
    "name:vol_x_preferred":[
        "Vargem Grande"
    ],
    "name:war_x_preferred":[
        "Vargem Grande"
    ],
    "name:zho_x_preferred":[
        "\u5927\u74e6\u5c14\u4efb"
    ],
    "wof:name":"Vargem Grande",
    "wof:placetype":"locality"
},
  "geometry": {"coordinates":[-39.46667,-12.53333],"type":"Point"}
}