{
  "type": "Feature",
  "properties": {
    "gn:admin1_code":"18",
    "gn:admin2_code":"4113205.0",
    "gn:asciiname":"Sitio Maria Branco",
    "gn:country_code":"BR",
    "gn:dem":916,
    "gn:feature_class":"P",
    "gn:feature_code":"PPL",
    "gn:name":"S\u00edtio Maria Branco",
    "gn:population":0,
    "gn:timezone":"America/Sao_Paulo",
    "iso:country":"BR",
    "name:por_x_preferred":[
        "S\u00edtio Maria Branco"
    ],
    "wof:name":"Sitio Maria Branco",
    "wof:placetype":"locality"
},
  "geometry": {"coordinates":[-49.65222,-25.78222],"type":"Point"}
}