{
  "type": "Feature",
  "properties": {
    "gn:admin1_code":"5",
    "gn:admin2_code":"2902807.0",
    "gn:asciiname":"Pereira",
    "gn:country_code":"BR",
    "gn:dem":742,
    "gn:feature_class":"P",
    "gn:feature_code":"PPL",
    "gn:name":"Pereira",
    "gn:population":0,
    "gn:timezone":"America/Bahia",
    "iso:country":"BR",
    "wof:name":"Pereira",
    "wof:placetype":"locality"
},
  "geometry": {"coordinates":[-41.11667,-13.61667],"type":"Point"}
}