{
  "type": "Feature",
  "properties": {
    "gn:admin1_code":"5",
    "gn:admin2_code":"2922730.0",
    "gn:asciiname":"Lagoa de Dentro",
    "gn:country_code":"BR",
    "gn:dem":292,
    "gn:feature_class":"P",
    "gn:feature_code":"PPL",
    "gn:name":"Lagoa de Dentro",
    "gn:population":0,
    "gn:timezone":"America/Bahia",
    "iso:country":"BR",
    "wof:name":"Lagoa de Dentro",
    "wof:placetype":"locality"
},
  "geometry": {"coordinates":[-39.62487,-11.60534],"type":"Point"}
}