{
  "type": "Feature",
  "properties": {
    "gn:admin1_code":"5",
    "gn:admin2_code":"2922730.0",
    "gn:asciiname":"Lagoa de Dentro",
    "gn:country_code":"BR",
    "gn:dem":292,
    "gn:feature_class":"P",
    "gn:feature_code":"PPL",
    "gn:name":"Lagoa de Dentro",
    "gn:population":0,
    "gn:timezone":"America/Bahia",
    "iso:country":"BR",
    "name:bpy_x_preferred":[
        "\u09b2\u09be\u0997\u09cb\u09af\u09bc\u09be \u09a1\u09c7 \u09a1\u09c7\u09a8\u09cd\u099f\u09cd\u09b0\u09cb"
    ],
    "name:hye_x_preferred":[
        "\u053c\u0561\u0563\u0578\u0561 \u0564\u056b \u0534\u0565\u0576\u057f\u0580\u0578\u0582"
    ],
    "name:kat_x_preferred":[
        "\u10da\u10d0\u10d2\u10dd\u10d0-\u10d3\u10d8-\u10d3\u10d4\u10dc\u10e2\u10e0\u10e3"
    ],
    "name:kaz_x_preferred":[
        "\u041b\u0430\u0433\u043e\u0430-\u0434\u0438-\u0414\u0435\u043d\u0442\u0440\u0443"
    ],
    "name:rus_x_preferred":[
        "\u041b\u0430\u0433\u043e\u0430-\u0434\u0438-\u0414\u0435\u043d\u0442\u0440\u0443"
    ],
    "name:urd_x_preferred":[
        "\u0644\u0627\u06af\u0648\u0627 \u062f\u06d2 \u0688\u06cc\u0646\u0679\u0631\u0648"
    ],
    "name:zho_x_preferred":[
        "\u62c9\u6208\u963f-\u8fea\u767b\u7279\u9c81"
    ],
    "wof:name":"Lagoa de Dentro",
    "wof:placetype":"locality"
},
  "geometry": {"coordinates":[-39.62487,-11.60534],"type":"Point"}
}