{
  "type": "Feature",
  "properties": {
    "gn:admin1_code":"27",
    "gn:admin2_code":"3507100.0",
    "gn:asciiname":"Sitio Vale do Paturi",
    "gn:country_code":"BR",
    "gn:dem":1131,
    "gn:feature_class":"P",
    "gn:feature_code":"PPL",
    "gn:name":"S\u00edtio Vale do Paturi",
    "gn:population":0,
    "gn:timezone":"America/Sao_Paulo",
    "iso:country":"BR",
    "name:por_x_preferred":[
        "S\u00edtio Vale do Paturi"
    ],
    "wof:name":"Sitio Vale do Paturi",
    "wof:placetype":"locality"
},
  "geometry": {"coordinates":[-46.52889,-23.21472],"type":"Point"}
}