{
  "type": "Feature",
  "properties": {
    "gn:admin1_code":"13",
    "gn:admin2_code":"2100907.0",
    "gn:asciiname":"Faveirinha",
    "gn:country_code":"BR",
    "gn:dem":38,
    "gn:feature_class":"P",
    "gn:feature_code":"PPL",
    "gn:name":"Faveirinha",
    "gn:population":0,
    "gn:timezone":"America/Fortaleza",
    "iso:country":"BR",
    "wof:name":"Faveirinha",
    "wof:placetype":"locality"
},
  "geometry": {"coordinates":[-42.20389,-3.13667],"type":"Point"}
}