{
  "type": "Feature",
  "properties": {
    "gn:admin1_code":"11",
    "gn:admin2_code":"5003207.0",
    "gn:asciiname":"Santo Antonio",
    "gn:country_code":"BR",
    "gn:dem":110,
    "gn:feature_class":"P",
    "gn:feature_code":"PPL",
    "gn:name":"Santo Ant\u00f4nio",
    "gn:population":0,
    "gn:timezone":"America/Campo_Grande",
    "iso:country":"BR",
    "wof:name":"Santo Antonio",
    "wof:placetype":"locality"
},
  "geometry": {"coordinates":[-56.45,-18.76667],"type":"Point"}
}