{
  "type": "Feature",
  "properties": {
    "gn:admin1_code":"25",
    "gn:admin2_code":"1400472.0",
    "gn:asciiname":"Tapera",
    "gn:country_code":"BR",
    "gn:dem":30,
    "gn:feature_class":"P",
    "gn:feature_code":"PPL",
    "gn:name":"Tapera",
    "gn:population":0,
    "gn:timezone":"America/Boa_Vista",
    "iso:country":"BR",
    "wof:name":"Tapera",
    "wof:placetype":"locality"
},
  "geometry": {"coordinates":[-61.79556,-0.53167],"type":"Point"}
}