{
  "type": "Feature",
  "properties": {
    "gn:admin1_code":"06",
    "gn:admin2_code":"2311264.0",
    "gn:asciiname":"Esperanca",
    "gn:country_code":"BR",
    "gn:dem":581,
    "gn:feature_class":"P",
    "gn:feature_code":"PPL",
    "gn:name":"Esperan\u00e7a",
    "gn:population":0,
    "gn:timezone":"America/Fortaleza",
    "iso:country":"BR",
    "wof:name":"Esperanca",
    "wof:placetype":"locality"
},
  "geometry": {"coordinates":[-40.78333,-5.98333],"type":"Point"}
}