{
  "type": "Feature",
  "properties": {
    "gn:admin1_code":"27",
    "gn:admin2_code":"3518305.0",
    "gn:asciiname":"Stio Sohiro Fuji",
    "gn:country_code":"BR",
    "gn:dem":605,
    "gn:feature_class":"P",
    "gn:feature_code":"PPL",
    "gn:name":"Stio Sohiro Fuji",
    "gn:population":0,
    "gn:timezone":"America/Sao_Paulo",
    "iso:country":"BR",
    "name:por_x_preferred":[
        "Stio Sohiro Fuji"
    ],
    "wof:name":"Stio Sohiro Fuji",
    "wof:placetype":"locality"
},
  "geometry": {"coordinates":[-46.1006,-23.3265],"type":"Point"}
}