{
  "type": "Feature",
  "properties": {
    "gn:admin1_code":"16.0",
    "gn:admin2_code":"1505106.0",
    "gn:asciiname":"Vila Vieira",
    "gn:country_code":"BR",
    "gn:dem":8,
    "gn:feature_class":"P",
    "gn:feature_code":"PPL",
    "gn:name":"Vila Vieira",
    "gn:population":0,
    "gn:timezone":"America/Santarem",
    "iso:country":"BR",
    "name:por_x_preferred":[
        "Vila Vieira"
    ],
    "wof:name":"Vila Vieira",
    "wof:placetype":"locality"
},
  "geometry": {"coordinates":[-55.34822,-2.10114],"type":"Point"}
}