{
  "type": "Feature",
  "properties": {
    "gn:admin1_code":"26",
    "gn:admin2_code":"4208807.0",
    "gn:asciiname":"Costa da Praia",
    "gn:country_code":"BR",
    "gn:dem":18,
    "gn:feature_class":"P",
    "gn:feature_code":"PPL",
    "gn:name":"Costa da Praia",
    "gn:population":0,
    "gn:timezone":"America/Sao_Paulo",
    "iso:country":"BR",
    "wof:name":"Costa da Praia",
    "wof:placetype":"locality"
},
  "geometry": {"coordinates":[-49.16667,-28.76667],"type":"Point"}
}