{
  "type": "Feature",
  "properties": {
    "gn:admin1_code":"17",
    "gn:admin2_code":"2500106.0",
    "gn:asciiname":"Muricoca",
    "gn:country_code":"BR",
    "gn:dem":774,
    "gn:feature_class":"P",
    "gn:feature_code":"PPL",
    "gn:name":"Muri\u00e7oca",
    "gn:population":0,
    "gn:timezone":"America/Fortaleza",
    "iso:country":"BR",
    "wof:name":"Muricoca",
    "wof:placetype":"locality"
},
  "geometry": {"coordinates":[-37.61667,-7.51667],"type":"Point"}
}