{
  "type": "Feature",
  "properties": {
    "gn:admin1_code":"30",
    "gn:admin2_code":"2614105.0",
    "gn:asciiname":"Urubu",
    "gn:country_code":"BR",
    "gn:dem":511,
    "gn:feature_class":"P",
    "gn:feature_code":"PPL",
    "gn:name":"Urubu",
    "gn:population":0,
    "gn:timezone":"America/Recife",
    "iso:country":"BR",
    "name:bre_x_preferred":[
        "Urubu"
    ],
    "name:fra_x_preferred":[
        "Urubu"
    ],
    "wof:name":"Urubu",
    "wof:placetype":"locality"
},
  "geometry": {"coordinates":[-37.38333,-8.28333],"type":"Point"}
}