{
  "type": "Feature",
  "properties": {
    "gn:admin1_code":"18.0",
    "gn:admin2_code":"4114302.0",
    "gn:asciiname":"Sitio Ardelino Gomes",
    "gn:country_code":"BR",
    "gn:dem":879,
    "gn:feature_class":"P",
    "gn:feature_code":"PPL",
    "gn:name":"S\u00edtio Ardelino Gomes",
    "gn:population":0,
    "gn:timezone":"America/Sao_Paulo",
    "iso:country":"BR",
    "name:por_x_preferred":[
        "S\u00edtio Ardelino Gomes"
    ],
    "wof:name":"Sitio Ardelino Gomes",
    "wof:placetype":"locality"
},
  "geometry": {"coordinates":[-49.3124,-25.9275],"type":"Point"}
}