{
  "type": "Feature",
  "properties": {
    "gn:admin1_code":"23",
    "gn:admin2_code":"4313003.0",
    "gn:asciiname":"Estefania",
    "gn:country_code":"BR",
    "gn:dem":427,
    "gn:feature_class":"P",
    "gn:feature_code":"PPL",
    "gn:name":"Estef\u00e2nia",
    "gn:population":0,
    "gn:timezone":"America/Sao_Paulo",
    "iso:country":"BR",
    "wof:name":"Estefania",
    "wof:placetype":"locality"
},
  "geometry": {"coordinates":[-52.03333,-29.25],"type":"Point"}
}