{
  "type": "Feature",
  "properties": {
    "gn:admin1_code":"30",
    "gn:admin2_code":"2602803.0",
    "gn:asciiname":"Umburana",
    "gn:cc2":"BR",
    "gn:country_code":"BR",
    "gn:dem":584,
    "gn:feature_class":"P",
    "gn:feature_code":"PPL",
    "gn:name":"Umburana",
    "gn:population":0,
    "gn:timezone":"America/Recife",
    "iso:country":"BR",
    "name:und_x_variant":[
        "Umburuna",
        "Umburana"
    ],
    "wof:name":"Umburana",
    "wof:placetype":"locality"
},
  "geometry": {"coordinates":[-37.18333,-8.41667],"type":"Point"}
}