{
  "type": "Feature",
  "properties": {
    "gn:admin1_code":"17",
    "gn:admin2_code":"2506509.0",
    "gn:asciiname":"Jose da Silva",
    "gn:country_code":"BR",
    "gn:dem":473,
    "gn:feature_class":"P",
    "gn:feature_code":"PPL",
    "gn:name":"Jos\u00e9 da Silva",
    "gn:population":0,
    "gn:timezone":"America/Fortaleza",
    "iso:country":"BR",
    "wof:name":"Jose da Silva",
    "wof:placetype":"locality"
},
  "geometry": {"coordinates":[-36.48333,-7.31667],"type":"Point"}
}