{
  "type": "Feature",
  "properties": {
    "gn:admin1_code":"18.0",
    "gn:admin2_code":"4120804.0",
    "gn:asciiname":"Sitio Raimundo Crukre",
    "gn:country_code":"BR",
    "gn:dem":842,
    "gn:feature_class":"P",
    "gn:feature_code":"PPL",
    "gn:name":"S\u00edtio Raimundo Crukre",
    "gn:population":0,
    "gn:timezone":"America/Sao_Paulo",
    "iso:country":"BR",
    "name:por_x_preferred":[
        "S\u00edtio Raimundo Crukre"
    ],
    "wof:name":"Sitio Raimundo Crukre",
    "wof:placetype":"locality"
},
  "geometry": {"coordinates":[-48.97924,-25.34465],"type":"Point"}
}