{
  "type": "Feature",
  "properties": {
    "gn:admin1_code":"27",
    "gn:admin2_code":"3550902.0",
    "gn:asciiname":"Estrela d'Oeste",
    "gn:country_code":"BR",
    "gn:dem":597,
    "gn:feature_class":"P",
    "gn:feature_code":"PPL",
    "gn:name":"Estr\u00eala d\u2019Oeste",
    "gn:population":0,
    "gn:timezone":"America/Sao_Paulo",
    "iso:country":"BR",
    "name:und_x_variant":[
        "Fazenda Estr\u00eala d\u2019Oeste",
        "Estr\u00eala d\u2019Oeste"
    ],
    "wof:name":"Estrela d'Oeste",
    "wof:placetype":"locality"
},
  "geometry": {"coordinates":[-47.71667,-21.43333],"type":"Point"}
}