{
  "type": "Feature",
  "properties": {
    "gn:admin1_code":"27",
    "gn:admin2_code":"3550902.0",
    "gn:asciiname":"Estrela d'Oeste",
    "gn:country_code":"BR",
    "gn:dem":597,
    "gn:feature_class":"P",
    "gn:feature_code":"PPL",
    "gn:name":"Estr\u00eala d\u2019Oeste",
    "gn:population":0,
    "gn:timezone":"America/Sao_Paulo",
    "iso:country":"BR",
    "name:bpy_x_preferred":[
        "\u098f\u09b8\u099f\u09cd\u09b0\u09c7\u09b2\u09be \u09a1\u09bf'\u0993\u098f\u09b8\u09cd\u099f\u09c7"
    ],
    "name:ceb_x_preferred":[
        "Estrela d'Oeste"
    ],
    "name:epo_x_preferred":[
        "Estrela d'Oeste"
    ],
    "name:eus_x_preferred":[
        "Estrela d'Oeste"
    ],
    "name:fra_x_preferred":[
        "Estrela d'Oeste"
    ],
    "name:ita_x_preferred":[
        "Estrela d'Oeste"
    ],
    "name:kaz_x_preferred":[
        "\u042d\u0441\u0442\u0440\u0435\u043b\u0430-\u0434\u2019\u0423\u044d\u0441\u0442\u0438"
    ],
    "name:mlg_x_preferred":[
        "Estrela d'Oeste"
    ],
    "name:nld_x_preferred":[
        "Estrela d'Oeste"
    ],
    "name:nor_x_preferred":[
        "Estrela d'Oeste"
    ],
    "name:pol_x_preferred":[
        "Estrela d'Oeste"
    ],
    "name:por_x_preferred":[
        "Estrela d'Oeste"
    ],
    "name:ron_x_preferred":[
        "Estrela d'Oeste"
    ],
    "name:rus_x_preferred":[
        "\u042d\u0441\u0442\u0440\u0435\u043b\u0430-\u0434\u2019\u0423\u044d\u0441\u0442\u0438"
    ],
    "name:spa_x_preferred":[
        "Estrela d'Oeste"
    ],
    "name:swe_x_preferred":[
        "Estrela d'Oeste"
    ],
    "name:und_x_variant":[
        "Fazenda Estr\u00eala d\u2019Oeste",
        "Estr\u00eala d\u2019Oeste"
    ],
    "name:vie_x_preferred":[
        "Estrela d'Oeste"
    ],
    "name:vol_x_preferred":[
        "Estrela d'Oeste"
    ],
    "name:war_x_preferred":[
        "Estrela d'Oeste"
    ],
    "name:zho_x_preferred":[
        "\u897f\u57c3\u65af\u7279\u96f7\u62c9"
    ],
    "wof:name":"Estrela d'Oeste",
    "wof:placetype":"locality"
},
  "geometry": {"coordinates":[-47.71667,-21.43333],"type":"Point"}
}