{
  "type": "Feature",
  "properties": {
    "gn:admin1_code":"8",
    "gn:admin2_code":"3200805.0",
    "gn:asciiname":"Sao Sebastiao do Bananal",
    "gn:country_code":"BR",
    "gn:dem":355,
    "gn:feature_class":"P",
    "gn:feature_code":"PPL",
    "gn:name":"S\u00e3o Sebasti\u00e3o do Bananal",
    "gn:population":0,
    "gn:timezone":"America/Sao_Paulo",
    "iso:country":"BR",
    "name:por_x_preferred":[
        "S\u00e3o Sebasti\u00e3o do Bananal"
    ],
    "wof:name":"Sao Sebastiao do Bananal",
    "wof:placetype":"locality"
},
  "geometry": {"coordinates":[-41.08333,-19.66667],"type":"Point"}
}