{
  "type": "Feature",
  "properties": {
    "gn:admin1_code":"5",
    "gn:admin2_code":"2911105.0",
    "gn:asciiname":"Sao Luis",
    "gn:cc2":"BR",
    "gn:country_code":"BR",
    "gn:dem":541,
    "gn:feature_class":"P",
    "gn:feature_code":"PPL",
    "gn:name":"S\u00e3o Lu\u00eds",
    "gn:population":0,
    "gn:timezone":"America/Bahia",
    "iso:country":"BR",
    "name:und_x_variant":[
        "S\u00e3o Luiz",
        "S\u00e3o Lu\u00eds"
    ],
    "wof:name":"Sao Luis",
    "wof:placetype":"locality"
},
  "geometry": {"coordinates":[-45.45,-10.91667],"type":"Point"}
}