{
  "type": "Feature",
  "properties": {
    "gn:admin1_code":"20",
    "gn:admin2_code":"2205359.0",
    "gn:asciiname":"Cache",
    "gn:country_code":"BR",
    "gn:dem":269,
    "gn:feature_class":"P",
    "gn:feature_code":"PPL",
    "gn:name":"Cach\u00e9",
    "gn:population":0,
    "gn:timezone":"America/Fortaleza",
    "iso:country":"BR",
    "name:bul_x_preferred":[
        "\u041a\u0435\u0448"
    ],
    "name:ceb_x_preferred":[
        "Cache"
    ],
    "name:deu_x_preferred":[
        "Cache"
    ],
    "name:fra_x_preferred":[
        "Cache"
    ],
    "name:ita_x_preferred":[
        "Cache"
    ],
    "name:jpn_x_preferred":[
        "\u30ad\u30e3\u30c3\u30b7\u30e5"
    ],
    "name:nld_x_preferred":[
        "Cache"
    ],
    "name:nrm_x_preferred":[
        "Cache"
    ],
    "name:pol_x_preferred":[
        "Cache"
    ],
    "name:por_x_preferred":[
        "Cache"
    ],
    "name:rus_x_preferred":[
        "\u041a\u044d\u0448"
    ],
    "name:spa_x_preferred":[
        "Cach\u00e9"
    ],
    "name:srp_x_preferred":[
        "\u041a\u0435\u0448"
    ],
    "name:swe_x_preferred":[
        "Cache"
    ],
    "name:und_x_variant":[
        "Cax\u00e9"
    ],
    "wof:name":"Cache",
    "wof:placetype":"locality"
},
  "geometry": {"coordinates":[-42.40557,-8.45118],"type":"Point"}
}