{
  "type": "Feature",
  "properties": {
    "gn:admin1_code":"15",
    "gn:admin2_code":"3112802.0",
    "gn:asciiname":"Horacio Alves",
    "gn:country_code":"BR",
    "gn:dem":1103,
    "gn:feature_class":"P",
    "gn:feature_code":"PPL",
    "gn:name":"Hor\u00e1cio Alves",
    "gn:population":0,
    "gn:timezone":"America/Sao_Paulo",
    "iso:country":"BR",
    "name:por_x_preferred":[
        "Hor\u00e1cio Alves"
    ],
    "wof:name":"Horacio Alves",
    "wof:placetype":"locality"
},
  "geometry": {"coordinates":[-46.18333,-20.61667000000001],"type":"Point"}
}