{
  "type": "Feature",
  "properties": {
    "gn:admin1_code":"15",
    "gn:admin2_code":"3115805.0",
    "gn:asciiname":"Joao Queiroz",
    "gn:country_code":"BR",
    "gn:dem":463,
    "gn:feature_class":"P",
    "gn:feature_code":"PPL",
    "gn:name":"Jo\u00e3o Queiroz",
    "gn:population":0,
    "gn:timezone":"America/Sao_Paulo",
    "iso:country":"BR",
    "name:por_x_preferred":[
        "Jo\u00e3o Queiroz"
    ],
    "wof:name":"Joao Queiroz",
    "wof:placetype":"locality"
},
  "geometry": {"coordinates":[-49.28333,-18.56667],"type":"Point"}
}