{
  "type": "Feature",
  "properties": {
    "gn:admin1_code":"18.0",
    "gn:admin2_code":"4103602.0",
    "gn:asciiname":"Sitio Pedro Zanai",
    "gn:country_code":"BR",
    "gn:dem":429,
    "gn:feature_class":"P",
    "gn:feature_code":"PPL",
    "gn:name":"S\u00edtio Pedro Zanai",
    "gn:population":0,
    "gn:timezone":"America/Sao_Paulo",
    "iso:country":"BR",
    "name:por_x_preferred":[
        "S\u00edtio Pedro Zanai"
    ],
    "wof:name":"Sitio Pedro Zanai",
    "wof:placetype":"locality"
},
  "geometry": {"coordinates":[-50.1255,-23.0049],"type":"Point"}
}