{
  "type": "Feature",
  "properties": {
    "gn:admin1_code":"18.0",
    "gn:admin2_code":"4109708.0",
    "gn:asciiname":"Sitio Bela Vista",
    "gn:country_code":"BR",
    "gn:dem":628,
    "gn:feature_class":"P",
    "gn:feature_code":"PPL",
    "gn:name":"S\u00edtio Bela Vista",
    "gn:population":0,
    "gn:timezone":"America/Sao_Paulo",
    "iso:country":"BR",
    "name:por_x_preferred":[
        "S\u00edtio Bela Vista"
    ],
    "wof:name":"Sitio Bela Vista",
    "wof:placetype":"locality"
},
  "geometry": {"coordinates":[-50.2045,-23.76109],"type":"Point"}
}