{
  "type": "Feature",
  "properties": {
    "gn:admin1_code":"5",
    "gn:admin2_code":"2927408.0",
    "gn:asciiname":"Boa Viagem",
    "gn:country_code":"BR",
    "gn:dem":10,
    "gn:feature_class":"P",
    "gn:feature_code":"PPL",
    "gn:name":"Boa Viagem",
    "gn:population":0,
    "gn:timezone":"America/Bahia",
    "iso:country":"BR",
    "name:bre_x_preferred":[
        "Boa Viagem"
    ],
    "name:ceb_x_preferred":[
        "Boa Viagem"
    ],
    "name:nld_x_preferred":[
        "Boa Viagem"
    ],
    "name:por_x_preferred":[
        "Boa Viagem"
    ],
    "name:swe_x_preferred":[
        "Boa Viagem"
    ],
    "wof:name":"Boa Viagem",
    "wof:placetype":"locality"
},
  "geometry": {"coordinates":[-38.51167,-12.92833],"type":"Point"}
}