{
  "type": "Feature",
  "properties": {
    "gn:admin1_code":"13",
    "gn:admin2_code":"2106672.0",
    "gn:asciiname":"Travessao",
    "gn:country_code":"BR",
    "gn:dem":63,
    "gn:feature_class":"P",
    "gn:feature_code":"PPL",
    "gn:name":"Travess\u00e3o",
    "gn:population":0,
    "gn:timezone":"America/Fortaleza",
    "iso:country":"BR",
    "wof:name":"Travessao",
    "wof:placetype":"locality"
},
  "geometry": {"coordinates":[-42.69056,-3.47139],"type":"Point"}
}