{
  "type": "Feature",
  "properties": {
    "gn:admin1_code":"21",
    "gn:admin2_code":"3301009.0",
    "gn:asciiname":"Bandeirantes",
    "gn:country_code":"BR",
    "gn:dem":72,
    "gn:feature_class":"P",
    "gn:feature_code":"PPL",
    "gn:name":"Bandeirantes",
    "gn:population":0,
    "gn:timezone":"America/Sao_Paulo",
    "iso:country":"BR",
    "name:ara_x_preferred":[
        "\u0628\u0627\u0646\u062f\u064a\u0631\u0627\u0646\u062a\u064a\u0633"
    ],
    "name:cat_x_preferred":[
        "Bandeirantes"
    ],
    "name:deu_x_preferred":[
        "Bandeirantes"
    ],
    "name:epo_x_preferred":[
        "Bandeirante"
    ],
    "name:fra_x_preferred":[
        "Bandeirante"
    ],
    "name:heb_x_preferred":[
        "\u05d1\u05e0\u05d3\u05d9\u05d9\u05e8\u05d0\u05e0\u05d8\u05e1"
    ],
    "name:ita_x_preferred":[
        "Bandeirantes"
    ],
    "name:jpn_x_preferred":[
        "\u30d0\u30f3\u30c7\u30a4\u30e9\u30f3\u30c6\u30b9"
    ],
    "name:mlg_x_preferred":[
        "Bandeirantes"
    ],
    "name:nld_x_preferred":[
        "Bandeirantes"
    ],
    "name:nor_x_preferred":[
        "Bandeirantes"
    ],
    "name:pol_x_preferred":[
        "Bandeirantes"
    ],
    "name:por_x_preferred":[
        "Bandeirantes"
    ],
    "name:rus_x_preferred":[
        "\u0411\u0430\u043d\u0434\u0435\u0439\u0440\u0430\u043d\u0442\u044b"
    ],
    "name:spa_x_preferred":[
        "Bandeirantes"
    ],
    "name:ukr_x_preferred":[
        "\u0411\u0430\u043d\u0434\u0435\u0439\u0440\u0430\u043d\u0442\u0438"
    ],
    "wof:name":"Bandeirantes",
    "wof:placetype":"locality"
},
  "geometry": {"coordinates":[-41.78333,-21.86667000000001],"type":"Point"}
}