{
  "type": "Feature",
  "properties": {
    "gn:admin1_code":"21",
    "gn:admin2_code":"3301009.0",
    "gn:asciiname":"Bandeirantes",
    "gn:country_code":"BR",
    "gn:dem":72,
    "gn:feature_class":"P",
    "gn:feature_code":"PPL",
    "gn:name":"Bandeirantes",
    "gn:population":0,
    "gn:timezone":"America/Sao_Paulo",
    "iso:country":"BR",
    "name:por_x_preferred":[
        "Bandeirantes"
    ],
    "wof:name":"Bandeirantes",
    "wof:placetype":"locality"
},
  "geometry": {"coordinates":[-41.78333,-21.86667000000001],"type":"Point"}
}