{
  "type": "Feature",
  "properties": {
    "gn:admin1_code":"15",
    "gn:admin2_code":"3169208.0",
    "gn:asciiname":"Catinga",
    "gn:country_code":"BR",
    "gn:dem":368,
    "gn:feature_class":"P",
    "gn:feature_code":"PPL",
    "gn:name":"Catinga",
    "gn:population":0,
    "gn:timezone":"America/Sao_Paulo",
    "iso:country":"BR",
    "name:por_x_preferred":[
        "Catinga"
    ],
    "wof:name":"Catinga",
    "wof:placetype":"locality"
},
  "geometry": {"coordinates":[-41.96667,-20.85],"type":"Point"}
}