{
  "type": "Feature",
  "properties": {
    "gn:admin1_code":"5",
    "gn:admin2_code":"2902708.0",
    "gn:asciiname":"Cabeceira",
    "gn:cc2":"BR",
    "gn:country_code":"BR",
    "gn:dem":497,
    "gn:feature_class":"P",
    "gn:feature_code":"PPL",
    "gn:name":"Cabeceira",
    "gn:population":0,
    "gn:timezone":"America/Bahia",
    "iso:country":"BR",
    "name:und_x_variant":[
        "Cabaceira",
        "Cabeceira"
    ],
    "wof:name":"Cabeceira",
    "wof:placetype":"locality"
},
  "geometry": {"coordinates":[-43.06667,-10.71667],"type":"Point"}
}