{
  "type": "Feature",
  "properties": {
    "gn:admin1_code":"18",
    "gn:admin2_code":"4117701.0",
    "gn:asciiname":"Colonia do Lago",
    "gn:country_code":"BR",
    "gn:dem":914,
    "gn:feature_class":"P",
    "gn:feature_code":"PPL",
    "gn:name":"Col\u00f4nia do Lago",
    "gn:population":0,
    "gn:timezone":"America/Sao_Paulo",
    "iso:country":"BR",
    "wof:name":"Colonia do Lago",
    "wof:placetype":"locality"
},
  "geometry": {"coordinates":[-50.04222,-25.35167],"type":"Point"}
}