{
  "type": "Feature",
  "properties": {
    "gn:admin1_code":"06",
    "gn:admin2_code":"2311603.0",
    "gn:asciiname":"Oiticica (1)",
    "gn:country_code":"BR",
    "gn:dem":647,
    "gn:feature_class":"P",
    "gn:feature_code":"PPL",
    "gn:name":"Oiticica (1)",
    "gn:population":0,
    "gn:timezone":"America/Fortaleza",
    "iso:country":"BR",
    "wof:name":"Oiticica (1)",
    "wof:placetype":"locality"
},
  "geometry": {"coordinates":[-38.76667,-4.23333],"type":"Point"}
}