{
  "type": "Feature",
  "properties": {
    "gn:admin1_code":"22",
    "gn:admin2_code":"2411403.0",
    "gn:asciiname":"Papagaio",
    "gn:country_code":"BR",
    "gn:dem":121,
    "gn:feature_class":"P",
    "gn:feature_code":"PPL",
    "gn:name":"Papagaio",
    "gn:population":0,
    "gn:timezone":"America/Fortaleza",
    "iso:country":"BR",
    "wof:name":"Papagaio",
    "wof:placetype":"locality"
},
  "geometry": {"coordinates":[-36.61611,-5.77861],"type":"Point"}
}