{
  "type": "Feature",
  "properties": {
    "gn:admin1_code":"5",
    "gn:admin2_code":"2906808.0",
    "gn:asciiname":"Ambrosio",
    "gn:country_code":"BR",
    "gn:dem":221,
    "gn:feature_class":"P",
    "gn:feature_code":"PPL",
    "gn:name":"Ambr\u00f3sio",
    "gn:population":0,
    "gn:timezone":"America/Bahia",
    "iso:country":"BR",
    "name:rus_x_preferred":[
        "\u0410\u043c\u0431\u0440\u043e\u0437\u0438\u043e"
    ],
    "name:und_x_variant":[
        "Moc\u00f3",
        "Ambr\u00f3sio",
        "Ambr\u00e3sio"
    ],
    "wof:name":"Ambrosio",
    "wof:placetype":"locality"
},
  "geometry": {"coordinates":[-39.20806,-10.99487],"type":"Point"}
}