{
  "type": "Feature",
  "properties": {
    "gn:admin1_code":"13",
    "gn:admin2_code":"2106672.0",
    "gn:asciiname":"Malhada das Pedras",
    "gn:country_code":"BR",
    "gn:dem":26,
    "gn:feature_class":"P",
    "gn:feature_code":"PPL",
    "gn:name":"Malhada das Pedras",
    "gn:population":0,
    "gn:timezone":"America/Fortaleza",
    "iso:country":"BR",
    "wof:name":"Malhada das Pedras",
    "wof:placetype":"locality"
},
  "geometry": {"coordinates":[-42.58722,-3.55806],"type":"Point"}
}