{
  "type": "Feature",
  "properties": {
    "gn:admin1_code":"15",
    "gn:admin2_code":"3116001.0",
    "gn:asciiname":"Sassego",
    "gn:country_code":"BR",
    "gn:dem":679,
    "gn:feature_class":"P",
    "gn:feature_code":"PPL",
    "gn:name":"S\u00e2ssego",
    "gn:population":0,
    "gn:timezone":"America/Sao_Paulo",
    "iso:country":"BR",
    "name:por_x_preferred":[
        "S\u00e2ssego"
    ],
    "wof:name":"Sassego",
    "wof:placetype":"locality"
},
  "geometry": {"coordinates":[-41.61667,-20.01667],"type":"Point"}
}