{
  "type": "Feature",
  "properties": {
    "gn:admin1_code":"22.0",
    "gn:admin2_code":"2408102.0",
    "gn:asciiname":"Neopolis",
    "gn:country_code":"BR",
    "gn:dem":51,
    "gn:feature_class":"P",
    "gn:feature_code":"PPL",
    "gn:name":"Ne\u00f3polis",
    "gn:population":0,
    "gn:timezone":"America/Fortaleza",
    "iso:country":"BR",
    "wof:name":"Neopolis",
    "wof:placetype":"locality"
},
  "geometry": {"coordinates":[-35.20844,-5.87389],"type":"Point"}
}