{
  "type": "Feature",
  "properties": {
    "gn:admin1_code":"06",
    "gn:admin2_code":"2303204.0",
    "gn:asciiname":"Fazenda Faustina",
    "gn:country_code":"BR",
    "gn:dem":434,
    "gn:feature_class":"P",
    "gn:feature_code":"PPL",
    "gn:name":"Fazenda Faustina",
    "gn:population":0,
    "gn:timezone":"America/Fortaleza",
    "iso:country":"BR",
    "wof:name":"Fazenda Faustina",
    "wof:placetype":"locality"
},
  "geometry": {"coordinates":[-39.16667,-7.05],"type":"Point"}
}