{
  "type": "Feature",
  "properties": {
    "gn:admin1_code":"18",
    "gn:admin2_code":"4117701.0",
    "gn:asciiname":"Vieiras",
    "gn:country_code":"BR",
    "gn:dem":830,
    "gn:feature_class":"P",
    "gn:feature_code":"PPL",
    "gn:name":"Vieiras",
    "gn:population":0,
    "gn:timezone":"America/Sao_Paulo",
    "iso:country":"BR",
    "wof:name":"Vieiras",
    "wof:placetype":"locality"
},
  "geometry": {"coordinates":[-50.295,-25.48944],"type":"Point"}
}