{
  "type": "Feature",
  "properties": {
    "gn:admin1_code":"18",
    "gn:admin2_code":"4117701.0",
    "gn:asciiname":"Vieiras",
    "gn:country_code":"BR",
    "gn:dem":830,
    "gn:feature_class":"P",
    "gn:feature_code":"PPL",
    "gn:name":"Vieiras",
    "gn:population":0,
    "gn:timezone":"America/Sao_Paulo",
    "iso:country":"BR",
    "name:bpy_x_preferred":[
        "\u09ad\u09bf\u09af\u09bc\u09c7\u0987\u09b0\u09be\u09b8"
    ],
    "name:ceb_x_preferred":[
        "Vieiras"
    ],
    "name:epo_x_preferred":[
        "Vieiras"
    ],
    "name:eus_x_preferred":[
        "Vieiras"
    ],
    "name:fra_x_preferred":[
        "Vieiras"
    ],
    "name:hye_x_preferred":[
        "\u054e\u056b\u0565\u0575\u0580\u0561\u057d"
    ],
    "name:ita_x_preferred":[
        "Vieiras"
    ],
    "name:kat_x_preferred":[
        "\u10d5\u10d8\u10d4\u10d8\u10e0\u10d0\u10e1\u10d8"
    ],
    "name:kaz_x_preferred":[
        "\u0412\u0438\u0435\u0439\u0440\u0430\u0441"
    ],
    "name:mlg_x_preferred":[
        "Vieiras"
    ],
    "name:nld_x_preferred":[
        "Vieiras"
    ],
    "name:nor_x_preferred":[
        "Vieiras"
    ],
    "name:pol_x_preferred":[
        "Vieiras"
    ],
    "name:por_x_preferred":[
        "Vieiras"
    ],
    "name:ron_x_preferred":[
        "Vieiras"
    ],
    "name:rus_x_preferred":[
        "\u0412\u0438\u0435\u0439\u0440\u0430\u0441"
    ],
    "name:spa_x_preferred":[
        "Vieiras"
    ],
    "name:swe_x_preferred":[
        "Vieiras"
    ],
    "name:vie_x_preferred":[
        "Vieiras"
    ],
    "name:vol_x_preferred":[
        "Vieiras"
    ],
    "name:war_x_preferred":[
        "Vieiras"
    ],
    "name:zho_x_preferred":[
        "\u6bd4\u57c3\u62c9\u65af"
    ],
    "wof:name":"Vieiras",
    "wof:placetype":"locality"
},
  "geometry": {"coordinates":[-50.295,-25.48944],"type":"Point"}
}