{
  "type": "Feature",
  "properties": {
    "gn:admin1_code":"4",
    "gn:admin2_code":"1303700.0",
    "gn:asciiname":"Balbina",
    "gn:country_code":"BR",
    "gn:dem":82,
    "gn:feature_class":"P",
    "gn:feature_code":"PPL",
    "gn:name":"Balbina",
    "gn:population":0,
    "gn:timezone":"America/Manaus",
    "iso:country":"BR",
    "name:deu_x_preferred":[
        "Balbina"
    ],
    "name:por_x_preferred":[
        "Balbina"
    ],
    "name:spa_x_preferred":[
        "Balbina"
    ],
    "wof:name":"Balbina",
    "wof:placetype":"locality"
},
  "geometry": {"coordinates":[-68.31401,-2.93022],"type":"Point"}
}