{
  "type": "Feature",
  "properties": {
    "gn:admin1_code":"13",
    "gn:admin2_code":"2100808.0",
    "gn:asciiname":"Japao",
    "gn:country_code":"BR",
    "gn:dem":68,
    "gn:feature_class":"P",
    "gn:feature_code":"PPL",
    "gn:name":"Jap\u00e3o",
    "gn:population":0,
    "gn:timezone":"America/Fortaleza",
    "iso:country":"BR",
    "wof:name":"Japao",
    "wof:placetype":"locality"
},
  "geometry": {"coordinates":[-43.01583,-3.51222],"type":"Point"}
}