{
  "type": "Feature",
  "properties": {
    "iso:country":"BR",
    "name:als_x_preferred":[
        "Sion"
    ],
    "name:bre_x_preferred":[
        "Sion"
    ],
    "name:bul_x_preferred":[
        "\u0421\u0438\u043e\u043d"
    ],
    "name:cat_x_preferred":[
        "Sion"
    ],
    "name:ceb_x_preferred":[
        "Sion"
    ],
    "name:ces_x_preferred":[
        "Sion"
    ],
    "name:cym_x_preferred":[
        "Sion"
    ],
    "name:dan_x_preferred":[
        "Sion"
    ],
    "name:deu_x_preferred":[
        "Sion"
    ],
    "name:eus_x_preferred":[
        "Sion"
    ],
    "name:fin_x_preferred":[
        "Sion"
    ],
    "name:fra_x_preferred":[
        "Sion"
    ],
    "name:hin_x_preferred":[
        "\u0938\u0940\u0911\u0928"
    ],
    "name:hun_x_preferred":[
        "Sion"
    ],
    "name:ind_x_preferred":[
        "Sion"
    ],
    "name:ita_x_preferred":[
        "Sion"
    ],
    "name:jpn_x_preferred":[
        "\u30b7\u30aa\u30f3"
    ],
    "name:kor_x_preferred":[
        "\uc2dc\uc628"
    ],
    "name:lat_x_preferred":[
        "Sion"
    ],
    "name:lit_x_preferred":[
        "Sionas"
    ],
    "name:nld_x_preferred":[
        "Sion"
    ],
    "name:nor_x_preferred":[
        "Sion"
    ],
    "name:pms_x_preferred":[
        "Sion"
    ],
    "name:por_x_preferred":[
        "Sion"
    ],
    "name:ron_x_preferred":[
        "Sion"
    ],
    "name:rus_x_preferred":[
        "\u0421\u0438\u043e\u043d"
    ],
    "name:slk_x_preferred":[
        "Sion"
    ],
    "name:spa_x_preferred":[
        "Sion"
    ],
    "name:swe_x_preferred":[
        "Sion"
    ],
    "qs:gn_adm0_cc":"BR",
    "qs:gn_local":3470127,
    "qs:gn_nam_loc":"Belo Horizonte, Belo Horizonte, Minas Gerais, BR",
    "qs:gn_namadm1":"15",
    "qs:local_max":8946,
    "qs:local_sum":53157,
    "qs:localhoods":65,
    "qs:name":"Sion",
    "qs:name_adm0":"Brasil",
    "qs:name_adm1":"Minas Gerais",
    "qs:name_adm2":"Belo Horizonte",
    "qs:name_local":"Belo Horizonte",
    "qs:photo_max":181,
    "qs:photo_sum":833,
    "qs:placetype":"Suburb",
    "qs:quad_count":16,
    "qs:woe_adm0":23424768,
    "qs:woe_adm1":2344856,
    "qs:woe_adm2":12579464,
    "qs:woe_lau":0,
    "qs:woe_local":455821,
    "qs:woe_ver":"7.10.0",
    "wof:lang":[
        "por"
    ],
    "wof:name":"Sion",
    "wof:placetype":"neighbourhood"
},
  "geometry": {"coordinates":[-43.93358,-19.952106],"type":"Point"}
}