{
  "type": "Feature",
  "properties": {
    "gn:admin1_code":"06",
    "gn:admin2_code":"2300903.0",
    "gn:asciiname":"Fazenda Santo Antonio",
    "gn:country_code":"BR",
    "gn:dem":92,
    "gn:feature_class":"P",
    "gn:feature_code":"PPL",
    "gn:name":"Fazenda Santo Antonio",
    "gn:population":0,
    "gn:timezone":"America/Fortaleza",
    "iso:country":"BR",
    "wof:name":"Fazenda Santo Antonio",
    "wof:placetype":"locality"
},
  "geometry": {"coordinates":[-39.38333,-3.91667],"type":"Point"}
}