{
  "type": "Feature",
  "properties": {
    "gn:admin1_code":"18.0",
    "gn:admin2_code":"4113205.0",
    "gn:asciiname":"Sitio Oswaldo Maia",
    "gn:country_code":"BR",
    "gn:dem":928,
    "gn:feature_class":"P",
    "gn:feature_code":"PPL",
    "gn:name":"S\u00edtio Oswaldo Maia",
    "gn:population":0,
    "gn:timezone":"America/Sao_Paulo",
    "iso:country":"BR",
    "name:por_x_preferred":[
        "S\u00edtio Oswaldo Maia"
    ],
    "wof:name":"Sitio Oswaldo Maia",
    "wof:placetype":"locality"
},
  "geometry": {"coordinates":[-49.93541,-25.84003],"type":"Point"}
}