{
  "type": "Feature",
  "properties": {
    "gn:admin1_code":"5",
    "gn:admin2_code":"2912608.0",
    "gn:asciiname":"Salvavida",
    "gn:cc2":"BR",
    "gn:country_code":"BR",
    "gn:dem":667,
    "gn:feature_class":"P",
    "gn:feature_code":"PPL",
    "gn:name":"Salvavida",
    "gn:population":0,
    "gn:timezone":"America/Bahia",
    "iso:country":"BR",
    "name:und_x_variant":[
        "Salvavidas",
        "Salvavida"
    ],
    "wof:name":"Salvavida",
    "wof:placetype":"locality"
},
  "geometry": {"coordinates":[-40.91667,-12.56667],"type":"Point"}
}