{
  "type": "Feature",
  "properties": {
    "gn:admin1_code":"05",
    "gn:admin2_code":"2930204.0",
    "gn:asciiname":"Quixaba",
    "gn:cc2":"BR",
    "gn:country_code":"BR",
    "gn:dem":451,
    "gn:feature_class":"P",
    "gn:feature_code":"PPL",
    "gn:name":"Quixaba",
    "gn:population":0,
    "gn:timezone":"America/Bahia",
    "iso:country":"BR",
    "name:und_x_variant":[
        "Quixoba",
        "Casa Morta",
        "Quixaba"
    ],
    "wof:name":"Quixaba",
    "wof:placetype":"locality"
},
  "geometry": {"coordinates":[-41.51667,-9.98333],"type":"Point"}
}