{
  "type": "Feature",
  "properties": {
    "gn:admin1_code":"05",
    "gn:admin2_code":"2930204.0",
    "gn:asciiname":"Quixaba",
    "gn:cc2":"BR",
    "gn:country_code":"BR",
    "gn:dem":451,
    "gn:feature_class":"P",
    "gn:feature_code":"PPL",
    "gn:name":"Quixaba",
    "gn:population":0,
    "gn:timezone":"America/Bahia",
    "iso:country":"BR",
    "name:bpy_x_preferred":[
        "\u0995\u09c1\u0987\u0995\u09cd\u09b8\u09be\u09ac\u09be"
    ],
    "name:bre_x_preferred":[
        "Quixaba"
    ],
    "name:ceb_x_preferred":[
        "Quixaba"
    ],
    "name:eus_x_preferred":[
        "Quixaba"
    ],
    "name:fra_x_preferred":[
        "Quixaba"
    ],
    "name:ita_x_preferred":[
        "Quixaba"
    ],
    "name:kat_x_preferred":[
        "\u10d9\u10d8\u10e8\u10d0\u10d1\u10d0"
    ],
    "name:mlg_x_preferred":[
        "Quixaba"
    ],
    "name:nld_x_preferred":[
        "Quixaba"
    ],
    "name:nor_x_preferred":[
        "Quixaba"
    ],
    "name:por_x_preferred":[
        "Quixaba"
    ],
    "name:ron_x_preferred":[
        "Quixaba"
    ],
    "name:rus_x_preferred":[
        "\u041a\u0438\u0448\u0430\u0431\u0430"
    ],
    "name:sco_x_preferred":[
        "Quixaba"
    ],
    "name:und_x_variant":[
        "Quixoba",
        "Casa Morta"
    ],
    "name:vie_x_preferred":[
        "Quixaba"
    ],
    "name:vol_x_preferred":[
        "Quixaba"
    ],
    "name:war_x_preferred":[
        "Quixaba"
    ],
    "name:zho_x_preferred":[
        "\u57fa\u6c99\u5df4"
    ],
    "wof:name":"Quixaba",
    "wof:placetype":"locality"
},
  "geometry": {"coordinates":[-41.51667,-9.98333],"type":"Point"}
}