{
  "type": "Feature",
  "properties": {
    "gn:admin1_code":"5",
    "gn:admin2_code":"2912004.0",
    "gn:asciiname":"Antas",
    "gn:cc2":"BR",
    "gn:country_code":"BR",
    "gn:dem":737,
    "gn:feature_class":"P",
    "gn:feature_code":"PPL",
    "gn:name":"Antas",
    "gn:population":0,
    "gn:timezone":"America/Bahia",
    "iso:country":"BR",
    "name:ara_x_preferred":[
        "\u0623\u0646\u062a\u0627\u0633"
    ],
    "name:arg_x_preferred":[
        "Antas"
    ],
    "name:ast_x_preferred":[
        "Alces"
    ],
    "name:azb_x_preferred":[
        "\u0622\u0646\u062a\u0627\u0633"
    ],
    "name:bpy_x_preferred":[
        "\u0986\u09a8\u09cd\u099f\u09be\u09b8"
    ],
    "name:bul_x_preferred":[
        "\u0410\u043d\u0442\u0430\u0441"
    ],
    "name:cat_x_preferred":[
        "Antas"
    ],
    "name:eus_x_preferred":[
        "Antas"
    ],
    "name:fas_x_preferred":[
        "\u0622\u0646\u062a\u0627\u0633"
    ],
    "name:fra_x_preferred":[
        "Antas"
    ],
    "name:hat_x_preferred":[
        "Antas"
    ],
    "name:hun_x_preferred":[
        "Antas"
    ],
    "name:hye_x_preferred":[
        "\u0531\u0576\u057f\u0561\u057d"
    ],
    "name:ina_x_preferred":[
        "Antas"
    ],
    "name:ita_x_preferred":[
        "Antas"
    ],
    "name:mkd_x_preferred":[
        "\u0410\u043d\u0442\u0430\u0441"
    ],
    "name:msa_x_preferred":[
        "Antas"
    ],
    "name:nld_x_preferred":[
        "Antas"
    ],
    "name:oci_x_preferred":[
        "Antas"
    ],
    "name:pol_x_preferred":[
        "Antas"
    ],
    "name:por_x_preferred":[
        "Antas"
    ],
    "name:ron_x_preferred":[
        "Antas"
    ],
    "name:rus_x_preferred":[
        "\u0410\u043d\u0442\u0430\u0441"
    ],
    "name:spa_x_preferred":[
        "Antas"
    ],
    "name:tur_x_preferred":[
        "Antas"
    ],
    "name:ukr_x_preferred":[
        "\u0410\u043d\u0442\u0430\u0441"
    ],
    "name:und_x_variant":[
        "Rio das Antas"
    ],
    "name:uzb_x_preferred":[
        "Antas"
    ],
    "name:vie_x_preferred":[
        "Antas"
    ],
    "name:war_x_preferred":[
        "Antas"
    ],
    "name:zho_x_preferred":[
        "\u5b89\u5854\u65af"
    ],
    "wof:name":"Antas",
    "wof:placetype":"locality"
},
  "geometry": {"coordinates":[-42.41667,-14.33333],"type":"Point"}
}