{
  "type": "Feature",
  "properties": {
    "gn:admin1_code":"5",
    "gn:admin2_code":"2912004.0",
    "gn:asciiname":"Antas",
    "gn:cc2":"BR",
    "gn:country_code":"BR",
    "gn:dem":737,
    "gn:feature_class":"P",
    "gn:feature_code":"PPL",
    "gn:name":"Antas",
    "gn:population":0,
    "gn:timezone":"America/Bahia",
    "iso:country":"BR",
    "name:und_x_variant":[
        "Rio das Antas",
        "Antas"
    ],
    "wof:name":"Antas",
    "wof:placetype":"locality"
},
  "geometry": {"coordinates":[-42.41667,-14.33333],"type":"Point"}
}