{
  "type": "Feature",
  "properties": {
    "gn:admin1_code":"5",
    "gn:admin2_code":"2900504.0",
    "gn:asciiname":"Agua Quente",
    "gn:country_code":"BR",
    "gn:dem":675,
    "gn:feature_class":"P",
    "gn:feature_code":"PPL",
    "gn:name":"\u00c1gua Quente",
    "gn:population":0,
    "gn:timezone":"America/Bahia",
    "iso:country":"BR",
    "name:por_x_preferred":[
        "\u00c1gua Quente"
    ],
    "wof:name":"Agua Quente",
    "wof:placetype":"locality"
},
  "geometry": {"coordinates":[-42.13753,-13.41675],"type":"Point"}
}