{
  "type": "Feature",
  "properties": {
    "gn:admin1_code":"20",
    "gn:admin2_code":"2211407.0",
    "gn:asciiname":"Cabeceira (1)",
    "gn:country_code":"BR",
    "gn:dem":295,
    "gn:feature_class":"P",
    "gn:feature_code":"PPL",
    "gn:name":"Cabeceira (1)",
    "gn:population":0,
    "gn:timezone":"America/Fortaleza",
    "iso:country":"BR",
    "wof:name":"Cabeceira (1)",
    "wof:placetype":"locality"
},
  "geometry": {"coordinates":[-42.21667,-6.58333],"type":"Point"}
}