{
  "type": "Feature",
  "properties": {
    "gn:admin1_code":"5",
    "gn:admin2_code":"2924900.0",
    "gn:asciiname":"Quatis",
    "gn:country_code":"BR",
    "gn:dem":754,
    "gn:feature_class":"P",
    "gn:feature_code":"PPL",
    "gn:name":"Quatis",
    "gn:population":0,
    "gn:timezone":"America/Bahia",
    "iso:country":"BR",
    "name:bpy_x_preferred":[
        "\u0995\u09c1\u09f1\u09be\u099f\u09bf\u09b8"
    ],
    "name:epo_x_preferred":[
        "Quatis"
    ],
    "name:eus_x_preferred":[
        "Quatis"
    ],
    "name:fra_x_preferred":[
        "Quatis"
    ],
    "name:ita_x_preferred":[
        "Quatis"
    ],
    "name:kat_x_preferred":[
        "\u10d9\u10e3\u10d0\u10e2\u10d8\u10e1\u10d8"
    ],
    "name:kaz_x_preferred":[
        "\u041a\u0443\u0430\u0442\u0438\u0441"
    ],
    "name:nld_x_preferred":[
        "Quatis"
    ],
    "name:nor_x_preferred":[
        "Quatis"
    ],
    "name:pol_x_preferred":[
        "Quatis"
    ],
    "name:por_x_preferred":[
        "Quatis"
    ],
    "name:ron_x_preferred":[
        "Quatis"
    ],
    "name:rus_x_preferred":[
        "\u041a\u0443\u0430\u0442\u0438\u0441"
    ],
    "name:spa_x_preferred":[
        "Quatis"
    ],
    "name:vie_x_preferred":[
        "Quatis"
    ],
    "name:vol_x_preferred":[
        "Quatis"
    ],
    "name:war_x_preferred":[
        "Quatis"
    ],
    "name:zho_x_preferred":[
        "\u5938\u8482\u65af"
    ],
    "wof:name":"Quatis",
    "wof:placetype":"locality"
},
  "geometry": {"coordinates":[-40.33333,-13.23333],"type":"Point"}
}