{
  "type": "Feature",
  "properties": {
    "gn:admin1_code":"5",
    "gn:admin2_code":"2924900.0",
    "gn:asciiname":"Quatis",
    "gn:country_code":"BR",
    "gn:dem":754,
    "gn:feature_class":"P",
    "gn:feature_code":"PPL",
    "gn:name":"Quatis",
    "gn:population":0,
    "gn:timezone":"America/Bahia",
    "iso:country":"BR",
    "wof:name":"Quatis",
    "wof:placetype":"locality"
},
  "geometry": {"coordinates":[-40.33333,-13.23333],"type":"Point"}
}