{
  "type": "Feature",
  "properties": {
    "gn:admin1_code":"18.0",
    "gn:admin2_code":"4112306.0",
    "gn:asciiname":"Sitio Geremias de Campos",
    "gn:country_code":"BR",
    "gn:dem":663,
    "gn:feature_class":"P",
    "gn:feature_code":"PPL",
    "gn:name":"S\u00edtio Geremias de Campos",
    "gn:population":0,
    "gn:timezone":"America/Sao_Paulo",
    "iso:country":"BR",
    "name:por_x_preferred":[
        "S\u00edtio Geremias de Campos"
    ],
    "wof:name":"Sitio Geremias de Campos",
    "wof:placetype":"locality"
},
  "geometry": {"coordinates":[-50.12356,-23.82481],"type":"Point"}
}