{
  "type": "Feature",
  "properties": {
    "gn:admin1_code":"18.0",
    "gn:admin2_code":"4109005.0",
    "gn:asciiname":"Sitio Jaci Vieira da Silva",
    "gn:country_code":"BR",
    "gn:dem":478,
    "gn:feature_class":"P",
    "gn:feature_code":"PPL",
    "gn:name":"S\u00edtio Jaci Vieira da Silva",
    "gn:population":0,
    "gn:timezone":"America/Sao_Paulo",
    "iso:country":"BR",
    "name:por_x_preferred":[
        "S\u00edtio Jaci Vieira da Silva"
    ],
    "wof:name":"Sitio Jaci Vieira da Silva",
    "wof:placetype":"locality"
},
  "geometry": {"coordinates":[-50.0357,-23.49147],"type":"Point"}
}