{
  "type": "Feature",
  "properties": {
    "gn:admin1_code":"23",
    "gn:admin2_code":"4305108.0",
    "gn:asciiname":"Sao Nicolau",
    "gn:country_code":"BR",
    "gn:dem":713,
    "gn:feature_class":"P",
    "gn:feature_code":"PPL",
    "gn:name":"S\u00e3o Nicolau",
    "gn:population":0,
    "gn:timezone":"America/Sao_Paulo",
    "iso:country":"BR",
    "name:por_x_preferred":[
        "S\u00e3o Nicolau"
    ],
    "wof:name":"Sao Nicolau",
    "wof:placetype":"locality"
},
  "geometry": {"coordinates":[-51.0408,-29.0966],"type":"Point"}
}