{
  "type": "Feature",
  "properties": {
    "gn:admin1_code":"27",
    "gn:admin2_code":"3509254.0",
    "gn:asciiname":"Sitio Ezeguias",
    "gn:country_code":"BR",
    "gn:dem":79,
    "gn:feature_class":"P",
    "gn:feature_code":"PPL",
    "gn:name":"S\u00edtio Ezeguias",
    "gn:population":0,
    "gn:timezone":"America/Sao_Paulo",
    "iso:country":"BR",
    "name:por_x_preferred":[
        "S\u00edtio Ezeguias"
    ],
    "wof:name":"Sitio Ezeguias",
    "wof:placetype":"locality"
},
  "geometry": {"coordinates":[-48.2063,-24.776],"type":"Point"}
}