{
  "type": "Feature",
  "properties": {
    "gn:admin1_code":"18.0",
    "gn:admin2_code":"4101309.0",
    "gn:asciiname":"Espigao",
    "gn:country_code":"BR",
    "gn:dem":810,
    "gn:feature_class":"P",
    "gn:feature_code":"PPLL",
    "gn:name":"Espig\u00e3o",
    "gn:population":0,
    "gn:timezone":"America/Sao_Paulo",
    "iso:country":"BR",
    "name:por_x_preferred":[
        "Espig\u00e3o"
    ],
    "wof:name":"Espigao",
    "wof:placetype":"locality"
},
  "geometry": {"coordinates":[-50.13914000000001,-25.94421],"type":"Point"}
}