{
  "type": "Feature",
  "properties": {
    "gn:admin1_code":"27.0",
    "gn:admin2_code":"3524600.0",
    "gn:asciiname":"Bairro Pindauva do Meio",
    "gn:country_code":"BR",
    "gn:dem":81,
    "gn:feature_class":"P",
    "gn:feature_code":"PPL",
    "gn:name":"Bairro Pinda\u00fava do Meio",
    "gn:population":0,
    "gn:timezone":"America/Sao_Paulo",
    "iso:country":"BR",
    "name:por_x_preferred":[
        "Bairro Pinda\u00fava do Meio"
    ],
    "wof:name":"Bairro Pindauva do Meio",
    "wof:placetype":"locality"
},
  "geometry": {"coordinates":[-48.0793,-24.884],"type":"Point"}
}