{
  "type": "Feature",
  "properties": {
    "gn:admin1_code":"5.0",
    "gn:admin2_code":"2914307.0",
    "gn:asciiname":"Placas",
    "gn:country_code":"BR",
    "gn:dem":419,
    "gn:feature_class":"P",
    "gn:feature_code":"PPL",
    "gn:name":"Placas",
    "gn:population":0,
    "gn:timezone":"America/Bahia",
    "iso:country":"BR",
    "name:bpy_x_preferred":[
        "\u09aa\u09cd\u09b2\u09be\u0995\u09be\u09b8"
    ],
    "name:ceb_x_preferred":[
        "Placas"
    ],
    "name:eus_x_preferred":[
        "Placas"
    ],
    "name:fra_x_preferred":[
        "Placas"
    ],
    "name:ita_x_preferred":[
        "Placas"
    ],
    "name:kaz_x_preferred":[
        "\u041f\u043b\u0430\u043a\u0430\u0441"
    ],
    "name:nld_x_preferred":[
        "Placas"
    ],
    "name:nor_x_preferred":[
        "Placas"
    ],
    "name:pol_x_preferred":[
        "Placas"
    ],
    "name:por_x_preferred":[
        "Placas"
    ],
    "name:ron_x_preferred":[
        "Placas"
    ],
    "name:rus_x_preferred":[
        "\u041f\u043b\u0430\u043a\u0430\u0441"
    ],
    "name:swe_x_preferred":[
        "Placas"
    ],
    "name:vie_x_preferred":[
        "Placas"
    ],
    "name:vol_x_preferred":[
        "Placas"
    ],
    "name:war_x_preferred":[
        "Placas"
    ],
    "name:zho_x_preferred":[
        "\u666e\u62c9\u5361\u65af"
    ],
    "wof:name":"Placas",
    "wof:placetype":"locality"
},
  "geometry": {"coordinates":[-40.84409,-13.4908],"type":"Point"}
}