{
  "type": "Feature",
  "properties": {
    "gn:admin1_code":"17",
    "gn:admin2_code":"2513356.0",
    "gn:asciiname":"Barreiros",
    "gn:country_code":"BR",
    "gn:dem":688,
    "gn:feature_class":"P",
    "gn:feature_code":"PPL",
    "gn:name":"Barreiros",
    "gn:population":0,
    "gn:timezone":"America/Recife",
    "iso:country":"BR",
    "wof:name":"Barreiros",
    "wof:placetype":"locality"
},
  "geometry": {"coordinates":[-38.68333,-7.63333],"type":"Point"}
}