{
  "type": "Feature",
  "properties": {
    "gn:admin1_code":"5",
    "gn:admin2_code":"2928604.0",
    "gn:asciiname":"Paraiso",
    "gn:country_code":"BR",
    "gn:dem":144,
    "gn:feature_class":"P",
    "gn:feature_code":"PPL",
    "gn:name":"Para\u00edso",
    "gn:population":0,
    "gn:timezone":"America/Bahia",
    "iso:country":"BR",
    "wof:name":"Paraiso",
    "wof:placetype":"locality"
},
  "geometry": {"coordinates":[-38.78333,-12.45],"type":"Point"}
}