{
  "type": "Feature",
  "properties": {
    "gn:admin1_code":"4",
    "gn:admin2_code":"1301308.0",
    "gn:asciiname":"Poco da Ilha",
    "gn:country_code":"BR",
    "gn:dem":25,
    "gn:feature_class":"P",
    "gn:feature_code":"PPL",
    "gn:name":"Po\u00e7o da Ilha",
    "gn:population":0,
    "gn:timezone":"America/Manaus",
    "iso:country":"BR",
    "wof:name":"Poco da Ilha",
    "wof:placetype":"locality"
},
  "geometry": {"coordinates":[-63.14444,-3.07917],"type":"Point"}
}