{
  "type": "Feature",
  "properties": {
    "gn:admin1_code":"18.0",
    "gn:admin2_code":"4107751.0",
    "gn:asciiname":"Sitio Sant'Ana",
    "gn:country_code":"BR",
    "gn:dem":684,
    "gn:feature_class":"P",
    "gn:feature_code":"PPL",
    "gn:name":"S\u00edtio Sant\u2019Ana",
    "gn:population":0,
    "gn:timezone":"America/Sao_Paulo",
    "iso:country":"BR",
    "name:por_x_preferred":[
        "S\u00edtio Sant\u2019Ana"
    ],
    "wof:name":"Sitio Sant'Ana",
    "wof:placetype":"locality"
},
  "geometry": {"coordinates":[-50.41212,-23.91889],"type":"Point"}
}