{
  "type": "Feature",
  "properties": {
    "gn:admin1_code":"5",
    "gn:admin2_code":"2920007.0",
    "gn:asciiname":"Gameleira",
    "gn:country_code":"BR",
    "gn:dem":357,
    "gn:feature_class":"P",
    "gn:feature_code":"PPL",
    "gn:name":"Gameleira",
    "gn:population":0,
    "gn:timezone":"America/Bahia",
    "iso:country":"BR",
    "wof:name":"Gameleira",
    "wof:placetype":"locality"
},
  "geometry": {"coordinates":[-40.23333,-15.71667],"type":"Point"}
}