{
  "type": "Feature",
  "properties": {
    "gn:admin1_code":"18.0",
    "gn:admin2_code":"4116901.0",
    "gn:asciiname":"Granjas",
    "gn:country_code":"BR",
    "gn:dem":533,
    "gn:feature_class":"P",
    "gn:feature_code":"PPL",
    "gn:name":"Granjas",
    "gn:population":0,
    "gn:timezone":"America/Sao_Paulo",
    "iso:country":"BR",
    "name:por_x_preferred":[
        "Granjas"
    ],
    "wof:name":"Granjas",
    "wof:placetype":"locality"
},
  "geometry": {"coordinates":[-52.20946,-23.19711],"type":"Point"}
}