{
  "type": "Feature",
  "properties": {
    "gn:admin1_code":"5",
    "gn:admin2_code":"2927408.0",
    "gn:asciiname":"Senhor dos Passos",
    "gn:cc2":"BR",
    "gn:country_code":"BR",
    "gn:dem":1,
    "gn:feature_class":"P",
    "gn:feature_code":"PPL",
    "gn:name":"Senhor dos Passos",
    "gn:population":0,
    "gn:timezone":"America/Bahia",
    "iso:country":"BR",
    "name:und_x_variant":[
        "Bom Jes\u00fas",
        "Senhor dos Passos"
    ],
    "wof:name":"Senhor dos Passos",
    "wof:placetype":"locality"
},
  "geometry": {"coordinates":[-38.63333,-12.76667],"type":"Point"}
}