{
  "type": "Feature",
  "properties": {
    "gn:admin1_code":"18.0",
    "gn:admin2_code":"4111803.0",
    "gn:asciiname":"Sitio Guilherme Guaudeline",
    "gn:country_code":"BR",
    "gn:dem":515,
    "gn:feature_class":"P",
    "gn:feature_code":"PPL",
    "gn:name":"S\u00edtio Guilherme Guaudeline",
    "gn:population":0,
    "gn:timezone":"America/Sao_Paulo",
    "iso:country":"BR",
    "name:por_x_preferred":[
        "S\u00edtio Guilherme Guaudeline"
    ],
    "wof:name":"Sitio Guilherme Guaudeline",
    "wof:placetype":"locality"
},
  "geometry": {"coordinates":[-49.85864,-23.1876],"type":"Point"}
}