{
  "type": "Feature",
  "properties": {
    "gn:admin1_code":"06",
    "gn:admin2_code":"2308500.0",
    "gn:asciiname":"Riacho da Palha",
    "gn:country_code":"BR",
    "gn:dem":290,
    "gn:feature_class":"P",
    "gn:feature_code":"PPL",
    "gn:name":"Riacho da Palha",
    "gn:population":0,
    "gn:timezone":"America/Fortaleza",
    "iso:country":"BR",
    "wof:name":"Riacho da Palha",
    "wof:placetype":"locality"
},
  "geometry": {"coordinates":[-39.65,-5.65],"type":"Point"}
}