{
  "type": "Feature",
  "properties": {
    "gn:admin1_code":"18.0",
    "gn:admin2_code":"4119202.0",
    "gn:asciiname":"Sitio Pedro C. dos Santos",
    "gn:country_code":"BR",
    "gn:dem":648,
    "gn:feature_class":"P",
    "gn:feature_code":"PPL",
    "gn:name":"S\u00edtio Pedro C. dos Santos",
    "gn:population":0,
    "gn:timezone":"America/Sao_Paulo",
    "iso:country":"BR",
    "name:por_x_preferred":[
        "S\u00edtio Pedro C. dos Santos"
    ],
    "wof:name":"Sitio Pedro C. dos Santos",
    "wof:placetype":"locality"
},
  "geometry": {"coordinates":[-50.03035,-23.96129],"type":"Point"}
}