{
  "type": "Feature",
  "properties": {
    "gn:admin1_code":"06",
    "gn:admin2_code":"2306306.0",
    "gn:asciiname":"Fazenda Laura",
    "gn:country_code":"BR",
    "gn:dem":131,
    "gn:feature_class":"P",
    "gn:feature_code":"PPL",
    "gn:name":"Fazenda Laura",
    "gn:population":0,
    "gn:timezone":"America/Fortaleza",
    "iso:country":"BR",
    "wof:name":"Fazenda Laura",
    "wof:placetype":"locality"
},
  "geometry": {"coordinates":[-39.58333,-3.81667],"type":"Point"}
}