{
  "type": "Feature",
  "properties": {
    "gn:admin1_code":"24.0",
    "gn:admin2_code":"1100015.0",
    "gn:asciiname":"Alta Floresta D'Oeste",
    "gn:country_code":"BR",
    "gn:dem":322,
    "gn:feature_class":"P",
    "gn:feature_code":"PPL",
    "gn:name":"Alta Floresta D\u2019Oeste",
    "gn:population":0,
    "gn:timezone":"America/Porto_Velho",
    "iso:country":"BR",
    "name:por_x_preferred":[
        "Alta Floresta D\u2019Oeste"
    ],
    "wof:name":"Alta Floresta D'Oeste",
    "wof:placetype":"locality"
},
  "geometry": {"coordinates":[-61.99829,-11.92871],"type":"Point"}
}