{
  "type": "Feature",
  "properties": {
    "gn:admin1_code":"18.0",
    "gn:admin2_code":"4120705.0",
    "gn:asciiname":"Sitio Amadeu Bonotto",
    "gn:country_code":"BR",
    "gn:dem":507,
    "gn:feature_class":"P",
    "gn:feature_code":"PPL",
    "gn:name":"S\u00edtio Amadeu Bonotto",
    "gn:population":0,
    "gn:timezone":"America/Sao_Paulo",
    "iso:country":"BR",
    "name:por_x_preferred":[
        "S\u00edtio Amadeu Bonotto"
    ],
    "wof:name":"Sitio Amadeu Bonotto",
    "wof:placetype":"locality"
},
  "geometry": {"coordinates":[-49.9709,-23.5689],"type":"Point"}
}