{
  "type": "Feature",
  "properties": {
    "gn:admin1_code":"30",
    "gn:admin2_code":"2613909.0",
    "gn:asciiname":"Serrinha",
    "gn:country_code":"BR",
    "gn:dem":373,
    "gn:feature_class":"P",
    "gn:feature_code":"PPL",
    "gn:name":"Serrinha",
    "gn:population":0,
    "gn:timezone":"America/Recife",
    "iso:country":"BR",
    "wof:name":"Serrinha",
    "wof:placetype":"locality"
},
  "geometry": {"coordinates":[-38.53333,-8.23333],"type":"Point"}
}