{
  "type": "Feature",
  "properties": {
    "gn:admin1_code":"06",
    "gn:admin2_code":"2307007.0",
    "gn:asciiname":"Pau Branco (3)",
    "gn:country_code":"BR",
    "gn:dem":14,
    "gn:feature_class":"P",
    "gn:feature_code":"PPL",
    "gn:name":"Pau Branco (3)",
    "gn:population":0,
    "gn:timezone":"America/Fortaleza",
    "iso:country":"BR",
    "wof:name":"Pau Branco (3)",
    "wof:placetype":"locality"
},
  "geometry": {"coordinates":[-37.88333,-4.86667],"type":"Point"}
}