{
  "type": "Feature",
  "properties": {
    "gn:admin1_code":"5",
    "gn:admin2_code":"2924504.0",
    "gn:asciiname":"Mato Grosso",
    "gn:country_code":"BR",
    "gn:dem":627,
    "gn:feature_class":"P",
    "gn:feature_code":"PPL",
    "gn:name":"Mato Grosso",
    "gn:population":0,
    "gn:timezone":"America/Bahia",
    "iso:country":"BR",
    "wof:name":"Mato Grosso",
    "wof:placetype":"locality"
},
  "geometry": {"coordinates":[-42.66667,-14.43333],"type":"Point"}
}