{
  "type": "Feature",
  "properties": {
    "gn:admin1_code":"27",
    "gn:admin2_code":"3556107.0",
    "gn:asciiname":"Santo Antonio",
    "gn:cc2":"BR",
    "gn:country_code":"BR",
    "gn:dem":420,
    "gn:feature_class":"P",
    "gn:feature_code":"PPL",
    "gn:name":"Santo Ant\u00f4nio",
    "gn:population":0,
    "gn:timezone":"America/Sao_Paulo",
    "iso:country":"BR",
    "name:und_x_variant":[
        "Virador",
        "Santo Ant\u00f4nio"
    ],
    "wof:name":"Santo Antonio",
    "wof:placetype":"locality"
},
  "geometry": {"coordinates":[-50.18333,-20.48333],"type":"Point"}
}