{
  "type": "Feature",
  "properties": {
    "gn:admin1_code":"5",
    "gn:admin2_code":"2910503.0",
    "gn:asciiname":"Catana",
    "gn:country_code":"BR",
    "gn:dem":85,
    "gn:feature_class":"P",
    "gn:feature_code":"PPL",
    "gn:name":"Catana",
    "gn:population":0,
    "gn:timezone":"America/Bahia",
    "iso:country":"BR",
    "wof:name":"Catana",
    "wof:placetype":"locality"
},
  "geometry": {"coordinates":[-38.08333,-12.08333],"type":"Point"}
}