{
  "type": "Feature",
  "properties": {
    "gn:admin1_code":"20",
    "gn:admin2_code":"2205359.0",
    "gn:asciiname":"Torres",
    "gn:country_code":"BR",
    "gn:dem":427,
    "gn:feature_class":"P",
    "gn:feature_code":"PPL",
    "gn:name":"T\u00f4rres",
    "gn:population":0,
    "gn:timezone":"America/Fortaleza",
    "iso:country":"BR",
    "wof:name":"Torres",
    "wof:placetype":"locality"
},
  "geometry": {"coordinates":[-42.63333,-8.53333],"type":"Point"}
}