{
  "type": "Feature",
  "properties": {
    "gn:admin1_code":"27",
    "gn:admin2_code":"3521200.0",
    "gn:asciiname":"Bairro Descalvado",
    "gn:country_code":"BR",
    "gn:dem":98,
    "gn:feature_class":"P",
    "gn:feature_code":"PPLL",
    "gn:name":"Bairro Descalvado",
    "gn:population":0,
    "gn:timezone":"America/Sao_Paulo",
    "iso:country":"BR",
    "name:por_x_preferred":[
        "Bairro Descalvado"
    ],
    "name:por_x_variant":[
        "Descalvado"
    ],
    "wof:name":"Bairro Descalvado",
    "wof:placetype":"locality"
},
  "geometry": {"coordinates":[-48.64681,-24.64509],"type":"Point"}
}