{
  "type": "Feature",
  "properties": {
    "gn:admin1_code":"22",
    "gn:admin2_code":"2409704.0",
    "gn:asciiname":"Deus-me-Guia",
    "gn:country_code":"BR",
    "gn:dem":115,
    "gn:feature_class":"P",
    "gn:feature_code":"PPL",
    "gn:name":"Deus-me-Guia",
    "gn:population":0,
    "gn:timezone":"America/Fortaleza",
    "iso:country":"BR",
    "wof:name":"Deus-me-Guia",
    "wof:placetype":"locality"
},
  "geometry": {"coordinates":[-36.3225,-5.42306],"type":"Point"}
}