{
  "type": "Feature",
  "properties": {
    "gn:admin1_code":"1",
    "gn:admin2_code":"1200203.0",
    "gn:asciiname":"Ponciano",
    "gn:country_code":"BR",
    "gn:dem":176,
    "gn:feature_class":"P",
    "gn:feature_code":"PPL",
    "gn:name":"Ponciano",
    "gn:population":0,
    "gn:timezone":"America/Rio_Branco",
    "iso:country":"BR",
    "wof:name":"Ponciano",
    "wof:placetype":"locality"
},
  "geometry": {"coordinates":[-72.75,-7.88333],"type":"Point"}
}