{
  "type": "Feature",
  "properties": {
    "gn:admin1_code":"27.0",
    "gn:admin2_code":"3528502.0",
    "gn:asciiname":"Campos da Cantareira",
    "gn:country_code":"BR",
    "gn:dem":821,
    "gn:feature_class":"P",
    "gn:feature_code":"PPLL",
    "gn:name":"Campos da Cantareira",
    "gn:population":0,
    "gn:timezone":"America/Sao_Paulo",
    "iso:country":"BR",
    "name:por_x_preferred":[
        "Campos da Cantareira"
    ],
    "wof:name":"Campos da Cantareira",
    "wof:placetype":"locality"
},
  "geometry": {"coordinates":[-46.6432,-23.37828],"type":"Point"}
}