{
  "type": "Feature",
  "properties": {
    "gn:admin1_code":"20",
    "gn:admin2_code":"2203701.0",
    "gn:asciiname":"Palmeira",
    "gn:country_code":"BR",
    "gn:dem":81,
    "gn:feature_class":"P",
    "gn:feature_code":"PPL",
    "gn:name":"Palmeira",
    "gn:population":0,
    "gn:timezone":"America/Fortaleza",
    "iso:country":"BR",
    "wof:name":"Palmeira",
    "wof:placetype":"locality"
},
  "geometry": {"coordinates":[-42.15222,-3.85778],"type":"Point"}
}