{
  "type": "Feature",
  "properties": {
    "gn:admin1_code":"14",
    "gn:admin2_code":"5100508.0",
    "gn:asciiname":"Tres Barras",
    "gn:cc2":"BR",
    "gn:country_code":"BR",
    "gn:dem":200,
    "gn:feature_class":"P",
    "gn:feature_code":"PPL",
    "gn:name":"Tr\u00eas Barras",
    "gn:population":0,
    "gn:timezone":"America/Cuiaba",
    "iso:country":"BR",
    "name:und_x_variant":[
        "Colonia de Minera\u00e7ao",
        "Tr\u00eas Barras"
    ],
    "wof:name":"Tres Barras",
    "wof:placetype":"locality"
},
  "geometry": {"coordinates":[-56.71666999999999,-14.66667],"type":"Point"}
}