{
  "type": "Feature",
  "properties": {
    "gn:admin1_code":"18.0",
    "gn:admin2_code":"4104709.0",
    "gn:asciiname":"Sitio Boa Vista",
    "gn:country_code":"BR",
    "gn:dem":487,
    "gn:feature_class":"P",
    "gn:feature_code":"PPL",
    "gn:name":"S\u00edtio Boa Vista",
    "gn:population":0,
    "gn:timezone":"America/Sao_Paulo",
    "iso:country":"BR",
    "name:por_x_preferred":[
        "S\u00edtio Boa Vista"
    ],
    "wof:name":"Sitio Boa Vista",
    "wof:placetype":"locality"
},
  "geometry": {"coordinates":[-49.76934,-23.41029],"type":"Point"}
}