{
  "type": "Feature",
  "properties": {
    "gn:admin1_code":"27",
    "gn:admin2_code":"3514809.0",
    "gn:asciiname":"Ouro Grosso",
    "gn:country_code":"BR",
    "gn:dem":35,
    "gn:feature_class":"P",
    "gn:feature_code":"PPLL",
    "gn:name":"Ouro Grosso",
    "gn:population":0,
    "gn:timezone":"America/Sao_Paulo",
    "iso:country":"BR",
    "name:por_x_preferred":[
        "Ouro Grosso"
    ],
    "wof:name":"Ouro Grosso",
    "wof:placetype":"locality"
},
  "geometry": {"coordinates":[-48.22074,-24.55007],"type":"Point"}
}