{
  "type": "Feature",
  "properties": {
    "gn:admin1_code":"13",
    "gn:admin2_code":"2105989.0",
    "gn:asciiname":"Gruta Funda",
    "gn:country_code":"BR",
    "gn:dem":238,
    "gn:feature_class":"P",
    "gn:feature_code":"PPL",
    "gn:name":"Gruta Funda",
    "gn:population":0,
    "gn:timezone":"America/Fortaleza",
    "iso:country":"BR",
    "wof:name":"Gruta Funda",
    "wof:placetype":"locality"
},
  "geometry": {"coordinates":[-46.93333,-6.18333],"type":"Point"}
}