{
  "type": "Feature",
  "properties": {
    "gn:admin1_code":"26",
    "gn:admin2_code":"4215802.0",
    "gn:asciiname":"Sitio Paulo Dums",
    "gn:country_code":"BR",
    "gn:dem":862,
    "gn:feature_class":"P",
    "gn:feature_code":"PPL",
    "gn:name":"S\u00edtio Paulo Dums",
    "gn:population":0,
    "gn:timezone":"America/Sao_Paulo",
    "iso:country":"BR",
    "name:por_x_preferred":[
        "S\u00edtio Paulo Dums"
    ],
    "wof:name":"Sitio Paulo Dums",
    "wof:placetype":"locality"
},
  "geometry": {"coordinates":[-49.46100000000001,-26.1929],"type":"Point"}
}