{
  "type": "Feature",
  "properties": {
    "gn:admin1_code":"22",
    "gn:admin2_code":"2413359.0",
    "gn:asciiname":"Massape",
    "gn:country_code":"BR",
    "gn:dem":105,
    "gn:feature_class":"P",
    "gn:feature_code":"PPL",
    "gn:name":"Massap\u00ea",
    "gn:population":0,
    "gn:timezone":"America/Fortaleza",
    "iso:country":"BR",
    "wof:name":"Massape",
    "wof:placetype":"locality"
},
  "geometry": {"coordinates":[-36.94667000000001,-5.22861],"type":"Point"}
}