{
  "type": "Feature",
  "properties": {
    "gn:admin1_code":"4",
    "gn:admin2_code":"1300805.0",
    "gn:asciiname":"Costa do Ipiranga",
    "gn:country_code":"BR",
    "gn:dem":32,
    "gn:feature_class":"P",
    "gn:feature_code":"PPL",
    "gn:name":"Costa do Ipiranga",
    "gn:population":0,
    "gn:timezone":"America/Manaus",
    "iso:country":"BR",
    "wof:name":"Costa do Ipiranga",
    "wof:placetype":"locality"
},
  "geometry": {"coordinates":[-59.76416999999999,-4.3625],"type":"Point"}
}