{
  "type": "Feature",
  "properties": {
    "gn:admin1_code":"23",
    "gn:admin2_code":"4316709.0",
    "gn:asciiname":"Porongos",
    "gn:country_code":"BR",
    "gn:dem":499,
    "gn:feature_class":"P",
    "gn:feature_code":"PPL",
    "gn:name":"Porongos",
    "gn:population":0,
    "gn:timezone":"America/Sao_Paulo",
    "iso:country":"BR",
    "wof:name":"Porongos",
    "wof:placetype":"locality"
},
  "geometry": {"coordinates":[-53.31667,-28.45],"type":"Point"}
}