{
  "type": "Feature",
  "properties": {
    "gn:admin1_code":"13",
    "gn:admin2_code":"2100808.0",
    "gn:asciiname":"Picada Velha",
    "gn:country_code":"BR",
    "gn:dem":103,
    "gn:feature_class":"P",
    "gn:feature_code":"PPL",
    "gn:name":"Picada Velha",
    "gn:population":0,
    "gn:timezone":"America/Fortaleza",
    "iso:country":"BR",
    "wof:name":"Picada Velha",
    "wof:placetype":"locality"
},
  "geometry": {"coordinates":[-43.04528,-3.71917],"type":"Point"}
}