{
  "type": "Feature",
  "properties": {
    "gn:admin1_code":"16.0",
    "gn:admin2_code":"1505304.0",
    "gn:asciiname":"La Ajutante",
    "gn:country_code":"BR",
    "gn:dem":10,
    "gn:feature_class":"P",
    "gn:feature_code":"PPL",
    "gn:name":"La Ajutante",
    "gn:population":0,
    "gn:timezone":"America/Santarem",
    "iso:country":"BR",
    "name:por_x_preferred":[
        "La Ajutante"
    ],
    "wof:name":"La Ajutante",
    "wof:placetype":"locality"
},
  "geometry": {"coordinates":[-56.38984,-1.44358],"type":"Point"}
}