{
  "type": "Feature",
  "properties": {
    "gn:admin1_code":"18",
    "gn:admin2_code":"4113205.0",
    "gn:asciiname":"Sitio Ohrains Petrus",
    "gn:country_code":"BR",
    "gn:dem":852,
    "gn:feature_class":"P",
    "gn:feature_code":"PPL",
    "gn:name":"S\u00edtio Ohrains Petrus",
    "gn:population":0,
    "gn:timezone":"America/Sao_Paulo",
    "iso:country":"BR",
    "name:por_x_preferred":[
        "S\u00edtio Ohrains Petrus"
    ],
    "wof:name":"Sitio Ohrains Petrus",
    "wof:placetype":"locality"
},
  "geometry": {"coordinates":[-49.72278,-25.78861],"type":"Point"}
}