{
  "type": "Feature",
  "properties": {
    "gn:admin1_code":"20",
    "gn:admin2_code":"2211308.0",
    "gn:asciiname":"Alivio",
    "gn:country_code":"BR",
    "gn:dem":165,
    "gn:feature_class":"P",
    "gn:feature_code":"PPL",
    "gn:name":"Alivio",
    "gn:population":0,
    "gn:timezone":"America/Fortaleza",
    "iso:country":"BR",
    "wof:name":"Alivio",
    "wof:placetype":"locality"
},
  "geometry": {"coordinates":[-41.95,-6.23333],"type":"Point"}
}