{
  "type": "Feature",
  "properties": {
    "gn:admin1_code":"18.0",
    "gn:admin2_code":"4116901.0",
    "gn:asciiname":"Bela Vista",
    "gn:country_code":"BR",
    "gn:dem":574,
    "gn:feature_class":"P",
    "gn:feature_code":"PPL",
    "gn:name":"Bela Vista",
    "gn:population":0,
    "gn:timezone":"America/Sao_Paulo",
    "iso:country":"BR",
    "name:por_x_preferred":[
        "Bela Vista"
    ],
    "wof:name":"Bela Vista",
    "wof:placetype":"locality"
},
  "geometry": {"coordinates":[-52.23156,-23.21559],"type":"Point"}
}