{
  "type": "Feature",
  "properties": {
    "gn:admin1_code":"15",
    "gn:admin2_code":"3136009.0",
    "gn:asciiname":"Baixa Seca",
    "gn:country_code":"BR",
    "gn:dem":716,
    "gn:feature_class":"P",
    "gn:feature_code":"PPL",
    "gn:name":"Baixa S\u00eaca",
    "gn:population":0,
    "gn:timezone":"America/Sao_Paulo",
    "iso:country":"BR",
    "name:por_x_preferred":[
        "Baixa S\u00eaca"
    ],
    "wof:name":"Baixa Seca",
    "wof:placetype":"locality"
},
  "geometry": {"coordinates":[-40.76667,-16.73333],"type":"Point"}
}