{
  "type": "Feature",
  "properties": {
    "gn:admin1_code":"17",
    "gn:admin2_code":"2515203.0",
    "gn:asciiname":"Lagoa da Legua",
    "gn:country_code":"BR",
    "gn:dem":640,
    "gn:feature_class":"P",
    "gn:feature_code":"PPL",
    "gn:name":"Lagoa da L\u00e9gua",
    "gn:population":0,
    "gn:timezone":"America/Fortaleza",
    "iso:country":"BR",
    "wof:name":"Lagoa da Legua",
    "wof:placetype":"locality"
},
  "geometry": {"coordinates":[-37.06667,-8.13333],"type":"Point"}
}