{
  "type": "Feature",
  "properties": {
    "gn:admin1_code":"30",
    "gn:admin2_code":"2607406.0",
    "gn:asciiname":"Jatina",
    "gn:country_code":"BR",
    "gn:dem":302,
    "gn:feature_class":"P",
    "gn:feature_code":"PPL",
    "gn:name":"Jatin\u00e3",
    "gn:population":0,
    "gn:timezone":"America/Bahia",
    "iso:country":"BR",
    "wof:name":"Jatina",
    "wof:placetype":"locality"
},
  "geometry": {"coordinates":[-38.81667,-8.78333],"type":"Point"}
}