{
  "type": "Feature",
  "properties": {
    "gn:admin1_code":"18.0",
    "gn:admin2_code":"4102406.0",
    "gn:asciiname":"Sitio Sertaozinho",
    "gn:country_code":"BR",
    "gn:dem":445,
    "gn:feature_class":"P",
    "gn:feature_code":"PPL",
    "gn:name":"S\u00edtio Sert\u00e3ozinho",
    "gn:population":0,
    "gn:timezone":"America/Sao_Paulo",
    "iso:country":"BR",
    "name:por_x_preferred":[
        "S\u00edtio Sert\u00e3ozinho"
    ],
    "wof:name":"Sitio Sertaozinho",
    "wof:placetype":"locality"
},
  "geometry": {"coordinates":[-50.2462,-23.1647],"type":"Point"}
}