{
  "type": "Feature",
  "properties": {
    "gn:admin1_code":"23",
    "gn:admin2_code":"4321477.0",
    "gn:asciiname":"Caa-Guacu",
    "gn:country_code":"BR",
    "gn:dem":120,
    "gn:feature_class":"P",
    "gn:feature_code":"PPL",
    "gn:name":"Caa-Gua\u00e7u",
    "gn:population":0,
    "gn:timezone":"America/Sao_Paulo",
    "iso:country":"BR",
    "wof:name":"Caa-Guacu",
    "wof:placetype":"locality"
},
  "geometry": {"coordinates":[-54.21666999999999,-27.38333],"type":"Point"}
}