{
  "type": "Feature",
  "properties": {
    "gn:admin1_code":"20",
    "gn:admin2_code":"2205508.0",
    "gn:asciiname":"Aprazivel",
    "gn:country_code":"BR",
    "gn:dem":106,
    "gn:feature_class":"P",
    "gn:feature_code":"PPL",
    "gn:name":"Apraz\u00edvel",
    "gn:population":0,
    "gn:timezone":"America/Fortaleza",
    "iso:country":"BR",
    "wof:name":"Aprazivel",
    "wof:placetype":"locality"
},
  "geometry": {"coordinates":[-42.71667,-4.83333],"type":"Point"}
}