{
  "type": "Feature",
  "properties": {
    "gn:admin1_code":"15",
    "gn:admin2_code":"3169208.0",
    "gn:asciiname":"Sertao",
    "gn:country_code":"BR",
    "gn:dem":872,
    "gn:feature_class":"P",
    "gn:feature_code":"PPL",
    "gn:name":"Sert\u00e3o",
    "gn:population":0,
    "gn:timezone":"America/Sao_Paulo",
    "iso:country":"BR",
    "name:por_x_preferred":[
        "Sert\u00e3o"
    ],
    "wof:name":"Sertao",
    "wof:placetype":"locality"
},
  "geometry": {"coordinates":[-42.13333,-20.85],"type":"Point"}
}