{
  "type": "Feature",
  "properties": {
    "gn:admin1_code":"20",
    "gn:admin2_code":"2210409.0",
    "gn:asciiname":"Marrecas",
    "gn:country_code":"BR",
    "gn:dem":169,
    "gn:feature_class":"P",
    "gn:feature_code":"PPL",
    "gn:name":"Marrecas",
    "gn:population":0,
    "gn:timezone":"America/Fortaleza",
    "iso:country":"BR",
    "wof:name":"Marrecas",
    "wof:placetype":"locality"
},
  "geometry": {"coordinates":[-41.74876,-5.64171],"type":"Point"}
}