{
  "type": "Feature",
  "properties": {
    "gn:admin1_code":"27.0",
    "gn:admin2_code":"3516408.0",
    "gn:asciiname":"Bairro dos Valos",
    "gn:country_code":"BR",
    "gn:dem":852,
    "gn:feature_class":"P",
    "gn:feature_code":"PPL",
    "gn:name":"Bairro dos Valos",
    "gn:population":0,
    "gn:timezone":"America/Sao_Paulo",
    "iso:country":"BR",
    "name:por_x_preferred":[
        "Bairro dos Valos"
    ],
    "wof:name":"Bairro dos Valos",
    "wof:placetype":"locality"
},
  "geometry": {"coordinates":[-46.66615,-23.30081],"type":"Point"}
}