{
  "type": "Feature",
  "properties": {
    "gn:admin1_code":"17",
    "gn:admin2_code":"2501708.0",
    "gn:asciiname":"Pedra Alta",
    "gn:country_code":"BR",
    "gn:dem":522,
    "gn:feature_class":"P",
    "gn:feature_code":"PPL",
    "gn:name":"Pedra Alta",
    "gn:population":0,
    "gn:timezone":"America/Fortaleza",
    "iso:country":"BR",
    "wof:name":"Pedra Alta",
    "wof:placetype":"locality"
},
  "geometry": {"coordinates":[-36.26667,-7.76667],"type":"Point"}
}