{
  "type": "Feature",
  "properties": {
    "gn:admin1_code":"27",
    "gn:admin2_code":"3524600.0",
    "gn:asciiname":"Guararema",
    "gn:country_code":"BR",
    "gn:dem":43,
    "gn:feature_class":"P",
    "gn:feature_code":"PPLL",
    "gn:name":"Guararema",
    "gn:population":0,
    "gn:timezone":"America/Sao_Paulo",
    "iso:country":"BR",
    "name:bpy_x_preferred":[
        "\u0997\u09c1\u09f1\u09be\u09b0\u09be\u09b0\u09c7\u09ae\u09be"
    ],
    "name:ceb_x_preferred":[
        "Guararema"
    ],
    "name:deu_x_preferred":[
        "Guararema"
    ],
    "name:epo_x_preferred":[
        "Guararema"
    ],
    "name:eus_x_preferred":[
        "Guararema"
    ],
    "name:fra_x_preferred":[
        "Guararema"
    ],
    "name:ita_x_preferred":[
        "Guararema"
    ],
    "name:kaz_x_preferred":[
        "\u0413\u0443\u0430\u0440\u0430\u0440\u0435\u043c\u0430"
    ],
    "name:mlg_x_preferred":[
        "Guararema"
    ],
    "name:nld_x_preferred":[
        "Guararema"
    ],
    "name:nor_x_preferred":[
        "Guararema"
    ],
    "name:pol_x_preferred":[
        "Guararema"
    ],
    "name:por_x_preferred":[
        "Guararema"
    ],
    "name:ron_x_preferred":[
        "Guararema"
    ],
    "name:rus_x_preferred":[
        "\u0413\u0443\u0430\u0440\u0430\u0440\u0435\u043c\u0430"
    ],
    "name:swe_x_preferred":[
        "Guararema"
    ],
    "name:vie_x_preferred":[
        "Guararema"
    ],
    "name:vol_x_preferred":[
        "Guararema"
    ],
    "name:war_x_preferred":[
        "Guararema"
    ],
    "name:zho_x_preferred":[
        "\u74dc\u62c9\u96f7\u9a6c"
    ],
    "wof:name":"Guararema",
    "wof:placetype":"locality"
},
  "geometry": {"coordinates":[-48.03038,-24.71674],"type":"Point"}
}