{
  "type": "Feature",
  "properties": {
    "gn:admin1_code":"27.0",
    "gn:admin2_code":"3545308.0",
    "gn:asciiname":"Barra",
    "gn:country_code":"BR",
    "gn:dem":604,
    "gn:feature_class":"P",
    "gn:feature_code":"PPLL",
    "gn:name":"Barra",
    "gn:population":0,
    "gn:timezone":"America/Sao_Paulo",
    "iso:country":"BR",
    "name:por_x_preferred":[
        "Barra"
    ],
    "wof:name":"Barra",
    "wof:placetype":"locality"
},
  "geometry": {"coordinates":[-47.67678,-23.63546],"type":"Point"}
}