{
  "type": "Feature",
  "properties": {
    "gn:admin1_code":"13",
    "gn:admin2_code":"2107803.0",
    "gn:asciiname":"Quiquara",
    "gn:country_code":"BR",
    "gn:dem":226,
    "gn:feature_class":"P",
    "gn:feature_code":"PPL",
    "gn:name":"Quiquara",
    "gn:population":0,
    "gn:timezone":"America/Fortaleza",
    "iso:country":"BR",
    "wof:name":"Quiquara",
    "wof:placetype":"locality"
},
  "geometry": {"coordinates":[-43.41667,-5.88333],"type":"Point"}
}