{
  "type": "Feature",
  "properties": {
    "gn:admin1_code":"18",
    "gn:admin2_code":"4120903.0",
    "gn:asciiname":"Fazendinha",
    "gn:country_code":"BR",
    "gn:dem":586,
    "gn:feature_class":"P",
    "gn:feature_code":"PPL",
    "gn:name":"Fazendinha",
    "gn:population":0,
    "gn:timezone":"America/Sao_Paulo",
    "iso:country":"BR",
    "wof:name":"Fazendinha",
    "wof:placetype":"locality"
},
  "geometry": {"coordinates":[-53.01667,-25.43333],"type":"Point"}
}