{
  "type": "Feature",
  "properties": {
    "gn:admin1_code":"02",
    "gn:admin2_code":"2701001.0",
    "gn:asciiname":"Sao Jose",
    "gn:country_code":"BR",
    "gn:dem":166,
    "gn:feature_class":"P",
    "gn:feature_code":"PPL",
    "gn:name":"S\u00e3o Jos\u00e9",
    "gn:population":0,
    "gn:timezone":"America/Maceio",
    "iso:country":"BR",
    "wof:name":"Sao Jose",
    "wof:placetype":"locality"
},
  "geometry": {"coordinates":[-36.16667,-9.65],"type":"Point"}
}