{
  "type": "Feature",
  "properties": {
    "gn:admin1_code":"18.0",
    "gn:admin2_code":"4100202.0",
    "gn:asciiname":"Area Residencial da Mineracao Plumbum",
    "gn:country_code":"BR",
    "gn:dem":156,
    "gn:feature_class":"P",
    "gn:feature_code":"PPL",
    "gn:name":"\u00c1rea Residencial da Minera\u00e7\u00e3o Plumbum",
    "gn:population":0,
    "gn:timezone":"America/Sao_Paulo",
    "iso:country":"BR",
    "name:por_x_preferred":[
        "\u00c1rea Residencial da Minera\u00e7\u00e3o Plumbum"
    ],
    "name:por_x_variant":[
        "Panelas de Br\u00e9jauva"
    ],
    "wof:name":"Area Residencial da Mineracao Plumbum",
    "wof:placetype":"locality"
},
  "geometry": {"coordinates":[-48.91998,-24.67934],"type":"Point"}
}