{
  "type": "Feature",
  "properties": {
    "gn:admin1_code":"13",
    "gn:admin2_code":"2103208.0",
    "gn:asciiname":"Caldeirao de Cima",
    "gn:country_code":"BR",
    "gn:dem":71,
    "gn:feature_class":"P",
    "gn:feature_code":"PPL",
    "gn:name":"Caldeir\u00e3o de Cima",
    "gn:population":0,
    "gn:timezone":"America/Fortaleza",
    "iso:country":"BR",
    "wof:name":"Caldeirao de Cima",
    "wof:placetype":"locality"
},
  "geometry": {"coordinates":[-43.36472,-3.96222],"type":"Point"}
}