{
  "type": "Feature",
  "properties": {
    "gn:admin1_code":"14",
    "gn:admin2_code":"5100508.0",
    "gn:asciiname":"Lavouras",
    "gn:country_code":"BR",
    "gn:dem":357,
    "gn:feature_class":"P",
    "gn:feature_code":"PPLL",
    "gn:name":"Lavouras",
    "gn:population":0,
    "gn:timezone":"America/Cuiaba",
    "iso:country":"BR",
    "wof:name":"Lavouras",
    "wof:placetype":"locality"
},
  "geometry": {"coordinates":[-56.59917,-14.83611],"type":"Point"}
}