{
  "type": "Feature",
  "properties": {
    "gn:admin1_code":"13",
    "gn:admin2_code":"2103208.0",
    "gn:asciiname":"Pocao",
    "gn:country_code":"BR",
    "gn:dem":39,
    "gn:feature_class":"P",
    "gn:feature_code":"PPL",
    "gn:name":"Po\u00e7\u00e3o",
    "gn:population":0,
    "gn:timezone":"America/Fortaleza",
    "iso:country":"BR",
    "wof:name":"Pocao",
    "wof:placetype":"locality"
},
  "geometry": {"coordinates":[-43.3225,-3.85167],"type":"Point"}
}