{
  "type": "Feature",
  "properties": {
    "gn:admin1_code":"18.0",
    "gn:admin2_code":"4111704.0",
    "gn:asciiname":"Sitio Luciano",
    "gn:country_code":"BR",
    "gn:dem":512,
    "gn:feature_class":"P",
    "gn:feature_code":"PPL",
    "gn:name":"S\u00edtio Luciano",
    "gn:population":0,
    "gn:timezone":"America/Sao_Paulo",
    "iso:country":"BR",
    "name:por_x_preferred":[
        "S\u00edtio Luciano"
    ],
    "wof:name":"Sitio Luciano",
    "wof:placetype":"locality"
},
  "geometry": {"coordinates":[-50.04843,-23.71899],"type":"Point"}
}