{
  "type": "Feature",
  "properties": {
    "gn:admin1_code":"18.0",
    "gn:admin2_code":"4113205.0",
    "gn:asciiname":"Sitio Tadeu Opelenki",
    "gn:country_code":"BR",
    "gn:dem":878,
    "gn:feature_class":"P",
    "gn:feature_code":"PPL",
    "gn:name":"S\u00edtio Tadeu Opelenki",
    "gn:population":0,
    "gn:timezone":"America/Sao_Paulo",
    "iso:country":"BR",
    "name:por_x_preferred":[
        "S\u00edtio Tadeu Opelenki"
    ],
    "wof:name":"Sitio Tadeu Opelenki",
    "wof:placetype":"locality"
},
  "geometry": {"coordinates":[-49.5503,-25.8116],"type":"Point"}
}