{
  "type": "Feature",
  "properties": {
    "gn:admin1_code":"14",
    "gn:admin2_code":"5106224.0",
    "gn:asciiname":"Porto Esperanca",
    "gn:country_code":"BR",
    "gn:dem":325,
    "gn:feature_class":"P",
    "gn:feature_code":"PPL",
    "gn:name":"Porto Esperan\u00e7a",
    "gn:population":0,
    "gn:timezone":"America/Cuiaba",
    "iso:country":"BR",
    "name:por_x_preferred":[
        "Porto Esperan\u00e7a"
    ],
    "wof:name":"Porto Esperanca",
    "wof:placetype":"locality"
},
  "geometry": {"coordinates":[-56.09786999999999,-14.14616],"type":"Point"}
}