{
  "type": "Feature",
  "properties": {
    "gn:admin1_code":"5.0",
    "gn:admin2_code":"2924405.0",
    "gn:asciiname":"Duas Veredas",
    "gn:country_code":"BR",
    "gn:dem":490,
    "gn:feature_class":"P",
    "gn:feature_code":"PPL",
    "gn:name":"Duas Veredas",
    "gn:population":0,
    "gn:timezone":"America/Bahia",
    "iso:country":"BR",
    "name:por_x_preferred":[
        "Duas Veredas"
    ],
    "wof:name":"Duas Veredas",
    "wof:placetype":"locality"
},
  "geometry": {"coordinates":[-43.67874000000001,-10.14276],"type":"Point"}
}