{
  "type": "Feature",
  "properties": {
    "gn:admin1_code":"8",
    "gn:admin2_code":"3201407.0",
    "gn:asciiname":"Povoacao",
    "gn:country_code":"BR",
    "gn:dem":573,
    "gn:feature_class":"P",
    "gn:feature_code":"PPL",
    "gn:name":"Povoa\u00e7\u00e3o",
    "gn:population":0,
    "gn:timezone":"America/Sao_Paulo",
    "iso:country":"BR",
    "name:por_x_preferred":[
        "Povoa\u00e7\u00e3o"
    ],
    "wof:name":"Povoacao",
    "wof:placetype":"locality"
},
  "geometry": {"coordinates":[-41.16667,-20.46667],"type":"Point"}
}