{
  "type": "Feature",
  "properties": {
    "iso:country":"BR",
    "qs_pg:aaroncc":"BR",
    "qs_pg:name":"Ta\u00edba",
    "qs_pg:name_adm0":"Brasil",
    "qs_pg:name_adm1":"Cear\u00e1",
    "qs_pg:photos":719,
    "qs_pg:photos_1k":146,
    "qs_pg:photos_9k":3,
    "qs_pg:photos_9r":5,
    "qs_pg:photos_all":719,
    "qs_pg:photos_sr":8,
    "qs_pg:pop_sr":0,
    "qs_pg:qs_pg_placetype":"locality",
    "qs_pg:qs_pg_placetype_gp":"Town",
    "qs_pg:woe_adm0":23424768,
    "woe:adm0_id":23424768,
    "woe:name_adm0":"Brasil",
    "woe:name_adm1":"Cear\u00e1",
    "woe:placetype":"Town",
    "wof:name":"Ta\u00edba",
    "wof:placetype":"locality"
},
  "geometry": {"coordinates":[-38.910592,-3.504206],"type":"Point"}
}