{
  "type": "Feature",
  "properties": {
    "gn:admin1_code":"26",
    "gn:admin2_code":"4212809.0",
    "gn:asciiname":"Camping das Palmeiras",
    "gn:country_code":"BR",
    "gn:dem":12,
    "gn:feature_class":"P",
    "gn:feature_code":"PPL",
    "gn:name":"Camping das Palmeiras",
    "gn:population":0,
    "gn:timezone":"America/Sao_Paulo",
    "iso:country":"BR",
    "name:por_x_preferred":[
        "Camping das Palmeiras"
    ],
    "wof:name":"Camping das Palmeiras",
    "wof:placetype":"locality"
},
  "geometry": {"coordinates":[-48.6834,-26.7206],"type":"Point"}
}