{
  "type": "Feature",
  "properties": {
    "gn:admin1_code":"03",
    "gn:admin2_code":"1600303.0",
    "gn:asciiname":"Manauara",
    "gn:country_code":"BR",
    "gn:dem":13,
    "gn:feature_class":"P",
    "gn:feature_code":"PPL",
    "gn:name":"Manauara",
    "gn:population":0,
    "gn:timezone":"America/Belem",
    "iso:country":"BR",
    "wof:name":"Manauara",
    "wof:placetype":"locality"
},
  "geometry": {"coordinates":[-51.16667,0.28333],"type":"Point"}
}