{
  "type": "Feature",
  "properties": {
    "gn:admin1_code":"17",
    "gn:admin2_code":"2513968.0",
    "gn:asciiname":"Sao Domingos",
    "gn:country_code":"BR",
    "gn:dem":190,
    "gn:feature_class":"P",
    "gn:feature_code":"PPL",
    "gn:name":"S\u00e3o Domingos",
    "gn:population":0,
    "gn:timezone":"America/Fortaleza",
    "iso:country":"BR",
    "name:und_x_variant":[
        "S\u00e3o Domingos"
    ],
    "wof:name":"Sao Domingos",
    "wof:placetype":"locality"
},
  "geometry": {"coordinates":[-37.93333,-6.81667],"type":"Point"}
}