{
  "type": "Feature",
  "properties": {
    "gn:admin1_code":"18.0",
    "gn:admin2_code":"4124103.0",
    "gn:asciiname":"Sitio Clarice Pereira Botta",
    "gn:country_code":"BR",
    "gn:dem":410,
    "gn:feature_class":"P",
    "gn:feature_code":"PPL",
    "gn:name":"S\u00edtio Clarice Pereira Botta",
    "gn:population":0,
    "gn:timezone":"America/Sao_Paulo",
    "iso:country":"BR",
    "name:por_x_preferred":[
        "S\u00edtio Clarice Pereira Botta"
    ],
    "wof:name":"Sitio Clarice Pereira Botta",
    "wof:placetype":"locality"
},
  "geometry": {"coordinates":[-50.2208,-23.1958],"type":"Point"}
}