{
  "type": "Feature",
  "properties": {
    "gn:admin1_code":"30",
    "gn:admin2_code":"2612604.0",
    "gn:asciiname":"Novolino",
    "gn:cc2":"BR",
    "gn:country_code":"BR",
    "gn:dem":353,
    "gn:feature_class":"P",
    "gn:feature_code":"PPL",
    "gn:name":"Novolino",
    "gn:population":0,
    "gn:timezone":"America/Recife",
    "iso:country":"BR",
    "name:und_x_variant":[
        "Nova Olinda",
        "Novolino"
    ],
    "wof:name":"Novolino",
    "wof:placetype":"locality"
},
  "geometry": {"coordinates":[-39.91667,-8.83333],"type":"Point"}
}