{
  "type": "Feature",
  "properties": {
    "gn:admin1_code":"18.0",
    "gn:admin2_code":"4100202.0",
    "gn:asciiname":"Bairro Tres Canais",
    "gn:country_code":"BR",
    "gn:dem":213,
    "gn:feature_class":"P",
    "gn:feature_code":"PPLL",
    "gn:name":"Bairro Tr\u00eas Canais",
    "gn:population":0,
    "gn:timezone":"America/Sao_Paulo",
    "iso:country":"BR",
    "name:por_x_preferred":[
        "Bairro Tr\u00eas Canais"
    ],
    "wof:name":"Bairro Tres Canais",
    "wof:placetype":"locality"
},
  "geometry": {"coordinates":[-48.572,-24.8213],"type":"Point"}
}