{
  "type": "Feature",
  "properties": {
    "gn:admin1_code":"18.0",
    "gn:admin2_code":"4113205.0",
    "gn:asciiname":"Barra dos Melos",
    "gn:country_code":"BR",
    "gn:dem":790,
    "gn:feature_class":"P",
    "gn:feature_code":"PPL",
    "gn:name":"Barra dos Melos",
    "gn:population":0,
    "gn:timezone":"America/Sao_Paulo",
    "iso:country":"BR",
    "name:por_x_preferred":[
        "Barra dos Melos"
    ],
    "wof:name":"Barra dos Melos",
    "wof:placetype":"locality"
},
  "geometry": {"coordinates":[-49.9061,-25.9582],"type":"Point"}
}