{
  "type": "Feature",
  "properties": {
    "gn:admin1_code":"27.0",
    "gn:admin2_code":"3502903.0",
    "gn:asciiname":"Jundiaquara",
    "gn:country_code":"BR",
    "gn:dem":658,
    "gn:feature_class":"P",
    "gn:feature_code":"PPL",
    "gn:name":"Jundiaquara",
    "gn:population":0,
    "gn:timezone":"America/Sao_Paulo",
    "iso:country":"BR",
    "name:por_x_preferred":[
        "Jundiaquara"
    ],
    "wof:name":"Jundiaquara",
    "wof:placetype":"locality"
},
  "geometry": {"coordinates":[-47.607,-23.5739],"type":"Point"}
}