{
  "type": "Feature",
  "properties": {
    "gn:admin1_code":"5",
    "gn:admin2_code":"2918001.0",
    "gn:asciiname":"Salgado",
    "gn:country_code":"BR",
    "gn:dem":454,
    "gn:feature_class":"P",
    "gn:feature_code":"PPL",
    "gn:name":"Salgado",
    "gn:population":0,
    "gn:timezone":"America/Bahia",
    "iso:country":"BR",
    "wof:name":"Salgado",
    "wof:placetype":"locality"
},
  "geometry": {"coordinates":[-40.18333,-13.95],"type":"Point"}
}