{
  "type": "Feature",
  "properties": {
    "gn:admin1_code":"22",
    "gn:admin2_code":"2414407.0",
    "gn:asciiname":"Sao Izidio",
    "gn:country_code":"BR",
    "gn:dem":97,
    "gn:feature_class":"P",
    "gn:feature_code":"PPL",
    "gn:name":"S\u00e3o Iz\u00eddio",
    "gn:population":0,
    "gn:timezone":"America/Fortaleza",
    "iso:country":"BR",
    "wof:name":"Sao Izidio",
    "wof:placetype":"locality"
},
  "geometry": {"coordinates":[-35.83333,-5.25],"type":"Point"}
}