{
  "type": "Feature",
  "properties": {
    "gn:admin1_code":"14",
    "gn:admin2_code":"5105200.0",
    "gn:asciiname":"Jorge Cury",
    "gn:country_code":"BR",
    "gn:dem":287,
    "gn:feature_class":"P",
    "gn:feature_code":"PPL",
    "gn:name":"Jorge Cury",
    "gn:population":0,
    "gn:timezone":"America/Cuiaba",
    "iso:country":"BR",
    "name:por_x_preferred":[
        "Jorge Cury"
    ],
    "wof:name":"Jorge Cury",
    "wof:placetype":"locality"
},
  "geometry": {"coordinates":[-54.95,-16.28333],"type":"Point"}
}