{
  "type": "Feature",
  "properties": {
    "gn:admin1_code":"06",
    "gn:admin2_code":"2313500.0",
    "gn:asciiname":"Cacimbas",
    "gn:country_code":"BR",
    "gn:dem":73,
    "gn:feature_class":"P",
    "gn:feature_code":"PPL",
    "gn:name":"Cacimbas",
    "gn:population":0,
    "gn:timezone":"America/Fortaleza",
    "iso:country":"BR",
    "wof:name":"Cacimbas",
    "wof:placetype":"locality"
},
  "geometry": {"coordinates":[-39.36667,-3.46667],"type":"Point"}
}