{
  "type": "Feature",
  "properties": {
    "gn:admin1_code":"13",
    "gn:admin2_code":"2110104.0",
    "gn:asciiname":"Guaribas II",
    "gn:country_code":"BR",
    "gn:dem":52,
    "gn:feature_class":"P",
    "gn:feature_code":"PPL",
    "gn:name":"Guaribas II",
    "gn:population":0,
    "gn:timezone":"America/Fortaleza",
    "iso:country":"BR",
    "wof:name":"Guaribas II",
    "wof:placetype":"locality"
},
  "geometry": {"coordinates":[-43.21194000000001,-3.14889],"type":"Point"}
}