{
  "type": "Feature",
  "properties": {
    "gn:admin1_code":"27.0",
    "gn:admin2_code":"3528502.0",
    "gn:asciiname":"Sitio Santa Adelia",
    "gn:country_code":"BR",
    "gn:dem":804,
    "gn:feature_class":"P",
    "gn:feature_code":"PPL",
    "gn:name":"S\u00edtio Santa Adelia",
    "gn:population":0,
    "gn:timezone":"America/Sao_Paulo",
    "iso:country":"BR",
    "name:por_x_preferred":[
        "S\u00edtio Santa Adelia"
    ],
    "wof:name":"Sitio Santa Adelia",
    "wof:placetype":"locality"
},
  "geometry": {"coordinates":[-46.64494000000001,-23.34677000000001],"type":"Point"}
}