{
  "type": "Feature",
  "properties": {
    "gn:admin1_code":"7",
    "gn:admin2_code":"5300108.0",
    "gn:asciiname":"Bom Sucesso",
    "gn:country_code":"BR",
    "gn:dem":1038,
    "gn:feature_class":"P",
    "gn:feature_code":"PPL",
    "gn:name":"Bom Sucesso",
    "gn:population":0,
    "gn:timezone":"America/Sao_Paulo",
    "iso:country":"BR",
    "wof:name":"Bom Sucesso",
    "wof:placetype":"locality"
},
  "geometry": {"coordinates":[-47.63333,-15.51667],"type":"Point"}
}