{
  "type": "Feature",
  "properties": {
    "gn:admin1_code":"7",
    "gn:admin2_code":"5300108.0",
    "gn:asciiname":"Bom Sucesso",
    "gn:country_code":"BR",
    "gn:dem":1038,
    "gn:feature_class":"P",
    "gn:feature_code":"PPL",
    "gn:name":"Bom Sucesso",
    "gn:population":0,
    "gn:timezone":"America/Sao_Paulo",
    "iso:country":"BR",
    "name:bpy_x_preferred":[
        "\u09ac\u09cb\u09ae \u09b8\u0989\u09b8\u09c7\u09b8\u09b8\u09cb"
    ],
    "name:ceb_x_preferred":[
        "Bom Sucesso"
    ],
    "name:deu_x_preferred":[
        "Bom Sucesso"
    ],
    "name:fra_x_preferred":[
        "Bom Sucesso"
    ],
    "name:ita_x_preferred":[
        "Bom Sucesso"
    ],
    "name:nld_x_preferred":[
        "Bom Sucesso"
    ],
    "name:nor_x_preferred":[
        "Bom Sucesso"
    ],
    "name:por_x_preferred":[
        "Bom Sucesso"
    ],
    "name:swe_x_preferred":[
        "Bom Sucesso"
    ],
    "name:vol_x_preferred":[
        "Bom Sucesso"
    ],
    "wof:name":"Bom Sucesso",
    "wof:placetype":"locality"
},
  "geometry": {"coordinates":[-47.63333,-15.51667],"type":"Point"}
}