{
  "type": "Feature",
  "properties": {
    "gn:admin1_code":"06",
    "gn:admin2_code":"2306553.0",
    "gn:asciiname":"Fazenda Cajueiro Grande",
    "gn:country_code":"BR",
    "gn:dem":37,
    "gn:feature_class":"P",
    "gn:feature_code":"PPL",
    "gn:name":"Fazenda Cajueiro Grande",
    "gn:population":0,
    "gn:timezone":"America/Fortaleza",
    "iso:country":"BR",
    "wof:name":"Fazenda Cajueiro Grande",
    "wof:placetype":"locality"
},
  "geometry": {"coordinates":[-39.95,-3.15],"type":"Point"}
}