{
  "type": "Feature",
  "properties": {
    "gn:admin1_code":"11",
    "gn:admin2_code":"5006200.0",
    "gn:asciiname":"Octaviano Fonseca",
    "gn:cc2":"BR",
    "gn:country_code":"BR",
    "gn:dem":312,
    "gn:feature_class":"P",
    "gn:feature_code":"PPL",
    "gn:name":"Octaviano Fonseca",
    "gn:population":0,
    "gn:timezone":"America/Campo_Grande",
    "iso:country":"BR",
    "name:und_x_variant":[
        "Fonc\u00eaca",
        "Octaviano Fonseca"
    ],
    "wof:name":"Octaviano Fonseca",
    "wof:placetype":"locality"
},
  "geometry": {"coordinates":[-53.46666999999999,-21.88333],"type":"Point"}
}