{
  "type": "Feature",
  "properties": {
    "gn:admin1_code":"27",
    "gn:admin2_code":"3504107.0",
    "gn:asciiname":"Sitio Santo Antonio de Padua",
    "gn:country_code":"BR",
    "gn:dem":778,
    "gn:feature_class":"P",
    "gn:feature_code":"PPL",
    "gn:name":"S\u00edtio Santo Ant\u00f4nio de P\u00e1dua",
    "gn:population":0,
    "gn:timezone":"America/Sao_Paulo",
    "iso:country":"BR",
    "name:por_x_preferred":[
        "S\u00edtio Santo Ant\u00f4nio de P\u00e1dua"
    ],
    "wof:name":"Sitio Santo Antonio de Padua",
    "wof:placetype":"locality"
},
  "geometry": {"coordinates":[-46.51167,-23.06278],"type":"Point"}
}