{
  "type": "Feature",
  "properties": {
    "gn:admin1_code":"18",
    "gn:admin2_code":"4113205.0",
    "gn:asciiname":"Sitio Teodoro Lipski",
    "gn:country_code":"BR",
    "gn:dem":906,
    "gn:feature_class":"P",
    "gn:feature_code":"PPL",
    "gn:name":"S\u00edtio Teodoro Lipski",
    "gn:population":0,
    "gn:timezone":"America/Sao_Paulo",
    "iso:country":"BR",
    "name:por_x_preferred":[
        "S\u00edtio Teodoro Lipski"
    ],
    "wof:name":"Sitio Teodoro Lipski",
    "wof:placetype":"locality"
},
  "geometry": {"coordinates":[-49.74444,-25.795],"type":"Point"}
}