{
  "type": "Feature",
  "properties": {
    "gn:admin1_code":"20",
    "gn:admin2_code":"2207504.0",
    "gn:asciiname":"Cafundo",
    "gn:country_code":"BR",
    "gn:dem":126,
    "gn:feature_class":"P",
    "gn:feature_code":"PPL",
    "gn:name":"Cafundo",
    "gn:population":0,
    "gn:timezone":"America/Fortaleza",
    "iso:country":"BR",
    "wof:name":"Cafundo",
    "wof:placetype":"locality"
},
  "geometry": {"coordinates":[-43.01667,-5.85],"type":"Point"}
}