{
  "type": "Feature",
  "properties": {
    "gn:admin1_code":"06",
    "gn:admin2_code":"2308708.0",
    "gn:asciiname":"Tapera (1)",
    "gn:country_code":"BR",
    "gn:dem":53,
    "gn:feature_class":"P",
    "gn:feature_code":"PPL",
    "gn:name":"Tapera (1)",
    "gn:population":0,
    "gn:timezone":"America/Fortaleza",
    "iso:country":"BR",
    "wof:name":"Tapera (1)",
    "wof:placetype":"locality"
},
  "geometry": {"coordinates":[-38.51667,-5.13333],"type":"Point"}
}