{
  "type": "Feature",
  "properties": {
    "gn:admin1_code":"23",
    "gn:admin2_code":"4310603.0",
    "gn:asciiname":"Charqueada",
    "gn:cc2":"BR",
    "gn:country_code":"BR",
    "gn:dem":76,
    "gn:feature_class":"P",
    "gn:feature_code":"PPL",
    "gn:name":"Charqueada",
    "gn:population":0,
    "gn:timezone":"America/Sao_Paulo",
    "iso:country":"BR",
    "name:bpy_x_preferred":[
        "\u099a\u09be\u09b0\u09cd\u0995\u09c1\u09af\u09bc\u09c7\u0986\u09a1\u09be"
    ],
    "name:ceb_x_preferred":[
        "Charqueada"
    ],
    "name:deu_x_preferred":[
        "Charqueada"
    ],
    "name:epo_x_preferred":[
        "Charqueada"
    ],
    "name:eus_x_preferred":[
        "Charqueada"
    ],
    "name:fra_x_preferred":[
        "Charqueada"
    ],
    "name:ita_x_preferred":[
        "Charqueada"
    ],
    "name:kaz_x_preferred":[
        "\u0428\u0430\u0440\u043a\u0435\u0430\u0434\u0430"
    ],
    "name:mlg_x_preferred":[
        "Charqueada"
    ],
    "name:nld_x_preferred":[
        "Charqueada"
    ],
    "name:nor_x_preferred":[
        "Charqueada"
    ],
    "name:pol_x_preferred":[
        "Charqueada"
    ],
    "name:por_x_preferred":[
        "Charqueada"
    ],
    "name:ron_x_preferred":[
        "Charqueada"
    ],
    "name:rus_x_preferred":[
        "\u0428\u0430\u0440\u043a\u0435\u0430\u0434\u0430"
    ],
    "name:spa_x_preferred":[
        "Charqueada"
    ],
    "name:swe_x_preferred":[
        "Charqueada"
    ],
    "name:und_x_variant":[
        "Xarqueada"
    ],
    "name:vie_x_preferred":[
        "Charqueada"
    ],
    "name:vol_x_preferred":[
        "Charqueada"
    ],
    "name:war_x_preferred":[
        "Charqueada"
    ],
    "name:zho_x_preferred":[
        "\u6c99\u5c14\u514b\u963f\u8fbe"
    ],
    "wof:name":"Charqueada",
    "wof:placetype":"locality"
},
  "geometry": {"coordinates":[-56.58333,-29.26667],"type":"Point"}
}