{
  "type": "Feature",
  "properties": {
    "gn:admin1_code":"20",
    "gn:admin2_code":"2202901.0",
    "gn:asciiname":"Pindaiba",
    "gn:country_code":"BR",
    "gn:dem":492,
    "gn:feature_class":"P",
    "gn:feature_code":"PPL",
    "gn:name":"Pinda\u00edba",
    "gn:population":0,
    "gn:timezone":"America/Fortaleza",
    "iso:country":"BR",
    "wof:name":"Pindaiba",
    "wof:placetype":"locality"
},
  "geometry": {"coordinates":[-45.26667,-10.55],"type":"Point"}
}