{
  "type": "Feature",
  "properties": {
    "gn:admin1_code":"23",
    "gn:admin2_code":"4309126.0",
    "gn:asciiname":"Trindade",
    "gn:country_code":"BR",
    "gn:dem":569,
    "gn:feature_class":"P",
    "gn:feature_code":"PPL",
    "gn:name":"Trindade",
    "gn:population":0,
    "gn:timezone":"America/Sao_Paulo",
    "iso:country":"BR",
    "name:bre_x_preferred":[
        "Trindade"
    ],
    "name:ceb_x_preferred":[
        "Trindade"
    ],
    "name:deu_x_preferred":[
        "Trindade"
    ],
    "name:fra_x_preferred":[
        "Trindade"
    ],
    "name:ita_x_preferred":[
        "Trindade"
    ],
    "name:kaz_x_preferred":[
        "\u0422\u0440\u0438\u043d\u0434\u0430\u0434\u0438"
    ],
    "name:mlg_x_preferred":[
        "Trindade"
    ],
    "name:nld_x_preferred":[
        "Trindade"
    ],
    "name:nor_x_preferred":[
        "Trindade"
    ],
    "name:pol_x_preferred":[
        "Trindade"
    ],
    "name:por_x_preferred":[
        "Trindade"
    ],
    "name:rus_x_preferred":[
        "\u0422\u0440\u0438\u043d\u0434\u0430\u0434\u0438"
    ],
    "name:slk_x_preferred":[
        "Trindade"
    ],
    "name:spa_x_preferred":[
        "Trindade"
    ],
    "name:swe_x_preferred":[
        "Trindade"
    ],
    "name:tur_x_preferred":[
        "Trindade"
    ],
    "name:ukr_x_preferred":[
        "\u0422\u0440\u0456\u043d\u0434\u0430\u0434\u0435"
    ],
    "name:vie_x_preferred":[
        "Trindade"
    ],
    "name:vol_x_preferred":[
        "Trindade"
    ],
    "wof:name":"Trindade",
    "wof:placetype":"locality"
},
  "geometry": {"coordinates":[-52.91667,-27.45],"type":"Point"}
}