{
  "type": "Feature",
  "properties": {
    "gn:admin1_code":"23",
    "gn:admin2_code":"4309126.0",
    "gn:asciiname":"Trindade",
    "gn:country_code":"BR",
    "gn:dem":569,
    "gn:feature_class":"P",
    "gn:feature_code":"PPL",
    "gn:name":"Trindade",
    "gn:population":0,
    "gn:timezone":"America/Sao_Paulo",
    "iso:country":"BR",
    "wof:name":"Trindade",
    "wof:placetype":"locality"
},
  "geometry": {"coordinates":[-52.91667,-27.45],"type":"Point"}
}