{
  "type": "Feature",
  "properties": {
    "gn:admin1_code":"20.0",
    "gn:admin2_code":"2211605.0",
    "gn:asciiname":"Desviado",
    "gn:country_code":"BR",
    "gn:dem":430,
    "gn:feature_class":"P",
    "gn:feature_code":"PPL",
    "gn:name":"Desviado",
    "gn:population":0,
    "gn:timezone":"America/Fortaleza",
    "iso:country":"BR",
    "wof:name":"Desviado",
    "wof:placetype":"locality"
},
  "geometry": {"coordinates":[-40.88852,-7.21082],"type":"Point"}
}