{
  "type": "Feature",
  "properties": {
    "gn:admin1_code":"5",
    "gn:admin2_code":"2910800.0",
    "gn:asciiname":"Riacho do Correia",
    "gn:country_code":"BR",
    "gn:dem":143,
    "gn:feature_class":"P",
    "gn:feature_code":"PPL",
    "gn:name":"Riacho do Correia",
    "gn:population":0,
    "gn:timezone":"America/Bahia",
    "iso:country":"BR",
    "wof:name":"Riacho do Correia",
    "wof:placetype":"locality"
},
  "geometry": {"coordinates":[-39.11667,-12.11667],"type":"Point"}
}