{
  "type": "Feature",
  "properties": {
    "gn:admin1_code":"27.0",
    "gn:admin2_code":"3550308.0",
    "gn:asciiname":"Sitio Tres Irmaos",
    "gn:country_code":"BR",
    "gn:dem":772,
    "gn:feature_class":"P",
    "gn:feature_code":"PPL",
    "gn:name":"S\u00edtio Tr\u00eas Irm\u00e3os",
    "gn:population":0,
    "gn:timezone":"America/Sao_Paulo",
    "iso:country":"BR",
    "name:por_x_preferred":[
        "S\u00edtio Tr\u00eas Irm\u00e3os"
    ],
    "wof:name":"Sitio Tres Irmaos",
    "wof:placetype":"locality"
},
  "geometry": {"coordinates":[-46.69108,-23.81536],"type":"Point"}
}