{
  "type": "Feature",
  "properties": {
    "gn:admin1_code":"18.0",
    "gn:admin2_code":"4107009.0",
    "gn:asciiname":"Sitio do Portugues",
    "gn:country_code":"BR",
    "gn:dem":672,
    "gn:feature_class":"P",
    "gn:feature_code":"PPL",
    "gn:name":"S\u00edtio do Portugu\u00eas",
    "gn:population":0,
    "gn:timezone":"America/Sao_Paulo",
    "iso:country":"BR",
    "name:por_x_preferred":[
        "S\u00edtio do Portugu\u00eas"
    ],
    "wof:name":"Sitio do Portugues",
    "wof:placetype":"locality"
},
  "geometry": {"coordinates":[-50.36534,-23.98499],"type":"Point"}
}