{
  "type": "Feature",
  "properties": {
    "gn:admin1_code":"13",
    "gn:admin2_code":"2103208.0",
    "gn:asciiname":"Bonfim II",
    "gn:country_code":"BR",
    "gn:dem":91,
    "gn:feature_class":"P",
    "gn:feature_code":"PPL",
    "gn:name":"Bonfim II",
    "gn:population":0,
    "gn:timezone":"America/Fortaleza",
    "iso:country":"BR",
    "wof:name":"Bonfim II",
    "wof:placetype":"locality"
},
  "geometry": {"coordinates":[-43.38111,-3.67722],"type":"Point"}
}