{
  "type": "Feature",
  "properties": {
    "gn:admin1_code":"25",
    "gn:admin2_code":"1400407.0",
    "gn:asciiname":"Mangueira",
    "gn:country_code":"BR",
    "gn:dem":81,
    "gn:feature_class":"P",
    "gn:feature_code":"PPL",
    "gn:name":"Mangueira",
    "gn:population":0,
    "gn:timezone":"America/Boa_Vista",
    "iso:country":"BR",
    "name:ita_x_preferred":[
        "Mangueira"
    ],
    "wof:name":"Mangueira",
    "wof:placetype":"locality"
},
  "geometry": {"coordinates":[-60.46666999999999,3.73333],"type":"Point"}
}