{
  "type": "Feature",
  "properties": {
    "gn:admin1_code":"20",
    "gn:admin2_code":"2209153.0",
    "gn:asciiname":"Melancia",
    "gn:country_code":"BR",
    "gn:dem":155,
    "gn:feature_class":"P",
    "gn:feature_code":"PPL",
    "gn:name":"Melancia",
    "gn:population":0,
    "gn:timezone":"America/Fortaleza",
    "iso:country":"BR",
    "wof:name":"Melancia",
    "wof:placetype":"locality"
},
  "geometry": {"coordinates":[-41.86667,-5.86667],"type":"Point"}
}