{
  "type": "Feature",
  "properties": {
    "gn:admin1_code":"27",
    "gn:admin2_code":"3518305.0",
    "gn:asciiname":"Itapeti do Salto",
    "gn:country_code":"BR",
    "gn:dem":798,
    "gn:feature_class":"P",
    "gn:feature_code":"PPLL",
    "gn:name":"Itapeti do Salto",
    "gn:population":0,
    "gn:timezone":"America/Sao_Paulo",
    "iso:country":"BR",
    "name:por_x_preferred":[
        "Itapeti do Salto"
    ],
    "wof:name":"Itapeti do Salto",
    "wof:placetype":"locality"
},
  "geometry": {"coordinates":[-46.0973,-23.449],"type":"Point"}
}