{
  "type": "Feature",
  "properties": {
    "gn:admin1_code":"27",
    "gn:admin2_code":"3525201.0",
    "gn:asciiname":"Sitio Uirapuru",
    "gn:country_code":"BR",
    "gn:dem":835,
    "gn:feature_class":"P",
    "gn:feature_code":"PPL",
    "gn:name":"S\u00edtio Uirapuru",
    "gn:population":0,
    "gn:timezone":"America/Sao_Paulo",
    "iso:country":"BR",
    "name:por_x_preferred":[
        "S\u00edtio Uirapuru"
    ],
    "wof:name":"Sitio Uirapuru",
    "wof:placetype":"locality"
},
  "geometry": {"coordinates":[-46.72472,-23.18361],"type":"Point"}
}