{
  "type": "Feature",
  "properties": {
    "gn:admin1_code":"5.0",
    "gn:admin2_code":"2922250.0",
    "gn:asciiname":"Javi",
    "gn:country_code":"BR",
    "gn:dem":478,
    "gn:feature_class":"P",
    "gn:feature_code":"PPL",
    "gn:name":"Javi",
    "gn:population":0,
    "gn:timezone":"America/Bahia",
    "iso:country":"BR",
    "wof:name":"Javi",
    "wof:placetype":"locality"
},
  "geometry": {"coordinates":[-43.67617,-12.19965],"type":"Point"}
}