{
  "type": "Feature",
  "properties": {
    "gn:admin1_code":"06",
    "gn:admin2_code":"2306405.0",
    "gn:asciiname":"Fazenda Oiticica",
    "gn:country_code":"BR",
    "gn:dem":648,
    "gn:feature_class":"P",
    "gn:feature_code":"PPL",
    "gn:name":"Fazenda Oiticica",
    "gn:population":0,
    "gn:timezone":"America/Fortaleza",
    "iso:country":"BR",
    "wof:name":"Fazenda Oiticica",
    "wof:placetype":"locality"
},
  "geometry": {"coordinates":[-39.68333,-3.63333],"type":"Point"}
}