{
  "type": "Feature",
  "properties": {
    "gn:admin1_code":"13",
    "gn:admin2_code":"2112001.0",
    "gn:asciiname":"Se-me-Apanhas",
    "gn:country_code":"BR",
    "gn:dem":278,
    "gn:feature_class":"P",
    "gn:feature_code":"PPL",
    "gn:name":"Se-me-Apanhas",
    "gn:population":0,
    "gn:timezone":"America/Fortaleza",
    "iso:country":"BR",
    "wof:name":"Se-me-Apanhas",
    "wof:placetype":"locality"
},
  "geometry": {"coordinates":[-45.63333,-8.16667],"type":"Point"}
}