{
  "type": "Feature",
  "properties": {
    "gn:admin1_code":"15",
    "gn:admin2_code":"3151701.0",
    "gn:asciiname":"Cachoeirinha",
    "gn:country_code":"BR",
    "gn:dem":1136,
    "gn:feature_class":"P",
    "gn:feature_code":"PPL",
    "gn:name":"Cachoeirinha",
    "gn:population":0,
    "gn:timezone":"America/Sao_Paulo",
    "iso:country":"BR",
    "name:por_x_preferred":[
        "Cachoeirinha"
    ],
    "wof:name":"Cachoeirinha",
    "wof:placetype":"locality"
},
  "geometry": {"coordinates":[-46.05,-21.78333],"type":"Point"}
}