{
  "type": "Feature",
  "properties": {
    "gn:admin1_code":"15",
    "gn:admin2_code":"3151701.0",
    "gn:asciiname":"Cachoeirinha",
    "gn:country_code":"BR",
    "gn:dem":1136,
    "gn:feature_class":"P",
    "gn:feature_code":"PPL",
    "gn:name":"Cachoeirinha",
    "gn:population":0,
    "gn:timezone":"America/Sao_Paulo",
    "iso:country":"BR",
    "name:ara_x_preferred":[
        "\u0643\u0627\u0634\u0648\u064a\u0631\u064a\u0646\u0647\u0627"
    ],
    "name:bpy_x_preferred":[
        "\u0995\u09be\u0995\u09b9\u09cb\u09af\u09bc\u09c7\u0987\u09b0\u09bf\u09a8\u09b9\u09be"
    ],
    "name:cat_x_preferred":[
        "Cachoeirinha"
    ],
    "name:deu_x_preferred":[
        "Cachoeirinha"
    ],
    "name:epo_x_preferred":[
        "Cachoeirinha"
    ],
    "name:fra_x_preferred":[
        "Cachoeirinha"
    ],
    "name:hak_x_preferred":[
        "Cachoeirinha"
    ],
    "name:kaz_x_preferred":[
        "\u041a\u0430\u0448\u0443\u044d\u0439\u0440\u0438\u043d\u044c\u044f"
    ],
    "name:pol_x_preferred":[
        "Cachoeirinha"
    ],
    "name:por_x_preferred":[
        "Cachoeirinha"
    ],
    "name:ron_x_preferred":[
        "Cachoeirinha"
    ],
    "name:rus_x_preferred":[
        "\u041a\u0430\u0448\u0443\u044d\u0439\u0440\u0438\u043d\u044c\u044f"
    ],
    "name:spa_x_preferred":[
        "Cachoeirinha"
    ],
    "name:swe_x_preferred":[
        "Cachoeirinha"
    ],
    "name:tat_x_preferred":[
        "\u041a\u0430\u0448\u0432\u0435\u0439\u0440\u0438\u043d\u044c\u044f"
    ],
    "name:war_x_preferred":[
        "Cachoeirinha"
    ],
    "name:zho_x_preferred":[
        "\u5361\u8212\u57c3\u91cc\u5c3c\u4e9e"
    ],
    "wof:name":"Cachoeirinha",
    "wof:placetype":"locality"
},
  "geometry": {"coordinates":[-46.05,-21.78333],"type":"Point"}
}