{
  "type": "Feature",
  "properties": {
    "gn:admin1_code":"20",
    "gn:admin2_code":"2206209.0",
    "gn:asciiname":"Matoes",
    "gn:country_code":"BR",
    "gn:dem":116,
    "gn:feature_class":"P",
    "gn:feature_code":"PPL",
    "gn:name":"Mat\u00f5es",
    "gn:population":0,
    "gn:timezone":"America/Fortaleza",
    "iso:country":"BR",
    "wof:name":"Matoes",
    "wof:placetype":"locality"
},
  "geometry": {"coordinates":[-42.68333,-4.35],"type":"Point"}
}