{
  "type": "Feature",
  "properties": {
    "gn:admin1_code":"21",
    "gn:admin2_code":"3302403.0",
    "gn:asciiname":"Sao Manuel",
    "gn:country_code":"BR",
    "gn:dem":148,
    "gn:feature_class":"P",
    "gn:feature_code":"PPL",
    "gn:name":"S\u00e3o Manuel",
    "gn:population":0,
    "gn:timezone":"America/Sao_Paulo",
    "iso:country":"BR",
    "name:por_x_preferred":[
        "S\u00e3o Manuel"
    ],
    "wof:name":"Sao Manuel",
    "wof:placetype":"locality"
},
  "geometry": {"coordinates":[-41.78333,-22.26667],"type":"Point"}
}