{
  "type": "Feature",
  "properties": {
    "gn:admin1_code":"04",
    "gn:admin2_code":"1300805.0",
    "gn:asciiname":"Mandiqui",
    "gn:cc2":"BR",
    "gn:country_code":"BR",
    "gn:dem":24,
    "gn:feature_class":"P",
    "gn:feature_code":"PPL",
    "gn:name":"Mandiqui",
    "gn:population":0,
    "gn:timezone":"America/Manaus",
    "iso:country":"BR",
    "name:und_x_variant":[
        "Mandihy",
        "Mandii",
        "Mandiqui"
    ],
    "wof:name":"Mandiqui",
    "wof:placetype":"locality"
},
  "geometry": {"coordinates":[-59.79611,-4.4625],"type":"Point"}
}