{
  "type": "Feature",
  "properties": {
    "gn:admin1_code":"18",
    "gn:admin2_code":"4122305.0",
    "gn:asciiname":"Sitio Germano Schossig",
    "gn:country_code":"BR",
    "gn:dem":808,
    "gn:feature_class":"P",
    "gn:feature_code":"PPL",
    "gn:name":"S\u00edtio Germano Schossig",
    "gn:population":0,
    "gn:timezone":"America/Sao_Paulo",
    "iso:country":"BR",
    "name:por_x_preferred":[
        "S\u00edtio Germano Schossig"
    ],
    "wof:name":"Sitio Germano Schossig",
    "wof:placetype":"locality"
},
  "geometry": {"coordinates":[-49.72752,-26.10241],"type":"Point"}
}