{
  "type": "Feature",
  "properties": {
    "gn:admin1_code":"13",
    "gn:admin2_code":"2102200.0",
    "gn:asciiname":"Urucuzeiro",
    "gn:country_code":"BR",
    "gn:dem":77,
    "gn:feature_class":"P",
    "gn:feature_code":"PPL",
    "gn:name":"Urucuzeiro",
    "gn:population":0,
    "gn:timezone":"America/Fortaleza",
    "iso:country":"BR",
    "wof:name":"Urucuzeiro",
    "wof:placetype":"locality"
},
  "geometry": {"coordinates":[-42.84222000000001,-3.86333],"type":"Point"}
}