{
  "type": "Feature",
  "properties": {
    "gn:admin1_code":"18.0",
    "gn:admin2_code":"4116208.0",
    "gn:asciiname":"Saquarema",
    "gn:country_code":"BR",
    "gn:dem":8,
    "gn:feature_class":"P",
    "gn:feature_code":"PPL",
    "gn:name":"Saquarema",
    "gn:population":0,
    "gn:timezone":"America/Sao_Paulo",
    "iso:country":"BR",
    "name:bpy_x_preferred":[
        "\u09b8\u09be\u0995\u09c1\u09f1\u09be\u09b0\u09c7\u09ae\u09be"
    ],
    "name:deu_x_preferred":[
        "Saquarema"
    ],
    "name:epo_x_preferred":[
        "Saquarema"
    ],
    "name:eus_x_preferred":[
        "Saquarema"
    ],
    "name:fra_x_preferred":[
        "Saquarema"
    ],
    "name:ita_x_preferred":[
        "Saquarema"
    ],
    "name:kat_x_preferred":[
        "\u10e1\u10d0\u10d9\u10e3\u10d0\u10e0\u10d4\u10db\u10d0"
    ],
    "name:kaz_x_preferred":[
        "\u0421\u0430\u043a\u0443\u0430\u0440\u0435\u043c\u0430"
    ],
    "name:mlg_x_preferred":[
        "Saquarema"
    ],
    "name:nld_x_preferred":[
        "Saquarema"
    ],
    "name:nor_x_preferred":[
        "Saquarema"
    ],
    "name:pol_x_preferred":[
        "Saquarema"
    ],
    "name:por_x_preferred":[
        "Saquarema"
    ],
    "name:ron_x_preferred":[
        "Saquarema"
    ],
    "name:rus_x_preferred":[
        "\u0421\u0430\u043a\u0443\u0430\u0440\u0435\u043c\u0430"
    ],
    "name:spa_x_preferred":[
        "Saquarema"
    ],
    "name:vie_x_preferred":[
        "Saquarema"
    ],
    "name:vol_x_preferred":[
        "Saquarema"
    ],
    "name:war_x_preferred":[
        "Saquarema"
    ],
    "name:zho_x_preferred":[
        "\u8428\u5938\u96f7\u9a6c"
    ],
    "wof:name":"Saquarema",
    "wof:placetype":"locality"
},
  "geometry": {"coordinates":[-48.68426,-25.52155],"type":"Point"}
}