{
  "type": "Feature",
  "properties": {
    "gn:admin1_code":"18.0",
    "gn:admin2_code":"4116208.0",
    "gn:asciiname":"Saquarema",
    "gn:country_code":"BR",
    "gn:dem":8,
    "gn:feature_class":"P",
    "gn:feature_code":"PPL",
    "gn:name":"Saquarema",
    "gn:population":0,
    "gn:timezone":"America/Sao_Paulo",
    "iso:country":"BR",
    "wof:name":"Saquarema",
    "wof:placetype":"locality"
},
  "geometry": {"coordinates":[-48.68426,-25.52155],"type":"Point"}
}