{
  "type": "Feature",
  "properties": {
    "gn:admin1_code":"27",
    "gn:admin2_code":"3530607.0",
    "gn:asciiname":"Stio Serra do Itapeti",
    "gn:country_code":"BR",
    "gn:dem":857,
    "gn:feature_class":"P",
    "gn:feature_code":"PPL",
    "gn:name":"Stio Serra do Itapeti",
    "gn:population":0,
    "gn:timezone":"America/Sao_Paulo",
    "iso:country":"BR",
    "name:por_x_preferred":[
        "Stio Serra do Itapeti"
    ],
    "wof:name":"Stio Serra do Itapeti",
    "wof:placetype":"locality"
},
  "geometry": {"coordinates":[-46.2174,-23.4934],"type":"Point"}
}