{
  "type": "Feature",
  "properties": {
    "gn:gn_country":"BR",
    "gn:gn_fcode":"PPL",
    "gn:gn_pop":0,
    "iso:country":"BR",
    "name:arm_x_preferred":[
        "\u053f\u0561\u0574\u057a\u056b\u0576\u0561\u057a\u0578\u056c\u056b\u057d"
    ],
    "name:baq_x_preferred":[
        "Campin\u00e1polis"
    ],
    "name:bpy_x_preferred":[
        "\u0995\u09be\u09ae\u09aa\u09bf\u09a8\u09be\u09aa\u09cb\u09b2\u09bf\u09b8"
    ],
    "name:chi_x_preferred":[
        "\u574e\u76ae\u7eb3\u6ce2\u5229\u65af"
    ],
    "name:dut_x_preferred":[
        "Campin\u00e1polis"
    ],
    "name:eng_x_preferred":[
        "Campin\u00e1polis"
    ],
    "name:fre_x_preferred":[
        "Campin\u00e1polis"
    ],
    "name:geo_x_preferred":[
        "\u10d9\u10d0\u10db\u10de\u10d8\u10dc\u10d0\u10de\u10dd\u10da\u10d8\u10e1\u10d8"
    ],
    "name:ger_x_preferred":[
        "Campin\u00e1polis"
    ],
    "name:hun_x_preferred":[
        "Campin\u00e1polis"
    ],
    "name:ita_x_preferred":[
        "Campin\u00e1polis"
    ],
    "name:kaz_x_preferred":[
        "\u041a\u0430\u043c\u043f\u0438\u043d\u0430\u043f\u043e\u043b\u0438\u0441"
    ],
    "name:nob_x_preferred":[
        "Campin\u00e1polis"
    ],
    "name:pol_x_preferred":[
        "Campin\u00e1polis"
    ],
    "name:por_x_preferred":[
        "Campin\u00e1polis"
    ],
    "name:rum_x_preferred":[
        "Campin\u00e1polis"
    ],
    "name:rus_x_preferred":[
        "\u041a\u0430\u043c\u043f\u0438\u043d\u0430\u043f\u043e\u043b\u0438\u0441"
    ],
    "name:spa_x_preferred":[
        "Campin\u00e1polis"
    ],
    "name:swe_x_preferred":[
        "Campin\u00e1polis"
    ],
    "name:vie_x_preferred":[
        "Campin\u00e1polis"
    ],
    "name:vol_x_preferred":[
        "Campin\u00e1polis"
    ],
    "name:war_x_preferred":[
        "Campin\u00e1polis"
    ],
    "qs_pg:aaroncc":"BR",
    "qs_pg:gn_country":"BR",
    "qs_pg:gn_fcode":"PPL",
    "qs_pg:gn_pop":0,
    "qs_pg:name":"Campin\u00e1polis",
    "qs_pg:name_adm0":"Brasil",
    "qs_pg:name_adm1":"Mato Grosso",
    "qs_pg:photos_9k":1,
    "qs_pg:photos_9r":1,
    "qs_pg:photos_all":2,
    "qs_pg:photos_sr":0,
    "qs_pg:pop_sr":0,
    "qs_pg:qs_pg_placetype":"locality",
    "qs_pg:qs_pg_placetype_gp":"Town",
    "qs_pg:woe_adm0":23424768,
    "woe:adm0_id":23424768,
    "woe:name_adm0":"Brasil",
    "woe:name_adm1":"Mato Grosso",
    "woe:placetype":"Town",
    "wof:name":"Campin\u00e1polis",
    "wof:placetype":"locality"
},
  "geometry": {"coordinates":[-52.89472,-14.51556],"type":"Point"}
}