{
  "type": "Feature",
  "properties": {
    "gn:admin1_code":"20",
    "gn:admin2_code":"2205805.0",
    "gn:asciiname":"Alto Bonito",
    "gn:country_code":"BR",
    "gn:dem":44,
    "gn:feature_class":"P",
    "gn:feature_code":"PPL",
    "gn:name":"Alto Bonito",
    "gn:population":0,
    "gn:timezone":"America/Fortaleza",
    "iso:country":"BR",
    "wof:name":"Alto Bonito",
    "wof:placetype":"locality"
},
  "geometry": {"coordinates":[-42.24306,-3.55528],"type":"Point"}
}