{
  "type": "Feature",
  "properties": {
    "gn:admin1_code":"06",
    "gn:admin2_code":"2308104.0",
    "gn:asciiname":"Solta de Dentro",
    "gn:country_code":"BR",
    "gn:dem":585,
    "gn:feature_class":"P",
    "gn:feature_code":"PPL",
    "gn:name":"S\u00f4lta de Dentro",
    "gn:population":0,
    "gn:timezone":"America/Fortaleza",
    "iso:country":"BR",
    "wof:name":"Solta de Dentro",
    "wof:placetype":"locality"
},
  "geometry": {"coordinates":[-38.71667,-7.56667],"type":"Point"}
}