{
  "type": "Feature",
  "properties": {
    "gn:admin1_code":"27",
    "gn:admin2_code":"3509908.0",
    "gn:asciiname":"Sitio Debeneti da Silva",
    "gn:country_code":"BR",
    "gn:dem":45,
    "gn:feature_class":"P",
    "gn:feature_code":"PPL",
    "gn:name":"S\u00edtio Debeneti da Silva",
    "gn:population":0,
    "gn:timezone":"America/Sao_Paulo",
    "iso:country":"BR",
    "name:por_x_preferred":[
        "S\u00edtio Debeneti da Silva"
    ],
    "wof:name":"Sitio Debeneti da Silva",
    "wof:placetype":"locality"
},
  "geometry": {"coordinates":[-48.1117,-25.1468],"type":"Point"}
}