{
  "type": "Feature",
  "properties": {
    "gn:admin1_code":"13",
    "gn:admin2_code":"2104800.0",
    "gn:asciiname":"Aldeia de Pedra",
    "gn:country_code":"BR",
    "gn:dem":266,
    "gn:feature_class":"P",
    "gn:feature_code":"PPL",
    "gn:name":"Aldeia de Pedra",
    "gn:population":0,
    "gn:timezone":"America/Fortaleza",
    "iso:country":"BR",
    "wof:name":"Aldeia de Pedra",
    "wof:placetype":"locality"
},
  "geometry": {"coordinates":[-45.93333,-5.83333],"type":"Point"}
}