{
  "type": "Feature",
  "properties": {
    "gn:admin1_code":"15",
    "gn:admin2_code":"3143203.0",
    "gn:asciiname":"Imperatriz",
    "gn:country_code":"BR",
    "gn:dem":903,
    "gn:feature_class":"P",
    "gn:feature_code":"PPL",
    "gn:name":"Imperatriz",
    "gn:population":0,
    "gn:timezone":"America/Sao_Paulo",
    "iso:country":"BR",
    "name:por_x_preferred":[
        "Imperatriz"
    ],
    "wof:name":"Imperatriz",
    "wof:placetype":"locality"
},
  "geometry": {"coordinates":[-47.06667,-21.23333],"type":"Point"}
}