{
  "type": "Feature",
  "properties": {
    "gn:admin1_code":"15",
    "gn:admin2_code":"3143203.0",
    "gn:asciiname":"Imperatriz",
    "gn:country_code":"BR",
    "gn:dem":903,
    "gn:feature_class":"P",
    "gn:feature_code":"PPL",
    "gn:name":"Imperatriz",
    "gn:population":0,
    "gn:timezone":"America/Sao_Paulo",
    "iso:country":"BR",
    "name:afr_x_preferred":[
        "Imperatriz"
    ],
    "name:ara_x_preferred":[
        "\u0627\u0645\u0628\u0631\u0627\u062a\u0631\u064a\u0632"
    ],
    "name:bpy_x_preferred":[
        "\u0987\u09ae\u09aa\u09c7\u09b0\u09be\u099f\u09cd\u09b0\u09bf\u099c"
    ],
    "name:bre_x_preferred":[
        "Imperatriz"
    ],
    "name:cat_x_preferred":[
        "Imperatriz"
    ],
    "name:ceb_x_preferred":[
        "Imperatriz"
    ],
    "name:deu_x_preferred":[
        "Imperatriz"
    ],
    "name:epo_x_preferred":[
        "Imperatriz"
    ],
    "name:eus_x_preferred":[
        "Imperatriz"
    ],
    "name:fas_x_preferred":[
        "\u0627\u0645\u067e\u0631\u0627\u062a\u0631\u06cc\u0632"
    ],
    "name:fin_x_preferred":[
        "Imperatriz"
    ],
    "name:fra_x_preferred":[
        "Imperatriz"
    ],
    "name:glg_x_preferred":[
        "Imperatriz"
    ],
    "name:hye_x_preferred":[
        "\u053b\u0574\u057a\u0565\u0580\u0561\u057f\u0580\u056b\u057d"
    ],
    "name:ido_x_preferred":[
        "Imperatriz"
    ],
    "name:ita_x_preferred":[
        "Imperatriz"
    ],
    "name:kat_x_preferred":[
        "\u10d8\u10db\u10de\u10d4\u10e0\u10d0\u10e2\u10e0\u10d8\u10e1\u10d8"
    ],
    "name:kaz_x_preferred":[
        "\u0418\u043c\u043f\u0435\u0440\u0430\u0442\u0440\u0438\u0441"
    ],
    "name:lit_x_preferred":[
        "Imperatrisas"
    ],
    "name:mlg_x_preferred":[
        "Imperatriz"
    ],
    "name:nld_x_preferred":[
        "Imperatriz"
    ],
    "name:nor_x_preferred":[
        "Imperatriz"
    ],
    "name:oci_x_preferred":[
        "Imperatriz"
    ],
    "name:pol_x_preferred":[
        "Imperatriz"
    ],
    "name:por_x_preferred":[
        "Imperatriz"
    ],
    "name:ron_x_preferred":[
        "Imperatriz"
    ],
    "name:rus_x_preferred":[
        "\u0418\u043c\u043f\u0435\u0440\u0430\u0442\u0440\u0438\u0441"
    ],
    "name:slk_x_preferred":[
        "Imperatriz"
    ],
    "name:spa_x_preferred":[
        "Imperatriz"
    ],
    "name:srp_x_preferred":[
        "\u0418\u043c\u043f\u0435\u0440\u0430\u0442\u0440\u0438\u0437"
    ],
    "name:swe_x_preferred":[
        "Imperatriz"
    ],
    "name:tat_x_preferred":[
        "\u0418\u043c\u043f\u0435\u0440\u0430\u0442\u0440\u0438\u0441"
    ],
    "name:tet_x_preferred":[
        "Imperatriz"
    ],
    "name:vie_x_preferred":[
        "Imperatriz"
    ],
    "name:vol_x_preferred":[
        "Imperatriz"
    ],
    "name:war_x_preferred":[
        "Imperatriz"
    ],
    "name:zho_x_preferred":[
        "\u56e0\u4f69\u62c9\u7279\u91cc\u65af"
    ],
    "wof:name":"Imperatriz",
    "wof:placetype":"locality"
},
  "geometry": {"coordinates":[-47.06667,-21.23333],"type":"Point"}
}