{
  "type": "Feature",
  "properties": {
    "gn:admin1_code":"4",
    "gn:admin2_code":"1302207.0",
    "gn:asciiname":"Paraiba",
    "gn:country_code":"BR",
    "gn:dem":60,
    "gn:feature_class":"P",
    "gn:feature_code":"PPL",
    "gn:name":"Para\u00edba",
    "gn:population":0,
    "gn:timezone":"America/Manaus",
    "iso:country":"BR",
    "name:ara_x_preferred":[
        "\u0628\u0627\u0631\u0627\u064a\u0628\u0627"
    ],
    "name:ben_x_preferred":[
        "\u09aa\u09be\u09b0\u09be\u0987\u09ac\u09be"
    ],
    "name:deu_x_preferred":[
        "Para\u00edba do Sul"
    ],
    "name:ell_x_preferred":[
        "\u03a0\u03b1\u03c1\u03b1\u03ca\u03bc\u03c0\u03b1"
    ],
    "name:fas_x_preferred":[
        "\u067e\u0627\u0631\u0627\u0626\u06cc\u0628\u0627"
    ],
    "name:fra_x_preferred":[
        "Para\u00edba"
    ],
    "name:heb_x_preferred":[
        "\u05e4\u05d0\u05e8\u05d0\u05d9\u05d1\u05d4"
    ],
    "name:hin_x_preferred":[
        "\u092a\u093e\u0930\u0948\u092c\u093e"
    ],
    "name:hun_x_preferred":[
        "Paraiba"
    ],
    "name:ind_x_preferred":[
        "Paraiba"
    ],
    "name:ita_x_preferred":[
        "Paraiba"
    ],
    "name:jpn_x_preferred":[
        "\u30d1\u30e9\u30a4\u30d0\u5ddd"
    ],
    "name:kor_x_preferred":[
        "\ud30c\ub77c\uc774\ubc14"
    ],
    "name:nld_x_preferred":[
        "Para\u00edba"
    ],
    "name:pol_x_preferred":[
        "Paraiba"
    ],
    "name:por_x_preferred":[
        "Para\u00edba"
    ],
    "name:rus_x_preferred":[
        "\u0440\u0435\u043a\u0430 \u041f\u0430\u0440\u0430\u0438\u0431\u0430"
    ],
    "name:spa_x_preferred":[
        "Paraiba"
    ],
    "name:swe_x_preferred":[
        "Paraiba"
    ],
    "name:tur_x_preferred":[
        "Paraiba"
    ],
    "name:ukr_x_preferred":[
        "\u041f\u0430\u0440\u0430\u0439\u0431\u0430"
    ],
    "name:urd_x_preferred":[
        "\u067e\u0627\u0631\u06cc\u0628\u0627"
    ],
    "name:vie_x_preferred":[
        "S\u00f4ng Paraiba"
    ],
    "name:zho_cn_x_preferred":[
        "\u5e15\u62c9\u4f0a\u5df4\u6cb3"
    ],
    "name:zho_tw_x_preferred":[
        "\u5e15\u840a\u5df4\u6cb3"
    ],
    "wof:name":"Paraiba",
    "wof:placetype":"locality"
},
  "geometry": {"coordinates":[-65.7911,-2.69655],"type":"Point"}
}