{
  "type": "Feature",
  "properties": {
    "gn:admin1_code":"4",
    "gn:admin2_code":"1302207.0",
    "gn:asciiname":"Paraiba",
    "gn:country_code":"BR",
    "gn:dem":60,
    "gn:feature_class":"P",
    "gn:feature_code":"PPL",
    "gn:name":"Para\u00edba",
    "gn:population":0,
    "gn:timezone":"America/Manaus",
    "iso:country":"BR",
    "wof:name":"Paraiba",
    "wof:placetype":"locality"
},
  "geometry": {"coordinates":[-65.7911,-2.69655],"type":"Point"}
}