{
  "type": "Feature",
  "properties": {
    "gn:admin1_code":"6",
    "gn:admin2_code":"2302503.0",
    "gn:asciiname":"Baixio do Boi",
    "gn:country_code":"BR",
    "gn:dem":423,
    "gn:feature_class":"P",
    "gn:feature_code":"PPL",
    "gn:name":"Baixio do Boi",
    "gn:population":0,
    "gn:timezone":"America/Fortaleza",
    "iso:country":"BR",
    "wof:name":"Baixio do Boi",
    "wof:placetype":"locality"
},
  "geometry": {"coordinates":[-39.01667,-7.51667],"type":"Point"}
}