{
  "type": "Feature",
  "properties": {
    "gn:admin1_code":"04",
    "gn:admin2_code":"1303106.0",
    "gn:asciiname":"Terra Preta",
    "gn:country_code":"BR",
    "gn:dem":43,
    "gn:feature_class":"P",
    "gn:feature_code":"PPL",
    "gn:name":"Terra Preta",
    "gn:population":0,
    "gn:timezone":"America/Manaus",
    "iso:country":"BR",
    "wof:name":"Terra Preta",
    "wof:placetype":"locality"
},
  "geometry": {"coordinates":[-58.43333000000001,-4.48333],"type":"Point"}
}