{
  "type": "Feature",
  "properties": {
    "gn:admin1_code":"1",
    "gn:admin2_code":"1200351.0",
    "gn:asciiname":"Tabocal",
    "gn:country_code":"BR",
    "gn:dem":219,
    "gn:feature_class":"P",
    "gn:feature_code":"PPL",
    "gn:name":"Tabocal",
    "gn:population":0,
    "gn:timezone":"America/Rio_Branco",
    "iso:country":"BR",
    "wof:name":"Tabocal",
    "wof:placetype":"locality"
},
  "geometry": {"coordinates":[-72.83333,-8.73333],"type":"Point"}
}