{
  "type": "Feature",
  "properties": {
    "gn:admin1_code":"18.0",
    "gn:admin2_code":"4126603.0",
    "gn:asciiname":"Sitio Joaquim Marciano",
    "gn:country_code":"BR",
    "gn:dem":643,
    "gn:feature_class":"P",
    "gn:feature_code":"PPL",
    "gn:name":"S\u00edtio Joaquim Marciano",
    "gn:population":0,
    "gn:timezone":"America/Sao_Paulo",
    "iso:country":"BR",
    "name:por_x_preferred":[
        "S\u00edtio Joaquim Marciano"
    ],
    "wof:name":"Sitio Joaquim Marciano",
    "wof:placetype":"locality"
},
  "geometry": {"coordinates":[-49.8662,-23.5878],"type":"Point"}
}