{
  "type": "Feature",
  "properties": {
    "gn:admin1_code":"15",
    "gn:admin2_code":"3114204.0",
    "gn:asciiname":"Jacaranda",
    "gn:country_code":"BR",
    "gn:dem":812,
    "gn:feature_class":"P",
    "gn:feature_code":"PPL",
    "gn:name":"Jacarand\u00e1",
    "gn:population":0,
    "gn:timezone":"America/Sao_Paulo",
    "iso:country":"BR",
    "name:por_x_preferred":[
        "Jacarand\u00e1"
    ],
    "wof:name":"Jacaranda",
    "wof:placetype":"locality"
},
  "geometry": {"coordinates":[-44.68333,-20.13333],"type":"Point"}
}