{
  "type": "Feature",
  "properties": {
    "gn:admin1_code":"17",
    "gn:admin2_code":"2512309.0",
    "gn:asciiname":"Esperanca",
    "gn:country_code":"BR",
    "gn:dem":653,
    "gn:feature_class":"P",
    "gn:feature_code":"PPL",
    "gn:name":"Esperan\u00e7a",
    "gn:population":0,
    "gn:timezone":"America/Fortaleza",
    "iso:country":"BR",
    "wof:name":"Esperanca",
    "wof:placetype":"locality"
},
  "geometry": {"coordinates":[-38.05,-7.66667],"type":"Point"}
}