{
  "type": "Feature",
  "properties": {
    "gn:admin1_code":"18",
    "gn:admin2_code":"4113205.0",
    "gn:asciiname":"Sitio Luiz C. B. da Silveira",
    "gn:country_code":"BR",
    "gn:dem":815,
    "gn:feature_class":"P",
    "gn:feature_code":"PPL",
    "gn:name":"S\u00edtio Luiz C. B. da Silveira",
    "gn:population":0,
    "gn:timezone":"America/Sao_Paulo",
    "iso:country":"BR",
    "name:por_x_preferred":[
        "S\u00edtio Luiz C. B. da Silveira"
    ],
    "wof:name":"Sitio Luiz C. B. da Silveira",
    "wof:placetype":"locality"
},
  "geometry": {"coordinates":[-49.72944,-25.85361],"type":"Point"}
}