{
  "type": "Feature",
  "properties": {
    "gn:admin1_code":"18.0",
    "gn:admin2_code":"4119202.0",
    "gn:asciiname":"Sitio Rosalena",
    "gn:country_code":"BR",
    "gn:dem":738,
    "gn:feature_class":"P",
    "gn:feature_code":"PPL",
    "gn:name":"S\u00edtio Rosalena",
    "gn:population":0,
    "gn:timezone":"America/Sao_Paulo",
    "iso:country":"BR",
    "name:por_x_preferred":[
        "S\u00edtio Rosalena"
    ],
    "wof:name":"Sitio Rosalena",
    "wof:placetype":"locality"
},
  "geometry": {"coordinates":[-50.1255,-23.92921],"type":"Point"}
}