{
  "type": "Feature",
  "properties": {
    "gn:admin1_code":"23.0",
    "gn:admin2_code":"4309050.0",
    "gn:asciiname":"Capao Grande",
    "gn:country_code":"BR",
    "gn:dem":30,
    "gn:feature_class":"P",
    "gn:feature_code":"PPLL",
    "gn:name":"Cap\u00e3o Grande",
    "gn:population":0,
    "gn:timezone":"America/Sao_Paulo",
    "iso:country":"BR",
    "name:por_x_preferred":[
        "Cap\u00e3o Grande"
    ],
    "wof:name":"Capao Grande",
    "wof:placetype":"locality"
},
  "geometry": {"coordinates":[-50.7781,-29.9516],"type":"Point"}
}