{
  "type": "Feature",
  "properties": {
    "gn:admin1_code":"18.0",
    "gn:admin2_code":"4116901.0",
    "gn:asciiname":"Sitio Cristo Rei",
    "gn:country_code":"BR",
    "gn:dem":483,
    "gn:feature_class":"P",
    "gn:feature_code":"PPL",
    "gn:name":"S\u00edtio Cristo Rei",
    "gn:population":0,
    "gn:timezone":"America/Sao_Paulo",
    "iso:country":"BR",
    "name:por_x_preferred":[
        "S\u00edtio Cristo Rei"
    ],
    "wof:name":"Sitio Cristo Rei",
    "wof:placetype":"locality"
},
  "geometry": {"coordinates":[-52.24347,-23.23894],"type":"Point"}
}