{
  "type": "Feature",
  "properties": {
    "gn:admin1_code":"06",
    "gn:admin2_code":"2302602.0",
    "gn:asciiname":"Jatoba",
    "gn:country_code":"BR",
    "gn:dem":12,
    "gn:feature_class":"P",
    "gn:feature_code":"PPL",
    "gn:name":"Jatob\u00e1",
    "gn:population":0,
    "gn:timezone":"America/Fortaleza",
    "iso:country":"BR",
    "wof:name":"Jatoba",
    "wof:placetype":"locality"
},
  "geometry": {"coordinates":[-40.97333,-2.98167],"type":"Point"}
}