{
  "type": "Feature",
  "properties": {
    "gn:admin1_code":"18.0",
    "gn:admin2_code":"4127809.0",
    "gn:asciiname":"Sitio Wilson B. Monteiro",
    "gn:country_code":"BR",
    "gn:dem":689,
    "gn:feature_class":"P",
    "gn:feature_code":"PPL",
    "gn:name":"S\u00edtio Wilson B. Monteiro",
    "gn:population":0,
    "gn:timezone":"America/Sao_Paulo",
    "iso:country":"BR",
    "name:por_x_preferred":[
        "S\u00edtio Wilson B. Monteiro"
    ],
    "wof:name":"Sitio Wilson B. Monteiro",
    "wof:placetype":"locality"
},
  "geometry": {"coordinates":[-49.9145,-23.6693],"type":"Point"}
}