{
  "type": "Feature",
  "properties": {
    "gn:admin1_code":"22",
    "gn:admin2_code":"2412906.0",
    "gn:asciiname":"Mal Assombrado",
    "gn:country_code":"BR",
    "gn:dem":225,
    "gn:feature_class":"P",
    "gn:feature_code":"PPL",
    "gn:name":"Mal Assombrado",
    "gn:population":0,
    "gn:timezone":"America/Fortaleza",
    "iso:country":"BR",
    "wof:name":"Mal Assombrado",
    "wof:placetype":"locality"
},
  "geometry": {"coordinates":[-36.11417,-5.9175],"type":"Point"}
}