{
  "type": "Feature",
  "properties": {
    "gn:admin1_code":"16.0",
    "gn:admin2_code":"1500404.0",
    "gn:asciiname":"Boa Floresta",
    "gn:country_code":"BR",
    "gn:dem":45,
    "gn:feature_class":"P",
    "gn:feature_code":"PPL",
    "gn:name":"Boa Floresta",
    "gn:population":0,
    "gn:timezone":"America/Santarem",
    "iso:country":"BR",
    "name:por_x_preferred":[
        "Boa Floresta"
    ],
    "wof:name":"Boa Floresta",
    "wof:placetype":"locality"
},
  "geometry": {"coordinates":[-54.96802,-1.58359],"type":"Point"}
}