{
  "type": "Feature",
  "properties": {
    "gn:admin1_code":"20.0",
    "gn:admin2_code":"2202117.0",
    "gn:asciiname":"Trinidade",
    "gn:country_code":"BR",
    "gn:dem":357,
    "gn:feature_class":"P",
    "gn:feature_code":"PPL",
    "gn:name":"Trinidade",
    "gn:population":0,
    "gn:timezone":"America/Fortaleza",
    "iso:country":"BR",
    "name:por_x_preferred":[
        "Trinidade"
    ],
    "wof:name":"Trinidade",
    "wof:placetype":"locality"
},
  "geometry": {"coordinates":[-41.8376,-8.31647],"type":"Point"}
}