{
  "type": "Feature",
  "properties": {
    "gn:admin1_code":"06",
    "gn:admin2_code":"2308609.0",
    "gn:asciiname":"Sitio do Passarinho",
    "gn:country_code":"BR",
    "gn:dem":765,
    "gn:feature_class":"P",
    "gn:feature_code":"PPL",
    "gn:name":"S\u00edtio do Passarinho",
    "gn:population":0,
    "gn:timezone":"America/Fortaleza",
    "iso:country":"BR",
    "wof:name":"Sitio do Passarinho",
    "wof:placetype":"locality"
},
  "geometry": {"coordinates":[-40.06667,-4.83333],"type":"Point"}
}