{
  "type": "Feature",
  "properties": {
    "gn:admin1_code":"4",
    "gn:admin2_code":"1301605.0",
    "gn:asciiname":"Piranhas",
    "gn:country_code":"BR",
    "gn:dem":45,
    "gn:feature_class":"P",
    "gn:feature_code":"PPL",
    "gn:name":"Piranhas",
    "gn:population":0,
    "gn:timezone":"America/Manaus",
    "iso:country":"BR",
    "wof:name":"Piranhas",
    "wof:placetype":"locality"
},
  "geometry": {"coordinates":[-65.46666999999999,-2.41667],"type":"Point"}
}