{
  "type": "Feature",
  "properties": {
    "gn:admin1_code":"4",
    "gn:admin2_code":"1301605.0",
    "gn:asciiname":"Piranhas",
    "gn:country_code":"BR",
    "gn:dem":45,
    "gn:feature_class":"P",
    "gn:feature_code":"PPL",
    "gn:name":"Piranhas",
    "gn:population":0,
    "gn:timezone":"America/Manaus",
    "iso:country":"BR",
    "name:ara_x_preferred":[
        "\u0628\u064a\u0631\u0627\u0646\u0627\u0633"
    ],
    "name:bpy_x_preferred":[
        "\u09aa\u09bf\u09b0\u09be\u09a8\u09b9\u09be\u09b8"
    ],
    "name:epo_x_preferred":[
        "Piranhas"
    ],
    "name:eus_x_preferred":[
        "Piranhas"
    ],
    "name:fra_x_preferred":[
        "Piranhas"
    ],
    "name:hye_x_preferred":[
        "\u054a\u056b\u0580\u0561\u0576\u0575\u0561\u057d"
    ],
    "name:ind_x_preferred":[
        "Piranhas"
    ],
    "name:ita_x_preferred":[
        "Piranhas"
    ],
    "name:kat_x_preferred":[
        "\u10de\u10d8\u10e0\u10d0\u10dc\u10d8\u10d0\u10e1\u10d8"
    ],
    "name:kaz_x_preferred":[
        "\u041f\u0438\u0440\u0430\u043d\u044c\u044f\u0441"
    ],
    "name:mlg_x_preferred":[
        "Piranhas"
    ],
    "name:nld_x_preferred":[
        "Piranhas"
    ],
    "name:nor_x_preferred":[
        "Piranhas"
    ],
    "name:por_x_preferred":[
        "Piranhas"
    ],
    "name:ron_x_preferred":[
        "Piranhas"
    ],
    "name:rus_x_preferred":[
        "\u041f\u0438\u0440\u0430\u043d\u044c\u044f\u0441"
    ],
    "name:vie_x_preferred":[
        "Piranhas"
    ],
    "name:vol_x_preferred":[
        "Piranhas"
    ],
    "name:war_x_preferred":[
        "Piranhas"
    ],
    "name:zho_x_preferred":[
        "\u76ae\u62c9\u5c3c\u4e9a\u65af"
    ],
    "wof:name":"Piranhas",
    "wof:placetype":"locality"
},
  "geometry": {"coordinates":[-65.46666999999999,-2.41667],"type":"Point"}
}