{
  "type": "Feature",
  "properties": {
    "gn:admin1_code":"18.0",
    "gn:admin2_code":"4122305.0",
    "gn:asciiname":"Sitio Madeireira Fefe",
    "gn:country_code":"BR",
    "gn:dem":855,
    "gn:feature_class":"P",
    "gn:feature_code":"PPL",
    "gn:name":"S\u00edtio Madeireira Fefe",
    "gn:population":0,
    "gn:timezone":"America/Sao_Paulo",
    "iso:country":"BR",
    "name:por_x_preferred":[
        "S\u00edtio Madeireira Fefe"
    ],
    "wof:name":"Sitio Madeireira Fefe",
    "wof:placetype":"locality"
},
  "geometry": {"coordinates":[-49.784,-26.0693],"type":"Point"}
}