{
  "type": "Feature",
  "properties": {
    "gn:admin1_code":"18.0",
    "gn:admin2_code":"4124707.0",
    "gn:asciiname":"Sitio Antonio Francisco",
    "gn:country_code":"BR",
    "gn:dem":953,
    "gn:feature_class":"P",
    "gn:feature_code":"PPL",
    "gn:name":"S\u00edtio Ant\u00f4nio Francisco",
    "gn:population":0,
    "gn:timezone":"America/Sao_Paulo",
    "iso:country":"BR",
    "name:por_x_preferred":[
        "S\u00edtio Ant\u00f4nio Francisco"
    ],
    "wof:name":"Sitio Antonio Francisco",
    "wof:placetype":"locality"
},
  "geometry": {"coordinates":[-50.75806,-23.80795],"type":"Point"}
}