{
  "type": "Feature",
  "properties": {
    "gn:admin1_code":"20",
    "gn:admin2_code":"2207751.0",
    "gn:asciiname":"Jenipapeiro",
    "gn:country_code":"BR",
    "gn:dem":148,
    "gn:feature_class":"P",
    "gn:feature_code":"PPL",
    "gn:name":"Jenipapeiro",
    "gn:population":0,
    "gn:timezone":"America/Fortaleza",
    "iso:country":"BR",
    "wof:name":"Jenipapeiro",
    "wof:placetype":"locality"
},
  "geometry": {"coordinates":[-42.31667,-5.81667],"type":"Point"}
}