{
  "type": "Feature",
  "properties": {
    "gn:admin1_code":"06",
    "gn:admin2_code":"2312205.0",
    "gn:asciiname":"Fazenda Jua",
    "gn:country_code":"BR",
    "gn:dem":236,
    "gn:feature_class":"P",
    "gn:feature_code":"PPL",
    "gn:name":"Fazenda Ju\u00e1",
    "gn:population":0,
    "gn:timezone":"America/Fortaleza",
    "iso:country":"BR",
    "wof:name":"Fazenda Jua",
    "wof:placetype":"locality"
},
  "geometry": {"coordinates":[-39.95,-4.28333],"type":"Point"}
}