{
  "type": "Feature",
  "properties": {
    "gn:admin1_code":"2.0",
    "gn:admin2_code":"2702306.0",
    "gn:asciiname":"Parana",
    "gn:country_code":"BR",
    "gn:dem":21,
    "gn:feature_class":"P",
    "gn:feature_code":"PPL",
    "gn:name":"Paran\u00e1",
    "gn:population":0,
    "gn:timezone":"America/Maceio",
    "iso:country":"BR",
    "name:por_x_preferred":[
        "Paran\u00e1"
    ],
    "wof:name":"Parana",
    "wof:placetype":"locality"
},
  "geometry": {"coordinates":[-36.27386,-10.11968],"type":"Point"}
}