{
  "type": "Feature",
  "properties": {
    "gn:admin1_code":"20",
    "gn:admin2_code":"2200905.0",
    "gn:asciiname":"Mocambo",
    "gn:country_code":"BR",
    "gn:dem":169,
    "gn:feature_class":"P",
    "gn:feature_code":"PPL",
    "gn:name":"Mocambo",
    "gn:population":0,
    "gn:timezone":"America/Fortaleza",
    "iso:country":"BR",
    "wof:name":"Mocambo",
    "wof:placetype":"locality"
},
  "geometry": {"coordinates":[-41.91667,-6.08333],"type":"Point"}
}