{
  "type": "Feature",
  "properties": {
    "gn:admin1_code":"27",
    "gn:admin2_code":"3518305.0",
    "gn:asciiname":"Stio Toli",
    "gn:country_code":"BR",
    "gn:dem":675,
    "gn:feature_class":"P",
    "gn:feature_code":"PPL",
    "gn:name":"Stio Toli",
    "gn:population":0,
    "gn:timezone":"America/Sao_Paulo",
    "iso:country":"BR",
    "name:por_x_preferred":[
        "Stio Toli"
    ],
    "wof:name":"Stio Toli",
    "wof:placetype":"locality"
},
  "geometry": {"coordinates":[-46.1258,-23.4141],"type":"Point"}
}