{
  "type": "Feature",
  "properties": {
    "iso:country":"BR",
    "name:cat_x_preferred":[
        "Retiro"
    ],
    "name:ceb_x_preferred":[
        "Retiro"
    ],
    "name:deu_x_preferred":[
        "Retiro"
    ],
    "name:eus_x_preferred":[
        "Retiro"
    ],
    "name:fra_x_preferred":[
        "Retiro"
    ],
    "name:ita_x_preferred":[
        "Retiro"
    ],
    "name:jpn_x_preferred":[
        "\u30ec\u30c6\u30a3\u30fc\u30ed"
    ],
    "name:kor_x_preferred":[
        "\ub808\ud2f0\ub85c"
    ],
    "name:mlg_x_preferred":[
        "Retiro"
    ],
    "name:nld_x_preferred":[
        "Retiro"
    ],
    "name:pol_x_preferred":[
        "Retiro"
    ],
    "name:por_x_preferred":[
        "Retiro"
    ],
    "name:rus_x_preferred":[
        "\u0420\u0435\u0442\u0438\u0440\u043e"
    ],
    "name:sco_x_preferred":[
        "Retiro"
    ],
    "name:spa_x_preferred":[
        "Retiro"
    ],
    "name:swe_x_preferred":[
        "Retiro"
    ],
    "name:ukr_x_preferred":[
        "\u0420\u0435\u0442\u0456\u0440\u043e"
    ],
    "name:vie_x_preferred":[
        "Retiro"
    ],
    "qs:gn_adm0_cc":"BR",
    "qs:gn_local":3463237,
    "qs:local_max":5086,
    "qs:local_sum":17720,
    "qs:localhoods":35,
    "qs:name":"Retiro",
    "qs:name_adm0":"Brasil",
    "qs:name_adm1":"Santa Catarina",
    "qs:name_adm2":"Florian\u00f3polis",
    "qs:name_local":"Florian\u00f3polis",
    "qs:photo_max":207,
    "qs:photo_sum":682,
    "qs:placetype":"Suburb",
    "qs:quad_count":34,
    "qs:woe_adm0":23424768,
    "qs:woe_adm1":2344867,
    "qs:woe_adm2":12581654,
    "qs:woe_lau":0,
    "qs:woe_local":455861,
    "qs:woe_ver":"7.10.0",
    "wof:lang":[
        "por"
    ],
    "wof:name":"Retiro",
    "wof:placetype":"neighbourhood"
},
  "geometry": {"coordinates":[-48.445537,-27.618575],"type":"Point"}
}