{
  "type": "Feature",
  "properties": {
    "gn:admin1_code":"18.0",
    "gn:admin2_code":"4112306.0",
    "gn:asciiname":"Sitio Joaquim Custodio Filho",
    "gn:country_code":"BR",
    "gn:dem":497,
    "gn:feature_class":"P",
    "gn:feature_code":"PPL",
    "gn:name":"S\u00edtio Joaquim Cust\u00f3dio Filho",
    "gn:population":0,
    "gn:timezone":"America/Sao_Paulo",
    "iso:country":"BR",
    "name:por_x_preferred":[
        "S\u00edtio Joaquim Cust\u00f3dio Filho"
    ],
    "wof:name":"Sitio Joaquim Custodio Filho",
    "wof:placetype":"locality"
},
  "geometry": {"coordinates":[-50.19721,-23.6332],"type":"Point"}
}