{
  "type": "Feature",
  "properties": {
    "gn:admin1_code":"21",
    "gn:admin2_code":"3302502.0",
    "gn:asciiname":"Fragoso",
    "gn:country_code":"BR",
    "gn:dem":22,
    "gn:feature_class":"P",
    "gn:feature_code":"PPL",
    "gn:name":"Fragoso",
    "gn:population":0,
    "gn:timezone":"America/Sao_Paulo",
    "iso:country":"BR",
    "name:ceb_x_preferred":[
        "Fragoso"
    ],
    "name:deu_x_preferred":[
        "Fragoso"
    ],
    "name:kaz_x_preferred":[
        "\u0424\u0440\u0430\u0433\u043e\u0437\u0443"
    ],
    "name:nld_x_preferred":[
        "Fragoso"
    ],
    "name:por_x_preferred":[
        "Fragoso"
    ],
    "name:rus_x_preferred":[
        "\u0424\u0440\u0430\u0433\u043e\u0437\u0443"
    ],
    "name:spa_x_preferred":[
        "Fragoso"
    ],
    "name:ukr_x_preferred":[
        "\u0424\u0440\u0430\u0433\u043e\u0437\u0443"
    ],
    "wof:name":"Fragoso",
    "wof:placetype":"locality"
},
  "geometry": {"coordinates":[-43.18333,-22.58889],"type":"Point"}
}