{
  "type": "Feature",
  "properties": {
    "gn:admin1_code":"21",
    "gn:admin2_code":"3302502.0",
    "gn:asciiname":"Fragoso",
    "gn:country_code":"BR",
    "gn:dem":22,
    "gn:feature_class":"P",
    "gn:feature_code":"PPL",
    "gn:name":"Fragoso",
    "gn:population":0,
    "gn:timezone":"America/Sao_Paulo",
    "iso:country":"BR",
    "name:por_x_preferred":[
        "Fragoso"
    ],
    "wof:name":"Fragoso",
    "wof:placetype":"locality"
},
  "geometry": {"coordinates":[-43.18333,-22.58889],"type":"Point"}
}