{
  "type": "Feature",
  "properties": {
    "gn:admin1_code":"27",
    "gn:admin2_code":"3538709.0",
    "gn:asciiname":"Sete Barracas",
    "gn:country_code":"BR",
    "gn:dem":544,
    "gn:feature_class":"P",
    "gn:feature_code":"PPL",
    "gn:name":"Sete Barracas",
    "gn:population":0,
    "gn:timezone":"America/Sao_Paulo",
    "iso:country":"BR",
    "name:por_x_preferred":[
        "Sete Barracas"
    ],
    "wof:name":"Sete Barracas",
    "wof:placetype":"locality"
},
  "geometry": {"coordinates":[-47.71667,-22.81667],"type":"Point"}
}