{
  "type": "Feature",
  "properties": {
    "gn:admin1_code":"16",
    "gn:admin2_code":"1504208.0",
    "gn:asciiname":"Viracao Grande",
    "gn:country_code":"BR",
    "gn:dem":100,
    "gn:feature_class":"P",
    "gn:feature_code":"PPL",
    "gn:name":"Vira\u00e7\u00e3o Grande",
    "gn:population":0,
    "gn:timezone":"America/Belem",
    "iso:country":"BR",
    "wof:name":"Viracao Grande",
    "wof:placetype":"locality"
},
  "geometry": {"coordinates":[-49.31667,-5.61667],"type":"Point"}
}