{
  "type": "Feature",
  "properties": {
    "gn:admin1_code":"15",
    "gn:admin2_code":"3103405.0",
    "gn:asciiname":"Baixa Quente",
    "gn:country_code":"BR",
    "gn:dem":399,
    "gn:feature_class":"P",
    "gn:feature_code":"PPL",
    "gn:name":"Baixa Quente",
    "gn:population":0,
    "gn:timezone":"America/Sao_Paulo",
    "iso:country":"BR",
    "name:por_x_preferred":[
        "Baixa Quente"
    ],
    "wof:name":"Baixa Quente",
    "wof:placetype":"locality"
},
  "geometry": {"coordinates":[-42.06667,-16.95],"type":"Point"}
}