{
  "type": "Feature",
  "properties": {
    "gn:admin1_code":"4",
    "gn:admin2_code":"1303536.0",
    "gn:asciiname":"Sitio Manoel dos Santos",
    "gn:country_code":"BR",
    "gn:dem":56,
    "gn:feature_class":"P",
    "gn:feature_code":"PPL",
    "gn:name":"S\u00edtio Manoel dos Santos",
    "gn:population":0,
    "gn:timezone":"America/Manaus",
    "iso:country":"BR",
    "wof:name":"Sitio Manoel dos Santos",
    "wof:placetype":"locality"
},
  "geometry": {"coordinates":[-60.28556,-1.46333],"type":"Point"}
}