{
  "type": "Feature",
  "properties": {
    "gn:admin1_code":"16.0",
    "gn:admin2_code":"1506807.0",
    "gn:asciiname":"Itapari",
    "gn:country_code":"BR",
    "gn:dem":25,
    "gn:feature_class":"P",
    "gn:feature_code":"PPL",
    "gn:name":"Itapari",
    "gn:population":0,
    "gn:timezone":"America/Santarem",
    "iso:country":"BR",
    "name:por_x_preferred":[
        "Itapari"
    ],
    "wof:name":"Itapari",
    "wof:placetype":"locality"
},
  "geometry": {"coordinates":[-54.90721,-2.43969],"type":"Point"}
}