{
  "type": "Feature",
  "properties": {
    "gn:admin1_code":"5",
    "gn:admin2_code":"2931509.0",
    "gn:asciiname":"Caraiba",
    "gn:country_code":"BR",
    "gn:dem":306,
    "gn:feature_class":"P",
    "gn:feature_code":"PPL",
    "gn:name":"Cara\u00edba",
    "gn:population":0,
    "gn:timezone":"America/Bahia",
    "iso:country":"BR",
    "name:est_x_preferred":[
        "Caraiba"
    ],
    "wof:name":"Caraiba",
    "wof:placetype":"locality"
},
  "geometry": {"coordinates":[-38.88333,-11.46667],"type":"Point"}
}