{
  "type": "Feature",
  "properties": {
    "gn:admin1_code":"11",
    "gn:admin2_code":"5006002.0",
    "gn:asciiname":"Anastacio",
    "gn:cc2":"BR",
    "gn:country_code":"BR",
    "gn:dem":370,
    "gn:feature_class":"P",
    "gn:feature_code":"PPL",
    "gn:name":"Anast\u00e1cio",
    "gn:population":0,
    "gn:timezone":"America/Campo_Grande",
    "iso:country":"BR",
    "name:und_x_variant":[
        "Fazenda Atan\u00e1cio",
        "Atam\u00e1sio",
        "Atanasio",
        "Anast\u00e1cio"
    ],
    "wof:name":"Anastacio",
    "wof:placetype":"locality"
},
  "geometry": {"coordinates":[-54.15,-21.51667],"type":"Point"}
}