{
  "type": "Feature",
  "properties": {
    "gn:admin1_code":"18.0",
    "gn:admin2_code":"4102703.0",
    "gn:asciiname":"Sitio Agua do Meio",
    "gn:country_code":"BR",
    "gn:dem":520,
    "gn:feature_class":"P",
    "gn:feature_code":"PPL",
    "gn:name":"S\u00edtio \u00c1gua do Meio",
    "gn:population":0,
    "gn:timezone":"America/Sao_Paulo",
    "iso:country":"BR",
    "name:por_x_preferred":[
        "S\u00edtio \u00c1gua do Meio"
    ],
    "wof:name":"Sitio Agua do Meio",
    "wof:placetype":"locality"
},
  "geometry": {"coordinates":[-50.1046,-23.0954],"type":"Point"}
}