{
  "type": "Feature",
  "properties": {
    "gn:country":"BR",
    "gn:fcode":"PPLA2",
    "gn:population":630008,
    "iso:country":"BR",
    "name:bpy_x_preferred":[
        "\u099c\u09be\u09ac\u09cb\u09f1\u09be\u099f\u09be\u0993 \u09a1\u09cb\u09b8 \u0997\u09c1\u09f1\u09be\u09b0\u09be\u09b0\u09be\u09aa\u09c7\u09b8"
    ],
    "name:bul_x_preferred":[
        "\u0416\u0430\u0431\u043e\u0430\u0442\u0430\u043e \u0434\u043e\u0441 \u0413\u0443\u0430\u0440\u0430\u0440\u0430\u043f\u0438\u0441"
    ],
    "name:jpn_x_preferred":[
        "\u30b8\u30e3\u30dc\u30a2\u30bf\u30f3\u30fb\u30c9\u30b9\u30fb\u30b0\u30a2\u30e9\u30e9\u30da\u30b9"
    ],
    "name:kaz_x_preferred":[
        "\u0416\u0430\u0431\u043e\u0430\u0442\u0430\u043d-\u0434\u0443\u0441-\u0413\u0443\u0430\u0440\u0430\u0440\u0430\u043f\u0438\u0441"
    ],
    "name:kor_x_preferred":[
        "\uc790\ubcf4\uc544\ud0d5\ub450\uc2a4\uad6c\uc544\ub77c\ub77c\ud398\uc2a4"
    ],
    "name:rus_x_preferred":[
        "\u0416\u0430\u0431\u043e\u0430\u0442\u0430\u043d-\u0434\u0443\u0441-\u0413\u0443\u0430\u0440\u0430\u0440\u0430\u043f\u0438\u0441"
    ],
    "name:srp_x_preferred":[
        "\u0416\u0430\u0431\u043e\u0430\u0442\u0430\u043e \u0434\u043e\u0441 \u0413\u0432\u0430\u0440\u0430\u0440\u0430\u043f\u0435\u0441"
    ],
    "name:ukr_x_preferred":[
        "\u0416\u0430\u0431\u0443\u0430\u0442\u0430\u043d-\u0434\u0443\u0441-\u0413\u0443\u0430\u0440\u0430\u0440\u0430\u043f\u0456\u0441"
    ],
    "name:zho_x_preferred":[
        "\u71b1\u535a\u963f\u9676"
    ],
    "qs_pg:aaroncc":"BR",
    "qs_pg:gn_country":"BR",
    "qs_pg:gn_fcode":"PPLA2",
    "qs_pg:gn_pop":630008,
    "qs_pg:name":"Jaboat\u00e3o Dos Guararapes",
    "qs_pg:name_adm0":"Brasil",
    "qs_pg:name_adm1":"Pernambuco",
    "qs_pg:photos_9r":0,
    "qs_pg:photos_sr":0,
    "qs_pg:pop_sr":11,
    "qs_pg:qs_pg_placetype":"neighbourhood",
    "qs_pg:qs_pg_placetype_gp":"Suburb",
    "qs_pg:woe_adm0":23424768,
    "woe:adm0_id":23424768,
    "woe:name_adm0":"Brasil",
    "woe:name_adm1":"Pernambuco",
    "woe:placetype":"Suburb",
    "wof:name":"Jaboat\u00e3o Dos Guararapes",
    "wof:placetype":"neighbourhood",
    "wof:population":630008
},
  "geometry": {"coordinates":[-35.01472,-8.11278],"type":"Point"}
}