{
  "type": "Feature",
  "properties": {
    "gn:admin1_code":"5",
    "gn:admin2_code":"2923407.0",
    "gn:asciiname":"Saco do Muquem",
    "gn:country_code":"BR",
    "gn:dem":456,
    "gn:feature_class":"P",
    "gn:feature_code":"PPL",
    "gn:name":"Saco do Muqu\u00e9m",
    "gn:population":0,
    "gn:timezone":"America/Bahia",
    "iso:country":"BR",
    "wof:name":"Saco do Muquem",
    "wof:placetype":"locality"
},
  "geometry": {"coordinates":[-43.36667,-14.01667],"type":"Point"}
}