{
  "type": "Feature",
  "properties": {
    "gn:admin1_code":"05",
    "gn:admin2_code":"2930204.0",
    "gn:asciiname":"Trairas",
    "gn:country_code":"BR",
    "gn:dem":385,
    "gn:feature_class":"P",
    "gn:feature_code":"PPL",
    "gn:name":"Tra\u00edras",
    "gn:population":0,
    "gn:timezone":"America/Bahia",
    "iso:country":"BR",
    "wof:name":"Trairas",
    "wof:placetype":"locality"
},
  "geometry": {"coordinates":[-41.63333,-9.71667],"type":"Point"}
}