{
  "type": "Feature",
  "properties": {
    "gn:admin1_code":"18",
    "gn:admin2_code":"4104907.0",
    "gn:asciiname":"Capao",
    "gn:cc2":"BR",
    "gn:country_code":"BR",
    "gn:dem":976,
    "gn:feature_class":"P",
    "gn:feature_code":"PPL",
    "gn:name":"Cap\u00e3o",
    "gn:population":0,
    "gn:timezone":"America/Sao_Paulo",
    "iso:country":"BR",
    "name:und_x_variant":[
        "Cap\u00e3o Alto",
        "Cap\u00e3o"
    ],
    "wof:name":"Capao",
    "wof:placetype":"locality"
},
  "geometry": {"coordinates":[-49.95,-24.75],"type":"Point"}
}