{
  "type": "Feature",
  "properties": {
    "gn:admin1_code":"15",
    "gn:admin2_code":"3150901.0",
    "gn:asciiname":"Sitio Benedito Pereira da Silva",
    "gn:country_code":"BR",
    "gn:dem":873,
    "gn:feature_class":"P",
    "gn:feature_code":"PPL",
    "gn:name":"S\u00edtio Benedito Pereira da Silva",
    "gn:population":0,
    "gn:timezone":"America/Sao_Paulo",
    "iso:country":"BR",
    "name:por_x_preferred":[
        "S\u00edtio Benedito Pereira da Silva"
    ],
    "wof:name":"Sitio Benedito Pereira da Silva",
    "wof:placetype":"locality"
},
  "geometry": {"coordinates":[-45.5233,-22.5014],"type":"Point"}
}