{
  "type": "Feature",
  "properties": {
    "gn:admin1_code":"18",
    "gn:admin2_code":"4124400.0",
    "gn:asciiname":"Aurora",
    "gn:country_code":"BR",
    "gn:dem":549,
    "gn:feature_class":"P",
    "gn:feature_code":"PPL",
    "gn:name":"Aurora",
    "gn:population":0,
    "gn:timezone":"America/Sao_Paulo",
    "iso:country":"BR",
    "wof:name":"Aurora",
    "wof:placetype":"locality"
},
  "geometry": {"coordinates":[-53.68806,-26.06083],"type":"Point"}
}