{
  "type": "Feature",
  "properties": {
    "gn:admin1_code":"26",
    "gn:admin2_code":"4202701.0",
    "gn:asciiname":"Ribeirao do Ouro",
    "gn:country_code":"BR",
    "gn:dem":273,
    "gn:feature_class":"P",
    "gn:feature_code":"PPL",
    "gn:name":"Ribeir\u00e3o do Ouro",
    "gn:population":0,
    "gn:timezone":"America/Sao_Paulo",
    "iso:country":"BR",
    "wof:name":"Ribeirao do Ouro",
    "wof:placetype":"locality"
},
  "geometry": {"coordinates":[-49.13349,-27.20406],"type":"Point"}
}