{
  "type": "Feature",
  "properties": {
    "gn:admin1_code":"15",
    "gn:admin2_code":"3100906.0",
    "gn:asciiname":"Maranhao",
    "gn:country_code":"BR",
    "gn:dem":496,
    "gn:feature_class":"P",
    "gn:feature_code":"PPLL",
    "gn:name":"Maranh\u00e3o",
    "gn:population":0,
    "gn:timezone":"America/Sao_Paulo",
    "iso:country":"BR",
    "wof:name":"Maranhao",
    "wof:placetype":"locality"
},
  "geometry": {"coordinates":[-40.98556,-17.09167],"type":"Point"}
}