{
  "type": "Feature",
  "properties": {
    "gn:admin1_code":"21",
    "gn:admin2_code":"3300233.0",
    "gn:asciiname":"Manguinhos",
    "gn:country_code":"BR",
    "gn:dem":7,
    "gn:feature_class":"P",
    "gn:feature_code":"PPL",
    "gn:name":"Manguinhos",
    "gn:population":0,
    "gn:timezone":"America/Sao_Paulo",
    "iso:country":"BR",
    "name:por_x_preferred":[
        "Manguinhos"
    ],
    "wof:name":"Manguinhos",
    "wof:placetype":"locality"
},
  "geometry": {"coordinates":[-41.93333,-22.78333],"type":"Point"}
}