{
  "type": "Feature",
  "properties": {
    "gn:admin1_code":"27.0",
    "gn:admin2_code":"3550308.0",
    "gn:asciiname":"Sitio do Moinho Pacifico",
    "gn:country_code":"BR",
    "gn:dem":810,
    "gn:feature_class":"P",
    "gn:feature_code":"PPL",
    "gn:name":"S\u00edtio do Moinho Pac\u00edfico",
    "gn:population":0,
    "gn:timezone":"America/Sao_Paulo",
    "iso:country":"BR",
    "name:por_x_preferred":[
        "S\u00edtio do Moinho Pac\u00edfico"
    ],
    "wof:name":"Sitio do Moinho Pacifico",
    "wof:placetype":"locality"
},
  "geometry": {"coordinates":[-46.7356,-23.8517],"type":"Point"}
}