{
  "type": "Feature",
  "properties": {
    "gn:admin1_code":"15",
    "gn:admin2_code":"3128600.0",
    "gn:asciiname":"Cangalhas",
    "gn:cc2":"BR",
    "gn:country_code":"BR",
    "gn:dem":964,
    "gn:feature_class":"P",
    "gn:feature_code":"PPL",
    "gn:name":"Cangalhas",
    "gn:population":0,
    "gn:timezone":"America/Sao_Paulo",
    "iso:country":"BR",
    "name:und_x_variant":[
        "Cangalha",
        "Cangalhas"
    ],
    "wof:name":"Cangalhas",
    "wof:placetype":"locality"
},
  "geometry": {"coordinates":[-47.18333,-17.66667],"type":"Point"}
}