{
  "type": "Feature",
  "properties": {
    "gn:admin1_code":"26",
    "gn:admin2_code":"4210100.0",
    "gn:asciiname":"Sitio Lili Neider",
    "gn:country_code":"BR",
    "gn:dem":847,
    "gn:feature_class":"P",
    "gn:feature_code":"PPL",
    "gn:name":"S\u00edtio Lili Neider",
    "gn:population":0,
    "gn:timezone":"America/Sao_Paulo",
    "iso:country":"BR",
    "name:por_x_preferred":[
        "S\u00edtio Lili Neider"
    ],
    "wof:name":"Sitio Lili Neider",
    "wof:placetype":"locality"
},
  "geometry": {"coordinates":[-49.62629,-26.22416],"type":"Point"}
}