{
  "type": "Feature",
  "properties": {
    "gn:admin1_code":"18.0",
    "gn:admin2_code":"4109708.0",
    "gn:asciiname":"Sitio Luiz F. F. Fader",
    "gn:country_code":"BR",
    "gn:dem":691,
    "gn:feature_class":"P",
    "gn:feature_code":"PPL",
    "gn:name":"S\u00edtio Luiz F. F. Fader",
    "gn:population":0,
    "gn:timezone":"America/Sao_Paulo",
    "iso:country":"BR",
    "name:por_x_preferred":[
        "S\u00edtio Luiz F. F. Fader"
    ],
    "wof:name":"Sitio Luiz F. F. Fader",
    "wof:placetype":"locality"
},
  "geometry": {"coordinates":[-50.15732,-23.84536],"type":"Point"}
}