{
  "type": "Feature",
  "properties": {
    "gn:admin1_code":"18.0",
    "gn:admin2_code":"4126207.0",
    "gn:asciiname":"Sitio Noel Rodrigues de Jesus",
    "gn:country_code":"BR",
    "gn:dem":755,
    "gn:feature_class":"P",
    "gn:feature_code":"PPL",
    "gn:name":"S\u00edtio Noel Rodrigues de Jesus",
    "gn:population":0,
    "gn:timezone":"America/Sao_Paulo",
    "iso:country":"BR",
    "name:por_x_preferred":[
        "S\u00edtio Noel Rodrigues de Jesus"
    ],
    "wof:name":"Sitio Noel Rodrigues de Jesus",
    "wof:placetype":"locality"
},
  "geometry": {"coordinates":[-50.64646,-23.89979],"type":"Point"}
}