{
  "type": "Feature",
  "properties": {
    "gn:country":"BR",
    "gn:fcode":"PPL",
    "gn:population":0,
    "iso:country":"BR",
    "name:und_x_variant":[
        "Jacareipe"
    ],
    "qs_pg:aaroncc":"BR",
    "qs_pg:gn_country":"BR",
    "qs_pg:gn_fcode":"PPL",
    "qs_pg:gn_pop":0,
    "qs_pg:name":"Jacara\u00edpe",
    "qs_pg:name_adm0":"Brasil",
    "qs_pg:name_adm1":"Esp\u00edrito Santo",
    "qs_pg:photos":324,
    "qs_pg:photos_1k":66,
    "qs_pg:photos_9k":1,
    "qs_pg:photos_9r":5,
    "qs_pg:photos_all":324,
    "qs_pg:photos_sr":5,
    "qs_pg:pop_sr":7,
    "qs_pg:qs_pg_placetype":"locality",
    "qs_pg:qs_pg_placetype_gp":"Town",
    "qs_pg:woe_adm0":23424768,
    "woe:adm0_id":23424768,
    "woe:name_adm0":"Brasil",
    "woe:name_adm1":"Esp\u00edrito Santo",
    "woe:placetype":"Town",
    "wof:name":"Jacara\u00edpe",
    "wof:placetype":"locality"
},
  "geometry": {"coordinates":[-40.18788,-20.13964],"type":"Point"}
}