{
  "type": "Feature",
  "properties": {
    "gn:admin1_code":"4",
    "gn:admin2_code":"1301308.0",
    "gn:asciiname":"Peritoro",
    "gn:country_code":"BR",
    "gn:dem":22,
    "gn:feature_class":"P",
    "gn:feature_code":"PPL",
    "gn:name":"Peritor\u00f3",
    "gn:population":0,
    "gn:timezone":"America/Manaus",
    "iso:country":"BR",
    "wof:name":"Peritoro",
    "wof:placetype":"locality"
},
  "geometry": {"coordinates":[-62.81,-3.22944],"type":"Point"}
}