{
  "type": "Feature",
  "properties": {
    "gn:admin1_code":"18.0",
    "gn:admin2_code":"4126603.0",
    "gn:asciiname":"Sitio Antonio Elias",
    "gn:country_code":"BR",
    "gn:dem":562,
    "gn:feature_class":"P",
    "gn:feature_code":"PPL",
    "gn:name":"S\u00edtio Ant\u00f4nio Elias",
    "gn:population":0,
    "gn:timezone":"America/Sao_Paulo",
    "iso:country":"BR",
    "name:por_x_preferred":[
        "S\u00edtio Ant\u00f4nio Elias"
    ],
    "wof:name":"Sitio Antonio Elias",
    "wof:placetype":"locality"
},
  "geometry": {"coordinates":[-49.7549,-23.6758],"type":"Point"}
}