{
  "type": "Feature",
  "properties": {
    "gn:admin1_code":"23",
    "gn:admin2_code":"4314902.0",
    "gn:asciiname":"Pintada",
    "gn:country_code":"BR",
    "gn:dem":1,
    "gn:feature_class":"P",
    "gn:feature_code":"PPL",
    "gn:name":"Pintada",
    "gn:population":0,
    "gn:timezone":"America/Sao_Paulo",
    "iso:country":"BR",
    "name:por_x_preferred":[
        "Pintada"
    ],
    "name:tgl_x_preferred":[
        "Pintada"
    ],
    "wof:name":"Pintada",
    "wof:placetype":"locality"
},
  "geometry": {"coordinates":[-51.25,-30.03333],"type":"Point"}
}