{
  "type": "Feature",
  "properties": {
    "gn:admin1_code":"18.0",
    "gn:admin2_code":"4126603.0",
    "gn:asciiname":"Sitio Alvaro M. Filho",
    "gn:country_code":"BR",
    "gn:dem":787,
    "gn:feature_class":"P",
    "gn:feature_code":"PPL",
    "gn:name":"S\u00edtio \u00c1lvaro M. Filho",
    "gn:population":0,
    "gn:timezone":"America/Sao_Paulo",
    "iso:country":"BR",
    "name:por_x_preferred":[
        "S\u00edtio \u00c1lvaro M. Filho"
    ],
    "wof:name":"Sitio Alvaro M. Filho",
    "wof:placetype":"locality"
},
  "geometry": {"coordinates":[-49.8621,-23.6293],"type":"Point"}
}