{
  "type": "Feature",
  "properties": {
    "gn:admin1_code":"06",
    "gn:admin2_code":"2312205.0",
    "gn:asciiname":"Fazenda Vargem da Cruz",
    "gn:country_code":"BR",
    "gn:dem":187,
    "gn:feature_class":"P",
    "gn:feature_code":"PPL",
    "gn:name":"Fazenda Vargem da Cruz",
    "gn:population":0,
    "gn:timezone":"America/Fortaleza",
    "iso:country":"BR",
    "wof:name":"Fazenda Vargem da Cruz",
    "wof:placetype":"locality"
},
  "geometry": {"coordinates":[-40.08333,-4.06667],"type":"Point"}
}