{
  "type": "Feature",
  "properties": {
    "gn:admin1_code":"18.0",
    "gn:admin2_code":"4113205.0",
    "gn:asciiname":"Palmital de Cima",
    "gn:country_code":"BR",
    "gn:dem":808,
    "gn:feature_class":"P",
    "gn:feature_code":"PPL",
    "gn:name":"Palmital de Cima",
    "gn:population":0,
    "gn:timezone":"America/Sao_Paulo",
    "iso:country":"BR",
    "name:por_x_preferred":[
        "Palmital de Cima"
    ],
    "wof:name":"Palmital de Cima",
    "wof:placetype":"locality"
},
  "geometry": {"coordinates":[-50.10509,-25.79991],"type":"Point"}
}