{
  "type": "Feature",
  "properties": {
    "gn:admin1_code":"26",
    "gn:admin2_code":"4205803.0",
    "gn:asciiname":"Porto Palmital",
    "gn:cc2":"BR",
    "gn:country_code":"BR",
    "gn:dem":21,
    "gn:feature_class":"P",
    "gn:feature_code":"PPL",
    "gn:name":"P\u00f4rto Palmital",
    "gn:population":0,
    "gn:timezone":"America/Sao_Paulo",
    "iso:country":"BR",
    "name:und_x_variant":[
        "P\u00f4rto do Palmital",
        "P\u00f4rto Palmital"
    ],
    "wof:name":"Porto Palmital",
    "wof:placetype":"locality"
},
  "geometry": {"coordinates":[-48.81667,-26.03333],"type":"Point"}
}