{
  "type": "Feature",
  "properties": {
    "iso:country":"BR",
    "ne:ADM0CAP":0.0,
    "ne:ADM0NAME":"Brazil",
    "ne:ADM0_A3":"BRA",
    "ne:ADM1NAME":"Rondinia",
    "ne:ADMIN1_COD":0,
    "ne:CAPALT":0,
    "ne:CHANGED":1,
    "ne:CHECKME":0,
    "ne:COMPARE":0,
    "ne:DIFFASCII":0,
    "ne:DIFFNOTE":"Changed scale rank.",
    "ne:ELEVATION":0.0,
    "ne:FEATURECLA":"Populated place",
    "ne:GEONAMEID":-1,
    "ne:GEONAMESNO":"No GeoNames match due to small population, not in GeoNames, or poor NEV placement.",
    "ne:GN_POP":0,
    "ne:GTOPO30":0.0,
    "ne:ISO_A2":"BR",
    "ne:LABELRANK":1,
    "ne:LATITUDE":-12.416672,
    "ne:LONGITUDE":-64.416647,
    "ne:LS_MATCH":1,
    "ne:LS_NAME":"Principe da Beira",
    "ne:MAX_AREAKM":2.0,
    "ne:MAX_AREAMI":1.0,
    "ne:MAX_BBXMAX":-64.416667,
    "ne:MAX_BBXMIN":-64.425,
    "ne:MAX_BBYMAX":-12.416667,
    "ne:MAX_BBYMIN":-12.433333,
    "ne:MAX_NATSCA":20.0,
    "ne:MAX_PERKM":5.0,
    "ne:MAX_PERMI":3.0,
    "ne:MAX_POP10":956,
    "ne:MAX_POP20":956,
    "ne:MAX_POP300":0,
    "ne:MAX_POP310":0,
    "ne:MAX_POP50":0,
    "ne:MEAN_BBXC":-64.420833,
    "ne:MEAN_BBYC":-12.425,
    "ne:MEGACITY":0,
    "ne:MIN_AREAKM":2.0,
    "ne:MIN_AREAMI":1.0,
    "ne:MIN_BBXMAX":-64.416667,
    "ne:MIN_BBXMIN":-64.425,
    "ne:MIN_BBYMAX":-12.416667,
    "ne:MIN_BBYMIN":-12.433333,
    "ne:MIN_PERKM":5.0,
    "ne:MIN_PERMI":3.0,
    "ne:NAME":"Principe da Beira",
    "ne:NAMEASCII":"Principe da Beira",
    "ne:NAMEDIFF":0,
    "ne:NATSCALE":30,
    "ne:POP1950":0,
    "ne:POP1955":0,
    "ne:POP1960":0,
    "ne:POP1965":0,
    "ne:POP1970":0,
    "ne:POP1975":0,
    "ne:POP1980":0,
    "ne:POP1985":0,
    "ne:POP1990":0,
    "ne:POP1995":0,
    "ne:POP2000":0,
    "ne:POP2005":0,
    "ne:POP2010":0,
    "ne:POP2015":0,
    "ne:POP2020":0,
    "ne:POP2025":0,
    "ne:POP2050":0,
    "ne:POP_MAX":956,
    "ne:POP_MIN":956,
    "ne:POP_OTHER":0,
    "ne:RANK_MAX":2,
    "ne:RANK_MIN":2,
    "ne:SCALERANK":6,
    "ne:SOV0NAME":"Brazil",
    "ne:SOV_A3":"BRA",
    "ne:UN_FID":0,
    "ne:UN_LAT":0.0,
    "ne:UN_LONG":0.0,
    "ne:WORLDCITY":0,
    "ne:min_zoom":6.0,
    "wof:name":"Principe da Beira",
    "wof:placetype":"locality"
},
  "geometry": {"coordinates":[-64.41664717777911,-12.4166723441088],"type":"Point"}
}