{
  "type": "Feature",
  "properties": {
    "gn:admin1_code":"18",
    "gn:admin2_code":"4113700.0",
    "gn:asciiname":"Iandrinopolis",
    "gn:country_code":"BR",
    "gn:dem":778,
    "gn:feature_class":"P",
    "gn:feature_code":"PPL",
    "gn:name":"Iandrin\u00f3polis",
    "gn:population":0,
    "gn:timezone":"America/Sao_Paulo",
    "iso:country":"BR",
    "wof:name":"Iandrinopolis",
    "wof:placetype":"locality"
},
  "geometry": {"coordinates":[-51.08333,-23.68333],"type":"Point"}
}