{
  "type": "Feature",
  "properties": {
    "gn:admin1_code":"11",
    "gn:admin2_code":"5005004.0",
    "gn:asciiname":"Santa Livrada",
    "gn:cc2":"BR",
    "gn:country_code":"BR",
    "gn:dem":434,
    "gn:feature_class":"P",
    "gn:feature_code":"PPL",
    "gn:name":"Santa Livrada",
    "gn:population":0,
    "gn:timezone":"America/Campo_Grande",
    "iso:country":"BR",
    "name:und_x_variant":[
        "Santa Livrado",
        "Santa Livrada"
    ],
    "wof:name":"Santa Livrada",
    "wof:placetype":"locality"
},
  "geometry": {"coordinates":[-56.68333000000001,-21.55],"type":"Point"}
}