{
  "type": "Feature",
  "properties": {
    "gn:admin1_code":"15",
    "gn:admin2_code":"3120706.0",
    "gn:asciiname":"Jacu",
    "gn:country_code":"BR",
    "gn:dem":939,
    "gn:feature_class":"P",
    "gn:feature_code":"PPL",
    "gn:name":"Jacu",
    "gn:population":0,
    "gn:timezone":"America/Sao_Paulo",
    "iso:country":"BR",
    "name:por_x_preferred":[
        "Jacu"
    ],
    "name:ukr_x_preferred":[
        "\u0416\u0430\u043a\u0443"
    ],
    "wof:name":"Jacu",
    "wof:placetype":"locality"
},
  "geometry": {"coordinates":[-46.66667,-19.01667],"type":"Point"}
}