{
  "type": "Feature",
  "properties": {
    "gn:admin1_code":"5",
    "gn:admin2_code":"2929305.0",
    "gn:asciiname":"Tupinamba",
    "gn:country_code":"BR",
    "gn:dem":207,
    "gn:feature_class":"P",
    "gn:feature_code":"PPL",
    "gn:name":"Tupinamb\u00e1",
    "gn:population":0,
    "gn:timezone":"America/Bahia",
    "iso:country":"BR",
    "wof:name":"Tupinamba",
    "wof:placetype":"locality"
},
  "geometry": {"coordinates":[-38.98333,-12.45],"type":"Point"}
}