{
  "type": "Feature",
  "properties": {
    "gn:admin1_code":"4",
    "gn:admin2_code":"1303809.0",
    "gn:asciiname":"Macuxixiri",
    "gn:cc2":"BR",
    "gn:country_code":"BR",
    "gn:dem":112,
    "gn:feature_class":"P",
    "gn:feature_code":"PPL",
    "gn:name":"Macuxixiri",
    "gn:population":0,
    "gn:timezone":"America/Manaus",
    "iso:country":"BR",
    "name:und_x_variant":[
        "Macuxiri",
        "Macuxixiri"
    ],
    "wof:name":"Macuxixiri",
    "wof:placetype":"locality"
},
  "geometry": {"coordinates":[-67.28333000000001,1.76667],"type":"Point"}
}