{
  "type": "Feature",
  "properties": {
    "gn:admin1_code":"15",
    "gn:admin2_code":"3108552.0",
    "gn:asciiname":"Sergio Correia",
    "gn:country_code":"BR",
    "gn:dem":512,
    "gn:feature_class":"P",
    "gn:feature_code":"PPL",
    "gn:name":"S\u00e9rgio Correia",
    "gn:population":0,
    "gn:timezone":"America/Sao_Paulo",
    "iso:country":"BR",
    "name:por_x_preferred":[
        "S\u00e9rgio Correia"
    ],
    "wof:name":"Sergio Correia",
    "wof:placetype":"locality"
},
  "geometry": {"coordinates":[-45.53333,-17.01667],"type":"Point"}
}