{
  "type": "Feature",
  "properties": {
    "gn:admin1_code":"5",
    "gn:admin2_code":"2911105.0",
    "gn:asciiname":"Brejao",
    "gn:country_code":"BR",
    "gn:dem":522,
    "gn:feature_class":"P",
    "gn:feature_code":"PPL",
    "gn:name":"Brej\u00e3o",
    "gn:population":0,
    "gn:timezone":"America/Bahia",
    "iso:country":"BR",
    "wof:name":"Brejao",
    "wof:placetype":"locality"
},
  "geometry": {"coordinates":[-45.71472,-10.93861],"type":"Point"}
}