{
  "type": "Feature",
  "properties": {
    "gn:admin1_code":"13",
    "gn:admin2_code":"2105989.0",
    "gn:asciiname":"Morro do Sal",
    "gn:country_code":"BR",
    "gn:dem":315,
    "gn:feature_class":"P",
    "gn:feature_code":"PPL",
    "gn:name":"Morro do Sal",
    "gn:population":0,
    "gn:timezone":"America/Fortaleza",
    "iso:country":"BR",
    "wof:name":"Morro do Sal",
    "wof:placetype":"locality"
},
  "geometry": {"coordinates":[-46.75,-6.01667],"type":"Point"}
}