{
  "type": "Feature",
  "properties": {
    "gn:admin1_code":"27",
    "gn:admin2_code":"3546801.0",
    "gn:asciiname":"Stio Bela Vista",
    "gn:country_code":"BR",
    "gn:dem":700,
    "gn:feature_class":"P",
    "gn:feature_code":"PPL",
    "gn:name":"Stio Bela Vista",
    "gn:population":0,
    "gn:timezone":"America/Sao_Paulo",
    "iso:country":"BR",
    "name:por_x_preferred":[
        "Stio Bela Vista"
    ],
    "wof:name":"Stio Bela Vista",
    "wof:placetype":"locality"
},
  "geometry": {"coordinates":[-46.2367,-23.2805],"type":"Point"}
}