{
  "type": "Feature",
  "properties": {
    "gn:admin1_code":"02",
    "gn:admin2_code":"2706406.0",
    "gn:asciiname":"Palma",
    "gn:country_code":"BR",
    "gn:dem":174,
    "gn:feature_class":"P",
    "gn:feature_code":"PPL",
    "gn:name":"Palma",
    "gn:population":0,
    "gn:timezone":"America/Maceio",
    "iso:country":"BR",
    "wof:name":"Palma",
    "wof:placetype":"locality"
},
  "geometry": {"coordinates":[-37.35,-9.65],"type":"Point"}
}