{
  "type": "Feature",
  "properties": {
    "gn:admin1_code":"17",
    "gn:admin2_code":"2513356.0",
    "gn:asciiname":"Lagoa do Vieira",
    "gn:country_code":"BR",
    "gn:dem":679,
    "gn:feature_class":"P",
    "gn:feature_code":"PPL",
    "gn:name":"Lagoa do Vieira",
    "gn:population":0,
    "gn:timezone":"America/Fortaleza",
    "iso:country":"BR",
    "wof:name":"Lagoa do Vieira",
    "wof:placetype":"locality"
},
  "geometry": {"coordinates":[-38.56667,-7.73333],"type":"Point"}
}