{
  "type": "Feature",
  "properties": {
    "gn:admin1_code":"27.0",
    "gn:admin2_code":"3550308.0",
    "gn:asciiname":"Sitio Mira Flores",
    "gn:country_code":"BR",
    "gn:dem":791,
    "gn:feature_class":"P",
    "gn:feature_code":"PPL",
    "gn:name":"S\u00edtio Mira Flores",
    "gn:population":0,
    "gn:timezone":"America/Sao_Paulo",
    "iso:country":"BR",
    "name:por_x_preferred":[
        "S\u00edtio Mira Flores"
    ],
    "wof:name":"Sitio Mira Flores",
    "wof:placetype":"locality"
},
  "geometry": {"coordinates":[-46.7342,-23.8947],"type":"Point"}
}