{
  "type": "Feature",
  "properties": {
    "gn:admin1_code":"18.0",
    "gn:admin2_code":"4109500.0",
    "gn:asciiname":"Barra do Poruquara",
    "gn:country_code":"BR",
    "gn:dem":4,
    "gn:feature_class":"P",
    "gn:feature_code":"PPLL",
    "gn:name":"Barra do Poruquara",
    "gn:population":0,
    "gn:timezone":"America/Sao_Paulo",
    "iso:country":"BR",
    "name:por_x_preferred":[
        "Barra do Poruquara"
    ],
    "wof:name":"Barra do Poruquara",
    "wof:placetype":"locality"
},
  "geometry": {"coordinates":[-48.27403,-25.30453],"type":"Point"}
}