{
  "type": "Feature",
  "properties": {
    "gn:admin1_code":"13",
    "gn:admin2_code":"2110005.0",
    "gn:asciiname":"Muricoca",
    "gn:country_code":"BR",
    "gn:dem":264,
    "gn:feature_class":"P",
    "gn:feature_code":"PPL",
    "gn:name":"Muri\u00e7oca",
    "gn:population":0,
    "gn:timezone":"America/Fortaleza",
    "iso:country":"BR",
    "wof:name":"Muricoca",
    "wof:placetype":"locality"
},
  "geometry": {"coordinates":[-45.71667,-4.41667],"type":"Point"}
}