{
  "type": "Feature",
  "properties": {
    "gn:admin1_code":"16",
    "gn:admin2_code":"1501006.0",
    "gn:asciiname":"Maracajatuba",
    "gn:country_code":"BR",
    "gn:dem":37,
    "gn:feature_class":"P",
    "gn:feature_code":"PPL",
    "gn:name":"Maracajatuba",
    "gn:population":0,
    "gn:timezone":"America/Santarem",
    "iso:country":"BR",
    "wof:name":"Maracajatuba",
    "wof:placetype":"locality"
},
  "geometry": {"coordinates":[-56.45,-3.41667],"type":"Point"}
}