{
  "type": "Feature",
  "properties": {
    "gn:admin1_code":"30",
    "gn:admin2_code":"2613107.0",
    "gn:asciiname":"Jaboticaba",
    "gn:country_code":"BR",
    "gn:dem":594,
    "gn:feature_class":"P",
    "gn:feature_code":"PPL",
    "gn:name":"Jaboticaba",
    "gn:population":0,
    "gn:timezone":"America/Recife",
    "iso:country":"BR",
    "wof:name":"Jaboticaba",
    "wof:placetype":"locality"
},
  "geometry": {"coordinates":[-36.15,-8.35],"type":"Point"}
}