{
  "type": "Feature",
  "properties": {
    "gn:admin1_code":"13",
    "gn:admin2_code":"2102804.0",
    "gn:asciiname":"Serrinha",
    "gn:country_code":"BR",
    "gn:dem":341,
    "gn:feature_class":"P",
    "gn:feature_code":"PPL",
    "gn:name":"Serrinha",
    "gn:population":0,
    "gn:timezone":"America/Fortaleza",
    "iso:country":"BR",
    "wof:name":"Serrinha",
    "wof:placetype":"locality"
},
  "geometry": {"coordinates":[-46.95,-7.91667],"type":"Point"}
}