{
  "type": "Feature",
  "properties": {
    "gn:admin1_code":"13",
    "gn:admin2_code":"2102804.0",
    "gn:asciiname":"Serrinha",
    "gn:country_code":"BR",
    "gn:dem":341,
    "gn:feature_class":"P",
    "gn:feature_code":"PPL",
    "gn:name":"Serrinha",
    "gn:population":0,
    "gn:timezone":"America/Fortaleza",
    "iso:country":"BR",
    "name:ara_x_preferred":[
        "\u0633\u064a\u0631\u064a\u0646\u064a\u0627"
    ],
    "name:ben_x_preferred":[
        "\u09b8\u09c7\u09b0\u09b0\u09bf\u09a8\u09b9\u09be"
    ],
    "name:bpy_x_preferred":[
        "\u09b8\u09c7\u09b0\u09b0\u09bf\u09a8\u09b9\u09be"
    ],
    "name:deu_x_preferred":[
        "Serrinha"
    ],
    "name:ell_x_preferred":[
        "\u03a3\u03b5\u03c1\u03af\u03bd\u03b9\u03b1"
    ],
    "name:epo_x_preferred":[
        "Serrinha"
    ],
    "name:eus_x_preferred":[
        "Serrinha"
    ],
    "name:fas_x_preferred":[
        "\u0633\u0631\u06cc\u0646\u0647\u0627"
    ],
    "name:fra_x_preferred":[
        "Serrinha"
    ],
    "name:heb_x_preferred":[
        "\u05e1\u05e8\u05d9\u05e0\u05d7\u05d4"
    ],
    "name:hin_x_preferred":[
        "\u0938\u0947\u0930\u094d\u0930\u093f\u0902\u0939\u093e"
    ],
    "name:hye_x_preferred":[
        "\u054d\u0565\u057c\u056b\u0576\u056b\u0561"
    ],
    "name:ind_x_preferred":[
        "Serrinha"
    ],
    "name:ita_x_preferred":[
        "Serrinha"
    ],
    "name:jpn_x_preferred":[
        "\u30bb\u30ea\u30cb\u30e3"
    ],
    "name:kat_x_preferred":[
        "\u10e1\u10d4\u10e0\u10d8\u10dc\u10d8\u10d0"
    ],
    "name:kaz_x_preferred":[
        "\u0421\u0435\u0440\u0440\u0438\u043d\u044c\u044f"
    ],
    "name:kor_x_preferred":[
        "\uc138\ub9ac\ub0d0"
    ],
    "name:mlg_x_preferred":[
        "Serrinha"
    ],
    "name:nld_x_preferred":[
        "Serrinha"
    ],
    "name:nor_x_preferred":[
        "Serrinha"
    ],
    "name:pol_x_preferred":[
        "Serrinha"
    ],
    "name:por_x_preferred":[
        "Serrinha"
    ],
    "name:ron_x_preferred":[
        "Serrinha"
    ],
    "name:rus_x_preferred":[
        "\u0421\u0435\u0440\u0440\u0438\u043d\u044c\u044f"
    ],
    "name:spa_x_preferred":[
        "Serrinha"
    ],
    "name:tur_x_preferred":[
        "Serrinha"
    ],
    "name:ukr_x_preferred":[
        "\u0421\u0435\u0440\u0440\u0456\u043d\u044c\u044f"
    ],
    "name:urd_x_preferred":[
        "\u0633\u06cc\u0631\u06cc\u0646\u06be\u0627"
    ],
    "name:vie_x_preferred":[
        "Serrinha"
    ],
    "name:vol_x_preferred":[
        "Serrinha"
    ],
    "name:war_x_preferred":[
        "Serrinha"
    ],
    "name:zho_x_preferred":[
        "\u585e\u91cc\u5c3c\u4e9a"
    ],
    "wof:name":"Serrinha",
    "wof:placetype":"locality"
},
  "geometry": {"coordinates":[-46.95,-7.91667],"type":"Point"}
}