{
  "type": "Feature",
  "properties": {
    "gn:admin1_code":"13",
    "gn:admin2_code":"2102804.0",
    "gn:asciiname":"Serrinha",
    "gn:country_code":"BR",
    "gn:dem":341,
    "gn:feature_class":"P",
    "gn:feature_code":"PPL",
    "gn:name":"Serrinha",
    "gn:population":0,
    "gn:timezone":"America/Fortaleza",
    "iso:country":"BR",
    "name:bpy_x_preferred":[
        "\u09b8\u09c7\u09b0\u09b0\u09bf\u09a8\u09b9\u09be"
    ],
    "name:deu_x_preferred":[
        "Serrinha"
    ],
    "name:epo_x_preferred":[
        "Serrinha"
    ],
    "name:eus_x_preferred":[
        "Serrinha"
    ],
    "name:fra_x_preferred":[
        "Serrinha"
    ],
    "name:hye_x_preferred":[
        "\u054d\u0565\u057c\u056b\u0576\u056b\u0561"
    ],
    "name:ita_x_preferred":[
        "Serrinha"
    ],
    "name:kat_x_preferred":[
        "\u10e1\u10d4\u10e0\u10d8\u10dc\u10d8\u10d0"
    ],
    "name:kaz_x_preferred":[
        "\u0421\u0435\u0440\u0440\u0438\u043d\u044c\u044f"
    ],
    "name:kor_x_preferred":[
        "\uc138\ub9ac\ub0d0"
    ],
    "name:mlg_x_preferred":[
        "Serrinha"
    ],
    "name:nld_x_preferred":[
        "Serrinha"
    ],
    "name:nor_x_preferred":[
        "Serrinha"
    ],
    "name:pol_x_preferred":[
        "Serrinha"
    ],
    "name:por_x_preferred":[
        "Serrinha"
    ],
    "name:ron_x_preferred":[
        "Serrinha"
    ],
    "name:rus_x_preferred":[
        "\u0421\u0435\u0440\u0440\u0438\u043d\u044c\u044f"
    ],
    "name:vol_x_preferred":[
        "Serrinha"
    ],
    "name:war_x_preferred":[
        "Serrinha"
    ],
    "name:zho_x_preferred":[
        "\u585e\u91cc\u5c3c\u4e9a"
    ],
    "wof:name":"Serrinha",
    "wof:placetype":"locality"
},
  "geometry": {"coordinates":[-46.95,-7.91667],"type":"Point"}
}