{
  "type": "Feature",
  "properties": {
    "gn:admin1_code":"20",
    "gn:admin2_code":"2211001.0",
    "gn:asciiname":"Cruzinha",
    "gn:country_code":"BR",
    "gn:dem":122,
    "gn:feature_class":"P",
    "gn:feature_code":"PPL",
    "gn:name":"Cruzinha",
    "gn:population":0,
    "gn:timezone":"America/Fortaleza",
    "iso:country":"BR",
    "wof:name":"Cruzinha",
    "wof:placetype":"locality"
},
  "geometry": {"coordinates":[-42.76667,-5.46667],"type":"Point"}
}