{
  "type": "Feature",
  "properties": {
    "gn:admin1_code":"13",
    "gn:admin2_code":"2102200.0",
    "gn:asciiname":"Taboquinha",
    "gn:country_code":"BR",
    "gn:dem":105,
    "gn:feature_class":"P",
    "gn:feature_code":"PPL",
    "gn:name":"Taboquinha",
    "gn:population":0,
    "gn:timezone":"America/Fortaleza",
    "iso:country":"BR",
    "wof:name":"Taboquinha",
    "wof:placetype":"locality"
},
  "geometry": {"coordinates":[-42.94667000000001,-3.82861],"type":"Point"}
}