{
  "type": "Feature",
  "properties": {
    "gn:admin1_code":"4",
    "gn:admin2_code":"1300805.0",
    "gn:asciiname":"Sao Benedito",
    "gn:country_code":"BR",
    "gn:dem":20,
    "gn:feature_class":"P",
    "gn:feature_code":"PPL",
    "gn:name":"S\u00e3o Benedito",
    "gn:population":0,
    "gn:timezone":"America/Manaus",
    "iso:country":"BR",
    "wof:name":"Sao Benedito",
    "wof:placetype":"locality"
},
  "geometry": {"coordinates":[-59.84721999999999,-4.38972],"type":"Point"}
}