{
  "type": "Feature",
  "properties": {
    "gn:admin1_code":"06",
    "gn:admin2_code":"2301901.0",
    "gn:asciiname":"Sitio Crioulo",
    "gn:country_code":"BR",
    "gn:dem":435,
    "gn:feature_class":"P",
    "gn:feature_code":"PPL",
    "gn:name":"S\u00edtio Crioulo",
    "gn:population":0,
    "gn:timezone":"America/Fortaleza",
    "iso:country":"BR",
    "wof:name":"Sitio Crioulo",
    "wof:placetype":"locality"
},
  "geometry": {"coordinates":[-39.25,-7.35],"type":"Point"}
}