{
  "type": "Feature",
  "properties": {
    "gn:admin1_code":"15",
    "gn:admin2_code":"3145307.0",
    "gn:asciiname":"Sao Bentinho",
    "gn:cc2":"BR",
    "gn:country_code":"BR",
    "gn:dem":805,
    "gn:feature_class":"P",
    "gn:feature_code":"PPL",
    "gn:name":"S\u00e3o Bentinho",
    "gn:population":0,
    "gn:timezone":"America/Sao_Paulo",
    "iso:country":"BR",
    "name:und_x_variant":[
        "Bentinho",
        "S\u00e3o Bentinho"
    ],
    "wof:name":"Sao Bentinho",
    "wof:placetype":"locality"
},
  "geometry": {"coordinates":[-41.88333,-17.46667],"type":"Point"}
}