{
  "type": "Feature",
  "properties": {
    "gn:admin1_code":"18",
    "gn:admin2_code":"4113700.0",
    "gn:asciiname":"Heimtal",
    "gn:country_code":"BR",
    "gn:dem":531,
    "gn:feature_class":"P",
    "gn:feature_code":"PPL",
    "gn:name":"Heimtal",
    "gn:population":0,
    "gn:timezone":"America/Sao_Paulo",
    "iso:country":"BR",
    "wof:name":"Heimtal",
    "wof:placetype":"locality"
},
  "geometry": {"coordinates":[-51.15,-23.25],"type":"Point"}
}