{
  "type": "Feature",
  "properties": {
    "gn:admin1_code":"24.0",
    "gn:admin2_code":"1100189.0",
    "gn:asciiname":"Serraria",
    "gn:country_code":"BR",
    "gn:dem":364,
    "gn:feature_class":"P",
    "gn:feature_code":"PPL",
    "gn:name":"Serraria",
    "gn:population":0,
    "gn:timezone":"America/Porto_Velho",
    "iso:country":"BR",
    "name:bpy_x_preferred":[
        "\u09b8\u09c7\u09b0\u09b0\u09be\u09b0\u09bf\u09af\u09bc\u09be"
    ],
    "name:ceb_x_preferred":[
        "Serraria"
    ],
    "name:eus_x_preferred":[
        "Serraria"
    ],
    "name:fra_x_preferred":[
        "Serraria"
    ],
    "name:hye_x_preferred":[
        "\u054d\u056b\u0565\u0580\u0561\u0580\u056b\u0561"
    ],
    "name:ita_x_preferred":[
        "Serraria"
    ],
    "name:kat_x_preferred":[
        "\u10e1\u10d4\u10e0\u10d0\u10e0\u10d8\u10d0"
    ],
    "name:kaz_x_preferred":[
        "\u0421\u0435\u0440\u0440\u0430\u0440\u0438\u044f"
    ],
    "name:nld_x_preferred":[
        "Serraria"
    ],
    "name:nor_x_preferred":[
        "Serraria"
    ],
    "name:por_x_preferred":[
        "Serraria"
    ],
    "name:ron_x_preferred":[
        "Serraria"
    ],
    "name:rus_x_preferred":[
        "\u0421\u0435\u0440\u0440\u0430\u0440\u0438\u044f"
    ],
    "name:swe_x_preferred":[
        "Serraria"
    ],
    "name:vie_x_preferred":[
        "Serraria"
    ],
    "name:vol_x_preferred":[
        "Serraria"
    ],
    "name:war_x_preferred":[
        "Serraria"
    ],
    "name:zho_x_preferred":[
        "\u585e\u62c9\u91cc\u4e9a"
    ],
    "wof:name":"Serraria",
    "wof:placetype":"locality"
},
  "geometry": {"coordinates":[-60.68753,-12.22516],"type":"Point"}
}