{
  "type": "Feature",
  "properties": {
    "gn:admin1_code":"13",
    "gn:admin2_code":"2106607.0",
    "gn:asciiname":"Passa Tempo",
    "gn:country_code":"BR",
    "gn:dem":169,
    "gn:feature_class":"P",
    "gn:feature_code":"PPL",
    "gn:name":"Passa Tempo",
    "gn:population":0,
    "gn:timezone":"America/Fortaleza",
    "iso:country":"BR",
    "name:bpy_x_preferred":[
        "\u09aa\u09be\u09b8\u09b8\u09be \u099f\u09c7\u09ae\u09cd\u09aa\u09cb"
    ],
    "name:ceb_x_preferred":[
        "Passa Tempo"
    ],
    "name:epo_x_preferred":[
        "Passa Tempo"
    ],
    "name:eus_x_preferred":[
        "Passa Tempo"
    ],
    "name:fra_x_preferred":[
        "Passa Tempo"
    ],
    "name:ita_x_preferred":[
        "Passa Tempo"
    ],
    "name:kat_x_preferred":[
        "\u10de\u10d0\u10e1\u10d0-\u10e2\u10d4\u10db\u10de\u10e3"
    ],
    "name:kaz_x_preferred":[
        "\u041f\u0430\u0441\u0430-\u0422\u0435\u043c\u043f\u0443"
    ],
    "name:mlg_x_preferred":[
        "Passa Tempo"
    ],
    "name:nld_x_preferred":[
        "Passa Tempo"
    ],
    "name:nor_x_preferred":[
        "Passa Tempo"
    ],
    "name:pol_x_preferred":[
        "Passa Tempo"
    ],
    "name:por_x_preferred":[
        "Passa Tempo"
    ],
    "name:ron_x_preferred":[
        "Passa Tempo"
    ],
    "name:rus_x_preferred":[
        "\u041f\u0430\u0441\u0430-\u0422\u0435\u043c\u043f\u0443"
    ],
    "name:swe_x_preferred":[
        "Passa Tempo"
    ],
    "name:vie_x_preferred":[
        "Passa Tempo"
    ],
    "name:vol_x_preferred":[
        "Passa Tempo"
    ],
    "name:war_x_preferred":[
        "Passa Tempo"
    ],
    "name:zho_x_preferred":[
        "\u5e15\u8428\u6ed5\u666e"
    ],
    "wof:name":"Passa Tempo",
    "wof:placetype":"locality"
},
  "geometry": {"coordinates":[-43.33333,-5.45],"type":"Point"}
}