{
  "type": "Feature",
  "properties": {
    "gn:admin1_code":"13",
    "gn:admin2_code":"2106607.0",
    "gn:asciiname":"Passa Tempo",
    "gn:country_code":"BR",
    "gn:dem":169,
    "gn:feature_class":"P",
    "gn:feature_code":"PPL",
    "gn:name":"Passa Tempo",
    "gn:population":0,
    "gn:timezone":"America/Fortaleza",
    "iso:country":"BR",
    "wof:name":"Passa Tempo",
    "wof:placetype":"locality"
},
  "geometry": {"coordinates":[-43.33333,-5.45],"type":"Point"}
}