{
  "type": "Feature",
  "properties": {
    "gn:admin1_code":"20",
    "gn:admin2_code":"2210938.0",
    "gn:asciiname":"Tamboril (2)",
    "gn:country_code":"BR",
    "gn:dem":238,
    "gn:feature_class":"P",
    "gn:feature_code":"PPL",
    "gn:name":"Tamboril (2)",
    "gn:population":0,
    "gn:timezone":"America/Fortaleza",
    "iso:country":"BR",
    "wof:name":"Tamboril (2)",
    "wof:placetype":"locality"
},
  "geometry": {"coordinates":[-41.36667,-6.98333],"type":"Point"}
}