{
  "type": "Feature",
  "properties": {
    "gn:admin1_code":"18.0",
    "gn:admin2_code":"4121208.0",
    "gn:asciiname":"Sitio Didigio F. de Lima",
    "gn:country_code":"BR",
    "gn:dem":825,
    "gn:feature_class":"P",
    "gn:feature_code":"PPL",
    "gn:name":"S\u00edtio Didigio F. de Lima",
    "gn:population":0,
    "gn:timezone":"America/Sao_Paulo",
    "iso:country":"BR",
    "name:por_x_preferred":[
        "S\u00edtio Didigio F. de Lima"
    ],
    "wof:name":"Sitio Didigio F. de Lima",
    "wof:placetype":"locality"
},
  "geometry": {"coordinates":[-49.3942,-25.9469],"type":"Point"}
}