{
  "type": "Feature",
  "properties": {
    "gn:admin1_code":"18.0",
    "gn:admin2_code":"4110706.0",
    "gn:asciiname":"Arroio do Pessegueiro",
    "gn:country_code":"BR",
    "gn:dem":887,
    "gn:feature_class":"P",
    "gn:feature_code":"PPL",
    "gn:name":"Arroio do Pessegueiro",
    "gn:population":0,
    "gn:timezone":"America/Sao_Paulo",
    "iso:country":"BR",
    "name:por_x_preferred":[
        "Arroio do Pessegueiro"
    ],
    "wof:name":"Arroio do Pessegueiro",
    "wof:placetype":"locality"
},
  "geometry": {"coordinates":[-50.62662,-25.51574],"type":"Point"}
}