{
  "type": "Feature",
  "properties": {
    "gn:admin1_code":"24",
    "gn:admin2_code":"1100940.0",
    "gn:asciiname":"Fortaleza",
    "gn:cc2":"BR",
    "gn:country_code":"BR",
    "gn:dem":106,
    "gn:feature_class":"P",
    "gn:feature_code":"PPL",
    "gn:name":"Fortaleza",
    "gn:population":0,
    "gn:timezone":"America/Porto_Velho",
    "iso:country":"BR",
    "name:rus_x_preferred":[
        "\u0424\u043e\u0440\u0442\u0430\u043b\u0435\u0437\u0430"
    ],
    "name:und_x_variant":[
        "S\u00e3o Pedro",
        "Fortaleza"
    ],
    "wof:name":"Fortaleza",
    "wof:placetype":"locality"
},
  "geometry": {"coordinates":[-62.35,-8.76667],"type":"Point"}
}