{
  "type": "Feature",
  "properties": {
    "gn:admin1_code":"18.0",
    "gn:admin2_code":"4116901.0",
    "gn:asciiname":"Sitio Salmo Noventa e Um",
    "gn:country_code":"BR",
    "gn:dem":523,
    "gn:feature_class":"P",
    "gn:feature_code":"PPL",
    "gn:name":"S\u00edtio Salmo Noventa e Um",
    "gn:population":0,
    "gn:timezone":"America/Sao_Paulo",
    "iso:country":"BR",
    "name:por_x_preferred":[
        "S\u00edtio Salmo Noventa e Um"
    ],
    "name:por_x_variant":[
        "S\u00edtio Salmo 91"
    ],
    "wof:name":"Sitio Salmo Noventa e Um",
    "wof:placetype":"locality"
},
  "geometry": {"coordinates":[-52.18417,-23.23361],"type":"Point"}
}