{
  "type": "Feature",
  "properties": {
    "gn:admin1_code":"06",
    "gn:admin2_code":"2310902.0",
    "gn:asciiname":"Conceicao (2)",
    "gn:country_code":"BR",
    "gn:dem":279,
    "gn:feature_class":"P",
    "gn:feature_code":"PPL",
    "gn:name":"Concei\u00e7\u00e3o (2)",
    "gn:population":0,
    "gn:timezone":"America/Fortaleza",
    "iso:country":"BR",
    "wof:name":"Conceicao (2)",
    "wof:placetype":"locality"
},
  "geometry": {"coordinates":[-39.38333,-5.81667],"type":"Point"}
}