{
  "type": "Feature",
  "properties": {
    "gn:admin1_code":"25.0",
    "gn:admin2_code":"1400209.0",
    "gn:asciiname":"Santos Pes",
    "gn:country_code":"BR",
    "gn:dem":28,
    "gn:feature_class":"P",
    "gn:feature_code":"PPLL",
    "gn:name":"Santos P\u00e9s",
    "gn:population":0,
    "gn:timezone":"America/Boa_Vista",
    "iso:country":"BR",
    "name:por_x_preferred":[
        "Santos P\u00e9s"
    ],
    "wof:name":"Santos Pes",
    "wof:placetype":"locality"
},
  "geometry": {"coordinates":[-62.37197,-0.86698],"type":"Point"}
}