{
  "type": "Feature",
  "properties": {
    "gn:admin1_code":"27",
    "gn:admin2_code":"3519709.0",
    "gn:asciiname":"Sitio Makamura",
    "gn:country_code":"BR",
    "gn:dem":881,
    "gn:feature_class":"P",
    "gn:feature_code":"PPL",
    "gn:name":"S\u00edtio Makamura",
    "gn:population":0,
    "gn:timezone":"America/Sao_Paulo",
    "iso:country":"BR",
    "name:por_x_preferred":[
        "S\u00edtio Makamura"
    ],
    "wof:name":"Sitio Makamura",
    "wof:placetype":"locality"
},
  "geometry": {"coordinates":[-47.20453,-23.72448],"type":"Point"}
}