{
  "type": "Feature",
  "properties": {
    "gn:admin1_code":"13",
    "gn:admin2_code":"2112209.0",
    "gn:asciiname":"Vermelha",
    "gn:country_code":"BR",
    "gn:dem":133,
    "gn:feature_class":"P",
    "gn:feature_code":"PPL",
    "gn:name":"Vermelha",
    "gn:population":0,
    "gn:timezone":"America/Fortaleza",
    "iso:country":"BR",
    "wof:name":"Vermelha",
    "wof:placetype":"locality"
},
  "geometry": {"coordinates":[-42.86667,-5.11667],"type":"Point"}
}