{
  "type": "Feature",
  "properties": {
    "gn:admin1_code":"25.0",
    "gn:admin2_code":"1400472.0",
    "gn:asciiname":"Posto FUNAI",
    "gn:country_code":"BR",
    "gn:dem":52,
    "gn:feature_class":"P",
    "gn:feature_code":"PPLL",
    "gn:name":"Posto FUNAI",
    "gn:population":0,
    "gn:timezone":"America/Boa_Vista",
    "iso:country":"BR",
    "name:por_x_preferred":[
        "Posto FUNAI"
    ],
    "wof:name":"Posto FUNAI",
    "wof:placetype":"locality"
},
  "geometry": {"coordinates":[-60.6279,-0.54904],"type":"Point"}
}