{
  "type": "Feature",
  "properties": {
    "gn:admin1_code":"15",
    "gn:admin2_code":"3100906.0",
    "gn:asciiname":"Jose Bravo",
    "gn:cc2":"BR",
    "gn:country_code":"BR",
    "gn:dem":617,
    "gn:feature_class":"P",
    "gn:feature_code":"PPL",
    "gn:name":"Jos\u00e9 Bravo",
    "gn:population":0,
    "gn:timezone":"America/Sao_Paulo",
    "iso:country":"BR",
    "name:und_x_variant":[
        "Fazenda Jos\u00e9 Bravo",
        "Jos\u00e9 Bravo"
    ],
    "wof:name":"Jose Bravo",
    "wof:placetype":"locality"
},
  "geometry": {"coordinates":[-41.11667,-17.06667],"type":"Point"}
}