{
  "type": "Feature",
  "properties": {
    "gn:admin1_code":"21.0",
    "gn:admin2_code":"3304557.0",
    "gn:asciiname":"Senador Vasconcelos",
    "gn:country_code":"BR",
    "gn:dem":70,
    "gn:feature_class":"P",
    "gn:feature_code":"PPL",
    "gn:name":"Senador Vasconcelos",
    "gn:population":0,
    "gn:timezone":"America/Sao_Paulo",
    "iso:country":"BR",
    "name:ita_x_preferred":[
        "Senador Vasconcelos"
    ],
    "name:por_x_preferred":[
        "Senador Vasconcelos"
    ],
    "wof:name":"Senador Vasconcelos",
    "wof:placetype":"locality"
},
  "geometry": {"coordinates":[-43.53195,-22.89556],"type":"Point"}
}