{
  "type": "Feature",
  "properties": {
    "gn:admin1_code":"26.0",
    "gn:admin2_code":"4205803.0",
    "gn:asciiname":"Sitio Edith Bruno",
    "gn:country_code":"BR",
    "gn:dem":5,
    "gn:feature_class":"P",
    "gn:feature_code":"PPL",
    "gn:name":"S\u00edtio Edith Bruno",
    "gn:population":0,
    "gn:timezone":"America/Sao_Paulo",
    "iso:country":"BR",
    "name:por_x_preferred":[
        "S\u00edtio Edith Bruno"
    ],
    "wof:name":"Sitio Edith Bruno",
    "wof:placetype":"locality"
},
  "geometry": {"coordinates":[-48.7248,-25.9957],"type":"Point"}
}