{
  "type": "Feature",
  "properties": {
    "gn:admin1_code":"06",
    "gn:admin2_code":"2308104.0",
    "gn:asciiname":"Flecheira",
    "gn:country_code":"BR",
    "gn:dem":564,
    "gn:feature_class":"P",
    "gn:feature_code":"PPL",
    "gn:name":"Flecheira",
    "gn:population":0,
    "gn:timezone":"America/Fortaleza",
    "iso:country":"BR",
    "wof:name":"Flecheira",
    "wof:placetype":"locality"
},
  "geometry": {"coordinates":[-38.75,-7.25],"type":"Point"}
}