{
  "type": "Feature",
  "properties": {
    "gn:admin1_code":"18",
    "gn:admin2_code":"4104105.0",
    "gn:asciiname":"Sitio Inacio Batista",
    "gn:country_code":"BR",
    "gn:dem":836,
    "gn:feature_class":"P",
    "gn:feature_code":"PPL",
    "gn:name":"S\u00edtio In\u00e1cio Batista",
    "gn:population":0,
    "gn:timezone":"America/Sao_Paulo",
    "iso:country":"BR",
    "name:por_x_preferred":[
        "S\u00edtio In\u00e1cio Batista"
    ],
    "wof:name":"Sitio Inacio Batista",
    "wof:placetype":"locality"
},
  "geometry": {"coordinates":[-49.62071,-26.03614],"type":"Point"}
}