{
  "type": "Feature",
  "properties": {
    "gn:admin1_code":"5",
    "gn:admin2_code":"2929503.0",
    "gn:asciiname":"Floresta",
    "gn:country_code":"BR",
    "gn:dem":50,
    "gn:feature_class":"P",
    "gn:feature_code":"PPL",
    "gn:name":"Floresta",
    "gn:population":0,
    "gn:timezone":"America/Bahia",
    "iso:country":"BR",
    "wof:name":"Floresta",
    "wof:placetype":"locality"
},
  "geometry": {"coordinates":[-38.46667,-12.55],"type":"Point"}
}