{
  "type": "Feature",
  "properties": {
    "gn:admin1_code":"4",
    "gn:admin2_code":"1300706.0",
    "gn:asciiname":"Colocacao Redencao Nova",
    "gn:country_code":"BR",
    "gn:dem":127,
    "gn:feature_class":"P",
    "gn:feature_code":"PPL",
    "gn:name":"Coloca\u00e7\u00e3o Reden\u00e7\u00e3o Nova",
    "gn:population":0,
    "gn:timezone":"America/Manaus",
    "iso:country":"BR",
    "wof:name":"Colocacao Redencao Nova",
    "wof:placetype":"locality"
},
  "geometry": {"coordinates":[-67.48333000000001,-9.31667],"type":"Point"}
}