{
  "type": "Feature",
  "properties": {
    "gn:admin1_code":"18.0",
    "gn:admin2_code":"4111803.0",
    "gn:asciiname":"Sitio Frazao",
    "gn:country_code":"BR",
    "gn:dem":501,
    "gn:feature_class":"P",
    "gn:feature_code":"PPL",
    "gn:name":"S\u00edtio Fraz\u00e3o",
    "gn:population":0,
    "gn:timezone":"America/Sao_Paulo",
    "iso:country":"BR",
    "name:por_x_preferred":[
        "S\u00edtio Fraz\u00e3o"
    ],
    "wof:name":"Sitio Frazao",
    "wof:placetype":"locality"
},
  "geometry": {"coordinates":[-49.87067,-23.13345],"type":"Point"}
}