{
  "type": "Feature",
  "properties": {
    "gn:admin1_code":"23",
    "gn:admin2_code":"4318200.0",
    "gn:asciiname":"Varzea do Cedro",
    "gn:country_code":"BR",
    "gn:dem":979,
    "gn:feature_class":"P",
    "gn:feature_code":"PPL",
    "gn:name":"V\u00e1rzea do Cedro",
    "gn:population":0,
    "gn:timezone":"America/Sao_Paulo",
    "iso:country":"BR",
    "wof:name":"Varzea do Cedro",
    "wof:placetype":"locality"
},
  "geometry": {"coordinates":[-50.46667,-29.21667],"type":"Point"}
}