{
  "type": "Feature",
  "properties": {
    "gn:admin1_code":"17",
    "gn:admin2_code":"2509370.0",
    "gn:asciiname":"Miquilina",
    "gn:country_code":"BR",
    "gn:dem":208,
    "gn:feature_class":"P",
    "gn:feature_code":"PPL",
    "gn:name":"Miquilina",
    "gn:population":0,
    "gn:timezone":"America/Fortaleza",
    "iso:country":"BR",
    "wof:name":"Miquilina",
    "wof:placetype":"locality"
},
  "geometry": {"coordinates":[-37.75,-6.55],"type":"Point"}
}