{
  "type": "Feature",
  "properties": {
    "gn:admin1_code":"21",
    "gn:admin2_code":"3306206.0",
    "gn:asciiname":"Monsores",
    "gn:country_code":"BR",
    "gn:dem":640,
    "gn:feature_class":"P",
    "gn:feature_code":"PPL",
    "gn:name":"Monsores",
    "gn:population":0,
    "gn:timezone":"America/Sao_Paulo",
    "iso:country":"BR",
    "name:por_x_preferred":[
        "Monsores"
    ],
    "wof:name":"Monsores",
    "wof:placetype":"locality"
},
  "geometry": {"coordinates":[-43.55639,-22.47],"type":"Point"}
}