{
  "type": "Feature",
  "properties": {
    "gn:admin1_code":"30",
    "gn:admin2_code":"2606507.0",
    "gn:asciiname":"Barra do Jenipapo",
    "gn:country_code":"BR",
    "gn:dem":263,
    "gn:feature_class":"P",
    "gn:feature_code":"PPL",
    "gn:name":"Barra do Jenipapo",
    "gn:population":0,
    "gn:timezone":"America/Recife",
    "iso:country":"BR",
    "wof:name":"Barra do Jenipapo",
    "wof:placetype":"locality"
},
  "geometry": {"coordinates":[-37.03333,-9.28333],"type":"Point"}
}