{
  "type": "Feature",
  "properties": {
    "gn:admin1_code":"13.0",
    "gn:admin2_code":"2111763.0",
    "gn:asciiname":"Mucuiba",
    "gn:country_code":"BR",
    "gn:dem":181,
    "gn:feature_class":"P",
    "gn:feature_code":"PPL",
    "gn:name":"Mucu\u00edba",
    "gn:population":0,
    "gn:timezone":"America/Fortaleza",
    "iso:country":"BR",
    "wof:name":"Mucuiba",
    "wof:placetype":"locality"
},
  "geometry": {"coordinates":[-47.28786,-5.44522],"type":"Point"}
}