{
  "type": "Feature",
  "properties": {
    "gn:admin1_code":"06",
    "gn:admin2_code":"2311264.0",
    "gn:asciiname":"Cajueiro",
    "gn:country_code":"BR",
    "gn:dem":650,
    "gn:feature_class":"P",
    "gn:feature_code":"PPL",
    "gn:name":"Cajueiro",
    "gn:population":0,
    "gn:timezone":"America/Fortaleza",
    "iso:country":"BR",
    "wof:name":"Cajueiro",
    "wof:placetype":"locality"
},
  "geometry": {"coordinates":[-40.83333,-5.81667],"type":"Point"}
}