{
  "type": "Feature",
  "properties": {
    "gn:admin1_code":"06",
    "gn:admin2_code":"2311264.0",
    "gn:asciiname":"Cajueiro",
    "gn:country_code":"BR",
    "gn:dem":650,
    "gn:feature_class":"P",
    "gn:feature_code":"PPL",
    "gn:name":"Cajueiro",
    "gn:population":0,
    "gn:timezone":"America/Fortaleza",
    "iso:country":"BR",
    "name:bpy_x_preferred":[
        "\u0995\u09be\u099c\u09c1\u09af\u09bc\u09c7\u0987\u09b0\u09cb"
    ],
    "name:epo_x_preferred":[
        "Cajueiro"
    ],
    "name:eus_x_preferred":[
        "Cajueiro"
    ],
    "name:fra_x_preferred":[
        "Cajueiro"
    ],
    "name:hye_x_preferred":[
        "\u053f\u0561\u056a\u0578\u0582\u0565\u0575\u0580\u0578\u0582"
    ],
    "name:ind_x_preferred":[
        "Cajueiro"
    ],
    "name:ita_x_preferred":[
        "Cajueiro"
    ],
    "name:kat_x_preferred":[
        "\u10d9\u10d0\u10df\u10e3\u10d4\u10d8\u10e0\u10e3"
    ],
    "name:kaz_x_preferred":[
        "\u041a\u0430\u0436\u0443\u044d\u0439\u0440\u0443"
    ],
    "name:mlg_x_preferred":[
        "Cajueiro"
    ],
    "name:nld_x_preferred":[
        "Cajueiro"
    ],
    "name:nor_x_preferred":[
        "Cajueiro"
    ],
    "name:por_x_preferred":[
        "Cajueiro"
    ],
    "name:ron_x_preferred":[
        "Cajueiro"
    ],
    "name:rus_x_preferred":[
        "\u041a\u0430\u0436\u0443\u044d\u0439\u0440\u0443"
    ],
    "name:spa_x_preferred":[
        "Cajueiro"
    ],
    "name:vie_x_preferred":[
        "Cajueiro"
    ],
    "name:vol_x_preferred":[
        "Cajueiro"
    ],
    "name:war_x_preferred":[
        "Cajueiro"
    ],
    "name:zho_x_preferred":[
        "\u5361\u8339\u57c3\u9c81"
    ],
    "wof:name":"Cajueiro",
    "wof:placetype":"locality"
},
  "geometry": {"coordinates":[-40.83333,-5.81667],"type":"Point"}
}