{
  "type": "Feature",
  "properties": {
    "gn:admin1_code":"18",
    "gn:admin2_code":"4119103.0",
    "gn:asciiname":"Sitio Henrique Senn",
    "gn:country_code":"BR",
    "gn:dem":850,
    "gn:feature_class":"P",
    "gn:feature_code":"PPL",
    "gn:name":"S\u00edtio Henrique Senn",
    "gn:population":0,
    "gn:timezone":"America/Sao_Paulo",
    "iso:country":"BR",
    "name:por_x_preferred":[
        "S\u00edtio Henrique Senn"
    ],
    "wof:name":"Sitio Henrique Senn",
    "wof:placetype":"locality"
},
  "geometry": {"coordinates":[-49.4969,-26.0158],"type":"Point"}
}