{
  "type": "Feature",
  "properties": {
    "gn:admin1_code":"26",
    "gn:admin2_code":"4202107.0",
    "gn:asciiname":"Tabuleiro",
    "gn:country_code":"BR",
    "gn:dem":16,
    "gn:feature_class":"P",
    "gn:feature_code":"PPL",
    "gn:name":"Tabuleiro",
    "gn:population":0,
    "gn:timezone":"America/Sao_Paulo",
    "iso:country":"BR",
    "name:por_x_preferred":[
        "Tabuleiro"
    ],
    "wof:name":"Tabuleiro",
    "wof:placetype":"locality"
},
  "geometry": {"coordinates":[-48.716,-26.6193],"type":"Point"}
}