{
  "type": "Feature",
  "properties": {
    "gn:admin1_code":"26",
    "gn:admin2_code":"4202107.0",
    "gn:asciiname":"Tabuleiro",
    "gn:country_code":"BR",
    "gn:dem":16,
    "gn:feature_class":"P",
    "gn:feature_code":"PPL",
    "gn:name":"Tabuleiro",
    "gn:population":0,
    "gn:timezone":"America/Sao_Paulo",
    "iso:country":"BR",
    "name:bpy_x_preferred":[
        "\u099f\u09be\u09ac\u09c1\u09b2\u09af\u09bc\u09c7\u0987\u09b0\u09cb"
    ],
    "name:ceb_x_preferred":[
        "Tabuleiro"
    ],
    "name:epo_x_preferred":[
        "Tabuleiro"
    ],
    "name:eus_x_preferred":[
        "Tabuleiro"
    ],
    "name:fra_x_preferred":[
        "Tabuleiro"
    ],
    "name:ita_x_preferred":[
        "Tabuleiro"
    ],
    "name:kat_x_preferred":[
        "\u10e2\u10d0\u10d1\u10e3\u10da\u10d4\u10d8\u10e0\u10e3"
    ],
    "name:kaz_x_preferred":[
        "\u0422\u0430\u0431\u0443\u043b\u0435\u0439\u0440\u0443"
    ],
    "name:mlg_x_preferred":[
        "Tabuleiro"
    ],
    "name:nld_x_preferred":[
        "Tabuleiro"
    ],
    "name:nor_x_preferred":[
        "Tabuleiro"
    ],
    "name:pol_x_preferred":[
        "Tabuleiro"
    ],
    "name:por_x_preferred":[
        "Tabuleiro"
    ],
    "name:ron_x_preferred":[
        "Tabuleiro"
    ],
    "name:rus_x_preferred":[
        "\u0422\u0430\u0431\u0443\u043b\u0435\u0439\u0440\u0443"
    ],
    "name:swe_x_preferred":[
        "Tabuleiro"
    ],
    "name:vie_x_preferred":[
        "Tabuleiro"
    ],
    "name:vol_x_preferred":[
        "Tabuleiro"
    ],
    "name:war_x_preferred":[
        "Tabuleiro"
    ],
    "name:zho_x_preferred":[
        "\u5854\u5e03\u83b1\u9c81"
    ],
    "wof:name":"Tabuleiro",
    "wof:placetype":"locality"
},
  "geometry": {"coordinates":[-48.716,-26.6193],"type":"Point"}
}