{
  "type": "Feature",
  "properties": {
    "gn:admin1_code":"16.0",
    "gn:admin2_code":"1501808.0",
    "gn:asciiname":"Porto Belo Horizonte",
    "gn:country_code":"BR",
    "gn:dem":18,
    "gn:feature_class":"P",
    "gn:feature_code":"PPL",
    "gn:name":"P\u00f4rto Belo Horizonte",
    "gn:population":0,
    "gn:timezone":"America/Belem",
    "iso:country":"BR",
    "wof:name":"Porto Belo Horizonte",
    "wof:placetype":"locality"
},
  "geometry": {"coordinates":[-50.60848,-1.14555],"type":"Point"}
}