{
  "type": "Feature",
  "properties": {
    "gn:admin1_code":"16.0",
    "gn:admin2_code":"1507300.0",
    "gn:asciiname":"Pedra do Ciriaco",
    "gn:country_code":"BR",
    "gn:dem":258,
    "gn:feature_class":"P",
    "gn:feature_code":"PPLL",
    "gn:name":"Pedra do Cir\u00edaco",
    "gn:population":0,
    "gn:timezone":"America/Belem",
    "iso:country":"BR",
    "name:por_x_preferred":[
        "Pedra do Cir\u00edaco"
    ],
    "wof:name":"Pedra do Ciriaco",
    "wof:placetype":"locality"
},
  "geometry": {"coordinates":[-52.02328,-6.85248],"type":"Point"}
}