{
  "type": "Feature",
  "properties": {
    "gn:admin1_code":"22",
    "gn:admin2_code":"2410108.0",
    "gn:asciiname":"Melancia",
    "gn:country_code":"BR",
    "gn:dem":108,
    "gn:feature_class":"P",
    "gn:feature_code":"PPL",
    "gn:name":"Melancia",
    "gn:population":0,
    "gn:timezone":"America/Fortaleza",
    "iso:country":"BR",
    "wof:name":"Melancia",
    "wof:placetype":"locality"
},
  "geometry": {"coordinates":[-35.71667,-5.58333],"type":"Point"}
}