{
  "type": "Feature",
  "properties": {
    "gn:admin1_code":"18.0",
    "gn:admin2_code":"4109708.0",
    "gn:asciiname":"Sitio Jose D. Mello",
    "gn:country_code":"BR",
    "gn:dem":625,
    "gn:feature_class":"P",
    "gn:feature_code":"PPL",
    "gn:name":"S\u00edtio Jos\u00e9 D. Mello",
    "gn:population":0,
    "gn:timezone":"America/Sao_Paulo",
    "iso:country":"BR",
    "name:por_x_preferred":[
        "S\u00edtio Jos\u00e9 D. Mello"
    ],
    "wof:name":"Sitio Jose D. Mello",
    "wof:placetype":"locality"
},
  "geometry": {"coordinates":[-50.24017,-23.93829],"type":"Point"}
}