{
  "type": "Feature",
  "properties": {
    "gn:admin1_code":"14",
    "gn:admin2_code":"5107701.0",
    "gn:asciiname":"Bocaina",
    "gn:country_code":"BR",
    "gn:dem":339,
    "gn:feature_class":"P",
    "gn:feature_code":"PPL",
    "gn:name":"Bocaina",
    "gn:population":0,
    "gn:timezone":"America/Cuiaba",
    "iso:country":"BR",
    "wof:name":"Bocaina",
    "wof:placetype":"locality"
},
  "geometry": {"coordinates":[-56.75,-15.26667],"type":"Point"}
}