{
  "type": "Feature",
  "properties": {
    "gn:admin1_code":"6",
    "gn:admin2_code":"2302800.0",
    "gn:asciiname":"Arisco",
    "gn:country_code":"BR",
    "gn:dem":707,
    "gn:feature_class":"P",
    "gn:feature_code":"PPL",
    "gn:name":"Arisco",
    "gn:population":0,
    "gn:timezone":"America/Fortaleza",
    "iso:country":"BR",
    "wof:name":"Arisco",
    "wof:placetype":"locality"
},
  "geometry": {"coordinates":[-39.66667,-4.51667],"type":"Point"}
}