{
  "type": "Feature",
  "properties": {
    "gn:admin1_code":"18.0",
    "gn:admin2_code":"4120705.0",
    "gn:asciiname":"Sitio Ismael L. Camargo e Irmaos",
    "gn:country_code":"BR",
    "gn:dem":540,
    "gn:feature_class":"P",
    "gn:feature_code":"PPL",
    "gn:name":"S\u00edtio Ismael L. Camargo e Irm\u00e3os",
    "gn:population":0,
    "gn:timezone":"America/Sao_Paulo",
    "iso:country":"BR",
    "name:por_x_preferred":[
        "S\u00edtio Ismael L. Camargo e Irm\u00e3os"
    ],
    "wof:name":"Sitio Ismael L. Camargo e Irmaos",
    "wof:placetype":"locality"
},
  "geometry": {"coordinates":[-49.9304,-23.5962],"type":"Point"}
}