{
  "type": "Feature",
  "properties": {
    "gn:admin1_code":"5",
    "gn:admin2_code":"2927606.0",
    "gn:asciiname":"Barriguda",
    "gn:country_code":"BR",
    "gn:dem":442,
    "gn:feature_class":"P",
    "gn:feature_code":"PPL",
    "gn:name":"Barriguda",
    "gn:population":0,
    "gn:timezone":"America/Bahia",
    "iso:country":"BR",
    "wof:name":"Barriguda",
    "wof:placetype":"locality"
},
  "geometry": {"coordinates":[-38.23333,-9.85],"type":"Point"}
}