{
  "type": "Feature",
  "properties": {
    "gn:admin1_code":"20",
    "gn:admin2_code":"2206670.0",
    "gn:asciiname":"Sambaiba",
    "gn:country_code":"BR",
    "gn:dem":102,
    "gn:feature_class":"P",
    "gn:feature_code":"PPL",
    "gn:name":"Samba\u00edba",
    "gn:population":0,
    "gn:timezone":"America/Fortaleza",
    "iso:country":"BR",
    "wof:name":"Sambaiba",
    "wof:placetype":"locality"
},
  "geometry": {"coordinates":[-42.24806,-3.74583],"type":"Point"}
}