{
  "type": "Feature",
  "properties": {
    "gn:admin1_code":"13",
    "gn:admin2_code":"2103802.0",
    "gn:asciiname":"Ouro Preto",
    "gn:country_code":"BR",
    "gn:dem":137,
    "gn:feature_class":"P",
    "gn:feature_code":"PPL",
    "gn:name":"Ouro Pr\u00eato",
    "gn:population":0,
    "gn:timezone":"America/Fortaleza",
    "iso:country":"BR",
    "wof:name":"Ouro Preto",
    "wof:placetype":"locality"
},
  "geometry": {"coordinates":[-44.36667,-4.93333],"type":"Point"}
}