{
  "type": "Feature",
  "properties": {
    "gn:admin1_code":"31",
    "gn:admin2_code":"1716208.0",
    "gn:asciiname":"Cristal",
    "gn:country_code":"BR",
    "gn:dem":313,
    "gn:feature_class":"P",
    "gn:feature_code":"PPL",
    "gn:name":"Cristal",
    "gn:population":0,
    "gn:timezone":"America/Araguaina",
    "iso:country":"BR",
    "name:ceb_x_preferred":[
        "Cristal"
    ],
    "name:deu_x_preferred":[
        "Cristal"
    ],
    "name:fra_x_preferred":[
        "Cristal"
    ],
    "name:glg_x_preferred":[
        "Cristal"
    ],
    "name:ita_x_preferred":[
        "Cristal"
    ],
    "name:nld_x_preferred":[
        "Cristal"
    ],
    "name:nor_x_preferred":[
        "Cristal"
    ],
    "name:por_x_preferred":[
        "Cristal"
    ],
    "name:spa_x_preferred":[
        "Cristal"
    ],
    "name:swe_x_preferred":[
        "Cristal"
    ],
    "name:vie_x_preferred":[
        "Cristal"
    ],
    "wof:name":"Cristal",
    "wof:placetype":"locality"
},
  "geometry": {"coordinates":[-47.78833,-13.01139],"type":"Point"}
}