{
  "type": "Feature",
  "properties": {
    "gn:admin1_code":"31",
    "gn:admin2_code":"1716208.0",
    "gn:asciiname":"Cristal",
    "gn:country_code":"BR",
    "gn:dem":313,
    "gn:feature_class":"P",
    "gn:feature_code":"PPL",
    "gn:name":"Cristal",
    "gn:population":0,
    "gn:timezone":"America/Araguaina",
    "iso:country":"BR",
    "wof:name":"Cristal",
    "wof:placetype":"locality"
},
  "geometry": {"coordinates":[-47.78833,-13.01139],"type":"Point"}
}