{
  "type": "Feature",
  "properties": {
    "gn:admin1_code":"26",
    "gn:admin2_code":"4214805.0",
    "gn:asciiname":"Matador",
    "gn:country_code":"BR",
    "gn:dem":459,
    "gn:feature_class":"P",
    "gn:feature_code":"PPLL",
    "gn:name":"Matador",
    "gn:population":0,
    "gn:timezone":"America/Sao_Paulo",
    "iso:country":"BR",
    "name:por_x_preferred":[
        "Matador"
    ],
    "wof:name":"Matador",
    "wof:placetype":"locality"
},
  "geometry": {"coordinates":[-49.5898,-27.20577],"type":"Point"}
}