{
  "type": "Feature",
  "properties": {
    "gn:admin1_code":"18",
    "gn:admin2_code":"4114302.0",
    "gn:asciiname":"Sitio Jose Z. Filho",
    "gn:country_code":"BR",
    "gn:dem":914,
    "gn:feature_class":"P",
    "gn:feature_code":"PPL",
    "gn:name":"S\u00edtio Jos\u00e9 Z. Filho",
    "gn:population":0,
    "gn:timezone":"America/Sao_Paulo",
    "iso:country":"BR",
    "name:por_x_preferred":[
        "S\u00edtio Jos\u00e9 Z. Filho"
    ],
    "wof:name":"Sitio Jose Z. Filho",
    "wof:placetype":"locality"
},
  "geometry": {"coordinates":[-49.219,-25.8644],"type":"Point"}
}