{
  "type": "Feature",
  "properties": {
    "gn:admin1_code":"26",
    "gn:admin2_code":"4202404.0",
    "gn:asciiname":"Bairro Vorstaht",
    "gn:country_code":"BR",
    "gn:dem":16,
    "gn:feature_class":"P",
    "gn:feature_code":"PPL",
    "gn:name":"Bairro Vorstaht",
    "gn:population":0,
    "gn:timezone":"America/Sao_Paulo",
    "iso:country":"BR",
    "name:por_x_preferred":[
        "Bairro Vorstaht"
    ],
    "wof:name":"Bairro Vorstaht",
    "wof:placetype":"locality"
},
  "geometry": {"coordinates":[-49.039,-26.9025],"type":"Point"}
}