{
  "type": "Feature",
  "properties": {
    "gn:admin1_code":"20",
    "gn:admin2_code":"2208601.0",
    "gn:asciiname":"Rodeador",
    "gn:country_code":"BR",
    "gn:dem":143,
    "gn:feature_class":"P",
    "gn:feature_code":"PPL",
    "gn:name":"Rodeador",
    "gn:population":0,
    "gn:timezone":"America/Fortaleza",
    "iso:country":"BR",
    "wof:name":"Rodeador",
    "wof:placetype":"locality"
},
  "geometry": {"coordinates":[-42.16667,-5.71667],"type":"Point"}
}