{
  "type": "Feature",
  "properties": {
    "gn:admin1_code":"18.0",
    "gn:admin2_code":"4101309.0",
    "gn:asciiname":"Butia dos Colaco",
    "gn:country_code":"BR",
    "gn:dem":785,
    "gn:feature_class":"P",
    "gn:feature_code":"PPL",
    "gn:name":"Buti\u00e1 dos Cola\u00e7o",
    "gn:population":0,
    "gn:timezone":"America/Sao_Paulo",
    "iso:country":"BR",
    "name:por_x_preferred":[
        "Buti\u00e1 dos Cola\u00e7o"
    ],
    "wof:name":"Butia dos Colaco",
    "wof:placetype":"locality"
},
  "geometry": {"coordinates":[-50.01691,-25.98204],"type":"Point"}
}