{
  "type": "Feature",
  "properties": {
    "gn:admin1_code":"27",
    "gn:admin2_code":"3506607.0",
    "gn:asciiname":"Casa Branca",
    "gn:country_code":"BR",
    "gn:dem":911,
    "gn:feature_class":"P",
    "gn:feature_code":"PPL",
    "gn:name":"Casa Branca",
    "gn:population":0,
    "gn:timezone":"America/Sao_Paulo",
    "iso:country":"BR",
    "name:por_x_preferred":[
        "Casa Branca"
    ],
    "wof:name":"Casa Branca",
    "wof:placetype":"locality"
},
  "geometry": {"coordinates":[-45.96667,-23.63333],"type":"Point"}
}