{
  "type": "Feature",
  "properties": {
    "gn:admin1_code":"06",
    "gn:admin2_code":"2312205.0",
    "gn:asciiname":"Fazenda Sao Luis",
    "gn:country_code":"BR",
    "gn:dem":246,
    "gn:feature_class":"P",
    "gn:feature_code":"PPL",
    "gn:name":"Fazenda S\u00e3o Lu\u00eds",
    "gn:population":0,
    "gn:timezone":"America/Fortaleza",
    "iso:country":"BR",
    "wof:name":"Fazenda Sao Luis",
    "wof:placetype":"locality"
},
  "geometry": {"coordinates":[-39.96667,-4.46667],"type":"Point"}
}