{
  "type": "Feature",
  "properties": {
    "gn:admin1_code":"14",
    "gn:admin2_code":"5103452.0",
    "gn:asciiname":"Gleba Brauna",
    "gn:country_code":"BR",
    "gn:dem":223,
    "gn:feature_class":"P",
    "gn:feature_code":"PPL",
    "gn:name":"Gleba Bra\u00fana",
    "gn:population":0,
    "gn:timezone":"America/Cuiaba",
    "iso:country":"BR",
    "wof:name":"Gleba Brauna",
    "wof:placetype":"locality"
},
  "geometry": {"coordinates":[-56.95,-14.66667],"type":"Point"}
}