{
  "type": "Feature",
  "properties": {
    "gn:admin1_code":"4",
    "gn:admin2_code":"1300904.0",
    "gn:asciiname":"Redencao",
    "gn:cc2":"BR",
    "gn:country_code":"BR",
    "gn:dem":45,
    "gn:feature_class":"P",
    "gn:feature_code":"PPL",
    "gn:name":"Reden\u00e7\u00e3o",
    "gn:population":0,
    "gn:timezone":"America/Manaus",
    "iso:country":"BR",
    "name:und_x_variant":[
        "Redemp\u00e7\u00e3o",
        "Reden\u00e7\u00e3o"
    ],
    "wof:name":"Redencao",
    "wof:placetype":"locality"
},
  "geometry": {"coordinates":[-64.40000000000001,-6.56667],"type":"Point"}
}