{
  "type": "Feature",
  "properties": {
    "gn:admin1_code":"18.0",
    "gn:admin2_code":"4117701.0",
    "gn:asciiname":"Faxinal dos Quartins",
    "gn:country_code":"BR",
    "gn:dem":972,
    "gn:feature_class":"P",
    "gn:feature_code":"PPL",
    "gn:name":"Faxinal dos Quartins",
    "gn:population":0,
    "gn:timezone":"America/Sao_Paulo",
    "iso:country":"BR",
    "name:por_x_preferred":[
        "Faxinal dos Quartins"
    ],
    "wof:name":"Faxinal dos Quartins",
    "wof:placetype":"locality"
},
  "geometry": {"coordinates":[-50.11555,-25.55826],"type":"Point"}
}