{
  "type": "Feature",
  "properties": {
    "gn:admin1_code":"18.0",
    "gn:admin2_code":"4109708.0",
    "gn:asciiname":"Sitio Darci da Costa",
    "gn:country_code":"BR",
    "gn:dem":649,
    "gn:feature_class":"P",
    "gn:feature_code":"PPL",
    "gn:name":"S\u00edtio Darci da Costa",
    "gn:population":0,
    "gn:timezone":"America/Sao_Paulo",
    "iso:country":"BR",
    "name:por_x_preferred":[
        "S\u00edtio Darci da Costa"
    ],
    "wof:name":"Sitio Darci da Costa",
    "wof:placetype":"locality"
},
  "geometry": {"coordinates":[-50.3184,-23.86946],"type":"Point"}
}