{
  "type": "Feature",
  "properties": {
    "gn:admin1_code":"27",
    "gn:admin2_code":"3550605.0",
    "gn:asciiname":"Sitio Cleomar",
    "gn:country_code":"BR",
    "gn:dem":905,
    "gn:feature_class":"P",
    "gn:feature_code":"PPL",
    "gn:name":"S\u00edtio Cleomar",
    "gn:population":0,
    "gn:timezone":"America/Sao_Paulo",
    "iso:country":"BR",
    "name:por_x_preferred":[
        "S\u00edtio Cleomar"
    ],
    "wof:name":"Sitio Cleomar",
    "wof:placetype":"locality"
},
  "geometry": {"coordinates":[-47.11568,-23.62785],"type":"Point"}
}