{
  "type": "Feature",
  "properties": {
    "gn:admin1_code":"06",
    "gn:admin2_code":"2306553.0",
    "gn:asciiname":"Olho d'Agua",
    "gn:country_code":"BR",
    "gn:dem":6,
    "gn:feature_class":"P",
    "gn:feature_code":"PPL",
    "gn:name":"Olho d\u2019Agua",
    "gn:population":0,
    "gn:timezone":"America/Fortaleza",
    "iso:country":"BR",
    "wof:name":"Olho d'Agua",
    "wof:placetype":"locality"
},
  "geometry": {"coordinates":[-39.95,-2.88333],"type":"Point"}
}