{
  "type": "Feature",
  "properties": {
    "gn:admin1_code":"18",
    "gn:admin2_code":"4125506.0",
    "gn:asciiname":"Sitio Maria D. Kuch",
    "gn:country_code":"BR",
    "gn:dem":938,
    "gn:feature_class":"P",
    "gn:feature_code":"PPL",
    "gn:name":"S\u00edtio Maria D. Kuch",
    "gn:population":0,
    "gn:timezone":"America/Sao_Paulo",
    "iso:country":"BR",
    "name:por_x_preferred":[
        "S\u00edtio Maria D. Kuch"
    ],
    "wof:name":"Sitio Maria D. Kuch",
    "wof:placetype":"locality"
},
  "geometry": {"coordinates":[-49.1805,-25.7711],"type":"Point"}
}