{
  "type": "Feature",
  "properties": {
    "gn:admin1_code":"11",
    "gn:admin2_code":"5003207.0",
    "gn:asciiname":"Castelo",
    "gn:cc2":"BR",
    "gn:country_code":"BR",
    "gn:dem":88,
    "gn:feature_class":"P",
    "gn:feature_code":"PPL",
    "gn:name":"Castelo",
    "gn:population":0,
    "gn:timezone":"America/Campo_Grande",
    "iso:country":"BR",
    "name:und_x_variant":[
        "Castello",
        "Castelo"
    ],
    "wof:name":"Castelo",
    "wof:placetype":"locality"
},
  "geometry": {"coordinates":[-57.55,-18.63333],"type":"Point"}
}