{
  "type": "Feature",
  "properties": {
    "gn:admin1_code":"30",
    "gn:admin2_code":"2614006.0",
    "gn:asciiname":"Varzinha",
    "gn:country_code":"BR",
    "gn:dem":442,
    "gn:feature_class":"P",
    "gn:feature_code":"PPL",
    "gn:name":"Varzinha",
    "gn:population":0,
    "gn:timezone":"America/Recife",
    "iso:country":"BR",
    "wof:name":"Varzinha",
    "wof:placetype":"locality"
},
  "geometry": {"coordinates":[-39.41667,-7.85],"type":"Point"}
}