{
  "type": "Feature",
  "properties": {
    "gn:admin1_code":"06",
    "gn:admin2_code":"2311207.0",
    "gn:asciiname":"Morrinhos",
    "gn:country_code":"BR",
    "gn:dem":534,
    "gn:feature_class":"P",
    "gn:feature_code":"PPL",
    "gn:name":"Morrinhos",
    "gn:population":0,
    "gn:timezone":"America/Fortaleza",
    "iso:country":"BR",
    "name:ara_x_preferred":[
        "\u0645\u0648\u0631\u064a\u0646\u064a\u0648\u0633"
    ],
    "name:ben_x_preferred":[
        "\u09ae\u09b0\u09b0\u09bf\u09a8\u09b9\u09cb\u09b8"
    ],
    "name:bpy_x_preferred":[
        "\u09ae\u09cb\u09b0\u09cd\u09b0\u09bf\u09a8\u09b9\u09cb\u09b8"
    ],
    "name:ceb_x_preferred":[
        "Morrinhos"
    ],
    "name:deu_x_preferred":[
        "Morrinhos"
    ],
    "name:ell_x_preferred":[
        "\u039c\u03bf\u03c1\u03af\u03bd\u03b9\u03bf\u03c2"
    ],
    "name:fas_x_preferred":[
        "\u0645\u0648\u0631\u06cc\u0646\u0648\u0633"
    ],
    "name:hin_x_preferred":[
        "\u092e\u094b\u0930\u093f\u0928\u094d\u0939\u094b\u0938"
    ],
    "name:ind_x_preferred":[
        "Morrinhos"
    ],
    "name:ita_x_preferred":[
        "Morrinhos"
    ],
    "name:jpn_x_preferred":[
        "\u30e2\u30ea\u30cb\u30e7\u30b9"
    ],
    "name:kor_x_preferred":[
        "\ubaa8\ub9ac\ub1e8\uc2a4"
    ],
    "name:mlg_x_preferred":[
        "Morrinhos"
    ],
    "name:nld_x_preferred":[
        "Morrinhos"
    ],
    "name:nor_x_preferred":[
        "Morrinhos"
    ],
    "name:por_x_preferred":[
        "Morrinhos"
    ],
    "name:rus_x_preferred":[
        "\u041c\u043e\u0440\u0440\u0438\u043d\u044c\u044e\u0441"
    ],
    "name:swe_x_preferred":[
        "Morrinhos"
    ],
    "name:tur_x_preferred":[
        "Morrinhos"
    ],
    "name:ukr_x_preferred":[
        "\u041c\u043e\u0440\u0438\u043d\u044c\u043e\u0441"
    ],
    "name:urd_x_preferred":[
        "\u0645\u0648\u0631\u06cc\u0646\u0648\u0633"
    ],
    "name:vie_x_preferred":[
        "Morrinhos"
    ],
    "name:vol_x_preferred":[
        "Morrinhos"
    ],
    "name:war_x_preferred":[
        "Morrinhos"
    ],
    "wof:name":"Morrinhos",
    "wof:placetype":"locality"
},
  "geometry": {"coordinates":[-40.03333,-7.05],"type":"Point"}
}