{
  "type": "Feature",
  "properties": {
    "gn:admin1_code":"18.0",
    "gn:admin2_code":"4113205.0",
    "gn:asciiname":"Peda Alta",
    "gn:country_code":"BR",
    "gn:dem":823,
    "gn:feature_class":"P",
    "gn:feature_code":"PPLL",
    "gn:name":"Peda Alta",
    "gn:population":0,
    "gn:timezone":"America/Sao_Paulo",
    "iso:country":"BR",
    "name:por_x_preferred":[
        "Peda Alta"
    ],
    "wof:name":"Peda Alta",
    "wof:placetype":"locality"
},
  "geometry": {"coordinates":[-49.88334,-25.77697],"type":"Point"}
}