{
  "type": "Feature",
  "properties": {
    "gn:admin1_code":"27.0",
    "gn:admin2_code":"3505401.0",
    "gn:asciiname":"Serra Grande",
    "gn:country_code":"BR",
    "gn:dem":256,
    "gn:feature_class":"P",
    "gn:feature_code":"PPLL",
    "gn:name":"Serra Grande",
    "gn:population":0,
    "gn:timezone":"America/Sao_Paulo",
    "iso:country":"BR",
    "name:por_x_preferred":[
        "Serra Grande"
    ],
    "wof:name":"Serra Grande",
    "wof:placetype":"locality"
},
  "geometry": {"coordinates":[-48.5881,-24.9873],"type":"Point"}
}