{
  "type": "Feature",
  "properties": {
    "gn:admin1_code":"18",
    "gn:admin2_code":"4103354.0",
    "gn:asciiname":"Sao Jose",
    "gn:country_code":"BR",
    "gn:dem":614,
    "gn:feature_class":"P",
    "gn:feature_code":"PPL",
    "gn:name":"S\u00e3o Jos\u00e9",
    "gn:population":0,
    "gn:timezone":"America/Sao_Paulo",
    "iso:country":"BR",
    "wof:name":"Sao Jose",
    "wof:placetype":"locality"
},
  "geometry": {"coordinates":[-53.16667,-24.81667],"type":"Point"}
}