{
  "type": "Feature",
  "properties": {
    "gn:admin1_code":"20",
    "gn:admin2_code":"2209500.0",
    "gn:asciiname":"Saco do Umbu",
    "gn:cc2":"BR",
    "gn:country_code":"BR",
    "gn:dem":253,
    "gn:feature_class":"P",
    "gn:feature_code":"PPL",
    "gn:name":"Saco do Umbu",
    "gn:population":0,
    "gn:timezone":"America/Fortaleza",
    "iso:country":"BR",
    "name:und_x_variant":[
        "Saco do Urubu",
        "Saco do Umbu"
    ],
    "wof:name":"Saco do Umbu",
    "wof:placetype":"locality"
},
  "geometry": {"coordinates":[-41.88333,-7.31667],"type":"Point"}
}