{
  "type": "Feature",
  "properties": {
    "gn:admin1_code":"11",
    "gn:admin2_code":"5006903.0",
    "gn:asciiname":"Xatelodo",
    "gn:cc2":"BR",
    "gn:country_code":"BR",
    "gn:dem":122,
    "gn:feature_class":"P",
    "gn:feature_code":"PPL",
    "gn:name":"Xatelodo",
    "gn:population":0,
    "gn:timezone":"America/Campo_Grande",
    "iso:country":"BR",
    "name:und_x_variant":[
        "Chatelodo",
        "Xatelodo"
    ],
    "wof:name":"Xatelodo",
    "wof:placetype":"locality"
},
  "geometry": {"coordinates":[-57.46666999999999,-21.31667],"type":"Point"}
}