{
  "type": "Feature",
  "properties": {
    "gn:admin1_code":"18.0",
    "gn:admin2_code":"4109708.0",
    "gn:asciiname":"Sitio Sinoju H. Kotsui",
    "gn:country_code":"BR",
    "gn:dem":810,
    "gn:feature_class":"P",
    "gn:feature_code":"PPL",
    "gn:name":"S\u00edtio Sinoju H. Kotsui",
    "gn:population":0,
    "gn:timezone":"America/Sao_Paulo",
    "iso:country":"BR",
    "name:por_x_preferred":[
        "S\u00edtio Sinoju H. Kotsui"
    ],
    "wof:name":"Sitio Sinoju H. Kotsui",
    "wof:placetype":"locality"
},
  "geometry": {"coordinates":[-50.15633,-23.91799],"type":"Point"}
}