{
  "type": "Feature",
  "properties": {
    "gn:admin1_code":"26.0",
    "gn:admin2_code":"4203204.0",
    "gn:asciiname":"Caetas",
    "gn:country_code":"BR",
    "gn:dem":139,
    "gn:feature_class":"P",
    "gn:feature_code":"PPL",
    "gn:name":"Caetas",
    "gn:population":0,
    "gn:timezone":"America/Sao_Paulo",
    "iso:country":"BR",
    "wof:name":"Caetas",
    "wof:placetype":"locality"
},
  "geometry": {"coordinates":[-48.7219,-27.12744],"type":"Point"}
}