{
  "type": "Feature",
  "properties": {
    "gn:admin1_code":"18.0",
    "gn:admin2_code":"4120101.0",
    "gn:asciiname":"Sitio Jovenal Martins",
    "gn:country_code":"BR",
    "gn:dem":933,
    "gn:feature_class":"P",
    "gn:feature_code":"PPL",
    "gn:name":"S\u00edtio Jovenal Martins",
    "gn:population":0,
    "gn:timezone":"America/Sao_Paulo",
    "iso:country":"BR",
    "name:por_x_preferred":[
        "S\u00edtio Jovenal Martins"
    ],
    "wof:name":"Sitio Jovenal Martins",
    "wof:placetype":"locality"
},
  "geometry": {"coordinates":[-49.9392,-25.5114],"type":"Point"}
}