{
  "type": "Feature",
  "properties": {
    "gn:admin1_code":"22",
    "gn:admin2_code":"2408003.0",
    "gn:asciiname":"Estreito",
    "gn:country_code":"BR",
    "gn:dem":22,
    "gn:feature_class":"P",
    "gn:feature_code":"PPL",
    "gn:name":"Estreito",
    "gn:population":0,
    "gn:timezone":"America/Fortaleza",
    "iso:country":"BR",
    "name:ceb_x_preferred":[
        "Estreito"
    ],
    "name:fra_x_preferred":[
        "Estreito"
    ],
    "name:nld_x_preferred":[
        "Estreito"
    ],
    "name:por_x_preferred":[
        "Estreito"
    ],
    "name:swe_x_preferred":[
        "Estreito"
    ],
    "wof:name":"Estreito",
    "wof:placetype":"locality"
},
  "geometry": {"coordinates":[-37.35,-5.23333],"type":"Point"}
}