{
  "type": "Feature",
  "properties": {
    "gn:admin1_code":"17",
    "gn:admin2_code":"2501401.0",
    "gn:asciiname":"Sao Francisco",
    "gn:country_code":"BR",
    "gn:dem":38,
    "gn:feature_class":"P",
    "gn:feature_code":"PPL",
    "gn:name":"S\u00e3o Francisco",
    "gn:population":0,
    "gn:timezone":"America/Fortaleza",
    "iso:country":"BR",
    "wof:name":"Sao Francisco",
    "wof:placetype":"locality"
},
  "geometry": {"coordinates":[-34.98333,-6.66667],"type":"Point"}
}