{
  "type": "Feature",
  "properties": {
    "gn:admin1_code":"18.0",
    "gn:admin2_code":"4111704.0",
    "gn:asciiname":"Sitio Luis Brandino",
    "gn:country_code":"BR",
    "gn:dem":483,
    "gn:feature_class":"P",
    "gn:feature_code":"PPL",
    "gn:name":"S\u00edtio Luis Brandino",
    "gn:population":0,
    "gn:timezone":"America/Sao_Paulo",
    "iso:country":"BR",
    "name:por_x_preferred":[
        "S\u00edtio Luis Brandino"
    ],
    "wof:name":"Sitio Luis Brandino",
    "wof:placetype":"locality"
},
  "geometry": {"coordinates":[-50.11843,-23.69151],"type":"Point"}
}