{
  "type": "Feature",
  "properties": {
    "gn:admin1_code":"05",
    "gn:admin2_code":"2927101.0",
    "gn:asciiname":"Volta",
    "gn:cc2":"BR",
    "gn:country_code":"BR",
    "gn:dem":302,
    "gn:feature_class":"P",
    "gn:feature_code":"PPL",
    "gn:name":"Volta",
    "gn:population":0,
    "gn:timezone":"America/Bahia",
    "iso:country":"BR",
    "name:und_x_variant":[
        "Retiro",
        "Volta"
    ],
    "wof:name":"Volta",
    "wof:placetype":"locality"
},
  "geometry": {"coordinates":[-38.48333,-8.86667],"type":"Point"}
}