{
  "type": "Feature",
  "properties": {
    "gn:admin1_code":"18.0",
    "gn:admin2_code":"4111704.0",
    "gn:asciiname":"Sitio Dorvalino M. Ferreira",
    "gn:country_code":"BR",
    "gn:dem":582,
    "gn:feature_class":"P",
    "gn:feature_code":"PPL",
    "gn:name":"S\u00edtio Dorvalino M. Ferreira",
    "gn:population":0,
    "gn:timezone":"America/Sao_Paulo",
    "iso:country":"BR",
    "name:por_x_preferred":[
        "S\u00edtio Dorvalino M. Ferreira"
    ],
    "wof:name":"Sitio Dorvalino M. Ferreira",
    "wof:placetype":"locality"
},
  "geometry": {"coordinates":[-50.07185,-23.76823],"type":"Point"}
}