{
  "type": "Feature",
  "properties": {
    "gn:admin1_code":"18.0",
    "gn:admin2_code":"4109005.0",
    "gn:asciiname":"Sitio Assadi Tuvico",
    "gn:country_code":"BR",
    "gn:dem":511,
    "gn:feature_class":"P",
    "gn:feature_code":"PPL",
    "gn:name":"S\u00edtio Assadi Tuvico",
    "gn:population":0,
    "gn:timezone":"America/Sao_Paulo",
    "iso:country":"BR",
    "name:por_x_preferred":[
        "S\u00edtio Assadi Tuvico"
    ],
    "wof:name":"Sitio Assadi Tuvico",
    "wof:placetype":"locality"
},
  "geometry": {"coordinates":[-50.04533,-23.53688],"type":"Point"}
}