{
  "type": "Feature",
  "properties": {
    "gn:admin1_code":"20",
    "gn:admin2_code":"2209203.0",
    "gn:asciiname":"Picos",
    "gn:country_code":"BR",
    "gn:dem":511,
    "gn:feature_class":"P",
    "gn:feature_code":"PPL",
    "gn:name":"Picos",
    "gn:population":0,
    "gn:timezone":"America/Fortaleza",
    "iso:country":"BR",
    "name:ara_x_preferred":[
        "\u0628\u064a\u0643\u0648\u0633"
    ],
    "name:ben_x_preferred":[
        "\u09aa\u09bf\u0995\u09cb\u09b8"
    ],
    "name:ceb_x_preferred":[
        "Picos"
    ],
    "name:ell_x_preferred":[
        "\u03a0\u03af\u03ba\u03bf\u03c2"
    ],
    "name:eml_x_preferred":[
        "Picos"
    ],
    "name:eus_x_preferred":[
        "Picos"
    ],
    "name:fas_x_preferred":[
        "\u067e\u06cc\u06a9\u0648\u0647\u0627"
    ],
    "name:fra_x_preferred":[
        "Picos"
    ],
    "name:heb_x_preferred":[
        "\u05e4\u05d9\u05e7\u05d5\u05e1"
    ],
    "name:hin_x_preferred":[
        "\u092a\u093f\u0915\u094b\u0938"
    ],
    "name:ind_x_preferred":[
        "Picos"
    ],
    "name:ita_x_preferred":[
        "Picos"
    ],
    "name:jpn_x_preferred":[
        "\u30d4\u30fc\u30af\u30b9"
    ],
    "name:kat_x_preferred":[
        "\u10de\u10d8\u10d9\u10e3\u10e1\u10d8"
    ],
    "name:kor_x_preferred":[
        "\ud53c\ucfe0\uc2a4"
    ],
    "name:mlg_x_preferred":[
        "Picos"
    ],
    "name:nld_x_preferred":[
        "Picos"
    ],
    "name:nor_x_preferred":[
        "Picos"
    ],
    "name:por_x_preferred":[
        "Picos"
    ],
    "name:ron_x_preferred":[
        "Picos"
    ],
    "name:rus_x_preferred":[
        "\u041f\u0438\u043a\u0443\u0441"
    ],
    "name:spa_x_preferred":[
        "Picos"
    ],
    "name:swe_x_preferred":[
        "Picos"
    ],
    "name:ukr_x_preferred":[
        "\u041f\u0456\u043a\u043e\u0441"
    ],
    "name:urd_x_preferred":[
        "\u067e\u0627\u0626\u06cc\u06a9\u0648\u0633"
    ],
    "name:vie_x_preferred":[
        "Picos"
    ],
    "name:war_x_preferred":[
        "Picos"
    ],
    "name:zho_x_preferred":[
        "\u76ae\u79d1\u65af"
    ],
    "wof:name":"Picos",
    "wof:placetype":"locality"
},
  "geometry": {"coordinates":[-45.56472,-9.22444],"type":"Point"}
}