{
  "type": "Feature",
  "properties": {
    "gn:admin1_code":"18.0",
    "gn:admin2_code":"4116208.0",
    "gn:asciiname":"Sitio Algeny U. Philippsen",
    "gn:country_code":"BR",
    "gn:dem":54,
    "gn:feature_class":"P",
    "gn:feature_code":"PPL",
    "gn:name":"S\u00edtio Algeny U. Philippsen",
    "gn:population":0,
    "gn:timezone":"America/Sao_Paulo",
    "iso:country":"BR",
    "name:por_x_preferred":[
        "S\u00edtio Algeny U. Philippsen"
    ],
    "wof:name":"Sitio Algeny U. Philippsen",
    "wof:placetype":"locality"
},
  "geometry": {"coordinates":[-48.87798,-25.49138],"type":"Point"}
}