{
  "type": "Feature",
  "properties": {
    "gn:admin1_code":"26.0",
    "gn:admin2_code":"4209151.0",
    "gn:asciiname":"Ribeirao Grieseback",
    "gn:country_code":"BR",
    "gn:dem":354,
    "gn:feature_class":"P",
    "gn:feature_code":"PPL",
    "gn:name":"Ribeir\u00e3o Grieseback",
    "gn:population":0,
    "gn:timezone":"America/Sao_Paulo",
    "iso:country":"BR",
    "name:por_x_preferred":[
        "Ribeir\u00e3o Grieseback"
    ],
    "wof:name":"Ribeirao Grieseback",
    "wof:placetype":"locality"
},
  "geometry": {"coordinates":[-49.64689,-26.90237],"type":"Point"}
}