{
  "type": "Feature",
  "properties": {
    "gn:admin1_code":"27",
    "gn:admin2_code":"3519709.0",
    "gn:asciiname":"Sitio Visconde de Sabugosa",
    "gn:country_code":"BR",
    "gn:dem":870,
    "gn:feature_class":"P",
    "gn:feature_code":"PPL",
    "gn:name":"S\u00edtio Visconde de Sabugosa",
    "gn:population":0,
    "gn:timezone":"America/Sao_Paulo",
    "iso:country":"BR",
    "name:por_x_preferred":[
        "S\u00edtio Visconde de Sabugosa"
    ],
    "wof:name":"Sitio Visconde de Sabugosa",
    "wof:placetype":"locality"
},
  "geometry": {"coordinates":[-47.13274000000001,-23.65626],"type":"Point"}
}