{
  "type": "Feature",
  "properties": {
    "gn:admin1_code":"1",
    "gn:admin2_code":"1200427.0",
    "gn:asciiname":"Colonia Rodrigues Alves",
    "gn:country_code":"BR",
    "gn:dem":186,
    "gn:feature_class":"P",
    "gn:feature_code":"PPL",
    "gn:name":"Col\u00f4nia Rodrigues Alves",
    "gn:population":0,
    "gn:timezone":"America/Rio_Branco",
    "iso:country":"BR",
    "wof:name":"Colonia Rodrigues Alves",
    "wof:placetype":"locality"
},
  "geometry": {"coordinates":[-72.65000000000001,-7.71667],"type":"Point"}
}