{
  "type": "Feature",
  "properties": {
    "gn:admin1_code":"4",
    "gn:admin2_code":"1301407.0",
    "gn:asciiname":"Foz do Tarauaca",
    "gn:country_code":"BR",
    "gn:dem":137,
    "gn:feature_class":"P",
    "gn:feature_code":"PPL",
    "gn:name":"Foz do Tarauac\u00e1",
    "gn:population":0,
    "gn:timezone":"America/Eirunepe",
    "iso:country":"BR",
    "wof:name":"Foz do Tarauaca",
    "wof:placetype":"locality"
},
  "geometry": {"coordinates":[-69.76739000000001,-6.71562],"type":"Point"}
}