{
  "type": "Feature",
  "properties": {
    "gn:admin1_code":"8",
    "gn:admin2_code":"3204708.0",
    "gn:asciiname":"Barra Seca",
    "gn:cc2":"BR",
    "gn:country_code":"BR",
    "gn:dem":196,
    "gn:feature_class":"P",
    "gn:feature_code":"PPL",
    "gn:name":"Barra S\u00eaca",
    "gn:population":0,
    "gn:timezone":"America/Sao_Paulo",
    "iso:country":"BR",
    "name:und_x_variant":[
        "S\u00e3o Sebasti\u00e3o da Barra S\u00eaca",
        "Barra S\u00eaca"
    ],
    "wof:name":"Barra Seca",
    "wof:placetype":"locality"
},
  "geometry": {"coordinates":[-40.58333,-18.91667],"type":"Point"}
}