{
  "type": "Feature",
  "properties": {
    "gn:admin1_code":"5",
    "gn:admin2_code":"2910503.0",
    "gn:asciiname":"Saudade",
    "gn:country_code":"BR",
    "gn:dem":89,
    "gn:feature_class":"P",
    "gn:feature_code":"PPL",
    "gn:name":"Saudade",
    "gn:population":0,
    "gn:timezone":"America/Bahia",
    "iso:country":"BR",
    "name:aze_x_preferred":[
        "Saudade"
    ],
    "name:bul_x_preferred":[
        "\u0421\u0430\u0443\u0434\u0430\u0434\u0435"
    ],
    "name:cat_x_preferred":[
        "Saudade"
    ],
    "name:deu_x_preferred":[
        "Saudade"
    ],
    "name:epo_x_preferred":[
        "Sa\u016ddado"
    ],
    "name:eus_x_preferred":[
        "Saudade"
    ],
    "name:fas_x_preferred":[
        "\u0633\u0648\u062f\u0627\u062f"
    ],
    "name:fra_x_preferred":[
        "Saudade"
    ],
    "name:glg_x_preferred":[
        "Saudade"
    ],
    "name:heb_x_preferred":[
        "\u05d2\u05e2\u05d2\u05d5\u05e2"
    ],
    "name:hrv_x_preferred":[
        "Saudade"
    ],
    "name:hye_x_preferred":[
        "\u054d\u0561\u0578\u0582\u0564\u0561\u0564\u056b"
    ],
    "name:ind_x_preferred":[
        "Saudade"
    ],
    "name:ita_x_preferred":[
        "Saudade"
    ],
    "name:jpn_x_preferred":[
        "\u30b5\u30a6\u30c0\u30fc\u30b8"
    ],
    "name:nld_x_preferred":[
        "Saudade"
    ],
    "name:oci_x_preferred":[
        "Saudade"
    ],
    "name:pol_x_preferred":[
        "Saudade"
    ],
    "name:por_x_preferred":[
        "Saudade"
    ],
    "name:rus_x_preferred":[
        "\u0421\u0430\u0443\u0434\u0430\u0434\u0435"
    ],
    "name:spa_x_preferred":[
        "Saudade"
    ],
    "name:tur_x_preferred":[
        "Saudade"
    ],
    "name:ukr_x_preferred":[
        "\u0421\u0430\u0443\u0434\u0430\u0434\u0435"
    ],
    "name:zho_x_preferred":[
        "\u8428\u4e4c\u8fbe\u5fb7"
    ],
    "wof:name":"Saudade",
    "wof:placetype":"locality"
},
  "geometry": {"coordinates":[-37.98333,-12.23333],"type":"Point"}
}