{
  "type": "Feature",
  "properties": {
    "gn:admin1_code":"5",
    "gn:admin2_code":"2910503.0",
    "gn:asciiname":"Saudade",
    "gn:country_code":"BR",
    "gn:dem":89,
    "gn:feature_class":"P",
    "gn:feature_code":"PPL",
    "gn:name":"Saudade",
    "gn:population":0,
    "gn:timezone":"America/Bahia",
    "iso:country":"BR",
    "wof:name":"Saudade",
    "wof:placetype":"locality"
},
  "geometry": {"coordinates":[-37.98333,-12.23333],"type":"Point"}
}