{
  "type": "Feature",
  "properties": {
    "gn:admin1_code":"04",
    "gn:admin2_code":"1302900.0",
    "gn:asciiname":"Curuca",
    "gn:country_code":"BR",
    "gn:dem":12,
    "gn:feature_class":"P",
    "gn:feature_code":"PPL",
    "gn:name":"Curu\u00e7\u00e1",
    "gn:population":0,
    "gn:timezone":"America/Manaus",
    "iso:country":"BR",
    "wof:name":"Curuca",
    "wof:placetype":"locality"
},
  "geometry": {"coordinates":[-57.96666999999999,-3.48333],"type":"Point"}
}