{
  "type": "Feature",
  "properties": {
    "gn:admin1_code":"15",
    "gn:admin2_code":"3135803.0",
    "gn:asciiname":"Oratorio",
    "gn:country_code":"BR",
    "gn:dem":720,
    "gn:feature_class":"P",
    "gn:feature_code":"PPL",
    "gn:name":"Orat\u00f3rio",
    "gn:population":0,
    "gn:timezone":"America/Sao_Paulo",
    "iso:country":"BR",
    "name:por_x_preferred":[
        "Orat\u00f3rio"
    ],
    "wof:name":"Oratorio",
    "wof:placetype":"locality"
},
  "geometry": {"coordinates":[-40.96667,-16.33333],"type":"Point"}
}