{
  "type": "Feature",
  "properties": {
    "gn:admin1_code":"18.0",
    "gn:admin2_code":"4111803.0",
    "gn:asciiname":"Sitio Usina Jacarezinho",
    "gn:country_code":"BR",
    "gn:dem":471,
    "gn:feature_class":"P",
    "gn:feature_code":"PPL",
    "gn:name":"S\u00edtio Usina Jacarezinho",
    "gn:population":0,
    "gn:timezone":"America/Sao_Paulo",
    "iso:country":"BR",
    "name:por_x_preferred":[
        "S\u00edtio Usina Jacarezinho"
    ],
    "wof:name":"Sitio Usina Jacarezinho",
    "wof:placetype":"locality"
},
  "geometry": {"coordinates":[-50.0195,-23.068],"type":"Point"}
}