{
  "type": "Feature",
  "properties": {
    "gn:admin1_code":"14",
    "gn:admin2_code":"5106505.0",
    "gn:asciiname":"Fazenda Sao Joao",
    "gn:cc2":"BR",
    "gn:country_code":"BR",
    "gn:dem":123,
    "gn:feature_class":"P",
    "gn:feature_code":"PPL",
    "gn:name":"Fazenda S\u00e3o Jo\u00e3o",
    "gn:population":0,
    "gn:timezone":"America/Cuiaba",
    "iso:country":"BR",
    "name:und_x_variant":[
        "S\u00e3o Jo\u00e3o",
        "Fazenda S\u00e3o Jo\u00e3o"
    ],
    "wof:name":"Fazenda Sao Joao",
    "wof:placetype":"locality"
},
  "geometry": {"coordinates":[-56.63333000000001,-16.93333],"type":"Point"}
}