{
  "type": "Feature",
  "properties": {
    "gn:admin1_code":"27.0",
    "gn:admin2_code":"3528502.0",
    "gn:asciiname":"Sitio Santa Rita",
    "gn:country_code":"BR",
    "gn:dem":846,
    "gn:feature_class":"P",
    "gn:feature_code":"PPL",
    "gn:name":"S\u00edtio Santa Rita",
    "gn:population":0,
    "gn:timezone":"America/Sao_Paulo",
    "iso:country":"BR",
    "name:por_x_preferred":[
        "S\u00edtio Santa Rita"
    ],
    "wof:name":"Sitio Santa Rita",
    "wof:placetype":"locality"
},
  "geometry": {"coordinates":[-46.63522,-23.26894],"type":"Point"}
}