{
  "type": "Feature",
  "properties": {
    "gn:admin1_code":"18.0",
    "gn:admin2_code":"4103107.0",
    "gn:asciiname":"Sitio Joao C. Viana",
    "gn:country_code":"BR",
    "gn:dem":850,
    "gn:feature_class":"P",
    "gn:feature_code":"PPL",
    "gn:name":"S\u00edtio Jo\u00e3o C. Viana",
    "gn:population":0,
    "gn:timezone":"America/Sao_Paulo",
    "iso:country":"BR",
    "name:por_x_preferred":[
        "S\u00edtio Jo\u00e3o C. Viana"
    ],
    "wof:name":"Sitio Joao C. Viana",
    "wof:placetype":"locality"
},
  "geometry": {"coordinates":[-48.96752,-25.17648],"type":"Point"}
}