{
  "type": "Feature",
  "properties": {
    "gn:admin1_code":"5",
    "gn:admin2_code":"2918803.0",
    "gn:asciiname":"Laje",
    "gn:cc2":"BR",
    "gn:country_code":"BR",
    "gn:dem":180,
    "gn:feature_class":"P",
    "gn:feature_code":"PPL",
    "gn:name":"Laje",
    "gn:population":0,
    "gn:timezone":"America/Bahia",
    "iso:country":"BR",
    "name:und_x_variant":[
        "Lage"
    ],
    "wof:name":"Laje",
    "wof:placetype":"locality"
},
  "geometry": {"coordinates":[-39.425,-13.18222],"type":"Point"}
}