{
  "type": "Feature",
  "properties": {
    "gn:admin1_code":"24",
    "gn:admin2_code":"1100254.0",
    "gn:asciiname":"Iracema",
    "gn:country_code":"BR",
    "gn:dem":156,
    "gn:feature_class":"P",
    "gn:feature_code":"PPL",
    "gn:name":"Iracema",
    "gn:population":0,
    "gn:timezone":"America/Porto_Velho",
    "iso:country":"BR",
    "wof:name":"Iracema",
    "wof:placetype":"locality"
},
  "geometry": {"coordinates":[-61.93333000000001,-11.25],"type":"Point"}
}