{
  "type": "Feature",
  "properties": {
    "gn:admin1_code":"27.0",
    "gn:admin2_code":"3548708.0",
    "gn:asciiname":"Sitio Porto Praia",
    "gn:country_code":"BR",
    "gn:dem":761,
    "gn:feature_class":"P",
    "gn:feature_code":"PPL",
    "gn:name":"S\u00edtio Porto Praia",
    "gn:population":0,
    "gn:timezone":"America/Sao_Paulo",
    "iso:country":"BR",
    "name:por_x_preferred":[
        "S\u00edtio Porto Praia"
    ],
    "wof:name":"Sitio Porto Praia",
    "wof:placetype":"locality"
},
  "geometry": {"coordinates":[-46.5557,-23.7898],"type":"Point"}
}