{
  "type": "Feature",
  "properties": {
    "iso:country":"BR",
    "name:ceb_x_preferred":[
        "Castelo"
    ],
    "name:deu_x_preferred":[
        "Castelo"
    ],
    "name:epo_x_preferred":[
        "Castelo"
    ],
    "name:fra_x_preferred":[
        "Castelo"
    ],
    "name:glg_x_preferred":[
        "Castelo"
    ],
    "name:nld_x_preferred":[
        "Castelo"
    ],
    "name:por_x_preferred":[
        "Castelo"
    ],
    "name:rus_x_preferred":[
        "\u041a\u0430\u0448\u0442\u0435\u043b\u0443"
    ],
    "name:sco_x_preferred":[
        "Castelo"
    ],
    "name:spa_x_preferred":[
        "Castelo"
    ],
    "name:swe_x_preferred":[
        "Castelo"
    ],
    "name:ukr_x_preferred":[
        "\u041a\u0430\u0448\u0442\u0435\u043b\u0443"
    ],
    "qs:gn_adm0_cc":"BR",
    "qs:gn_local":3449433,
    "qs:gn_nam_loc":"Santos, Santos, S\u00e3o Paulo, BR",
    "qs:gn_namadm1":"27",
    "qs:local_max":2045,
    "qs:local_sum":15648,
    "qs:localhoods":22,
    "qs:name":"Castelo",
    "qs:name_adm0":"Brasil",
    "qs:name_adm1":"S\u00e3o Paulo",
    "qs:name_adm2":"Santos",
    "qs:name_local":"Santos",
    "qs:photo_max":140,
    "qs:photo_sum":841,
    "qs:placetype":"Suburb",
    "qs:quad_count":42,
    "qs:woe_adm0":23424768,
    "qs:woe_adm1":2344868,
    "qs:woe_adm2":12582296,
    "qs:woe_lau":0,
    "qs:woe_local":455991,
    "qs:woe_ver":"7.10.0",
    "wof:lang":[
        "por"
    ],
    "wof:name":"Castelo",
    "wof:placetype":"neighbourhood"
},
  "geometry": {"coordinates":[-46.383445,-23.965216],"type":"Point"}
}