{
  "type": "Feature",
  "properties": {
    "gn:admin1_code":"18.0",
    "gn:admin2_code":"4100202.0",
    "gn:asciiname":"Bairro Estreitinho",
    "gn:country_code":"BR",
    "gn:dem":267,
    "gn:feature_class":"P",
    "gn:feature_code":"PPLL",
    "gn:name":"Bairro Estreitinho",
    "gn:population":0,
    "gn:timezone":"America/Sao_Paulo",
    "iso:country":"BR",
    "name:por_x_preferred":[
        "Bairro Estreitinho"
    ],
    "wof:name":"Bairro Estreitinho",
    "wof:placetype":"locality"
},
  "geometry": {"coordinates":[-48.5799,-24.899],"type":"Point"}
}