{
  "type": "Feature",
  "properties": {
    "gn:admin1_code":"16",
    "gn:admin2_code":"1507474.0",
    "gn:asciiname":"Sao Lourenco",
    "gn:country_code":"BR",
    "gn:dem":22,
    "gn:feature_class":"P",
    "gn:feature_code":"PPL",
    "gn:name":"S\u00e3o Louren\u00e7o",
    "gn:population":0,
    "gn:timezone":"America/Belem",
    "iso:country":"BR",
    "wof:name":"Sao Lourenco",
    "wof:placetype":"locality"
},
  "geometry": {"coordinates":[-47.36667,-0.83333],"type":"Point"}
}