{
  "type": "Feature",
  "properties": {
    "gn:admin1_code":"20",
    "gn:admin2_code":"2209005.0",
    "gn:asciiname":"Saco",
    "gn:country_code":"BR",
    "gn:dem":333,
    "gn:feature_class":"P",
    "gn:feature_code":"PPL",
    "gn:name":"Saco",
    "gn:population":0,
    "gn:timezone":"America/Fortaleza",
    "iso:country":"BR",
    "name:ceb_x_preferred":[
        "Saco"
    ],
    "name:fra_x_preferred":[
        "Saco"
    ],
    "name:ita_x_preferred":[
        "Saco"
    ],
    "name:nld_x_preferred":[
        "Saco"
    ],
    "name:pol_x_preferred":[
        "Saco"
    ],
    "name:por_x_preferred":[
        "Saco"
    ],
    "name:spa_x_preferred":[
        "Saco"
    ],
    "name:swe_x_preferred":[
        "Saco"
    ],
    "name:vol_x_preferred":[
        "Saco"
    ],
    "wof:name":"Saco",
    "wof:placetype":"locality"
},
  "geometry": {"coordinates":[-43.18333,-7.78333],"type":"Point"}
}