{
  "type": "Feature",
  "properties": {
    "gn:admin1_code":"18",
    "gn:admin2_code":"4119103.0",
    "gn:asciiname":"Sitio Raulino M. Ribeiro",
    "gn:country_code":"BR",
    "gn:dem":862,
    "gn:feature_class":"P",
    "gn:feature_code":"PPL",
    "gn:name":"S\u00edtio Raulino M. Ribeiro",
    "gn:population":0,
    "gn:timezone":"America/Sao_Paulo",
    "iso:country":"BR",
    "name:por_x_preferred":[
        "S\u00edtio Raulino M. Ribeiro"
    ],
    "wof:name":"Sitio Raulino M. Ribeiro",
    "wof:placetype":"locality"
},
  "geometry": {"coordinates":[-49.50843,-26.11427],"type":"Point"}
}