{
  "type": "Feature",
  "properties": {
    "gn:admin1_code":"16",
    "gn:admin2_code":"1500503.0",
    "gn:asciiname":"Eritima",
    "gn:cc2":"BR",
    "gn:country_code":"BR",
    "gn:dem":321,
    "gn:feature_class":"P",
    "gn:feature_code":"PPL",
    "gn:name":"Eritim\u00e3",
    "gn:population":0,
    "gn:timezone":"America/Santarem",
    "iso:country":"BR",
    "name:und_x_variant":[
        "Eritiman",
        "Eritim\u00e3"
    ],
    "wof:name":"Eritima",
    "wof:placetype":"locality"
},
  "geometry": {"coordinates":[-54.11666999999999,0.58333],"type":"Point"}
}