{
  "type": "Feature",
  "properties": {
    "gn:admin1_code":"15",
    "gn:admin2_code":"3116100.0",
    "gn:asciiname":"Chapada",
    "gn:country_code":"BR",
    "gn:dem":605,
    "gn:feature_class":"P",
    "gn:feature_code":"PPL",
    "gn:name":"Chapada",
    "gn:population":0,
    "gn:timezone":"America/Sao_Paulo",
    "iso:country":"BR",
    "name:ara_x_preferred":[
        "\u0634\u0628\u0627\u062f\u0627"
    ],
    "name:bpy_x_preferred":[
        "\u099a\u09be\u09aa\u09be\u09a1\u09be"
    ],
    "name:fra_x_preferred":[
        "Chapada"
    ],
    "name:por_x_preferred":[
        "Chapada"
    ],
    "name:spa_x_preferred":[
        "Chapada"
    ],
    "wof:name":"Chapada",
    "wof:placetype":"locality"
},
  "geometry": {"coordinates":[-42.53871,-17.10873],"type":"Point"}
}