{
  "type": "Feature",
  "properties": {
    "gn:admin1_code":"13",
    "gn:admin2_code":"2110104.0",
    "gn:asciiname":"Sao Francisco",
    "gn:country_code":"BR",
    "gn:dem":56,
    "gn:feature_class":"P",
    "gn:feature_code":"PPL",
    "gn:name":"S\u00e3o Francisco",
    "gn:population":0,
    "gn:timezone":"America/Fortaleza",
    "iso:country":"BR",
    "wof:name":"Sao Francisco",
    "wof:placetype":"locality"
},
  "geometry": {"coordinates":[-42.75833,-3.41028],"type":"Point"}
}