{
  "type": "Feature",
  "properties": {
    "gn:admin1_code":"27",
    "gn:admin2_code":"3508207.0",
    "gn:asciiname":"Lavrinha",
    "gn:cc2":"BR",
    "gn:country_code":"BR",
    "gn:dem":820,
    "gn:feature_class":"P",
    "gn:feature_code":"PPL",
    "gn:name":"Lavrinha",
    "gn:population":0,
    "gn:timezone":"America/Sao_Paulo",
    "iso:country":"BR",
    "name:und_x_variant":[
        "Fazenda Lavorinha",
        "Lavrinha"
    ],
    "wof:name":"Lavrinha",
    "wof:placetype":"locality"
},
  "geometry": {"coordinates":[-47.63333,-20.16667],"type":"Point"}
}