{
  "type": "Feature",
  "properties": {
    "gn:admin1_code":"29",
    "gn:admin2_code":"5211305.0",
    "gn:asciiname":"Porto Sao Domingos",
    "gn:cc2":"BR",
    "gn:country_code":"BR",
    "gn:dem":355,
    "gn:feature_class":"P",
    "gn:feature_code":"PPL",
    "gn:name":"P\u00f4rto S\u00e3o Domingos",
    "gn:population":0,
    "gn:timezone":"America/Sao_Paulo",
    "iso:country":"BR",
    "name:und_x_variant":[
        "Porto de S\u00e3o Domingos",
        "P\u00f4rto S\u00e3o Domingos"
    ],
    "wof:name":"Porto Sao Domingos",
    "wof:placetype":"locality"
},
  "geometry": {"coordinates":[-50.75,-19.21667],"type":"Point"}
}