{
  "type": "Feature",
  "properties": {
    "gn:admin1_code":"30",
    "gn:admin2_code":"2615003.0",
    "gn:asciiname":"Pao de Acucar",
    "gn:country_code":"BR",
    "gn:dem":402,
    "gn:feature_class":"P",
    "gn:feature_code":"PPL",
    "gn:name":"P\u00e3o de A\u00e7\u00facar",
    "gn:population":0,
    "gn:timezone":"America/Recife",
    "iso:country":"BR",
    "wof:name":"Pao de Acucar",
    "wof:placetype":"locality"
},
  "geometry": {"coordinates":[-36.11667,-7.96667],"type":"Point"}
}