{
  "type": "Feature",
  "properties": {
    "gn:admin1_code":"15",
    "gn:admin2_code":"3154804.0",
    "gn:asciiname":"Ribeiro Machado",
    "gn:country_code":"BR",
    "gn:dem":804,
    "gn:feature_class":"P",
    "gn:feature_code":"PPL",
    "gn:name":"Ribeiro Machado",
    "gn:population":0,
    "gn:timezone":"America/Sao_Paulo",
    "iso:country":"BR",
    "name:por_x_preferred":[
        "Ribeiro Machado"
    ],
    "wof:name":"Ribeiro Machado",
    "wof:placetype":"locality"
},
  "geometry": {"coordinates":[-43.7739,-20.1124],"type":"Point"}
}