{
  "type": "Feature",
  "properties": {
    "gn:admin1_code":"31",
    "gn:admin2_code":"1720200.0",
    "gn:asciiname":"Sao Miguel do Tocantins",
    "gn:country_code":"BR",
    "gn:dem":99,
    "gn:feature_class":"P",
    "gn:feature_code":"PPL",
    "gn:name":"S\u00e3o Miguel do Tocantins",
    "gn:population":0,
    "gn:timezone":"America/Araguaina",
    "iso:country":"BR",
    "wof:name":"Sao Miguel do Tocantins",
    "wof:placetype":"locality"
},
  "geometry": {"coordinates":[-47.57811,-5.55196],"type":"Point"}
}