{
  "type": "Feature",
  "properties": {
    "gn:admin1_code":"1",
    "gn:admin2_code":"1200401.0",
    "gn:asciiname":"Amelia",
    "gn:country_code":"BR",
    "gn:dem":187,
    "gn:feature_class":"P",
    "gn:feature_code":"PPL",
    "gn:name":"Am\u00e9lia",
    "gn:population":0,
    "gn:timezone":"America/Rio_Branco",
    "iso:country":"BR",
    "wof:name":"Amelia",
    "wof:placetype":"locality"
},
  "geometry": {"coordinates":[-67.92471999999999,-9.88472],"type":"Point"}
}