{
  "type": "Feature",
  "properties": {
    "gn:admin1_code":"1",
    "gn:admin2_code":"1200401.0",
    "gn:asciiname":"Amelia",
    "gn:country_code":"BR",
    "gn:dem":187,
    "gn:feature_class":"P",
    "gn:feature_code":"PPL",
    "gn:name":"Am\u00e9lia",
    "gn:population":0,
    "gn:timezone":"America/Rio_Branco",
    "iso:country":"BR",
    "name:ceb_x_preferred":[
        "Amelia"
    ],
    "name:deu_x_preferred":[
        "Amelia"
    ],
    "name:est_x_preferred":[
        "Amelia"
    ],
    "name:fas_x_preferred":[
        "\u0622\u0645\u0644\u06cc\u0627"
    ],
    "name:fin_x_preferred":[
        "Amelia"
    ],
    "name:fra_x_preferred":[
        "Amelia"
    ],
    "name:hun_x_preferred":[
        "Am\u00e9lia"
    ],
    "name:hye_x_preferred":[
        "\u0531\u0574\u0565\u056c\u056b\u0561"
    ],
    "name:ita_x_preferred":[
        "Amelia"
    ],
    "name:jpn_x_preferred":[
        "\u30a2\u30e1\u30ea\u30a2"
    ],
    "name:kor_x_preferred":[
        "\uc544\uba5c\ub9ac\uc544"
    ],
    "name:msa_x_preferred":[
        "Amelia"
    ],
    "name:nld_x_preferred":[
        "Amelia"
    ],
    "name:pol_x_preferred":[
        "Amelia"
    ],
    "name:por_x_preferred":[
        "Am\u00e9lia"
    ],
    "name:rus_x_preferred":[
        "\u0410\u043c\u0435\u043b\u0438\u044f"
    ],
    "name:spa_x_preferred":[
        "Amelia"
    ],
    "name:srp_x_preferred":[
        "\u0410\u043c\u0438\u043b\u0438\u0458\u0430"
    ],
    "name:swe_x_preferred":[
        "Amelia"
    ],
    "name:tur_x_preferred":[
        "Amelia"
    ],
    "name:ukr_x_preferred":[
        "\u0410\u043c\u0435\u043b\u0456\u044f"
    ],
    "name:vol_x_preferred":[
        "Amelia"
    ],
    "wof:name":"Amelia",
    "wof:placetype":"locality"
},
  "geometry": {"coordinates":[-67.92471999999999,-9.88472],"type":"Point"}
}