{
  "type": "Feature",
  "properties": {
    "gn:admin1_code":"14",
    "gn:admin2_code":"5106505.0",
    "gn:asciiname":"Lavrinhas",
    "gn:country_code":"BR",
    "gn:dem":195,
    "gn:feature_class":"P",
    "gn:feature_code":"PPL",
    "gn:name":"Lavrinhas",
    "gn:population":0,
    "gn:timezone":"America/Cuiaba",
    "iso:country":"BR",
    "name:und_x_variant":[
        "Lavrinha",
        "Lavrinhas"
    ],
    "wof:name":"Lavrinhas",
    "wof:placetype":"locality"
},
  "geometry": {"coordinates":[-56.94728000000001,-15.94643],"type":"Point"}
}