{
  "type": "Feature",
  "properties": {
    "gn:admin1_code":"14",
    "gn:admin2_code":"5106505.0",
    "gn:asciiname":"Lavrinhas",
    "gn:country_code":"BR",
    "gn:dem":195,
    "gn:feature_class":"P",
    "gn:feature_code":"PPL",
    "gn:name":"Lavrinhas",
    "gn:population":0,
    "gn:timezone":"America/Cuiaba",
    "iso:country":"BR",
    "name:bpy_x_preferred":[
        "\u09b2\u09be\u09ad\u09b0\u09bf\u09a8\u09b9\u09be\u09b8"
    ],
    "name:ceb_x_preferred":[
        "Lavrinhas"
    ],
    "name:epo_x_preferred":[
        "Lavrinhas"
    ],
    "name:eus_x_preferred":[
        "Lavrinhas"
    ],
    "name:fra_x_preferred":[
        "Lavrinhas"
    ],
    "name:ita_x_preferred":[
        "Lavrinhas"
    ],
    "name:kaz_x_preferred":[
        "\u041b\u0430\u0432\u0440\u0438\u043d\u044c\u044f\u0441"
    ],
    "name:mlg_x_preferred":[
        "Lavrinhas"
    ],
    "name:nld_x_preferred":[
        "Lavrinhas"
    ],
    "name:nor_x_preferred":[
        "Lavrinhas"
    ],
    "name:pol_x_preferred":[
        "Lavrinhas"
    ],
    "name:por_x_preferred":[
        "Lavrinhas"
    ],
    "name:ron_x_preferred":[
        "Lavrinhas"
    ],
    "name:rus_x_preferred":[
        "\u041b\u0430\u0432\u0440\u0438\u043d\u044c\u044f\u0441"
    ],
    "name:swe_x_preferred":[
        "Lavrinhas"
    ],
    "name:und_x_variant":[
        "Lavrinha"
    ],
    "name:vie_x_preferred":[
        "Lavrinhas"
    ],
    "name:vol_x_preferred":[
        "Lavrinhas"
    ],
    "name:war_x_preferred":[
        "Lavrinhas"
    ],
    "name:zho_x_preferred":[
        "\u62c9\u592b\u91cc\u5c3c\u4e9a\u65af"
    ],
    "wof:name":"Lavrinhas",
    "wof:placetype":"locality"
},
  "geometry": {"coordinates":[-56.94728000000001,-15.94643],"type":"Point"}
}