{
  "type": "Feature",
  "properties": {
    "gn:admin1_code":"20",
    "gn:admin2_code":"2208809.0",
    "gn:asciiname":"Vista Alegre (1)",
    "gn:country_code":"BR",
    "gn:dem":365,
    "gn:feature_class":"P",
    "gn:feature_code":"PPL",
    "gn:name":"Vista Alegre (1)",
    "gn:population":0,
    "gn:timezone":"America/Fortaleza",
    "iso:country":"BR",
    "wof:name":"Vista Alegre (1)",
    "wof:placetype":"locality"
},
  "geometry": {"coordinates":[-42.35,-6.45],"type":"Point"}
}