{
  "type": "Feature",
  "properties": {
    "gn:admin1_code":"18.0",
    "gn:admin2_code":"4124103.0",
    "gn:asciiname":"Guimaraes Carneiro",
    "gn:country_code":"BR",
    "gn:dem":542,
    "gn:feature_class":"P",
    "gn:feature_code":"PPLL",
    "gn:name":"Guimar\u00e3es Carneiro",
    "gn:population":0,
    "gn:timezone":"America/Sao_Paulo",
    "iso:country":"BR",
    "name:por_x_preferred":[
        "Guimar\u00e3es Carneiro"
    ],
    "wof:name":"Guimaraes Carneiro",
    "wof:placetype":"locality"
},
  "geometry": {"coordinates":[-50.01331,-23.25853],"type":"Point"}
}