{
  "type": "Feature",
  "properties": {
    "gn:admin1_code":"06",
    "gn:admin2_code":"2312007.0",
    "gn:asciiname":"Vertentes (1)",
    "gn:country_code":"BR",
    "gn:dem":95,
    "gn:feature_class":"P",
    "gn:feature_code":"PPL",
    "gn:name":"Vertentes (1)",
    "gn:population":0,
    "gn:timezone":"America/Fortaleza",
    "iso:country":"BR",
    "wof:name":"Vertentes (1)",
    "wof:placetype":"locality"
},
  "geometry": {"coordinates":[-40.11667,-3.41667],"type":"Point"}
}