{
  "type": "Feature",
  "properties": {
    "gn:admin1_code":"5",
    "gn:admin2_code":"2915601.0",
    "gn:asciiname":"Fortaleza",
    "gn:country_code":"BR",
    "gn:dem":43,
    "gn:feature_class":"P",
    "gn:feature_code":"PPL",
    "gn:name":"Fortaleza",
    "gn:population":0,
    "gn:timezone":"America/Bahia",
    "iso:country":"BR",
    "name:por_x_preferred":[
        "Fortaleza"
    ],
    "wof:name":"Fortaleza",
    "wof:placetype":"locality"
},
  "geometry": {"coordinates":[-39.65,-16.98333],"type":"Point"}
}