{
  "type": "Feature",
  "properties": {
    "gn:admin1_code":"05",
    "gn:admin2_code":"2911402.0",
    "gn:asciiname":"Mari",
    "gn:country_code":"BR",
    "gn:dem":276,
    "gn:feature_class":"P",
    "gn:feature_code":"PPL",
    "gn:name":"Mari",
    "gn:population":0,
    "gn:timezone":"America/Bahia",
    "iso:country":"BR",
    "wof:name":"Mari",
    "wof:placetype":"locality"
},
  "geometry": {"coordinates":[-38.31667,-9.21667],"type":"Point"}
}