{
  "type": "Feature",
  "properties": {
    "gn:gn_country":"BR",
    "gn:gn_fcode":"PPL",
    "gn:gn_pop":50,
    "gn:population":50,
    "iso:country":"BR",
    "name:ceb_x_preferred":[
        "Barro Alto"
    ],
    "name:ita_x_preferred":[
        "Barro Alto"
    ],
    "name:nld_x_preferred":[
        "Barro Alto"
    ],
    "name:nor_x_preferred":[
        "Barro Alto"
    ],
    "name:por_x_preferred":[
        "Barro Alto"
    ],
    "name:ron_x_preferred":[
        "Barro Alto"
    ],
    "name:rus_x_preferred":[
        "\u0411\u0430\u0440\u0440\u0443-\u0410\u043b\u0442\u0443"
    ],
    "name:swe_x_preferred":[
        "Barro Alto"
    ],
    "name:vol_x_preferred":[
        "Barro Alto"
    ],
    "qs_pg:aaroncc":"BR",
    "qs_pg:gn_country":"BR",
    "qs_pg:gn_fcode":"PPL",
    "qs_pg:gn_pop":50,
    "qs_pg:name":"Barro Alto",
    "qs_pg:photos_9r":0,
    "qs_pg:photos_sr":0,
    "qs_pg:pop_sr":1,
    "qs_pg:qs_pg_placetype":"locality",
    "wof:name":"Barro Alto",
    "wof:placetype":"locality",
    "wof:population":50
},
  "geometry": {"coordinates":[-63.76667,-3.88333],"type":"Point"}
}