{
  "type": "Feature",
  "properties": {
    "gn:admin1_code":"06",
    "gn:admin2_code":"2303709.0",
    "gn:asciiname":"Icarai",
    "gn:country_code":"BR",
    "gn:dem":8,
    "gn:feature_class":"P",
    "gn:feature_code":"PPL",
    "gn:name":"Icara\u00ed",
    "gn:population":0,
    "gn:timezone":"America/Fortaleza",
    "iso:country":"BR",
    "name:por_x_preferred":[
        "Veraneio Icara\u00ed"
    ],
    "name:por_x_variant":[
        "Icara\u00ed"
    ],
    "wof:name":"Icarai",
    "wof:placetype":"locality"
},
  "geometry": {"coordinates":[-38.66755,-3.68788],"type":"Point"}
}