{
  "type": "Feature",
  "properties": {
    "gn:admin1_code":"27.0",
    "gn:admin2_code":"3502903.0",
    "gn:asciiname":"Sitio dos Frias",
    "gn:country_code":"BR",
    "gn:dem":632,
    "gn:feature_class":"P",
    "gn:feature_code":"PPL",
    "gn:name":"S\u00edtio dos Frias",
    "gn:population":0,
    "gn:timezone":"America/Sao_Paulo",
    "iso:country":"BR",
    "name:por_x_preferred":[
        "S\u00edtio dos Frias"
    ],
    "wof:name":"Sitio dos Frias",
    "wof:placetype":"locality"
},
  "geometry": {"coordinates":[-47.6449,-23.5701],"type":"Point"}
}