{
  "type": "Feature",
  "properties": {
    "gn:admin1_code":"26",
    "gn:admin2_code":"4210100.0",
    "gn:asciiname":"Sitio Otto Kohlbeck",
    "gn:country_code":"BR",
    "gn:dem":862,
    "gn:feature_class":"P",
    "gn:feature_code":"PPL",
    "gn:name":"S\u00edtio Otto Kohlbeck",
    "gn:population":0,
    "gn:timezone":"America/Sao_Paulo",
    "iso:country":"BR",
    "name:por_x_preferred":[
        "S\u00edtio Otto Kohlbeck"
    ],
    "wof:name":"Sitio Otto Kohlbeck",
    "wof:placetype":"locality"
},
  "geometry": {"coordinates":[-49.765,-26.1918],"type":"Point"}
}