{
  "type": "Feature",
  "properties": {
    "gn:admin1_code":"8",
    "gn:admin2_code":"3200102.0",
    "gn:asciiname":"Lagoinha",
    "gn:country_code":"BR",
    "gn:dem":1098,
    "gn:feature_class":"P",
    "gn:feature_code":"PPL",
    "gn:name":"Lagoinha",
    "gn:population":0,
    "gn:timezone":"America/Sao_Paulo",
    "iso:country":"BR",
    "name:por_x_preferred":[
        "Lagoinha"
    ],
    "wof:name":"Lagoinha",
    "wof:placetype":"locality"
},
  "geometry": {"coordinates":[-41.06667,-20.23333],"type":"Point"}
}