{
  "type": "Feature",
  "properties": {
    "gn:admin1_code":"18",
    "gn:admin2_code":"4128559.0",
    "gn:asciiname":"Aratinga",
    "gn:country_code":"BR",
    "gn:dem":569,
    "gn:feature_class":"P",
    "gn:feature_code":"PPLL",
    "gn:name":"Aratinga",
    "gn:population":0,
    "gn:timezone":"America/Sao_Paulo",
    "iso:country":"BR",
    "name:por_x_preferred":[
        "Aratinga"
    ],
    "wof:name":"Aratinga",
    "wof:placetype":"locality"
},
  "geometry": {"coordinates":[-53.8422,-25.0084],"type":"Point"}
}