{
  "type": "Feature",
  "properties": {
    "gn:admin1_code":"18",
    "gn:admin2_code":"4128559.0",
    "gn:asciiname":"Aratinga",
    "gn:country_code":"BR",
    "gn:dem":569,
    "gn:feature_class":"P",
    "gn:feature_code":"PPLL",
    "gn:name":"Aratinga",
    "gn:population":0,
    "gn:timezone":"America/Sao_Paulo",
    "iso:country":"BR",
    "name:bre_x_preferred":[
        "Aratinga"
    ],
    "name:cat_x_preferred":[
        "Aratinga"
    ],
    "name:ceb_x_preferred":[
        "Aratinga"
    ],
    "name:ces_x_preferred":[
        "Aratinga"
    ],
    "name:deu_x_preferred":[
        "Keilschwanzsittiche"
    ],
    "name:fas_x_preferred":[
        "\u062f\u0645\u200c\u0642\u06cc\u0641\u06cc\u200c\u0647\u0627"
    ],
    "name:fin_x_preferred":[
        "Viheraratit"
    ],
    "name:fra_x_preferred":[
        "Aratinga"
    ],
    "name:grn_x_preferred":[
        "Arat\u0129nga"
    ],
    "name:heb_x_preferred":[
        "\u05e7\u05d5\u05e0\u05d9\u05d5\u05e8"
    ],
    "name:hun_x_preferred":[
        "Aratinga"
    ],
    "name:ita_x_preferred":[
        "Aratinga"
    ],
    "name:jpn_x_preferred":[
        "\u30af\u30b5\u30d3\u30aa\u30a4\u30f3\u30b3\u5c5e"
    ],
    "name:lit_x_preferred":[
        "Tikrosios aratingos"
    ],
    "name:mrj_x_preferred":[
        "\u0410\u0440\u0430\u0442\u0438\u043d\u0433\u0430"
    ],
    "name:msa_x_preferred":[
        "Aratinga"
    ],
    "name:nld_x_preferred":[
        "Aratinga"
    ],
    "name:nno_x_preferred":[
        "Aratinga"
    ],
    "name:pol_x_preferred":[
        "Aratinga"
    ],
    "name:por_x_preferred":[
        "Aratinga"
    ],
    "name:que_x_preferred":[
        "Q'aqchu"
    ],
    "name:rus_x_preferred":[
        "\u0410\u0440\u0430\u0442\u0438\u043d\u0433\u0438"
    ],
    "name:spa_x_preferred":[
        "Aratinga"
    ],
    "name:swe_x_preferred":[
        "Aratinga"
    ],
    "name:ukr_x_preferred":[
        "\u0410\u0440\u0430\u0442\u0438\u043d\u0433\u0430"
    ],
    "name:vie_x_preferred":[
        "Aratinga"
    ],
    "name:war_x_preferred":[
        "Aratinga"
    ],
    "name:zho_x_preferred":[
        "\u9525\u5c3e\u9e66\u54e5\u5c5e"
    ],
    "wof:name":"Aratinga",
    "wof:placetype":"locality"
},
  "geometry": {"coordinates":[-53.8422,-25.0084],"type":"Point"}
}