{
  "type": "Feature",
  "properties": {
    "gn:admin1_code":"22",
    "gn:admin2_code":"2400307.0",
    "gn:asciiname":"Juazeiro",
    "gn:country_code":"BR",
    "gn:dem":50,
    "gn:feature_class":"P",
    "gn:feature_code":"PPL",
    "gn:name":"Juazeiro",
    "gn:population":0,
    "gn:timezone":"America/Fortaleza",
    "iso:country":"BR",
    "wof:name":"Juazeiro",
    "wof:placetype":"locality"
},
  "geometry": {"coordinates":[-36.52056,-5.47861],"type":"Point"}
}