{
  "type": "Feature",
  "properties": {
    "gn:admin1_code":"22",
    "gn:admin2_code":"2400307.0",
    "gn:asciiname":"Juazeiro",
    "gn:country_code":"BR",
    "gn:dem":50,
    "gn:feature_class":"P",
    "gn:feature_code":"PPL",
    "gn:name":"Juazeiro",
    "gn:population":0,
    "gn:timezone":"America/Fortaleza",
    "iso:country":"BR",
    "name:ara_x_preferred":[
        "\u062c\u0648\u0627\u0632\u064a\u0631\u0648"
    ],
    "name:bpy_x_preferred":[
        "\u099c\u09c1\u09f1\u09be\u099c\u09af\u09bc\u09c7\u0987\u09b0\u09cb"
    ],
    "name:bre_x_preferred":[
        "Juazeiro"
    ],
    "name:bul_x_preferred":[
        "\u0416\u0443\u0430\u0437\u0435\u0439\u0440\u043e"
    ],
    "name:cat_x_preferred":[
        "Juazeiro"
    ],
    "name:ceb_x_preferred":[
        "Juazeiro"
    ],
    "name:deu_x_preferred":[
        "Juazeiro"
    ],
    "name:epo_x_preferred":[
        "Juazeiro"
    ],
    "name:eus_x_preferred":[
        "Juazeiro"
    ],
    "name:fra_x_preferred":[
        "Juazeiro"
    ],
    "name:heb_x_preferred":[
        "\u05d6'\u05d5\u05d0\u05d6\u05d9\u05d9\u05e8\u05d5"
    ],
    "name:hrv_x_preferred":[
        "Juazeiro"
    ],
    "name:hye_x_preferred":[
        "\u053a\u0578\u0582\u0561\u0566\u0565\u0575\u0580\u0578\u0582"
    ],
    "name:ido_x_preferred":[
        "Juazeiro"
    ],
    "name:ita_x_preferred":[
        "Juazeiro"
    ],
    "name:kat_x_preferred":[
        "\u10df\u10e3\u10d0\u10d6\u10d4\u10d8\u10e0\u10e3"
    ],
    "name:kaz_x_preferred":[
        "\u0416\u0443\u0430\u0437\u0435\u0439\u0440\u0443"
    ],
    "name:lit_x_preferred":[
        "\u017duazeiras"
    ],
    "name:mlg_x_preferred":[
        "Juazeiro"
    ],
    "name:nld_x_preferred":[
        "Juazeiro"
    ],
    "name:nor_x_preferred":[
        "Juazeiro"
    ],
    "name:pol_x_preferred":[
        "Juazeiro"
    ],
    "name:por_x_preferred":[
        "Juazeiro"
    ],
    "name:ron_x_preferred":[
        "Juazeiro"
    ],
    "name:rus_x_preferred":[
        "\u0416\u0443\u0430\u0437\u0435\u0439\u0440\u0443"
    ],
    "name:spa_x_preferred":[
        "Juazeiro"
    ],
    "name:srp_x_preferred":[
        "\u0416\u0443\u0430\u0437\u0435\u0438\u0440\u043e"
    ],
    "name:swe_x_preferred":[
        "Juazeiro"
    ],
    "name:szl_x_preferred":[
        "Juazeiro"
    ],
    "name:tat_x_preferred":[
        "\u0416\u0432\u0430\u0437\u0435\u0439\u0440\u0443"
    ],
    "name:tha_x_preferred":[
        "\u0e08\u0e39\u0e2d\u0e32\u0e40\u0e0b\u0e22\u0e4c\u0e23\u0e39"
    ],
    "name:vie_x_preferred":[
        "Juazeiro"
    ],
    "name:vol_x_preferred":[
        "Juazeiro"
    ],
    "name:war_x_preferred":[
        "Juazeiro"
    ],
    "name:zho_x_preferred":[
        "\u8339\u963f\u6fa4\u9b6f"
    ],
    "wof:name":"Juazeiro",
    "wof:placetype":"locality"
},
  "geometry": {"coordinates":[-36.52056,-5.47861],"type":"Point"}
}