{
  "type": "Feature",
  "properties": {
    "gn:admin1_code":"06",
    "gn:admin2_code":"2303303.0",
    "gn:asciiname":"Xiquexique",
    "gn:country_code":"BR",
    "gn:dem":295,
    "gn:feature_class":"P",
    "gn:feature_code":"PPL",
    "gn:name":"Xiquexique",
    "gn:population":0,
    "gn:timezone":"America/Fortaleza",
    "iso:country":"BR",
    "wof:name":"Xiquexique",
    "wof:placetype":"locality"
},
  "geometry": {"coordinates":[-39.43333,-6.61667],"type":"Point"}
}