{
  "type": "Feature",
  "properties": {
    "gn:admin1_code":"20",
    "gn:admin2_code":"2200301.0",
    "gn:asciiname":"Sao Paulo",
    "gn:country_code":"BR",
    "gn:dem":103,
    "gn:feature_class":"P",
    "gn:feature_code":"PPL",
    "gn:name":"S\u00e3o Paulo",
    "gn:population":0,
    "gn:timezone":"America/Fortaleza",
    "iso:country":"BR",
    "wof:name":"Sao Paulo",
    "wof:placetype":"locality"
},
  "geometry": {"coordinates":[-42.06667,-5.56667],"type":"Point"}
}