{
  "type": "Feature",
  "properties": {
    "gn:admin1_code":"15",
    "gn:admin2_code":"3122405.0",
    "gn:asciiname":"Francisco Pereira",
    "gn:country_code":"BR",
    "gn:dem":798,
    "gn:feature_class":"P",
    "gn:feature_code":"PPL",
    "gn:name":"Francisco Pereira",
    "gn:population":0,
    "gn:timezone":"America/Sao_Paulo",
    "iso:country":"BR",
    "name:por_x_preferred":[
        "Francisco Pereira"
    ],
    "wof:name":"Francisco Pereira",
    "wof:placetype":"locality"
},
  "geometry": {"coordinates":[-46.23333,-21.46667],"type":"Point"}
}