{
  "type": "Feature",
  "properties": {
    "gn:admin1_code":"18.0",
    "gn:admin2_code":"4116208.0",
    "gn:asciiname":"Sitio Izac Forui",
    "gn:country_code":"BR",
    "gn:dem":20,
    "gn:feature_class":"P",
    "gn:feature_code":"PPL",
    "gn:name":"S\u00edtio Izac Forui",
    "gn:population":0,
    "gn:timezone":"America/Sao_Paulo",
    "iso:country":"BR",
    "name:por_x_preferred":[
        "S\u00edtio Izac Forui"
    ],
    "wof:name":"Sitio Izac Forui",
    "wof:placetype":"locality"
},
  "geometry": {"coordinates":[-48.81185,-25.46097],"type":"Point"}
}