{
  "type": "Feature",
  "properties": {
    "gn:admin1_code":"28",
    "gn:admin2_code":"2805604.0",
    "gn:asciiname":"Caicara",
    "gn:country_code":"BR",
    "gn:dem":38,
    "gn:feature_class":"P",
    "gn:feature_code":"PPL",
    "gn:name":"Cai\u00e7ara",
    "gn:population":0,
    "gn:timezone":"America/Maceio",
    "iso:country":"BR",
    "wof:name":"Caicara",
    "wof:placetype":"locality"
},
  "geometry": {"coordinates":[-37.26667,-9.86667],"type":"Point"}
}