{
  "type": "Feature",
  "properties": {
    "gn:admin1_code":"27",
    "gn:admin2_code":"3519709.0",
    "gn:asciiname":"Colegio",
    "gn:country_code":"BR",
    "gn:dem":873,
    "gn:feature_class":"P",
    "gn:feature_code":"PPL",
    "gn:name":"Col\u00e9gio",
    "gn:population":0,
    "gn:timezone":"America/Sao_Paulo",
    "iso:country":"BR",
    "name:por_x_preferred":[
        "Col\u00e9gio"
    ],
    "wof:name":"Colegio",
    "wof:placetype":"locality"
},
  "geometry": {"coordinates":[-47.30793,-23.71131],"type":"Point"}
}