{
  "type": "Feature",
  "properties": {
    "gn:admin1_code":"24",
    "gn:admin2_code":"1100940.0",
    "gn:asciiname":"Vera Cruz",
    "gn:cc2":"BR",
    "gn:country_code":"BR",
    "gn:dem":165,
    "gn:feature_class":"P",
    "gn:feature_code":"PPL",
    "gn:name":"Vera Cruz",
    "gn:population":0,
    "gn:timezone":"America/Porto_Velho",
    "iso:country":"BR",
    "name:und_x_variant":[
        "Santa Cruz",
        "Vera Cruz"
    ],
    "wof:name":"Vera Cruz",
    "wof:placetype":"locality"
},
  "geometry": {"coordinates":[-62.38333000000001,-9.26667],"type":"Point"}
}