{
  "type": "Feature",
  "properties": {
    "gn:admin1_code":"18.0",
    "gn:admin2_code":"4107751.0",
    "gn:asciiname":"Sitio Sinesio I. Ferreira",
    "gn:country_code":"BR",
    "gn:dem":644,
    "gn:feature_class":"P",
    "gn:feature_code":"PPL",
    "gn:name":"S\u00edtio Sin\u00e9sio I. Ferreira",
    "gn:population":0,
    "gn:timezone":"America/Sao_Paulo",
    "iso:country":"BR",
    "name:por_x_preferred":[
        "S\u00edtio Sin\u00e9sio I. Ferreira"
    ],
    "wof:name":"Sitio Sinesio I. Ferreira",
    "wof:placetype":"locality"
},
  "geometry": {"coordinates":[-50.40942,-23.91642],"type":"Point"}
}