{
  "type": "Feature",
  "properties": {
    "gn:admin1_code":"27",
    "gn:admin2_code":"3550605.0",
    "gn:asciiname":"Moinho Grande",
    "gn:country_code":"BR",
    "gn:dem":854,
    "gn:feature_class":"P",
    "gn:feature_code":"PPLL",
    "gn:name":"Moinho Grande",
    "gn:population":0,
    "gn:timezone":"America/Sao_Paulo",
    "iso:country":"BR",
    "name:por_x_preferred":[
        "Moinho Grande"
    ],
    "wof:name":"Moinho Grande",
    "wof:placetype":"locality"
},
  "geometry": {"coordinates":[-47.03414,-23.55314],"type":"Point"}
}