{
  "type": "Feature",
  "properties": {
    "gn:admin1_code":"11",
    "gn:admin2_code":"5002209.0",
    "gn:asciiname":"Erval",
    "gn:cc2":"BR",
    "gn:country_code":"BR",
    "gn:dem":245,
    "gn:feature_class":"P",
    "gn:feature_code":"PPL",
    "gn:name":"Erval",
    "gn:population":0,
    "gn:timezone":"America/Campo_Grande",
    "iso:country":"BR",
    "name:und_x_variant":[
        "Herval",
        "Erval"
    ],
    "wof:name":"Erval",
    "wof:placetype":"locality"
},
  "geometry": {"coordinates":[-56.28333000000001,-20.73333],"type":"Point"}
}