{
  "type": "Feature",
  "properties": {
    "gn:admin1_code":"5",
    "gn:admin2_code":"2933406.0",
    "gn:asciiname":"Piraja",
    "gn:country_code":"BR",
    "gn:dem":504,
    "gn:feature_class":"P",
    "gn:feature_code":"PPL",
    "gn:name":"Piraj\u00e1",
    "gn:population":0,
    "gn:timezone":"America/Bahia",
    "iso:country":"BR",
    "wof:name":"Piraja",
    "wof:placetype":"locality"
},
  "geometry": {"coordinates":[-41.15,-12.25],"type":"Point"}
}