{
  "type": "Feature",
  "properties": {
    "gn:admin1_code":"5",
    "gn:admin2_code":"2902708.0",
    "gn:asciiname":"Riacho",
    "gn:country_code":"BR",
    "gn:dem":427,
    "gn:feature_class":"P",
    "gn:feature_code":"PPL",
    "gn:name":"Riacho",
    "gn:population":0,
    "gn:timezone":"America/Bahia",
    "iso:country":"BR",
    "name:fra_x_preferred":[
        "Riacho"
    ],
    "name:por_x_preferred":[
        "Riacho"
    ],
    "wof:name":"Riacho",
    "wof:placetype":"locality"
},
  "geometry": {"coordinates":[-43.28333,-10.88333],"type":"Point"}
}