{
  "type": "Feature",
  "properties": {
    "gn:admin1_code":"15",
    "gn:admin2_code":"3121308.0",
    "gn:asciiname":"Araci",
    "gn:country_code":"BR",
    "gn:dem":378,
    "gn:feature_class":"P",
    "gn:feature_code":"PPL",
    "gn:name":"Araci",
    "gn:population":0,
    "gn:timezone":"America/Sao_Paulo",
    "iso:country":"BR",
    "name:bpy_x_preferred":[
        "\u09f1\u09be\u09b0\u09be\u09b8\u09bf"
    ],
    "name:ceb_x_preferred":[
        "Araci"
    ],
    "name:epo_x_preferred":[
        "Araci"
    ],
    "name:eus_x_preferred":[
        "Araci"
    ],
    "name:fra_x_preferred":[
        "Araci"
    ],
    "name:hye_x_preferred":[
        "\u0531\u0580\u0561\u057d\u056b"
    ],
    "name:ita_x_preferred":[
        "Araci"
    ],
    "name:kat_x_preferred":[
        "\u10d0\u10e0\u10d0\u10e1\u10d8"
    ],
    "name:kaz_x_preferred":[
        "\u0410\u0440\u0430\u0441\u0438"
    ],
    "name:mlg_x_preferred":[
        "Araci"
    ],
    "name:nld_x_preferred":[
        "Araci"
    ],
    "name:nor_x_preferred":[
        "Araci"
    ],
    "name:pol_x_preferred":[
        "Araci"
    ],
    "name:por_x_preferred":[
        "Araci"
    ],
    "name:ron_x_preferred":[
        "Araci"
    ],
    "name:rus_x_preferred":[
        "\u0410\u0440\u0430\u0441\u0438"
    ],
    "name:spa_x_preferred":[
        "Araci"
    ],
    "name:swe_x_preferred":[
        "Araci"
    ],
    "name:vie_x_preferred":[
        "Araci"
    ],
    "name:vol_x_preferred":[
        "Araci"
    ],
    "name:war_x_preferred":[
        "Araci"
    ],
    "name:zho_x_preferred":[
        "\u963f\u62c9\u897f"
    ],
    "wof:name":"Araci",
    "wof:placetype":"locality"
},
  "geometry": {"coordinates":[-42.93333,-21.51667],"type":"Point"}
}