{
  "type": "Feature",
  "properties": {
    "gn:admin1_code":"15",
    "gn:admin2_code":"3121308.0",
    "gn:asciiname":"Araci",
    "gn:country_code":"BR",
    "gn:dem":378,
    "gn:feature_class":"P",
    "gn:feature_code":"PPL",
    "gn:name":"Araci",
    "gn:population":0,
    "gn:timezone":"America/Sao_Paulo",
    "iso:country":"BR",
    "name:por_x_preferred":[
        "Araci"
    ],
    "wof:name":"Araci",
    "wof:placetype":"locality"
},
  "geometry": {"coordinates":[-42.93333,-21.51667],"type":"Point"}
}