{
  "type": "Feature",
  "properties": {
    "gn:admin1_code":"22",
    "gn:admin2_code":"2414506.0",
    "gn:asciiname":"Jurema",
    "gn:country_code":"BR",
    "gn:dem":180,
    "gn:feature_class":"P",
    "gn:feature_code":"PPL",
    "gn:name":"Jurema",
    "gn:population":0,
    "gn:timezone":"America/Fortaleza",
    "iso:country":"BR",
    "wof:name":"Jurema",
    "wof:placetype":"locality"
},
  "geometry": {"coordinates":[-37.81667,-6.05],"type":"Point"}
}