{
  "type": "Feature",
  "properties": {
    "gn:admin1_code":"23",
    "gn:admin2_code":"4308201.0",
    "gn:asciiname":"Travessa Lagoa Bela",
    "gn:country_code":"BR",
    "gn:dem":745,
    "gn:feature_class":"P",
    "gn:feature_code":"PPLL",
    "gn:name":"Travessa Lagoa Bela",
    "gn:population":0,
    "gn:timezone":"America/Sao_Paulo",
    "iso:country":"BR",
    "name:por_x_preferred":[
        "Travessa Lagoa Bela"
    ],
    "wof:name":"Travessa Lagoa Bela",
    "wof:placetype":"locality"
},
  "geometry": {"coordinates":[-51.2039,-29.0121],"type":"Point"}
}