{
  "type": "Feature",
  "properties": {
    "gn:admin1_code":"18.0",
    "gn:admin2_code":"4126207.0",
    "gn:asciiname":"Sitio Senhor Bom Jesus",
    "gn:country_code":"BR",
    "gn:dem":797,
    "gn:feature_class":"P",
    "gn:feature_code":"PPL",
    "gn:name":"S\u00edtio Senhor Bom Jesus",
    "gn:population":0,
    "gn:timezone":"America/Sao_Paulo",
    "iso:country":"BR",
    "name:por_x_preferred":[
        "S\u00edtio Senhor Bom Jesus"
    ],
    "wof:name":"Sitio Senhor Bom Jesus",
    "wof:placetype":"locality"
},
  "geometry": {"coordinates":[-50.56946,-23.86777],"type":"Point"}
}