{
  "type": "Feature",
  "properties": {
    "gn:admin1_code":"5",
    "gn:admin2_code":"2900108.0",
    "gn:asciiname":"Mandiocal",
    "gn:country_code":"BR",
    "gn:dem":663,
    "gn:feature_class":"P",
    "gn:feature_code":"PPL",
    "gn:name":"Mandiocal",
    "gn:population":0,
    "gn:timezone":"America/Bahia",
    "iso:country":"BR",
    "wof:name":"Mandiocal",
    "wof:placetype":"locality"
},
  "geometry": {"coordinates":[-41.61667,-13.25],"type":"Point"}
}