{
  "type": "Feature",
  "properties": {
    "gn:admin1_code":"4",
    "gn:admin2_code":"1300805.0",
    "gn:asciiname":"Novo Remedio",
    "gn:country_code":"BR",
    "gn:dem":28,
    "gn:feature_class":"P",
    "gn:feature_code":"PPL",
    "gn:name":"Novo Rem\u00e9dio",
    "gn:population":0,
    "gn:timezone":"America/Manaus",
    "iso:country":"BR",
    "wof:name":"Novo Remedio",
    "wof:placetype":"locality"
},
  "geometry": {"coordinates":[-59.76778,-4.3675],"type":"Point"}
}