{
  "type": "Feature",
  "properties": {
    "gn:admin1_code":"4",
    "gn:admin2_code":"1304104.0",
    "gn:asciiname":"Ancori",
    "gn:cc2":"BR",
    "gn:country_code":"BR",
    "gn:dem":68,
    "gn:feature_class":"P",
    "gn:feature_code":"PPL",
    "gn:name":"Ancori",
    "gn:population":0,
    "gn:timezone":"America/Manaus",
    "iso:country":"BR",
    "name:und_x_variant":[
        "Anacory",
        "Ancari",
        "Ancori"
    ],
    "wof:name":"Ancori",
    "wof:placetype":"locality"
},
  "geometry": {"coordinates":[-63.13166999999999,-5.66417],"type":"Point"}
}