{
  "type": "Feature",
  "properties": {
    "gn:admin1_code":"25",
    "gn:admin2_code":"1400027.0",
    "gn:asciiname":"Sao Joaquim",
    "gn:country_code":"BR",
    "gn:dem":129,
    "gn:feature_class":"P",
    "gn:feature_code":"PPL",
    "gn:name":"S\u00e3o Joaquim",
    "gn:population":0,
    "gn:timezone":"America/Boa_Vista",
    "iso:country":"BR",
    "wof:name":"Sao Joaquim",
    "wof:placetype":"locality"
},
  "geometry": {"coordinates":[-61.46666999999999,3.83333],"type":"Point"}
}