{
  "type": "Feature",
  "properties": {
    "gn:admin1_code":"18.0",
    "gn:admin2_code":"4114302.0",
    "gn:asciiname":"Sitio Lourenco Megosek",
    "gn:country_code":"BR",
    "gn:dem":914,
    "gn:feature_class":"P",
    "gn:feature_code":"PPL",
    "gn:name":"S\u00edtio Louren\u00e7o Megosek",
    "gn:population":0,
    "gn:timezone":"America/Sao_Paulo",
    "iso:country":"BR",
    "name:por_x_preferred":[
        "S\u00edtio Louren\u00e7o Megosek"
    ],
    "wof:name":"Sitio Lourenco Megosek",
    "wof:placetype":"locality"
},
  "geometry": {"coordinates":[-49.3664,-25.893],"type":"Point"}
}