{
  "type": "Feature",
  "properties": {
    "gn:admin1_code":"13",
    "gn:admin2_code":"2112605.0",
    "gn:asciiname":"Barreiro",
    "gn:country_code":"BR",
    "gn:dem":64,
    "gn:feature_class":"P",
    "gn:feature_code":"PPL",
    "gn:name":"Barreiro",
    "gn:population":0,
    "gn:timezone":"America/Fortaleza",
    "iso:country":"BR",
    "name:ceb_x_preferred":[
        "Barreiro"
    ],
    "name:deu_x_preferred":[
        "Barreiro"
    ],
    "name:fra_x_preferred":[
        "Barreiro"
    ],
    "name:glg_x_preferred":[
        "Barreiro"
    ],
    "name:ita_x_preferred":[
        "Barreiro"
    ],
    "name:nld_x_preferred":[
        "Barreiro"
    ],
    "name:por_x_preferred":[
        "Barreiro"
    ],
    "name:spa_x_preferred":[
        "Barreiro"
    ],
    "name:swe_x_preferred":[
        "Barreiro"
    ],
    "wof:name":"Barreiro",
    "wof:placetype":"locality"
},
  "geometry": {"coordinates":[-43.33583,-3.21083],"type":"Point"}
}