{
  "type": "Feature",
  "properties": {
    "gn:admin1_code":"23",
    "gn:admin2_code":"4315602.0",
    "gn:asciiname":"Vila Siqueira",
    "gn:country_code":"BR",
    "gn:dem":1,
    "gn:feature_class":"P",
    "gn:feature_code":"PPL",
    "gn:name":"Vila Siqueira",
    "gn:population":0,
    "gn:timezone":"America/Sao_Paulo",
    "iso:country":"BR",
    "wof:name":"Vila Siqueira",
    "wof:placetype":"locality"
},
  "geometry": {"coordinates":[-52.10833,-32.15],"type":"Point"}
}