{
  "type": "Feature",
  "properties": {
    "gn:admin1_code":"16",
    "gn:admin2_code":"1507458.0",
    "gn:asciiname":"Sao Geraldo do Araguaia",
    "gn:country_code":"BR",
    "gn:dem":131,
    "gn:feature_class":"P",
    "gn:feature_code":"PPL",
    "gn:name":"S\u00e3o Geraldo do Araguaia",
    "gn:population":12925,
    "gn:timezone":"America/Araguaina",
    "iso:country":"BR",
    "wof:name":"Sao Geraldo do Araguaia",
    "wof:placetype":"locality",
    "wof:population":12925
},
  "geometry": {"coordinates":[-48.555,-6.40056],"type":"Point"}
}