{
  "type": "Feature",
  "properties": {
    "gn:admin1_code":"27.0",
    "gn:admin2_code":"3521200.0",
    "gn:asciiname":"Bairro Camargo",
    "gn:country_code":"BR",
    "gn:dem":147,
    "gn:feature_class":"P",
    "gn:feature_code":"PPLL",
    "gn:name":"Bairro Camargo",
    "gn:population":0,
    "gn:timezone":"America/Sao_Paulo",
    "iso:country":"BR",
    "name:por_x_preferred":[
        "Bairro Camargo"
    ],
    "wof:name":"Bairro Camargo",
    "wof:placetype":"locality"
},
  "geometry": {"coordinates":[-48.58128,-24.50942],"type":"Point"}
}