{
  "type": "Feature",
  "properties": {
    "gn:admin1_code":"4",
    "gn:admin2_code":"1300409.0",
    "gn:asciiname":"Baruri",
    "gn:country_code":"BR",
    "gn:dem":41,
    "gn:feature_class":"P",
    "gn:feature_code":"PPL",
    "gn:name":"Baruri",
    "gn:population":0,
    "gn:timezone":"America/Manaus",
    "iso:country":"BR",
    "wof:name":"Baruri",
    "wof:placetype":"locality"
},
  "geometry": {"coordinates":[-63.01667,-0.88333],"type":"Point"}
}