{
  "type": "Feature",
  "properties": {
    "gn:admin1_code":"16",
    "gn:admin2_code":"1503754.0",
    "gn:asciiname":"Prainha",
    "gn:country_code":"BR",
    "gn:dem":216,
    "gn:feature_class":"P",
    "gn:feature_code":"PPL",
    "gn:name":"Prainha",
    "gn:population":0,
    "gn:timezone":"America/Santarem",
    "iso:country":"BR",
    "name:bpy_x_preferred":[
        "\u09aa\u09cd\u09b0\u09be\u0987\u09a8\u09b9\u09be"
    ],
    "name:ceb_x_preferred":[
        "Prainha"
    ],
    "name:deu_x_preferred":[
        "Prainha"
    ],
    "name:nld_x_preferred":[
        "Prainha"
    ],
    "name:por_x_preferred":[
        "Prainha"
    ],
    "name:rus_x_preferred":[
        "\u041f\u0440\u0430\u0438\u043d\u044c\u044f"
    ],
    "name:swe_x_preferred":[
        "Prainha"
    ],
    "wof:name":"Prainha",
    "wof:placetype":"locality"
},
  "geometry": {"coordinates":[-57.75,-6.66667],"type":"Point"}
}