{
  "type": "Feature",
  "properties": {
    "gn:admin1_code":"16",
    "gn:admin2_code":"1503754.0",
    "gn:asciiname":"Prainha",
    "gn:country_code":"BR",
    "gn:dem":216,
    "gn:feature_class":"P",
    "gn:feature_code":"PPL",
    "gn:name":"Prainha",
    "gn:population":0,
    "gn:timezone":"America/Santarem",
    "iso:country":"BR",
    "wof:name":"Prainha",
    "wof:placetype":"locality"
},
  "geometry": {"coordinates":[-57.75,-6.66667],"type":"Point"}
}