{
  "type": "Feature",
  "properties": {
    "gn:admin1_code":"18.0",
    "gn:admin2_code":"4122305.0",
    "gn:asciiname":"Sitio Anastacio Kimiescki",
    "gn:country_code":"BR",
    "gn:dem":885,
    "gn:feature_class":"P",
    "gn:feature_code":"PPL",
    "gn:name":"S\u00edtio Anast\u00e1cio Kimiescki",
    "gn:population":0,
    "gn:timezone":"America/Sao_Paulo",
    "iso:country":"BR",
    "name:por_x_preferred":[
        "S\u00edtio Anast\u00e1cio Kimiescki"
    ],
    "wof:name":"Sitio Anastacio Kimiescki",
    "wof:placetype":"locality"
},
  "geometry": {"coordinates":[-49.8293,-26.012],"type":"Point"}
}