{
  "type": "Feature",
  "properties": {
    "gn:admin1_code":"15",
    "gn:admin2_code":"3157658.0",
    "gn:asciiname":"Aldeia do Prata",
    "gn:cc2":"BR",
    "gn:country_code":"BR",
    "gn:dem":585,
    "gn:feature_class":"P",
    "gn:feature_code":"PPL",
    "gn:name":"Aldeia do Prata",
    "gn:population":0,
    "gn:timezone":"America/Sao_Paulo",
    "iso:country":"BR",
    "name:und_x_variant":[
        "Aideia do Prata",
        "Aldeia do Prata"
    ],
    "wof:name":"Aldeia do Prata",
    "wof:placetype":"locality"
},
  "geometry": {"coordinates":[-40.61667,-16.81667],"type":"Point"}
}