{
  "type": "Feature",
  "properties": {
    "gn:admin1_code":"30",
    "gn:admin2_code":"2608602.0",
    "gn:asciiname":"Alecrim",
    "gn:country_code":"BR",
    "gn:dem":595,
    "gn:feature_class":"P",
    "gn:feature_code":"PPL",
    "gn:name":"Alecrim",
    "gn:population":0,
    "gn:timezone":"America/Recife",
    "iso:country":"BR",
    "wof:name":"Alecrim",
    "wof:placetype":"locality"
},
  "geometry": {"coordinates":[-36.48333,-9.15],"type":"Point"}
}