{
  "type": "Feature",
  "properties": {
    "iso:country":"BR",
    "name:por_x_preferred":[
        "Vila Matias",
        "Esta\u00e7\u00e3o Concei\u00e7\u00e3o"
    ],
    "name:spa_x_preferred":[
        "Estaci\u00f3n Concei\u00e7\u00e3o"
    ],
    "qs:gn_adm0_cc":"BR",
    "qs:gn_fcode":"PPLX",
    "qs:gn_local":3449433,
    "qs:gn_nam_loc":"Santos, Santos, S\u00e3o Paulo, BR",
    "qs:gn_namadm1":"27",
    "qs:gn_name":"Vila Matias",
    "qs:local_max":2045,
    "qs:local_sum":15648,
    "qs:localhoods":22,
    "qs:name":"Vila Matias",
    "qs:name_adm0":"Brasil",
    "qs:name_adm1":"S\u00e3o Paulo",
    "qs:name_adm2":"Santos",
    "qs:name_local":"Santos",
    "qs:photo_max":358,
    "qs:photo_sum":1563,
    "qs:placetype":"Suburb",
    "qs:quad_count":25,
    "qs:woe_adm0":23424768,
    "qs:woe_adm1":2344868,
    "qs:woe_adm2":12582296,
    "qs:woe_lau":0,
    "qs:woe_local":455991,
    "qs:woe_ver":"7.10.0",
    "wof:lang":[
        "por"
    ],
    "wof:name":"Vila Matias",
    "wof:placetype":"neighbourhood"
},
  "geometry": {"coordinates":[-46.331614,-23.949055],"type":"Point"}
}