{
  "type": "Feature",
  "properties": {
    "gn:admin1_code":"16",
    "gn:admin2_code":"1507300.0",
    "gn:asciiname":"Maguari",
    "gn:country_code":"BR",
    "gn:dem":206,
    "gn:feature_class":"P",
    "gn:feature_code":"PPL",
    "gn:name":"Maguari",
    "gn:population":0,
    "gn:timezone":"America/Belem",
    "iso:country":"BR",
    "wof:name":"Maguari",
    "wof:placetype":"locality"
},
  "geometry": {"coordinates":[-51.88333,-6.63333],"type":"Point"}
}