{
  "type": "Feature",
  "properties": {
    "gn:admin1_code":"06",
    "gn:admin2_code":"2313500.0",
    "gn:asciiname":"Olho d'Agua (2)",
    "gn:country_code":"BR",
    "gn:dem":30,
    "gn:feature_class":"P",
    "gn:feature_code":"PPL",
    "gn:name":"\u00d4lho d\u2019\u00c1gua (2)",
    "gn:population":0,
    "gn:timezone":"America/Fortaleza",
    "iso:country":"BR",
    "wof:name":"Olho d'Agua (2)",
    "wof:placetype":"locality"
},
  "geometry": {"coordinates":[-39.38333,-3.26667],"type":"Point"}
}