{
  "type": "Feature",
  "properties": {
    "gn:admin1_code":"21",
    "gn:admin2_code":"3304144.0",
    "gn:asciiname":"Engenheiro Pedreira",
    "gn:country_code":"BR",
    "gn:dem":40,
    "gn:feature_class":"P",
    "gn:feature_code":"PPL",
    "gn:name":"Engenheiro Pedreira",
    "gn:population":0,
    "gn:timezone":"America/Sao_Paulo",
    "iso:country":"BR",
    "name:por_x_preferred":[
        "Engenheiro Pedreira"
    ],
    "wof:name":"Engenheiro Pedreira",
    "wof:placetype":"locality"
},
  "geometry": {"coordinates":[-43.59556,-22.68944],"type":"Point"}
}