{
  "type": "Feature",
  "properties": {
    "gn:admin1_code":"30",
    "gn:admin2_code":"2601607.0",
    "gn:asciiname":"Matias",
    "gn:country_code":"BR",
    "gn:dem":355,
    "gn:feature_class":"P",
    "gn:feature_code":"PPL",
    "gn:name":"Matias",
    "gn:population":0,
    "gn:timezone":"America/Recife",
    "iso:country":"BR",
    "wof:name":"Matias",
    "wof:placetype":"locality"
},
  "geometry": {"coordinates":[-38.78333,-8.55],"type":"Point"}
}