{
  "type": "Feature",
  "properties": {
    "gn:admin1_code":"26",
    "gn:admin2_code":"4218202.0",
    "gn:asciiname":"Estrada da Mulde",
    "gn:country_code":"BR",
    "gn:dem":315,
    "gn:feature_class":"P",
    "gn:feature_code":"PPLL",
    "gn:name":"Estrada da Mulde",
    "gn:population":0,
    "gn:timezone":"America/Sao_Paulo",
    "iso:country":"BR",
    "name:por_x_preferred":[
        "Estrada da Mulde"
    ],
    "wof:name":"Estrada da Mulde",
    "wof:placetype":"locality"
},
  "geometry": {"coordinates":[-49.2355,-26.8247],"type":"Point"}
}