{
  "type": "Feature",
  "properties": {
    "gn:admin1_code":"30",
    "gn:admin2_code":"2605707.0",
    "gn:asciiname":"Caraiba",
    "gn:country_code":"BR",
    "gn:dem":326,
    "gn:feature_class":"P",
    "gn:feature_code":"PPL",
    "gn:name":"Cara\u00edba",
    "gn:population":0,
    "gn:timezone":"America/Recife",
    "iso:country":"BR",
    "name:est_x_preferred":[
        "Caraiba"
    ],
    "wof:name":"Caraiba",
    "wof:placetype":"locality"
},
  "geometry": {"coordinates":[-38.51667,-8.73333],"type":"Point"}
}