{
  "type": "Feature",
  "properties": {
    "gn:admin1_code":"8",
    "gn:admin2_code":"3205002.0",
    "gn:asciiname":"Aroaba",
    "gn:country_code":"BR",
    "gn:dem":54,
    "gn:feature_class":"P",
    "gn:feature_code":"PPL",
    "gn:name":"Aroaba",
    "gn:population":0,
    "gn:timezone":"America/Sao_Paulo",
    "iso:country":"BR",
    "name:por_x_preferred":[
        "Aroaba"
    ],
    "wof:name":"Aroaba",
    "wof:placetype":"locality"
},
  "geometry": {"coordinates":[-40.38333,-20.13333],"type":"Point"}
}