{
  "type": "Feature",
  "properties": {
    "gn:admin1_code":"27",
    "gn:admin2_code":"3519709.0",
    "gn:asciiname":"Sitio Estancia Triangulo",
    "gn:country_code":"BR",
    "gn:dem":884,
    "gn:feature_class":"P",
    "gn:feature_code":"PPL",
    "gn:name":"S\u00edtio Est\u00e2ncia Tri\u00e2ngulo",
    "gn:population":0,
    "gn:timezone":"America/Sao_Paulo",
    "iso:country":"BR",
    "name:por_x_preferred":[
        "S\u00edtio Est\u00e2ncia Tri\u00e2ngulo"
    ],
    "wof:name":"Sitio Estancia Triangulo",
    "wof:placetype":"locality"
},
  "geometry": {"coordinates":[-47.2205,-23.7793],"type":"Point"}
}