{
  "type": "Feature",
  "properties": {
    "gn:admin1_code":"5",
    "gn:admin2_code":"2921906.0",
    "gn:asciiname":"Tres Cancelas",
    "gn:country_code":"BR",
    "gn:dem":1341,
    "gn:feature_class":"P",
    "gn:feature_code":"PPL",
    "gn:name":"Tr\u00eas Cancelas",
    "gn:population":0,
    "gn:timezone":"America/Bahia",
    "iso:country":"BR",
    "wof:name":"Tres Cancelas",
    "wof:placetype":"locality"
},
  "geometry": {"coordinates":[-41.48333,-12.86667],"type":"Point"}
}