{
  "type": "Feature",
  "properties": {
    "gn:admin1_code":"14",
    "gn:admin2_code":"5106182.0",
    "gn:asciiname":"Aldeia Waikiso",
    "gn:country_code":"BR",
    "gn:dem":242,
    "gn:feature_class":"P",
    "gn:feature_code":"PPL",
    "gn:name":"Aldeia Waikiso",
    "gn:population":0,
    "gn:timezone":"America/Cuiaba",
    "iso:country":"BR",
    "wof:name":"Aldeia Waikiso",
    "wof:placetype":"locality"
},
  "geometry": {"coordinates":[-59.68333000000001,-14.1875],"type":"Point"}
}