{
  "type": "Feature",
  "properties": {
    "gn:admin1_code":"27",
    "gn:admin2_code":"3536000.0",
    "gn:asciiname":"Vitoria Paulista",
    "gn:cc2":"BR",
    "gn:country_code":"BR",
    "gn:dem":484,
    "gn:feature_class":"P",
    "gn:feature_code":"PPL",
    "gn:name":"Vit\u00f3ria Paulista",
    "gn:population":0,
    "gn:timezone":"America/Sao_Paulo",
    "iso:country":"BR",
    "name:und_x_variant":[
        "Vit\u00f4ria",
        "Vit\u00f3ria Paulista"
    ],
    "wof:name":"Vitoria Paulista",
    "wof:placetype":"locality"
},
  "geometry": {"coordinates":[-50.76667,-21.78333],"type":"Point"}
}