{
  "type": "Feature",
  "properties": {
    "gn:admin1_code":"18.0",
    "gn:admin2_code":"4122909.0",
    "gn:asciiname":"Sitio Joaquim D. da Silva",
    "gn:country_code":"BR",
    "gn:dem":685,
    "gn:feature_class":"P",
    "gn:feature_code":"PPL",
    "gn:name":"S\u00edtio Joaquim D. da Silva",
    "gn:population":0,
    "gn:timezone":"America/Sao_Paulo",
    "iso:country":"BR",
    "name:por_x_preferred":[
        "S\u00edtio Joaquim D. da Silva"
    ],
    "wof:name":"Sitio Joaquim D. da Silva",
    "wof:placetype":"locality"
},
  "geometry": {"coordinates":[-49.7865,-23.6115],"type":"Point"}
}