{
  "type": "Feature",
  "properties": {
    "gn:admin1_code":"30",
    "gn:admin2_code":"2613503.0",
    "gn:asciiname":"Mariola",
    "gn:country_code":"BR",
    "gn:dem":491,
    "gn:feature_class":"P",
    "gn:feature_code":"PPL",
    "gn:name":"Mariola",
    "gn:population":0,
    "gn:timezone":"America/Recife",
    "iso:country":"BR",
    "name:cat_x_preferred":[
        "Mariola"
    ],
    "name:glg_x_preferred":[
        "Mariola"
    ],
    "name:ita_x_preferred":[
        "Mariola"
    ],
    "name:por_x_preferred":[
        "Mariola"
    ],
    "name:spa_x_preferred":[
        "Mariola"
    ],
    "wof:name":"Mariola",
    "wof:placetype":"locality"
},
  "geometry": {"coordinates":[-38.81667,-7.81667],"type":"Point"}
}