{
  "type": "Feature",
  "properties": {
    "gn:admin1_code":"18.0",
    "gn:admin2_code":"4112306.0",
    "gn:asciiname":"Mundo Novo",
    "gn:country_code":"BR",
    "gn:dem":644,
    "gn:feature_class":"P",
    "gn:feature_code":"PPL",
    "gn:name":"Mundo Novo",
    "gn:population":0,
    "gn:timezone":"America/Sao_Paulo",
    "iso:country":"BR",
    "name:ceb_x_preferred":[
        "Mundo Novo"
    ],
    "name:deu_x_preferred":[
        "Mundo Novo"
    ],
    "name:ita_x_preferred":[
        "Mundo Novo"
    ],
    "name:nld_x_preferred":[
        "Mundo Novo"
    ],
    "name:nor_x_preferred":[
        "Mundo Novo"
    ],
    "name:pol_x_preferred":[
        "Mundo Novo"
    ],
    "name:por_x_preferred":[
        "Mundo Novo"
    ],
    "name:spa_x_preferred":[
        "Mundo Novo"
    ],
    "name:swe_x_preferred":[
        "Mundo Novo"
    ],
    "name:vie_x_preferred":[
        "Mundo Novo"
    ],
    "name:vol_x_preferred":[
        "Mundo Novo"
    ],
    "wof:name":"Mundo Novo",
    "wof:placetype":"locality"
},
  "geometry": {"coordinates":[-50.13301,-23.80595],"type":"Point"}
}