{
  "type": "Feature",
  "properties": {
    "gn:admin1_code":"16.0",
    "gn:admin2_code":"1500347.0",
    "gn:asciiname":"Fazenda Santa Fe",
    "gn:country_code":"BR",
    "gn:dem":357,
    "gn:feature_class":"P",
    "gn:feature_code":"PPL",
    "gn:name":"Fazenda Santa F\u00e9",
    "gn:population":0,
    "gn:timezone":"America/Belem",
    "iso:country":"BR",
    "wof:name":"Fazenda Santa Fe",
    "wof:placetype":"locality"
},
  "geometry": {"coordinates":[-50.63037,-6.81565],"type":"Point"}
}