{
  "type": "Feature",
  "properties": {
    "gn:admin1_code":"18",
    "gn:admin2_code":"4122305.0",
    "gn:asciiname":"Sitio Pedro Valerio",
    "gn:country_code":"BR",
    "gn:dem":922,
    "gn:feature_class":"P",
    "gn:feature_code":"PPL",
    "gn:name":"S\u00edtio Pedro Val\u00e9rio",
    "gn:population":0,
    "gn:timezone":"America/Sao_Paulo",
    "iso:country":"BR",
    "name:por_x_preferred":[
        "S\u00edtio Pedro Val\u00e9rio"
    ],
    "wof:name":"Sitio Pedro Valerio",
    "wof:placetype":"locality"
},
  "geometry": {"coordinates":[-49.59261,-26.16355],"type":"Point"}
}