{
  "type": "Feature",
  "properties": {
    "gn:admin1_code":"27.0",
    "gn:admin2_code":"3518800.0",
    "gn:asciiname":"Sitio Ingazeiro",
    "gn:country_code":"BR",
    "gn:dem":751,
    "gn:feature_class":"P",
    "gn:feature_code":"PPL",
    "gn:name":"S\u00edtio Ingazeiro",
    "gn:population":0,
    "gn:timezone":"America/Sao_Paulo",
    "iso:country":"BR",
    "name:por_x_preferred":[
        "S\u00edtio Ingazeiro"
    ],
    "wof:name":"Sitio Ingazeiro",
    "wof:placetype":"locality"
},
  "geometry": {"coordinates":[-46.50528,-23.41139],"type":"Point"}
}