{
  "type": "Feature",
  "properties": {
    "gn:admin1_code":"18",
    "gn:admin2_code":"4104105.0",
    "gn:asciiname":"Sitio Joao Ribeiro",
    "gn:country_code":"BR",
    "gn:dem":827,
    "gn:feature_class":"P",
    "gn:feature_code":"PPL",
    "gn:name":"S\u00edtio Jo\u00e3o Ribeiro",
    "gn:population":0,
    "gn:timezone":"America/Sao_Paulo",
    "iso:country":"BR",
    "name:por_x_preferred":[
        "S\u00edtio Jo\u00e3o Ribeiro"
    ],
    "wof:name":"Sitio Joao Ribeiro",
    "wof:placetype":"locality"
},
  "geometry": {"coordinates":[-49.73444,-25.99556],"type":"Point"}
}