{
  "type": "Feature",
  "properties": {
    "gn:admin1_code":"06",
    "gn:admin2_code":"2308203.0",
    "gn:asciiname":"Sao Cipriano",
    "gn:country_code":"BR",
    "gn:dem":825,
    "gn:feature_class":"P",
    "gn:feature_code":"PPL",
    "gn:name":"S\u00e3o Cipriano",
    "gn:population":0,
    "gn:timezone":"America/Fortaleza",
    "iso:country":"BR",
    "wof:name":"Sao Cipriano",
    "wof:placetype":"locality"
},
  "geometry": {"coordinates":[-40.48333,-3.58333],"type":"Point"}
}