{
  "type": "Feature",
  "properties": {
    "gn:admin1_code":"1",
    "gn:admin2_code":"1200393.0",
    "gn:asciiname":"Remanso",
    "gn:country_code":"BR",
    "gn:dem":209,
    "gn:feature_class":"P",
    "gn:feature_code":"PPL",
    "gn:name":"Remanso",
    "gn:population":0,
    "gn:timezone":"America/Rio_Branco",
    "iso:country":"BR",
    "wof:name":"Remanso",
    "wof:placetype":"locality"
},
  "geometry": {"coordinates":[-72.98083000000003,-8.43889],"type":"Point"}
}