{
  "type": "Feature",
  "properties": {
    "gn:admin1_code":"1",
    "gn:admin2_code":"1200393.0",
    "gn:asciiname":"Remanso",
    "gn:country_code":"BR",
    "gn:dem":209,
    "gn:feature_class":"P",
    "gn:feature_code":"PPL",
    "gn:name":"Remanso",
    "gn:population":0,
    "gn:timezone":"America/Rio_Branco",
    "iso:country":"BR",
    "name:bpy_x_preferred":[
        "\u09b0\u09c7\u09ae\u09be\u09a8\u09cd\u09b8\u09cb"
    ],
    "name:bul_x_preferred":[
        "\u0420\u0435\u043c\u0430\u043d\u0441\u043e"
    ],
    "name:ceb_x_preferred":[
        "Remanso"
    ],
    "name:epo_x_preferred":[
        "Remanso"
    ],
    "name:eus_x_preferred":[
        "Remanso"
    ],
    "name:fra_x_preferred":[
        "Remanso"
    ],
    "name:hye_x_preferred":[
        "\u054c\u0565\u0574\u0561\u0576\u057d\u0578\u0582"
    ],
    "name:ita_x_preferred":[
        "Remanso"
    ],
    "name:kat_x_preferred":[
        "\u10e0\u10d4\u10db\u10d0\u10dc\u10e1\u10e3"
    ],
    "name:kaz_x_preferred":[
        "\u0420\u0435\u043c\u0430\u043d\u0441\u0443"
    ],
    "name:mlg_x_preferred":[
        "Remanso"
    ],
    "name:nld_x_preferred":[
        "Remanso"
    ],
    "name:nor_x_preferred":[
        "Remanso"
    ],
    "name:pol_x_preferred":[
        "Remanso"
    ],
    "name:por_x_preferred":[
        "Remanso"
    ],
    "name:ron_x_preferred":[
        "Remanso"
    ],
    "name:rus_x_preferred":[
        "\u0420\u0435\u043c\u0430\u043d\u0441\u0443"
    ],
    "name:spa_x_preferred":[
        "Remanso"
    ],
    "name:swe_x_preferred":[
        "Remanso"
    ],
    "name:vie_x_preferred":[
        "Remanso"
    ],
    "name:vol_x_preferred":[
        "Remanso"
    ],
    "name:war_x_preferred":[
        "Remanso"
    ],
    "name:zho_x_preferred":[
        "\u96f7\u66fc\u82cf"
    ],
    "wof:name":"Remanso",
    "wof:placetype":"locality"
},
  "geometry": {"coordinates":[-72.98083000000003,-8.43889],"type":"Point"}
}