{
  "type": "Feature",
  "properties": {
    "gn:admin1_code":"05",
    "gn:admin2_code":"2932002.0",
    "gn:asciiname":"Curundundum",
    "gn:country_code":"BR",
    "gn:dem":462,
    "gn:feature_class":"P",
    "gn:feature_code":"PPL",
    "gn:name":"Curundundum",
    "gn:population":0,
    "gn:timezone":"America/Bahia",
    "iso:country":"BR",
    "wof:name":"Curundundum",
    "wof:placetype":"locality"
},
  "geometry": {"coordinates":[-39.27187,-9.73975],"type":"Point"}
}