{
  "type": "Feature",
  "properties": {
    "gn:admin1_code":"4",
    "gn:admin2_code":"1301852.0",
    "gn:asciiname":"Aiparuca",
    "gn:country_code":"BR",
    "gn:dem":46,
    "gn:feature_class":"P",
    "gn:feature_code":"PPL",
    "gn:name":"Aiparu\u00e7a",
    "gn:population":0,
    "gn:timezone":"America/Manaus",
    "iso:country":"BR",
    "wof:name":"Aiparuca",
    "wof:placetype":"locality"
},
  "geometry": {"coordinates":[-60.60806,-2.98111],"type":"Point"}
}