{
  "type": "Feature",
  "properties": {
    "gn:admin1_code":"15",
    "gn:admin2_code":"3162708.0",
    "gn:asciiname":"Mamona",
    "gn:country_code":"BR",
    "gn:dem":779,
    "gn:feature_class":"P",
    "gn:feature_code":"PPL",
    "gn:name":"Mamona",
    "gn:population":0,
    "gn:timezone":"America/Sao_Paulo",
    "iso:country":"BR",
    "name:por_x_preferred":[
        "Mamona"
    ],
    "name:ron_x_preferred":[
        "Mamona"
    ],
    "name:spa_x_preferred":[
        "Mamona"
    ],
    "wof:name":"Mamona",
    "wof:placetype":"locality"
},
  "geometry": {"coordinates":[-41.78333,-15.51667],"type":"Point"}
}