{
  "type": "Feature",
  "properties": {
    "gn:admin1_code":"27",
    "gn:admin2_code":"3526209.0",
    "gn:asciiname":"Sitio Tamandare",
    "gn:country_code":"BR",
    "gn:dem":745,
    "gn:feature_class":"P",
    "gn:feature_code":"PPL",
    "gn:name":"S\u00edtio Tamandar\u00e9",
    "gn:population":0,
    "gn:timezone":"America/Sao_Paulo",
    "iso:country":"BR",
    "name:por_x_preferred":[
        "S\u00edtio Tamandar\u00e9"
    ],
    "wof:name":"Sitio Tamandare",
    "wof:placetype":"locality"
},
  "geometry": {"coordinates":[-47.1568,-23.9615],"type":"Point"}
}