{
  "type": "Feature",
  "properties": {
    "gn:admin1_code":"14",
    "gn:admin2_code":"5101605.0",
    "gn:asciiname":"Sao Luis",
    "gn:country_code":"BR",
    "gn:dem":137,
    "gn:feature_class":"P",
    "gn:feature_code":"PPL",
    "gn:name":"S\u00e3o Lu\u00eds",
    "gn:population":0,
    "gn:timezone":"America/Cuiaba",
    "iso:country":"BR",
    "name:por_x_preferred":[
        "S\u00e3o Lu\u00eds"
    ],
    "wof:name":"Sao Luis",
    "wof:placetype":"locality"
},
  "geometry": {"coordinates":[-55.89358000000001,-16.53963],"type":"Point"}
}