{
  "type": "Feature",
  "properties": {
    "gn:admin1_code":"06",
    "gn:admin2_code":"2303808.0",
    "gn:asciiname":"Tambor",
    "gn:country_code":"BR",
    "gn:dem":232,
    "gn:feature_class":"P",
    "gn:feature_code":"PPL",
    "gn:name":"Tambor",
    "gn:population":0,
    "gn:timezone":"America/Fortaleza",
    "iso:country":"BR",
    "name:ceb_x_preferred":[
        "Tambor"
    ],
    "name:ces_x_preferred":[
        "Tambor"
    ],
    "name:deu_x_preferred":[
        "Tambor"
    ],
    "name:fra_x_preferred":[
        "Tambor"
    ],
    "name:por_x_preferred":[
        "Tambor"
    ],
    "name:spa_x_preferred":[
        "Tambor"
    ],
    "name:swe_x_preferred":[
        "Tambor"
    ],
    "wof:name":"Tambor",
    "wof:placetype":"locality"
},
  "geometry": {"coordinates":[-38.96667,-6.65],"type":"Point"}
}