{
  "type": "Feature",
  "properties": {
    "gn:admin1_code":"27.0",
    "gn:admin2_code":"3514809.0",
    "gn:asciiname":"Ivaporunduvinha",
    "gn:country_code":"BR",
    "gn:dem":85,
    "gn:feature_class":"P",
    "gn:feature_code":"PPLL",
    "gn:name":"Ivaporunduvinha",
    "gn:population":0,
    "gn:timezone":"America/Sao_Paulo",
    "iso:country":"BR",
    "name:por_x_preferred":[
        "Ivaporunduvinha"
    ],
    "wof:name":"Ivaporunduvinha",
    "wof:placetype":"locality"
},
  "geometry": {"coordinates":[-48.30016,-24.52506],"type":"Point"}
}