{
  "type": "Feature",
  "properties": {
    "gn:admin1_code":"13",
    "gn:admin2_code":"2113009.0",
    "gn:asciiname":"Matinha",
    "gn:country_code":"BR",
    "gn:dem":40,
    "gn:feature_class":"P",
    "gn:feature_code":"PPL",
    "gn:name":"Matinha",
    "gn:population":0,
    "gn:timezone":"America/Fortaleza",
    "iso:country":"BR",
    "wof:name":"Matinha",
    "wof:placetype":"locality"
},
  "geometry": {"coordinates":[-45.33333,-4.16667],"type":"Point"}
}