{
  "type": "Feature",
  "properties": {
    "gn:admin1_code":"13",
    "gn:admin2_code":"2113009.0",
    "gn:asciiname":"Matinha",
    "gn:country_code":"BR",
    "gn:dem":40,
    "gn:feature_class":"P",
    "gn:feature_code":"PPL",
    "gn:name":"Matinha",
    "gn:population":0,
    "gn:timezone":"America/Fortaleza",
    "iso:country":"BR",
    "name:bpy_x_preferred":[
        "\u09ae\u09be\u099f\u09bf\u09a8\u09b9\u09be"
    ],
    "name:eus_x_preferred":[
        "Matinha"
    ],
    "name:fra_x_preferred":[
        "Matinha"
    ],
    "name:hye_x_preferred":[
        "\u0544\u0561\u057f\u056b\u0576\u056b\u0561"
    ],
    "name:ita_x_preferred":[
        "Matinha"
    ],
    "name:kat_x_preferred":[
        "\u10db\u10d0\u10e2\u10d8\u10dc\u10d8\u10d0"
    ],
    "name:kaz_x_preferred":[
        "\u041c\u0430\u0442\u0438\u043d\u044c\u044f"
    ],
    "name:nld_x_preferred":[
        "Matinha"
    ],
    "name:nor_x_preferred":[
        "Matinha"
    ],
    "name:pol_x_preferred":[
        "Matinha"
    ],
    "name:por_x_preferred":[
        "Matinha"
    ],
    "name:ron_x_preferred":[
        "Matinha"
    ],
    "name:rus_x_preferred":[
        "\u041c\u0430\u0442\u0438\u043d\u044c\u044f"
    ],
    "name:spa_x_preferred":[
        "Matinha"
    ],
    "name:vie_x_preferred":[
        "Matinha"
    ],
    "name:vol_x_preferred":[
        "Matinha"
    ],
    "name:war_x_preferred":[
        "Matinha"
    ],
    "name:zho_x_preferred":[
        "\u9a6c\u8482\u5c3c\u4e9a"
    ],
    "wof:name":"Matinha",
    "wof:placetype":"locality"
},
  "geometry": {"coordinates":[-45.33333,-4.16667],"type":"Point"}
}