{
  "type": "Feature",
  "properties": {
    "gn:admin1_code":"18",
    "gn:admin2_code":"4100301.0",
    "gn:asciiname":"Sitio Luis Andreoli",
    "gn:country_code":"BR",
    "gn:dem":935,
    "gn:feature_class":"P",
    "gn:feature_code":"PPL",
    "gn:name":"S\u00edtio Luis Andreoli",
    "gn:population":0,
    "gn:timezone":"America/Sao_Paulo",
    "iso:country":"BR",
    "name:por_x_preferred":[
        "S\u00edtio Luis Andreoli"
    ],
    "wof:name":"Sitio Luis Andreoli",
    "wof:placetype":"locality"
},
  "geometry": {"coordinates":[-49.331,-26.0231],"type":"Point"}
}