{
  "type": "Feature",
  "properties": {
    "gn:admin1_code":"27",
    "gn:admin2_code":"3514601.0",
    "gn:asciiname":"Santa Albertina",
    "gn:country_code":"BR",
    "gn:dem":555,
    "gn:feature_class":"P",
    "gn:feature_code":"PPL",
    "gn:name":"Santa Albertina",
    "gn:population":0,
    "gn:timezone":"America/Sao_Paulo",
    "iso:country":"BR",
    "name:por_x_preferred":[
        "Santa Albertina"
    ],
    "wof:name":"Santa Albertina",
    "wof:placetype":"locality"
},
  "geometry": {"coordinates":[-47.96667,-21.26667],"type":"Point"}
}