{
  "type": "Feature",
  "properties": {
    "gn:admin1_code":"27",
    "gn:admin2_code":"3514601.0",
    "gn:asciiname":"Santa Albertina",
    "gn:country_code":"BR",
    "gn:dem":555,
    "gn:feature_class":"P",
    "gn:feature_code":"PPL",
    "gn:name":"Santa Albertina",
    "gn:population":0,
    "gn:timezone":"America/Sao_Paulo",
    "iso:country":"BR",
    "name:bpy_x_preferred":[
        "\u09b8\u09be\u09a8\u09cd\u099f\u09be \u0986\u09b2\u09ac\u09c7\u09b0\u09cd\u099f\u09bf\u09a8\u09be"
    ],
    "name:ceb_x_preferred":[
        "Santa Albertina"
    ],
    "name:epo_x_preferred":[
        "Santa Albertina"
    ],
    "name:eus_x_preferred":[
        "Santa Albertina"
    ],
    "name:fra_x_preferred":[
        "Santa Albertina"
    ],
    "name:ita_x_preferred":[
        "Santa Albertina"
    ],
    "name:kaz_x_preferred":[
        "\u0421\u0430\u043d\u0442\u0430-\u0410\u043b\u0431\u0435\u0440\u0442\u0438\u043d\u0430"
    ],
    "name:mlg_x_preferred":[
        "Santa Albertina"
    ],
    "name:nld_x_preferred":[
        "Santa Albertina"
    ],
    "name:nor_x_preferred":[
        "Santa Albertina"
    ],
    "name:pol_x_preferred":[
        "Santa Albertina"
    ],
    "name:por_x_preferred":[
        "Santa Albertina"
    ],
    "name:ron_x_preferred":[
        "Santa Albertina"
    ],
    "name:rus_x_preferred":[
        "\u0421\u0430\u043d\u0442\u0430-\u0410\u043b\u0431\u0435\u0440\u0442\u0438\u043d\u0430"
    ],
    "name:spa_x_preferred":[
        "Santa Albertina"
    ],
    "name:swe_x_preferred":[
        "Santa Albertina"
    ],
    "name:vie_x_preferred":[
        "Santa Albertina"
    ],
    "name:vol_x_preferred":[
        "Santa Albertina"
    ],
    "name:war_x_preferred":[
        "Santa Albertina"
    ],
    "name:zho_x_preferred":[
        "\u5723\u963f\u5c14\u8d1d\u8482\u7eb3"
    ],
    "wof:name":"Santa Albertina",
    "wof:placetype":"locality"
},
  "geometry": {"coordinates":[-47.96667,-21.26667],"type":"Point"}
}