{
  "type": "Feature",
  "properties": {
    "iso:country":"BR",
    "name:bar_x_preferred":[
        "Bauanhof"
    ],
    "name:deu_x_preferred":[
        "Fazenda"
    ],
    "name:fra_x_preferred":[
        "Fazenda"
    ],
    "name:ita_x_preferred":[
        "Fazenda"
    ],
    "name:jpn_x_preferred":[
        "\u30d5\u30a1\u30bc\u30f3\u30c0"
    ],
    "name:por_x_preferred":[
        "Fazenda"
    ],
    "name:ron_x_preferred":[
        "Fazend\u0103"
    ],
    "name:rus_x_preferred":[
        "\u0424\u0430\u0437\u0435\u043d\u0434\u0430"
    ],
    "name:spa_x_preferred":[
        "Hacienda colonial"
    ],
    "qs:gn_adm0_cc":"BR",
    "qs:gn_local":3460845,
    "qs:gn_nam_loc":"Itaja\u00ed, Itaja\u00ed, Santa Catarina, BR",
    "qs:gn_namadm1":"26",
    "qs:local_max":702,
    "qs:local_sum":1194,
    "qs:localhoods":4,
    "qs:name":"Fazenda",
    "qs:name_adm0":"Brasil",
    "qs:name_adm1":"Santa Catarina",
    "qs:name_adm2":"Itaja\u00ed",
    "qs:name_local":"Itaja\u00ed",
    "qs:photo_max":95,
    "qs:photo_sum":332,
    "qs:placetype":"Suburb",
    "qs:quad_count":32,
    "qs:woe_adm0":23424768,
    "qs:woe_adm1":2344867,
    "qs:woe_adm2":12581685,
    "qs:woe_lau":0,
    "qs:woe_local":455870,
    "qs:woe_ver":"7.10.0",
    "wof:lang":[
        "por"
    ],
    "wof:name":"Fazenda",
    "wof:placetype":"neighbourhood"
},
  "geometry": {"coordinates":[-48.64328,-26.91754],"type":"Point"}
}