{
  "type": "Feature",
  "properties": {
    "gn:admin1_code":"1",
    "gn:admin2_code":"1200344.0",
    "gn:asciiname":"Sao Bras",
    "gn:country_code":"BR",
    "gn:dem":166,
    "gn:feature_class":"P",
    "gn:feature_code":"PPL",
    "gn:name":"S\u00e3o Br\u00e1s",
    "gn:population":0,
    "gn:timezone":"America/Rio_Branco",
    "iso:country":"BR",
    "wof:name":"Sao Bras",
    "wof:placetype":"locality"
},
  "geometry": {"coordinates":[-69.76666999999999,-9.06667],"type":"Point"}
}