{
  "type": "Feature",
  "properties": {
    "gn:admin1_code":"18.0",
    "gn:admin2_code":"4114302.0",
    "gn:asciiname":"Sitio Rosalina Peixoto",
    "gn:country_code":"BR",
    "gn:dem":909,
    "gn:feature_class":"P",
    "gn:feature_code":"PPL",
    "gn:name":"S\u00edtio Rosalina Peixoto",
    "gn:population":0,
    "gn:timezone":"America/Sao_Paulo",
    "iso:country":"BR",
    "name:por_x_preferred":[
        "S\u00edtio Rosalina Peixoto"
    ],
    "wof:name":"Sitio Rosalina Peixoto",
    "wof:placetype":"locality"
},
  "geometry": {"coordinates":[-49.3596,-25.8257],"type":"Point"}
}