{
  "type": "Feature",
  "properties": {
    "gn:admin1_code":"30",
    "gn:admin2_code":"2615706.0",
    "gn:asciiname":"Saco dos Bois",
    "gn:country_code":"BR",
    "gn:dem":511,
    "gn:feature_class":"P",
    "gn:feature_code":"PPL",
    "gn:name":"Saco dos Bois",
    "gn:population":0,
    "gn:timezone":"America/Recife",
    "iso:country":"BR",
    "wof:name":"Saco dos Bois",
    "wof:placetype":"locality"
},
  "geometry": {"coordinates":[-38.08333,-7.88333],"type":"Point"}
}