{
  "type": "Feature",
  "properties": {
    "gn:admin1_code":"5",
    "gn:admin2_code":"2912608.0",
    "gn:asciiname":"Lagoa de Pedras",
    "gn:country_code":"BR",
    "gn:dem":515,
    "gn:feature_class":"P",
    "gn:feature_code":"PPL",
    "gn:name":"Lagoa de Pedras",
    "gn:population":0,
    "gn:timezone":"America/Bahia",
    "iso:country":"BR",
    "wof:name":"Lagoa de Pedras",
    "wof:placetype":"locality"
},
  "geometry": {"coordinates":[-40.81667,-12.66667],"type":"Point"}
}