{
  "type": "Feature",
  "properties": {
    "gn:admin1_code":"5",
    "gn:admin2_code":"2912608.0",
    "gn:asciiname":"Lagoa de Pedras",
    "gn:country_code":"BR",
    "gn:dem":515,
    "gn:feature_class":"P",
    "gn:feature_code":"PPL",
    "gn:name":"Lagoa de Pedras",
    "gn:population":0,
    "gn:timezone":"America/Bahia",
    "iso:country":"BR",
    "name:bpy_x_preferred":[
        "\u09b2\u09be\u0997\u09cb\u09af\u09bc\u09be \u09a1\u09c7 \u09aa\u09c7\u09a1\u09cd\u09b0\u09be\u09b8"
    ],
    "name:kat_x_preferred":[
        "\u10da\u10d0\u10d2\u10dd\u10d0-\u10d3\u10d8-\u10de\u10d4\u10d3\u10e0\u10d0\u10e1\u10d8"
    ],
    "name:kaz_x_preferred":[
        "\u041b\u0430\u0433\u043e\u0430-\u0434\u0438-\u041f\u0435\u0434\u0440\u0430\u0441"
    ],
    "name:rus_x_preferred":[
        "\u041b\u0430\u0433\u043e\u0430-\u0434\u0438-\u041f\u0435\u0434\u0440\u0430\u0441"
    ],
    "name:urd_x_preferred":[
        "\u0644\u0627\u06af\u0648\u0627 \u062f\u06d2 \u067e\u06cc\u0688\u0631\u0627\u0633"
    ],
    "name:zho_x_preferred":[
        "\u62c9\u6208\u963f-\u8fea\u4f69\u5fb7\u62c9\u65af"
    ],
    "wof:name":"Lagoa de Pedras",
    "wof:placetype":"locality"
},
  "geometry": {"coordinates":[-40.81667,-12.66667],"type":"Point"}
}