{
  "type": "Feature",
  "properties": {
    "gn:admin1_code":"23.0",
    "gn:admin2_code":"4309209.0",
    "gn:asciiname":"Jardim das Oliveiras",
    "gn:country_code":"BR",
    "gn:dem":59,
    "gn:feature_class":"P",
    "gn:feature_code":"PPL",
    "gn:name":"Jardim das Oliveiras",
    "gn:population":0,
    "gn:timezone":"America/Sao_Paulo",
    "iso:country":"BR",
    "name:por_x_preferred":[
        "Jardim das Oliveiras"
    ],
    "wof:name":"Jardim das Oliveiras",
    "wof:placetype":"locality"
},
  "geometry": {"coordinates":[-50.8793,-29.9035],"type":"Point"}
}