{
  "type": "Feature",
  "properties": {
    "gn:admin1_code":"5",
    "gn:admin2_code":"2915353.0",
    "gn:asciiname":"Passagem",
    "gn:cc2":"BR",
    "gn:country_code":"BR",
    "gn:dem":419,
    "gn:feature_class":"P",
    "gn:feature_code":"PPL",
    "gn:name":"Passagem",
    "gn:population":0,
    "gn:timezone":"America/Bahia",
    "iso:country":"BR",
    "name:und_x_variant":[
        "Passagem do Rio Verde",
        "Porto do Rio Verde",
        "Passagem"
    ],
    "wof:name":"Passagem",
    "wof:placetype":"locality"
},
  "geometry": {"coordinates":[-42.31667,-10.93333],"type":"Point"}
}