{
  "type": "Feature",
  "properties": {
    "gn:admin1_code":"22",
    "gn:admin2_code":"2400802.0",
    "gn:asciiname":"Boa Vista",
    "gn:country_code":"BR",
    "gn:dem":152,
    "gn:feature_class":"P",
    "gn:feature_code":"PPL",
    "gn:name":"Boa Vista",
    "gn:population":0,
    "gn:timezone":"America/Fortaleza",
    "iso:country":"BR",
    "wof:name":"Boa Vista",
    "wof:placetype":"locality"
},
  "geometry": {"coordinates":[-36.43139,-5.68667],"type":"Point"}
}