{
  "type": "Feature",
  "properties": {
    "iso:country":"BR",
    "qs_pg:aaroncc":"BR",
    "qs_pg:name":"Luiz Correia",
    "qs_pg:name_adm0":"Brasil",
    "qs_pg:name_adm1":"Piau\u00ed",
    "qs_pg:photos":100,
    "qs_pg:photos_1k":20,
    "qs_pg:photos_9k":1,
    "qs_pg:photos_9r":3,
    "qs_pg:photos_all":100,
    "qs_pg:photos_sr":3,
    "qs_pg:pop_sr":0,
    "qs_pg:qs_pg_placetype":"locality",
    "qs_pg:qs_pg_placetype_gp":"Town",
    "qs_pg:woe_adm0":23424768,
    "woe:adm0_id":23424768,
    "woe:name_adm0":"Brasil",
    "woe:name_adm1":"Piau\u00ed",
    "woe:placetype":"Town",
    "wof:name":"Luiz Correia",
    "wof:placetype":"locality"
},
  "geometry": {"coordinates":[-41.656036,-2.881022],"type":"Point"}
}