{
  "type": "Feature",
  "properties": {
    "gn:admin1_code":"18.0",
    "gn:admin2_code":"4109708.0",
    "gn:asciiname":"Sitio Aires caldense",
    "gn:country_code":"BR",
    "gn:dem":638,
    "gn:feature_class":"P",
    "gn:feature_code":"PPL",
    "gn:name":"S\u00edtio Aires caldense",
    "gn:population":0,
    "gn:timezone":"America/Sao_Paulo",
    "iso:country":"BR",
    "name:por_x_preferred":[
        "S\u00edtio Aires caldense"
    ],
    "wof:name":"Sitio Aires caldense",
    "wof:placetype":"locality"
},
  "geometry": {"coordinates":[-50.32053,-23.87598],"type":"Point"}
}