{
  "type": "Feature",
  "properties": {
    "gn:admin1_code":"06",
    "gn:admin2_code":"2312007.0",
    "gn:asciiname":"Theogenes Rocha",
    "gn:country_code":"BR",
    "gn:dem":115,
    "gn:feature_class":"P",
    "gn:feature_code":"PPL",
    "gn:name":"Theogenes Rocha",
    "gn:population":0,
    "gn:timezone":"America/Fortaleza",
    "iso:country":"BR",
    "wof:name":"Theogenes Rocha",
    "wof:placetype":"locality"
},
  "geometry": {"coordinates":[-40.13333,-3.61667],"type":"Point"}
}