{
  "type": "Feature",
  "properties": {
    "gn:admin1_code":"06",
    "gn:admin2_code":"2304202.0",
    "gn:asciiname":"Zabele",
    "gn:country_code":"BR",
    "gn:dem":930,
    "gn:feature_class":"P",
    "gn:feature_code":"PPL",
    "gn:name":"Zabel\u00ea",
    "gn:population":0,
    "gn:timezone":"America/Fortaleza",
    "iso:country":"BR",
    "wof:name":"Zabele",
    "wof:placetype":"locality"
},
  "geometry": {"coordinates":[-39.58333,-7.18333],"type":"Point"}
}