{
  "type": "Feature",
  "properties": {
    "gn:admin1_code":"20",
    "gn:admin2_code":"2205854.0",
    "gn:asciiname":"Araca",
    "gn:country_code":"BR",
    "gn:dem":27,
    "gn:feature_class":"P",
    "gn:feature_code":"PPL",
    "gn:name":"Ara\u00e7\u00e1",
    "gn:population":0,
    "gn:timezone":"America/Fortaleza",
    "iso:country":"BR",
    "wof:name":"Araca",
    "wof:placetype":"locality"
},
  "geometry": {"coordinates":[-42.49194,-3.48944],"type":"Point"}
}