{
  "type": "Feature",
  "properties": {
    "gn:admin1_code":"14",
    "gn:admin2_code":"5106505.0",
    "gn:asciiname":"Carona",
    "gn:country_code":"BR",
    "gn:dem":125,
    "gn:feature_class":"P",
    "gn:feature_code":"PPL",
    "gn:name":"Carona",
    "gn:population":0,
    "gn:timezone":"America/Cuiaba",
    "iso:country":"BR",
    "name:als_x_preferred":[
        "Carona"
    ],
    "name:bel_x_preferred":[
        "\u041a\u0430\u0440\u043e\u043d\u0430"
    ],
    "name:ceb_x_preferred":[
        "Carona"
    ],
    "name:deu_x_preferred":[
        "Carona"
    ],
    "name:epo_x_preferred":[
        "Carona"
    ],
    "name:eus_x_preferred":[
        "Carona"
    ],
    "name:fra_x_preferred":[
        "Carona"
    ],
    "name:ita_x_preferred":[
        "Carona"
    ],
    "name:lmo_x_preferred":[
        "Carona"
    ],
    "name:nld_x_preferred":[
        "Carona"
    ],
    "name:por_x_preferred":[
        "Carona"
    ],
    "name:spa_x_preferred":[
        "Carona"
    ],
    "name:srp_x_preferred":[
        "Karona"
    ],
    "name:swe_x_preferred":[
        "Carona"
    ],
    "name:vol_x_preferred":[
        "Carona"
    ],
    "wof:name":"Carona",
    "wof:placetype":"locality"
},
  "geometry": {"coordinates":[-56.43333000000001,-16.41667],"type":"Point"}
}