{
  "type": "Feature",
  "properties": {
    "gn:admin1_code":"18.0",
    "gn:admin2_code":"4117701.0",
    "gn:asciiname":"Sitio Porto Alegre",
    "gn:country_code":"BR",
    "gn:dem":885,
    "gn:feature_class":"P",
    "gn:feature_code":"PPL",
    "gn:name":"S\u00edtio Porto Alegre",
    "gn:population":0,
    "gn:timezone":"America/Sao_Paulo",
    "iso:country":"BR",
    "name:por_x_preferred":[
        "S\u00edtio Porto Alegre"
    ],
    "wof:name":"Sitio Porto Alegre",
    "wof:placetype":"locality"
},
  "geometry": {"coordinates":[-50.22042,-25.53274],"type":"Point"}
}