{
  "type": "Feature",
  "properties": {
    "gn:admin1_code":"18.0",
    "gn:admin2_code":"4112801.0",
    "gn:asciiname":"Colonia Nova Varsovia",
    "gn:country_code":"BR",
    "gn:dem":540,
    "gn:feature_class":"P",
    "gn:feature_code":"PPLL",
    "gn:name":"Col\u00f4nia Nova Vars\u00f3via",
    "gn:population":0,
    "gn:timezone":"America/Sao_Paulo",
    "iso:country":"BR",
    "name:por_x_preferred":[
        "Col\u00f4nia Nova Vars\u00f3via"
    ],
    "wof:name":"Colonia Nova Varsovia",
    "wof:placetype":"locality"
},
  "geometry": {"coordinates":[-49.9429,-23.5287],"type":"Point"}
}