{
  "type": "Feature",
  "properties": {
    "gn:admin1_code":"18.0",
    "gn:admin2_code":"4109708.0",
    "gn:asciiname":"Sitio Manoelino P. dos Santos",
    "gn:country_code":"BR",
    "gn:dem":781,
    "gn:feature_class":"P",
    "gn:feature_code":"PPL",
    "gn:name":"S\u00edtio Manoelino P. dos Santos",
    "gn:population":0,
    "gn:timezone":"America/Sao_Paulo",
    "iso:country":"BR",
    "name:por_x_preferred":[
        "S\u00edtio Manoelino P. dos Santos"
    ],
    "wof:name":"Sitio Manoelino P. dos Santos",
    "wof:placetype":"locality"
},
  "geometry": {"coordinates":[-50.16689,-23.84224],"type":"Point"}
}