{
  "type": "Feature",
  "properties": {
    "gn:admin1_code":"1",
    "gn:admin2_code":"1200203.0",
    "gn:asciiname":"Sao Luis",
    "gn:country_code":"BR",
    "gn:dem":203,
    "gn:feature_class":"P",
    "gn:feature_code":"PPL",
    "gn:name":"S\u00e3o Lu\u00eds",
    "gn:population":0,
    "gn:timezone":"America/Rio_Branco",
    "iso:country":"BR",
    "wof:name":"Sao Luis",
    "wof:placetype":"locality"
},
  "geometry": {"coordinates":[-73.01666999999998,-8.23333],"type":"Point"}
}