{
  "type": "Feature",
  "properties": {
    "gn:admin1_code":"06",
    "gn:admin2_code":"2312007.0",
    "gn:asciiname":"Fazenda Inez",
    "gn:country_code":"BR",
    "gn:dem":46,
    "gn:feature_class":"P",
    "gn:feature_code":"PPL",
    "gn:name":"Fazenda In\u00eaz",
    "gn:population":0,
    "gn:timezone":"America/Fortaleza",
    "iso:country":"BR",
    "wof:name":"Fazenda Inez",
    "wof:placetype":"locality"
},
  "geometry": {"coordinates":[-40.25,-3.48333],"type":"Point"}
}