{
  "type": "Feature",
  "properties": {
    "gn:admin1_code":"13",
    "gn:admin2_code":"2102200.0",
    "gn:asciiname":"Para-Mirim",
    "gn:country_code":"BR",
    "gn:dem":54,
    "gn:feature_class":"P",
    "gn:feature_code":"PPL",
    "gn:name":"Para-Mirim",
    "gn:population":0,
    "gn:timezone":"America/Fortaleza",
    "iso:country":"BR",
    "wof:name":"Para-Mirim",
    "wof:placetype":"locality"
},
  "geometry": {"coordinates":[-42.95972,-3.98472],"type":"Point"}
}