{
  "type": "Feature",
  "properties": {
    "gn:admin1_code":"18.0",
    "gn:admin2_code":"4122305.0",
    "gn:asciiname":"Sitio Antonio Seidel",
    "gn:country_code":"BR",
    "gn:dem":820,
    "gn:feature_class":"P",
    "gn:feature_code":"PPL",
    "gn:name":"S\u00edtio Ant\u00f4nio Seidel",
    "gn:population":0,
    "gn:timezone":"America/Sao_Paulo",
    "iso:country":"BR",
    "name:por_x_preferred":[
        "S\u00edtio Ant\u00f4nio Seidel"
    ],
    "wof:name":"Sitio Antonio Seidel",
    "wof:placetype":"locality"
},
  "geometry": {"coordinates":[-49.8112,-26.0787],"type":"Point"}
}