{
  "type": "Feature",
  "properties": {
    "gn:admin1_code":"24",
    "gn:admin2_code":"1101468.0",
    "gn:asciiname":"Uacurizal",
    "gn:cc2":"BR",
    "gn:country_code":"BR",
    "gn:dem":162,
    "gn:feature_class":"P",
    "gn:feature_code":"PPL",
    "gn:name":"Uacurizal",
    "gn:population":0,
    "gn:timezone":"America/Porto_Velho",
    "iso:country":"BR",
    "name:und_x_variant":[
        "Acurizal",
        "Uacorisal",
        "Uacurizal"
    ],
    "wof:name":"Uacurizal",
    "wof:placetype":"locality"
},
  "geometry": {"coordinates":[-61.73333,-13.51667],"type":"Point"}
}