{
  "type": "Feature",
  "properties": {
    "gn:admin1_code":"15.0",
    "gn:admin2_code":"3106200.0",
    "gn:asciiname":"Xangrila",
    "gn:country_code":"BR",
    "gn:dem":872,
    "gn:feature_class":"P",
    "gn:feature_code":"PPL",
    "gn:name":"Xangril\u00e1",
    "gn:population":0,
    "gn:timezone":"America/Sao_Paulo",
    "iso:country":"BR",
    "wof:name":"Xangrila",
    "wof:placetype":"locality"
},
  "geometry": {"coordinates":[-44.01732,-19.84354],"type":"Point"}
}