{
  "type": "Feature",
  "properties": {
    "gn:admin1_code":"8.0",
    "gn:admin2_code":"3202207.0",
    "gn:asciiname":"Beira-Rio",
    "gn:country_code":"BR",
    "gn:dem":36,
    "gn:feature_class":"P",
    "gn:feature_code":"PPL",
    "gn:name":"Beira-Rio",
    "gn:population":0,
    "gn:timezone":"America/Sao_Paulo",
    "iso:country":"BR",
    "wof:name":"Beira-Rio",
    "wof:placetype":"locality"
},
  "geometry": {"coordinates":[-40.40789,-19.93204],"type":"Point"}
}