{
  "type": "Feature",
  "properties": {
    "gn:admin1_code":"5",
    "gn:admin2_code":"2908804.0",
    "gn:asciiname":"Sao Joao",
    "gn:country_code":"BR",
    "gn:dem":401,
    "gn:feature_class":"P",
    "gn:feature_code":"PPL",
    "gn:name":"S\u00e3o Jo\u00e3o",
    "gn:population":0,
    "gn:timezone":"America/Bahia",
    "iso:country":"BR",
    "wof:name":"Sao Joao",
    "wof:placetype":"locality"
},
  "geometry": {"coordinates":[-41.15,-13.78333],"type":"Point"}
}