{
  "type": "Feature",
  "properties": {
    "gn:admin1_code":"17",
    "gn:admin2_code":"2510907.0",
    "gn:asciiname":"Acude de Leite",
    "gn:country_code":"BR",
    "gn:dem":250,
    "gn:feature_class":"P",
    "gn:feature_code":"PPL",
    "gn:name":"A\u00e7ude de Leite",
    "gn:population":0,
    "gn:timezone":"America/Fortaleza",
    "iso:country":"BR",
    "wof:name":"Acude de Leite",
    "wof:placetype":"locality"
},
  "geometry": {"coordinates":[-37.75,-6.65],"type":"Point"}
}