{
  "type": "Feature",
  "properties": {
    "gn:admin1_code":"11",
    "gn:admin2_code":"5006002.0",
    "gn:asciiname":"Jauru",
    "gn:cc2":"BR",
    "gn:country_code":"BR",
    "gn:dem":340,
    "gn:feature_class":"P",
    "gn:feature_code":"PPL",
    "gn:name":"Jauru",
    "gn:population":0,
    "gn:timezone":"America/Campo_Grande",
    "iso:country":"BR",
    "name:bpy_x_preferred":[
        "\u099c\u09be\u0989\u09b0\u09c1"
    ],
    "name:ceb_x_preferred":[
        "Jauru"
    ],
    "name:eus_x_preferred":[
        "Jauru"
    ],
    "name:fra_x_preferred":[
        "Jauru"
    ],
    "name:hye_x_preferred":[
        "\u053a\u0561\u0578\u0582\u0580\u0578\u0582"
    ],
    "name:ita_x_preferred":[
        "Jauru"
    ],
    "name:kat_x_preferred":[
        "\u10df\u10d0\u10e3\u10e0\u10e3"
    ],
    "name:kaz_x_preferred":[
        "\u0416\u0430\u0443\u0440\u0443"
    ],
    "name:nld_x_preferred":[
        "Jauru"
    ],
    "name:nor_x_preferred":[
        "Jauru"
    ],
    "name:pol_x_preferred":[
        "Jauru"
    ],
    "name:por_x_preferred":[
        "Jauru"
    ],
    "name:ron_x_preferred":[
        "Jauru"
    ],
    "name:rus_x_preferred":[
        "\u0416\u0430\u0443\u0440\u0443"
    ],
    "name:swe_x_preferred":[
        "Jauru"
    ],
    "name:und_x_variant":[
        "Fazenda Jaur\u00fa"
    ],
    "name:vie_x_preferred":[
        "Jauru"
    ],
    "name:vol_x_preferred":[
        "Jauru"
    ],
    "name:war_x_preferred":[
        "Jauru"
    ],
    "name:zho_x_preferred":[
        "\u9976\u9c81"
    ],
    "wof:name":"Jauru",
    "wof:placetype":"locality"
},
  "geometry": {"coordinates":[-53.83333,-21.66667],"type":"Point"}
}