{
  "type": "Feature",
  "properties": {
    "gn:admin1_code":"11",
    "gn:admin2_code":"5006002.0",
    "gn:asciiname":"Jauru",
    "gn:cc2":"BR",
    "gn:country_code":"BR",
    "gn:dem":340,
    "gn:feature_class":"P",
    "gn:feature_code":"PPL",
    "gn:name":"Jauru",
    "gn:population":0,
    "gn:timezone":"America/Campo_Grande",
    "iso:country":"BR",
    "name:und_x_variant":[
        "Fazenda Jaur\u00fa",
        "Jauru"
    ],
    "wof:name":"Jauru",
    "wof:placetype":"locality"
},
  "geometry": {"coordinates":[-53.83333,-21.66667],"type":"Point"}
}