{
  "type": "Feature",
  "properties": {
    "gn:admin1_code":"11",
    "gn:admin2_code":"5002209.0",
    "gn:asciiname":"Arvoredo",
    "gn:country_code":"BR",
    "gn:dem":342,
    "gn:feature_class":"P",
    "gn:feature_code":"PPL",
    "gn:name":"Arvoredo",
    "gn:population":0,
    "gn:timezone":"America/Campo_Grande",
    "iso:country":"BR",
    "name:aze_x_preferred":[
        "Arvoredu"
    ],
    "name:bpy_x_preferred":[
        "\u0986\u09b0\u09cd\u09ad\u09cb\u09b0\u09c7\u09a1\u09cb"
    ],
    "name:ceb_x_preferred":[
        "Arvoredo"
    ],
    "name:eus_x_preferred":[
        "Arvoredo"
    ],
    "name:fra_x_preferred":[
        "Arvoredo"
    ],
    "name:ina_x_preferred":[
        "Arvoredo"
    ],
    "name:ita_x_preferred":[
        "Arvoredo"
    ],
    "name:kat_x_preferred":[
        "\u10d0\u10e0\u10d5\u10dd\u10e0\u10d4\u10d3\u10e3"
    ],
    "name:nld_x_preferred":[
        "Arvoredo"
    ],
    "name:nor_x_preferred":[
        "Arvoredo"
    ],
    "name:oci_x_preferred":[
        "Arvoredo"
    ],
    "name:pol_x_preferred":[
        "Arvoredo"
    ],
    "name:por_x_preferred":[
        "Arvoredo"
    ],
    "name:ron_x_preferred":[
        "Arvoredo"
    ],
    "name:rus_x_preferred":[
        "\u0410\u0440\u0432\u043e\u0440\u0435\u0434\u0443"
    ],
    "name:spa_x_preferred":[
        "Arvoredo"
    ],
    "name:swe_x_preferred":[
        "Arvoredo"
    ],
    "name:vie_x_preferred":[
        "Arvoredo"
    ],
    "name:vol_x_preferred":[
        "Arvoredo"
    ],
    "name:war_x_preferred":[
        "Arvoredo"
    ],
    "name:zho_x_preferred":[
        "\u963f\u5c14\u6c83\u96f7\u591a"
    ],
    "wof:name":"Arvoredo",
    "wof:placetype":"locality"
},
  "geometry": {"coordinates":[-56.41667,-21.35],"type":"Point"}
}