{
  "type": "Feature",
  "properties": {
    "gn:admin1_code":"03",
    "gn:admin2_code":"1600204.0",
    "gn:asciiname":"Maye",
    "gn:country_code":"BR",
    "gn:dem":8,
    "gn:feature_class":"P",
    "gn:feature_code":"PPL",
    "gn:name":"Maye",
    "gn:population":0,
    "gn:timezone":"America/Belem",
    "iso:country":"BR",
    "name:ceb_x_preferred":[
        "Maye"
    ],
    "name:deu_x_preferred":[
        "Maye"
    ],
    "name:fra_x_preferred":[
        "Maye"
    ],
    "name:swe_x_preferred":[
        "Maye"
    ],
    "name:und_x_variant":[
        "Mate"
    ],
    "wof:name":"Maye",
    "wof:placetype":"locality"
},
  "geometry": {"coordinates":[-50.77707,2.4582],"type":"Point"}
}