{
  "type": "Feature",
  "properties": {
    "gn:admin1_code":"30",
    "gn:admin2_code":"2614006.0",
    "gn:asciiname":"Inga",
    "gn:country_code":"BR",
    "gn:dem":487,
    "gn:feature_class":"P",
    "gn:feature_code":"PPL",
    "gn:name":"Ing\u00e1",
    "gn:population":0,
    "gn:timezone":"America/Recife",
    "iso:country":"BR",
    "wof:name":"Inga",
    "wof:placetype":"locality"
},
  "geometry": {"coordinates":[-39.26667,-7.83333],"type":"Point"}
}