{
  "type": "Feature",
  "properties": {
    "gn:admin1_code":"30",
    "gn:admin2_code":"2614006.0",
    "gn:asciiname":"Inga",
    "gn:country_code":"BR",
    "gn:dem":487,
    "gn:feature_class":"P",
    "gn:feature_code":"PPL",
    "gn:name":"Ing\u00e1",
    "gn:population":0,
    "gn:timezone":"America/Recife",
    "iso:country":"BR",
    "name:aze_x_preferred":[
        "\u0130nqa"
    ],
    "name:bel_x_preferred":[
        "Inga"
    ],
    "name:cat_x_preferred":[
        "Inga"
    ],
    "name:ceb_x_preferred":[
        "Inga"
    ],
    "name:ces_x_preferred":[
        "Inga"
    ],
    "name:deu_x_preferred":[
        "Inga"
    ],
    "name:fra_x_preferred":[
        "Inga"
    ],
    "name:ita_x_preferred":[
        "Inga"
    ],
    "name:nld_x_preferred":[
        "Inga"
    ],
    "name:por_x_preferred":[
        "Ing\u00e1"
    ],
    "name:que_x_preferred":[
        "Pakay yura"
    ],
    "name:rus_x_preferred":[
        "\u0418\u043d\u0433\u0430"
    ],
    "name:spa_x_preferred":[
        "Inga"
    ],
    "name:swe_x_preferred":[
        "Inga"
    ],
    "name:vie_x_preferred":[
        "Inga"
    ],
    "name:war_x_preferred":[
        "Inga"
    ],
    "wof:name":"Inga",
    "wof:placetype":"locality"
},
  "geometry": {"coordinates":[-39.26667,-7.83333],"type":"Point"}
}