{
  "type": "Feature",
  "properties": {
    "gn:admin1_code":"23",
    "gn:admin2_code":"4317103.0",
    "gn:asciiname":"Poco do Contrabando",
    "gn:country_code":"BR",
    "gn:dem":122,
    "gn:feature_class":"P",
    "gn:feature_code":"PPL",
    "gn:name":"Po\u00e7o do Contrabando",
    "gn:population":0,
    "gn:timezone":"America/Sao_Paulo",
    "iso:country":"BR",
    "wof:name":"Poco do Contrabando",
    "wof:placetype":"locality"
},
  "geometry": {"coordinates":[-56.25,-30.56667],"type":"Point"}
}