{
  "type": "Feature",
  "properties": {
    "gn:admin1_code":"27.0",
    "gn:admin2_code":"3550308.0",
    "gn:asciiname":"Engenheiro Marsilac",
    "gn:country_code":"BR",
    "gn:dem":732,
    "gn:feature_class":"P",
    "gn:feature_code":"PPLL",
    "gn:name":"Engenheiro Marsilac",
    "gn:population":0,
    "gn:timezone":"America/Sao_Paulo",
    "iso:country":"BR",
    "name:por_x_preferred":[
        "Engenheiro Marsilac"
    ],
    "wof:name":"Engenheiro Marsilac",
    "wof:placetype":"locality"
},
  "geometry": {"coordinates":[-46.6793,-23.9242],"type":"Point"}
}