{
  "type": "Feature",
  "properties": {
    "gn:admin1_code":"11",
    "gn:admin2_code":"5006903.0",
    "gn:asciiname":"Santa Cruz",
    "gn:country_code":"BR",
    "gn:dem":142,
    "gn:feature_class":"P",
    "gn:feature_code":"PPL",
    "gn:name":"Santa Cruz",
    "gn:population":0,
    "gn:timezone":"America/Campo_Grande",
    "iso:country":"BR",
    "wof:name":"Santa Cruz",
    "wof:placetype":"locality"
},
  "geometry": {"coordinates":[-57.11666999999999,-20.95],"type":"Point"}
}