{
  "type": "Feature",
  "properties": {
    "gn:admin1_code":"06",
    "gn:admin2_code":"2304459.0",
    "gn:asciiname":"Jardim",
    "gn:country_code":"BR",
    "gn:dem":6,
    "gn:feature_class":"P",
    "gn:feature_code":"PPL",
    "gn:name":"Jardim",
    "gn:population":0,
    "gn:timezone":"America/Fortaleza",
    "iso:country":"BR",
    "wof:name":"Jardim",
    "wof:placetype":"locality"
},
  "geometry": {"coordinates":[-37.78333,-4.48333],"type":"Point"}
}