{
  "type": "Feature",
  "properties": {
    "gn:admin1_code":"27.0",
    "gn:admin2_code":"3550308.0",
    "gn:asciiname":"Sitio Sete Lagoas",
    "gn:country_code":"BR",
    "gn:dem":795,
    "gn:feature_class":"P",
    "gn:feature_code":"PPL",
    "gn:name":"S\u00edtio Sete Lagoas",
    "gn:population":0,
    "gn:timezone":"America/Sao_Paulo",
    "iso:country":"BR",
    "name:por_x_preferred":[
        "S\u00edtio Sete Lagoas"
    ],
    "wof:name":"Sitio Sete Lagoas",
    "wof:placetype":"locality"
},
  "geometry": {"coordinates":[-46.69595,-23.80127],"type":"Point"}
}