{
  "type": "Feature",
  "properties": {
    "gn:admin1_code":"18.0",
    "gn:admin2_code":"4109005.0",
    "gn:asciiname":"Sitio Dois Vizinhos",
    "gn:country_code":"BR",
    "gn:dem":545,
    "gn:feature_class":"P",
    "gn:feature_code":"PPL",
    "gn:name":"S\u00edtio Dois Vizinhos",
    "gn:population":0,
    "gn:timezone":"America/Sao_Paulo",
    "iso:country":"BR",
    "name:por_x_preferred":[
        "S\u00edtio Dois Vizinhos"
    ],
    "wof:name":"Sitio Dois Vizinhos",
    "wof:placetype":"locality"
},
  "geometry": {"coordinates":[-50.00516,-23.51076],"type":"Point"}
}