{
  "type": "Feature",
  "properties": {
    "gn:admin1_code":"27",
    "gn:admin2_code":"3504107.0",
    "gn:asciiname":"Bairro Rio Abaixo",
    "gn:country_code":"BR",
    "gn:dem":776,
    "gn:feature_class":"P",
    "gn:feature_code":"PPL",
    "gn:name":"Bairro Rio Abaixo",
    "gn:population":0,
    "gn:timezone":"America/Sao_Paulo",
    "iso:country":"BR",
    "name:por_x_preferred":[
        "Bairro Rio Abaixo"
    ],
    "wof:name":"Bairro Rio Abaixo",
    "wof:placetype":"locality"
},
  "geometry": {"coordinates":[-46.64111,-23.04417],"type":"Point"}
}