{
  "type": "Feature",
  "properties": {
    "gn:admin1_code":"4",
    "gn:admin2_code":"1302405.0",
    "gn:asciiname":"Huitanaa",
    "gn:cc2":"BR",
    "gn:country_code":"BR",
    "gn:dem":91,
    "gn:feature_class":"P",
    "gn:feature_code":"PPL",
    "gn:name":"Huitana\u00e3",
    "gn:population":0,
    "gn:timezone":"America/Manaus",
    "iso:country":"BR",
    "name:und_x_variant":[
        "Hyutanah\u00e3",
        "Huitana\u00e3"
    ],
    "wof:name":"Huitanaa",
    "wof:placetype":"locality"
},
  "geometry": {"coordinates":[-65.76666999999999,-7.66667],"type":"Point"}
}