{
  "type": "Feature",
  "properties": {
    "gn:admin1_code":"21",
    "gn:admin2_code":"3304151.0",
    "gn:asciiname":"Carmo",
    "gn:country_code":"BR",
    "gn:dem":11,
    "gn:feature_class":"P",
    "gn:feature_code":"PPL",
    "gn:name":"Carmo",
    "gn:population":0,
    "gn:timezone":"America/Sao_Paulo",
    "iso:country":"BR",
    "name:ceb_x_preferred":[
        "Carmo"
    ],
    "name:deu_x_preferred":[
        "Carmo"
    ],
    "name:epo_x_preferred":[
        "Carmo"
    ],
    "name:fra_x_preferred":[
        "Carmo"
    ],
    "name:ita_x_preferred":[
        "Carmo"
    ],
    "name:nld_x_preferred":[
        "Carmo"
    ],
    "name:por_x_preferred":[
        "Carmo"
    ],
    "name:ron_x_preferred":[
        "Carmo"
    ],
    "name:rus_x_preferred":[
        "\u041a\u0430\u0440\u043c\u0443"
    ],
    "name:sco_x_preferred":[
        "Carmo"
    ],
    "name:spa_x_preferred":[
        "Carmo"
    ],
    "name:swe_x_preferred":[
        "Carmo"
    ],
    "wof:name":"Carmo",
    "wof:placetype":"locality"
},
  "geometry": {"coordinates":[-41.48333,-22.11667000000001],"type":"Point"}
}