{
  "type": "Feature",
  "properties": {
    "gn:admin1_code":"13",
    "gn:admin2_code":"2102200.0",
    "gn:asciiname":"Baixinha",
    "gn:country_code":"BR",
    "gn:dem":99,
    "gn:feature_class":"P",
    "gn:feature_code":"PPL",
    "gn:name":"Baixinha",
    "gn:population":0,
    "gn:timezone":"America/Fortaleza",
    "iso:country":"BR",
    "wof:name":"Baixinha",
    "wof:placetype":"locality"
},
  "geometry": {"coordinates":[-43.06306,-3.81139],"type":"Point"}
}