{
  "type": "Feature",
  "properties": {
    "gn:admin1_code":"18.0",
    "gn:admin2_code":"4112306.0",
    "gn:asciiname":"Taquara Lisa",
    "gn:country_code":"BR",
    "gn:dem":653,
    "gn:feature_class":"P",
    "gn:feature_code":"PPLL",
    "gn:name":"Taquara Lisa",
    "gn:population":0,
    "gn:timezone":"America/Sao_Paulo",
    "iso:country":"BR",
    "name:por_x_preferred":[
        "Taquara Lisa"
    ],
    "wof:name":"Taquara Lisa",
    "wof:placetype":"locality"
},
  "geometry": {"coordinates":[-50.16238,-23.76822],"type":"Point"}
}