{
  "type": "Feature",
  "properties": {
    "gn:admin1_code":"06",
    "gn:admin2_code":"2311009.0",
    "gn:asciiname":"Poranga",
    "gn:country_code":"BR",
    "gn:dem":716,
    "gn:feature_class":"P",
    "gn:feature_code":"PPL",
    "gn:name":"Poranga",
    "gn:population":0,
    "gn:timezone":"America/Fortaleza",
    "iso:country":"BR",
    "name:bpy_x_preferred":[
        "\u09aa\u09cb\u09b0\u09be\u0999\u09cd\u0997\u09be"
    ],
    "name:ceb_x_preferred":[
        "Poranga"
    ],
    "name:eus_x_preferred":[
        "Poranga"
    ],
    "name:fra_x_preferred":[
        "Poranga"
    ],
    "name:ita_x_preferred":[
        "Poranga"
    ],
    "name:kat_x_preferred":[
        "\u10de\u10dd\u10e0\u10d0\u10dc\u10d2\u10d0"
    ],
    "name:kaz_x_preferred":[
        "\u041f\u043e\u0440\u0430\u043d\u0433\u0430"
    ],
    "name:nld_x_preferred":[
        "Poranga"
    ],
    "name:nor_x_preferred":[
        "Poranga"
    ],
    "name:por_x_preferred":[
        "Poranga"
    ],
    "name:ron_x_preferred":[
        "Poranga"
    ],
    "name:rus_x_preferred":[
        "\u041f\u043e\u0440\u0430\u043d\u0433\u0430"
    ],
    "name:swe_x_preferred":[
        "Poranga"
    ],
    "name:vie_x_preferred":[
        "Poranga"
    ],
    "name:vol_x_preferred":[
        "Poranga"
    ],
    "name:war_x_preferred":[
        "Poranga"
    ],
    "name:zho_x_preferred":[
        "\u6ce2\u5170\u52a0"
    ],
    "wof:name":"Poranga",
    "wof:placetype":"locality"
},
  "geometry": {"coordinates":[-40.92611,-4.74472],"type":"Point"}
}