{
  "type": "Feature",
  "properties": {
    "gn:admin1_code":"06",
    "gn:admin2_code":"2311009.0",
    "gn:asciiname":"Poranga",
    "gn:country_code":"BR",
    "gn:dem":716,
    "gn:feature_class":"P",
    "gn:feature_code":"PPL",
    "gn:name":"Poranga",
    "gn:population":0,
    "gn:timezone":"America/Fortaleza",
    "iso:country":"BR",
    "wof:name":"Poranga",
    "wof:placetype":"locality"
},
  "geometry": {"coordinates":[-40.92611,-4.74472],"type":"Point"}
}