{
  "type": "Feature",
  "properties": {
    "gn:admin1_code":"18.0",
    "gn:admin2_code":"4100202.0",
    "gn:asciiname":"Mato Limpo",
    "gn:country_code":"BR",
    "gn:dem":937,
    "gn:feature_class":"P",
    "gn:feature_code":"PPLL",
    "gn:name":"Mato Limpo",
    "gn:population":0,
    "gn:timezone":"America/Sao_Paulo",
    "iso:country":"BR",
    "name:por_x_preferred":[
        "Mato Limpo"
    ],
    "wof:name":"Mato Limpo",
    "wof:placetype":"locality"
},
  "geometry": {"coordinates":[-48.735,-24.8487],"type":"Point"}
}