{
  "type": "Feature",
  "properties": {
    "gn:admin1_code":"22",
    "gn:admin2_code":"2406106.0",
    "gn:asciiname":"Salina",
    "gn:country_code":"BR",
    "gn:dem":83,
    "gn:feature_class":"P",
    "gn:feature_code":"PPL",
    "gn:name":"Salina",
    "gn:population":0,
    "gn:timezone":"America/Fortaleza",
    "iso:country":"BR",
    "wof:name":"Salina",
    "wof:placetype":"locality"
},
  "geometry": {"coordinates":[-36.92083,-5.97444],"type":"Point"}
}