{
  "type": "Feature",
  "properties": {
    "gn:admin1_code":"23",
    "gn:admin2_code":"4307906.0",
    "gn:asciiname":"Blauth",
    "gn:country_code":"BR",
    "gn:dem":695,
    "gn:feature_class":"P",
    "gn:feature_code":"PPL",
    "gn:name":"Blauth",
    "gn:population":0,
    "gn:timezone":"America/Sao_Paulo",
    "iso:country":"BR",
    "wof:name":"Blauth",
    "wof:placetype":"locality"
},
  "geometry": {"coordinates":[-51.45,-29.23333],"type":"Point"}
}