{
  "type": "Feature",
  "properties": {
    "gn:admin1_code":"17",
    "gn:admin2_code":"2511400.0",
    "gn:asciiname":"Olho d'Agua",
    "gn:country_code":"BR",
    "gn:dem":574,
    "gn:feature_class":"P",
    "gn:feature_code":"PPL",
    "gn:name":"\u00d4lho d\u2019\u00c1gua",
    "gn:population":0,
    "gn:timezone":"America/Fortaleza",
    "iso:country":"BR",
    "wof:name":"Olho d'Agua",
    "wof:placetype":"locality"
},
  "geometry": {"coordinates":[-36.43333,-6.53333],"type":"Point"}
}