{
  "type": "Feature",
  "properties": {
    "gn:admin1_code":"15",
    "gn:admin2_code":"3130903.0",
    "gn:asciiname":"Sao Tome",
    "gn:cc2":"BR",
    "gn:country_code":"BR",
    "gn:dem":864,
    "gn:feature_class":"P",
    "gn:feature_code":"PPL",
    "gn:name":"S\u00e3o Tom\u00e9",
    "gn:population":0,
    "gn:timezone":"America/Sao_Paulo",
    "iso:country":"BR",
    "name:und_x_variant":[
        "Tom\u00e9",
        "S\u00e3o Tom\u00e9"
    ],
    "wof:name":"Sao Tome",
    "wof:placetype":"locality"
},
  "geometry": {"coordinates":[-41.68333,-19.51667],"type":"Point"}
}