{
  "type": "Feature",
  "properties": {
    "gn:admin1_code":"5",
    "gn:admin2_code":"2904753.0",
    "gn:asciiname":"Baixao Velho",
    "gn:country_code":"BR",
    "gn:dem":488,
    "gn:feature_class":"P",
    "gn:feature_code":"PPL",
    "gn:name":"Baix\u00e3o Velho",
    "gn:population":0,
    "gn:timezone":"America/Bahia",
    "iso:country":"BR",
    "name:und_x_variant":[
        "Baix\u00e3o Velho",
        "Baixa Velha"
    ],
    "wof:name":"Baixao Velho",
    "wof:placetype":"locality"
},
  "geometry": {"coordinates":[-43.52652,-10.56867],"type":"Point"}
}