{
  "type": "Feature",
  "properties": {
    "gn:admin1_code":"22",
    "gn:admin2_code":"2410405.0",
    "gn:asciiname":"Jerusalem",
    "gn:country_code":"BR",
    "gn:dem":71,
    "gn:feature_class":"P",
    "gn:feature_code":"PPL",
    "gn:name":"Jerusal\u00e9m",
    "gn:population":0,
    "gn:timezone":"America/Fortaleza",
    "iso:country":"BR",
    "wof:name":"Jerusalem",
    "wof:placetype":"locality"
},
  "geometry": {"coordinates":[-35.53333,-5.36667],"type":"Point"}
}