{
  "type": "Feature",
  "properties": {
    "gn:admin1_code":"21",
    "gn:admin2_code":"3305158.0",
    "gn:asciiname":"Sao Jose do Rio Preto",
    "gn:country_code":"BR",
    "gn:dem":656,
    "gn:feature_class":"P",
    "gn:feature_code":"PPL",
    "gn:name":"S\u00e3o Jos\u00e9 do Rio Pr\u00eato",
    "gn:population":0,
    "gn:timezone":"America/Sao_Paulo",
    "iso:country":"BR",
    "name:und_x_variant":[
        "Parana\u00fana",
        "S\u00e3o Jos\u00e9",
        "S\u00e3o Jos\u00e9 do Rio Pr\u00eato"
    ],
    "wof:name":"Sao Jose do Rio Preto",
    "wof:placetype":"locality"
},
  "geometry": {"coordinates":[-42.92474,-22.14987],"type":"Point"}
}