{
  "type": "Feature",
  "properties": {
    "gn:admin1_code":"13",
    "gn:admin2_code":"2112209.0",
    "gn:asciiname":"Buritirana",
    "gn:country_code":"BR",
    "gn:dem":217,
    "gn:feature_class":"P",
    "gn:feature_code":"PPL",
    "gn:name":"Buritirana",
    "gn:population":0,
    "gn:timezone":"America/Fortaleza",
    "iso:country":"BR",
    "wof:name":"Buritirana",
    "wof:placetype":"locality"
},
  "geometry": {"coordinates":[-43.06667,-5.16667],"type":"Point"}
}