{
  "type": "Feature",
  "properties": {
    "gn:admin1_code":"13",
    "gn:admin2_code":"2112209.0",
    "gn:asciiname":"Buritirana",
    "gn:country_code":"BR",
    "gn:dem":217,
    "gn:feature_class":"P",
    "gn:feature_code":"PPL",
    "gn:name":"Buritirana",
    "gn:population":0,
    "gn:timezone":"America/Fortaleza",
    "iso:country":"BR",
    "name:bpy_x_preferred":[
        "\u09ac\u09c1\u09b0\u09bf\u099f\u09bf\u09b0\u09be\u09a8\u09be"
    ],
    "name:ceb_x_preferred":[
        "Buritirana"
    ],
    "name:eus_x_preferred":[
        "Buritirana"
    ],
    "name:fra_x_preferred":[
        "Buritirana"
    ],
    "name:hye_x_preferred":[
        "\u0532\u0578\u0582\u0580\u056b\u057f\u056b\u0580\u0561\u0576\u0561"
    ],
    "name:ita_x_preferred":[
        "Buritirana"
    ],
    "name:kaz_x_preferred":[
        "\u0411\u0443\u0440\u0438\u0442\u0438\u0440\u0430\u043d\u0430"
    ],
    "name:nld_x_preferred":[
        "Buritirana"
    ],
    "name:nor_x_preferred":[
        "Buritirana"
    ],
    "name:por_x_preferred":[
        "Buritirana"
    ],
    "name:ron_x_preferred":[
        "Buritirana"
    ],
    "name:rus_x_preferred":[
        "\u0411\u0443\u0440\u0438\u0442\u0438\u0440\u0430\u043d\u0430"
    ],
    "name:spa_x_preferred":[
        "Buritirana"
    ],
    "name:swe_x_preferred":[
        "Buritirana"
    ],
    "name:vie_x_preferred":[
        "Buritirana"
    ],
    "name:vol_x_preferred":[
        "Buritirana"
    ],
    "name:war_x_preferred":[
        "Buritirana"
    ],
    "name:zho_x_preferred":[
        "\u5e03\u91cc\u8482\u62c9\u7eb3"
    ],
    "wof:name":"Buritirana",
    "wof:placetype":"locality"
},
  "geometry": {"coordinates":[-43.06667,-5.16667],"type":"Point"}
}