{
  "type": "Feature",
  "properties": {
    "gn:admin1_code":"18.0",
    "gn:admin2_code":"4100202.0",
    "gn:asciiname":"Varginha",
    "gn:country_code":"BR",
    "gn:dem":310,
    "gn:feature_class":"P",
    "gn:feature_code":"PPLL",
    "gn:name":"Varginha",
    "gn:population":0,
    "gn:timezone":"America/Sao_Paulo",
    "iso:country":"BR",
    "name:ara_x_preferred":[
        "\u0641\u0627\u0631\u062c\u064a\u0646\u0647\u0627"
    ],
    "name:bpy_x_preferred":[
        "\u09ad\u09be\u09b0\u09cd\u0997\u09bf\u09a8\u09b9\u09be"
    ],
    "name:ceb_x_preferred":[
        "Varginha"
    ],
    "name:deu_x_preferred":[
        "Varginha"
    ],
    "name:epo_x_preferred":[
        "Varginha"
    ],
    "name:eus_x_preferred":[
        "Varginha"
    ],
    "name:fas_x_preferred":[
        "\u0648\u0631\u06af\u06cc\u0646\u0647\u0627"
    ],
    "name:fra_x_preferred":[
        "Varginha"
    ],
    "name:haw_x_preferred":[
        "Walinia"
    ],
    "name:hye_x_preferred":[
        "\u054e\u0561\u0580\u056a\u056b\u0576\u056b\u0561"
    ],
    "name:ita_x_preferred":[
        "Varginha"
    ],
    "name:kat_x_preferred":[
        "\u10d5\u10d0\u10e0\u10df\u10d8\u10dc\u10d8\u10d0"
    ],
    "name:kaz_x_preferred":[
        "\u0412\u0430\u0440\u0436\u0438\u043d\u044c\u044f"
    ],
    "name:mlg_x_preferred":[
        "Varginha"
    ],
    "name:nld_x_preferred":[
        "Varginha"
    ],
    "name:nor_x_preferred":[
        "Varginha"
    ],
    "name:pol_x_preferred":[
        "Varginha"
    ],
    "name:por_x_preferred":[
        "Varginha"
    ],
    "name:ron_x_preferred":[
        "Varginha"
    ],
    "name:rus_x_preferred":[
        "\u0412\u0430\u0440\u0436\u0438\u043d\u044c\u044f"
    ],
    "name:srp_x_preferred":[
        "\u0412\u0430\u0440\u0436\u0438\u045a\u0430"
    ],
    "name:swe_x_preferred":[
        "Varginha"
    ],
    "name:tat_x_preferred":[
        "\u0412\u0430\u0440\u0436\u0438\u043d\u044c\u044f"
    ],
    "name:vie_x_preferred":[
        "Varginha"
    ],
    "name:vol_x_preferred":[
        "Varginha"
    ],
    "name:war_x_preferred":[
        "Varginha"
    ],
    "name:zho_x_preferred":[
        "\u74e6\u5c14\u4efb\u963f"
    ],
    "wof:name":"Varginha",
    "wof:placetype":"locality"
},
  "geometry": {"coordinates":[-48.88876,-24.79154],"type":"Point"}
}