{
  "type": "Feature",
  "properties": {
    "gn:admin1_code":"8",
    "gn:admin2_code":"3200102.0",
    "gn:asciiname":"Santa Luzia",
    "gn:country_code":"BR",
    "gn:dem":532,
    "gn:feature_class":"P",
    "gn:feature_code":"PPL",
    "gn:name":"Santa Luzia",
    "gn:population":0,
    "gn:timezone":"America/Sao_Paulo",
    "iso:country":"BR",
    "name:por_x_preferred":[
        "Santa Luzia"
    ],
    "wof:name":"Santa Luzia",
    "wof:placetype":"locality"
},
  "geometry": {"coordinates":[-41.15,-20.15],"type":"Point"}
}