{
  "type": "Feature",
  "properties": {
    "gn:admin1_code":"31",
    "gn:admin2_code":"1702109.0",
    "gn:asciiname":"Nazare",
    "gn:country_code":"BR",
    "gn:dem":244,
    "gn:feature_class":"P",
    "gn:feature_code":"PPL",
    "gn:name":"Nazar\u00e9",
    "gn:population":0,
    "gn:timezone":"America/Araguaina",
    "iso:country":"BR",
    "wof:name":"Nazare",
    "wof:placetype":"locality"
},
  "geometry": {"coordinates":[-48.35,-7.35],"type":"Point"}
}