{
  "type": "Feature",
  "properties": {
    "gn:admin1_code":"20",
    "gn:admin2_code":"2204303.0",
    "gn:asciiname":"Coqueiro",
    "gn:country_code":"BR",
    "gn:dem":468,
    "gn:feature_class":"P",
    "gn:feature_code":"PPL",
    "gn:name":"Coqueiro",
    "gn:population":0,
    "gn:timezone":"America/Fortaleza",
    "iso:country":"BR",
    "wof:name":"Coqueiro",
    "wof:placetype":"locality"
},
  "geometry": {"coordinates":[-40.65,-7.06667],"type":"Point"}
}