{
  "type": "Feature",
  "properties": {
    "gn:admin1_code":"20",
    "gn:admin2_code":"2208106.0",
    "gn:asciiname":"Serra do Joaozinho do Mestre Pedro",
    "gn:country_code":"BR",
    "gn:dem":820,
    "gn:feature_class":"P",
    "gn:feature_code":"PPL",
    "gn:name":"Serra do Jo\u00e2ozinho do Mestre Pedro",
    "gn:population":0,
    "gn:timezone":"America/Fortaleza",
    "iso:country":"BR",
    "wof:name":"Serra do Joaozinho do Mestre Pedro",
    "wof:placetype":"locality"
},
  "geometry": {"coordinates":[-40.85,-6.26667],"type":"Point"}
}