{
  "type": "Feature",
  "properties": {
    "gn:admin1_code":"18.0",
    "gn:admin2_code":"4120804.0",
    "gn:asciiname":"Sitio Altino Pires dos Santos",
    "gn:country_code":"BR",
    "gn:dem":851,
    "gn:feature_class":"P",
    "gn:feature_code":"PPL",
    "gn:name":"S\u00edtio Altino Pires dos Santos",
    "gn:population":0,
    "gn:timezone":"America/Sao_Paulo",
    "iso:country":"BR",
    "name:por_x_preferred":[
        "S\u00edtio Altino Pires dos Santos"
    ],
    "wof:name":"Sitio Altino Pires dos Santos",
    "wof:placetype":"locality"
},
  "geometry": {"coordinates":[-48.9736,-25.38566],"type":"Point"}
}