{
  "type": "Feature",
  "properties": {
    "gn:admin1_code":"06",
    "gn:admin2_code":"2310308.0",
    "gn:asciiname":"Riacho Fundo",
    "gn:country_code":"BR",
    "gn:dem":587,
    "gn:feature_class":"P",
    "gn:feature_code":"PPL",
    "gn:name":"Riacho Fundo",
    "gn:population":0,
    "gn:timezone":"America/Fortaleza",
    "iso:country":"BR",
    "name:deu_x_preferred":[
        "Riacho Fundo"
    ],
    "name:fra_x_preferred":[
        "Riacho Fundo"
    ],
    "name:ita_x_preferred":[
        "Riacho Fundo"
    ],
    "name:por_x_preferred":[
        "Riacho Fundo"
    ],
    "wof:name":"Riacho Fundo",
    "wof:placetype":"locality"
},
  "geometry": {"coordinates":[-40.75,-6.25],"type":"Point"}
}