{
  "type": "Feature",
  "properties": {
    "gn:admin1_code":"27.0",
    "gn:admin2_code":"3528502.0",
    "gn:asciiname":"Sitio Vovo Nene",
    "gn:country_code":"BR",
    "gn:dem":875,
    "gn:feature_class":"P",
    "gn:feature_code":"PPL",
    "gn:name":"S\u00edtio Vov\u00f3 Nen\u00ea",
    "gn:population":0,
    "gn:timezone":"America/Sao_Paulo",
    "iso:country":"BR",
    "name:por_x_preferred":[
        "S\u00edtio Vov\u00f3 Nen\u00ea"
    ],
    "wof:name":"Sitio Vovo Nene",
    "wof:placetype":"locality"
},
  "geometry": {"coordinates":[-46.51657,-23.26413],"type":"Point"}
}