{
  "type": "Feature",
  "properties": {
    "gn:admin1_code":"20",
    "gn:admin2_code":"2210409.0",
    "gn:asciiname":"Lagoa de Sao Joaquim",
    "gn:country_code":"BR",
    "gn:dem":402,
    "gn:feature_class":"P",
    "gn:feature_code":"PPL",
    "gn:name":"Lagoa de S\u00e3o Joaquim",
    "gn:population":0,
    "gn:timezone":"America/Fortaleza",
    "iso:country":"BR",
    "wof:name":"Lagoa de Sao Joaquim",
    "wof:placetype":"locality"
},
  "geometry": {"coordinates":[-41.41667,-5.61667],"type":"Point"}
}