{
  "type": "Feature",
  "properties": {
    "gn:admin1_code":"18.0",
    "gn:admin2_code":"4113205.0",
    "gn:asciiname":"Sitio Joao M. de Siqueira",
    "gn:country_code":"BR",
    "gn:dem":855,
    "gn:feature_class":"P",
    "gn:feature_code":"PPL",
    "gn:name":"S\u00edtio Jo\u00e3o M. de Siqueira",
    "gn:population":0,
    "gn:timezone":"America/Sao_Paulo",
    "iso:country":"BR",
    "name:por_x_preferred":[
        "S\u00edtio Jo\u00e3o M. de Siqueira"
    ],
    "wof:name":"Sitio Joao M. de Siqueira",
    "wof:placetype":"locality"
},
  "geometry": {"coordinates":[-49.5518,-25.8137],"type":"Point"}
}