{
  "type": "Feature",
  "properties": {
    "gn:admin1_code":"14",
    "gn:admin2_code":"5101258.0",
    "gn:asciiname":"Gaucha",
    "gn:country_code":"BR",
    "gn:dem":554,
    "gn:feature_class":"P",
    "gn:feature_code":"PPL",
    "gn:name":"Ga\u00facha",
    "gn:population":0,
    "gn:timezone":"America/Cuiaba",
    "iso:country":"BR",
    "name:und_x_variant":[
        "Ga\u00facha"
    ],
    "wof:name":"Gaucha",
    "wof:placetype":"locality"
},
  "geometry": {"coordinates":[-58.56667,-15.06667],"type":"Point"}
}