{
  "type": "Feature",
  "properties": {
    "gn:admin1_code":"18.0",
    "gn:admin2_code":"4106001.0",
    "gn:asciiname":"Sitio Minas Gerais",
    "gn:country_code":"BR",
    "gn:dem":661,
    "gn:feature_class":"P",
    "gn:feature_code":"PPL",
    "gn:name":"S\u00edtio Minas Gerais",
    "gn:population":0,
    "gn:timezone":"America/Sao_Paulo",
    "iso:country":"BR",
    "name:por_x_preferred":[
        "S\u00edtio Minas Gerais"
    ],
    "wof:name":"Sitio Minas Gerais",
    "wof:placetype":"locality"
},
  "geometry": {"coordinates":[-50.50187,-23.6123],"type":"Point"}
}