{
  "type": "Feature",
  "properties": {
    "gn:admin1_code":"30",
    "gn:admin2_code":"2613503.0",
    "gn:asciiname":"Luis Pereira",
    "gn:country_code":"BR",
    "gn:dem":459,
    "gn:feature_class":"P",
    "gn:feature_code":"PPL",
    "gn:name":"Lu\u00eds Pereira",
    "gn:population":0,
    "gn:timezone":"America/Recife",
    "iso:country":"BR",
    "wof:name":"Luis Pereira",
    "wof:placetype":"locality"
},
  "geometry": {"coordinates":[-38.68333,-7.95],"type":"Point"}
}