{
  "type": "Feature",
  "properties": {
    "gn:admin1_code":"1",
    "gn:admin2_code":"1200385.0",
    "gn:asciiname":"Fazenda Aquario",
    "gn:country_code":"BR",
    "gn:dem":173,
    "gn:feature_class":"P",
    "gn:feature_code":"PPL",
    "gn:name":"Fazenda Aqu\u00e1rio",
    "gn:population":0,
    "gn:timezone":"America/Rio_Branco",
    "iso:country":"BR",
    "wof:name":"Fazenda Aquario",
    "wof:placetype":"locality"
},
  "geometry": {"coordinates":[-67.15000000000001,-9.98333],"type":"Point"}
}