{
  "type": "Feature",
  "properties": {
    "gn:admin1_code":"27",
    "gn:admin2_code":"3502408.0",
    "gn:asciiname":"Noite Negra",
    "gn:country_code":"BR",
    "gn:dem":463,
    "gn:feature_class":"P",
    "gn:feature_code":"PPL",
    "gn:name":"Noite Negra",
    "gn:population":0,
    "gn:timezone":"America/Sao_Paulo",
    "iso:country":"BR",
    "wof:name":"Noite Negra",
    "wof:placetype":"locality"
},
  "geometry": {"coordinates":[-51.41667,-22.26667],"type":"Point"}
}