{
  "type": "Feature",
  "properties": {
    "gn:admin1_code":"18",
    "gn:admin2_code":"4127601.0",
    "gn:asciiname":"Sitio Antonio S. de Lima",
    "gn:country_code":"BR",
    "gn:dem":932,
    "gn:feature_class":"P",
    "gn:feature_code":"PPL",
    "gn:name":"S\u00edtio Ant\u00f4nio S. de Lima",
    "gn:population":0,
    "gn:timezone":"America/Sao_Paulo",
    "iso:country":"BR",
    "name:por_x_preferred":[
        "S\u00edtio Ant\u00f4nio S. de Lima"
    ],
    "wof:name":"Sitio Antonio S. de Lima",
    "wof:placetype":"locality"
},
  "geometry": {"coordinates":[-49.12851,-25.93596],"type":"Point"}
}