{
  "type": "Feature",
  "properties": {
    "gn:admin1_code":"20",
    "gn:admin2_code":"2200277.0",
    "gn:asciiname":"Jardim",
    "gn:country_code":"BR",
    "gn:dem":435,
    "gn:feature_class":"P",
    "gn:feature_code":"PPL",
    "gn:name":"Jardim",
    "gn:population":0,
    "gn:timezone":"America/Fortaleza",
    "iso:country":"BR",
    "name:ceb_x_preferred":[
        "Jardim"
    ],
    "name:deu_x_preferred":[
        "Jardim"
    ],
    "name:fra_x_preferred":[
        "Jardim"
    ],
    "name:glg_x_preferred":[
        "Jardim"
    ],
    "name:hye_x_preferred":[
        "\u053a\u0561\u0580\u0564\u056b\u0576"
    ],
    "name:ita_x_preferred":[
        "Jardim"
    ],
    "name:nld_x_preferred":[
        "Jardim"
    ],
    "name:nor_x_preferred":[
        "Jardim"
    ],
    "name:pol_x_preferred":[
        "Jardim"
    ],
    "name:por_x_preferred":[
        "Jardim"
    ],
    "name:rus_x_preferred":[
        "\u0416\u0430\u0440\u0434\u0438\u043d"
    ],
    "name:swe_x_preferred":[
        "Jardim"
    ],
    "name:vie_x_preferred":[
        "Jardim"
    ],
    "name:vol_x_preferred":[
        "Jardim"
    ],
    "wof:name":"Jardim",
    "wof:placetype":"locality"
},
  "geometry": {"coordinates":[-40.76667,-7.25],"type":"Point"}
}