{
  "type": "Feature",
  "properties": {
    "gn:admin1_code":"20",
    "gn:admin2_code":"2200277.0",
    "gn:asciiname":"Jardim",
    "gn:country_code":"BR",
    "gn:dem":435,
    "gn:feature_class":"P",
    "gn:feature_code":"PPL",
    "gn:name":"Jardim",
    "gn:population":0,
    "gn:timezone":"America/Fortaleza",
    "iso:country":"BR",
    "wof:name":"Jardim",
    "wof:placetype":"locality"
},
  "geometry": {"coordinates":[-40.76667,-7.25],"type":"Point"}
}