{
  "type": "Feature",
  "properties": {
    "gn:admin1_code":"18.0",
    "gn:admin2_code":"4119202.0",
    "gn:asciiname":"Sitio Joao C. de Melo",
    "gn:country_code":"BR",
    "gn:dem":712,
    "gn:feature_class":"P",
    "gn:feature_code":"PPL",
    "gn:name":"S\u00edtio Jo\u00e3o C. de Melo",
    "gn:population":0,
    "gn:timezone":"America/Sao_Paulo",
    "iso:country":"BR",
    "name:por_x_preferred":[
        "S\u00edtio Jo\u00e3o C. de Melo"
    ],
    "wof:name":"Sitio Joao C. de Melo",
    "wof:placetype":"locality"
},
  "geometry": {"coordinates":[-50.08355,-23.89837],"type":"Point"}
}