{
  "type": "Feature",
  "properties": {
    "gn:admin1_code":"18.0",
    "gn:admin2_code":"4126603.0",
    "gn:asciiname":"Sitio Helena Batista",
    "gn:country_code":"BR",
    "gn:dem":626,
    "gn:feature_class":"P",
    "gn:feature_code":"PPL",
    "gn:name":"S\u00edtio Helena Batista",
    "gn:population":0,
    "gn:timezone":"America/Sao_Paulo",
    "iso:country":"BR",
    "name:por_x_preferred":[
        "S\u00edtio Helena Batista"
    ],
    "wof:name":"Sitio Helena Batista",
    "wof:placetype":"locality"
},
  "geometry": {"coordinates":[-49.78100000000001,-23.5889],"type":"Point"}
}