{
  "type": "Feature",
  "properties": {
    "gn:admin1_code":"18",
    "gn:admin2_code":"4119103.0",
    "gn:asciiname":"Sitio Leonides Cruz",
    "gn:country_code":"BR",
    "gn:dem":940,
    "gn:feature_class":"P",
    "gn:feature_code":"PPL",
    "gn:name":"S\u00edtio Le\u00f4nides Cruz",
    "gn:population":0,
    "gn:timezone":"America/Sao_Paulo",
    "iso:country":"BR",
    "name:por_x_preferred":[
        "S\u00edtio Le\u00f4nides Cruz"
    ],
    "wof:name":"Sitio Leonides Cruz",
    "wof:placetype":"locality"
},
  "geometry": {"coordinates":[-49.4984,-26.0431],"type":"Point"}
}