{
  "type": "Feature",
  "properties": {
    "gn:admin1_code":"15",
    "gn:admin2_code":"3128006.0",
    "gn:asciiname":"Palmital",
    "gn:country_code":"BR",
    "gn:dem":534,
    "gn:feature_class":"P",
    "gn:feature_code":"PPL",
    "gn:name":"Palmital",
    "gn:population":0,
    "gn:timezone":"America/Sao_Paulo",
    "iso:country":"BR",
    "name:ceb_x_preferred":[
        "Palmital"
    ],
    "name:ita_x_preferred":[
        "Palmital"
    ],
    "name:nld_x_preferred":[
        "Palmital"
    ],
    "name:nor_x_preferred":[
        "Palmital"
    ],
    "name:por_x_preferred":[
        "Palmital"
    ],
    "name:rus_x_preferred":[
        "\u041f\u0430\u043b\u043c\u0438\u0442\u0430\u043b"
    ],
    "name:swe_x_preferred":[
        "Palmital"
    ],
    "name:vol_x_preferred":[
        "Palmital"
    ],
    "wof:name":"Palmital",
    "wof:placetype":"locality"
},
  "geometry": {"coordinates":[-42.56667,-18.95],"type":"Point"}
}