{
  "type": "Feature",
  "properties": {
    "gn:admin1_code":"18",
    "gn:admin2_code":"4119103.0",
    "gn:asciiname":"Sitio Terra do Alto",
    "gn:country_code":"BR",
    "gn:dem":952,
    "gn:feature_class":"P",
    "gn:feature_code":"PPL",
    "gn:name":"S\u00edtio Terra do Alto",
    "gn:population":0,
    "gn:timezone":"America/Sao_Paulo",
    "iso:country":"BR",
    "name:por_x_preferred":[
        "S\u00edtio Terra do Alto"
    ],
    "wof:name":"Sitio Terra do Alto",
    "wof:placetype":"locality"
},
  "geometry": {"coordinates":[-49.3737,-26.0699],"type":"Point"}
}