{
  "type": "Feature",
  "properties": {
    "gn:admin1_code":"18.0",
    "gn:admin2_code":"4104006.0",
    "gn:asciiname":"Sitio Pedro P. de Carvalho",
    "gn:country_code":"BR",
    "gn:dem":859,
    "gn:feature_class":"P",
    "gn:feature_code":"PPL",
    "gn:name":"S\u00edtio Pedro P. de Carvalho",
    "gn:population":0,
    "gn:timezone":"America/Sao_Paulo",
    "iso:country":"BR",
    "name:por_x_preferred":[
        "S\u00edtio Pedro P. de Carvalho"
    ],
    "wof:name":"Sitio Pedro P. de Carvalho",
    "wof:placetype":"locality"
},
  "geometry": {"coordinates":[-48.89682,-25.19946],"type":"Point"}
}