{
  "type": "Feature",
  "properties": {
    "gn:admin1_code":"21",
    "gn:admin2_code":"3303500.0",
    "gn:asciiname":"Jardim Marambaia",
    "gn:country_code":"BR",
    "gn:dem":12,
    "gn:feature_class":"P",
    "gn:feature_code":"PPL",
    "gn:name":"Jardim Marambaia",
    "gn:population":0,
    "gn:timezone":"America/Sao_Paulo",
    "iso:country":"BR",
    "name:por_x_preferred":[
        "Jardim Marambaia"
    ],
    "wof:name":"Jardim Marambaia",
    "wof:placetype":"locality"
},
  "geometry": {"coordinates":[-43.40528,-22.64278],"type":"Point"}
}