{
  "type": "Feature",
  "properties": {
    "gn:admin1_code":"5",
    "gn:admin2_code":"2922102.0",
    "gn:asciiname":"Palmeira",
    "gn:country_code":"BR",
    "gn:dem":590,
    "gn:feature_class":"P",
    "gn:feature_code":"PPL",
    "gn:name":"Palmeira",
    "gn:population":0,
    "gn:timezone":"America/Bahia",
    "iso:country":"BR",
    "name:ceb_x_preferred":[
        "Palmeira"
    ],
    "name:ces_x_preferred":[
        "Palmeira"
    ],
    "name:deu_x_preferred":[
        "Palmeira"
    ],
    "name:fra_x_preferred":[
        "Palmeira"
    ],
    "name:glg_x_preferred":[
        "Palmeira"
    ],
    "name:ita_x_preferred":[
        "Palmeira"
    ],
    "name:nds_x_preferred":[
        "Palmeira"
    ],
    "name:nld_x_preferred":[
        "Palmeira"
    ],
    "name:nor_x_preferred":[
        "Palmeira"
    ],
    "name:pol_x_preferred":[
        "Palmeira"
    ],
    "name:por_x_preferred":[
        "Palmeira"
    ],
    "name:rus_x_preferred":[
        "\u041f\u0430\u043b\u043c\u0435\u0439\u0440\u0430"
    ],
    "name:swe_x_preferred":[
        "Palmeira"
    ],
    "name:ukr_x_preferred":[
        "\u041f\u0430\u043b\u043c\u0435\u0439\u0440\u0430"
    ],
    "name:vol_x_preferred":[
        "Palmeira"
    ],
    "wof:name":"Palmeira",
    "wof:placetype":"locality"
},
  "geometry": {"coordinates":[-40.78333,-11.96667],"type":"Point"}
}