{
  "type": "Feature",
  "properties": {
    "gn:admin1_code":"11",
    "gn:admin2_code":"5007695.0",
    "gn:asciiname":"Jose Franca",
    "gn:country_code":"BR",
    "gn:dem":339,
    "gn:feature_class":"P",
    "gn:feature_code":"PPL",
    "gn:name":"Jos\u00e9 Fran\u00e7a",
    "gn:population":0,
    "gn:timezone":"America/Campo_Grande",
    "iso:country":"BR",
    "name:por_x_preferred":[
        "Jos\u00e9 Fran\u00e7a"
    ],
    "wof:name":"Jose Franca",
    "wof:placetype":"locality"
},
  "geometry": {"coordinates":[-54.43333000000001,-18.86667000000001],"type":"Point"}
}