{
  "type": "Feature",
  "properties": {
    "gn:admin1_code":"21",
    "gn:admin2_code":"3303401.0",
    "gn:asciiname":"Conquista",
    "gn:country_code":"BR",
    "gn:dem":1098,
    "gn:feature_class":"P",
    "gn:feature_code":"PPL",
    "gn:name":"Conquista",
    "gn:population":0,
    "gn:timezone":"America/Sao_Paulo",
    "iso:country":"BR",
    "name:por_x_preferred":[
        "Conquista"
    ],
    "wof:name":"Conquista",
    "wof:placetype":"locality"
},
  "geometry": {"coordinates":[-42.68333,-22.28333],"type":"Point"}
}