{
  "type": "Feature",
  "properties": {
    "gn:admin1_code":"5",
    "gn:admin2_code":"2906501.0",
    "gn:asciiname":"Pasto de Fora",
    "gn:country_code":"BR",
    "gn:dem":48,
    "gn:feature_class":"P",
    "gn:feature_code":"PPL",
    "gn:name":"Pasto de Fora",
    "gn:population":0,
    "gn:timezone":"America/Bahia",
    "iso:country":"BR",
    "wof:name":"Pasto de Fora",
    "wof:placetype":"locality"
},
  "geometry": {"coordinates":[-38.48333,-12.71667],"type":"Point"}
}