{
  "type": "Feature",
  "properties": {
    "gn:admin1_code":"26",
    "gn:admin2_code":"4206009.0",
    "gn:asciiname":"Caieira do Norte",
    "gn:country_code":"BR",
    "gn:dem":23,
    "gn:feature_class":"P",
    "gn:feature_code":"PPL",
    "gn:name":"Caieira do Norte",
    "gn:population":0,
    "gn:timezone":"America/Sao_Paulo",
    "iso:country":"BR",
    "wof:name":"Caieira do Norte",
    "wof:placetype":"locality"
},
  "geometry": {"coordinates":[-48.59064,-27.42747],"type":"Point"}
}