{
  "type": "Feature",
  "properties": {
    "gn:admin1_code":"18.0",
    "gn:admin2_code":"4109708.0",
    "gn:asciiname":"Sitio Antonio B. de Camargo",
    "gn:country_code":"BR",
    "gn:dem":658,
    "gn:feature_class":"P",
    "gn:feature_code":"PPL",
    "gn:name":"S\u00edtio Ant\u00f4nio B. de Camargo",
    "gn:population":0,
    "gn:timezone":"America/Sao_Paulo",
    "iso:country":"BR",
    "name:por_x_preferred":[
        "S\u00edtio Ant\u00f4nio B. de Camargo"
    ],
    "wof:name":"Sitio Antonio B. de Camargo",
    "wof:placetype":"locality"
},
  "geometry": {"coordinates":[-50.30278,-23.91413],"type":"Point"}
}