{
  "type": "Feature",
  "properties": {
    "gn:admin1_code":"28",
    "gn:admin2_code":"2805406.0",
    "gn:asciiname":"Riacho Largo",
    "gn:country_code":"BR",
    "gn:dem":203,
    "gn:feature_class":"P",
    "gn:feature_code":"PPL",
    "gn:name":"Riacho Largo",
    "gn:population":0,
    "gn:timezone":"America/Maceio",
    "iso:country":"BR",
    "wof:name":"Riacho Largo",
    "wof:placetype":"locality"
},
  "geometry": {"coordinates":[-37.68333,-9.85],"type":"Point"}
}