{
  "type": "Feature",
  "properties": {
    "gn:admin1_code":"18.0",
    "gn:admin2_code":"4107751.0",
    "gn:asciiname":"Sitio Boa Esperanca",
    "gn:country_code":"BR",
    "gn:dem":604,
    "gn:feature_class":"P",
    "gn:feature_code":"PPL",
    "gn:name":"S\u00edtio Boa Esperan\u00e7a",
    "gn:population":0,
    "gn:timezone":"America/Sao_Paulo",
    "iso:country":"BR",
    "name:por_x_preferred":[
        "S\u00edtio Boa Esperan\u00e7a"
    ],
    "wof:name":"Sitio Boa Esperanca",
    "wof:placetype":"locality"
},
  "geometry": {"coordinates":[-50.46622,-23.89755],"type":"Point"}
}