{
  "type": "Feature",
  "properties": {
    "gn:admin1_code":"15",
    "gn:admin2_code":"3112109.0",
    "gn:asciiname":"Sao Geraldo",
    "gn:country_code":"BR",
    "gn:dem":882,
    "gn:feature_class":"P",
    "gn:feature_code":"PPL",
    "gn:name":"S\u00e3o Geraldo",
    "gn:population":0,
    "gn:timezone":"America/Sao_Paulo",
    "iso:country":"BR",
    "name:por_x_preferred":[
        "S\u00e3o Geraldo"
    ],
    "wof:name":"Sao Geraldo",
    "wof:placetype":"locality"
},
  "geometry": {"coordinates":[-41.91667,-20.51667],"type":"Point"}
}