{
  "type": "Feature",
  "properties": {
    "gn:admin1_code":"27.0",
    "gn:admin2_code":"3518800.0",
    "gn:asciiname":"Vila Imaculada",
    "gn:country_code":"BR",
    "gn:dem":796,
    "gn:feature_class":"P",
    "gn:feature_code":"PPL",
    "gn:name":"Vila Imaculada",
    "gn:population":0,
    "gn:timezone":"America/Sao_Paulo",
    "iso:country":"BR",
    "name:por_x_preferred":[
        "Vila Imaculada"
    ],
    "wof:name":"Vila Imaculada",
    "wof:placetype":"locality"
},
  "geometry": {"coordinates":[-46.53238,-23.43796],"type":"Point"}
}