{
  "type": "Feature",
  "properties": {
    "gn:admin1_code":"18.0",
    "gn:admin2_code":"4124103.0",
    "gn:asciiname":"Sitio Sao Lazaro",
    "gn:country_code":"BR",
    "gn:dem":523,
    "gn:feature_class":"P",
    "gn:feature_code":"PPL",
    "gn:name":"S\u00edtio S\u00e3o L\u00e1zaro",
    "gn:population":0,
    "gn:timezone":"America/Sao_Paulo",
    "iso:country":"BR",
    "name:por_x_preferred":[
        "S\u00edtio S\u00e3o L\u00e1zaro"
    ],
    "wof:name":"Sitio Sao Lazaro",
    "wof:placetype":"locality"
},
  "geometry": {"coordinates":[-50.04719,-23.33751],"type":"Point"}
}