{
  "type": "Feature",
  "properties": {
    "gn:admin1_code":"13",
    "gn:admin2_code":"2106300.0",
    "gn:asciiname":"Canto Grande III",
    "gn:country_code":"BR",
    "gn:dem":29,
    "gn:feature_class":"P",
    "gn:feature_code":"PPL",
    "gn:name":"Canto Grande III",
    "gn:population":0,
    "gn:timezone":"America/Fortaleza",
    "iso:country":"BR",
    "wof:name":"Canto Grande III",
    "wof:placetype":"locality"
},
  "geometry": {"coordinates":[-42.23833,-3.27194],"type":"Point"}
}