{
  "type": "Feature",
  "properties": {
    "gn:admin1_code":"4",
    "gn:admin2_code":"1301209.0",
    "gn:asciiname":"Sao Jose do Miriti",
    "gn:country_code":"BR",
    "gn:dem":39,
    "gn:feature_class":"P",
    "gn:feature_code":"PPL",
    "gn:name":"S\u00e3o Jos\u00e9 do Miriti",
    "gn:population":0,
    "gn:timezone":"America/Manaus",
    "iso:country":"BR",
    "wof:name":"Sao Jose do Miriti",
    "wof:placetype":"locality"
},
  "geometry": {"coordinates":[-62.9375,-3.92611],"type":"Point"}
}