{
  "type": "Feature",
  "properties": {
    "gn:admin1_code":"18.0",
    "gn:admin2_code":"4111803.0",
    "gn:asciiname":"Sitio Pedra Alta",
    "gn:country_code":"BR",
    "gn:dem":482,
    "gn:feature_class":"P",
    "gn:feature_code":"PPL",
    "gn:name":"S\u00edtio Pedra Alta",
    "gn:population":0,
    "gn:timezone":"America/Sao_Paulo",
    "iso:country":"BR",
    "name:por_x_preferred":[
        "S\u00edtio Pedra Alta"
    ],
    "wof:name":"Sitio Pedra Alta",
    "wof:placetype":"locality"
},
  "geometry": {"coordinates":[-49.90217,-23.15184],"type":"Point"}
}