{
  "type": "Feature",
  "properties": {
    "gn:admin1_code":"13",
    "gn:admin2_code":"2110104.0",
    "gn:asciiname":"Buritizinho II",
    "gn:country_code":"BR",
    "gn:dem":63,
    "gn:feature_class":"P",
    "gn:feature_code":"PPL",
    "gn:name":"Buritizinho II",
    "gn:population":0,
    "gn:timezone":"America/Fortaleza",
    "iso:country":"BR",
    "wof:name":"Buritizinho II",
    "wof:placetype":"locality"
},
  "geometry": {"coordinates":[-43.13472,-3.31583],"type":"Point"}
}