{
  "type": "Feature",
  "properties": {
    "gn:admin1_code":"27",
    "gn:admin2_code":"3509254.0",
    "gn:asciiname":"Sitio Julio da Guia",
    "gn:country_code":"BR",
    "gn:dem":238,
    "gn:feature_class":"P",
    "gn:feature_code":"PPL",
    "gn:name":"S\u00edtio J\u00falio da Guia",
    "gn:population":0,
    "gn:timezone":"America/Sao_Paulo",
    "iso:country":"BR",
    "name:por_x_preferred":[
        "S\u00edtio J\u00falio da Guia"
    ],
    "wof:name":"Sitio Julio da Guia",
    "wof:placetype":"locality"
},
  "geometry": {"coordinates":[-48.21503,-24.8442],"type":"Point"}
}