{
  "type": "Feature",
  "properties": {
    "gn:admin1_code":"13",
    "gn:admin2_code":"2106409.0",
    "gn:asciiname":"Jacu VI",
    "gn:country_code":"BR",
    "gn:dem":65,
    "gn:feature_class":"P",
    "gn:feature_code":"PPL",
    "gn:name":"Jacu VI",
    "gn:population":0,
    "gn:timezone":"America/Fortaleza",
    "iso:country":"BR",
    "wof:name":"Jacu VI",
    "wof:placetype":"locality"
},
  "geometry": {"coordinates":[-43.14833,-3.57306],"type":"Point"}
}