{
  "type": "Feature",
  "properties": {
    "gn:admin1_code":"22",
    "gn:admin2_code":"2401503.0",
    "gn:asciiname":"Boqueirao",
    "gn:country_code":"BR",
    "gn:dem":140,
    "gn:feature_class":"P",
    "gn:feature_code":"PPL",
    "gn:name":"Boqueir\u00e3o",
    "gn:population":0,
    "gn:timezone":"America/Fortaleza",
    "iso:country":"BR",
    "wof:name":"Boqueirao",
    "wof:placetype":"locality"
},
  "geometry": {"coordinates":[-35.88333,-5.93333],"type":"Point"}
}