{
  "type": "Feature",
  "properties": {
    "gn:admin1_code":"11",
    "gn:admin2_code":"5005608.0",
    "gn:asciiname":"Carrapatinho",
    "gn:country_code":"BR",
    "gn:dem":209,
    "gn:feature_class":"P",
    "gn:feature_code":"PPL",
    "gn:name":"Carrapatinho",
    "gn:population":0,
    "gn:timezone":"America/Campo_Grande",
    "iso:country":"BR",
    "wof:name":"Carrapatinho",
    "wof:placetype":"locality"
},
  "geometry": {"coordinates":[-56.31667,-20.15],"type":"Point"}
}