{
  "type": "Feature",
  "properties": {
    "gn:admin1_code":"22",
    "gn:admin2_code":"2403103.0",
    "gn:asciiname":"Malhada da Cruz",
    "gn:country_code":"BR",
    "gn:dem":430,
    "gn:feature_class":"P",
    "gn:feature_code":"PPL",
    "gn:name":"Malhada da Cruz",
    "gn:population":0,
    "gn:timezone":"America/Fortaleza",
    "iso:country":"BR",
    "wof:name":"Malhada da Cruz",
    "wof:placetype":"locality"
},
  "geometry": {"coordinates":[-36.38333,-6.15],"type":"Point"}
}