{
  "type": "Feature",
  "properties": {
    "gn:admin1_code":"17",
    "gn:admin2_code":"2504504.0",
    "gn:asciiname":"Sao Concalo",
    "gn:country_code":"BR",
    "gn:dem":223,
    "gn:feature_class":"P",
    "gn:feature_code":"PPL",
    "gn:name":"S\u00e3o Con\u00e7alo",
    "gn:population":0,
    "gn:timezone":"America/Fortaleza",
    "iso:country":"BR",
    "wof:name":"Sao Concalo",
    "wof:placetype":"locality"
},
  "geometry": {"coordinates":[-37.66667,-6.88333],"type":"Point"}
}