{
  "type": "Feature",
  "properties": {
    "gn:admin1_code":"20",
    "gn:admin2_code":"2203206.0",
    "gn:asciiname":"Boca da Catinga",
    "gn:country_code":"BR",
    "gn:dem":332,
    "gn:feature_class":"P",
    "gn:feature_code":"PPL",
    "gn:name":"B\u00f4ca da Catinga",
    "gn:population":0,
    "gn:timezone":"America/Fortaleza",
    "iso:country":"BR",
    "wof:name":"Boca da Catinga",
    "wof:placetype":"locality"
},
  "geometry": {"coordinates":[-44.43333,-10.01667],"type":"Point"}
}