{
  "type": "Feature",
  "properties": {
    "gn:admin1_code":"06",
    "gn:admin2_code":"2300200.0",
    "gn:asciiname":"Catarina",
    "gn:country_code":"BR",
    "gn:dem":27,
    "gn:feature_class":"P",
    "gn:feature_code":"PPL",
    "gn:name":"Catarina",
    "gn:population":0,
    "gn:timezone":"America/Fortaleza",
    "iso:country":"BR",
    "name:bre_x_preferred":[
        "Catarina"
    ],
    "name:cat_x_preferred":[
        "Catarina"
    ],
    "name:ceb_x_preferred":[
        "Catarina"
    ],
    "name:deu_x_preferred":[
        "Catarina"
    ],
    "name:fra_x_preferred":[
        "Catarina"
    ],
    "name:ita_x_preferred":[
        "Catarina"
    ],
    "name:jpn_x_preferred":[
        "\u30ab\u30bf\u30ea\u30ca"
    ],
    "name:kor_x_preferred":[
        "\uce74\ud0c0\ub9ac\ub098"
    ],
    "name:nld_x_preferred":[
        "Catarina"
    ],
    "name:por_x_preferred":[
        "Catarina"
    ],
    "name:spa_x_preferred":[
        "Catarina"
    ],
    "name:swe_x_preferred":[
        "Catarina"
    ],
    "name:vol_x_preferred":[
        "Catarina"
    ],
    "wof:name":"Catarina",
    "wof:placetype":"locality"
},
  "geometry": {"coordinates":[-39.98333,-2.96667],"type":"Point"}
}