{
  "type": "Feature",
  "properties": {
    "gn:admin1_code":"4",
    "gn:admin2_code":"1304062.0",
    "gn:asciiname":"Belem do Solimoes",
    "gn:country_code":"BR",
    "gn:dem":88,
    "gn:feature_class":"P",
    "gn:feature_code":"PPL",
    "gn:name":"Bel\u00e9m do Solimoes",
    "gn:population":0,
    "gn:timezone":"America/Manaus",
    "iso:country":"BR",
    "wof:name":"Belem do Solimoes",
    "wof:placetype":"locality"
},
  "geometry": {"coordinates":[-69.52346,-4.0293],"type":"Point"}
}