{
  "type": "Feature",
  "properties": {
    "gn:admin1_code":"18.0",
    "gn:admin2_code":"4122305.0",
    "gn:asciiname":"Sitio Bola Lisinzg",
    "gn:country_code":"BR",
    "gn:dem":782,
    "gn:feature_class":"P",
    "gn:feature_code":"PPL",
    "gn:name":"S\u00edtio Bola Lisinzg",
    "gn:population":0,
    "gn:timezone":"America/Sao_Paulo",
    "iso:country":"BR",
    "name:por_x_preferred":[
        "S\u00edtio Bola Lisinzg"
    ],
    "wof:name":"Sitio Bola Lisinzg",
    "wof:placetype":"locality"
},
  "geometry": {"coordinates":[-49.8572,-26.0451],"type":"Point"}
}