{
  "type": "Feature",
  "properties": {
    "gn:admin1_code":"21",
    "gn:admin2_code":"3306008.0",
    "gn:asciiname":"Monte Castelo",
    "gn:country_code":"BR",
    "gn:dem":383,
    "gn:feature_class":"P",
    "gn:feature_code":"PPL",
    "gn:name":"Monte Castelo",
    "gn:population":0,
    "gn:timezone":"America/Sao_Paulo",
    "iso:country":"BR",
    "name:bpy_x_preferred":[
        "\u09ae\u09cb\u09a8\u09cd\u099f\u09c7 \u0995\u09be\u09b8\u099f\u09c7\u09b2\u09cb"
    ],
    "name:ceb_x_preferred":[
        "Monte Castelo"
    ],
    "name:fra_x_preferred":[
        "Monte Castelo"
    ],
    "name:ita_x_preferred":[
        "Monte Castelo"
    ],
    "name:nld_x_preferred":[
        "Monte Castelo"
    ],
    "name:nor_x_preferred":[
        "Monte Castelo"
    ],
    "name:por_x_preferred":[
        "Monte Castelo"
    ],
    "name:swe_x_preferred":[
        "Monte Castelo"
    ],
    "name:vie_x_preferred":[
        "Monte Castelo"
    ],
    "name:vol_x_preferred":[
        "Monte Castelo"
    ],
    "wof:name":"Monte Castelo",
    "wof:placetype":"locality"
},
  "geometry": {"coordinates":[-43.21722000000001,-22.09417],"type":"Point"}
}