{
  "type": "Feature",
  "properties": {
    "gn:admin1_code":"18.0",
    "gn:admin2_code":"4121208.0",
    "gn:asciiname":"Sitio Lourdes Patras",
    "gn:country_code":"BR",
    "gn:dem":888,
    "gn:feature_class":"P",
    "gn:feature_code":"PPL",
    "gn:name":"S\u00edtio Lourdes Patras",
    "gn:population":0,
    "gn:timezone":"America/Sao_Paulo",
    "iso:country":"BR",
    "name:por_x_preferred":[
        "S\u00edtio Lourdes Patras"
    ],
    "wof:name":"Sitio Lourdes Patras",
    "wof:placetype":"locality"
},
  "geometry": {"coordinates":[-49.4356,-25.8059],"type":"Point"}
}