{
  "type": "Feature",
  "properties": {
    "gn:admin1_code":"27.0",
    "gn:admin2_code":"3551108.0",
    "gn:asciiname":"Varzea",
    "gn:country_code":"BR",
    "gn:dem":695,
    "gn:feature_class":"P",
    "gn:feature_code":"PPLL",
    "gn:name":"V\u00e1rzea",
    "gn:population":0,
    "gn:timezone":"America/Sao_Paulo",
    "iso:country":"BR",
    "name:por_x_preferred":[
        "V\u00e1rzea"
    ],
    "wof:name":"Varzea",
    "wof:placetype":"locality"
},
  "geometry": {"coordinates":[-47.881,-23.6195],"type":"Point"}
}