{
  "type": "Feature",
  "properties": {
    "gn:admin1_code":"13",
    "gn:admin2_code":"2107803.0",
    "gn:asciiname":"Tamandua",
    "gn:country_code":"BR",
    "gn:dem":165,
    "gn:feature_class":"P",
    "gn:feature_code":"PPL",
    "gn:name":"Tamandu\u00e1",
    "gn:population":0,
    "gn:timezone":"America/Fortaleza",
    "iso:country":"BR",
    "name:ara_x_preferred":[
        "\u062a\u0645\u0646\u062f\u0648\u0629"
    ],
    "name:bre_x_preferred":[
        "Tamandua"
    ],
    "name:cat_x_preferred":[
        "Tam\u00e0ndua"
    ],
    "name:ceb_x_preferred":[
        "Tamandua"
    ],
    "name:deu_x_preferred":[
        "Tamanduas"
    ],
    "name:epo_x_preferred":[
        "Tamanduo"
    ],
    "name:eus_x_preferred":[
        "Tamandua"
    ],
    "name:fas_x_preferred":[
        "\u0645\u0648\u0631\u0686\u0647\u200c\u062e\u0648\u0627\u0631 \u062f\u0631\u062e\u062a\u06cc"
    ],
    "name:fra_x_preferred":[
        "Tamandua"
    ],
    "name:glg_x_preferred":[
        "Tamandua"
    ],
    "name:heb_x_preferred":[
        "\u05d8\u05de\u05e0\u05d3\u05d5\u05d0\u05d4"
    ],
    "name:hun_x_preferred":[
        "Tamandua"
    ],
    "name:ita_x_preferred":[
        "Tamandua"
    ],
    "name:kaz_x_preferred":[
        "\u0422\u0430\u043c\u0430\u043d\u0434\u0443\u0430"
    ],
    "name:kor_x_preferred":[
        "\uc791\uc740\uac1c\ubbf8\ud565\uae30"
    ],
    "name:msa_x_preferred":[
        "Tamandua"
    ],
    "name:nld_x_preferred":[
        "Boommiereneters"
    ],
    "name:pol_x_preferred":[
        "Tamandua"
    ],
    "name:por_x_preferred":[
        "Tamandua"
    ],
    "name:ron_x_preferred":[
        "Tamandua"
    ],
    "name:rus_x_preferred":[
        "\u0427\u0435\u0442\u044b\u0440\u0451\u0445\u043f\u0430\u043b\u044b\u0435 \u043c\u0443\u0440\u0430\u0432\u044c\u0435\u0434\u044b"
    ],
    "name:spa_x_preferred":[
        "Tamandua"
    ],
    "name:swe_x_preferred":[
        "Tamanduor"
    ],
    "name:tha_x_preferred":[
        "\u0e17\u0e32\u0e41\u0e21\u0e19\u0e14\u0e31\u0e27"
    ],
    "name:vie_x_preferred":[
        "Tamandua"
    ],
    "name:war_x_preferred":[
        "Tamandua"
    ],
    "name:zho_x_preferred":[
        "\u5c0f\u98df\u8681\u517d\u5c5e"
    ],
    "wof:name":"Tamandua",
    "wof:placetype":"locality"
},
  "geometry": {"coordinates":[-43.16667,-5.65],"type":"Point"}
}