{
  "type": "Feature",
  "properties": {
    "gn:admin1_code":"26",
    "gn:admin2_code":"4210100.0",
    "gn:asciiname":"Sitio Albano Agostinho",
    "gn:country_code":"BR",
    "gn:dem":828,
    "gn:feature_class":"P",
    "gn:feature_code":"PPL",
    "gn:name":"S\u00edtio Albano Agostinho",
    "gn:population":0,
    "gn:timezone":"America/Sao_Paulo",
    "iso:country":"BR",
    "name:por_x_preferred":[
        "S\u00edtio Albano Agostinho"
    ],
    "wof:name":"Sitio Albano Agostinho",
    "wof:placetype":"locality"
},
  "geometry": {"coordinates":[-49.7551,-26.2363],"type":"Point"}
}