{
  "type": "Feature",
  "properties": {
    "gn:admin1_code":"13",
    "gn:admin2_code":"2109809.0",
    "gn:asciiname":"Sao Joao",
    "gn:country_code":"BR",
    "gn:dem":46,
    "gn:feature_class":"P",
    "gn:feature_code":"PPL",
    "gn:name":"S\u00e3o Jo\u00e3o",
    "gn:population":0,
    "gn:timezone":"America/Fortaleza",
    "iso:country":"BR",
    "wof:name":"Sao Joao",
    "wof:placetype":"locality"
},
  "geometry": {"coordinates":[-45.05,-2.21667],"type":"Point"}
}