{
  "type": "Feature",
  "properties": {
    "gn:admin1_code":"02",
    "gn:admin2_code":"2704203.0",
    "gn:asciiname":"Jiquiazinho",
    "gn:country_code":"BR",
    "gn:dem":204,
    "gn:feature_class":"P",
    "gn:feature_code":"PPL",
    "gn:name":"Jiqui\u00e0zinho",
    "gn:population":0,
    "gn:timezone":"America/Maceio",
    "iso:country":"BR",
    "wof:name":"Jiquiazinho",
    "wof:placetype":"locality"
},
  "geometry": {"coordinates":[-36.36667,-9.71667],"type":"Point"}
}