{
  "type": "Feature",
  "properties": {
    "gn:admin1_code":"22",
    "gn:admin2_code":"2411403.0",
    "gn:asciiname":"Passagem da Raiz",
    "gn:country_code":"BR",
    "gn:dem":197,
    "gn:feature_class":"P",
    "gn:feature_code":"PPL",
    "gn:name":"Passagem da Raiz",
    "gn:population":0,
    "gn:timezone":"America/Fortaleza",
    "iso:country":"BR",
    "wof:name":"Passagem da Raiz",
    "wof:placetype":"locality"
},
  "geometry": {"coordinates":[-36.43333,-5.86667],"type":"Point"}
}