{
  "type": "Feature",
  "properties": {
    "gn:admin1_code":"4",
    "gn:admin2_code":"1301704.0",
    "gn:asciiname":"Faro",
    "gn:cc2":"BR",
    "gn:country_code":"BR",
    "gn:dem":57,
    "gn:feature_class":"P",
    "gn:feature_code":"PPL",
    "gn:name":"Faro",
    "gn:population":0,
    "gn:timezone":"America/Manaus",
    "iso:country":"BR",
    "name:und_x_variant":[
        "Papunhas",
        "Faro"
    ],
    "wof:name":"Faro",
    "wof:placetype":"locality"
},
  "geometry": {"coordinates":[-62.93333000000001,-7.31667],"type":"Point"}
}