{
  "type": "Feature",
  "properties": {
    "gn:admin1_code":"20",
    "gn:admin2_code":"2206670.0",
    "gn:asciiname":"Acude Velho",
    "gn:country_code":"BR",
    "gn:dem":82,
    "gn:feature_class":"P",
    "gn:feature_code":"PPL",
    "gn:name":"A\u00e7ude Velho",
    "gn:population":0,
    "gn:timezone":"America/Fortaleza",
    "iso:country":"BR",
    "wof:name":"Acude Velho",
    "wof:placetype":"locality"
},
  "geometry": {"coordinates":[-42.24389,-3.71806],"type":"Point"}
}