{
  "type": "Feature",
  "properties": {
    "gn:admin1_code":"18",
    "gn:admin2_code":"4101200.0",
    "gn:asciiname":"Bairro Alto",
    "gn:country_code":"BR",
    "gn:dem":67,
    "gn:feature_class":"P",
    "gn:feature_code":"PPLL",
    "gn:name":"Bairro Alto",
    "gn:population":0,
    "gn:timezone":"America/Sao_Paulo",
    "iso:country":"BR",
    "name:por_x_preferred":[
        "Bairro Alto"
    ],
    "wof:name":"Bairro Alto",
    "wof:placetype":"locality"
},
  "geometry": {"coordinates":[-48.74921,-25.23299],"type":"Point"}
}