{
  "type": "Feature",
  "properties": {
    "gn:admin1_code":"15",
    "gn:admin2_code":"3126109.0",
    "gn:asciiname":"Jose Alves",
    "gn:country_code":"BR",
    "gn:dem":794,
    "gn:feature_class":"P",
    "gn:feature_code":"PPL",
    "gn:name":"Jos\u00e9 Alves",
    "gn:population":0,
    "gn:timezone":"America/Sao_Paulo",
    "iso:country":"BR",
    "name:por_x_preferred":[
        "Jos\u00e9 Alves"
    ],
    "wof:name":"Jose Alves",
    "wof:placetype":"locality"
},
  "geometry": {"coordinates":[-45.66667,-20.55],"type":"Point"}
}