{
  "type": "Feature",
  "properties": {
    "gn:admin1_code":"02",
    "gn:admin2_code":"2705002.0",
    "gn:asciiname":"Pe da Serra",
    "gn:cc2":"BR",
    "gn:country_code":"BR",
    "gn:dem":607,
    "gn:feature_class":"P",
    "gn:feature_code":"PPL",
    "gn:name":"P\u00e9 da Serra",
    "gn:population":0,
    "gn:timezone":"America/Maceio",
    "iso:country":"BR",
    "name:und_x_variant":[
        "P\u00e9 de Serra",
        "P\u00e9 da Serra"
    ],
    "wof:name":"Pe da Serra",
    "wof:placetype":"locality"
},
  "geometry": {"coordinates":[-37.53333,-8.96667],"type":"Point"}
}