{
  "type": "Feature",
  "properties": {
    "gn:admin1_code":"18.0",
    "gn:admin2_code":"4122305.0",
    "gn:asciiname":"Laranjal",
    "gn:country_code":"BR",
    "gn:dem":906,
    "gn:feature_class":"P",
    "gn:feature_code":"PPLL",
    "gn:name":"Laranjal",
    "gn:population":0,
    "gn:timezone":"America/Sao_Paulo",
    "iso:country":"BR",
    "name:por_x_preferred":[
        "Laranjal"
    ],
    "wof:name":"Laranjal",
    "wof:placetype":"locality"
},
  "geometry": {"coordinates":[-49.8192,-26.0128],"type":"Point"}
}