{
  "type": "Feature",
  "properties": {
    "gn:admin1_code":"18.0",
    "gn:admin2_code":"4122305.0",
    "gn:asciiname":"Laranjal",
    "gn:country_code":"BR",
    "gn:dem":906,
    "gn:feature_class":"P",
    "gn:feature_code":"PPLL",
    "gn:name":"Laranjal",
    "gn:population":0,
    "gn:timezone":"America/Sao_Paulo",
    "iso:country":"BR",
    "name:ceb_x_preferred":[
        "Laranjal"
    ],
    "name:ita_x_preferred":[
        "Laranjal"
    ],
    "name:nld_x_preferred":[
        "Laranjal"
    ],
    "name:nor_x_preferred":[
        "Laranjal"
    ],
    "name:pol_x_preferred":[
        "Laranjal"
    ],
    "name:por_x_preferred":[
        "Laranjal"
    ],
    "name:rus_x_preferred":[
        "\u041b\u0430\u0440\u0430\u043d\u0436\u0430\u043b"
    ],
    "name:swe_x_preferred":[
        "Laranjal"
    ],
    "name:vol_x_preferred":[
        "Laranjal"
    ],
    "wof:name":"Laranjal",
    "wof:placetype":"locality"
},
  "geometry": {"coordinates":[-49.8192,-26.0128],"type":"Point"}
}