{
  "type": "Feature",
  "properties": {
    "gn:admin1_code":"18.0",
    "gn:admin2_code":"4109609.0",
    "gn:asciiname":"Sitio Toca da Onca",
    "gn:country_code":"BR",
    "gn:dem":720,
    "gn:feature_class":"P",
    "gn:feature_code":"PPL",
    "gn:name":"S\u00edtio Toca da On\u00e7a",
    "gn:population":0,
    "gn:timezone":"America/Sao_Paulo",
    "iso:country":"BR",
    "name:por_x_preferred":[
        "S\u00edtio Toca da On\u00e7a"
    ],
    "wof:name":"Sitio Toca da Onca",
    "wof:placetype":"locality"
},
  "geometry": {"coordinates":[-48.9418,-25.85049],"type":"Point"}
}