{
  "type": "Feature",
  "properties": {
    "gn:admin1_code":"13",
    "gn:admin2_code":"2110104.0",
    "gn:asciiname":"Sitio do Meio II",
    "gn:country_code":"BR",
    "gn:dem":80,
    "gn:feature_class":"P",
    "gn:feature_code":"PPL",
    "gn:name":"S\u00edtio do Meio II",
    "gn:population":0,
    "gn:timezone":"America/Fortaleza",
    "iso:country":"BR",
    "wof:name":"Sitio do Meio II",
    "wof:placetype":"locality"
},
  "geometry": {"coordinates":[-43.05111,-3.44556],"type":"Point"}
}