{
  "type": "Feature",
  "properties": {
    "gn:admin1_code":"13",
    "gn:admin2_code":"2101202.0",
    "gn:asciiname":"Madalena",
    "gn:country_code":"BR",
    "gn:dem":24,
    "gn:feature_class":"P",
    "gn:feature_code":"PPL",
    "gn:name":"Madalena",
    "gn:population":0,
    "gn:timezone":"America/Fortaleza",
    "iso:country":"BR",
    "name:bpy_x_preferred":[
        "\u09ae\u09be\u09a1\u09be\u09b2\u09c7\u09a8\u09be"
    ],
    "name:ceb_x_preferred":[
        "Madalena"
    ],
    "name:deu_x_preferred":[
        "Madalena"
    ],
    "name:ell_x_preferred":[
        "\u039c\u03b1\u03bd\u03c4\u03b1\u03bb\u03ad\u03bd\u03b1"
    ],
    "name:fra_x_preferred":[
        "Madalena"
    ],
    "name:glg_x_preferred":[
        "Madalena"
    ],
    "name:ita_x_preferred":[
        "Madalena"
    ],
    "name:kor_x_preferred":[
        "\ub9c8\ub2ec\ub808\ub098"
    ],
    "name:nld_x_preferred":[
        "Madalena"
    ],
    "name:pol_x_preferred":[
        "Madalena"
    ],
    "name:por_x_preferred":[
        "Madalena"
    ],
    "name:rus_x_preferred":[
        "\u041c\u0430\u0434\u0430\u043b\u0435\u043d\u0430"
    ],
    "name:spa_x_preferred":[
        "Madalena"
    ],
    "name:swe_x_preferred":[
        "Madalena"
    ],
    "name:tur_x_preferred":[
        "Madalena"
    ],
    "name:ukr_x_preferred":[
        "\u041c\u0430\u0434\u0430\u043b\u0435\u043d\u0430"
    ],
    "name:vie_x_preferred":[
        "Madalena"
    ],
    "name:vol_x_preferred":[
        "Madalena"
    ],
    "wof:name":"Madalena",
    "wof:placetype":"locality"
},
  "geometry": {"coordinates":[-44.88333,-4.15],"type":"Point"}
}