{
  "type": "Feature",
  "properties": {
    "gn:admin1_code":"13",
    "gn:admin2_code":"2101202.0",
    "gn:asciiname":"Madalena",
    "gn:country_code":"BR",
    "gn:dem":24,
    "gn:feature_class":"P",
    "gn:feature_code":"PPL",
    "gn:name":"Madalena",
    "gn:population":0,
    "gn:timezone":"America/Fortaleza",
    "iso:country":"BR",
    "wof:name":"Madalena",
    "wof:placetype":"locality"
},
  "geometry": {"coordinates":[-44.88333,-4.15],"type":"Point"}
}