{
  "type": "Feature",
  "properties": {
    "gn:admin1_code":"5",
    "gn:admin2_code":"2903003.0",
    "gn:asciiname":"Paramirim",
    "gn:country_code":"BR",
    "gn:dem":1163,
    "gn:feature_class":"P",
    "gn:feature_code":"PPL",
    "gn:name":"Paramirim",
    "gn:population":0,
    "gn:timezone":"America/Bahia",
    "iso:country":"BR",
    "name:bpy_x_preferred":[
        "\u09aa\u09be\u09b0\u09be\u09ae\u09bf\u09b0\u09bf\u09ae"
    ],
    "name:epo_x_preferred":[
        "Paramirim"
    ],
    "name:eus_x_preferred":[
        "Paramirim"
    ],
    "name:fra_x_preferred":[
        "Paramirim"
    ],
    "name:hye_x_preferred":[
        "\u054a\u0561\u0580\u0561\u0574\u056b\u0580\u056b\u0576"
    ],
    "name:ita_x_preferred":[
        "Paramirim"
    ],
    "name:kat_x_preferred":[
        "\u10de\u10d0\u10e0\u10d0\u10db\u10d8\u10e0\u10d8\u10dc\u10d8"
    ],
    "name:kaz_x_preferred":[
        "\u041f\u0430\u0440\u0430\u043c\u0438\u0440\u0438\u043d"
    ],
    "name:mlg_x_preferred":[
        "Paramirim"
    ],
    "name:nld_x_preferred":[
        "Paramirim"
    ],
    "name:nor_x_preferred":[
        "Paramirim"
    ],
    "name:pol_x_preferred":[
        "Paramirim"
    ],
    "name:por_x_preferred":[
        "Paramirim"
    ],
    "name:ron_x_preferred":[
        "Paramirim"
    ],
    "name:rus_x_preferred":[
        "\u041f\u0430\u0440\u0430\u043c\u0438\u0440\u0438\u043d"
    ],
    "name:vie_x_preferred":[
        "Paramirim"
    ],
    "name:vol_x_preferred":[
        "Paramirim"
    ],
    "name:war_x_preferred":[
        "Paramirim"
    ],
    "name:zho_x_preferred":[
        "\u5e15\u62c9\u7c73\u6797"
    ],
    "wof:name":"Paramirim",
    "wof:placetype":"locality"
},
  "geometry": {"coordinates":[-42.21667,-12.01667],"type":"Point"}
}