{
  "type": "Feature",
  "properties": {
    "gn:admin1_code":"18.0",
    "gn:admin2_code":"4113205.0",
    "gn:asciiname":"Sitio Jose H. Pedro",
    "gn:country_code":"BR",
    "gn:dem":918,
    "gn:feature_class":"P",
    "gn:feature_code":"PPL",
    "gn:name":"S\u00edtio Jos\u00e9 H. Pedro",
    "gn:population":0,
    "gn:timezone":"America/Sao_Paulo",
    "iso:country":"BR",
    "name:por_x_preferred":[
        "S\u00edtio Jos\u00e9 H. Pedro"
    ],
    "wof:name":"Sitio Jose H. Pedro",
    "wof:placetype":"locality"
},
  "geometry": {"coordinates":[-49.8006,-25.7226],"type":"Point"}
}