{
  "type": "Feature",
  "properties": {
    "gn:admin1_code":"18.0",
    "gn:admin2_code":"4121802.0",
    "gn:asciiname":"Sitio Joao Waldir",
    "gn:country_code":"BR",
    "gn:dem":563,
    "gn:feature_class":"P",
    "gn:feature_code":"PPL",
    "gn:name":"S\u00edtio Jo\u00e3o Waldir",
    "gn:population":0,
    "gn:timezone":"America/Sao_Paulo",
    "iso:country":"BR",
    "name:por_x_preferred":[
        "S\u00edtio Jo\u00e3o Waldir"
    ],
    "wof:name":"Sitio Joao Waldir",
    "wof:placetype":"locality"
},
  "geometry": {"coordinates":[-49.7709,-23.2839],"type":"Point"}
}