{
  "type": "Feature",
  "properties": {
    "gn:admin1_code":"27",
    "gn:admin2_code":"3510203.0",
    "gn:asciiname":"Abaitinga",
    "gn:country_code":"BR",
    "gn:dem":728,
    "gn:feature_class":"P",
    "gn:feature_code":"PPL",
    "gn:name":"Abaitinga",
    "gn:population":0,
    "gn:timezone":"America/Sao_Paulo",
    "iso:country":"BR",
    "name:por_x_preferred":[
        "Abaitinga"
    ],
    "wof:name":"Abaitinga",
    "wof:placetype":"locality"
},
  "geometry": {"coordinates":[-48.05,-24.03333],"type":"Point"}
}