{
  "type": "Feature",
  "properties": {
    "gn:admin1_code":"18.0",
    "gn:admin2_code":"4124103.0",
    "gn:asciiname":"Sitio Ribeirao Bonito",
    "gn:country_code":"BR",
    "gn:dem":511,
    "gn:feature_class":"P",
    "gn:feature_code":"PPL",
    "gn:name":"S\u00edtio Ribeir\u00e3o Bonito",
    "gn:population":0,
    "gn:timezone":"America/Sao_Paulo",
    "iso:country":"BR",
    "name:por_x_preferred":[
        "S\u00edtio Ribeir\u00e3o Bonito"
    ],
    "wof:name":"Sitio Ribeirao Bonito",
    "wof:placetype":"locality"
},
  "geometry": {"coordinates":[-50.12895,-23.38181],"type":"Point"}
}