{
  "type": "Feature",
  "properties": {
    "gn:admin1_code":"14",
    "gn:admin2_code":"5104609.0",
    "gn:asciiname":"Peixe de Couro",
    "gn:country_code":"BR",
    "gn:dem":143,
    "gn:feature_class":"P",
    "gn:feature_code":"PPL",
    "gn:name":"Peixe de Couro",
    "gn:population":0,
    "gn:timezone":"America/Cuiaba",
    "iso:country":"BR",
    "name:por_x_preferred":[
        "Peixe de Couro"
    ],
    "wof:name":"Peixe de Couro",
    "wof:placetype":"locality"
},
  "geometry": {"coordinates":[-55.33333,-17.36667000000001],"type":"Point"}
}