{
  "type": "Feature",
  "properties": {
    "gn:admin1_code":"4",
    "gn:admin2_code":"1303304.0",
    "gn:asciiname":"Santo Amaro",
    "gn:country_code":"BR",
    "gn:dem":25,
    "gn:feature_class":"P",
    "gn:feature_code":"PPL",
    "gn:name":"Santo Amaro",
    "gn:population":0,
    "gn:timezone":"America/Manaus",
    "iso:country":"BR",
    "wof:name":"Santo Amaro",
    "wof:placetype":"locality"
},
  "geometry": {"coordinates":[-60.22939,-4.94405],"type":"Point"}
}