{
  "type": "Feature",
  "properties": {
    "gn:admin1_code":"15",
    "gn:admin2_code":"3134004.0",
    "gn:asciiname":"Humaita",
    "gn:country_code":"BR",
    "gn:dem":416,
    "gn:feature_class":"P",
    "gn:feature_code":"PPL",
    "gn:name":"Humait\u00e1",
    "gn:population":0,
    "gn:timezone":"America/Sao_Paulo",
    "iso:country":"BR",
    "name:por_x_preferred":[
        "Humait\u00e1"
    ],
    "wof:name":"Humaita",
    "wof:placetype":"locality"
},
  "geometry": {"coordinates":[-41.81667,-16.76667],"type":"Point"}
}