{
  "type": "Feature",
  "properties": {
    "gn:admin1_code":"5",
    "gn:admin2_code":"2931350.0",
    "gn:asciiname":"Cascata",
    "gn:country_code":"BR",
    "gn:dem":18,
    "gn:feature_class":"P",
    "gn:feature_code":"PPL",
    "gn:name":"Cascata",
    "gn:population":0,
    "gn:timezone":"America/Bahia",
    "iso:country":"BR",
    "name:fra_x_preferred":[
        "Cascata"
    ],
    "name:por_x_preferred":[
        "Cascata"
    ],
    "wof:name":"Cascata",
    "wof:placetype":"locality"
},
  "geometry": {"coordinates":[-39.61667,-17.51667],"type":"Point"}
}