{
  "type": "Feature",
  "properties": {
    "gn:admin1_code":"17",
    "gn:admin2_code":"2503704.0",
    "gn:asciiname":"Marias Pretas",
    "gn:country_code":"BR",
    "gn:dem":319,
    "gn:feature_class":"P",
    "gn:feature_code":"PPL",
    "gn:name":"Marias Pretas",
    "gn:population":0,
    "gn:timezone":"America/Fortaleza",
    "iso:country":"BR",
    "wof:name":"Marias Pretas",
    "wof:placetype":"locality"
},
  "geometry": {"coordinates":[-38.56667,-6.93333],"type":"Point"}
}