{
  "type": "Feature",
  "properties": {
    "gn:admin1_code":"16",
    "gn:admin2_code":"1506401.0",
    "gn:asciiname":"Sao Luis",
    "gn:country_code":"BR",
    "gn:dem":4,
    "gn:feature_class":"P",
    "gn:feature_code":"PPL",
    "gn:name":"S\u00e3o Lu\u00eds",
    "gn:population":0,
    "gn:timezone":"America/Belem",
    "iso:country":"BR",
    "wof:name":"Sao Luis",
    "wof:placetype":"locality"
},
  "geometry": {"coordinates":[-49.31667,-0.68333],"type":"Point"}
}