{
  "type": "Feature",
  "properties": {
    "gn:admin1_code":"26",
    "gn:admin2_code":"4207601.0",
    "gn:asciiname":"Barra do Pinheiro",
    "gn:country_code":"BR",
    "gn:dem":550,
    "gn:feature_class":"P",
    "gn:feature_code":"PPL",
    "gn:name":"Barra do Pinheiro",
    "gn:population":0,
    "gn:timezone":"America/Sao_Paulo",
    "iso:country":"BR",
    "wof:name":"Barra do Pinheiro",
    "wof:placetype":"locality"
},
  "geometry": {"coordinates":[-51.75,-27.33333],"type":"Point"}
}