{
  "type": "Feature",
  "properties": {
    "gn:admin1_code":"22",
    "gn:admin2_code":"2404606.0",
    "gn:asciiname":"Samambaia",
    "gn:country_code":"BR",
    "gn:dem":111,
    "gn:feature_class":"P",
    "gn:feature_code":"PPL",
    "gn:name":"Samambaia",
    "gn:population":0,
    "gn:timezone":"America/Fortaleza",
    "iso:country":"BR",
    "wof:name":"Samambaia",
    "wof:placetype":"locality"
},
  "geometry": {"coordinates":[-35.65,-5.73333],"type":"Point"}
}