{
  "type": "Feature",
  "properties": {
    "gn:admin1_code":"27",
    "gn:admin2_code":"3510401.0",
    "gn:asciiname":"Bairro Nossa Senhora de Fatima",
    "gn:country_code":"BR",
    "gn:dem":510,
    "gn:feature_class":"P",
    "gn:feature_code":"PPL",
    "gn:name":"Bairro Nossa Senhora de F\u00e1tima",
    "gn:population":0,
    "gn:timezone":"America/Sao_Paulo",
    "iso:country":"BR",
    "name:por_x_preferred":[
        "Bairro Nossa Senhora de F\u00e1tima"
    ],
    "wof:name":"Bairro Nossa Senhora de Fatima",
    "wof:placetype":"locality"
},
  "geometry": {"coordinates":[-47.50393,-23.0086],"type":"Point"}
}