{
  "type": "Feature",
  "properties": {
    "gn:admin1_code":"18",
    "gn:admin2_code":"4109401.0",
    "gn:asciiname":"Vitoria",
    "gn:country_code":"BR",
    "gn:dem":1169,
    "gn:feature_class":"P",
    "gn:feature_code":"PPL",
    "gn:name":"Vit\u00f3ria",
    "gn:population":0,
    "gn:timezone":"America/Sao_Paulo",
    "iso:country":"BR",
    "wof:name":"Vitoria",
    "wof:placetype":"locality"
},
  "geometry": {"coordinates":[-51.43333,-25.51667],"type":"Point"}
}