{
  "type": "Feature",
  "properties": {
    "gn:admin1_code":"26",
    "gn:admin2_code":"4211900.0",
    "gn:asciiname":"Guarda do Embau",
    "gn:country_code":"BR",
    "gn:dem":5,
    "gn:feature_class":"P",
    "gn:feature_code":"PPL",
    "gn:name":"Guarda do Emba\u00fa",
    "gn:population":0,
    "gn:timezone":"America/Sao_Paulo",
    "iso:country":"BR",
    "name:und_x_variant":[
        "Guarda do Emba\u00fa"
    ],
    "wof:name":"Guarda do Embau",
    "wof:placetype":"locality"
},
  "geometry": {"coordinates":[-48.59111,-27.9025],"type":"Point"}
}