{
  "type": "Feature",
  "properties": {
    "gn:admin1_code":"20",
    "gn:admin2_code":"2208106.0",
    "gn:asciiname":"Sao Bento",
    "gn:country_code":"BR",
    "gn:dem":312,
    "gn:feature_class":"P",
    "gn:feature_code":"PPL",
    "gn:name":"S\u00e3o Bento",
    "gn:population":0,
    "gn:timezone":"America/Fortaleza",
    "iso:country":"BR",
    "wof:name":"Sao Bento",
    "wof:placetype":"locality"
},
  "geometry": {"coordinates":[-41.35,-6.41667],"type":"Point"}
}