{
  "type": "Feature",
  "properties": {
    "gn:admin1_code":"18.0",
    "gn:admin2_code":"4113205.0",
    "gn:asciiname":"Sitio Joao M. do A. Alves",
    "gn:country_code":"BR",
    "gn:dem":821,
    "gn:feature_class":"P",
    "gn:feature_code":"PPL",
    "gn:name":"S\u00edtio Jo\u00e3o M. do A. Alves",
    "gn:population":0,
    "gn:timezone":"America/Sao_Paulo",
    "iso:country":"BR",
    "name:por_x_preferred":[
        "S\u00edtio Jo\u00e3o M. do A. Alves"
    ],
    "wof:name":"Sitio Joao M. do A. Alves",
    "wof:placetype":"locality"
},
  "geometry": {"coordinates":[-49.6078,-25.7928],"type":"Point"}
}