{
  "type": "Feature",
  "properties": {
    "gn:admin1_code":"18.0",
    "gn:admin2_code":"4116208.0",
    "gn:asciiname":"Sitio Zacarias Gomes",
    "gn:country_code":"BR",
    "gn:dem":35,
    "gn:feature_class":"P",
    "gn:feature_code":"PPL",
    "gn:name":"S\u00edtio Zacarias Gomes",
    "gn:population":0,
    "gn:timezone":"America/Sao_Paulo",
    "iso:country":"BR",
    "name:por_x_preferred":[
        "S\u00edtio Zacarias Gomes"
    ],
    "wof:name":"Sitio Zacarias Gomes",
    "wof:placetype":"locality"
},
  "geometry": {"coordinates":[-48.8567,-25.512],"type":"Point"}
}