{
  "type": "Feature",
  "properties": {
    "gn:admin1_code":"05",
    "gn:admin2_code":"2927606.0",
    "gn:asciiname":"Panasco",
    "gn:country_code":"BR",
    "gn:dem":307,
    "gn:feature_class":"P",
    "gn:feature_code":"PPL",
    "gn:name":"Panasco",
    "gn:population":0,
    "gn:timezone":"America/Bahia",
    "iso:country":"BR",
    "wof:name":"Panasco",
    "wof:placetype":"locality"
},
  "geometry": {"coordinates":[-38.05,-9.86667],"type":"Point"}
}