{
  "type": "Feature",
  "properties": {
    "gn:admin1_code":"18.0",
    "gn:admin2_code":"4111803.0",
    "gn:asciiname":"Sitio Lorena Gomes",
    "gn:country_code":"BR",
    "gn:dem":453,
    "gn:feature_class":"P",
    "gn:feature_code":"PPL",
    "gn:name":"S\u00edtio Lorena Gomes",
    "gn:population":0,
    "gn:timezone":"America/Sao_Paulo",
    "iso:country":"BR",
    "name:por_x_preferred":[
        "S\u00edtio Lorena Gomes"
    ],
    "wof:name":"Sitio Lorena Gomes",
    "wof:placetype":"locality"
},
  "geometry": {"coordinates":[-49.92992,-23.15641],"type":"Point"}
}