{
  "type": "Feature",
  "properties": {
    "gn:admin1_code":"18",
    "gn:admin2_code":"4125605.0",
    "gn:asciiname":"Saldanha",
    "gn:country_code":"BR",
    "gn:dem":811,
    "gn:feature_class":"P",
    "gn:feature_code":"PPL",
    "gn:name":"Saldanha",
    "gn:population":0,
    "gn:timezone":"America/Sao_Paulo",
    "iso:country":"BR",
    "name:ceb_x_preferred":[
        "Saldanha"
    ],
    "name:deu_x_preferred":[
        "Saldanha"
    ],
    "name:fin_x_preferred":[
        "Saldanha"
    ],
    "name:fra_x_preferred":[
        "Saldanha"
    ],
    "name:ita_x_preferred":[
        "Saldanha"
    ],
    "name:mlg_x_preferred":[
        "Saldanha"
    ],
    "name:por_x_preferred":[
        "Saldanha"
    ],
    "name:rus_x_preferred":[
        "\u0421\u0430\u043b\u0434\u0430\u043d\u044c\u044f"
    ],
    "name:ukr_x_preferred":[
        "\u0421\u0430\u043b\u0434\u0430\u043d\u044c\u044f"
    ],
    "wof:name":"Saldanha",
    "wof:placetype":"locality"
},
  "geometry": {"coordinates":[-50.5134,-25.73487],"type":"Point"}
}