{
  "type": "Feature",
  "properties": {
    "gn:admin1_code":"18",
    "gn:admin2_code":"4125605.0",
    "gn:asciiname":"Saldanha",
    "gn:country_code":"BR",
    "gn:dem":811,
    "gn:feature_class":"P",
    "gn:feature_code":"PPL",
    "gn:name":"Saldanha",
    "gn:population":0,
    "gn:timezone":"America/Sao_Paulo",
    "iso:country":"BR",
    "name:por_x_preferred":[
        "Saldanha"
    ],
    "wof:name":"Saldanha",
    "wof:placetype":"locality"
},
  "geometry": {"coordinates":[-50.5134,-25.73487],"type":"Point"}
}