{
  "type": "Feature",
  "properties": {
    "gn:admin1_code":"18",
    "gn:admin2_code":"4125605.0",
    "gn:asciiname":"Saldanha",
    "gn:country_code":"BR",
    "gn:dem":811,
    "gn:feature_class":"P",
    "gn:feature_code":"PPL",
    "gn:name":"Saldanha",
    "gn:population":0,
    "gn:timezone":"America/Sao_Paulo",
    "iso:country":"BR",
    "name:ben_x_preferred":[
        "\u09b8\u09be\u09b2\u09a6\u09be\u09a8\u09b9\u09be"
    ],
    "name:ceb_x_preferred":[
        "Saldanha"
    ],
    "name:deu_x_preferred":[
        "Saldanha"
    ],
    "name:ell_x_preferred":[
        "\u03a3\u03b1\u03bb\u03bd\u03c4\u03ac\u03bd\u03b9\u03b1"
    ],
    "name:fas_x_preferred":[
        "\u0633\u0627\u0644\u062f\u0627\u0646\u0647\u0627"
    ],
    "name:fin_x_preferred":[
        "Saldanha"
    ],
    "name:fra_x_preferred":[
        "Saldanha"
    ],
    "name:hin_x_preferred":[
        "\u0938\u0932\u0926\u093e\u0928\u093e"
    ],
    "name:hun_x_preferred":[
        "Saldanha"
    ],
    "name:ind_x_preferred":[
        "Saldanha"
    ],
    "name:ita_x_preferred":[
        "Saldanha"
    ],
    "name:kor_x_preferred":[
        "\uc0b4\ub2e4\ub0d0"
    ],
    "name:mlg_x_preferred":[
        "Saldanha"
    ],
    "name:pol_x_preferred":[
        "Saldanha"
    ],
    "name:por_x_preferred":[
        "Saldanha"
    ],
    "name:rus_x_preferred":[
        "\u0421\u0430\u043b\u0434\u0430\u043d\u044c\u044f"
    ],
    "name:spa_x_preferred":[
        "Saldanha"
    ],
    "name:swe_x_preferred":[
        "Saldanha"
    ],
    "name:tur_x_preferred":[
        "Saldanha"
    ],
    "name:ukr_x_preferred":[
        "\u0421\u0430\u043b\u0434\u0430\u043d\u044c\u044f"
    ],
    "name:urd_x_preferred":[
        "\u0633\u06cc\u0644\u0688\u0627\u0646\u06c1\u0627"
    ],
    "name:vie_x_preferred":[
        "Saldanha"
    ],
    "name:zho_cn_x_preferred":[
        "\u8428\u5c14\u8fbe\u5c3c\u4e9a"
    ],
    "name:zho_tw_x_preferred":[
        "\u85a9\u723e\u9054\u5c3c\u4e9e"
    ],
    "wof:name":"Saldanha",
    "wof:placetype":"locality"
},
  "geometry": {"coordinates":[-50.5134,-25.73487],"type":"Point"}
}