{
  "type": "Feature",
  "properties": {
    "gn:admin1_code":"4",
    "gn:admin2_code":"1303809.0",
    "gn:asciiname":"Uira Paco",
    "gn:country_code":"BR",
    "gn:dem":112,
    "gn:feature_class":"P",
    "gn:feature_code":"PPL",
    "gn:name":"Uira Pa\u00e7o",
    "gn:population":0,
    "gn:timezone":"America/Manaus",
    "iso:country":"BR",
    "wof:name":"Uira Paco",
    "wof:placetype":"locality"
},
  "geometry": {"coordinates":[-69.53333000000001,0.18333],"type":"Point"}
}