{
  "type": "Feature",
  "properties": {
    "gn:admin1_code":"20",
    "gn:admin2_code":"2202109.0",
    "gn:asciiname":"Gangorra (1)",
    "gn:country_code":"BR",
    "gn:dem":222,
    "gn:feature_class":"P",
    "gn:feature_code":"PPL",
    "gn:name":"Gangorra (1)",
    "gn:population":0,
    "gn:timezone":"America/Fortaleza",
    "iso:country":"BR",
    "wof:name":"Gangorra (1)",
    "wof:placetype":"locality"
},
  "geometry": {"coordinates":[-41.76667,-7.66667],"type":"Point"}
}