{
  "type": "Feature",
  "properties": {
    "gn:admin1_code":"28",
    "gn:admin2_code":"2802403.0",
    "gn:asciiname":"Tanque de Pedra",
    "gn:cc2":"BR",
    "gn:country_code":"BR",
    "gn:dem":121,
    "gn:feature_class":"P",
    "gn:feature_code":"PPL",
    "gn:name":"Tanque de Pedra",
    "gn:population":0,
    "gn:timezone":"America/Maceio",
    "iso:country":"BR",
    "name:und_x_variant":[
        "Tanque da Pedra",
        "Tanque de Pedra"
    ],
    "wof:name":"Tanque de Pedra",
    "wof:placetype":"locality"
},
  "geometry": {"coordinates":[-37.15,-9.95],"type":"Point"}
}