{
  "type": "Feature",
  "properties": {
    "gn:admin1_code":"31",
    "gn:admin2_code":"1710508.0",
    "gn:asciiname":"Conceicao",
    "gn:country_code":"BR",
    "gn:dem":319,
    "gn:feature_class":"P",
    "gn:feature_code":"PPL",
    "gn:name":"Concei\u00e7\u00e3o",
    "gn:population":0,
    "gn:timezone":"America/Araguaina",
    "iso:country":"BR",
    "wof:name":"Conceicao",
    "wof:placetype":"locality"
},
  "geometry": {"coordinates":[-47.34972,-8.72056],"type":"Point"}
}