{
  "type": "Feature",
  "properties": {
    "gn:admin1_code":"15",
    "gn:admin2_code":"3153806.0",
    "gn:asciiname":"Buraco do Bicho",
    "gn:country_code":"BR",
    "gn:dem":966,
    "gn:feature_class":"P",
    "gn:feature_code":"PPL",
    "gn:name":"Buraco do Bicho",
    "gn:population":0,
    "gn:timezone":"America/Sao_Paulo",
    "iso:country":"BR",
    "name:por_x_preferred":[
        "Buraco do Bicho"
    ],
    "wof:name":"Buraco do Bicho",
    "wof:placetype":"locality"
},
  "geometry": {"coordinates":[-43.91667,-20.66667],"type":"Point"}
}