{
  "type": "Feature",
  "properties": {
    "gn:admin1_code":"16",
    "gn:admin2_code":"1507201.0",
    "gn:asciiname":"Cumaru",
    "gn:country_code":"BR",
    "gn:dem":25,
    "gn:feature_class":"P",
    "gn:feature_code":"PPL",
    "gn:name":"Cumaru",
    "gn:population":0,
    "gn:timezone":"America/Belem",
    "iso:country":"BR",
    "wof:name":"Cumaru",
    "wof:placetype":"locality"
},
  "geometry": {"coordinates":[-47.81135,-1.72455],"type":"Point"}
}