{
  "type": "Feature",
  "properties": {
    "gn:admin1_code":"16",
    "gn:admin2_code":"1507201.0",
    "gn:asciiname":"Cumaru",
    "gn:country_code":"BR",
    "gn:dem":25,
    "gn:feature_class":"P",
    "gn:feature_code":"PPL",
    "gn:name":"Cumaru",
    "gn:population":0,
    "gn:timezone":"America/Belem",
    "iso:country":"BR",
    "name:bpy_x_preferred":[
        "\u0995\u09c1\u09ae\u09be\u09b0\u09c1"
    ],
    "name:eus_x_preferred":[
        "Cumaru"
    ],
    "name:fra_x_preferred":[
        "Cumaru"
    ],
    "name:ita_x_preferred":[
        "Cumaru"
    ],
    "name:kat_x_preferred":[
        "\u10d9\u10e3\u10db\u10d0\u10e0\u10e3"
    ],
    "name:nld_x_preferred":[
        "Cumaru"
    ],
    "name:nor_x_preferred":[
        "Cumaru"
    ],
    "name:por_x_preferred":[
        "Cumaru"
    ],
    "name:ron_x_preferred":[
        "Cumaru"
    ],
    "name:rus_x_preferred":[
        "\u041a\u0443\u043c\u0430\u0440\u0443"
    ],
    "name:vie_x_preferred":[
        "Cumaru"
    ],
    "name:vol_x_preferred":[
        "Cumaru"
    ],
    "name:war_x_preferred":[
        "Cumaru"
    ],
    "name:zho_x_preferred":[
        "\u5e93\u9a6c\u9c81"
    ],
    "wof:name":"Cumaru",
    "wof:placetype":"locality"
},
  "geometry": {"coordinates":[-47.81135,-1.72455],"type":"Point"}
}