{
  "type": "Feature",
  "properties": {
    "gn:admin1_code":"20",
    "gn:admin2_code":"2205102.0",
    "gn:asciiname":"Mosquito",
    "gn:country_code":"BR",
    "gn:dem":255,
    "gn:feature_class":"P",
    "gn:feature_code":"PPL",
    "gn:name":"Mosquito",
    "gn:population":0,
    "gn:timezone":"America/Fortaleza",
    "iso:country":"BR",
    "wof:name":"Mosquito",
    "wof:placetype":"locality"
},
  "geometry": {"coordinates":[-43.11667,-7.58333],"type":"Point"}
}