{
  "type": "Feature",
  "properties": {
    "gn:admin1_code":"5",
    "gn:admin2_code":"2907400.0",
    "gn:asciiname":"Tiririca",
    "gn:country_code":"BR",
    "gn:dem":672,
    "gn:feature_class":"P",
    "gn:feature_code":"PPL",
    "gn:name":"Tiririca",
    "gn:population":0,
    "gn:timezone":"America/Bahia",
    "iso:country":"BR",
    "name:eml_x_preferred":[
        "Tiririca"
    ],
    "name:epo_x_preferred":[
        "Tiririca"
    ],
    "name:fra_x_preferred":[
        "Tiririca"
    ],
    "name:glg_x_preferred":[
        "Tiririca"
    ],
    "name:ita_x_preferred":[
        "Tiririca"
    ],
    "name:lat_x_preferred":[
        "Tiririca"
    ],
    "name:lmo_x_preferred":[
        "Tiririca"
    ],
    "name:por_x_preferred":[
        "Tiririca"
    ],
    "name:spa_x_preferred":[
        "Tiririca"
    ],
    "wof:name":"Tiririca",
    "wof:placetype":"locality"
},
  "geometry": {"coordinates":[-44.85,-12.33333],"type":"Point"}
}