{
  "type": "Feature",
  "properties": {
    "gn:admin1_code":"11",
    "gn:admin2_code":"5005400.0",
    "gn:asciiname":"Leonel Barbosa",
    "gn:cc2":"BR",
    "gn:country_code":"BR",
    "gn:dem":547,
    "gn:feature_class":"P",
    "gn:feature_code":"PPL",
    "gn:name":"Leonel Barbosa",
    "gn:population":0,
    "gn:timezone":"America/Campo_Grande",
    "iso:country":"BR",
    "name:und_x_variant":[
        "A. Barbosa",
        "Leonel Barbosa"
    ],
    "wof:name":"Leonel Barbosa",
    "wof:placetype":"locality"
},
  "geometry": {"coordinates":[-55.53333000000001,-21.63333],"type":"Point"}
}