{
  "type": "Feature",
  "properties": {
    "gn:admin1_code":"17",
    "gn:admin2_code":"2508000.0",
    "gn:asciiname":"Catole",
    "gn:country_code":"BR",
    "gn:dem":674,
    "gn:feature_class":"P",
    "gn:feature_code":"PPL",
    "gn:name":"Catol\u00e9",
    "gn:population":0,
    "gn:timezone":"America/Fortaleza",
    "iso:country":"BR",
    "wof:name":"Catole",
    "wof:placetype":"locality"
},
  "geometry": {"coordinates":[-37.83333,-7.58333],"type":"Point"}
}