{
  "type": "Feature",
  "properties": {
    "gn:admin1_code":"18.0",
    "gn:admin2_code":"4126603.0",
    "gn:asciiname":"Tres Barras",
    "gn:country_code":"BR",
    "gn:dem":621,
    "gn:feature_class":"P",
    "gn:feature_code":"PPLL",
    "gn:name":"Tr\u00eas Barras",
    "gn:population":0,
    "gn:timezone":"America/Sao_Paulo",
    "iso:country":"BR",
    "name:por_x_preferred":[
        "Tr\u00eas Barras"
    ],
    "wof:name":"Tres Barras",
    "wof:placetype":"locality"
},
  "geometry": {"coordinates":[-49.79751,-23.58004],"type":"Point"}
}