{
  "type": "Feature",
  "properties": {
    "gn:admin1_code":"20",
    "gn:admin2_code":"2205300.0",
    "gn:asciiname":"Cidreira",
    "gn:country_code":"BR",
    "gn:dem":249,
    "gn:feature_class":"P",
    "gn:feature_code":"PPL",
    "gn:name":"Cidreira",
    "gn:population":0,
    "gn:timezone":"America/Fortaleza",
    "iso:country":"BR",
    "name:bpy_x_preferred":[
        "\u09b8\u09bf\u09a1\u09cd\u09b0\u09c7\u0987\u09b0\u09be"
    ],
    "name:ceb_x_preferred":[
        "Cidreira"
    ],
    "name:epo_x_preferred":[
        "Cidreira"
    ],
    "name:fra_x_preferred":[
        "Cidreira"
    ],
    "name:ita_x_preferred":[
        "Cidreira"
    ],
    "name:kaz_x_preferred":[
        "\u0421\u0438\u0434\u0440\u0435\u0439\u0440\u0430"
    ],
    "name:mlg_x_preferred":[
        "Cidreira"
    ],
    "name:nld_x_preferred":[
        "Cidreira"
    ],
    "name:nor_x_preferred":[
        "Cidreira"
    ],
    "name:pol_x_preferred":[
        "Cidreira"
    ],
    "name:ron_x_preferred":[
        "Cidreira"
    ],
    "name:rus_x_preferred":[
        "\u0421\u0438\u0434\u0440\u0435\u0439\u0440\u0430"
    ],
    "name:spa_x_preferred":[
        "Cidreira"
    ],
    "name:swe_x_preferred":[
        "Cidreira"
    ],
    "name:vie_x_preferred":[
        "Cidreira"
    ],
    "name:vol_x_preferred":[
        "Cidreira"
    ],
    "name:war_x_preferred":[
        "Cidreira"
    ],
    "name:zho_x_preferred":[
        "\u897f\u5fb7\u96f7\u62c9"
    ],
    "wof:name":"Cidreira",
    "wof:placetype":"locality"
},
  "geometry": {"coordinates":[-43.28333,-7.35],"type":"Point"}
}