{
  "type": "Feature",
  "properties": {
    "gn:admin1_code":"20",
    "gn:admin2_code":"2205300.0",
    "gn:asciiname":"Cidreira",
    "gn:country_code":"BR",
    "gn:dem":249,
    "gn:feature_class":"P",
    "gn:feature_code":"PPL",
    "gn:name":"Cidreira",
    "gn:population":0,
    "gn:timezone":"America/Fortaleza",
    "iso:country":"BR",
    "wof:name":"Cidreira",
    "wof:placetype":"locality"
},
  "geometry": {"coordinates":[-43.28333,-7.35],"type":"Point"}
}