{
  "type": "Feature",
  "properties": {
    "gn:admin1_code":"18.0",
    "gn:admin2_code":"4124103.0",
    "gn:asciiname":"Sitio Alorovano A. Ferreira",
    "gn:country_code":"BR",
    "gn:dem":446,
    "gn:feature_class":"P",
    "gn:feature_code":"PPL",
    "gn:name":"S\u00edtio Alorovano A. Ferreira",
    "gn:population":0,
    "gn:timezone":"America/Sao_Paulo",
    "iso:country":"BR",
    "name:por_x_preferred":[
        "S\u00edtio Alorovano A. Ferreira"
    ],
    "wof:name":"Sitio Alorovano A. Ferreira",
    "wof:placetype":"locality"
},
  "geometry": {"coordinates":[-50.15752,-23.39233],"type":"Point"}
}