{
  "type": "Feature",
  "properties": {
    "gn:admin1_code":"06",
    "gn:admin2_code":"2304103.0",
    "gn:asciiname":"Gado Bravo",
    "gn:country_code":"BR",
    "gn:dem":311,
    "gn:feature_class":"P",
    "gn:feature_code":"PPL",
    "gn:name":"Gado Bravo",
    "gn:population":0,
    "gn:timezone":"America/Fortaleza",
    "iso:country":"BR",
    "wof:name":"Gado Bravo",
    "wof:placetype":"locality"
},
  "geometry": {"coordinates":[-40.56667,-5.28333],"type":"Point"}
}