{
  "type": "Feature",
  "properties": {
    "gn:admin1_code":"06",
    "gn:admin2_code":"2304103.0",
    "gn:asciiname":"Gado Bravo",
    "gn:country_code":"BR",
    "gn:dem":311,
    "gn:feature_class":"P",
    "gn:feature_code":"PPL",
    "gn:name":"Gado Bravo",
    "gn:population":0,
    "gn:timezone":"America/Fortaleza",
    "iso:country":"BR",
    "name:bpy_x_preferred":[
        "\u0997\u09be\u09a1\u09cb \u09ac\u09cd\u09b0\u09be\u09ad\u09cb"
    ],
    "name:ceb_x_preferred":[
        "Gado Bravo"
    ],
    "name:eus_x_preferred":[
        "Gado Bravo"
    ],
    "name:fra_x_preferred":[
        "Gado Bravo"
    ],
    "name:hye_x_preferred":[
        "\u0533\u0561\u0564\u0578\u0582 \u0532\u0580\u0561\u057e\u0578\u0582"
    ],
    "name:ita_x_preferred":[
        "Gado Bravo"
    ],
    "name:kat_x_preferred":[
        "\u10d2\u10d0\u10d3\u10e3-\u10d1\u10e0\u10d0\u10d5\u10e3"
    ],
    "name:kaz_x_preferred":[
        "\u0413\u0430\u0434\u0443-\u0411\u0440\u0430\u0432\u0443"
    ],
    "name:nld_x_preferred":[
        "Gado Bravo"
    ],
    "name:nor_x_preferred":[
        "Gado Bravo"
    ],
    "name:por_x_preferred":[
        "Gado Bravo"
    ],
    "name:ron_x_preferred":[
        "Gado Bravo"
    ],
    "name:rus_x_preferred":[
        "\u0413\u0430\u0434\u0443-\u0411\u0440\u0430\u0432\u0443"
    ],
    "name:swe_x_preferred":[
        "Gado Bravo"
    ],
    "name:vie_x_preferred":[
        "Gado Bravo"
    ],
    "name:vol_x_preferred":[
        "Gado Bravo"
    ],
    "name:war_x_preferred":[
        "Gado Bravo"
    ],
    "name:zho_x_preferred":[
        "\u52a0\u675c\u5e03\u62c9\u6b66"
    ],
    "wof:name":"Gado Bravo",
    "wof:placetype":"locality"
},
  "geometry": {"coordinates":[-40.56667,-5.28333],"type":"Point"}
}