{
  "type": "Feature",
  "properties": {
    "gn:admin1_code":"18.0",
    "gn:admin2_code":"4114302.0",
    "gn:asciiname":"Sitio Custodio P. Batista",
    "gn:country_code":"BR",
    "gn:dem":921,
    "gn:feature_class":"P",
    "gn:feature_code":"PPL",
    "gn:name":"S\u00edtio Cust\u00f3dio P. Batista",
    "gn:population":0,
    "gn:timezone":"America/Sao_Paulo",
    "iso:country":"BR",
    "name:por_x_preferred":[
        "S\u00edtio Cust\u00f3dio P. Batista"
    ],
    "wof:name":"Sitio Custodio P. Batista",
    "wof:placetype":"locality"
},
  "geometry": {"coordinates":[-49.2683,-25.8994],"type":"Point"}
}