{
  "type": "Feature",
  "properties": {
    "gn:admin1_code":"13.0",
    "gn:admin2_code":"2107258.0",
    "gn:asciiname":"Canto dos Currals",
    "gn:country_code":"BR",
    "gn:dem":397,
    "gn:feature_class":"P",
    "gn:feature_code":"PPL",
    "gn:name":"Canto dos Currals",
    "gn:population":0,
    "gn:timezone":"America/Fortaleza",
    "iso:country":"BR",
    "wof:name":"Canto dos Currals",
    "wof:placetype":"locality"
},
  "geometry": {"coordinates":[-46.25504,-7.12194],"type":"Point"}
}