{
  "type": "Feature",
  "properties": {
    "gn:admin1_code":"20",
    "gn:admin2_code":"2202026.0",
    "gn:asciiname":"Carire",
    "gn:country_code":"BR",
    "gn:dem":384,
    "gn:feature_class":"P",
    "gn:feature_code":"PPL",
    "gn:name":"Carir\u00e9",
    "gn:population":0,
    "gn:timezone":"America/Fortaleza",
    "iso:country":"BR",
    "wof:name":"Carire",
    "wof:placetype":"locality"
},
  "geometry": {"coordinates":[-41.23333,-5.16667],"type":"Point"}
}