{
  "type": "Feature",
  "properties": {
    "gn:admin1_code":"20",
    "gn:admin2_code":"2202604.0",
    "gn:asciiname":"Malhada do Meio",
    "gn:country_code":"BR",
    "gn:dem":249,
    "gn:feature_class":"P",
    "gn:feature_code":"PPL",
    "gn:name":"Malhada do Meio",
    "gn:population":0,
    "gn:timezone":"America/Fortaleza",
    "iso:country":"BR",
    "wof:name":"Malhada do Meio",
    "wof:placetype":"locality"
},
  "geometry": {"coordinates":[-41.48333,-5.45],"type":"Point"}
}