{
  "type": "Feature",
  "properties": {
    "gn:admin1_code":"26",
    "gn:admin2_code":"4218756.0",
    "gn:asciiname":"Ipora",
    "gn:cc2":"BR",
    "gn:country_code":"BR",
    "gn:dem":505,
    "gn:feature_class":"P",
    "gn:feature_code":"PPL",
    "gn:name":"Ipor\u00e3",
    "gn:population":0,
    "gn:timezone":"America/Sao_Paulo",
    "iso:country":"BR",
    "name:und_x_variant":[
        "Ipur\u00e1",
        "Ipor\u00e3"
    ],
    "wof:name":"Ipora",
    "wof:placetype":"locality"
},
  "geometry": {"coordinates":[-53.58333,-26.98333],"type":"Point"}
}