{
  "type": "Feature",
  "properties": {
    "gn:admin1_code":"4",
    "gn:admin2_code":"1302702.0",
    "gn:asciiname":"Pilao",
    "gn:country_code":"BR",
    "gn:dem":32,
    "gn:feature_class":"P",
    "gn:feature_code":"PPL",
    "gn:name":"Pil\u00e3o",
    "gn:population":0,
    "gn:timezone":"America/Manaus",
    "iso:country":"BR",
    "wof:name":"Pilao",
    "wof:placetype":"locality"
},
  "geometry": {"coordinates":[-60.94,-5.72333],"type":"Point"}
}