{
  "type": "Feature",
  "properties": {
    "gn:admin1_code":"13",
    "gn:admin2_code":"2103208.0",
    "gn:asciiname":"Cavaca",
    "gn:country_code":"BR",
    "gn:dem":43,
    "gn:feature_class":"P",
    "gn:feature_code":"PPL",
    "gn:name":"Cavaca",
    "gn:population":0,
    "gn:timezone":"America/Fortaleza",
    "iso:country":"BR",
    "wof:name":"Cavaca",
    "wof:placetype":"locality"
},
  "geometry": {"coordinates":[-43.41972,-3.82694],"type":"Point"}
}