{
  "type": "Feature",
  "properties": {
    "gn:admin1_code":"18.0",
    "gn:admin2_code":"4100202.0",
    "gn:asciiname":"Bairro Ocorrencia",
    "gn:country_code":"BR",
    "gn:dem":109,
    "gn:feature_class":"P",
    "gn:feature_code":"PPLL",
    "gn:name":"Bairro Ocorr\u00eancia",
    "gn:population":0,
    "gn:timezone":"America/Sao_Paulo",
    "iso:country":"BR",
    "name:por_x_preferred":[
        "Bairro Ocorr\u00eancia"
    ],
    "wof:name":"Bairro Ocorrencia",
    "wof:placetype":"locality"
},
  "geometry": {"coordinates":[-48.60992,-24.67113],"type":"Point"}
}