{
  "type": "Feature",
  "properties": {
    "gn:admin1_code":"18.0",
    "gn:admin2_code":"4124103.0",
    "gn:asciiname":"Sitio Waldemar Gobati",
    "gn:country_code":"BR",
    "gn:dem":582,
    "gn:feature_class":"P",
    "gn:feature_code":"PPL",
    "gn:name":"S\u00edtio Waldemar Gobati",
    "gn:population":0,
    "gn:timezone":"America/Sao_Paulo",
    "iso:country":"BR",
    "name:por_x_preferred":[
        "S\u00edtio Waldemar Gobati"
    ],
    "wof:name":"Sitio Waldemar Gobati",
    "wof:placetype":"locality"
},
  "geometry": {"coordinates":[-50.13800000000001,-23.2421],"type":"Point"}
}