{
  "type": "Feature",
  "properties": {
    "gn:admin1_code":"27.0",
    "gn:admin2_code":"3522158.0",
    "gn:asciiname":"Bairro do Lajeado",
    "gn:country_code":"BR",
    "gn:dem":252,
    "gn:feature_class":"P",
    "gn:feature_code":"PPLL",
    "gn:name":"Bairro do Lajeado",
    "gn:population":0,
    "gn:timezone":"America/Sao_Paulo",
    "iso:country":"BR",
    "name:por_x_preferred":[
        "Bairro do Lajeado"
    ],
    "wof:name":"Bairro do Lajeado",
    "wof:placetype":"locality"
},
  "geometry": {"coordinates":[-48.87116,-24.59772],"type":"Point"}
}