{
  "type": "Feature",
  "properties": {
    "gn:admin1_code":"18",
    "gn:admin2_code":"4119103.0",
    "gn:asciiname":"Sitio Gumercino Calizario",
    "gn:country_code":"BR",
    "gn:dem":856,
    "gn:feature_class":"P",
    "gn:feature_code":"PPL",
    "gn:name":"S\u00edtio Gumercino Caliz\u00e1rio",
    "gn:population":0,
    "gn:timezone":"America/Sao_Paulo",
    "iso:country":"BR",
    "name:por_x_preferred":[
        "S\u00edtio Gumercino Caliz\u00e1rio"
    ],
    "wof:name":"Sitio Gumercino Calizario",
    "wof:placetype":"locality"
},
  "geometry": {"coordinates":[-49.50497,-26.0155],"type":"Point"}
}