{
  "type": "Feature",
  "properties": {
    "gn:admin1_code":"18.0",
    "gn:admin2_code":"4122305.0",
    "gn:asciiname":"Sitio Antonio Marques",
    "gn:country_code":"BR",
    "gn:dem":832,
    "gn:feature_class":"P",
    "gn:feature_code":"PPL",
    "gn:name":"S\u00edtio Ant\u00f4nio Marques",
    "gn:population":0,
    "gn:timezone":"America/Sao_Paulo",
    "iso:country":"BR",
    "name:por_x_preferred":[
        "S\u00edtio Ant\u00f4nio Marques"
    ],
    "wof:name":"Sitio Antonio Marques",
    "wof:placetype":"locality"
},
  "geometry": {"coordinates":[-49.80831,-25.98018],"type":"Point"}
}