{
  "type": "Feature",
  "properties": {
    "gn:admin1_code":"25",
    "gn:admin2_code":"1400704.0",
    "gn:asciiname":"Companugamu",
    "gn:cc2":"BR",
    "gn:country_code":"BR",
    "gn:dem":548,
    "gn:feature_class":"P",
    "gn:feature_code":"PPL",
    "gn:name":"Companugamu",
    "gn:population":0,
    "gn:timezone":"America/Boa_Vista",
    "iso:country":"BR",
    "name:und_x_variant":[
        "Kumparuyamon",
        "Kumparuymou",
        "Companugamu"
    ],
    "wof:name":"Companugamu",
    "wof:placetype":"locality"
},
  "geometry": {"coordinates":[-60.13333000000001,4.31667],"type":"Point"}
}