{
  "type": "Feature",
  "properties": {
    "gn:admin1_code":"06",
    "gn:admin2_code":"2312205.0",
    "gn:asciiname":"Fazenda Boqueirao",
    "gn:country_code":"BR",
    "gn:dem":216,
    "gn:feature_class":"P",
    "gn:feature_code":"PPL",
    "gn:name":"Fazenda Boqueir\u00e3o",
    "gn:population":0,
    "gn:timezone":"America/Fortaleza",
    "iso:country":"BR",
    "wof:name":"Fazenda Boqueirao",
    "wof:placetype":"locality"
},
  "geometry": {"coordinates":[-40.25,-4.38333],"type":"Point"}
}