{
  "type": "Feature",
  "properties": {
    "gn:admin1_code":"5",
    "gn:admin2_code":"2918001.0",
    "gn:asciiname":"Amaralina",
    "gn:country_code":"BR",
    "gn:dem":255,
    "gn:feature_class":"P",
    "gn:feature_code":"PPL",
    "gn:name":"Amaralina",
    "gn:population":0,
    "gn:timezone":"America/Bahia",
    "iso:country":"BR",
    "name:bpy_x_preferred":[
        "\u0986\u09ae\u09be\u09b0\u09cd\u0986\u09b2\u09bf\u09a8\u09be"
    ],
    "name:ceb_x_preferred":[
        "Amaralina"
    ],
    "name:deu_x_preferred":[
        "Amaralina"
    ],
    "name:epo_x_preferred":[
        "Amaralina"
    ],
    "name:eus_x_preferred":[
        "Amaralina"
    ],
    "name:fra_x_preferred":[
        "Amaralina"
    ],
    "name:hye_x_preferred":[
        "\u0531\u0574\u0561\u0580\u0561\u056c\u056b\u0576\u0561"
    ],
    "name:ita_x_preferred":[
        "Amaralina"
    ],
    "name:kat_x_preferred":[
        "\u10d0\u10db\u10d0\u10e0\u10d0\u10da\u10d8\u10dc\u10d0"
    ],
    "name:kaz_x_preferred":[
        "\u0410\u043c\u0430\u0440\u0430\u043b\u0438\u043d\u0430"
    ],
    "name:mlg_x_preferred":[
        "Amaralina"
    ],
    "name:nld_x_preferred":[
        "Amaralina"
    ],
    "name:nor_x_preferred":[
        "Amaralina"
    ],
    "name:por_x_preferred":[
        "Amaralina"
    ],
    "name:ron_x_preferred":[
        "Amaralina"
    ],
    "name:rus_x_preferred":[
        "\u0410\u043c\u0430\u0440\u0430\u043b\u0438\u043d\u0430"
    ],
    "name:spa_x_preferred":[
        "Amaralina"
    ],
    "name:swe_x_preferred":[
        "Amaralina"
    ],
    "name:vie_x_preferred":[
        "Amaralina"
    ],
    "name:vol_x_preferred":[
        "Amaralina"
    ],
    "name:war_x_preferred":[
        "Amaralina"
    ],
    "name:zho_x_preferred":[
        "\u963f\u9a6c\u62c9\u5229\u90a3"
    ],
    "wof:name":"Amaralina",
    "wof:placetype":"locality"
},
  "geometry": {"coordinates":[-40.08333,-13.85],"type":"Point"}
}