{
  "type": "Feature",
  "properties": {
    "gn:admin1_code":"27",
    "gn:admin2_code":"3504107.0",
    "gn:asciiname":"Sitio Rouxinol",
    "gn:country_code":"BR",
    "gn:dem":800,
    "gn:feature_class":"P",
    "gn:feature_code":"PPL",
    "gn:name":"S\u00edtio Rouxinol",
    "gn:population":0,
    "gn:timezone":"America/Sao_Paulo",
    "iso:country":"BR",
    "name:por_x_preferred":[
        "S\u00edtio Rouxinol"
    ],
    "wof:name":"Sitio Rouxinol",
    "wof:placetype":"locality"
},
  "geometry": {"coordinates":[-46.7075,-23.21694],"type":"Point"}
}