{
  "type": "Feature",
  "properties": {
    "gn:admin1_code":"18.0",
    "gn:admin2_code":"4109708.0",
    "gn:asciiname":"Sitio Paulino",
    "gn:country_code":"BR",
    "gn:dem":546,
    "gn:feature_class":"P",
    "gn:feature_code":"PPL",
    "gn:name":"S\u00edtio Paulino",
    "gn:population":0,
    "gn:timezone":"America/Sao_Paulo",
    "iso:country":"BR",
    "name:por_x_preferred":[
        "S\u00edtio Paulino"
    ],
    "wof:name":"Sitio Paulino",
    "wof:placetype":"locality"
},
  "geometry": {"coordinates":[-50.30013,-23.79477],"type":"Point"}
}