{
  "type": "Feature",
  "properties": {
    "gn:admin1_code":"25",
    "gn:admin2_code":"1400209.0",
    "gn:asciiname":"Porto Alegre",
    "gn:country_code":"BR",
    "gn:dem":35,
    "gn:feature_class":"P",
    "gn:feature_code":"PPL",
    "gn:name":"Porto Alegre",
    "gn:population":0,
    "gn:timezone":"America/Boa_Vista",
    "iso:country":"BR",
    "wof:name":"Porto Alegre",
    "wof:placetype":"locality"
},
  "geometry": {"coordinates":[-61.92528000000001,-0.88639],"type":"Point"}
}