{
  "type": "Feature",
  "properties": {
    "gn:admin1_code":"5",
    "gn:admin2_code":"2930758.0",
    "gn:asciiname":"Estreito",
    "gn:country_code":"BR",
    "gn:dem":426,
    "gn:feature_class":"P",
    "gn:feature_code":"PPL",
    "gn:name":"Estreito",
    "gn:population":0,
    "gn:timezone":"America/Bahia",
    "iso:country":"BR",
    "name:ceb_x_preferred":[
        "Estreito"
    ],
    "name:fra_x_preferred":[
        "Estreito"
    ],
    "name:nld_x_preferred":[
        "Estreito"
    ],
    "name:por_x_preferred":[
        "Estreito"
    ],
    "name:swe_x_preferred":[
        "Estreito"
    ],
    "wof:name":"Estreito",
    "wof:placetype":"locality"
},
  "geometry": {"coordinates":[-43.53333,-13.13333],"type":"Point"}
}