{
  "type": "Feature",
  "properties": {
    "gn:admin1_code":"18.0",
    "gn:admin2_code":"4114302.0",
    "gn:asciiname":"Sitio Marli Bizzoto",
    "gn:country_code":"BR",
    "gn:dem":842,
    "gn:feature_class":"P",
    "gn:feature_code":"PPL",
    "gn:name":"S\u00edtio Marli Bizzoto",
    "gn:population":0,
    "gn:timezone":"America/Sao_Paulo",
    "iso:country":"BR",
    "name:por_x_preferred":[
        "S\u00edtio Marli Bizzoto"
    ],
    "wof:name":"Sitio Marli Bizzoto",
    "wof:placetype":"locality"
},
  "geometry": {"coordinates":[-49.3453,-25.9308],"type":"Point"}
}