{
  "type": "Feature",
  "properties": {
    "gn:admin1_code":"26",
    "gn:admin2_code":"4215505.0",
    "gn:asciiname":"Sepultura",
    "gn:country_code":"BR",
    "gn:dem":1016,
    "gn:feature_class":"P",
    "gn:feature_code":"PPL",
    "gn:name":"Sepultura",
    "gn:population":0,
    "gn:timezone":"America/Sao_Paulo",
    "iso:country":"BR",
    "wof:name":"Sepultura",
    "wof:placetype":"locality"
},
  "geometry": {"coordinates":[-50.45,-26.93333],"type":"Point"}
}