{
  "type": "Feature",
  "properties": {
    "gn:admin1_code":"15",
    "gn:admin2_code":"3102704.0",
    "gn:asciiname":"Andre Fernandes",
    "gn:country_code":"BR",
    "gn:dem":752,
    "gn:feature_class":"P",
    "gn:feature_code":"PPL",
    "gn:name":"Andr\u00e9 Fernandes",
    "gn:population":0,
    "gn:timezone":"America/Sao_Paulo",
    "iso:country":"BR",
    "name:und_x_variant":[
        "Cachoeira do Paje\u00fa",
        "Cachoeira do Pajehu",
        "Andr\u00e9 Fernandes"
    ],
    "wof:name":"Andre Fernandes",
    "wof:placetype":"locality"
},
  "geometry": {"coordinates":[-41.49703,-15.9588],"type":"Point"}
}