{
  "type": "Feature",
  "properties": {
    "gn:admin1_code":"20",
    "gn:admin2_code":"2209377.0",
    "gn:asciiname":"Paragua",
    "gn:country_code":"BR",
    "gn:dem":177,
    "gn:feature_class":"P",
    "gn:feature_code":"PPL",
    "gn:name":"Paragua",
    "gn:population":0,
    "gn:timezone":"America/Fortaleza",
    "iso:country":"BR",
    "wof:name":"Paragua",
    "wof:placetype":"locality"
},
  "geometry": {"coordinates":[-42.23333,-6.85],"type":"Point"}
}