{
  "type": "Feature",
  "properties": {
    "gn:admin1_code":"23",
    "gn:admin2_code":"4312104.0",
    "gn:asciiname":"Demetrio Ribeiro",
    "gn:country_code":"BR",
    "gn:dem":143,
    "gn:feature_class":"P",
    "gn:feature_code":"PPL",
    "gn:name":"Dem\u00e9trio Ribeiro",
    "gn:population":0,
    "gn:timezone":"America/Sao_Paulo",
    "iso:country":"BR",
    "wof:name":"Demetrio Ribeiro",
    "wof:placetype":"locality"
},
  "geometry": {"coordinates":[-54.55,-29.56667],"type":"Point"}
}