{
  "type": "Feature",
  "properties": {
    "gn:admin1_code":"18.0",
    "gn:admin2_code":"4124707.0",
    "gn:asciiname":"Sitio Nossa Senhora Aparecida",
    "gn:country_code":"BR",
    "gn:dem":686,
    "gn:feature_class":"P",
    "gn:feature_code":"PPL",
    "gn:name":"S\u00edtio Nossa Senhora Aparecida",
    "gn:population":0,
    "gn:timezone":"America/Sao_Paulo",
    "iso:country":"BR",
    "name:por_x_preferred":[
        "S\u00edtio Nossa Senhora Aparecida"
    ],
    "wof:name":"Sitio Nossa Senhora Aparecida",
    "wof:placetype":"locality"
},
  "geometry": {"coordinates":[-50.72911,-23.61677],"type":"Point"}
}