{
  "type": "Feature",
  "properties": {
    "gn:admin1_code":"20",
    "gn:admin2_code":"2202505.0",
    "gn:asciiname":"Gaviao",
    "gn:country_code":"BR",
    "gn:dem":536,
    "gn:feature_class":"P",
    "gn:feature_code":"PPL",
    "gn:name":"Gavi\u00e3o",
    "gn:population":0,
    "gn:timezone":"America/Fortaleza",
    "iso:country":"BR",
    "wof:name":"Gaviao",
    "wof:placetype":"locality"
},
  "geometry": {"coordinates":[-43.31667,-9.31667],"type":"Point"}
}