{
  "type": "Feature",
  "properties": {
    "gn:admin1_code":"18.0",
    "gn:admin2_code":"4109500.0",
    "gn:asciiname":"Sitio Joao Costa",
    "gn:country_code":"BR",
    "gn:dem":91,
    "gn:feature_class":"P",
    "gn:feature_code":"PPL",
    "gn:name":"S\u00edtio Jo\u00e3o Costa",
    "gn:population":0,
    "gn:timezone":"America/Sao_Paulo",
    "iso:country":"BR",
    "name:por_x_preferred":[
        "S\u00edtio Jo\u00e3o Costa"
    ],
    "wof:name":"Sitio Joao Costa",
    "wof:placetype":"locality"
},
  "geometry": {"coordinates":[-48.5851,-25.2668],"type":"Point"}
}