{
  "type": "Feature",
  "properties": {
    "gn:admin1_code":"27",
    "gn:admin2_code":"3527207.0",
    "gn:asciiname":"Haras Mondesir",
    "gn:country_code":"BR",
    "gn:dem":563,
    "gn:elevation":"0.0",
    "gn:feature_class":"P",
    "gn:feature_code":"PPL",
    "gn:name":"Haras Mondesir",
    "gn:population":0,
    "gn:timezone":"America/Sao_Paulo",
    "iso:country":"BR",
    "name:por_x_preferred":[
        "Haras Mondesir"
    ],
    "wof:name":"Haras Mondesir",
    "wof:placetype":"locality"
},
  "geometry": {"coordinates":[-45.11152,-22.76465],"type":"Point"}
}