{
  "type": "Feature",
  "properties": {
    "gn:admin1_code":"5",
    "gn:admin2_code":"2912509.0",
    "gn:asciiname":"Vargem do Capim",
    "gn:country_code":"BR",
    "gn:dem":519,
    "gn:feature_class":"P",
    "gn:feature_code":"PPL",
    "gn:name":"Vargem do Capim",
    "gn:population":0,
    "gn:timezone":"America/Bahia",
    "iso:country":"BR",
    "wof:name":"Vargem do Capim",
    "wof:placetype":"locality"
},
  "geometry": {"coordinates":[-42.36667,-12.76667],"type":"Point"}
}