{
  "type": "Feature",
  "properties": {
    "gn:admin1_code":"17",
    "gn:admin2_code":"2513943.0",
    "gn:asciiname":"Ipueirinha",
    "gn:country_code":"BR",
    "gn:dem":413,
    "gn:feature_class":"P",
    "gn:feature_code":"PPL",
    "gn:name":"Ipueirinha",
    "gn:population":0,
    "gn:timezone":"America/Fortaleza",
    "iso:country":"BR",
    "wof:name":"Ipueirinha",
    "wof:placetype":"locality"
},
  "geometry": {"coordinates":[-36.43333,-7.65],"type":"Point"}
}