{
  "type": "Feature",
  "properties": {
    "gn:admin1_code":"18.0",
    "gn:admin2_code":"4110409.0",
    "gn:asciiname":"Sambaiba",
    "gn:country_code":"BR",
    "gn:dem":417,
    "gn:feature_class":"P",
    "gn:feature_code":"PPL",
    "gn:name":"Samba\u00edba",
    "gn:population":0,
    "gn:timezone":"America/Sao_Paulo",
    "iso:country":"BR",
    "name:por_x_preferred":[
        "Samba\u00edba"
    ],
    "wof:name":"Sambaiba",
    "wof:placetype":"locality"
},
  "geometry": {"coordinates":[-52.63931,-23.47467],"type":"Point"}
}