{
  "type": "Feature",
  "properties": {
    "gn:admin1_code":"20",
    "gn:admin2_code":"2209203.0",
    "gn:asciiname":"Monte Alegre",
    "gn:country_code":"BR",
    "gn:dem":547,
    "gn:feature_class":"P",
    "gn:feature_code":"PPL",
    "gn:name":"Monte Alegre",
    "gn:population":0,
    "gn:timezone":"America/Fortaleza",
    "iso:country":"BR",
    "wof:name":"Monte Alegre",
    "wof:placetype":"locality"
},
  "geometry": {"coordinates":[-45.58333,-9.21667],"type":"Point"}
}