{
  "type": "Feature",
  "properties": {
    "gn:admin1_code":"27",
    "gn:admin2_code":"3526209.0",
    "gn:asciiname":"Sitio Bela Napoli",
    "gn:country_code":"BR",
    "gn:dem":682,
    "gn:feature_class":"P",
    "gn:feature_code":"PPL",
    "gn:name":"S\u00edtio Bela Napoli",
    "gn:population":0,
    "gn:timezone":"America/Sao_Paulo",
    "iso:country":"BR",
    "name:por_x_preferred":[
        "S\u00edtio Bela Napoli"
    ],
    "wof:name":"Sitio Bela Napoli",
    "wof:placetype":"locality"
},
  "geometry": {"coordinates":[-47.1022,-23.9169],"type":"Point"}
}