{
  "type": "Feature",
  "properties": {
    "gn:admin1_code":"06",
    "gn:admin2_code":"2301307.0",
    "gn:asciiname":"Sao Bento (1)",
    "gn:country_code":"BR",
    "gn:dem":634,
    "gn:feature_class":"P",
    "gn:feature_code":"PPL",
    "gn:name":"S\u00e3o Bento (1)",
    "gn:population":0,
    "gn:timezone":"America/Fortaleza",
    "iso:country":"BR",
    "wof:name":"Sao Bento (1)",
    "wof:placetype":"locality"
},
  "geometry": {"coordinates":[-40.05,-7.16667],"type":"Point"}
}