{
  "type": "Feature",
  "properties": {
    "gn:admin1_code":"20",
    "gn:admin2_code":"2208007.0",
    "gn:asciiname":"Saco do Cruzeiro",
    "gn:country_code":"BR",
    "gn:dem":286,
    "gn:feature_class":"P",
    "gn:feature_code":"PPL",
    "gn:name":"Saco do Cruzeiro",
    "gn:population":0,
    "gn:timezone":"America/Fortaleza",
    "iso:country":"BR",
    "wof:name":"Saco do Cruzeiro",
    "wof:placetype":"locality"
},
  "geometry": {"coordinates":[-41.45,-7.01667],"type":"Point"}
}