{
  "type": "Feature",
  "properties": {
    "gn:admin1_code":"27",
    "gn:admin2_code":"3509254.0",
    "gn:asciiname":"Sitio Santa Rosa",
    "gn:country_code":"BR",
    "gn:dem":162,
    "gn:feature_class":"P",
    "gn:feature_code":"PPL",
    "gn:name":"S\u00edtio Santa Rosa",
    "gn:population":0,
    "gn:timezone":"America/Sao_Paulo",
    "iso:country":"BR",
    "name:por_x_preferred":[
        "S\u00edtio Santa Rosa"
    ],
    "wof:name":"Sitio Santa Rosa",
    "wof:placetype":"locality"
},
  "geometry": {"coordinates":[-48.1889,-24.8074],"type":"Point"}
}