{
  "type": "Feature",
  "properties": {
    "gn:admin1_code":"1",
    "gn:admin2_code":"1200708.0",
    "gn:asciiname":"Alto Alegre",
    "gn:country_code":"BR",
    "gn:dem":207,
    "gn:feature_class":"P",
    "gn:feature_code":"PPL",
    "gn:name":"Alto Alegre",
    "gn:population":0,
    "gn:timezone":"America/Rio_Branco",
    "iso:country":"BR",
    "wof:name":"Alto Alegre",
    "wof:placetype":"locality"
},
  "geometry": {"coordinates":[-68.18333,-10.61667],"type":"Point"}
}