{
  "type": "Feature",
  "properties": {
    "gn:admin1_code":"18",
    "gn:admin2_code":"4127601.0",
    "gn:asciiname":"Sitio Valdomiro A. da Cruz",
    "gn:country_code":"BR",
    "gn:dem":876,
    "gn:feature_class":"P",
    "gn:feature_code":"PPL",
    "gn:name":"S\u00edtio Valdomiro A. da Cruz",
    "gn:population":0,
    "gn:timezone":"America/Sao_Paulo",
    "iso:country":"BR",
    "name:por_x_preferred":[
        "S\u00edtio Valdomiro A. da Cruz"
    ],
    "wof:name":"Sitio Valdomiro A. da Cruz",
    "wof:placetype":"locality"
},
  "geometry": {"coordinates":[-49.0343,-25.8678],"type":"Point"}
}