{
  "type": "Feature",
  "properties": {
    "gn:admin1_code":"18",
    "gn:admin2_code":"4127601.0",
    "gn:asciiname":"Sitio Serrinha",
    "gn:country_code":"BR",
    "gn:dem":930,
    "gn:feature_class":"P",
    "gn:feature_code":"PPL",
    "gn:name":"S\u00edtio Serrinha",
    "gn:population":0,
    "gn:timezone":"America/Sao_Paulo",
    "iso:country":"BR",
    "name:por_x_preferred":[
        "S\u00edtio Serrinha"
    ],
    "wof:name":"Sitio Serrinha",
    "wof:placetype":"locality"
},
  "geometry": {"coordinates":[-49.0797,-25.8105],"type":"Point"}
}