{
  "type": "Feature",
  "properties": {
    "gn:admin1_code":"27",
    "gn:admin2_code":"3500808.0",
    "gn:asciiname":"Machados",
    "gn:country_code":"BR",
    "gn:dem":338,
    "gn:feature_class":"P",
    "gn:feature_code":"PPL",
    "gn:name":"Machados",
    "gn:population":0,
    "gn:timezone":"America/Sao_Paulo",
    "iso:country":"BR",
    "wof:name":"Machados",
    "wof:placetype":"locality"
},
  "geometry": {"coordinates":[-51.36667,-21.88333],"type":"Point"}
}