{
  "type": "Feature",
  "properties": {
    "gn:admin1_code":"27",
    "gn:admin2_code":"3500808.0",
    "gn:asciiname":"Machados",
    "gn:country_code":"BR",
    "gn:dem":338,
    "gn:feature_class":"P",
    "gn:feature_code":"PPL",
    "gn:name":"Machados",
    "gn:population":0,
    "gn:timezone":"America/Sao_Paulo",
    "iso:country":"BR",
    "name:bpy_x_preferred":[
        "\u09ae\u09be\u099a\u09be\u09a1\u09cb\u09b8"
    ],
    "name:ceb_x_preferred":[
        "Machados"
    ],
    "name:eus_x_preferred":[
        "Machados"
    ],
    "name:fra_x_preferred":[
        "Machados"
    ],
    "name:ita_x_preferred":[
        "Machados"
    ],
    "name:kat_x_preferred":[
        "\u10db\u10d0\u10e8\u10d0\u10d3\u10e3\u10e1\u10d8"
    ],
    "name:mlg_x_preferred":[
        "Machados"
    ],
    "name:nld_x_preferred":[
        "Machados"
    ],
    "name:nor_x_preferred":[
        "Machados"
    ],
    "name:por_x_preferred":[
        "Machados"
    ],
    "name:ron_x_preferred":[
        "Machados"
    ],
    "name:rus_x_preferred":[
        "\u041c\u0430\u0448\u0430\u0434\u0443\u0441"
    ],
    "name:swe_x_preferred":[
        "Machados"
    ],
    "name:urd_x_preferred":[
        "\u0645\u0627\u0686\u0627\u0688\u0648\u0633"
    ],
    "name:vie_x_preferred":[
        "Machados"
    ],
    "name:vol_x_preferred":[
        "Machados"
    ],
    "name:war_x_preferred":[
        "Machados"
    ],
    "name:zho_x_preferred":[
        "\u9a6c\u6c99\u675c\u65af"
    ],
    "wof:name":"Machados",
    "wof:placetype":"locality"
},
  "geometry": {"coordinates":[-51.36667,-21.88333],"type":"Point"}
}