{
  "type": "Feature",
  "properties": {
    "gn:admin1_code":"15",
    "gn:admin2_code":"3144102.0",
    "gn:asciiname":"Campestre",
    "gn:country_code":"BR",
    "gn:dem":1110,
    "gn:feature_class":"P",
    "gn:feature_code":"PPL",
    "gn:name":"Campestre",
    "gn:population":0,
    "gn:timezone":"America/Sao_Paulo",
    "iso:country":"BR",
    "name:ceb_x_preferred":[
        "Campestre"
    ],
    "name:deu_x_preferred":[
        "Campestre"
    ],
    "name:epo_x_preferred":[
        "Campestre"
    ],
    "name:fra_x_preferred":[
        "Campestre"
    ],
    "name:ita_x_preferred":[
        "Campestre"
    ],
    "name:nld_x_preferred":[
        "Campestre"
    ],
    "name:nor_x_preferred":[
        "Campestre"
    ],
    "name:pol_x_preferred":[
        "Campestre"
    ],
    "name:por_x_preferred":[
        "Campestre"
    ],
    "name:ron_x_preferred":[
        "Campestre"
    ],
    "name:rus_x_preferred":[
        "\u041a\u0430\u043c\u043f\u0435\u0441\u0442\u0440\u0438"
    ],
    "name:sco_x_preferred":[
        "Campestre"
    ],
    "name:spa_x_preferred":[
        "Campestre"
    ],
    "name:swe_x_preferred":[
        "Campestre"
    ],
    "name:vol_x_preferred":[
        "Campestre"
    ],
    "wof:name":"Campestre",
    "wof:placetype":"locality"
},
  "geometry": {"coordinates":[-46.58333,-21.41667],"type":"Point"}
}