{
  "type": "Feature",
  "properties": {
    "gn:admin1_code":"06",
    "gn:admin2_code":"2311355.0",
    "gn:asciiname":"Corrego (2)",
    "gn:country_code":"BR",
    "gn:dem":228,
    "gn:feature_class":"P",
    "gn:feature_code":"PPL",
    "gn:name":"C\u00f3rrego (2)",
    "gn:population":0,
    "gn:timezone":"America/Fortaleza",
    "iso:country":"BR",
    "wof:name":"Corrego (2)",
    "wof:placetype":"locality"
},
  "geometry": {"coordinates":[-39.08333,-6.16667],"type":"Point"}
}