{
  "type": "Feature",
  "properties": {
    "gn:admin1_code":"4",
    "gn:admin2_code":"1300300.0",
    "gn:asciiname":"Sao Joao",
    "gn:country_code":"BR",
    "gn:dem":11,
    "gn:feature_class":"P",
    "gn:feature_code":"PPL",
    "gn:name":"S\u00e3o Jo\u00e3o",
    "gn:population":0,
    "gn:timezone":"America/Manaus",
    "iso:country":"BR",
    "wof:name":"Sao Joao",
    "wof:placetype":"locality"
},
  "geometry": {"coordinates":[-59.93,-4.21361],"type":"Point"}
}