{
  "type": "Feature",
  "properties": {
    "gn:admin1_code":"17",
    "gn:admin2_code":"2512101.0",
    "gn:asciiname":"Cajazeiras dos Lourencos",
    "gn:country_code":"BR",
    "gn:dem":215,
    "gn:feature_class":"P",
    "gn:feature_code":"PPL",
    "gn:name":"Caj\u00e0zeiras dos Louren\u00e7os",
    "gn:population":0,
    "gn:timezone":"America/Fortaleza",
    "iso:country":"BR",
    "wof:name":"Cajazeiras dos Lourencos",
    "wof:placetype":"locality"
},
  "geometry": {"coordinates":[-37.91667,-6.85],"type":"Point"}
}