{
  "type": "Feature",
  "properties": {
    "gn:admin1_code":"16",
    "gn:admin2_code":"1503754.0",
    "gn:asciiname":"Maloca Velha",
    "gn:country_code":"BR",
    "gn:dem":262,
    "gn:feature_class":"P",
    "gn:feature_code":"PPL",
    "gn:name":"Maloca Velha",
    "gn:population":0,
    "gn:timezone":"America/Santarem",
    "iso:country":"BR",
    "wof:name":"Maloca Velha",
    "wof:placetype":"locality"
},
  "geometry": {"coordinates":[-57.31667,-7.65],"type":"Point"}
}