{
  "type": "Feature",
  "properties": {
    "gn:admin1_code":"16",
    "gn:admin2_code":"1504307.0",
    "gn:asciiname":"Curucazinho",
    "gn:country_code":"BR",
    "gn:dem":12,
    "gn:feature_class":"P",
    "gn:feature_code":"PPL",
    "gn:name":"Curu\u00e7\u00e0zinho",
    "gn:population":0,
    "gn:timezone":"America/Belem",
    "iso:country":"BR",
    "wof:name":"Curucazinho",
    "wof:placetype":"locality"
},
  "geometry": {"coordinates":[-47.46667,-0.63333],"type":"Point"}
}