{
  "type": "Feature",
  "properties": {
    "gn:admin1_code":"27",
    "gn:admin2_code":"3505401.0",
    "gn:asciiname":"Ribeirao Bonito",
    "gn:country_code":"BR",
    "gn:dem":590,
    "gn:feature_class":"P",
    "gn:feature_code":"PPLL",
    "gn:name":"Ribeir\u00e3o Bonito",
    "gn:population":0,
    "gn:timezone":"America/Sao_Paulo",
    "iso:country":"BR",
    "name:por_x_preferred":[
        "Ribeir\u00e3o Bonito"
    ],
    "wof:name":"Ribeirao Bonito",
    "wof:placetype":"locality"
},
  "geometry": {"coordinates":[-48.5209,-24.8547],"type":"Point"}
}