{
  "type": "Feature",
  "properties": {
    "gn:admin1_code":"06",
    "gn:admin2_code":"2310308.0",
    "gn:asciiname":"Massape (1)",
    "gn:country_code":"BR",
    "gn:dem":482,
    "gn:feature_class":"P",
    "gn:feature_code":"PPL",
    "gn:name":"Massap\u00ea (1)",
    "gn:population":0,
    "gn:timezone":"America/Fortaleza",
    "iso:country":"BR",
    "wof:name":"Massape (1)",
    "wof:placetype":"locality"
},
  "geometry": {"coordinates":[-40.56667,-6.08333],"type":"Point"}
}