{
  "type": "Feature",
  "properties": {
    "gn:admin1_code":"27",
    "gn:admin2_code":"3528403.0",
    "gn:asciiname":"Sitio Pia-Gui",
    "gn:country_code":"BR",
    "gn:dem":871,
    "gn:feature_class":"P",
    "gn:feature_code":"PPL",
    "gn:name":"S\u00edtio Pia-Gui",
    "gn:population":0,
    "gn:timezone":"America/Sao_Paulo",
    "iso:country":"BR",
    "name:por_x_preferred":[
        "S\u00edtio Pia-Gui"
    ],
    "wof:name":"Sitio Pia-Gui",
    "wof:placetype":"locality"
},
  "geometry": {"coordinates":[-47.22648,-23.61161],"type":"Point"}
}