{
  "type": "Feature",
  "properties": {
    "gn:admin1_code":"27",
    "gn:admin2_code":"3524600.0",
    "gn:asciiname":"Bairro Lencol",
    "gn:country_code":"BR",
    "gn:dem":105,
    "gn:feature_class":"P",
    "gn:feature_code":"PPLL",
    "gn:name":"Bairro Len\u00e7ol",
    "gn:population":0,
    "gn:timezone":"America/Sao_Paulo",
    "iso:country":"BR",
    "name:por_x_preferred":[
        "Bairro Len\u00e7ol"
    ],
    "wof:name":"Bairro Lencol",
    "wof:placetype":"locality"
},
  "geometry": {"coordinates":[-48.03471,-24.59004],"type":"Point"}
}