{
  "type": "Feature",
  "properties": {
    "gn:admin1_code":"4",
    "gn:admin2_code":"1301407.0",
    "gn:asciiname":"Paraiso",
    "gn:country_code":"BR",
    "gn:dem":167,
    "gn:feature_class":"P",
    "gn:feature_code":"PPL",
    "gn:name":"Para\u00edso",
    "gn:population":0,
    "gn:timezone":"America/Eirunepe",
    "iso:country":"BR",
    "wof:name":"Paraiso",
    "wof:placetype":"locality"
},
  "geometry": {"coordinates":[-71.0775,-7.4225],"type":"Point"}
}