{
  "type": "Feature",
  "properties": {
    "gn:admin1_code":"22",
    "gn:admin2_code":"2408003.0",
    "gn:asciiname":"Bom Destino",
    "gn:country_code":"BR",
    "gn:dem":96,
    "gn:feature_class":"P",
    "gn:feature_code":"PPL",
    "gn:name":"Bom Destino",
    "gn:population":0,
    "gn:timezone":"America/Fortaleza",
    "iso:country":"BR",
    "wof:name":"Bom Destino",
    "wof:placetype":"locality"
},
  "geometry": {"coordinates":[-37.42583,-5.06528],"type":"Point"}
}