{
  "type": "Feature",
  "properties": {
    "gn:admin1_code":"4",
    "gn:admin2_code":"1300102.0",
    "gn:asciiname":"Itauba",
    "gn:country_code":"BR",
    "gn:dem":49,
    "gn:feature_class":"P",
    "gn:feature_code":"PPL",
    "gn:name":"Ita\u00faba",
    "gn:population":0,
    "gn:timezone":"America/Manaus",
    "iso:country":"BR",
    "wof:name":"Itauba",
    "wof:placetype":"locality"
},
  "geometry": {"coordinates":[-62.38083,-4.465],"type":"Point"}
}