{
  "type": "Feature",
  "properties": {
    "gn:admin1_code":"27",
    "gn:admin2_code":"3509908.0",
    "gn:asciiname":"Ipiranguinha",
    "gn:country_code":"BR",
    "gn:dem":30,
    "gn:feature_class":"P",
    "gn:feature_code":"PPLL",
    "gn:name":"Ipiranguinha",
    "gn:population":0,
    "gn:timezone":"America/Sao_Paulo",
    "iso:country":"BR",
    "name:por_x_preferred":[
        "Ipiranguinha"
    ],
    "wof:name":"Ipiranguinha",
    "wof:placetype":"locality"
},
  "geometry": {"coordinates":[-48.14861,-25.035],"type":"Point"}
}