{
  "type": "Feature",
  "properties": {
    "gn:admin1_code":"18.0",
    "gn:admin2_code":"4104709.0",
    "gn:asciiname":"Jacinto",
    "gn:country_code":"BR",
    "gn:dem":579,
    "gn:feature_class":"P",
    "gn:feature_code":"PPLL",
    "gn:name":"Jacinto",
    "gn:population":0,
    "gn:timezone":"America/Sao_Paulo",
    "iso:country":"BR",
    "name:por_x_preferred":[
        "Jacinto"
    ],
    "wof:name":"Jacinto",
    "wof:placetype":"locality"
},
  "geometry": {"coordinates":[-49.7532,-23.4865],"type":"Point"}
}