{
  "type": "Feature",
  "properties": {
    "gn:admin1_code":"20",
    "gn:admin2_code":"2205409.0",
    "gn:asciiname":"Salgado",
    "gn:country_code":"BR",
    "gn:dem":57,
    "gn:feature_class":"P",
    "gn:feature_code":"PPL",
    "gn:name":"Salgado",
    "gn:population":0,
    "gn:timezone":"America/Fortaleza",
    "iso:country":"BR",
    "wof:name":"Salgado",
    "wof:placetype":"locality"
},
  "geometry": {"coordinates":[-42.12667,-3.52889],"type":"Point"}
}