{
  "type": "Feature",
  "properties": {
    "gn:admin1_code":"27.0",
    "gn:admin2_code":"3522307.0",
    "gn:asciiname":"Faxinal do Rio-Acima",
    "gn:country_code":"BR",
    "gn:dem":689,
    "gn:feature_class":"P",
    "gn:feature_code":"PPLL",
    "gn:name":"Faxinal do Rio-Acima",
    "gn:population":0,
    "gn:timezone":"America/Sao_Paulo",
    "iso:country":"BR",
    "name:por_x_preferred":[
        "Faxinal do Rio-Acima"
    ],
    "wof:name":"Faxinal do Rio-Acima",
    "wof:placetype":"locality"
},
  "geometry": {"coordinates":[-47.9107,-23.7425],"type":"Point"}
}