{
  "type": "Feature",
  "properties": {
    "gn:admin1_code":"30",
    "gn:admin2_code":"2609303.0",
    "gn:asciiname":"Barriguda",
    "gn:country_code":"BR",
    "gn:dem":502,
    "gn:feature_class":"P",
    "gn:feature_code":"PPL",
    "gn:name":"Barriguda",
    "gn:population":0,
    "gn:timezone":"America/Recife",
    "iso:country":"BR",
    "wof:name":"Barriguda",
    "wof:placetype":"locality"
},
  "geometry": {"coordinates":[-38.78333,-8.03333],"type":"Point"}
}