{
  "type": "Feature",
  "properties": {
    "gn:admin1_code":"20",
    "gn:admin2_code":"2203909.0",
    "gn:asciiname":"Fortaleza",
    "gn:country_code":"BR",
    "gn:dem":180,
    "gn:feature_class":"P",
    "gn:feature_code":"PPL",
    "gn:name":"Fortaleza",
    "gn:population":0,
    "gn:timezone":"America/Fortaleza",
    "iso:country":"BR",
    "wof:name":"Fortaleza",
    "wof:placetype":"locality"
},
  "geometry": {"coordinates":[-43.05,-7.01667],"type":"Point"}
}