{
  "type": "Feature",
  "properties": {
    "gn:admin1_code":"14",
    "gn:admin2_code":"5102637.0",
    "gn:asciiname":"Utiariti",
    "gn:country_code":"BR",
    "gn:dem":355,
    "gn:feature_class":"P",
    "gn:feature_code":"PPL",
    "gn:name":"Utiariti",
    "gn:population":0,
    "gn:timezone":"America/Cuiaba",
    "iso:country":"BR",
    "name:und_x_variant":[
        "Estac\u00e3o de Utiarity",
        "Utiarity",
        "Utiariti"
    ],
    "wof:name":"Utiariti",
    "wof:placetype":"locality"
},
  "geometry": {"coordinates":[-58.28698000000001,-13.02151],"type":"Point"}
}