{
  "type": "Feature",
  "properties": {
    "gn:admin1_code":"18.0",
    "gn:admin2_code":"4101804.0",
    "gn:asciiname":"Sitio Araucaria",
    "gn:country_code":"BR",
    "gn:dem":931,
    "gn:feature_class":"P",
    "gn:feature_code":"PPL",
    "gn:name":"S\u00edtio Arauc\u00e1ria",
    "gn:population":0,
    "gn:timezone":"America/Sao_Paulo",
    "iso:country":"BR",
    "name:por_x_preferred":[
        "S\u00edtio Arauc\u00e1ria"
    ],
    "wof:name":"Sitio Araucaria",
    "wof:placetype":"locality"
},
  "geometry": {"coordinates":[-49.3833,-25.7643],"type":"Point"}
}