{
  "type": "Feature",
  "properties": {
    "gn:admin1_code":"27",
    "gn:admin2_code":"3546801.0",
    "gn:asciiname":"Stio Santa Filomena",
    "gn:country_code":"BR",
    "gn:dem":725,
    "gn:feature_class":"P",
    "gn:feature_code":"PPL",
    "gn:name":"Stio Santa Filomena",
    "gn:population":0,
    "gn:timezone":"America/Sao_Paulo",
    "iso:country":"BR",
    "name:por_x_preferred":[
        "Stio Santa Filomena"
    ],
    "wof:name":"Stio Santa Filomena",
    "wof:placetype":"locality"
},
  "geometry": {"coordinates":[-46.1695,-23.284],"type":"Point"}
}