{
  "type": "Feature",
  "properties": {
    "gn:admin1_code":"16.0",
    "gn:admin2_code":"1504406.0",
    "gn:asciiname":"Vista Alegre do Para",
    "gn:country_code":"BR",
    "gn:dem":15,
    "gn:feature_class":"P",
    "gn:feature_code":"PPL",
    "gn:name":"Vista Alegre do Para",
    "gn:population":0,
    "gn:timezone":"America/Belem",
    "iso:country":"BR",
    "wof:name":"Vista Alegre do Para",
    "wof:placetype":"locality"
},
  "geometry": {"coordinates":[-47.71088,-0.64681],"type":"Point"}
}