{
  "type": "Feature",
  "properties": {
    "gn:admin1_code":"22",
    "gn:admin2_code":"2403756.0",
    "gn:asciiname":"Espinheiro",
    "gn:country_code":"BR",
    "gn:dem":332,
    "gn:feature_class":"P",
    "gn:feature_code":"PPL",
    "gn:name":"Espinheiro",
    "gn:population":0,
    "gn:timezone":"America/Fortaleza",
    "iso:country":"BR",
    "wof:name":"Espinheiro",
    "wof:placetype":"locality"
},
  "geometry": {"coordinates":[-36.30361,-5.84917],"type":"Point"}
}