{
  "type": "Feature",
  "properties": {
    "gn:admin1_code":"18.0",
    "gn:admin2_code":"4106209.0",
    "gn:asciiname":"Sitio Andre Setlek",
    "gn:country_code":"BR",
    "gn:dem":908,
    "gn:feature_class":"P",
    "gn:feature_code":"PPL",
    "gn:name":"S\u00edtio Andr\u00e9 Setlek",
    "gn:population":0,
    "gn:timezone":"America/Sao_Paulo",
    "iso:country":"BR",
    "name:por_x_preferred":[
        "S\u00edtio Andr\u00e9 Setlek"
    ],
    "wof:name":"Sitio Andre Setlek",
    "wof:placetype":"locality"
},
  "geometry": {"coordinates":[-49.4463,-25.7816],"type":"Point"}
}