{
  "type": "Feature",
  "properties": {
    "gn:admin1_code":"5",
    "gn:admin2_code":"2930402.0",
    "gn:asciiname":"Roma",
    "gn:country_code":"BR",
    "gn:dem":237,
    "gn:feature_class":"P",
    "gn:feature_code":"PPL",
    "gn:name":"Roma",
    "gn:population":0,
    "gn:timezone":"America/Bahia",
    "iso:country":"BR",
    "name:ara_x_preferred":[
        "\u0631\u0648\u0645\u0627"
    ],
    "name:ast_x_preferred":[
        "Roma"
    ],
    "name:bar_x_preferred":[
        "Roma"
    ],
    "name:bul_x_preferred":[
        "\u0420\u043e\u043c\u0430"
    ],
    "name:cat_x_preferred":[
        "Roma"
    ],
    "name:ceb_x_preferred":[
        "Roma"
    ],
    "name:ces_x_preferred":[
        "Roma"
    ],
    "name:cym_x_preferred":[
        "Roma"
    ],
    "name:dan_x_preferred":[
        "Roma"
    ],
    "name:deu_x_preferred":[
        "Roma"
    ],
    "name:fas_x_preferred":[
        "\u0631\u0648\u0645\u0627"
    ],
    "name:fin_x_preferred":[
        "Rooma"
    ],
    "name:fra_x_preferred":[
        "Roma"
    ],
    "name:glg_x_preferred":[
        "Roma"
    ],
    "name:heb_x_preferred":[
        "\u05e8\u05d5\u05de\u05d0"
    ],
    "name:hun_x_preferred":[
        "Roma"
    ],
    "name:hye_x_preferred":[
        "\u054c\u0578\u0574\u0561"
    ],
    "name:ind_x_preferred":[
        "Roma"
    ],
    "name:ita_x_preferred":[
        "Roma"
    ],
    "name:jpn_x_preferred":[
        "\u30ed\u30fc\u30de"
    ],
    "name:kat_x_preferred":[
        "\u10e0\u10dd\u10db\u10d8"
    ],
    "name:kor_x_preferred":[
        "\ub85c\ub9c8"
    ],
    "name:lat_x_preferred":[
        "Roma"
    ],
    "name:lav_x_preferred":[
        "Roma"
    ],
    "name:lit_x_preferred":[
        "Roma"
    ],
    "name:nld_x_preferred":[
        "Roma"
    ],
    "name:nor_x_preferred":[
        "Roma"
    ],
    "name:pol_x_preferred":[
        "Roma"
    ],
    "name:por_x_preferred":[
        "Roma"
    ],
    "name:ron_x_preferred":[
        "Roma"
    ],
    "name:rus_x_preferred":[
        "\u0420\u043e\u043c\u0430"
    ],
    "name:slk_x_preferred":[
        "Roma"
    ],
    "name:slv_x_preferred":[
        "Roma"
    ],
    "name:spa_x_preferred":[
        "Roma"
    ],
    "name:srp_x_preferred":[
        "Roma"
    ],
    "name:swa_x_preferred":[
        "Roma"
    ],
    "name:swe_x_preferred":[
        "Roma"
    ],
    "name:tam_x_preferred":[
        "\u0b89\u0bb0\u0bcb\u0bae\u0bc8"
    ],
    "name:tgl_x_preferred":[
        "Roma"
    ],
    "name:tha_x_preferred":[
        "\u0e42\u0e23\u0e21\u0e32"
    ],
    "name:tur_x_preferred":[
        "Roma"
    ],
    "name:ukr_x_preferred":[
        "\u0420\u043e\u043c\u0430"
    ],
    "name:vol_x_preferred":[
        "Roma"
    ],
    "name:zho_x_preferred":[
        "\u7f57\u9a6c"
    ],
    "wof:name":"Roma",
    "wof:placetype":"locality"
},
  "geometry": {"coordinates":[-39.26667,-12.13333],"type":"Point"}
}