{
  "type": "Feature",
  "properties": {
    "gn:admin1_code":"5",
    "gn:admin2_code":"2930402.0",
    "gn:asciiname":"Roma",
    "gn:country_code":"BR",
    "gn:dem":237,
    "gn:feature_class":"P",
    "gn:feature_code":"PPL",
    "gn:name":"Roma",
    "gn:population":0,
    "gn:timezone":"America/Bahia",
    "iso:country":"BR",
    "wof:name":"Roma",
    "wof:placetype":"locality"
},
  "geometry": {"coordinates":[-39.26667,-12.13333],"type":"Point"}
}