{
  "type": "Feature",
  "properties": {
    "gn:admin1_code":"5.0",
    "gn:admin2_code":"2907103.0",
    "gn:asciiname":"Taua",
    "gn:country_code":"BR",
    "gn:dem":446,
    "gn:feature_class":"P",
    "gn:feature_code":"PPL",
    "gn:name":"Tau\u00e1",
    "gn:population":0,
    "gn:timezone":"America/Bahia",
    "iso:country":"BR",
    "name:por_x_preferred":[
        "Tau\u00e1"
    ],
    "wof:name":"Taua",
    "wof:placetype":"locality"
},
  "geometry": {"coordinates":[-43.70736,-14.20702],"type":"Point"}
}