{
  "type": "Feature",
  "properties": {
    "gn:admin1_code":"1",
    "gn:admin2_code":"1200435.0",
    "gn:asciiname":"Fazenda Nossa Senhora Aparecida",
    "gn:country_code":"BR",
    "gn:dem":194,
    "gn:feature_class":"P",
    "gn:feature_code":"PPL",
    "gn:name":"Fazenda Nossa Senhora Aparecida",
    "gn:population":0,
    "gn:timezone":"America/Rio_Branco",
    "iso:country":"BR",
    "wof:name":"Fazenda Nossa Senhora Aparecida",
    "wof:placetype":"locality"
},
  "geometry": {"coordinates":[-70.31667,-9.25],"type":"Point"}
}