{
  "type": "Feature",
  "properties": {
    "gn:admin1_code":"18",
    "gn:admin2_code":"4112702.0",
    "gn:asciiname":"Roseira",
    "gn:cc2":"BR",
    "gn:country_code":"BR",
    "gn:dem":481,
    "gn:feature_class":"P",
    "gn:feature_code":"PPL",
    "gn:name":"Roseira",
    "gn:population":0,
    "gn:timezone":"America/Sao_Paulo",
    "iso:country":"BR",
    "name:bpy_x_preferred":[
        "\u09b0\u09cb\u09b8\u09c7\u0987\u09b0\u09be"
    ],
    "name:bul_x_preferred":[
        "\u0420\u043e\u0437\u0435\u0439\u0440\u0430"
    ],
    "name:ceb_x_preferred":[
        "Roseira"
    ],
    "name:epo_x_preferred":[
        "Roseira"
    ],
    "name:eus_x_preferred":[
        "Roseira"
    ],
    "name:fra_x_preferred":[
        "Roseira"
    ],
    "name:ita_x_preferred":[
        "Roseira"
    ],
    "name:kaz_x_preferred":[
        "\u0420\u043e\u0437\u0435\u0439\u0440\u0430"
    ],
    "name:mlg_x_preferred":[
        "Roseira"
    ],
    "name:nld_x_preferred":[
        "Roseira"
    ],
    "name:nor_x_preferred":[
        "Roseira"
    ],
    "name:oci_x_preferred":[
        "Roseira"
    ],
    "name:pol_x_preferred":[
        "Roseira"
    ],
    "name:por_x_preferred":[
        "Roseira"
    ],
    "name:ron_x_preferred":[
        "Roseira"
    ],
    "name:rus_x_preferred":[
        "\u0420\u043e\u0437\u0435\u0439\u0440\u0430"
    ],
    "name:swe_x_preferred":[
        "Roseira"
    ],
    "name:und_x_variant":[
        "Jata\u00eczinho"
    ],
    "name:vie_x_preferred":[
        "Roseira"
    ],
    "name:vol_x_preferred":[
        "Roseira"
    ],
    "name:war_x_preferred":[
        "Roseira"
    ],
    "name:zho_x_preferred":[
        "\u7f57\u585e\u62c9"
    ],
    "wof:name":"Roseira",
    "wof:placetype":"locality"
},
  "geometry": {"coordinates":[-50.88333,-23.31667],"type":"Point"}
}