{
  "type": "Feature",
  "properties": {
    "gn:admin1_code":"18",
    "gn:admin2_code":"4112702.0",
    "gn:asciiname":"Roseira",
    "gn:cc2":"BR",
    "gn:country_code":"BR",
    "gn:dem":481,
    "gn:feature_class":"P",
    "gn:feature_code":"PPL",
    "gn:name":"Roseira",
    "gn:population":0,
    "gn:timezone":"America/Sao_Paulo",
    "iso:country":"BR",
    "name:und_x_variant":[
        "Jata\u00eczinho",
        "Roseira"
    ],
    "wof:name":"Roseira",
    "wof:placetype":"locality"
},
  "geometry": {"coordinates":[-50.88333,-23.31667],"type":"Point"}
}