{
  "type": "Feature",
  "properties": {
    "gn:admin1_code":"11",
    "gn:admin2_code":"5006408.0",
    "gn:asciiname":"Pedro Severo",
    "gn:cc2":"BR",
    "gn:country_code":"BR",
    "gn:dem":375,
    "gn:feature_class":"P",
    "gn:feature_code":"PPL",
    "gn:name":"Pedro Severo",
    "gn:population":0,
    "gn:timezone":"America/Campo_Grande",
    "iso:country":"BR",
    "name:und_x_variant":[
        "Fazenda Pedro Severo",
        "Pedro Severo"
    ],
    "wof:name":"Pedro Severo",
    "wof:placetype":"locality"
},
  "geometry": {"coordinates":[-54.03333000000001,-17.66667],"type":"Point"}
}