{
  "type": "Feature",
  "properties": {
    "gn:admin1_code":"30",
    "gn:admin2_code":"2603207.0",
    "gn:asciiname":"Boa Vista",
    "gn:country_code":"BR",
    "gn:dem":869,
    "gn:feature_class":"P",
    "gn:feature_code":"PPL",
    "gn:name":"Boa Vista",
    "gn:population":0,
    "gn:timezone":"America/Recife",
    "iso:country":"BR",
    "wof:name":"Boa Vista",
    "wof:placetype":"locality"
},
  "geometry": {"coordinates":[-36.65,-8.78333],"type":"Point"}
}