{
  "type": "Feature",
  "properties": {
    "gn:admin1_code":"31",
    "gn:admin2_code":"1713809.0",
    "gn:asciiname":"Mosquito",
    "gn:country_code":"BR",
    "gn:dem":182,
    "gn:feature_class":"P",
    "gn:feature_code":"PPL",
    "gn:name":"Mosquito",
    "gn:population":0,
    "gn:timezone":"America/Araguaina",
    "iso:country":"BR",
    "wof:name":"Mosquito",
    "wof:placetype":"locality"
},
  "geometry": {"coordinates":[-47.54583,-6.6125],"type":"Point"}
}