{
  "type": "Feature",
  "properties": {
    "gn:admin1_code":"4",
    "gn:admin2_code":"1300706.0",
    "gn:asciiname":"Colocacao Bom Jardim",
    "gn:country_code":"BR",
    "gn:dem":123,
    "gn:feature_class":"P",
    "gn:feature_code":"PPL",
    "gn:name":"Coloca\u00e7\u00e3o Bom Jardim",
    "gn:population":0,
    "gn:timezone":"America/Manaus",
    "iso:country":"BR",
    "wof:name":"Colocacao Bom Jardim",
    "wof:placetype":"locality"
},
  "geometry": {"coordinates":[-67.46666999999999,-9.26667],"type":"Point"}
}