{
  "type": "Feature",
  "properties": {
    "gn:admin1_code":"31",
    "gn:admin2_code":"1720499.0",
    "gn:asciiname":"Guariroba",
    "gn:cc2":"BR",
    "gn:country_code":"BR",
    "gn:dem":288,
    "gn:feature_class":"P",
    "gn:feature_code":"PPL",
    "gn:name":"Guariroba",
    "gn:population":0,
    "gn:timezone":"America/Araguaina",
    "iso:country":"BR",
    "name:und_x_variant":[
        "Gueriroba",
        "Guariroba"
    ],
    "wof:name":"Guariroba",
    "wof:placetype":"locality"
},
  "geometry": {"coordinates":[-48.18333,-11.76667],"type":"Point"}
}