{
  "type": "Feature",
  "properties": {
    "gn:admin1_code":"27",
    "gn:admin2_code":"3526209.0",
    "gn:asciiname":"Bairro dos Farias",
    "gn:country_code":"BR",
    "gn:dem":659,
    "gn:feature_class":"P",
    "gn:feature_code":"PPLL",
    "gn:name":"Bairro dos Farias",
    "gn:population":0,
    "gn:timezone":"America/Sao_Paulo",
    "iso:country":"BR",
    "name:por_x_preferred":[
        "Bairro dos Farias"
    ],
    "wof:name":"Bairro dos Farias",
    "wof:placetype":"locality"
},
  "geometry": {"coordinates":[-47.1254,-23.87744],"type":"Point"}
}