{
  "type": "Feature",
  "properties": {
    "gn:admin1_code":"18",
    "gn:admin2_code":"4125100.0",
    "gn:asciiname":"Coxilha do Meio",
    "gn:country_code":"BR",
    "gn:dem":918,
    "gn:feature_class":"P",
    "gn:feature_code":"PPL",
    "gn:name":"Coxilha do Meio",
    "gn:population":0,
    "gn:timezone":"America/Sao_Paulo",
    "iso:country":"BR",
    "wof:name":"Coxilha do Meio",
    "wof:placetype":"locality"
},
  "geometry": {"coordinates":[-50.25,-25.65],"type":"Point"}
}