{
  "type": "Feature",
  "properties": {
    "gn:admin1_code":"18.0",
    "gn:admin2_code":"4113205.0",
    "gn:asciiname":"Sitio Pedro Askaski",
    "gn:country_code":"BR",
    "gn:dem":810,
    "gn:feature_class":"P",
    "gn:feature_code":"PPL",
    "gn:name":"S\u00edtio Pedro Askaski",
    "gn:population":0,
    "gn:timezone":"America/Sao_Paulo",
    "iso:country":"BR",
    "name:por_x_preferred":[
        "S\u00edtio Pedro Askaski"
    ],
    "wof:name":"Sitio Pedro Askaski",
    "wof:placetype":"locality"
},
  "geometry": {"coordinates":[-49.6045,-25.8258],"type":"Point"}
}