{
  "type": "Feature",
  "properties": {
    "gn:admin1_code":"5",
    "gn:admin2_code":"2922508.0",
    "gn:asciiname":"Ponta do Leone",
    "gn:cc2":"BR",
    "gn:country_code":"BR",
    "gn:dem":4,
    "gn:feature_class":"P",
    "gn:feature_code":"PPL",
    "gn:name":"Ponta do Leone",
    "gn:population":0,
    "gn:timezone":"America/Bahia",
    "iso:country":"BR",
    "name:und_x_variant":[
        "Ponto do L\u00e9one",
        "Ponta do Leone"
    ],
    "wof:name":"Ponta do Leone",
    "wof:placetype":"locality"
},
  "geometry": {"coordinates":[-38.95,-12.96667],"type":"Point"}
}