{
  "type": "Feature",
  "properties": {
    "gn:admin1_code":"29",
    "gn:admin2_code":"5210109.0",
    "gn:asciiname":"Verissimo",
    "gn:country_code":"BR",
    "gn:dem":619,
    "gn:feature_class":"P",
    "gn:feature_code":"PPL",
    "gn:name":"Ver\u00edssimo",
    "gn:population":0,
    "gn:timezone":"America/Sao_Paulo",
    "iso:country":"BR",
    "name:ceb_x_preferred":[
        "Ver\u00edssimo"
    ],
    "name:deu_x_preferred":[
        "Ver\u00edssimo"
    ],
    "name:fra_x_preferred":[
        "Ver\u00edssimo"
    ],
    "name:ita_x_preferred":[
        "Verissimo"
    ],
    "name:por_x_preferred":[
        "Ver\u00edssimo"
    ],
    "name:spa_x_preferred":[
        "Ver\u00edssimo"
    ],
    "name:swe_x_preferred":[
        "Ver\u00edssimo"
    ],
    "wof:name":"Verissimo",
    "wof:placetype":"locality"
},
  "geometry": {"coordinates":[-48.16667,-17.96667],"type":"Point"}
}