{
  "type": "Feature",
  "properties": {
    "gn:admin1_code":"11",
    "gn:admin2_code":"5006903.0",
    "gn:asciiname":"Pocinho",
    "gn:country_code":"BR",
    "gn:dem":172,
    "gn:feature_class":"P",
    "gn:feature_code":"PPL",
    "gn:name":"Pocinho",
    "gn:population":0,
    "gn:timezone":"America/Campo_Grande",
    "iso:country":"BR",
    "name:deu_x_preferred":[
        "Pocinho"
    ],
    "name:por_x_preferred":[
        "Pocinho"
    ],
    "name:spa_x_preferred":[
        "Pocinho"
    ],
    "wof:name":"Pocinho",
    "wof:placetype":"locality"
},
  "geometry": {"coordinates":[-57.45,-21.81667],"type":"Point"}
}