{
  "type": "Feature",
  "properties": {
    "gn:admin1_code":"13",
    "gn:admin2_code":"2107308.0",
    "gn:asciiname":"Bocaina",
    "gn:cc2":"BR",
    "gn:country_code":"BR",
    "gn:dem":164,
    "gn:feature_class":"P",
    "gn:feature_code":"PPL",
    "gn:name":"Bocaina",
    "gn:population":0,
    "gn:timezone":"America/Fortaleza",
    "iso:country":"BR",
    "name:und_x_variant":[
        "Baca\u00edna",
        "Bocaina"
    ],
    "wof:name":"Bocaina",
    "wof:placetype":"locality"
},
  "geometry": {"coordinates":[-44.06667,-6.75],"type":"Point"}
}