{
  "type": "Feature",
  "properties": {
    "gn:admin1_code":"4.0",
    "gn:admin2_code":"1303502.0",
    "gn:asciiname":"Serra Verde",
    "gn:country_code":"BR",
    "gn:dem":157,
    "gn:feature_class":"P",
    "gn:feature_code":"PPL",
    "gn:name":"Serra Verde",
    "gn:population":0,
    "gn:timezone":"America/Manaus",
    "iso:country":"BR",
    "wof:name":"Serra Verde",
    "wof:placetype":"locality"
},
  "geometry": {"coordinates":[-67.54409,-7.51823],"type":"Point"}
}