{
  "type": "Feature",
  "properties": {
    "gn:admin1_code":"18.0",
    "gn:admin2_code":"4111803.0",
    "gn:asciiname":"Sitio Pampano",
    "gn:country_code":"BR",
    "gn:dem":522,
    "gn:feature_class":"P",
    "gn:feature_code":"PPL",
    "gn:name":"S\u00edtio P\u00e2mpano",
    "gn:population":0,
    "gn:timezone":"America/Sao_Paulo",
    "iso:country":"BR",
    "name:por_x_preferred":[
        "S\u00edtio P\u00e2mpano"
    ],
    "wof:name":"Sitio Pampano",
    "wof:placetype":"locality"
},
  "geometry": {"coordinates":[-49.87148,-23.16682],"type":"Point"}
}