{
  "type": "Feature",
  "properties": {
    "gn:admin1_code":"21",
    "gn:admin2_code":"3302270.0",
    "gn:asciiname":"Parque Sao Jorge",
    "gn:country_code":"BR",
    "gn:dem":65,
    "gn:feature_class":"P",
    "gn:feature_code":"PPL",
    "gn:name":"Parque S\u00e3o Jorge",
    "gn:population":0,
    "gn:timezone":"America/Sao_Paulo",
    "iso:country":"BR",
    "name:por_x_preferred":[
        "Parque S\u00e3o Jorge"
    ],
    "wof:name":"Parque Sao Jorge",
    "wof:placetype":"locality"
},
  "geometry": {"coordinates":[-43.61833,-22.67278],"type":"Point"}
}