{
  "type": "Feature",
  "properties": {
    "gn:admin1_code":"27.0",
    "gn:admin2_code":"3522158.0",
    "gn:asciiname":"Bairro Caracas",
    "gn:country_code":"BR",
    "gn:dem":159,
    "gn:feature_class":"P",
    "gn:feature_code":"PPLL",
    "gn:name":"Bairro Cara\u00e7as",
    "gn:population":0,
    "gn:timezone":"America/Sao_Paulo",
    "iso:country":"BR",
    "name:por_x_preferred":[
        "Bairro Cara\u00e7as"
    ],
    "wof:name":"Bairro Caracas",
    "wof:placetype":"locality"
},
  "geometry": {"coordinates":[-48.89328,-24.66546],"type":"Point"}
}