{
  "type": "Feature",
  "properties": {
    "gn:admin1_code":"06",
    "gn:admin2_code":"2308500.0",
    "gn:asciiname":"Serafim Dias",
    "gn:country_code":"BR",
    "gn:dem":262,
    "gn:feature_class":"P",
    "gn:feature_code":"PPL",
    "gn:name":"Serafim Dias",
    "gn:population":0,
    "gn:timezone":"America/Fortaleza",
    "iso:country":"BR",
    "wof:name":"Serafim Dias",
    "wof:placetype":"locality"
},
  "geometry": {"coordinates":[-39.66667,-5.71667],"type":"Point"}
}