{
  "type": "Feature",
  "properties": {
    "gn:admin1_code":"22",
    "gn:admin2_code":"2400208.0",
    "gn:asciiname":"Sitio Estevao",
    "gn:country_code":"BR",
    "gn:dem":15,
    "gn:feature_class":"P",
    "gn:feature_code":"PPL",
    "gn:name":"S\u00edtio Estevao",
    "gn:population":0,
    "gn:timezone":"America/Fortaleza",
    "iso:country":"BR",
    "wof:name":"Sitio Estevao",
    "wof:placetype":"locality"
},
  "geometry": {"coordinates":[-36.86528,-5.4125],"type":"Point"}
}