{
  "type": "Feature",
  "properties": {
    "gn:admin1_code":"18.0",
    "gn:admin2_code":"4124103.0",
    "gn:asciiname":"Sitio Americo Bonacim",
    "gn:country_code":"BR",
    "gn:dem":410,
    "gn:feature_class":"P",
    "gn:feature_code":"PPL",
    "gn:name":"S\u00edtio Am\u00e9rico Bonacim",
    "gn:population":0,
    "gn:timezone":"America/Sao_Paulo",
    "iso:country":"BR",
    "name:por_x_preferred":[
        "S\u00edtio Am\u00e9rico Bonacim"
    ],
    "wof:name":"Sitio Americo Bonacim",
    "wof:placetype":"locality"
},
  "geometry": {"coordinates":[-50.2078,-23.1572],"type":"Point"}
}