{
  "type": "Feature",
  "properties": {
    "gn:admin1_code":"15",
    "gn:admin2_code":"3161106.0",
    "gn:asciiname":"Jiboia",
    "gn:country_code":"BR",
    "gn:dem":554,
    "gn:feature_class":"P",
    "gn:feature_code":"PPLL",
    "gn:name":"Jib\u00f3ia",
    "gn:population":0,
    "gn:timezone":"America/Sao_Paulo",
    "iso:country":"BR",
    "name:por_x_preferred":[
        "Jib\u00f3ia"
    ],
    "wof:name":"Jiboia",
    "wof:placetype":"locality"
},
  "geometry": {"coordinates":[-44.85,-16.0925],"type":"Point"}
}