{
  "type": "Feature",
  "properties": {
    "gn:admin1_code":"23",
    "gn:admin2_code":"4308201.0",
    "gn:asciiname":"Joao Betti",
    "gn:country_code":"BR",
    "gn:dem":808,
    "gn:feature_class":"P",
    "gn:feature_code":"PPLL",
    "gn:name":"Jo\u00e3o Betti",
    "gn:population":0,
    "gn:timezone":"America/Sao_Paulo",
    "iso:country":"BR",
    "name:por_x_preferred":[
        "Jo\u00e3o Betti"
    ],
    "wof:name":"Joao Betti",
    "wof:placetype":"locality"
},
  "geometry": {"coordinates":[-51.1519,-29.0506],"type":"Point"}
}