{
  "type": "Feature",
  "properties": {
    "gn:admin1_code":"18.0",
    "gn:admin2_code":"4109500.0",
    "gn:asciiname":"Massarapua",
    "gn:country_code":"BR",
    "gn:dem":8,
    "gn:feature_class":"P",
    "gn:feature_code":"PPLL",
    "gn:name":"Massarapu\u00e3",
    "gn:population":0,
    "gn:timezone":"America/Sao_Paulo",
    "iso:country":"BR",
    "name:por_x_preferred":[
        "Massarapu\u00e3"
    ],
    "wof:name":"Massarapua",
    "wof:placetype":"locality"
},
  "geometry": {"coordinates":[-48.43274,-25.35965],"type":"Point"}
}