{
  "type": "Feature",
  "properties": {
    "gn:admin1_code":"06",
    "gn:admin2_code":"2314003.0",
    "gn:asciiname":"Sitio Charneca",
    "gn:country_code":"BR",
    "gn:dem":463,
    "gn:feature_class":"P",
    "gn:feature_code":"PPL",
    "gn:name":"S\u00edtio Charneca",
    "gn:population":0,
    "gn:timezone":"America/Fortaleza",
    "iso:country":"BR",
    "wof:name":"Sitio Charneca",
    "wof:placetype":"locality"
},
  "geometry": {"coordinates":[-39.31667,-6.71667],"type":"Point"}
}