{
  "type": "Feature",
  "properties": {
    "gn:admin1_code":"18.0",
    "gn:admin2_code":"4113205.0",
    "gn:asciiname":"Sitio Ismael F. da Silva",
    "gn:country_code":"BR",
    "gn:dem":978,
    "gn:feature_class":"P",
    "gn:feature_code":"PPL",
    "gn:name":"S\u00edtio Ismael F. da Silva",
    "gn:population":0,
    "gn:timezone":"America/Sao_Paulo",
    "iso:country":"BR",
    "name:por_x_preferred":[
        "S\u00edtio Ismael F. da Silva"
    ],
    "wof:name":"Sitio Ismael F. da Silva",
    "wof:placetype":"locality"
},
  "geometry": {"coordinates":[-49.9099,-25.7019],"type":"Point"}
}