{
  "type": "Feature",
  "properties": {
    "gn:admin1_code":"27",
    "gn:admin2_code":"3530607.0",
    "gn:asciiname":"Stio Eldorado",
    "gn:country_code":"BR",
    "gn:dem":857,
    "gn:feature_class":"P",
    "gn:feature_code":"PPL",
    "gn:name":"Stio Eldorado",
    "gn:population":0,
    "gn:timezone":"America/Sao_Paulo",
    "iso:country":"BR",
    "name:por_x_preferred":[
        "Stio Eldorado"
    ],
    "wof:name":"Stio Eldorado",
    "wof:placetype":"locality"
},
  "geometry": {"coordinates":[-46.1125,-23.4625],"type":"Point"}
}