{
  "type": "Feature",
  "properties": {
    "gn:admin1_code":"17",
    "gn:admin2_code":"2505600.0",
    "gn:asciiname":"Pontais",
    "gn:country_code":"BR",
    "gn:dem":357,
    "gn:feature_class":"P",
    "gn:feature_code":"PPL",
    "gn:name":"Pontais",
    "gn:population":0,
    "gn:timezone":"America/Fortaleza",
    "iso:country":"BR",
    "wof:name":"Pontais",
    "wof:placetype":"locality"
},
  "geometry": {"coordinates":[-38.36667,-7.41667],"type":"Point"}
}