{
  "type": "Feature",
  "properties": {
    "gn:admin1_code":"18",
    "gn:admin2_code":"4109500.0",
    "gn:asciiname":"Barra do Cedro",
    "gn:country_code":"BR",
    "gn:dem":29,
    "gn:feature_class":"P",
    "gn:feature_code":"PPLL",
    "gn:name":"Barra do Cedro",
    "gn:population":0,
    "gn:timezone":"America/Sao_Paulo",
    "iso:country":"BR",
    "name:por_x_preferred":[
        "Barra do Cedro"
    ],
    "wof:name":"Barra do Cedro",
    "wof:placetype":"locality"
},
  "geometry": {"coordinates":[-48.22,-25.15917],"type":"Point"}
}