{
  "type": "Feature",
  "properties": {
    "gn:admin1_code":"22",
    "gn:admin2_code":"2410702.0",
    "gn:asciiname":"Riacho da Cruz",
    "gn:country_code":"BR",
    "gn:dem":171,
    "gn:feature_class":"P",
    "gn:feature_code":"PPL",
    "gn:name":"Riacho da Cruz",
    "gn:population":0,
    "gn:timezone":"America/Fortaleza",
    "iso:country":"BR",
    "wof:name":"Riacho da Cruz",
    "wof:placetype":"locality"
},
  "geometry": {"coordinates":[-37.94639,-5.93639],"type":"Point"}
}