{
  "type": "Feature",
  "properties": {
    "gn:admin1_code":"22",
    "gn:admin2_code":"2410702.0",
    "gn:asciiname":"Riacho da Cruz",
    "gn:country_code":"BR",
    "gn:dem":171,
    "gn:feature_class":"P",
    "gn:feature_code":"PPL",
    "gn:name":"Riacho da Cruz",
    "gn:population":0,
    "gn:timezone":"America/Fortaleza",
    "iso:country":"BR",
    "name:bpy_x_preferred":[
        "\u09b0\u09bf\u09af\u09bc\u09be\u0995\u09b9\u09cb \u09a1\u09be \u0995\u09cd\u09b0\u09c1\u099c"
    ],
    "name:epo_x_preferred":[
        "Riacho da Cruz"
    ],
    "name:eus_x_preferred":[
        "Riacho da Cruz"
    ],
    "name:fra_x_preferred":[
        "Riacho da Cruz"
    ],
    "name:ita_x_preferred":[
        "Riacho da Cruz"
    ],
    "name:kat_x_preferred":[
        "\u10e0\u10d8\u10d0\u10e8\u10e3-\u10d3\u10d0-\u10d9\u10e0\u10e3\u10e1\u10d8"
    ],
    "name:kaz_x_preferred":[
        "\u0420\u0438\u0430\u0448\u0443-\u0434\u0430-\u041a\u0440\u0443\u0441"
    ],
    "name:mlg_x_preferred":[
        "Riacho da Cruz"
    ],
    "name:nld_x_preferred":[
        "Riacho da Cruz"
    ],
    "name:nor_x_preferred":[
        "Riacho da Cruz"
    ],
    "name:por_x_preferred":[
        "Riacho da Cruz"
    ],
    "name:ron_x_preferred":[
        "Riacho da Cruz"
    ],
    "name:rus_x_preferred":[
        "\u0420\u0438\u0430\u0448\u0443-\u0434\u0430-\u041a\u0440\u0443\u0441"
    ],
    "name:vie_x_preferred":[
        "Riacho da Cruz"
    ],
    "name:vol_x_preferred":[
        "Riacho da Cruz"
    ],
    "name:war_x_preferred":[
        "Riacho da Cruz"
    ],
    "name:zho_x_preferred":[
        "\u91cc\u4e9a\u8212-\u8fbe\u514b\u9c81\u65af"
    ],
    "wof:name":"Riacho da Cruz",
    "wof:placetype":"locality"
},
  "geometry": {"coordinates":[-37.94639,-5.93639],"type":"Point"}
}