{
  "type": "Feature",
  "properties": {
    "gn:admin1_code":"18.0",
    "gn:admin2_code":"4126603.0",
    "gn:asciiname":"Sitio Helio Velasques",
    "gn:country_code":"BR",
    "gn:dem":579,
    "gn:feature_class":"P",
    "gn:feature_code":"PPL",
    "gn:name":"S\u00edtio H\u00e9lio Velasques",
    "gn:population":0,
    "gn:timezone":"America/Sao_Paulo",
    "iso:country":"BR",
    "name:por_x_preferred":[
        "S\u00edtio H\u00e9lio Velasques"
    ],
    "wof:name":"Sitio Helio Velasques",
    "wof:placetype":"locality"
},
  "geometry": {"coordinates":[-49.7603,-23.6718],"type":"Point"}
}