{
  "type": "Feature",
  "properties": {
    "gn:admin1_code":"18.0",
    "gn:admin2_code":"4126603.0",
    "gn:asciiname":"Freitas",
    "gn:country_code":"BR",
    "gn:dem":583,
    "gn:feature_class":"P",
    "gn:feature_code":"PPLL",
    "gn:name":"Freitas",
    "gn:population":0,
    "gn:timezone":"America/Sao_Paulo",
    "iso:country":"BR",
    "name:cat_x_preferred":[
        "Freitas"
    ],
    "name:deu_x_preferred":[
        "Freitas"
    ],
    "name:fra_x_preferred":[
        "Freitas"
    ],
    "name:por_x_preferred":[
        "Freitas"
    ],
    "name:rus_x_preferred":[
        "\u0424\u0440\u0435\u0439\u0442\u0430\u0448"
    ],
    "wof:name":"Freitas",
    "wof:placetype":"locality"
},
  "geometry": {"coordinates":[-49.7532,-23.6854],"type":"Point"}
}