{
  "type": "Feature",
  "properties": {
    "gn:admin1_code":"18",
    "gn:admin2_code":"4100301.0",
    "gn:asciiname":"Sitio Ari P. da Cruz",
    "gn:country_code":"BR",
    "gn:dem":887,
    "gn:feature_class":"P",
    "gn:feature_code":"PPL",
    "gn:name":"S\u00edtio Ari P. da Cruz",
    "gn:population":0,
    "gn:timezone":"America/Sao_Paulo",
    "iso:country":"BR",
    "name:por_x_preferred":[
        "S\u00edtio Ari P. da Cruz"
    ],
    "wof:name":"Sitio Ari P. da Cruz",
    "wof:placetype":"locality"
},
  "geometry": {"coordinates":[-49.2575,-26.0077],"type":"Point"}
}