{
  "type": "Feature",
  "properties": {
    "gn:admin1_code":"27",
    "gn:admin2_code":"3538808.0",
    "gn:asciiname":"Jurumirim",
    "gn:country_code":"BR",
    "gn:dem":556,
    "gn:feature_class":"P",
    "gn:feature_code":"PPL",
    "gn:name":"Jurumirim",
    "gn:population":0,
    "gn:timezone":"America/Sao_Paulo",
    "iso:country":"BR",
    "name:por_x_preferred":[
        "Jurumirim"
    ],
    "wof:name":"Jurumirim",
    "wof:placetype":"locality"
},
  "geometry": {"coordinates":[-49.26667,-23.18333],"type":"Point"}
}