{
  "type": "Feature",
  "properties": {
    "gn:admin1_code":"18.0",
    "gn:admin2_code":"4124707.0",
    "gn:asciiname":"Sitio Jaime de Melo",
    "gn:country_code":"BR",
    "gn:dem":1019,
    "gn:feature_class":"P",
    "gn:feature_code":"PPL",
    "gn:name":"S\u00edtio Jaime de Melo",
    "gn:population":0,
    "gn:timezone":"America/Sao_Paulo",
    "iso:country":"BR",
    "name:por_x_preferred":[
        "S\u00edtio Jaime de Melo"
    ],
    "wof:name":"Sitio Jaime de Melo",
    "wof:placetype":"locality"
},
  "geometry": {"coordinates":[-50.71369,-23.76107],"type":"Point"}
}