{
  "type": "Feature",
  "properties": {
    "gn:admin1_code":"27.0",
    "gn:admin2_code":"3548708.0",
    "gn:asciiname":"Nucleo Santa Cruz",
    "gn:country_code":"BR",
    "gn:dem":768,
    "gn:feature_class":"P",
    "gn:feature_code":"PPLL",
    "gn:name":"N\u00facleo Santa Cruz",
    "gn:population":0,
    "gn:timezone":"America/Sao_Paulo",
    "iso:country":"BR",
    "name:por_x_preferred":[
        "N\u00facleo Santa Cruz"
    ],
    "wof:name":"Nucleo Santa Cruz",
    "wof:placetype":"locality"
},
  "geometry": {"coordinates":[-46.59625,-23.84277],"type":"Point"}
}