{
  "type": "Feature",
  "properties": {
    "gn:admin1_code":"27.0",
    "gn:admin2_code":"3502705.0",
    "gn:asciiname":"Sitio Rio Acima",
    "gn:country_code":"BR",
    "gn:dem":616,
    "gn:feature_class":"P",
    "gn:feature_code":"PPL",
    "gn:name":"S\u00edtio Rio Acima",
    "gn:population":0,
    "gn:timezone":"America/Sao_Paulo",
    "iso:country":"BR",
    "name:por_x_preferred":[
        "S\u00edtio Rio Acima"
    ],
    "wof:name":"Sitio Rio Acima",
    "wof:placetype":"locality"
},
  "geometry": {"coordinates":[-48.79084,-24.54771],"type":"Point"}
}