{
  "type": "Feature",
  "properties": {
    "gn:admin1_code":"15",
    "gn:admin2_code":"3119302.0",
    "gn:asciiname":"Pantano",
    "gn:country_code":"BR",
    "gn:dem":1037,
    "gn:feature_class":"P",
    "gn:feature_code":"PPL",
    "gn:name":"P\u00e2ntano",
    "gn:population":0,
    "gn:timezone":"America/Sao_Paulo",
    "iso:country":"BR",
    "name:ceb_x_preferred":[
        "Pantano"
    ],
    "name:deu_x_preferred":[
        "Pantano"
    ],
    "name:ita_x_preferred":[
        "Pantano"
    ],
    "name:pol_x_preferred":[
        "Pantano"
    ],
    "name:por_x_preferred":[
        "P\u00e2ntano"
    ],
    "name:rus_x_preferred":[
        "\u041f\u0430\u043d\u0442\u0430\u043d\u043e"
    ],
    "name:spa_x_preferred":[
        "Pantano"
    ],
    "name:srp_x_preferred":[
        "Pantano"
    ],
    "name:swe_x_preferred":[
        "Pantano"
    ],
    "wof:name":"Pantano",
    "wof:placetype":"locality"
},
  "geometry": {"coordinates":[-46.83333,-18.55],"type":"Point"}
}