{
  "type": "Feature",
  "properties": {
    "gn:admin1_code":"20",
    "gn:admin2_code":"2205599.0",
    "gn:asciiname":"Teodoro",
    "gn:country_code":"BR",
    "gn:dem":357,
    "gn:feature_class":"P",
    "gn:feature_code":"PPL",
    "gn:name":"Teodoro",
    "gn:population":0,
    "gn:timezone":"America/Fortaleza",
    "iso:country":"BR",
    "name:deu_x_preferred":[
        "Teodoro"
    ],
    "name:glg_x_preferred":[
        "Teodoro"
    ],
    "name:ita_x_preferred":[
        "Teodoro"
    ],
    "name:por_x_preferred":[
        "Teodoro"
    ],
    "name:spa_x_preferred":[
        "Teodoro"
    ],
    "wof:name":"Teodoro",
    "wof:placetype":"locality"
},
  "geometry": {"coordinates":[-41.35,-6.56667],"type":"Point"}
}