{
  "type": "Feature",
  "properties": {
    "gn:admin1_code":"27",
    "gn:admin2_code":"3526100.0",
    "gn:asciiname":"Bom Jardim",
    "gn:country_code":"BR",
    "gn:dem":67,
    "gn:feature_class":"P",
    "gn:feature_code":"PPL",
    "gn:name":"Bom Jardim",
    "gn:population":0,
    "gn:timezone":"America/Sao_Paulo",
    "iso:country":"BR",
    "name:ceb_x_preferred":[
        "Bom Jardim"
    ],
    "name:deu_x_preferred":[
        "Bom Jardim"
    ],
    "name:fra_x_preferred":[
        "Bom Jardim"
    ],
    "name:ita_x_preferred":[
        "Bom Jardim"
    ],
    "name:nld_x_preferred":[
        "Bom Jardim"
    ],
    "name:nor_x_preferred":[
        "Bom Jardim"
    ],
    "name:por_x_preferred":[
        "Bom Jardim"
    ],
    "name:swe_x_preferred":[
        "Bom Jardim"
    ],
    "name:vol_x_preferred":[
        "Bom Jardim"
    ],
    "wof:name":"Bom Jardim",
    "wof:placetype":"locality"
},
  "geometry": {"coordinates":[-47.61667,-24.18333],"type":"Point"}
}