{
  "type": "Feature",
  "properties": {
    "gn:admin1_code":"20",
    "gn:admin2_code":"2200459.0",
    "gn:asciiname":"Mangabeira",
    "gn:country_code":"BR",
    "gn:dem":272,
    "gn:feature_class":"P",
    "gn:feature_code":"PPL",
    "gn:name":"Mangabeira",
    "gn:population":0,
    "gn:timezone":"America/Fortaleza",
    "iso:country":"BR",
    "wof:name":"Mangabeira",
    "wof:placetype":"locality"
},
  "geometry": {"coordinates":[-44.01667,-8.55],"type":"Point"}
}