{
  "type": "Feature",
  "properties": {
    "gn:admin1_code":"5",
    "gn:admin2_code":"2917805.0",
    "gn:asciiname":"Garibe",
    "gn:country_code":"BR",
    "gn:dem":4,
    "gn:feature_class":"P",
    "gn:feature_code":"PPL",
    "gn:name":"Garib\u00e9",
    "gn:population":0,
    "gn:timezone":"America/Bahia",
    "iso:country":"BR",
    "wof:name":"Garibe",
    "wof:placetype":"locality"
},
  "geometry": {"coordinates":[-38.98333,-13.13333],"type":"Point"}
}