{
  "type": "Feature",
  "properties": {
    "gn:admin1_code":"27.0",
    "gn:admin2_code":"3524600.0",
    "gn:asciiname":"Sitio Padre Andre",
    "gn:country_code":"BR",
    "gn:dem":34,
    "gn:feature_class":"P",
    "gn:feature_code":"PPL",
    "gn:name":"S\u00edtio Padre Andr\u00e9",
    "gn:population":0,
    "gn:timezone":"America/Sao_Paulo",
    "iso:country":"BR",
    "name:por_x_preferred":[
        "S\u00edtio Padre Andr\u00e9"
    ],
    "wof:name":"Sitio Padre Andre",
    "wof:placetype":"locality"
},
  "geometry": {"coordinates":[-48.02223,-24.61194],"type":"Point"}
}