{
  "type": "Feature",
  "properties": {
    "gn:admin1_code":"5",
    "gn:admin2_code":"2911907.0",
    "gn:asciiname":"Umbuzeiro",
    "gn:country_code":"BR",
    "gn:dem":576,
    "gn:feature_class":"P",
    "gn:feature_code":"PPL",
    "gn:name":"Umbuzeiro",
    "gn:population":0,
    "gn:timezone":"America/Bahia",
    "iso:country":"BR",
    "name:bpy_x_preferred":[
        "\u0989\u09ae\u09ac\u09c1\u099c\u09af\u09bc\u09c7\u0987\u09b0\u09cb"
    ],
    "name:ceb_x_preferred":[
        "Umbuzeiro"
    ],
    "name:eus_x_preferred":[
        "Umbuzeiro"
    ],
    "name:fra_x_preferred":[
        "Umbuzeiro"
    ],
    "name:ita_x_preferred":[
        "Umbuzeiro"
    ],
    "name:kat_x_preferred":[
        "\u10e3\u10db\u10d1\u10e3\u10d6\u10d4\u10d8\u10e0\u10e3"
    ],
    "name:kaz_x_preferred":[
        "\u0423\u043c\u0431\u0443\u0437\u0435\u0439\u0440\u0443"
    ],
    "name:nld_x_preferred":[
        "Umbuzeiro"
    ],
    "name:nor_x_preferred":[
        "Umbuzeiro"
    ],
    "name:por_x_preferred":[
        "Umbuzeiro"
    ],
    "name:ron_x_preferred":[
        "Umbuzeiro"
    ],
    "name:rus_x_preferred":[
        "\u0423\u043c\u0431\u0443\u0437\u0435\u0439\u0440\u0443"
    ],
    "name:spa_x_preferred":[
        "Umbuzeiro"
    ],
    "name:swe_x_preferred":[
        "Umbuzeiro"
    ],
    "name:ukr_x_preferred":[
        "\u0423\u043c\u0431\u0443\u0437\u0435\u0439\u0440\u0443"
    ],
    "name:vol_x_preferred":[
        "Umbuzeiro"
    ],
    "name:war_x_preferred":[
        "Umbuzeiro"
    ],
    "name:zho_x_preferred":[
        "\u6e29\u5e03\u6cfd\u9c81"
    ],
    "wof:name":"Umbuzeiro",
    "wof:placetype":"locality"
},
  "geometry": {"coordinates":[-39.98333,-12.95],"type":"Point"}
}