{
  "type": "Feature",
  "properties": {
    "gn:admin1_code":"5",
    "gn:admin2_code":"2911907.0",
    "gn:asciiname":"Umbuzeiro",
    "gn:country_code":"BR",
    "gn:dem":576,
    "gn:feature_class":"P",
    "gn:feature_code":"PPL",
    "gn:name":"Umbuzeiro",
    "gn:population":0,
    "gn:timezone":"America/Bahia",
    "iso:country":"BR",
    "wof:name":"Umbuzeiro",
    "wof:placetype":"locality"
},
  "geometry": {"coordinates":[-39.98333,-12.95],"type":"Point"}
}