{
  "type": "Feature",
  "properties": {
    "gn:admin1_code":"6",
    "gn:admin2_code":"2300754.0",
    "gn:asciiname":"Baixa Grande",
    "gn:country_code":"BR",
    "gn:dem":49,
    "gn:feature_class":"P",
    "gn:feature_code":"PPL",
    "gn:name":"Baixa Grande",
    "gn:population":0,
    "gn:timezone":"America/Fortaleza",
    "iso:country":"BR",
    "name:bpy_x_preferred":[
        "\u09ac\u09be\u0987\u0995\u09cd\u09b8\u09be \u0997\u09cd\u09b0\u09be\u09a8\u09cd\u09a1\u09c7"
    ],
    "name:ceb_x_preferred":[
        "Baixa Grande"
    ],
    "name:epo_x_preferred":[
        "Baixa Grande"
    ],
    "name:eus_x_preferred":[
        "Baixa Grande"
    ],
    "name:fra_x_preferred":[
        "Baixa Grande"
    ],
    "name:hye_x_preferred":[
        "\u0532\u0561\u0575\u0577\u0561 \u0533\u0580\u0561\u0576\u0564\u056b"
    ],
    "name:ita_x_preferred":[
        "Baixa Grande"
    ],
    "name:kat_x_preferred":[
        "\u10d1\u10d0\u10d8\u10e8\u10d0-\u10d2\u10e0\u10d0\u10dc\u10d3\u10d8"
    ],
    "name:kaz_x_preferred":[
        "\u0411\u0430\u0439\u0448\u0430-\u0413\u0440\u0430\u043d\u0434\u0438"
    ],
    "name:mlg_x_preferred":[
        "Baixa Grande"
    ],
    "name:nld_x_preferred":[
        "Baixa Grande"
    ],
    "name:nor_x_preferred":[
        "Baixa Grande"
    ],
    "name:pol_x_preferred":[
        "Baixa Grande"
    ],
    "name:por_x_preferred":[
        "Baixa Grande"
    ],
    "name:ron_x_preferred":[
        "Baixa Grande"
    ],
    "name:rus_x_preferred":[
        "\u0411\u0430\u0439\u0448\u0430-\u0413\u0440\u0430\u043d\u0434\u0438"
    ],
    "name:spa_x_preferred":[
        "Baixa Grande"
    ],
    "name:swe_x_preferred":[
        "Baixa Grande"
    ],
    "name:vie_x_preferred":[
        "Baixa Grande"
    ],
    "name:vol_x_preferred":[
        "Baixa Grande"
    ],
    "name:war_x_preferred":[
        "Baixa Grande"
    ],
    "name:zho_x_preferred":[
        "\u5927\u62dc\u6c99"
    ],
    "wof:name":"Baixa Grande",
    "wof:placetype":"locality"
},
  "geometry": {"coordinates":[-39.81667,-3.21667],"type":"Point"}
}