{
  "type": "Feature",
  "properties": {
    "gn:admin1_code":"6",
    "gn:admin2_code":"2300754.0",
    "gn:asciiname":"Baixa Grande",
    "gn:country_code":"BR",
    "gn:dem":49,
    "gn:feature_class":"P",
    "gn:feature_code":"PPL",
    "gn:name":"Baixa Grande",
    "gn:population":0,
    "gn:timezone":"America/Fortaleza",
    "iso:country":"BR",
    "wof:name":"Baixa Grande",
    "wof:placetype":"locality"
},
  "geometry": {"coordinates":[-39.81667,-3.21667],"type":"Point"}
}