{
  "type": "Feature",
  "properties": {
    "gn:admin1_code":"18.0",
    "gn:admin2_code":"4113205.0",
    "gn:asciiname":"Cerro Alegre",
    "gn:country_code":"BR",
    "gn:dem":782,
    "gn:feature_class":"P",
    "gn:feature_code":"PPLL",
    "gn:name":"Cerro Alegre",
    "gn:population":0,
    "gn:timezone":"America/Sao_Paulo",
    "iso:country":"BR",
    "name:por_x_preferred":[
        "Cerro Alegre"
    ],
    "wof:name":"Cerro Alegre",
    "wof:placetype":"locality"
},
  "geometry": {"coordinates":[-50.04933,-25.75802],"type":"Point"}
}