{
  "type": "Feature",
  "properties": {
    "gn:admin1_code":"5",
    "gn:admin2_code":"2901403.0",
    "gn:asciiname":"Riachao",
    "gn:country_code":"BR",
    "gn:dem":464,
    "gn:feature_class":"P",
    "gn:feature_code":"PPL",
    "gn:name":"Riach\u00e3o",
    "gn:population":0,
    "gn:timezone":"America/Bahia",
    "iso:country":"BR",
    "wof:name":"Riachao",
    "wof:placetype":"locality"
},
  "geometry": {"coordinates":[-44.51667,-11.98333],"type":"Point"}
}