{
  "type": "Feature",
  "properties": {
    "gn:admin1_code":"18.0",
    "gn:admin2_code":"4107009.0",
    "gn:asciiname":"Sitio Orlando Avanco",
    "gn:country_code":"BR",
    "gn:dem":818,
    "gn:feature_class":"P",
    "gn:feature_code":"PPL",
    "gn:name":"S\u00edtio Orlando Avan\u00e7o",
    "gn:population":0,
    "gn:timezone":"America/Sao_Paulo",
    "iso:country":"BR",
    "name:por_x_preferred":[
        "S\u00edtio Orlando Avan\u00e7o"
    ],
    "wof:name":"Sitio Orlando Avanco",
    "wof:placetype":"locality"
},
  "geometry": {"coordinates":[-50.44837,-23.99259],"type":"Point"}
}