{
  "type": "Feature",
  "properties": {
    "gn:admin1_code":"20",
    "gn:admin2_code":"2209500.0",
    "gn:asciiname":"Estreito",
    "gn:country_code":"BR",
    "gn:dem":250,
    "gn:feature_class":"P",
    "gn:feature_code":"PPL",
    "gn:name":"Estreito",
    "gn:population":0,
    "gn:timezone":"America/Fortaleza",
    "iso:country":"BR",
    "wof:name":"Estreito",
    "wof:placetype":"locality"
},
  "geometry": {"coordinates":[-41.88333,-7.38333],"type":"Point"}
}