{
  "type": "Feature",
  "properties": {
    "gn:admin1_code":"17",
    "gn:admin2_code":"2510907.0",
    "gn:asciiname":"Ponta da Serra",
    "gn:country_code":"BR",
    "gn:dem":359,
    "gn:feature_class":"P",
    "gn:feature_code":"PPL",
    "gn:name":"Ponta da Serra",
    "gn:population":0,
    "gn:timezone":"America/Fortaleza",
    "iso:country":"BR",
    "wof:name":"Ponta da Serra",
    "wof:placetype":"locality"
},
  "geometry": {"coordinates":[-37.6195,-6.53322],"type":"Point"}
}