{
  "type": "Feature",
  "properties": {
    "gn:admin1_code":"5",
    "gn:admin2_code":"2932507.0",
    "gn:asciiname":"Nucleo Colonial de Uma",
    "gn:country_code":"BR",
    "gn:dem":104,
    "gn:feature_class":"P",
    "gn:feature_code":"PPL",
    "gn:name":"N\u00facleo Colonial de Uma",
    "gn:population":0,
    "gn:timezone":"America/Bahia",
    "iso:country":"BR",
    "name:und_x_variant":[
        "N\u00facleo Colonial de Una",
        "N\u00facleo Colonial de Uma",
        "Col\u00f4nia do Una"
    ],
    "wof:name":"Nucleo Colonial de Uma",
    "wof:placetype":"locality"
},
  "geometry": {"coordinates":[-39.14644000000001,-15.26257],"type":"Point"}
}