{
  "type": "Feature",
  "properties": {
    "gn:admin1_code":"14",
    "gn:admin2_code":"5100805.0",
    "gn:asciiname":"Liberdade",
    "gn:country_code":"BR",
    "gn:dem":112,
    "gn:feature_class":"P",
    "gn:feature_code":"PPL",
    "gn:name":"Liberdade",
    "gn:population":0,
    "gn:timezone":"America/Cuiaba",
    "iso:country":"BR",
    "wof:name":"Liberdade",
    "wof:placetype":"locality"
},
  "geometry": {"coordinates":[-58.03333000000001,-7.46667],"type":"Point"}
}