{
  "type": "Feature",
  "properties": {
    "gn:admin1_code":"18",
    "gn:admin2_code":"4124020.0",
    "gn:asciiname":"Caroveira",
    "gn:cc2":"BR",
    "gn:country_code":"BR",
    "gn:dem":608,
    "gn:feature_class":"P",
    "gn:feature_code":"PPL",
    "gn:name":"Caroveira",
    "gn:population":0,
    "gn:timezone":"America/Sao_Paulo",
    "iso:country":"BR",
    "name:und_x_variant":[
        "Coroveira",
        "Caroveira"
    ],
    "wof:name":"Caroveira",
    "wof:placetype":"locality"
},
  "geometry": {"coordinates":[-53.55,-25.16667],"type":"Point"}
}