{
  "type": "Feature",
  "properties": {
    "gn:admin1_code":"15",
    "gn:admin2_code":"3140506.0",
    "gn:asciiname":"Retiro",
    "gn:country_code":"BR",
    "gn:dem":636,
    "gn:feature_class":"P",
    "gn:feature_code":"PPL",
    "gn:name":"Retiro",
    "gn:population":0,
    "gn:timezone":"America/Sao_Paulo",
    "iso:country":"BR",
    "name:cat_x_preferred":[
        "Retiro"
    ],
    "name:ceb_x_preferred":[
        "Retiro"
    ],
    "name:deu_x_preferred":[
        "Retiro"
    ],
    "name:eus_x_preferred":[
        "Retiro"
    ],
    "name:fra_x_preferred":[
        "Retiro"
    ],
    "name:ita_x_preferred":[
        "Retiro"
    ],
    "name:jpn_x_preferred":[
        "\u30ec\u30c6\u30a3\u30fc\u30ed"
    ],
    "name:kor_x_preferred":[
        "\ub808\ud2f0\ub85c"
    ],
    "name:mlg_x_preferred":[
        "Retiro"
    ],
    "name:nld_x_preferred":[
        "Retiro"
    ],
    "name:pol_x_preferred":[
        "Retiro"
    ],
    "name:por_x_preferred":[
        "Retiro"
    ],
    "name:rus_x_preferred":[
        "\u0420\u0435\u0442\u0438\u0440\u043e"
    ],
    "name:sco_x_preferred":[
        "Retiro"
    ],
    "name:spa_x_preferred":[
        "Retiro"
    ],
    "name:swe_x_preferred":[
        "Retiro"
    ],
    "name:ukr_x_preferred":[
        "\u0420\u0435\u0442\u0456\u0440\u043e"
    ],
    "name:vie_x_preferred":[
        "Retiro"
    ],
    "wof:name":"Retiro",
    "wof:placetype":"locality"
},
  "geometry": {"coordinates":[-45.08333,-19.38333],"type":"Point"}
}