{
  "type": "Feature",
  "properties": {
    "gn:admin1_code":"21",
    "gn:admin2_code":"3305604.0",
    "gn:asciiname":"Poco d'Anta",
    "gn:country_code":"BR",
    "gn:dem":12,
    "gn:feature_class":"P",
    "gn:feature_code":"PPL",
    "gn:name":"Po\u00e7o d\u2019Anta",
    "gn:population":0,
    "gn:timezone":"America/Sao_Paulo",
    "iso:country":"BR",
    "name:por_x_preferred":[
        "Po\u00e7o d\u2019Anta"
    ],
    "wof:name":"Poco d'Anta",
    "wof:placetype":"locality"
},
  "geometry": {"coordinates":[-42.28333,-22.58333],"type":"Point"}
}