{
  "type": "Feature",
  "properties": {
    "gn:admin1_code":"06",
    "gn:admin2_code":"2312205.0",
    "gn:asciiname":"Fazenda Carauba",
    "gn:country_code":"BR",
    "gn:dem":256,
    "gn:feature_class":"P",
    "gn:feature_code":"PPL",
    "gn:name":"Fazenda Cara\u00faba",
    "gn:population":0,
    "gn:timezone":"America/Fortaleza",
    "iso:country":"BR",
    "wof:name":"Fazenda Carauba",
    "wof:placetype":"locality"
},
  "geometry": {"coordinates":[-39.95,-4.45],"type":"Point"}
}