{
  "type": "Feature",
  "properties": {
    "gn:admin1_code":"16.0",
    "gn:admin2_code":"1506187.0",
    "gn:asciiname":"Palestina",
    "gn:country_code":"BR",
    "gn:dem":233,
    "gn:feature_class":"P",
    "gn:feature_code":"PPL",
    "gn:name":"Palestina",
    "gn:population":0,
    "gn:timezone":"America/Belem",
    "iso:country":"BR",
    "wof:name":"Palestina",
    "wof:placetype":"locality"
},
  "geometry": {"coordinates":[-47.9371,-4.67828],"type":"Point"}
}