{
  "type": "Feature",
  "properties": {
    "gn:admin1_code":"18.0",
    "gn:admin2_code":"4117305.0",
    "gn:asciiname":"Sitio Bonfim",
    "gn:country_code":"BR",
    "gn:dem":671,
    "gn:feature_class":"P",
    "gn:feature_code":"PPL",
    "gn:name":"S\u00edtio Bonfim",
    "gn:population":0,
    "gn:timezone":"America/Sao_Paulo",
    "iso:country":"BR",
    "name:por_x_preferred":[
        "S\u00edtio Bonfim"
    ],
    "wof:name":"Sitio Bonfim",
    "wof:placetype":"locality"
},
  "geometry": {"coordinates":[-50.8957,-23.9396],"type":"Point"}
}