{
  "type": "Feature",
  "properties": {
    "gn:admin1_code":"17",
    "gn:admin2_code":"2507002.0",
    "gn:asciiname":"Cochos",
    "gn:country_code":"BR",
    "gn:dem":360,
    "gn:feature_class":"P",
    "gn:feature_code":"PPL",
    "gn:name":"Cochos",
    "gn:population":0,
    "gn:timezone":"America/Fortaleza",
    "iso:country":"BR",
    "wof:name":"Cochos",
    "wof:placetype":"locality"
},
  "geometry": {"coordinates":[-38.18333,-7.21667],"type":"Point"}
}