{
  "type": "Feature",
  "properties": {
    "gn:admin1_code":"30",
    "gn:admin2_code":"2600500.0",
    "gn:asciiname":"Imprensa",
    "gn:country_code":"BR",
    "gn:dem":484,
    "gn:feature_class":"P",
    "gn:feature_code":"PPL",
    "gn:name":"Imprensa",
    "gn:population":0,
    "gn:timezone":"America/Maceio",
    "iso:country":"BR",
    "wof:name":"Imprensa",
    "wof:placetype":"locality"
},
  "geometry": {"coordinates":[-37.16667,-9.26667],"type":"Point"}
}