{
  "type": "Feature",
  "properties": {
    "gn:admin1_code":"18.0",
    "gn:admin2_code":"4106209.0",
    "gn:asciiname":"Sitio Felix Kulevisck",
    "gn:country_code":"BR",
    "gn:dem":925,
    "gn:feature_class":"P",
    "gn:feature_code":"PPL",
    "gn:name":"S\u00edtio F\u00e9lix Kulevisck",
    "gn:population":0,
    "gn:timezone":"America/Sao_Paulo",
    "iso:country":"BR",
    "name:por_x_preferred":[
        "S\u00edtio F\u00e9lix Kulevisck"
    ],
    "wof:name":"Sitio Felix Kulevisck",
    "wof:placetype":"locality"
},
  "geometry": {"coordinates":[-49.5259,-25.7523],"type":"Point"}
}