{
  "type": "Feature",
  "properties": {
    "gn:admin1_code":"27",
    "gn:admin2_code":"3550605.0",
    "gn:asciiname":"Sitio Sumauma",
    "gn:country_code":"BR",
    "gn:dem":862,
    "gn:feature_class":"P",
    "gn:feature_code":"PPL",
    "gn:name":"S\u00edtio Suma\u00fama",
    "gn:population":0,
    "gn:timezone":"America/Sao_Paulo",
    "iso:country":"BR",
    "name:por_x_preferred":[
        "S\u00edtio Suma\u00fama"
    ],
    "wof:name":"Sitio Sumauma",
    "wof:placetype":"locality"
},
  "geometry": {"coordinates":[-47.16217,-23.55881],"type":"Point"}
}