{
  "type": "Feature",
  "properties": {
    "iso:country":"BR",
    "name:por_x_preferred":[
        "Santa Catarina"
    ],
    "name:unk_x_variant":[
        "Santa Catarina"
    ],
    "qs:gn_adm0_cc":"BR",
    "qs:gn_local":3466537,
    "qs:gn_nam_loc":"Caxias do Sul, Rio Grande do Sul, BR",
    "qs:gn_namadm1":"23",
    "qs:local_max":1157,
    "qs:local_sum":2127,
    "qs:localhoods":8,
    "qs:name":"Santa Catarina",
    "qs:name_adm0":"Brasil",
    "qs:name_adm1":"Rio Grande do Sul",
    "qs:name_adm2":"Caxias do Sul",
    "qs:name_local":"Caxias do Sul",
    "qs:photo_max":23,
    "qs:photo_sum":26,
    "qs:placetype":"Suburb",
    "qs:quad_count":4,
    "qs:woe_adm0":23424768,
    "qs:woe_adm1":2344864,
    "qs:woe_adm2":12581299,
    "qs:woe_lau":0,
    "qs:woe_local":429100,
    "qs:woe_ver":"7.10.0",
    "wof:lang":[
        "por"
    ],
    "wof:name":"Santa Catarina",
    "wof:placetype":"neighbourhood"
},
  "geometry": {"coordinates":[-51.210023,-29.150132],"type":"Point"}
}