{
  "type": "Feature",
  "properties": {
    "iso:country":"BR",
    "name:bre_x_preferred":[
        "Santa Catarina"
    ],
    "name:cat_x_preferred":[
        "Santa Catarina"
    ],
    "name:ceb_x_preferred":[
        "Santa Catarina"
    ],
    "name:deu_x_preferred":[
        "Santa Catarina"
    ],
    "name:epo_x_preferred":[
        "Sankta Katarino"
    ],
    "name:fin_x_preferred":[
        "Santa Catarina"
    ],
    "name:fra_x_preferred":[
        "Santa Catarina"
    ],
    "name:glg_x_preferred":[
        "Santa Catarina"
    ],
    "name:hrv_x_preferred":[
        "Santa Catarina"
    ],
    "name:hun_x_preferred":[
        "Santa Catarina"
    ],
    "name:ita_x_preferred":[
        "Santa Catarina"
    ],
    "name:jpn_x_preferred":[
        "\u30b5\u30f3\u30bf\u30ab\u30bf\u30ea\u30ca"
    ],
    "name:kor_x_preferred":[
        "\uc0b0\ud0c0\uce74\ud0c0\ub9ac\ub098"
    ],
    "name:nld_x_preferred":[
        "Santa Catarina"
    ],
    "name:nor_x_preferred":[
        "Santa Catarina"
    ],
    "name:pol_x_preferred":[
        "Santa Catarina"
    ],
    "name:por_x_preferred":[
        "Santa Catarina"
    ],
    "name:rus_x_preferred":[
        "\u0421\u0430\u043d\u0442\u0430-\u041a\u0430\u0442\u0430\u0440\u0438\u043d\u0430"
    ],
    "name:scn_x_preferred":[
        "Santa Catarina"
    ],
    "name:sco_x_preferred":[
        "Santa Catarina"
    ],
    "name:spa_x_preferred":[
        "Santa Catarina"
    ],
    "name:srp_x_preferred":[
        "\u0421\u0430\u043d\u0442\u0430 \u041a\u0430\u0442\u0430\u0440\u0438\u043d\u0430"
    ],
    "name:swe_x_preferred":[
        "Santa Catarina"
    ],
    "name:tur_x_preferred":[
        "Santa Catarina"
    ],
    "name:ukr_x_preferred":[
        "\u0421\u0430\u043d\u0442\u0430-\u041a\u0430\u0442\u0430\u0440\u0456\u043d\u0430"
    ],
    "qs:gn_adm0_cc":"BR",
    "qs:gn_local":3466537,
    "qs:gn_nam_loc":"Caxias do Sul, Rio Grande do Sul, BR",
    "qs:gn_namadm1":"23",
    "qs:local_max":1157,
    "qs:local_sum":2127,
    "qs:localhoods":8,
    "qs:name":"Santa Catarina",
    "qs:name_adm0":"Brasil",
    "qs:name_adm1":"Rio Grande do Sul",
    "qs:name_adm2":"Caxias do Sul",
    "qs:name_local":"Caxias do Sul",
    "qs:photo_max":23,
    "qs:photo_sum":26,
    "qs:placetype":"Suburb",
    "qs:quad_count":4,
    "qs:woe_adm0":23424768,
    "qs:woe_adm1":2344864,
    "qs:woe_adm2":12581299,
    "qs:woe_lau":0,
    "qs:woe_local":429100,
    "qs:woe_ver":"7.10.0",
    "wof:lang":[
        "por"
    ],
    "wof:name":"Santa Catarina",
    "wof:placetype":"neighbourhood"
},
  "geometry": {"coordinates":[-51.210023,-29.150132],"type":"Point"}
}