{
  "type": "Feature",
  "properties": {
    "gn:admin1_code":"27.0",
    "gn:admin2_code":"3548708.0",
    "gn:asciiname":"Capivari",
    "gn:country_code":"BR",
    "gn:dem":782,
    "gn:feature_class":"P",
    "gn:feature_code":"PPLL",
    "gn:name":"Capivari",
    "gn:population":0,
    "gn:timezone":"America/Sao_Paulo",
    "iso:country":"BR",
    "name:bpy_x_preferred":[
        "\u0995\u09be\u09aa\u09bf\u09ad\u09be\u09b0\u09bf"
    ],
    "name:ceb_x_preferred":[
        "Capivari"
    ],
    "name:epo_x_preferred":[
        "Capivari"
    ],
    "name:eus_x_preferred":[
        "Capivari"
    ],
    "name:fra_x_preferred":[
        "Capivari"
    ],
    "name:ita_x_preferred":[
        "Capivari"
    ],
    "name:kaz_x_preferred":[
        "\u041a\u0430\u043f\u0438\u0432\u0430\u0440\u0438"
    ],
    "name:mlg_x_preferred":[
        "Capivari"
    ],
    "name:nld_x_preferred":[
        "Capivari"
    ],
    "name:nor_x_preferred":[
        "Capivari"
    ],
    "name:pol_x_preferred":[
        "Capivari"
    ],
    "name:por_x_preferred":[
        "Capivari"
    ],
    "name:ron_x_preferred":[
        "Capivari"
    ],
    "name:rus_x_preferred":[
        "\u041a\u0430\u043f\u0438\u0432\u0430\u0440\u0438"
    ],
    "name:spa_x_preferred":[
        "Capivari"
    ],
    "name:swe_x_preferred":[
        "Capivari"
    ],
    "name:vie_x_preferred":[
        "Capivari"
    ],
    "name:vol_x_preferred":[
        "Capivari"
    ],
    "name:war_x_preferred":[
        "Capivari"
    ],
    "name:zho_x_preferred":[
        "\u5361\u76ae\u74e6\u91cc"
    ],
    "wof:name":"Capivari",
    "wof:placetype":"locality"
},
  "geometry": {"coordinates":[-46.5819,-23.8833],"type":"Point"}
}