{
  "type": "Feature",
  "properties": {
    "gn:admin1_code":"27.0",
    "gn:admin2_code":"3548708.0",
    "gn:asciiname":"Capivari",
    "gn:country_code":"BR",
    "gn:dem":782,
    "gn:feature_class":"P",
    "gn:feature_code":"PPLL",
    "gn:name":"Capivari",
    "gn:population":0,
    "gn:timezone":"America/Sao_Paulo",
    "iso:country":"BR",
    "name:por_x_preferred":[
        "Capivari"
    ],
    "wof:name":"Capivari",
    "wof:placetype":"locality"
},
  "geometry": {"coordinates":[-46.5819,-23.8833],"type":"Point"}
}