{
  "type": "Feature",
  "properties": {
    "gn:country":"BR",
    "gn:fcode":"PPL",
    "gn:population":0,
    "iso:country":"BR",
    "name:por_x_preferred":[
        "Periperi"
    ],
    "name:und_x_variant":[
        "Piripiri"
    ],
    "qs_pg:aaroncc":"BR",
    "qs_pg:gn_country":"BR",
    "qs_pg:gn_fcode":"PPL",
    "qs_pg:gn_pop":0,
    "qs_pg:name":"Periperi",
    "qs_pg:name_adm0":"Brasil",
    "qs_pg:name_adm1":"Bahia",
    "qs_pg:photos":131,
    "qs_pg:photos_1k":27,
    "qs_pg:photos_9k":1,
    "qs_pg:photos_9r":3,
    "qs_pg:photos_all":131,
    "qs_pg:photos_sr":3,
    "qs_pg:pop_sr":0,
    "qs_pg:qs_pg_placetype":"locality",
    "qs_pg:qs_pg_placetype_gp":"Town",
    "qs_pg:woe_adm0":23424768,
    "woe:adm0_id":23424768,
    "woe:name_adm0":"Brasil",
    "woe:name_adm1":"Bahia",
    "woe:placetype":"Town",
    "wof:name":"Periperi",
    "wof:placetype":"locality"
},
  "geometry": {"coordinates":[-38.46667,-12.86667],"type":"Point"}
}