{
  "type": "Feature",
  "properties": {
    "gn:admin1_code":"13",
    "gn:admin2_code":"2111789.0",
    "gn:asciiname":"Silverio",
    "gn:country_code":"BR",
    "gn:dem":19,
    "gn:feature_class":"P",
    "gn:feature_code":"PPL",
    "gn:name":"Silv\u00e9rio",
    "gn:population":0,
    "gn:timezone":"America/Fortaleza",
    "iso:country":"BR",
    "wof:name":"Silverio",
    "wof:placetype":"locality"
},
  "geometry": {"coordinates":[-44.86667,-1.65],"type":"Point"}
}