{
  "type": "Feature",
  "properties": {
    "gn:admin1_code":"18",
    "gn:admin2_code":"4122305.0",
    "gn:asciiname":"Sitio Stanislau Wrobel",
    "gn:country_code":"BR",
    "gn:dem":917,
    "gn:feature_class":"P",
    "gn:feature_code":"PPL",
    "gn:name":"S\u00edtio Stanislau Wrobel",
    "gn:population":0,
    "gn:timezone":"America/Sao_Paulo",
    "iso:country":"BR",
    "name:por_x_preferred":[
        "S\u00edtio Stanislau Wrobel"
    ],
    "wof:name":"Sitio Stanislau Wrobel",
    "wof:placetype":"locality"
},
  "geometry": {"coordinates":[-49.71753,-26.03254],"type":"Point"}
}