{
  "type": "Feature",
  "properties": {
    "gn:admin1_code":"27",
    "gn:admin2_code":"3536307.0",
    "gn:asciiname":"Taquaral",
    "gn:country_code":"BR",
    "gn:dem":942,
    "gn:feature_class":"P",
    "gn:feature_code":"PPL",
    "gn:name":"Taquaral",
    "gn:population":0,
    "gn:timezone":"America/Sao_Paulo",
    "iso:country":"BR",
    "name:por_x_preferred":[
        "Taquaral"
    ],
    "wof:name":"Taquaral",
    "wof:placetype":"locality"
},
  "geometry": {"coordinates":[-47.26667,-20.55],"type":"Point"}
}