{
  "type": "Feature",
  "properties": {
    "gn:admin1_code":"23",
    "gn:admin2_code":"4313904.0",
    "gn:asciiname":"Assis Brasil",
    "gn:country_code":"BR",
    "gn:dem":404,
    "gn:feature_class":"P",
    "gn:feature_code":"PPL",
    "gn:name":"Assis Brasil",
    "gn:population":0,
    "gn:timezone":"America/Sao_Paulo",
    "iso:country":"BR",
    "wof:name":"Assis Brasil",
    "wof:placetype":"locality"
},
  "geometry": {"coordinates":[-53.56667,-28.26667],"type":"Point"}
}