{
  "type": "Feature",
  "properties": {
    "gn:admin1_code":"23",
    "gn:admin2_code":"4313904.0",
    "gn:asciiname":"Assis Brasil",
    "gn:country_code":"BR",
    "gn:dem":404,
    "gn:feature_class":"P",
    "gn:feature_code":"PPL",
    "gn:name":"Assis Brasil",
    "gn:population":0,
    "gn:timezone":"America/Sao_Paulo",
    "iso:country":"BR",
    "name:ara_x_preferred":[
        "\u0623\u0633\u064a\u0633 \u0628\u0631\u0627\u0633\u064a\u0644"
    ],
    "name:bpy_x_preferred":[
        "\u0986\u09b8\u09b8\u09bf\u09b8 \u09ac\u09cd\u09b0\u09be\u09b8\u09bf\u09b2"
    ],
    "name:bul_x_preferred":[
        "\u0410\u0441\u0438\u0441 \u0411\u0440\u0430\u0437\u0438\u043b"
    ],
    "name:ceb_x_preferred":[
        "Assis Brasil"
    ],
    "name:deu_x_preferred":[
        "Assis Brasil"
    ],
    "name:epo_x_preferred":[
        "Assis Brasil"
    ],
    "name:eus_x_preferred":[
        "Assis Brasil"
    ],
    "name:fas_x_preferred":[
        "\u0627\u0633\u06cc\u0633 \u0628\u0631\u0627\u0632\u06cc\u0644"
    ],
    "name:fra_x_preferred":[
        "Assis Brasil"
    ],
    "name:hye_x_preferred":[
        "\u0531\u057d\u056b\u057d \u0532\u0580\u0561\u0566\u056b\u056c"
    ],
    "name:ind_x_preferred":[
        "Assis Brasil"
    ],
    "name:ita_x_preferred":[
        "Assis Brasil"
    ],
    "name:kat_x_preferred":[
        "\u10d0\u10e1\u10d8\u10e1-\u10d1\u10e0\u10d0\u10d6\u10d8\u10da\u10d8"
    ],
    "name:kaz_x_preferred":[
        "\u0410\u0441\u0438\u0441-\u0411\u0440\u0430\u0437\u0438\u043b"
    ],
    "name:msa_x_preferred":[
        "Assis Brasil"
    ],
    "name:nld_x_preferred":[
        "Assis Brasil"
    ],
    "name:nor_x_preferred":[
        "Assis Brasil"
    ],
    "name:pol_x_preferred":[
        "Assis Brasil"
    ],
    "name:por_x_preferred":[
        "Assis Brasil"
    ],
    "name:ron_x_preferred":[
        "Assis Brasil"
    ],
    "name:rus_x_preferred":[
        "\u0410\u0441\u0438\u0441-\u0411\u0440\u0430\u0437\u0438\u043b"
    ],
    "name:spa_x_preferred":[
        "Assis Brasil"
    ],
    "name:vie_x_preferred":[
        "Assis Brasil"
    ],
    "name:vol_x_preferred":[
        "Assis Brasil"
    ],
    "name:war_x_preferred":[
        "Assis Brasil"
    ],
    "name:zho_x_preferred":[
        "\u963f\u897f\u65af\u5df4\u897f"
    ],
    "wof:name":"Assis Brasil",
    "wof:placetype":"locality"
},
  "geometry": {"coordinates":[-53.56667,-28.26667],"type":"Point"}
}