{
  "type": "Feature",
  "properties": {
    "gn:admin1_code":"18.0",
    "gn:admin2_code":"4101200.0",
    "gn:asciiname":"Sitio Ramiro Dias Pereira",
    "gn:country_code":"BR",
    "gn:dem":34,
    "gn:feature_class":"P",
    "gn:feature_code":"PPL",
    "gn:name":"S\u00edtio Ramiro Dias Pereira",
    "gn:population":0,
    "gn:timezone":"America/Sao_Paulo",
    "iso:country":"BR",
    "name:por_x_preferred":[
        "S\u00edtio Ramiro Dias Pereira"
    ],
    "wof:name":"Sitio Ramiro Dias Pereira",
    "wof:placetype":"locality"
},
  "geometry": {"coordinates":[-48.6994,-25.4041],"type":"Point"}
}