{
  "type": "Feature",
  "properties": {
    "gn:admin1_code":"22",
    "gn:admin2_code":"2414407.0",
    "gn:asciiname":"Serra Verde Zabele",
    "gn:country_code":"BR",
    "gn:dem":195,
    "gn:feature_class":"P",
    "gn:feature_code":"PPL",
    "gn:name":"Serra Verde Zabele",
    "gn:population":0,
    "gn:timezone":"America/Fortaleza",
    "iso:country":"BR",
    "wof:name":"Serra Verde Zabele",
    "wof:placetype":"locality"
},
  "geometry": {"coordinates":[-35.73333,-5.36667],"type":"Point"}
}