{
  "type": "Feature",
  "properties": {
    "gn:admin1_code":"4",
    "gn:admin2_code":"1303502.0",
    "gn:asciiname":"Ituxi",
    "gn:cc2":"BR",
    "gn:country_code":"BR",
    "gn:dem":93,
    "gn:feature_class":"P",
    "gn:feature_code":"PPL",
    "gn:name":"Ituxi",
    "gn:population":0,
    "gn:timezone":"America/Manaus",
    "iso:country":"BR",
    "name:und_x_variant":[
        "S\u00e3o Lu\u00eds de Mamori\u00e1",
        "Ituxi"
    ],
    "wof:name":"Ituxi",
    "wof:placetype":"locality"
},
  "geometry": {"coordinates":[-66.41667,-7.55],"type":"Point"}
}