{
  "type": "Feature",
  "properties": {
    "gn:admin1_code":"14",
    "gn:admin2_code":"5106828.0",
    "gn:asciiname":"Santa Barbara",
    "gn:cc2":"BR",
    "gn:country_code":"BR",
    "gn:dem":386,
    "gn:feature_class":"P",
    "gn:feature_code":"PPL",
    "gn:name":"Santa B\u00e1rbara",
    "gn:population":0,
    "gn:timezone":"America/Cuiaba",
    "iso:country":"BR",
    "name:und_x_variant":[
        "Antigo Arraial de Santa Barbara",
        "Fazenda Santa Barbara",
        "Santa B\u00e1rbara"
    ],
    "wof:name":"Santa Barbara",
    "wof:placetype":"locality"
},
  "geometry": {"coordinates":[-59.15,-15.65],"type":"Point"}
}