{
  "type": "Feature",
  "properties": {
    "gn:admin1_code":"29.0",
    "gn:admin2_code":"5208301.0",
    "gn:asciiname":"Porteira",
    "gn:country_code":"BR",
    "gn:dem":707,
    "gn:feature_class":"P",
    "gn:feature_code":"PPL",
    "gn:name":"Porteira",
    "gn:population":0,
    "gn:timezone":"America/Sao_Paulo",
    "iso:country":"BR",
    "wof:name":"Porteira",
    "wof:placetype":"locality"
},
  "geometry": {"coordinates":[-46.40472000000001,-13.12655],"type":"Point"}
}