{
  "type": "Feature",
  "properties": {
    "iso:country":"BR",
    "name:deu_x_preferred":[
        "Candangol\u00e2ndia"
    ],
    "name:fra_x_preferred":[
        "Candangol\u00e2ndia"
    ],
    "name:ita_x_preferred":[
        "Candangol\u00e2ndia"
    ],
    "name:por_x_preferred":[
        "Candangol\u00e2ndia"
    ],
    "qs_pg:aaroncc":"BR",
    "qs_pg:name":"Candangol\u00e2ndia",
    "qs_pg:name_adm0":"Brasil",
    "qs_pg:name_adm1":"Distrito Federal",
    "qs_pg:photos":2024,
    "qs_pg:photos_1k":410,
    "qs_pg:photos_9k":9,
    "qs_pg:photos_9r":9,
    "qs_pg:photos_all":2024,
    "qs_pg:photos_sr":15,
    "qs_pg:pop_sr":0,
    "qs_pg:qs_pg_placetype":"locality",
    "qs_pg:qs_pg_placetype_gp":"Town",
    "qs_pg:woe_adm0":23424768,
    "woe:adm0_id":23424768,
    "woe:name_adm0":"Brasil",
    "woe:name_adm1":"Distrito Federal",
    "woe:placetype":"Town",
    "wof:name":"Candangol\u00e2ndia",
    "wof:placetype":"locality"
},
  "geometry": {"coordinates":[-47.940731,-15.845501],"type":"Point"}
}