{
  "type": "Feature",
  "properties": {
    "gn:admin1_code":"06",
    "gn:admin2_code":"2303956.0",
    "gn:asciiname":"Villa Rosa",
    "gn:country_code":"BR",
    "gn:dem":48,
    "gn:feature_class":"P",
    "gn:feature_code":"PPL",
    "gn:name":"Villa Rosa",
    "gn:population":0,
    "gn:timezone":"America/Fortaleza",
    "iso:country":"BR",
    "name:azb_x_preferred":[
        "\u0648\u06cc\u0644\u0627 \u0631\u0648\u0632\u0627"
    ],
    "name:ceb_x_preferred":[
        "Villa Rosa"
    ],
    "name:fas_x_preferred":[
        "\u0648\u06cc\u0644\u0627 \u0631\u0648\u0632\u0627"
    ],
    "name:ita_x_preferred":[
        "Villa Rosa"
    ],
    "name:srp_x_preferred":[
        "\u0412\u0438\u043b\u0430 \u0420\u043e\u0437\u0430"
    ],
    "wof:name":"Villa Rosa",
    "wof:placetype":"locality"
},
  "geometry": {"coordinates":[-38.51667,-4.33333],"type":"Point"}
}