{
  "type": "Feature",
  "properties": {
    "gn:admin1_code":"06",
    "gn:admin2_code":"2303956.0",
    "gn:asciiname":"Villa Rosa",
    "gn:country_code":"BR",
    "gn:dem":48,
    "gn:feature_class":"P",
    "gn:feature_code":"PPL",
    "gn:name":"Villa Rosa",
    "gn:population":0,
    "gn:timezone":"America/Fortaleza",
    "iso:country":"BR",
    "wof:name":"Villa Rosa",
    "wof:placetype":"locality"
},
  "geometry": {"coordinates":[-38.51667,-4.33333],"type":"Point"}
}