{
  "type": "Feature",
  "properties": {
    "gn:admin1_code":"5",
    "gn:admin2_code":"2917805.0",
    "gn:asciiname":"Tijuca de Baixo",
    "gn:country_code":"BR",
    "gn:dem":20,
    "gn:feature_class":"P",
    "gn:feature_code":"PPL",
    "gn:name":"Tijuca de Baixo",
    "gn:population":0,
    "gn:timezone":"America/Bahia",
    "iso:country":"BR",
    "wof:name":"Tijuca de Baixo",
    "wof:placetype":"locality"
},
  "geometry": {"coordinates":[-38.95,-13.05],"type":"Point"}
}