{
  "type": "Feature",
  "properties": {
    "gn:admin1_code":"30",
    "gn:admin2_code":"2611606.0",
    "gn:asciiname":"Werneck",
    "gn:cc2":"BR",
    "gn:country_code":"BR",
    "gn:dem":12,
    "gn:feature_class":"P",
    "gn:feature_code":"PPL",
    "gn:name":"Werneck",
    "gn:population":0,
    "gn:timezone":"America/Recife",
    "iso:country":"BR",
    "name:ceb_x_preferred":[
        "Werneck"
    ],
    "name:deu_x_preferred":[
        "Werneck"
    ],
    "name:epo_x_preferred":[
        "Werneck"
    ],
    "name:eus_x_preferred":[
        "Werneck"
    ],
    "name:fra_x_preferred":[
        "Werneck"
    ],
    "name:hun_x_preferred":[
        "Werneck"
    ],
    "name:hye_x_preferred":[
        "\u054e\u0565\u0580\u0576\u0565\u0584"
    ],
    "name:ita_x_preferred":[
        "Werneck"
    ],
    "name:kaz_x_preferred":[
        "\u0412\u0435\u0440\u043d\u0435\u043a"
    ],
    "name:kir_x_preferred":[
        "\u0412\u0435\u0440\u043d\u0435\u043a"
    ],
    "name:lmo_x_preferred":[
        "Werneck"
    ],
    "name:msa_x_preferred":[
        "Werneck"
    ],
    "name:nld_x_preferred":[
        "Werneck"
    ],
    "name:pol_x_preferred":[
        "Werneck"
    ],
    "name:por_x_preferred":[
        "Werneck"
    ],
    "name:ron_x_preferred":[
        "Werneck"
    ],
    "name:rus_x_preferred":[
        "\u0412\u0435\u0440\u043d\u044d\u043a\u043a"
    ],
    "name:spa_x_preferred":[
        "Werneck"
    ],
    "name:srp_x_preferred":[
        "\u0412\u0435\u0440\u043d\u0435\u043a"
    ],
    "name:swe_x_preferred":[
        "Werneck"
    ],
    "name:ukr_x_preferred":[
        "\u0412\u0435\u0440\u043d\u0435\u043a"
    ],
    "name:und_x_variant":[
        "Edgard Verneque",
        "Edgar Werneck"
    ],
    "name:uzb_x_preferred":[
        "Werneck"
    ],
    "name:vie_x_preferred":[
        "Werneck"
    ],
    "name:vol_x_preferred":[
        "Werneck"
    ],
    "name:war_x_preferred":[
        "Werneck"
    ],
    "name:zho_x_preferred":[
        "\u97e6\u5c14\u5185\u514b"
    ],
    "wof:name":"Werneck",
    "wof:placetype":"locality"
},
  "geometry": {"coordinates":[-34.93333,-8.08333],"type":"Point"}
}