{
  "type": "Feature",
  "properties": {
    "gn:admin1_code":"30",
    "gn:admin2_code":"2611606.0",
    "gn:asciiname":"Werneck",
    "gn:cc2":"BR",
    "gn:country_code":"BR",
    "gn:dem":12,
    "gn:feature_class":"P",
    "gn:feature_code":"PPL",
    "gn:name":"Werneck",
    "gn:population":0,
    "gn:timezone":"America/Recife",
    "iso:country":"BR",
    "name:und_x_variant":[
        "Edgard Verneque",
        "Edgar Werneck",
        "Werneck"
    ],
    "wof:name":"Werneck",
    "wof:placetype":"locality"
},
  "geometry": {"coordinates":[-34.93333,-8.08333],"type":"Point"}
}