{
  "type": "Feature",
  "properties": {
    "gn:admin1_code":"18.0",
    "gn:admin2_code":"4109708.0",
    "gn:asciiname":"Sitio Vale do Rio d'Ouro",
    "gn:country_code":"BR",
    "gn:dem":693,
    "gn:feature_class":"P",
    "gn:feature_code":"PPL",
    "gn:name":"S\u00edtio Vale do Rio d\u2019Ouro",
    "gn:population":0,
    "gn:timezone":"America/Sao_Paulo",
    "iso:country":"BR",
    "name:por_x_preferred":[
        "S\u00edtio Vale do Rio d\u2019Ouro"
    ],
    "wof:name":"Sitio Vale do Rio d'Ouro",
    "wof:placetype":"locality"
},
  "geometry": {"coordinates":[-50.17694,-23.89287],"type":"Point"}
}