{
  "type": "Feature",
  "properties": {
    "gn:admin1_code":"5",
    "gn:admin2_code":"2921906.0",
    "gn:asciiname":"Frio",
    "gn:country_code":"BR",
    "gn:dem":1005,
    "gn:feature_class":"P",
    "gn:feature_code":"PPL",
    "gn:name":"Frio",
    "gn:population":0,
    "gn:timezone":"America/Bahia",
    "iso:country":"BR",
    "wof:name":"Frio",
    "wof:placetype":"locality"
},
  "geometry": {"coordinates":[-41.58333,-12.71667],"type":"Point"}
}