{
  "type": "Feature",
  "properties": {
    "gn:admin1_code":"18.0",
    "gn:admin2_code":"4124707.0",
    "gn:asciiname":"Sitio Santo Antonio",
    "gn:country_code":"BR",
    "gn:dem":844,
    "gn:feature_class":"P",
    "gn:feature_code":"PPL",
    "gn:name":"S\u00edtio Santo Ant\u00f4nio",
    "gn:population":0,
    "gn:timezone":"America/Sao_Paulo",
    "iso:country":"BR",
    "name:por_x_preferred":[
        "S\u00edtio Santo Ant\u00f4nio"
    ],
    "wof:name":"Sitio Santo Antonio",
    "wof:placetype":"locality"
},
  "geometry": {"coordinates":[-50.75571,-23.77731],"type":"Point"}
}