{
  "type": "Feature",
  "properties": {
    "gn:admin1_code":"15",
    "gn:admin2_code":"3121209.0",
    "gn:asciiname":"Lindolfo Almeida",
    "gn:country_code":"BR",
    "gn:dem":1195,
    "gn:feature_class":"P",
    "gn:feature_code":"PPL",
    "gn:name":"Lindolfo Almeida",
    "gn:population":0,
    "gn:timezone":"America/Sao_Paulo",
    "iso:country":"BR",
    "name:por_x_preferred":[
        "Lindolfo Almeida"
    ],
    "wof:name":"Lindolfo Almeida",
    "wof:placetype":"locality"
},
  "geometry": {"coordinates":[-46.55,-20.43333],"type":"Point"}
}