{
  "type": "Feature",
  "properties": {
    "gn:admin1_code":"18.0",
    "gn:admin2_code":"4106209.0",
    "gn:asciiname":"Sitio Valentim S. Cortes",
    "gn:country_code":"BR",
    "gn:dem":848,
    "gn:feature_class":"P",
    "gn:feature_code":"PPL",
    "gn:name":"S\u00edtio Valentim S. Cortes",
    "gn:population":0,
    "gn:timezone":"America/Sao_Paulo",
    "iso:country":"BR",
    "name:por_x_preferred":[
        "S\u00edtio Valentim S. Cortes"
    ],
    "wof:name":"Sitio Valentim S. Cortes",
    "wof:placetype":"locality"
},
  "geometry": {"coordinates":[-49.5807,-25.7703],"type":"Point"}
}