{
  "type": "Feature",
  "properties": {
    "gn:admin1_code":"4",
    "gn:admin2_code":"1301308.0",
    "gn:asciiname":"Veneza",
    "gn:country_code":"BR",
    "gn:dem":23,
    "gn:feature_class":"P",
    "gn:feature_code":"PPL",
    "gn:name":"Veneza",
    "gn:population":0,
    "gn:timezone":"America/Manaus",
    "iso:country":"BR",
    "wof:name":"Veneza",
    "wof:placetype":"locality"
},
  "geometry": {"coordinates":[-62.92667,-3.28694],"type":"Point"}
}