{
  "type": "Feature",
  "properties": {
    "gn:admin1_code":"5",
    "gn:admin2_code":"2926905.0",
    "gn:asciiname":"Barbado",
    "gn:country_code":"BR",
    "gn:dem":1341,
    "gn:feature_class":"P",
    "gn:feature_code":"PPL",
    "gn:name":"Barbado",
    "gn:population":0,
    "gn:timezone":"America/Bahia",
    "iso:country":"BR",
    "wof:name":"Barbado",
    "wof:placetype":"locality"
},
  "geometry": {"coordinates":[-41.93333,-13.28333],"type":"Point"}
}