{
  "type": "Feature",
  "properties": {
    "gn:admin1_code":"18.0",
    "gn:admin2_code":"4126603.0",
    "gn:asciiname":"Sitio Sao Carlos",
    "gn:country_code":"BR",
    "gn:dem":571,
    "gn:feature_class":"P",
    "gn:feature_code":"PPL",
    "gn:name":"S\u00edtio S\u00e3o Carlos",
    "gn:population":0,
    "gn:timezone":"America/Sao_Paulo",
    "iso:country":"BR",
    "name:por_x_preferred":[
        "S\u00edtio S\u00e3o Carlos"
    ],
    "wof:name":"Sitio Sao Carlos",
    "wof:placetype":"locality"
},
  "geometry": {"coordinates":[-49.7809,-23.5757],"type":"Point"}
}