{
  "type": "Feature",
  "properties": {
    "gn:admin1_code":"18",
    "gn:admin2_code":"4100301.0",
    "gn:asciiname":"Sitio Paulo Kochan",
    "gn:country_code":"BR",
    "gn:dem":836,
    "gn:feature_class":"P",
    "gn:feature_code":"PPL",
    "gn:name":"S\u00edtio Paulo Kochan",
    "gn:population":0,
    "gn:timezone":"America/Sao_Paulo",
    "iso:country":"BR",
    "name:por_x_preferred":[
        "S\u00edtio Paulo Kochan"
    ],
    "wof:name":"Sitio Paulo Kochan",
    "wof:placetype":"locality"
},
  "geometry": {"coordinates":[-49.2832,-26.0544],"type":"Point"}
}