{
  "type": "Feature",
  "properties": {
    "gn:admin1_code":"25",
    "gn:admin2_code":"1400407.0",
    "gn:asciiname":"Anemutu",
    "gn:country_code":"BR",
    "gn:dem":347,
    "gn:feature_class":"P",
    "gn:feature_code":"PPL",
    "gn:name":"Anemutu",
    "gn:population":0,
    "gn:timezone":"America/Boa_Vista",
    "iso:country":"BR",
    "wof:name":"Anemutu",
    "wof:placetype":"locality"
},
  "geometry": {"coordinates":[-59.88333000000001,4.08333],"type":"Point"}
}