{
  "type": "Feature",
  "properties": {
    "gn:admin1_code":"24",
    "gn:admin2_code":"1100601.0",
    "gn:asciiname":"Nova Vida",
    "gn:country_code":"BR",
    "gn:dem":138,
    "gn:feature_class":"P",
    "gn:feature_code":"PPL",
    "gn:name":"Nova Vida",
    "gn:population":0,
    "gn:timezone":"America/Porto_Velho",
    "iso:country":"BR",
    "name:por_x_preferred":[
        "Nova Vida"
    ],
    "wof:name":"Nova Vida",
    "wof:placetype":"locality"
},
  "geometry": {"coordinates":[-62.82318000000001,-10.17942],"type":"Point"}
}