{
  "type": "Feature",
  "properties": {
    "gn:admin1_code":"27.0",
    "gn:admin2_code":"3537800.0",
    "gn:asciiname":"Buenos",
    "gn:country_code":"BR",
    "gn:dem":764,
    "gn:feature_class":"P",
    "gn:feature_code":"PPLL",
    "gn:name":"Buenos",
    "gn:population":0,
    "gn:timezone":"America/Sao_Paulo",
    "iso:country":"BR",
    "name:por_x_preferred":[
        "Buenos"
    ],
    "wof:name":"Buenos",
    "wof:placetype":"locality"
},
  "geometry": {"coordinates":[-47.54261,-23.73042],"type":"Point"}
}