{
  "type": "Feature",
  "properties": {
    "gn:admin1_code":"30",
    "gn:admin2_code":"2605608.0",
    "gn:asciiname":"Brejinho",
    "gn:country_code":"BR",
    "gn:dem":586,
    "gn:feature_class":"P",
    "gn:feature_code":"PPL",
    "gn:name":"Brejinho",
    "gn:population":0,
    "gn:timezone":"America/Recife",
    "iso:country":"BR",
    "wof:name":"Brejinho",
    "wof:placetype":"locality"
},
  "geometry": {"coordinates":[-37.95,-7.81667],"type":"Point"}
}