{
  "type": "Feature",
  "properties": {
    "gn:admin1_code":"18.0",
    "gn:admin2_code":"4104105.0",
    "gn:asciiname":"Sitio Felix Jaros",
    "gn:country_code":"BR",
    "gn:dem":846,
    "gn:feature_class":"P",
    "gn:feature_code":"PPL",
    "gn:name":"S\u00edtio F\u00e9lix Jaros",
    "gn:population":0,
    "gn:timezone":"America/Sao_Paulo",
    "iso:country":"BR",
    "name:por_x_preferred":[
        "S\u00edtio F\u00e9lix Jaros"
    ],
    "wof:name":"Sitio Felix Jaros",
    "wof:placetype":"locality"
},
  "geometry": {"coordinates":[-49.7565,-26.017],"type":"Point"}
}