{
  "type": "Feature",
  "properties": {
    "gn:admin1_code":"6",
    "gn:admin2_code":"2302107.0",
    "gn:asciiname":"Alfredo Dutra",
    "gn:country_code":"BR",
    "gn:dem":169,
    "gn:feature_class":"P",
    "gn:feature_code":"PPL",
    "gn:name":"Alfredo Dutra",
    "gn:population":0,
    "gn:timezone":"America/Fortaleza",
    "iso:country":"BR",
    "wof:name":"Alfredo Dutra",
    "wof:placetype":"locality"
},
  "geometry": {"coordinates":[-38.88333,-4.38333],"type":"Point"}
}