{
  "type": "Feature",
  "properties": {
    "gn:admin1_code":"26.0",
    "gn:admin2_code":"4210100.0",
    "gn:asciiname":"Campo Novo",
    "gn:country_code":"BR",
    "gn:dem":813,
    "gn:feature_class":"P",
    "gn:feature_code":"PPLL",
    "gn:name":"Campo Novo",
    "gn:population":0,
    "gn:timezone":"America/Sao_Paulo",
    "iso:country":"BR",
    "name:por_x_preferred":[
        "Campo Novo"
    ],
    "wof:name":"Campo Novo",
    "wof:placetype":"locality"
},
  "geometry": {"coordinates":[-49.8498,-26.0723],"type":"Point"}
}