{
  "type": "Feature",
  "properties": {
    "gn:admin1_code":"26.0",
    "gn:admin2_code":"4210100.0",
    "gn:asciiname":"Campo Novo",
    "gn:country_code":"BR",
    "gn:dem":813,
    "gn:feature_class":"P",
    "gn:feature_code":"PPLL",
    "gn:name":"Campo Novo",
    "gn:population":0,
    "gn:timezone":"America/Sao_Paulo",
    "iso:country":"BR",
    "name:bpy_x_preferred":[
        "\u0995\u09be\u09ae\u09cd\u09aa\u09cb \u09a8\u09cb\u09ad\u09cb"
    ],
    "name:ceb_x_preferred":[
        "Campo Novo"
    ],
    "name:epo_x_preferred":[
        "Campo Novo"
    ],
    "name:eus_x_preferred":[
        "Campo Novo"
    ],
    "name:hye_x_preferred":[
        "\u053f\u0561\u0574\u057a\u0578\u0582 \u0546\u0578\u057e\u0578\u0582"
    ],
    "name:ita_x_preferred":[
        "Campo Novo"
    ],
    "name:kaz_x_preferred":[
        "\u041a\u0430\u043c\u043f\u0443-\u041d\u043e\u0432\u0443"
    ],
    "name:mlg_x_preferred":[
        "Campo Novo"
    ],
    "name:nld_x_preferred":[
        "Campo Novo"
    ],
    "name:nor_x_preferred":[
        "Campo Novo"
    ],
    "name:pol_x_preferred":[
        "Campo Novo"
    ],
    "name:por_x_preferred":[
        "Campo Novo"
    ],
    "name:ron_x_preferred":[
        "Campo Novo"
    ],
    "name:rus_x_preferred":[
        "\u041a\u0430\u043c\u043f\u0443-\u041d\u043e\u0432\u0443"
    ],
    "name:spa_x_preferred":[
        "Campo Novo"
    ],
    "name:swe_x_preferred":[
        "Campo Novo"
    ],
    "name:vie_x_preferred":[
        "Campo Novo"
    ],
    "name:vol_x_preferred":[
        "Campo Novo"
    ],
    "name:war_x_preferred":[
        "Campo Novo"
    ],
    "name:zho_x_preferred":[
        "\u574e\u666e\u8bfa\u6b66"
    ],
    "wof:name":"Campo Novo",
    "wof:placetype":"locality"
},
  "geometry": {"coordinates":[-49.8498,-26.0723],"type":"Point"}
}