{
  "type": "Feature",
  "properties": {
    "gn:admin1_code":"18.0",
    "gn:admin2_code":"4116208.0",
    "gn:asciiname":"Sitio Odenir Pereira",
    "gn:country_code":"BR",
    "gn:dem":110,
    "gn:feature_class":"P",
    "gn:feature_code":"PPL",
    "gn:name":"S\u00edtio Odenir Pereira",
    "gn:population":0,
    "gn:timezone":"America/Sao_Paulo",
    "iso:country":"BR",
    "name:por_x_preferred":[
        "S\u00edtio Odenir Pereira"
    ],
    "wof:name":"Sitio Odenir Pereira",
    "wof:placetype":"locality"
},
  "geometry": {"coordinates":[-48.87598,-25.4758],"type":"Point"}
}