{
  "type": "Feature",
  "properties": {
    "gn:admin1_code":"13",
    "gn:admin2_code":"2101608.0",
    "gn:asciiname":"Crioli",
    "gn:country_code":"BR",
    "gn:dem":187,
    "gn:feature_class":"P",
    "gn:feature_code":"PPL",
    "gn:name":"Crioli",
    "gn:population":0,
    "gn:timezone":"America/Fortaleza",
    "iso:country":"BR",
    "wof:name":"Crioli",
    "wof:placetype":"locality"
},
  "geometry": {"coordinates":[-45.48333,-5.66667],"type":"Point"}
}