{
  "type": "Feature",
  "properties": {
    "gn:admin1_code":"18.0",
    "gn:admin2_code":"4121208.0",
    "gn:asciiname":"Sitio Joao J. Colaco",
    "gn:country_code":"BR",
    "gn:dem":840,
    "gn:feature_class":"P",
    "gn:feature_code":"PPL",
    "gn:name":"S\u00edtio Jo\u00e3o J. Cola\u00e7o",
    "gn:population":0,
    "gn:timezone":"America/Sao_Paulo",
    "iso:country":"BR",
    "name:por_x_preferred":[
        "S\u00edtio Jo\u00e3o J. Cola\u00e7o"
    ],
    "wof:name":"Sitio Joao J. Colaco",
    "wof:placetype":"locality"
},
  "geometry": {"coordinates":[-49.5399,-25.8838],"type":"Point"}
}