{
  "type": "Feature",
  "properties": {
    "gn:admin1_code":"27",
    "gn:admin2_code":"3504107.0",
    "gn:asciiname":"Sitio Vera Cruz",
    "gn:country_code":"BR",
    "gn:dem":767,
    "gn:feature_class":"P",
    "gn:feature_code":"PPL",
    "gn:name":"S\u00edtio Vera Cruz",
    "gn:population":0,
    "gn:timezone":"America/Sao_Paulo",
    "iso:country":"BR",
    "name:por_x_preferred":[
        "S\u00edtio Vera Cruz"
    ],
    "wof:name":"Sitio Vera Cruz",
    "wof:placetype":"locality"
},
  "geometry": {"coordinates":[-46.60083,-23.12472],"type":"Point"}
}