{
  "type": "Feature",
  "properties": {
    "gn:admin1_code":"6",
    "gn:admin2_code":"2307106.0",
    "gn:asciiname":"Bonsucesso",
    "gn:country_code":"BR",
    "gn:dem":592,
    "gn:feature_class":"P",
    "gn:feature_code":"PPL",
    "gn:name":"Bonsucesso",
    "gn:population":0,
    "gn:timezone":"America/Fortaleza",
    "iso:country":"BR",
    "name:ita_x_preferred":[
        "Bonsucesso"
    ],
    "name:por_x_preferred":[
        "Bonsucesso"
    ],
    "wof:name":"Bonsucesso",
    "wof:placetype":"locality"
},
  "geometry": {"coordinates":[-39.21667,-7.63333],"type":"Point"}
}