{
  "type": "Feature",
  "properties": {
    "gn:admin1_code":"23",
    "gn:admin2_code":"4310363.0",
    "gn:asciiname":"Daltro Filho",
    "gn:cc2":"BR",
    "gn:country_code":"BR",
    "gn:dem":183,
    "gn:feature_class":"P",
    "gn:feature_code":"PPL",
    "gn:name":"Daltro Filho",
    "gn:population":0,
    "gn:timezone":"America/Sao_Paulo",
    "iso:country":"BR",
    "name:und_x_variant":[
        "General Daltro Filho",
        "Daltro Filho"
    ],
    "wof:name":"Daltro Filho",
    "wof:placetype":"locality"
},
  "geometry": {"coordinates":[-51.76667,-29.33333],"type":"Point"}
}