{
  "type": "Feature",
  "properties": {
    "gn:admin1_code":"20.0",
    "gn:admin2_code":"2203230.0",
    "gn:asciiname":"Correntinho",
    "gn:country_code":"BR",
    "gn:dem":355,
    "gn:feature_class":"P",
    "gn:feature_code":"PPL",
    "gn:name":"Correntinho",
    "gn:population":0,
    "gn:timezone":"America/Fortaleza",
    "iso:country":"BR",
    "name:por_x_preferred":[
        "Correntinho"
    ],
    "wof:name":"Correntinho",
    "wof:placetype":"locality"
},
  "geometry": {"coordinates":[-44.93064,-8.99345],"type":"Point"}
}