{
  "type": "Feature",
  "properties": {
    "gn:admin1_code":"13",
    "gn:admin2_code":"2110104.0",
    "gn:asciiname":"Sao Benedito",
    "gn:country_code":"BR",
    "gn:dem":53,
    "gn:feature_class":"P",
    "gn:feature_code":"PPL",
    "gn:name":"S\u00e3o Benedito",
    "gn:population":0,
    "gn:timezone":"America/Fortaleza",
    "iso:country":"BR",
    "wof:name":"Sao Benedito",
    "wof:placetype":"locality"
},
  "geometry": {"coordinates":[-42.64306,-3.41639],"type":"Point"}
}