{
  "type": "Feature",
  "properties": {
    "gn:admin1_code":"5",
    "gn:admin2_code":"2914000.0",
    "gn:asciiname":"Canto do Rumo",
    "gn:country_code":"BR",
    "gn:dem":303,
    "gn:feature_class":"P",
    "gn:feature_code":"PPL",
    "gn:name":"Canto do Rumo",
    "gn:population":0,
    "gn:timezone":"America/Bahia",
    "iso:country":"BR",
    "wof:name":"Canto do Rumo",
    "wof:placetype":"locality"
},
  "geometry": {"coordinates":[-39.73333,-12.05],"type":"Point"}
}