{
  "type": "Feature",
  "properties": {
    "gn:admin1_code":"16",
    "gn:admin2_code":"1506401.0",
    "gn:asciiname":"Ananatuba",
    "gn:country_code":"BR",
    "gn:dem":2,
    "gn:feature_class":"P",
    "gn:feature_code":"PPL",
    "gn:name":"Ananatuba",
    "gn:population":0,
    "gn:timezone":"America/Belem",
    "iso:country":"BR",
    "wof:name":"Ananatuba",
    "wof:placetype":"locality"
},
  "geometry": {"coordinates":[-49.18333,-0.58333],"type":"Point"}
}