{
  "type": "Feature",
  "properties": {
    "gn:admin1_code":"4.0",
    "gn:admin2_code":"1302900.0",
    "gn:asciiname":"Vila Santo Antonio",
    "gn:country_code":"BR",
    "gn:dem":23,
    "gn:feature_class":"P",
    "gn:feature_code":"PPL",
    "gn:name":"Vila Santo Ant\u00f4nio",
    "gn:population":0,
    "gn:timezone":"America/Manaus",
    "iso:country":"BR",
    "name:por_x_preferred":[
        "Vila Santo Ant\u00f4nio"
    ],
    "wof:name":"Vila Santo Antonio",
    "wof:placetype":"locality"
},
  "geometry": {"coordinates":[-57.50292,-3.89762],"type":"Point"}
}