{
  "type": "Feature",
  "properties": {
    "gn:admin1_code":"06",
    "gn:admin2_code":"2313005.0",
    "gn:asciiname":"Guedeslandia",
    "gn:country_code":"BR",
    "gn:dem":165,
    "gn:feature_class":"P",
    "gn:feature_code":"PPL",
    "gn:name":"Guedesl\u00e2ndia",
    "gn:population":0,
    "gn:timezone":"America/Fortaleza",
    "iso:country":"BR",
    "wof:name":"Guedeslandia",
    "wof:placetype":"locality"
},
  "geometry": {"coordinates":[-38.85,-5.76667],"type":"Point"}
}