{
  "type": "Feature",
  "properties": {
    "gn:admin1_code":"16",
    "gn:admin2_code":"1508357.0",
    "gn:asciiname":"Boa Vista",
    "gn:country_code":"BR",
    "gn:dem":117,
    "gn:feature_class":"P",
    "gn:feature_code":"PPL",
    "gn:name":"Boa Vista",
    "gn:population":0,
    "gn:timezone":"America/Santarem",
    "iso:country":"BR",
    "wof:name":"Boa Vista",
    "wof:placetype":"locality"
},
  "geometry": {"coordinates":[-52.18333,-3.06667],"type":"Point"}
}