{
  "type": "Feature",
  "properties": {
    "gn:admin1_code":"13",
    "gn:admin2_code":"2100808.0",
    "gn:asciiname":"Riacho do Meio",
    "gn:country_code":"BR",
    "gn:dem":52,
    "gn:feature_class":"P",
    "gn:feature_code":"PPL",
    "gn:name":"Riacho do Meio",
    "gn:population":0,
    "gn:timezone":"America/Fortaleza",
    "iso:country":"BR",
    "wof:name":"Riacho do Meio",
    "wof:placetype":"locality"
},
  "geometry": {"coordinates":[-43.3025,-3.54278],"type":"Point"}
}