{
  "type": "Feature",
  "properties": {
    "gn:admin1_code":"18",
    "gn:admin2_code":"4108809.0",
    "gn:asciiname":"Porto Novo",
    "gn:country_code":"BR",
    "gn:dem":223,
    "gn:feature_class":"P",
    "gn:feature_code":"PPL",
    "gn:name":"P\u00f4rto Novo",
    "gn:population":0,
    "gn:timezone":"America/Sao_Paulo",
    "iso:country":"BR",
    "wof:name":"Porto Novo",
    "wof:placetype":"locality"
},
  "geometry": {"coordinates":[-54.16667,-24.05],"type":"Point"}
}