{
  "type": "Feature",
  "properties": {
    "gn:admin1_code":"18.0",
    "gn:admin2_code":"4127809.0",
    "gn:asciiname":"Sitio Jorge Arruda",
    "gn:country_code":"BR",
    "gn:dem":639,
    "gn:feature_class":"P",
    "gn:feature_code":"PPL",
    "gn:name":"S\u00edtio Jorge Arruda",
    "gn:population":0,
    "gn:timezone":"America/Sao_Paulo",
    "iso:country":"BR",
    "name:por_x_preferred":[
        "S\u00edtio Jorge Arruda"
    ],
    "wof:name":"Sitio Jorge Arruda",
    "wof:placetype":"locality"
},
  "geometry": {"coordinates":[-49.9082,-23.6654],"type":"Point"}
}