{
  "type": "Feature",
  "properties": {
    "gn:admin1_code":"15",
    "gn:admin2_code":"3143302.0",
    "gn:asciiname":"Veado",
    "gn:cc2":"BR",
    "gn:country_code":"BR",
    "gn:dem":798,
    "gn:feature_class":"P",
    "gn:feature_code":"PPL",
    "gn:name":"Veado",
    "gn:population":0,
    "gn:timezone":"America/Sao_Paulo",
    "iso:country":"BR",
    "name:und_x_variant":[
        "Veodos",
        "Veado"
    ],
    "wof:name":"Veado",
    "wof:placetype":"locality"
},
  "geometry": {"coordinates":[-43.98333,-16.61667000000001],"type":"Point"}
}