{
  "type": "Feature",
  "properties": {
    "gn:admin1_code":"14",
    "gn:admin2_code":"5104906.0",
    "gn:asciiname":"Coronel Retiro",
    "gn:country_code":"BR",
    "gn:dem":251,
    "gn:feature_class":"P",
    "gn:feature_code":"PPL",
    "gn:name":"Coronel Retiro",
    "gn:population":0,
    "gn:timezone":"America/Cuiaba",
    "iso:country":"BR",
    "wof:name":"Coronel Retiro",
    "wof:placetype":"locality"
},
  "geometry": {"coordinates":[-56.6253,-15.37131],"type":"Point"}
}