{
  "type": "Feature",
  "properties": {
    "gn:admin1_code":"31",
    "gn:admin2_code":"1703867.0",
    "gn:asciiname":"Brejo Verde",
    "gn:country_code":"BR",
    "gn:dem":307,
    "gn:feature_class":"P",
    "gn:feature_code":"PPL",
    "gn:name":"Brejo Verde",
    "gn:population":0,
    "gn:timezone":"America/Araguaina",
    "iso:country":"BR",
    "wof:name":"Brejo Verde",
    "wof:placetype":"locality"
},
  "geometry": {"coordinates":[-49.25056,-11.96694],"type":"Point"}
}