{
  "type": "Feature",
  "properties": {
    "gn:admin1_code":"27.0",
    "gn:admin2_code":"3514809.0",
    "gn:asciiname":"Sitio Sapatu",
    "gn:country_code":"BR",
    "gn:dem":59,
    "gn:feature_class":"P",
    "gn:feature_code":"PPL",
    "gn:name":"S\u00edtio Sapatu",
    "gn:population":0,
    "gn:timezone":"America/Sao_Paulo",
    "iso:country":"BR",
    "name:por_x_preferred":[
        "S\u00edtio Sapatu"
    ],
    "wof:name":"Sitio Sapatu",
    "wof:placetype":"locality"
},
  "geometry": {"coordinates":[-48.30474,-24.65152],"type":"Point"}
}