{
  "type": "Feature",
  "properties": {
    "gn:admin1_code":"5",
    "gn:admin2_code":"2901809.0",
    "gn:asciiname":"Itinga da Serra",
    "gn:cc2":"BR",
    "gn:country_code":"BR",
    "gn:dem":637,
    "gn:feature_class":"P",
    "gn:feature_code":"PPL",
    "gn:name":"Itinga da Serra",
    "gn:population":0,
    "gn:timezone":"America/Bahia",
    "iso:country":"BR",
    "name:und_x_variant":[
        "Itinga",
        "Itinga da Serra"
    ],
    "wof:name":"Itinga da Serra",
    "wof:placetype":"locality"
},
  "geometry": {"coordinates":[-40.28333,-10.56667],"type":"Point"}
}