{
  "type": "Feature",
  "properties": {
    "gn:admin1_code":"29.0",
    "gn:admin2_code":"5202155.0",
    "gn:asciiname":"Sao Jose da Fazendinha",
    "gn:country_code":"BR",
    "gn:dem":384,
    "gn:feature_class":"P",
    "gn:feature_code":"PPL",
    "gn:name":"S\u00e3o Jos\u00e9 da Fazendinha",
    "gn:population":0,
    "gn:timezone":"America/Sao_Paulo",
    "iso:country":"BR",
    "name:por_x_preferred":[
        "S\u00e3o Jos\u00e9 da Fazendinha"
    ],
    "wof:name":"Sao Jose da Fazendinha",
    "wof:placetype":"locality"
},
  "geometry": {"coordinates":[-50.2479,-15.19792],"type":"Point"}
}