{
  "type": "Feature",
  "properties": {
    "gn:admin1_code":"4",
    "gn:admin2_code":"1303809.0",
    "gn:asciiname":"Bauta",
    "gn:country_code":"BR",
    "gn:dem":88,
    "gn:feature_class":"P",
    "gn:feature_code":"PPL",
    "gn:name":"Baut\u00e1",
    "gn:population":0,
    "gn:timezone":"America/Manaus",
    "iso:country":"BR",
    "name:ceb_x_preferred":[
        "Bauta"
    ],
    "name:deu_x_preferred":[
        "Bauta"
    ],
    "name:fra_x_preferred":[
        "Bauta"
    ],
    "name:ita_x_preferred":[
        "Bauta"
    ],
    "name:vec_x_preferred":[
        "Bauta"
    ],
    "wof:name":"Bauta",
    "wof:placetype":"locality"
},
  "geometry": {"coordinates":[-67.28333000000001,0.31667],"type":"Point"}
}