{
  "type": "Feature",
  "properties": {
    "gn:admin1_code":"06",
    "gn:admin2_code":"2302305.0",
    "gn:asciiname":"Caldeirao",
    "gn:country_code":"BR",
    "gn:dem":33,
    "gn:feature_class":"P",
    "gn:feature_code":"PPL",
    "gn:name":"Caldeir\u00e3o",
    "gn:population":0,
    "gn:timezone":"America/Fortaleza",
    "iso:country":"BR",
    "wof:name":"Caldeirao",
    "wof:placetype":"locality"
},
  "geometry": {"coordinates":[-40.31667,-2.95],"type":"Point"}
}