{
  "type": "Feature",
  "properties": {
    "gn:admin1_code":"13",
    "gn:admin2_code":"2105922.0",
    "gn:asciiname":"Pe de Serra",
    "gn:country_code":"BR",
    "gn:dem":160,
    "gn:feature_class":"P",
    "gn:feature_code":"PPL",
    "gn:name":"P\u00e9 de Serra",
    "gn:population":0,
    "gn:timezone":"America/Fortaleza",
    "iso:country":"BR",
    "wof:name":"Pe de Serra",
    "wof:placetype":"locality"
},
  "geometry": {"coordinates":[-43.31667,-6.03333],"type":"Point"}
}