{
  "type": "Feature",
  "properties": {
    "gn:admin1_code":"18",
    "gn:admin2_code":"4114302.0",
    "gn:asciiname":"Sitio Jose Bucco",
    "gn:country_code":"BR",
    "gn:dem":891,
    "gn:feature_class":"P",
    "gn:feature_code":"PPL",
    "gn:name":"S\u00edtio Jos\u00e9 Bucco",
    "gn:population":0,
    "gn:timezone":"America/Sao_Paulo",
    "iso:country":"BR",
    "name:por_x_preferred":[
        "S\u00edtio Jos\u00e9 Bucco"
    ],
    "wof:name":"Sitio Jose Bucco",
    "wof:placetype":"locality"
},
  "geometry": {"coordinates":[-49.23223,-25.8781],"type":"Point"}
}