{
  "type": "Feature",
  "properties": {
    "gn:admin1_code":"21",
    "gn:admin2_code":"3302700.0",
    "gn:asciiname":"Itaipuacu",
    "gn:country_code":"BR",
    "gn:dem":20,
    "gn:feature_class":"P",
    "gn:feature_code":"PPL",
    "gn:name":"Itaipua\u00e7u",
    "gn:population":0,
    "gn:timezone":"America/Sao_Paulo",
    "iso:country":"BR",
    "name:por_x_preferred":[
        "Itaipua\u00e7u"
    ],
    "wof:name":"Itaipuacu",
    "wof:placetype":"locality"
},
  "geometry": {"coordinates":[-43.01667,-22.96667],"type":"Point"}
}