{
  "type": "Feature",
  "properties": {
    "gn:admin1_code":"18",
    "gn:admin2_code":"4104105.0",
    "gn:asciiname":"Sitio Vitorio Bonatti",
    "gn:country_code":"BR",
    "gn:dem":861,
    "gn:feature_class":"P",
    "gn:feature_code":"PPL",
    "gn:name":"S\u00edtio Vitorio Bonatti",
    "gn:population":0,
    "gn:timezone":"America/Sao_Paulo",
    "iso:country":"BR",
    "name:por_x_preferred":[
        "S\u00edtio Vitorio Bonatti"
    ],
    "wof:name":"Sitio Vitorio Bonatti",
    "wof:placetype":"locality"
},
  "geometry": {"coordinates":[-49.68333,-25.99667],"type":"Point"}
}