{
  "type": "Feature",
  "properties": {
    "gn:admin1_code":"5",
    "gn:admin2_code":"2922003.0",
    "gn:asciiname":"Ostras",
    "gn:country_code":"BR",
    "gn:dem":45,
    "gn:feature_class":"P",
    "gn:feature_code":"PPL",
    "gn:name":"Ostras",
    "gn:population":0,
    "gn:timezone":"America/Bahia",
    "iso:country":"BR",
    "name:por_x_preferred":[
        "Ostras"
    ],
    "wof:name":"Ostras",
    "wof:placetype":"locality"
},
  "geometry": {"coordinates":[-39.63333,-18.18333],"type":"Point"}
}