{
  "type": "Feature",
  "properties": {
    "gn:admin1_code":"5",
    "gn:admin2_code":"2924405.0",
    "gn:asciiname":"Pato",
    "gn:country_code":"BR",
    "gn:dem":459,
    "gn:feature_class":"P",
    "gn:feature_code":"PPL",
    "gn:name":"Pato",
    "gn:population":0,
    "gn:timezone":"America/Bahia",
    "iso:country":"BR",
    "name:ara_x_preferred":[
        "\u0628\u0627\u062a\u0648"
    ],
    "name:cat_x_preferred":[
        "Pato"
    ],
    "name:deu_x_preferred":[
        "Pato"
    ],
    "name:fas_x_preferred":[
        "\u067e\u0627\u062a\u0648"
    ],
    "name:fin_x_preferred":[
        "Pato"
    ],
    "name:fra_x_preferred":[
        "Pato"
    ],
    "name:new_x_preferred":[
        "\u092a\u093e\u091f\u094b"
    ],
    "name:oci_x_preferred":[
        "Pato"
    ],
    "name:por_x_preferred":[
        "Pato"
    ],
    "name:spa_x_preferred":[
        "Pato"
    ],
    "name:swe_x_preferred":[
        "Pato"
    ],
    "name:und_x_variant":[
        "Patos"
    ],
    "wof:name":"Pato",
    "wof:placetype":"locality"
},
  "geometry": {"coordinates":[-43.44819,-10.11228],"type":"Point"}
}