{
  "type": "Feature",
  "properties": {
    "gn:admin1_code":"25",
    "gn:admin2_code":"1400175.0",
    "gn:asciiname":"Uainiame",
    "gn:country_code":"BR",
    "gn:dem":97,
    "gn:feature_class":"P",
    "gn:feature_code":"PPL",
    "gn:name":"Uainiame",
    "gn:population":0,
    "gn:timezone":"America/Boa_Vista",
    "iso:country":"BR",
    "wof:name":"Uainiame",
    "wof:placetype":"locality"
},
  "geometry": {"coordinates":[-60.38333000000001,2.76667],"type":"Point"}
}