{
  "type": "Feature",
  "properties": {
    "gn:admin1_code":"22",
    "gn:admin2_code":"2400802.0",
    "gn:asciiname":"Riacho do Prato",
    "gn:country_code":"BR",
    "gn:dem":126,
    "gn:feature_class":"P",
    "gn:feature_code":"PPL",
    "gn:name":"Riacho do Prato",
    "gn:population":0,
    "gn:timezone":"America/Fortaleza",
    "iso:country":"BR",
    "wof:name":"Riacho do Prato",
    "wof:placetype":"locality"
},
  "geometry": {"coordinates":[-36.635,-5.675],"type":"Point"}
}