{
  "type": "Feature",
  "properties": {
    "gn:admin1_code":"16",
    "gn:admin2_code":"1501303.0",
    "gn:asciiname":"Cafezal",
    "gn:country_code":"BR",
    "gn:dem":17,
    "gn:feature_class":"P",
    "gn:feature_code":"PPL",
    "gn:name":"Caf\u00e8zal",
    "gn:population":0,
    "gn:timezone":"America/Belem",
    "iso:country":"BR",
    "wof:name":"Cafezal",
    "wof:placetype":"locality"
},
  "geometry": {"coordinates":[-48.58333,-1.55],"type":"Point"}
}