{
  "type": "Feature",
  "properties": {
    "gn:admin1_code":"18.0",
    "gn:admin2_code":"4121802.0",
    "gn:asciiname":"Sitio Marcilio Neto",
    "gn:country_code":"BR",
    "gn:dem":585,
    "gn:feature_class":"P",
    "gn:feature_code":"PPL",
    "gn:name":"S\u00edtio Marc\u00edlio Neto",
    "gn:population":0,
    "gn:timezone":"America/Sao_Paulo",
    "iso:country":"BR",
    "name:por_x_preferred":[
        "S\u00edtio Marc\u00edlio Neto"
    ],
    "wof:name":"Sitio Marcilio Neto",
    "wof:placetype":"locality"
},
  "geometry": {"coordinates":[-49.83572,-23.43832],"type":"Point"}
}