{
  "type": "Feature",
  "properties": {
    "gn:admin1_code":"15",
    "gn:admin2_code":"3117504.0",
    "gn:asciiname":"Ouro Fino",
    "gn:country_code":"BR",
    "gn:dem":816,
    "gn:feature_class":"P",
    "gn:feature_code":"PPL",
    "gn:name":"Ouro Fino",
    "gn:population":0,
    "gn:timezone":"America/Sao_Paulo",
    "iso:country":"BR",
    "name:bpy_x_preferred":[
        "\u0994\u09b0\u09cb \u09ab\u09bf\u09a8\u09cb"
    ],
    "name:ceb_x_preferred":[
        "Ouro Fino"
    ],
    "name:epo_x_preferred":[
        "Ouro Fino"
    ],
    "name:eus_x_preferred":[
        "Ouro Fino"
    ],
    "name:fra_x_preferred":[
        "Ouro Fino"
    ],
    "name:ita_x_preferred":[
        "Ouro Fino"
    ],
    "name:kat_x_preferred":[
        "\u10dd\u10e0\u10e3-\u10e4\u10d8\u10dc\u10e3"
    ],
    "name:kaz_x_preferred":[
        "\u041e\u0440\u0443-\u0424\u0438\u043d\u0443"
    ],
    "name:mlg_x_preferred":[
        "Ouro Fino"
    ],
    "name:nld_x_preferred":[
        "Ouro Fino"
    ],
    "name:nor_x_preferred":[
        "Ouro Fino"
    ],
    "name:pol_x_preferred":[
        "Ouro Fino"
    ],
    "name:por_x_preferred":[
        "Ouro Fino"
    ],
    "name:ron_x_preferred":[
        "Ouro Fino"
    ],
    "name:rus_x_preferred":[
        "\u041e\u0440\u0443-\u0424\u0438\u043d\u0443"
    ],
    "name:sco_x_preferred":[
        "Ouro Fino"
    ],
    "name:spa_x_preferred":[
        "Ouro Fino"
    ],
    "name:swe_x_preferred":[
        "Ouro Fino"
    ],
    "name:vie_x_preferred":[
        "Ouro Fino"
    ],
    "name:vol_x_preferred":[
        "Ouro Fino"
    ],
    "name:war_x_preferred":[
        "Ouro Fino"
    ],
    "name:zho_x_preferred":[
        "\u6b27\u9c81\u83f2\u52aa"
    ],
    "wof:name":"Ouro Fino",
    "wof:placetype":"locality"
},
  "geometry": {"coordinates":[-43.61667,-18.95],"type":"Point"}
}