{
  "type": "Feature",
  "properties": {
    "gn:admin1_code":"27",
    "gn:admin2_code":"3535408.0",
    "gn:asciiname":"Porto Marrecas",
    "gn:cc2":"BR",
    "gn:country_code":"BR",
    "gn:dem":256,
    "gn:feature_class":"P",
    "gn:feature_code":"PPL",
    "gn:name":"P\u00f4rto Marrecas",
    "gn:population":0,
    "gn:timezone":"America/Sao_Paulo",
    "iso:country":"BR",
    "name:und_x_variant":[
        "Marrecas",
        "Porto",
        "P\u00f4rto das Marrecas",
        "P\u00f4rto Marrecas"
    ],
    "wof:name":"Porto Marrecas",
    "wof:placetype":"locality"
},
  "geometry": {"coordinates":[-51.86667,-21.35],"type":"Point"}
}