{
  "type": "Feature",
  "properties": {
    "gn:admin1_code":"11",
    "gn:admin2_code":"5007976.0",
    "gn:asciiname":"Porto Quinze de Agosto",
    "gn:cc2":"BR",
    "gn:country_code":"BR",
    "gn:dem":245,
    "gn:feature_class":"P",
    "gn:feature_code":"PPL",
    "gn:name":"P\u00f4rto Quinze de Ag\u00f4sto",
    "gn:population":0,
    "gn:timezone":"America/Campo_Grande",
    "iso:country":"BR",
    "name:und_x_variant":[
        "P\u00f4rto 15 de Ag\u00f4sto",
        "P\u00f4rto Quinze de Ag\u00f4sto"
    ],
    "wof:name":"Porto Quinze de Agosto",
    "wof:placetype":"locality"
},
  "geometry": {"coordinates":[-53.53333000000001,-22.65],"type":"Point"}
}