{
  "type": "Feature",
  "properties": {
    "gn:admin1_code":"17",
    "gn:admin2_code":"2508109.0",
    "gn:asciiname":"Lagoa Seca",
    "gn:country_code":"BR",
    "gn:dem":252,
    "gn:feature_class":"P",
    "gn:feature_code":"PPL",
    "gn:name":"Lagoa S\u00eaca",
    "gn:population":0,
    "gn:timezone":"America/Fortaleza",
    "iso:country":"BR",
    "wof:name":"Lagoa Seca",
    "wof:placetype":"locality"
},
  "geometry": {"coordinates":[-37.85,-6.56667],"type":"Point"}
}