{
  "type": "Feature",
  "properties": {
    "gn:admin1_code":"17",
    "gn:admin2_code":"2508109.0",
    "gn:asciiname":"Lagoa Seca",
    "gn:country_code":"BR",
    "gn:dem":252,
    "gn:feature_class":"P",
    "gn:feature_code":"PPL",
    "gn:name":"Lagoa S\u00eaca",
    "gn:population":0,
    "gn:timezone":"America/Fortaleza",
    "iso:country":"BR",
    "name:bpy_x_preferred":[
        "\u09b2\u09be\u0997\u09cb\u09af\u09bc\u09be \u09b8\u09c7\u0995\u09be"
    ],
    "name:eus_x_preferred":[
        "Lagoa Seca"
    ],
    "name:fra_x_preferred":[
        "Lagoa Seca"
    ],
    "name:hye_x_preferred":[
        "\u053c\u0561\u0563\u0578\u0561 \u054d\u0565\u056f\u0561"
    ],
    "name:ita_x_preferred":[
        "Lagoa Seca"
    ],
    "name:kat_x_preferred":[
        "\u10da\u10d0\u10d2\u10dd\u10d0-\u10e1\u10d4\u10d9\u10d0"
    ],
    "name:kaz_x_preferred":[
        "\u041b\u0430\u0433\u043e\u0430-\u0421\u0435\u043a\u0430"
    ],
    "name:nld_x_preferred":[
        "Lagoa Seca"
    ],
    "name:nor_x_preferred":[
        "Lagoa Seca"
    ],
    "name:por_x_preferred":[
        "Lagoa Seca"
    ],
    "name:ron_x_preferred":[
        "Lagoa Seca"
    ],
    "name:rus_x_preferred":[
        "\u041b\u0430\u0433\u043e\u0430-\u0421\u0435\u043a\u0430"
    ],
    "name:urd_x_preferred":[
        "\u0644\u0627\u06af\u0648\u0627 \u0633\u06cc\u06a9\u0627"
    ],
    "name:vie_x_preferred":[
        "Lagoa Seca"
    ],
    "name:vol_x_preferred":[
        "Lagoa Seca"
    ],
    "name:war_x_preferred":[
        "Lagoa Seca"
    ],
    "name:zho_x_preferred":[
        "\u62c9\u6208\u963f-\u585e\u5361"
    ],
    "wof:name":"Lagoa Seca",
    "wof:placetype":"locality"
},
  "geometry": {"coordinates":[-37.85,-6.56667],"type":"Point"}
}