{
  "type": "Feature",
  "properties": {
    "gn:admin1_code":"30",
    "gn:admin2_code":"2610905.0",
    "gn:asciiname":"Capunga",
    "gn:country_code":"BR",
    "gn:dem":651,
    "gn:feature_class":"P",
    "gn:feature_code":"PPL",
    "gn:name":"Capunga",
    "gn:population":0,
    "gn:timezone":"America/Recife",
    "iso:country":"BR",
    "wof:name":"Capunga",
    "wof:placetype":"locality"
},
  "geometry": {"coordinates":[-36.66667,-8.36667],"type":"Point"}
}