{
  "type": "Feature",
  "properties": {
    "gn:admin1_code":"30",
    "gn:admin2_code":"2607505.0",
    "gn:asciiname":"Riacho dos Negros",
    "gn:country_code":"BR",
    "gn:dem":397,
    "gn:feature_class":"P",
    "gn:feature_code":"PPL",
    "gn:name":"Riacho dos Negros",
    "gn:population":0,
    "gn:timezone":"America/Recife",
    "iso:country":"BR",
    "wof:name":"Riacho dos Negros",
    "wof:placetype":"locality"
},
  "geometry": {"coordinates":[-37.28333,-9.03333],"type":"Point"}
}