{
  "type": "Feature",
  "properties": {
    "gn:admin1_code":"30",
    "gn:admin2_code":"2605301.0",
    "gn:asciiname":"Ambrozio",
    "gn:country_code":"BR",
    "gn:dem":814,
    "gn:feature_class":"P",
    "gn:feature_code":"PPL",
    "gn:name":"Ambr\u00f3zio",
    "gn:population":0,
    "gn:timezone":"America/Recife",
    "iso:country":"BR",
    "wof:name":"Ambrozio",
    "wof:placetype":"locality"
},
  "geometry": {"coordinates":[-39.86667,-7.58333],"type":"Point"}
}