{
  "type": "Feature",
  "properties": {
    "iso:country":"BR",
    "name:ceb_x_preferred":[
        "Vila Rica Airport"
    ],
    "name:deu_x_preferred":[
        "Flughafen Vila Rica"
    ],
    "name:eng_x_preferred":[
        "Vila Rica Airport"
    ],
    "name:msa_x_preferred":[
        "Lapangan Terbang Vila Rica"
    ],
    "name:ron_x_preferred":[
        "Aeroportul Vila Rica"
    ],
    "name:swe_x_preferred":[
        "Vila Rica Airport"
    ],
    "oa:elevation_ft":"892",
    "oa:type":"small_airport",
    "woe:hierarchy":{
        "country_id":23424768,
        "county_id":12579403,
        "planet_id":1,
        "state_id":2344855
    },
    "wof:name":"Aeroporto Municipal de Vila Rica",
    "wof:placetype":"campus"
},
  "geometry": {"coordinates":[-51.142222,-9.979445],"type":"Point"}
}