{
  "type": "Feature",
  "properties": {
    "gn:admin1_code":"18.0",
    "gn:admin2_code":"4124301.0",
    "gn:asciiname":"Sitio Vicente F. de Oliveira",
    "gn:country_code":"BR",
    "gn:dem":670,
    "gn:feature_class":"P",
    "gn:feature_code":"PPL",
    "gn:name":"S\u00edtio Vicente F. de Oliveira",
    "gn:population":0,
    "gn:timezone":"America/Sao_Paulo",
    "iso:country":"BR",
    "name:por_x_preferred":[
        "S\u00edtio Vicente F. de Oliveira"
    ],
    "wof:name":"Sitio Vicente F. de Oliveira",
    "wof:placetype":"locality"
},
  "geometry": {"coordinates":[-50.63898,-23.52857],"type":"Point"}
}