{
  "type": "Feature",
  "properties": {
    "gn:admin1_code":"27.0",
    "gn:admin2_code":"3518800.0",
    "gn:asciiname":"Jardim Paraiso",
    "gn:country_code":"BR",
    "gn:dem":769,
    "gn:feature_class":"P",
    "gn:feature_code":"PPL",
    "gn:name":"Jardim Para\u00edso",
    "gn:population":0,
    "gn:timezone":"America/Sao_Paulo",
    "iso:country":"BR",
    "name:por_x_preferred":[
        "Jardim Para\u00edso"
    ],
    "wof:name":"Jardim Paraiso",
    "wof:placetype":"locality"
},
  "geometry": {"coordinates":[-46.50345,-23.41493],"type":"Point"}
}