{
  "type": "Feature",
  "properties": {
    "gn:admin1_code":"13",
    "gn:admin2_code":"2106672.0",
    "gn:asciiname":"Cambota",
    "gn:country_code":"BR",
    "gn:dem":50,
    "gn:feature_class":"P",
    "gn:feature_code":"PPL",
    "gn:name":"Cambot\u00e1",
    "gn:population":0,
    "gn:timezone":"America/Fortaleza",
    "iso:country":"BR",
    "wof:name":"Cambota",
    "wof:placetype":"locality"
},
  "geometry": {"coordinates":[-42.7925,-3.44833],"type":"Point"}
}