{
  "type": "Feature",
  "properties": {
    "gn:admin1_code":"17",
    "gn:admin2_code":"2516300.0",
    "gn:asciiname":"Feijao",
    "gn:country_code":"BR",
    "gn:dem":540,
    "gn:feature_class":"P",
    "gn:feature_code":"PPL",
    "gn:name":"Feij\u00e3o",
    "gn:population":0,
    "gn:timezone":"America/Fortaleza",
    "iso:country":"BR",
    "wof:name":"Feijao",
    "wof:placetype":"locality"
},
  "geometry": {"coordinates":[-36.95,-7.68333],"type":"Point"}
}