{
  "type": "Feature",
  "properties": {
    "gn:admin1_code":"06",
    "gn:admin2_code":"2311504.0",
    "gn:asciiname":"Nova (1)",
    "gn:country_code":"BR",
    "gn:dem":131,
    "gn:feature_class":"P",
    "gn:feature_code":"PPL",
    "gn:name":"Nova (1)",
    "gn:population":0,
    "gn:timezone":"America/Fortaleza",
    "iso:country":"BR",
    "wof:name":"Nova (1)",
    "wof:placetype":"locality"
},
  "geometry": {"coordinates":[-37.85,-5.08333],"type":"Point"}
}