{
  "type": "Feature",
  "properties": {
    "gn:admin1_code":"24",
    "gn:admin2_code":"1100940.0",
    "gn:asciiname":"Sao Carlos",
    "gn:cc2":"BR",
    "gn:country_code":"BR",
    "gn:dem":159,
    "gn:feature_class":"P",
    "gn:feature_code":"PPL",
    "gn:name":"S\u00e3o Carlos",
    "gn:population":0,
    "gn:timezone":"America/Porto_Velho",
    "iso:country":"BR",
    "name:und_x_variant":[
        "Jatuarama",
        "S\u00e3o Carlos"
    ],
    "wof:name":"Sao Carlos",
    "wof:placetype":"locality"
},
  "geometry": {"coordinates":[-62.53333000000001,-9.41667],"type":"Point"}
}