{
  "type": "Feature",
  "properties": {
    "gn:admin1_code":"18",
    "gn:admin2_code":"4127601.0",
    "gn:asciiname":"Sitio Jose Pereira",
    "gn:country_code":"BR",
    "gn:dem":929,
    "gn:feature_class":"P",
    "gn:feature_code":"PPL",
    "gn:name":"S\u00edtio Jos\u00e9 Pereira",
    "gn:population":0,
    "gn:timezone":"America/Sao_Paulo",
    "iso:country":"BR",
    "name:por_x_preferred":[
        "S\u00edtio Jos\u00e9 Pereira"
    ],
    "wof:name":"Sitio Jose Pereira",
    "wof:placetype":"locality"
},
  "geometry": {"coordinates":[-49.1686,-25.8586],"type":"Point"}
}