{
  "type": "Feature",
  "properties": {
    "gn:admin1_code":"5",
    "gn:admin2_code":"2902708.0",
    "gn:asciiname":"Umburanas",
    "gn:country_code":"BR",
    "gn:dem":542,
    "gn:feature_class":"P",
    "gn:feature_code":"PPL",
    "gn:name":"Umburanas",
    "gn:population":0,
    "gn:timezone":"America/Bahia",
    "iso:country":"BR",
    "name:bpy_x_preferred":[
        "\u0989\u09ae\u09ac\u09c1\u09b0\u09be\u09a8\u09be\u09b8"
    ],
    "name:ceb_x_preferred":[
        "Umburanas"
    ],
    "name:epo_x_preferred":[
        "Umburanas"
    ],
    "name:eus_x_preferred":[
        "Umburanas"
    ],
    "name:fra_x_preferred":[
        "Umburanas"
    ],
    "name:hye_x_preferred":[
        "\u0548\u0582\u0574\u0562\u0578\u0582\u0580\u0561\u0576\u0561\u057d"
    ],
    "name:ita_x_preferred":[
        "Umburanas"
    ],
    "name:kat_x_preferred":[
        "\u10e3\u10db\u10d1\u10e3\u10e0\u10d0\u10dc\u10d0\u10e1\u10d8"
    ],
    "name:kaz_x_preferred":[
        "\u0423\u043c\u0431\u0443\u0440\u0430\u043d\u0430\u0441"
    ],
    "name:mlg_x_preferred":[
        "Umburanas"
    ],
    "name:nld_x_preferred":[
        "Umburanas"
    ],
    "name:nor_x_preferred":[
        "Umburanas"
    ],
    "name:pol_x_preferred":[
        "Umburanas"
    ],
    "name:por_x_preferred":[
        "Umburanas"
    ],
    "name:ron_x_preferred":[
        "Umburanas"
    ],
    "name:rus_x_preferred":[
        "\u0423\u043c\u0431\u0443\u0440\u0430\u043d\u0430\u0441"
    ],
    "name:swe_x_preferred":[
        "Umburanas"
    ],
    "name:vie_x_preferred":[
        "Umburanas"
    ],
    "name:vol_x_preferred":[
        "Umburanas"
    ],
    "name:war_x_preferred":[
        "Umburanas"
    ],
    "name:zho_x_preferred":[
        "\u6e29\u5e03\u62c9\u7eb3\u65af"
    ],
    "wof:name":"Umburanas",
    "wof:placetype":"locality"
},
  "geometry": {"coordinates":[-43.28847,-10.56373],"type":"Point"}
}