{
  "type": "Feature",
  "properties": {
    "gn:admin1_code":"5",
    "gn:admin2_code":"2902708.0",
    "gn:asciiname":"Umburanas",
    "gn:country_code":"BR",
    "gn:dem":542,
    "gn:feature_class":"P",
    "gn:feature_code":"PPL",
    "gn:name":"Umburanas",
    "gn:population":0,
    "gn:timezone":"America/Bahia",
    "iso:country":"BR",
    "wof:name":"Umburanas",
    "wof:placetype":"locality"
},
  "geometry": {"coordinates":[-43.28847,-10.56373],"type":"Point"}
}