{
  "type": "Feature",
  "properties": {
    "gn:admin1_code":"31",
    "gn:admin2_code":"1718659.0",
    "gn:asciiname":"Brejo Fechado",
    "gn:cc2":"BR",
    "gn:country_code":"BR",
    "gn:dem":585,
    "gn:feature_class":"P",
    "gn:feature_code":"PPL",
    "gn:name":"Brejo Fechado",
    "gn:population":0,
    "gn:timezone":"America/Araguaina",
    "iso:country":"BR",
    "name:und_x_variant":[
        "Brejo Feichado",
        "Brajo Faichada",
        "Brejo Fechado"
    ],
    "wof:name":"Brejo Fechado",
    "wof:placetype":"locality"
},
  "geometry": {"coordinates":[-46.66667,-11.26667],"type":"Point"}
}