{
  "type": "Feature",
  "properties": {
    "gn:admin1_code":"13",
    "gn:admin2_code":"2106607.0",
    "gn:asciiname":"Brejinho",
    "gn:country_code":"BR",
    "gn:dem":189,
    "gn:feature_class":"P",
    "gn:feature_code":"PPL",
    "gn:name":"Brejinho",
    "gn:population":0,
    "gn:timezone":"America/Fortaleza",
    "iso:country":"BR",
    "wof:name":"Brejinho",
    "wof:placetype":"locality"
},
  "geometry": {"coordinates":[-43.15,-5.35],"type":"Point"}
}