{
  "type": "Feature",
  "properties": {
    "gn:admin1_code":"13",
    "gn:admin2_code":"2106607.0",
    "gn:asciiname":"Brejinho",
    "gn:country_code":"BR",
    "gn:dem":189,
    "gn:feature_class":"P",
    "gn:feature_code":"PPL",
    "gn:name":"Brejinho",
    "gn:population":0,
    "gn:timezone":"America/Fortaleza",
    "iso:country":"BR",
    "name:bpy_x_preferred":[
        "\u09ac\u09cd\u09b0\u09c7\u099c\u09bf\u09a8\u09b9\u09cb"
    ],
    "name:eus_x_preferred":[
        "Brejinho"
    ],
    "name:fra_x_preferred":[
        "Brejinho"
    ],
    "name:ita_x_preferred":[
        "Brejinho"
    ],
    "name:kat_x_preferred":[
        "\u10d1\u10e0\u10d4\u10df\u10d8\u10dc\u10d8\u10e3"
    ],
    "name:mlg_x_preferred":[
        "Brejinho"
    ],
    "name:nld_x_preferred":[
        "Brejinho"
    ],
    "name:nor_x_preferred":[
        "Brejinho"
    ],
    "name:por_x_preferred":[
        "Brejinho"
    ],
    "name:ron_x_preferred":[
        "Brejinho"
    ],
    "name:rus_x_preferred":[
        "\u0411\u0440\u0435\u0436\u0438\u043d\u044c\u044e"
    ],
    "name:vol_x_preferred":[
        "Brejinho"
    ],
    "name:war_x_preferred":[
        "Brejinho"
    ],
    "name:zho_x_preferred":[
        "\u5e03\u96f7\u65e5\u5c3c\u5965"
    ],
    "wof:name":"Brejinho",
    "wof:placetype":"locality"
},
  "geometry": {"coordinates":[-43.15,-5.35],"type":"Point"}
}