{
  "type": "Feature",
  "properties": {
    "gn:admin1_code":"15",
    "gn:admin2_code":"3136306.0",
    "gn:asciiname":"Espirito Santo",
    "gn:country_code":"BR",
    "gn:dem":669,
    "gn:feature_class":"P",
    "gn:feature_code":"PPL",
    "gn:name":"Esp\u00edrito Santo",
    "gn:population":0,
    "gn:timezone":"America/Sao_Paulo",
    "iso:country":"BR",
    "name:por_x_preferred":[
        "Esp\u00edrito Santo"
    ],
    "wof:name":"Espirito Santo",
    "wof:placetype":"locality"
},
  "geometry": {"coordinates":[-45.93333,-17.65],"type":"Point"}
}