{
  "type": "Feature",
  "properties": {
    "gn:admin1_code":"15",
    "gn:admin2_code":"3131000.0",
    "gn:asciiname":"Riacho da Areia",
    "gn:cc2":"BR",
    "gn:country_code":"BR",
    "gn:dem":795,
    "gn:feature_class":"P",
    "gn:feature_code":"PPL",
    "gn:name":"Riacho da Areia",
    "gn:population":0,
    "gn:timezone":"America/Sao_Paulo",
    "iso:country":"BR",
    "name:und_x_variant":[
        "Areias",
        "Riacho da Areia"
    ],
    "wof:name":"Riacho da Areia",
    "wof:placetype":"locality"
},
  "geometry": {"coordinates":[-44.38333,-19.53333],"type":"Point"}
}