{
  "type": "Feature",
  "properties": {
    "gn:admin1_code":"5",
    "gn:admin2_code":"2903706.0",
    "gn:asciiname":"Modesto",
    "gn:country_code":"BR",
    "gn:dem":552,
    "gn:feature_class":"P",
    "gn:feature_code":"PPL",
    "gn:name":"Modesto",
    "gn:population":0,
    "gn:timezone":"America/Bahia",
    "iso:country":"BR",
    "wof:name":"Modesto",
    "wof:placetype":"locality"
},
  "geometry": {"coordinates":[-40.45,-14.31667],"type":"Point"}
}