{
  "type": "Feature",
  "properties": {
    "gn:admin1_code":"25",
    "gn:admin2_code":"1400159.0",
    "gn:asciiname":"Porre",
    "gn:country_code":"BR",
    "gn:dem":79,
    "gn:feature_class":"P",
    "gn:feature_code":"PPL",
    "gn:name":"Porre",
    "gn:population":0,
    "gn:timezone":"America/Boa_Vista",
    "iso:country":"BR",
    "wof:name":"Porre",
    "wof:placetype":"locality"
},
  "geometry": {"coordinates":[-60.36666999999999,3.13333],"type":"Point"}
}