{
  "type": "Feature",
  "properties": {
    "gn:admin1_code":"22",
    "gn:admin2_code":"2406601.0",
    "gn:asciiname":"Lagoa Nova",
    "gn:country_code":"BR",
    "gn:dem":105,
    "gn:feature_class":"P",
    "gn:feature_code":"PPL",
    "gn:name":"Lagoa Nova",
    "gn:population":0,
    "gn:timezone":"America/Fortaleza",
    "iso:country":"BR",
    "name:bpy_x_preferred":[
        "\u09b2\u09be\u0997\u09cb\u09af\u09bc\u09be \u09a8\u09cb\u09ad\u09be"
    ],
    "name:ceb_x_preferred":[
        "Lagoa Nova"
    ],
    "name:epo_x_preferred":[
        "Lagoa Nova"
    ],
    "name:eus_x_preferred":[
        "Lagoa Nova"
    ],
    "name:fas_x_preferred":[
        "\u0644\u0627\u06af\u0648\u0627 \u0646\u0648\u0648\u0627"
    ],
    "name:fra_x_preferred":[
        "Lagoa Nova"
    ],
    "name:ita_x_preferred":[
        "Lagoa Nova"
    ],
    "name:kat_x_preferred":[
        "\u10da\u10d0\u10d2\u10dd\u10d0-\u10dc\u10dd\u10d5\u10d0"
    ],
    "name:kaz_x_preferred":[
        "\u041b\u0430\u0433\u043e\u0430-\u041d\u043e\u0432\u0430"
    ],
    "name:mlg_x_preferred":[
        "Lagoa Nova"
    ],
    "name:nld_x_preferred":[
        "Lagoa Nova"
    ],
    "name:nor_x_preferred":[
        "Lagoa Nova"
    ],
    "name:por_x_preferred":[
        "Lagoa Nova"
    ],
    "name:ron_x_preferred":[
        "Lagoa Nova"
    ],
    "name:rus_x_preferred":[
        "\u041b\u0430\u0433\u043e\u0430-\u041d\u043e\u0432\u0430"
    ],
    "name:spa_x_preferred":[
        "Lagoa Nova"
    ],
    "name:swe_x_preferred":[
        "Lagoa Nova"
    ],
    "name:urd_x_preferred":[
        "\u0644\u0627\u06af\u0648\u0627 \u0646\u0648\u0648\u0627"
    ],
    "name:vie_x_preferred":[
        "Lagoa Nova"
    ],
    "name:vol_x_preferred":[
        "Lagoa Nova"
    ],
    "name:war_x_preferred":[
        "Lagoa Nova"
    ],
    "name:zho_x_preferred":[
        "\u65b0\u62c9\u6208\u963f"
    ],
    "wof:name":"Lagoa Nova",
    "wof:placetype":"locality"
},
  "geometry": {"coordinates":[-35.47722,-6.12111],"type":"Point"}
}