{
  "type": "Feature",
  "properties": {
    "gn:admin1_code":"22",
    "gn:admin2_code":"2406601.0",
    "gn:asciiname":"Lagoa Nova",
    "gn:country_code":"BR",
    "gn:dem":105,
    "gn:feature_class":"P",
    "gn:feature_code":"PPL",
    "gn:name":"Lagoa Nova",
    "gn:population":0,
    "gn:timezone":"America/Fortaleza",
    "iso:country":"BR",
    "wof:name":"Lagoa Nova",
    "wof:placetype":"locality"
},
  "geometry": {"coordinates":[-35.47722,-6.12111],"type":"Point"}
}