{
  "type": "Feature",
  "properties": {
    "gn:admin1_code":"27",
    "gn:admin2_code":"3509601.0",
    "gn:asciiname":"Sitio Santo Agostinho",
    "gn:country_code":"BR",
    "gn:dem":784,
    "gn:feature_class":"P",
    "gn:feature_code":"PPL",
    "gn:name":"S\u00edtio Santo Agostinho",
    "gn:population":0,
    "gn:timezone":"America/Sao_Paulo",
    "iso:country":"BR",
    "name:por_x_preferred":[
        "S\u00edtio Santo Agostinho"
    ],
    "wof:name":"Sitio Santo Agostinho",
    "wof:placetype":"locality"
},
  "geometry": {"coordinates":[-46.73861,-23.21917],"type":"Point"}
}