{
  "type": "Feature",
  "properties": {
    "gn:admin1_code":"30",
    "gn:admin2_code":"2610301.0",
    "gn:asciiname":"Queimada do Andre",
    "gn:country_code":"BR",
    "gn:dem":840,
    "gn:feature_class":"P",
    "gn:feature_code":"PPL",
    "gn:name":"Queimada do Andr\u00e9",
    "gn:population":0,
    "gn:timezone":"America/Recife",
    "iso:country":"BR",
    "wof:name":"Queimada do Andre",
    "wof:placetype":"locality"
},
  "geometry": {"coordinates":[-36.66667,-8.88333],"type":"Point"}
}