{
  "type": "Feature",
  "properties": {
    "gn:admin1_code":"27",
    "gn:admin2_code":"3524600.0",
    "gn:asciiname":"Sitio Sao Luis",
    "gn:country_code":"BR",
    "gn:dem":37,
    "gn:feature_class":"P",
    "gn:feature_code":"PPL",
    "gn:name":"S\u00edtio S\u00e3o Luis",
    "gn:population":0,
    "gn:timezone":"America/Sao_Paulo",
    "iso:country":"BR",
    "name:por_x_preferred":[
        "S\u00edtio S\u00e3o Luis"
    ],
    "wof:name":"Sitio Sao Luis",
    "wof:placetype":"locality"
},
  "geometry": {"coordinates":[-48.0601,-24.7681],"type":"Point"}
}