{
  "type": "Feature",
  "properties": {
    "gn:admin1_code":"27.0",
    "gn:admin2_code":"3509908.0",
    "gn:asciiname":"Capuava",
    "gn:country_code":"BR",
    "gn:dem":56,
    "gn:feature_class":"P",
    "gn:feature_code":"PPLL",
    "gn:name":"Capuava",
    "gn:population":0,
    "gn:timezone":"America/Sao_Paulo",
    "iso:country":"BR",
    "name:por_x_preferred":[
        "Capuava"
    ],
    "wof:name":"Capuava",
    "wof:placetype":"locality"
},
  "geometry": {"coordinates":[-48.1122,-25.1434],"type":"Point"}
}