{
  "type": "Feature",
  "properties": {
    "gn:admin1_code":"26.0",
    "gn:admin2_code":"4210100.0",
    "gn:asciiname":"Sitio Nelson de Souza",
    "gn:country_code":"BR",
    "gn:dem":803,
    "gn:feature_class":"P",
    "gn:feature_code":"PPL",
    "gn:name":"S\u00edtio Nelson de Souza",
    "gn:population":0,
    "gn:timezone":"America/Sao_Paulo",
    "iso:country":"BR",
    "name:por_x_preferred":[
        "S\u00edtio Nelson de Souza"
    ],
    "wof:name":"Sitio Nelson de Souza",
    "wof:placetype":"locality"
},
  "geometry": {"coordinates":[-49.9791,-26.0531],"type":"Point"}
}