{
  "type": "Feature",
  "properties": {
    "gn:admin1_code":"13",
    "gn:admin2_code":"2106409.0",
    "gn:asciiname":"Murici",
    "gn:country_code":"BR",
    "gn:dem":58,
    "gn:feature_class":"P",
    "gn:feature_code":"PPL",
    "gn:name":"Murici",
    "gn:population":0,
    "gn:timezone":"America/Fortaleza",
    "iso:country":"BR",
    "name:bpy_x_preferred":[
        "\u09ae\u09c1\u09b0\u09bf\u09b8\u09bf"
    ],
    "name:ceb_x_preferred":[
        "Murici"
    ],
    "name:epo_x_preferred":[
        "Murici"
    ],
    "name:eus_x_preferred":[
        "Murici"
    ],
    "name:fra_x_preferred":[
        "Murici"
    ],
    "name:hye_x_preferred":[
        "\u0544\u0578\u0582\u0580\u056b\u057d\u056b"
    ],
    "name:ind_x_preferred":[
        "Murici"
    ],
    "name:ita_x_preferred":[
        "Murici"
    ],
    "name:kat_x_preferred":[
        "\u10db\u10e3\u10e0\u10d8\u10e1\u10d8"
    ],
    "name:kaz_x_preferred":[
        "\u041c\u0443\u0440\u0438\u0441\u0438"
    ],
    "name:mlg_x_preferred":[
        "Murici"
    ],
    "name:nld_x_preferred":[
        "Murici"
    ],
    "name:nor_x_preferred":[
        "Murici"
    ],
    "name:por_x_preferred":[
        "Murici"
    ],
    "name:ron_x_preferred":[
        "Murici"
    ],
    "name:rus_x_preferred":[
        "\u041c\u0443\u0440\u0438\u0441\u0438"
    ],
    "name:swe_x_preferred":[
        "Murici"
    ],
    "name:vie_x_preferred":[
        "Murici"
    ],
    "name:vol_x_preferred":[
        "Murici"
    ],
    "name:war_x_preferred":[
        "Murici"
    ],
    "name:zho_x_preferred":[
        "\u7a46\u91cc\u897f"
    ],
    "wof:name":"Murici",
    "wof:placetype":"locality"
},
  "geometry": {"coordinates":[-43.38472,-3.57583],"type":"Point"}
}