{
  "type": "Feature",
  "properties": {
    "gn:admin1_code":"30",
    "gn:admin2_code":"2610905.0",
    "gn:asciiname":"Riacho do Couro",
    "gn:country_code":"BR",
    "gn:dem":760,
    "gn:feature_class":"P",
    "gn:feature_code":"PPL",
    "gn:name":"Riacho do Couro",
    "gn:population":0,
    "gn:timezone":"America/Recife",
    "iso:country":"BR",
    "wof:name":"Riacho do Couro",
    "wof:placetype":"locality"
},
  "geometry": {"coordinates":[-36.71667,-8.58333],"type":"Point"}
}