{
  "type": "Feature",
  "properties": {
    "gn:admin1_code":"22",
    "gn:admin2_code":"2405801.0",
    "gn:asciiname":"Cajueiro",
    "gn:country_code":"BR",
    "gn:dem":152,
    "gn:feature_class":"P",
    "gn:feature_code":"PPL",
    "gn:name":"Cajueiro",
    "gn:population":0,
    "gn:timezone":"America/Fortaleza",
    "iso:country":"BR",
    "wof:name":"Cajueiro",
    "wof:placetype":"locality"
},
  "geometry": {"coordinates":[-35.85,-5.51667],"type":"Point"}
}