{
  "type": "Feature",
  "properties": {
    "gn:admin1_code":"30",
    "gn:admin2_code":"2601706.0",
    "gn:asciiname":"Lagoa dos Couros",
    "gn:country_code":"BR",
    "gn:dem":658,
    "gn:feature_class":"P",
    "gn:feature_code":"PPL",
    "gn:name":"Lagoa dos Couros",
    "gn:population":0,
    "gn:timezone":"America/Recife",
    "iso:country":"BR",
    "wof:name":"Lagoa dos Couros",
    "wof:placetype":"locality"
},
  "geometry": {"coordinates":[-36.31667,-8.26667],"type":"Point"}
}