{
  "type": "Feature",
  "properties": {
    "gn:admin1_code":"06",
    "gn:admin2_code":"2310001.0",
    "gn:asciiname":"Sao Luiz",
    "gn:country_code":"BR",
    "gn:dem":29,
    "gn:feature_class":"P",
    "gn:feature_code":"PPL",
    "gn:name":"S\u00e3o Luiz",
    "gn:population":0,
    "gn:timezone":"America/Fortaleza",
    "iso:country":"BR",
    "wof:name":"Sao Luiz",
    "wof:placetype":"locality"
},
  "geometry": {"coordinates":[-37.95,-4.75],"type":"Point"}
}