{
  "type": "Feature",
  "properties": {
    "gn:admin1_code":"18",
    "gn:admin2_code":"4106506.0",
    "gn:asciiname":"Rio Quieto",
    "gn:cc2":"BR",
    "gn:country_code":"BR",
    "gn:dem":492,
    "gn:feature_class":"P",
    "gn:feature_code":"PPL",
    "gn:name":"Rio Quieto",
    "gn:population":0,
    "gn:timezone":"America/Sao_Paulo",
    "iso:country":"BR",
    "name:und_x_variant":[
        "Quieto",
        "Rio Quieto"
    ],
    "wof:name":"Rio Quieto",
    "wof:placetype":"locality"
},
  "geometry": {"coordinates":[-52.66667,-25.96667],"type":"Point"}
}