{
  "type": "Feature",
  "properties": {
    "gn:admin1_code":"20",
    "gn:admin2_code":"2211308.0",
    "gn:asciiname":"Piacaba",
    "gn:country_code":"BR",
    "gn:dem":250,
    "gn:feature_class":"P",
    "gn:feature_code":"PPL",
    "gn:name":"Pia\u00e7aba",
    "gn:population":0,
    "gn:timezone":"America/Fortaleza",
    "iso:country":"BR",
    "wof:name":"Piacaba",
    "wof:placetype":"locality"
},
  "geometry": {"coordinates":[-41.73333,-6.31667],"type":"Point"}
}