{
  "type": "Feature",
  "properties": {
    "gn:admin1_code":"5",
    "gn:admin2_code":"2905008.0",
    "gn:asciiname":"Palmeiras",
    "gn:country_code":"BR",
    "gn:dem":721,
    "gn:feature_class":"P",
    "gn:feature_code":"PPL",
    "gn:name":"Palmeiras",
    "gn:population":0,
    "gn:timezone":"America/Bahia",
    "iso:country":"BR",
    "wof:name":"Palmeiras",
    "wof:placetype":"locality"
},
  "geometry": {"coordinates":[-42.31667,-14.61667],"type":"Point"}
}