{
  "type": "Feature",
  "properties": {
    "gn:admin1_code":"06",
    "gn:admin2_code":"2301406.0",
    "gn:asciiname":"Tope",
    "gn:country_code":"BR",
    "gn:dem":611,
    "gn:feature_class":"P",
    "gn:feature_code":"PPL",
    "gn:name":"Tope",
    "gn:population":0,
    "gn:timezone":"America/Fortaleza",
    "iso:country":"BR",
    "name:deu_x_preferred":[
        "Tope"
    ],
    "name:vls_x_preferred":[
        "Tope"
    ],
    "wof:name":"Tope",
    "wof:placetype":"locality"
},
  "geometry": {"coordinates":[-39.06667,-4.36667],"type":"Point"}
}