{
  "type": "Feature",
  "properties": {
    "gn:admin1_code":"06",
    "gn:admin2_code":"2303303.0",
    "gn:asciiname":"Conceicao",
    "gn:country_code":"BR",
    "gn:dem":249,
    "gn:feature_class":"P",
    "gn:feature_code":"PPL",
    "gn:name":"Concei\u00e7\u00e3o",
    "gn:population":0,
    "gn:timezone":"America/Fortaleza",
    "iso:country":"BR",
    "wof:name":"Conceicao",
    "wof:placetype":"locality"
},
  "geometry": {"coordinates":[-39.48333,-6.55],"type":"Point"}
}