{
  "type": "Feature",
  "properties": {
    "gn:admin1_code":"11",
    "gn:admin2_code":"5007950.0",
    "gn:asciiname":"Caraguatei",
    "gn:cc2":"BR",
    "gn:country_code":"BR",
    "gn:dem":435,
    "gn:feature_class":"P",
    "gn:feature_code":"PPL",
    "gn:name":"Caraguate\u00ed",
    "gn:population":0,
    "gn:timezone":"America/Campo_Grande",
    "iso:country":"BR",
    "name:und_x_variant":[
        "Caraguatehy",
        "Caraquatchi",
        "Caraguata\u00ed",
        "Caraguate\u00ed"
    ],
    "wof:name":"Caraguatei",
    "wof:placetype":"locality"
},
  "geometry": {"coordinates":[-55.23333,-23.56667],"type":"Point"}
}