{
  "type": "Feature",
  "properties": {
    "gn:admin1_code":"18.0",
    "gn:admin2_code":"4109708.0",
    "gn:asciiname":"Sitio Nicolau G. Lopes",
    "gn:country_code":"BR",
    "gn:dem":772,
    "gn:feature_class":"P",
    "gn:feature_code":"PPL",
    "gn:name":"S\u00edtio Nicolau G. Lopes",
    "gn:population":0,
    "gn:timezone":"America/Sao_Paulo",
    "iso:country":"BR",
    "name:por_x_preferred":[
        "S\u00edtio Nicolau G. Lopes"
    ],
    "wof:name":"Sitio Nicolau G. Lopes",
    "wof:placetype":"locality"
},
  "geometry": {"coordinates":[-50.24652,-23.90094],"type":"Point"}
}