{
  "type": "Feature",
  "properties": {
    "gn:admin1_code":"03",
    "gn:admin2_code":"1600279.0",
    "gn:asciiname":"Miguel Bento",
    "gn:country_code":"BR",
    "gn:dem":116,
    "gn:feature_class":"P",
    "gn:feature_code":"PPL",
    "gn:name":"Miguel Bento",
    "gn:population":0,
    "gn:timezone":"America/Belem",
    "iso:country":"BR",
    "wof:name":"Miguel Bento",
    "wof:placetype":"locality"
},
  "geometry": {"coordinates":[-52.51667,-0.53333],"type":"Point"}
}