{
  "type": "Feature",
  "properties": {
    "gn:admin1_code":"13",
    "gn:admin2_code":"2102200.0",
    "gn:asciiname":"Todos os Santos",
    "gn:country_code":"BR",
    "gn:dem":94,
    "gn:feature_class":"P",
    "gn:feature_code":"PPL",
    "gn:name":"Todos os Santos",
    "gn:population":0,
    "gn:timezone":"America/Fortaleza",
    "iso:country":"BR",
    "wof:name":"Todos os Santos",
    "wof:placetype":"locality"
},
  "geometry": {"coordinates":[-42.97833,-3.81861],"type":"Point"}
}