{
  "type": "Feature",
  "properties": {
    "gn:admin1_code":"06",
    "gn:admin2_code":"2304905.0",
    "gn:asciiname":"Veados",
    "gn:country_code":"BR",
    "gn:dem":101,
    "gn:feature_class":"P",
    "gn:feature_code":"PPL",
    "gn:name":"Veados",
    "gn:population":0,
    "gn:timezone":"America/Fortaleza",
    "iso:country":"BR",
    "wof:name":"Veados",
    "wof:placetype":"locality"
},
  "geometry": {"coordinates":[-40.38333,-3.86667],"type":"Point"}
}