{
  "type": "Feature",
  "properties": {
    "gn:admin1_code":"30",
    "gn:admin2_code":"2602100.0",
    "gn:asciiname":"Lagoa do Jacu",
    "gn:country_code":"BR",
    "gn:dem":633,
    "gn:feature_class":"P",
    "gn:feature_code":"PPL",
    "gn:name":"Lagoa do Jacu",
    "gn:population":0,
    "gn:timezone":"America/Recife",
    "iso:country":"BR",
    "wof:name":"Lagoa do Jacu",
    "wof:placetype":"locality"
},
  "geometry": {"coordinates":[-36.68333,-9.15],"type":"Point"}
}