{
  "type": "Feature",
  "properties": {
    "gn:admin1_code":"31",
    "gn:admin2_code":"1702109.0",
    "gn:asciiname":"Pedra Santa",
    "gn:country_code":"BR",
    "gn:dem":432,
    "gn:feature_class":"P",
    "gn:feature_code":"PPL",
    "gn:name":"Pedra Santa",
    "gn:population":0,
    "gn:timezone":"America/Araguaina",
    "iso:country":"BR",
    "wof:name":"Pedra Santa",
    "wof:placetype":"locality"
},
  "geometry": {"coordinates":[-48.46667,-7.23333],"type":"Point"}
}