{
  "type": "Feature",
  "properties": {
    "gn:admin1_code":"15",
    "gn:admin2_code":"3136108.0",
    "gn:asciiname":"Araras",
    "gn:cc2":"BR",
    "gn:country_code":"BR",
    "gn:dem":343,
    "gn:feature_class":"P",
    "gn:feature_code":"PPL",
    "gn:name":"Araras",
    "gn:population":0,
    "gn:timezone":"America/Sao_Paulo",
    "iso:country":"BR",
    "name:und_x_variant":[
        "Ponte das Araras",
        "Araras"
    ],
    "wof:name":"Araras",
    "wof:placetype":"locality"
},
  "geometry": {"coordinates":[-42.76667,-19.15],"type":"Point"}
}