{
  "type": "Feature",
  "properties": {
    "gn:admin1_code":"27",
    "gn:admin2_code":"3546801.0",
    "gn:asciiname":"Stio So Bernardino",
    "gn:country_code":"BR",
    "gn:dem":648,
    "gn:feature_class":"P",
    "gn:feature_code":"PPL",
    "gn:name":"Stio So Bernardino",
    "gn:population":0,
    "gn:timezone":"America/Sao_Paulo",
    "iso:country":"BR",
    "name:por_x_preferred":[
        "Stio So Bernardino"
    ],
    "wof:name":"Stio So Bernardino",
    "wof:placetype":"locality"
},
  "geometry": {"coordinates":[-46.2077,-23.3627],"type":"Point"}
}