{
  "type": "Feature",
  "properties": {
    "gn:admin1_code":"22",
    "gn:admin2_code":"2413904.0",
    "gn:asciiname":"Mariseira",
    "gn:country_code":"BR",
    "gn:dem":102,
    "gn:feature_class":"P",
    "gn:feature_code":"PPL",
    "gn:name":"Mariseira",
    "gn:population":0,
    "gn:timezone":"America/Fortaleza",
    "iso:country":"BR",
    "wof:name":"Mariseira",
    "wof:placetype":"locality"
},
  "geometry": {"coordinates":[-35.55,-5.66667],"type":"Point"}
}