{
  "type": "Feature",
  "properties": {
    "gn:admin1_code":"06",
    "gn:admin2_code":"2308302.0",
    "gn:asciiname":"Manoel Mororo",
    "gn:country_code":"BR",
    "gn:dem":344,
    "gn:feature_class":"P",
    "gn:feature_code":"PPL",
    "gn:name":"Manoel Moror\u00f3",
    "gn:population":0,
    "gn:timezone":"America/Fortaleza",
    "iso:country":"BR",
    "wof:name":"Manoel Mororo",
    "wof:placetype":"locality"
},
  "geometry": {"coordinates":[-38.93333,-7.35],"type":"Point"}
}