{
  "type": "Feature",
  "properties": {
    "gn:admin1_code":"18.0",
    "gn:admin2_code":"4123204.0",
    "gn:asciiname":"Sitio Clovis Santos",
    "gn:country_code":"BR",
    "gn:dem":667,
    "gn:feature_class":"P",
    "gn:feature_code":"PPL",
    "gn:name":"S\u00edtio Cl\u00f3vis Santos",
    "gn:population":0,
    "gn:timezone":"America/Sao_Paulo",
    "iso:country":"BR",
    "name:por_x_preferred":[
        "S\u00edtio Cl\u00f3vis Santos"
    ],
    "wof:name":"Sitio Clovis Santos",
    "wof:placetype":"locality"
},
  "geometry": {"coordinates":[-50.74349,-23.53675],"type":"Point"}
}