{
  "type": "Feature",
  "properties": {
    "gn:admin1_code":"22",
    "gn:admin2_code":"2412500.0",
    "gn:asciiname":"Sao Severino",
    "gn:country_code":"BR",
    "gn:dem":700,
    "gn:feature_class":"P",
    "gn:feature_code":"PPL",
    "gn:name":"S\u00e3o Severino",
    "gn:population":0,
    "gn:timezone":"America/Fortaleza",
    "iso:country":"BR",
    "wof:name":"Sao Severino",
    "wof:placetype":"locality"
},
  "geometry": {"coordinates":[-38.46667,-6.15],"type":"Point"}
}