{
  "type": "Feature",
  "properties": {
    "gn:admin1_code":"27.0",
    "gn:admin2_code":"3516309.0",
    "gn:asciiname":"Bairro Jardim Nossa Senhora Aparecida",
    "gn:country_code":"BR",
    "gn:dem":889,
    "gn:feature_class":"P",
    "gn:feature_code":"PPL",
    "gn:name":"Bairro Jardim Nossa Senhora Aparecida",
    "gn:population":0,
    "gn:timezone":"America/Sao_Paulo",
    "iso:country":"BR",
    "name:por_x_preferred":[
        "Bairro Jardim Nossa Senhora Aparecida"
    ],
    "wof:name":"Bairro Jardim Nossa Senhora Aparecida",
    "wof:placetype":"locality"
},
  "geometry": {"coordinates":[-46.7371,-23.25951],"type":"Point"}
}