{
  "type": "Feature",
  "properties": {
    "gn:admin1_code":"4",
    "gn:admin2_code":"1303809.0",
    "gn:asciiname":"Parnaiuicava",
    "gn:country_code":"BR",
    "gn:dem":142,
    "gn:feature_class":"P",
    "gn:feature_code":"PPL",
    "gn:name":"Parnaiuicava",
    "gn:population":0,
    "gn:timezone":"America/Manaus",
    "iso:country":"BR",
    "wof:name":"Parnaiuicava",
    "wof:placetype":"locality"
},
  "geometry": {"coordinates":[-69.08333,0.35],"type":"Point"}
}