{
  "type": "Feature",
  "properties": {
    "gn:admin1_code":"5",
    "gn:admin2_code":"2930907.0",
    "gn:asciiname":"Olho d'Agua da Mariquinha",
    "gn:country_code":"BR",
    "gn:dem":744,
    "gn:feature_class":"P",
    "gn:feature_code":"PPL",
    "gn:name":"\u00d4lho d\u2019\u00c1gua da Mariquinha",
    "gn:population":0,
    "gn:timezone":"America/Bahia",
    "iso:country":"BR",
    "wof:name":"Olho d'Agua da Mariquinha",
    "wof:placetype":"locality"
},
  "geometry": {"coordinates":[-44.25,-12.43333],"type":"Point"}
}