{
  "type": "Feature",
  "properties": {
    "gn:admin1_code":"18.0",
    "gn:admin2_code":"4121802.0",
    "gn:asciiname":"Sitio Sebastiao Pereira",
    "gn:country_code":"BR",
    "gn:dem":581,
    "gn:feature_class":"P",
    "gn:feature_code":"PPL",
    "gn:name":"S\u00edtio Sebasti\u00e3o Pereira",
    "gn:population":0,
    "gn:timezone":"America/Sao_Paulo",
    "iso:country":"BR",
    "name:por_x_preferred":[
        "S\u00edtio Sebasti\u00e3o Pereira"
    ],
    "wof:name":"Sitio Sebastiao Pereira",
    "wof:placetype":"locality"
},
  "geometry": {"coordinates":[-49.82341,-23.35981],"type":"Point"}
}