{
  "type": "Feature",
  "properties": {
    "gn:admin1_code":"06",
    "gn:admin2_code":"2311306.0",
    "gn:asciiname":"Fazenda Espirito Santo",
    "gn:country_code":"BR",
    "gn:dem":208,
    "gn:feature_class":"P",
    "gn:feature_code":"PPL",
    "gn:name":"Fazenda Esp\u00edrito Santo",
    "gn:population":0,
    "gn:timezone":"America/Fortaleza",
    "iso:country":"BR",
    "wof:name":"Fazenda Espirito Santo",
    "wof:placetype":"locality"
},
  "geometry": {"coordinates":[-39.05,-4.93333],"type":"Point"}
}