{
  "type": "Feature",
  "properties": {
    "gn:admin1_code":"17",
    "gn:admin2_code":"2500205.0",
    "gn:asciiname":"Vassoura",
    "gn:country_code":"BR",
    "gn:dem":342,
    "gn:feature_class":"P",
    "gn:feature_code":"PPL",
    "gn:name":"Vassoura",
    "gn:population":0,
    "gn:timezone":"America/Fortaleza",
    "iso:country":"BR",
    "wof:name":"Vassoura",
    "wof:placetype":"locality"
},
  "geometry": {"coordinates":[-38.21667,-7.06667],"type":"Point"}
}