{
  "type": "Feature",
  "properties": {
    "gn:admin1_code":"18.0",
    "gn:admin2_code":"4112306.0",
    "gn:asciiname":"Sitio Joao Rocha de Araujo",
    "gn:country_code":"BR",
    "gn:dem":551,
    "gn:feature_class":"P",
    "gn:feature_code":"PPL",
    "gn:name":"S\u00edtio Jo\u00e3o Rocha de Ara\u00fajo",
    "gn:population":0,
    "gn:timezone":"America/Sao_Paulo",
    "iso:country":"BR",
    "name:por_x_preferred":[
        "S\u00edtio Jo\u00e3o Rocha de Ara\u00fajo"
    ],
    "wof:name":"Sitio Joao Rocha de Araujo",
    "wof:placetype":"locality"
},
  "geometry": {"coordinates":[-50.21444,-23.63209],"type":"Point"}
}