{
  "type": "Feature",
  "properties": {
    "gn:admin1_code":"17",
    "gn:admin2_code":"2510659.0",
    "gn:asciiname":"Riacho de Fora",
    "gn:country_code":"BR",
    "gn:dem":508,
    "gn:feature_class":"P",
    "gn:feature_code":"PPL",
    "gn:name":"Riacho de Fora",
    "gn:population":0,
    "gn:timezone":"America/Fortaleza",
    "iso:country":"BR",
    "wof:name":"Riacho de Fora",
    "wof:placetype":"locality"
},
  "geometry": {"coordinates":[-36.73333,-7.33333],"type":"Point"}
}