{
  "type": "Feature",
  "properties": {
    "gn:admin1_code":"20",
    "gn:admin2_code":"2207801.0",
    "gn:asciiname":"Alto Novo (2)",
    "gn:country_code":"BR",
    "gn:dem":365,
    "gn:feature_class":"P",
    "gn:feature_code":"PPL",
    "gn:name":"Alto N\u00f4vo (2)",
    "gn:population":0,
    "gn:timezone":"America/Fortaleza",
    "iso:country":"BR",
    "wof:name":"Alto Novo (2)",
    "wof:placetype":"locality"
},
  "geometry": {"coordinates":[-41.01667,-7.93333],"type":"Point"}
}