{
  "type": "Feature",
  "properties": {
    "gn:admin1_code":"11",
    "gn:admin2_code":"5002308.0",
    "gn:asciiname":"Mimoso",
    "gn:cc2":"BR",
    "gn:country_code":"BR",
    "gn:dem":458,
    "gn:feature_class":"P",
    "gn:feature_code":"PPL",
    "gn:name":"Mimoso",
    "gn:population":0,
    "gn:timezone":"America/Campo_Grande",
    "iso:country":"BR",
    "name:por_x_preferred":[
        "Mimoso"
    ],
    "name:und_x_variant":[
        "Fazenda Mimoso"
    ],
    "wof:name":"Mimoso",
    "wof:placetype":"locality"
},
  "geometry": {"coordinates":[-52.88333000000001,-20.93333],"type":"Point"}
}