{
  "type": "Feature",
  "properties": {
    "gn:admin1_code":"11",
    "gn:admin2_code":"5003157.0",
    "gn:asciiname":"Curralinho",
    "gn:cc2":"BR",
    "gn:country_code":"BR",
    "gn:dem":517,
    "gn:feature_class":"P",
    "gn:feature_code":"PPL",
    "gn:name":"Curralinho",
    "gn:population":0,
    "gn:timezone":"America/Campo_Grande",
    "iso:country":"BR",
    "name:und_x_variant":[
        "Curralito",
        "Curralinho"
    ],
    "wof:name":"Curralinho",
    "wof:placetype":"locality"
},
  "geometry": {"coordinates":[-55.38333000000001,-23.18333],"type":"Point"}
}