{
  "type": "Feature",
  "properties": {
    "gn:admin1_code":"06",
    "gn:admin2_code":"2311801.0",
    "gn:asciiname":"Fazenda Acude das Melancias",
    "gn:country_code":"BR",
    "gn:dem":62,
    "gn:feature_class":"P",
    "gn:feature_code":"PPL",
    "gn:name":"Fazenda A\u00e7ude das Melancias",
    "gn:population":0,
    "gn:timezone":"America/Fortaleza",
    "iso:country":"BR",
    "wof:name":"Fazenda Acude das Melancias",
    "wof:placetype":"locality"
},
  "geometry": {"coordinates":[-38.28333,-4.75],"type":"Point"}
}