{
  "type": "Feature",
  "properties": {
    "gn:admin1_code":"18.0",
    "gn:admin2_code":"4126207.0",
    "gn:asciiname":"Sitio Sao Estevao",
    "gn:country_code":"BR",
    "gn:dem":741,
    "gn:feature_class":"P",
    "gn:feature_code":"PPL",
    "gn:name":"S\u00edtio S\u00e3o Est\u00eav\u00e3o",
    "gn:population":0,
    "gn:timezone":"America/Sao_Paulo",
    "iso:country":"BR",
    "name:por_x_preferred":[
        "S\u00edtio S\u00e3o Est\u00eav\u00e3o"
    ],
    "wof:name":"Sitio Sao Estevao",
    "wof:placetype":"locality"
},
  "geometry": {"coordinates":[-50.54932,-23.91215],"type":"Point"}
}