{
  "type": "Feature",
  "properties": {
    "gn:admin1_code":"20.0",
    "gn:admin2_code":"2203230.0",
    "gn:asciiname":"Fazenda Larga",
    "gn:country_code":"BR",
    "gn:dem":357,
    "gn:feature_class":"P",
    "gn:feature_code":"PPL",
    "gn:name":"Fazenda Larga",
    "gn:population":0,
    "gn:timezone":"America/Fortaleza",
    "iso:country":"BR",
    "name:por_x_preferred":[
        "Fazenda Larga"
    ],
    "wof:name":"Fazenda Larga",
    "wof:placetype":"locality"
},
  "geometry": {"coordinates":[-44.83731,-8.84566],"type":"Point"}
}