{
  "type": "Feature",
  "properties": {
    "gn:admin1_code":"16",
    "gn:admin2_code":"1500602.0",
    "gn:asciiname":"Sao Francisco Novo",
    "gn:cc2":"BR",
    "gn:country_code":"BR",
    "gn:dem":267,
    "gn:feature_class":"P",
    "gn:feature_code":"PPL",
    "gn:name":"S\u00e3o Francisco Novo",
    "gn:population":0,
    "gn:timezone":"America/Santarem",
    "iso:country":"BR",
    "name:und_x_variant":[
        "S\u00e3o Francisco",
        "S\u00e3o Francisco Novo"
    ],
    "wof:name":"Sao Francisco Novo",
    "wof:placetype":"locality"
},
  "geometry": {"coordinates":[-54.46666999999999,-4.81667],"type":"Point"}
}