{
  "type": "Feature",
  "properties": {
    "gn:admin1_code":"18",
    "gn:admin2_code":"4104105.0",
    "gn:asciiname":"Sitio Andre Lopata",
    "gn:country_code":"BR",
    "gn:dem":851,
    "gn:feature_class":"P",
    "gn:feature_code":"PPL",
    "gn:name":"S\u00edtio Andr\u00e9 Lopata",
    "gn:population":0,
    "gn:timezone":"America/Sao_Paulo",
    "iso:country":"BR",
    "name:por_x_preferred":[
        "S\u00edtio Andr\u00e9 Lopata"
    ],
    "wof:name":"Sitio Andre Lopata",
    "wof:placetype":"locality"
},
  "geometry": {"coordinates":[-49.72748,-26.01057],"type":"Point"}
}