{
  "type": "Feature",
  "properties": {
    "gn:admin1_code":"18.0",
    "gn:admin2_code":"4127809.0",
    "gn:asciiname":"Sitio Ovidio G. Menino",
    "gn:country_code":"BR",
    "gn:dem":771,
    "gn:feature_class":"P",
    "gn:feature_code":"PPL",
    "gn:name":"S\u00edtio Ov\u00eddio G. Menino",
    "gn:population":0,
    "gn:timezone":"America/Sao_Paulo",
    "iso:country":"BR",
    "name:por_x_preferred":[
        "S\u00edtio Ov\u00eddio G. Menino"
    ],
    "wof:name":"Sitio Ovidio G. Menino",
    "wof:placetype":"locality"
},
  "geometry": {"coordinates":[-49.8918,-23.6295],"type":"Point"}
}