{
  "type": "Feature",
  "properties": {
    "gn:admin1_code":"23",
    "gn:admin2_code":"4313037.0",
    "gn:asciiname":"Nova Esperanca",
    "gn:cc2":"BR",
    "gn:country_code":"BR",
    "gn:dem":339,
    "gn:feature_class":"P",
    "gn:feature_code":"PPL",
    "gn:name":"Nova Esperan\u00e7a",
    "gn:population":0,
    "gn:timezone":"America/Sao_Paulo",
    "iso:country":"BR",
    "name:und_x_variant":[
        "Esperan\u00e7a",
        "Nova Esperan\u00e7a"
    ],
    "wof:name":"Nova Esperanca",
    "wof:placetype":"locality"
},
  "geometry": {"coordinates":[-54.83333,-29.41667],"type":"Point"}
}