{
  "type": "Feature",
  "properties": {
    "gn:admin1_code":"18",
    "gn:admin2_code":"4101804.0",
    "gn:asciiname":"Guajuvira de Cima",
    "gn:country_code":"BR",
    "gn:dem":885,
    "gn:feature_class":"P",
    "gn:feature_code":"PPL",
    "gn:name":"Guajuvira de Cima",
    "gn:population":0,
    "gn:timezone":"America/Sao_Paulo",
    "iso:country":"BR",
    "wof:name":"Guajuvira de Cima",
    "wof:placetype":"locality"
},
  "geometry": {"coordinates":[-49.46667,-25.63333],"type":"Point"}
}