{
  "type": "Feature",
  "properties": {
    "gn:admin1_code":"23",
    "gn:admin2_code":"4308201.0",
    "gn:asciiname":"Travessa Jacinto",
    "gn:country_code":"BR",
    "gn:dem":776,
    "gn:feature_class":"P",
    "gn:feature_code":"PPL",
    "gn:name":"Travessa Jacinto",
    "gn:population":0,
    "gn:timezone":"America/Sao_Paulo",
    "iso:country":"BR",
    "name:por_x_preferred":[
        "Travessa Jacinto"
    ],
    "wof:name":"Travessa Jacinto",
    "wof:placetype":"locality"
},
  "geometry": {"coordinates":[-51.2364,-29.0772],"type":"Point"}
}