{
  "type": "Feature",
  "properties": {
    "gn:admin1_code":"1",
    "gn:admin2_code":"1200500.0",
    "gn:asciiname":"Colocacao Poti",
    "gn:country_code":"BR",
    "gn:dem":257,
    "gn:feature_class":"P",
    "gn:feature_code":"PPL",
    "gn:name":"Coloca\u00e7\u00e3o Poti",
    "gn:population":0,
    "gn:timezone":"America/Rio_Branco",
    "iso:country":"BR",
    "name:por_x_preferred":[
        "Poti"
    ],
    "name:und_x_variant":[
        "Coloca\u00e7\u00e3o Poti"
    ],
    "wof:name":"Colocacao Poti",
    "wof:placetype":"locality"
},
  "geometry": {"coordinates":[-69.36667,-10.41667],"type":"Point"}
}