{
  "type": "Feature",
  "properties": {
    "gn:admin1_code":"05",
    "gn:admin2_code":"2919900.0",
    "gn:asciiname":"Mandacaru",
    "gn:country_code":"BR",
    "gn:dem":379,
    "gn:feature_class":"P",
    "gn:feature_code":"PPL",
    "gn:name":"Mandacaru",
    "gn:population":0,
    "gn:timezone":"America/Bahia",
    "iso:country":"BR",
    "wof:name":"Mandacaru",
    "wof:placetype":"locality"
},
  "geometry": {"coordinates":[-38.98333,-9.38333],"type":"Point"}
}