{
  "type": "Feature",
  "properties": {
    "gn:admin1_code":"03",
    "gn:admin2_code":"1600279.0",
    "gn:asciiname":"Porto Poet",
    "gn:country_code":"BR",
    "gn:dem":241,
    "gn:feature_class":"P",
    "gn:feature_code":"PPL",
    "gn:name":"P\u00f4rto Poet",
    "gn:population":0,
    "gn:timezone":"America/Belem",
    "iso:country":"BR",
    "wof:name":"Porto Poet",
    "wof:placetype":"locality"
},
  "geometry": {"coordinates":[-54.65,1.78333],"type":"Point"}
}