{
  "type": "Feature",
  "properties": {
    "gn:admin1_code":"18.0",
    "gn:admin2_code":"4124301.0",
    "gn:asciiname":"Sitio Zuza",
    "gn:country_code":"BR",
    "gn:dem":774,
    "gn:feature_class":"P",
    "gn:feature_code":"PPL",
    "gn:name":"S\u00edtio Zuza",
    "gn:population":0,
    "gn:timezone":"America/Sao_Paulo",
    "iso:country":"BR",
    "name:por_x_preferred":[
        "S\u00edtio Zuza"
    ],
    "wof:name":"Sitio Zuza",
    "wof:placetype":"locality"
},
  "geometry": {"coordinates":[-50.64605,-23.59657],"type":"Point"}
}