{
  "type": "Feature",
  "properties": {
    "gn:admin1_code":"16",
    "gn:admin2_code":"1508357.0",
    "gn:asciiname":"Favania",
    "gn:country_code":"BR",
    "gn:dem":9,
    "gn:feature_class":"P",
    "gn:feature_code":"PPL",
    "gn:name":"Fav\u00e2nia",
    "gn:population":0,
    "gn:timezone":"America/Santarem",
    "iso:country":"BR",
    "wof:name":"Favania",
    "wof:placetype":"locality"
},
  "geometry": {"coordinates":[-51.79533,-3.11533],"type":"Point"}
}