{
  "type": "Feature",
  "properties": {
    "gn:admin1_code":"18.0",
    "gn:admin2_code":"4114302.0",
    "gn:asciiname":"Sitio Ladislau Escrab",
    "gn:country_code":"BR",
    "gn:dem":880,
    "gn:feature_class":"P",
    "gn:feature_code":"PPL",
    "gn:name":"S\u00edtio Ladislau Escrab",
    "gn:population":0,
    "gn:timezone":"America/Sao_Paulo",
    "iso:country":"BR",
    "name:por_x_preferred":[
        "S\u00edtio Ladislau Escrab"
    ],
    "wof:name":"Sitio Ladislau Escrab",
    "wof:placetype":"locality"
},
  "geometry": {"coordinates":[-49.368,-25.8865],"type":"Point"}
}