{
  "type": "Feature",
  "properties": {
    "gn:admin1_code":"5",
    "gn:admin2_code":"2905305.0",
    "gn:asciiname":"Canais",
    "gn:country_code":"BR",
    "gn:dem":796,
    "gn:feature_class":"P",
    "gn:feature_code":"PPL",
    "gn:name":"Canais",
    "gn:population":0,
    "gn:timezone":"America/Bahia",
    "iso:country":"BR",
    "wof:name":"Canais",
    "wof:placetype":"locality"
},
  "geometry": {"coordinates":[-41.58333,-11.83333],"type":"Point"}
}