{
  "type": "Feature",
  "properties": {
    "gn:country":"BR",
    "gn:fcode":"PPL",
    "gn:population":0,
    "iso:country":"BR",
    "qs_pg:aaroncc":"BR",
    "qs_pg:gn_country":"BR",
    "qs_pg:gn_fcode":"PPL",
    "qs_pg:gn_pop":0,
    "qs_pg:name":"Santinho",
    "qs_pg:name_adm0":"Brasil",
    "qs_pg:name_adm1":"Santa Catarina",
    "qs_pg:photos":753,
    "qs_pg:photos_1k":153,
    "qs_pg:photos_9k":3,
    "qs_pg:photos_9r":6,
    "qs_pg:photos_all":753,
    "qs_pg:photos_sr":9,
    "qs_pg:pop_sr":0,
    "qs_pg:qs_pg_placetype":"locality",
    "qs_pg:qs_pg_placetype_gp":"Town",
    "qs_pg:woe_adm0":23424768,
    "woe:adm0_id":23424768,
    "woe:name_adm0":"Brasil",
    "woe:name_adm1":"Santa Catarina",
    "woe:placetype":"Town",
    "wof:name":"Santinho",
    "wof:placetype":"locality"
},
  "geometry": {"coordinates":[-48.3801,-27.45558],"type":"Point"}
}