{
  "type": "Feature",
  "properties": {
    "gn:admin1_code":"15",
    "gn:admin2_code":"3155702.0",
    "gn:asciiname":"Bicas",
    "gn:country_code":"BR",
    "gn:dem":646,
    "gn:feature_class":"P",
    "gn:feature_code":"PPL",
    "gn:name":"Bicas",
    "gn:population":0,
    "gn:timezone":"America/Sao_Paulo",
    "iso:country":"BR",
    "name:por_x_preferred":[
        "Bicas"
    ],
    "wof:name":"Bicas",
    "wof:placetype":"locality"
},
  "geometry": {"coordinates":[-43.16667,-19.95],"type":"Point"}
}