{
  "type": "Feature",
  "properties": {
    "gn:admin1_code":"15",
    "gn:admin2_code":"3155702.0",
    "gn:asciiname":"Bicas",
    "gn:country_code":"BR",
    "gn:dem":646,
    "gn:feature_class":"P",
    "gn:feature_code":"PPL",
    "gn:name":"Bicas",
    "gn:population":0,
    "gn:timezone":"America/Sao_Paulo",
    "iso:country":"BR",
    "name:bpy_x_preferred":[
        "\u09ac\u09bf\u0995\u09be\u09b8"
    ],
    "name:ceb_x_preferred":[
        "Bicas"
    ],
    "name:epo_x_preferred":[
        "Bicas"
    ],
    "name:eus_x_preferred":[
        "Bicas"
    ],
    "name:fra_x_preferred":[
        "Bicas"
    ],
    "name:hye_x_preferred":[
        "\u0532\u056b\u056f\u0561\u057d"
    ],
    "name:ita_x_preferred":[
        "Bicas"
    ],
    "name:kat_x_preferred":[
        "\u10d1\u10d8\u10d9\u10d0\u10e1\u10d8"
    ],
    "name:kaz_x_preferred":[
        "\u0411\u0438\u043a\u0430\u0441"
    ],
    "name:mlg_x_preferred":[
        "Bicas"
    ],
    "name:nld_x_preferred":[
        "Bicas"
    ],
    "name:nor_x_preferred":[
        "Bicas"
    ],
    "name:pol_x_preferred":[
        "Bicas"
    ],
    "name:por_x_preferred":[
        "Bicas"
    ],
    "name:ron_x_preferred":[
        "Bicas"
    ],
    "name:rus_x_preferred":[
        "\u0411\u0438\u043a\u0430\u0441"
    ],
    "name:swe_x_preferred":[
        "Bicas"
    ],
    "name:vie_x_preferred":[
        "Bicas"
    ],
    "name:vol_x_preferred":[
        "Bicas"
    ],
    "name:war_x_preferred":[
        "Bicas"
    ],
    "name:zho_x_preferred":[
        "\u6bd4\u5361\u65af"
    ],
    "wof:name":"Bicas",
    "wof:placetype":"locality"
},
  "geometry": {"coordinates":[-43.16667,-19.95],"type":"Point"}
}