{
  "type": "Feature",
  "properties": {
    "gn:admin1_code":"5",
    "gn:admin2_code":"2923407.0",
    "gn:asciiname":"Golfos",
    "gn:country_code":"BR",
    "gn:dem":463,
    "gn:feature_class":"P",
    "gn:feature_code":"PPL",
    "gn:name":"Golfos",
    "gn:population":0,
    "gn:timezone":"America/Bahia",
    "iso:country":"BR",
    "wof:name":"Golfos",
    "wof:placetype":"locality"
},
  "geometry": {"coordinates":[-43.43333,-14.13333],"type":"Point"}
}