{
  "type": "Feature",
  "properties": {
    "gn:admin1_code":"18.0",
    "gn:admin2_code":"4104006.0",
    "gn:asciiname":"Posto Marcajo Blanquina",
    "gn:country_code":"BR",
    "gn:dem":643,
    "gn:feature_class":"P",
    "gn:feature_code":"PPL",
    "gn:name":"Posto Marcajo Blanquina",
    "gn:population":0,
    "gn:timezone":"America/Sao_Paulo",
    "iso:country":"BR",
    "wof:name":"Posto Marcajo Blanquina",
    "wof:placetype":"locality"
},
  "geometry": {"coordinates":[-48.59832,-25.08758],"type":"Point"}
}