{
  "type": "Feature",
  "properties": {
    "gn:admin1_code":"13",
    "gn:admin2_code":"2103208.0",
    "gn:asciiname":"Pitombeira de Baixo",
    "gn:country_code":"BR",
    "gn:dem":74,
    "gn:feature_class":"P",
    "gn:feature_code":"PPL",
    "gn:name":"Pitombeira de Baixo",
    "gn:population":0,
    "gn:timezone":"America/Fortaleza",
    "iso:country":"BR",
    "wof:name":"Pitombeira de Baixo",
    "wof:placetype":"locality"
},
  "geometry": {"coordinates":[-43.36639,-3.63889],"type":"Point"}
}