{
  "type": "Feature",
  "properties": {
    "gn:admin1_code":"18.0",
    "gn:admin2_code":"4114302.0",
    "gn:asciiname":"Sitio Estefanio",
    "gn:country_code":"BR",
    "gn:dem":905,
    "gn:feature_class":"P",
    "gn:feature_code":"PPL",
    "gn:name":"S\u00edtio Estef\u00e2nio",
    "gn:population":0,
    "gn:timezone":"America/Sao_Paulo",
    "iso:country":"BR",
    "name:por_x_preferred":[
        "S\u00edtio Estef\u00e2nio"
    ],
    "wof:name":"Sitio Estefanio",
    "wof:placetype":"locality"
},
  "geometry": {"coordinates":[-49.3197,-25.8933],"type":"Point"}
}