{
  "type": "Feature",
  "properties": {
    "gn:admin1_code":"27.0",
    "gn:admin2_code":"3505401.0",
    "gn:asciiname":"Bairro Areia Branca",
    "gn:country_code":"BR",
    "gn:dem":267,
    "gn:feature_class":"P",
    "gn:feature_code":"PPLL",
    "gn:name":"Bairro Areia Branca",
    "gn:population":0,
    "gn:timezone":"America/Sao_Paulo",
    "iso:country":"BR",
    "name:por_x_preferred":[
        "Bairro Areia Branca"
    ],
    "wof:name":"Bairro Areia Branca",
    "wof:placetype":"locality"
},
  "geometry": {"coordinates":[-48.56609,-24.97189],"type":"Point"}
}