{
  "type": "Feature",
  "properties": {
    "gn:admin1_code":"18.0",
    "gn:admin2_code":"4106209.0",
    "gn:asciiname":"Sitio Casemiro Knaut",
    "gn:country_code":"BR",
    "gn:dem":856,
    "gn:feature_class":"P",
    "gn:feature_code":"PPL",
    "gn:name":"S\u00edtio Casemiro Knaut",
    "gn:population":0,
    "gn:timezone":"America/Sao_Paulo",
    "iso:country":"BR",
    "name:por_x_preferred":[
        "S\u00edtio Casemiro Knaut"
    ],
    "wof:name":"Sitio Casemiro Knaut",
    "wof:placetype":"locality"
},
  "geometry": {"coordinates":[-49.4502,-25.7911],"type":"Point"}
}