{
  "type": "Feature",
  "properties": {
    "gn:admin1_code":"18.0",
    "gn:admin2_code":"4126678.0",
    "gn:asciiname":"Sitio Joao Pereira de Moraes",
    "gn:country_code":"BR",
    "gn:dem":706,
    "gn:feature_class":"P",
    "gn:feature_code":"PPL",
    "gn:name":"S\u00edtio Jo\u00e3o Pereira de Moraes",
    "gn:population":0,
    "gn:timezone":"America/Sao_Paulo",
    "iso:country":"BR",
    "name:por_x_preferred":[
        "S\u00edtio Jo\u00e3o Pereira de Moraes"
    ],
    "wof:name":"Sitio Joao Pereira de Moraes",
    "wof:placetype":"locality"
},
  "geometry": {"coordinates":[-50.9732,-23.8791],"type":"Point"}
}