{
  "type": "Feature",
  "properties": {
    "gn:country":"BR",
    "gn:fcode":"PPL",
    "gn:population":0,
    "iso:country":"BR",
    "name:por_x_preferred":[
        "Barro Branco"
    ],
    "qs_pg:aaroncc":"BR",
    "qs_pg:gn_country":"BR",
    "qs_pg:gn_fcode":"PPL",
    "qs_pg:gn_pop":0,
    "qs_pg:name":"Barro Branco",
    "qs_pg:name_adm0":"Brasil",
    "qs_pg:name_adm1":"Esp\u00edrito Santo",
    "qs_pg:photos":1,
    "qs_pg:photos_1k":1,
    "qs_pg:photos_9k":1,
    "qs_pg:photos_9r":1,
    "qs_pg:photos_all":1,
    "qs_pg:photos_sr":1,
    "qs_pg:pop_sr":0,
    "qs_pg:qs_pg_placetype":"neighbourhood",
    "qs_pg:qs_pg_placetype_gp":"Suburb",
    "qs_pg:woe_adm0":23424768,
    "woe:adm0_id":23424768,
    "woe:name_adm0":"Brasil",
    "woe:name_adm1":"Esp\u00edrito Santo",
    "woe:placetype":"Suburb",
    "wof:name":"Barro Branco",
    "wof:placetype":"neighbourhood"
},
  "geometry": {"coordinates":[-40.48333,-20.55],"type":"Point"}
}