{
  "type": "Feature",
  "properties": {
    "gn:admin1_code":"03",
    "gn:admin2_code":"1600105.0",
    "gn:asciiname":"Carmo",
    "gn:country_code":"BR",
    "gn:dem":6,
    "gn:feature_class":"P",
    "gn:feature_code":"PPL",
    "gn:name":"Carmo",
    "gn:population":0,
    "gn:timezone":"America/Belem",
    "iso:country":"BR",
    "wof:name":"Carmo",
    "wof:placetype":"locality"
},
  "geometry": {"coordinates":[-50.76618,1.16419],"type":"Point"}
}