{
  "type": "Feature",
  "properties": {
    "gn:admin1_code":"5",
    "gn:admin2_code":"2922755.0",
    "gn:asciiname":"Pedra Branca",
    "gn:country_code":"BR",
    "gn:dem":232,
    "gn:feature_class":"P",
    "gn:feature_code":"PPL",
    "gn:name":"Pedra Branca",
    "gn:population":0,
    "gn:timezone":"America/Bahia",
    "iso:country":"BR",
    "wof:name":"Pedra Branca",
    "wof:placetype":"locality"
},
  "geometry": {"coordinates":[-39.58333,-13.83333],"type":"Point"}
}