{
  "type": "Feature",
  "properties": {
    "gn:admin1_code":"5",
    "gn:admin2_code":"2922755.0",
    "gn:asciiname":"Pedra Branca",
    "gn:country_code":"BR",
    "gn:dem":232,
    "gn:feature_class":"P",
    "gn:feature_code":"PPL",
    "gn:name":"Pedra Branca",
    "gn:population":0,
    "gn:timezone":"America/Bahia",
    "iso:country":"BR",
    "name:bpy_x_preferred":[
        "\u09aa\u09c7\u09a1\u09cd\u09b0\u09be \u09ac\u09cd\u09b0\u09be\u0999\u09cd\u0995\u09be"
    ],
    "name:ceb_x_preferred":[
        "Pedra Branca"
    ],
    "name:deu_x_preferred":[
        "Pedra Branca"
    ],
    "name:fra_x_preferred":[
        "Pedra Branca"
    ],
    "name:ita_x_preferred":[
        "Pedra Branca"
    ],
    "name:kor_x_preferred":[
        "\ud398\ub4dc\ub77c \ube0c\ub791\uce74"
    ],
    "name:msa_x_preferred":[
        "Pedra Branca"
    ],
    "name:nld_x_preferred":[
        "Pedra Branca"
    ],
    "name:nor_x_preferred":[
        "Pedra Branca"
    ],
    "name:por_x_preferred":[
        "Pedra Branca"
    ],
    "name:sin_x_preferred":[
        "\u0db4\u0dda\u0daf\u0dca\u200d\u0dbb\u0dcf \u0db6\u0dca\u200d\u0dbb\u0db1\u0dca\u0d9a\u0dcf"
    ],
    "name:swe_x_preferred":[
        "Pedra Branca"
    ],
    "name:vol_x_preferred":[
        "Pedra Branca"
    ],
    "wof:name":"Pedra Branca",
    "wof:placetype":"locality"
},
  "geometry": {"coordinates":[-39.58333,-13.83333],"type":"Point"}
}