{
  "type": "Feature",
  "properties": {
    "gn:admin1_code":"18.0",
    "gn:admin2_code":"4113205.0",
    "gn:asciiname":"Sitio Pedro A. Correa",
    "gn:country_code":"BR",
    "gn:dem":827,
    "gn:feature_class":"P",
    "gn:feature_code":"PPL",
    "gn:name":"S\u00edtio Pedro A. Corr\u00eaa",
    "gn:population":0,
    "gn:timezone":"America/Sao_Paulo",
    "iso:country":"BR",
    "name:por_x_preferred":[
        "S\u00edtio Pedro A. Corr\u00eaa"
    ],
    "wof:name":"Sitio Pedro A. Correa",
    "wof:placetype":"locality"
},
  "geometry": {"coordinates":[-49.622,-25.8202],"type":"Point"}
}