{
  "type": "Feature",
  "properties": {
    "gn:admin1_code":"24",
    "gn:admin2_code":"1100403.0",
    "gn:asciiname":"Monte Alegre",
    "gn:country_code":"BR",
    "gn:dem":110,
    "gn:feature_class":"P",
    "gn:feature_code":"PPL",
    "gn:name":"Monte Alegre",
    "gn:population":0,
    "gn:timezone":"America/Porto_Velho",
    "iso:country":"BR",
    "wof:name":"Monte Alegre",
    "wof:placetype":"locality"
},
  "geometry": {"coordinates":[-63.53333000000001,-9.53333],"type":"Point"}
}