{
  "type": "Feature",
  "properties": {
    "gn:admin1_code":"27.0",
    "gn:admin2_code":"3551108.0",
    "gn:asciiname":"Bateias",
    "gn:country_code":"BR",
    "gn:dem":665,
    "gn:feature_class":"P",
    "gn:feature_code":"PPLL",
    "gn:name":"Bateias",
    "gn:population":0,
    "gn:timezone":"America/Sao_Paulo",
    "iso:country":"BR",
    "name:por_x_preferred":[
        "Bateias"
    ],
    "wof:name":"Bateias",
    "wof:placetype":"locality"
},
  "geometry": {"coordinates":[-47.7711,-23.7035],"type":"Point"}
}