{
  "type": "Feature",
  "properties": {
    "gn:admin1_code":"18",
    "gn:admin2_code":"4119103.0",
    "gn:asciiname":"Sitio Jose V. Tschoki",
    "gn:country_code":"BR",
    "gn:dem":826,
    "gn:feature_class":"P",
    "gn:feature_code":"PPL",
    "gn:name":"S\u00edtio Jos\u00e9 V. Tschoki",
    "gn:population":0,
    "gn:timezone":"America/Sao_Paulo",
    "iso:country":"BR",
    "name:por_x_preferred":[
        "S\u00edtio Jos\u00e9 V. Tschoki"
    ],
    "wof:name":"Sitio Jose V. Tschoki",
    "wof:placetype":"locality"
},
  "geometry": {"coordinates":[-49.4451,-26.1267],"type":"Point"}
}