{
  "type": "Feature",
  "properties": {
    "gn:admin1_code":"18",
    "gn:admin2_code":"4113205.0",
    "gn:asciiname":"Sitio Euvira Linhares",
    "gn:country_code":"BR",
    "gn:dem":840,
    "gn:feature_class":"P",
    "gn:feature_code":"PPL",
    "gn:name":"S\u00edtio Euvira Linhares",
    "gn:population":0,
    "gn:timezone":"America/Sao_Paulo",
    "iso:country":"BR",
    "name:por_x_preferred":[
        "S\u00edtio Euvira Linhares"
    ],
    "wof:name":"Sitio Euvira Linhares",
    "wof:placetype":"locality"
},
  "geometry": {"coordinates":[-49.73056,-25.8375],"type":"Point"}
}