{
  "type": "Feature",
  "properties": {
    "gn:admin1_code":"18.0",
    "gn:admin2_code":"4113205.0",
    "gn:asciiname":"Sitio Jose Antonio Hammerschmidt",
    "gn:country_code":"BR",
    "gn:dem":792,
    "gn:feature_class":"P",
    "gn:feature_code":"PPL",
    "gn:name":"S\u00edtio Jos\u00e9 Ant\u00f4nio Hammerschmidt",
    "gn:population":0,
    "gn:timezone":"America/Sao_Paulo",
    "iso:country":"BR",
    "name:por_x_preferred":[
        "S\u00edtio Jos\u00e9 Ant\u00f4nio Hammerschmidt"
    ],
    "wof:name":"Sitio Jose Antonio Hammerschmidt",
    "wof:placetype":"locality"
},
  "geometry": {"coordinates":[-49.81805,-25.91967],"type":"Point"}
}