{
  "type": "Feature",
  "properties": {
    "gn:admin1_code":"18.0",
    "gn:admin2_code":"4111803.0",
    "gn:asciiname":"Sitio Sete Pinheiros",
    "gn:country_code":"BR",
    "gn:dem":440,
    "gn:feature_class":"P",
    "gn:feature_code":"PPL",
    "gn:name":"S\u00edtio Sete Pinheiros",
    "gn:population":0,
    "gn:timezone":"America/Sao_Paulo",
    "iso:country":"BR",
    "name:por_x_preferred":[
        "S\u00edtio Sete Pinheiros"
    ],
    "wof:name":"Sitio Sete Pinheiros",
    "wof:placetype":"locality"
},
  "geometry": {"coordinates":[-49.88708,-23.10737],"type":"Point"}
}