{
  "type": "Feature",
  "properties": {
    "gn:admin1_code":"17",
    "gn:admin2_code":"2504801.0",
    "gn:asciiname":"Pedra Branca",
    "gn:country_code":"BR",
    "gn:dem":276,
    "gn:feature_class":"P",
    "gn:feature_code":"PPL",
    "gn:name":"Pedra Branca",
    "gn:population":0,
    "gn:timezone":"America/Fortaleza",
    "iso:country":"BR",
    "wof:name":"Pedra Branca",
    "wof:placetype":"locality"
},
  "geometry": {"coordinates":[-38.03333,-7.05],"type":"Point"}
}