{
  "type": "Feature",
  "properties": {
    "gn:admin1_code":"18.0",
    "gn:admin2_code":"4112306.0",
    "gn:asciiname":"Sitio Jose de Paula",
    "gn:country_code":"BR",
    "gn:dem":655,
    "gn:feature_class":"P",
    "gn:feature_code":"PPL",
    "gn:name":"S\u00edtio Jos\u00e9 de Paula",
    "gn:population":0,
    "gn:timezone":"America/Sao_Paulo",
    "iso:country":"BR",
    "name:por_x_preferred":[
        "S\u00edtio Jos\u00e9 de Paula"
    ],
    "wof:name":"Sitio Jose de Paula",
    "wof:placetype":"locality"
},
  "geometry": {"coordinates":[-50.10939000000001,-23.84866],"type":"Point"}
}