{
  "type": "Feature",
  "properties": {
    "gn:admin1_code":"5",
    "gn:admin2_code":"2920502.0",
    "gn:asciiname":"Camolengue",
    "gn:country_code":"BR",
    "gn:dem":855,
    "gn:feature_class":"P",
    "gn:feature_code":"PPL",
    "gn:name":"Camolengue",
    "gn:population":0,
    "gn:timezone":"America/Bahia",
    "iso:country":"BR",
    "wof:name":"Camolengue",
    "wof:placetype":"locality"
},
  "geometry": {"coordinates":[-40.46667,-13.56667],"type":"Point"}
}