{
  "type": "Feature",
  "properties": {
    "gn:admin1_code":"06",
    "gn:admin2_code":"2308104.0",
    "gn:asciiname":"Pitombeira",
    "gn:country_code":"BR",
    "gn:dem":620,
    "gn:feature_class":"P",
    "gn:feature_code":"PPL",
    "gn:name":"Pitombeira",
    "gn:population":0,
    "gn:timezone":"America/Fortaleza",
    "iso:country":"BR",
    "wof:name":"Pitombeira",
    "wof:placetype":"locality"
},
  "geometry": {"coordinates":[-38.58333,-7.26667],"type":"Point"}
}