{
  "type": "Feature",
  "properties": {
    "gn:admin1_code":"18.0",
    "gn:admin2_code":"4104006.0",
    "gn:asciiname":"Praia Grande",
    "gn:country_code":"BR",
    "gn:dem":871,
    "gn:feature_class":"P",
    "gn:feature_code":"PPLL",
    "gn:name":"Praia Grande",
    "gn:population":0,
    "gn:timezone":"America/Sao_Paulo",
    "iso:country":"BR",
    "name:por_x_preferred":[
        "Praia Grande"
    ],
    "wof:name":"Praia Grande",
    "wof:placetype":"locality"
},
  "geometry": {"coordinates":[-48.89072,-25.18752000000001],"type":"Point"}
}