{
  "type": "Feature",
  "properties": {
    "gn:admin1_code":"14",
    "gn:admin2_code":"5102504.0",
    "gn:asciiname":"Toca Vaca",
    "gn:country_code":"BR",
    "gn:dem":144,
    "gn:feature_class":"P",
    "gn:feature_code":"PPL",
    "gn:name":"Toca Vaca",
    "gn:population":0,
    "gn:timezone":"America/Cuiaba",
    "iso:country":"BR",
    "wof:name":"Toca Vaca",
    "wof:placetype":"locality"
},
  "geometry": {"coordinates":[-58.36666999999999,-16.26667],"type":"Point"}
}