{
  "type": "Feature",
  "properties": {
    "gn:admin1_code":"4",
    "gn:admin2_code":"1304104.0",
    "gn:asciiname":"Guajaratubinha",
    "gn:cc2":"BR",
    "gn:country_code":"BR",
    "gn:dem":47,
    "gn:feature_class":"P",
    "gn:feature_code":"PPL",
    "gn:name":"Guajaratubinha",
    "gn:population":0,
    "gn:timezone":"America/Manaus",
    "iso:country":"BR",
    "name:und_x_variant":[
        "Guajara Sinha",
        "Guajaratubinha"
    ],
    "wof:name":"Guajaratubinha",
    "wof:placetype":"locality"
},
  "geometry": {"coordinates":[-63.37111,-5.63556],"type":"Point"}
}