{
  "type": "Feature",
  "properties": {
    "gn:admin1_code":"13",
    "gn:admin2_code":"2111300.0",
    "gn:asciiname":"Vila Maranhao",
    "gn:country_code":"BR",
    "gn:dem":26,
    "gn:feature_class":"P",
    "gn:feature_code":"PPL",
    "gn:name":"Vila Maranh\u00e3o",
    "gn:population":0,
    "gn:timezone":"America/Fortaleza",
    "iso:country":"BR",
    "wof:name":"Vila Maranhao",
    "wof:placetype":"locality"
},
  "geometry": {"coordinates":[-44.31667,-2.61667],"type":"Point"}
}