{
  "type": "Feature",
  "properties": {
    "gn:admin1_code":"06",
    "gn:admin2_code":"2302503.0",
    "gn:asciiname":"Malhada Grande",
    "gn:country_code":"BR",
    "gn:dem":561,
    "gn:feature_class":"P",
    "gn:feature_code":"PPL",
    "gn:name":"Malhada Grande",
    "gn:population":0,
    "gn:timezone":"America/Recife",
    "iso:country":"BR",
    "wof:name":"Malhada Grande",
    "wof:placetype":"locality"
},
  "geometry": {"coordinates":[-38.85,-7.71667],"type":"Point"}
}