{
  "type": "Feature",
  "properties": {
    "gn:admin1_code":"18.0",
    "gn:admin2_code":"4126603.0",
    "gn:asciiname":"Sitio Eugenio Caetano",
    "gn:country_code":"BR",
    "gn:dem":714,
    "gn:feature_class":"P",
    "gn:feature_code":"PPL",
    "gn:name":"S\u00edtio Eug\u00eanio Caetano",
    "gn:population":0,
    "gn:timezone":"America/Sao_Paulo",
    "iso:country":"BR",
    "name:por_x_preferred":[
        "S\u00edtio Eug\u00eanio Caetano"
    ],
    "wof:name":"Sitio Eugenio Caetano",
    "wof:placetype":"locality"
},
  "geometry": {"coordinates":[-49.7715,-23.6478],"type":"Point"}
}