{
  "type": "Feature",
  "properties": {
    "gn:admin1_code":"18.0",
    "gn:admin2_code":"4124103.0",
    "gn:asciiname":"Sitio Santa Cecilia",
    "gn:country_code":"BR",
    "gn:dem":521,
    "gn:feature_class":"P",
    "gn:feature_code":"PPL",
    "gn:name":"S\u00edtio Santa Cec\u00edlia",
    "gn:population":0,
    "gn:timezone":"America/Sao_Paulo",
    "iso:country":"BR",
    "name:por_x_preferred":[
        "S\u00edtio Santa Cec\u00edlia"
    ],
    "wof:name":"Sitio Santa Cecilia",
    "wof:placetype":"locality"
},
  "geometry": {"coordinates":[-50.15762,-23.27677000000001],"type":"Point"}
}