{
  "type": "Feature",
  "properties": {
    "gn:admin1_code":"06",
    "gn:admin2_code":"2302305.0",
    "gn:asciiname":"Corrego (1)",
    "gn:country_code":"BR",
    "gn:dem":51,
    "gn:feature_class":"P",
    "gn:feature_code":"PPL",
    "gn:name":"C\u00f3rrego (1)",
    "gn:population":0,
    "gn:timezone":"America/Fortaleza",
    "iso:country":"BR",
    "wof:name":"Corrego (1)",
    "wof:placetype":"locality"
},
  "geometry": {"coordinates":[-40.35,-3.03333],"type":"Point"}
}