{
  "type": "Feature",
  "properties": {
    "gn:admin1_code":"18.0",
    "gn:admin2_code":"4127809.0",
    "gn:asciiname":"Sitio Nilson A. e Irmao",
    "gn:country_code":"BR",
    "gn:dem":509,
    "gn:feature_class":"P",
    "gn:feature_code":"PPL",
    "gn:name":"S\u00edtio Nilson A. e Irm\u00e3o",
    "gn:population":0,
    "gn:timezone":"America/Sao_Paulo",
    "iso:country":"BR",
    "name:por_x_preferred":[
        "S\u00edtio Nilson A. e Irm\u00e3o"
    ],
    "wof:name":"Sitio Nilson A. e Irmao",
    "wof:placetype":"locality"
},
  "geometry": {"coordinates":[-49.9652,-23.5974],"type":"Point"}
}