{
  "type": "Feature",
  "properties": {
    "gn:admin1_code":"11",
    "gn:admin2_code":"5003207.0",
    "gn:asciiname":"Viveirinho",
    "gn:country_code":"BR",
    "gn:dem":135,
    "gn:feature_class":"P",
    "gn:feature_code":"PPL",
    "gn:name":"Viveirinho",
    "gn:population":0,
    "gn:timezone":"America/Campo_Grande",
    "iso:country":"BR",
    "name:por_x_preferred":[
        "Viveirinho"
    ],
    "wof:name":"Viveirinho",
    "wof:placetype":"locality"
},
  "geometry": {"coordinates":[-56.05,-17.83333],"type":"Point"}
}