{
  "type": "Feature",
  "properties": {
    "gn:admin1_code":"18.0",
    "gn:admin2_code":"4120705.0",
    "gn:asciiname":"Sitio Vicente Xavier",
    "gn:country_code":"BR",
    "gn:dem":492,
    "gn:feature_class":"P",
    "gn:feature_code":"PPL",
    "gn:name":"S\u00edtio Vicente Xavier",
    "gn:population":0,
    "gn:timezone":"America/Sao_Paulo",
    "iso:country":"BR",
    "name:por_x_preferred":[
        "S\u00edtio Vicente Xavier"
    ],
    "wof:name":"Sitio Vicente Xavier",
    "wof:placetype":"locality"
},
  "geometry": {"coordinates":[-49.9763,-23.5388],"type":"Point"}
}