{
  "type": "Feature",
  "properties": {
    "gn:admin1_code":"8",
    "gn:admin2_code":"3203809.0",
    "gn:asciiname":"Vargem Alegre",
    "gn:country_code":"BR",
    "gn:dem":526,
    "gn:feature_class":"P",
    "gn:feature_code":"PPL",
    "gn:name":"Vargem Alegre",
    "gn:population":0,
    "gn:timezone":"America/Sao_Paulo",
    "iso:country":"BR",
    "name:por_x_preferred":[
        "Vargem Alegre"
    ],
    "wof:name":"Vargem Alegre",
    "wof:placetype":"locality"
},
  "geometry": {"coordinates":[-41.41667,-20.91667],"type":"Point"}
}