{
  "type": "Feature",
  "properties": {
    "gn:admin1_code":"15.0",
    "gn:admin2_code":"3172202.0",
    "gn:asciiname":"Venceslau Bras",
    "gn:country_code":"BR",
    "gn:dem":1163,
    "gn:feature_class":"P",
    "gn:feature_code":"PPL",
    "gn:name":"Venceslau Bras",
    "gn:population":0,
    "gn:timezone":"America/Sao_Paulo",
    "iso:country":"BR",
    "name:por_x_preferred":[
        "Venceslau Bras"
    ],
    "wof:name":"Venceslau Bras",
    "wof:placetype":"locality"
},
  "geometry": {"coordinates":[-45.35824,-22.54022],"type":"Point"}
}