{
  "type": "Feature",
  "properties": {
    "gn:admin1_code":"18.0",
    "gn:admin2_code":"4109609.0",
    "gn:asciiname":"Sitio Pedra Branca",
    "gn:country_code":"BR",
    "gn:dem":133,
    "gn:feature_class":"P",
    "gn:feature_code":"PPL",
    "gn:name":"S\u00edtio Pedra Branca",
    "gn:population":0,
    "gn:timezone":"America/Sao_Paulo",
    "iso:country":"BR",
    "name:por_x_preferred":[
        "S\u00edtio Pedra Branca"
    ],
    "wof:name":"Sitio Pedra Branca",
    "wof:placetype":"locality"
},
  "geometry": {"coordinates":[-48.90523,-25.95091],"type":"Point"}
}