{
  "type": "Feature",
  "properties": {
    "gn:admin1_code":"13",
    "gn:admin2_code":"2100501.0",
    "gn:asciiname":"Ipane",
    "gn:country_code":"BR",
    "gn:dem":394,
    "gn:feature_class":"P",
    "gn:feature_code":"PPL",
    "gn:name":"Ipan\u00e9",
    "gn:population":0,
    "gn:timezone":"America/Fortaleza",
    "iso:country":"BR",
    "wof:name":"Ipane",
    "wof:placetype":"locality"
},
  "geometry": {"coordinates":[-46.15,-9.55],"type":"Point"}
}