{
  "type": "Feature",
  "properties": {
    "gn:admin1_code":"18",
    "gn:admin2_code":"4121208.0",
    "gn:asciiname":"Sitio Maria Sureck",
    "gn:country_code":"BR",
    "gn:dem":845,
    "gn:feature_class":"P",
    "gn:feature_code":"PPL",
    "gn:name":"S\u00edtio Maria Sureck",
    "gn:population":0,
    "gn:timezone":"America/Sao_Paulo",
    "iso:country":"BR",
    "name:por_x_preferred":[
        "S\u00edtio Maria Sureck"
    ],
    "wof:name":"Sitio Maria Sureck",
    "wof:placetype":"locality"
},
  "geometry": {"coordinates":[-49.57167000000001,-25.90694],"type":"Point"}
}