{
  "type": "Feature",
  "properties": {
    "gn:admin1_code":"13",
    "gn:admin2_code":"2106409.0",
    "gn:asciiname":"Mata do Irigadeiro",
    "gn:country_code":"BR",
    "gn:dem":70,
    "gn:feature_class":"P",
    "gn:feature_code":"PPL",
    "gn:name":"Mata do Irigadeiro",
    "gn:population":0,
    "gn:timezone":"America/Fortaleza",
    "iso:country":"BR",
    "wof:name":"Mata do Irigadeiro",
    "wof:placetype":"locality"
},
  "geometry": {"coordinates":[-43.22417,-3.71528],"type":"Point"}
}