{
  "type": "Feature",
  "properties": {
    "gn:admin1_code":"02",
    "gn:admin2_code":"2700904.0",
    "gn:asciiname":"Farias",
    "gn:country_code":"BR",
    "gn:dem":19,
    "gn:feature_class":"P",
    "gn:feature_code":"PPL",
    "gn:name":"Farias",
    "gn:population":0,
    "gn:timezone":"America/Maceio",
    "iso:country":"BR",
    "wof:name":"Farias",
    "wof:placetype":"locality"
},
  "geometry": {"coordinates":[-37.25,-9.86667],"type":"Point"}
}