{
  "type": "Feature",
  "properties": {
    "gn:admin1_code":"18",
    "gn:admin2_code":"4121208.0",
    "gn:asciiname":"Sitio Stanislau Prussaki",
    "gn:country_code":"BR",
    "gn:dem":886,
    "gn:feature_class":"P",
    "gn:feature_code":"PPL",
    "gn:name":"S\u00edtio Stanislau Prussaki",
    "gn:population":0,
    "gn:timezone":"America/Sao_Paulo",
    "iso:country":"BR",
    "name:por_x_preferred":[
        "S\u00edtio Stanislau Prussaki"
    ],
    "wof:name":"Sitio Stanislau Prussaki",
    "wof:placetype":"locality"
},
  "geometry": {"coordinates":[-49.3889,-26.0416],"type":"Point"}
}