{
  "type": "Feature",
  "properties": {
    "gn:admin1_code":"23",
    "gn:admin2_code":"4301206.0",
    "gn:asciiname":"Sitio",
    "gn:country_code":"BR",
    "gn:dem":344,
    "gn:feature_class":"P",
    "gn:feature_code":"PPLL",
    "gn:name":"S\u00edtio",
    "gn:population":0,
    "gn:timezone":"America/Sao_Paulo",
    "iso:country":"BR",
    "name:deu_x_preferred":[
        "Sitio"
    ],
    "name:ilo_x_preferred":[
        "Sitio"
    ],
    "wof:name":"Sitio",
    "wof:placetype":"locality"
},
  "geometry": {"coordinates":[-53.03583,-29.17444],"type":"Point"}
}