{
  "type": "Feature",
  "properties": {
    "gn:admin1_code":"27.0",
    "gn:admin2_code":"3524600.0",
    "gn:asciiname":"Barra Ribeirao do Salto",
    "gn:country_code":"BR",
    "gn:dem":96,
    "gn:feature_class":"P",
    "gn:feature_code":"PPLL",
    "gn:name":"Barra Ribeir\u00e3o do Salto",
    "gn:population":0,
    "gn:timezone":"America/Sao_Paulo",
    "iso:country":"BR",
    "name:por_x_preferred":[
        "Barra Ribeir\u00e3o do Salto"
    ],
    "wof:name":"Barra Ribeirao do Salto",
    "wof:placetype":"locality"
},
  "geometry": {"coordinates":[-48.1038,-24.8639],"type":"Point"}
}