{
  "type": "Feature",
  "properties": {
    "gn:admin1_code":"13",
    "gn:admin2_code":"2112605.0",
    "gn:asciiname":"Raiz",
    "gn:country_code":"BR",
    "gn:dem":53,
    "gn:feature_class":"P",
    "gn:feature_code":"PPL",
    "gn:name":"Raiz",
    "gn:population":0,
    "gn:timezone":"America/Fortaleza",
    "iso:country":"BR",
    "wof:name":"Raiz",
    "wof:placetype":"locality"
},
  "geometry": {"coordinates":[-43.36,-3.26833],"type":"Point"}
}