{
  "type": "Feature",
  "properties": {
    "gn:admin1_code":"18.0",
    "gn:admin2_code":"4100202.0",
    "gn:asciiname":"Barra do Mendes",
    "gn:country_code":"BR",
    "gn:dem":251,
    "gn:feature_class":"P",
    "gn:feature_code":"PPLL",
    "gn:name":"Barra do Mendes",
    "gn:population":0,
    "gn:timezone":"America/Sao_Paulo",
    "iso:country":"BR",
    "name:bpy_x_preferred":[
        "\u09ac\u09be\u09b0\u09cd\u09b0\u09be \u09a1\u09cb \u09ae\u09c7\u09a8\u09a1\u09c7\u09b8"
    ],
    "name:hye_x_preferred":[
        "\u0532\u0561\u0580\u0580\u0561 \u0564\u0578\u0582 \u0544\u0565\u0576\u0564\u056b\u0581"
    ],
    "name:kat_x_preferred":[
        "\u10d1\u10d0\u10e0\u10d0-\u10d3\u10e3-\u10db\u10d4\u10dc\u10d3\u10d4\u10e1\u10d8"
    ],
    "name:kaz_x_preferred":[
        "\u0411\u0430\u0440\u0440\u0430-\u0434\u0443-\u041c\u0435\u043d\u0434\u0438\u0441"
    ],
    "name:por_x_preferred":[
        "Barra do Mendes"
    ],
    "name:rus_x_preferred":[
        "\u0411\u0430\u0440\u0440\u0430-\u0434\u0443-\u041c\u0435\u043d\u0434\u0438\u0441"
    ],
    "name:zho_x_preferred":[
        "\u5df4\u62c9-\u675c\u95e8\u8fea\u65af"
    ],
    "wof:name":"Barra do Mendes",
    "wof:placetype":"locality"
},
  "geometry": {"coordinates":[-48.88425,-24.76127],"type":"Point"}
}