{
  "type": "Feature",
  "properties": {
    "gn:admin1_code":"18.0",
    "gn:admin2_code":"4100202.0",
    "gn:asciiname":"Barra do Mendes",
    "gn:country_code":"BR",
    "gn:dem":251,
    "gn:feature_class":"P",
    "gn:feature_code":"PPLL",
    "gn:name":"Barra do Mendes",
    "gn:population":0,
    "gn:timezone":"America/Sao_Paulo",
    "iso:country":"BR",
    "name:por_x_preferred":[
        "Barra do Mendes"
    ],
    "wof:name":"Barra do Mendes",
    "wof:placetype":"locality"
},
  "geometry": {"coordinates":[-48.88425,-24.76127],"type":"Point"}
}