{
  "type": "Feature",
  "properties": {
    "gn:admin1_code":"23",
    "gn:admin2_code":"4322400.0",
    "gn:asciiname":"Estancia Mimosa",
    "gn:country_code":"BR",
    "gn:dem":83,
    "gn:feature_class":"P",
    "gn:feature_code":"PPL",
    "gn:name":"Est\u00e2ncia Mimosa",
    "gn:population":0,
    "gn:timezone":"America/Sao_Paulo",
    "iso:country":"BR",
    "wof:name":"Estancia Mimosa",
    "wof:placetype":"locality"
},
  "geometry": {"coordinates":[-56.38333000000001,-29.78333],"type":"Point"}
}