{
  "type": "Feature",
  "properties": {
    "gn:admin1_code":"15",
    "gn:admin2_code":"3168507.0",
    "gn:asciiname":"Bom Jardim de Cima",
    "gn:country_code":"BR",
    "gn:dem":748,
    "gn:feature_class":"P",
    "gn:feature_code":"PPL",
    "gn:name":"Bom Jardim de Cima",
    "gn:population":0,
    "gn:timezone":"America/Sao_Paulo",
    "iso:country":"BR",
    "name:por_x_preferred":[
        "Bom Jardim de Cima"
    ],
    "wof:name":"Bom Jardim de Cima",
    "wof:placetype":"locality"
},
  "geometry": {"coordinates":[-42.88333,-20.58333],"type":"Point"}
}