{
  "type": "Feature",
  "properties": {
    "gn:admin1_code":"20",
    "gn:admin2_code":"2208502.0",
    "gn:asciiname":"Fernando",
    "gn:country_code":"BR",
    "gn:dem":31,
    "gn:feature_class":"P",
    "gn:feature_code":"PPL",
    "gn:name":"Fernando",
    "gn:population":0,
    "gn:timezone":"America/Fortaleza",
    "iso:country":"BR",
    "wof:name":"Fernando",
    "wof:placetype":"locality"
},
  "geometry": {"coordinates":[-42.71028,-3.86528],"type":"Point"}
}