{
  "type": "Feature",
  "properties": {
    "gn:admin1_code":"13",
    "gn:admin2_code":"2112605.0",
    "gn:asciiname":"Boa Vista",
    "gn:country_code":"BR",
    "gn:dem":74,
    "gn:feature_class":"P",
    "gn:feature_code":"PPL",
    "gn:name":"Boa Vista",
    "gn:population":0,
    "gn:timezone":"America/Fortaleza",
    "iso:country":"BR",
    "wof:name":"Boa Vista",
    "wof:placetype":"locality"
},
  "geometry": {"coordinates":[-43.21778,-3.2875],"type":"Point"}
}