{
  "type": "Feature",
  "properties": {
    "gn:admin1_code":"27",
    "gn:admin2_code":"3509908.0",
    "gn:asciiname":"Barranco Alto",
    "gn:country_code":"BR",
    "gn:dem":12,
    "gn:feature_class":"P",
    "gn:feature_code":"PPLL",
    "gn:name":"Barranco Alto",
    "gn:population":0,
    "gn:timezone":"America/Sao_Paulo",
    "iso:country":"BR",
    "name:por_x_preferred":[
        "Barranco Alto"
    ],
    "wof:name":"Barranco Alto",
    "wof:placetype":"locality"
},
  "geometry": {"coordinates":[-48.06866,-25.21453],"type":"Point"}
}