{
  "type": "Feature",
  "properties": {
    "gn:admin1_code":"18.0",
    "gn:admin2_code":"4124103.0",
    "gn:asciiname":"Sitio Antonio Piculo",
    "gn:country_code":"BR",
    "gn:dem":419,
    "gn:feature_class":"P",
    "gn:feature_code":"PPL",
    "gn:name":"S\u00edtio Ant\u00f4nio Piculo",
    "gn:population":0,
    "gn:timezone":"America/Sao_Paulo",
    "iso:country":"BR",
    "name:por_x_preferred":[
        "S\u00edtio Ant\u00f4nio Piculo"
    ],
    "wof:name":"Sitio Antonio Piculo",
    "wof:placetype":"locality"
},
  "geometry": {"coordinates":[-50.14945,-23.14793],"type":"Point"}
}