{
  "type": "Feature",
  "properties": {
    "gn:admin1_code":"26.0",
    "gn:admin2_code":"4216503.0",
    "gn:asciiname":"Despraiado",
    "gn:country_code":"BR",
    "gn:dem":1106,
    "gn:feature_class":"P",
    "gn:feature_code":"PPL",
    "gn:name":"Despraiado",
    "gn:population":0,
    "gn:timezone":"America/Sao_Paulo",
    "iso:country":"BR",
    "wof:name":"Despraiado",
    "wof:placetype":"locality"
},
  "geometry": {"coordinates":[-49.80098,-28.36733],"type":"Point"}
}