{
  "type": "Feature",
  "properties": {
    "gn:admin1_code":"18.0",
    "gn:admin2_code":"4103107.0",
    "gn:asciiname":"Sitio Marco Antonio",
    "gn:country_code":"BR",
    "gn:dem":865,
    "gn:feature_class":"P",
    "gn:feature_code":"PPL",
    "gn:name":"S\u00edtio Marco Ant\u00f4nio",
    "gn:population":0,
    "gn:timezone":"America/Sao_Paulo",
    "iso:country":"BR",
    "name:por_x_preferred":[
        "S\u00edtio Marco Ant\u00f4nio"
    ],
    "wof:name":"Sitio Marco Antonio",
    "wof:placetype":"locality"
},
  "geometry": {"coordinates":[-48.84122,-25.05709],"type":"Point"}
}