{
  "type": "Feature",
  "properties": {
    "gn:admin1_code":"18.0",
    "gn:admin2_code":"4118204.0",
    "gn:asciiname":"Medeiros de Cima",
    "gn:country_code":"BR",
    "gn:dem":9,
    "gn:feature_class":"P",
    "gn:feature_code":"PPLL",
    "gn:name":"Medeiros de Cima",
    "gn:population":0,
    "gn:timezone":"America/Sao_Paulo",
    "iso:country":"BR",
    "name:por_x_preferred":[
        "Medeiros de Cima"
    ],
    "wof:name":"Medeiros de Cima",
    "wof:placetype":"locality"
},
  "geometry": {"coordinates":[-48.45861,-25.4087],"type":"Point"}
}