{
  "type": "Feature",
  "properties": {
    "gn:admin1_code":"18.0",
    "gn:admin2_code":"4127882.0",
    "gn:asciiname":"Sitio Angelo P. Santos",
    "gn:country_code":"BR",
    "gn:dem":955,
    "gn:feature_class":"P",
    "gn:feature_code":"PPL",
    "gn:name":"S\u00edtio Angelo P. Santos",
    "gn:population":0,
    "gn:timezone":"America/Sao_Paulo",
    "iso:country":"BR",
    "name:por_x_preferred":[
        "S\u00edtio Angelo P. Santos"
    ],
    "wof:name":"Sitio Angelo P. Santos",
    "wof:placetype":"locality"
},
  "geometry": {"coordinates":[-48.9656,-25.04241],"type":"Point"}
}