{
  "type": "Feature",
  "properties": {
    "gn:admin1_code":"2",
    "gn:admin2_code":"2709301.0",
    "gn:asciiname":"Amolar",
    "gn:country_code":"BR",
    "gn:dem":201,
    "gn:feature_class":"P",
    "gn:feature_code":"PPL",
    "gn:name":"Amolar",
    "gn:population":0,
    "gn:timezone":"America/Maceio",
    "iso:country":"BR",
    "wof:name":"Amolar",
    "wof:placetype":"locality"
},
  "geometry": {"coordinates":[-36.13333,-9.18333],"type":"Point"}
}