{
  "type": "Feature",
  "properties": {
    "gn:admin1_code":"20",
    "gn:admin2_code":"2206670.0",
    "gn:asciiname":"Baixa do Coxo",
    "gn:country_code":"BR",
    "gn:dem":87,
    "gn:feature_class":"P",
    "gn:feature_code":"PPL",
    "gn:name":"Baixa do Coxo",
    "gn:population":0,
    "gn:timezone":"America/Fortaleza",
    "iso:country":"BR",
    "wof:name":"Baixa do Coxo",
    "wof:placetype":"locality"
},
  "geometry": {"coordinates":[-42.18167,-3.65972],"type":"Point"}
}