{
  "type": "Feature",
  "properties": {
    "gn:admin1_code":"15",
    "gn:admin2_code":"3162203.0",
    "gn:asciiname":"Joaquim Hilario",
    "gn:country_code":"BR",
    "gn:dem":860,
    "gn:feature_class":"P",
    "gn:feature_code":"PPL",
    "gn:name":"Joaquim Hil\u00e1rio",
    "gn:population":0,
    "gn:timezone":"America/Sao_Paulo",
    "iso:country":"BR",
    "name:por_x_preferred":[
        "Joaquim Hil\u00e1rio"
    ],
    "wof:name":"Joaquim Hilario",
    "wof:placetype":"locality"
},
  "geometry": {"coordinates":[-46.41667,-20.58333],"type":"Point"}
}