{
  "type": "Feature",
  "properties": {
    "gn:admin1_code":"06",
    "gn:admin2_code":"2312205.0",
    "gn:asciiname":"Fazenda Varzea do Jua",
    "gn:country_code":"BR",
    "gn:dem":183,
    "gn:feature_class":"P",
    "gn:feature_code":"PPL",
    "gn:name":"Fazenda V\u00e1rzea do Ju\u00e1",
    "gn:population":0,
    "gn:timezone":"America/Fortaleza",
    "iso:country":"BR",
    "wof:name":"Fazenda Varzea do Jua",
    "wof:placetype":"locality"
},
  "geometry": {"coordinates":[-40.21667,-4.25],"type":"Point"}
}