{
  "type": "Feature",
  "properties": {
    "iso:country":"BR",
    "name:ara_x_preferred":[
        "\u0643\u0627\u0634\u0648\u064a\u0631\u064a\u0646\u0647\u0627"
    ],
    "name:bpy_x_preferred":[
        "\u0995\u09be\u0995\u09b9\u09cb\u09af\u09bc\u09c7\u0987\u09b0\u09bf\u09a8\u09b9\u09be"
    ],
    "name:cat_x_preferred":[
        "Cachoeirinha"
    ],
    "name:deu_x_preferred":[
        "Cachoeirinha"
    ],
    "name:epo_x_preferred":[
        "Cachoeirinha"
    ],
    "name:fra_x_preferred":[
        "Cachoeirinha"
    ],
    "name:hak_x_preferred":[
        "Cachoeirinha"
    ],
    "name:kaz_x_preferred":[
        "\u041a\u0430\u0448\u0443\u044d\u0439\u0440\u0438\u043d\u044c\u044f"
    ],
    "name:pol_x_preferred":[
        "Cachoeirinha"
    ],
    "name:por_x_preferred":[
        "Cachoeirinha"
    ],
    "name:ron_x_preferred":[
        "Cachoeirinha"
    ],
    "name:rus_x_preferred":[
        "\u041a\u0430\u0448\u0443\u044d\u0439\u0440\u0438\u043d\u044c\u044f"
    ],
    "name:spa_x_preferred":[
        "Cachoeirinha"
    ],
    "name:swe_x_preferred":[
        "Cachoeirinha"
    ],
    "name:tat_x_preferred":[
        "\u041a\u0430\u0448\u0432\u0435\u0439\u0440\u0438\u043d\u044c\u044f"
    ],
    "name:war_x_preferred":[
        "Cachoeirinha"
    ],
    "name:zho_x_preferred":[
        "\u5361\u8212\u57c3\u91cc\u5c3c\u4e9e"
    ],
    "qs:gn_adm0_cc":"BR",
    "qs:gn_fcode":"PPLX",
    "qs:gn_local":3663517,
    "qs:gn_namadm1":"04",
    "qs:gn_name":"Cachoeirinha",
    "qs:local_max":3574,
    "qs:local_sum":8876,
    "qs:localhoods":22,
    "qs:name":"Cachoeirinha",
    "qs:name_adm0":"Brasil",
    "qs:name_adm1":"Amazonas",
    "qs:name_adm2":"Manaus",
    "qs:name_local":"Manaus",
    "qs:photo_max":129,
    "qs:photo_sum":379,
    "qs:placetype":"Suburb",
    "qs:quad_count":23,
    "qs:woe_adm0":23424768,
    "qs:woe_adm1":2344847,
    "qs:woe_adm2":12578206,
    "qs:woe_lau":0,
    "qs:woe_local":455833,
    "qs:woe_ver":"7.10.0",
    "wof:lang":[
        "por"
    ],
    "wof:name":"Cachoeirinha",
    "wof:placetype":"neighbourhood"
},
  "geometry": {"coordinates":[-60.007863,-3.119006],"type":"Point"}
}