{
  "type": "Feature",
  "properties": {
    "gn:admin1_code":"18.0",
    "gn:admin2_code":"4113205.0",
    "gn:asciiname":"Santos Reis",
    "gn:country_code":"BR",
    "gn:dem":936,
    "gn:feature_class":"P",
    "gn:feature_code":"PPL",
    "gn:name":"Santos Reis",
    "gn:population":0,
    "gn:timezone":"America/Sao_Paulo",
    "iso:country":"BR",
    "name:por_x_preferred":[
        "Santos Reis"
    ],
    "wof:name":"Santos Reis",
    "wof:placetype":"locality"
},
  "geometry": {"coordinates":[-50.08281,-25.85805],"type":"Point"}
}