{
  "type": "Feature",
  "properties": {
    "gn:admin1_code":"20",
    "gn:admin2_code":"2205300.0",
    "gn:asciiname":"Surdo",
    "gn:country_code":"BR",
    "gn:dem":203,
    "gn:feature_class":"P",
    "gn:feature_code":"PPL",
    "gn:name":"Surdo",
    "gn:population":0,
    "gn:timezone":"America/Fortaleza",
    "iso:country":"BR",
    "wof:name":"Surdo",
    "wof:placetype":"locality"
},
  "geometry": {"coordinates":[-43.47722,-7.16626],"type":"Point"}
}