{
  "type": "Feature",
  "properties": {
    "gn:admin1_code":"20",
    "gn:admin2_code":"2205300.0",
    "gn:asciiname":"Surdo",
    "gn:country_code":"BR",
    "gn:dem":203,
    "gn:feature_class":"P",
    "gn:feature_code":"PPL",
    "gn:name":"Surdo",
    "gn:population":0,
    "gn:timezone":"America/Fortaleza",
    "iso:country":"BR",
    "name:bul_x_preferred":[
        "\u0421\u0443\u0440\u0434\u043e"
    ],
    "name:cat_x_preferred":[
        "Surdo"
    ],
    "name:dan_x_preferred":[
        "Surdo"
    ],
    "name:deu_x_preferred":[
        "Surdo"
    ],
    "name:epo_x_preferred":[
        "Surdo"
    ],
    "name:fra_x_preferred":[
        "Surdo"
    ],
    "name:ita_x_preferred":[
        "Surdo"
    ],
    "name:jpn_x_preferred":[
        "\u30b9\u30eb\u30c9"
    ],
    "name:nld_x_preferred":[
        "Surdo"
    ],
    "name:spa_x_preferred":[
        "Surdo"
    ],
    "name:swe_x_preferred":[
        "Surdo"
    ],
    "wof:name":"Surdo",
    "wof:placetype":"locality"
},
  "geometry": {"coordinates":[-43.47722,-7.16626],"type":"Point"}
}