{
  "type": "Feature",
  "properties": {
    "gn:admin1_code":"20",
    "gn:admin2_code":"2206100.0",
    "gn:asciiname":"Mocambo",
    "gn:country_code":"BR",
    "gn:dem":47,
    "gn:feature_class":"P",
    "gn:feature_code":"PPL",
    "gn:name":"Mocambo",
    "gn:population":0,
    "gn:timezone":"America/Fortaleza",
    "iso:country":"BR",
    "wof:name":"Mocambo",
    "wof:placetype":"locality"
},
  "geometry": {"coordinates":[-42.625,-3.67278],"type":"Point"}
}