{
  "type": "Feature",
  "properties": {
    "iso:country":"BR",
    "name:ara_x_preferred":[
        "\u062a\u064a\u0631\u0627\u062f\u064a\u0646\u062a\u064a\u0633"
    ],
    "name:ces_x_preferred":[
        "Tiradentes"
    ],
    "name:deu_x_preferred":[
        "Tiradentes"
    ],
    "name:ell_x_preferred":[
        "\u03a4\u03b9\u03c1\u03b1\u03bd\u03c4\u03ad\u03bd\u03c4\u03b5\u03c2"
    ],
    "name:epo_x_preferred":[
        "Tiradentes"
    ],
    "name:hun_x_preferred":[
        "Tiradentes"
    ],
    "name:ita_x_preferred":[
        "Tiradentes"
    ],
    "name:jpn_x_preferred":[
        "\u30c1\u30e9\u30c7\u30f3\u30c6\u30b9"
    ],
    "name:kaz_x_preferred":[
        "\u0422\u0438\u0440\u0430\u0434\u0435\u043d\u0442\u0438\u0441"
    ],
    "name:mal_x_preferred":[
        "\u0d1f\u0d3f\u0d31\u0d46\u0d21\u0d46\u0d28\u0d4d\u0d31\u0d3f\u0d38\u0d4d"
    ],
    "name:msa_x_preferred":[
        "Tiradentes"
    ],
    "name:por_x_preferred":[
        "Tiradentes"
    ],
    "name:rus_x_preferred":[
        "\u0422\u0438\u0440\u0430\u0434\u0435\u043d\u0442\u0438\u0441"
    ],
    "name:spa_x_preferred":[
        "Tiradentes"
    ],
    "name:srp_x_preferred":[
        "\u0422\u0438\u0440\u0430\u0434\u0435\u043d\u0442\u0435\u0441"
    ],
    "name:vie_x_preferred":[
        "Tiradentes"
    ],
    "name:zho_x_preferred":[
        "\u8482\u62c9\u767b\u7279\u65af"
    ],
    "qs_pg:aaroncc":"BR",
    "qs_pg:name":"Tiradentes",
    "qs_pg:name_adm0":"Brasil",
    "qs_pg:name_adm1":"Mato Grosso do Sul",
    "qs_pg:photos":79,
    "qs_pg:photos_1k":16,
    "qs_pg:photos_9k":1,
    "qs_pg:photos_9r":3,
    "qs_pg:photos_all":79,
    "qs_pg:photos_sr":3,
    "qs_pg:pop_sr":0,
    "qs_pg:qs_pg_placetype":"neighbourhood",
    "qs_pg:qs_pg_placetype_gp":"Suburb",
    "qs_pg:woe_adm0":23424768,
    "woe:adm0_id":23424768,
    "woe:name_adm0":"Brasil",
    "woe:name_adm1":"Mato Grosso do Sul",
    "woe:placetype":"Suburb",
    "wof:name":"Tiradentes",
    "wof:placetype":"neighbourhood"
},
  "geometry": {"coordinates":[-54.584369,-20.473305],"type":"Point"}
}