{
  "type": "Feature",
  "properties": {
    "iso:country":"BR",
    "qs_pg:aaroncc":"BR",
    "qs_pg:name":"Tiradentes",
    "qs_pg:name_adm0":"Brasil",
    "qs_pg:name_adm1":"Mato Grosso do Sul",
    "qs_pg:photos":79,
    "qs_pg:photos_1k":16,
    "qs_pg:photos_9k":1,
    "qs_pg:photos_9r":3,
    "qs_pg:photos_all":79,
    "qs_pg:photos_sr":3,
    "qs_pg:pop_sr":0,
    "qs_pg:qs_pg_placetype":"neighbourhood",
    "qs_pg:qs_pg_placetype_gp":"Suburb",
    "qs_pg:woe_adm0":23424768,
    "woe:adm0_id":23424768,
    "woe:name_adm0":"Brasil",
    "woe:name_adm1":"Mato Grosso do Sul",
    "woe:placetype":"Suburb",
    "wof:name":"Tiradentes",
    "wof:placetype":"neighbourhood"
},
  "geometry": {"coordinates":[-54.584369,-20.473305],"type":"Point"}
}