{
  "type": "Feature",
  "properties": {
    "gn:admin1_code":"13",
    "gn:admin2_code":"2101707.0",
    "gn:asciiname":"Jucaral",
    "gn:country_code":"BR",
    "gn:dem":26,
    "gn:feature_class":"P",
    "gn:feature_code":"PPL",
    "gn:name":"Ju\u00e7aral",
    "gn:population":0,
    "gn:timezone":"America/Fortaleza",
    "iso:country":"BR",
    "wof:name":"Jucaral",
    "wof:placetype":"locality"
},
  "geometry": {"coordinates":[-43.05333,-3.04083],"type":"Point"}
}