{
  "type": "Feature",
  "properties": {
    "gn:admin1_code":"20",
    "gn:admin2_code":"2200301.0",
    "gn:asciiname":"Fazenda Jurema",
    "gn:country_code":"BR",
    "gn:dem":156,
    "gn:feature_class":"P",
    "gn:feature_code":"PPL",
    "gn:name":"Fazenda Jurema",
    "gn:population":0,
    "gn:timezone":"America/Fortaleza",
    "iso:country":"BR",
    "wof:name":"Fazenda Jurema",
    "wof:placetype":"locality"
},
  "geometry": {"coordinates":[-42.15,-5.43333],"type":"Point"}
}