{
  "type": "Feature",
  "properties": {
    "gn:admin1_code":"5",
    "gn:admin2_code":"2922003.0",
    "gn:asciiname":"Riacho Doce",
    "gn:country_code":"BR",
    "gn:dem":20,
    "gn:feature_class":"P",
    "gn:feature_code":"PPL",
    "gn:name":"Riacho Doce",
    "gn:population":0,
    "gn:timezone":"America/Bahia",
    "iso:country":"BR",
    "name:por_x_preferred":[
        "Riacho Doce"
    ],
    "wof:name":"Riacho Doce",
    "wof:placetype":"locality"
},
  "geometry": {"coordinates":[-39.63333,-18.21667],"type":"Point"}
}