{
  "type": "Feature",
  "properties": {
    "gn:admin1_code":"18.0",
    "gn:admin2_code":"4124103.0",
    "gn:asciiname":"Sitio Edson Goncalves",
    "gn:country_code":"BR",
    "gn:dem":536,
    "gn:feature_class":"P",
    "gn:feature_code":"PPL",
    "gn:name":"S\u00edtio Edson Gon\u00e7alves",
    "gn:population":0,
    "gn:timezone":"America/Sao_Paulo",
    "iso:country":"BR",
    "name:por_x_preferred":[
        "S\u00edtio Edson Gon\u00e7alves"
    ],
    "wof:name":"Sitio Edson Goncalves",
    "wof:placetype":"locality"
},
  "geometry": {"coordinates":[-50.1495,-23.2358],"type":"Point"}
}