{
  "type": "Feature",
  "properties": {
    "gn:admin1_code":"18",
    "gn:admin2_code":"4104105.0",
    "gn:asciiname":"Sitio Germano Basso",
    "gn:country_code":"BR",
    "gn:dem":808,
    "gn:feature_class":"P",
    "gn:feature_code":"PPL",
    "gn:name":"S\u00edtio Germano Basso",
    "gn:population":0,
    "gn:timezone":"America/Sao_Paulo",
    "iso:country":"BR",
    "name:por_x_preferred":[
        "S\u00edtio Germano Basso"
    ],
    "wof:name":"Sitio Germano Basso",
    "wof:placetype":"locality"
},
  "geometry": {"coordinates":[-49.66444,-25.99722],"type":"Point"}
}