{
  "type": "Feature",
  "properties": {
    "gn:admin1_code":"27",
    "gn:admin2_code":"3507902.0",
    "gn:asciiname":"Campo Redondo",
    "gn:country_code":"BR",
    "gn:dem":705,
    "gn:feature_class":"P",
    "gn:feature_code":"PPL",
    "gn:name":"Campo Redondo",
    "gn:population":0,
    "gn:timezone":"America/Sao_Paulo",
    "iso:country":"BR",
    "name:bpy_x_preferred":[
        "\u0995\u09be\u09ae\u09cd\u09aa\u09cb \u09b0\u09c7\u09a1\u09cb\u09a8\u09a1\u09cb"
    ],
    "name:ceb_x_preferred":[
        "Campo Redondo"
    ],
    "name:epo_x_preferred":[
        "Campo Redondo"
    ],
    "name:eus_x_preferred":[
        "Campo Redondo"
    ],
    "name:fas_x_preferred":[
        "\u06a9\u0627\u0645\u067e\u0648 \u0631\u062f\u0648\u0646\u062f\u0648"
    ],
    "name:fra_x_preferred":[
        "Campo Redondo"
    ],
    "name:ita_x_preferred":[
        "Campo Redondo"
    ],
    "name:kat_x_preferred":[
        "\u10d9\u10d0\u10db\u10de\u10e3-\u10e0\u10d4\u10d3\u10dd\u10dc\u10d3\u10e3"
    ],
    "name:kaz_x_preferred":[
        "\u041a\u0430\u043c\u043f\u0443-\u0420\u0435\u0434\u043e\u043d\u0434\u0443"
    ],
    "name:mlg_x_preferred":[
        "Campo Redondo"
    ],
    "name:nld_x_preferred":[
        "Campo Redondo"
    ],
    "name:nor_x_preferred":[
        "Campo Redondo"
    ],
    "name:por_x_preferred":[
        "Campo Redondo"
    ],
    "name:ron_x_preferred":[
        "Campo Redondo"
    ],
    "name:rus_x_preferred":[
        "\u041a\u0430\u043c\u043f\u0443-\u0420\u0435\u0434\u043e\u043d\u0434\u0443"
    ],
    "name:swe_x_preferred":[
        "Campo Redondo"
    ],
    "name:vie_x_preferred":[
        "Campo Redondo"
    ],
    "name:vol_x_preferred":[
        "Campo Redondo"
    ],
    "name:zho_x_preferred":[
        "\u574e\u666e\u96f7\u4e1c\u675c"
    ],
    "wof:name":"Campo Redondo",
    "wof:placetype":"locality"
},
  "geometry": {"coordinates":[-47.98333,-22.35],"type":"Point"}
}