{
  "type": "Feature",
  "properties": {
    "gn:admin1_code":"27",
    "gn:admin2_code":"3509254.0",
    "gn:asciiname":"Vila Deco",
    "gn:country_code":"BR",
    "gn:dem":71,
    "gn:feature_class":"P",
    "gn:feature_code":"PPLL",
    "gn:name":"Vila Deco",
    "gn:population":0,
    "gn:timezone":"America/Sao_Paulo",
    "iso:country":"BR",
    "name:por_x_preferred":[
        "Vila Deco"
    ],
    "wof:name":"Vila Deco",
    "wof:placetype":"locality"
},
  "geometry": {"coordinates":[-48.1423,-24.68007],"type":"Point"}
}