{
  "type": "Feature",
  "properties": {
    "gn:admin1_code":"26",
    "gn:admin2_code":"4202057.0",
    "gn:asciiname":"Conquista",
    "gn:country_code":"BR",
    "gn:dem":10,
    "gn:feature_class":"P",
    "gn:feature_code":"PPL",
    "gn:name":"Conquista",
    "gn:population":0,
    "gn:timezone":"America/Sao_Paulo",
    "iso:country":"BR",
    "name:por_x_preferred":[
        "Conquista"
    ],
    "name:por_x_variant":[
        "Areias Grandes"
    ],
    "wof:name":"Conquista",
    "wof:placetype":"locality"
},
  "geometry": {"coordinates":[-48.6578,-26.3947],"type":"Point"}
}