{
  "type": "Feature",
  "properties": {
    "gn:admin1_code":"27.0",
    "gn:admin2_code":"3518800.0",
    "gn:asciiname":"Bairro Jardim Cambara",
    "gn:country_code":"BR",
    "gn:dem":767,
    "gn:feature_class":"P",
    "gn:feature_code":"PPL",
    "gn:name":"Bairro Jardim Cambar\u00e1",
    "gn:population":0,
    "gn:timezone":"America/Sao_Paulo",
    "iso:country":"BR",
    "name:por_x_preferred":[
        "Bairro Jardim Cambar\u00e1"
    ],
    "wof:name":"Bairro Jardim Cambara",
    "wof:placetype":"locality"
},
  "geometry": {"coordinates":[-46.55521,-23.41985],"type":"Point"}
}