{
  "type": "Feature",
  "properties": {
    "gn:admin1_code":"27",
    "gn:admin2_code":"3513009.0",
    "gn:asciiname":"Brotas",
    "gn:country_code":"BR",
    "gn:dem":988,
    "gn:feature_class":"P",
    "gn:feature_code":"PPLL",
    "gn:name":"Brotas",
    "gn:population":0,
    "gn:timezone":"America/Sao_Paulo",
    "iso:country":"BR",
    "name:bpy_x_preferred":[
        "\u09ac\u09cd\u09b0\u09cb\u099f\u09be\u09b8"
    ],
    "name:ceb_x_preferred":[
        "Brotas"
    ],
    "name:epo_x_preferred":[
        "Brotas"
    ],
    "name:eus_x_preferred":[
        "Brotas"
    ],
    "name:fra_x_preferred":[
        "Brotas"
    ],
    "name:ita_x_preferred":[
        "Brotas"
    ],
    "name:kaz_x_preferred":[
        "\u0411\u0440\u043e\u0442\u0430\u0441"
    ],
    "name:mlg_x_preferred":[
        "Brotas"
    ],
    "name:nld_x_preferred":[
        "Brotas"
    ],
    "name:nor_x_preferred":[
        "Brotas"
    ],
    "name:pol_x_preferred":[
        "Brotas"
    ],
    "name:por_x_preferred":[
        "Brotas"
    ],
    "name:ron_x_preferred":[
        "Brotas"
    ],
    "name:rus_x_preferred":[
        "\u0411\u0440\u043e\u0442\u0430\u0441"
    ],
    "name:spa_x_preferred":[
        "Brotas"
    ],
    "name:swe_x_preferred":[
        "Brotas"
    ],
    "name:vie_x_preferred":[
        "Brotas"
    ],
    "name:vol_x_preferred":[
        "Brotas"
    ],
    "name:war_x_preferred":[
        "Brotas"
    ],
    "name:zho_x_preferred":[
        "\u5e03\u7f57\u5854\u65af"
    ],
    "wof:name":"Brotas",
    "wof:placetype":"locality"
},
  "geometry": {"coordinates":[-47.02914000000001,-23.70326],"type":"Point"}
}