{
  "type": "Feature",
  "properties": {
    "gn:admin1_code":"27",
    "gn:admin2_code":"3513009.0",
    "gn:asciiname":"Brotas",
    "gn:country_code":"BR",
    "gn:dem":988,
    "gn:feature_class":"P",
    "gn:feature_code":"PPLL",
    "gn:name":"Brotas",
    "gn:population":0,
    "gn:timezone":"America/Sao_Paulo",
    "iso:country":"BR",
    "name:por_x_preferred":[
        "Brotas"
    ],
    "wof:name":"Brotas",
    "wof:placetype":"locality"
},
  "geometry": {"coordinates":[-47.02914000000001,-23.70326],"type":"Point"}
}