{
  "type": "Feature",
  "properties": {
    "gn:admin1_code":"26",
    "gn:admin2_code":"4205902.0",
    "gn:asciiname":"Bateia",
    "gn:cc2":"BR",
    "gn:country_code":"BR",
    "gn:dem":70,
    "gn:feature_class":"P",
    "gn:feature_code":"PPL",
    "gn:name":"Bateia",
    "gn:population":0,
    "gn:timezone":"America/Sao_Paulo",
    "iso:country":"BR",
    "name:und_x_variant":[
        "Bat\u00e9ia do Barrac\u00e3o",
        "Bateia"
    ],
    "wof:name":"Bateia",
    "wof:placetype":"locality"
},
  "geometry": {"coordinates":[-48.91667,-26.96667],"type":"Point"}
}