{
  "type": "Feature",
  "properties": {
    "gn:admin1_code":"26.0",
    "gn:admin2_code":"4210100.0",
    "gn:asciiname":"Sitio Olimpio Radoll",
    "gn:country_code":"BR",
    "gn:dem":795,
    "gn:feature_class":"P",
    "gn:feature_code":"PPL",
    "gn:name":"S\u00edtio Olimpio Radoll",
    "gn:population":0,
    "gn:timezone":"America/Sao_Paulo",
    "iso:country":"BR",
    "name:por_x_preferred":[
        "S\u00edtio Olimpio Radoll"
    ],
    "wof:name":"Sitio Olimpio Radoll",
    "wof:placetype":"locality"
},
  "geometry": {"coordinates":[-49.9238,-26.0633],"type":"Point"}
}