{
  "type": "Feature",
  "properties": {
    "iso:country":"BR",
    "name:bre_x_preferred":[
        "S\u00e3o Francisco"
    ],
    "name:ceb_x_preferred":[
        "S\u00e3o Francisco"
    ],
    "name:deu_x_preferred":[
        "S\u00e3o Francisco"
    ],
    "name:fra_x_preferred":[
        "S\u00e3o Francisco"
    ],
    "name:hrv_x_preferred":[
        "S\u00e3o Francisco"
    ],
    "name:ita_x_preferred":[
        "S\u00e3o Francisco"
    ],
    "name:mlg_x_preferred":[
        "S\u00e3o Francisco"
    ],
    "name:nld_x_preferred":[
        "S\u00e3o Francisco"
    ],
    "name:nor_x_preferred":[
        "S\u00e3o Francisco"
    ],
    "name:pol_x_preferred":[
        "S\u00e3o Francisco"
    ],
    "name:por_x_colloquial":[
        "Sao Francisco"
    ],
    "name:por_x_preferred":[
        "S\u00e3o Francisco"
    ],
    "name:rus_x_preferred":[
        "\u0421\u0430\u043d-\u0424\u0440\u0430\u043d\u0441\u0438\u0441\u043a\u0443"
    ],
    "name:sco_x_preferred":[
        "S\u00e3o Francisco"
    ],
    "name:spa_x_preferred":[
        "S\u00e3o Francisco"
    ],
    "name:swe_x_preferred":[
        "S\u00e3o Francisco"
    ],
    "name:und_x_variant":[
        "Fazenda S\u00e3o Francisco"
    ],
    "name:vie_x_preferred":[
        "S\u00e3o Francisco"
    ],
    "name:vol_x_preferred":[
        "S\u00e3o Francisco"
    ],
    "qs:gn_adm0_cc":"BR",
    "qs:gn_fcode":"PPL",
    "qs:gn_local":3467747,
    "qs:gn_namadm1":"11",
    "qs:gn_name":"S\u00e3o Francisco",
    "qs:local_max":946,
    "qs:local_sum":2816,
    "qs:localhoods":12,
    "qs:name":"S\u00e3o Francisco",
    "qs:name_adm0":"Brasil",
    "qs:name_adm1":"Mato Grosso do Sul",
    "qs:name_adm2":"Campo Grande",
    "qs:name_local":"Campo Grande",
    "qs:photo_max":16,
    "qs:photo_sum":39,
    "qs:placetype":"Suburb",
    "qs:quad_count":5,
    "qs:woe_adm0":23424768,
    "qs:woe_adm1":2344853,
    "qs:woe_adm2":12579121,
    "qs:woe_lau":0,
    "qs:woe_local":455849,
    "qs:woe_ver":"7.10.0",
    "wof:lang":[
        "por"
    ],
    "wof:name":"S\u00e3o Francisco",
    "wof:placetype":"neighbourhood"
},
  "geometry": {"coordinates":[-54.624502,-20.442232],"type":"Point"}
}