{
  "type": "Feature",
  "properties": {
    "gn:admin1_code":"5",
    "gn:admin2_code":"2927408.0",
    "gn:asciiname":"Ondina",
    "gn:country_code":"BR",
    "gn:dem":14,
    "gn:feature_class":"P",
    "gn:feature_code":"PPL",
    "gn:name":"Ondina",
    "gn:population":0,
    "gn:timezone":"America/Bahia",
    "iso:country":"BR",
    "wof:name":"Ondina",
    "wof:placetype":"locality"
},
  "geometry": {"coordinates":[-38.50833,-13.00333],"type":"Point"}
}