{
  "type": "Feature",
  "properties": {
    "gn:admin1_code":"18.0",
    "gn:admin2_code":"4111704.0",
    "gn:asciiname":"Sitio Pedro Josino",
    "gn:country_code":"BR",
    "gn:dem":529,
    "gn:feature_class":"P",
    "gn:feature_code":"PPL",
    "gn:name":"S\u00edtio Pedro Josino",
    "gn:population":0,
    "gn:timezone":"America/Sao_Paulo",
    "iso:country":"BR",
    "name:por_x_preferred":[
        "S\u00edtio Pedro Josino"
    ],
    "wof:name":"Sitio Pedro Josino",
    "wof:placetype":"locality"
},
  "geometry": {"coordinates":[-50.1101,-23.72741],"type":"Point"}
}