{
  "type": "Feature",
  "properties": {
    "gn:admin1_code":"18.0",
    "gn:admin2_code":"4103602.0",
    "gn:asciiname":"Agua dos Coqueiros",
    "gn:country_code":"BR",
    "gn:dem":443,
    "gn:feature_class":"P",
    "gn:feature_code":"PPL",
    "gn:name":"\u00c1gua dos Coqueiros",
    "gn:population":0,
    "gn:timezone":"America/Sao_Paulo",
    "iso:country":"BR",
    "name:por_x_preferred":[
        "\u00c1gua dos Coqueiros"
    ],
    "wof:name":"Agua dos Coqueiros",
    "wof:placetype":"locality"
},
  "geometry": {"coordinates":[-50.1315,-23.0271],"type":"Point"}
}