{
  "type": "Feature",
  "properties": {
    "gn:admin1_code":"22",
    "gn:admin2_code":"2413359.0",
    "gn:asciiname":"Raimundo Agostinho",
    "gn:country_code":"BR",
    "gn:dem":202,
    "gn:feature_class":"P",
    "gn:feature_code":"PPL",
    "gn:name":"Raimundo Agostinho",
    "gn:population":0,
    "gn:timezone":"America/Fortaleza",
    "iso:country":"BR",
    "wof:name":"Raimundo Agostinho",
    "wof:placetype":"locality"
},
  "geometry": {"coordinates":[-37.08694000000001,-5.1625],"type":"Point"}
}