{
  "type": "Feature",
  "properties": {
    "gn:admin1_code":"6",
    "gn:admin2_code":"2306702.0",
    "gn:asciiname":"Barbatao",
    "gn:country_code":"BR",
    "gn:dem":140,
    "gn:feature_class":"P",
    "gn:feature_code":"PPL",
    "gn:name":"Barbat\u00e3o",
    "gn:population":0,
    "gn:timezone":"America/Fortaleza",
    "iso:country":"BR",
    "wof:name":"Barbatao",
    "wof:placetype":"locality"
},
  "geometry": {"coordinates":[-38.61667,-5.36667],"type":"Point"}
}