{
  "type": "Feature",
  "properties": {
    "gn:admin1_code":"4",
    "gn:admin2_code":"1302405.0",
    "gn:asciiname":"Fazenda Sao Jose",
    "gn:country_code":"BR",
    "gn:dem":131,
    "gn:feature_class":"P",
    "gn:feature_code":"PPL",
    "gn:name":"Fazenda S\u00e3o Jos\u00e9",
    "gn:population":0,
    "gn:timezone":"America/Manaus",
    "iso:country":"BR",
    "wof:name":"Fazenda Sao Jose",
    "wof:placetype":"locality"
},
  "geometry": {"coordinates":[-67.03333000000001,-9.25],"type":"Point"}
}