{
  "type": "Feature",
  "properties": {
    "gn:admin1_code":"20",
    "gn:admin2_code":"2207801.0",
    "gn:asciiname":"Barrinha",
    "gn:country_code":"BR",
    "gn:dem":375,
    "gn:feature_class":"P",
    "gn:feature_code":"PPL",
    "gn:name":"Barrinha",
    "gn:population":0,
    "gn:timezone":"America/Fortaleza",
    "iso:country":"BR",
    "wof:name":"Barrinha",
    "wof:placetype":"locality"
},
  "geometry": {"coordinates":[-41.01667,-7.91667],"type":"Point"}
}