{
  "type": "Feature",
  "properties": {
    "gn:admin1_code":"20",
    "gn:admin2_code":"2207801.0",
    "gn:asciiname":"Barrinha",
    "gn:country_code":"BR",
    "gn:dem":375,
    "gn:feature_class":"P",
    "gn:feature_code":"PPL",
    "gn:name":"Barrinha",
    "gn:population":0,
    "gn:timezone":"America/Fortaleza",
    "iso:country":"BR",
    "name:bpy_x_preferred":[
        "\u09ac\u09be\u09b0\u09cd\u09b0\u09bf\u09a8\u09b9\u09be"
    ],
    "name:ceb_x_preferred":[
        "Barrinha"
    ],
    "name:epo_x_preferred":[
        "Barrinha"
    ],
    "name:eus_x_preferred":[
        "Barrinha"
    ],
    "name:fra_x_preferred":[
        "Barrinha"
    ],
    "name:ita_x_preferred":[
        "Barrinha"
    ],
    "name:kaz_x_preferred":[
        "\u0411\u0430\u0440\u0440\u0438\u043d\u044c\u044f"
    ],
    "name:mlg_x_preferred":[
        "Barrinha"
    ],
    "name:nld_x_preferred":[
        "Barrinha"
    ],
    "name:nor_x_preferred":[
        "Barrinha"
    ],
    "name:pol_x_preferred":[
        "Barrinha"
    ],
    "name:por_x_preferred":[
        "Barrinha"
    ],
    "name:ron_x_preferred":[
        "Barrinha"
    ],
    "name:rus_x_preferred":[
        "\u0411\u0430\u0440\u0440\u0438\u043d\u044c\u044f"
    ],
    "name:sco_x_preferred":[
        "Barrinha"
    ],
    "name:spa_x_preferred":[
        "Barrinha"
    ],
    "name:swe_x_preferred":[
        "Barrinha"
    ],
    "name:vie_x_preferred":[
        "Barrinha"
    ],
    "name:vol_x_preferred":[
        "Barrinha"
    ],
    "name:war_x_preferred":[
        "Barrinha"
    ],
    "name:zho_x_preferred":[
        "\u5df4\u91cc\u5c3c\u4e9a"
    ],
    "wof:name":"Barrinha",
    "wof:placetype":"locality"
},
  "geometry": {"coordinates":[-41.01667,-7.91667],"type":"Point"}
}