{
  "type": "Feature",
  "properties": {
    "gn:admin1_code":"30",
    "gn:admin2_code":"2601201.0",
    "gn:asciiname":"Mutuca",
    "gn:country_code":"BR",
    "gn:dem":845,
    "gn:feature_class":"P",
    "gn:feature_code":"PPL",
    "gn:name":"Mutuca",
    "gn:population":0,
    "gn:timezone":"America/Recife",
    "iso:country":"BR",
    "wof:name":"Mutuca",
    "wof:placetype":"locality"
},
  "geometry": {"coordinates":[-36.98333,-8.43333],"type":"Point"}
}