{
  "type": "Feature",
  "properties": {
    "gn:admin1_code":"18.0",
    "gn:admin2_code":"4126207.0",
    "gn:asciiname":"Sitio das Pedras",
    "gn:country_code":"BR",
    "gn:dem":603,
    "gn:feature_class":"P",
    "gn:feature_code":"PPL",
    "gn:name":"S\u00edtio das Pedras",
    "gn:population":0,
    "gn:timezone":"America/Sao_Paulo",
    "iso:country":"BR",
    "name:por_x_preferred":[
        "S\u00edtio das Pedras"
    ],
    "wof:name":"Sitio das Pedras",
    "wof:placetype":"locality"
},
  "geometry": {"coordinates":[-50.50713,-23.79918],"type":"Point"}
}