{
  "type": "Feature",
  "properties": {
    "gn:admin1_code":"17",
    "gn:admin2_code":"2511004.0",
    "gn:asciiname":"Poco do Cachorro",
    "gn:country_code":"BR",
    "gn:dem":366,
    "gn:feature_class":"P",
    "gn:feature_code":"PPL",
    "gn:name":"Po\u00e7o do Cachorro",
    "gn:population":0,
    "gn:timezone":"America/Fortaleza",
    "iso:country":"BR",
    "wof:name":"Poco do Cachorro",
    "wof:placetype":"locality"
},
  "geometry": {"coordinates":[-38.05,-7.51667],"type":"Point"}
}