{
  "type": "Feature",
  "properties": {
    "gn:admin1_code":"06",
    "gn:admin2_code":"2311405.0",
    "gn:asciiname":"Campinas",
    "gn:country_code":"BR",
    "gn:dem":183,
    "gn:feature_class":"P",
    "gn:feature_code":"PPL",
    "gn:name":"Campinas",
    "gn:population":0,
    "gn:timezone":"America/Fortaleza",
    "iso:country":"BR",
    "wof:name":"Campinas",
    "wof:placetype":"locality"
},
  "geometry": {"coordinates":[-39.08333,-5.18333],"type":"Point"}
}