{
  "type": "Feature",
  "properties": {
    "gn:admin1_code":"06",
    "gn:admin2_code":"2307809.0",
    "gn:asciiname":"Carauba",
    "gn:country_code":"BR",
    "gn:dem":55,
    "gn:feature_class":"P",
    "gn:feature_code":"PPL",
    "gn:name":"Cara\u00faba",
    "gn:population":0,
    "gn:timezone":"America/Fortaleza",
    "iso:country":"BR",
    "wof:name":"Carauba",
    "wof:placetype":"locality"
},
  "geometry": {"coordinates":[-40.46667,-3.11667],"type":"Point"}
}