{
  "type": "Feature",
  "properties": {
    "gn:admin1_code":"18.0",
    "gn:admin2_code":"4106209.0",
    "gn:asciiname":"Sitio Luiz Vonzovisk",
    "gn:country_code":"BR",
    "gn:dem":864,
    "gn:feature_class":"P",
    "gn:feature_code":"PPL",
    "gn:name":"S\u00edtio Luiz Vonzovisk",
    "gn:population":0,
    "gn:timezone":"America/Sao_Paulo",
    "iso:country":"BR",
    "name:por_x_preferred":[
        "S\u00edtio Luiz Vonzovisk"
    ],
    "wof:name":"Sitio Luiz Vonzovisk",
    "wof:placetype":"locality"
},
  "geometry": {"coordinates":[-49.4624,-25.7767],"type":"Point"}
}