{
  "type": "Feature",
  "properties": {
    "gn:admin1_code":"18.0",
    "gn:admin2_code":"4124707.0",
    "gn:asciiname":"Sitio Osvaldo Nigri",
    "gn:country_code":"BR",
    "gn:dem":904,
    "gn:feature_class":"P",
    "gn:feature_code":"PPL",
    "gn:name":"S\u00edtio Osvaldo Nigri",
    "gn:population":0,
    "gn:timezone":"America/Sao_Paulo",
    "iso:country":"BR",
    "name:por_x_preferred":[
        "S\u00edtio Osvaldo Nigri"
    ],
    "wof:name":"Sitio Osvaldo Nigri",
    "wof:placetype":"locality"
},
  "geometry": {"coordinates":[-50.81737,-23.80061],"type":"Point"}
}