{
  "type": "Feature",
  "properties": {
    "gn:admin1_code":"20",
    "gn:admin2_code":"2201903.0",
    "gn:asciiname":"Tabocas",
    "gn:country_code":"BR",
    "gn:dem":707,
    "gn:feature_class":"P",
    "gn:feature_code":"PPL",
    "gn:name":"Tabocas",
    "gn:population":0,
    "gn:timezone":"America/Bahia",
    "iso:country":"BR",
    "wof:name":"Tabocas",
    "wof:placetype":"locality"
},
  "geometry": {"coordinates":[-43.81667,-9.45],"type":"Point"}
}