{
  "type": "Feature",
  "properties": {
    "gn:admin1_code":"13",
    "gn:admin2_code":"2105906.0",
    "gn:asciiname":"Tajatuba",
    "gn:country_code":"BR",
    "gn:dem":6,
    "gn:feature_class":"P",
    "gn:feature_code":"PPL",
    "gn:name":"Tajatuba",
    "gn:population":0,
    "gn:timezone":"America/Fortaleza",
    "iso:country":"BR",
    "wof:name":"Tajatuba",
    "wof:placetype":"locality"
},
  "geometry": {"coordinates":[-44.93333,-3.91667],"type":"Point"}
}