{
  "type": "Feature",
  "properties": {
    "gn:admin1_code":"15",
    "gn:admin2_code":"3105103.0",
    "gn:asciiname":"Paulino",
    "gn:country_code":"BR",
    "gn:dem":738,
    "gn:feature_class":"P",
    "gn:feature_code":"PPL",
    "gn:name":"Paulino",
    "gn:population":0,
    "gn:timezone":"America/Sao_Paulo",
    "iso:country":"BR",
    "name:deu_x_preferred":[
        "Paulino"
    ],
    "name:por_x_preferred":[
        "Paulino"
    ],
    "wof:name":"Paulino",
    "wof:placetype":"locality"
},
  "geometry": {"coordinates":[-46.06667,-20.23333],"type":"Point"}
}