{
  "type": "Feature",
  "properties": {
    "gn:admin1_code":"13",
    "gn:admin2_code":"2105922.0",
    "gn:asciiname":"Fonte Rica",
    "gn:country_code":"BR",
    "gn:dem":270,
    "gn:feature_class":"P",
    "gn:feature_code":"PPL",
    "gn:name":"Fonte Rica",
    "gn:population":0,
    "gn:timezone":"America/Fortaleza",
    "iso:country":"BR",
    "wof:name":"Fonte Rica",
    "wof:placetype":"locality"
},
  "geometry": {"coordinates":[-43.35,-5.96667],"type":"Point"}
}