{
  "type": "Feature",
  "properties": {
    "gn:admin1_code":"27",
    "gn:admin2_code":"3518404.0",
    "gn:asciiname":"Vila Molica",
    "gn:country_code":"BR",
    "gn:dem":537,
    "gn:elevation":"0.0",
    "gn:feature_class":"P",
    "gn:feature_code":"PPL",
    "gn:name":"Vila Molica",
    "gn:population":0,
    "gn:timezone":"America/Sao_Paulo",
    "iso:country":"BR",
    "name:por_x_preferred":[
        "Vila Molica"
    ],
    "wof:name":"Vila Molica",
    "wof:placetype":"locality"
},
  "geometry": {"coordinates":[-45.20816,-22.79437],"type":"Point"}
}