{
  "type": "Feature",
  "properties": {
    "gn:admin1_code":"20",
    "gn:admin2_code":"2206696.0",
    "gn:asciiname":"Belo Hurizonte",
    "gn:country_code":"BR",
    "gn:dem":60,
    "gn:feature_class":"P",
    "gn:feature_code":"PPL",
    "gn:name":"Belo Hurizonte",
    "gn:population":0,
    "gn:timezone":"America/Fortaleza",
    "iso:country":"BR",
    "wof:name":"Belo Hurizonte",
    "wof:placetype":"locality"
},
  "geometry": {"coordinates":[-42.03556,-3.37417],"type":"Point"}
}