{
  "type": "Feature",
  "properties": {
    "gn:admin1_code":"18.0",
    "gn:admin2_code":"4109708.0",
    "gn:asciiname":"Sitio Aparecido Abaete",
    "gn:country_code":"BR",
    "gn:dem":685,
    "gn:feature_class":"P",
    "gn:feature_code":"PPL",
    "gn:name":"S\u00edtio Aparecido Abaet\u00e9",
    "gn:population":0,
    "gn:timezone":"America/Sao_Paulo",
    "iso:country":"BR",
    "name:por_x_preferred":[
        "S\u00edtio Aparecido Abaet\u00e9"
    ],
    "wof:name":"Sitio Aparecido Abaete",
    "wof:placetype":"locality"
},
  "geometry": {"coordinates":[-50.2808,-23.9108],"type":"Point"}
}