{
  "type": "Feature",
  "properties": {
    "gn:admin1_code":"21",
    "gn:admin2_code":"3300605.0",
    "gn:asciiname":"Cachoeira Alegre",
    "gn:country_code":"BR",
    "gn:dem":99,
    "gn:feature_class":"P",
    "gn:feature_code":"PPL",
    "gn:name":"Cachoeira Alegre",
    "gn:population":0,
    "gn:timezone":"America/Sao_Paulo",
    "iso:country":"BR",
    "name:por_x_preferred":[
        "Cachoeira Alegre"
    ],
    "wof:name":"Cachoeira Alegre",
    "wof:placetype":"locality"
},
  "geometry": {"coordinates":[-41.51667,-21.25],"type":"Point"}
}