{
  "type": "Feature",
  "properties": {
    "gn:admin1_code":"22",
    "gn:admin2_code":"2400703.0",
    "gn:asciiname":"Estreito",
    "gn:country_code":"BR",
    "gn:dem":23,
    "gn:feature_class":"P",
    "gn:feature_code":"PPL",
    "gn:name":"Estreito",
    "gn:population":0,
    "gn:timezone":"America/Fortaleza",
    "iso:country":"BR",
    "wof:name":"Estreito",
    "wof:placetype":"locality"
},
  "geometry": {"coordinates":[-36.80444,-5.35417],"type":"Point"}
}