{
  "type": "Feature",
  "properties": {
    "gn:admin1_code":"17",
    "gn:admin2_code":"2504850.0",
    "gn:asciiname":"Sao Joazinho",
    "gn:country_code":"BR",
    "gn:dem":496,
    "gn:feature_class":"P",
    "gn:feature_code":"PPL",
    "gn:name":"S\u00e3o Jo\u00e3zinho",
    "gn:population":0,
    "gn:timezone":"America/Fortaleza",
    "iso:country":"BR",
    "wof:name":"Sao Joazinho",
    "wof:placetype":"locality"
},
  "geometry": {"coordinates":[-36.61667,-7.68333],"type":"Point"}
}