{
  "type": "Feature",
  "properties": {
    "gn:admin1_code":"02",
    "gn:admin2_code":"2703304.0",
    "gn:asciiname":"Curralinho",
    "gn:country_code":"BR",
    "gn:dem":408,
    "gn:feature_class":"P",
    "gn:feature_code":"PPL",
    "gn:name":"Curralinho",
    "gn:population":0,
    "gn:timezone":"America/Maceio",
    "iso:country":"BR",
    "wof:name":"Curralinho",
    "wof:placetype":"locality"
},
  "geometry": {"coordinates":[-37.78333,-9.26667],"type":"Point"}
}