{
  "type": "Feature",
  "properties": {
    "gn:admin1_code":"1",
    "gn:admin2_code":"1200351.0",
    "gn:asciiname":"Restauracao",
    "gn:country_code":"BR",
    "gn:dem":303,
    "gn:feature_class":"P",
    "gn:feature_code":"PPL",
    "gn:name":"Restaura\u00e7\u00e3o",
    "gn:population":0,
    "gn:timezone":"America/Rio_Branco",
    "iso:country":"BR",
    "wof:name":"Restauracao",
    "wof:placetype":"locality"
},
  "geometry": {"coordinates":[-72.23333000000002,-9.21667],"type":"Point"}
}