{
  "type": "Feature",
  "properties": {
    "gn:admin1_code":"23.0",
    "gn:admin2_code":"4301305.0",
    "gn:asciiname":"Campo de Pouso",
    "gn:country_code":"BR",
    "gn:dem":9,
    "gn:feature_class":"P",
    "gn:feature_code":"PPL",
    "gn:name":"Campo de Pouso",
    "gn:population":0,
    "gn:timezone":"America/Sao_Paulo",
    "iso:country":"BR",
    "name:por_x_preferred":[
        "Campo de Pouso"
    ],
    "wof:name":"Campo de Pouso",
    "wof:placetype":"locality"
},
  "geometry": {"coordinates":[-52.606,-32.0995],"type":"Point"}
}