{
  "type": "Feature",
  "properties": {
    "gn:admin1_code":"24",
    "gn:admin2_code":"1101500.0",
    "gn:asciiname":"Porto Bicentenario",
    "gn:country_code":"BR",
    "gn:dem":189,
    "gn:feature_class":"P",
    "gn:feature_code":"PPL",
    "gn:name":"P\u00f4rto Bicenten\u00e1rio",
    "gn:population":0,
    "gn:timezone":"America/Porto_Velho",
    "iso:country":"BR",
    "name:und_x_variant":[
        "P\u00f4rto Bicenten\u00e1rio",
        "Porto Bicenten\u00e1rio"
    ],
    "wof:name":"Porto Bicentenario",
    "wof:placetype":"locality"
},
  "geometry": {"coordinates":[-63.24149,-11.70838],"type":"Point"}
}