{
  "type": "Feature",
  "properties": {
    "gn:admin1_code":"18.0",
    "gn:admin2_code":"4111704.0",
    "gn:asciiname":"Sitio Vicente Mendes Morais",
    "gn:country_code":"BR",
    "gn:dem":515,
    "gn:feature_class":"P",
    "gn:feature_code":"PPL",
    "gn:name":"S\u00edtio Vicente Mendes Morais",
    "gn:population":0,
    "gn:timezone":"America/Sao_Paulo",
    "iso:country":"BR",
    "name:por_x_preferred":[
        "S\u00edtio Vicente Mendes Morais"
    ],
    "wof:name":"Sitio Vicente Mendes Morais",
    "wof:placetype":"locality"
},
  "geometry": {"coordinates":[-50.10365,-23.68714],"type":"Point"}
}