{
  "type": "Feature",
  "properties": {
    "gn:admin1_code":"13",
    "gn:admin2_code":"2100501.0",
    "gn:asciiname":"Mata Dentro",
    "gn:cc2":"BR",
    "gn:country_code":"BR",
    "gn:dem":516,
    "gn:feature_class":"P",
    "gn:feature_code":"PPL",
    "gn:name":"Mata Dentro",
    "gn:population":0,
    "gn:timezone":"America/Fortaleza",
    "iso:country":"BR",
    "name:und_x_variant":[
        "Matos Dentro",
        "Mata Dentro"
    ],
    "wof:name":"Mata Dentro",
    "wof:placetype":"locality"
},
  "geometry": {"coordinates":[-46.58333,-9.31667],"type":"Point"}
}