{
  "type": "Feature",
  "properties": {
    "gn:admin1_code":"5",
    "gn:admin2_code":"2923407.0",
    "gn:asciiname":"Boqueiraozinho",
    "gn:country_code":"BR",
    "gn:dem":533,
    "gn:feature_class":"P",
    "gn:feature_code":"PPL",
    "gn:name":"Boqueir\u00e3ozinho",
    "gn:population":0,
    "gn:timezone":"America/Bahia",
    "iso:country":"BR",
    "wof:name":"Boqueiraozinho",
    "wof:placetype":"locality"
},
  "geometry": {"coordinates":[-43.16667,-14.33333],"type":"Point"}
}