{
  "type": "Feature",
  "properties": {
    "gn:admin1_code":"20",
    "gn:admin2_code":"2208007.0",
    "gn:asciiname":"Boqueirao (1)",
    "gn:country_code":"BR",
    "gn:dem":280,
    "gn:feature_class":"P",
    "gn:feature_code":"PPL",
    "gn:name":"Boqueir\u00e3o (1)",
    "gn:population":0,
    "gn:timezone":"America/Fortaleza",
    "iso:country":"BR",
    "wof:name":"Boqueirao (1)",
    "wof:placetype":"locality"
},
  "geometry": {"coordinates":[-41.56667,-7.13333],"type":"Point"}
}