{
  "type": "Feature",
  "properties": {
    "gn:admin1_code":"4",
    "gn:admin2_code":"1304104.0",
    "gn:asciiname":"Macuripari",
    "gn:cc2":"BR",
    "gn:country_code":"BR",
    "gn:dem":45,
    "gn:feature_class":"P",
    "gn:feature_code":"PPL",
    "gn:name":"Macuripari",
    "gn:population":0,
    "gn:timezone":"America/Manaus",
    "iso:country":"BR",
    "name:und_x_variant":[
        "Macuripary",
        "Macuripari"
    ],
    "wof:name":"Macuripari",
    "wof:placetype":"locality"
},
  "geometry": {"coordinates":[-63.97833000000001,-5.56944],"type":"Point"}
}