{
  "type": "Feature",
  "properties": {
    "gn:admin1_code":"11",
    "gn:admin2_code":"5001243.0",
    "gn:asciiname":"Cerro Alegre",
    "gn:country_code":"BR",
    "gn:dem":621,
    "gn:feature_class":"P",
    "gn:feature_code":"PPL",
    "gn:name":"C\u00earro Alegre",
    "gn:population":0,
    "gn:timezone":"America/Campo_Grande",
    "iso:country":"BR",
    "wof:name":"Cerro Alegre",
    "wof:placetype":"locality"
},
  "geometry": {"coordinates":[-55.61666999999999,-22.88333],"type":"Point"}
}