{
  "type": "Feature",
  "properties": {
    "gn:admin1_code":"18",
    "gn:admin2_code":"4110508.0",
    "gn:asciiname":"Avenca",
    "gn:country_code":"BR",
    "gn:dem":795,
    "gn:feature_class":"P",
    "gn:feature_code":"PPL",
    "gn:name":"Avenca",
    "gn:population":0,
    "gn:timezone":"America/Sao_Paulo",
    "iso:country":"BR",
    "wof:name":"Avenca",
    "wof:placetype":"locality"
},
  "geometry": {"coordinates":[-50.63333,-24.98333],"type":"Point"}
}