{
  "type": "Feature",
  "properties": {
    "gn:admin1_code":"16",
    "gn:admin2_code":"1503606.0",
    "gn:asciiname":"Bonfim",
    "gn:country_code":"BR",
    "gn:dem":74,
    "gn:feature_class":"P",
    "gn:feature_code":"PPL",
    "gn:name":"Bonfim",
    "gn:population":0,
    "gn:timezone":"America/Santarem",
    "iso:country":"BR",
    "wof:name":"Bonfim",
    "wof:placetype":"locality"
},
  "geometry": {"coordinates":[-56.51667,-4.76667],"type":"Point"}
}