{
  "type": "Feature",
  "properties": {
    "gn:admin1_code":"16",
    "gn:admin2_code":"1503606.0",
    "gn:asciiname":"Bonfim",
    "gn:country_code":"BR",
    "gn:dem":74,
    "gn:feature_class":"P",
    "gn:feature_code":"PPL",
    "gn:name":"Bonfim",
    "gn:population":0,
    "gn:timezone":"America/Santarem",
    "iso:country":"BR",
    "name:bpy_x_preferred":[
        "\u09ac\u09cb\u09a8\u09ab\u09bf\u09ae"
    ],
    "name:bre_x_preferred":[
        "Bonfim"
    ],
    "name:ceb_x_preferred":[
        "Bonfim"
    ],
    "name:deu_x_preferred":[
        "Bonfim"
    ],
    "name:fra_x_preferred":[
        "Bonfim"
    ],
    "name:ita_x_preferred":[
        "Bonfim"
    ],
    "name:nld_x_preferred":[
        "Bonfim"
    ],
    "name:nor_x_preferred":[
        "Bonfim"
    ],
    "name:pol_x_preferred":[
        "Bonfim"
    ],
    "name:por_x_preferred":[
        "Bonfim"
    ],
    "name:sco_x_preferred":[
        "Bonfim"
    ],
    "name:spa_x_preferred":[
        "Bonfim"
    ],
    "name:swe_x_preferred":[
        "Bonfim"
    ],
    "name:vol_x_preferred":[
        "Bonfim"
    ],
    "name:war_x_preferred":[
        "Bonfim"
    ],
    "wof:name":"Bonfim",
    "wof:placetype":"locality"
},
  "geometry": {"coordinates":[-56.51667,-4.76667],"type":"Point"}
}