{
  "type": "Feature",
  "properties": {
    "gn:admin1_code":"5",
    "gn:admin2_code":"2907202.0",
    "gn:asciiname":"Casa Nova",
    "gn:country_code":"BR",
    "gn:dem":406,
    "gn:feature_class":"P",
    "gn:feature_code":"PPL",
    "gn:name":"Casa Nova",
    "gn:population":0,
    "gn:timezone":"America/Bahia",
    "iso:country":"BR",
    "wof:name":"Casa Nova",
    "wof:placetype":"locality"
},
  "geometry": {"coordinates":[-40.97083,-9.16194],"type":"Point"}
}