{
  "type": "Feature",
  "properties": {
    "gn:admin1_code":"27",
    "gn:admin2_code":"3509700.0",
    "gn:asciiname":"Sitio Sao Roque",
    "gn:country_code":"BR",
    "gn:dem":1345,
    "gn:feature_class":"P",
    "gn:feature_code":"PPL",
    "gn:name":"S\u00edtio S\u00e3o Roque",
    "gn:population":0,
    "gn:timezone":"America/Sao_Paulo",
    "iso:country":"BR",
    "name:por_x_preferred":[
        "S\u00edtio S\u00e3o Roque"
    ],
    "wof:name":"Sitio Sao Roque",
    "wof:placetype":"locality"
},
  "geometry": {"coordinates":[-45.5169,-22.6439],"type":"Point"}
}