{
  "type": "Feature",
  "properties": {
    "gn:admin1_code":"21.0",
    "gn:admin2_code":"3301009.0",
    "gn:asciiname":"Sao Eduardo",
    "gn:country_code":"BR",
    "gn:dem":58,
    "gn:feature_class":"P",
    "gn:feature_code":"PPL",
    "gn:name":"S\u00e3o Eduardo",
    "gn:population":0,
    "gn:timezone":"America/Sao_Paulo",
    "iso:country":"BR",
    "name:por_x_preferred":[
        "S\u00e3o Eduardo"
    ],
    "wof:name":"Sao Eduardo",
    "wof:placetype":"locality"
},
  "geometry": {"coordinates":[-41.46145,-21.22008],"type":"Point"}
}