{
  "type": "Feature",
  "properties": {
    "gn:admin1_code":"27.0",
    "gn:admin2_code":"3550308.0",
    "gn:asciiname":"Sitio da Vovo",
    "gn:country_code":"BR",
    "gn:dem":746,
    "gn:feature_class":"P",
    "gn:feature_code":"PPL",
    "gn:name":"S\u00edtio da Vov\u00f3",
    "gn:population":0,
    "gn:timezone":"America/Sao_Paulo",
    "iso:country":"BR",
    "name:por_x_preferred":[
        "S\u00edtio da Vov\u00f3"
    ],
    "wof:name":"Sitio da Vovo",
    "wof:placetype":"locality"
},
  "geometry": {"coordinates":[-46.73581,-23.38891],"type":"Point"}
}