{
  "type": "Feature",
  "properties": {
    "gn:admin1_code":"27",
    "gn:admin2_code":"3518305.0",
    "gn:asciiname":"Stio Tapera",
    "gn:country_code":"BR",
    "gn:dem":621,
    "gn:feature_class":"P",
    "gn:feature_code":"PPL",
    "gn:name":"Stio Tapera",
    "gn:population":0,
    "gn:timezone":"America/Sao_Paulo",
    "iso:country":"BR",
    "name:por_x_preferred":[
        "Stio Tapera"
    ],
    "wof:name":"Stio Tapera",
    "wof:placetype":"locality"
},
  "geometry": {"coordinates":[-46.0748,-23.3954],"type":"Point"}
}