{
  "type": "Feature",
  "properties": {
    "gn:admin1_code":"15",
    "gn:admin2_code":"3125200.0",
    "gn:asciiname":"Rocha",
    "gn:country_code":"BR",
    "gn:dem":824,
    "gn:feature_class":"P",
    "gn:feature_code":"PPL",
    "gn:name":"Rocha",
    "gn:population":0,
    "gn:timezone":"America/Sao_Paulo",
    "iso:country":"BR",
    "name:por_x_preferred":[
        "Rocha"
    ],
    "wof:name":"Rocha",
    "wof:placetype":"locality"
},
  "geometry": {"coordinates":[-45.81667,-21.46667],"type":"Point"}
}