{
  "type": "Feature",
  "properties": {
    "gn:admin1_code":"4",
    "gn:admin2_code":"1303908.0",
    "gn:asciiname":"Sao Jeronimo",
    "gn:cc2":"BR",
    "gn:country_code":"BR",
    "gn:dem":74,
    "gn:feature_class":"P",
    "gn:feature_code":"PPL",
    "gn:name":"S\u00e3o Jer\u00f4nimo",
    "gn:population":0,
    "gn:timezone":"America/Manaus",
    "iso:country":"BR",
    "name:und_x_variant":[
        "S\u00e3o Jeronymo",
        "S\u00e3o Jer\u00f4nimo"
    ],
    "wof:name":"Sao Jeronimo",
    "wof:placetype":"locality"
},
  "geometry": {"coordinates":[-69.41667,-3.61667],"type":"Point"}
}