{
  "type": "Feature",
  "properties": {
    "gn:admin1_code":"5",
    "gn:admin2_code":"2903235.0",
    "gn:asciiname":"Sanharo",
    "gn:country_code":"BR",
    "gn:dem":719,
    "gn:feature_class":"P",
    "gn:feature_code":"PPL",
    "gn:name":"Sanhar\u00f3",
    "gn:population":0,
    "gn:timezone":"America/Bahia",
    "iso:country":"BR",
    "wof:name":"Sanharo",
    "wof:placetype":"locality"
},
  "geometry": {"coordinates":[-42.01667,-11.81667],"type":"Point"}
}