{
  "type": "Feature",
  "properties": {
    "gn:admin1_code":"4",
    "gn:admin2_code":"1303809.0",
    "gn:asciiname":"Micui",
    "gn:country_code":"BR",
    "gn:dem":119,
    "gn:feature_class":"P",
    "gn:feature_code":"PPL",
    "gn:name":"Micui",
    "gn:population":0,
    "gn:timezone":"America/Manaus",
    "iso:country":"BR",
    "wof:name":"Micui",
    "wof:placetype":"locality"
},
  "geometry": {"coordinates":[-69.05,0.48333],"type":"Point"}
}