{
  "type": "Feature",
  "properties": {
    "gn:admin1_code":"4",
    "gn:admin2_code":"1300904.0",
    "gn:asciiname":"Alianca",
    "gn:cc2":"BR",
    "gn:country_code":"BR",
    "gn:dem":57,
    "gn:feature_class":"P",
    "gn:feature_code":"PPL",
    "gn:name":"Alian\u00e7a",
    "gn:population":0,
    "gn:timezone":"America/Manaus",
    "iso:country":"BR",
    "name:und_x_variant":[
        "Allian\u00e7a",
        "Alian\u00e7a"
    ],
    "wof:name":"Alianca",
    "wof:placetype":"locality"
},
  "geometry": {"coordinates":[-64.34999999999999,-6.58333],"type":"Point"}
}