{
  "type": "Feature",
  "properties": {
    "gn:admin1_code":"22",
    "gn:admin2_code":"2413557.0",
    "gn:asciiname":"Varginha",
    "gn:country_code":"BR",
    "gn:dem":479,
    "gn:feature_class":"P",
    "gn:feature_code":"PPL",
    "gn:name":"Varginha",
    "gn:population":0,
    "gn:timezone":"America/Fortaleza",
    "iso:country":"BR",
    "wof:name":"Varginha",
    "wof:placetype":"locality"
},
  "geometry": {"coordinates":[-37.98333,-6.15],"type":"Point"}
}