{
  "type": "Feature",
  "properties": {
    "gn:admin1_code":"22",
    "gn:admin2_code":"2403905.0",
    "gn:asciiname":"Tapuio",
    "gn:country_code":"BR",
    "gn:dem":245,
    "gn:feature_class":"P",
    "gn:feature_code":"PPL",
    "gn:name":"Tapuio",
    "gn:population":0,
    "gn:timezone":"America/Fortaleza",
    "iso:country":"BR",
    "wof:name":"Tapuio",
    "wof:placetype":"locality"
},
  "geometry": {"coordinates":[-38.08333,-6.11667],"type":"Point"}
}