{
  "type": "Feature",
  "properties": {
    "gn:admin1_code":"22",
    "gn:admin2_code":"2401305.0",
    "gn:asciiname":"Alto Grande",
    "gn:country_code":"BR",
    "gn:dem":119,
    "gn:feature_class":"P",
    "gn:feature_code":"PPL",
    "gn:name":"Alto Grande",
    "gn:population":0,
    "gn:timezone":"America/Fortaleza",
    "iso:country":"BR",
    "wof:name":"Alto Grande",
    "wof:placetype":"locality"
},
  "geometry": {"coordinates":[-37.25417,-5.86667],"type":"Point"}
}