{
  "type": "Feature",
  "properties": {
    "gn:country":"BR",
    "gn:fcode":"PPL",
    "gn:population":10385,
    "iso:country":"BR",
    "name:bpy_x_preferred":[
        "\u09a8\u09cb\u09ad\u09cb \u0995\u09cd\u09b0\u09c1\u099c\u09af\u09bc\u09c7\u0987\u09b0\u09cb"
    ],
    "name:ceb_x_preferred":[
        "Novo Cruzeiro"
    ],
    "name:deu_x_preferred":[
        "Novo Cruzeiro"
    ],
    "name:eng_x_preferred":[
        "Novo Cruzeiro"
    ],
    "name:epo_x_preferred":[
        "Novo Cruzeiro"
    ],
    "name:eus_x_preferred":[
        "Novo Cruzeiro"
    ],
    "name:fra_x_preferred":[
        "Novo Cruzeiro"
    ],
    "name:hun_x_preferred":[
        "Novo Cruzeiro"
    ],
    "name:ita_x_preferred":[
        "Novo Cruzeiro"
    ],
    "name:kat_x_preferred":[
        "\u10dc\u10dd\u10d5\u10e3-\u10d9\u10e0\u10e3\u10d6\u10d4\u10d8\u10e0\u10e3"
    ],
    "name:kaz_x_preferred":[
        "\u041d\u043e\u0432\u0443-\u041a\u0440\u0443\u0437\u0435\u0439\u0440\u0443"
    ],
    "name:mlg_x_preferred":[
        "Novo Cruzeiro"
    ],
    "name:nan_x_preferred":[
        "Novo Cruzeiro"
    ],
    "name:nld_x_preferred":[
        "Novo Cruzeiro"
    ],
    "name:nob_x_preferred":[
        "Novo Cruzeiro"
    ],
    "name:pol_x_preferred":[
        "Novo Cruzeiro"
    ],
    "name:por_x_preferred":[
        "Novo Cruzeiro"
    ],
    "name:ron_x_preferred":[
        "Novo Cruzeiro"
    ],
    "name:rus_x_preferred":[
        "\u041d\u043e\u0432\u0443-\u041a\u0440\u0443\u0437\u0435\u0439\u0440\u0443"
    ],
    "name:spa_x_preferred":[
        "Novo Cruzeiro"
    ],
    "name:swe_x_preferred":[
        "Novo Cruzeiro"
    ],
    "name:vie_x_preferred":[
        "Novo Cruzeiro"
    ],
    "name:vol_x_preferred":[
        "Novo Cruzeiro"
    ],
    "name:war_x_preferred":[
        "Novo Cruzeiro"
    ],
    "name:zho_x_preferred":[
        "\u65b0\u514b\u9c81\u8d5b\u7f57"
    ],
    "qs_pg:aaroncc":"BR",
    "qs_pg:gn_country":"BR",
    "qs_pg:gn_fcode":"PPL",
    "qs_pg:gn_pop":10385,
    "qs_pg:name":"Gravata",
    "qs_pg:name_adm0":"Brasil",
    "qs_pg:name_adm1":"Minas Gerais",
    "qs_pg:photos_9r":0,
    "qs_pg:photos_sr":0,
    "qs_pg:pop_sr":6,
    "qs_pg:qs_pg_placetype":"locality",
    "qs_pg:qs_pg_placetype_gp":"Town",
    "qs_pg:woe_adm0":23424768,
    "woe:adm0_id":23424768,
    "woe:name_adm0":"Brasil",
    "woe:name_adm1":"Minas Gerais",
    "woe:placetype":"Town",
    "wof:name":"Gravata",
    "wof:placetype":"locality",
    "wof:population":10385
},
  "geometry": {"coordinates":[-41.87528,-17.46806],"type":"Point"}
}