{
  "type": "Feature",
  "properties": {
    "gn:admin1_code":"4",
    "gn:admin2_code":"1303205.0",
    "gn:asciiname":"Velho Airao",
    "gn:cc2":"BR",
    "gn:country_code":"BR",
    "gn:dem":47,
    "gn:feature_class":"P",
    "gn:feature_code":"PPL",
    "gn:name":"Velho Air\u00e3o",
    "gn:population":0,
    "gn:timezone":"America/Manaus",
    "iso:country":"BR",
    "name:und_x_variant":[
        "Air\u00e3o",
        "Velho Air\u00e3o"
    ],
    "wof:name":"Velho Airao",
    "wof:placetype":"locality"
},
  "geometry": {"coordinates":[-61.36666999999999,-1.95],"type":"Point"}
}