{
  "type": "Feature",
  "properties": {
    "gn:admin1_code":"02",
    "gn:admin2_code":"2707206.0",
    "gn:asciiname":"Pinhaozinho",
    "gn:cc2":"BR",
    "gn:country_code":"BR",
    "gn:dem":530,
    "gn:feature_class":"P",
    "gn:feature_code":"PPL",
    "gn:name":"Pinh\u00e3ozinho",
    "gn:population":0,
    "gn:timezone":"America/Maceio",
    "iso:country":"BR",
    "name:und_x_variant":[
        "Pinh\u00e3ozeiro",
        "Pinh\u00e3ozinho"
    ],
    "wof:name":"Pinhaozinho",
    "wof:placetype":"locality"
},
  "geometry": {"coordinates":[-37.18333,-9.26667],"type":"Point"}
}