{
  "type": "Feature",
  "properties": {
    "gn:admin1_code":"13",
    "gn:admin2_code":"2103208.0",
    "gn:asciiname":"Leandro",
    "gn:country_code":"BR",
    "gn:dem":60,
    "gn:feature_class":"P",
    "gn:feature_code":"PPL",
    "gn:name":"Leandro",
    "gn:population":0,
    "gn:timezone":"America/Fortaleza",
    "iso:country":"BR",
    "name:deu_x_preferred":[
        "Leandro"
    ],
    "name:fra_x_preferred":[
        "Leandro"
    ],
    "name:ita_x_preferred":[
        "Leandro"
    ],
    "name:jpn_x_preferred":[
        "\u30ec\u30a2\u30f3\u30c9\u30ed"
    ],
    "name:pol_x_preferred":[
        "Leandro"
    ],
    "name:por_x_preferred":[
        "Leandro"
    ],
    "name:rus_x_preferred":[
        "\u041b\u0435\u0430\u043d\u0434\u0440\u043e"
    ],
    "name:spa_x_preferred":[
        "Leandro"
    ],
    "wof:name":"Leandro",
    "wof:placetype":"locality"
},
  "geometry": {"coordinates":[-43.48778,-3.8425],"type":"Point"}
}