{
  "type": "Feature",
  "properties": {
    "iso:country":"BR",
    "name:ceb_x_preferred":[
        "S\u00e3o Geraldo"
    ],
    "name:fra_x_preferred":[
        "S\u00e3o Geraldo"
    ],
    "name:pol_x_preferred":[
        "S\u00e3o Geraldo"
    ],
    "name:por_x_colloquial":[
        "Sao Geraldo"
    ],
    "name:por_x_preferred":[
        "S\u00e3o Geraldo"
    ],
    "name:sco_x_preferred":[
        "S\u00e3o Geraldo"
    ],
    "name:swe_x_preferred":[
        "S\u00e3o Geraldo"
    ],
    "qs:gn_adm0_cc":"BR",
    "qs:gn_local":3663517,
    "qs:local_max":3574,
    "qs:local_sum":8876,
    "qs:localhoods":22,
    "qs:name":"S\u00e3o Geraldo",
    "qs:name_adm0":"Brasil",
    "qs:name_adm1":"Amazonas",
    "qs:name_adm2":"Manaus",
    "qs:name_local":"Manaus",
    "qs:photo_max":302,
    "qs:photo_sum":367,
    "qs:placetype":"Suburb",
    "qs:quad_count":6,
    "qs:woe_adm0":23424768,
    "qs:woe_adm1":2344847,
    "qs:woe_adm2":12578206,
    "qs:woe_lau":0,
    "qs:woe_local":455833,
    "qs:woe_ver":"7.10.0",
    "wof:lang":[
        "por"
    ],
    "wof:name":"S\u00e3o Geraldo",
    "wof:placetype":"neighbourhood"
},
  "geometry": {"coordinates":[-60.027599,-3.101127],"type":"Point"}
}