{
  "type": "Feature",
  "properties": {
    "gn:admin1_code":"20",
    "gn:admin2_code":"2208809.0",
    "gn:asciiname":"Chapada da Vereda",
    "gn:country_code":"BR",
    "gn:dem":254,
    "gn:feature_class":"P",
    "gn:feature_code":"PPL",
    "gn:name":"Chapada da Vereda",
    "gn:population":0,
    "gn:timezone":"America/Fortaleza",
    "iso:country":"BR",
    "wof:name":"Chapada da Vereda",
    "wof:placetype":"locality"
},
  "geometry": {"coordinates":[-42.61667,-6.28333],"type":"Point"}
}