{
  "type": "Feature",
  "properties": {
    "gn:admin1_code":"20",
    "gn:admin2_code":"2202802.0",
    "gn:asciiname":"Chapadinha",
    "gn:country_code":"BR",
    "gn:dem":258,
    "gn:feature_class":"P",
    "gn:feature_code":"PPL",
    "gn:name":"Chapadinha",
    "gn:population":0,
    "gn:timezone":"America/Fortaleza",
    "iso:country":"BR",
    "name:bpy_x_preferred":[
        "\u099a\u09be\u09aa\u09be\u09a1\u09bf\u09a8\u09b9\u09be"
    ],
    "name:deu_x_preferred":[
        "Chapadinha"
    ],
    "name:eus_x_preferred":[
        "Chapadinha"
    ],
    "name:fra_x_preferred":[
        "Chapadinha"
    ],
    "name:hye_x_preferred":[
        "\u0547\u0561\u057a\u0561\u0564\u056b\u0576\u056b\u0561"
    ],
    "name:ita_x_preferred":[
        "Chapadinha"
    ],
    "name:kat_x_preferred":[
        "\u10e9\u10d0\u10de\u10d0\u10d3\u10d8\u10dc\u10d8\u10d0"
    ],
    "name:kaz_x_preferred":[
        "\u0428\u0430\u043f\u0430\u0434\u0438\u043d\u044c\u044f"
    ],
    "name:mlg_x_preferred":[
        "Chapadinha"
    ],
    "name:nld_x_preferred":[
        "Chapadinha"
    ],
    "name:nor_x_preferred":[
        "Chapadinha"
    ],
    "name:pol_x_preferred":[
        "Chapadinha"
    ],
    "name:por_x_preferred":[
        "Chapadinha"
    ],
    "name:ron_x_preferred":[
        "Chapadinha"
    ],
    "name:rus_x_preferred":[
        "\u0428\u0430\u043f\u0430\u0434\u0438\u043d\u044c\u044f"
    ],
    "name:slk_x_preferred":[
        "Chapadinha"
    ],
    "name:spa_x_preferred":[
        "Chapadinha"
    ],
    "name:vie_x_preferred":[
        "Chapadinha"
    ],
    "name:vol_x_preferred":[
        "Chapadinha"
    ],
    "name:war_x_preferred":[
        "Chapadinha"
    ],
    "name:zho_x_preferred":[
        "\u6c99\u5e15\u8fea\u5c3c\u4e9a"
    ],
    "wof:name":"Chapadinha",
    "wof:placetype":"locality"
},
  "geometry": {"coordinates":[-41.51667,-7.88333],"type":"Point"}
}