{
  "type": "Feature",
  "properties": {
    "gn:admin1_code":"06",
    "gn:admin2_code":"2302008.0",
    "gn:asciiname":"Largo",
    "gn:country_code":"BR",
    "gn:dem":361,
    "gn:feature_class":"P",
    "gn:feature_code":"PPL",
    "gn:name":"Largo",
    "gn:population":0,
    "gn:timezone":"America/Fortaleza",
    "iso:country":"BR",
    "wof:name":"Largo",
    "wof:placetype":"locality"
},
  "geometry": {"coordinates":[-38.85,-7.08333],"type":"Point"}
}