{
  "type": "Feature",
  "properties": {
    "gn:admin1_code":"06",
    "gn:admin2_code":"2302008.0",
    "gn:asciiname":"Largo",
    "gn:country_code":"BR",
    "gn:dem":361,
    "gn:feature_class":"P",
    "gn:feature_code":"PPL",
    "gn:name":"Largo",
    "gn:population":0,
    "gn:timezone":"America/Fortaleza",
    "iso:country":"BR",
    "name:ceb_x_preferred":[
        "Largo"
    ],
    "name:ces_x_preferred":[
        "Largo"
    ],
    "name:deu_x_preferred":[
        "Largo"
    ],
    "name:fin_x_preferred":[
        "Largo"
    ],
    "name:fra_x_preferred":[
        "Largo"
    ],
    "name:ita_x_preferred":[
        "Largo"
    ],
    "name:jpn_x_preferred":[
        "\u30e9\u30eb\u30b4"
    ],
    "name:kor_x_preferred":[
        "\ub77c\ub974\uace0"
    ],
    "name:nld_x_preferred":[
        "Largo"
    ],
    "name:nor_x_preferred":[
        "Largo"
    ],
    "name:pol_x_preferred":[
        "Largo"
    ],
    "name:por_x_preferred":[
        "Largo"
    ],
    "name:rus_x_preferred":[
        "\u041b\u0430\u0440\u0433\u043e"
    ],
    "name:spa_x_preferred":[
        "Largo"
    ],
    "name:srp_x_preferred":[
        "\u041b\u0430\u0440\u0433\u043e"
    ],
    "name:swe_x_preferred":[
        "Largo"
    ],
    "name:ukr_x_preferred":[
        "\u041b\u0430\u0440\u0433\u043e"
    ],
    "name:urd_x_preferred":[
        "\u0644\u0627\u0631\u06af\u0648"
    ],
    "name:vol_x_preferred":[
        "Largo"
    ],
    "wof:name":"Largo",
    "wof:placetype":"locality"
},
  "geometry": {"coordinates":[-38.85,-7.08333],"type":"Point"}
}