{
  "type": "Feature",
  "properties": {
    "gn:admin1_code":"15",
    "gn:admin2_code":"3101607.0",
    "gn:asciiname":"Limeira",
    "gn:country_code":"BR",
    "gn:dem":862,
    "gn:feature_class":"P",
    "gn:feature_code":"PPL",
    "gn:name":"Limeira",
    "gn:population":0,
    "gn:timezone":"America/Sao_Paulo",
    "iso:country":"BR",
    "name:por_x_preferred":[
        "Limeira"
    ],
    "wof:name":"Limeira",
    "wof:placetype":"locality"
},
  "geometry": {"coordinates":[-45.96667,-21.53333],"type":"Point"}
}