{
  "type": "Feature",
  "properties": {
    "gn:admin1_code":"18.0",
    "gn:admin2_code":"4121208.0",
    "gn:asciiname":"Sitio Luiz Ribeiro",
    "gn:country_code":"BR",
    "gn:dem":851,
    "gn:feature_class":"P",
    "gn:feature_code":"PPL",
    "gn:name":"S\u00edtio Luiz Ribeiro",
    "gn:population":0,
    "gn:timezone":"America/Sao_Paulo",
    "iso:country":"BR",
    "name:por_x_preferred":[
        "S\u00edtio Luiz Ribeiro"
    ],
    "wof:name":"Sitio Luiz Ribeiro",
    "wof:placetype":"locality"
},
  "geometry": {"coordinates":[-49.45837,-25.84339],"type":"Point"}
}