{
  "type": "Feature",
  "properties": {
    "gn:admin1_code":"18.0",
    "gn:admin2_code":"4121208.0",
    "gn:asciiname":"Sitio Pedro Olsho",
    "gn:country_code":"BR",
    "gn:dem":866,
    "gn:feature_class":"P",
    "gn:feature_code":"PPL",
    "gn:name":"S\u00edtio Pedro Olsho",
    "gn:population":0,
    "gn:timezone":"America/Sao_Paulo",
    "iso:country":"BR",
    "name:por_x_preferred":[
        "S\u00edtio Pedro Olsho"
    ],
    "wof:name":"Sitio Pedro Olsho",
    "wof:placetype":"locality"
},
  "geometry": {"coordinates":[-49.45656,-25.80319],"type":"Point"}
}