{
  "type": "Feature",
  "properties": {
    "gn:admin1_code":"5",
    "gn:admin2_code":"2927903.0",
    "gn:asciiname":"Boa Fe",
    "gn:country_code":"BR",
    "gn:dem":424,
    "gn:feature_class":"P",
    "gn:feature_code":"PPL",
    "gn:name":"Boa F\u00e9",
    "gn:population":0,
    "gn:timezone":"America/Bahia",
    "iso:country":"BR",
    "wof:name":"Boa Fe",
    "wof:placetype":"locality"
},
  "geometry": {"coordinates":[-39.83333,-13.28333],"type":"Point"}
}