{
  "type": "Feature",
  "properties": {
    "gn:gn_country":"BR",
    "gn:gn_fcode":"PPL",
    "gn:gn_pop":0,
    "iso:country":"BR",
    "name:bpy_x_preferred":[
        "\u09ac\u09cb\u09f1\u09be \u09ad\u09bf\u09b8\u09cd\u099f\u09be"
    ],
    "name:bre_x_preferred":[
        "Boa Vista"
    ],
    "name:ceb_x_preferred":[
        "Boa Vista"
    ],
    "name:ces_x_preferred":[
        "Boa Vista"
    ],
    "name:deu_x_preferred":[
        "Boa Vista"
    ],
    "name:epo_x_preferred":[
        "Boa Vista"
    ],
    "name:fin_x_preferred":[
        "Boa Vista"
    ],
    "name:fra_x_preferred":[
        "Boa Vista"
    ],
    "name:glg_x_preferred":[
        "Boa Vista"
    ],
    "name:hrv_x_preferred":[
        "Boa Vista"
    ],
    "name:hun_x_preferred":[
        "Boa Vista"
    ],
    "name:ita_x_preferred":[
        "Boa Vista"
    ],
    "name:jpn_x_preferred":[
        "\u30dc\u30a2\u30f4\u30a3\u30b9\u30bf"
    ],
    "name:kor_x_preferred":[
        "\ubcf4\uc544\ube44\uc2a4\ud0c0"
    ],
    "name:lav_x_preferred":[
        "Boa Vista"
    ],
    "name:mlg_x_preferred":[
        "Boa Vista"
    ],
    "name:nds_x_preferred":[
        "Boa Vista"
    ],
    "name:nld_x_preferred":[
        "Boa Vista"
    ],
    "name:nor_x_preferred":[
        "Boa Vista"
    ],
    "name:pol_x_preferred":[
        "Boa Vista"
    ],
    "name:por_x_preferred":[
        "Boa Vista"
    ],
    "name:rus_x_preferred":[
        "\u0411\u043e\u0430-\u0412\u0438\u0441\u0442\u0430"
    ],
    "name:sco_x_preferred":[
        "Boa Vista"
    ],
    "name:swe_x_preferred":[
        "Boa Vista"
    ],
    "name:vol_x_preferred":[
        "Boa Vista"
    ],
    "name:zho_x_preferred":[
        "\u535a\u963f\u7ef4\u65af\u5854"
    ],
    "qs_pg:aaroncc":"BR",
    "qs_pg:gn_country":"BR",
    "qs_pg:gn_fcode":"PPL",
    "qs_pg:gn_pop":0,
    "qs_pg:name":"Boa Vista",
    "qs_pg:name_adm0":"Brasil",
    "qs_pg:name_adm1":"Minas Gerais",
    "qs_pg:photos":10,
    "qs_pg:photos_1k":2,
    "qs_pg:photos_9k":1,
    "qs_pg:photos_9r":1,
    "qs_pg:photos_all":10,
    "qs_pg:photos_sr":1,
    "qs_pg:pop_sr":0,
    "qs_pg:qs_pg_placetype":"neighbourhood",
    "qs_pg:qs_pg_placetype_gp":"Suburb",
    "qs_pg:woe_adm0":23424768,
    "woe:adm0_id":23424768,
    "woe:name_adm0":"Brasil",
    "woe:name_adm1":"Minas Gerais",
    "woe:placetype":"Suburb",
    "wof:name":"Boa Vista",
    "wof:placetype":"neighbourhood"
},
  "geometry": {"coordinates":[-43.68639,-22.23111],"type":"Point"}
}