{
  "type": "Feature",
  "properties": {
    "gn:admin1_code":"23",
    "gn:admin2_code":"4317103.0",
    "gn:asciiname":"Estancia de Lima",
    "gn:country_code":"BR",
    "gn:dem":337,
    "gn:feature_class":"P",
    "gn:feature_code":"PPL",
    "gn:name":"Est\u00e2ncia de Lima",
    "gn:population":0,
    "gn:timezone":"America/Sao_Paulo",
    "iso:country":"BR",
    "wof:name":"Estancia de Lima",
    "wof:placetype":"locality"
},
  "geometry": {"coordinates":[-55.85,-31.01667],"type":"Point"}
}