{
  "type": "Feature",
  "properties": {
    "gn:admin1_code":"18.0",
    "gn:admin2_code":"4100202.0",
    "gn:asciiname":"Joao Surra",
    "gn:country_code":"BR",
    "gn:dem":104,
    "gn:feature_class":"P",
    "gn:feature_code":"PPL",
    "gn:name":"Jo\u00e3o Surr\u00e1",
    "gn:population":0,
    "gn:timezone":"America/Sao_Paulo",
    "iso:country":"BR",
    "name:por_x_preferred":[
        "Jo\u00e3o Surr\u00e1"
    ],
    "wof:name":"Joao Surra",
    "wof:placetype":"locality"
},
  "geometry": {"coordinates":[-48.66012,-24.70221],"type":"Point"}
}