{
  "type": "Feature",
  "properties": {
    "gn:admin1_code":"16",
    "gn:admin2_code":"1504406.0",
    "gn:asciiname":"Araucumirim",
    "gn:country_code":"BR",
    "gn:dem":13,
    "gn:feature_class":"P",
    "gn:feature_code":"PPL",
    "gn:name":"Araucumirim",
    "gn:population":0,
    "gn:timezone":"America/Belem",
    "iso:country":"BR",
    "wof:name":"Araucumirim",
    "wof:placetype":"locality"
},
  "geometry": {"coordinates":[-47.65,-0.61667],"type":"Point"}
}