{
  "type": "Feature",
  "properties": {
    "gn:admin1_code":"4.0",
    "gn:admin2_code":"1304302.0",
    "gn:asciiname":"Rancho de Jose Batista",
    "gn:country_code":"BR",
    "gn:dem":33,
    "gn:feature_class":"P",
    "gn:feature_code":"PPLL",
    "gn:name":"Rancho de Jos\u00e9 Batista",
    "gn:population":0,
    "gn:timezone":"America/Manaus",
    "iso:country":"BR",
    "name:por_x_preferred":[
        "Rancho de Jos\u00e9 Batista"
    ],
    "wof:name":"Rancho de Jose Batista",
    "wof:placetype":"locality"
},
  "geometry": {"coordinates":[-58.25308,-1.92477],"type":"Point"}
}