{
  "type": "Feature",
  "properties": {
    "gn:admin1_code":"06",
    "gn:admin2_code":"2310704.0",
    "gn:asciiname":"Fazenda Feijao",
    "gn:country_code":"BR",
    "gn:dem":85,
    "gn:feature_class":"P",
    "gn:feature_code":"PPL",
    "gn:name":"Fazenda Feij\u00e3o",
    "gn:population":0,
    "gn:timezone":"America/Fortaleza",
    "iso:country":"BR",
    "wof:name":"Fazenda Feijao",
    "wof:placetype":"locality"
},
  "geometry": {"coordinates":[-39.13333,-3.95],"type":"Point"}
}