{
  "type": "Feature",
  "properties": {
    "gn:admin1_code":"18.0",
    "gn:admin2_code":"4121208.0",
    "gn:asciiname":"Cai de Cima",
    "gn:country_code":"BR",
    "gn:dem":896,
    "gn:feature_class":"P",
    "gn:feature_code":"PPLL",
    "gn:name":"Ca\u00ed de Cima",
    "gn:population":0,
    "gn:timezone":"America/Sao_Paulo",
    "iso:country":"BR",
    "name:por_x_preferred":[
        "Ca\u00ed de Cima"
    ],
    "wof:name":"Cai de Cima",
    "wof:placetype":"locality"
},
  "geometry": {"coordinates":[-49.4545,-25.856],"type":"Point"}
}