{
  "type": "Feature",
  "properties": {
    "gn:admin1_code":"27",
    "gn:admin2_code":"3530607.0",
    "gn:asciiname":"Stio So Jorge",
    "gn:country_code":"BR",
    "gn:dem":774,
    "gn:feature_class":"P",
    "gn:feature_code":"PPL",
    "gn:name":"Stio So Jorge",
    "gn:population":0,
    "gn:timezone":"America/Sao_Paulo",
    "iso:country":"BR",
    "name:por_x_preferred":[
        "Stio So Jorge"
    ],
    "wof:name":"Stio So Jorge",
    "wof:placetype":"locality"
},
  "geometry": {"coordinates":[-46.2133,-23.4968],"type":"Point"}
}