{
  "type": "Feature",
  "properties": {
    "gn:admin1_code":"20",
    "gn:admin2_code":"2201739.0",
    "gn:asciiname":"Soledade",
    "gn:country_code":"BR",
    "gn:dem":565,
    "gn:feature_class":"P",
    "gn:feature_code":"PPL",
    "gn:name":"Soledade",
    "gn:population":0,
    "gn:timezone":"America/Fortaleza",
    "iso:country":"BR",
    "wof:name":"Soledade",
    "wof:placetype":"locality"
},
  "geometry": {"coordinates":[-40.68333,-8.13333],"type":"Point"}
}