{
  "type": "Feature",
  "properties": {
    "gn:admin1_code":"20",
    "gn:admin2_code":"2201739.0",
    "gn:asciiname":"Soledade",
    "gn:country_code":"BR",
    "gn:dem":565,
    "gn:feature_class":"P",
    "gn:feature_code":"PPL",
    "gn:name":"Soledade",
    "gn:population":0,
    "gn:timezone":"America/Fortaleza",
    "iso:country":"BR",
    "name:bpy_x_preferred":[
        "\u09b8\u09cb\u09b2\u09c7\u09a1\u09be\u09a1\u09c7"
    ],
    "name:epo_x_preferred":[
        "Soledade"
    ],
    "name:fin_x_preferred":[
        "Soledade"
    ],
    "name:kaz_x_preferred":[
        "\u0421\u043e\u043b\u0435\u0434\u0430\u0434\u0438"
    ],
    "name:pol_x_preferred":[
        "Soledade"
    ],
    "name:rus_x_preferred":[
        "\u0421\u043e\u043b\u0435\u0434\u0430\u0434\u0438"
    ],
    "name:spa_x_preferred":[
        "Soledade"
    ],
    "name:war_x_preferred":[
        "Soledade"
    ],
    "name:zho_x_preferred":[
        "\u7d22\u840a\u9054\u5fb7"
    ],
    "wof:name":"Soledade",
    "wof:placetype":"locality"
},
  "geometry": {"coordinates":[-40.68333,-8.13333],"type":"Point"}
}