{
  "type": "Feature",
  "properties": {
    "gn:admin1_code":"18",
    "gn:admin2_code":"4105201.0",
    "gn:asciiname":"Sobradinho",
    "gn:country_code":"BR",
    "gn:dem":958,
    "gn:feature_class":"P",
    "gn:feature_code":"PPL",
    "gn:name":"Sobradinho",
    "gn:population":0,
    "gn:timezone":"America/Sao_Paulo",
    "iso:country":"BR",
    "name:bpy_x_preferred":[
        "\u09b8\u09cb\u09ac\u09cd\u09b0\u09be\u09a1\u09bf\u09a8\u09b9\u09cb"
    ],
    "name:ceb_x_preferred":[
        "Sobradinho"
    ],
    "name:deu_x_preferred":[
        "Sobradinho"
    ],
    "name:fra_x_preferred":[
        "Sobradinho"
    ],
    "name:ita_x_preferred":[
        "Sobradinho"
    ],
    "name:nld_x_preferred":[
        "Sobradinho"
    ],
    "name:nor_x_preferred":[
        "Sobradinho"
    ],
    "name:por_x_preferred":[
        "Sobradinho"
    ],
    "name:rus_x_preferred":[
        "\u0421\u043e\u0431\u0440\u0430\u0434\u0438\u043d\u044c\u044e"
    ],
    "name:sco_x_preferred":[
        "Sobradihno"
    ],
    "name:swe_x_preferred":[
        "Sobradinho"
    ],
    "name:vie_x_preferred":[
        "Sobradinho"
    ],
    "name:vol_x_preferred":[
        "Sobradinho"
    ],
    "wof:name":"Sobradinho",
    "wof:placetype":"locality"
},
  "geometry": {"coordinates":[-49.13333,-24.95],"type":"Point"}
}