{
  "type": "Feature",
  "properties": {
    "gn:admin1_code":"18",
    "gn:admin2_code":"4105201.0",
    "gn:asciiname":"Sobradinho",
    "gn:country_code":"BR",
    "gn:dem":958,
    "gn:feature_class":"P",
    "gn:feature_code":"PPL",
    "gn:name":"Sobradinho",
    "gn:population":0,
    "gn:timezone":"America/Sao_Paulo",
    "iso:country":"BR",
    "wof:name":"Sobradinho",
    "wof:placetype":"locality"
},
  "geometry": {"coordinates":[-49.13333,-24.95],"type":"Point"}
}