{
  "type": "Feature",
  "properties": {
    "iso:country":"BR",
    "name:por_x_preferred":[
        "Sto. Agostinho"
    ],
    "qs:gn_adm0_cc":"BR",
    "qs:gn_local":3470127,
    "qs:gn_nam_loc":"Belo Horizonte, Belo Horizonte, Minas Gerais, BR",
    "qs:gn_namadm1":"15",
    "qs:local_max":8946,
    "qs:local_sum":53157,
    "qs:localhoods":65,
    "qs:name":"Sto. Agostinho",
    "qs:name_adm0":"Brasil",
    "qs:name_adm1":"Minas Gerais",
    "qs:name_adm2":"Belo Horizonte",
    "qs:name_local":"Belo Horizonte",
    "qs:photo_max":1308,
    "qs:photo_sum":2604,
    "qs:placetype":"Suburb",
    "qs:quad_count":27,
    "qs:woe_adm0":23424768,
    "qs:woe_adm1":2344856,
    "qs:woe_adm2":12579464,
    "qs:woe_lau":0,
    "qs:woe_local":455821,
    "qs:woe_ver":"7.10.0",
    "wof:lang":[
        "por"
    ],
    "wof:name":"Sto. Agostinho",
    "wof:placetype":"neighbourhood"
},
  "geometry": {"coordinates":[-43.949778,-19.932663],"type":"Point"}
}