{
  "type": "Feature",
  "properties": {
    "gn:admin1_code":"22",
    "gn:admin2_code":"2404309.0",
    "gn:asciiname":"Umari",
    "gn:country_code":"BR",
    "gn:dem":26,
    "gn:feature_class":"P",
    "gn:feature_code":"PPL",
    "gn:name":"Umari",
    "gn:population":0,
    "gn:timezone":"America/Fortaleza",
    "iso:country":"BR",
    "name:ceb_x_preferred":[
        "Umari"
    ],
    "name:deu_x_preferred":[
        "Umari"
    ],
    "name:ita_x_preferred":[
        "Umari"
    ],
    "name:swe_x_preferred":[
        "Umari"
    ],
    "wof:name":"Umari",
    "wof:placetype":"locality"
},
  "geometry": {"coordinates":[-37.49417,-5.39944],"type":"Point"}
}