{
  "type": "Feature",
  "properties": {
    "gn:admin1_code":"18.0",
    "gn:admin2_code":"4113205.0",
    "gn:asciiname":"Sitio Antonio Lopes",
    "gn:country_code":"BR",
    "gn:dem":814,
    "gn:feature_class":"P",
    "gn:feature_code":"PPL",
    "gn:name":"S\u00edtio Ant\u00f4nio Lopes",
    "gn:population":0,
    "gn:timezone":"America/Sao_Paulo",
    "iso:country":"BR",
    "name:por_x_preferred":[
        "S\u00edtio Ant\u00f4nio Lopes"
    ],
    "wof:name":"Sitio Antonio Lopes",
    "wof:placetype":"locality"
},
  "geometry": {"coordinates":[-49.9612,-26.0112],"type":"Point"}
}