{
  "type": "Feature",
  "properties": {
    "gn:admin1_code":"18",
    "gn:admin2_code":"4121208.0",
    "gn:asciiname":"Sitio Jose Carax",
    "gn:country_code":"BR",
    "gn:dem":848,
    "gn:feature_class":"P",
    "gn:feature_code":"PPL",
    "gn:name":"S\u00edtio Jos\u00e9 Carax",
    "gn:population":0,
    "gn:timezone":"America/Sao_Paulo",
    "iso:country":"BR",
    "name:por_x_preferred":[
        "S\u00edtio Jos\u00e9 Carax"
    ],
    "wof:name":"Sitio Jose Carax",
    "wof:placetype":"locality"
},
  "geometry": {"coordinates":[-49.5175,-25.96583],"type":"Point"}
}