{
  "type": "Feature",
  "properties": {
    "gn:admin1_code":"06",
    "gn:admin2_code":"2304954.0",
    "gn:asciiname":"Horizonte",
    "gn:country_code":"BR",
    "gn:dem":76,
    "gn:feature_class":"P",
    "gn:feature_code":"PPL",
    "gn:name":"Horizonte",
    "gn:population":0,
    "gn:timezone":"America/Fortaleza",
    "iso:country":"BR",
    "name:mlg_x_preferred":[
        "Horizonte"
    ],
    "wof:name":"Horizonte",
    "wof:placetype":"locality"
},
  "geometry": {"coordinates":[-38.65139,-4.08583],"type":"Point"}
}