{
  "type": "Feature",
  "properties": {
    "gn:admin1_code":"13",
    "gn:admin2_code":"2102200.0",
    "gn:asciiname":"Alazao dos Cardosos",
    "gn:country_code":"BR",
    "gn:dem":60,
    "gn:feature_class":"P",
    "gn:feature_code":"PPL",
    "gn:name":"Alaz\u00e3o dos Cardosos",
    "gn:population":0,
    "gn:timezone":"America/Fortaleza",
    "iso:country":"BR",
    "wof:name":"Alazao dos Cardosos",
    "wof:placetype":"locality"
},
  "geometry": {"coordinates":[-42.90611,-3.99278],"type":"Point"}
}