{
  "type": "Feature",
  "properties": {
    "gn:admin1_code":"20.0",
    "gn:admin2_code":"2209302.0",
    "gn:asciiname":"Barroquinha",
    "gn:country_code":"BR",
    "gn:dem":252,
    "gn:feature_class":"P",
    "gn:feature_code":"PPL",
    "gn:name":"Barroquinha",
    "gn:population":0,
    "gn:timezone":"America/Fortaleza",
    "iso:country":"BR",
    "name:por_x_preferred":[
        "Barroquinha"
    ],
    "wof:name":"Barroquinha",
    "wof:placetype":"locality"
},
  "geometry": {"coordinates":[-44.30302,-9.00807],"type":"Point"}
}