{
  "type": "Feature",
  "properties": {
    "gn:admin1_code":"20.0",
    "gn:admin2_code":"2209302.0",
    "gn:asciiname":"Barroquinha",
    "gn:country_code":"BR",
    "gn:dem":252,
    "gn:feature_class":"P",
    "gn:feature_code":"PPL",
    "gn:name":"Barroquinha",
    "gn:population":0,
    "gn:timezone":"America/Fortaleza",
    "iso:country":"BR",
    "name:bpy_x_preferred":[
        "\u09ac\u09be\u09b0\u09cd\u09b0\u09cb\u0995\u09c1\u0987\u09a8\u09b9\u09be"
    ],
    "name:eus_x_preferred":[
        "Barroquinha"
    ],
    "name:fra_x_preferred":[
        "Barroquinha"
    ],
    "name:hye_x_preferred":[
        "\u0532\u0561\u057c\u0578\u056f\u056b\u0576\u0575\u0561"
    ],
    "name:ita_x_preferred":[
        "Barroquinha"
    ],
    "name:kat_x_preferred":[
        "\u10d1\u10d0\u10e0\u10dd\u10d9\u10d8\u10dc\u10d8\u10d0"
    ],
    "name:kaz_x_preferred":[
        "\u0411\u0430\u0440\u0440\u043e\u043a\u0438\u043d\u044c\u044f"
    ],
    "name:nld_x_preferred":[
        "Barroquinha"
    ],
    "name:nor_x_preferred":[
        "Barroquinha"
    ],
    "name:por_x_preferred":[
        "Barroquinha"
    ],
    "name:ron_x_preferred":[
        "Barroquinha"
    ],
    "name:rus_x_preferred":[
        "\u0411\u0430\u0440\u0440\u043e\u043a\u0438\u043d\u044c\u044f"
    ],
    "name:spa_x_preferred":[
        "Barroquinha"
    ],
    "name:vie_x_preferred":[
        "Barroquinha"
    ],
    "name:vol_x_preferred":[
        "Barroquinha"
    ],
    "name:war_x_preferred":[
        "Barroquinha"
    ],
    "name:zho_x_preferred":[
        "\u5df4\u7f57\u57fa\u5c3c\u4e9a"
    ],
    "wof:name":"Barroquinha",
    "wof:placetype":"locality"
},
  "geometry": {"coordinates":[-44.30302,-9.00807],"type":"Point"}
}