{
  "type": "Feature",
  "properties": {
    "gn:admin1_code":"18.0",
    "gn:admin2_code":"4121208.0",
    "gn:asciiname":"Sitio Eugenio Scraba",
    "gn:country_code":"BR",
    "gn:dem":916,
    "gn:feature_class":"P",
    "gn:feature_code":"PPL",
    "gn:name":"S\u00edtio Eug\u00eanio Scraba",
    "gn:population":0,
    "gn:timezone":"America/Sao_Paulo",
    "iso:country":"BR",
    "name:por_x_preferred":[
        "S\u00edtio Eug\u00eanio Scraba"
    ],
    "wof:name":"Sitio Eugenio Scraba",
    "wof:placetype":"locality"
},
  "geometry": {"coordinates":[-49.4799,-25.823],"type":"Point"}
}