{
  "type": "Feature",
  "properties": {
    "gn:admin1_code":"17",
    "gn:admin2_code":"2504306.0",
    "gn:asciiname":"Valparaiso",
    "gn:country_code":"BR",
    "gn:dem":265,
    "gn:feature_class":"P",
    "gn:feature_code":"PPL",
    "gn:name":"Valparaiso",
    "gn:population":0,
    "gn:timezone":"America/Fortaleza",
    "iso:country":"BR",
    "wof:name":"Valparaiso",
    "wof:placetype":"locality"
},
  "geometry": {"coordinates":[-37.75,-6.36667],"type":"Point"}
}