{
  "type": "Feature",
  "properties": {
    "gn:admin1_code":"18.0",
    "gn:admin2_code":"4104006.0",
    "gn:asciiname":"Sitio Olimpio B. de Oliveira",
    "gn:country_code":"BR",
    "gn:dem":823,
    "gn:feature_class":"P",
    "gn:feature_code":"PPL",
    "gn:name":"S\u00edtio Ol\u00edmpio B. de Oliveira",
    "gn:population":0,
    "gn:timezone":"America/Sao_Paulo",
    "iso:country":"BR",
    "name:por_x_preferred":[
        "S\u00edtio Ol\u00edmpio B. de Oliveira"
    ],
    "wof:name":"Sitio Olimpio B. de Oliveira",
    "wof:placetype":"locality"
},
  "geometry": {"coordinates":[-48.86633,-25.17139],"type":"Point"}
}