{
  "type": "Feature",
  "properties": {
    "gn:admin1_code":"11",
    "gn:admin2_code":"5003108.0",
    "gn:asciiname":"Sao Jeronimo",
    "gn:country_code":"BR",
    "gn:dem":287,
    "gn:feature_class":"P",
    "gn:feature_code":"PPL",
    "gn:name":"S\u00e3o Jer\u00f4nimo",
    "gn:population":0,
    "gn:timezone":"America/Campo_Grande",
    "iso:country":"BR",
    "name:por_x_preferred":[
        "S\u00e3o Jer\u00f4nimo"
    ],
    "wof:name":"Sao Jeronimo",
    "wof:placetype":"locality"
},
  "geometry": {"coordinates":[-55.23333,-19.88333],"type":"Point"}
}