{
  "type": "Feature",
  "properties": {
    "gn:admin1_code":"4",
    "gn:admin2_code":"1300201.0",
    "gn:asciiname":"Canama",
    "gn:country_code":"BR",
    "gn:dem":129,
    "gn:feature_class":"P",
    "gn:feature_code":"PPL",
    "gn:name":"Canam\u00e3",
    "gn:population":0,
    "gn:timezone":"America/Eirunepe",
    "iso:country":"BR",
    "name:ceb_x_preferred":[
        "Canama"
    ],
    "name:fra_x_preferred":[
        "Canama"
    ],
    "name:ita_x_preferred":[
        "Canama"
    ],
    "name:nld_x_preferred":[
        "Canama"
    ],
    "name:ron_x_preferred":[
        "Canama"
    ],
    "name:swe_x_preferred":[
        "Canama"
    ],
    "name:vie_x_preferred":[
        "Canama"
    ],
    "name:war_x_preferred":[
        "Canama"
    ],
    "wof:name":"Canama",
    "wof:placetype":"locality"
},
  "geometry": {"coordinates":[-72.09999999999999,-5.61667],"type":"Point"}
}