{
  "type": "Feature",
  "properties": {
    "gn:gn_country":"BR",
    "gn:gn_fcode":"PPL",
    "gn:gn_pop":0,
    "iso:country":"BR",
    "name:eng_x_preferred":[
        "Rocha Miranda"
    ],
    "name:fra_x_preferred":[
        "Rocha Miranda"
    ],
    "name:ita_x_preferred":[
        "Rocha Miranda"
    ],
    "name:nld_x_preferred":[
        "Rocha Miranda"
    ],
    "name:por_x_preferred":[
        "Rocha Miranda"
    ],
    "qs_pg:aaroncc":"BR",
    "qs_pg:gn_country":"BR",
    "qs_pg:gn_fcode":"PPL",
    "qs_pg:gn_pop":0,
    "qs_pg:name":"Rocha Miranda",
    "qs_pg:name_adm0":"Brasil",
    "qs_pg:name_adm1":"Rio de Janeiro",
    "qs_pg:photos_9r":0,
    "qs_pg:photos_sr":0,
    "qs_pg:pop_sr":0,
    "qs_pg:qs_pg_placetype":"neighbourhood",
    "qs_pg:qs_pg_placetype_gp":"Suburb",
    "qs_pg:woe_adm0":23424768,
    "woe:adm0_id":23424768,
    "woe:name_adm0":"Brasil",
    "woe:name_adm1":"Rio de Janeiro",
    "woe:placetype":"Suburb",
    "wof:name":"Rocha Miranda",
    "wof:placetype":"neighbourhood"
},
  "geometry": {"coordinates":[-43.35841,-22.8528],"type":"Point"}
}