{
  "type": "Feature",
  "properties": {
    "gn:admin1_code":"18.0",
    "gn:admin2_code":"4117701.0",
    "gn:asciiname":"Agro-Pecuaria Palmeirense",
    "gn:country_code":"BR",
    "gn:dem":939,
    "gn:feature_class":"P",
    "gn:feature_code":"PPL",
    "gn:name":"Agro-Pecu\u00e1ria Palmeirense",
    "gn:population":0,
    "gn:timezone":"America/Sao_Paulo",
    "iso:country":"BR",
    "name:por_x_preferred":[
        "Agro-Pecu\u00e1ria Palmeirense"
    ],
    "wof:name":"Agro-Pecuaria Palmeirense",
    "wof:placetype":"locality"
},
  "geometry": {"coordinates":[-50.35314,-25.52433],"type":"Point"}
}