{
  "type": "Feature",
  "properties": {
    "gn:admin1_code":"18.0",
    "gn:admin2_code":"4122305.0",
    "gn:asciiname":"Sitio Niveldo Lazarine",
    "gn:country_code":"BR",
    "gn:dem":811,
    "gn:feature_class":"P",
    "gn:feature_code":"PPL",
    "gn:name":"S\u00edtio Niveldo Lazarine",
    "gn:population":0,
    "gn:timezone":"America/Sao_Paulo",
    "iso:country":"BR",
    "name:por_x_preferred":[
        "S\u00edtio Niveldo Lazarine"
    ],
    "wof:name":"Sitio Niveldo Lazarine",
    "wof:placetype":"locality"
},
  "geometry": {"coordinates":[-49.8188,-26.0792],"type":"Point"}
}