{
  "type": "Feature",
  "properties": {
    "gn:admin1_code":"27",
    "gn:admin2_code":"3507001.0",
    "gn:asciiname":"Sitio Nosso Cantinho",
    "gn:country_code":"BR",
    "gn:dem":590,
    "gn:feature_class":"P",
    "gn:feature_code":"PPL",
    "gn:name":"S\u00edtio Nosso Cantinho",
    "gn:population":0,
    "gn:timezone":"America/Sao_Paulo",
    "iso:country":"BR",
    "name:por_x_preferred":[
        "S\u00edtio Nosso Cantinho"
    ],
    "wof:name":"Sitio Nosso Cantinho",
    "wof:placetype":"locality"
},
  "geometry": {"coordinates":[-47.63528,-23.19361],"type":"Point"}
}