{
  "type": "Feature",
  "properties": {
    "gn:admin1_code":"18",
    "gn:admin2_code":"4110706.0",
    "gn:asciiname":"Linha Cinco",
    "gn:country_code":"BR",
    "gn:dem":931,
    "gn:feature_class":"P",
    "gn:feature_code":"PPLL",
    "gn:name":"Linha Cinco",
    "gn:population":0,
    "gn:timezone":"America/Sao_Paulo",
    "iso:country":"BR",
    "name:por_x_preferred":[
        "Linha Cinco"
    ],
    "name:por_x_variant":[
        "Linha 5"
    ],
    "wof:name":"Linha Cinco",
    "wof:placetype":"locality"
},
  "geometry": {"coordinates":[-50.7463,-25.4325],"type":"Point"}
}