{
  "type": "Feature",
  "properties": {
    "gn:admin1_code":"18",
    "gn:admin2_code":"4104105.0",
    "gn:asciiname":"Sitio Ovidio C. de Paula",
    "gn:country_code":"BR",
    "gn:dem":803,
    "gn:feature_class":"P",
    "gn:feature_code":"PPL",
    "gn:name":"S\u00edtio Ov\u00eddio C. de Paula",
    "gn:population":0,
    "gn:timezone":"America/Sao_Paulo",
    "iso:country":"BR",
    "name:por_x_preferred":[
        "S\u00edtio Ov\u00eddio C. de Paula"
    ],
    "wof:name":"Sitio Ovidio C. de Paula",
    "wof:placetype":"locality"
},
  "geometry": {"coordinates":[-49.59583,-25.935],"type":"Point"}
}