{
  "type": "Feature",
  "properties": {
    "gn:admin1_code":"06",
    "gn:admin2_code":"2302404.0",
    "gn:asciiname":"Olho d'Agua de Milho",
    "gn:country_code":"BR",
    "gn:dem":477,
    "gn:feature_class":"P",
    "gn:feature_code":"PPL",
    "gn:name":"\u00d4lho d\u2019\u00c1gua de Milho",
    "gn:population":0,
    "gn:timezone":"America/Fortaleza",
    "iso:country":"BR",
    "wof:name":"Olho d'Agua de Milho",
    "wof:placetype":"locality"
},
  "geometry": {"coordinates":[-39.63333,-5.33333],"type":"Point"}
}