{
  "type": "Feature",
  "properties": {
    "gn:admin1_code":"4",
    "gn:admin2_code":"1303700.0",
    "gn:asciiname":"Monte Carmelo",
    "gn:country_code":"BR",
    "gn:dem":53,
    "gn:feature_class":"P",
    "gn:feature_code":"PPL",
    "gn:name":"Monte Carmelo",
    "gn:population":0,
    "gn:timezone":"America/Manaus",
    "iso:country":"BR",
    "wof:name":"Monte Carmelo",
    "wof:placetype":"locality"
},
  "geometry": {"coordinates":[-68.55,-2.91667],"type":"Point"}
}