{
  "type": "Feature",
  "properties": {
    "gn:admin1_code":"20",
    "gn:admin2_code":"2208205.0",
    "gn:asciiname":"Sanharo",
    "gn:country_code":"BR",
    "gn:dem":430,
    "gn:feature_class":"P",
    "gn:feature_code":"PPL",
    "gn:name":"Sanhar\u00f3",
    "gn:population":0,
    "gn:timezone":"America/Fortaleza",
    "iso:country":"BR",
    "wof:name":"Sanharo",
    "wof:placetype":"locality"
},
  "geometry": {"coordinates":[-40.63333,-6.98333],"type":"Point"}
}