{
  "type": "Feature",
  "properties": {
    "gn:admin1_code":"26.0",
    "gn:admin2_code":"4205803.0",
    "gn:asciiname":"Sitio Ingo Klietzke",
    "gn:country_code":"BR",
    "gn:dem":8,
    "gn:feature_class":"P",
    "gn:feature_code":"PPL",
    "gn:name":"S\u00edtio Ingo Klietzke",
    "gn:population":0,
    "gn:timezone":"America/Sao_Paulo",
    "iso:country":"BR",
    "name:por_x_preferred":[
        "S\u00edtio Ingo Klietzke"
    ],
    "wof:name":"Sitio Ingo Klietzke",
    "wof:placetype":"locality"
},
  "geometry": {"coordinates":[-48.81776,-25.98396],"type":"Point"}
}