{
  "type": "Feature",
  "properties": {
    "gn:admin1_code":"15",
    "gn:admin2_code":"3170206.0",
    "gn:asciiname":"Aroeira",
    "gn:country_code":"BR",
    "gn:dem":885,
    "gn:feature_class":"P",
    "gn:feature_code":"PPL",
    "gn:name":"Aroeira",
    "gn:population":0,
    "gn:timezone":"America/Sao_Paulo",
    "iso:country":"BR",
    "name:por_x_preferred":[
        "Aroeira"
    ],
    "wof:name":"Aroeira",
    "wof:placetype":"locality"
},
  "geometry": {"coordinates":[-48.28333,-19.21667],"type":"Point"}
}