{
  "type": "Feature",
  "properties": {
    "gn:admin1_code":"26",
    "gn:admin2_code":"4210100.0",
    "gn:asciiname":"Sitio Libio Roscheski",
    "gn:country_code":"BR",
    "gn:dem":880,
    "gn:feature_class":"P",
    "gn:feature_code":"PPL",
    "gn:name":"S\u00edtio L\u00edbio Roscheski",
    "gn:population":0,
    "gn:timezone":"America/Sao_Paulo",
    "iso:country":"BR",
    "name:por_x_preferred":[
        "S\u00edtio L\u00edbio Roscheski"
    ],
    "wof:name":"Sitio Libio Roscheski",
    "wof:placetype":"locality"
},
  "geometry": {"coordinates":[-49.8467,-26.2039],"type":"Point"}
}