{
  "type": "Feature",
  "properties": {
    "iso:country":"BR",
    "name:por_x_preferred":[
        "Martelos"
    ],
    "qs:gn_adm0_cc":"BR",
    "qs:gn_local":3459505,
    "qs:gn_nam_loc":"Juiz de Fora, Juiz de Fora, Minas Gerais, BR",
    "qs:gn_namadm1":"15",
    "qs:local_max":681,
    "qs:local_sum":1249,
    "qs:localhoods":9,
    "qs:name":"Martelos",
    "qs:name_adm0":"Brasil",
    "qs:name_adm1":"Minas Gerais",
    "qs:name_adm2":"Juiz de Fora",
    "qs:name_local":"Juiz de Fora",
    "qs:photo_max":34,
    "qs:photo_sum":70,
    "qs:placetype":"Suburb",
    "qs:quad_count":9,
    "qs:woe_adm0":23424768,
    "qs:woe_adm1":2344856,
    "qs:woe_adm2":12579770,
    "qs:woe_lau":0,
    "qs:woe_local":455875,
    "qs:woe_ver":"7.10.0",
    "wof:lang":[
        "por"
    ],
    "wof:name":"Martelos",
    "wof:placetype":"neighbourhood"
},
  "geometry": {"coordinates":[-43.370682,-21.773701],"type":"Point"}
}