{
  "type": "Feature",
  "properties": {
    "gn:admin1_code":"18.0",
    "gn:admin2_code":"4106209.0",
    "gn:asciiname":"Sitio Francisco Stiagar",
    "gn:country_code":"BR",
    "gn:dem":921,
    "gn:feature_class":"P",
    "gn:feature_code":"PPL",
    "gn:name":"S\u00edtio Francisco Stiagar",
    "gn:population":0,
    "gn:timezone":"America/Sao_Paulo",
    "iso:country":"BR",
    "name:por_x_preferred":[
        "S\u00edtio Francisco Stiagar"
    ],
    "wof:name":"Sitio Francisco Stiagar",
    "wof:placetype":"locality"
},
  "geometry": {"coordinates":[-49.3979,-25.7794],"type":"Point"}
}