{
  "type": "Feature",
  "properties": {
    "gn:admin1_code":"16",
    "gn:admin2_code":"1502509.0",
    "gn:asciiname":"Cego",
    "gn:country_code":"BR",
    "gn:dem":5,
    "gn:feature_class":"P",
    "gn:feature_code":"PPL",
    "gn:name":"Cego",
    "gn:population":0,
    "gn:timezone":"America/Belem",
    "iso:country":"BR",
    "name:deu_x_preferred":[
        "Cego"
    ],
    "wof:name":"Cego",
    "wof:placetype":"locality"
},
  "geometry": {"coordinates":[-50.03333,-0.25],"type":"Point"}
}