{
  "type": "Feature",
  "properties": {
    "gn:admin1_code":"06",
    "gn:admin2_code":"2300754.0",
    "gn:asciiname":"Fazendinha",
    "gn:country_code":"BR",
    "gn:dem":30,
    "gn:feature_class":"P",
    "gn:feature_code":"PPL",
    "gn:name":"Fazendinha",
    "gn:population":0,
    "gn:timezone":"America/Fortaleza",
    "iso:country":"BR",
    "wof:name":"Fazendinha",
    "wof:placetype":"locality"
},
  "geometry": {"coordinates":[-39.73333,-3.06667],"type":"Point"}
}