{
  "type": "Feature",
  "properties": {
    "gn:admin1_code":"30",
    "gn:admin2_code":"2606309.0",
    "gn:asciiname":"Mata Boi",
    "gn:country_code":"BR",
    "gn:dem":428,
    "gn:feature_class":"P",
    "gn:feature_code":"PPL",
    "gn:name":"Mata Boi",
    "gn:population":0,
    "gn:timezone":"America/Recife",
    "iso:country":"BR",
    "wof:name":"Mata Boi",
    "wof:placetype":"locality"
},
  "geometry": {"coordinates":[-39.56667,-7.85],"type":"Point"}
}