{
  "type": "Feature",
  "properties": {
    "gn:admin1_code":"18.0",
    "gn:admin2_code":"4124103.0",
    "gn:asciiname":"Sitio Santa Fe",
    "gn:country_code":"BR",
    "gn:dem":535,
    "gn:feature_class":"P",
    "gn:feature_code":"PPL",
    "gn:name":"S\u00edtio Santa F\u00e9",
    "gn:population":0,
    "gn:timezone":"America/Sao_Paulo",
    "iso:country":"BR",
    "name:por_x_preferred":[
        "S\u00edtio Santa F\u00e9"
    ],
    "wof:name":"Sitio Santa Fe",
    "wof:placetype":"locality"
},
  "geometry": {"coordinates":[-50.0603,-23.2224],"type":"Point"}
}