{
  "type": "Feature",
  "properties": {
    "gn:admin1_code":"22",
    "gn:admin2_code":"2407104.0",
    "gn:asciiname":"Mata Verde",
    "gn:country_code":"BR",
    "gn:dem":79,
    "gn:feature_class":"P",
    "gn:feature_code":"PPL",
    "gn:name":"Mata Verde",
    "gn:population":0,
    "gn:timezone":"America/Fortaleza",
    "iso:country":"BR",
    "wof:name":"Mata Verde",
    "wof:placetype":"locality"
},
  "geometry": {"coordinates":[-35.51667,-5.95],"type":"Point"}
}