{
  "type": "Feature",
  "properties": {
    "gn:admin1_code":"20",
    "gn:admin2_code":"2202802.0",
    "gn:asciiname":"Moco",
    "gn:country_code":"BR",
    "gn:dem":245,
    "gn:feature_class":"P",
    "gn:feature_code":"PPL",
    "gn:name":"Moc\u00f3",
    "gn:population":0,
    "gn:timezone":"America/Fortaleza",
    "iso:country":"BR",
    "name:deu_x_preferred":[
        "Moco"
    ],
    "name:spa_x_preferred":[
        "Moco"
    ],
    "name:swe_x_preferred":[
        "Moco"
    ],
    "wof:name":"Moco",
    "wof:placetype":"locality"
},
  "geometry": {"coordinates":[-41.56667,-7.86667],"type":"Point"}
}