{
  "type": "Feature",
  "properties": {
    "gn:admin1_code":"27",
    "gn:admin2_code":"3548906.0",
    "gn:asciiname":"Santa Candida",
    "gn:cc2":"BR",
    "gn:country_code":"BR",
    "gn:dem":611,
    "gn:feature_class":"P",
    "gn:feature_code":"PPL",
    "gn:name":"Santa C\u00e2ndida",
    "gn:population":0,
    "gn:timezone":"America/Sao_Paulo",
    "iso:country":"BR",
    "name:und_x_variant":[
        "Santa C\u00e2ndido",
        "Santa C\u00e2ndida"
    ],
    "wof:name":"Santa Candida",
    "wof:placetype":"locality"
},
  "geometry": {"coordinates":[-47.91667,-21.75],"type":"Point"}
}