{
  "type": "Feature",
  "properties": {
    "gn:admin1_code":"5",
    "gn:admin2_code":"2903805.0",
    "gn:asciiname":"Boa Vista do Tupim",
    "gn:country_code":"BR",
    "gn:dem":315,
    "gn:feature_class":"P",
    "gn:feature_code":"PPL",
    "gn:name":"Boa Vista do Tupim",
    "gn:population":0,
    "gn:timezone":"America/Bahia",
    "iso:country":"BR",
    "name:bpy_x_preferred":[
        "\u09ac\u09cb\u09f1\u09be \u09ad\u09bf\u09b8\u09cd\u099f\u09be \u09a1\u09cb \u099f\u09c1\u09aa\u09bf\u09ae"
    ],
    "name:hye_x_preferred":[
        "\u0532\u0578\u0561 \u054e\u056b\u057d\u057f\u0561 \u0564\u0578\u0582 \u054f\u0578\u0582\u057a\u056b\u0576"
    ],
    "name:por_x_preferred":[
        "Boa Vista do Tupim"
    ],
    "name:und_x_variant":[
        "Boa-Vista",
        "Tupim"
    ],
    "wof:name":"Boa Vista do Tupim",
    "wof:placetype":"locality"
},
  "geometry": {"coordinates":[-40.60836,-12.66085],"type":"Point"}
}