{
  "type": "Feature",
  "properties": {
    "gn:admin1_code":"17",
    "gn:admin2_code":"2515203.0",
    "gn:asciiname":"Pitombos",
    "gn:cc2":"BR",
    "gn:country_code":"BR",
    "gn:dem":635,
    "gn:feature_class":"P",
    "gn:feature_code":"PPL",
    "gn:name":"Pitombos",
    "gn:population":0,
    "gn:timezone":"America/Fortaleza",
    "iso:country":"BR",
    "name:und_x_variant":[
        "Pitombas",
        "Pitombos"
    ],
    "wof:name":"Pitombos",
    "wof:placetype":"locality"
},
  "geometry": {"coordinates":[-37.05,-8.16667],"type":"Point"}
}