{
  "type": "Feature",
  "properties": {
    "gn:admin1_code":"18.0",
    "gn:admin2_code":"4119202.0",
    "gn:asciiname":"Sitio Sao Sebastiao",
    "gn:country_code":"BR",
    "gn:dem":725,
    "gn:feature_class":"P",
    "gn:feature_code":"PPL",
    "gn:name":"S\u00edtio S\u00e3o Sebasti\u00e3o",
    "gn:population":0,
    "gn:timezone":"America/Sao_Paulo",
    "iso:country":"BR",
    "name:por_x_preferred":[
        "S\u00edtio S\u00e3o Sebasti\u00e3o"
    ],
    "wof:name":"Sitio Sao Sebastiao",
    "wof:placetype":"locality"
},
  "geometry": {"coordinates":[-50.05258,-23.83421],"type":"Point"}
}