{
  "type": "Feature",
  "properties": {
    "gn:admin1_code":"31",
    "gn:admin2_code":"1721257.0",
    "gn:asciiname":"Nova",
    "gn:country_code":"BR",
    "gn:dem":241,
    "gn:feature_class":"P",
    "gn:feature_code":"PPL",
    "gn:name":"Nova",
    "gn:population":0,
    "gn:timezone":"America/Araguaina",
    "iso:country":"BR",
    "wof:name":"Nova",
    "wof:placetype":"locality"
},
  "geometry": {"coordinates":[-48.31667,-8.93333],"type":"Point"}
}