{
  "type": "Feature",
  "properties": {
    "gn:admin1_code":"5.0",
    "gn:admin2_code":"2900801.0",
    "gn:asciiname":"Arraial Pouso Alegre",
    "gn:country_code":"BR",
    "gn:dem":65,
    "gn:feature_class":"P",
    "gn:feature_code":"PPL",
    "gn:name":"Arraial Pouso Alegre",
    "gn:population":0,
    "gn:timezone":"America/Bahia",
    "iso:country":"BR",
    "name:por_x_preferred":[
        "Arraial Pouso Alegre"
    ],
    "wof:name":"Arraial Pouso Alegre",
    "wof:placetype":"locality"
},
  "geometry": {"coordinates":[-39.59743,-17.41245],"type":"Point"}
}