{
  "type": "Feature",
  "properties": {
    "gn:admin1_code":"5",
    "gn:admin2_code":"2932903.0",
    "gn:asciiname":"Tacanha Grande",
    "gn:country_code":"BR",
    "gn:dem":172,
    "gn:feature_class":"P",
    "gn:feature_code":"PPL",
    "gn:name":"Tacanha Grande",
    "gn:population":0,
    "gn:timezone":"America/Bahia",
    "iso:country":"BR",
    "wof:name":"Tacanha Grande",
    "wof:placetype":"locality"
},
  "geometry": {"coordinates":[-39.35,-13.26667],"type":"Point"}
}