{
  "type": "Feature",
  "properties": {
    "gn:admin1_code":"16",
    "gn:admin2_code":"1505494.0",
    "gn:asciiname":"Sao Manuel",
    "gn:country_code":"BR",
    "gn:dem":131,
    "gn:feature_class":"P",
    "gn:feature_code":"PPL",
    "gn:name":"S\u00e3o Manuel",
    "gn:population":0,
    "gn:timezone":"America/Belem",
    "iso:country":"BR",
    "wof:name":"Sao Manuel",
    "wof:placetype":"locality"
},
  "geometry": {"coordinates":[-48.36667,-6.01667],"type":"Point"}
}