{
  "type": "Feature",
  "properties": {
    "gn:admin1_code":"18.0",
    "gn:admin2_code":"4121208.0",
    "gn:asciiname":"Sitio Renato S. Maier",
    "gn:country_code":"BR",
    "gn:dem":813,
    "gn:feature_class":"P",
    "gn:feature_code":"PPL",
    "gn:name":"S\u00edtio Renato S. M\u00e1ier",
    "gn:population":0,
    "gn:timezone":"America/Sao_Paulo",
    "iso:country":"BR",
    "name:por_x_preferred":[
        "S\u00edtio Renato S. M\u00e1ier"
    ],
    "wof:name":"Sitio Renato S. Maier",
    "wof:placetype":"locality"
},
  "geometry": {"coordinates":[-49.51300000000001,-25.8938],"type":"Point"}
}