{
  "type": "Feature",
  "properties": {
    "gn:admin1_code":"21",
    "gn:admin2_code":"3305158.0",
    "gn:asciiname":"Serra do Capim",
    "gn:country_code":"BR",
    "gn:dem":1014,
    "gn:feature_class":"P",
    "gn:feature_code":"PPL",
    "gn:name":"Serra do Capim",
    "gn:population":0,
    "gn:timezone":"America/Sao_Paulo",
    "iso:country":"BR",
    "name:por_x_preferred":[
        "Serra do Capim"
    ],
    "wof:name":"Serra do Capim",
    "wof:placetype":"locality"
},
  "geometry": {"coordinates":[-42.85,-22.16667],"type":"Point"}
}