{
  "type": "Feature",
  "properties": {
    "gn:admin1_code":"21",
    "gn:admin2_code":"3301207.0",
    "gn:asciiname":"Bacelar",
    "gn:cc2":"BR",
    "gn:country_code":"BR",
    "gn:dem":244,
    "gn:feature_class":"P",
    "gn:feature_code":"PPL",
    "gn:name":"Bacelar",
    "gn:population":0,
    "gn:timezone":"America/Sao_Paulo",
    "iso:country":"BR",
    "name:und_x_variant":[
        "Barcelar",
        "Bacelar"
    ],
    "wof:name":"Bacelar",
    "wof:placetype":"locality"
},
  "geometry": {"coordinates":[-42.61667,-21.91667],"type":"Point"}
}