{
  "type": "Feature",
  "properties": {
    "gn:admin1_code":"27",
    "gn:admin2_code":"3553906.0",
    "gn:asciiname":"Rebojo",
    "gn:country_code":"BR",
    "gn:dem":409,
    "gn:feature_class":"P",
    "gn:feature_code":"PPL",
    "gn:name":"Rebojo",
    "gn:population":0,
    "gn:timezone":"America/Sao_Paulo",
    "iso:country":"BR",
    "wof:name":"Rebojo",
    "wof:placetype":"locality"
},
  "geometry": {"coordinates":[-51.65,-22.33333],"type":"Point"}
}