{
  "type": "Feature",
  "properties": {
    "gn:admin1_code":"20",
    "gn:admin2_code":"2210003.0",
    "gn:asciiname":"Passagem Nova",
    "gn:country_code":"BR",
    "gn:dem":282,
    "gn:feature_class":"P",
    "gn:feature_code":"PPL",
    "gn:name":"Passagem Nova",
    "gn:population":0,
    "gn:timezone":"America/Fortaleza",
    "iso:country":"BR",
    "wof:name":"Passagem Nova",
    "wof:placetype":"locality"
},
  "geometry": {"coordinates":[-42.13333,-8.55],"type":"Point"}
}