{
  "type": "Feature",
  "properties": {
    "gn:admin1_code":"27",
    "gn:admin2_code":"3518305.0",
    "gn:asciiname":"Lambari",
    "gn:country_code":"BR",
    "gn:dem":626,
    "gn:feature_class":"P",
    "gn:feature_code":"PPLL",
    "gn:name":"Lambari",
    "gn:population":0,
    "gn:timezone":"America/Sao_Paulo",
    "iso:country":"BR",
    "name:ceb_x_preferred":[
        "Lambari"
    ],
    "name:nld_x_preferred":[
        "Lambari"
    ],
    "name:por_x_preferred":[
        "Lambari"
    ],
    "name:swe_x_preferred":[
        "Lambari"
    ],
    "wof:name":"Lambari",
    "wof:placetype":"locality"
},
  "geometry": {"coordinates":[-46.10989,-23.32767],"type":"Point"}
}