{
  "type": "Feature",
  "properties": {
    "gn:admin1_code":"27.0",
    "gn:admin2_code":"3550308.0",
    "gn:asciiname":"Bairro Caminho do Sitio",
    "gn:country_code":"BR",
    "gn:dem":788,
    "gn:feature_class":"P",
    "gn:feature_code":"PPL",
    "gn:name":"Bairro Caminho do S\u00edtio",
    "gn:population":0,
    "gn:timezone":"America/Sao_Paulo",
    "iso:country":"BR",
    "name:por_x_preferred":[
        "Bairro Caminho do S\u00edtio"
    ],
    "wof:name":"Bairro Caminho do Sitio",
    "wof:placetype":"locality"
},
  "geometry": {"coordinates":[-46.7449,-23.8288],"type":"Point"}
}