{
  "type": "Feature",
  "properties": {
    "gn:admin1_code":"18.0",
    "gn:admin2_code":"4111704.0",
    "gn:asciiname":"Sitio Beira-Rio",
    "gn:country_code":"BR",
    "gn:dem":476,
    "gn:feature_class":"P",
    "gn:feature_code":"PPL",
    "gn:name":"S\u00edtio Beira-Rio",
    "gn:population":0,
    "gn:timezone":"America/Sao_Paulo",
    "iso:country":"BR",
    "name:por_x_preferred":[
        "S\u00edtio Beira-Rio"
    ],
    "wof:name":"Sitio Beira-Rio",
    "wof:placetype":"locality"
},
  "geometry": {"coordinates":[-50.0141,-23.69928],"type":"Point"}
}