{
  "type": "Feature",
  "properties": {
    "gn:admin1_code":"20",
    "gn:admin2_code":"2202091.0",
    "gn:asciiname":"Caldeirao Grande",
    "gn:country_code":"BR",
    "gn:dem":666,
    "gn:feature_class":"P",
    "gn:feature_code":"PPL",
    "gn:name":"Caldeir\u00e3o Grande",
    "gn:population":0,
    "gn:timezone":"America/Fortaleza",
    "iso:country":"BR",
    "wof:name":"Caldeirao Grande",
    "wof:placetype":"locality"
},
  "geometry": {"coordinates":[-40.63333,-7.35],"type":"Point"}
}