{
  "type": "Feature",
  "properties": {
    "gn:admin1_code":"20",
    "gn:admin2_code":"2200905.0",
    "gn:asciiname":"Buraco d'Agua",
    "gn:country_code":"BR",
    "gn:dem":283,
    "gn:feature_class":"P",
    "gn:feature_code":"PPL",
    "gn:name":"Buraco d\u2019\u00c1gua",
    "gn:population":0,
    "gn:timezone":"America/Fortaleza",
    "iso:country":"BR",
    "wof:name":"Buraco d'Agua",
    "wof:placetype":"locality"
},
  "geometry": {"coordinates":[-41.73333,-6.08333],"type":"Point"}
}