{
  "type": "Feature",
  "properties": {
    "gn:admin1_code":"06",
    "gn:admin2_code":"2304251.0",
    "gn:asciiname":"Solidao",
    "gn:country_code":"BR",
    "gn:dem":30,
    "gn:feature_class":"P",
    "gn:feature_code":"PPL",
    "gn:name":"Solid\u00e3o",
    "gn:population":0,
    "gn:timezone":"America/Fortaleza",
    "iso:country":"BR",
    "wof:name":"Solidao",
    "wof:placetype":"locality"
},
  "geometry": {"coordinates":[-40.41667,-2.93333],"type":"Point"}
}