{
  "type": "Feature",
  "properties": {
    "gn:admin1_code":"1",
    "gn:admin2_code":"1200427.0",
    "gn:asciiname":"Treze de Maio",
    "gn:country_code":"BR",
    "gn:dem":185,
    "gn:feature_class":"P",
    "gn:feature_code":"PPL",
    "gn:name":"Treze de Maio",
    "gn:population":0,
    "gn:timezone":"America/Rio_Branco",
    "iso:country":"BR",
    "name:aze_x_preferred":[
        "Treze-de-Mayo"
    ],
    "name:bpy_x_preferred":[
        "\u099f\u09cd\u09b0\u09c7\u099c\u09c7 \u09a1\u09c7 \u09ae\u09be\u0987\u0993"
    ],
    "name:rus_x_preferred":[
        "\u0422\u0440\u0435\u0437\u0438-\u0434\u0438-\u041c\u0430\u044e"
    ],
    "name:zho_x_preferred":[
        "\u7279\u96f7\u9f50\u8fea\u9a6c\u5c24"
    ],
    "wof:name":"Treze de Maio",
    "wof:placetype":"locality"
},
  "geometry": {"coordinates":[-72.65000000000001,-7.76667],"type":"Point"}
}