{
  "type": "Feature",
  "properties": {
    "gn:admin1_code":"21",
    "gn:admin2_code":"3304557.0",
    "gn:asciiname":"Turiaca",
    "gn:country_code":"BR",
    "gn:dem":39,
    "gn:feature_class":"P",
    "gn:feature_code":"PPL",
    "gn:name":"Turia\u00e7a",
    "gn:population":0,
    "gn:timezone":"America/Sao_Paulo",
    "iso:country":"BR",
    "name:fas_x_preferred":[
        "\u062a\u0648\u0631\u06cc\u0627\u0686\u0648"
    ],
    "name:por_x_preferred":[
        "Turia\u00e7a"
    ],
    "name:por_x_variant":[
        "Turia\u00e7u"
    ],
    "name:urd_x_preferred":[
        "\u062a\u0648\u0631\u06cc\u0627\u0686\u0648"
    ],
    "wof:name":"Turiaca",
    "wof:placetype":"locality"
},
  "geometry": {"coordinates":[-43.33943,-22.86099],"type":"Point"}
}