{
  "type": "Feature",
  "properties": {
    "gn:admin1_code":"21",
    "gn:admin2_code":"3304607.0",
    "gn:asciiname":"Amazonas",
    "gn:country_code":"BR",
    "gn:dem":60,
    "gn:feature_class":"P",
    "gn:feature_code":"PPL",
    "gn:name":"Amazonas",
    "gn:population":0,
    "gn:timezone":"America/Sao_Paulo",
    "iso:country":"BR",
    "name:als_x_preferred":[
        "Amazonas"
    ],
    "name:arg_x_preferred":[
        "Amazonas"
    ],
    "name:bos_x_preferred":[
        "Amazonas"
    ],
    "name:bre_x_preferred":[
        "Amazonas"
    ],
    "name:ceb_x_preferred":[
        "Amazonas"
    ],
    "name:ces_x_preferred":[
        "Amazonas"
    ],
    "name:dan_x_preferred":[
        "Amazonas"
    ],
    "name:deu_x_preferred":[
        "Amazonas"
    ],
    "name:est_x_preferred":[
        "Amazonas"
    ],
    "name:fas_x_preferred":[
        "\u0622\u0645\u0627\u0632\u0648\u0646\u0627\u0633"
    ],
    "name:fin_x_preferred":[
        "Amazonas"
    ],
    "name:fra_x_preferred":[
        "Amazonas"
    ],
    "name:frr_x_preferred":[
        "Amazonas"
    ],
    "name:glg_x_preferred":[
        "Amazonas"
    ],
    "name:heb_x_preferred":[
        "\u05d0\u05de\u05d6\u05d5\u05e0\u05d0\u05e1"
    ],
    "name:hrv_x_preferred":[
        "Amazonas"
    ],
    "name:hun_x_preferred":[
        "Amazonas"
    ],
    "name:hye_x_preferred":[
        "\u0531\u0574\u0561\u0566\u0578\u0576\u0561\u057d"
    ],
    "name:ido_x_preferred":[
        "Amazonas"
    ],
    "name:ina_x_preferred":[
        "Amazonas"
    ],
    "name:ind_x_preferred":[
        "Amazonas"
    ],
    "name:ita_x_preferred":[
        "Amazonas"
    ],
    "name:jpn_x_preferred":[
        "\u30a2\u30de\u30be\u30ca\u30b9\u5dde"
    ],
    "name:kor_x_preferred":[
        "\uc544\ub9c8\uc18c\ub098\uc2a4\uc8fc"
    ],
    "name:lim_x_preferred":[
        "Amazonas"
    ],
    "name:nld_x_preferred":[
        "Amazonas"
    ],
    "name:nno_x_preferred":[
        "Amazonas"
    ],
    "name:nor_x_preferred":[
        "Amazonas"
    ],
    "name:oci_x_preferred":[
        "Amazonas"
    ],
    "name:pol_x_preferred":[
        "Amazonas"
    ],
    "name:por_x_preferred":[
        "Amazonas"
    ],
    "name:ron_x_preferred":[
        "Amazonas"
    ],
    "name:rus_x_preferred":[
        "\u0410\u043c\u0430\u0437\u043e\u043d\u0430\u0441"
    ],
    "name:sco_x_preferred":[
        "Amazonas"
    ],
    "name:slk_x_preferred":[
        "Amazonas"
    ],
    "name:spa_x_preferred":[
        "Amazonas"
    ],
    "name:sqi_x_preferred":[
        "Amazonas"
    ],
    "name:srp_x_preferred":[
        "\u0410\u043c\u0430\u0437\u043e\u043d\u0430\u0441"
    ],
    "name:swa_x_preferred":[
        "Amazonas"
    ],
    "name:tgk_x_preferred":[
        "\u0410\u043c\u0430\u0437\u043e\u043d\u0430\u0441"
    ],
    "name:tha_x_preferred":[
        "\u0e2d\u0e32\u0e21\u0e32\u0e42\u0e0b\u0e19\u0e31\u0e2a"
    ],
    "name:tur_x_preferred":[
        "Amazonas"
    ],
    "name:ukr_x_preferred":[
        "\u0410\u043c\u0430\u0437\u043e\u043d\u0430\u0441"
    ],
    "name:urd_x_preferred":[
        "\u0627\u06cc\u0645\u0627\u0632\u0648\u0646\u0627\u0633"
    ],
    "name:uzb_x_preferred":[
        "Amazonas"
    ],
    "name:vie_x_preferred":[
        "Amazonas"
    ],
    "wof:name":"Amazonas",
    "wof:placetype":"locality"
},
  "geometry": {"coordinates":[-41.83333,-22.05],"type":"Point"}
}