{
  "type": "Feature",
  "properties": {
    "gn:admin1_code":"21",
    "gn:admin2_code":"3304607.0",
    "gn:asciiname":"Amazonas",
    "gn:country_code":"BR",
    "gn:dem":60,
    "gn:feature_class":"P",
    "gn:feature_code":"PPL",
    "gn:name":"Amazonas",
    "gn:population":0,
    "gn:timezone":"America/Sao_Paulo",
    "iso:country":"BR",
    "name:por_x_preferred":[
        "Amazonas"
    ],
    "wof:name":"Amazonas",
    "wof:placetype":"locality"
},
  "geometry": {"coordinates":[-41.83333,-22.05],"type":"Point"}
}