{
  "type": "Feature",
  "properties": {
    "gn:admin1_code":"22",
    "gn:admin2_code":"2401107.0",
    "gn:asciiname":"Benfica",
    "gn:country_code":"BR",
    "gn:dem":10,
    "gn:feature_class":"P",
    "gn:feature_code":"PPL",
    "gn:name":"Benfica",
    "gn:population":0,
    "gn:timezone":"America/Fortaleza",
    "iso:country":"BR",
    "wof:name":"Benfica",
    "wof:placetype":"locality"
},
  "geometry": {"coordinates":[-37.06806,-4.97222],"type":"Point"}
}