{
  "type": "Feature",
  "properties": {
    "gn:admin1_code":"18.0",
    "gn:admin2_code":"4109005.0",
    "gn:asciiname":"Sitio Borges",
    "gn:country_code":"BR",
    "gn:dem":471,
    "gn:feature_class":"P",
    "gn:feature_code":"PPL",
    "gn:name":"S\u00edtio Borges",
    "gn:population":0,
    "gn:timezone":"America/Sao_Paulo",
    "iso:country":"BR",
    "name:por_x_preferred":[
        "S\u00edtio Borges"
    ],
    "wof:name":"Sitio Borges",
    "wof:placetype":"locality"
},
  "geometry": {"coordinates":[-50.02607,-23.49081],"type":"Point"}
}