{
  "type": "Feature",
  "properties": {
    "gn:admin1_code":"18.0",
    "gn:admin2_code":"4112306.0",
    "gn:asciiname":"Sitio Lazaro Silveira",
    "gn:country_code":"BR",
    "gn:dem":670,
    "gn:feature_class":"P",
    "gn:feature_code":"PPL",
    "gn:name":"S\u00edtio L\u00e1zaro Silveira",
    "gn:population":0,
    "gn:timezone":"America/Sao_Paulo",
    "iso:country":"BR",
    "name:por_x_preferred":[
        "S\u00edtio L\u00e1zaro Silveira"
    ],
    "wof:name":"Sitio Lazaro Silveira",
    "wof:placetype":"locality"
},
  "geometry": {"coordinates":[-50.1317,-23.84639],"type":"Point"}
}