{
  "type": "Feature",
  "properties": {
    "gn:admin1_code":"15",
    "gn:admin2_code":"3146503.0",
    "gn:asciiname":"Filipe",
    "gn:country_code":"BR",
    "gn:dem":707,
    "gn:feature_class":"P",
    "gn:feature_code":"PPL",
    "gn:name":"Filipe",
    "gn:population":0,
    "gn:timezone":"America/Sao_Paulo",
    "iso:country":"BR",
    "name:bre_x_preferred":[
        "Filipe"
    ],
    "name:deu_x_preferred":[
        "Filipe"
    ],
    "name:glg_x_preferred":[
        "Filipe"
    ],
    "name:jpn_x_preferred":[
        "\u30d5\u30a3\u30ea\u30da"
    ],
    "name:por_x_preferred":[
        "Filipe"
    ],
    "wof:name":"Filipe",
    "wof:placetype":"locality"
},
  "geometry": {"coordinates":[-45.66667,-20.43333],"type":"Point"}
}