{
  "type": "Feature",
  "properties": {
    "gn:admin1_code":"27",
    "gn:admin2_code":"3519709.0",
    "gn:asciiname":"Bairro dos Alves",
    "gn:country_code":"BR",
    "gn:dem":907,
    "gn:feature_class":"P",
    "gn:feature_code":"PPLL",
    "gn:name":"Bairro dos Alves",
    "gn:population":0,
    "gn:timezone":"America/Sao_Paulo",
    "iso:country":"BR",
    "name:por_x_preferred":[
        "Bairro dos Alves"
    ],
    "wof:name":"Bairro dos Alves",
    "wof:placetype":"locality"
},
  "geometry": {"coordinates":[-47.20129,-23.81097],"type":"Point"}
}