{
  "type": "Feature",
  "properties": {
    "gn:admin1_code":"18.0",
    "gn:admin2_code":"4109609.0",
    "gn:asciiname":"Sitio Pedro Wiegosz",
    "gn:country_code":"BR",
    "gn:dem":153,
    "gn:feature_class":"P",
    "gn:feature_code":"PPL",
    "gn:name":"S\u00edtio Pedro Wiegosz",
    "gn:population":0,
    "gn:timezone":"America/Sao_Paulo",
    "iso:country":"BR",
    "name:por_x_preferred":[
        "S\u00edtio Pedro Wiegosz"
    ],
    "wof:name":"Sitio Pedro Wiegosz",
    "wof:placetype":"locality"
},
  "geometry": {"coordinates":[-48.90935,-25.93136],"type":"Point"}
}