{
  "type": "Feature",
  "properties": {
    "gn:admin1_code":"18.0",
    "gn:admin2_code":"4127809.0",
    "gn:asciiname":"Sitio Bento Goes",
    "gn:country_code":"BR",
    "gn:dem":538,
    "gn:feature_class":"P",
    "gn:feature_code":"PPL",
    "gn:name":"S\u00edtio Bento G\u00f3es",
    "gn:population":0,
    "gn:timezone":"America/Sao_Paulo",
    "iso:country":"BR",
    "name:por_x_preferred":[
        "S\u00edtio Bento G\u00f3es"
    ],
    "wof:name":"Sitio Bento Goes",
    "wof:placetype":"locality"
},
  "geometry": {"coordinates":[-49.9533,-23.62],"type":"Point"}
}