{
  "type": "Feature",
  "properties": {
    "gn:admin1_code":"22",
    "gn:admin2_code":"2400604.0",
    "gn:asciiname":"Saquinho",
    "gn:country_code":"BR",
    "gn:dem":343,
    "gn:feature_class":"P",
    "gn:feature_code":"PPL",
    "gn:name":"Saquinho",
    "gn:population":0,
    "gn:timezone":"America/Fortaleza",
    "iso:country":"BR",
    "wof:name":"Saquinho",
    "wof:placetype":"locality"
},
  "geometry": {"coordinates":[-37.78333,-6.21667],"type":"Point"}
}