{
  "type": "Feature",
  "properties": {
    "gn:admin1_code":"2",
    "gn:admin2_code":"2701902.0",
    "gn:asciiname":"Bela Vista",
    "gn:country_code":"BR",
    "gn:dem":445,
    "gn:feature_class":"P",
    "gn:feature_code":"PPL",
    "gn:name":"Bela Vista",
    "gn:population":0,
    "gn:timezone":"America/Maceio",
    "iso:country":"BR",
    "name:ukr_x_preferred":[
        "\u0411\u0435\u043b\u0430-\u0412\u0456\u0441\u0442\u0430"
    ],
    "wof:name":"Bela Vista",
    "wof:placetype":"locality"
},
  "geometry": {"coordinates":[-36.23333,-9.28333],"type":"Point"}
}