{
  "type": "Feature",
  "properties": {
    "gn:admin1_code":"22",
    "gn:admin2_code":"2400505.0",
    "gn:asciiname":"Serrota",
    "gn:country_code":"BR",
    "gn:dem":461,
    "gn:feature_class":"P",
    "gn:feature_code":"PPL",
    "gn:name":"Serrota",
    "gn:population":0,
    "gn:timezone":"America/Fortaleza",
    "iso:country":"BR",
    "wof:name":"Serrota",
    "wof:placetype":"locality"
},
  "geometry": {"coordinates":[-38.05,-6.43333],"type":"Point"}
}