{
  "type": "Feature",
  "properties": {
    "gn:admin1_code":"4",
    "gn:admin2_code":"1302207.0",
    "gn:asciiname":"Martirio",
    "gn:country_code":"BR",
    "gn:dem":55,
    "gn:feature_class":"P",
    "gn:feature_code":"PPL",
    "gn:name":"Mart\u00edrio",
    "gn:population":0,
    "gn:timezone":"America/Manaus",
    "iso:country":"BR",
    "name:bre_x_preferred":[
        "Martirio"
    ],
    "name:cat_x_preferred":[
        "Martirio"
    ],
    "name:deu_x_preferred":[
        "Martirio"
    ],
    "name:glg_x_preferred":[
        "Martirio"
    ],
    "name:nor_x_preferred":[
        "Martirio"
    ],
    "name:spa_x_preferred":[
        "Martirio"
    ],
    "wof:name":"Martirio",
    "wof:placetype":"locality"
},
  "geometry": {"coordinates":[-65.86896999999999,-2.96329],"type":"Point"}
}