{
  "type": "Feature",
  "properties": {
    "gn:admin1_code":"30",
    "gn:admin2_code":"2603306.0",
    "gn:asciiname":"Jacare",
    "gn:country_code":"BR",
    "gn:dem":681,
    "gn:feature_class":"P",
    "gn:feature_code":"PPL",
    "gn:name":"Jacar\u00e9",
    "gn:population":0,
    "gn:timezone":"America/Recife",
    "iso:country":"BR",
    "wof:name":"Jacare",
    "wof:placetype":"locality"
},
  "geometry": {"coordinates":[-36.31667,-8.75],"type":"Point"}
}