{
  "type": "Feature",
  "properties": {
    "gn:admin1_code":"15",
    "gn:admin2_code":"3114402.0",
    "gn:asciiname":"Joaquim Adolfo",
    "gn:country_code":"BR",
    "gn:dem":817,
    "gn:feature_class":"P",
    "gn:feature_code":"PPL",
    "gn:name":"Joaquim Adolfo",
    "gn:population":0,
    "gn:timezone":"America/Sao_Paulo",
    "iso:country":"BR",
    "name:por_x_preferred":[
        "Joaquim Adolfo"
    ],
    "wof:name":"Joaquim Adolfo",
    "wof:placetype":"locality"
},
  "geometry": {"coordinates":[-46.06667,-20.93333],"type":"Point"}
}