{
  "type": "Feature",
  "properties": {
    "gn:admin1_code":"5",
    "gn:admin2_code":"2910750.0",
    "gn:asciiname":"Alegres",
    "gn:country_code":"BR",
    "gn:dem":321,
    "gn:feature_class":"P",
    "gn:feature_code":"PPL",
    "gn:name":"Alegres",
    "gn:population":0,
    "gn:timezone":"America/Bahia",
    "iso:country":"BR",
    "wof:name":"Alegres",
    "wof:placetype":"locality"
},
  "geometry": {"coordinates":[-38.23333,-10.51667],"type":"Point"}
}