{
  "type": "Feature",
  "properties": {
    "gn:admin1_code":"8",
    "gn:admin2_code":"3204302.0",
    "gn:asciiname":"Palmorindo",
    "gn:country_code":"BR",
    "gn:dem":91,
    "gn:feature_class":"P",
    "gn:feature_code":"PPL",
    "gn:name":"Palmorindo",
    "gn:population":0,
    "gn:timezone":"America/Sao_Paulo",
    "iso:country":"BR",
    "name:por_x_preferred":[
        "Palmorindo"
    ],
    "wof:name":"Palmorindo",
    "wof:placetype":"locality"
},
  "geometry": {"coordinates":[-41.11667,-21.06667],"type":"Point"}
}