{
  "type": "Feature",
  "properties": {
    "gn:admin1_code":"26",
    "gn:admin2_code":"4210100.0",
    "gn:asciiname":"Sitio Carlos Mirval",
    "gn:country_code":"BR",
    "gn:dem":857,
    "gn:feature_class":"P",
    "gn:feature_code":"PPL",
    "gn:name":"S\u00edtio Carlos Mirval",
    "gn:population":0,
    "gn:timezone":"America/Sao_Paulo",
    "iso:country":"BR",
    "name:por_x_preferred":[
        "S\u00edtio Carlos Mirval"
    ],
    "wof:name":"Sitio Carlos Mirval",
    "wof:placetype":"locality"
},
  "geometry": {"coordinates":[-49.66546,-26.23433],"type":"Point"}
}