{
  "type": "Feature",
  "properties": {
    "gn:admin1_code":"02",
    "gn:admin2_code":"2705309.0",
    "gn:asciiname":"Lagoa do Caminho",
    "gn:country_code":"BR",
    "gn:dem":275,
    "gn:feature_class":"P",
    "gn:feature_code":"PPL",
    "gn:name":"Lagoa do Caminho",
    "gn:population":0,
    "gn:timezone":"America/Maceio",
    "iso:country":"BR",
    "wof:name":"Lagoa do Caminho",
    "wof:placetype":"locality"
},
  "geometry": {"coordinates":[-36.86667,-9.33333],"type":"Point"}
}