{
  "type": "Feature",
  "properties": {
    "gn:admin1_code":"6.0",
    "gn:admin2_code":"2301000.0",
    "gn:asciiname":"Pau Pombo",
    "gn:country_code":"BR",
    "gn:dem":33,
    "gn:feature_class":"P",
    "gn:feature_code":"PPL",
    "gn:name":"Pau Pombo",
    "gn:population":0,
    "gn:timezone":"America/Fortaleza",
    "iso:country":"BR",
    "wof:name":"Pau Pombo",
    "wof:placetype":"locality"
},
  "geometry": {"coordinates":[-38.34248,-3.97125],"type":"Point"}
}