{
  "type": "Feature",
  "properties": {
    "gn:admin1_code":"13",
    "gn:admin2_code":"2100808.0",
    "gn:asciiname":"Jacaranda",
    "gn:country_code":"BR",
    "gn:dem":71,
    "gn:feature_class":"P",
    "gn:feature_code":"PPL",
    "gn:name":"Jacarand\u00e1",
    "gn:population":0,
    "gn:timezone":"America/Fortaleza",
    "iso:country":"BR",
    "wof:name":"Jacaranda",
    "wof:placetype":"locality"
},
  "geometry": {"coordinates":[-43.08028,-3.60667],"type":"Point"}
}