{
  "type": "Feature",
  "properties": {
    "gn:admin1_code":"13",
    "gn:admin2_code":"2103208.0",
    "gn:asciiname":"Pau-d'Arco",
    "gn:country_code":"BR",
    "gn:dem":43,
    "gn:feature_class":"P",
    "gn:feature_code":"PPL",
    "gn:name":"Pau-d\u2019Arco",
    "gn:population":0,
    "gn:timezone":"America/Fortaleza",
    "iso:country":"BR",
    "wof:name":"Pau-d'Arco",
    "wof:placetype":"locality"
},
  "geometry": {"coordinates":[-43.46333,-3.78306],"type":"Point"}
}