{
  "type": "Feature",
  "properties": {
    "gn:admin1_code":"18.0",
    "gn:admin2_code":"4109609.0",
    "gn:asciiname":"Porteiro",
    "gn:country_code":"BR",
    "gn:dem":332,
    "gn:feature_class":"P",
    "gn:feature_code":"PPLL",
    "gn:name":"Porteiro",
    "gn:population":0,
    "gn:timezone":"America/Sao_Paulo",
    "iso:country":"BR",
    "name:por_x_preferred":[
        "Porteiro"
    ],
    "wof:name":"Porteiro",
    "wof:placetype":"locality"
},
  "geometry": {"coordinates":[-48.8933,-25.8302],"type":"Point"}
}