{
  "type": "Feature",
  "properties": {
    "gn:admin1_code":"18",
    "gn:admin2_code":"4117701.0",
    "gn:asciiname":"Chacara",
    "gn:country_code":"BR",
    "gn:dem":950,
    "gn:feature_class":"P",
    "gn:feature_code":"PPL",
    "gn:name":"Ch\u00e1cara",
    "gn:population":0,
    "gn:timezone":"America/Sao_Paulo",
    "iso:country":"BR",
    "wof:name":"Chacara",
    "wof:placetype":"locality"
},
  "geometry": {"coordinates":[-50.07833,-25.49667],"type":"Point"}
}