{
  "type": "Feature",
  "properties": {
    "gn:admin1_code":"18",
    "gn:admin2_code":"4109302.0",
    "gn:asciiname":"Rocinha",
    "gn:country_code":"BR",
    "gn:dem":864,
    "gn:feature_class":"P",
    "gn:feature_code":"PPL",
    "gn:name":"Rocinha",
    "gn:population":0,
    "gn:timezone":"America/Sao_Paulo",
    "iso:country":"BR",
    "name:deu_x_preferred":[
        "Rocinha"
    ],
    "name:epo_x_preferred":[
        "Rocinha"
    ],
    "name:fin_x_preferred":[
        "Rocinha"
    ],
    "name:fra_x_preferred":[
        "Rocinha"
    ],
    "name:frp_x_preferred":[
        "Rocinha"
    ],
    "name:ita_x_preferred":[
        "Rocinha"
    ],
    "name:nld_x_preferred":[
        "Rocinha"
    ],
    "name:nor_x_preferred":[
        "Rocinha"
    ],
    "name:pol_x_preferred":[
        "Rocinha"
    ],
    "name:por_x_preferred":[
        "Rocinha"
    ],
    "name:rus_x_preferred":[
        "\u0420\u043e\u0441\u0438\u043d\u044c\u044f"
    ],
    "name:spa_x_preferred":[
        "Rocinha"
    ],
    "wof:name":"Rocinha",
    "wof:placetype":"locality"
},
  "geometry": {"coordinates":[-52.85,-25.11667000000001],"type":"Point"}
}