{
  "type": "Feature",
  "properties": {
    "gn:admin1_code":"18",
    "gn:admin2_code":"4109302.0",
    "gn:asciiname":"Rocinha",
    "gn:country_code":"BR",
    "gn:dem":864,
    "gn:feature_class":"P",
    "gn:feature_code":"PPL",
    "gn:name":"Rocinha",
    "gn:population":0,
    "gn:timezone":"America/Sao_Paulo",
    "iso:country":"BR",
    "wof:name":"Rocinha",
    "wof:placetype":"locality"
},
  "geometry": {"coordinates":[-52.85,-25.11667000000001],"type":"Point"}
}