{
  "type": "Feature",
  "properties": {
    "gn:admin1_code":"16",
    "gn:admin2_code":"1503606.0",
    "gn:asciiname":"Vila Nova",
    "gn:country_code":"BR",
    "gn:dem":33,
    "gn:feature_class":"P",
    "gn:feature_code":"PPL",
    "gn:name":"Vila Nova",
    "gn:population":0,
    "gn:timezone":"America/Santarem",
    "iso:country":"BR",
    "wof:name":"Vila Nova",
    "wof:placetype":"locality"
},
  "geometry": {"coordinates":[-56.28333000000001,-4.43333],"type":"Point"}
}