{
  "type": "Feature",
  "properties": {
    "gn:admin1_code":"17",
    "gn:admin2_code":"2500536.0",
    "gn:asciiname":"Maranhao",
    "gn:country_code":"BR",
    "gn:dem":555,
    "gn:feature_class":"P",
    "gn:feature_code":"PPL",
    "gn:name":"Maranh\u00e3o",
    "gn:population":0,
    "gn:timezone":"America/Fortaleza",
    "iso:country":"BR",
    "wof:name":"Maranhao",
    "wof:placetype":"locality"
},
  "geometry": {"coordinates":[-36.11667,-7.76667],"type":"Point"}
}