{
  "type": "Feature",
  "properties": {
    "gn:admin1_code":"27.0",
    "gn:admin2_code":"3550308.0",
    "gn:asciiname":"Sitio Ugao",
    "gn:country_code":"BR",
    "gn:dem":797,
    "gn:feature_class":"P",
    "gn:feature_code":"PPL",
    "gn:name":"S\u00edtio Ug\u00e3o",
    "gn:population":0,
    "gn:timezone":"America/Sao_Paulo",
    "iso:country":"BR",
    "name:por_x_preferred":[
        "S\u00edtio Ug\u00e3o"
    ],
    "wof:name":"Sitio Ugao",
    "wof:placetype":"locality"
},
  "geometry": {"coordinates":[-46.7441,-23.8291],"type":"Point"}
}