{
  "type": "Feature",
  "properties": {
    "gn:admin1_code":"5",
    "gn:admin2_code":"2922003.0",
    "gn:asciiname":"Varjota",
    "gn:country_code":"BR",
    "gn:dem":26,
    "gn:feature_class":"P",
    "gn:feature_code":"PPL",
    "gn:name":"Varjota",
    "gn:population":0,
    "gn:timezone":"America/Bahia",
    "iso:country":"BR",
    "name:bpy_x_preferred":[
        "\u09ad\u09be\u09b0\u09cd\u099c\u09cb\u099f\u09be"
    ],
    "name:bre_x_preferred":[
        "Varjota"
    ],
    "name:eus_x_preferred":[
        "Varjota"
    ],
    "name:fas_x_preferred":[
        "\u0648\u0631\u062c\u062a\u0627"
    ],
    "name:fra_x_preferred":[
        "Varjota"
    ],
    "name:hye_x_preferred":[
        "\u054e\u0561\u0580\u056a\u0578\u057f\u0561"
    ],
    "name:ita_x_preferred":[
        "Varjota"
    ],
    "name:kat_x_preferred":[
        "\u10d5\u10d0\u10e0\u10df\u10dd\u10e2\u10d0"
    ],
    "name:kaz_x_preferred":[
        "\u0412\u0430\u0440\u0436\u043e\u0442\u0430"
    ],
    "name:nld_x_preferred":[
        "Varjota"
    ],
    "name:nor_x_preferred":[
        "Varjota"
    ],
    "name:por_x_preferred":[
        "Varjota"
    ],
    "name:ron_x_preferred":[
        "Varjota"
    ],
    "name:rus_x_preferred":[
        "\u0412\u0430\u0440\u0436\u043e\u0442\u0430"
    ],
    "name:vie_x_preferred":[
        "Varjota"
    ],
    "name:vol_x_preferred":[
        "Varjota"
    ],
    "name:war_x_preferred":[
        "Varjota"
    ],
    "name:zho_x_preferred":[
        "\u74e6\u5c14\u82e5\u5854"
    ],
    "wof:name":"Varjota",
    "wof:placetype":"locality"
},
  "geometry": {"coordinates":[-39.96667,-18.03333],"type":"Point"}
}