{
  "type": "Feature",
  "properties": {
    "gn:admin1_code":"5",
    "gn:admin2_code":"2922003.0",
    "gn:asciiname":"Varjota",
    "gn:country_code":"BR",
    "gn:dem":26,
    "gn:feature_class":"P",
    "gn:feature_code":"PPL",
    "gn:name":"Varjota",
    "gn:population":0,
    "gn:timezone":"America/Bahia",
    "iso:country":"BR",
    "name:por_x_preferred":[
        "Varjota"
    ],
    "wof:name":"Varjota",
    "wof:placetype":"locality"
},
  "geometry": {"coordinates":[-39.96667,-18.03333],"type":"Point"}
}