{
  "type": "Feature",
  "properties": {
    "gn:admin1_code":"16",
    "gn:admin2_code":"1505106.0",
    "gn:asciiname":"Boa Vista",
    "gn:country_code":"BR",
    "gn:dem":1,
    "gn:feature_class":"P",
    "gn:feature_code":"PPL",
    "gn:name":"Boa Vista",
    "gn:population":0,
    "gn:timezone":"America/Santarem",
    "iso:country":"BR",
    "name:ben_x_preferred":[
        "\u09ac\u09cb\u09df\u09be \u09ad\u09bf\u09b8\u09cd\u09a4\u09be"
    ],
    "name:bpy_x_preferred":[
        "\u09ac\u09cb\u09f1\u09be \u09ad\u09bf\u09b8\u09cd\u099f\u09be"
    ],
    "name:bre_x_preferred":[
        "Boa Vista"
    ],
    "name:ceb_x_preferred":[
        "Boa Vista"
    ],
    "name:ces_x_preferred":[
        "Boa Vista"
    ],
    "name:deu_x_preferred":[
        "Boa Vista"
    ],
    "name:epo_x_preferred":[
        "Boa Vista"
    ],
    "name:fas_x_preferred":[
        "\u0628\u0648\u0622 \u0648\u06cc\u0633\u062a\u0627"
    ],
    "name:fin_x_preferred":[
        "Boa Vista"
    ],
    "name:fra_x_preferred":[
        "Boa Vista"
    ],
    "name:glg_x_preferred":[
        "Boa Vista"
    ],
    "name:heb_x_preferred":[
        "\u05d4\u05d0\u05d9 \u05d1\u05d5\u05d0\u05d4 \u05d5\u05d9\u05e1\u05d8\u05d4"
    ],
    "name:hin_x_preferred":[
        "\u092c\u094b\u0906 \u0935\u093f\u0938\u094d\u091f\u093e"
    ],
    "name:hrv_x_preferred":[
        "Boa Vista"
    ],
    "name:hun_x_preferred":[
        "Boa Vista"
    ],
    "name:ita_x_preferred":[
        "Boa Vista"
    ],
    "name:jpn_x_preferred":[
        "\u30dc\u30a2\u30f4\u30a3\u30b9\u30bf"
    ],
    "name:kor_x_preferred":[
        "\ubcf4\uc544\ube44\uc2a4\ud0c0"
    ],
    "name:lav_x_preferred":[
        "Boa Vista"
    ],
    "name:mlg_x_preferred":[
        "Boa Vista"
    ],
    "name:nds_x_preferred":[
        "Boa Vista"
    ],
    "name:nld_x_preferred":[
        "Boa Vista"
    ],
    "name:nor_x_preferred":[
        "Boa Vista"
    ],
    "name:pol_x_preferred":[
        "Boa Vista"
    ],
    "name:por_x_preferred":[
        "Boa Vista"
    ],
    "name:rus_x_preferred":[
        "\u0411\u043e\u0430-\u0412\u0438\u0441\u0442\u0430"
    ],
    "name:sco_x_preferred":[
        "Boa Vista"
    ],
    "name:swe_x_preferred":[
        "Boa Vista"
    ],
    "name:vie_x_preferred":[
        "\u0110\u1ea3o Boa Vista"
    ],
    "name:vol_x_preferred":[
        "Boa Vista"
    ],
    "name:zho_x_preferred":[
        "\u535a\u963f\u7ef4\u65af\u5854"
    ],
    "wof:name":"Boa Vista",
    "wof:placetype":"locality"
},
  "geometry": {"coordinates":[-55.36667,-2.06667],"type":"Point"}
}