{
  "type": "Feature",
  "properties": {
    "gn:admin1_code":"02",
    "gn:admin2_code":"2706307.0",
    "gn:asciiname":"Posangue",
    "gn:country_code":"BR",
    "gn:dem":505,
    "gn:feature_class":"P",
    "gn:feature_code":"PPL",
    "gn:name":"Posangue",
    "gn:population":0,
    "gn:timezone":"America/Maceio",
    "iso:country":"BR",
    "wof:name":"Posangue",
    "wof:placetype":"locality"
},
  "geometry": {"coordinates":[-36.58333,-9.36667],"type":"Point"}
}