{
  "type": "Feature",
  "properties": {
    "gn:admin1_code":"26.0",
    "gn:admin2_code":"4209300.0",
    "gn:asciiname":"Ramada",
    "gn:country_code":"BR",
    "gn:dem":991,
    "gn:feature_class":"P",
    "gn:feature_code":"PPL",
    "gn:name":"Ramada",
    "gn:population":0,
    "gn:timezone":"America/Sao_Paulo",
    "iso:country":"BR",
    "name:deu_x_preferred":[
        "Ramada Worldwide"
    ],
    "name:kor_x_preferred":[
        "\ub77c\ub9c8\ub2e4"
    ],
    "name:mal_x_preferred":[
        "\u0d30\u0d2e\u0d3e\u0d26 \u0d05\u0d2e\u0d43\u0d24\u0d4d\u0d38\u0d7c"
    ],
    "name:msa_x_preferred":[
        "Ramada"
    ],
    "name:ron_x_preferred":[
        "Ramada"
    ],
    "name:rus_x_preferred":[
        "\u0420\u0430\u043c\u0430\u0434\u0430"
    ],
    "name:sco_x_preferred":[
        "Ramada"
    ],
    "name:spa_x_preferred":[
        "Ramada Worldwide"
    ],
    "name:ukr_x_preferred":[
        "\u0420\u0430\u043c\u0430\u0434\u0430"
    ],
    "wof:name":"Ramada",
    "wof:placetype":"locality"
},
  "geometry": {"coordinates":[-50.58964,-28.35968],"type":"Point"}
}