{
  "type": "Feature",
  "properties": {
    "gn:admin1_code":"26.0",
    "gn:admin2_code":"4209300.0",
    "gn:asciiname":"Ramada",
    "gn:country_code":"BR",
    "gn:dem":991,
    "gn:feature_class":"P",
    "gn:feature_code":"PPL",
    "gn:name":"Ramada",
    "gn:population":0,
    "gn:timezone":"America/Sao_Paulo",
    "iso:country":"BR",
    "wof:name":"Ramada",
    "wof:placetype":"locality"
},
  "geometry": {"coordinates":[-50.58964,-28.35968],"type":"Point"}
}