{
  "type": "Feature",
  "properties": {
    "gn:admin1_code":"18.0",
    "gn:admin2_code":"4114302.0",
    "gn:asciiname":"Sitio Manoel de Oliveira",
    "gn:country_code":"BR",
    "gn:dem":904,
    "gn:feature_class":"P",
    "gn:feature_code":"PPL",
    "gn:name":"S\u00edtio Manoel de Oliveira",
    "gn:population":0,
    "gn:timezone":"America/Sao_Paulo",
    "iso:country":"BR",
    "name:por_x_preferred":[
        "S\u00edtio Manoel de Oliveira"
    ],
    "wof:name":"Sitio Manoel de Oliveira",
    "wof:placetype":"locality"
},
  "geometry": {"coordinates":[-49.3172,-25.8374],"type":"Point"}
}