{
  "type": "Feature",
  "properties": {
    "gn:admin1_code":"5",
    "gn:admin2_code":"2921203.0",
    "gn:asciiname":"Praca",
    "gn:country_code":"BR",
    "gn:dem":914,
    "gn:feature_class":"P",
    "gn:feature_code":"PPL",
    "gn:name":"Pra\u00e7a",
    "gn:population":0,
    "gn:timezone":"America/Bahia",
    "iso:country":"BR",
    "name:ceb_x_preferred":[
        "Praca"
    ],
    "name:swe_x_preferred":[
        "Praca"
    ],
    "wof:name":"Praca",
    "wof:placetype":"locality"
},
  "geometry": {"coordinates":[-40.75,-11.26667],"type":"Point"}
}