{
  "type": "Feature",
  "properties": {
    "gn:admin1_code":"5",
    "gn:admin2_code":"2917201.0",
    "gn:asciiname":"Fernanda",
    "gn:country_code":"BR",
    "gn:dem":635,
    "gn:feature_class":"P",
    "gn:feature_code":"PPL",
    "gn:name":"Fernanda",
    "gn:population":0,
    "gn:timezone":"America/Bahia",
    "iso:country":"BR",
    "name:bre_x_preferred":[
        "Fernanda"
    ],
    "name:deu_x_preferred":[
        "Fernanda"
    ],
    "name:epo_x_preferred":[
        "Ferdinanda"
    ],
    "name:spa_x_preferred":[
        "Fernanda"
    ],
    "wof:name":"Fernanda",
    "wof:placetype":"locality"
},
  "geometry": {"coordinates":[-41.59179,-13.67251],"type":"Point"}
}