{
  "type": "Feature",
  "properties": {
    "gn:admin1_code":"18",
    "gn:admin2_code":"4119004.0",
    "gn:asciiname":"Santo Antonio",
    "gn:country_code":"BR",
    "gn:dem":367,
    "gn:feature_class":"P",
    "gn:feature_code":"PPL",
    "gn:name":"Santo Ant\u00f4nio",
    "gn:population":0,
    "gn:timezone":"America/Sao_Paulo",
    "iso:country":"BR",
    "wof:name":"Santo Antonio",
    "wof:placetype":"locality"
},
  "geometry": {"coordinates":[-53.83333,-25.83333],"type":"Point"}
}