{
  "type": "Feature",
  "properties": {
    "gn:admin1_code":"15.0",
    "gn:admin2_code":"3135076.0",
    "gn:asciiname":"Sao Sebastiao do Barriero",
    "gn:country_code":"BR",
    "gn:dem":314,
    "gn:feature_class":"P",
    "gn:feature_code":"PPL",
    "gn:name":"S\u00e3o Sebasti\u00e3o do Barriero",
    "gn:population":0,
    "gn:timezone":"America/Sao_Paulo",
    "iso:country":"BR",
    "name:por_x_preferred":[
        "S\u00e3o Sebasti\u00e3o do Barriero"
    ],
    "wof:name":"Sao Sebastiao do Barriero",
    "wof:placetype":"locality"
},
  "geometry": {"coordinates":[-41.64484,-18.58976],"type":"Point"}
}