{
  "type": "Feature",
  "properties": {
    "gn:admin1_code":"23",
    "gn:admin2_code":"4302709.0",
    "gn:asciiname":"Alfredo Silveira",
    "gn:country_code":"BR",
    "gn:dem":193,
    "gn:feature_class":"P",
    "gn:feature_code":"PPL",
    "gn:name":"Alfredo Silveira",
    "gn:population":0,
    "gn:timezone":"America/Sao_Paulo",
    "iso:country":"BR",
    "wof:name":"Alfredo Silveira",
    "wof:placetype":"locality"
},
  "geometry": {"coordinates":[-52.08333,-30.35],"type":"Point"}
}