{
  "type": "Feature",
  "properties": {
    "gn:admin1_code":"18.0",
    "gn:admin2_code":"4114302.0",
    "gn:asciiname":"Sitio Alfredo S. Camargo",
    "gn:country_code":"BR",
    "gn:dem":873,
    "gn:feature_class":"P",
    "gn:feature_code":"PPL",
    "gn:name":"S\u00edtio Alfredo S. Camargo",
    "gn:population":0,
    "gn:timezone":"America/Sao_Paulo",
    "iso:country":"BR",
    "name:por_x_preferred":[
        "S\u00edtio Alfredo S. Camargo"
    ],
    "wof:name":"Sitio Alfredo S. Camargo",
    "wof:placetype":"locality"
},
  "geometry": {"coordinates":[-49.2882,-25.9212],"type":"Point"}
}