{
  "type": "Feature",
  "properties": {
    "gn:admin1_code":"18",
    "gn:admin2_code":"4104105.0",
    "gn:asciiname":"Sitio Luiz Dimbiski",
    "gn:country_code":"BR",
    "gn:dem":868,
    "gn:feature_class":"P",
    "gn:feature_code":"PPL",
    "gn:name":"S\u00edtio Luiz Dimbiski",
    "gn:population":0,
    "gn:timezone":"America/Sao_Paulo",
    "iso:country":"BR",
    "name:por_x_preferred":[
        "S\u00edtio Luiz Dimbiski"
    ],
    "wof:name":"Sitio Luiz Dimbiski",
    "wof:placetype":"locality"
},
  "geometry": {"coordinates":[-49.72669000000001,-26.00452],"type":"Point"}
}