{
  "type": "Feature",
  "properties": {
    "gn:admin1_code":"13",
    "gn:admin2_code":"2100808.0",
    "gn:asciiname":"Macuna",
    "gn:country_code":"BR",
    "gn:dem":84,
    "gn:feature_class":"P",
    "gn:feature_code":"PPL",
    "gn:name":"Macun\u00e3",
    "gn:population":0,
    "gn:timezone":"America/Fortaleza",
    "iso:country":"BR",
    "name:cat_x_preferred":[
        "Makuna"
    ],
    "name:cym_x_preferred":[
        "Macuna"
    ],
    "name:ita_x_preferred":[
        "Makuna"
    ],
    "name:por_x_preferred":[
        "Makuna"
    ],
    "name:spa_x_preferred":[
        "Macuna"
    ],
    "wof:name":"Macuna",
    "wof:placetype":"locality"
},
  "geometry": {"coordinates":[-43.09306,-3.63278],"type":"Point"}
}