{
  "type": "Feature",
  "properties": {
    "gn:admin1_code":"3",
    "gn:admin2_code":"1600204.0",
    "gn:asciiname":"Boa Esperanca",
    "gn:country_code":"BR",
    "gn:dem":21,
    "gn:feature_class":"P",
    "gn:feature_code":"PPL",
    "gn:name":"Boa Esperan\u00e7a",
    "gn:population":0,
    "gn:timezone":"America/Belem",
    "iso:country":"BR",
    "wof:name":"Boa Esperanca",
    "wof:placetype":"locality"
},
  "geometry": {"coordinates":[-51.03314,2.82809],"type":"Point"}
}