{
  "type": "Feature",
  "properties": {
    "gn:admin1_code":"18.0",
    "gn:admin2_code":"4127809.0",
    "gn:asciiname":"Sitio Tarcisio Mendonca",
    "gn:country_code":"BR",
    "gn:dem":702,
    "gn:feature_class":"P",
    "gn:feature_code":"PPL",
    "gn:name":"S\u00edtio Tarc\u00edsio Mendon\u00e7a",
    "gn:population":0,
    "gn:timezone":"America/Sao_Paulo",
    "iso:country":"BR",
    "name:por_x_preferred":[
        "S\u00edtio Tarc\u00edsio Mendon\u00e7a"
    ],
    "wof:name":"Sitio Tarcisio Mendonca",
    "wof:placetype":"locality"
},
  "geometry": {"coordinates":[-49.9122,-23.6751],"type":"Point"}
}