{
  "type": "Feature",
  "properties": {
    "gn:admin1_code":"18.0",
    "gn:admin2_code":"4126207.0",
    "gn:asciiname":"Sitio Luis",
    "gn:country_code":"BR",
    "gn:dem":756,
    "gn:feature_class":"P",
    "gn:feature_code":"PPL",
    "gn:name":"S\u00edtio Lu\u00eds",
    "gn:population":0,
    "gn:timezone":"America/Sao_Paulo",
    "iso:country":"BR",
    "name:por_x_preferred":[
        "S\u00edtio Lu\u00eds"
    ],
    "wof:name":"Sitio Luis",
    "wof:placetype":"locality"
},
  "geometry": {"coordinates":[-50.58562,-23.8185],"type":"Point"}
}