{
  "type": "Feature",
  "properties": {
    "gn:admin1_code":"5",
    "gn:admin2_code":"2921401.0",
    "gn:asciiname":"Gado Bravo",
    "gn:cc2":"BR",
    "gn:country_code":"BR",
    "gn:dem":719,
    "gn:feature_class":"P",
    "gn:feature_code":"PPL",
    "gn:name":"Gado Bravo",
    "gn:population":0,
    "gn:timezone":"America/Bahia",
    "iso:country":"BR",
    "name:und_x_variant":[
        "Cado Bravo",
        "Gado Bravo"
    ],
    "wof:name":"Gado Bravo",
    "wof:placetype":"locality"
},
  "geometry": {"coordinates":[-40.56667,-10.73333],"type":"Point"}
}