{
  "type": "Feature",
  "properties": {
    "gn:admin1_code":"27",
    "gn:admin2_code":"3519709.0",
    "gn:asciiname":"Sitio Kanie",
    "gn:country_code":"BR",
    "gn:dem":873,
    "gn:feature_class":"P",
    "gn:feature_code":"PPL",
    "gn:name":"S\u00edtio Kanie",
    "gn:population":0,
    "gn:timezone":"America/Sao_Paulo",
    "iso:country":"BR",
    "name:por_x_preferred":[
        "S\u00edtio Kanie"
    ],
    "wof:name":"Sitio Kanie",
    "wof:placetype":"locality"
},
  "geometry": {"coordinates":[-47.12513,-23.7492],"type":"Point"}
}