{
  "type": "Feature",
  "properties": {
    "gn:admin1_code":"02",
    "gn:admin2_code":"2701605.0",
    "gn:asciiname":"Raimundo",
    "gn:country_code":"BR",
    "gn:dem":377,
    "gn:feature_class":"P",
    "gn:feature_code":"PPL",
    "gn:name":"Raimundo",
    "gn:population":0,
    "gn:timezone":"America/Maceio",
    "iso:country":"BR",
    "name:ceb_x_preferred":[
        "Raimundo"
    ],
    "name:jpn_x_preferred":[
        "\u30e9\u30a4\u30e0\u30f3\u30c9"
    ],
    "name:por_x_preferred":[
        "Raimundo"
    ],
    "name:swe_x_preferred":[
        "Raimundo"
    ],
    "wof:name":"Raimundo",
    "wof:placetype":"locality"
},
  "geometry": {"coordinates":[-37.56667,-9.05],"type":"Point"}
}