{
  "type": "Feature",
  "properties": {
    "gn:admin1_code":"02",
    "gn:admin2_code":"2701605.0",
    "gn:asciiname":"Raimundo",
    "gn:country_code":"BR",
    "gn:dem":377,
    "gn:feature_class":"P",
    "gn:feature_code":"PPL",
    "gn:name":"Raimundo",
    "gn:population":0,
    "gn:timezone":"America/Maceio",
    "iso:country":"BR",
    "wof:name":"Raimundo",
    "wof:placetype":"locality"
},
  "geometry": {"coordinates":[-37.56667,-9.05],"type":"Point"}
}