{
  "type": "Feature",
  "properties": {
    "gn:admin1_code":"27",
    "gn:admin2_code":"3546801.0",
    "gn:asciiname":"Stio Ip",
    "gn:country_code":"BR",
    "gn:dem":698,
    "gn:feature_class":"P",
    "gn:feature_code":"PPL",
    "gn:name":"Stio Ip",
    "gn:population":0,
    "gn:timezone":"America/Sao_Paulo",
    "iso:country":"BR",
    "name:por_x_preferred":[
        "Stio Ip"
    ],
    "wof:name":"Stio Ip",
    "wof:placetype":"locality"
},
  "geometry": {"coordinates":[-46.2451,-23.3415],"type":"Point"}
}