{
  "type": "Feature",
  "properties": {
    "gn:admin1_code":"17",
    "gn:admin2_code":"2504504.0",
    "gn:asciiname":"Mororo",
    "gn:country_code":"BR",
    "gn:dem":200,
    "gn:feature_class":"P",
    "gn:feature_code":"PPL",
    "gn:name":"Moror\u00f3",
    "gn:population":0,
    "gn:timezone":"America/Fortaleza",
    "iso:country":"BR",
    "wof:name":"Mororo",
    "wof:placetype":"locality"
},
  "geometry": {"coordinates":[-37.63333,-6.75],"type":"Point"}
}