{
  "type": "Feature",
  "properties": {
    "gn:admin1_code":"04",
    "gn:admin2_code":"1300144.0",
    "gn:asciiname":"Paraiso",
    "gn:country_code":"BR",
    "gn:dem":109,
    "gn:feature_class":"P",
    "gn:feature_code":"PPL",
    "gn:name":"Para\u00edso",
    "gn:population":0,
    "gn:timezone":"America/Manaus",
    "iso:country":"BR",
    "wof:name":"Paraiso",
    "wof:placetype":"locality"
},
  "geometry": {"coordinates":[-58.97528000000001,-6.69306],"type":"Point"}
}