{
  "type": "Feature",
  "properties": {
    "gn:admin1_code":"4",
    "gn:admin2_code":"1301209.0",
    "gn:asciiname":"Moura",
    "gn:country_code":"BR",
    "gn:dem":43,
    "gn:feature_class":"P",
    "gn:feature_code":"PPL",
    "gn:name":"Moura",
    "gn:population":0,
    "gn:timezone":"America/Manaus",
    "iso:country":"BR",
    "name:ceb_x_preferred":[
        "Moura"
    ],
    "name:deu_x_preferred":[
        "Moura"
    ],
    "name:fra_x_preferred":[
        "Moura"
    ],
    "name:glg_x_preferred":[
        "Moura"
    ],
    "name:jpn_x_preferred":[
        "\u30e2\u30a6\u30e9"
    ],
    "name:por_x_preferred":[
        "Moura"
    ],
    "name:rus_x_preferred":[
        "\u041c\u043e\u0443\u0440\u0430"
    ],
    "wof:name":"Moura",
    "wof:placetype":"locality"
},
  "geometry": {"coordinates":[-63.4175,-4.11833],"type":"Point"}
}