{
  "type": "Feature",
  "properties": {
    "gn:admin1_code":"4",
    "gn:admin2_code":"1301209.0",
    "gn:asciiname":"Moura",
    "gn:country_code":"BR",
    "gn:dem":43,
    "gn:feature_class":"P",
    "gn:feature_code":"PPL",
    "gn:name":"Moura",
    "gn:population":0,
    "gn:timezone":"America/Manaus",
    "iso:country":"BR",
    "wof:name":"Moura",
    "wof:placetype":"locality"
},
  "geometry": {"coordinates":[-63.4175,-4.11833],"type":"Point"}
}