{
  "type": "Feature",
  "properties": {
    "gn:admin1_code":"5",
    "gn:admin2_code":"2914703.0",
    "gn:asciiname":"Lajedo de Baixo",
    "gn:country_code":"BR",
    "gn:dem":342,
    "gn:feature_class":"P",
    "gn:feature_code":"PPL",
    "gn:name":"Lajedo de Baixo",
    "gn:population":0,
    "gn:timezone":"America/Bahia",
    "iso:country":"BR",
    "wof:name":"Lajedo de Baixo",
    "wof:placetype":"locality"
},
  "geometry": {"coordinates":[-40.41667,-12.48333],"type":"Point"}
}