{
  "type": "Feature",
  "properties": {
    "gn:admin1_code":"27.0",
    "gn:admin2_code":"3542800.0",
    "gn:asciiname":"Lavra",
    "gn:country_code":"BR",
    "gn:dem":830,
    "gn:feature_class":"P",
    "gn:feature_code":"PPLL",
    "gn:name":"Lavra",
    "gn:population":0,
    "gn:timezone":"America/Sao_Paulo",
    "iso:country":"BR",
    "name:afr_x_preferred":[
        "Lawra"
    ],
    "name:bel_x_preferred":[
        "\u041b\u0430\u045e\u0440\u0430"
    ],
    "name:cat_x_preferred":[
        "Laura"
    ],
    "name:ces_x_preferred":[
        "L\u00e1vra"
    ],
    "name:dan_x_preferred":[
        "Lavra"
    ],
    "name:deu_x_preferred":[
        "Lawra"
    ],
    "name:fin_x_preferred":[
        "Lavra"
    ],
    "name:fra_x_preferred":[
        "Laure"
    ],
    "name:heb_x_preferred":[
        "\u05dc\u05d0\u05d5\u05e8\u05d4"
    ],
    "name:hrv_x_preferred":[
        "Lavra"
    ],
    "name:hun_x_preferred":[
        "Lavra"
    ],
    "name:hye_x_preferred":[
        "\u0544\u0561\u0575\u0580\u0561\u057e\u0561\u0576\u0584"
    ],
    "name:ita_x_preferred":[
        "Laura"
    ],
    "name:jpn_x_preferred":[
        "\u30e9\u30f4\u30e9"
    ],
    "name:kat_x_preferred":[
        "\u10da\u10d0\u10d5\u10e0\u10d0"
    ],
    "name:kor_x_preferred":[
        "\ub77c\ube0c\ub77c"
    ],
    "name:nld_x_preferred":[
        "Laura"
    ],
    "name:nor_x_preferred":[
        "Lavra"
    ],
    "name:pol_x_preferred":[
        "\u0141awra"
    ],
    "name:por_x_preferred":[
        "Lavra"
    ],
    "name:ron_x_preferred":[
        "Lavr\u0103"
    ],
    "name:rus_x_preferred":[
        "\u041b\u0430\u0432\u0440\u0430"
    ],
    "name:slk_x_preferred":[
        "Lavra"
    ],
    "name:spa_x_preferred":[
        "Laura"
    ],
    "name:srp_x_preferred":[
        "\u041b\u0430\u0432\u0440\u0430"
    ],
    "name:swe_x_preferred":[
        "Lavra"
    ],
    "name:ukr_x_preferred":[
        "\u041b\u0430\u0432\u0440\u0430"
    ],
    "name:zho_x_preferred":[
        "\u62c9\u4f0f\u62c9"
    ],
    "wof:name":"Lavra",
    "wof:placetype":"locality"
},
  "geometry": {"coordinates":[-48.98546,-24.53219],"type":"Point"}
}