{
  "type": "Feature",
  "properties": {
    "gn:admin1_code":"15",
    "gn:admin2_code":"3141306.0",
    "gn:asciiname":"Anacleto",
    "gn:country_code":"BR",
    "gn:dem":930,
    "gn:feature_class":"P",
    "gn:feature_code":"PPL",
    "gn:name":"Anacleto",
    "gn:population":0,
    "gn:timezone":"America/Sao_Paulo",
    "iso:country":"BR",
    "name:por_x_preferred":[
        "Anacleto"
    ],
    "wof:name":"Anacleto",
    "wof:placetype":"locality"
},
  "geometry": {"coordinates":[-46.36667,-20.03333],"type":"Point"}
}