{
  "type": "Feature",
  "properties": {
    "gn:admin1_code":"18.0",
    "gn:admin2_code":"4121208.0",
    "gn:asciiname":"Sitio Albano Patla",
    "gn:country_code":"BR",
    "gn:dem":927,
    "gn:feature_class":"P",
    "gn:feature_code":"PPL",
    "gn:name":"S\u00edtio Albano Patla",
    "gn:population":0,
    "gn:timezone":"America/Sao_Paulo",
    "iso:country":"BR",
    "name:por_x_preferred":[
        "S\u00edtio Albano Patla"
    ],
    "wof:name":"Sitio Albano Patla",
    "wof:placetype":"locality"
},
  "geometry": {"coordinates":[-49.4157,-25.8196],"type":"Point"}
}