{
  "type": "Feature",
  "properties": {
    "gn:admin1_code":"20",
    "gn:admin2_code":"2206670.0",
    "gn:asciiname":"Malhada de Baixo",
    "gn:country_code":"BR",
    "gn:dem":33,
    "gn:feature_class":"P",
    "gn:feature_code":"PPL",
    "gn:name":"Malhada de Baixo",
    "gn:population":0,
    "gn:timezone":"America/Fortaleza",
    "iso:country":"BR",
    "wof:name":"Malhada de Baixo",
    "wof:placetype":"locality"
},
  "geometry": {"coordinates":[-42.23194,-3.62361],"type":"Point"}
}