{
  "type": "Feature",
  "properties": {
    "gn:admin1_code":"06",
    "gn:admin2_code":"2312601.0",
    "gn:asciiname":"Fazenda Curral Velho",
    "gn:country_code":"BR",
    "gn:dem":35,
    "gn:feature_class":"P",
    "gn:feature_code":"PPL",
    "gn:name":"Fazenda Curral Velho",
    "gn:population":0,
    "gn:timezone":"America/Fortaleza",
    "iso:country":"BR",
    "wof:name":"Fazenda Curral Velho",
    "wof:placetype":"locality"
},
  "geometry": {"coordinates":[-39.26667,-3.61667],"type":"Point"}
}