{
  "type": "Feature",
  "properties": {
    "gn:admin1_code":"20",
    "gn:admin2_code":"2206951.0",
    "gn:asciiname":"Pau d'Arco",
    "gn:country_code":"BR",
    "gn:dem":220,
    "gn:feature_class":"P",
    "gn:feature_code":"PPL",
    "gn:name":"Pau d\u2019Arco",
    "gn:population":0,
    "gn:timezone":"America/Fortaleza",
    "iso:country":"BR",
    "wof:name":"Pau d'Arco",
    "wof:placetype":"locality"
},
  "geometry": {"coordinates":[-41.91667,-5.18333],"type":"Point"}
}