{
  "type": "Feature",
  "properties": {
    "gn:admin1_code":"27",
    "gn:admin2_code":"3504107.0",
    "gn:asciiname":"Sitio Bonanza",
    "gn:country_code":"BR",
    "gn:dem":777,
    "gn:feature_class":"P",
    "gn:feature_code":"PPL",
    "gn:name":"S\u00edtio Bonanza",
    "gn:population":0,
    "gn:timezone":"America/Sao_Paulo",
    "iso:country":"BR",
    "name:por_x_preferred":[
        "S\u00edtio Bonanza"
    ],
    "wof:name":"Sitio Bonanza",
    "wof:placetype":"locality"
},
  "geometry": {"coordinates":[-46.66542000000001,-23.03312],"type":"Point"}
}