{
  "type": "Feature",
  "properties": {
    "gn:admin1_code":"20",
    "gn:admin2_code":"2205359.0",
    "gn:asciiname":"Sao Joao Vermelho",
    "gn:country_code":"BR",
    "gn:dem":418,
    "gn:feature_class":"P",
    "gn:feature_code":"PPL",
    "gn:name":"S\u00e3o Jo\u00e3o Vermelho",
    "gn:population":0,
    "gn:timezone":"America/Fortaleza",
    "iso:country":"BR",
    "wof:name":"Sao Joao Vermelho",
    "wof:placetype":"locality"
},
  "geometry": {"coordinates":[-42.48333,-8.63333],"type":"Point"}
}