{
  "type": "Feature",
  "properties": {
    "gn:admin1_code":"20",
    "gn:admin2_code":"2209955.0",
    "gn:asciiname":"Barro Branco",
    "gn:country_code":"BR",
    "gn:dem":232,
    "gn:feature_class":"P",
    "gn:feature_code":"PPL",
    "gn:name":"Barro Branco",
    "gn:population":0,
    "gn:timezone":"America/Fortaleza",
    "iso:country":"BR",
    "wof:name":"Barro Branco",
    "wof:placetype":"locality"
},
  "geometry": {"coordinates":[-41.93333,-6.96667],"type":"Point"}
}