{
  "type": "Feature",
  "properties": {
    "gn:admin1_code":"17",
    "gn:admin2_code":"2508604.0",
    "gn:asciiname":"Costinha",
    "gn:country_code":"BR",
    "gn:dem":9,
    "gn:feature_class":"P",
    "gn:feature_code":"PPL",
    "gn:name":"Costinha",
    "gn:population":0,
    "gn:timezone":"America/Fortaleza",
    "iso:country":"BR",
    "wof:name":"Costinha",
    "wof:placetype":"locality"
},
  "geometry": {"coordinates":[-34.85833,-6.96556],"type":"Point"}
}