{
  "type": "Feature",
  "properties": {
    "gn:admin1_code":"17",
    "gn:admin2_code":"2508604.0",
    "gn:asciiname":"Costinha",
    "gn:country_code":"BR",
    "gn:dem":9,
    "gn:feature_class":"P",
    "gn:feature_code":"PPL",
    "gn:name":"Costinha",
    "gn:population":0,
    "gn:timezone":"America/Fortaleza",
    "iso:country":"BR",
    "name:ara_x_preferred":[
        "\u0643\u0648\u0633\u062a\u064a\u0646\u064a\u0627"
    ],
    "name:azb_x_preferred":[
        "\u06a9\u0627\u0633\u062a\u06cc\u0646\u0627"
    ],
    "name:bul_x_preferred":[
        "\u041a\u043e\u0449\u0438\u043d\u044f"
    ],
    "name:ces_x_preferred":[
        "Costinha"
    ],
    "name:deu_x_preferred":[
        "Costinha"
    ],
    "name:fas_x_preferred":[
        "\u06a9\u0627\u0633\u062a\u06cc\u0646\u0627"
    ],
    "name:fin_x_preferred":[
        "Costinha"
    ],
    "name:heb_x_preferred":[
        "\u05e7\u05d5\u05e9\u05d8\u05d9\u05e0\u05d9\u05d4"
    ],
    "name:hrv_x_preferred":[
        "Costinha"
    ],
    "name:hun_x_preferred":[
        "Costinha"
    ],
    "name:ind_x_preferred":[
        "Costinha"
    ],
    "name:ita_x_preferred":[
        "Costinha"
    ],
    "name:jpn_x_preferred":[
        "\u30b3\u30b9\u30c1\u30fc\u30cb\u30e3"
    ],
    "name:kaz_x_preferred":[
        "\u041a\u043e\u0448\u0442\u0438\u043d\u044c\u044f"
    ],
    "name:lit_x_preferred":[
        "Costinha"
    ],
    "name:mkd_x_preferred":[
        "\u041a\u043e\u0448\u0442\u0438\u045a\u0430"
    ],
    "name:nld_x_preferred":[
        "Costinha"
    ],
    "name:nor_x_preferred":[
        "Costinha"
    ],
    "name:pol_x_preferred":[
        "Costinha"
    ],
    "name:por_x_preferred":[
        "Costinha"
    ],
    "name:rus_x_preferred":[
        "\u041a\u043e\u0448\u0442\u0438\u043d\u044c\u044f"
    ],
    "name:spa_x_preferred":[
        "Costinha"
    ],
    "name:srp_x_preferred":[
        "\u041a\u043e\u0448\u0442\u0438\u045a\u0430"
    ],
    "name:swe_x_preferred":[
        "Costinha"
    ],
    "name:tur_x_preferred":[
        "Costinha"
    ],
    "name:ukr_x_preferred":[
        "\u041a\u043e\u0448\u0442\u0456\u043d\u044c\u044f"
    ],
    "name:zho_x_preferred":[
        "\u54e5\u65af\u7538\u4e9e"
    ],
    "wof:name":"Costinha",
    "wof:placetype":"locality"
},
  "geometry": {"coordinates":[-34.85833,-6.96556],"type":"Point"}
}