{
  "type": "Feature",
  "properties": {
    "gn:admin1_code":"15",
    "gn:admin2_code":"3129905.0",
    "gn:asciiname":"Serrote",
    "gn:country_code":"BR",
    "gn:dem":995,
    "gn:feature_class":"P",
    "gn:feature_code":"PPL",
    "gn:name":"Serrote",
    "gn:population":0,
    "gn:timezone":"America/Sao_Paulo",
    "iso:country":"BR",
    "name:por_x_preferred":[
        "Serrote"
    ],
    "wof:name":"Serrote",
    "wof:placetype":"locality"
},
  "geometry": {"coordinates":[-46.38333,-22.06667],"type":"Point"}
}