{
  "type": "Feature",
  "properties": {
    "gn:admin1_code":"26",
    "gn:admin2_code":"4202057.0",
    "gn:asciiname":"Barra do Sul",
    "gn:country_code":"BR",
    "gn:dem":6,
    "gn:feature_class":"P",
    "gn:feature_code":"PPL",
    "gn:name":"Barra do Sul",
    "gn:population":0,
    "gn:timezone":"America/Sao_Paulo",
    "iso:country":"BR",
    "name:por_x_preferred":[
        "Barra do Sul"
    ],
    "name:por_x_variant":[
        "Barra do Araquari"
    ],
    "wof:name":"Barra do Sul",
    "wof:placetype":"locality"
},
  "geometry": {"coordinates":[-48.61042,-26.46816],"type":"Point"}
}