{
  "type": "Feature",
  "properties": {
    "gn:admin1_code":"27",
    "gn:admin2_code":"3530706.0",
    "gn:asciiname":"Barreiro",
    "gn:cc2":"BR",
    "gn:country_code":"BR",
    "gn:dem":717,
    "gn:feature_class":"P",
    "gn:feature_code":"PPL",
    "gn:name":"Barreiro",
    "gn:population":0,
    "gn:timezone":"America/Sao_Paulo",
    "iso:country":"BR",
    "name:ceb_x_preferred":[
        "Barreiro"
    ],
    "name:deu_x_preferred":[
        "Barreiro"
    ],
    "name:fra_x_preferred":[
        "Barreiro"
    ],
    "name:glg_x_preferred":[
        "Barreiro"
    ],
    "name:ita_x_preferred":[
        "Barreiro"
    ],
    "name:nld_x_preferred":[
        "Barreiro"
    ],
    "name:por_x_preferred":[
        "Barreiro"
    ],
    "name:spa_x_preferred":[
        "Barreiro"
    ],
    "name:swe_x_preferred":[
        "Barreiro"
    ],
    "name:und_x_variant":[
        "Fazenda Barreiro",
        "Barreiro"
    ],
    "wof:name":"Barreiro",
    "wof:placetype":"locality"
},
  "geometry": {"coordinates":[-47.11804,-22.21657],"type":"Point"}
}