{
  "type": "Feature",
  "properties": {
    "gn:admin1_code":"18.0",
    "gn:admin2_code":"4124301.0",
    "gn:asciiname":"Sitio Sao Manuel",
    "gn:country_code":"BR",
    "gn:dem":708,
    "gn:feature_class":"P",
    "gn:feature_code":"PPL",
    "gn:name":"S\u00edtio S\u00e3o Manuel",
    "gn:population":0,
    "gn:timezone":"America/Sao_Paulo",
    "iso:country":"BR",
    "name:por_x_preferred":[
        "S\u00edtio S\u00e3o Manuel"
    ],
    "wof:name":"Sitio Sao Manuel",
    "wof:placetype":"locality"
},
  "geometry": {"coordinates":[-50.64188,-23.56654],"type":"Point"}
}