{
  "type": "Feature",
  "properties": {
    "gn:admin1_code":"18",
    "gn:admin2_code":"4104105.0",
    "gn:asciiname":"Sitio Adalberto Bicudo",
    "gn:country_code":"BR",
    "gn:dem":810,
    "gn:feature_class":"P",
    "gn:feature_code":"PPL",
    "gn:name":"S\u00edtio Adalberto Bicudo",
    "gn:population":0,
    "gn:timezone":"America/Sao_Paulo",
    "iso:country":"BR",
    "name:por_x_preferred":[
        "S\u00edtio Adalberto Bicudo"
    ],
    "wof:name":"Sitio Adalberto Bicudo",
    "wof:placetype":"locality"
},
  "geometry": {"coordinates":[-49.64729000000001,-26.01038],"type":"Point"}
}