{
  "type": "Feature",
  "properties": {
    "gn:admin1_code":"21",
    "gn:admin2_code":"3304755.0",
    "gn:asciiname":"Porto de Santana",
    "gn:country_code":"BR",
    "gn:dem":2,
    "gn:feature_class":"P",
    "gn:feature_code":"PPL",
    "gn:name":"P\u00f4rto de Santana",
    "gn:population":0,
    "gn:timezone":"America/Sao_Paulo",
    "iso:country":"BR",
    "name:por_x_preferred":[
        "P\u00f4rto de Santana"
    ],
    "wof:name":"Porto de Santana",
    "wof:placetype":"locality"
},
  "geometry": {"coordinates":[-41.13333,-21.23333],"type":"Point"}
}