{
  "type": "Feature",
  "properties": {
    "gn:admin1_code":"22",
    "gn:admin2_code":"2409605.0",
    "gn:asciiname":"Catinga da Areia",
    "gn:country_code":"BR",
    "gn:dem":174,
    "gn:feature_class":"P",
    "gn:feature_code":"PPL",
    "gn:name":"Catinga da Areia",
    "gn:population":0,
    "gn:timezone":"America/Fortaleza",
    "iso:country":"BR",
    "wof:name":"Catinga da Areia",
    "wof:placetype":"locality"
},
  "geometry": {"coordinates":[-36.07667,-5.61972],"type":"Point"}
}