{
  "type": "Feature",
  "properties": {
    "gn:admin1_code":"4",
    "gn:admin2_code":"1302207.0",
    "gn:asciiname":"Pauxis",
    "gn:country_code":"BR",
    "gn:dem":59,
    "gn:feature_class":"P",
    "gn:feature_code":"PPL",
    "gn:name":"Pauxis",
    "gn:population":0,
    "gn:timezone":"America/Manaus",
    "iso:country":"BR",
    "wof:name":"Pauxis",
    "wof:placetype":"locality"
},
  "geometry": {"coordinates":[-66.03333000000001,-3.36667],"type":"Point"}
}