{
  "type": "Feature",
  "properties": {
    "gn:admin1_code":"17",
    "gn:admin2_code":"2504405.0",
    "gn:asciiname":"Gatos",
    "gn:country_code":"BR",
    "gn:dem":585,
    "gn:feature_class":"P",
    "gn:feature_code":"PPL",
    "gn:name":"Gatos",
    "gn:population":0,
    "gn:timezone":"America/Fortaleza",
    "iso:country":"BR",
    "wof:name":"Gatos",
    "wof:placetype":"locality"
},
  "geometry": {"coordinates":[-38.41667,-7.38333],"type":"Point"}
}