{
  "type": "Feature",
  "properties": {
    "gn:admin1_code":"18.0",
    "gn:admin2_code":"4116208.0",
    "gn:asciiname":"Sitio Adelino A. da Silva",
    "gn:country_code":"BR",
    "gn:dem":265,
    "gn:feature_class":"P",
    "gn:feature_code":"PPL",
    "gn:name":"S\u00edtio Adelino A. da Silva",
    "gn:population":0,
    "gn:timezone":"America/Sao_Paulo",
    "iso:country":"BR",
    "name:por_x_preferred":[
        "S\u00edtio Adelino A. da Silva"
    ],
    "wof:name":"Sitio Adelino A. da Silva",
    "wof:placetype":"locality"
},
  "geometry": {"coordinates":[-48.8436,-25.5636],"type":"Point"}
}