{
  "type": "Feature",
  "properties": {
    "gn:admin1_code":"30",
    "gn:admin2_code":"2607307.0",
    "gn:asciiname":"Feira Nova",
    "gn:country_code":"BR",
    "gn:dem":762,
    "gn:feature_class":"P",
    "gn:feature_code":"PPL",
    "gn:name":"Feira Nova",
    "gn:population":0,
    "gn:timezone":"America/Recife",
    "iso:country":"BR",
    "name:ceb_x_preferred":[
        "Feira Nova"
    ],
    "name:deu_x_preferred":[
        "Feira Nova"
    ],
    "name:fra_x_preferred":[
        "Feira Nova"
    ],
    "name:ita_x_preferred":[
        "Feira Nova"
    ],
    "name:kaz_x_preferred":[
        "\u0424\u0435\u0439\u0440\u0430-\u041d\u043e\u0432\u0430"
    ],
    "name:nld_x_preferred":[
        "Feira Nova"
    ],
    "name:nor_x_preferred":[
        "Feira Nova"
    ],
    "name:por_x_preferred":[
        "Feira Nova"
    ],
    "name:rus_x_preferred":[
        "\u0424\u0435\u0439\u0440\u0430-\u041d\u043e\u0432\u0430"
    ],
    "name:swe_x_preferred":[
        "Feira Nova"
    ],
    "name:vie_x_preferred":[
        "Feira Nova"
    ],
    "name:vol_x_preferred":[
        "Feira Nova"
    ],
    "wof:name":"Feira Nova",
    "wof:placetype":"locality"
},
  "geometry": {"coordinates":[-40.26667,-7.46667],"type":"Point"}
}