{
  "type": "Feature",
  "properties": {
    "gn:admin1_code":"20",
    "gn:admin2_code":"2209203.0",
    "gn:asciiname":"Taji",
    "gn:cc2":"BR",
    "gn:country_code":"BR",
    "gn:dem":259,
    "gn:feature_class":"P",
    "gn:feature_code":"PPL",
    "gn:name":"Taji",
    "gn:population":0,
    "gn:timezone":"America/Fortaleza",
    "iso:country":"BR",
    "name:und_x_variant":[
        "Fazenda Tagy",
        "Tagi",
        "Taji"
    ],
    "wof:name":"Taji",
    "wof:placetype":"locality"
},
  "geometry": {"coordinates":[-45.86667,-8.73333],"type":"Point"}
}