{
  "type": "Feature",
  "properties": {
    "gn:admin1_code":"20",
    "gn:admin2_code":"2205102.0",
    "gn:asciiname":"Tabuleiro Bom",
    "gn:country_code":"BR",
    "gn:dem":235,
    "gn:feature_class":"P",
    "gn:feature_code":"PPL",
    "gn:name":"Tabuleiro Bom",
    "gn:population":0,
    "gn:timezone":"America/Fortaleza",
    "iso:country":"BR",
    "wof:name":"Tabuleiro Bom",
    "wof:placetype":"locality"
},
  "geometry": {"coordinates":[-43.06667,-7.35],"type":"Point"}
}