{
  "type": "Feature",
  "properties": {
    "gn:admin1_code":"17",
    "gn:admin2_code":"2505907.0",
    "gn:asciiname":"Jenipapo",
    "gn:country_code":"BR",
    "gn:dem":274,
    "gn:feature_class":"P",
    "gn:feature_code":"PPL",
    "gn:name":"Jenipapo",
    "gn:population":0,
    "gn:timezone":"America/Fortaleza",
    "iso:country":"BR",
    "wof:name":"Jenipapo",
    "wof:placetype":"locality"
},
  "geometry": {"coordinates":[-37.76667,-7.13333],"type":"Point"}
}