{
  "type": "Feature",
  "properties": {
    "gn:admin1_code":"5",
    "gn:admin2_code":"2926301.0",
    "gn:asciiname":"Pau Branco",
    "gn:country_code":"BR",
    "gn:dem":243,
    "gn:feature_class":"P",
    "gn:feature_code":"PPL",
    "gn:name":"Pau Branco",
    "gn:population":0,
    "gn:timezone":"America/Bahia",
    "iso:country":"BR",
    "wof:name":"Pau Branco",
    "wof:placetype":"locality"
},
  "geometry": {"coordinates":[-39.45,-11.81667],"type":"Point"}
}