{
  "type": "Feature",
  "properties": {
    "gn:admin1_code":"20",
    "gn:admin2_code":"2202026.0",
    "gn:asciiname":"Espirito Santo",
    "gn:country_code":"BR",
    "gn:dem":202,
    "gn:feature_class":"P",
    "gn:feature_code":"PPL",
    "gn:name":"Esp\u00edrito Santo",
    "gn:population":0,
    "gn:timezone":"America/Fortaleza",
    "iso:country":"BR",
    "wof:name":"Espirito Santo",
    "wof:placetype":"locality"
},
  "geometry": {"coordinates":[-41.23333,-5.01667],"type":"Point"}
}