{
  "type": "Feature",
  "properties": {
    "gn:admin1_code":"15",
    "gn:admin2_code":"3134004.0",
    "gn:asciiname":"Franquilino Marques",
    "gn:cc2":"BR",
    "gn:country_code":"BR",
    "gn:dem":306,
    "gn:feature_class":"P",
    "gn:feature_code":"PPL",
    "gn:name":"Franquilino Marques",
    "gn:population":0,
    "gn:timezone":"America/Sao_Paulo",
    "iso:country":"BR",
    "name:und_x_variant":[
        "Fazenda Franquilino Marques",
        "Franquilino Marques"
    ],
    "wof:name":"Franquilino Marques",
    "wof:placetype":"locality"
},
  "geometry": {"coordinates":[-41.76667,-16.53333],"type":"Point"}
}