{
  "type": "Feature",
  "properties": {
    "gn:admin1_code":"15",
    "gn:admin2_code":"3121209.0",
    "gn:asciiname":"Guilhermino",
    "gn:country_code":"BR",
    "gn:dem":808,
    "gn:feature_class":"P",
    "gn:feature_code":"PPL",
    "gn:name":"Guilhermino",
    "gn:population":0,
    "gn:timezone":"America/Sao_Paulo",
    "iso:country":"BR",
    "name:por_x_preferred":[
        "Guilhermino"
    ],
    "wof:name":"Guilhermino",
    "wof:placetype":"locality"
},
  "geometry": {"coordinates":[-46.88333,-20.23333],"type":"Point"}
}