{
  "type": "Feature",
  "properties": {
    "gn:admin1_code":"18.0",
    "gn:admin2_code":"4101200.0",
    "gn:asciiname":"Sitio Vo Santos",
    "gn:country_code":"BR",
    "gn:dem":9,
    "gn:feature_class":"P",
    "gn:feature_code":"PPL",
    "gn:name":"S\u00edtio V\u00f4 Santos",
    "gn:population":0,
    "gn:timezone":"America/Sao_Paulo",
    "iso:country":"BR",
    "name:por_x_preferred":[
        "S\u00edtio V\u00f4 Santos"
    ],
    "wof:name":"Sitio Vo Santos",
    "wof:placetype":"locality"
},
  "geometry": {"coordinates":[-48.7329,-25.4546],"type":"Point"}
}