{
  "type": "Feature",
  "properties": {
    "gn:admin1_code":"27",
    "gn:admin2_code":"3513009.0",
    "gn:asciiname":"Sitio Pununduva",
    "gn:country_code":"BR",
    "gn:dem":928,
    "gn:feature_class":"P",
    "gn:feature_code":"PPL",
    "gn:name":"S\u00edtio Pununduva",
    "gn:population":0,
    "gn:timezone":"America/Sao_Paulo",
    "iso:country":"BR",
    "name:por_x_preferred":[
        "S\u00edtio Pununduva"
    ],
    "wof:name":"Sitio Pununduva",
    "wof:placetype":"locality"
},
  "geometry": {"coordinates":[-47.04279,-23.69599],"type":"Point"}
}