{
  "type": "Feature",
  "properties": {
    "gn:admin1_code":"20",
    "gn:admin2_code":"2202604.0",
    "gn:asciiname":"Arrecife",
    "gn:country_code":"BR",
    "gn:dem":329,
    "gn:feature_class":"P",
    "gn:feature_code":"PPL",
    "gn:name":"Arrecife",
    "gn:population":0,
    "gn:timezone":"America/Fortaleza",
    "iso:country":"BR",
    "name:ara_x_preferred":[
        "\u0623\u0631\u064a\u062b\u064a\u0641\u064a"
    ],
    "name:ast_x_preferred":[
        "Arrecife"
    ],
    "name:azb_x_preferred":[
        "\u0622\u0631\u062b\u06cc\u0641\u0647"
    ],
    "name:cat_x_preferred":[
        "Arrecife"
    ],
    "name:ceb_x_preferred":[
        "Arrecife"
    ],
    "name:dan_x_preferred":[
        "Arrecife"
    ],
    "name:deu_x_preferred":[
        "Arrecife"
    ],
    "name:eus_x_preferred":[
        "Arrecife"
    ],
    "name:fas_x_preferred":[
        "\u0622\u0631\u062b\u06cc\u0641\u0647"
    ],
    "name:fin_x_preferred":[
        "Arrecife"
    ],
    "name:fra_x_preferred":[
        "Arrecife"
    ],
    "name:gla_x_preferred":[
        "Arrecife"
    ],
    "name:glg_x_preferred":[
        "Arrecife"
    ],
    "name:heb_x_preferred":[
        "\u05d0\u05e8\u05e1\u05d9\u05e4\u05d4"
    ],
    "name:hun_x_preferred":[
        "Arrecife"
    ],
    "name:hye_x_preferred":[
        "\u0531\u0580\u0580\u0565\u057d\u056b\u0586\u0565"
    ],
    "name:ita_x_preferred":[
        "Arrecife"
    ],
    "name:jpn_x_preferred":[
        "\u30a2\u30ec\u30b7\u30d5\u30a7"
    ],
    "name:lat_x_preferred":[
        "Arrecife"
    ],
    "name:lit_x_preferred":[
        "Aresif\u0117"
    ],
    "name:ltz_x_preferred":[
        "Arrecife"
    ],
    "name:mlg_x_preferred":[
        "Arrecife"
    ],
    "name:msa_x_preferred":[
        "Arrecife"
    ],
    "name:nld_x_preferred":[
        "Arrecife"
    ],
    "name:nno_x_preferred":[
        "Arrecife"
    ],
    "name:nor_x_preferred":[
        "Arrecife"
    ],
    "name:pol_x_preferred":[
        "Arrecife"
    ],
    "name:por_x_preferred":[
        "Arrecife"
    ],
    "name:ron_x_preferred":[
        "Arrecife"
    ],
    "name:rus_x_preferred":[
        "\u0410\u0440\u0440\u0435\u0441\u0438\u0444\u0435"
    ],
    "name:spa_x_preferred":[
        "Arrecife"
    ],
    "name:srp_x_preferred":[
        "\u0410\u0440\u0435\u0441\u0438\u0444\u0435"
    ],
    "name:swe_x_preferred":[
        "Arrecife"
    ],
    "name:tat_x_preferred":[
        "\u0410\u0440\u0440\u0435\u0441\u0438\u0444\u0435"
    ],
    "name:ukr_x_preferred":[
        "\u0410\u0440\u0440\u0435\u0441\u0456\u0444\u0435"
    ],
    "name:uzb_x_preferred":[
        "Arrecife"
    ],
    "name:war_x_preferred":[
        "Arrecife"
    ],
    "name:zho_x_preferred":[
        "\u963f\u96f7\u897f\u8d39"
    ],
    "wof:name":"Arrecife",
    "wof:placetype":"locality"
},
  "geometry": {"coordinates":[-41.45,-5.21667],"type":"Point"}
}