{
  "type": "Feature",
  "properties": {
    "gn:admin1_code":"20",
    "gn:admin2_code":"2202604.0",
    "gn:asciiname":"Arrecife",
    "gn:country_code":"BR",
    "gn:dem":329,
    "gn:feature_class":"P",
    "gn:feature_code":"PPL",
    "gn:name":"Arrecife",
    "gn:population":0,
    "gn:timezone":"America/Fortaleza",
    "iso:country":"BR",
    "wof:name":"Arrecife",
    "wof:placetype":"locality"
},
  "geometry": {"coordinates":[-41.45,-5.21667],"type":"Point"}
}