{
  "type": "Feature",
  "properties": {
    "gn:admin1_code":"11",
    "gn:admin2_code":"5003207.0",
    "gn:asciiname":"Sao Cristovao",
    "gn:country_code":"BR",
    "gn:dem":134,
    "gn:feature_class":"P",
    "gn:feature_code":"PPL",
    "gn:name":"S\u00e3o Crist\u00f3v\u00e3o",
    "gn:population":0,
    "gn:timezone":"America/Campo_Grande",
    "iso:country":"BR",
    "wof:name":"Sao Cristovao",
    "wof:placetype":"locality"
},
  "geometry": {"coordinates":[-56.13333000000001,-17.75],"type":"Point"}
}