{
  "type": "Feature",
  "properties": {
    "gn:admin1_code":"13",
    "gn:admin2_code":"2101400.0",
    "gn:asciiname":"Ouro",
    "gn:country_code":"BR",
    "gn:dem":345,
    "gn:feature_class":"P",
    "gn:feature_code":"PPL",
    "gn:name":"Ouro",
    "gn:population":0,
    "gn:timezone":"America/Fortaleza",
    "iso:country":"BR",
    "wof:name":"Ouro",
    "wof:placetype":"locality"
},
  "geometry": {"coordinates":[-46.235,-8.16306],"type":"Point"}
}