{
  "type": "Feature",
  "properties": {
    "gn:admin1_code":"05",
    "gn:admin2_code":"2926004.0",
    "gn:asciiname":"Coroa da Ilha",
    "gn:country_code":"BR",
    "gn:dem":385,
    "gn:feature_class":"P",
    "gn:feature_code":"PPL",
    "gn:name":"Coroa da Ilha",
    "gn:population":0,
    "gn:timezone":"America/Bahia",
    "iso:country":"BR",
    "wof:name":"Coroa da Ilha",
    "wof:placetype":"locality"
},
  "geometry": {"coordinates":[-41.96667,-9.68333],"type":"Point"}
}