{
  "type": "Feature",
  "properties": {
    "gn:admin1_code":"27",
    "gn:admin2_code":"3554508.0",
    "gn:asciiname":"Ponte Alta",
    "gn:country_code":"BR",
    "gn:dem":605,
    "gn:feature_class":"P",
    "gn:feature_code":"PPLL",
    "gn:name":"Ponte Alta",
    "gn:population":0,
    "gn:timezone":"America/Sao_Paulo",
    "iso:country":"BR",
    "name:por_x_preferred":[
        "Ponte Alta"
    ],
    "wof:name":"Ponte Alta",
    "wof:placetype":"locality"
},
  "geometry": {"coordinates":[-47.72526,-23.04205],"type":"Point"}
}