{
  "type": "Feature",
  "properties": {
    "gn:admin1_code":"27",
    "gn:admin2_code":"3554508.0",
    "gn:asciiname":"Ponte Alta",
    "gn:country_code":"BR",
    "gn:dem":605,
    "gn:feature_class":"P",
    "gn:feature_code":"PPLL",
    "gn:name":"Ponte Alta",
    "gn:population":0,
    "gn:timezone":"America/Sao_Paulo",
    "iso:country":"BR",
    "name:bpy_x_preferred":[
        "\u09aa\u09cb\u09a8\u09cd\u099f\u09c7 \u0986\u09b2\u09cd\u099f\u09be"
    ],
    "name:ceb_x_preferred":[
        "Ponte Alta"
    ],
    "name:eus_x_preferred":[
        "Ponte Alta"
    ],
    "name:fra_x_preferred":[
        "Ponte Alta"
    ],
    "name:ina_x_preferred":[
        "Ponte Alta"
    ],
    "name:ita_x_preferred":[
        "Ponte Alta"
    ],
    "name:kat_x_preferred":[
        "\u10de\u10dd\u10dc\u10e2\u10d8-\u10d0\u10da\u10e2\u10d0"
    ],
    "name:mlg_x_preferred":[
        "Ponte Alta"
    ],
    "name:nld_x_preferred":[
        "Ponte Alta"
    ],
    "name:nor_x_preferred":[
        "Ponte Alta"
    ],
    "name:oci_x_preferred":[
        "Ponte Alta"
    ],
    "name:pol_x_preferred":[
        "Ponte Alta"
    ],
    "name:por_x_preferred":[
        "Ponte Alta"
    ],
    "name:ron_x_preferred":[
        "Ponte Alta"
    ],
    "name:rus_x_preferred":[
        "\u041f\u043e\u043d\u0442\u0438-\u0410\u043b\u0442\u0430"
    ],
    "name:swe_x_preferred":[
        "Ponte Alta"
    ],
    "name:vie_x_preferred":[
        "Ponte Alta"
    ],
    "name:vol_x_preferred":[
        "Ponte Alta"
    ],
    "name:war_x_preferred":[
        "Ponte Alta"
    ],
    "name:zho_x_preferred":[
        "\u84ec\u8482\u963f\u5c14\u5854"
    ],
    "wof:name":"Ponte Alta",
    "wof:placetype":"locality"
},
  "geometry": {"coordinates":[-47.72526,-23.04205],"type":"Point"}
}