{
  "type": "Feature",
  "properties": {
    "gn:admin1_code":"30",
    "gn:admin2_code":"2606507.0",
    "gn:asciiname":"Cercado",
    "gn:country_code":"BR",
    "gn:dem":388,
    "gn:feature_class":"P",
    "gn:feature_code":"PPL",
    "gn:name":"Cercado",
    "gn:population":0,
    "gn:timezone":"America/Maceio",
    "iso:country":"BR",
    "wof:name":"Cercado",
    "wof:placetype":"locality"
},
  "geometry": {"coordinates":[-36.96667,-9.35],"type":"Point"}
}