{
  "type": "Feature",
  "properties": {
    "gn:admin1_code":"30",
    "gn:admin2_code":"2614600.0",
    "gn:asciiname":"Queimadas",
    "gn:country_code":"BR",
    "gn:dem":574,
    "gn:feature_class":"P",
    "gn:feature_code":"PPL",
    "gn:name":"Queimadas",
    "gn:population":0,
    "gn:timezone":"America/Recife",
    "iso:country":"BR",
    "wof:name":"Queimadas",
    "wof:placetype":"locality"
},
  "geometry": {"coordinates":[-37.51667,-7.63333],"type":"Point"}
}