{
  "type": "Feature",
  "properties": {
    "gn:admin1_code":"11",
    "gn:admin2_code":"5003207.0",
    "gn:asciiname":"Tiradentes",
    "gn:country_code":"BR",
    "gn:dem":102,
    "gn:feature_class":"P",
    "gn:feature_code":"PPL",
    "gn:name":"Tiradentes",
    "gn:population":0,
    "gn:timezone":"America/Campo_Grande",
    "iso:country":"BR",
    "wof:name":"Tiradentes",
    "wof:placetype":"locality"
},
  "geometry": {"coordinates":[-56.71666999999999,-19.45],"type":"Point"}
}