{
  "type": "Feature",
  "properties": {
    "gn:admin1_code":"6",
    "gn:admin2_code":"2311959.0",
    "gn:asciiname":"Baixa do Meio",
    "gn:country_code":"BR",
    "gn:dem":609,
    "gn:feature_class":"P",
    "gn:feature_code":"PPL",
    "gn:name":"Baixa do Meio",
    "gn:population":0,
    "gn:timezone":"America/Fortaleza",
    "iso:country":"BR",
    "wof:name":"Baixa do Meio",
    "wof:placetype":"locality"
},
  "geometry": {"coordinates":[-40.38333,-7.16667],"type":"Point"}
}