{
  "type": "Feature",
  "properties": {
    "gn:admin1_code":"15",
    "gn:admin2_code":"3118403.0",
    "gn:asciiname":"Joao Pinto",
    "gn:country_code":"BR",
    "gn:dem":281,
    "gn:feature_class":"P",
    "gn:feature_code":"PPL",
    "gn:name":"Jo\u00e3o Pinto",
    "gn:population":0,
    "gn:timezone":"America/Sao_Paulo",
    "iso:country":"BR",
    "name:por_x_preferred":[
        "Jo\u00e3o Pinto"
    ],
    "wof:name":"Joao Pinto",
    "wof:placetype":"locality"
},
  "geometry": {"coordinates":[-41.51667,-19.26667],"type":"Point"}
}