{
  "type": "Feature",
  "properties": {
    "gn:admin1_code":"13",
    "gn:admin2_code":"2103208.0",
    "gn:asciiname":"Santo Antonio",
    "gn:country_code":"BR",
    "gn:dem":52,
    "gn:feature_class":"P",
    "gn:feature_code":"PPL",
    "gn:name":"Santo Ant\u00f4nio",
    "gn:population":0,
    "gn:timezone":"America/Fortaleza",
    "iso:country":"BR",
    "wof:name":"Santo Antonio",
    "wof:placetype":"locality"
},
  "geometry": {"coordinates":[-43.2925,-3.92639],"type":"Point"}
}