{
  "type": "Feature",
  "properties": {
    "gn:admin1_code":"27",
    "gn:admin2_code":"3533007.0",
    "gn:asciiname":"Pocao",
    "gn:country_code":"BR",
    "gn:dem":480,
    "gn:feature_class":"P",
    "gn:feature_code":"PPL",
    "gn:name":"Po\u00e7\u00e3o",
    "gn:population":0,
    "gn:timezone":"America/Sao_Paulo",
    "iso:country":"BR",
    "name:por_x_preferred":[
        "Po\u00e7\u00e3o"
    ],
    "wof:name":"Pocao",
    "wof:placetype":"locality"
},
  "geometry": {"coordinates":[-49.26667,-20.43333],"type":"Point"}
}