{
  "type": "Feature",
  "properties": {
    "gn:admin1_code":"5.0",
    "gn:admin2_code":"2905909.0",
    "gn:asciiname":"Genipapinho",
    "gn:country_code":"BR",
    "gn:dem":466,
    "gn:feature_class":"P",
    "gn:feature_code":"PPL",
    "gn:name":"Genipapinho",
    "gn:population":0,
    "gn:timezone":"America/Bahia",
    "iso:country":"BR",
    "name:por_x_preferred":[
        "Genipapinho"
    ],
    "wof:name":"Genipapinho",
    "wof:placetype":"locality"
},
  "geometry": {"coordinates":[-43.00887,-9.58793],"type":"Point"}
}