{
  "type": "Feature",
  "properties": {
    "gn:admin1_code":"18",
    "gn:admin2_code":"4108957.0",
    "gn:asciiname":"Barra Mansa",
    "gn:country_code":"BR",
    "gn:dem":818,
    "gn:feature_class":"P",
    "gn:feature_code":"PPL",
    "gn:name":"Barra Mansa",
    "gn:population":0,
    "gn:timezone":"America/Sao_Paulo",
    "iso:country":"BR",
    "name:ara_x_preferred":[
        "\u0628\u0627\u0631\u0627 \u0645\u0627\u0646\u0633\u0627"
    ],
    "name:bpy_x_preferred":[
        "\u09ac\u09be\u09b0\u09cd\u09b0\u09be \u09ae\u09be\u09a8\u09cd\u09b8\u09be"
    ],
    "name:cat_x_preferred":[
        "Barra Mansa"
    ],
    "name:ceb_x_preferred":[
        "Barra Mansa"
    ],
    "name:deu_x_preferred":[
        "Barra Mansa"
    ],
    "name:epo_x_preferred":[
        "Barra Mansa"
    ],
    "name:eus_x_preferred":[
        "Barra Mansa"
    ],
    "name:fra_x_preferred":[
        "Barra Mansa"
    ],
    "name:heb_x_preferred":[
        "\u05d1\u05d0\u05e8\u05d4 \u05de\u05d0\u05e0\u05e1\u05d4"
    ],
    "name:hye_x_preferred":[
        "\u0532\u0561\u0580\u0580\u0561 \u0544\u0561\u0576\u057d\u0561"
    ],
    "name:ita_x_preferred":[
        "Barra Mansa"
    ],
    "name:kat_x_preferred":[
        "\u10d1\u10d0\u10e0\u10d0-\u10db\u10d0\u10dc\u10e1\u10d0"
    ],
    "name:kaz_x_preferred":[
        "\u0411\u0430\u0440\u0440\u0430-\u041c\u0430\u043d\u0441\u0430"
    ],
    "name:lit_x_preferred":[
        "Bara Mansa"
    ],
    "name:mlg_x_preferred":[
        "Barra Mansa"
    ],
    "name:nld_x_preferred":[
        "Barra Mansa"
    ],
    "name:nor_x_preferred":[
        "Barra Mansa"
    ],
    "name:pol_x_preferred":[
        "Barra Mansa"
    ],
    "name:por_x_preferred":[
        "Barra Mansa"
    ],
    "name:ron_x_preferred":[
        "Barra Mansa"
    ],
    "name:rus_x_preferred":[
        "\u0411\u0430\u0440\u0440\u0430-\u041c\u0430\u043d\u0441\u0430"
    ],
    "name:sco_x_preferred":[
        "Barra Mansa"
    ],
    "name:spa_x_preferred":[
        "Barra Mansa"
    ],
    "name:swe_x_preferred":[
        "Barra Mansa"
    ],
    "name:szl_x_preferred":[
        "Barra Mansa"
    ],
    "name:tat_x_preferred":[
        "\u0411\u0430\u0440\u0440\u0430-\u041c\u0430\u043d\u0441\u0430"
    ],
    "name:ukr_x_preferred":[
        "\u0411\u0430\u0440\u0440\u0430-\u041c\u0430\u043d\u0441\u0430"
    ],
    "name:vie_x_preferred":[
        "Barra Mansa"
    ],
    "name:vol_x_preferred":[
        "Barra Mansa"
    ],
    "name:war_x_preferred":[
        "Barra Mansa"
    ],
    "name:zho_x_preferred":[
        "\u5df4\u62c9\u66fc\u8428\u5e02"
    ],
    "wof:name":"Barra Mansa",
    "wof:placetype":"locality"
},
  "geometry": {"coordinates":[-50.91667,-25.13333],"type":"Point"}
}