{
  "type": "Feature",
  "properties": {
    "gn:admin1_code":"18",
    "gn:admin2_code":"4108957.0",
    "gn:asciiname":"Barra Mansa",
    "gn:country_code":"BR",
    "gn:dem":818,
    "gn:feature_class":"P",
    "gn:feature_code":"PPL",
    "gn:name":"Barra Mansa",
    "gn:population":0,
    "gn:timezone":"America/Sao_Paulo",
    "iso:country":"BR",
    "wof:name":"Barra Mansa",
    "wof:placetype":"locality"
},
  "geometry": {"coordinates":[-50.91667,-25.13333],"type":"Point"}
}