{
  "type": "Feature",
  "properties": {
    "gn:admin1_code":"30",
    "gn:admin2_code":"2611200.0",
    "gn:asciiname":"Tambor",
    "gn:country_code":"BR",
    "gn:dem":706,
    "gn:feature_class":"P",
    "gn:feature_code":"PPL",
    "gn:name":"Tambor",
    "gn:population":0,
    "gn:timezone":"America/Recife",
    "iso:country":"BR",
    "wof:name":"Tambor",
    "wof:placetype":"locality"
},
  "geometry": {"coordinates":[-36.61667,-8.16667],"type":"Point"}
}