{
  "type": "Feature",
  "properties": {
    "gn:admin1_code":"14",
    "gn:admin2_code":"5103007.0",
    "gn:asciiname":"Rio Casca",
    "gn:country_code":"BR",
    "gn:dem":672,
    "gn:feature_class":"P",
    "gn:feature_code":"PPL",
    "gn:name":"Rio Casca",
    "gn:population":0,
    "gn:timezone":"America/Cuiaba",
    "iso:country":"BR",
    "name:bpy_x_preferred":[
        "\u09b0\u09bf\u0993 \u0995\u09be\u09b8\u0995\u09be"
    ],
    "name:ceb_x_preferred":[
        "Rio Casca"
    ],
    "name:epo_x_preferred":[
        "Rio Casca"
    ],
    "name:eus_x_preferred":[
        "Rio Casca"
    ],
    "name:fra_x_preferred":[
        "Rio Casca"
    ],
    "name:ita_x_preferred":[
        "Rio Casca"
    ],
    "name:kat_x_preferred":[
        "\u10e0\u10d8\u10e3-\u10d9\u10d0\u10e1\u10d9\u10d0"
    ],
    "name:kaz_x_preferred":[
        "\u0420\u0438\u0443-\u041a\u0430\u0441\u043a\u0430"
    ],
    "name:mlg_x_preferred":[
        "Rio Casca"
    ],
    "name:nld_x_preferred":[
        "Rio Casca"
    ],
    "name:nor_x_preferred":[
        "Rio Casca"
    ],
    "name:pol_x_preferred":[
        "Rio Casca"
    ],
    "name:por_x_preferred":[
        "Rio Casca"
    ],
    "name:ron_x_preferred":[
        "Rio Casca"
    ],
    "name:rus_x_preferred":[
        "\u0420\u0438\u0443-\u041a\u0430\u0441\u043a\u0430"
    ],
    "name:swe_x_preferred":[
        "Rio Casca"
    ],
    "name:vie_x_preferred":[
        "Rio Casca"
    ],
    "name:vol_x_preferred":[
        "Rio Casca"
    ],
    "name:war_x_preferred":[
        "Rio Casca"
    ],
    "name:zho_x_preferred":[
        "\u91cc\u5965\u5361\u65af\u5361"
    ],
    "wof:name":"Rio Casca",
    "wof:placetype":"locality"
},
  "geometry": {"coordinates":[-55.35,-15.45],"type":"Point"}
}