{
  "type": "Feature",
  "properties": {
    "gn:admin1_code":"14",
    "gn:admin2_code":"5103007.0",
    "gn:asciiname":"Rio Casca",
    "gn:country_code":"BR",
    "gn:dem":672,
    "gn:feature_class":"P",
    "gn:feature_code":"PPL",
    "gn:name":"Rio Casca",
    "gn:population":0,
    "gn:timezone":"America/Cuiaba",
    "iso:country":"BR",
    "wof:name":"Rio Casca",
    "wof:placetype":"locality"
},
  "geometry": {"coordinates":[-55.35,-15.45],"type":"Point"}
}