{
  "type": "Feature",
  "properties": {
    "gn:admin1_code":"23",
    "gn:admin2_code":"4304507.0",
    "gn:asciiname":"Borba",
    "gn:country_code":"BR",
    "gn:dem":202,
    "gn:feature_class":"P",
    "gn:feature_code":"PPL",
    "gn:name":"Borba",
    "gn:population":0,
    "gn:timezone":"America/Sao_Paulo",
    "iso:country":"BR",
    "name:ceb_x_preferred":[
        "Borba"
    ],
    "name:deu_x_preferred":[
        "Borba"
    ],
    "name:fra_x_preferred":[
        "Borba"
    ],
    "name:ita_x_preferred":[
        "Borba"
    ],
    "name:nld_x_preferred":[
        "Borba"
    ],
    "name:por_x_preferred":[
        "Borba"
    ],
    "name:swe_x_preferred":[
        "Borba"
    ],
    "name:ukr_x_preferred":[
        "\u0411\u043e\u0440\u0431\u0430"
    ],
    "name:vie_x_preferred":[
        "Borba"
    ],
    "name:vol_x_preferred":[
        "Borba"
    ],
    "wof:name":"Borba",
    "wof:placetype":"locality"
},
  "geometry": {"coordinates":[-52.38333,-30.96667],"type":"Point"}
}