{
  "type": "Feature",
  "properties": {
    "gn:admin1_code":"23",
    "gn:admin2_code":"4304507.0",
    "gn:asciiname":"Borba",
    "gn:country_code":"BR",
    "gn:dem":202,
    "gn:feature_class":"P",
    "gn:feature_code":"PPL",
    "gn:name":"Borba",
    "gn:population":0,
    "gn:timezone":"America/Sao_Paulo",
    "iso:country":"BR",
    "wof:name":"Borba",
    "wof:placetype":"locality"
},
  "geometry": {"coordinates":[-52.38333,-30.96667],"type":"Point"}
}