{
  "type": "Feature",
  "properties": {
    "gn:admin1_code":"18.0",
    "gn:admin2_code":"4109708.0",
    "gn:asciiname":"Sitio Joaquim P. Silva",
    "gn:country_code":"BR",
    "gn:dem":699,
    "gn:feature_class":"P",
    "gn:feature_code":"PPL",
    "gn:name":"S\u00edtio Joaquim P. Silva",
    "gn:population":0,
    "gn:timezone":"America/Sao_Paulo",
    "iso:country":"BR",
    "name:por_x_preferred":[
        "S\u00edtio Joaquim P. Silva"
    ],
    "wof:name":"Sitio Joaquim P. Silva",
    "wof:placetype":"locality"
},
  "geometry": {"coordinates":[-50.22018,-23.92511],"type":"Point"}
}