{
  "type": "Feature",
  "properties": {
    "gn:admin1_code":"15",
    "gn:admin2_code":"3170206.0",
    "gn:asciiname":"Rovaldo",
    "gn:country_code":"BR",
    "gn:dem":880,
    "gn:feature_class":"P",
    "gn:feature_code":"PPL",
    "gn:name":"Rovaldo",
    "gn:population":0,
    "gn:timezone":"America/Sao_Paulo",
    "iso:country":"BR",
    "name:por_x_preferred":[
        "Rovaldo"
    ],
    "wof:name":"Rovaldo",
    "wof:placetype":"locality"
},
  "geometry": {"coordinates":[-48.08333,-19.05],"type":"Point"}
}