{
  "type": "Feature",
  "properties": {
    "gn:admin1_code":"06",
    "gn:admin2_code":"2307635.0",
    "gn:asciiname":"Fazenda Barrigas",
    "gn:country_code":"BR",
    "gn:dem":296,
    "gn:feature_class":"P",
    "gn:feature_code":"PPL",
    "gn:name":"Fazenda Barrigas",
    "gn:population":0,
    "gn:timezone":"America/Fortaleza",
    "iso:country":"BR",
    "wof:name":"Fazenda Barrigas",
    "wof:placetype":"locality"
},
  "geometry": {"coordinates":[-39.58333,-4.91667],"type":"Point"}
}