{
  "type": "Feature",
  "properties": {
    "gn:admin1_code":"20",
    "gn:admin2_code":"2203503.0",
    "gn:asciiname":"Baixa do Cerral",
    "gn:country_code":"BR",
    "gn:dem":244,
    "gn:feature_class":"P",
    "gn:feature_code":"PPL",
    "gn:name":"Baixa do Cerral",
    "gn:population":0,
    "gn:timezone":"America/Fortaleza",
    "iso:country":"BR",
    "wof:name":"Baixa do Cerral",
    "wof:placetype":"locality"
},
  "geometry": {"coordinates":[-42.13333,-6.23333],"type":"Point"}
}