{
  "type": "Feature",
  "properties": {
    "gn:admin1_code":"8",
    "gn:admin2_code":"3205036.0",
    "gn:asciiname":"Vargem Grande",
    "gn:country_code":"BR",
    "gn:dem":710,
    "gn:feature_class":"P",
    "gn:feature_code":"PPL",
    "gn:name":"Vargem Grande",
    "gn:population":0,
    "gn:timezone":"America/Sao_Paulo",
    "iso:country":"BR",
    "name:por_x_preferred":[
        "Vargem Grande"
    ],
    "wof:name":"Vargem Grande",
    "wof:placetype":"locality"
},
  "geometry": {"coordinates":[-40.98333,-20.66667],"type":"Point"}
}