{
  "type": "Feature",
  "properties": {
    "iso:country":"BR",
    "name:ceb_x_preferred":[
        "Vitoria Da Conquista"
    ],
    "name:deu_x_preferred":[
        "Flughafen Pedro Otac\u00edlio Figueiredo"
    ],
    "name:eng_x_preferred":[
        "Vit\u00f3ria da Conquista Airport"
    ],
    "name:fas_x_preferred":[
        "\u0641\u0631\u0648\u062f\u06af\u0627\u0647 \u0648\u06cc\u062a\u0648\u0631\u06cc\u0627 \u062f\u0627 \u06a9\u0648\u0646\u06a9\u06cc\u0633\u062a\u0627"
    ],
    "name:msa_x_preferred":[
        "Lapangan Terbang Vitoria Da Conquista"
    ],
    "name:por_x_preferred":[
        "Aeroporto de Vit\u00f3ria da Conquista"
    ],
    "name:por_x_variant":[
        "Aeroporto Pedro Otac\u00edlio Figueiredo"
    ],
    "name:ron_x_preferred":[
        "Aeroportul Vit\u00f3ria da Conquista"
    ],
    "name:tgk_x_preferred":[
        "\u0424\u0443\u0440\u0443\u0434\u0433\u043e\u04b3\u0438 \u0432\u0438\u0442\u0443\u0440\u0438\u043e \u0434\u043e \u043a\u0443\u043d\u043a\u0438\u0441\u0442\u043e"
    ],
    "oa:elevation_ft":"3002",
    "oa:type":"medium_airport",
    "wd:wordcount":342,
    "woe:hierarchy":{
        "country_id":23424768,
        "county_id":12578641,
        "planet_id":1,
        "state_id":2344848
    },
    "wof:name":"Aeroporto Vitoria da Conquista",
    "wof:placetype":"campus"
},
  "geometry": {"coordinates":[-40.863055555556,-14.863611111111],"type":"Point"}
}