{
  "type": "Feature",
  "properties": {
    "gn:admin1_code":"30",
    "gn:admin2_code":"2614006.0",
    "gn:asciiname":"Salgueirinho",
    "gn:country_code":"BR",
    "gn:dem":472,
    "gn:feature_class":"P",
    "gn:feature_code":"PPL",
    "gn:name":"Salgueirinho",
    "gn:population":0,
    "gn:timezone":"America/Recife",
    "iso:country":"BR",
    "wof:name":"Salgueirinho",
    "wof:placetype":"locality"
},
  "geometry": {"coordinates":[-39.46667,-7.78333],"type":"Point"}
}