{
  "type": "Feature",
  "properties": {
    "gn:admin1_code":"5",
    "gn:admin2_code":"2931103.0",
    "gn:asciiname":"Caldeirao do Mato",
    "gn:country_code":"BR",
    "gn:dem":218,
    "gn:feature_class":"P",
    "gn:feature_code":"PPL",
    "gn:name":"Caldeir\u00e3o do Mato",
    "gn:population":0,
    "gn:timezone":"America/Bahia",
    "iso:country":"BR",
    "wof:name":"Caldeirao do Mato",
    "wof:placetype":"locality"
},
  "geometry": {"coordinates":[-39.11667,-12.01667],"type":"Point"}
}