{
  "type": "Feature",
  "properties": {
    "gn:admin1_code":"18.0",
    "gn:admin2_code":"4113205.0",
    "gn:asciiname":"Sitio Onestario S. Pinto",
    "gn:country_code":"BR",
    "gn:dem":949,
    "gn:feature_class":"P",
    "gn:feature_code":"PPL",
    "gn:name":"S\u00edtio Onest\u00e1rio S. Pinto",
    "gn:population":0,
    "gn:timezone":"America/Sao_Paulo",
    "iso:country":"BR",
    "name:por_x_preferred":[
        "S\u00edtio Onest\u00e1rio S. Pinto"
    ],
    "wof:name":"Sitio Onestario S. Pinto",
    "wof:placetype":"locality"
},
  "geometry": {"coordinates":[-49.8721,-25.7473],"type":"Point"}
}