{
  "type": "Feature",
  "properties": {
    "gn:admin1_code":"22",
    "gn:admin2_code":"2400208.0",
    "gn:asciiname":"Lagoa do Pore",
    "gn:country_code":"BR",
    "gn:dem":19,
    "gn:feature_class":"P",
    "gn:feature_code":"PPL",
    "gn:name":"Lagoa do Por\u00e9",
    "gn:population":0,
    "gn:timezone":"America/Fortaleza",
    "iso:country":"BR",
    "wof:name":"Lagoa do Pore",
    "wof:placetype":"locality"
},
  "geometry": {"coordinates":[-36.88111,-5.38611],"type":"Point"}
}