{
  "type": "Feature",
  "properties": {
    "gn:admin1_code":"27",
    "gn:admin2_code":"3513702.0",
    "gn:asciiname":"Santa Etelvina",
    "gn:cc2":"BR",
    "gn:country_code":"BR",
    "gn:dem":657,
    "gn:feature_class":"P",
    "gn:feature_code":"PPL",
    "gn:name":"Santa Etelvina",
    "gn:population":0,
    "gn:timezone":"America/Sao_Paulo",
    "iso:country":"BR",
    "name:und_x_variant":[
        "Fazenda Santa Etelvina",
        "Santa Etelvina"
    ],
    "wof:name":"Santa Etelvina",
    "wof:placetype":"locality"
},
  "geometry": {"coordinates":[-47.63333,-21.76667],"type":"Point"}
}