{
  "type": "Feature",
  "properties": {
    "gn:admin1_code":"8",
    "gn:admin2_code":"3201902.0",
    "gn:asciiname":"Nossa Senhora do Carmo",
    "gn:country_code":"BR",
    "gn:dem":1100,
    "gn:feature_class":"P",
    "gn:feature_code":"PPL",
    "gn:name":"Nossa Senhora do Carmo",
    "gn:population":0,
    "gn:timezone":"America/Sao_Paulo",
    "iso:country":"BR",
    "name:por_x_preferred":[
        "Nossa Senhora do Carmo"
    ],
    "wof:name":"Nossa Senhora do Carmo",
    "wof:placetype":"locality"
},
  "geometry": {"coordinates":[-41.01667,-20.33333],"type":"Point"}
}