{
  "type": "Feature",
  "properties": {
    "gn:admin1_code":"18.0",
    "gn:admin2_code":"4120101.0",
    "gn:asciiname":"Sitio Morro da Cruz",
    "gn:country_code":"BR",
    "gn:dem":841,
    "gn:feature_class":"P",
    "gn:feature_code":"PPL",
    "gn:name":"S\u00edtio Morro da Cruz",
    "gn:population":0,
    "gn:timezone":"America/Sao_Paulo",
    "iso:country":"BR",
    "name:por_x_preferred":[
        "S\u00edtio Morro da Cruz"
    ],
    "wof:name":"Sitio Morro da Cruz",
    "wof:placetype":"locality"
},
  "geometry": {"coordinates":[-49.9684,-25.5578],"type":"Point"}
}