{
  "type": "Feature",
  "properties": {
    "gn:admin1_code":"15",
    "gn:admin2_code":"3144805.0",
    "gn:asciiname":"Seabra",
    "gn:country_code":"BR",
    "gn:dem":744,
    "gn:feature_class":"P",
    "gn:feature_code":"PPL",
    "gn:name":"Seabra",
    "gn:population":0,
    "gn:timezone":"America/Sao_Paulo",
    "iso:country":"BR",
    "name:bpy_x_preferred":[
        "\u09b8\u09c7\u0986\u09ac\u09b0\u09be"
    ],
    "name:epo_x_preferred":[
        "Seabra"
    ],
    "name:eus_x_preferred":[
        "Seabra"
    ],
    "name:fra_x_preferred":[
        "Seabra"
    ],
    "name:hye_x_preferred":[
        "\u054d\u0565\u0561\u0562\u0580\u0561"
    ],
    "name:ita_x_preferred":[
        "Seabra"
    ],
    "name:kat_x_preferred":[
        "\u10e1\u10d4\u10d0\u10d1\u10e0\u10d0"
    ],
    "name:kaz_x_preferred":[
        "\u0421\u0435\u0430\u0431\u0440\u0430"
    ],
    "name:mlg_x_preferred":[
        "Seabra"
    ],
    "name:nld_x_preferred":[
        "Seabra"
    ],
    "name:nor_x_preferred":[
        "Seabra"
    ],
    "name:pol_x_preferred":[
        "Seabra"
    ],
    "name:por_x_preferred":[
        "Seabra"
    ],
    "name:ron_x_preferred":[
        "Seabra"
    ],
    "name:rus_x_preferred":[
        "\u0421\u0435\u0430\u0431\u0440\u0430"
    ],
    "name:vie_x_preferred":[
        "Seabra"
    ],
    "name:vol_x_preferred":[
        "Seabra"
    ],
    "name:war_x_preferred":[
        "Seabra"
    ],
    "name:zho_x_preferred":[
        "\u585e\u963f\u5e03\u62c9"
    ],
    "wof:name":"Seabra",
    "wof:placetype":"locality"
},
  "geometry": {"coordinates":[-43.8327,-20.0188],"type":"Point"}
}