{
  "type": "Feature",
  "properties": {
    "gn:admin1_code":"15",
    "gn:admin2_code":"3144805.0",
    "gn:asciiname":"Seabra",
    "gn:country_code":"BR",
    "gn:dem":744,
    "gn:feature_class":"P",
    "gn:feature_code":"PPL",
    "gn:name":"Seabra",
    "gn:population":0,
    "gn:timezone":"America/Sao_Paulo",
    "iso:country":"BR",
    "name:por_x_preferred":[
        "Seabra"
    ],
    "wof:name":"Seabra",
    "wof:placetype":"locality"
},
  "geometry": {"coordinates":[-43.8327,-20.0188],"type":"Point"}
}