{
  "type": "Feature",
  "properties": {
    "gn:admin1_code":"1",
    "gn:admin2_code":"1200203.0",
    "gn:asciiname":"Luzeiro",
    "gn:country_code":"BR",
    "gn:dem":185,
    "gn:feature_class":"P",
    "gn:feature_code":"PPL",
    "gn:name":"Luzeiro",
    "gn:population":0,
    "gn:timezone":"America/Rio_Branco",
    "iso:country":"BR",
    "wof:name":"Luzeiro",
    "wof:placetype":"locality"
},
  "geometry": {"coordinates":[-72.68333,-7.83333],"type":"Point"}
}