{
  "type": "Feature",
  "properties": {
    "gn:admin1_code":"18.0",
    "gn:admin2_code":"4126603.0",
    "gn:asciiname":"Sitio Vitor P. da Silva",
    "gn:country_code":"BR",
    "gn:dem":587,
    "gn:feature_class":"P",
    "gn:feature_code":"PPL",
    "gn:name":"S\u00edtio Vitor P. da Silva",
    "gn:population":0,
    "gn:timezone":"America/Sao_Paulo",
    "iso:country":"BR",
    "name:por_x_preferred":[
        "S\u00edtio Vitor P. da Silva"
    ],
    "wof:name":"Sitio Vitor P. da Silva",
    "wof:placetype":"locality"
},
  "geometry": {"coordinates":[-49.7667,-23.6898],"type":"Point"}
}