{
  "type": "Feature",
  "properties": {
    "gn:admin1_code":"15",
    "gn:admin2_code":"3150901.0",
    "gn:asciiname":"Taquaral",
    "gn:country_code":"BR",
    "gn:dem":873,
    "gn:feature_class":"P",
    "gn:feature_code":"PPLL",
    "gn:name":"Taquaral",
    "gn:population":0,
    "gn:timezone":"America/Sao_Paulo",
    "iso:country":"BR",
    "name:por_x_preferred":[
        "Taquaral"
    ],
    "wof:name":"Taquaral",
    "wof:placetype":"locality"
},
  "geometry": {"coordinates":[-45.50821,-22.51875],"type":"Point"}
}