{
  "type": "Feature",
  "properties": {
    "gn:admin1_code":"15",
    "gn:admin2_code":"3150901.0",
    "gn:asciiname":"Taquaral",
    "gn:country_code":"BR",
    "gn:dem":873,
    "gn:feature_class":"P",
    "gn:feature_code":"PPLL",
    "gn:name":"Taquaral",
    "gn:population":0,
    "gn:timezone":"America/Sao_Paulo",
    "iso:country":"BR",
    "name:bpy_x_preferred":[
        "\u099f\u09be\u0995\u09c1\u09f1\u09be\u09b0\u09cd\u09af\u09bc\u09be\u09b2"
    ],
    "name:ceb_x_preferred":[
        "Taquaral"
    ],
    "name:epo_x_preferred":[
        "Taquaral"
    ],
    "name:eus_x_preferred":[
        "Taquaral"
    ],
    "name:fra_x_preferred":[
        "Taquaral"
    ],
    "name:ita_x_preferred":[
        "Taquaral"
    ],
    "name:kaz_x_preferred":[
        "\u0422\u0430\u043a\u0443\u0430\u0440\u0430\u043b"
    ],
    "name:mlg_x_preferred":[
        "Taquaral"
    ],
    "name:nld_x_preferred":[
        "Taquaral"
    ],
    "name:nor_x_preferred":[
        "Taquaral"
    ],
    "name:pol_x_preferred":[
        "Taquaral"
    ],
    "name:por_x_preferred":[
        "Taquaral"
    ],
    "name:ron_x_preferred":[
        "Taquaral"
    ],
    "name:rus_x_preferred":[
        "\u0422\u0430\u043a\u0443\u0430\u0440\u0430\u043b"
    ],
    "name:spa_x_preferred":[
        "Taquaral"
    ],
    "name:swe_x_preferred":[
        "Taquaral"
    ],
    "name:vie_x_preferred":[
        "Taquaral"
    ],
    "name:vol_x_preferred":[
        "Taquaral"
    ],
    "name:war_x_preferred":[
        "Taquaral"
    ],
    "name:zho_x_preferred":[
        "\u5854\u5938\u62c9\u723e"
    ],
    "wof:name":"Taquaral",
    "wof:placetype":"locality"
},
  "geometry": {"coordinates":[-45.50821,-22.51875],"type":"Point"}
}