{
  "type": "Feature",
  "properties": {
    "gn:admin1_code":"31.0",
    "gn:admin2_code":"1720804.0",
    "gn:asciiname":"Sitio Novo de Goias",
    "gn:country_code":"BR",
    "gn:dem":189,
    "gn:feature_class":"P",
    "gn:feature_code":"PPL",
    "gn:name":"S\u00edtio Novo de Goi\u00e1s",
    "gn:population":0,
    "gn:timezone":"America/Araguaina",
    "iso:country":"BR",
    "wof:name":"Sitio Novo de Goias",
    "wof:placetype":"locality"
},
  "geometry": {"coordinates":[-47.63731,-5.60283],"type":"Point"}
}