{
  "type": "Feature",
  "properties": {
    "gn:admin1_code":"16",
    "gn:admin2_code":"1508050.0",
    "gn:asciiname":"Sao Lourenco",
    "gn:country_code":"BR",
    "gn:dem":194,
    "gn:feature_class":"P",
    "gn:feature_code":"PPL",
    "gn:name":"S\u00e3o Louren\u00e7o",
    "gn:population":0,
    "gn:timezone":"America/Santarem",
    "iso:country":"BR",
    "wof:name":"Sao Lourenco",
    "wof:placetype":"locality"
},
  "geometry": {"coordinates":[-55.83333,-5.15],"type":"Point"}
}