{
  "type": "Feature",
  "properties": {
    "gn:admin1_code":"11",
    "gn:admin2_code":"5007554.0",
    "gn:asciiname":"Senho",
    "gn:country_code":"BR",
    "gn:dem":398,
    "gn:feature_class":"P",
    "gn:feature_code":"PPL",
    "gn:name":"Senh\u00f4",
    "gn:population":0,
    "gn:timezone":"America/Campo_Grande",
    "iso:country":"BR",
    "wof:name":"Senho",
    "wof:placetype":"locality"
},
  "geometry": {"coordinates":[-53.16667,-20.95],"type":"Point"}
}