{
  "type": "Feature",
  "properties": {
    "gn:admin1_code":"25",
    "gn:admin2_code":"1400456.0",
    "gn:asciiname":"Flexal",
    "gn:country_code":"BR",
    "gn:dem":90,
    "gn:feature_class":"P",
    "gn:feature_code":"PPL",
    "gn:name":"Flexal",
    "gn:population":0,
    "gn:timezone":"America/Boa_Vista",
    "iso:country":"BR",
    "wof:name":"Flexal",
    "wof:placetype":"locality"
},
  "geometry": {"coordinates":[-60.53333000000001,3.83333],"type":"Point"}
}