{
  "type": "Feature",
  "properties": {
    "gn:admin1_code":"17",
    "gn:admin2_code":"2514008.0",
    "gn:asciiname":"Gravata (1)",
    "gn:country_code":"BR",
    "gn:dem":509,
    "gn:feature_class":"P",
    "gn:feature_code":"PPL",
    "gn:name":"Gravat\u00e1 (1)",
    "gn:population":0,
    "gn:timezone":"America/Fortaleza",
    "iso:country":"BR",
    "wof:name":"Gravata (1)",
    "wof:placetype":"locality"
},
  "geometry": {"coordinates":[-36.48333,-7.56667],"type":"Point"}
}