{
  "type": "Feature",
  "properties": {
    "gn:admin1_code":"5",
    "gn:admin2_code":"2920700.0",
    "gn:asciiname":"Tabatinga",
    "gn:country_code":"BR",
    "gn:dem":10,
    "gn:feature_class":"P",
    "gn:feature_code":"PPL",
    "gn:name":"Tabatinga",
    "gn:population":0,
    "gn:timezone":"America/Bahia",
    "iso:country":"BR",
    "name:ara_x_preferred":[
        "\u062a\u0627\u0628\u0627\u062a\u064a\u0646\u063a\u0627"
    ],
    "name:bpy_x_preferred":[
        "\u099f\u09be\u09ac\u09be\u099f\u09bf\u0999\u09cd\u0997\u09be"
    ],
    "name:deu_x_preferred":[
        "Tabatinga"
    ],
    "name:epo_x_preferred":[
        "Tabatinga"
    ],
    "name:eus_x_preferred":[
        "Tabatinga"
    ],
    "name:fin_x_preferred":[
        "Tabatinga"
    ],
    "name:fra_x_preferred":[
        "Tabatinga"
    ],
    "name:heb_x_preferred":[
        "\u05d8\u05d1\u05e6'\u05d9\u05e0\u05d2\u05d4"
    ],
    "name:hye_x_preferred":[
        "\u054f\u0561\u0562\u0561\u057f\u056b\u0576\u0563\u0561"
    ],
    "name:ita_x_preferred":[
        "Tabatinga"
    ],
    "name:jpn_x_preferred":[
        "\u30bf\u30d0\u30c1\u30f3\u30ac"
    ],
    "name:kat_x_preferred":[
        "\u10e2\u10d0\u10d1\u10d0\u10e2\u10d8\u10dc\u10d2\u10d0"
    ],
    "name:mlg_x_preferred":[
        "Tabatinga"
    ],
    "name:nld_x_preferred":[
        "Tabatinga"
    ],
    "name:nor_x_preferred":[
        "Tabatinga"
    ],
    "name:pol_x_preferred":[
        "Tabatinga"
    ],
    "name:por_x_preferred":[
        "Tabatinga"
    ],
    "name:ron_x_preferred":[
        "Tabatinga"
    ],
    "name:rus_x_preferred":[
        "\u0422\u0430\u0431\u0430\u0442\u0438\u043d\u0433\u0430"
    ],
    "name:spa_x_preferred":[
        "Tabatinga"
    ],
    "name:vie_x_preferred":[
        "Tabatinga"
    ],
    "name:vol_x_preferred":[
        "Tabatinga"
    ],
    "name:war_x_preferred":[
        "Tabatinga"
    ],
    "name:zho_x_preferred":[
        "\u5854\u5df4\u5ef7\u52a0"
    ],
    "wof:name":"Tabatinga",
    "wof:placetype":"locality"
},
  "geometry": {"coordinates":[-38.93469,-13.96639],"type":"Point"}
}