{
  "type": "Feature",
  "properties": {
    "gn:admin1_code":"5",
    "gn:admin2_code":"2920700.0",
    "gn:asciiname":"Tabatinga",
    "gn:country_code":"BR",
    "gn:dem":10,
    "gn:feature_class":"P",
    "gn:feature_code":"PPL",
    "gn:name":"Tabatinga",
    "gn:population":0,
    "gn:timezone":"America/Bahia",
    "iso:country":"BR",
    "wof:name":"Tabatinga",
    "wof:placetype":"locality"
},
  "geometry": {"coordinates":[-38.93469,-13.96639],"type":"Point"}
}