{
  "type": "Feature",
  "properties": {
    "gn:admin1_code":"18.0",
    "gn:admin2_code":"4109500.0",
    "gn:asciiname":"Sitio Levi Braselino",
    "gn:country_code":"BR",
    "gn:dem":18,
    "gn:feature_class":"P",
    "gn:feature_code":"PPL",
    "gn:name":"S\u00edtio Levi Braselino",
    "gn:population":0,
    "gn:timezone":"America/Sao_Paulo",
    "iso:country":"BR",
    "name:por_x_preferred":[
        "S\u00edtio Levi Braselino"
    ],
    "wof:name":"Sitio Levi Braselino",
    "wof:placetype":"locality"
},
  "geometry": {"coordinates":[-48.53643,-25.23674],"type":"Point"}
}