{
  "type": "Feature",
  "properties": {
    "gn:admin1_code":"30",
    "gn:admin2_code":"2602803.0",
    "gn:asciiname":"Imbauba",
    "gn:country_code":"BR",
    "gn:dem":825,
    "gn:feature_class":"P",
    "gn:feature_code":"PPL",
    "gn:name":"Imba\u00faba",
    "gn:population":0,
    "gn:timezone":"America/Recife",
    "iso:country":"BR",
    "wof:name":"Imbauba",
    "wof:placetype":"locality"
},
  "geometry": {"coordinates":[-37.13333,-8.58333],"type":"Point"}
}