{
  "type": "Feature",
  "properties": {
    "gn:country":"BR",
    "gn:fcode":"PPL",
    "gn:population":0,
    "iso:country":"BR",
    "name:bpy_x_preferred":[
        "\u0986\u0997\u09c1\u09f1\u09be \u09b8\u09be\u09a8\u09cd\u099f\u09be"
    ],
    "name:ceb_x_preferred":[
        "\u00c1gua Santa"
    ],
    "name:epo_x_preferred":[
        "\u00c1gua Santa"
    ],
    "name:ina_x_preferred":[
        "\u00c1gua Santa"
    ],
    "name:ita_x_preferred":[
        "\u00c1gua Santa"
    ],
    "name:kaz_x_preferred":[
        "\u0410\u0433\u0443\u0430-\u0421\u0430\u043d\u0442\u0430"
    ],
    "name:mlg_x_preferred":[
        "\u00c1gua Santa"
    ],
    "name:nld_x_preferred":[
        "\u00c1gua Santa"
    ],
    "name:nor_x_preferred":[
        "\u00c1gua Santa"
    ],
    "name:pol_x_preferred":[
        "\u00c1gua Santa"
    ],
    "name:por_x_preferred":[
        "\u00c1gua Santa"
    ],
    "name:por_x_variant":[
        "Agua Santa"
    ],
    "name:ron_x_preferred":[
        "\u00c1gua Santa"
    ],
    "name:rus_x_preferred":[
        "\u0410\u0433\u0443\u0430-\u0421\u0430\u043d\u0442\u0430"
    ],
    "name:spa_x_preferred":[
        "\u00c1gua Santa"
    ],
    "name:swe_x_preferred":[
        "\u00c1gua Santa"
    ],
    "name:vie_x_preferred":[
        "\u00c1gua Santa"
    ],
    "name:vol_x_preferred":[
        "\u00c1gua Santa"
    ],
    "name:war_x_preferred":[
        "\u00c1gua Santa"
    ],
    "name:zho_x_preferred":[
        "\u963f\u74dc\u6851\u5854"
    ],
    "qs_pg:aaroncc":"BR",
    "qs_pg:gn_country":"BR",
    "qs_pg:gn_fcode":"PPL",
    "qs_pg:gn_pop":0,
    "qs_pg:name":"\u00c1gua Santa",
    "qs_pg:name_adm0":"Brasil",
    "qs_pg:name_adm1":"Rio de Janeiro",
    "qs_pg:photos":155,
    "qs_pg:photos_1k":31,
    "qs_pg:photos_9k":1,
    "qs_pg:photos_9r":4,
    "qs_pg:photos_all":155,
    "qs_pg:photos_sr":4,
    "qs_pg:pop_sr":0,
    "qs_pg:qs_pg_placetype":"neighbourhood",
    "qs_pg:qs_pg_placetype_gp":"Suburb",
    "qs_pg:woe_adm0":23424768,
    "woe:adm0_id":23424768,
    "woe:name_adm0":"Brasil",
    "woe:name_adm1":"Rio de Janeiro",
    "woe:placetype":"Suburb",
    "wof:name":"\u00c1gua Santa",
    "wof:placetype":"neighbourhood"
},
  "geometry": {"coordinates":[-43.30834,-22.90971],"type":"Point"}
}