{
  "type": "Feature",
  "properties": {
    "gn:admin1_code":"27.0",
    "gn:admin2_code":"3505401.0",
    "gn:asciiname":"Bairro dos Canudos",
    "gn:country_code":"BR",
    "gn:dem":218,
    "gn:feature_class":"P",
    "gn:feature_code":"PPL",
    "gn:name":"Bairro dos Canudos",
    "gn:population":0,
    "gn:timezone":"America/Sao_Paulo",
    "iso:country":"BR",
    "name:por_x_preferred":[
        "Bairro dos Canudos"
    ],
    "wof:name":"Bairro dos Canudos",
    "wof:placetype":"locality"
},
  "geometry": {"coordinates":[-48.5395,-24.8965],"type":"Point"}
}