{
  "type": "Feature",
  "properties": {
    "gn:admin1_code":"26",
    "gn:admin2_code":"4205159.0",
    "gn:asciiname":"Heimat",
    "gn:country_code":"BR",
    "gn:dem":781,
    "gn:feature_class":"P",
    "gn:feature_code":"PPL",
    "gn:name":"Heimat",
    "gn:population":0,
    "gn:timezone":"America/Sao_Paulo",
    "iso:country":"BR",
    "wof:name":"Heimat",
    "wof:placetype":"locality"
},
  "geometry": {"coordinates":[-49.55,-26.71667],"type":"Point"}
}