{
  "type": "Feature",
  "properties": {
    "gn:admin1_code":"8",
    "gn:admin2_code":"3202405.0",
    "gn:asciiname":"Campo Grande",
    "gn:country_code":"BR",
    "gn:dem":24,
    "gn:feature_class":"P",
    "gn:feature_code":"PPL",
    "gn:name":"Campo Grande",
    "gn:population":0,
    "gn:timezone":"America/Sao_Paulo",
    "iso:country":"BR",
    "name:por_x_preferred":[
        "Campo Grande"
    ],
    "wof:name":"Campo Grande",
    "wof:placetype":"locality"
},
  "geometry": {"coordinates":[-40.46667,-20.55],"type":"Point"}
}