{
  "type": "Feature",
  "properties": {
    "gn:admin1_code":"15",
    "gn:admin2_code":"3144409.0",
    "gn:asciiname":"Atirado",
    "gn:country_code":"BR",
    "gn:dem":929,
    "gn:feature_class":"P",
    "gn:feature_code":"PPL",
    "gn:name":"Atirado",
    "gn:population":0,
    "gn:timezone":"America/Sao_Paulo",
    "iso:country":"BR",
    "name:por_x_preferred":[
        "Atirado"
    ],
    "wof:name":"Atirado",
    "wof:placetype":"locality"
},
  "geometry": {"coordinates":[-45.58333,-22.13333],"type":"Point"}
}