{
  "type": "Feature",
  "properties": {
    "gn:admin1_code":"30",
    "gn:admin2_code":"2607406.0",
    "gn:asciiname":"Campo Grande",
    "gn:country_code":"BR",
    "gn:dem":317,
    "gn:feature_class":"P",
    "gn:feature_code":"PPL",
    "gn:name":"Campo Grande",
    "gn:population":0,
    "gn:timezone":"America/Recife",
    "iso:country":"BR",
    "wof:name":"Campo Grande",
    "wof:placetype":"locality"
},
  "geometry": {"coordinates":[-38.63333,-8.66667],"type":"Point"}
}