{
  "type": "Feature",
  "properties": {
    "gn:admin1_code":"5",
    "gn:admin2_code":"2921203.0",
    "gn:asciiname":"Lajedinho",
    "gn:country_code":"BR",
    "gn:dem":576,
    "gn:feature_class":"P",
    "gn:feature_code":"PPL",
    "gn:name":"Lajedinho",
    "gn:population":0,
    "gn:timezone":"America/Bahia",
    "iso:country":"BR",
    "name:bpy_x_preferred":[
        "\u09b2\u09be\u099c\u09c7\u09a1\u09bf\u09a8\u09b9\u09cb"
    ],
    "name:ceb_x_preferred":[
        "Lajedinho"
    ],
    "name:epo_x_preferred":[
        "Lajedinho"
    ],
    "name:eus_x_preferred":[
        "Lajedinho"
    ],
    "name:fra_x_preferred":[
        "Lajedinho"
    ],
    "name:hye_x_preferred":[
        "\u053c\u0561\u056a\u0565\u0564\u056b\u0576\u056b\u0578\u0582"
    ],
    "name:ita_x_preferred":[
        "Lajedinho"
    ],
    "name:kat_x_preferred":[
        "\u10da\u10d0\u10df\u10d4\u10d3\u10d8\u10dc\u10d8\u10e3"
    ],
    "name:kaz_x_preferred":[
        "\u041b\u0430\u0436\u0435\u0434\u0438\u043d\u044c\u044e"
    ],
    "name:mlg_x_preferred":[
        "Lajedinho"
    ],
    "name:nld_x_preferred":[
        "Lajedinho"
    ],
    "name:nor_x_preferred":[
        "Lajedinho"
    ],
    "name:pol_x_preferred":[
        "Lajedinho"
    ],
    "name:por_x_preferred":[
        "Lajedinho"
    ],
    "name:ron_x_preferred":[
        "Lajedinho"
    ],
    "name:rus_x_preferred":[
        "\u041b\u0430\u0436\u0435\u0434\u0438\u043d\u044c\u044e"
    ],
    "name:spa_x_preferred":[
        "Lajedinho"
    ],
    "name:swe_x_preferred":[
        "Lajedinho"
    ],
    "name:urd_x_preferred":[
        "\u0644\u0627\u062c\u06cc\u0688\u06cc\u0646 \u06c1\u0648"
    ],
    "name:vie_x_preferred":[
        "Lajedinho"
    ],
    "name:vol_x_preferred":[
        "Lajedinho"
    ],
    "name:war_x_preferred":[
        "Lajedinho"
    ],
    "name:zho_x_preferred":[
        "\u62c9\u70ed\u8fea\u7ebd"
    ],
    "wof:name":"Lajedinho",
    "wof:placetype":"locality"
},
  "geometry": {"coordinates":[-40.63333,-11.38333],"type":"Point"}
}