{
  "type": "Feature",
  "properties": {
    "gn:admin1_code":"18.0",
    "gn:admin2_code":"4121208.0",
    "gn:asciiname":"Sitio Geraldo Itake",
    "gn:country_code":"BR",
    "gn:dem":849,
    "gn:feature_class":"P",
    "gn:feature_code":"PPL",
    "gn:name":"S\u00edtio Geraldo Itake",
    "gn:population":0,
    "gn:timezone":"America/Sao_Paulo",
    "iso:country":"BR",
    "name:por_x_preferred":[
        "S\u00edtio Geraldo Itake"
    ],
    "wof:name":"Sitio Geraldo Itake",
    "wof:placetype":"locality"
},
  "geometry": {"coordinates":[-49.5712,-25.8582],"type":"Point"}
}