{
  "type": "Feature",
  "properties": {
    "gn:admin1_code":"13",
    "gn:admin2_code":"2104081.0",
    "gn:asciiname":"Resplandes",
    "gn:country_code":"BR",
    "gn:dem":271,
    "gn:feature_class":"P",
    "gn:feature_code":"PPL",
    "gn:name":"Resplandes",
    "gn:population":0,
    "gn:timezone":"America/Fortaleza",
    "iso:country":"BR",
    "name:und_x_variant":[
        "Resplendes",
        "Resplandes"
    ],
    "wof:name":"Resplandes",
    "wof:placetype":"locality"
},
  "geometry": {"coordinates":[-45.2828,-6.15838],"type":"Point"}
}