{
  "type": "Feature",
  "properties": {
    "gn:admin1_code":"27",
    "gn:admin2_code":"3507001.0",
    "gn:asciiname":"Sitio Sao Miguel",
    "gn:country_code":"BR",
    "gn:dem":601,
    "gn:feature_class":"P",
    "gn:feature_code":"PPL",
    "gn:name":"S\u00edtio S\u00e3o Miguel",
    "gn:population":0,
    "gn:timezone":"America/Sao_Paulo",
    "iso:country":"BR",
    "name:por_x_preferred":[
        "S\u00edtio S\u00e3o Miguel"
    ],
    "wof:name":"Sitio Sao Miguel",
    "wof:placetype":"locality"
},
  "geometry": {"coordinates":[-47.67019000000001,-23.21463],"type":"Point"}
}