{
  "type": "Feature",
  "properties": {
    "gn:admin1_code":"06",
    "gn:admin2_code":"2303709.0",
    "gn:asciiname":"Mangabeira",
    "gn:country_code":"BR",
    "gn:dem":39,
    "gn:feature_class":"P",
    "gn:feature_code":"PPL",
    "gn:name":"Mangabeira",
    "gn:population":0,
    "gn:timezone":"America/Fortaleza",
    "iso:country":"BR",
    "wof:name":"Mangabeira",
    "wof:placetype":"locality"
},
  "geometry": {"coordinates":[-38.75,-3.66667],"type":"Point"}
}