{
  "type": "Feature",
  "properties": {
    "gn:admin1_code":"18.0",
    "gn:admin2_code":"4113205.0",
    "gn:asciiname":"Sitio Sergio R. Martins",
    "gn:country_code":"BR",
    "gn:dem":790,
    "gn:feature_class":"P",
    "gn:feature_code":"PPL",
    "gn:name":"S\u00edtio S\u00e9rgio R. Martins",
    "gn:population":0,
    "gn:timezone":"America/Sao_Paulo",
    "iso:country":"BR",
    "name:por_x_preferred":[
        "S\u00edtio S\u00e9rgio R. Martins"
    ],
    "wof:name":"Sitio Sergio R. Martins",
    "wof:placetype":"locality"
},
  "geometry": {"coordinates":[-49.9114,-25.576],"type":"Point"}
}