{
  "type": "Feature",
  "properties": {
    "gn:admin1_code":"20",
    "gn:admin2_code":"2209971.0",
    "gn:asciiname":"Arraial",
    "gn:country_code":"BR",
    "gn:dem":101,
    "gn:feature_class":"P",
    "gn:feature_code":"PPL",
    "gn:name":"Arraial",
    "gn:population":0,
    "gn:timezone":"America/Fortaleza",
    "iso:country":"BR",
    "name:bpy_x_preferred":[
        "\u0986\u09b0\u09cd\u09b0\u09be\u0987\u0986\u09b2"
    ],
    "name:eus_x_preferred":[
        "Arraial"
    ],
    "name:fra_x_preferred":[
        "Arraial"
    ],
    "name:ita_x_preferred":[
        "Arraial"
    ],
    "name:kaz_x_preferred":[
        "\u0410\u0440\u0440\u0430\u044f\u043b"
    ],
    "name:nld_x_preferred":[
        "Arraial"
    ],
    "name:nor_x_preferred":[
        "Arraial"
    ],
    "name:por_x_preferred":[
        "Arraial"
    ],
    "name:ron_x_preferred":[
        "Arraial"
    ],
    "name:rus_x_preferred":[
        "\u0410\u0440\u0440\u0430\u044f\u043b"
    ],
    "name:vie_x_preferred":[
        "Arraial"
    ],
    "name:vol_x_preferred":[
        "Arraial"
    ],
    "name:war_x_preferred":[
        "Arraial"
    ],
    "name:zho_x_preferred":[
        "\u963f\u62c9\u4e9a\u5c14"
    ],
    "wof:name":"Arraial",
    "wof:placetype":"locality"
},
  "geometry": {"coordinates":[-42.44611,-3.81972],"type":"Point"}
}