{
  "type": "Feature",
  "properties": {
    "gn:admin1_code":"18",
    "gn:admin2_code":"4106209.0",
    "gn:asciiname":"Sitio Alberto Kava",
    "gn:country_code":"BR",
    "gn:dem":866,
    "gn:feature_class":"P",
    "gn:feature_code":"PPL",
    "gn:name":"S\u00edtio Alberto Kava",
    "gn:population":0,
    "gn:timezone":"America/Sao_Paulo",
    "iso:country":"BR",
    "name:por_x_preferred":[
        "S\u00edtio Alberto Kava"
    ],
    "wof:name":"Sitio Alberto Kava",
    "wof:placetype":"locality"
},
  "geometry": {"coordinates":[-49.53417,-25.75194],"type":"Point"}
}