{
  "type": "Feature",
  "properties": {
    "gn:admin1_code":"27.0",
    "gn:admin2_code":"3552205.0",
    "gn:asciiname":"Sitio Larecio",
    "gn:country_code":"BR",
    "gn:dem":612,
    "gn:feature_class":"P",
    "gn:feature_code":"PPL",
    "gn:name":"S\u00edtio Larec\u00edo",
    "gn:population":0,
    "gn:timezone":"America/Sao_Paulo",
    "iso:country":"BR",
    "name:por_x_preferred":[
        "S\u00edtio Larec\u00edo"
    ],
    "wof:name":"Sitio Larecio",
    "wof:placetype":"locality"
},
  "geometry": {"coordinates":[-47.5435,-23.5453],"type":"Point"}
}