{
  "type": "Feature",
  "properties": {
    "gn:admin1_code":"5",
    "gn:admin2_code":"2927200.0",
    "gn:asciiname":"Serra da Rosa",
    "gn:country_code":"BR",
    "gn:dem":542,
    "gn:feature_class":"P",
    "gn:feature_code":"PPL",
    "gn:name":"Serra da Rosa",
    "gn:population":0,
    "gn:timezone":"America/Bahia",
    "iso:country":"BR",
    "wof:name":"Serra da Rosa",
    "wof:placetype":"locality"
},
  "geometry": {"coordinates":[-40.55,-12.13333],"type":"Point"}
}