{
  "type": "Feature",
  "properties": {
    "gn:admin1_code":"4",
    "gn:admin2_code":"1301209.0",
    "gn:asciiname":"Andrade",
    "gn:country_code":"BR",
    "gn:dem":21,
    "gn:feature_class":"P",
    "gn:feature_code":"PPL",
    "gn:name":"Andrade",
    "gn:population":0,
    "gn:timezone":"America/Manaus",
    "iso:country":"BR",
    "name:deu_x_preferred":[
        "Andrade"
    ],
    "name:glg_x_preferred":[
        "Andrade"
    ],
    "name:por_x_preferred":[
        "Andrade"
    ],
    "wof:name":"Andrade",
    "wof:placetype":"locality"
},
  "geometry": {"coordinates":[-63.55694,-4.50889],"type":"Point"}
}