{
  "type": "Feature",
  "properties": {
    "gn:admin1_code":"18.0",
    "gn:admin2_code":"4104709.0",
    "gn:asciiname":"Sitio Pedro Rivelino",
    "gn:country_code":"BR",
    "gn:dem":635,
    "gn:feature_class":"P",
    "gn:feature_code":"PPL",
    "gn:name":"S\u00edtio Pedro Rivelino",
    "gn:population":0,
    "gn:timezone":"America/Sao_Paulo",
    "iso:country":"BR",
    "name:por_x_preferred":[
        "S\u00edtio Pedro Rivelino"
    ],
    "wof:name":"Sitio Pedro Rivelino",
    "wof:placetype":"locality"
},
  "geometry": {"coordinates":[-49.84576,-23.4524],"type":"Point"}
}