{
  "type": "Feature",
  "properties": {
    "gn:admin1_code":"8",
    "gn:admin2_code":"3201209.0",
    "gn:asciiname":"Mutum",
    "gn:country_code":"BR",
    "gn:dem":142,
    "gn:feature_class":"P",
    "gn:feature_code":"PPL",
    "gn:name":"Mutum",
    "gn:population":0,
    "gn:timezone":"America/Sao_Paulo",
    "iso:country":"BR",
    "name:ceb_x_preferred":[
        "Mutum"
    ],
    "name:fra_x_preferred":[
        "Mutum"
    ],
    "name:por_x_preferred":[
        "Mutum"
    ],
    "name:swe_x_preferred":[
        "Mutum"
    ],
    "wof:name":"Mutum",
    "wof:placetype":"locality"
},
  "geometry": {"coordinates":[-41.23333,-20.75],"type":"Point"}
}