{
  "type": "Feature",
  "properties": {
    "gn:admin1_code":"18",
    "gn:admin2_code":"4122503.0",
    "gn:asciiname":"Macacos",
    "gn:cc2":"BR",
    "gn:country_code":"BR",
    "gn:dem":616,
    "gn:feature_class":"P",
    "gn:feature_code":"PPL",
    "gn:name":"Macacos",
    "gn:population":0,
    "gn:timezone":"America/Sao_Paulo",
    "iso:country":"BR",
    "name:und_x_variant":[
        "Macacas",
        "Macacos"
    ],
    "wof:name":"Macacos",
    "wof:placetype":"locality"
},
  "geometry": {"coordinates":[-52.33333,-24.63333],"type":"Point"}
}