{
  "type": "Feature",
  "properties": {
    "gn:admin1_code":"17",
    "gn:admin2_code":"2512788.0",
    "gn:asciiname":"Compos das Almas",
    "gn:country_code":"BR",
    "gn:dem":504,
    "gn:feature_class":"P",
    "gn:feature_code":"PPL",
    "gn:name":"Compos das Almas",
    "gn:population":0,
    "gn:timezone":"America/Fortaleza",
    "iso:country":"BR",
    "wof:name":"Compos das Almas",
    "wof:placetype":"locality"
},
  "geometry": {"coordinates":[-36.15,-7.73333],"type":"Point"}
}