{
  "type": "Feature",
  "properties": {
    "gn:admin1_code":"17",
    "gn:admin2_code":"2501708.0",
    "gn:asciiname":"Patas",
    "gn:country_code":"BR",
    "gn:dem":393,
    "gn:feature_class":"P",
    "gn:feature_code":"PPL",
    "gn:name":"Patas",
    "gn:population":0,
    "gn:timezone":"America/Fortaleza",
    "iso:country":"BR",
    "wof:name":"Patas",
    "wof:placetype":"locality"
},
  "geometry": {"coordinates":[-36.26667,-7.56667],"type":"Point"}
}