{
  "type": "Feature",
  "properties": {
    "gn:admin1_code":"16.0",
    "gn:admin2_code":"1504802.0",
    "gn:asciiname":"Jacarateua",
    "gn:country_code":"BR",
    "gn:dem":18,
    "gn:feature_class":"P",
    "gn:feature_code":"PPL",
    "gn:name":"Jacarateua",
    "gn:population":0,
    "gn:timezone":"America/Santarem",
    "iso:country":"BR",
    "name:por_x_preferred":[
        "Jacarateua"
    ],
    "wof:name":"Jacarateua",
    "wof:placetype":"locality"
},
  "geometry": {"coordinates":[-54.03533,-1.97231],"type":"Point"}
}