{
  "type": "Feature",
  "properties": {
    "gn:admin1_code":"30",
    "gn:admin2_code":"2614857.0",
    "gn:asciiname":"Praia dos Carneiros",
    "gn:country_code":"BR",
    "gn:dem":11,
    "gn:feature_class":"P",
    "gn:feature_code":"PPL",
    "gn:name":"Praia dos Carneiros",
    "gn:population":0,
    "gn:timezone":"America/Recife",
    "iso:country":"BR",
    "wof:name":"Praia dos Carneiros",
    "wof:placetype":"locality"
},
  "geometry": {"coordinates":[-35.08759000000001,-8.70729],"type":"Point"}
}