{
  "type": "Feature",
  "properties": {
    "gn:admin1_code":"06",
    "gn:admin2_code":"2306405.0",
    "gn:asciiname":"Capote",
    "gn:country_code":"BR",
    "gn:dem":63,
    "gn:feature_class":"P",
    "gn:feature_code":"PPL",
    "gn:name":"Capote",
    "gn:population":0,
    "gn:timezone":"America/Fortaleza",
    "iso:country":"BR",
    "wof:name":"Capote",
    "wof:placetype":"locality"
},
  "geometry": {"coordinates":[-39.51667,-3.35],"type":"Point"}
}