{
  "type": "Feature",
  "properties": {
    "gn:admin1_code":"06",
    "gn:admin2_code":"2306405.0",
    "gn:asciiname":"Capote",
    "gn:country_code":"BR",
    "gn:dem":63,
    "gn:feature_class":"P",
    "gn:feature_code":"PPL",
    "gn:name":"Capote",
    "gn:population":0,
    "gn:timezone":"America/Fortaleza",
    "iso:country":"BR",
    "name:ceb_x_preferred":[
        "Capote"
    ],
    "name:dan_x_preferred":[
        "Capote"
    ],
    "name:deu_x_preferred":[
        "Capote"
    ],
    "name:fra_x_preferred":[
        "Capote"
    ],
    "name:hrv_x_preferred":[
        "Capote"
    ],
    "name:ita_x_preferred":[
        "Capote"
    ],
    "name:nld_x_preferred":[
        "Capote"
    ],
    "name:pol_x_preferred":[
        "Capote"
    ],
    "name:rus_x_preferred":[
        "\u041a\u0430\u043f\u043e\u0442\u0435"
    ],
    "name:spa_x_preferred":[
        "Capote"
    ],
    "name:swe_x_preferred":[
        "Capote"
    ],
    "name:tur_x_preferred":[
        "Capote"
    ],
    "name:wln_x_preferred":[
        "Capote"
    ],
    "wof:name":"Capote",
    "wof:placetype":"locality"
},
  "geometry": {"coordinates":[-39.51667,-3.35],"type":"Point"}
}