{
  "type": "Feature",
  "properties": {
    "gn:admin1_code":"18.0",
    "gn:admin2_code":"4114302.0",
    "gn:asciiname":"Colonia Retiro",
    "gn:country_code":"BR",
    "gn:dem":938,
    "gn:feature_class":"P",
    "gn:feature_code":"PPLL",
    "gn:name":"Col\u00f4nia Retiro",
    "gn:population":0,
    "gn:timezone":"America/Sao_Paulo",
    "iso:country":"BR",
    "name:por_x_preferred":[
        "Col\u00f4nia Retiro"
    ],
    "wof:name":"Colonia Retiro",
    "wof:placetype":"locality"
},
  "geometry": {"coordinates":[-49.2794,-25.7884],"type":"Point"}
}