{
  "type": "Feature",
  "properties": {
    "gn:admin1_code":"5",
    "gn:admin2_code":"2904753.0",
    "gn:asciiname":"Lameirao",
    "gn:cc2":"BR",
    "gn:country_code":"BR",
    "gn:dem":537,
    "gn:feature_class":"P",
    "gn:feature_code":"PPL",
    "gn:name":"Lameir\u00e3o",
    "gn:population":0,
    "gn:timezone":"America/Bahia",
    "iso:country":"BR",
    "name:und_x_variant":[
        "Lamar\u00e3o",
        "Lameir\u00e3o"
    ],
    "wof:name":"Lameirao",
    "wof:placetype":"locality"
},
  "geometry": {"coordinates":[-43.61667,-10.65],"type":"Point"}
}