{
  "type": "Feature",
  "properties": {
    "gn:admin1_code":"26",
    "gn:admin2_code":"4209003.0",
    "gn:asciiname":"Erval d'Oeste",
    "gn:country_code":"BR",
    "gn:dem":657,
    "gn:feature_class":"P",
    "gn:feature_code":"PPL",
    "gn:name":"Erval d\u2019Oeste",
    "gn:population":0,
    "gn:timezone":"America/Sao_Paulo",
    "iso:country":"BR",
    "name:und_x_variant":[
        "Herval",
        "Erval",
        "Erval d\u2019Oeste"
    ],
    "wof:name":"Erval d'Oeste",
    "wof:placetype":"locality"
},
  "geometry": {"coordinates":[-51.56667,-27.21667],"type":"Point"}
}