{
  "type": "Feature",
  "properties": {
    "gn:admin1_code":"4",
    "gn:admin2_code":"1301209.0",
    "gn:asciiname":"Nazaria de Baixo",
    "gn:country_code":"BR",
    "gn:dem":34,
    "gn:feature_class":"P",
    "gn:feature_code":"PPLL",
    "gn:name":"Naz\u00e1ria de Baixo",
    "gn:population":0,
    "gn:timezone":"America/Manaus",
    "iso:country":"BR",
    "wof:name":"Nazaria de Baixo",
    "wof:placetype":"locality"
},
  "geometry": {"coordinates":[-62.60542,-3.85486],"type":"Point"}
}