{
  "type": "Feature",
  "properties": {
    "gn:admin1_code":"18.0",
    "gn:admin2_code":"4124103.0",
    "gn:asciiname":"Sitio Inacio",
    "gn:country_code":"BR",
    "gn:dem":528,
    "gn:feature_class":"P",
    "gn:feature_code":"PPL",
    "gn:name":"S\u00edtio In\u00e1cio",
    "gn:population":0,
    "gn:timezone":"America/Sao_Paulo",
    "iso:country":"BR",
    "name:por_x_preferred":[
        "S\u00edtio In\u00e1cio"
    ],
    "wof:name":"Sitio Inacio",
    "wof:placetype":"locality"
},
  "geometry": {"coordinates":[-50.03504,-23.34089],"type":"Point"}
}