{
  "type": "Feature",
  "properties": {
    "gn:admin1_code":"20",
    "gn:admin2_code":"2202901.0",
    "gn:asciiname":"Projeto",
    "gn:country_code":"BR",
    "gn:dem":612,
    "gn:feature_class":"P",
    "gn:feature_code":"PPL",
    "gn:name":"Projeto",
    "gn:population":0,
    "gn:timezone":"America/Fortaleza",
    "iso:country":"BR",
    "wof:name":"Projeto",
    "wof:placetype":"locality"
},
  "geometry": {"coordinates":[-45.25,-10.23333],"type":"Point"}
}