{
  "type": "Feature",
  "properties": {
    "gn:admin1_code":"27",
    "gn:admin2_code":"3555406.0",
    "gn:asciiname":"Itamambuca",
    "gn:country_code":"BR",
    "gn:dem":8,
    "gn:feature_class":"P",
    "gn:feature_code":"PPL",
    "gn:name":"Itamambuca",
    "gn:population":0,
    "gn:timezone":"America/Sao_Paulo",
    "iso:country":"BR",
    "wof:name":"Itamambuca",
    "wof:placetype":"locality"
},
  "geometry": {"coordinates":[-45.00412,-23.39835],"type":"Point"}
}