{
  "type": "Feature",
  "properties": {
    "gn:admin1_code":"06",
    "gn:admin2_code":"2310803.0",
    "gn:asciiname":"Cruz",
    "gn:country_code":"BR",
    "gn:dem":729,
    "gn:feature_class":"P",
    "gn:feature_code":"PPL",
    "gn:name":"Cruz",
    "gn:population":0,
    "gn:timezone":"America/Fortaleza",
    "iso:country":"BR",
    "wof:name":"Cruz",
    "wof:placetype":"locality"
},
  "geometry": {"coordinates":[-38.51667,-6.18333],"type":"Point"}
}