{
  "type": "Feature",
  "properties": {
    "gn:admin1_code":"18",
    "gn:admin2_code":"4119400.0",
    "gn:asciiname":"Curralinho",
    "gn:cc2":"BR",
    "gn:country_code":"BR",
    "gn:dem":1025,
    "gn:feature_class":"P",
    "gn:feature_code":"PPL",
    "gn:name":"Curralinho",
    "gn:population":0,
    "gn:timezone":"America/Sao_Paulo",
    "iso:country":"BR",
    "name:bpy_x_preferred":[
        "\u0995\u09c1\u09b0\u09cd\u09b0\u09be\u09b2\u09bf\u09a8\u09b9\u09cb"
    ],
    "name:eus_x_preferred":[
        "Curralinho"
    ],
    "name:fra_x_preferred":[
        "Curralinho"
    ],
    "name:ita_x_preferred":[
        "Curralinho"
    ],
    "name:kaz_x_preferred":[
        "\u041a\u0443\u0440\u0440\u0430\u043b\u0438\u043d\u044c\u044e"
    ],
    "name:nld_x_preferred":[
        "Curralinho"
    ],
    "name:nor_x_preferred":[
        "Curralinho"
    ],
    "name:pol_x_preferred":[
        "Curralinho"
    ],
    "name:por_x_preferred":[
        "Curralinho"
    ],
    "name:ron_x_preferred":[
        "Curralinho"
    ],
    "name:rus_x_preferred":[
        "\u041a\u0443\u0440\u0440\u0430\u043b\u0438\u043d\u044c\u044e"
    ],
    "name:und_x_variant":[
        "Fazenda Curralinho"
    ],
    "name:vie_x_preferred":[
        "Curralinho"
    ],
    "name:vol_x_preferred":[
        "Curralinho"
    ],
    "name:war_x_preferred":[
        "Curralinho"
    ],
    "name:zho_x_preferred":[
        "\u5eab\u62c9\u5229\u7d10"
    ],
    "wof:name":"Curralinho",
    "wof:placetype":"locality"
},
  "geometry": {"coordinates":[-50.05,-24.43333],"type":"Point"}
}