{
  "type": "Feature",
  "properties": {
    "gn:admin1_code":"18",
    "gn:admin2_code":"4119400.0",
    "gn:asciiname":"Curralinho",
    "gn:cc2":"BR",
    "gn:country_code":"BR",
    "gn:dem":1025,
    "gn:feature_class":"P",
    "gn:feature_code":"PPL",
    "gn:name":"Curralinho",
    "gn:population":0,
    "gn:timezone":"America/Sao_Paulo",
    "iso:country":"BR",
    "name:und_x_variant":[
        "Fazenda Curralinho",
        "Curralinho"
    ],
    "wof:name":"Curralinho",
    "wof:placetype":"locality"
},
  "geometry": {"coordinates":[-50.05,-24.43333],"type":"Point"}
}