{
  "type": "Feature",
  "properties": {
    "gn:admin1_code":"27",
    "gn:admin2_code":"3525201.0",
    "gn:asciiname":"Sitio Coraj",
    "gn:country_code":"BR",
    "gn:dem":821,
    "gn:feature_class":"P",
    "gn:feature_code":"PPL",
    "gn:name":"S\u00edtio Coraj",
    "gn:population":0,
    "gn:timezone":"America/Sao_Paulo",
    "iso:country":"BR",
    "name:por_x_preferred":[
        "S\u00edtio Coraj"
    ],
    "wof:name":"Sitio Coraj",
    "wof:placetype":"locality"
},
  "geometry": {"coordinates":[-46.69277,-23.13974],"type":"Point"}
}