{
  "type": "Feature",
  "properties": {
    "gn:admin1_code":"4",
    "gn:admin2_code":"1302207.0",
    "gn:asciiname":"Renascenca",
    "gn:country_code":"BR",
    "gn:dem":64,
    "gn:feature_class":"P",
    "gn:feature_code":"PPL",
    "gn:name":"Renascen\u00e7a",
    "gn:population":0,
    "gn:timezone":"America/Manaus",
    "iso:country":"BR",
    "wof:name":"Renascenca",
    "wof:placetype":"locality"
},
  "geometry": {"coordinates":[-66.34999999999999,-3.83333],"type":"Point"}
}