{
  "type": "Feature",
  "properties": {
    "gn:admin1_code":"15",
    "gn:admin2_code":"3133501.0",
    "gn:asciiname":"Calambau",
    "gn:country_code":"BR",
    "gn:dem":861,
    "gn:feature_class":"P",
    "gn:feature_code":"PPL",
    "gn:name":"Calambau",
    "gn:population":0,
    "gn:timezone":"America/Sao_Paulo",
    "iso:country":"BR",
    "name:por_x_preferred":[
        "Calambau"
    ],
    "wof:name":"Calambau",
    "wof:placetype":"locality"
},
  "geometry": {"coordinates":[-45.05,-20.58333],"type":"Point"}
}