{
  "type": "Feature",
  "properties": {
    "gn:admin1_code":"18.0",
    "gn:admin2_code":"4112801.0",
    "gn:asciiname":"Sitio Agua Limpa",
    "gn:country_code":"BR",
    "gn:dem":609,
    "gn:feature_class":"P",
    "gn:feature_code":"PPL",
    "gn:name":"S\u00edtio \u00c1gua Limpa",
    "gn:population":0,
    "gn:timezone":"America/Sao_Paulo",
    "iso:country":"BR",
    "name:por_x_preferred":[
        "S\u00edtio \u00c1gua Limpa"
    ],
    "wof:name":"Sitio Agua Limpa",
    "wof:placetype":"locality"
},
  "geometry": {"coordinates":[-49.8962,-23.5157],"type":"Point"}
}