{
  "type": "Feature",
  "properties": {
    "gn:admin1_code":"27",
    "gn:admin2_code":"3556453.0",
    "gn:asciiname":"Bairro Jardim Betania",
    "gn:country_code":"BR",
    "gn:dem":911,
    "gn:feature_class":"P",
    "gn:feature_code":"PPL",
    "gn:name":"Bairro Jardim Bet\u00e2nia",
    "gn:population":0,
    "gn:timezone":"America/Sao_Paulo",
    "iso:country":"BR",
    "name:por_x_preferred":[
        "Bairro Jardim Bet\u00e2nia"
    ],
    "wof:name":"Bairro Jardim Betania",
    "wof:placetype":"locality"
},
  "geometry": {"coordinates":[-47.02045,-23.5985],"type":"Point"}
}