{
  "type": "Feature",
  "properties": {
    "gn:admin1_code":"16.0",
    "gn:admin2_code":"1503077.0",
    "gn:asciiname":"Garrafao",
    "gn:country_code":"BR",
    "gn:dem":47,
    "gn:feature_class":"P",
    "gn:feature_code":"PPL",
    "gn:name":"Garraf\u00e3o",
    "gn:population":0,
    "gn:timezone":"America/Belem",
    "iso:country":"BR",
    "wof:name":"Garrafao",
    "wof:placetype":"locality"
},
  "geometry": {"coordinates":[-47.0508,-1.93455],"type":"Point"}
}