{
  "type": "Feature",
  "properties": {
    "gn:admin1_code":"31",
    "gn:admin2_code":"1700350.0",
    "gn:asciiname":"Porteira",
    "gn:country_code":"BR",
    "gn:dem":251,
    "gn:feature_class":"P",
    "gn:feature_code":"PPL",
    "gn:name":"Porteira",
    "gn:population":0,
    "gn:timezone":"America/Araguaina",
    "iso:country":"BR",
    "wof:name":"Porteira",
    "wof:placetype":"locality"
},
  "geometry": {"coordinates":[-48.61667,-11.38333],"type":"Point"}
}