{
  "type": "Feature",
  "properties": {
    "gn:admin1_code":"30",
    "gn:admin2_code":"2603900.0",
    "gn:asciiname":"Marias Pretas",
    "gn:country_code":"BR",
    "gn:dem":518,
    "gn:feature_class":"P",
    "gn:feature_code":"PPL",
    "gn:name":"Marias Pretas",
    "gn:population":0,
    "gn:timezone":"America/Recife",
    "iso:country":"BR",
    "wof:name":"Marias Pretas",
    "wof:placetype":"locality"
},
  "geometry": {"coordinates":[-37.78333,-7.85],"type":"Point"}
}