{
  "type": "Feature",
  "properties": {
    "gn:admin1_code":"4",
    "gn:admin2_code":"1302405.0",
    "gn:asciiname":"Cachoeira",
    "gn:country_code":"BR",
    "gn:dem":75,
    "gn:feature_class":"P",
    "gn:feature_code":"PPL",
    "gn:name":"Cachoeira",
    "gn:population":0,
    "gn:timezone":"America/Manaus",
    "iso:country":"BR",
    "wof:name":"Cachoeira",
    "wof:placetype":"locality"
},
  "geometry": {"coordinates":[-65.98796,-7.68101],"type":"Point"}
}