{
  "type": "Feature",
  "properties": {
    "gn:admin1_code":"27",
    "gn:admin2_code":"3554508.0",
    "gn:asciiname":"Sitio Chimbo",
    "gn:country_code":"BR",
    "gn:dem":518,
    "gn:feature_class":"P",
    "gn:feature_code":"PPL",
    "gn:name":"S\u00edtio Chimbo",
    "gn:population":0,
    "gn:timezone":"America/Sao_Paulo",
    "iso:country":"BR",
    "name:por_x_preferred":[
        "S\u00edtio Chimbo"
    ],
    "wof:name":"Sitio Chimbo",
    "wof:placetype":"locality"
},
  "geometry": {"coordinates":[-47.68167,-23.17056],"type":"Point"}
}