{
  "type": "Feature",
  "properties": {
    "gn:admin1_code":"18.0",
    "gn:admin2_code":"4112306.0",
    "gn:asciiname":"Sitio Monte Sol",
    "gn:country_code":"BR",
    "gn:dem":674,
    "gn:feature_class":"P",
    "gn:feature_code":"PPL",
    "gn:name":"S\u00edtio Monte Sol",
    "gn:population":0,
    "gn:timezone":"America/Sao_Paulo",
    "iso:country":"BR",
    "name:por_x_preferred":[
        "S\u00edtio Monte Sol"
    ],
    "wof:name":"Sitio Monte Sol",
    "wof:placetype":"locality"
},
  "geometry": {"coordinates":[-50.11782,-23.8079],"type":"Point"}
}