{
  "type": "Feature",
  "properties": {
    "gn:admin1_code":"18.0",
    "gn:admin2_code":"4104006.0",
    "gn:asciiname":"Sitio Zenobio A. de Oliveira",
    "gn:country_code":"BR",
    "gn:dem":817,
    "gn:feature_class":"P",
    "gn:feature_code":"PPL",
    "gn:name":"S\u00edtio Zen\u00f3bio A. de Oliveira",
    "gn:population":0,
    "gn:timezone":"America/Sao_Paulo",
    "iso:country":"BR",
    "name:por_x_preferred":[
        "S\u00edtio Zen\u00f3bio A. de Oliveira"
    ],
    "wof:name":"Sitio Zenobio A. de Oliveira",
    "wof:placetype":"locality"
},
  "geometry": {"coordinates":[-48.91371,-25.257],"type":"Point"}
}