{
  "type": "Feature",
  "properties": {
    "gn:admin1_code":"30",
    "gn:admin2_code":"2615805.0",
    "gn:asciiname":"Urubu Choco",
    "gn:country_code":"BR",
    "gn:dem":732,
    "gn:feature_class":"P",
    "gn:feature_code":"PPL",
    "gn:name":"Urubu Ch\u00f4co",
    "gn:population":0,
    "gn:timezone":"America/Recife",
    "iso:country":"BR",
    "wof:name":"Urubu Choco",
    "wof:placetype":"locality"
},
  "geometry": {"coordinates":[-37.31667,-8.71667],"type":"Point"}
}