{
  "type": "Feature",
  "properties": {
    "gn:admin1_code":"02",
    "gn:admin2_code":"2700409.0",
    "gn:asciiname":"Ouricuri",
    "gn:country_code":"BR",
    "gn:dem":158,
    "gn:feature_class":"P",
    "gn:feature_code":"PPL",
    "gn:name":"Ouricuri",
    "gn:population":0,
    "gn:timezone":"America/Maceio",
    "iso:country":"BR",
    "name:bpy_x_preferred":[
        "\u0994\u09b0\u09bf\u0995\u09c1\u09b0\u09bf"
    ],
    "name:bre_x_preferred":[
        "Ouricuri"
    ],
    "name:eus_x_preferred":[
        "Ouricuri"
    ],
    "name:fra_x_preferred":[
        "Ouricuri"
    ],
    "name:ita_x_preferred":[
        "Ouricuri"
    ],
    "name:kat_x_preferred":[
        "\u10dd\u10e0\u10d8\u10d9\u10e3\u10e0\u10d8"
    ],
    "name:kaz_x_preferred":[
        "\u041e\u0440\u0438\u043a\u0443\u0440\u0438"
    ],
    "name:nld_x_preferred":[
        "Ouricuri"
    ],
    "name:nor_x_preferred":[
        "Ouricuri"
    ],
    "name:por_x_preferred":[
        "Ouricuri"
    ],
    "name:ron_x_preferred":[
        "Ouricuri"
    ],
    "name:rus_x_preferred":[
        "\u041e\u0440\u0438\u043a\u0443\u0440\u0438"
    ],
    "name:vie_x_preferred":[
        "Ouricuri"
    ],
    "name:vol_x_preferred":[
        "Ouricuri"
    ],
    "name:war_x_preferred":[
        "Ouricuri"
    ],
    "name:zho_x_preferred":[
        "\u6b27\u91cc\u5e93\u91cc"
    ],
    "wof:name":"Ouricuri",
    "wof:placetype":"locality"
},
  "geometry": {"coordinates":[-36.18333,-9.55],"type":"Point"}
}