{
  "type": "Feature",
  "properties": {
    "gn:admin1_code":"02",
    "gn:admin2_code":"2700409.0",
    "gn:asciiname":"Ouricuri",
    "gn:country_code":"BR",
    "gn:dem":158,
    "gn:feature_class":"P",
    "gn:feature_code":"PPL",
    "gn:name":"Ouricuri",
    "gn:population":0,
    "gn:timezone":"America/Maceio",
    "iso:country":"BR",
    "wof:name":"Ouricuri",
    "wof:placetype":"locality"
},
  "geometry": {"coordinates":[-36.18333,-9.55],"type":"Point"}
}