{
  "type": "Feature",
  "properties": {
    "gn:admin1_code":"18.0",
    "gn:admin2_code":"4114302.0",
    "gn:asciiname":"Sitio Daniel B. dos Santos",
    "gn:country_code":"BR",
    "gn:dem":837,
    "gn:feature_class":"P",
    "gn:feature_code":"PPL",
    "gn:name":"S\u00edtio Daniel B. dos Santos",
    "gn:population":0,
    "gn:timezone":"America/Sao_Paulo",
    "iso:country":"BR",
    "name:por_x_preferred":[
        "S\u00edtio Daniel B. dos Santos"
    ],
    "wof:name":"Sitio Daniel B. dos Santos",
    "wof:placetype":"locality"
},
  "geometry": {"coordinates":[-49.3636,-25.9251],"type":"Point"}
}