{
  "type": "Feature",
  "properties": {
    "gn:admin1_code":"18.0",
    "gn:admin2_code":"4113205.0",
    "gn:asciiname":"Sitio Arnaldo do F. Guedes",
    "gn:country_code":"BR",
    "gn:dem":884,
    "gn:feature_class":"P",
    "gn:feature_code":"PPL",
    "gn:name":"S\u00edtio Arnaldo do F. Guedes",
    "gn:population":0,
    "gn:timezone":"America/Sao_Paulo",
    "iso:country":"BR",
    "name:por_x_preferred":[
        "S\u00edtio Arnaldo do F. Guedes"
    ],
    "wof:name":"Sitio Arnaldo do F. Guedes",
    "wof:placetype":"locality"
},
  "geometry": {"coordinates":[-49.98615,-25.84043],"type":"Point"}
}