{
  "type": "Feature",
  "properties": {
    "gn:admin1_code":"23",
    "gn:admin2_code":"4306007.0",
    "gn:asciiname":"Estradaozinho",
    "gn:country_code":"BR",
    "gn:dem":301,
    "gn:feature_class":"P",
    "gn:feature_code":"PPL",
    "gn:name":"Estrad\u00e3ozinho",
    "gn:population":0,
    "gn:timezone":"America/Sao_Paulo",
    "iso:country":"BR",
    "wof:name":"Estradaozinho",
    "wof:placetype":"locality"
},
  "geometry": {"coordinates":[-54.16667,-27.51667],"type":"Point"}
}