{
  "type": "Feature",
  "properties": {
    "gn:admin1_code":"06",
    "gn:admin2_code":"2303931.0",
    "gn:asciiname":"Saco do Feijao",
    "gn:country_code":"BR",
    "gn:dem":222,
    "gn:feature_class":"P",
    "gn:feature_code":"PPL",
    "gn:name":"Saco do Feij\u00e3o",
    "gn:population":0,
    "gn:timezone":"America/Fortaleza",
    "iso:country":"BR",
    "wof:name":"Saco do Feijao",
    "wof:placetype":"locality"
},
  "geometry": {"coordinates":[-39.26667,-4.71667],"type":"Point"}
}