{
  "type": "Feature",
  "properties": {
    "iso:country":"BR",
    "name:por_x_preferred":[
        "U.t.p. Pedro Ludovico"
    ],
    "name:unk_x_variant":[
        "U.t.p. Pedro Ludovico"
    ],
    "qs:gn_adm0_cc":"BR",
    "qs:gn_local":3462377,
    "qs:gn_nam_loc":"Goi\u00e2nia, Goi\u00e2nia, Goi\u00e1s, BR",
    "qs:gn_namadm1":"29",
    "qs:local_max":1622,
    "qs:local_sum":8361,
    "qs:localhoods":16,
    "qs:name":"U.t.p. Pedro Ludovico",
    "qs:name_adm0":"Brasil",
    "qs:name_adm1":"Goi\u00e1s",
    "qs:name_adm2":"Goi\u00e2nia",
    "qs:name_local":"Goi\u00e2nia",
    "qs:photo_max":256,
    "qs:photo_sum":641,
    "qs:placetype":"Suburb",
    "qs:quad_count":25,
    "qs:woe_adm0":23424768,
    "qs:woe_adm1":2344852,
    "qs:woe_adm2":12578971,
    "qs:woe_lau":0,
    "qs:woe_local":455831,
    "qs:woe_ver":"7.10.0",
    "wof:lang":[
        "por"
    ],
    "wof:name":"U.t.p. Pedro Ludovico",
    "wof:placetype":"neighbourhood"
},
  "geometry": {"coordinates":[-49.264529,-16.711251],"type":"Point"}
}