{
  "type": "Feature",
  "properties": {
    "gn:admin1_code":"18.0",
    "gn:admin2_code":"4117305.0",
    "gn:asciiname":"Sitio Valdir Baggio",
    "gn:country_code":"BR",
    "gn:dem":676,
    "gn:feature_class":"P",
    "gn:feature_code":"PPL",
    "gn:name":"S\u00edtio Valdir Baggio",
    "gn:population":0,
    "gn:timezone":"America/Sao_Paulo",
    "iso:country":"BR",
    "name:por_x_preferred":[
        "S\u00edtio Valdir Baggio"
    ],
    "wof:name":"Sitio Valdir Baggio",
    "wof:placetype":"locality"
},
  "geometry": {"coordinates":[-50.85651,-23.97958],"type":"Point"}
}