{
  "type": "Feature",
  "properties": {
    "gn:admin1_code":"30.0",
    "gn:admin2_code":"2614204.0",
    "gn:asciiname":"Cohab",
    "gn:country_code":"BR",
    "gn:dem":27,
    "gn:feature_class":"P",
    "gn:feature_code":"PPL",
    "gn:name":"Cohab",
    "gn:population":0,
    "gn:timezone":"America/Recife",
    "iso:country":"BR",
    "wof:name":"Cohab",
    "wof:placetype":"locality"
},
  "geometry": {"coordinates":[-35.11252,-8.5986],"type":"Point"}
}