{
  "type": "Feature",
  "properties": {
    "gn:admin1_code":"4",
    "gn:admin2_code":"1301407.0",
    "gn:asciiname":"Tres Unidos",
    "gn:country_code":"BR",
    "gn:dem":126,
    "gn:feature_class":"P",
    "gn:feature_code":"PPL",
    "gn:name":"Tr\u00eas Unidos",
    "gn:population":0,
    "gn:timezone":"America/Eirunepe",
    "iso:country":"BR",
    "wof:name":"Tres Unidos",
    "wof:placetype":"locality"
},
  "geometry": {"coordinates":[-69.54399000000001,-6.6173],"type":"Point"}
}