{
  "type": "Feature",
  "properties": {
    "gn:admin1_code":"15",
    "gn:admin2_code":"3150901.0",
    "gn:asciiname":"Sitio Itapora",
    "gn:country_code":"BR",
    "gn:dem":1376,
    "gn:feature_class":"P",
    "gn:feature_code":"PPL",
    "gn:name":"S\u00edtio Itapor\u00e3",
    "gn:population":0,
    "gn:timezone":"America/Sao_Paulo",
    "iso:country":"BR",
    "name:por_x_preferred":[
        "S\u00edtio Itapor\u00e3"
    ],
    "wof:name":"Sitio Itapora",
    "wof:placetype":"locality"
},
  "geometry": {"coordinates":[-45.5382,-22.581],"type":"Point"}
}