{
  "type": "Feature",
  "properties": {
    "gn:admin1_code":"27.0",
    "gn:admin2_code":"3550308.0",
    "gn:asciiname":"Vila Galvao",
    "gn:country_code":"BR",
    "gn:dem":750,
    "gn:feature_class":"P",
    "gn:feature_code":"PPL",
    "gn:name":"Vila Galv\u00e3o",
    "gn:population":0,
    "gn:timezone":"America/Sao_Paulo",
    "iso:country":"BR",
    "name:por_x_preferred":[
        "Vila Galv\u00e3o"
    ],
    "wof:name":"Vila Galvao",
    "wof:placetype":"locality"
},
  "geometry": {"coordinates":[-46.57923,-23.4717],"type":"Point"}
}