{
  "type": "Feature",
  "properties": {
    "gn:admin1_code":"4",
    "gn:admin2_code":"1302702.0",
    "gn:asciiname":"Oncas",
    "gn:country_code":"BR",
    "gn:dem":44,
    "gn:feature_class":"P",
    "gn:feature_code":"PPL",
    "gn:name":"On\u00e7as",
    "gn:population":0,
    "gn:timezone":"America/Manaus",
    "iso:country":"BR",
    "wof:name":"Oncas",
    "wof:placetype":"locality"
},
  "geometry": {"coordinates":[-61.56667,-5.91667],"type":"Point"}
}