{
  "type": "Feature",
  "properties": {
    "gn:admin1_code":"3.0",
    "gn:admin2_code":"1600501.0",
    "gn:asciiname":"Jari",
    "gn:country_code":"BR",
    "gn:dem":32,
    "gn:feature_class":"P",
    "gn:feature_code":"PPL",
    "gn:name":"Jari",
    "gn:population":0,
    "gn:timezone":"America/Belem",
    "iso:country":"BR",
    "name:ceb_x_preferred":[
        "Jari"
    ],
    "name:ces_x_preferred":[
        "Jari"
    ],
    "name:deu_x_preferred":[
        "Jari"
    ],
    "name:fin_x_preferred":[
        "Jari"
    ],
    "name:fra_x_preferred":[
        "Jari"
    ],
    "name:nld_x_preferred":[
        "Jari"
    ],
    "name:por_x_preferred":[
        "Jari"
    ],
    "name:spa_x_preferred":[
        "Jari"
    ],
    "name:swe_x_preferred":[
        "Jari"
    ],
    "wof:name":"Jari",
    "wof:placetype":"locality"
},
  "geometry": {"coordinates":[-51.25191,3.20463],"type":"Point"}
}