{
  "type": "Feature",
  "properties": {
    "gn:admin1_code":"23",
    "gn:admin2_code":"4318309.0",
    "gn:asciiname":"Estancia Nova",
    "gn:cc2":"BR",
    "gn:country_code":"BR",
    "gn:dem":104,
    "gn:feature_class":"P",
    "gn:feature_code":"PPL",
    "gn:name":"Est\u00e2ncia Nova",
    "gn:population":0,
    "gn:timezone":"America/Sao_Paulo",
    "iso:country":"BR",
    "name:und_x_variant":[
        "Nova",
        "Est\u00e2ncia Nova"
    ],
    "wof:name":"Estancia Nova",
    "wof:placetype":"locality"
},
  "geometry": {"coordinates":[-54.51667,-30.13333],"type":"Point"}
}