{
  "type": "Feature",
  "properties": {
    "gn:admin1_code":"20",
    "gn:admin2_code":"2205409.0",
    "gn:asciiname":"Jaburu",
    "gn:country_code":"BR",
    "gn:dem":26,
    "gn:feature_class":"P",
    "gn:feature_code":"PPL",
    "gn:name":"Jaburu",
    "gn:population":0,
    "gn:timezone":"America/Fortaleza",
    "iso:country":"BR",
    "wof:name":"Jaburu",
    "wof:placetype":"locality"
},
  "geometry": {"coordinates":[-42.13028,-3.39806],"type":"Point"}
}