{
  "type": "Feature",
  "properties": {
    "gn:admin1_code":"27",
    "gn:admin2_code":"3504107.0",
    "gn:asciiname":"Sitio Sao Judas Tadeu",
    "gn:country_code":"BR",
    "gn:dem":821,
    "gn:feature_class":"P",
    "gn:feature_code":"PPL",
    "gn:name":"S\u00edtio S\u00e3o Judas Tadeu",
    "gn:population":0,
    "gn:timezone":"America/Sao_Paulo",
    "iso:country":"BR",
    "name:por_x_preferred":[
        "S\u00edtio S\u00e3o Judas Tadeu"
    ],
    "wof:name":"Sitio Sao Judas Tadeu",
    "wof:placetype":"locality"
},
  "geometry": {"coordinates":[-46.58444,-23.21028],"type":"Point"}
}