{
  "type": "Feature",
  "properties": {
    "gn:admin1_code":"13",
    "gn:admin2_code":"2100907.0",
    "gn:asciiname":"Sao Domingos",
    "gn:country_code":"BR",
    "gn:dem":14,
    "gn:feature_class":"P",
    "gn:feature_code":"PPL",
    "gn:name":"S\u00e3o Domingos",
    "gn:population":0,
    "gn:timezone":"America/Fortaleza",
    "iso:country":"BR",
    "wof:name":"Sao Domingos",
    "wof:placetype":"locality"
},
  "geometry": {"coordinates":[-42.12889000000001,-3.04528],"type":"Point"}
}