{
  "type": "Feature",
  "properties": {
    "gn:admin1_code":"06",
    "gn:admin2_code":"2312403.0",
    "gn:asciiname":"Fazenda Lagoa do Mato",
    "gn:country_code":"BR",
    "gn:dem":37,
    "gn:feature_class":"P",
    "gn:feature_code":"PPL",
    "gn:name":"Fazenda Lagoa do Mato",
    "gn:population":0,
    "gn:timezone":"America/Fortaleza",
    "iso:country":"BR",
    "wof:name":"Fazenda Lagoa do Mato",
    "wof:placetype":"locality"
},
  "geometry": {"coordinates":[-39.08333,-3.58333],"type":"Point"}
}