{
  "type": "Feature",
  "properties": {
    "gn:admin1_code":"15",
    "gn:admin2_code":"3168200.0",
    "gn:asciiname":"Urubu",
    "gn:country_code":"BR",
    "gn:dem":709,
    "gn:feature_class":"P",
    "gn:feature_code":"PPL",
    "gn:name":"Urubu",
    "gn:population":0,
    "gn:timezone":"America/Sao_Paulo",
    "iso:country":"BR",
    "name:bre_x_preferred":[
        "Urubu"
    ],
    "name:fra_x_preferred":[
        "Urubu"
    ],
    "name:por_x_preferred":[
        "Urubu"
    ],
    "wof:name":"Urubu",
    "wof:placetype":"locality"
},
  "geometry": {"coordinates":[-46.05,-19.88333],"type":"Point"}
}