{
  "type": "Feature",
  "properties": {
    "gn:admin1_code":"22",
    "gn:admin2_code":"2411403.0",
    "gn:asciiname":"Cabeco de Joao Ferino",
    "gn:country_code":"BR",
    "gn:dem":163,
    "gn:feature_class":"P",
    "gn:feature_code":"PPL",
    "gn:name":"Cabe\u00e7o de Jo\u00e3o Ferino",
    "gn:population":0,
    "gn:timezone":"America/Fortaleza",
    "iso:country":"BR",
    "wof:name":"Cabeco de Joao Ferino",
    "wof:placetype":"locality"
},
  "geometry": {"coordinates":[-36.61611,-5.97444],"type":"Point"}
}