{
  "type": "Feature",
  "properties": {
    "gn:admin1_code":"18.0",
    "gn:admin2_code":"4126603.0",
    "gn:asciiname":"Sitio Sebastiao Tiburcio",
    "gn:country_code":"BR",
    "gn:dem":615,
    "gn:feature_class":"P",
    "gn:feature_code":"PPL",
    "gn:name":"S\u00edtio Sebasti\u00e3o Tib\u00farcio",
    "gn:population":0,
    "gn:timezone":"America/Sao_Paulo",
    "iso:country":"BR",
    "name:por_x_preferred":[
        "S\u00edtio Sebasti\u00e3o Tib\u00farcio"
    ],
    "wof:name":"Sitio Sebastiao Tiburcio",
    "wof:placetype":"locality"
},
  "geometry": {"coordinates":[-49.7924,-23.6565],"type":"Point"}
}