{
  "type": "Feature",
  "properties": {
    "gn:admin1_code":"5",
    "gn:admin2_code":"2930204.0",
    "gn:asciiname":"Batateira",
    "gn:cc2":"BR",
    "gn:country_code":"BR",
    "gn:dem":961,
    "gn:feature_class":"P",
    "gn:feature_code":"PPL",
    "gn:name":"Batateira",
    "gn:population":0,
    "gn:timezone":"America/Bahia",
    "iso:country":"BR",
    "name:und_x_variant":[
        "Casa Morta",
        "Batateira"
    ],
    "wof:name":"Batateira",
    "wof:placetype":"locality"
},
  "geometry": {"coordinates":[-41.36667,-9.95],"type":"Point"}
}