{
  "type": "Feature",
  "properties": {
    "gn:admin1_code":"15",
    "gn:admin2_code":"3160405.0",
    "gn:asciiname":"Roncador",
    "gn:country_code":"BR",
    "gn:dem":909,
    "gn:feature_class":"P",
    "gn:feature_code":"PPL",
    "gn:name":"Roncador",
    "gn:population":0,
    "gn:timezone":"America/Sao_Paulo",
    "iso:country":"BR",
    "name:por_x_preferred":[
        "Roncador"
    ],
    "wof:name":"Roncador",
    "wof:placetype":"locality"
},
  "geometry": {"coordinates":[-45.05,-20.01667],"type":"Point"}
}