{
  "type": "Feature",
  "properties": {
    "gn:admin1_code":"06",
    "gn:admin2_code":"2305407.0",
    "gn:asciiname":"Saco do Jorge",
    "gn:country_code":"BR",
    "gn:dem":178,
    "gn:feature_class":"P",
    "gn:feature_code":"PPL",
    "gn:name":"Saco do Jorge",
    "gn:population":0,
    "gn:timezone":"America/Fortaleza",
    "iso:country":"BR",
    "wof:name":"Saco do Jorge",
    "wof:placetype":"locality"
},
  "geometry": {"coordinates":[-38.78333,-6.38333],"type":"Point"}
}