{
  "type": "Feature",
  "properties": {
    "gn:admin1_code":"21",
    "gn:admin2_code":"3301009.0",
    "gn:asciiname":"Mocoto",
    "gn:cc2":"BR",
    "gn:country_code":"BR",
    "gn:dem":57,
    "gn:feature_class":"P",
    "gn:feature_code":"PPL",
    "gn:name":"Mocot\u00f3",
    "gn:population":0,
    "gn:timezone":"America/Sao_Paulo",
    "iso:country":"BR",
    "name:und_x_variant":[
        "Macot\u00f3",
        "Mocot\u00f3"
    ],
    "wof:name":"Mocoto",
    "wof:placetype":"locality"
},
  "geometry": {"coordinates":[-41.68333,-21.85],"type":"Point"}
}