{
  "type": "Feature",
  "properties": {
    "gn:admin1_code":"18.0",
    "gn:admin2_code":"4119202.0",
    "gn:asciiname":"Sitio Aquiles Vanzele",
    "gn:country_code":"BR",
    "gn:dem":632,
    "gn:feature_class":"P",
    "gn:feature_code":"PPL",
    "gn:name":"S\u00edtio Aquiles Vanzele",
    "gn:population":0,
    "gn:timezone":"America/Sao_Paulo",
    "iso:country":"BR",
    "name:por_x_preferred":[
        "S\u00edtio Aquiles Vanzele"
    ],
    "wof:name":"Sitio Aquiles Vanzele",
    "wof:placetype":"locality"
},
  "geometry": {"coordinates":[-50.07957,-23.81609],"type":"Point"}
}