{
  "type": "Feature",
  "properties": {
    "gn:admin1_code":"27",
    "gn:admin2_code":"3519709.0",
    "gn:asciiname":"Sitio Sabia",
    "gn:country_code":"BR",
    "gn:dem":910,
    "gn:feature_class":"P",
    "gn:feature_code":"PPL",
    "gn:name":"S\u00edtio Sabi\u00e1",
    "gn:population":0,
    "gn:timezone":"America/Sao_Paulo",
    "iso:country":"BR",
    "name:por_x_preferred":[
        "S\u00edtio Sabi\u00e1"
    ],
    "wof:name":"Sitio Sabia",
    "wof:placetype":"locality"
},
  "geometry": {"coordinates":[-47.126,-23.72313],"type":"Point"}
}