{
  "type": "Feature",
  "properties": {
    "gn:admin1_code":"18.0",
    "gn:admin2_code":"4121208.0",
    "gn:asciiname":"Sitio Carlos B. Filho",
    "gn:country_code":"BR",
    "gn:dem":868,
    "gn:feature_class":"P",
    "gn:feature_code":"PPL",
    "gn:name":"S\u00edtio Carlos B. Filho",
    "gn:population":0,
    "gn:timezone":"America/Sao_Paulo",
    "iso:country":"BR",
    "name:por_x_preferred":[
        "S\u00edtio Carlos B. Filho"
    ],
    "wof:name":"Sitio Carlos B. Filho",
    "wof:placetype":"locality"
},
  "geometry": {"coordinates":[-49.3765,-25.8141],"type":"Point"}
}