{
  "type": "Feature",
  "properties": {
    "gn:admin1_code":"15",
    "gn:admin2_code":"3160454.0",
    "gn:asciiname":"Santo Antonio do Retiro",
    "gn:country_code":"BR",
    "gn:dem":836,
    "gn:feature_class":"P",
    "gn:feature_code":"PPL",
    "gn:name":"Santo Ant\u00f4nio do Retiro",
    "gn:population":0,
    "gn:timezone":"America/Sao_Paulo",
    "iso:country":"BR",
    "name:bpy_x_preferred":[
        "\u09b8\u09be\u09a8\u09cd\u099f\u09cb \u0986\u09a8\u09cd\u099f\u09cb\u09a8\u09bf\u0993 \u09a1\u09cb \u09b0\u09c7\u099f\u09bf\u09b0\u09cb"
    ],
    "wof:name":"Santo Antonio do Retiro",
    "wof:placetype":"locality"
},
  "geometry": {"coordinates":[-42.62361,-15.33944],"type":"Point"}
}