{
  "type": "Feature",
  "properties": {
    "gn:admin1_code":"06",
    "gn:admin2_code":"2307601.0",
    "gn:asciiname":"Gangorra (1)",
    "gn:country_code":"BR",
    "gn:dem":30,
    "gn:feature_class":"P",
    "gn:feature_code":"PPL",
    "gn:name":"Gangorra (1)",
    "gn:population":0,
    "gn:timezone":"America/Fortaleza",
    "iso:country":"BR",
    "wof:name":"Gangorra (1)",
    "wof:placetype":"locality"
},
  "geometry": {"coordinates":[-38.08333,-5.08333],"type":"Point"}
}