{
  "type": "Feature",
  "properties": {
    "gn:admin1_code":"23.0",
    "gn:admin2_code":"4321204.0",
    "gn:asciiname":"Mato Fino",
    "gn:country_code":"BR",
    "gn:dem":207,
    "gn:feature_class":"P",
    "gn:feature_code":"PPLL",
    "gn:name":"Mato Fino",
    "gn:population":0,
    "gn:timezone":"America/Sao_Paulo",
    "iso:country":"BR",
    "name:por_x_preferred":[
        "Mato Fino"
    ],
    "wof:name":"Mato Fino",
    "wof:placetype":"locality"
},
  "geometry": {"coordinates":[-50.8995,-29.7929],"type":"Point"}
}