{
  "type": "Feature",
  "properties": {
    "gn:admin1_code":"29",
    "gn:admin2_code":"5216452.0",
    "gn:asciiname":"Joao Branco",
    "gn:country_code":"BR",
    "gn:dem":850,
    "gn:feature_class":"P",
    "gn:feature_code":"PPL",
    "gn:name":"Jo\u00e3o Branco",
    "gn:population":0,
    "gn:timezone":"America/Sao_Paulo",
    "iso:country":"BR",
    "name:por_x_preferred":[
        "Jo\u00e3o Branco"
    ],
    "wof:name":"Joao Branco",
    "wof:placetype":"locality"
},
  "geometry": {"coordinates":[-52.23333,-17.46667],"type":"Point"}
}