{
  "type": "Feature",
  "properties": {
    "gn:admin1_code":"22",
    "gn:admin2_code":"2414605.0",
    "gn:asciiname":"Quixabeiru Sozinha",
    "gn:country_code":"BR",
    "gn:dem":76,
    "gn:feature_class":"P",
    "gn:feature_code":"PPL",
    "gn:name":"Quixabeiru Sozinha",
    "gn:population":0,
    "gn:timezone":"America/Fortaleza",
    "iso:country":"BR",
    "wof:name":"Quixabeiru Sozinha",
    "wof:placetype":"locality"
},
  "geometry": {"coordinates":[-37.355,-5.60361],"type":"Point"}
}