{
  "type": "Feature",
  "properties": {
    "gn:admin1_code":"5",
    "gn:admin2_code":"2917201.0",
    "gn:asciiname":"Sucuarana de Cima",
    "gn:country_code":"BR",
    "gn:dem":501,
    "gn:feature_class":"P",
    "gn:feature_code":"PPL",
    "gn:name":"Su\u00e7uarana de Cima",
    "gn:population":0,
    "gn:timezone":"America/Bahia",
    "iso:country":"BR",
    "wof:name":"Sucuarana de Cima",
    "wof:placetype":"locality"
},
  "geometry": {"coordinates":[-41.28333,-13.93333],"type":"Point"}
}