{
  "type": "Feature",
  "properties": {
    "gn:admin1_code":"18.0",
    "gn:admin2_code":"4109500.0",
    "gn:asciiname":"Rio dos Patos",
    "gn:country_code":"BR",
    "gn:dem":29,
    "gn:feature_class":"P",
    "gn:feature_code":"PPLL",
    "gn:name":"Rio dos Patos",
    "gn:population":0,
    "gn:timezone":"America/Sao_Paulo",
    "iso:country":"BR",
    "name:por_x_preferred":[
        "Rio dos Patos"
    ],
    "wof:name":"Rio dos Patos",
    "wof:placetype":"locality"
},
  "geometry": {"coordinates":[-48.1891,-25.2393],"type":"Point"}
}