{
  "type": "Feature",
  "properties": {
    "gn:admin1_code":"22",
    "gn:admin2_code":"2402501.0",
    "gn:asciiname":"Pacheco",
    "gn:country_code":"BR",
    "gn:dem":12,
    "gn:feature_class":"P",
    "gn:feature_code":"PPL",
    "gn:name":"Pacheco",
    "gn:population":0,
    "gn:timezone":"America/Fortaleza",
    "iso:country":"BR",
    "name:kor_x_preferred":[
        "\ud30c\uccb4\ucf54"
    ],
    "wof:name":"Pacheco",
    "wof:placetype":"locality"
},
  "geometry": {"coordinates":[-36.82389000000001,-5.3225],"type":"Point"}
}