{
  "type": "Feature",
  "properties": {
    "gn:admin1_code":"14",
    "gn:admin2_code":"5101605.0",
    "gn:asciiname":"Coqueiro",
    "gn:country_code":"BR",
    "gn:dem":131,
    "gn:feature_class":"P",
    "gn:feature_code":"PPL",
    "gn:name":"Coqueiro",
    "gn:population":0,
    "gn:timezone":"America/Cuiaba",
    "iso:country":"BR",
    "name:und_x_variant":[
        "P\u00f4rto do Coqueiro",
        "Porto Coqueiro",
        "Coqueiro"
    ],
    "wof:name":"Coqueiro",
    "wof:placetype":"locality"
},
  "geometry": {"coordinates":[-55.68094,-17.35342],"type":"Point"}
}