{
  "type": "Feature",
  "properties": {
    "gn:admin1_code":"20",
    "gn:admin2_code":"2210359.0",
    "gn:asciiname":"Lagoa das Vacas",
    "gn:country_code":"BR",
    "gn:dem":417,
    "gn:feature_class":"P",
    "gn:feature_code":"PPL",
    "gn:name":"Lagoa das Vacas",
    "gn:population":0,
    "gn:timezone":"America/Fortaleza",
    "iso:country":"BR",
    "wof:name":"Lagoa das Vacas",
    "wof:placetype":"locality"
},
  "geometry": {"coordinates":[-42.61667,-9.18333],"type":"Point"}
}