{
  "type": "Feature",
  "properties": {
    "gn:admin1_code":"26.0",
    "gn:admin2_code":"4214003.0",
    "gn:asciiname":"Quadro Novo",
    "gn:country_code":"BR",
    "gn:dem":622,
    "gn:feature_class":"P",
    "gn:feature_code":"PPL",
    "gn:name":"Quadro Novo",
    "gn:population":0,
    "gn:timezone":"America/Sao_Paulo",
    "iso:country":"BR",
    "name:por_x_preferred":[
        "Quadro Novo"
    ],
    "wof:name":"Quadro Novo",
    "wof:placetype":"locality"
},
  "geometry": {"coordinates":[-49.67921,-26.94428],"type":"Point"}
}