{
  "type": "Feature",
  "properties": {
    "gn:admin1_code":"18.0",
    "gn:admin2_code":"4124103.0",
    "gn:asciiname":"Sitio Duas Meninas",
    "gn:country_code":"BR",
    "gn:dem":494,
    "gn:feature_class":"P",
    "gn:feature_code":"PPL",
    "gn:name":"S\u00edtio Duas Meninas",
    "gn:population":0,
    "gn:timezone":"America/Sao_Paulo",
    "iso:country":"BR",
    "name:por_x_preferred":[
        "S\u00edtio Duas Meninas"
    ],
    "wof:name":"Sitio Duas Meninas",
    "wof:placetype":"locality"
},
  "geometry": {"coordinates":[-50.0442,-23.35198],"type":"Point"}
}