{
  "type": "Feature",
  "properties": {
    "gn:admin1_code":"13",
    "gn:admin2_code":"2105963.0",
    "gn:asciiname":"Antoniao",
    "gn:country_code":"BR",
    "gn:dem":184,
    "gn:feature_class":"P",
    "gn:feature_code":"PPL",
    "gn:name":"Antoni\u00e3o",
    "gn:population":0,
    "gn:timezone":"America/Fortaleza",
    "iso:country":"BR",
    "wof:name":"Antoniao",
    "wof:placetype":"locality"
},
  "geometry": {"coordinates":[-45.31667,-4.81667],"type":"Point"}
}