{
  "type": "Feature",
  "properties": {
    "gn:admin1_code":"27",
    "gn:admin2_code":"3507001.0",
    "gn:asciiname":"Sitio Santa Lucia",
    "gn:country_code":"BR",
    "gn:dem":616,
    "gn:feature_class":"P",
    "gn:feature_code":"PPL",
    "gn:name":"S\u00edtio Santa L\u00facia",
    "gn:population":0,
    "gn:timezone":"America/Sao_Paulo",
    "iso:country":"BR",
    "name:por_x_preferred":[
        "S\u00edtio Santa L\u00facia"
    ],
    "wof:name":"Sitio Santa Lucia",
    "wof:placetype":"locality"
},
  "geometry": {"coordinates":[-47.67583,-23.21861],"type":"Point"}
}