{
  "type": "Feature",
  "properties": {
    "gn:admin1_code":"4.0",
    "gn:admin2_code":"1303403.0",
    "gn:asciiname":"Vila Araua",
    "gn:country_code":"BR",
    "gn:dem":27,
    "gn:feature_class":"P",
    "gn:feature_code":"PPL",
    "gn:name":"Vila Arau\u00e1",
    "gn:population":0,
    "gn:timezone":"America/Manaus",
    "iso:country":"BR",
    "name:por_x_preferred":[
        "Vila Arau\u00e1"
    ],
    "wof:name":"Vila Araua",
    "wof:placetype":"locality"
},
  "geometry": {"coordinates":[-56.66556,-2.92307],"type":"Point"}
}