{
  "type": "Feature",
  "properties": {
    "gn:admin1_code":"18.0",
    "gn:admin2_code":"4112801.0",
    "gn:asciiname":"Sitio Joao Rodrigues",
    "gn:country_code":"BR",
    "gn:dem":686,
    "gn:feature_class":"P",
    "gn:feature_code":"PPL",
    "gn:name":"S\u00edtio Jo\u00e1o Rodrigues",
    "gn:population":0,
    "gn:timezone":"America/Sao_Paulo",
    "iso:country":"BR",
    "name:por_x_preferred":[
        "S\u00edtio Jo\u00e1o Rodrigues"
    ],
    "wof:name":"Sitio Joao Rodrigues",
    "wof:placetype":"locality"
},
  "geometry": {"coordinates":[-49.9019,-23.3919],"type":"Point"}
}