{
  "type": "Feature",
  "properties": {
    "gn:admin1_code":"18.0",
    "gn:admin2_code":"4112306.0",
    "gn:asciiname":"Sitio Ribeirao Grande",
    "gn:country_code":"BR",
    "gn:dem":652,
    "gn:feature_class":"P",
    "gn:feature_code":"PPL",
    "gn:name":"S\u00edtio Ribeir\u00e3o Grande",
    "gn:population":0,
    "gn:timezone":"America/Sao_Paulo",
    "iso:country":"BR",
    "name:por_x_preferred":[
        "S\u00edtio Ribeir\u00e3o Grande"
    ],
    "wof:name":"Sitio Ribeirao Grande",
    "wof:placetype":"locality"
},
  "geometry": {"coordinates":[-50.0936,-23.80237],"type":"Point"}
}