{
  "type": "Feature",
  "properties": {
    "gn:admin1_code":"18.0",
    "gn:admin2_code":"4112801.0",
    "gn:asciiname":"Sitio Sao Manoel",
    "gn:country_code":"BR",
    "gn:dem":579,
    "gn:feature_class":"P",
    "gn:feature_code":"PPL",
    "gn:name":"S\u00edtio S\u00e3o Manoel",
    "gn:population":0,
    "gn:timezone":"America/Sao_Paulo",
    "iso:country":"BR",
    "name:por_x_preferred":[
        "S\u00edtio S\u00e3o Manoel"
    ],
    "wof:name":"Sitio Sao Manoel",
    "wof:placetype":"locality"
},
  "geometry": {"coordinates":[-49.91148,-23.46114],"type":"Point"}
}