{
  "type": "Feature",
  "properties": {
    "gn:admin1_code":"21",
    "gn:admin2_code":"3305802.0",
    "gn:asciiname":"Engano",
    "gn:country_code":"BR",
    "gn:dem":852,
    "gn:feature_class":"P",
    "gn:feature_code":"PPLL",
    "gn:name":"Engano",
    "gn:population":0,
    "gn:timezone":"America/Sao_Paulo",
    "iso:country":"BR",
    "name:por_x_preferred":[
        "Engano"
    ],
    "wof:name":"Engano",
    "wof:placetype":"locality"
},
  "geometry": {"coordinates":[-42.98756,-22.32263],"type":"Point"}
}