{
  "type": "Feature",
  "properties": {
    "gn:admin1_code":"27",
    "gn:admin2_code":"3524600.0",
    "gn:asciiname":"Sitio Ribeirao da Marreca",
    "gn:country_code":"BR",
    "gn:dem":137,
    "gn:feature_class":"P",
    "gn:feature_code":"PPL",
    "gn:name":"S\u00edtio Ribeir\u00e3o da Marreca",
    "gn:population":0,
    "gn:timezone":"America/Sao_Paulo",
    "iso:country":"BR",
    "name:por_x_preferred":[
        "S\u00edtio Ribeir\u00e3o da Marreca"
    ],
    "wof:name":"Sitio Ribeirao da Marreca",
    "wof:placetype":"locality"
},
  "geometry": {"coordinates":[-48.0893,-24.8778],"type":"Point"}
}