{
  "type": "Feature",
  "properties": {
    "gn:admin1_code":"17",
    "gn:admin2_code":"2510907.0",
    "gn:asciiname":"Malhada de Areia",
    "gn:country_code":"BR",
    "gn:dem":222,
    "gn:feature_class":"P",
    "gn:feature_code":"PPL",
    "gn:name":"Malhada de Areia",
    "gn:population":0,
    "gn:timezone":"America/Fortaleza",
    "iso:country":"BR",
    "wof:name":"Malhada de Areia",
    "wof:placetype":"locality"
},
  "geometry": {"coordinates":[-37.48333,-6.65],"type":"Point"}
}