{
  "type": "Feature",
  "properties": {
    "gn:admin1_code":"18",
    "gn:admin2_code":"4119905.0",
    "gn:asciiname":"Pombinhas",
    "gn:country_code":"BR",
    "gn:dem":892,
    "gn:feature_class":"P",
    "gn:feature_code":"PPL",
    "gn:name":"Pombinhas",
    "gn:population":0,
    "gn:timezone":"America/Sao_Paulo",
    "iso:country":"BR",
    "wof:name":"Pombinhas",
    "wof:placetype":"locality"
},
  "geometry": {"coordinates":[-50.25,-25.03333],"type":"Point"}
}