{
  "type": "Feature",
  "properties": {
    "gn:admin1_code":"18.0",
    "gn:admin2_code":"4109708.0",
    "gn:asciiname":"Sitio Francisco M. Ferreira",
    "gn:country_code":"BR",
    "gn:dem":757,
    "gn:feature_class":"P",
    "gn:feature_code":"PPL",
    "gn:name":"S\u00edtio Francisco M. Ferreira",
    "gn:population":0,
    "gn:timezone":"America/Sao_Paulo",
    "iso:country":"BR",
    "name:por_x_preferred":[
        "S\u00edtio Francisco M. Ferreira"
    ],
    "wof:name":"Sitio Francisco M. Ferreira",
    "wof:placetype":"locality"
},
  "geometry": {"coordinates":[-50.14446,-23.90519],"type":"Point"}
}