{
  "type": "Feature",
  "properties": {
    "gn:admin1_code":"18.0",
    "gn:admin2_code":"4114302.0",
    "gn:asciiname":"Sitio Luiz E. Claudino",
    "gn:country_code":"BR",
    "gn:dem":925,
    "gn:feature_class":"P",
    "gn:feature_code":"PPL",
    "gn:name":"S\u00edtio Luiz E. Claudino",
    "gn:population":0,
    "gn:timezone":"America/Sao_Paulo",
    "iso:country":"BR",
    "name:por_x_preferred":[
        "S\u00edtio Luiz E. Claudino"
    ],
    "wof:name":"Sitio Luiz E. Claudino",
    "wof:placetype":"locality"
},
  "geometry": {"coordinates":[-49.2858,-25.7513],"type":"Point"}
}