{
  "type": "Feature",
  "properties": {
    "gn:admin1_code":"16",
    "gn:admin2_code":"1508308.0",
    "gn:asciiname":"Campinho",
    "gn:country_code":"BR",
    "gn:dem":16,
    "gn:feature_class":"P",
    "gn:feature_code":"PPL",
    "gn:name":"Campinho",
    "gn:population":0,
    "gn:timezone":"America/Fortaleza",
    "iso:country":"BR",
    "name:nld_x_preferred":[
        "Campinho"
    ],
    "name:por_x_preferred":[
        "Campinho"
    ],
    "wof:name":"Campinho",
    "wof:placetype":"locality"
},
  "geometry": {"coordinates":[-46.22196,-1.71679],"type":"Point"}
}