{
  "type": "Feature",
  "properties": {
    "gn:admin1_code":"23.0",
    "gn:admin2_code":"4313201.0",
    "gn:asciiname":"Linha Temeraria",
    "gn:country_code":"BR",
    "gn:dem":62,
    "gn:feature_class":"P",
    "gn:feature_code":"PPL",
    "gn:name":"Linha Temeraria",
    "gn:population":0,
    "gn:timezone":"America/Sao_Paulo",
    "iso:country":"BR",
    "wof:name":"Linha Temeraria",
    "wof:placetype":"locality"
},
  "geometry": {"coordinates":[-51.19985,-29.36729],"type":"Point"}
}