{
  "type": "Feature",
  "properties": {
    "gn:admin1_code":"18",
    "gn:admin2_code":"4127502.0",
    "gn:asciiname":"Taquara",
    "gn:cc2":"BR",
    "gn:country_code":"BR",
    "gn:dem":1043,
    "gn:feature_class":"P",
    "gn:feature_code":"PPL",
    "gn:name":"Taquara",
    "gn:population":0,
    "gn:timezone":"America/Sao_Paulo",
    "iso:country":"BR",
    "name:und_x_variant":[
        "Fazenda Taquara",
        "Taquara"
    ],
    "wof:name":"Taquara",
    "wof:placetype":"locality"
},
  "geometry": {"coordinates":[-50.16667,-24.68333],"type":"Point"}
}