{
  "type": "Feature",
  "properties": {
    "gn:admin1_code":"18",
    "gn:admin2_code":"4127502.0",
    "gn:asciiname":"Taquara",
    "gn:cc2":"BR",
    "gn:country_code":"BR",
    "gn:dem":1043,
    "gn:feature_class":"P",
    "gn:feature_code":"PPL",
    "gn:name":"Taquara",
    "gn:population":0,
    "gn:timezone":"America/Sao_Paulo",
    "iso:country":"BR",
    "name:ara_x_preferred":[
        "\u062a\u0627\u0643\u0627\u0631\u0627"
    ],
    "name:bpy_x_preferred":[
        "\u099f\u09be\u0995\u09c1\u09f1\u09be\u09b0\u09be"
    ],
    "name:ceb_x_preferred":[
        "Taquara"
    ],
    "name:deu_x_preferred":[
        "Taquara"
    ],
    "name:epo_x_preferred":[
        "Taquara"
    ],
    "name:fra_x_preferred":[
        "Taquara"
    ],
    "name:hye_x_preferred":[
        "\u054f\u0561\u056f\u0578\u0582\u0561\u0580\u0561"
    ],
    "name:ita_x_preferred":[
        "Taquara"
    ],
    "name:kaz_x_preferred":[
        "\u0422\u0430\u043a\u0443\u0430\u0440\u0430"
    ],
    "name:mlg_x_preferred":[
        "Taquara"
    ],
    "name:nor_x_preferred":[
        "Taquara"
    ],
    "name:pol_x_preferred":[
        "Taquara"
    ],
    "name:ron_x_preferred":[
        "Taquara"
    ],
    "name:rus_x_preferred":[
        "\u0422\u0430\u043a\u0443\u0430\u0440\u0430"
    ],
    "name:spa_x_preferred":[
        "Taquara"
    ],
    "name:swe_x_preferred":[
        "Taquara"
    ],
    "name:und_x_variant":[
        "Fazenda Taquara",
        "Taquara"
    ],
    "name:vie_x_preferred":[
        "Taquara"
    ],
    "name:vol_x_preferred":[
        "Taquara"
    ],
    "name:war_x_preferred":[
        "Taquara"
    ],
    "name:zho_x_preferred":[
        "\u5854\u5938\u62c9"
    ],
    "wof:name":"Taquara",
    "wof:placetype":"locality"
},
  "geometry": {"coordinates":[-50.16667,-24.68333],"type":"Point"}
}