{
  "type": "Feature",
  "properties": {
    "gn:admin1_code":"06",
    "gn:admin2_code":"2303659.0",
    "gn:asciiname":"Trapia",
    "gn:country_code":"BR",
    "gn:dem":298,
    "gn:feature_class":"P",
    "gn:feature_code":"PPL",
    "gn:name":"Trapi\u00e1",
    "gn:population":0,
    "gn:timezone":"America/Fortaleza",
    "iso:country":"BR",
    "wof:name":"Trapia",
    "wof:placetype":"locality"
},
  "geometry": {"coordinates":[-40.18333,-4.68333],"type":"Point"}
}