{
  "type": "Feature",
  "properties": {
    "gn:admin1_code":"27",
    "gn:admin2_code":"3526209.0",
    "gn:asciiname":"Sitio Paraiso da Vovo",
    "gn:country_code":"BR",
    "gn:dem":761,
    "gn:feature_class":"P",
    "gn:feature_code":"PPL",
    "gn:name":"S\u00edtio Para\u00edso da Vov\u00f3",
    "gn:population":0,
    "gn:timezone":"America/Sao_Paulo",
    "iso:country":"BR",
    "name:por_x_preferred":[
        "S\u00edtio Para\u00edso da Vov\u00f3"
    ],
    "wof:name":"Sitio Paraiso da Vovo",
    "wof:placetype":"locality"
},
  "geometry": {"coordinates":[-47.01452000000001,-23.89341],"type":"Point"}
}