{
  "type": "Feature",
  "properties": {
    "gn:admin1_code":"30",
    "gn:admin2_code":"2603702.0",
    "gn:asciiname":"Olhos d'Agua",
    "gn:country_code":"BR",
    "gn:dem":596,
    "gn:feature_class":"P",
    "gn:feature_code":"PPL",
    "gn:name":"Olhos d\u2019\u00c1gua",
    "gn:population":0,
    "gn:timezone":"America/Recife",
    "iso:country":"BR",
    "wof:name":"Olhos d'Agua",
    "wof:placetype":"locality"
},
  "geometry": {"coordinates":[-36.23333,-8.81667],"type":"Point"}
}