{
  "type": "Feature",
  "properties": {
    "gn:admin1_code":"18",
    "gn:admin2_code":"4121208.0",
    "gn:asciiname":"Sitio Joao Alfredo",
    "gn:country_code":"BR",
    "gn:dem":847,
    "gn:feature_class":"P",
    "gn:feature_code":"PPL",
    "gn:name":"S\u00edtio Jo\u00e3o Alfredo",
    "gn:population":0,
    "gn:timezone":"America/Sao_Paulo",
    "iso:country":"BR",
    "name:por_x_preferred":[
        "S\u00edtio Jo\u00e3o Alfredo"
    ],
    "wof:name":"Sitio Joao Alfredo",
    "wof:placetype":"locality"
},
  "geometry": {"coordinates":[-49.58,-25.90917],"type":"Point"}
}