{
  "type": "Feature",
  "properties": {
    "gn:admin1_code":"15",
    "gn:admin2_code":"3168606.0",
    "gn:asciiname":"Clemente Apolonio",
    "gn:country_code":"BR",
    "gn:dem":430,
    "gn:feature_class":"P",
    "gn:feature_code":"PPL",
    "gn:name":"Clemente Apol\u00f4nio",
    "gn:population":0,
    "gn:timezone":"America/Sao_Paulo",
    "iso:country":"BR",
    "name:por_x_preferred":[
        "Clemente Apol\u00f4nio"
    ],
    "wof:name":"Clemente Apolonio",
    "wof:placetype":"locality"
},
  "geometry": {"coordinates":[-41.63333,-17.63332999999999],"type":"Point"}
}