{
  "type": "Feature",
  "properties": {
    "gn:admin1_code":"5.0",
    "gn:admin2_code":"2905909.0",
    "gn:asciiname":"Lagoa da Onca",
    "gn:country_code":"BR",
    "gn:dem":483,
    "gn:feature_class":"P",
    "gn:feature_code":"PPL",
    "gn:name":"Lagoa da On\u00e7a",
    "gn:population":0,
    "gn:timezone":"America/Bahia",
    "iso:country":"BR",
    "name:por_x_preferred":[
        "Lagoa da On\u00e7a"
    ],
    "wof:name":"Lagoa da Onca",
    "wof:placetype":"locality"
},
  "geometry": {"coordinates":[-43.38555,-9.59145],"type":"Point"}
}