{
  "type": "Feature",
  "properties": {
    "gn:admin1_code":"18.0",
    "gn:admin2_code":"4102703.0",
    "gn:asciiname":"Sitio Luiz Fredigotto",
    "gn:country_code":"BR",
    "gn:dem":461,
    "gn:feature_class":"P",
    "gn:feature_code":"PPL",
    "gn:name":"S\u00edtio Luiz Fredigotto",
    "gn:population":0,
    "gn:timezone":"America/Sao_Paulo",
    "iso:country":"BR",
    "name:por_x_preferred":[
        "S\u00edtio Luiz Fredigotto"
    ],
    "wof:name":"Sitio Luiz Fredigotto",
    "wof:placetype":"locality"
},
  "geometry": {"coordinates":[-50.1193,-23.0936],"type":"Point"}
}