{
  "type": "Feature",
  "properties": {
    "gn:admin1_code":"06",
    "gn:admin2_code":"2302800.0",
    "gn:asciiname":"Ubiracu",
    "gn:cc2":"BR",
    "gn:country_code":"BR",
    "gn:dem":295,
    "gn:feature_class":"P",
    "gn:feature_code":"PPLL",
    "gn:name":"Ubira\u00e7u",
    "gn:population":0,
    "gn:timezone":"America/Fortaleza",
    "iso:country":"BR",
    "name:und_x_variant":[
        "Jatob\u00e1"
    ],
    "wof:name":"Ubiracu",
    "wof:placetype":"locality"
},
  "geometry": {"coordinates":[-39.61111,-4.41944],"type":"Point"}
}