{
  "type": "Feature",
  "properties": {
    "gn:admin1_code":"16",
    "gn:admin2_code":"1507508.0",
    "gn:asciiname":"Carmo",
    "gn:country_code":"BR",
    "gn:dem":111,
    "gn:feature_class":"P",
    "gn:feature_code":"PPL",
    "gn:name":"Carmo",
    "gn:population":0,
    "gn:timezone":"America/Belem",
    "iso:country":"BR",
    "name:ceb_x_preferred":[
        "Carmo"
    ],
    "name:deu_x_preferred":[
        "Carmo"
    ],
    "name:epo_x_preferred":[
        "Carmo"
    ],
    "name:fra_x_preferred":[
        "Carmo"
    ],
    "name:ita_x_preferred":[
        "Carmo"
    ],
    "name:nld_x_preferred":[
        "Carmo"
    ],
    "name:por_x_preferred":[
        "Carmo"
    ],
    "name:ron_x_preferred":[
        "Carmo"
    ],
    "name:rus_x_preferred":[
        "\u041a\u0430\u0440\u043c\u0443"
    ],
    "name:sco_x_preferred":[
        "Carmo"
    ],
    "name:spa_x_preferred":[
        "Carmo"
    ],
    "name:swe_x_preferred":[
        "Carmo"
    ],
    "wof:name":"Carmo",
    "wof:placetype":"locality"
},
  "geometry": {"coordinates":[-48.36667,-5.45],"type":"Point"}
}