{
  "type": "Feature",
  "properties": {
    "gn:admin1_code":"27",
    "gn:admin2_code":"3509908.0",
    "gn:asciiname":"Mandira",
    "gn:country_code":"BR",
    "gn:dem":15,
    "gn:feature_class":"P",
    "gn:feature_code":"PPLL",
    "gn:name":"Mandira",
    "gn:population":0,
    "gn:timezone":"America/Sao_Paulo",
    "iso:country":"BR",
    "name:por_x_preferred":[
        "Mandira"
    ],
    "wof:name":"Mandira",
    "wof:placetype":"locality"
},
  "geometry": {"coordinates":[-48.06664,-25.00386],"type":"Point"}
}