{
  "type": "Feature",
  "properties": {
    "gn:admin1_code":"24.0",
    "gn:admin2_code":"1100908.0",
    "gn:asciiname":"Teixeiropolis",
    "gn:country_code":"BR",
    "gn:dem":214,
    "gn:feature_class":"P",
    "gn:feature_code":"PPL",
    "gn:name":"Teixeir\u00f3polis",
    "gn:population":0,
    "gn:timezone":"America/Porto_Velho",
    "iso:country":"BR",
    "name:por_x_preferred":[
        "Teixeir\u00f3polis"
    ],
    "wof:name":"Teixeiropolis",
    "wof:placetype":"locality"
},
  "geometry": {"coordinates":[-61.94856,-11.42697],"type":"Point"}
}