{
  "type": "Feature",
  "properties": {
    "gn:admin1_code":"18.0",
    "gn:admin2_code":"4126678.0",
    "gn:asciiname":"Sitio Antonizio Cipriano",
    "gn:country_code":"BR",
    "gn:dem":706,
    "gn:feature_class":"P",
    "gn:feature_code":"PPL",
    "gn:name":"S\u00edtio Anton\u00edzio Cipriano",
    "gn:population":0,
    "gn:timezone":"America/Sao_Paulo",
    "iso:country":"BR",
    "name:por_x_preferred":[
        "S\u00edtio Anton\u00edzio Cipriano"
    ],
    "wof:name":"Sitio Antonizio Cipriano",
    "wof:placetype":"locality"
},
  "geometry": {"coordinates":[-50.9748,-23.8562],"type":"Point"}
}