{
  "type": "Feature",
  "properties": {
    "gn:admin1_code":"30",
    "gn:admin2_code":"2607406.0",
    "gn:asciiname":"Pereira",
    "gn:country_code":"BR",
    "gn:dem":312,
    "gn:feature_class":"P",
    "gn:feature_code":"PPL",
    "gn:name":"Pereira",
    "gn:population":0,
    "gn:timezone":"America/Recife",
    "iso:country":"BR",
    "name:cat_x_preferred":[
        "Pereira"
    ],
    "name:ceb_x_preferred":[
        "Pereira"
    ],
    "name:ces_x_preferred":[
        "Pereira"
    ],
    "name:deu_x_preferred":[
        "Pereira"
    ],
    "name:fin_x_preferred":[
        "Pereira"
    ],
    "name:fra_x_preferred":[
        "Pereira"
    ],
    "name:glg_x_preferred":[
        "Pereira"
    ],
    "name:ita_x_preferred":[
        "Pereira"
    ],
    "name:jpn_x_preferred":[
        "\u30da\u30ec\u30a4\u30e9"
    ],
    "name:kor_x_preferred":[
        "\ud398\ub808\uc774\ub77c"
    ],
    "name:msa_x_preferred":[
        "Pereira"
    ],
    "name:nld_x_preferred":[
        "Pereira"
    ],
    "name:nor_x_preferred":[
        "Pereira"
    ],
    "name:pol_x_preferred":[
        "Pereira"
    ],
    "name:por_x_preferred":[
        "Pereira"
    ],
    "name:ron_x_preferred":[
        "Pereira"
    ],
    "name:spa_x_preferred":[
        "Pereira"
    ],
    "name:swe_x_preferred":[
        "Pereira"
    ],
    "name:ukr_x_preferred":[
        "\u041f\u0435\u0440\u0435\u0439\u0440\u0430"
    ],
    "name:vie_x_preferred":[
        "Pereira"
    ],
    "name:war_x_preferred":[
        "Pereira"
    ],
    "wof:name":"Pereira",
    "wof:placetype":"locality"
},
  "geometry": {"coordinates":[-38.66667,-8.78333],"type":"Point"}
}