{
  "type": "Feature",
  "properties": {
    "gn:admin1_code":"30",
    "gn:admin2_code":"2607406.0",
    "gn:asciiname":"Pereira",
    "gn:country_code":"BR",
    "gn:dem":312,
    "gn:feature_class":"P",
    "gn:feature_code":"PPL",
    "gn:name":"Pereira",
    "gn:population":0,
    "gn:timezone":"America/Recife",
    "iso:country":"BR",
    "wof:name":"Pereira",
    "wof:placetype":"locality"
},
  "geometry": {"coordinates":[-38.66667,-8.78333],"type":"Point"}
}