{
  "type": "Feature",
  "properties": {
    "gn:country":"BR",
    "gn:fcode":"PPL",
    "gn:population":2500,
    "iso:country":"BR",
    "name:por_x_preferred":[
        "Praia da Arma\u00e7\u00e3o do P\u00e2ntano do Sul"
    ],
    "name:por_x_variant":[
        "Praia da Arma\u00e7\u00e3o",
        "Arma\u00e7\u00e3o"
    ],
    "qs_pg:aaroncc":"BR",
    "qs_pg:gn_country":"BR",
    "qs_pg:gn_fcode":"PPL",
    "qs_pg:gn_pop":2500,
    "qs_pg:name":"Arma\u00e7\u00e3o",
    "qs_pg:name_adm0":"Brasil",
    "qs_pg:name_adm1":"Santa Catarina",
    "qs_pg:photos":657,
    "qs_pg:photos_1k":133,
    "qs_pg:photos_9k":3,
    "qs_pg:photos_9r":5,
    "qs_pg:photos_all":657,
    "qs_pg:photos_sr":8,
    "qs_pg:pop_sr":4,
    "qs_pg:qs_pg_placetype":"locality",
    "qs_pg:qs_pg_placetype_gp":"Town",
    "qs_pg:woe_adm0":23424768,
    "woe:adm0_id":23424768,
    "woe:name_adm0":"Brasil",
    "woe:name_adm1":"Santa Catarina",
    "woe:placetype":"Town",
    "wof:name":"Arma\u00e7\u00e3o",
    "wof:placetype":"locality",
    "wof:population":2500
},
  "geometry": {"coordinates":[-48.50713,-27.74963],"type":"Point"}
}