{
  "type": "Feature",
  "properties": {
    "gn:admin1_code":"15",
    "gn:admin2_code":"3109402.0",
    "gn:asciiname":"Capao",
    "gn:country_code":"BR",
    "gn:dem":505,
    "gn:feature_class":"P",
    "gn:feature_code":"PPL",
    "gn:name":"Cap\u00e3o",
    "gn:population":0,
    "gn:timezone":"America/Sao_Paulo",
    "iso:country":"BR",
    "name:por_x_preferred":[
        "Cap\u00e3o"
    ],
    "wof:name":"Capao",
    "wof:placetype":"locality"
},
  "geometry": {"coordinates":[-44.85,-17.08333],"type":"Point"}
}