{
  "type": "Feature",
  "properties": {
    "gn:admin1_code":"17",
    "gn:admin2_code":"2504405.0",
    "gn:asciiname":"Serra Vermelha",
    "gn:country_code":"BR",
    "gn:dem":609,
    "gn:feature_class":"P",
    "gn:feature_code":"PPL",
    "gn:name":"Serra Vermelha",
    "gn:population":0,
    "gn:timezone":"America/Fortaleza",
    "iso:country":"BR",
    "wof:name":"Serra Vermelha",
    "wof:placetype":"locality"
},
  "geometry": {"coordinates":[-38.56667,-7.46667],"type":"Point"}
}