{
  "type": "Feature",
  "properties": {
    "gn:admin1_code":"18.0",
    "gn:admin2_code":"4109609.0",
    "gn:asciiname":"Cabaraquara",
    "gn:country_code":"BR",
    "gn:dem":252,
    "gn:feature_class":"P",
    "gn:feature_code":"PPLL",
    "gn:name":"Cabaraquara",
    "gn:population":0,
    "gn:timezone":"America/Sao_Paulo",
    "iso:country":"BR",
    "name:por_x_preferred":[
        "Cabaraquara"
    ],
    "wof:name":"Cabaraquara",
    "wof:placetype":"locality"
},
  "geometry": {"coordinates":[-48.57100000000001,-25.8304],"type":"Point"}
}