{
  "type": "Feature",
  "properties": {
    "gn:admin1_code":"20",
    "gn:admin2_code":"2209104.0",
    "gn:asciiname":"Vargem Grande (1)",
    "gn:country_code":"BR",
    "gn:dem":162,
    "gn:feature_class":"P",
    "gn:feature_code":"PPL",
    "gn:name":"Vargem Grande (1)",
    "gn:population":0,
    "gn:timezone":"America/Fortaleza",
    "iso:country":"BR",
    "wof:name":"Vargem Grande (1)",
    "wof:placetype":"locality"
},
  "geometry": {"coordinates":[-41.85,-7.11667],"type":"Point"}
}