{
  "type": "Feature",
  "properties": {
    "gn:admin1_code":"4.0",
    "gn:admin2_code":"1301951.0",
    "gn:asciiname":"Obidos",
    "gn:country_code":"BR",
    "gn:dem":106,
    "gn:feature_class":"P",
    "gn:feature_code":"PPL",
    "gn:name":"Obidos",
    "gn:population":0,
    "gn:timezone":"America/Eirunepe",
    "iso:country":"BR",
    "wof:name":"Obidos",
    "wof:placetype":"locality"
},
  "geometry": {"coordinates":[-68.93539,-6.58367],"type":"Point"}
}