{
  "type": "Feature",
  "properties": {
    "iso:country":"BR",
    "name:ceb_x_preferred":[
        "Montes Claros"
    ],
    "name:fas_x_preferred":[
        "\u0641\u0631\u0648\u062f\u06af\u0627\u0647 \u0645\u0648\u0646\u062a\u0633 \u06a9\u0644\u0627\u0631\u0648"
    ],
    "name:msa_x_preferred":[
        "Lapangan Terbang Mario Ribeiro"
    ],
    "name:por_x_preferred":[
        "Aeroporto de Montes Claros"
    ],
    "name:tgk_x_preferred":[
        "\u0424\u0443\u0440\u0443\u0434\u0433\u043e\u04b3\u0438 \u043c\u0443\u043d\u0442\u0441 \u043a\u043b\u043e\u0440\u0443"
    ],
    "oa:elevation_ft":"2191",
    "oa:type":"medium_airport",
    "wd:wordcount":127,
    "woe:hierarchy":{
        "country_id":23424768,
        "county_id":12579838,
        "planet_id":1,
        "state_id":2344856
    },
    "wof:name":"Aeroporto Montes Claros",
    "wof:placetype":"campus"
},
  "geometry": {"coordinates":[-43.82194444,-16.70611111],"type":"Point"}
}