{
  "type": "Feature",
  "properties": {
    "gn:admin1_code":"18.0",
    "gn:admin2_code":"4112306.0",
    "gn:asciiname":"Sitio Esmeraldina de Oliveira",
    "gn:country_code":"BR",
    "gn:dem":704,
    "gn:feature_class":"P",
    "gn:feature_code":"PPL",
    "gn:name":"S\u00edtio Esmeraldina de Oliveira",
    "gn:population":0,
    "gn:timezone":"America/Sao_Paulo",
    "iso:country":"BR",
    "name:por_x_preferred":[
        "S\u00edtio Esmeraldina de Oliveira"
    ],
    "wof:name":"Sitio Esmeraldina de Oliveira",
    "wof:placetype":"locality"
},
  "geometry": {"coordinates":[-50.17251,-23.78559],"type":"Point"}
}