{
  "type": "Feature",
  "properties": {
    "gn:admin1_code":"6",
    "gn:admin2_code":"2305407.0",
    "gn:asciiname":"Baixa do Sitio",
    "gn:country_code":"BR",
    "gn:dem":265,
    "gn:feature_class":"P",
    "gn:feature_code":"PPL",
    "gn:name":"Baixa do S\u00edtio",
    "gn:population":0,
    "gn:timezone":"America/Fortaleza",
    "iso:country":"BR",
    "wof:name":"Baixa do Sitio",
    "wof:placetype":"locality"
},
  "geometry": {"coordinates":[-38.96667,-6.41667],"type":"Point"}
}