{
  "type": "Feature",
  "properties": {
    "iso:country":"BR",
    "name:por_x_colloquial":[
        "Jordanopolis"
    ],
    "name:por_x_preferred":[
        "Jordan\u00f3polis"
    ],
    "name:por_x_variant":[
        "Bairro Briquituba"
    ],
    "qs:gn_adm0_cc":"BR",
    "qs:gn_fcode":"PPL",
    "qs:gn_local":3449344,
    "qs:gn_nam_loc":"sao bernardo do campo",
    "qs:gn_namadm1":"27",
    "qs:gn_name":"Bairro Briquituba",
    "qs:local_max":910,
    "qs:local_sum":2761,
    "qs:localhoods":9,
    "qs:name":"Jordan\u00f3polis",
    "qs:name_adm0":"Brasil",
    "qs:name_adm1":"S\u00e3o Paulo",
    "qs:name_adm2":"S\u00e3o Bernardo do Campo",
    "qs:name_local":"S\u00e3o Bernardo do Campo",
    "qs:photo_max":29,
    "qs:photo_sum":115,
    "qs:placetype":"Suburb",
    "qs:quad_count":10,
    "qs:woe_adm0":23424768,
    "qs:woe_adm1":2344868,
    "qs:woe_adm2":12582298,
    "qs:woe_lau":0,
    "qs:woe_local":449648,
    "qs:woe_ver":"7.10.0",
    "wof:lang":[
        "por"
    ],
    "wof:name":"Jordan\u00f3polis",
    "wof:placetype":"neighbourhood"
},
  "geometry": {"coordinates":[-46.56522,-23.685988],"type":"Point"}
}