{
  "type": "Feature",
  "properties": {
    "gn:admin1_code":"13",
    "gn:admin2_code":"2106409.0",
    "gn:asciiname":"Bacuri",
    "gn:country_code":"BR",
    "gn:dem":67,
    "gn:feature_class":"P",
    "gn:feature_code":"PPL",
    "gn:name":"Bacuri",
    "gn:population":0,
    "gn:timezone":"America/Fortaleza",
    "iso:country":"BR",
    "wof:name":"Bacuri",
    "wof:placetype":"locality"
},
  "geometry": {"coordinates":[-43.18806,-3.56417],"type":"Point"}
}