{
  "type": "Feature",
  "properties": {
    "gn:admin1_code":"30",
    "gn:admin2_code":"2613909.0",
    "gn:asciiname":"Tres Irmaos",
    "gn:country_code":"BR",
    "gn:dem":400,
    "gn:feature_class":"P",
    "gn:feature_code":"PPL",
    "gn:name":"Tr\u00eas Irm\u00e3os",
    "gn:population":0,
    "gn:timezone":"America/Recife",
    "iso:country":"BR",
    "wof:name":"Tres Irmaos",
    "wof:placetype":"locality"
},
  "geometry": {"coordinates":[-38.53333,-8.16667],"type":"Point"}
}