{
  "type": "Feature",
  "properties": {
    "gn:admin1_code":"4",
    "gn:admin2_code":"1301308.0",
    "gn:asciiname":"Ponta do Peixoto",
    "gn:country_code":"BR",
    "gn:dem":41,
    "gn:feature_class":"P",
    "gn:feature_code":"PPL",
    "gn:name":"Ponta do Peixoto",
    "gn:population":0,
    "gn:timezone":"America/Manaus",
    "iso:country":"BR",
    "wof:name":"Ponta do Peixoto",
    "wof:placetype":"locality"
},
  "geometry": {"coordinates":[-62.90861,-3.25333],"type":"Point"}
}