{
  "type": "Feature",
  "properties": {
    "gn:admin1_code":"4",
    "gn:admin2_code":"1300631.0",
    "gn:asciiname":"Macaco-Prego",
    "gn:country_code":"BR",
    "gn:dem":25,
    "gn:feature_class":"P",
    "gn:feature_code":"PPL",
    "gn:name":"Macaco-Prego",
    "gn:population":0,
    "gn:timezone":"America/Manaus",
    "iso:country":"BR",
    "wof:name":"Macaco-Prego",
    "wof:placetype":"locality"
},
  "geometry": {"coordinates":[-60.84194,-4.16806],"type":"Point"}
}