{
  "type": "Feature",
  "properties": {
    "gn:admin1_code":"06",
    "gn:admin2_code":"2302008.0",
    "gn:asciiname":"Riacho de Melc",
    "gn:country_code":"BR",
    "gn:dem":376,
    "gn:feature_class":"P",
    "gn:feature_code":"PPL",
    "gn:name":"Riacho de Melc",
    "gn:population":0,
    "gn:timezone":"America/Fortaleza",
    "iso:country":"BR",
    "wof:name":"Riacho de Melc",
    "wof:placetype":"locality"
},
  "geometry": {"coordinates":[-38.86667,-7.16667],"type":"Point"}
}