{
  "type": "Feature",
  "properties": {
    "gn:admin1_code":"22",
    "gn:admin2_code":"2410603.0",
    "gn:asciiname":"Carvoeiro",
    "gn:country_code":"BR",
    "gn:dem":243,
    "gn:feature_class":"P",
    "gn:feature_code":"PPL",
    "gn:name":"Carvoeiro",
    "gn:population":0,
    "gn:timezone":"America/Fortaleza",
    "iso:country":"BR",
    "name:ceb_x_preferred":[
        "Carvoeiro"
    ],
    "name:deu_x_preferred":[
        "Carvoeiro"
    ],
    "name:nld_x_preferred":[
        "Carvoeiro"
    ],
    "name:por_x_preferred":[
        "Carvoeiro"
    ],
    "name:rus_x_preferred":[
        "\u041a\u0430\u0440\u0432\u043e\u044d\u0439\u0440\u0430"
    ],
    "name:tur_x_preferred":[
        "Carvoeiro"
    ],
    "wof:name":"Carvoeiro",
    "wof:placetype":"locality"
},
  "geometry": {"coordinates":[-37.73333,-6.11667],"type":"Point"}
}