{
  "type": "Feature",
  "properties": {
    "gn:admin1_code":"22",
    "gn:admin2_code":"2410603.0",
    "gn:asciiname":"Carvoeiro",
    "gn:country_code":"BR",
    "gn:dem":243,
    "gn:feature_class":"P",
    "gn:feature_code":"PPL",
    "gn:name":"Carvoeiro",
    "gn:population":0,
    "gn:timezone":"America/Fortaleza",
    "iso:country":"BR",
    "wof:name":"Carvoeiro",
    "wof:placetype":"locality"
},
  "geometry": {"coordinates":[-37.73333,-6.11667],"type":"Point"}
}