{
  "type": "Feature",
  "properties": {
    "gn:admin1_code":"6",
    "gn:admin2_code":"2308104.0",
    "gn:asciiname":"Beleza",
    "gn:country_code":"BR",
    "gn:dem":620,
    "gn:feature_class":"P",
    "gn:feature_code":"PPL",
    "gn:name":"Beleza",
    "gn:population":0,
    "gn:timezone":"America/Fortaleza",
    "iso:country":"BR",
    "wof:name":"Beleza",
    "wof:placetype":"locality"
},
  "geometry": {"coordinates":[-38.66667,-7.28333],"type":"Point"}
}