{
  "type": "Feature",
  "properties": {
    "gn:admin1_code":"18.0",
    "gn:admin2_code":"4103602.0",
    "gn:asciiname":"Conjugado Habitacao Companhia de Habitacao do Parana",
    "gn:country_code":"BR",
    "gn:dem":430,
    "gn:feature_class":"P",
    "gn:feature_code":"PPL",
    "gn:name":"Conjugado Habita\u00e7\u00e3o Companhia de Habita\u00e7\u00e3o do Paran\u00e1",
    "gn:population":0,
    "gn:timezone":"America/Sao_Paulo",
    "iso:country":"BR",
    "name:por_x_preferred":[
        "Conjugado Habita\u00e7\u00e3o Companhia de Habita\u00e7\u00e3o do Paran\u00e1"
    ],
    "wof:name":"Conjugado Habitacao Companhia de Habitacao do Parana",
    "wof:placetype":"locality"
},
  "geometry": {"coordinates":[-50.0721,-23.02981],"type":"Point"}
}