{
  "type": "Feature",
  "properties": {
    "gn:admin1_code":"29.0",
    "gn:admin2_code":"5214051.0",
    "gn:asciiname":"Sao Joao da Mata Azul",
    "gn:country_code":"BR",
    "gn:dem":253,
    "gn:feature_class":"P",
    "gn:feature_code":"PPL",
    "gn:name":"S\u00e3o Jo\u00e3o da Mata Azul",
    "gn:population":0,
    "gn:timezone":"America/Sao_Paulo",
    "iso:country":"BR",
    "name:por_x_preferred":[
        "S\u00e3o Jo\u00e3o da Mata Azul"
    ],
    "wof:name":"Sao Joao da Mata Azul",
    "wof:placetype":"locality"
},
  "geometry": {"coordinates":[-50.19131,-13.79754],"type":"Point"}
}