{
  "type": "Feature",
  "properties": {
    "gn:admin1_code":"26",
    "gn:admin2_code":"4210100.0",
    "gn:asciiname":"Sitio Luiz A. Gelbk",
    "gn:country_code":"BR",
    "gn:dem":841,
    "gn:feature_class":"P",
    "gn:feature_code":"PPL",
    "gn:name":"S\u00edtio Luiz A. Gelbk",
    "gn:population":0,
    "gn:timezone":"America/Sao_Paulo",
    "iso:country":"BR",
    "name:por_x_preferred":[
        "S\u00edtio Luiz A. Gelbk"
    ],
    "wof:name":"Sitio Luiz A. Gelbk",
    "wof:placetype":"locality"
},
  "geometry": {"coordinates":[-49.9428,-26.202],"type":"Point"}
}