{
  "type": "Feature",
  "properties": {
    "gn:admin1_code":"18.0",
    "gn:admin2_code":"4106209.0",
    "gn:asciiname":"Sitio Jorge Strugal",
    "gn:country_code":"BR",
    "gn:dem":876,
    "gn:feature_class":"P",
    "gn:feature_code":"PPL",
    "gn:name":"S\u00edtio Jorge Strugal",
    "gn:population":0,
    "gn:timezone":"America/Sao_Paulo",
    "iso:country":"BR",
    "name:por_x_preferred":[
        "S\u00edtio Jorge Strugal"
    ],
    "wof:name":"Sitio Jorge Strugal",
    "wof:placetype":"locality"
},
  "geometry": {"coordinates":[-49.485,-25.7566],"type":"Point"}
}