{
  "type": "Feature",
  "properties": {
    "gn:admin1_code":"26.0",
    "gn:admin2_code":"4209904.0",
    "gn:asciiname":"Concordia",
    "gn:country_code":"BR",
    "gn:dem":353,
    "gn:feature_class":"P",
    "gn:feature_code":"PPLL",
    "gn:name":"Conc\u00f3rdia",
    "gn:population":0,
    "gn:timezone":"America/Sao_Paulo",
    "iso:country":"BR",
    "name:por_x_preferred":[
        "Conc\u00f3rdia"
    ],
    "wof:name":"Concordia",
    "wof:placetype":"locality"
},
  "geometry": {"coordinates":[-49.5178,-27.1811],"type":"Point"}
}