{
  "type": "Feature",
  "properties": {
    "gn:admin1_code":"30",
    "gn:admin2_code":"2614600.0",
    "gn:asciiname":"Saco da Onca",
    "gn:country_code":"BR",
    "gn:dem":560,
    "gn:feature_class":"P",
    "gn:feature_code":"PPL",
    "gn:name":"Saco da On\u00e7a",
    "gn:population":0,
    "gn:timezone":"America/Recife",
    "iso:country":"BR",
    "wof:name":"Saco da Onca",
    "wof:placetype":"locality"
},
  "geometry": {"coordinates":[-37.53333,-7.68333],"type":"Point"}
}