{
  "type": "Feature",
  "properties": {
    "gn:admin1_code":"22",
    "gn:admin2_code":"2414605.0",
    "gn:asciiname":"Cabana",
    "gn:country_code":"BR",
    "gn:dem":87,
    "gn:feature_class":"P",
    "gn:feature_code":"PPL",
    "gn:name":"Cabana",
    "gn:population":0,
    "gn:timezone":"America/Fortaleza",
    "iso:country":"BR",
    "name:bre_x_preferred":[
        "Cabana"
    ],
    "name:ceb_x_preferred":[
        "Cabana"
    ],
    "name:deu_x_preferred":[
        "Cabana"
    ],
    "name:fra_x_preferred":[
        "Cabana"
    ],
    "name:glg_x_preferred":[
        "Cabana"
    ],
    "name:ita_x_preferred":[
        "Cabana"
    ],
    "name:por_x_preferred":[
        "Cabana"
    ],
    "name:spa_x_preferred":[
        "Cabana"
    ],
    "wof:name":"Cabana",
    "wof:placetype":"locality"
},
  "geometry": {"coordinates":[-37.19222,-5.60167],"type":"Point"}
}