{
  "type": "Feature",
  "properties": {
    "gn:admin1_code":"6",
    "gn:admin2_code":"2313500.0",
    "gn:asciiname":"Bacumixa",
    "gn:country_code":"BR",
    "gn:dem":48,
    "gn:feature_class":"P",
    "gn:feature_code":"PPL",
    "gn:name":"Bacumix\u00e1",
    "gn:population":0,
    "gn:timezone":"America/Fortaleza",
    "iso:country":"BR",
    "wof:name":"Bacumixa",
    "wof:placetype":"locality"
},
  "geometry": {"coordinates":[-39.46667,-3.31667],"type":"Point"}
}