{
  "type": "Feature",
  "properties": {
    "gn:admin1_code":"30",
    "gn:admin2_code":"2614808.0",
    "gn:asciiname":"Morena",
    "gn:country_code":"BR",
    "gn:dem":363,
    "gn:feature_class":"P",
    "gn:feature_code":"PPL",
    "gn:name":"Morena",
    "gn:population":0,
    "gn:timezone":"America/Recife",
    "iso:country":"BR",
    "wof:name":"Morena",
    "wof:placetype":"locality"
},
  "geometry": {"coordinates":[-38.15,-8.93333],"type":"Point"}
}