{
  "type": "Feature",
  "properties": {
    "gn:admin1_code":"6",
    "gn:admin2_code":"2302602.0",
    "gn:asciiname":"Montevidi",
    "gn:country_code":"BR",
    "gn:dem":22,
    "gn:feature_class":"P",
    "gn:feature_code":"PPL",
    "gn:name":"Montevidi",
    "gn:population":0,
    "gn:timezone":"America/Fortaleza",
    "iso:country":"BR",
    "wof:name":"Montevidi",
    "wof:placetype":"locality"
},
  "geometry": {"coordinates":[-41.0425,-2.95694],"type":"Point"}
}