{
  "type": "Feature",
  "properties": {
    "gn:admin1_code":"15",
    "gn:admin2_code":"3114600.0",
    "gn:asciiname":"Verrugas",
    "gn:country_code":"BR",
    "gn:dem":1010,
    "gn:feature_class":"P",
    "gn:feature_code":"PPL",
    "gn:name":"Verrugas",
    "gn:population":0,
    "gn:timezone":"America/Sao_Paulo",
    "iso:country":"BR",
    "name:por_x_preferred":[
        "Verrugas"
    ],
    "wof:name":"Verrugas",
    "wof:placetype":"locality"
},
  "geometry": {"coordinates":[-44.58333,-21.41667],"type":"Point"}
}