{
  "type": "Feature",
  "properties": {
    "gn:admin1_code":"27",
    "gn:admin2_code":"3526209.0",
    "gn:asciiname":"Sitio dos Seis Porquinhos",
    "gn:country_code":"BR",
    "gn:dem":714,
    "gn:feature_class":"P",
    "gn:feature_code":"PPL",
    "gn:name":"S\u00edtio dos Seis Porquinhos",
    "gn:population":0,
    "gn:timezone":"America/Sao_Paulo",
    "iso:country":"BR",
    "name:por_x_preferred":[
        "S\u00edtio dos Seis Porquinhos"
    ],
    "wof:name":"Sitio dos Seis Porquinhos",
    "wof:placetype":"locality"
},
  "geometry": {"coordinates":[-47.0641,-23.9862],"type":"Point"}
}