{
  "type": "Feature",
  "properties": {
    "gn:admin1_code":"18.0",
    "gn:admin2_code":"4107751.0",
    "gn:asciiname":"Sitio Silverio P. Carneiro",
    "gn:country_code":"BR",
    "gn:dem":777,
    "gn:feature_class":"P",
    "gn:feature_code":"PPL",
    "gn:name":"S\u00edtio Silv\u00e9rio P. Carneiro",
    "gn:population":0,
    "gn:timezone":"America/Sao_Paulo",
    "iso:country":"BR",
    "name:por_x_preferred":[
        "S\u00edtio Silv\u00e9rio P. Carneiro"
    ],
    "wof:name":"Sitio Silverio P. Carneiro",
    "wof:placetype":"locality"
},
  "geometry": {"coordinates":[-50.44084,-23.9504],"type":"Point"}
}