{
  "type": "Feature",
  "properties": {
    "gn:admin1_code":"13",
    "gn:admin2_code":"2103208.0",
    "gn:asciiname":"Cipo III",
    "gn:country_code":"BR",
    "gn:dem":90,
    "gn:feature_class":"P",
    "gn:feature_code":"PPL",
    "gn:name":"Cip\u00f3 III",
    "gn:population":0,
    "gn:timezone":"America/Fortaleza",
    "iso:country":"BR",
    "wof:name":"Cipo III",
    "wof:placetype":"locality"
},
  "geometry": {"coordinates":[-43.405,-3.65806],"type":"Point"}
}