{
  "type": "Feature",
  "properties": {
    "gn:admin1_code":"18",
    "gn:admin2_code":"4104105.0",
    "gn:asciiname":"Sitio Iracema da Silva",
    "gn:country_code":"BR",
    "gn:dem":805,
    "gn:feature_class":"P",
    "gn:feature_code":"PPL",
    "gn:name":"S\u00edtio Iracema da Silva",
    "gn:population":0,
    "gn:timezone":"America/Sao_Paulo",
    "iso:country":"BR",
    "name:por_x_preferred":[
        "S\u00edtio Iracema da Silva"
    ],
    "wof:name":"Sitio Iracema da Silva",
    "wof:placetype":"locality"
},
  "geometry": {"coordinates":[-49.60919000000001,-25.9111],"type":"Point"}
}