{
  "type": "Feature",
  "properties": {
    "gn:admin1_code":"17",
    "gn:admin2_code":"2501609.0",
    "gn:asciiname":"Serrote Verde",
    "gn:country_code":"BR",
    "gn:dem":580,
    "gn:feature_class":"P",
    "gn:feature_code":"PPL",
    "gn:name":"Serrote Verde",
    "gn:population":0,
    "gn:timezone":"America/Fortaleza",
    "iso:country":"BR",
    "wof:name":"Serrote Verde",
    "wof:placetype":"locality"
},
  "geometry": {"coordinates":[-36.16667,-6.86667],"type":"Point"}
}