{
  "type": "Feature",
  "properties": {
    "gn:admin1_code":"14",
    "gn:admin2_code":"5107958.0",
    "gn:asciiname":"Porfirio",
    "gn:country_code":"BR",
    "gn:dem":322,
    "gn:feature_class":"P",
    "gn:feature_code":"PPL",
    "gn:name":"Porf\u00edrio",
    "gn:population":0,
    "gn:timezone":"America/Cuiaba",
    "iso:country":"BR",
    "name:ita_x_preferred":[
        "Porfirio"
    ],
    "wof:name":"Porfirio",
    "wof:placetype":"locality"
},
  "geometry": {"coordinates":[-57.41667,-14.51667],"type":"Point"}
}