{
  "type": "Feature",
  "properties": {
    "gn:admin1_code":"18.0",
    "gn:admin2_code":"4100301.0",
    "gn:asciiname":"Tabuao",
    "gn:country_code":"BR",
    "gn:dem":829,
    "gn:feature_class":"P",
    "gn:feature_code":"PPLL",
    "gn:name":"Tabu\u00e3o",
    "gn:population":0,
    "gn:timezone":"America/Sao_Paulo",
    "iso:country":"BR",
    "name:por_x_preferred":[
        "Tabu\u00e3o"
    ],
    "wof:name":"Tabuao",
    "wof:placetype":"locality"
},
  "geometry": {"coordinates":[-49.3645,-25.9675],"type":"Point"}
}