{
  "type": "Feature",
  "properties": {
    "gn:admin1_code":"26",
    "gn:admin2_code":"4207908.0",
    "gn:asciiname":"Sao Roque",
    "gn:country_code":"BR",
    "gn:dem":764,
    "gn:feature_class":"P",
    "gn:feature_code":"PPL",
    "gn:name":"S\u00e3o Roque",
    "gn:population":0,
    "gn:timezone":"America/Sao_Paulo",
    "iso:country":"BR",
    "wof:name":"Sao Roque",
    "wof:placetype":"locality"
},
  "geometry": {"coordinates":[-50.78333,-26.41667],"type":"Point"}
}