{
  "type": "Feature",
  "properties": {
    "gn:admin1_code":"18.0",
    "gn:admin2_code":"4119202.0",
    "gn:asciiname":"Sitio Hilario Galan",
    "gn:country_code":"BR",
    "gn:dem":645,
    "gn:feature_class":"P",
    "gn:feature_code":"PPL",
    "gn:name":"S\u00edtio Hil\u00e1rio Galan",
    "gn:population":0,
    "gn:timezone":"America/Sao_Paulo",
    "iso:country":"BR",
    "name:por_x_preferred":[
        "S\u00edtio Hil\u00e1rio Galan"
    ],
    "wof:name":"Sitio Hilario Galan",
    "wof:placetype":"locality"
},
  "geometry": {"coordinates":[-50.06629,-23.82258],"type":"Point"}
}