{
  "type": "Feature",
  "properties": {
    "gn:admin1_code":"5",
    "gn:admin2_code":"2920502.0",
    "gn:asciiname":"Estiva",
    "gn:country_code":"BR",
    "gn:dem":851,
    "gn:feature_class":"P",
    "gn:feature_code":"PPL",
    "gn:name":"Estiva",
    "gn:population":0,
    "gn:timezone":"America/Bahia",
    "iso:country":"BR",
    "wof:name":"Estiva",
    "wof:placetype":"locality"
},
  "geometry": {"coordinates":[-40.43333,-13.56667],"type":"Point"}
}