{
  "type": "Feature",
  "properties": {
    "gn:admin1_code":"26",
    "gn:admin2_code":"4210100.0",
    "gn:asciiname":"Sitio Vitorio Ianoviscki",
    "gn:country_code":"BR",
    "gn:dem":922,
    "gn:feature_class":"P",
    "gn:feature_code":"PPL",
    "gn:name":"S\u00edtio Vit\u00f3rio Ianoviscki",
    "gn:population":0,
    "gn:timezone":"America/Sao_Paulo",
    "iso:country":"BR",
    "name:por_x_preferred":[
        "S\u00edtio Vit\u00f3rio Ianoviscki"
    ],
    "wof:name":"Sitio Vitorio Ianoviscki",
    "wof:placetype":"locality"
},
  "geometry": {"coordinates":[-49.9975,-26.1916],"type":"Point"}
}