{
  "type": "Feature",
  "properties": {
    "gn:admin1_code":"18.0",
    "gn:admin2_code":"4102406.0",
    "gn:asciiname":"Sitio Francisco Bezerra",
    "gn:country_code":"BR",
    "gn:dem":451,
    "gn:feature_class":"P",
    "gn:feature_code":"PPL",
    "gn:name":"S\u00edtio Francisco Bezerra",
    "gn:population":0,
    "gn:timezone":"America/Sao_Paulo",
    "iso:country":"BR",
    "name:por_x_preferred":[
        "S\u00edtio Francisco Bezerra"
    ],
    "wof:name":"Sitio Francisco Bezerra",
    "wof:placetype":"locality"
},
  "geometry": {"coordinates":[-50.2324,-23.2062],"type":"Point"}
}