{
  "type": "Feature",
  "properties": {
    "gn:admin1_code":"13",
    "gn:admin2_code":"2110104.0",
    "gn:asciiname":"Pa Serrada",
    "gn:country_code":"BR",
    "gn:dem":44,
    "gn:feature_class":"P",
    "gn:feature_code":"PPL",
    "gn:name":"P\u00e1 Serrada",
    "gn:population":0,
    "gn:timezone":"America/Fortaleza",
    "iso:country":"BR",
    "wof:name":"Pa Serrada",
    "wof:placetype":"locality"
},
  "geometry": {"coordinates":[-43.01472,-3.20722],"type":"Point"}
}