{
  "type": "Feature",
  "properties": {
    "gn:admin1_code":"06",
    "gn:admin2_code":"2303709.0",
    "gn:asciiname":"Matoes",
    "gn:country_code":"BR",
    "gn:dem":37,
    "gn:feature_class":"P",
    "gn:feature_code":"PPL",
    "gn:name":"Mat\u00f5es",
    "gn:population":0,
    "gn:timezone":"America/Fortaleza",
    "iso:country":"BR",
    "wof:name":"Matoes",
    "wof:placetype":"locality"
},
  "geometry": {"coordinates":[-38.81667,-3.58333],"type":"Point"}
}