{
  "type": "Feature",
  "properties": {
    "gn:admin1_code":"06",
    "gn:admin2_code":"2310308.0",
    "gn:asciiname":"Merejo",
    "gn:country_code":"BR",
    "gn:dem":542,
    "gn:feature_class":"P",
    "gn:feature_code":"PPL",
    "gn:name":"Mer\u00eajo",
    "gn:population":0,
    "gn:timezone":"America/Fortaleza",
    "iso:country":"BR",
    "wof:name":"Merejo",
    "wof:placetype":"locality"
},
  "geometry": {"coordinates":[-40.68333,-6.16667],"type":"Point"}
}