{
  "type": "Feature",
  "properties": {
    "gn:admin1_code":"15",
    "gn:admin2_code":"3168903.0",
    "gn:asciiname":"Lagoa do Gouveia",
    "gn:cc2":"BR",
    "gn:country_code":"BR",
    "gn:dem":1001,
    "gn:feature_class":"P",
    "gn:feature_code":"PPL",
    "gn:name":"Lagoa do Gouveia",
    "gn:population":0,
    "gn:timezone":"America/Sao_Paulo",
    "iso:country":"BR",
    "name:und_x_variant":[
        "Lagoa",
        "Lagoa do Gouveia"
    ],
    "wof:name":"Lagoa do Gouveia",
    "wof:placetype":"locality"
},
  "geometry": {"coordinates":[-45.83333,-18.81667],"type":"Point"}
}