{
  "type": "Feature",
  "properties": {
    "gn:admin1_code":"17",
    "gn:admin2_code":"2514503.0",
    "gn:asciiname":"Saco",
    "gn:country_code":"BR",
    "gn:dem":350,
    "gn:feature_class":"P",
    "gn:feature_code":"PPL",
    "gn:name":"Saco",
    "gn:population":0,
    "gn:timezone":"America/Fortaleza",
    "iso:country":"BR",
    "wof:name":"Saco",
    "wof:placetype":"locality"
},
  "geometry": {"coordinates":[-38.51667,-7.13333],"type":"Point"}
}