{
  "type": "Feature",
  "properties": {
    "gn:admin1_code":"06",
    "gn:admin2_code":"2311405.0",
    "gn:asciiname":"Mulungu",
    "gn:country_code":"BR",
    "gn:dem":572,
    "gn:feature_class":"P",
    "gn:feature_code":"PPL",
    "gn:name":"Mulungu",
    "gn:population":0,
    "gn:timezone":"America/Fortaleza",
    "iso:country":"BR",
    "name:ita_x_preferred":[
        "Mulungu"
    ],
    "name:lit_x_preferred":[
        "Mulungu"
    ],
    "name:swe_x_preferred":[
        "Mulungu"
    ],
    "wof:name":"Mulungu",
    "wof:placetype":"locality"
},
  "geometry": {"coordinates":[-39.25,-5.08333],"type":"Point"}
}