{
  "type": "Feature",
  "properties": {
    "gn:admin1_code":"18.0",
    "gn:admin2_code":"4126678.0",
    "gn:asciiname":"Sitio Mario Souza Rodrigues",
    "gn:country_code":"BR",
    "gn:dem":720,
    "gn:feature_class":"P",
    "gn:feature_code":"PPL",
    "gn:name":"S\u00edtio M\u00e1rio Souza Rodrigues",
    "gn:population":0,
    "gn:timezone":"America/Sao_Paulo",
    "iso:country":"BR",
    "name:por_x_preferred":[
        "S\u00edtio M\u00e1rio Souza Rodrigues"
    ],
    "wof:name":"Sitio Mario Souza Rodrigues",
    "wof:placetype":"locality"
},
  "geometry": {"coordinates":[-50.9794,-23.873],"type":"Point"}
}