{
  "type": "Feature",
  "properties": {
    "gn:admin1_code":"27.0",
    "gn:admin2_code":"3528502.0",
    "gn:asciiname":"Sitio Nossa Senhora Aparecida",
    "gn:country_code":"BR",
    "gn:dem":946,
    "gn:feature_class":"P",
    "gn:feature_code":"PPL",
    "gn:name":"S\u00edtio Nossa Senhora Aparecida",
    "gn:population":0,
    "gn:timezone":"America/Sao_Paulo",
    "iso:country":"BR",
    "name:por_x_preferred":[
        "S\u00edtio Nossa Senhora Aparecida"
    ],
    "wof:name":"Sitio Nossa Senhora Aparecida",
    "wof:placetype":"locality"
},
  "geometry": {"coordinates":[-46.60963,-23.2722],"type":"Point"}
}