{
  "type": "Feature",
  "properties": {
    "gn:admin1_code":"18",
    "gn:admin2_code":"4127601.0",
    "gn:asciiname":"Sitio Antonio Pandeleque",
    "gn:country_code":"BR",
    "gn:dem":931,
    "gn:feature_class":"P",
    "gn:feature_code":"PPL",
    "gn:name":"S\u00edtio Ant\u00f4nio Pandeleque",
    "gn:population":0,
    "gn:timezone":"America/Sao_Paulo",
    "iso:country":"BR",
    "name:por_x_preferred":[
        "S\u00edtio Ant\u00f4nio Pandeleque"
    ],
    "wof:name":"Sitio Antonio Pandeleque",
    "wof:placetype":"locality"
},
  "geometry": {"coordinates":[-49.0911,-25.8753],"type":"Point"}
}