{
  "type": "Feature",
  "properties": {
    "gn:admin1_code":"18.0",
    "gn:admin2_code":"4124103.0",
    "gn:asciiname":"Sitio Santa Maria",
    "gn:country_code":"BR",
    "gn:dem":487,
    "gn:feature_class":"P",
    "gn:feature_code":"PPL",
    "gn:name":"S\u00edtio Santa Maria",
    "gn:population":0,
    "gn:timezone":"America/Sao_Paulo",
    "iso:country":"BR",
    "name:por_x_preferred":[
        "S\u00edtio Santa Maria"
    ],
    "wof:name":"Sitio Santa Maria",
    "wof:placetype":"locality"
},
  "geometry": {"coordinates":[-50.13994,-23.32929],"type":"Point"}
}