{
  "type": "Feature",
  "properties": {
    "gn:admin1_code":"17",
    "gn:admin2_code":"2503100.0",
    "gn:asciiname":"Macambira",
    "gn:country_code":"BR",
    "gn:dem":477,
    "gn:feature_class":"P",
    "gn:feature_code":"PPL",
    "gn:name":"Macambira",
    "gn:population":0,
    "gn:timezone":"America/Fortaleza",
    "iso:country":"BR",
    "name:bpy_x_preferred":[
        "\u09ae\u09be\u0995\u09be\u09ae\u09ac\u09bf\u09b0\u09be"
    ],
    "name:ceb_x_preferred":[
        "Macambira"
    ],
    "name:epo_x_preferred":[
        "Macambira"
    ],
    "name:eus_x_preferred":[
        "Macambira"
    ],
    "name:fra_x_preferred":[
        "Macambira"
    ],
    "name:ita_x_preferred":[
        "Macambira"
    ],
    "name:nld_x_preferred":[
        "Macambira"
    ],
    "name:nor_x_preferred":[
        "Macambira"
    ],
    "name:por_x_preferred":[
        "Macambira"
    ],
    "name:ron_x_preferred":[
        "Macambira"
    ],
    "name:rus_x_preferred":[
        "\u041c\u0430\u043a\u0430\u043c\u0431\u0438\u0440\u0430"
    ],
    "name:spa_x_preferred":[
        "Macambira"
    ],
    "name:swe_x_preferred":[
        "Macambira"
    ],
    "name:vie_x_preferred":[
        "Macambira"
    ],
    "name:vol_x_preferred":[
        "Macambira"
    ],
    "name:war_x_preferred":[
        "Macambira"
    ],
    "name:zho_x_preferred":[
        "\u99ac\u574e\u6bd4\u62c9"
    ],
    "wof:name":"Macambira",
    "wof:placetype":"locality"
},
  "geometry": {"coordinates":[-36.41667,-7.48333],"type":"Point"}
}