{
  "type": "Feature",
  "properties": {
    "gn:admin1_code":"17",
    "gn:admin2_code":"2503100.0",
    "gn:asciiname":"Macambira",
    "gn:country_code":"BR",
    "gn:dem":477,
    "gn:feature_class":"P",
    "gn:feature_code":"PPL",
    "gn:name":"Macambira",
    "gn:population":0,
    "gn:timezone":"America/Fortaleza",
    "iso:country":"BR",
    "wof:name":"Macambira",
    "wof:placetype":"locality"
},
  "geometry": {"coordinates":[-36.41667,-7.48333],"type":"Point"}
}