{
  "type": "Feature",
  "properties": {
    "gn:gn_country":"BR",
    "gn:gn_fcode":"PPLH",
    "gn:gn_pop":500,
    "gn:population":500,
    "iso:country":"BR",
    "qs_pg:aaroncc":"BR",
    "qs_pg:gn_country":"BR",
    "qs_pg:gn_fcode":"PPLH",
    "qs_pg:gn_pop":500,
    "qs_pg:name":"Vila Militar Copacabana - VMC - Ex\u00e9rcito - Army",
    "qs_pg:photos_9r":0,
    "qs_pg:photos_sr":0,
    "qs_pg:pop_sr":2,
    "qs_pg:qs_pg_placetype":"locality",
    "wof:name":"Vila Militar Copacabana - VMC - Ex\u00e9rcito - Army",
    "wof:placetype":"locality",
    "wof:population":500
},
  "geometry": {"coordinates":[-43.17918,-22.96251],"type":"Point"}
}