{
  "type": "Feature",
  "properties": {
    "gn:admin1_code":"1",
    "gn:admin2_code":"1200708.0",
    "gn:asciiname":"Iracema",
    "gn:country_code":"BR",
    "gn:dem":172,
    "gn:feature_class":"P",
    "gn:feature_code":"PPL",
    "gn:name":"Iracema",
    "gn:population":0,
    "gn:timezone":"America/Rio_Branco",
    "iso:country":"BR",
    "name:bpy_x_preferred":[
        "\u0987\u09b0\u09be\u09b8\u09c7\u09ae\u09be"
    ],
    "name:deu_x_preferred":[
        "Iracema"
    ],
    "name:epo_x_preferred":[
        "Iracema"
    ],
    "name:fra_x_preferred":[
        "Iracema"
    ],
    "name:por_x_preferred":[
        "Iracema"
    ],
    "name:war_x_preferred":[
        "Iracema"
    ],
    "wof:name":"Iracema",
    "wof:placetype":"locality"
},
  "geometry": {"coordinates":[-68.15000000000001,-10.53333],"type":"Point"}
}