{
  "type": "Feature",
  "properties": {
    "gn:admin1_code":"26.0",
    "gn:admin2_code":"4205407.0",
    "gn:asciiname":"Abraao",
    "gn:country_code":"BR",
    "gn:dem":7,
    "gn:feature_class":"P",
    "gn:feature_code":"PPLL",
    "gn:name":"Abraao",
    "gn:population":0,
    "gn:timezone":"America/Sao_Paulo",
    "iso:country":"BR",
    "wof:name":"Abraao",
    "wof:placetype":"locality"
},
  "geometry": {"coordinates":[-48.59433,-27.60651],"type":"Point"}
}