{
  "type": "Feature",
  "properties": {
    "gn:admin1_code":"5",
    "gn:admin2_code":"2924009.0",
    "gn:asciiname":"Alagadico",
    "gn:cc2":"BR",
    "gn:country_code":"BR",
    "gn:dem":347,
    "gn:feature_class":"P",
    "gn:feature_code":"PPL",
    "gn:name":"Alagadi\u00e7o",
    "gn:population":0,
    "gn:timezone":"America/Bahia",
    "iso:country":"BR",
    "name:und_x_variant":[
        "Alagaci\u00e7o",
        "Alagadi\u00e7o"
    ],
    "wof:name":"Alagadico",
    "wof:placetype":"locality"
},
  "geometry": {"coordinates":[-38.36667,-9.53333],"type":"Point"}
}