{
  "type": "Feature",
  "properties": {
    "gn:admin1_code":"6",
    "gn:admin2_code":"2312205.0",
    "gn:asciiname":"Cachoeira",
    "gn:country_code":"BR",
    "gn:dem":478,
    "gn:feature_class":"P",
    "gn:feature_code":"PPL",
    "gn:name":"Cachoeira",
    "gn:population":0,
    "gn:timezone":"America/Fortaleza",
    "iso:country":"BR",
    "name:bpy_x_preferred":[
        "\u0995\u09be\u0995\u09b9\u09cb\u09af\u09bc\u09c7\u0987\u09b0\u09be"
    ],
    "name:ceb_x_preferred":[
        "Cachoeira"
    ],
    "name:deu_x_preferred":[
        "Cachoeira"
    ],
    "name:epo_x_preferred":[
        "Cachoeira"
    ],
    "name:eus_x_preferred":[
        "Cachoeira"
    ],
    "name:fra_x_preferred":[
        "Cachoeira"
    ],
    "name:hye_x_preferred":[
        "\u053f\u0561\u0577\u0578\u0582\u0565\u0575\u0580\u0561"
    ],
    "name:ita_x_preferred":[
        "Cachoeira"
    ],
    "name:kat_x_preferred":[
        "\u10d9\u10d0\u10e8\u10e3\u10d4\u10d8\u10e0\u10d0"
    ],
    "name:kaz_x_preferred":[
        "\u041a\u0430\u0448\u0443\u044d\u0439\u0440\u0430"
    ],
    "name:mlg_x_preferred":[
        "Cachoeira"
    ],
    "name:nld_x_preferred":[
        "Cachoeira"
    ],
    "name:nor_x_preferred":[
        "Cachoeira"
    ],
    "name:pol_x_preferred":[
        "Cachoeira"
    ],
    "name:por_x_preferred":[
        "Cachoeira"
    ],
    "name:ron_x_preferred":[
        "Cachoeira"
    ],
    "name:rus_x_preferred":[
        "\u041a\u0430\u0448\u0443\u044d\u0439\u0440\u0430"
    ],
    "name:spa_x_preferred":[
        "Cachoeira"
    ],
    "name:swe_x_preferred":[
        "Cachoeira"
    ],
    "name:vie_x_preferred":[
        "Cachoeira"
    ],
    "name:vol_x_preferred":[
        "Cachoeira"
    ],
    "name:war_x_preferred":[
        "Cachoeira"
    ],
    "name:zho_x_preferred":[
        "\u5361\u8212\u57c3\u62c9"
    ],
    "wof:name":"Cachoeira",
    "wof:placetype":"locality"
},
  "geometry": {"coordinates":[-39.88333,-4.78333],"type":"Point"}
}