{
  "type": "Feature",
  "properties": {
    "gn:admin1_code":"6",
    "gn:admin2_code":"2312205.0",
    "gn:asciiname":"Cachoeira",
    "gn:country_code":"BR",
    "gn:dem":478,
    "gn:feature_class":"P",
    "gn:feature_code":"PPL",
    "gn:name":"Cachoeira",
    "gn:population":0,
    "gn:timezone":"America/Fortaleza",
    "iso:country":"BR",
    "wof:name":"Cachoeira",
    "wof:placetype":"locality"
},
  "geometry": {"coordinates":[-39.88333,-4.78333],"type":"Point"}
}