{
  "type": "Feature",
  "properties": {
    "gn:admin1_code":"20",
    "gn:admin2_code":"2207009.0",
    "gn:asciiname":"Pe da Ladeira",
    "gn:country_code":"BR",
    "gn:dem":269,
    "gn:feature_class":"P",
    "gn:feature_code":"PPL",
    "gn:name":"P\u00e9 da Ladeira",
    "gn:population":0,
    "gn:timezone":"America/Fortaleza",
    "iso:country":"BR",
    "wof:name":"Pe da Ladeira",
    "wof:placetype":"locality"
},
  "geometry": {"coordinates":[-41.98333,-6.88333],"type":"Point"}
}