{
  "type": "Feature",
  "properties": {
    "gn:admin1_code":"15",
    "gn:admin2_code":"3103504.0",
    "gn:asciiname":"Cascao",
    "gn:country_code":"BR",
    "gn:dem":637,
    "gn:feature_class":"P",
    "gn:feature_code":"PPL",
    "gn:name":"Casc\u00e3o",
    "gn:population":0,
    "gn:timezone":"America/Sao_Paulo",
    "iso:country":"BR",
    "name:por_x_preferred":[
        "Casc\u00e3o"
    ],
    "wof:name":"Cascao",
    "wof:placetype":"locality"
},
  "geometry": {"coordinates":[-48.16667,-18.46667],"type":"Point"}
}