{
  "type": "Feature",
  "properties": {
    "gn:admin1_code":"29",
    "gn:admin2_code":"5211909.0",
    "gn:asciiname":"Sao Pedro",
    "gn:country_code":"BR",
    "gn:dem":937,
    "gn:feature_class":"P",
    "gn:feature_code":"PPL",
    "gn:name":"S\u00e3o Pedro",
    "gn:population":0,
    "gn:timezone":"America/Sao_Paulo",
    "iso:country":"BR",
    "name:por_x_preferred":[
        "S\u00e3o Pedro"
    ],
    "wof:name":"Sao Pedro",
    "wof:placetype":"locality"
},
  "geometry": {"coordinates":[-51.91667,-17.45],"type":"Point"}
}