{
  "type": "Feature",
  "properties": {
    "gn:admin1_code":"5",
    "gn:admin2_code":"2918001.0",
    "gn:asciiname":"Esperancinha",
    "gn:country_code":"BR",
    "gn:dem":521,
    "gn:feature_class":"P",
    "gn:feature_code":"PPL",
    "gn:name":"Esperancinha",
    "gn:population":0,
    "gn:timezone":"America/Bahia",
    "iso:country":"BR",
    "wof:name":"Esperancinha",
    "wof:placetype":"locality"
},
  "geometry": {"coordinates":[-40.25,-13.73333],"type":"Point"}
}