{
  "type": "Feature",
  "properties": {
    "gn:admin1_code":"26",
    "gn:admin2_code":"4205803.0",
    "gn:asciiname":"Barranco",
    "gn:country_code":"BR",
    "gn:dem":83,
    "gn:feature_class":"P",
    "gn:feature_code":"PPL",
    "gn:name":"Barranco",
    "gn:population":0,
    "gn:timezone":"America/Sao_Paulo",
    "iso:country":"BR",
    "name:ceb_x_preferred":[
        "Barranco"
    ],
    "name:deu_x_preferred":[
        "Barranco"
    ],
    "name:glg_x_preferred":[
        "Barranco"
    ],
    "name:nds_x_preferred":[
        "Barranco"
    ],
    "name:por_x_preferred":[
        "Barranco"
    ],
    "name:spa_x_preferred":[
        "Barranco"
    ],
    "name:swe_x_preferred":[
        "Barranco"
    ],
    "wof:name":"Barranco",
    "wof:placetype":"locality"
},
  "geometry": {"coordinates":[-48.76316,-26.11167],"type":"Point"}
}