{
  "type": "Feature",
  "properties": {
    "gn:admin1_code":"16.0",
    "gn:admin2_code":"1506807.0",
    "gn:asciiname":"Vila Brasil",
    "gn:country_code":"BR",
    "gn:dem":20,
    "gn:feature_class":"P",
    "gn:feature_code":"PPL",
    "gn:name":"Vila Brasil",
    "gn:population":0,
    "gn:timezone":"America/Santarem",
    "iso:country":"BR",
    "name:por_x_preferred":[
        "Vila Brasil"
    ],
    "wof:name":"Vila Brasil",
    "wof:placetype":"locality"
},
  "geometry": {"coordinates":[-55.2289,-2.39595],"type":"Point"}
}