{
  "type": "Feature",
  "properties": {
    "gn:admin1_code":"27.0",
    "gn:admin2_code":"3514809.0",
    "gn:asciiname":"Vargens",
    "gn:country_code":"BR",
    "gn:dem":147,
    "gn:feature_class":"P",
    "gn:feature_code":"PPLL",
    "gn:name":"Vargens",
    "gn:population":0,
    "gn:timezone":"America/Sao_Paulo",
    "iso:country":"BR",
    "name:por_x_preferred":[
        "Vargens"
    ],
    "wof:name":"Vargens",
    "wof:placetype":"locality"
},
  "geometry": {"coordinates":[-48.38081,-24.52369],"type":"Point"}
}