{
  "type": "Feature",
  "properties": {
    "gn:admin1_code":"20",
    "gn:admin2_code":"2207009.0",
    "gn:asciiname":"Cajazeiras (2)",
    "gn:country_code":"BR",
    "gn:dem":235,
    "gn:feature_class":"P",
    "gn:feature_code":"PPL",
    "gn:name":"Cajazeiras (2)",
    "gn:population":0,
    "gn:timezone":"America/Fortaleza",
    "iso:country":"BR",
    "wof:name":"Cajazeiras (2)",
    "wof:placetype":"locality"
},
  "geometry": {"coordinates":[-42.05,-6.86667],"type":"Point"}
}