{
  "type": "Feature",
  "properties": {
    "gn:admin1_code":"2",
    "gn:admin2_code":"2708956.0",
    "gn:asciiname":"Branquinha",
    "gn:country_code":"BR",
    "gn:dem":244,
    "gn:feature_class":"P",
    "gn:feature_code":"PPL",
    "gn:name":"Branquinha",
    "gn:population":0,
    "gn:timezone":"America/Maceio",
    "iso:country":"BR",
    "name:bpy_x_preferred":[
        "\u09ac\u09cd\u09b0\u09be\u09a8\u0995\u09c1\u0987\u09a8\u09b9\u09be"
    ],
    "name:ceb_x_preferred":[
        "Branquinha"
    ],
    "name:epo_x_preferred":[
        "Branquinha"
    ],
    "name:eus_x_preferred":[
        "Branquinha"
    ],
    "name:fra_x_preferred":[
        "Branquinha"
    ],
    "name:hye_x_preferred":[
        "\u0532\u0580\u0561\u0576\u056f\u056b\u0576\u056b\u0561"
    ],
    "name:ind_x_preferred":[
        "Branquinha"
    ],
    "name:ita_x_preferred":[
        "Branquinha"
    ],
    "name:kat_x_preferred":[
        "\u10d1\u10e0\u10d0\u10dc\u10d9\u10d8\u10dc\u10d8\u10d0"
    ],
    "name:mlg_x_preferred":[
        "Branquinha"
    ],
    "name:nld_x_preferred":[
        "Branquinha"
    ],
    "name:nor_x_preferred":[
        "Branquinha"
    ],
    "name:por_x_preferred":[
        "Branquinha"
    ],
    "name:ron_x_preferred":[
        "Branquinha"
    ],
    "name:rus_x_preferred":[
        "\u0411\u0440\u0430\u043d\u043a\u0438\u043d\u044c\u044f"
    ],
    "name:swe_x_preferred":[
        "Branquinha"
    ],
    "name:vie_x_preferred":[
        "Branquinha"
    ],
    "name:vol_x_preferred":[
        "Branquinha"
    ],
    "name:war_x_preferred":[
        "Branquinha"
    ],
    "name:zho_x_preferred":[
        "\u5e03\u5170\u57fa\u5c3c\u4e9a"
    ],
    "wof:name":"Branquinha",
    "wof:placetype":"locality"
},
  "geometry": {"coordinates":[-37.63333,-9.38333],"type":"Point"}
}