{
  "type": "Feature",
  "properties": {
    "gn:admin1_code":"2",
    "gn:admin2_code":"2708956.0",
    "gn:asciiname":"Branquinha",
    "gn:country_code":"BR",
    "gn:dem":244,
    "gn:feature_class":"P",
    "gn:feature_code":"PPL",
    "gn:name":"Branquinha",
    "gn:population":0,
    "gn:timezone":"America/Maceio",
    "iso:country":"BR",
    "wof:name":"Branquinha",
    "wof:placetype":"locality"
},
  "geometry": {"coordinates":[-37.63333,-9.38333],"type":"Point"}
}