{
  "type": "Feature",
  "properties": {
    "gn:admin1_code":"11",
    "gn:admin2_code":"5003207.0",
    "gn:asciiname":"Taruma",
    "gn:country_code":"BR",
    "gn:dem":86,
    "gn:feature_class":"P",
    "gn:feature_code":"PPL",
    "gn:name":"Tarum\u00e1",
    "gn:population":0,
    "gn:timezone":"America/Campo_Grande",
    "iso:country":"BR",
    "name:ceb_x_preferred":[
        "Tarum\u00e3"
    ],
    "name:nld_x_preferred":[
        "Tarum\u00e3"
    ],
    "name:por_x_preferred":[
        "Tarum\u00e3"
    ],
    "name:sco_x_preferred":[
        "Taruma"
    ],
    "name:swe_x_preferred":[
        "Tarum\u00e3"
    ],
    "wof:name":"Taruma",
    "wof:placetype":"locality"
},
  "geometry": {"coordinates":[-57.21666999999999,-19.11667000000001],"type":"Point"}
}