{
  "type": "Feature",
  "properties": {
    "gn:gn_country":"BR",
    "gn:gn_fcode":"PPL",
    "gn:gn_pop":0,
    "iso:country":"BR",
    "name:bpy_x_preferred":[
        "\u0987\u09ae\u09bf\u0997\u09cd\u09b0\u09be\u09a8\u09cd\u099f\u09c7"
    ],
    "name:ceb_x_preferred":[
        "Imigrante"
    ],
    "name:epo_x_preferred":[
        "Imigrante"
    ],
    "name:eus_x_preferred":[
        "Imigrante"
    ],
    "name:fra_x_preferred":[
        "Imigrante"
    ],
    "name:ita_x_preferred":[
        "Imigrante"
    ],
    "name:kaz_x_preferred":[
        "\u0418\u043c\u0438\u0433\u0440\u0430\u043d\u0442\u0438"
    ],
    "name:mlg_x_preferred":[
        "Imigrante"
    ],
    "name:nld_x_preferred":[
        "Imigrante"
    ],
    "name:nor_x_preferred":[
        "Imigrante"
    ],
    "name:pol_x_preferred":[
        "Imigrante"
    ],
    "name:por_x_preferred":[
        "Imigrante"
    ],
    "name:ron_x_preferred":[
        "Imigrante"
    ],
    "name:rus_x_preferred":[
        "\u0418\u043c\u0438\u0433\u0440\u0430\u043d\u0442\u0438"
    ],
    "name:spa_x_preferred":[
        "Imigrante"
    ],
    "name:swe_x_preferred":[
        "Imigrante"
    ],
    "name:vie_x_preferred":[
        "Imigrante"
    ],
    "name:vol_x_preferred":[
        "Imigrante"
    ],
    "name:war_x_preferred":[
        "Imigrante"
    ],
    "name:zho_x_preferred":[
        "\u4f0a\u7c73\u683c\u5170\u8482"
    ],
    "qs_pg:aaroncc":"BR",
    "qs_pg:gn_country":"BR",
    "qs_pg:gn_fcode":"PPL",
    "qs_pg:gn_pop":0,
    "qs_pg:name":"Imigrante",
    "qs_pg:name_adm0":"Brasil",
    "qs_pg:name_adm1":"Rio Grande do Sul",
    "qs_pg:photos_9r":0,
    "qs_pg:photos_sr":0,
    "qs_pg:pop_sr":0,
    "qs_pg:qs_pg_placetype":"neighbourhood",
    "qs_pg:qs_pg_placetype_gp":"Suburb",
    "qs_pg:woe_adm0":23424768,
    "woe:adm0_id":23424768,
    "woe:name_adm0":"Brasil",
    "woe:name_adm1":"Rio Grande do Sul",
    "woe:placetype":"Suburb",
    "wof:name":"Imigrante",
    "wof:placetype":"neighbourhood"
},
  "geometry": {"coordinates":[-51.77694,-29.35528],"type":"Point"}
}