{
  "type": "Feature",
  "properties": {
    "gn:admin1_code":"26",
    "gn:admin2_code":"4210100.0",
    "gn:asciiname":"Sitio Darci Rodrigues",
    "gn:country_code":"BR",
    "gn:dem":857,
    "gn:feature_class":"P",
    "gn:feature_code":"PPL",
    "gn:name":"S\u00edtio Darci Rodrigues",
    "gn:population":0,
    "gn:timezone":"America/Sao_Paulo",
    "iso:country":"BR",
    "name:por_x_preferred":[
        "S\u00edtio Darci Rodrigues"
    ],
    "wof:name":"Sitio Darci Rodrigues",
    "wof:placetype":"locality"
},
  "geometry": {"coordinates":[-49.86600000000001,-26.1945],"type":"Point"}
}