{
  "type": "Feature",
  "properties": {
    "gn:admin1_code":"31",
    "gn:admin2_code":"1707009.0",
    "gn:asciiname":"Missoes",
    "gn:cc2":"BR",
    "gn:country_code":"BR",
    "gn:dem":599,
    "gn:feature_class":"P",
    "gn:feature_code":"PPL",
    "gn:name":"Miss\u00f5es",
    "gn:population":0,
    "gn:timezone":"America/Araguaina",
    "iso:country":"BR",
    "name:und_x_variant":[
        "Miss\u00e3o",
        "Miss\u00f5es"
    ],
    "wof:name":"Missoes",
    "wof:placetype":"locality"
},
  "geometry": {"coordinates":[-46.80333,-11.55194],"type":"Point"}
}