{
  "type": "Feature",
  "properties": {
    "gn:admin1_code":"8",
    "gn:admin2_code":"3200300.0",
    "gn:asciiname":"Sao Bento",
    "gn:country_code":"BR",
    "gn:dem":979,
    "gn:feature_class":"P",
    "gn:feature_code":"PPL",
    "gn:name":"S\u00e3o Bento",
    "gn:population":0,
    "gn:timezone":"America/Sao_Paulo",
    "iso:country":"BR",
    "name:por_x_preferred":[
        "S\u00e3o Bento"
    ],
    "wof:name":"Sao Bento",
    "wof:placetype":"locality"
},
  "geometry": {"coordinates":[-40.93333,-20.48333],"type":"Point"}
}