{
  "type": "Feature",
  "properties": {
    "gn:admin1_code":"15",
    "gn:admin2_code":"3127057.0",
    "gn:asciiname":"Jose Martins",
    "gn:country_code":"BR",
    "gn:dem":386,
    "gn:feature_class":"P",
    "gn:feature_code":"PPL",
    "gn:name":"Jos\u00e9 Martins",
    "gn:population":0,
    "gn:timezone":"America/Sao_Paulo",
    "iso:country":"BR",
    "name:por_x_preferred":[
        "Jos\u00e9 Martins"
    ],
    "wof:name":"Jose Martins",
    "wof:placetype":"locality"
},
  "geometry": {"coordinates":[-40.86667,-16.95],"type":"Point"}
}