{
  "type": "Feature",
  "properties": {
    "gn:admin1_code":"30",
    "gn:admin2_code":"2613909.0",
    "gn:asciiname":"Lajinha",
    "gn:country_code":"BR",
    "gn:dem":518,
    "gn:feature_class":"P",
    "gn:feature_code":"PPL",
    "gn:name":"Lajinha",
    "gn:population":0,
    "gn:timezone":"America/Recife",
    "iso:country":"BR",
    "name:bpy_x_preferred":[
        "\u09b2\u09be\u099c\u09bf\u09a8\u09b9\u09be"
    ],
    "name:ceb_x_preferred":[
        "Lajinha"
    ],
    "name:epo_x_preferred":[
        "Lajinha"
    ],
    "name:eus_x_preferred":[
        "Lajinha"
    ],
    "name:fra_x_preferred":[
        "Lajinha"
    ],
    "name:ita_x_preferred":[
        "Lajinha"
    ],
    "name:kat_x_preferred":[
        "\u10da\u10d0\u10df\u10d8\u10dc\u10d8\u10d0"
    ],
    "name:kaz_x_preferred":[
        "\u041b\u0430\u0436\u0438\u043d\u044c\u044f"
    ],
    "name:mlg_x_preferred":[
        "Lajinha"
    ],
    "name:nld_x_preferred":[
        "Lajinha"
    ],
    "name:nor_x_preferred":[
        "Lajinha"
    ],
    "name:pol_x_preferred":[
        "Lajinha"
    ],
    "name:por_x_preferred":[
        "Lajinha"
    ],
    "name:ron_x_preferred":[
        "Lajinha"
    ],
    "name:rus_x_preferred":[
        "\u041b\u0430\u0436\u0438\u043d\u044c\u044f"
    ],
    "name:spa_x_preferred":[
        "Lajinha"
    ],
    "name:swe_x_preferred":[
        "Lajinha"
    ],
    "name:vie_x_preferred":[
        "Lajinha"
    ],
    "name:vol_x_preferred":[
        "Lajinha"
    ],
    "name:war_x_preferred":[
        "Lajinha"
    ],
    "name:zho_x_preferred":[
        "\u62c9\u65e5\u5c3c\u4e9a"
    ],
    "wof:name":"Lajinha",
    "wof:placetype":"locality"
},
  "geometry": {"coordinates":[-38.43333,-7.85],"type":"Point"}
}