{
  "type": "Feature",
  "properties": {
    "gn:admin1_code":"4",
    "gn:admin2_code":"1303601.0",
    "gn:asciiname":"Jauari",
    "gn:country_code":"BR",
    "gn:dem":46,
    "gn:feature_class":"P",
    "gn:feature_code":"PPL",
    "gn:name":"Jauari",
    "gn:population":0,
    "gn:timezone":"America/Manaus",
    "iso:country":"BR",
    "name:por_x_preferred":[
        "Janari"
    ],
    "name:por_x_variant":[
        "Jauari",
        "R\u00edo Jauar\u00ed"
    ],
    "wof:name":"Jauari",
    "wof:placetype":"locality"
},
  "geometry": {"coordinates":[-64.2256,-0.32478],"type":"Point"}
}