{
  "type": "Feature",
  "properties": {
    "gn:admin1_code":"18.0",
    "gn:admin2_code":"4101606.0",
    "gn:asciiname":"Sitio Sao Judas Tadeu",
    "gn:country_code":"BR",
    "gn:dem":822,
    "gn:feature_class":"P",
    "gn:feature_code":"PPL",
    "gn:name":"S\u00edtio S\u00e3o Judas Tadeu",
    "gn:population":0,
    "gn:timezone":"America/Sao_Paulo",
    "iso:country":"BR",
    "name:por_x_preferred":[
        "S\u00edtio S\u00e3o Judas Tadeu"
    ],
    "wof:name":"Sitio Sao Judas Tadeu",
    "wof:placetype":"locality"
},
  "geometry": {"coordinates":[-50.14514000000001,-23.99374],"type":"Point"}
}