{
  "type": "Feature",
  "properties": {
    "gn:admin1_code":"13",
    "gn:admin2_code":"2112209.0",
    "gn:asciiname":"Onca",
    "gn:country_code":"BR",
    "gn:dem":100,
    "gn:feature_class":"P",
    "gn:feature_code":"PPL",
    "gn:name":"On\u00e7a",
    "gn:population":0,
    "gn:timezone":"America/Fortaleza",
    "iso:country":"BR",
    "wof:name":"Onca",
    "wof:placetype":"locality"
},
  "geometry": {"coordinates":[-42.88333,-5.18333],"type":"Point"}
}