{
  "type": "Feature",
  "properties": {
    "gn:admin1_code":"13",
    "gn:admin2_code":"2102200.0",
    "gn:asciiname":"Cacimba I",
    "gn:country_code":"BR",
    "gn:dem":110,
    "gn:feature_class":"P",
    "gn:feature_code":"PPL",
    "gn:name":"Cacimba I",
    "gn:population":0,
    "gn:timezone":"America/Fortaleza",
    "iso:country":"BR",
    "wof:name":"Cacimba I",
    "wof:placetype":"locality"
},
  "geometry": {"coordinates":[-43.04139,-3.94167],"type":"Point"}
}