{
  "type": "Feature",
  "properties": {
    "gn:admin1_code":"18.0",
    "gn:admin2_code":"4112900.0",
    "gn:asciiname":"Sitio Lidia Esperti",
    "gn:country_code":"BR",
    "gn:dem":504,
    "gn:feature_class":"P",
    "gn:feature_code":"PPL",
    "gn:name":"S\u00edtio L\u00eddia Esperti",
    "gn:population":0,
    "gn:timezone":"America/Sao_Paulo",
    "iso:country":"BR",
    "name:por_x_preferred":[
        "S\u00edtio L\u00eddia Esperti"
    ],
    "wof:name":"Sitio Lidia Esperti",
    "wof:placetype":"locality"
},
  "geometry": {"coordinates":[-50.23949,-23.42181],"type":"Point"}
}