{
  "type": "Feature",
  "properties": {
    "gn:admin1_code":"8",
    "gn:admin2_code":"3202207.0",
    "gn:asciiname":"Valao Grande",
    "gn:country_code":"BR",
    "gn:dem":46,
    "gn:feature_class":"P",
    "gn:feature_code":"PPL",
    "gn:name":"Val\u00e3o Grande",
    "gn:population":0,
    "gn:timezone":"America/Sao_Paulo",
    "iso:country":"BR",
    "name:por_x_preferred":[
        "Val\u00e3o Grande"
    ],
    "wof:name":"Valao Grande",
    "wof:placetype":"locality"
},
  "geometry": {"coordinates":[-40.41667,-19.93333],"type":"Point"}
}