{
  "type": "Feature",
  "properties": {
    "gn:admin1_code":"18.0",
    "gn:admin2_code":"4126603.0",
    "gn:asciiname":"Sitio Benicio Bardarini",
    "gn:country_code":"BR",
    "gn:dem":672,
    "gn:feature_class":"P",
    "gn:feature_code":"PPL",
    "gn:name":"S\u00edtio Ben\u00edcio Bardarini",
    "gn:population":0,
    "gn:timezone":"America/Sao_Paulo",
    "iso:country":"BR",
    "name:por_x_preferred":[
        "S\u00edtio Ben\u00edcio Bardarini"
    ],
    "wof:name":"Sitio Benicio Bardarini",
    "wof:placetype":"locality"
},
  "geometry": {"coordinates":[-49.8452,-23.6937],"type":"Point"}
}