{
  "type": "Feature",
  "properties": {
    "gn:admin1_code":"21",
    "gn:admin2_code":"3300803.0",
    "gn:asciiname":"Patis",
    "gn:country_code":"BR",
    "gn:dem":265,
    "gn:feature_class":"P",
    "gn:feature_code":"PPL",
    "gn:name":"Patis",
    "gn:population":0,
    "gn:timezone":"America/Sao_Paulo",
    "iso:country":"BR",
    "name:por_x_preferred":[
        "Patis"
    ],
    "wof:name":"Patis",
    "wof:placetype":"locality"
},
  "geometry": {"coordinates":[-42.63333,-22.61667000000001],"type":"Point"}
}