{
  "type": "Feature",
  "properties": {
    "gn:admin1_code":"13",
    "gn:admin2_code":"2100808.0",
    "gn:asciiname":"Lagoa do Cigano",
    "gn:country_code":"BR",
    "gn:dem":78,
    "gn:feature_class":"P",
    "gn:feature_code":"PPL",
    "gn:name":"Lagoa do Cigano",
    "gn:population":0,
    "gn:timezone":"America/Fortaleza",
    "iso:country":"BR",
    "wof:name":"Lagoa do Cigano",
    "wof:placetype":"locality"
},
  "geometry": {"coordinates":[-43.08083,-3.48278],"type":"Point"}
}