{
  "type": "Feature",
  "properties": {
    "gn:admin1_code":"5",
    "gn:admin2_code":"2923407.0",
    "gn:asciiname":"Picado do Zuza",
    "gn:cc2":"BR",
    "gn:country_code":"BR",
    "gn:dem":534,
    "gn:feature_class":"P",
    "gn:feature_code":"PPL",
    "gn:name":"Picado do Zuza",
    "gn:population":0,
    "gn:timezone":"America/Bahia",
    "iso:country":"BR",
    "name:und_x_variant":[
        "Picada do Zuza",
        "Picado do Zuza"
    ],
    "wof:name":"Picado do Zuza",
    "wof:placetype":"locality"
},
  "geometry": {"coordinates":[-43.13333,-14.25],"type":"Point"}
}