{
  "type": "Feature",
  "properties": {
    "gn:admin1_code":"18",
    "gn:admin2_code":"4126678.0",
    "gn:asciiname":"Lagoa",
    "gn:country_code":"BR",
    "gn:dem":846,
    "gn:feature_class":"P",
    "gn:feature_code":"PPL",
    "gn:name":"Lagoa",
    "gn:population":0,
    "gn:timezone":"America/Sao_Paulo",
    "iso:country":"BR",
    "wof:name":"Lagoa",
    "wof:placetype":"locality"
},
  "geometry": {"coordinates":[-51.11667,-23.83333],"type":"Point"}
}