{
  "type": "Feature",
  "properties": {
    "gn:admin1_code":"18.0",
    "gn:admin2_code":"4114302.0",
    "gn:asciiname":"Sitio Antonio Aires",
    "gn:country_code":"BR",
    "gn:dem":993,
    "gn:feature_class":"P",
    "gn:feature_code":"PPL",
    "gn:name":"S\u00edtio Ant\u00f4nio Aires",
    "gn:population":0,
    "gn:timezone":"America/Sao_Paulo",
    "iso:country":"BR",
    "name:por_x_preferred":[
        "S\u00edtio Ant\u00f4nio Aires"
    ],
    "wof:name":"Sitio Antonio Aires",
    "wof:placetype":"locality"
},
  "geometry": {"coordinates":[-49.2672,-25.8206],"type":"Point"}
}