{
  "type": "Feature",
  "properties": {
    "gn:country":"BR",
    "gn:fcode":"PPL",
    "gn:population":5812,
    "iso:country":"BR",
    "name:bpy_x_preferred":[
        "\u0995\u09cd\u09b0\u09c1\u099c \u09a1\u09cb \u098f\u09b8\u09aa\u09bf\u09b0\u09bf\u099f\u09cb \u09b8\u09be\u09a8\u09cd\u099f\u09cb"
    ],
    "name:deu_x_preferred":[
        "Cruz do Esp\u00edrito Santo"
    ],
    "name:eng_x_preferred":[
        "Cruz do Esp\u00edrito Santo"
    ],
    "name:eus_x_preferred":[
        "Cruz do Esp\u00edrito Santo"
    ],
    "name:fra_x_preferred":[
        "Cruz do Esp\u00edrito Santo"
    ],
    "name:hun_x_preferred":[
        "Cruz do Esp\u00edrito Santo"
    ],
    "name:hye_x_preferred":[
        "\u053f\u0580\u0578\u0582\u057d \u0564\u0578\u0582 \u0537\u057d\u057a\u056b\u0580\u056b\u057f\u0578\u0582 \u054d\u0561\u0576\u057f\u0578\u0582"
    ],
    "name:ita_x_preferred":[
        "Cruz do Esp\u00edrito Santo"
    ],
    "name:kat_x_preferred":[
        "\u10d9\u10e0\u10e3\u10e1-\u10d3\u10e3-\u10d4\u10e1\u10de\u10d8\u10e0\u10d8\u10e2\u10e3-\u10e1\u10d0\u10dc\u10e2\u10e3"
    ],
    "name:kaz_x_preferred":[
        "\u041a\u0440\u0443\u0441-\u0434\u0443-\u042d\u0441\u043f\u0438\u0440\u0438\u0442\u0443-\u0421\u0430\u043d\u0442\u0443"
    ],
    "name:nan_x_preferred":[
        "Cruz do Esp\u00edrito Santo"
    ],
    "name:nld_x_preferred":[
        "Cruz do Esp\u00edrito Santo"
    ],
    "name:nob_x_preferred":[
        "Cruz do Esp\u00edrito Santo"
    ],
    "name:por_x_preferred":[
        "Cruz do Esp\u00edrito Santo"
    ],
    "name:ron_x_preferred":[
        "Cruz do Esp\u00edrito Santo"
    ],
    "name:rus_x_preferred":[
        "\u041a\u0440\u0443\u0441-\u0434\u0443-\u042d\u0441\u043f\u0438\u0440\u0438\u0442\u0443-\u0421\u0430\u043d\u0442\u0443"
    ],
    "name:und_x_variant":[
        "Espirito Santo"
    ],
    "name:vie_x_preferred":[
        "Cruz do Esp\u00edrito Santo"
    ],
    "name:vol_x_preferred":[
        "Cruz do Esp\u00edrito Santo"
    ],
    "name:war_x_preferred":[
        "Cruz do Esp\u00edrito Santo"
    ],
    "name:zho_x_preferred":[
        "\u514b\u9c81\u65af-\u675c\u5723\u57c3\u65af\u76ae\u91cc\u56fe"
    ],
    "qs_pg:aaroncc":"BR",
    "qs_pg:gn_country":"BR",
    "qs_pg:gn_fcode":"PPL",
    "qs_pg:gn_pop":5812,
    "qs_pg:name":"Maguari",
    "qs_pg:name_adm0":"Brasil",
    "qs_pg:name_adm1":"Para\u00edba",
    "qs_pg:photos_9k":1,
    "qs_pg:photos_9r":1,
    "qs_pg:photos_all":2,
    "qs_pg:photos_sr":0,
    "qs_pg:pop_sr":5,
    "qs_pg:qs_pg_placetype":"locality",
    "qs_pg:qs_pg_placetype_gp":"Town",
    "qs_pg:woe_adm0":23424768,
    "woe:adm0_id":23424768,
    "woe:name_adm0":"Brasil",
    "woe:name_adm1":"Para\u00edba",
    "woe:placetype":"Town",
    "wof:name":"Maguari",
    "wof:placetype":"locality",
    "wof:population":5812
},
  "geometry": {"coordinates":[-35.08639,-7.14],"type":"Point"}
}