{
  "type": "Feature",
  "properties": {
    "gn:admin1_code":"11",
    "gn:admin2_code":"5003207.0",
    "gn:asciiname":"Bonfim",
    "gn:country_code":"BR",
    "gn:dem":175,
    "gn:feature_class":"P",
    "gn:feature_code":"PPL",
    "gn:name":"Bonfim",
    "gn:population":0,
    "gn:timezone":"America/Campo_Grande",
    "iso:country":"BR",
    "wof:name":"Bonfim",
    "wof:placetype":"locality"
},
  "geometry": {"coordinates":[-57.46666999999999,-18.26667],"type":"Point"}
}