{
  "type": "Feature",
  "properties": {
    "gn:admin1_code":"31",
    "gn:admin2_code":"1715705.0",
    "gn:asciiname":"Sao Francisco",
    "gn:country_code":"BR",
    "gn:dem":185,
    "gn:feature_class":"P",
    "gn:feature_code":"PPL",
    "gn:name":"S\u00e3o Francisco",
    "gn:population":0,
    "gn:timezone":"America/Araguaina",
    "iso:country":"BR",
    "wof:name":"Sao Francisco",
    "wof:placetype":"locality"
},
  "geometry": {"coordinates":[-47.95,-7.78333],"type":"Point"}
}