{
  "type": "Feature",
  "properties": {
    "gn:admin1_code":"18.0",
    "gn:admin2_code":"4124301.0",
    "gn:asciiname":"Sitio Adelino G. Ribeiro",
    "gn:country_code":"BR",
    "gn:dem":732,
    "gn:feature_class":"P",
    "gn:feature_code":"PPL",
    "gn:name":"S\u00edtio Adelino G. Ribeiro",
    "gn:population":0,
    "gn:timezone":"America/Sao_Paulo",
    "iso:country":"BR",
    "name:por_x_preferred":[
        "S\u00edtio Adelino G. Ribeiro"
    ],
    "wof:name":"Sitio Adelino G. Ribeiro",
    "wof:placetype":"locality"
},
  "geometry": {"coordinates":[-50.661,-23.53389],"type":"Point"}
}