{
  "type": "Feature",
  "properties": {
    "gn:admin1_code":"18.0",
    "gn:admin2_code":"4109500.0",
    "gn:asciiname":"Sitio Bernardo Sebo",
    "gn:country_code":"BR",
    "gn:dem":20,
    "gn:feature_class":"P",
    "gn:feature_code":"PPL",
    "gn:name":"S\u00edtio Bernardo Sebo",
    "gn:population":0,
    "gn:timezone":"America/Sao_Paulo",
    "iso:country":"BR",
    "name:por_x_preferred":[
        "S\u00edtio Bernardo Sebo"
    ],
    "wof:name":"Sitio Bernardo Sebo",
    "wof:placetype":"locality"
},
  "geometry": {"coordinates":[-48.55273,-25.23563],"type":"Point"}
}