{
  "type": "Feature",
  "properties": {
    "gn:admin1_code":"18",
    "gn:admin2_code":"4121208.0",
    "gn:asciiname":"Sitio Aleixo Smoqivcz",
    "gn:country_code":"BR",
    "gn:dem":813,
    "gn:feature_class":"P",
    "gn:feature_code":"PPL",
    "gn:name":"S\u00edtio Aleixo Smoqivcz",
    "gn:population":0,
    "gn:timezone":"America/Sao_Paulo",
    "iso:country":"BR",
    "name:por_x_preferred":[
        "S\u00edtio Aleixo Smoqivcz"
    ],
    "wof:name":"Sitio Aleixo Smoqivcz",
    "wof:placetype":"locality"
},
  "geometry": {"coordinates":[-49.53333,-25.935],"type":"Point"}
}