{
  "type": "Feature",
  "properties": {
    "gn:admin1_code":"06",
    "gn:admin2_code":"2305605.0",
    "gn:asciiname":"Morada Nova (1)",
    "gn:country_code":"BR",
    "gn:dem":317,
    "gn:feature_class":"P",
    "gn:feature_code":"PPL",
    "gn:name":"Morada Nova (1)",
    "gn:population":0,
    "gn:timezone":"America/Fortaleza",
    "iso:country":"BR",
    "wof:name":"Morada Nova (1)",
    "wof:placetype":"locality"
},
  "geometry": {"coordinates":[-40.48333,-5.36667],"type":"Point"}
}