{
  "type": "Feature",
  "properties": {
    "gn:admin1_code":"20",
    "gn:admin2_code":"2201150.0",
    "gn:asciiname":"Malica",
    "gn:country_code":"BR",
    "gn:dem":384,
    "gn:feature_class":"P",
    "gn:feature_code":"PPL",
    "gn:name":"Mali\u00e7a",
    "gn:population":0,
    "gn:timezone":"America/Fortaleza",
    "iso:country":"BR",
    "wof:name":"Malica",
    "wof:placetype":"locality"
},
  "geometry": {"coordinates":[-45.23333,-7.98333],"type":"Point"}
}