{
  "type": "Feature",
  "properties": {
    "gn:admin1_code":"13",
    "gn:admin2_code":"2111904.0",
    "gn:asciiname":"Pesqueiro",
    "gn:country_code":"BR",
    "gn:dem":276,
    "gn:feature_class":"P",
    "gn:feature_code":"PPL",
    "gn:name":"Pesqueiro",
    "gn:population":0,
    "gn:timezone":"America/Fortaleza",
    "iso:country":"BR",
    "wof:name":"Pesqueiro",
    "wof:placetype":"locality"
},
  "geometry": {"coordinates":[-44.33333,-6.48333],"type":"Point"}
}