{
  "type": "Feature",
  "properties": {
    "gn:admin1_code":"23",
    "gn:admin2_code":"4308201.0",
    "gn:asciiname":"Linha Sessenta",
    "gn:country_code":"BR",
    "gn:dem":763,
    "gn:feature_class":"P",
    "gn:feature_code":"PPL",
    "gn:name":"Linha Sessenta",
    "gn:population":0,
    "gn:timezone":"America/Sao_Paulo",
    "iso:country":"BR",
    "name:por_x_preferred":[
        "Linha Sessenta"
    ],
    "name:por_x_variant":[
        "Linha 60"
    ],
    "wof:name":"Linha Sessenta",
    "wof:placetype":"locality"
},
  "geometry": {"coordinates":[-51.2169,-29.0816],"type":"Point"}
}