{
  "type": "Feature",
  "properties": {
    "gn:admin1_code":"27",
    "gn:admin2_code":"3541307.0",
    "gn:asciiname":"Porto Tibirica",
    "gn:cc2":"BR",
    "gn:country_code":"BR",
    "gn:dem":297,
    "gn:feature_class":"P",
    "gn:feature_code":"PPL",
    "gn:name":"P\u00f4rto Tibiri\u00e7\u00e1",
    "gn:population":0,
    "gn:timezone":"America/Campo_Grande",
    "iso:country":"BR",
    "name:und_x_variant":[
        "Tibiri\u00e7a",
        "P\u00f4rto Tibiri\u00e7\u00e1"
    ],
    "wof:name":"Porto Tibirica",
    "wof:placetype":"locality"
},
  "geometry": {"coordinates":[-52.16667,-21.81667],"type":"Point"}
}