{
  "type": "Feature",
  "properties": {
    "gn:admin1_code":"17",
    "gn:admin2_code":"2504801.0",
    "gn:asciiname":"Mata Burro",
    "gn:country_code":"BR",
    "gn:dem":252,
    "gn:feature_class":"P",
    "gn:feature_code":"PPL",
    "gn:name":"Mata Burro",
    "gn:population":0,
    "gn:timezone":"America/Fortaleza",
    "iso:country":"BR",
    "wof:name":"Mata Burro",
    "wof:placetype":"locality"
},
  "geometry": {"coordinates":[-37.96667,-7.08333],"type":"Point"}
}