{
  "type": "Feature",
  "properties": {
    "gn:admin1_code":"15.0",
    "gn:admin2_code":"3147303.0",
    "gn:asciiname":"Carneiros",
    "gn:country_code":"BR",
    "gn:dem":907,
    "gn:feature_class":"P",
    "gn:feature_code":"PPLL",
    "gn:name":"Carneiros",
    "gn:population":0,
    "gn:timezone":"America/Sao_Paulo",
    "iso:country":"BR",
    "name:por_x_preferred":[
        "Carneiros"
    ],
    "wof:name":"Carneiros",
    "wof:placetype":"locality"
},
  "geometry": {"coordinates":[-45.7455,-22.5283],"type":"Point"}
}