{
  "type": "Feature",
  "properties": {
    "gn:admin1_code":"30",
    "gn:admin2_code":"2613008.0",
    "gn:asciiname":"Caiana",
    "gn:country_code":"BR",
    "gn:dem":613,
    "gn:feature_class":"P",
    "gn:feature_code":"PPL",
    "gn:name":"Caiana",
    "gn:population":0,
    "gn:timezone":"America/Recife",
    "iso:country":"BR",
    "wof:name":"Caiana",
    "wof:placetype":"locality"
},
  "geometry": {"coordinates":[-36.38333,-8.46667],"type":"Point"}
}