{
  "type": "Feature",
  "properties": {
    "gn:admin1_code":"30",
    "gn:admin2_code":"2613008.0",
    "gn:asciiname":"Caiana",
    "gn:country_code":"BR",
    "gn:dem":613,
    "gn:feature_class":"P",
    "gn:feature_code":"PPL",
    "gn:name":"Caiana",
    "gn:population":0,
    "gn:timezone":"America/Recife",
    "iso:country":"BR",
    "name:bpy_x_preferred":[
        "\u0995\u09be\u0987\u09af\u09bc\u09be\u09a8\u09be"
    ],
    "name:ceb_x_preferred":[
        "Caiana"
    ],
    "name:epo_x_preferred":[
        "Caiana"
    ],
    "name:eus_x_preferred":[
        "Caiana"
    ],
    "name:fra_x_preferred":[
        "Caiana"
    ],
    "name:ita_x_preferred":[
        "Caiana"
    ],
    "name:kat_x_preferred":[
        "\u10d9\u10d0\u10d8\u10d0\u10dc\u10d0"
    ],
    "name:kaz_x_preferred":[
        "\u041a\u0430\u044f\u043d\u0430"
    ],
    "name:mlg_x_preferred":[
        "Caiana"
    ],
    "name:nld_x_preferred":[
        "Caiana"
    ],
    "name:nor_x_preferred":[
        "Caiana"
    ],
    "name:pol_x_preferred":[
        "Caiana"
    ],
    "name:por_x_preferred":[
        "Caiana"
    ],
    "name:ron_x_preferred":[
        "Caiana"
    ],
    "name:rus_x_preferred":[
        "\u041a\u0430\u044f\u043d\u0430"
    ],
    "name:swe_x_preferred":[
        "Caiana"
    ],
    "name:vie_x_preferred":[
        "Caiana"
    ],
    "name:vol_x_preferred":[
        "Caiana"
    ],
    "name:war_x_preferred":[
        "Caiana"
    ],
    "name:zho_x_preferred":[
        "\u5361\u4e9a\u7eb3"
    ],
    "wof:name":"Caiana",
    "wof:placetype":"locality"
},
  "geometry": {"coordinates":[-36.38333,-8.46667],"type":"Point"}
}