{
  "type": "Feature",
  "properties": {
    "gn:admin1_code":"27.0",
    "gn:admin2_code":"3545308.0",
    "gn:asciiname":"Pirapora",
    "gn:country_code":"BR",
    "gn:dem":589,
    "gn:feature_class":"P",
    "gn:feature_code":"PPLL",
    "gn:name":"Pirapora",
    "gn:population":0,
    "gn:timezone":"America/Sao_Paulo",
    "iso:country":"BR",
    "name:bpy_x_preferred":[
        "\u09aa\u09bf\u09b0\u09be\u09aa\u09cb\u09b0\u09be"
    ],
    "name:ceb_x_preferred":[
        "Pirapora"
    ],
    "name:epo_x_preferred":[
        "Pirapora"
    ],
    "name:eus_x_preferred":[
        "Pirapora"
    ],
    "name:fra_x_preferred":[
        "Pirapora"
    ],
    "name:ita_x_preferred":[
        "Pirapora"
    ],
    "name:kat_x_preferred":[
        "\u10de\u10d8\u10e0\u10d0\u10de\u10dd\u10e0\u10d0"
    ],
    "name:kaz_x_preferred":[
        "\u041f\u0438\u0440\u0430\u043f\u043e\u0440\u0430"
    ],
    "name:mlg_x_preferred":[
        "Pirapora"
    ],
    "name:nld_x_preferred":[
        "Pirapora"
    ],
    "name:nor_x_preferred":[
        "Pirapora"
    ],
    "name:pol_x_preferred":[
        "Pirapora"
    ],
    "name:por_x_preferred":[
        "Pirapora"
    ],
    "name:ron_x_preferred":[
        "Pirapora"
    ],
    "name:rus_x_preferred":[
        "\u041f\u0438\u0440\u0430\u043f\u043e\u0440\u0430"
    ],
    "name:sco_x_preferred":[
        "Pirapora"
    ],
    "name:spa_x_preferred":[
        "Pirapora"
    ],
    "name:srp_x_preferred":[
        "\u041f\u0438\u0440\u0430\u043f\u043e\u0440\u0430"
    ],
    "name:swe_x_preferred":[
        "Pirapora"
    ],
    "name:vie_x_preferred":[
        "Pirapora"
    ],
    "name:vol_x_preferred":[
        "Pirapora"
    ],
    "name:war_x_preferred":[
        "Pirapora"
    ],
    "name:zho_x_preferred":[
        "\u76ae\u62c9\u6ce2\u62c9"
    ],
    "wof:name":"Pirapora",
    "wof:placetype":"locality"
},
  "geometry": {"coordinates":[-47.60087,-23.59991],"type":"Point"}
}