{
  "type": "Feature",
  "properties": {
    "gn:admin1_code":"27.0",
    "gn:admin2_code":"3545308.0",
    "gn:asciiname":"Pirapora",
    "gn:country_code":"BR",
    "gn:dem":589,
    "gn:feature_class":"P",
    "gn:feature_code":"PPLL",
    "gn:name":"Pirapora",
    "gn:population":0,
    "gn:timezone":"America/Sao_Paulo",
    "iso:country":"BR",
    "name:ara_x_preferred":[
        "\u0628\u064a\u0631\u0627\u0628\u0648\u0631\u0627"
    ],
    "name:ben_x_preferred":[
        "\u09aa\u09bf\u09b0\u09be\u09aa\u09cb\u09b0\u09be"
    ],
    "name:bpy_x_preferred":[
        "\u09aa\u09bf\u09b0\u09be\u09aa\u09cb\u09b0\u09be"
    ],
    "name:ceb_x_preferred":[
        "Pirapora"
    ],
    "name:ell_x_preferred":[
        "\u03a0\u03b9\u03c1\u03b1\u03c0\u03cc\u03c1\u03b1"
    ],
    "name:epo_x_preferred":[
        "Pirapora"
    ],
    "name:eus_x_preferred":[
        "Pirapora"
    ],
    "name:fas_x_preferred":[
        "\u067e\u06cc\u0631\u0627\u067e\u0648\u0631\u0627"
    ],
    "name:fra_x_preferred":[
        "Pirapora"
    ],
    "name:heb_x_preferred":[
        "\u05e4\u05d9\u05e8\u05e4\u05d5\u05e8\u05d4"
    ],
    "name:hin_x_preferred":[
        "\u092a\u093f\u0930\u093e\u092a\u094b\u0930\u093e"
    ],
    "name:ind_x_preferred":[
        "Pirapora"
    ],
    "name:ita_x_preferred":[
        "Pirapora"
    ],
    "name:jpn_x_preferred":[
        "\u30d4\u30e9\u30dd\u30e9"
    ],
    "name:kat_x_preferred":[
        "\u10de\u10d8\u10e0\u10d0\u10de\u10dd\u10e0\u10d0"
    ],
    "name:kaz_x_preferred":[
        "\u041f\u0438\u0440\u0430\u043f\u043e\u0440\u0430"
    ],
    "name:kor_x_preferred":[
        "\ud53c\ub77c\ud3ec\ub77c"
    ],
    "name:mlg_x_preferred":[
        "Pirapora"
    ],
    "name:nld_x_preferred":[
        "Pirapora"
    ],
    "name:nor_x_preferred":[
        "Pirapora"
    ],
    "name:pol_x_preferred":[
        "Pirapora"
    ],
    "name:por_x_preferred":[
        "Pirapora"
    ],
    "name:ron_x_preferred":[
        "Pirapora"
    ],
    "name:rus_x_preferred":[
        "\u041f\u0438\u0440\u0430\u043f\u043e\u0440\u0430"
    ],
    "name:sco_x_preferred":[
        "Pirapora"
    ],
    "name:spa_x_preferred":[
        "Pirapora"
    ],
    "name:srp_x_preferred":[
        "\u041f\u0438\u0440\u0430\u043f\u043e\u0440\u0430"
    ],
    "name:swe_x_preferred":[
        "Pirapora"
    ],
    "name:tur_x_preferred":[
        "Pirapora"
    ],
    "name:ukr_x_preferred":[
        "\u041f\u0456\u0440\u0430\u043f\u043e\u0440\u0430"
    ],
    "name:urd_x_preferred":[
        "\u067e\u0627\u0626\u06cc\u0631\u0627\u067e\u0648\u0631\u0627"
    ],
    "name:vie_x_preferred":[
        "Pirapora"
    ],
    "name:vol_x_preferred":[
        "Pirapora"
    ],
    "name:war_x_preferred":[
        "Pirapora"
    ],
    "name:zho_x_preferred":[
        "\u76ae\u62c9\u6ce2\u62c9"
    ],
    "wof:name":"Pirapora",
    "wof:placetype":"locality"
},
  "geometry": {"coordinates":[-47.60087,-23.59991],"type":"Point"}
}