{
  "type": "Feature",
  "properties": {
    "gn:admin1_code":"06",
    "gn:admin2_code":"2312205.0",
    "gn:asciiname":"Fazenda Aprazivel",
    "gn:country_code":"BR",
    "gn:dem":170,
    "gn:feature_class":"P",
    "gn:feature_code":"PPL",
    "gn:name":"Fazenda Apraz\u00edvel",
    "gn:population":0,
    "gn:timezone":"America/Fortaleza",
    "iso:country":"BR",
    "wof:name":"Fazenda Aprazivel",
    "wof:placetype":"locality"
},
  "geometry": {"coordinates":[-40.26667,-4.18333],"type":"Point"}
}