{
  "type": "Feature",
  "properties": {
    "gn:admin1_code":"8",
    "gn:admin2_code":"3203809.0",
    "gn:asciiname":"Babilonia",
    "gn:country_code":"BR",
    "gn:dem":542,
    "gn:feature_class":"P",
    "gn:feature_code":"PPL",
    "gn:name":"Babil\u00f4nia",
    "gn:population":0,
    "gn:timezone":"America/Sao_Paulo",
    "iso:country":"BR",
    "name:por_x_preferred":[
        "Babil\u00f4nia"
    ],
    "name:spa_x_preferred":[
        "Babilonia"
    ],
    "wof:name":"Babilonia",
    "wof:placetype":"locality"
},
  "geometry": {"coordinates":[-41.41667,-20.93333],"type":"Point"}
}