{
  "type": "Feature",
  "properties": {
    "gn:admin1_code":"22",
    "gn:admin2_code":"2404002.0",
    "gn:asciiname":"Pe da Serra do Geraldo",
    "gn:cc2":"BR",
    "gn:country_code":"BR",
    "gn:dem":247,
    "gn:feature_class":"P",
    "gn:feature_code":"PPL",
    "gn:name":"P\u00e9 da Serra do Geraldo",
    "gn:population":0,
    "gn:timezone":"America/Fortaleza",
    "iso:country":"BR",
    "name:und_x_variant":[
        "P\u00e9 da Serra",
        "P\u00e9 da Serra do Geraldo"
    ],
    "wof:name":"Pe da Serra do Geraldo",
    "wof:placetype":"locality"
},
  "geometry": {"coordinates":[-37.86667,-6.13333],"type":"Point"}
}