{
  "type": "Feature",
  "properties": {
    "gn:admin1_code":"5",
    "gn:admin2_code":"2927200.0",
    "gn:asciiname":"Brandao",
    "gn:country_code":"BR",
    "gn:dem":434,
    "gn:feature_class":"P",
    "gn:feature_code":"PPL",
    "gn:name":"Brand\u00e3o",
    "gn:population":0,
    "gn:timezone":"America/Bahia",
    "iso:country":"BR",
    "wof:name":"Brandao",
    "wof:placetype":"locality"
},
  "geometry": {"coordinates":[-40.58333,-12.28333],"type":"Point"}
}