{
  "type": "Feature",
  "properties": {
    "gn:admin1_code":"11",
    "gn:admin2_code":"5005400.0",
    "gn:asciiname":"Voluntario",
    "gn:country_code":"BR",
    "gn:dem":600,
    "gn:feature_class":"P",
    "gn:feature_code":"PPL",
    "gn:name":"Volunt\u00e1rio",
    "gn:population":0,
    "gn:timezone":"America/Campo_Grande",
    "iso:country":"BR",
    "wof:name":"Voluntario",
    "wof:placetype":"locality"
},
  "geometry": {"coordinates":[-55.61666999999999,-21.68333],"type":"Point"}
}