{
  "type": "Feature",
  "properties": {
    "gn:admin1_code":"20",
    "gn:admin2_code":"2208106.0",
    "gn:asciiname":"Cachoeira",
    "gn:country_code":"BR",
    "gn:dem":479,
    "gn:feature_class":"P",
    "gn:feature_code":"PPL",
    "gn:name":"Cachoeira",
    "gn:population":0,
    "gn:timezone":"America/Fortaleza",
    "iso:country":"BR",
    "wof:name":"Cachoeira",
    "wof:placetype":"locality"
},
  "geometry": {"coordinates":[-41.06667,-6.11667],"type":"Point"}
}