{
  "type": "Feature",
  "properties": {
    "gn:admin1_code":"18",
    "gn:admin2_code":"4107736.0",
    "gn:asciiname":"Colonia Sao Lourenco",
    "gn:country_code":"BR",
    "gn:dem":866,
    "gn:feature_class":"P",
    "gn:feature_code":"PPL",
    "gn:name":"Col\u00f4nia S\u00e3o Louren\u00e7o",
    "gn:population":0,
    "gn:timezone":"America/Sao_Paulo",
    "iso:country":"BR",
    "name:por_x_preferred":[
        "Col\u00f4nia S\u00e3o Louren\u00e7o"
    ],
    "wof:name":"Colonia Sao Lourenco",
    "wof:placetype":"locality"
},
  "geometry": {"coordinates":[-50.5909,-25.50861],"type":"Point"}
}