{
  "type": "Feature",
  "properties": {
    "gn:admin1_code":"4",
    "gn:admin2_code":"1301506.0",
    "gn:asciiname":"Vila Gomes",
    "gn:cc2":"BR",
    "gn:country_code":"BR",
    "gn:dem":179,
    "gn:feature_class":"P",
    "gn:feature_code":"PPL",
    "gn:name":"Vila Gomes",
    "gn:population":0,
    "gn:timezone":"America/Eirunepe",
    "iso:country":"BR",
    "name:und_x_variant":[
        "Villa Gomez",
        "Vila Gomez",
        "Vila Gomes"
    ],
    "wof:name":"Vila Gomes",
    "wof:placetype":"locality"
},
  "geometry": {"coordinates":[-70.11667,-7.58333],"type":"Point"}
}