{
  "type": "Feature",
  "properties": {
    "gn:admin1_code":"22",
    "gn:admin2_code":"2407500.0",
    "gn:asciiname":"Sao Miguel",
    "gn:country_code":"BR",
    "gn:dem":23,
    "gn:feature_class":"P",
    "gn:feature_code":"PPL",
    "gn:name":"S\u00e3o Miguel",
    "gn:population":12838,
    "gn:timezone":"America/Fortaleza",
    "iso:country":"BR",
    "wof:name":"Sao Miguel",
    "wof:placetype":"locality",
    "wof:population":12838
},
  "geometry": {"coordinates":[-35.36667,-5.46667],"type":"Point"}
}