{
  "type": "Feature",
  "properties": {
    "gn:admin1_code":"27",
    "gn:admin2_code":"3518305.0",
    "gn:asciiname":"Bairro Fregueisa da Escada",
    "gn:country_code":"BR",
    "gn:dem":591,
    "gn:feature_class":"P",
    "gn:feature_code":"PPL",
    "gn:name":"Bairro Fregueisa da Escada",
    "gn:population":0,
    "gn:timezone":"America/Sao_Paulo",
    "iso:country":"BR",
    "name:por_x_preferred":[
        "Bairro Fregueisa da Escada"
    ],
    "wof:name":"Bairro Fregueisa da Escada",
    "wof:placetype":"locality"
},
  "geometry": {"coordinates":[-46.0581,-23.3844],"type":"Point"}
}