{
  "type": "Feature",
  "properties": {
    "gn:admin1_code":"23",
    "gn:admin2_code":"4322103.0",
    "gn:asciiname":"Esquina Tucunduva",
    "gn:cc2":"BR",
    "gn:country_code":"BR",
    "gn:dem":229,
    "gn:feature_class":"P",
    "gn:feature_code":"PPL",
    "gn:name":"Esquina Tucunduva",
    "gn:population":0,
    "gn:timezone":"America/Sao_Paulo",
    "iso:country":"BR",
    "name:und_x_variant":[
        "Esquina Tudunduva",
        "Esquina Tucunduva"
    ],
    "wof:name":"Esquina Tucunduva",
    "wof:placetype":"locality"
},
  "geometry": {"coordinates":[-54.41667,-27.63333],"type":"Point"}
}