{
  "type": "Feature",
  "properties": {
    "gn:admin1_code":"23",
    "gn:admin2_code":"4322608.0",
    "gn:asciiname":"Serafim Schmidt",
    "gn:country_code":"BR",
    "gn:dem":652,
    "gn:feature_class":"P",
    "gn:feature_code":"PPL",
    "gn:name":"Serafim Schmidt",
    "gn:population":0,
    "gn:timezone":"America/Sao_Paulo",
    "iso:country":"BR",
    "wof:name":"Serafim Schmidt",
    "wof:placetype":"locality"
},
  "geometry": {"coordinates":[-52.38333,-29.36667000000001],"type":"Point"}
}