{
  "type": "Feature",
  "properties": {
    "gn:admin1_code":"18",
    "gn:admin2_code":"4122305.0",
    "gn:asciiname":"Sitio Estanislau Hitner",
    "gn:country_code":"BR",
    "gn:dem":832,
    "gn:feature_class":"P",
    "gn:feature_code":"PPL",
    "gn:name":"S\u00edtio Estanislau Hitner",
    "gn:population":0,
    "gn:timezone":"America/Sao_Paulo",
    "iso:country":"BR",
    "name:por_x_preferred":[
        "S\u00edtio Estanislau Hitner"
    ],
    "wof:name":"Sitio Estanislau Hitner",
    "wof:placetype":"locality"
},
  "geometry": {"coordinates":[-49.7427,-26.08291],"type":"Point"}
}