{
  "type": "Feature",
  "properties": {
    "gn:admin1_code":"15",
    "gn:admin2_code":"3136009.0",
    "gn:asciiname":"Safiro",
    "gn:country_code":"BR",
    "gn:dem":639,
    "gn:feature_class":"P",
    "gn:feature_code":"PPL",
    "gn:name":"Safiro",
    "gn:population":0,
    "gn:timezone":"America/Sao_Paulo",
    "iso:country":"BR",
    "name:por_x_preferred":[
        "Safiro"
    ],
    "wof:name":"Safiro",
    "wof:placetype":"locality"
},
  "geometry": {"coordinates":[-40.83333,-16.83333],"type":"Point"}
}