{
  "type": "Feature",
  "properties": {
    "gn:admin1_code":"23",
    "gn:admin2_code":"4303509.0",
    "gn:asciiname":"Capela Sao Pedro",
    "gn:country_code":"BR",
    "gn:dem":77,
    "gn:feature_class":"P",
    "gn:feature_code":"PPLL",
    "gn:name":"Capela S\u00e3o Pedro",
    "gn:population":0,
    "gn:timezone":"America/Sao_Paulo",
    "iso:country":"BR",
    "wof:name":"Capela Sao Pedro",
    "wof:placetype":"locality"
},
  "geometry": {"coordinates":[-52.0875,-30.86528],"type":"Point"}
}