{
  "type": "Feature",
  "properties": {
    "gn:admin1_code":"26",
    "gn:admin2_code":"4202453.0",
    "gn:asciiname":"Canto Grande",
    "gn:country_code":"BR",
    "gn:dem":7,
    "gn:feature_class":"P",
    "gn:feature_code":"PPL",
    "gn:name":"Canto Grande",
    "gn:population":0,
    "gn:timezone":"America/Sao_Paulo",
    "iso:country":"BR",
    "wof:name":"Canto Grande",
    "wof:placetype":"locality"
},
  "geometry": {"coordinates":[-48.49944,-27.19639],"type":"Point"}
}