{
  "type": "Feature",
  "properties": {
    "gn:admin1_code":"18.0",
    "gn:admin2_code":"4115705.0",
    "gn:asciiname":"Sitio do Camarao",
    "gn:country_code":"BR",
    "gn:dem":11,
    "gn:feature_class":"P",
    "gn:feature_code":"PPL",
    "gn:name":"S\u00edtio do Camar\u00e3o",
    "gn:population":0,
    "gn:timezone":"America/Sao_Paulo",
    "iso:country":"BR",
    "name:por_x_preferred":[
        "S\u00edtio do Camar\u00e3o"
    ],
    "wof:name":"Sitio do Camarao",
    "wof:placetype":"locality"
},
  "geometry": {"coordinates":[-48.5546,-25.7997],"type":"Point"}
}