{
  "type": "Feature",
  "properties": {
    "gn:admin1_code":"5.0",
    "gn:admin2_code":"2922706.0",
    "gn:asciiname":"Vila Icarai",
    "gn:country_code":"BR",
    "gn:dem":643,
    "gn:feature_class":"P",
    "gn:feature_code":"PPL",
    "gn:name":"Vila Icara\u00ed",
    "gn:population":0,
    "gn:timezone":"America/Bahia",
    "iso:country":"BR",
    "wof:name":"Vila Icarai",
    "wof:placetype":"locality"
},
  "geometry": {"coordinates":[-40.22954,-14.93784],"type":"Point"}
}