{
  "type": "Feature",
  "properties": {
    "gn:admin1_code":"04",
    "gn:admin2_code":"1300144.0",
    "gn:asciiname":"Nova Vista",
    "gn:country_code":"BR",
    "gn:dem":130,
    "gn:feature_class":"P",
    "gn:feature_code":"PPL",
    "gn:name":"Nova Vista",
    "gn:population":0,
    "gn:timezone":"America/Manaus",
    "iso:country":"BR",
    "wof:name":"Nova Vista",
    "wof:placetype":"locality"
},
  "geometry": {"coordinates":[-58.21666999999999,-7.38333],"type":"Point"}
}