{
  "type": "Feature",
  "properties": {
    "gn:admin1_code":"06",
    "gn:admin2_code":"2313351.0",
    "gn:asciiname":"Fazenda Olho d'Agua",
    "gn:country_code":"BR",
    "gn:dem":192,
    "gn:feature_class":"P",
    "gn:feature_code":"PPL",
    "gn:name":"Fazenda \u00d4lho d\u2019\u00c1gua",
    "gn:population":0,
    "gn:timezone":"America/Fortaleza",
    "iso:country":"BR",
    "wof:name":"Fazenda Olho d'Agua",
    "wof:placetype":"locality"
},
  "geometry": {"coordinates":[-39.58333,-3.88333],"type":"Point"}
}