{
  "type": "Feature",
  "properties": {
    "iso:country":"BR",
    "name:eng_x_preferred":[
        "Camboinhas"
    ],
    "name:nld_x_preferred":[
        "Camboinhas"
    ],
    "name:por_x_preferred":[
        "Camboinhas"
    ],
    "qs:gn_adm0_cc":"BR",
    "qs:gn_fcode":"PPLX",
    "qs:gn_local":3456283,
    "qs:gn_nam_loc":"Niter\u00f3i, Niter\u00f3i, Rio de Janeiro, BR",
    "qs:gn_namadm1":"21",
    "qs:gn_name":"Camboinhas",
    "qs:local_max":2228,
    "qs:local_sum":7420,
    "qs:localhoods":12,
    "qs:name":"Camboinhas",
    "qs:name_adm0":"Brasil",
    "qs:name_adm1":"Rio de Janeiro",
    "qs:name_adm2":"Niter\u00f3i",
    "qs:name_local":"Niter\u00f3i",
    "qs:photo_max":618,
    "qs:photo_sum":1088,
    "qs:placetype":"Suburb",
    "qs:quad_count":38,
    "qs:woe_adm0":23424768,
    "qs:woe_adm1":2344862,
    "qs:woe_adm2":12581047,
    "qs:woe_lau":0,
    "qs:woe_local":455891,
    "qs:woe_ver":"7.10.0",
    "wd:wordcount":322,
    "wof:lang":[
        "por"
    ],
    "wof:name":"Camboinhas",
    "wof:placetype":"neighbourhood"
},
  "geometry": {"coordinates":[-43.050935,-22.945531],"type":"Point"}
}