{
  "type": "Feature",
  "properties": {
    "gn:admin1_code":"26",
    "gn:admin2_code":"4203303.0",
    "gn:asciiname":"Sitio Mario Kotovicz",
    "gn:country_code":"BR",
    "gn:dem":867,
    "gn:feature_class":"P",
    "gn:feature_code":"PPL",
    "gn:name":"S\u00edtio M\u00e1rio Kotovicz",
    "gn:population":0,
    "gn:timezone":"America/Sao_Paulo",
    "iso:country":"BR",
    "name:por_x_preferred":[
        "S\u00edtio M\u00e1rio Kotovicz"
    ],
    "wof:name":"Sitio Mario Kotovicz",
    "wof:placetype":"locality"
},
  "geometry": {"coordinates":[-49.2844,-26.139],"type":"Point"}
}