{
  "type": "Feature",
  "properties": {
    "gn:admin1_code":"5",
    "gn:admin2_code":"2927200.0",
    "gn:asciiname":"Manuel Pereira",
    "gn:cc2":"BR",
    "gn:country_code":"BR",
    "gn:dem":384,
    "gn:feature_class":"P",
    "gn:feature_code":"PPL",
    "gn:name":"Manuel Pereira",
    "gn:population":0,
    "gn:timezone":"America/Bahia",
    "iso:country":"BR",
    "name:und_x_variant":[
        "Manoel Pereira",
        "Manuel Pereira"
    ],
    "wof:name":"Manuel Pereira",
    "wof:placetype":"locality"
},
  "geometry": {"coordinates":[-40.53333,-12.31667],"type":"Point"}
}