{
  "type": "Feature",
  "properties": {
    "gn:admin1_code":"5",
    "gn:admin2_code":"2927200.0",
    "gn:asciiname":"Manuel Pereira",
    "gn:cc2":"BR",
    "gn:country_code":"BR",
    "gn:dem":384,
    "gn:feature_class":"P",
    "gn:feature_code":"PPL",
    "gn:name":"Manuel Pereira",
    "gn:population":0,
    "gn:timezone":"America/Bahia",
    "iso:country":"BR",
    "name:ara_x_preferred":[
        "\u0645\u0627\u0646\u0648\u064a\u0644 \u0628\u064a\u0631\u064a\u0631\u0627"
    ],
    "name:ces_x_preferred":[
        "Manuel Pereira"
    ],
    "name:deu_x_preferred":[
        "Manuel Pereira"
    ],
    "name:fra_x_preferred":[
        "Manuel Pereira"
    ],
    "name:hun_x_preferred":[
        "Manuel Pereira"
    ],
    "name:ita_x_preferred":[
        "Manuel Pereira"
    ],
    "name:spa_x_preferred":[
        "Manuel Pereira Senabre"
    ],
    "name:und_x_variant":[
        "Manoel Pereira"
    ],
    "wof:name":"Manuel Pereira",
    "wof:placetype":"locality"
},
  "geometry": {"coordinates":[-40.53333,-12.31667],"type":"Point"}
}