{
  "type": "Feature",
  "properties": {
    "gn:admin1_code":"27.0",
    "gn:admin2_code":"3502903.0",
    "gn:asciiname":"Sitio Dilceu Goncalves",
    "gn:country_code":"BR",
    "gn:dem":619,
    "gn:feature_class":"P",
    "gn:feature_code":"PPL",
    "gn:name":"S\u00edtio Dilceu Gon\u00e7alves",
    "gn:population":0,
    "gn:timezone":"America/Sao_Paulo",
    "iso:country":"BR",
    "name:por_x_preferred":[
        "S\u00edtio Dilceu Gon\u00e7alves"
    ],
    "wof:name":"Sitio Dilceu Goncalves",
    "wof:placetype":"locality"
},
  "geometry": {"coordinates":[-47.6583,-23.5325],"type":"Point"}
}