{
  "type": "Feature",
  "properties": {
    "gn:admin1_code":"5",
    "gn:admin2_code":"2907004.0",
    "gn:asciiname":"Panelas",
    "gn:country_code":"BR",
    "gn:dem":100,
    "gn:feature_class":"P",
    "gn:feature_code":"PPL",
    "gn:name":"Panelas",
    "gn:population":0,
    "gn:timezone":"America/Bahia",
    "iso:country":"BR",
    "wof:name":"Panelas",
    "wof:placetype":"locality"
},
  "geometry": {"coordinates":[-37.91667,-12.01667],"type":"Point"}
}