{
  "type": "Feature",
  "properties": {
    "gn:admin1_code":"22",
    "gn:admin2_code":"2412609.0",
    "gn:asciiname":"Cachoeira",
    "gn:country_code":"BR",
    "gn:dem":111,
    "gn:feature_class":"P",
    "gn:feature_code":"PPL",
    "gn:name":"Cachoeira",
    "gn:population":0,
    "gn:timezone":"America/Fortaleza",
    "iso:country":"BR",
    "wof:name":"Cachoeira",
    "wof:placetype":"locality"
},
  "geometry": {"coordinates":[-35.78333,-5.91667],"type":"Point"}
}