{
  "type": "Feature",
  "properties": {
    "gn:admin1_code":"27",
    "gn:admin2_code":"3524402.0",
    "gn:asciiname":"Recanto Santa Ana",
    "gn:country_code":"BR",
    "gn:dem":601,
    "gn:feature_class":"P",
    "gn:feature_code":"PPL",
    "gn:name":"Recanto Santa Ana",
    "gn:population":0,
    "gn:timezone":"America/Sao_Paulo",
    "iso:country":"BR",
    "name:por_x_preferred":[
        "Recanto Santa Ana"
    ],
    "wof:name":"Recanto Santa Ana",
    "wof:placetype":"locality"
},
  "geometry": {"coordinates":[-46.0512,-23.2975],"type":"Point"}
}