{
  "type": "Feature",
  "properties": {
    "gn:admin1_code":"23",
    "gn:admin2_code":"4316972.0",
    "gn:asciiname":"Estancia Sao Francisco",
    "gn:country_code":"BR",
    "gn:dem":145,
    "gn:feature_class":"P",
    "gn:feature_code":"PPL",
    "gn:name":"Est\u00e2ncia S\u00e3o Francisco",
    "gn:population":0,
    "gn:timezone":"America/Sao_Paulo",
    "iso:country":"BR",
    "wof:name":"Estancia Sao Francisco",
    "wof:placetype":"locality"
},
  "geometry": {"coordinates":[-54.15,-30.38333],"type":"Point"}
}