{
  "type": "Feature",
  "properties": {
    "gn:admin1_code":"30.0",
    "gn:admin2_code":"2609907.0",
    "gn:asciiname":"Antonopolis",
    "gn:country_code":"BR",
    "gn:dem":447,
    "gn:feature_class":"P",
    "gn:feature_code":"PPL",
    "gn:name":"Anton\u00f3polis",
    "gn:population":0,
    "gn:timezone":"America/Recife",
    "iso:country":"BR",
    "name:por_x_preferred":[
        "Anton\u00f3polis"
    ],
    "wof:name":"Antonopolis",
    "wof:placetype":"locality"
},
  "geometry": {"coordinates":[-40.31486,-8.05553],"type":"Point"}
}