{
  "type": "Feature",
  "properties": {
    "gn:admin1_code":"11",
    "gn:admin2_code":"5002704.0",
    "gn:asciiname":"Pontal",
    "gn:cc2":"BR",
    "gn:country_code":"BR",
    "gn:dem":577,
    "gn:feature_class":"P",
    "gn:feature_code":"PPL",
    "gn:name":"Pontal",
    "gn:population":0,
    "gn:timezone":"America/Campo_Grande",
    "iso:country":"BR",
    "name:bpy_x_preferred":[
        "\u09aa\u09cb\u09a8\u09cd\u099f\u09be\u09b2"
    ],
    "name:ceb_x_preferred":[
        "Pontal"
    ],
    "name:epo_x_preferred":[
        "Pontal"
    ],
    "name:eus_x_preferred":[
        "Pontal"
    ],
    "name:fra_x_preferred":[
        "Pontal"
    ],
    "name:ita_x_preferred":[
        "Pontal"
    ],
    "name:kaz_x_preferred":[
        "\u041f\u043e\u043d\u0442\u0430\u043b"
    ],
    "name:mlg_x_preferred":[
        "Pontal"
    ],
    "name:nld_x_preferred":[
        "Pontal"
    ],
    "name:nor_x_preferred":[
        "Pontal"
    ],
    "name:pol_x_preferred":[
        "Pontal"
    ],
    "name:por_x_preferred":[
        "Pontal"
    ],
    "name:ron_x_preferred":[
        "Pontal"
    ],
    "name:rus_x_preferred":[
        "\u041f\u043e\u043d\u0442\u0430\u043b"
    ],
    "name:sco_x_preferred":[
        "Pontal"
    ],
    "name:swe_x_preferred":[
        "Pontal"
    ],
    "name:und_x_variant":[
        "Fazenda Pontal"
    ],
    "name:vie_x_preferred":[
        "Pontal"
    ],
    "name:vol_x_preferred":[
        "Pontal"
    ],
    "name:war_x_preferred":[
        "Pontal"
    ],
    "name:zho_x_preferred":[
        "\u84ec\u5854\u5c14"
    ],
    "wof:name":"Pontal",
    "wof:placetype":"locality"
},
  "geometry": {"coordinates":[-54.41667,-20.46667],"type":"Point"}
}