{
  "type": "Feature",
  "properties": {
    "gn:admin1_code":"11",
    "gn:admin2_code":"5002704.0",
    "gn:asciiname":"Pontal",
    "gn:cc2":"BR",
    "gn:country_code":"BR",
    "gn:dem":577,
    "gn:feature_class":"P",
    "gn:feature_code":"PPL",
    "gn:name":"Pontal",
    "gn:population":0,
    "gn:timezone":"America/Campo_Grande",
    "iso:country":"BR",
    "name:und_x_variant":[
        "Fazenda Pontal",
        "Pontal"
    ],
    "wof:name":"Pontal",
    "wof:placetype":"locality"
},
  "geometry": {"coordinates":[-54.41667,-20.46667],"type":"Point"}
}