{
  "type": "Feature",
  "properties": {
    "gn:admin1_code":"15",
    "gn:admin2_code":"3161106.0",
    "gn:asciiname":"Cipoal",
    "gn:country_code":"BR",
    "gn:dem":464,
    "gn:feature_class":"P",
    "gn:feature_code":"PPL",
    "gn:name":"Cipoal",
    "gn:population":0,
    "gn:timezone":"America/Sao_Paulo",
    "iso:country":"BR",
    "wof:name":"Cipoal",
    "wof:placetype":"locality"
},
  "geometry": {"coordinates":[-44.75,-15.81667],"type":"Point"}
}