{
  "type": "Feature",
  "properties": {
    "gn:admin1_code":"18.0",
    "gn:admin2_code":"4109708.0",
    "gn:asciiname":"Alto Alegre",
    "gn:country_code":"BR",
    "gn:dem":715,
    "gn:feature_class":"P",
    "gn:feature_code":"PPL",
    "gn:name":"Alto Alegre",
    "gn:population":0,
    "gn:timezone":"America/Sao_Paulo",
    "iso:country":"BR",
    "name:bpy_x_preferred":[
        "\u0986\u09b2\u09cd\u099f\u09cb \u0986\u09b2\u09c7\u0997\u09cd\u09b0\u09c7"
    ],
    "name:ceb_x_preferred":[
        "Alto Alegre"
    ],
    "name:deu_x_preferred":[
        "Alto Alegre"
    ],
    "name:fra_x_preferred":[
        "Alto Alegre"
    ],
    "name:ita_x_preferred":[
        "Alto Alegre"
    ],
    "name:nld_x_preferred":[
        "Alto Alegre"
    ],
    "name:nor_x_preferred":[
        "Alto Alegre"
    ],
    "name:pol_x_preferred":[
        "Alto Alegre"
    ],
    "name:por_x_preferred":[
        "Alto Alegre"
    ],
    "name:sco_x_preferred":[
        "Alto Alegre"
    ],
    "name:spa_x_preferred":[
        "Alto Alegre"
    ],
    "name:swe_x_preferred":[
        "Alto Alegre"
    ],
    "name:vie_x_preferred":[
        "Alto Alegre"
    ],
    "name:vol_x_preferred":[
        "Alto Alegre"
    ],
    "wof:name":"Alto Alegre",
    "wof:placetype":"locality"
},
  "geometry": {"coordinates":[-50.2635,-23.8871],"type":"Point"}
}