{
  "type": "Feature",
  "properties": {
    "gn:admin1_code":"18.0",
    "gn:admin2_code":"4109708.0",
    "gn:asciiname":"Alto Alegre",
    "gn:country_code":"BR",
    "gn:dem":715,
    "gn:feature_class":"P",
    "gn:feature_code":"PPL",
    "gn:name":"Alto Alegre",
    "gn:population":0,
    "gn:timezone":"America/Sao_Paulo",
    "iso:country":"BR",
    "name:por_x_preferred":[
        "Alto Alegre"
    ],
    "wof:name":"Alto Alegre",
    "wof:placetype":"locality"
},
  "geometry": {"coordinates":[-50.2635,-23.8871],"type":"Point"}
}