{
  "type": "Feature",
  "properties": {
    "gn:admin1_code":"18.0",
    "gn:admin2_code":"4109708.0",
    "gn:asciiname":"Sitio Wilson Langnier",
    "gn:country_code":"BR",
    "gn:dem":722,
    "gn:feature_class":"P",
    "gn:feature_code":"PPL",
    "gn:name":"S\u00edtio Wilson Langnier",
    "gn:population":0,
    "gn:timezone":"America/Sao_Paulo",
    "iso:country":"BR",
    "name:por_x_preferred":[
        "S\u00edtio Wilson Langnier"
    ],
    "wof:name":"Sitio Wilson Langnier",
    "wof:placetype":"locality"
},
  "geometry": {"coordinates":[-50.25281,-23.90221],"type":"Point"}
}