{
  "type": "Feature",
  "properties": {
    "gn:admin1_code":"18.0",
    "gn:admin2_code":"4122305.0",
    "gn:asciiname":"Sitio Paulo Lachoviski",
    "gn:country_code":"BR",
    "gn:dem":841,
    "gn:feature_class":"P",
    "gn:feature_code":"PPL",
    "gn:name":"S\u00edtio Paulo Lachoviski",
    "gn:population":0,
    "gn:timezone":"America/Sao_Paulo",
    "iso:country":"BR",
    "name:por_x_preferred":[
        "S\u00edtio Paulo Lachoviski"
    ],
    "wof:name":"Sitio Paulo Lachoviski",
    "wof:placetype":"locality"
},
  "geometry": {"coordinates":[-49.8166,-26.0534],"type":"Point"}
}