{
  "type": "Feature",
  "properties": {
    "gn:admin1_code":"21",
    "gn:admin2_code":"3304300.0",
    "gn:asciiname":"Morro das Moedas",
    "gn:cc2":"BR",
    "gn:country_code":"BR",
    "gn:dem":49,
    "gn:feature_class":"P",
    "gn:feature_code":"PPL",
    "gn:name":"Morro das Moedas",
    "gn:population":0,
    "gn:timezone":"America/Sao_Paulo",
    "iso:country":"BR",
    "name:und_x_variant":[
        "Morro das Moendas",
        "Morro das Moedas"
    ],
    "wof:name":"Morro das Moedas",
    "wof:placetype":"locality"
},
  "geometry": {"coordinates":[-42.45,-22.76667],"type":"Point"}
}