{
  "type": "Feature",
  "properties": {
    "gn:admin1_code":"27.0",
    "gn:admin2_code":"3538600.0",
    "gn:asciiname":"Jorge de Almeida",
    "gn:country_code":"BR",
    "gn:dem":955,
    "gn:feature_class":"P",
    "gn:feature_code":"PPL",
    "gn:name":"Jorge de Almeida",
    "gn:population":0,
    "gn:timezone":"America/Sao_Paulo",
    "iso:country":"BR",
    "name:por_x_preferred":[
        "Jorge de Almeida"
    ],
    "wof:name":"Jorge de Almeida",
    "wof:placetype":"locality"
},
  "geometry": {"coordinates":[-46.23511,-23.09865],"type":"Point"}
}