{
  "type": "Feature",
  "properties": {
    "gn:admin1_code":"27",
    "gn:admin2_code":"3554300.0",
    "gn:asciiname":"Porto Cabral",
    "gn:country_code":"BR",
    "gn:dem":270,
    "gn:feature_class":"P",
    "gn:feature_code":"PPL",
    "gn:name":"P\u00f4rto Cabral",
    "gn:population":0,
    "gn:timezone":"America/Sao_Paulo",
    "iso:country":"BR",
    "wof:name":"Porto Cabral",
    "wof:placetype":"locality"
},
  "geometry": {"coordinates":[-52.6242,-22.28988],"type":"Point"}
}