{
  "type": "Feature",
  "properties": {
    "gn:admin1_code":"06",
    "gn:admin2_code":"2311801.0",
    "gn:asciiname":"Fazenda Monte Alegre",
    "gn:country_code":"BR",
    "gn:dem":55,
    "gn:feature_class":"P",
    "gn:feature_code":"PPL",
    "gn:name":"Fazenda Monte Alegre",
    "gn:population":0,
    "gn:timezone":"America/Fortaleza",
    "iso:country":"BR",
    "wof:name":"Fazenda Monte Alegre",
    "wof:placetype":"locality"
},
  "geometry": {"coordinates":[-38.03333,-4.85],"type":"Point"}
}