{
  "type": "Feature",
  "properties": {
    "gn:admin1_code":"18.0",
    "gn:admin2_code":"4113205.0",
    "gn:asciiname":"Sitio Getulio de O. Santos",
    "gn:country_code":"BR",
    "gn:dem":808,
    "gn:feature_class":"P",
    "gn:feature_code":"PPL",
    "gn:name":"S\u00edtio Get\u00falio de O. Santos",
    "gn:population":0,
    "gn:timezone":"America/Sao_Paulo",
    "iso:country":"BR",
    "name:por_x_preferred":[
        "S\u00edtio Get\u00falio de O. Santos"
    ],
    "wof:name":"Sitio Getulio de O. Santos",
    "wof:placetype":"locality"
},
  "geometry": {"coordinates":[-49.5891,-25.8458],"type":"Point"}
}