{
  "type": "Feature",
  "properties": {
    "gn:admin1_code":"18.0",
    "gn:admin2_code":"4109708.0",
    "gn:asciiname":"Sitio Paraiso",
    "gn:country_code":"BR",
    "gn:dem":583,
    "gn:feature_class":"P",
    "gn:feature_code":"PPL",
    "gn:name":"S\u00edtio Para\u00edso",
    "gn:population":0,
    "gn:timezone":"America/Sao_Paulo",
    "iso:country":"BR",
    "name:por_x_preferred":[
        "S\u00edtio Para\u00edso"
    ],
    "wof:name":"Sitio Paraiso",
    "wof:placetype":"locality"
},
  "geometry": {"coordinates":[-50.21498,-23.79287],"type":"Point"}
}