{
  "type": "Feature",
  "properties": {
    "gn:admin1_code":"20",
    "gn:admin2_code":"2206670.0",
    "gn:asciiname":"Talhado",
    "gn:country_code":"BR",
    "gn:dem":108,
    "gn:feature_class":"P",
    "gn:feature_code":"PPL",
    "gn:name":"Talhado",
    "gn:population":0,
    "gn:timezone":"America/Fortaleza",
    "iso:country":"BR",
    "wof:name":"Talhado",
    "wof:placetype":"locality"
},
  "geometry": {"coordinates":[-42.26,-3.71889],"type":"Point"}
}