{
  "type": "Feature",
  "properties": {
    "gn:admin1_code":"22",
    "gn:admin2_code":"2414605.0",
    "gn:asciiname":"Upanema",
    "gn:country_code":"BR",
    "gn:dem":46,
    "gn:feature_class":"P",
    "gn:feature_code":"PPL",
    "gn:name":"Upanema",
    "gn:population":6704,
    "gn:timezone":"America/Fortaleza",
    "iso:country":"BR",
    "wof:name":"Upanema",
    "wof:placetype":"locality",
    "wof:population":6704
},
  "geometry": {"coordinates":[-37.25778,-5.64194],"type":"Point"}
}