{
  "type": "Feature",
  "properties": {
    "gn:admin1_code":"18.0",
    "gn:admin2_code":"4116208.0",
    "gn:asciiname":"Sitio Osmar Rosina",
    "gn:country_code":"BR",
    "gn:dem":18,
    "gn:feature_class":"P",
    "gn:feature_code":"PPL",
    "gn:name":"S\u00edtio Osmar Rosina",
    "gn:population":0,
    "gn:timezone":"America/Sao_Paulo",
    "iso:country":"BR",
    "name:por_x_preferred":[
        "S\u00edtio Osmar Rosina"
    ],
    "wof:name":"Sitio Osmar Rosina",
    "wof:placetype":"locality"
},
  "geometry": {"coordinates":[-48.84993,-25.49307],"type":"Point"}
}