{
  "type": "Feature",
  "properties": {
    "gn:admin1_code":"18",
    "gn:admin2_code":"4122305.0",
    "gn:asciiname":"Sitio Antonio Fagundes",
    "gn:country_code":"BR",
    "gn:dem":885,
    "gn:feature_class":"P",
    "gn:feature_code":"PPL",
    "gn:name":"S\u00edtio Ant\u00f4nio Fagundes",
    "gn:population":0,
    "gn:timezone":"America/Sao_Paulo",
    "iso:country":"BR",
    "name:por_x_preferred":[
        "S\u00edtio Ant\u00f4nio Fagundes"
    ],
    "wof:name":"Sitio Antonio Fagundes",
    "wof:placetype":"locality"
},
  "geometry": {"coordinates":[-49.61126,-26.12354],"type":"Point"}
}