{
  "type": "Feature",
  "properties": {
    "gn:admin1_code":"27",
    "gn:admin2_code":"3519709.0",
    "gn:asciiname":"Sitio Beija-Flor",
    "gn:country_code":"BR",
    "gn:dem":905,
    "gn:feature_class":"P",
    "gn:feature_code":"PPL",
    "gn:name":"S\u00edtio Beija-Flor",
    "gn:population":0,
    "gn:timezone":"America/Sao_Paulo",
    "iso:country":"BR",
    "name:por_x_preferred":[
        "S\u00edtio Beija-Flor"
    ],
    "wof:name":"Sitio Beija-Flor",
    "wof:placetype":"locality"
},
  "geometry": {"coordinates":[-47.23002,-23.6931],"type":"Point"}
}