{
  "type": "Feature",
  "properties": {
    "gn:admin1_code":"4",
    "gn:admin2_code":"1304104.0",
    "gn:asciiname":"Bem-te-vi",
    "gn:country_code":"BR",
    "gn:dem":30,
    "gn:feature_class":"P",
    "gn:feature_code":"PPL",
    "gn:name":"Bem-te-vi",
    "gn:population":0,
    "gn:timezone":"America/Manaus",
    "iso:country":"BR",
    "wof:name":"Bem-te-vi",
    "wof:placetype":"locality"
},
  "geometry": {"coordinates":[-63.04139,-5.41722],"type":"Point"}
}