{
  "type": "Feature",
  "properties": {
    "gn:admin1_code":"13",
    "gn:admin2_code":"2102101.0",
    "gn:asciiname":"Piabas",
    "gn:country_code":"BR",
    "gn:dem":61,
    "gn:feature_class":"P",
    "gn:feature_code":"PPL",
    "gn:name":"Piabas",
    "gn:population":0,
    "gn:timezone":"America/Fortaleza",
    "iso:country":"BR",
    "wof:name":"Piabas",
    "wof:placetype":"locality"
},
  "geometry": {"coordinates":[-42.76667,-3.82778],"type":"Point"}
}