{
  "type": "Feature",
  "properties": {
    "gn:admin1_code":"20",
    "gn:admin2_code":"2211001.0",
    "gn:asciiname":"Sao Raimundo",
    "gn:country_code":"BR",
    "gn:dem":87,
    "gn:feature_class":"P",
    "gn:feature_code":"PPL",
    "gn:name":"S\u00e3o Raimundo",
    "gn:population":0,
    "gn:timezone":"America/Fortaleza",
    "iso:country":"BR",
    "wof:name":"Sao Raimundo",
    "wof:placetype":"locality"
},
  "geometry": {"coordinates":[-42.78333,-5.11667],"type":"Point"}
}