{
  "type": "Feature",
  "properties": {
    "gn:admin1_code":"18.0",
    "gn:admin2_code":"4111803.0",
    "gn:asciiname":"Sitio Reginaldo Andrade",
    "gn:country_code":"BR",
    "gn:dem":582,
    "gn:feature_class":"P",
    "gn:feature_code":"PPL",
    "gn:name":"S\u00edtio Reginaldo Andrade",
    "gn:population":0,
    "gn:timezone":"America/Sao_Paulo",
    "iso:country":"BR",
    "name:por_x_preferred":[
        "S\u00edtio Reginaldo Andrade"
    ],
    "wof:name":"Sitio Reginaldo Andrade",
    "wof:placetype":"locality"
},
  "geometry": {"coordinates":[-49.86189,-23.17973],"type":"Point"}
}