{
  "type": "Feature",
  "properties": {
    "gn:admin1_code":"06",
    "gn:admin2_code":"2311108.0",
    "gn:asciiname":"Massape",
    "gn:country_code":"BR",
    "gn:dem":965,
    "gn:feature_class":"P",
    "gn:feature_code":"PPL",
    "gn:name":"Massap\u00ea",
    "gn:population":0,
    "gn:timezone":"America/Fortaleza",
    "iso:country":"BR",
    "wof:name":"Massape",
    "wof:placetype":"locality"
},
  "geometry": {"coordinates":[-39.13333,-7.48333],"type":"Point"}
}