{
  "type": "Feature",
  "properties": {
    "gn:admin1_code":"22",
    "gn:admin2_code":"2410801.0",
    "gn:asciiname":"Catolezinho",
    "gn:country_code":"BR",
    "gn:dem":275,
    "gn:feature_class":"P",
    "gn:feature_code":"PPL",
    "gn:name":"Catol\u00e9zinho",
    "gn:population":0,
    "gn:timezone":"America/Fortaleza",
    "iso:country":"BR",
    "wof:name":"Catolezinho",
    "wof:placetype":"locality"
},
  "geometry": {"coordinates":[-38.26667,-6.26667],"type":"Point"}
}