{
  "type": "Feature",
  "properties": {
    "gn:admin1_code":"30",
    "gn:admin2_code":"2609907.0",
    "gn:asciiname":"Sitio Novo",
    "gn:country_code":"BR",
    "gn:dem":487,
    "gn:feature_class":"P",
    "gn:feature_code":"PPL",
    "gn:name":"S\u00edtio Novo",
    "gn:population":0,
    "gn:timezone":"America/Recife",
    "iso:country":"BR",
    "wof:name":"Sitio Novo",
    "wof:placetype":"locality"
},
  "geometry": {"coordinates":[-40.38333,-7.96667],"type":"Point"}
}