{
  "type": "Feature",
  "properties": {
    "gn:admin1_code":"18.0",
    "gn:admin2_code":"4106001.0",
    "gn:asciiname":"Sitio Tejadamaro",
    "gn:country_code":"BR",
    "gn:dem":642,
    "gn:feature_class":"P",
    "gn:feature_code":"PPL",
    "gn:name":"S\u00edtio Tejadamaro",
    "gn:population":0,
    "gn:timezone":"America/Sao_Paulo",
    "iso:country":"BR",
    "name:por_x_preferred":[
        "S\u00edtio Tejadamaro"
    ],
    "wof:name":"Sitio Tejadamaro",
    "wof:placetype":"locality"
},
  "geometry": {"coordinates":[-50.51634,-23.58742],"type":"Point"}
}