{
  "type": "Feature",
  "properties": {
    "gn:admin1_code":"4",
    "gn:admin2_code":"1304104.0",
    "gn:asciiname":"Mapixi",
    "gn:country_code":"BR",
    "gn:dem":54,
    "gn:feature_class":"P",
    "gn:feature_code":"PPL",
    "gn:name":"Mapixi",
    "gn:population":0,
    "gn:timezone":"America/Manaus",
    "iso:country":"BR",
    "wof:name":"Mapixi",
    "wof:placetype":"locality"
},
  "geometry": {"coordinates":[-64.01278000000001,-5.61722],"type":"Point"}
}