{
  "type": "Feature",
  "properties": {
    "gn:admin1_code":"18.0",
    "gn:admin2_code":"4126603.0",
    "gn:asciiname":"Sitio Sao Vicente",
    "gn:country_code":"BR",
    "gn:dem":585,
    "gn:feature_class":"P",
    "gn:feature_code":"PPL",
    "gn:name":"S\u00edtio S\u00e3o Vicente",
    "gn:population":0,
    "gn:timezone":"America/Sao_Paulo",
    "iso:country":"BR",
    "name:por_x_preferred":[
        "S\u00edtio S\u00e3o Vicente"
    ],
    "wof:name":"Sitio Sao Vicente",
    "wof:placetype":"locality"
},
  "geometry": {"coordinates":[-49.808,-23.7174],"type":"Point"}
}