{
  "type": "Feature",
  "properties": {
    "gn:admin1_code":"24",
    "gn:admin2_code":"1100205.0",
    "gn:asciiname":"Taquara",
    "gn:cc2":"BR",
    "gn:country_code":"BR",
    "gn:dem":111,
    "gn:feature_class":"P",
    "gn:feature_code":"PPL",
    "gn:name":"Taquara",
    "gn:population":0,
    "gn:timezone":"America/Porto_Velho",
    "iso:country":"BR",
    "name:und_x_variant":[
        "Taquaras",
        "Taquaral",
        "Taquara"
    ],
    "wof:name":"Taquara",
    "wof:placetype":"locality"
},
  "geometry": {"coordinates":[-65.31667,-9.93333],"type":"Point"}
}