{
  "type": "Feature",
  "properties": {
    "gn:admin1_code":"5",
    "gn:admin2_code":"2922250.0",
    "gn:asciiname":"Itai",
    "gn:country_code":"BR",
    "gn:dem":416,
    "gn:feature_class":"P",
    "gn:feature_code":"PPL",
    "gn:name":"Ita\u00ed",
    "gn:population":0,
    "gn:timezone":"America/Bahia",
    "iso:country":"BR",
    "name:heb_x_preferred":[
        "\u05d0\u05d9\u05ea\u05d9"
    ],
    "name:por_x_preferred":[
        "Itai"
    ],
    "name:spa_x_preferred":[
        "Itai"
    ],
    "wof:name":"Itai",
    "wof:placetype":"locality"
},
  "geometry": {"coordinates":[-43.28333,-12.15],"type":"Point"}
}