{
  "type": "Feature",
  "properties": {
    "gn:admin1_code":"27.0",
    "gn:admin2_code":"3528502.0",
    "gn:asciiname":"Jardim Olimpio",
    "gn:country_code":"BR",
    "gn:dem":911,
    "gn:feature_class":"P",
    "gn:feature_code":"PPLL",
    "gn:name":"Jardim Ol\u00edmpio",
    "gn:population":0,
    "gn:timezone":"America/Sao_Paulo",
    "iso:country":"BR",
    "name:por_x_preferred":[
        "Jardim Ol\u00edmpio"
    ],
    "wof:name":"Jardim Olimpio",
    "wof:placetype":"locality"
},
  "geometry": {"coordinates":[-46.59247,-23.25148],"type":"Point"}
}