{
  "type": "Feature",
  "properties": {
    "gn:admin1_code":"30",
    "gn:admin2_code":"2600807.0",
    "gn:asciiname":"Saguim",
    "gn:country_code":"BR",
    "gn:dem":453,
    "gn:feature_class":"P",
    "gn:feature_code":"PPL",
    "gn:name":"Saguim",
    "gn:population":0,
    "gn:timezone":"America/Recife",
    "iso:country":"BR",
    "wof:name":"Saguim",
    "wof:placetype":"locality"
},
  "geometry": {"coordinates":[-36.08333,-8.51667],"type":"Point"}
}