{
  "type": "Feature",
  "properties": {
    "gn:admin1_code":"14",
    "gn:admin2_code":"5107875.0",
    "gn:asciiname":"Feitoria Pedro Pinheiro",
    "gn:country_code":"BR",
    "gn:dem":482,
    "gn:feature_class":"P",
    "gn:feature_code":"PPL",
    "gn:name":"Feitoria Pedro Pinheiro",
    "gn:population":0,
    "gn:timezone":"America/Cuiaba",
    "iso:country":"BR",
    "wof:name":"Feitoria Pedro Pinheiro",
    "wof:placetype":"locality"
},
  "geometry": {"coordinates":[-58.41667,-13.35],"type":"Point"}
}