{
  "type": "Feature",
  "properties": {
    "gn:admin1_code":"06",
    "gn:admin2_code":"2313500.0",
    "gn:asciiname":"Curralinho",
    "gn:country_code":"BR",
    "gn:dem":24,
    "gn:feature_class":"P",
    "gn:feature_code":"PPL",
    "gn:name":"Curralinho",
    "gn:population":0,
    "gn:timezone":"America/Fortaleza",
    "iso:country":"BR",
    "wof:name":"Curralinho",
    "wof:placetype":"locality"
},
  "geometry": {"coordinates":[-39.38333,-3.23333],"type":"Point"}
}