{
  "type": "Feature",
  "properties": {
    "gn:admin1_code":"22",
    "gn:admin2_code":"2401701.0",
    "gn:asciiname":"Caiada",
    "gn:country_code":"BR",
    "gn:dem":124,
    "gn:feature_class":"P",
    "gn:feature_code":"PPL",
    "gn:name":"Caiada",
    "gn:population":0,
    "gn:timezone":"America/Fortaleza",
    "iso:country":"BR",
    "wof:name":"Caiada",
    "wof:placetype":"locality"
},
  "geometry": {"coordinates":[-35.63333,-6.01667],"type":"Point"}
}