{
  "type": "Feature",
  "properties": {
    "gn:admin1_code":"11",
    "gn:admin2_code":"5000708.0",
    "gn:asciiname":"Monjolinho",
    "gn:country_code":"BR",
    "gn:dem":263,
    "gn:feature_class":"P",
    "gn:feature_code":"PPL",
    "gn:name":"Monjolinho",
    "gn:population":0,
    "gn:timezone":"America/Campo_Grande",
    "iso:country":"BR",
    "wof:name":"Monjolinho",
    "wof:placetype":"locality"
},
  "geometry": {"coordinates":[-55.63333000000001,-20.81667],"type":"Point"}
}