{
  "type": "Feature",
  "properties": {
    "gn:admin1_code":"02",
    "gn:admin2_code":"2702553.0",
    "gn:asciiname":"Lagoa dos Caboclos",
    "gn:country_code":"BR",
    "gn:dem":243,
    "gn:feature_class":"P",
    "gn:feature_code":"PPL",
    "gn:name":"Lagoa dos Caboclos",
    "gn:population":0,
    "gn:timezone":"America/Maceio",
    "iso:country":"BR",
    "wof:name":"Lagoa dos Caboclos",
    "wof:placetype":"locality"
},
  "geometry": {"coordinates":[-36.78333,-9.48333],"type":"Point"}
}