{
  "type": "Feature",
  "properties": {
    "gn:admin1_code":"18.0",
    "gn:admin2_code":"4122305.0",
    "gn:asciiname":"Sitio Jair de Andrade",
    "gn:country_code":"BR",
    "gn:dem":816,
    "gn:feature_class":"P",
    "gn:feature_code":"PPL",
    "gn:name":"S\u00edtio Jair de Andrade",
    "gn:population":0,
    "gn:timezone":"America/Sao_Paulo",
    "iso:country":"BR",
    "name:por_x_preferred":[
        "S\u00edtio Jair de Andrade"
    ],
    "wof:name":"Sitio Jair de Andrade",
    "wof:placetype":"locality"
},
  "geometry": {"coordinates":[-49.9172,-26.0228],"type":"Point"}
}