{
  "type": "Feature",
  "properties": {
    "gn:admin1_code":"27.0",
    "gn:admin2_code":"3521200.0",
    "gn:asciiname":"Bairro Rio das Pedras",
    "gn:country_code":"BR",
    "gn:dem":97,
    "gn:feature_class":"P",
    "gn:feature_code":"PPLL",
    "gn:name":"Bairro Rio das Pedras",
    "gn:population":0,
    "gn:timezone":"America/Sao_Paulo",
    "iso:country":"BR",
    "name:por_x_preferred":[
        "Bairro Rio das Pedras"
    ],
    "wof:name":"Bairro Rio das Pedras",
    "wof:placetype":"locality"
},
  "geometry": {"coordinates":[-48.59159,-24.61008],"type":"Point"}
}