{
  "type": "Feature",
  "properties": {
    "gn:admin1_code":"27.0",
    "gn:admin2_code":"3514809.0",
    "gn:asciiname":"Sitio da Revessa",
    "gn:country_code":"BR",
    "gn:dem":44,
    "gn:feature_class":"P",
    "gn:feature_code":"PPL",
    "gn:name":"S\u00edtio da Revessa",
    "gn:population":0,
    "gn:timezone":"America/Sao_Paulo",
    "iso:country":"BR",
    "name:por_x_preferred":[
        "S\u00edtio da Revessa"
    ],
    "wof:name":"Sitio da Revessa",
    "wof:placetype":"locality"
},
  "geometry": {"coordinates":[-48.13271,-24.52055],"type":"Point"}
}