{
  "type": "Feature",
  "properties": {
    "gn:admin1_code":"27",
    "gn:admin2_code":"3519709.0",
    "gn:asciiname":"Juquia-Grande",
    "gn:country_code":"BR",
    "gn:dem":639,
    "gn:feature_class":"P",
    "gn:feature_code":"PPLL",
    "gn:name":"Juqui\u00e1-Grande",
    "gn:population":0,
    "gn:timezone":"America/Sao_Paulo",
    "iso:country":"BR",
    "name:por_x_preferred":[
        "Juqui\u00e1-Grande"
    ],
    "wof:name":"Juquia-Grande",
    "wof:placetype":"locality"
},
  "geometry": {"coordinates":[-47.2265,-23.9771],"type":"Point"}
}