{
  "type": "Feature",
  "properties": {
    "gn:admin1_code":"18",
    "gn:admin2_code":"4122305.0",
    "gn:asciiname":"Sitio Luiz Pscheidt",
    "gn:country_code":"BR",
    "gn:dem":824,
    "gn:feature_class":"P",
    "gn:feature_code":"PPL",
    "gn:name":"S\u00edtio Luiz Pscheidt",
    "gn:population":0,
    "gn:timezone":"America/Sao_Paulo",
    "iso:country":"BR",
    "name:por_x_preferred":[
        "S\u00edtio Luiz Pscheidt"
    ],
    "wof:name":"Sitio Luiz Pscheidt",
    "wof:placetype":"locality"
},
  "geometry": {"coordinates":[-49.51431,-26.18414],"type":"Point"}
}