{
  "type": "Feature",
  "properties": {
    "gn:admin1_code":"5",
    "gn:admin2_code":"2930204.0",
    "gn:asciiname":"Serrote",
    "gn:country_code":"BR",
    "gn:dem":464,
    "gn:feature_class":"P",
    "gn:feature_code":"PPL",
    "gn:name":"Serrote",
    "gn:population":0,
    "gn:timezone":"America/Bahia",
    "iso:country":"BR",
    "wof:name":"Serrote",
    "wof:placetype":"locality"
},
  "geometry": {"coordinates":[-41.46667,-10.05],"type":"Point"}
}