{
  "type": "Feature",
  "properties": {
    "gn:admin1_code":"6",
    "gn:admin2_code":"2311959.0",
    "gn:asciiname":"Barreiro (3)",
    "gn:country_code":"BR",
    "gn:dem":660,
    "gn:feature_class":"P",
    "gn:feature_code":"PPL",
    "gn:name":"Barreiro (3)",
    "gn:population":0,
    "gn:timezone":"America/Fortaleza",
    "iso:country":"BR",
    "wof:name":"Barreiro (3)",
    "wof:placetype":"locality"
},
  "geometry": {"coordinates":[-40.43333,-7.25],"type":"Point"}
}