{
  "type": "Feature",
  "properties": {
    "gn:admin1_code":"30",
    "gn:admin2_code":"2603207.0",
    "gn:asciiname":"Formosa",
    "gn:country_code":"BR",
    "gn:dem":802,
    "gn:feature_class":"P",
    "gn:feature_code":"PPL",
    "gn:name":"Formosa",
    "gn:population":0,
    "gn:timezone":"America/Recife",
    "iso:country":"BR",
    "name:heb_x_preferred":[
        "\u05e4\u05d5\u05e8\u05de\u05d5\u05d6\u05d4"
    ],
    "wof:name":"Formosa",
    "wof:placetype":"locality"
},
  "geometry": {"coordinates":[-36.58333,-8.78333],"type":"Point"}
}