{
  "type": "Feature",
  "properties": {
    "gn:admin1_code":"18",
    "gn:admin2_code":"4122305.0",
    "gn:asciiname":"Sitio Migueis Padilha",
    "gn:country_code":"BR",
    "gn:dem":891,
    "gn:feature_class":"P",
    "gn:feature_code":"PPL",
    "gn:name":"S\u00edtio Migueis Padilha",
    "gn:population":0,
    "gn:timezone":"America/Sao_Paulo",
    "iso:country":"BR",
    "name:por_x_preferred":[
        "S\u00edtio Migueis Padilha"
    ],
    "wof:name":"Sitio Migueis Padilha",
    "wof:placetype":"locality"
},
  "geometry": {"coordinates":[-49.68666,-26.08802],"type":"Point"}
}