{
  "type": "Feature",
  "properties": {
    "gn:admin1_code":"4",
    "gn:admin2_code":"1302603.0",
    "gn:asciiname":"Jaraqui",
    "gn:country_code":"BR",
    "gn:dem":38,
    "gn:feature_class":"P",
    "gn:feature_code":"PPL",
    "gn:name":"Jaraqui",
    "gn:population":0,
    "gn:timezone":"America/Manaus",
    "iso:country":"BR",
    "wof:name":"Jaraqui",
    "wof:placetype":"locality"
},
  "geometry": {"coordinates":[-60.43889,-2.95361],"type":"Point"}
}