{
  "type": "Feature",
  "properties": {
    "gn:admin1_code":"18",
    "gn:admin2_code":"4121208.0",
    "gn:asciiname":"Sitio Waldemar Valesk",
    "gn:country_code":"BR",
    "gn:dem":845,
    "gn:feature_class":"P",
    "gn:feature_code":"PPL",
    "gn:name":"S\u00edtio Waldemar Valesk",
    "gn:population":0,
    "gn:timezone":"America/Sao_Paulo",
    "iso:country":"BR",
    "name:por_x_preferred":[
        "S\u00edtio Waldemar Valesk"
    ],
    "wof:name":"Sitio Waldemar Valesk",
    "wof:placetype":"locality"
},
  "geometry": {"coordinates":[-49.5475,-25.91056],"type":"Point"}
}