{
  "type": "Feature",
  "properties": {
    "gn:admin1_code":"23",
    "gn:admin2_code":"4322400.0",
    "gn:asciiname":"Estancia da Saudade",
    "gn:country_code":"BR",
    "gn:dem":50,
    "gn:feature_class":"P",
    "gn:feature_code":"PPL",
    "gn:name":"Est\u00e2ncia da Saudade",
    "gn:population":0,
    "gn:timezone":"America/Sao_Paulo",
    "iso:country":"BR",
    "wof:name":"Estancia da Saudade",
    "wof:placetype":"locality"
},
  "geometry": {"coordinates":[-56.81667,-29.55],"type":"Point"}
}