{
  "type": "Feature",
  "properties": {
    "gn:admin1_code":"06",
    "gn:admin2_code":"2307700.0",
    "gn:asciiname":"Fazenda Passagem Franca",
    "gn:country_code":"BR",
    "gn:dem":271,
    "gn:feature_class":"P",
    "gn:feature_code":"PPL",
    "gn:name":"Fazenda Passagem Franca",
    "gn:population":0,
    "gn:timezone":"America/Fortaleza",
    "iso:country":"BR",
    "wof:name":"Fazenda Passagem Franca",
    "wof:placetype":"locality"
},
  "geometry": {"coordinates":[-38.73333,-3.96667],"type":"Point"}
}