{
  "type": "Feature",
  "properties": {
    "gn:admin1_code":"18.0",
    "gn:admin2_code":"4121208.0",
    "gn:asciiname":"Sitio Gereinias F. dos Santos",
    "gn:country_code":"BR",
    "gn:dem":839,
    "gn:feature_class":"P",
    "gn:feature_code":"PPL",
    "gn:name":"S\u00edtio Gereinias F. dos Santos",
    "gn:population":0,
    "gn:timezone":"America/Sao_Paulo",
    "iso:country":"BR",
    "name:por_x_preferred":[
        "S\u00edtio Gereinias F. dos Santos"
    ],
    "wof:name":"Sitio Gereinias F. dos Santos",
    "wof:placetype":"locality"
},
  "geometry": {"coordinates":[-49.4689,-25.9302],"type":"Point"}
}