{
  "type": "Feature",
  "properties": {
    "gn:admin1_code":"18",
    "gn:admin2_code":"4115457.0",
    "gn:asciiname":"Guampara",
    "gn:country_code":"BR",
    "gn:dem":799,
    "gn:feature_class":"P",
    "gn:feature_code":"PPL",
    "gn:name":"Guampar\u00e1",
    "gn:population":0,
    "gn:timezone":"America/Sao_Paulo",
    "iso:country":"BR",
    "wof:name":"Guampara",
    "wof:placetype":"locality"
},
  "geometry": {"coordinates":[-52.18333,-25.03333],"type":"Point"}
}