{
  "type": "Feature",
  "properties": {
    "gn:admin1_code":"1",
    "gn:admin2_code":"1200450.0",
    "gn:asciiname":"Colocacao Sao Jose",
    "gn:country_code":"BR",
    "gn:dem":161,
    "gn:feature_class":"P",
    "gn:feature_code":"PPL",
    "gn:name":"Coloca\u00e7\u00e3o S\u00e3o Jos\u00e9",
    "gn:population":0,
    "gn:timezone":"America/Rio_Branco",
    "iso:country":"BR",
    "wof:name":"Colocacao Sao Jose",
    "wof:placetype":"locality"
},
  "geometry": {"coordinates":[-67.25,-9.85],"type":"Point"}
}