{
  "type": "Feature",
  "properties": {
    "gn:admin1_code":"16.0",
    "gn:admin2_code":"1501006.0",
    "gn:asciiname":"Ceara",
    "gn:country_code":"BR",
    "gn:dem":65,
    "gn:feature_class":"P",
    "gn:feature_code":"PPL",
    "gn:name":"Ceara",
    "gn:population":0,
    "gn:timezone":"America/Santarem",
    "iso:country":"BR",
    "wof:name":"Ceara",
    "wof:placetype":"locality"
},
  "geometry": {"coordinates":[-55.45388000000001,-3.8598],"type":"Point"}
}