{
  "type": "Feature",
  "properties": {
    "gn:admin1_code":"22",
    "gn:admin2_code":"2404101.0",
    "gn:asciiname":"Riacho do Cabelo",
    "gn:country_code":"BR",
    "gn:dem":18,
    "gn:feature_class":"P",
    "gn:feature_code":"PPL",
    "gn:name":"Riacho do Cabelo",
    "gn:population":0,
    "gn:timezone":"America/Fortaleza",
    "iso:country":"BR",
    "wof:name":"Riacho do Cabelo",
    "wof:placetype":"locality"
},
  "geometry": {"coordinates":[-36.13139,-5.14222],"type":"Point"}
}