{
  "type": "Feature",
  "properties": {
    "gn:admin1_code":"18.0",
    "gn:admin2_code":"4106209.0",
    "gn:asciiname":"Sitio Lavrinha",
    "gn:country_code":"BR",
    "gn:dem":913,
    "gn:feature_class":"P",
    "gn:feature_code":"PPL",
    "gn:name":"S\u00edtio Lavrinha",
    "gn:population":0,
    "gn:timezone":"America/Sao_Paulo",
    "iso:country":"BR",
    "name:por_x_preferred":[
        "S\u00edtio Lavrinha"
    ],
    "wof:name":"Sitio Lavrinha",
    "wof:placetype":"locality"
},
  "geometry": {"coordinates":[-49.5355,-25.7665],"type":"Point"}
}