{
  "type": "Feature",
  "properties": {
    "gn:admin1_code":"29",
    "gn:admin2_code":"5215306.0",
    "gn:asciiname":"Porto",
    "gn:country_code":"BR",
    "gn:dem":716,
    "gn:feature_class":"P",
    "gn:feature_code":"PPL",
    "gn:name":"P\u00f4rto",
    "gn:population":0,
    "gn:timezone":"America/Sao_Paulo",
    "iso:country":"BR",
    "name:por_x_preferred":[
        "P\u00f4rto"
    ],
    "wof:name":"Porto",
    "wof:placetype":"locality"
},
  "geometry": {"coordinates":[-48.18333,-17.28333],"type":"Point"}
}