{
  "type": "Feature",
  "properties": {
    "gn:admin1_code":"18.0",
    "gn:admin2_code":"4126207.0",
    "gn:asciiname":"Sitio Monjolinho",
    "gn:country_code":"BR",
    "gn:dem":760,
    "gn:feature_class":"P",
    "gn:feature_code":"PPL",
    "gn:name":"S\u00edtio Monjolinho",
    "gn:population":0,
    "gn:timezone":"America/Sao_Paulo",
    "iso:country":"BR",
    "name:por_x_preferred":[
        "S\u00edtio Monjolinho"
    ],
    "wof:name":"Sitio Monjolinho",
    "wof:placetype":"locality"
},
  "geometry": {"coordinates":[-50.66487,-23.86032],"type":"Point"}
}