{
  "type": "Feature",
  "properties": {
    "gn:admin1_code":"11",
    "gn:admin2_code":"5003488.0",
    "gn:asciiname":"Remanso",
    "gn:country_code":"BR",
    "gn:dem":337,
    "gn:feature_class":"P",
    "gn:feature_code":"PPL",
    "gn:name":"Remanso",
    "gn:population":0,
    "gn:timezone":"America/Campo_Grande",
    "iso:country":"BR",
    "wof:name":"Remanso",
    "wof:placetype":"locality"
},
  "geometry": {"coordinates":[-55.33333,-20.85],"type":"Point"}
}