{
  "type": "Feature",
  "properties": {
    "gn:admin1_code":"4",
    "gn:admin2_code":"1302702.0",
    "gn:asciiname":"Mirari",
    "gn:country_code":"BR",
    "gn:dem":52,
    "gn:feature_class":"P",
    "gn:feature_code":"PPL",
    "gn:name":"Mirari",
    "gn:population":0,
    "gn:timezone":"America/Manaus",
    "iso:country":"BR",
    "wof:name":"Mirari",
    "wof:placetype":"locality"
},
  "geometry": {"coordinates":[-60.9225,-5.66694],"type":"Point"}
}