{
  "type": "Feature",
  "properties": {
    "gn:admin1_code":"17",
    "gn:admin2_code":"2510808.0",
    "gn:asciiname":"Saco da Conceicao",
    "gn:country_code":"BR",
    "gn:dem":293,
    "gn:feature_class":"P",
    "gn:feature_code":"PPL",
    "gn:name":"Saco da Concei\u00e7\u00e3o",
    "gn:population":0,
    "gn:timezone":"America/Fortaleza",
    "iso:country":"BR",
    "wof:name":"Saco da Conceicao",
    "wof:placetype":"locality"
},
  "geometry": {"coordinates":[-37.46667,-6.98333],"type":"Point"}
}