{
  "type": "Feature",
  "properties": {
    "gn:admin1_code":"11",
    "gn:admin2_code":"5003207.0",
    "gn:asciiname":"Todos os Santos",
    "gn:country_code":"BR",
    "gn:dem":90,
    "gn:feature_class":"P",
    "gn:feature_code":"PPL",
    "gn:name":"Todos os Santos",
    "gn:population":0,
    "gn:timezone":"America/Campo_Grande",
    "iso:country":"BR",
    "wof:name":"Todos os Santos",
    "wof:placetype":"locality"
},
  "geometry": {"coordinates":[-56.96666999999999,-19.58333],"type":"Point"}
}