{
  "type": "Feature",
  "properties": {
    "gn:admin1_code":"27",
    "gn:admin2_code":"3523206.0",
    "gn:asciiname":"Pedra Branca de Itarare",
    "gn:country_code":"BR",
    "gn:dem":518,
    "gn:feature_class":"P",
    "gn:feature_code":"PPLL",
    "gn:name":"Pedra Branca de Itarar\u00e9",
    "gn:population":0,
    "gn:timezone":"America/Sao_Paulo",
    "iso:country":"BR",
    "wof:name":"Pedra Branca de Itarare",
    "wof:placetype":"locality"
},
  "geometry": {"coordinates":[-49.49583,-23.94917],"type":"Point"}
}