{
  "type": "Feature",
  "properties": {
    "gn:admin1_code":"13",
    "gn:admin2_code":"2106409.0",
    "gn:asciiname":"Alagoinha",
    "gn:country_code":"BR",
    "gn:dem":74,
    "gn:feature_class":"P",
    "gn:feature_code":"PPL",
    "gn:name":"Alago\u00ednha",
    "gn:population":0,
    "gn:timezone":"America/Fortaleza",
    "iso:country":"BR",
    "wof:name":"Alagoinha",
    "wof:placetype":"locality"
},
  "geometry": {"coordinates":[-43.16389,-3.61306],"type":"Point"}
}