{
  "type": "Feature",
  "properties": {
    "gn:admin1_code":"13",
    "gn:admin2_code":"2106409.0",
    "gn:asciiname":"Alagoinha",
    "gn:country_code":"BR",
    "gn:dem":74,
    "gn:feature_class":"P",
    "gn:feature_code":"PPL",
    "gn:name":"Alago\u00ednha",
    "gn:population":0,
    "gn:timezone":"America/Fortaleza",
    "iso:country":"BR",
    "name:bpy_x_preferred":[
        "\u0986\u09b2\u09be\u0997\u09cb\u0987\u09a8\u09b9\u09be"
    ],
    "name:ceb_x_preferred":[
        "Alagoinha"
    ],
    "name:eus_x_preferred":[
        "Alagoinha"
    ],
    "name:fra_x_preferred":[
        "Alagoinha"
    ],
    "name:ita_x_preferred":[
        "Alagoinha"
    ],
    "name:kat_x_preferred":[
        "\u10d0\u10da\u10d0\u10d2\u10dd\u10d8\u10dc\u10d8\u10d0"
    ],
    "name:kaz_x_preferred":[
        "\u0410\u043b\u0430\u0433\u043e\u0438\u043d\u044c\u044f"
    ],
    "name:mlg_x_preferred":[
        "Alagoinha"
    ],
    "name:nld_x_preferred":[
        "Alagoinha"
    ],
    "name:nor_x_preferred":[
        "Alagoinha"
    ],
    "name:por_x_preferred":[
        "Alagoinha"
    ],
    "name:rus_x_preferred":[
        "\u0410\u043b\u0430\u0433\u043e\u0438\u043d\u044c\u044f"
    ],
    "name:spa_x_preferred":[
        "Alagoinha"
    ],
    "name:vol_x_preferred":[
        "Alagoinha"
    ],
    "name:war_x_preferred":[
        "Alagoinha"
    ],
    "name:zho_x_preferred":[
        "\u963f\u62c9\u6208\u4f0a\u5c3c\u4e9e"
    ],
    "wof:name":"Alagoinha",
    "wof:placetype":"locality"
},
  "geometry": {"coordinates":[-43.16389,-3.61306],"type":"Point"}
}