{
  "type": "Feature",
  "properties": {
    "gn:admin1_code":"4",
    "gn:admin2_code":"1304104.0",
    "gn:asciiname":"Puruzinho",
    "gn:country_code":"BR",
    "gn:dem":48,
    "gn:feature_class":"P",
    "gn:feature_code":"PPL",
    "gn:name":"Puruzinho",
    "gn:population":0,
    "gn:timezone":"America/Manaus",
    "iso:country":"BR",
    "wof:name":"Puruzinho",
    "wof:placetype":"locality"
},
  "geometry": {"coordinates":[-64.39391999999999,-5.85961],"type":"Point"}
}