{
  "type": "Feature",
  "properties": {
    "gn:admin1_code":"18.0",
    "gn:admin2_code":"4112306.0",
    "gn:asciiname":"Serra Feia",
    "gn:country_code":"BR",
    "gn:dem":557,
    "gn:feature_class":"P",
    "gn:feature_code":"PPLL",
    "gn:name":"Serra Feia",
    "gn:population":0,
    "gn:timezone":"America/Sao_Paulo",
    "iso:country":"BR",
    "name:por_x_preferred":[
        "Serra Feia"
    ],
    "wof:name":"Serra Feia",
    "wof:placetype":"locality"
},
  "geometry": {"coordinates":[-50.22736,-23.63456],"type":"Point"}
}