{
  "type": "Feature",
  "properties": {
    "gn:admin1_code":"06",
    "gn:admin2_code":"2300200.0",
    "gn:asciiname":"Celsolandia",
    "gn:country_code":"BR",
    "gn:dem":30,
    "gn:feature_class":"P",
    "gn:feature_code":"PPL",
    "gn:name":"Celsol\u00e2ndia",
    "gn:population":0,
    "gn:timezone":"America/Fortaleza",
    "iso:country":"BR",
    "wof:name":"Celsolandia",
    "wof:placetype":"locality"
},
  "geometry": {"coordinates":[-40.11667,-2.98333],"type":"Point"}
}