{
  "type": "Feature",
  "properties": {
    "gn:admin1_code":"16",
    "gn:admin2_code":"1500602.0",
    "gn:asciiname":"Bom Jardim",
    "gn:country_code":"BR",
    "gn:dem":373,
    "gn:feature_class":"P",
    "gn:feature_code":"PPL",
    "gn:name":"Bom Jardim",
    "gn:population":0,
    "gn:timezone":"America/Santarem",
    "iso:country":"BR",
    "wof:name":"Bom Jardim",
    "wof:placetype":"locality"
},
  "geometry": {"coordinates":[-54.08333,-5.01667],"type":"Point"}
}