{
  "type": "Feature",
  "properties": {
    "gn:admin1_code":"06",
    "gn:admin2_code":"2302800.0",
    "gn:asciiname":"Vila dos Targinos",
    "gn:country_code":"BR",
    "gn:dem":201,
    "gn:feature_class":"P",
    "gn:feature_code":"PPL",
    "gn:name":"Vila dos Targinos",
    "gn:population":0,
    "gn:timezone":"America/Fortaleza",
    "iso:country":"BR",
    "wof:name":"Vila dos Targinos",
    "wof:placetype":"locality"
},
  "geometry": {"coordinates":[-39.23333,-4.63333],"type":"Point"}
}