{
  "type": "Feature",
  "properties": {
    "iso:country":"BR",
    "name:por_x_preferred":[
        "Dias Macedo"
    ],
    "qs:gn_adm0_cc":"BR",
    "qs:gn_local":3399415,
    "qs:gn_nam_loc":"Cear\u00e1, Fortaleza, Fortaleza, BR",
    "qs:gn_namadm1":"06",
    "qs:local_max":2317,
    "qs:local_sum":14311,
    "qs:localhoods":31,
    "qs:name":"Dias Macedo",
    "qs:name_adm0":"Brasil",
    "qs:name_adm1":"Cear\u00e1",
    "qs:name_adm2":"Fortaleza",
    "qs:name_local":"Fortaleza",
    "qs:photo_max":13,
    "qs:photo_sum":22,
    "qs:placetype":"Suburb",
    "qs:quad_count":5,
    "qs:woe_adm0":23424768,
    "qs:woe_adm1":2344849,
    "qs:woe_adm2":12578701,
    "qs:woe_lau":0,
    "qs:woe_local":455830,
    "qs:woe_ver":"7.10.0",
    "wof:lang":[
        "por"
    ],
    "wof:name":"Dias Macedo",
    "wof:placetype":"neighbourhood"
},
  "geometry": {"coordinates":[-38.524988,-3.782808],"type":"Point"}
}