{
  "type": "Feature",
  "properties": {
    "gn:admin1_code":"6",
    "gn:admin2_code":"2306108.0",
    "gn:asciiname":"Angico (2)",
    "gn:country_code":"BR",
    "gn:dem":181,
    "gn:feature_class":"P",
    "gn:feature_code":"PPL",
    "gn:name":"Angico (2)",
    "gn:population":0,
    "gn:timezone":"America/Fortaleza",
    "iso:country":"BR",
    "wof:name":"Angico (2)",
    "wof:placetype":"locality"
},
  "geometry": {"coordinates":[-39.91667,-3.78333],"type":"Point"}
}