{
  "type": "Feature",
  "properties": {
    "gn:admin1_code":"05",
    "gn:admin2_code":"2907202.0",
    "gn:asciiname":"Fazenda de Fora",
    "gn:country_code":"BR",
    "gn:dem":385,
    "gn:feature_class":"P",
    "gn:feature_code":"PPL",
    "gn:name":"Fazenda de Fora",
    "gn:population":0,
    "gn:timezone":"America/Bahia",
    "iso:country":"BR",
    "wof:name":"Fazenda de Fora",
    "wof:placetype":"locality"
},
  "geometry": {"coordinates":[-41.71667,-9.66667],"type":"Point"}
}