{
  "type": "Feature",
  "properties": {
    "gn:admin1_code":"18",
    "gn:admin2_code":"4119103.0",
    "gn:asciiname":"Sitio Jorge Dencki",
    "gn:country_code":"BR",
    "gn:dem":810,
    "gn:feature_class":"P",
    "gn:feature_code":"PPL",
    "gn:name":"S\u00edtio Jorge Dencki",
    "gn:population":0,
    "gn:timezone":"America/Sao_Paulo",
    "iso:country":"BR",
    "name:por_x_preferred":[
        "S\u00edtio Jorge Dencki"
    ],
    "wof:name":"Sitio Jorge Dencki",
    "wof:placetype":"locality"
},
  "geometry": {"coordinates":[-49.4704,-26.1376],"type":"Point"}
}