{
  "type": "Feature",
  "properties": {
    "gn:admin1_code":"30",
    "gn:admin2_code":"2611533.0",
    "gn:asciiname":"Quixaba",
    "gn:country_code":"BR",
    "gn:dem":554,
    "gn:feature_class":"P",
    "gn:feature_code":"PPL",
    "gn:name":"Quixab\u00e1",
    "gn:population":0,
    "gn:timezone":"America/Recife",
    "iso:country":"BR",
    "wof:name":"Quixaba",
    "wof:placetype":"locality"
},
  "geometry": {"coordinates":[-37.84833,-7.72028],"type":"Point"}
}