{
  "type": "Feature",
  "properties": {
    "gn:admin1_code":"18.0",
    "gn:admin2_code":"4113205.0",
    "gn:asciiname":"Sitio Jose Hoffmann",
    "gn:country_code":"BR",
    "gn:dem":969,
    "gn:feature_class":"P",
    "gn:feature_code":"PPL",
    "gn:name":"S\u00edtio Jos\u00e9 Hoffmann",
    "gn:population":0,
    "gn:timezone":"America/Sao_Paulo",
    "iso:country":"BR",
    "name:por_x_preferred":[
        "S\u00edtio Jos\u00e9 Hoffmann"
    ],
    "wof:name":"Sitio Jose Hoffmann",
    "wof:placetype":"locality"
},
  "geometry": {"coordinates":[-49.699,-25.7584],"type":"Point"}
}