{
  "type": "Feature",
  "properties": {
    "gn:admin1_code":"14",
    "gn:admin2_code":"5103502.0",
    "gn:asciiname":"Caju",
    "gn:country_code":"BR",
    "gn:dem":469,
    "gn:feature_class":"P",
    "gn:feature_code":"PPL",
    "gn:name":"Caju",
    "gn:population":0,
    "gn:timezone":"America/Cuiaba",
    "iso:country":"BR",
    "wof:name":"Caju",
    "wof:placetype":"locality"
},
  "geometry": {"coordinates":[-56.43333000000001,-14.36667],"type":"Point"}
}