{
  "type": "Feature",
  "properties": {
    "gn:admin1_code":"4",
    "gn:admin2_code":"1303502.0",
    "gn:asciiname":"Grande Oriente",
    "gn:country_code":"BR",
    "gn:dem":155,
    "gn:feature_class":"P",
    "gn:feature_code":"PPL",
    "gn:name":"Grande Oriente",
    "gn:population":0,
    "gn:timezone":"America/Manaus",
    "iso:country":"BR",
    "wof:name":"Grande Oriente",
    "wof:placetype":"locality"
},
  "geometry": {"coordinates":[-67.66667,-7.66667],"type":"Point"}
}