{
  "type": "Feature",
  "properties": {
    "gn:admin1_code":"5",
    "gn:admin2_code":"2908309.0",
    "gn:asciiname":"Conceicao",
    "gn:country_code":"BR",
    "gn:dem":235,
    "gn:feature_class":"P",
    "gn:feature_code":"PPL",
    "gn:name":"Concei\u00e7\u00e3o",
    "gn:population":0,
    "gn:timezone":"America/Bahia",
    "iso:country":"BR",
    "wof:name":"Conceicao",
    "wof:placetype":"locality"
},
  "geometry": {"coordinates":[-39.33333,-12.85],"type":"Point"}
}