{
  "type": "Feature",
  "properties": {
    "gn:admin1_code":"14",
    "gn:admin2_code":"5103403.0",
    "gn:asciiname":"Pires",
    "gn:country_code":"BR",
    "gn:dem":202,
    "gn:feature_class":"P",
    "gn:feature_code":"PPL",
    "gn:name":"Pires",
    "gn:population":0,
    "gn:timezone":"America/Cuiaba",
    "iso:country":"BR",
    "name:deu_x_preferred":[
        "Pires"
    ],
    "name:fra_x_preferred":[
        "Pires"
    ],
    "name:ita_x_preferred":[
        "Pires"
    ],
    "name:por_x_preferred":[
        "Pires"
    ],
    "name:rus_x_preferred":[
        "\u041f\u0438\u0440\u0435\u0441"
    ],
    "name:spa_x_preferred":[
        "Pires"
    ],
    "name:ukr_x_preferred":[
        "\u041f\u0456\u0440\u0435\u0448"
    ],
    "wof:name":"Pires",
    "wof:placetype":"locality"
},
  "geometry": {"coordinates":[-55.95,-15.46667],"type":"Point"}
}