{
  "type": "Feature",
  "properties": {
    "gn:admin1_code":"4",
    "gn:admin2_code":"1302306.0",
    "gn:asciiname":"Aracatuba",
    "gn:country_code":"BR",
    "gn:dem":59,
    "gn:feature_class":"P",
    "gn:feature_code":"PPL",
    "gn:name":"Ara\u00e7atuba",
    "gn:population":0,
    "gn:timezone":"America/Manaus",
    "iso:country":"BR",
    "wof:name":"Aracatuba",
    "wof:placetype":"locality"
},
  "geometry": {"coordinates":[-66.36535000000001,-2.54183],"type":"Point"}
}