{
  "type": "Feature",
  "properties": {
    "gn:admin1_code":"4",
    "gn:admin2_code":"1303536.0",
    "gn:asciiname":"Sitio Boa Vista",
    "gn:country_code":"BR",
    "gn:dem":97,
    "gn:feature_class":"P",
    "gn:feature_code":"PPL",
    "gn:name":"S\u00edtio Boa Vista",
    "gn:population":0,
    "gn:timezone":"America/Manaus",
    "iso:country":"BR",
    "wof:name":"Sitio Boa Vista",
    "wof:placetype":"locality"
},
  "geometry": {"coordinates":[-60.14972,-1.81444],"type":"Point"}
}