{
  "type": "Feature",
  "properties": {
    "gn:admin1_code":"15",
    "gn:admin2_code":"3121902.0",
    "gn:asciiname":"Santa Filomena",
    "gn:country_code":"BR",
    "gn:dem":890,
    "gn:feature_class":"P",
    "gn:feature_code":"PPL",
    "gn:name":"Santa Filomena",
    "gn:population":0,
    "gn:timezone":"America/Sao_Paulo",
    "iso:country":"BR",
    "name:por_x_preferred":[
        "Santa Filomena"
    ],
    "wof:name":"Santa Filomena",
    "wof:placetype":"locality"
},
  "geometry": {"coordinates":[-42.98333,-20.98333],"type":"Point"}
}