{
  "type": "Feature",
  "properties": {
    "gn:admin1_code":"26",
    "gn:admin2_code":"4210100.0",
    "gn:asciiname":"Sitio Nivaldo Sao Santos",
    "gn:country_code":"BR",
    "gn:dem":860,
    "gn:feature_class":"P",
    "gn:feature_code":"PPL",
    "gn:name":"S\u00edtio Nivaldo S\u00e3o Santos",
    "gn:population":0,
    "gn:timezone":"America/Sao_Paulo",
    "iso:country":"BR",
    "name:por_x_preferred":[
        "S\u00edtio Nivaldo S\u00e3o Santos"
    ],
    "wof:name":"Sitio Nivaldo Sao Santos",
    "wof:placetype":"locality"
},
  "geometry": {"coordinates":[-49.8777,-26.2093],"type":"Point"}
}