{
  "type": "Feature",
  "properties": {
    "gn:admin1_code":"27.0",
    "gn:admin2_code":"3552205.0",
    "gn:asciiname":"Jardim Primavera",
    "gn:country_code":"BR",
    "gn:dem":650,
    "gn:feature_class":"P",
    "gn:feature_code":"PPLL",
    "gn:name":"Jardim Primavera",
    "gn:population":0,
    "gn:timezone":"America/Sao_Paulo",
    "iso:country":"BR",
    "name:por_x_preferred":[
        "Jardim Primavera"
    ],
    "wof:name":"Jardim Primavera",
    "wof:placetype":"locality"
},
  "geometry": {"coordinates":[-47.5271,-23.5831],"type":"Point"}
}