{
  "type": "Feature",
  "properties": {
    "gn:admin1_code":"30",
    "gn:admin2_code":"2605608.0",
    "gn:asciiname":"Moca Branca",
    "gn:country_code":"BR",
    "gn:dem":766,
    "gn:feature_class":"P",
    "gn:feature_code":"PPL",
    "gn:name":"Mo\u00e7a Branca",
    "gn:population":0,
    "gn:timezone":"America/Recife",
    "iso:country":"BR",
    "wof:name":"Moca Branca",
    "wof:placetype":"locality"
},
  "geometry": {"coordinates":[-37.96667,-7.78333],"type":"Point"}
}