{
  "type": "Feature",
  "properties": {
    "gn:admin1_code":"23",
    "gn:admin2_code":"4311122.0",
    "gn:asciiname":"Rio das Trainhas",
    "gn:country_code":"BR",
    "gn:dem":778,
    "gn:feature_class":"P",
    "gn:feature_code":"PPL",
    "gn:name":"Rio das Trainhas",
    "gn:population":0,
    "gn:timezone":"America/Sao_Paulo",
    "iso:country":"BR",
    "wof:name":"Rio das Trainhas",
    "wof:placetype":"locality"
},
  "geometry": {"coordinates":[-50.45,-28.85],"type":"Point"}
}