{
  "type": "Feature",
  "properties": {
    "gn:admin1_code":"27.0",
    "gn:admin2_code":"3502705.0",
    "gn:asciiname":"Sitio Corrego Novo",
    "gn:country_code":"BR",
    "gn:dem":754,
    "gn:feature_class":"P",
    "gn:feature_code":"PPL",
    "gn:name":"S\u00edtio C\u00f3rrego Novo",
    "gn:population":0,
    "gn:timezone":"America/Sao_Paulo",
    "iso:country":"BR",
    "name:por_x_preferred":[
        "S\u00edtio C\u00f3rrego Novo"
    ],
    "wof:name":"Sitio Corrego Novo",
    "wof:placetype":"locality"
},
  "geometry": {"coordinates":[-48.93222,-24.51549],"type":"Point"}
}