{
  "type": "Feature",
  "properties": {
    "gn:admin1_code":"20",
    "gn:admin2_code":"2206696.0",
    "gn:asciiname":"Cabecote",
    "gn:country_code":"BR",
    "gn:dem":39,
    "gn:feature_class":"P",
    "gn:feature_code":"PPL",
    "gn:name":"Cabe\u00e7ote",
    "gn:population":0,
    "gn:timezone":"America/Fortaleza",
    "iso:country":"BR",
    "wof:name":"Cabecote",
    "wof:placetype":"locality"
},
  "geometry": {"coordinates":[-42.02222,-3.27361],"type":"Point"}
}