{
  "type": "Feature",
  "properties": {
    "gn:admin1_code":"18.0",
    "gn:admin2_code":"4124103.0",
    "gn:asciiname":"Sitio Irmaos Baiao",
    "gn:country_code":"BR",
    "gn:dem":529,
    "gn:feature_class":"P",
    "gn:feature_code":"PPL",
    "gn:name":"S\u00edtio Irm\u00e3os Bai\u00e3o",
    "gn:population":0,
    "gn:timezone":"America/Sao_Paulo",
    "iso:country":"BR",
    "name:por_x_preferred":[
        "S\u00edtio Irm\u00e3os Bai\u00e3o"
    ],
    "wof:name":"Sitio Irmaos Baiao",
    "wof:placetype":"locality"
},
  "geometry": {"coordinates":[-50.15361,-23.28645],"type":"Point"}
}