{
  "type": "Feature",
  "properties": {
    "gn:admin1_code":"18.0",
    "gn:admin2_code":"4106209.0",
    "gn:asciiname":"Sitio Ladislau Chuviskiw",
    "gn:country_code":"BR",
    "gn:dem":892,
    "gn:feature_class":"P",
    "gn:feature_code":"PPL",
    "gn:name":"S\u00edtio Ladislau Chuviskiw",
    "gn:population":0,
    "gn:timezone":"America/Sao_Paulo",
    "iso:country":"BR",
    "name:por_x_preferred":[
        "S\u00edtio Ladislau Chuviskiw"
    ],
    "wof:name":"Sitio Ladislau Chuviskiw",
    "wof:placetype":"locality"
},
  "geometry": {"coordinates":[-49.4118,-25.7837],"type":"Point"}
}