{
  "type": "Feature",
  "properties": {
    "gn:admin1_code":"05",
    "gn:admin2_code":"2924405.0",
    "gn:asciiname":"Caraiba de Santa Teresa",
    "gn:country_code":"BR",
    "gn:dem":462,
    "gn:feature_class":"P",
    "gn:feature_code":"PPL",
    "gn:name":"Cara\u00edba de Santa Teresa",
    "gn:population":0,
    "gn:timezone":"America/Bahia",
    "iso:country":"BR",
    "name:und_x_variant":[
        "Santa Tereza",
        "Cara\u00edba de Santa Tereza",
        "Cara\u00edba de Santa Teresa",
        "Cara\u00edba"
    ],
    "wof:name":"Caraiba de Santa Teresa",
    "wof:placetype":"locality"
},
  "geometry": {"coordinates":[-43.65206,-9.66818],"type":"Point"}
}