{
  "type": "Feature",
  "properties": {
    "gn:admin1_code":"18.0",
    "gn:admin2_code":"4111803.0",
    "gn:asciiname":"Monjolinho",
    "gn:country_code":"BR",
    "gn:dem":525,
    "gn:feature_class":"P",
    "gn:feature_code":"PPL",
    "gn:name":"Monjolinho",
    "gn:population":0,
    "gn:timezone":"America/Sao_Paulo",
    "iso:country":"BR",
    "name:por_x_preferred":[
        "Monjolinho"
    ],
    "wof:name":"Monjolinho",
    "wof:placetype":"locality"
},
  "geometry": {"coordinates":[-49.92223,-23.26782],"type":"Point"}
}