{
  "type": "Feature",
  "properties": {
    "gn:admin1_code":"5",
    "gn:admin2_code":"2910727.0",
    "gn:asciiname":"Manuel Feliciano",
    "gn:cc2":"BR",
    "gn:country_code":"BR",
    "gn:dem":298,
    "gn:feature_class":"P",
    "gn:feature_code":"PPL",
    "gn:name":"Manuel Feliciano",
    "gn:population":0,
    "gn:timezone":"America/Bahia",
    "iso:country":"BR",
    "name:und_x_variant":[
        "Muanel Feliciano",
        "Manuel Feliciano"
    ],
    "wof:name":"Manuel Feliciano",
    "wof:placetype":"locality"
},
  "geometry": {"coordinates":[-39.85,-16.26667],"type":"Point"}
}