{
  "type": "Feature",
  "properties": {
    "gn:admin1_code":"06",
    "gn:admin2_code":"2311900.0",
    "gn:asciiname":"Santa Fe",
    "gn:country_code":"BR",
    "gn:dem":518,
    "gn:feature_class":"P",
    "gn:feature_code":"PPL",
    "gn:name":"Santa F\u00e9",
    "gn:population":0,
    "gn:timezone":"America/Fortaleza",
    "iso:country":"BR",
    "wof:name":"Santa Fe",
    "wof:placetype":"locality"
},
  "geometry": {"coordinates":[-39.9211,-6.37574],"type":"Point"}
}