{
  "type": "Feature",
  "properties": {
    "gn:admin1_code":"30",
    "gn:admin2_code":"2608008.0",
    "gn:asciiname":"Apolinario",
    "gn:country_code":"BR",
    "gn:dem":536,
    "gn:feature_class":"P",
    "gn:feature_code":"PPL",
    "gn:name":"Apolin\u00e1rio",
    "gn:population":0,
    "gn:timezone":"America/Recife",
    "iso:country":"BR",
    "wof:name":"Apolinario",
    "wof:placetype":"locality"
},
  "geometry": {"coordinates":[-36.43333,-8.08333],"type":"Point"}
}