{
  "type": "Feature",
  "properties": {
    "gn:admin1_code":"5",
    "gn:admin2_code":"2906501.0",
    "gn:asciiname":"Neves",
    "gn:country_code":"BR",
    "gn:dem":61,
    "gn:feature_class":"P",
    "gn:feature_code":"PPL",
    "gn:name":"Neves",
    "gn:population":0,
    "gn:timezone":"America/Bahia",
    "iso:country":"BR",
    "wof:name":"Neves",
    "wof:placetype":"locality"
},
  "geometry": {"coordinates":[-38.45,-12.65],"type":"Point"}
}