{
  "type": "Feature",
  "properties": {
    "gn:admin1_code":"5",
    "gn:admin2_code":"2906501.0",
    "gn:asciiname":"Neves",
    "gn:country_code":"BR",
    "gn:dem":61,
    "gn:feature_class":"P",
    "gn:feature_code":"PPL",
    "gn:name":"Neves",
    "gn:population":0,
    "gn:timezone":"America/Bahia",
    "iso:country":"BR",
    "name:cat_x_preferred":[
        "Neves"
    ],
    "name:ceb_x_preferred":[
        "Neves"
    ],
    "name:deu_x_preferred":[
        "Neves"
    ],
    "name:fra_x_preferred":[
        "Neves"
    ],
    "name:ita_x_preferred":[
        "Neves"
    ],
    "name:por_x_preferred":[
        "Neves"
    ],
    "name:rus_x_preferred":[
        "\u041d\u0435\u0432\u0438\u0448"
    ],
    "name:spa_x_preferred":[
        "Neves"
    ],
    "name:swe_x_preferred":[
        "Neves"
    ],
    "wof:name":"Neves",
    "wof:placetype":"locality"
},
  "geometry": {"coordinates":[-38.45,-12.65],"type":"Point"}
}