{
  "type": "Feature",
  "properties": {
    "gn:admin1_code":"15",
    "gn:admin2_code":"3108909.0",
    "gn:asciiname":"Roca",
    "gn:country_code":"BR",
    "gn:dem":983,
    "gn:feature_class":"P",
    "gn:feature_code":"PPLL",
    "gn:name":"Ro\u00e7a",
    "gn:population":0,
    "gn:timezone":"America/Sao_Paulo",
    "iso:country":"BR",
    "name:bre_x_preferred":[
        "Roca"
    ],
    "name:cat_x_preferred":[
        "Roca"
    ],
    "name:ceb_x_preferred":[
        "Roca"
    ],
    "name:deu_x_preferred":[
        "Roca"
    ],
    "name:eus_x_preferred":[
        "Roca"
    ],
    "name:fra_x_preferred":[
        "Roca"
    ],
    "name:glg_x_preferred":[
        "Roca"
    ],
    "name:ita_x_preferred":[
        "Roca"
    ],
    "name:jpn_x_preferred":[
        "\u30ed\u30ab"
    ],
    "name:pol_x_preferred":[
        "Roca"
    ],
    "name:por_x_preferred":[
        "Ro\u00e7a"
    ],
    "name:por_x_variant":[
        "Roca"
    ],
    "name:spa_x_preferred":[
        "Roca"
    ],
    "name:swe_x_preferred":[
        "Roca"
    ],
    "wof:name":"Roca",
    "wof:placetype":"locality"
},
  "geometry": {"coordinates":[-45.6697,-22.5062],"type":"Point"}
}