{
  "type": "Feature",
  "properties": {
    "gn:admin1_code":"27",
    "gn:admin2_code":"3511003.0",
    "gn:asciiname":"Vila Nordestina",
    "gn:country_code":"BR",
    "gn:dem":340,
    "gn:feature_class":"P",
    "gn:feature_code":"PPL",
    "gn:name":"Vila Nordestina",
    "gn:population":0,
    "gn:timezone":"America/Sao_Paulo",
    "iso:country":"BR",
    "wof:name":"Vila Nordestina",
    "wof:placetype":"locality"
},
  "geometry": {"coordinates":[-51.56667,-21.06667],"type":"Point"}
}