{
  "type": "Feature",
  "properties": {
    "gn:admin1_code":"20",
    "gn:admin2_code":"2203909.0",
    "gn:asciiname":"Retiro Sao Jose",
    "gn:country_code":"BR",
    "gn:dem":119,
    "gn:feature_class":"P",
    "gn:feature_code":"PPL",
    "gn:name":"Retiro S\u00e3o Jos\u00e9",
    "gn:population":0,
    "gn:timezone":"America/Fortaleza",
    "iso:country":"BR",
    "wof:name":"Retiro Sao Jose",
    "wof:placetype":"locality"
},
  "geometry": {"coordinates":[-43.38333,-6.81667],"type":"Point"}
}