{
  "type": "Feature",
  "properties": {
    "gn:admin1_code":"20",
    "gn:admin2_code":"2202091.0",
    "gn:asciiname":"Ruestao",
    "gn:country_code":"BR",
    "gn:dem":457,
    "gn:feature_class":"P",
    "gn:feature_code":"PPL",
    "gn:name":"Ruest\u00e3o",
    "gn:population":0,
    "gn:timezone":"America/Fortaleza",
    "iso:country":"BR",
    "wof:name":"Ruestao",
    "wof:placetype":"locality"
},
  "geometry": {"coordinates":[-40.73333,-7.25],"type":"Point"}
}