{
  "type": "Feature",
  "properties": {
    "gn:admin1_code":"18.0",
    "gn:admin2_code":"4100103.0",
    "gn:asciiname":"Figueira",
    "gn:country_code":"BR",
    "gn:dem":550,
    "gn:feature_class":"P",
    "gn:feature_code":"PPLL",
    "gn:name":"Figueira",
    "gn:population":0,
    "gn:timezone":"America/Sao_Paulo",
    "iso:country":"BR",
    "name:ceb_x_preferred":[
        "Figueira"
    ],
    "name:deu_x_preferred":[
        "Figueira"
    ],
    "name:fra_x_preferred":[
        "Figueira"
    ],
    "name:glg_x_preferred":[
        "Figueira"
    ],
    "name:nld_x_preferred":[
        "Figueira"
    ],
    "name:por_x_preferred":[
        "Figueira"
    ],
    "name:rus_x_preferred":[
        "\u0424\u0438\u0433\u0435\u0439\u0440\u0430"
    ],
    "name:swe_x_preferred":[
        "Figueira"
    ],
    "name:ukr_x_preferred":[
        "\u0424\u0456\u0433\u0435\u0439\u0440\u0430"
    ],
    "wof:name":"Figueira",
    "wof:placetype":"locality"
},
  "geometry": {"coordinates":[-50.23461,-23.33495],"type":"Point"}
}