{
  "type": "Feature",
  "properties": {
    "gn:admin1_code":"18.0",
    "gn:admin2_code":"4100103.0",
    "gn:asciiname":"Figueira",
    "gn:country_code":"BR",
    "gn:dem":550,
    "gn:feature_class":"P",
    "gn:feature_code":"PPLL",
    "gn:name":"Figueira",
    "gn:population":0,
    "gn:timezone":"America/Sao_Paulo",
    "iso:country":"BR",
    "name:por_x_preferred":[
        "Figueira"
    ],
    "wof:name":"Figueira",
    "wof:placetype":"locality"
},
  "geometry": {"coordinates":[-50.23461,-23.33495],"type":"Point"}
}