{
  "type": "Feature",
  "properties": {
    "gn:admin1_code":"13",
    "gn:admin2_code":"2110104.0",
    "gn:asciiname":"Bracinho",
    "gn:country_code":"BR",
    "gn:dem":64,
    "gn:feature_class":"P",
    "gn:feature_code":"PPL",
    "gn:name":"Bracinho",
    "gn:population":0,
    "gn:timezone":"America/Fortaleza",
    "iso:country":"BR",
    "wof:name":"Bracinho",
    "wof:placetype":"locality"
},
  "geometry": {"coordinates":[-43.08972,-3.31],"type":"Point"}
}