{
  "type": "Feature",
  "properties": {
    "gn:admin1_code":"20",
    "gn:admin2_code":"2203909.0",
    "gn:asciiname":"Santos",
    "gn:country_code":"BR",
    "gn:dem":189,
    "gn:feature_class":"P",
    "gn:feature_code":"PPL",
    "gn:name":"Santos",
    "gn:population":0,
    "gn:timezone":"America/Fortaleza",
    "iso:country":"BR",
    "name:ara_x_preferred":[
        "\u0633\u0627\u0646\u062a\u0648\u0633"
    ],
    "name:arg_x_preferred":[
        "Santos"
    ],
    "name:ceb_x_preferred":[
        "Santos"
    ],
    "name:ces_x_preferred":[
        "Santos"
    ],
    "name:deu_x_preferred":[
        "Santos"
    ],
    "name:fas_x_preferred":[
        "\u0633\u0627\u0646\u062a\u0648\u0633"
    ],
    "name:fin_x_preferred":[
        "Santos"
    ],
    "name:fra_x_preferred":[
        "Santos"
    ],
    "name:heb_x_preferred":[
        "\u05e1\u05e0\u05d8\u05d5\u05e1"
    ],
    "name:ita_x_preferred":[
        "Santos"
    ],
    "name:jpn_x_preferred":[
        "\u30b5\u30f3\u30c8\u30b9"
    ],
    "name:kor_x_preferred":[
        "\uc0b0\ud1a0\uc2a4"
    ],
    "name:lav_x_preferred":[
        "Santos"
    ],
    "name:nld_x_preferred":[
        "Santos"
    ],
    "name:pol_x_preferred":[
        "Santos"
    ],
    "name:por_x_preferred":[
        "Santos"
    ],
    "name:rus_x_preferred":[
        "\u0421\u0430\u043d\u0442\u043e\u0441"
    ],
    "name:sco_x_preferred":[
        "Santos"
    ],
    "name:slk_x_preferred":[
        "Santos"
    ],
    "name:spa_x_preferred":[
        "Santos"
    ],
    "name:srp_x_preferred":[
        "\u0421\u0430\u043d\u0442\u043e\u0441"
    ],
    "name:swe_x_preferred":[
        "Santos"
    ],
    "name:ukr_x_preferred":[
        "\u0421\u0430\u043d\u0442\u043e\u0441"
    ],
    "name:war_x_preferred":[
        "Santos"
    ],
    "wof:name":"Santos",
    "wof:placetype":"locality"
},
  "geometry": {"coordinates":[-43.13333,-7.06667],"type":"Point"}
}