{
  "type": "Feature",
  "properties": {
    "gn:admin1_code":"27",
    "gn:admin2_code":"3519006.0",
    "gn:asciiname":"Quilometro Sete",
    "gn:cc2":"BR",
    "gn:country_code":"BR",
    "gn:dem":494,
    "gn:feature_class":"P",
    "gn:feature_code":"PPL",
    "gn:name":"Quil\u00f4metro Sete",
    "gn:population":0,
    "gn:timezone":"America/Sao_Paulo",
    "iso:country":"BR",
    "name:und_x_variant":[
        "Kilometer Sete",
        "Quil\u00f4metro Sete"
    ],
    "wof:name":"Quilometro Sete",
    "wof:placetype":"locality"
},
  "geometry": {"coordinates":[-50.46667,-22.03333],"type":"Point"}
}