{
  "type": "Feature",
  "properties": {
    "gn:admin1_code":"20",
    "gn:admin2_code":"2200509.0",
    "gn:asciiname":"Jatoba (3)",
    "gn:country_code":"BR",
    "gn:dem":102,
    "gn:feature_class":"P",
    "gn:feature_code":"PPL",
    "gn:name":"Jatob\u00e1 (3)",
    "gn:population":0,
    "gn:timezone":"America/Fortaleza",
    "iso:country":"BR",
    "wof:name":"Jatoba (3)",
    "wof:placetype":"locality"
},
  "geometry": {"coordinates":[-42.88333,-6.56667],"type":"Point"}
}