{
  "type": "Feature",
  "properties": {
    "gn:admin1_code":"27",
    "gn:admin2_code":"3554508.0",
    "gn:asciiname":"Areia Vermelha",
    "gn:country_code":"BR",
    "gn:dem":520,
    "gn:feature_class":"P",
    "gn:feature_code":"PPLL",
    "gn:name":"Areia Vermelha",
    "gn:population":0,
    "gn:timezone":"America/Sao_Paulo",
    "iso:country":"BR",
    "name:por_x_preferred":[
        "Areia Vermelha"
    ],
    "wof:name":"Areia Vermelha",
    "wof:placetype":"locality"
},
  "geometry": {"coordinates":[-47.70883,-23.14088],"type":"Point"}
}