{
  "type": "Feature",
  "properties": {
    "gn:admin1_code":"27",
    "gn:admin2_code":"3525201.0",
    "gn:asciiname":"Sitio Dois Lagos",
    "gn:country_code":"BR",
    "gn:dem":829,
    "gn:feature_class":"P",
    "gn:feature_code":"PPL",
    "gn:name":"S\u00edtio Dois Lagos",
    "gn:population":0,
    "gn:timezone":"America/Sao_Paulo",
    "iso:country":"BR",
    "name:por_x_preferred":[
        "S\u00edtio Dois Lagos"
    ],
    "wof:name":"Sitio Dois Lagos",
    "wof:placetype":"locality"
},
  "geometry": {"coordinates":[-46.67028,-23.18222],"type":"Point"}
}