{
  "type": "Feature",
  "properties": {
    "gn:admin1_code":"13",
    "gn:admin2_code":"2105427.0",
    "gn:asciiname":"Aldeia Amanajas Tauai",
    "gn:cc2":"BR",
    "gn:country_code":"BR",
    "gn:dem":209,
    "gn:feature_class":"P",
    "gn:feature_code":"PPL",
    "gn:name":"Aldeia Amanaj\u00e1s Taua\u00ed",
    "gn:population":0,
    "gn:timezone":"America/Fortaleza",
    "iso:country":"BR",
    "name:und_x_variant":[
        "Aldeia Amanajaz Taud\u00ed",
        "Aldeia Amanajaz Taua\u00ed",
        "Aldeia Amanaj\u00e1s Taua\u00ed"
    ],
    "wof:name":"Aldeia Amanajas Tauai",
    "wof:placetype":"locality"
},
  "geometry": {"coordinates":[-47.36667,-4.53333],"type":"Point"}
}