{
  "type": "Feature",
  "properties": {
    "gn:admin1_code":"1",
    "gn:admin2_code":"1200450.0",
    "gn:asciiname":"Colocacao Lagoa de Barro",
    "gn:country_code":"BR",
    "gn:dem":156,
    "gn:feature_class":"P",
    "gn:feature_code":"PPL",
    "gn:name":"Coloca\u00e7\u00e3o Lagoa de Barro",
    "gn:population":0,
    "gn:timezone":"America/Rio_Branco",
    "iso:country":"BR",
    "wof:name":"Colocacao Lagoa de Barro",
    "wof:placetype":"locality"
},
  "geometry": {"coordinates":[-67.25,-9.75],"type":"Point"}
}