{
  "type": "Feature",
  "properties": {
    "gn:admin1_code":"14",
    "gn:admin2_code":"5107701.0",
    "gn:asciiname":"Forquilha",
    "gn:country_code":"BR",
    "gn:dem":207,
    "gn:feature_class":"P",
    "gn:feature_code":"PPL",
    "gn:name":"Forquilha",
    "gn:population":0,
    "gn:timezone":"America/Cuiaba",
    "iso:country":"BR",
    "wof:name":"Forquilha",
    "wof:placetype":"locality"
},
  "geometry": {"coordinates":[-56.36666999999999,-14.95],"type":"Point"}
}