{
  "type": "Feature",
  "properties": {
    "gn:admin1_code":"26",
    "gn:admin2_code":"4203303.0",
    "gn:asciiname":"Sitio Alexandre W. Brand",
    "gn:country_code":"BR",
    "gn:dem":863,
    "gn:feature_class":"P",
    "gn:feature_code":"PPL",
    "gn:name":"S\u00edtio Alexandre W. Brand",
    "gn:population":0,
    "gn:timezone":"America/Sao_Paulo",
    "iso:country":"BR",
    "name:por_x_preferred":[
        "S\u00edtio Alexandre W. Brand"
    ],
    "wof:name":"Sitio Alexandre W. Brand",
    "wof:placetype":"locality"
},
  "geometry": {"coordinates":[-49.3465,-26.1883],"type":"Point"}
}