{
  "type": "Feature",
  "properties": {
    "gn:admin1_code":"11",
    "gn:admin2_code":"5005400.0",
    "gn:asciiname":"Mimoso",
    "gn:country_code":"BR",
    "gn:dem":555,
    "gn:feature_class":"P",
    "gn:feature_code":"PPL",
    "gn:name":"Mimoso",
    "gn:population":0,
    "gn:timezone":"America/Campo_Grande",
    "iso:country":"BR",
    "name:por_x_preferred":[
        "Mimoso"
    ],
    "wof:name":"Mimoso",
    "wof:placetype":"locality"
},
  "geometry": {"coordinates":[-55.56667,-21.41667],"type":"Point"}
}