{
  "type": "Feature",
  "properties": {
    "gn:admin1_code":"20",
    "gn:admin2_code":"2208205.0",
    "gn:asciiname":"Salina",
    "gn:country_code":"BR",
    "gn:dem":475,
    "gn:feature_class":"P",
    "gn:feature_code":"PPL",
    "gn:name":"Salina",
    "gn:population":0,
    "gn:timezone":"America/Fortaleza",
    "iso:country":"BR",
    "wof:name":"Salina",
    "wof:placetype":"locality"
},
  "geometry": {"coordinates":[-40.71667,-6.83333],"type":"Point"}
}