{
  "type": "Feature",
  "properties": {
    "gn:admin1_code":"21",
    "gn:admin2_code":"3305208.0",
    "gn:asciiname":"Itai",
    "gn:country_code":"BR",
    "gn:dem":10,
    "gn:feature_class":"P",
    "gn:feature_code":"PPL",
    "gn:name":"Ita\u00ed",
    "gn:population":0,
    "gn:timezone":"America/Sao_Paulo",
    "iso:country":"BR",
    "name:por_x_preferred":[
        "Ita\u00ed"
    ],
    "wof:name":"Itai",
    "wof:placetype":"locality"
},
  "geometry": {"coordinates":[-42.18333,-22.71667],"type":"Point"}
}