{
  "type": "Feature",
  "properties": {
    "gn:admin1_code":"18.0",
    "gn:admin2_code":"4127809.0",
    "gn:asciiname":"Sitio Valdemar R. Ponde",
    "gn:country_code":"BR",
    "gn:dem":619,
    "gn:feature_class":"P",
    "gn:feature_code":"PPL",
    "gn:name":"S\u00edtio Valdemar R. Pond\u00e9",
    "gn:population":0,
    "gn:timezone":"America/Sao_Paulo",
    "iso:country":"BR",
    "name:por_x_preferred":[
        "S\u00edtio Valdemar R. Pond\u00e9"
    ],
    "wof:name":"Sitio Valdemar R. Ponde",
    "wof:placetype":"locality"
},
  "geometry": {"coordinates":[-49.9414,-23.6238],"type":"Point"}
}