{
  "type": "Feature",
  "properties": {
    "gn:admin1_code":"25",
    "gn:admin2_code":"1400308.0",
    "gn:asciiname":"Porto Veado",
    "gn:country_code":"BR",
    "gn:dem":84,
    "gn:feature_class":"P",
    "gn:feature_code":"PPL",
    "gn:name":"P\u00f4rto Veado",
    "gn:population":0,
    "gn:timezone":"America/Boa_Vista",
    "iso:country":"BR",
    "wof:name":"Porto Veado",
    "wof:placetype":"locality"
},
  "geometry": {"coordinates":[-60.93333000000001,2.25],"type":"Point"}
}