{
  "type": "Feature",
  "properties": {
    "gn:admin1_code":"18.0",
    "gn:admin2_code":"4112405.0",
    "gn:asciiname":"Carioca",
    "gn:country_code":"BR",
    "gn:dem":343,
    "gn:feature_class":"P",
    "gn:feature_code":"PPLL",
    "gn:name":"Carioca",
    "gn:population":0,
    "gn:timezone":"America/Sao_Paulo",
    "iso:country":"BR",
    "name:hrv_x_preferred":[
        "Carioca"
    ],
    "name:nld_x_preferred":[
        "Carioca"
    ],
    "name:por_x_preferred":[
        "Carioca"
    ],
    "name:spa_x_preferred":[
        "Carioca"
    ],
    "name:srp_x_preferred":[
        "\u041a\u0430\u0440\u0438\u043e\u043a\u0430"
    ],
    "wof:name":"Carioca",
    "wof:placetype":"locality"
},
  "geometry": {"coordinates":[-52.57352,-23.4109],"type":"Point"}
}