{
  "type": "Feature",
  "properties": {
    "gn:admin1_code":"27.0",
    "gn:admin2_code":"3550308.0",
    "gn:asciiname":"Sitio da Serra",
    "gn:country_code":"BR",
    "gn:dem":913,
    "gn:feature_class":"P",
    "gn:feature_code":"PPL",
    "gn:name":"S\u00edtio da Serra",
    "gn:population":0,
    "gn:timezone":"America/Sao_Paulo",
    "iso:country":"BR",
    "name:por_x_preferred":[
        "S\u00edtio da Serra"
    ],
    "wof:name":"Sitio da Serra",
    "wof:placetype":"locality"
},
  "geometry": {"coordinates":[-46.57256,-23.39109],"type":"Point"}
}