{
  "type": "Feature",
  "properties": {
    "gn:admin1_code":"31",
    "gn:admin2_code":"1716604.0",
    "gn:asciiname":"Dois Irmaos",
    "gn:country_code":"BR",
    "gn:dem":229,
    "gn:feature_class":"P",
    "gn:feature_code":"PPL",
    "gn:name":"Dois Irm\u00e3os",
    "gn:population":0,
    "gn:timezone":"America/Araguaina",
    "iso:country":"BR",
    "wof:name":"Dois Irmaos",
    "wof:placetype":"locality"
},
  "geometry": {"coordinates":[-48.63333,-11.75],"type":"Point"}
}