{
  "type": "Feature",
  "properties": {
    "gn:admin1_code":"4.0",
    "gn:admin2_code":"1302207.0",
    "gn:asciiname":"Sao Jose do Aumento",
    "gn:country_code":"BR",
    "gn:dem":79,
    "gn:feature_class":"P",
    "gn:feature_code":"PPL",
    "gn:name":"S\u00e3o Jos\u00e9 do Aumento",
    "gn:population":0,
    "gn:timezone":"America/Manaus",
    "iso:country":"BR",
    "wof:name":"Sao Jose do Aumento",
    "wof:placetype":"locality"
},
  "geometry": {"coordinates":[-66.14594,-3.69081],"type":"Point"}
}