{
  "type": "Feature",
  "properties": {
    "gn:admin1_code":"18.0",
    "gn:admin2_code":"4104709.0",
    "gn:asciiname":"Sitio Paulo Sayto",
    "gn:country_code":"BR",
    "gn:dem":497,
    "gn:feature_class":"P",
    "gn:feature_code":"PPL",
    "gn:name":"S\u00edtio Paulo Sayto",
    "gn:population":0,
    "gn:timezone":"America/Sao_Paulo",
    "iso:country":"BR",
    "name:por_x_preferred":[
        "S\u00edtio Paulo Sayto"
    ],
    "wof:name":"Sitio Paulo Sayto",
    "wof:placetype":"locality"
},
  "geometry": {"coordinates":[-49.76547,-23.42502],"type":"Point"}
}