{
  "type": "Feature",
  "properties": {
    "gn:admin1_code":"20",
    "gn:admin2_code":"2205805.0",
    "gn:asciiname":"Campos",
    "gn:country_code":"BR",
    "gn:dem":75,
    "gn:feature_class":"P",
    "gn:feature_code":"PPL",
    "gn:name":"Campos",
    "gn:population":0,
    "gn:timezone":"America/Fortaleza",
    "iso:country":"BR",
    "name:bre_x_preferred":[
        "Campos"
    ],
    "name:cat_x_preferred":[
        "Campos"
    ],
    "name:ceb_x_preferred":[
        "Campos"
    ],
    "name:deu_x_preferred":[
        "Campos"
    ],
    "name:fin_x_preferred":[
        "Campos"
    ],
    "name:fra_x_preferred":[
        "Campos"
    ],
    "name:glg_x_preferred":[
        "Campos"
    ],
    "name:ita_x_preferred":[
        "Campos"
    ],
    "name:kor_x_preferred":[
        "\uce84\ud3ec\uc2a4"
    ],
    "name:nld_x_preferred":[
        "Campos"
    ],
    "name:pol_x_preferred":[
        "Campos"
    ],
    "name:por_x_preferred":[
        "Campos"
    ],
    "name:rus_x_preferred":[
        "\u041a\u0430\u043c\u043f\u0443\u0448"
    ],
    "name:spa_x_preferred":[
        "Campos"
    ],
    "name:swe_x_preferred":[
        "Campos"
    ],
    "name:zho_x_preferred":[
        "\u574e\u6ce2\u65af"
    ],
    "wof:name":"Campos",
    "wof:placetype":"locality"
},
  "geometry": {"coordinates":[-42.45139,-3.74139],"type":"Point"}
}