{
  "type": "Feature",
  "properties": {
    "gn:admin1_code":"20",
    "gn:admin2_code":"2205805.0",
    "gn:asciiname":"Campos",
    "gn:country_code":"BR",
    "gn:dem":75,
    "gn:feature_class":"P",
    "gn:feature_code":"PPL",
    "gn:name":"Campos",
    "gn:population":0,
    "gn:timezone":"America/Fortaleza",
    "iso:country":"BR",
    "wof:name":"Campos",
    "wof:placetype":"locality"
},
  "geometry": {"coordinates":[-42.45139,-3.74139],"type":"Point"}
}