{
  "type": "Feature",
  "properties": {
    "gn:admin1_code":"18.0",
    "gn:admin2_code":"4124707.0",
    "gn:asciiname":"Sitio Alcides D. Goncalves",
    "gn:country_code":"BR",
    "gn:dem":1121,
    "gn:feature_class":"P",
    "gn:feature_code":"PPL",
    "gn:name":"S\u00edtio Alcides D. Gon\u00e7alves",
    "gn:population":0,
    "gn:timezone":"America/Sao_Paulo",
    "iso:country":"BR",
    "name:por_x_preferred":[
        "S\u00edtio Alcides D. Gon\u00e7alves"
    ],
    "wof:name":"Sitio Alcides D. Goncalves",
    "wof:placetype":"locality"
},
  "geometry": {"coordinates":[-50.66782,-23.79332],"type":"Point"}
}