{
  "type": "Feature",
  "properties": {
    "iso:country":"BR",
    "name:fra_x_preferred":[
        "S\u00e3o Raimundo"
    ],
    "name:kor_x_preferred":[
        "\uc0c1\ud558\uc774\ubb38\ub450"
    ],
    "name:por_x_colloquial":[
        "S Raimundo",
        "S. Raimundo",
        "Sao Raimundo"
    ],
    "name:por_x_preferred":[
        "S\u00e3o Raimundo"
    ],
    "qs:gn_adm0_cc":"BR",
    "qs:gn_fcode":"PPLX",
    "qs:gn_local":3663517,
    "qs:gn_namadm1":"04",
    "qs:gn_name":"S\u00e3o Raimundo",
    "qs:local_max":3574,
    "qs:local_sum":8876,
    "qs:localhoods":22,
    "qs:name":"S\u00e3o Raimundo",
    "qs:name_adm0":"Brasil",
    "qs:name_adm1":"Amazonas",
    "qs:name_adm2":"Manaus",
    "qs:name_local":"Manaus",
    "qs:photo_max":29,
    "qs:photo_sum":118,
    "qs:placetype":"Suburb",
    "qs:quad_count":13,
    "qs:woe_adm0":23424768,
    "qs:woe_adm1":2344847,
    "qs:woe_adm2":12578206,
    "qs:woe_lau":0,
    "qs:woe_local":455833,
    "qs:woe_ver":"7.10.0",
    "wof:lang":[
        "por"
    ],
    "wof:name":"S\u00e3o Raimundo",
    "wof:placetype":"neighbourhood"
},
  "geometry": {"coordinates":[-60.037823,-3.122816],"type":"Point"}
}