{
  "type": "Feature",
  "properties": {
    "gn:admin1_code":"18.0",
    "gn:admin2_code":"4122909.0",
    "gn:asciiname":"Sitio Francisco Siqueira",
    "gn:country_code":"BR",
    "gn:dem":706,
    "gn:feature_class":"P",
    "gn:feature_code":"PPL",
    "gn:name":"S\u00edtio Francisco Siqueira",
    "gn:population":0,
    "gn:timezone":"America/Sao_Paulo",
    "iso:country":"BR",
    "name:por_x_preferred":[
        "S\u00edtio Francisco Siqueira"
    ],
    "wof:name":"Sitio Francisco Siqueira",
    "wof:placetype":"locality"
},
  "geometry": {"coordinates":[-49.7838,-23.6233],"type":"Point"}
}