{
  "type": "Feature",
  "properties": {
    "gn:admin1_code":"27.0",
    "gn:admin2_code":"3550308.0",
    "gn:asciiname":"Sitio Santa Monica",
    "gn:country_code":"BR",
    "gn:dem":760,
    "gn:feature_class":"P",
    "gn:feature_code":"PPL",
    "gn:name":"S\u00edtio Santa M\u00f4nica",
    "gn:population":0,
    "gn:timezone":"America/Sao_Paulo",
    "iso:country":"BR",
    "name:por_x_preferred":[
        "S\u00edtio Santa M\u00f4nica"
    ],
    "wof:name":"Sitio Santa Monica",
    "wof:placetype":"locality"
},
  "geometry": {"coordinates":[-46.6461,-23.7771],"type":"Point"}
}