{
  "type": "Feature",
  "properties": {
    "gn:admin1_code":"4",
    "gn:admin2_code":"1302207.0",
    "gn:asciiname":"Pauapixuna",
    "gn:cc2":"BR",
    "gn:country_code":"BR",
    "gn:dem":48,
    "gn:feature_class":"P",
    "gn:feature_code":"PPL",
    "gn:name":"Pauapixuna",
    "gn:population":0,
    "gn:timezone":"America/Manaus",
    "iso:country":"BR",
    "name:und_x_variant":[
        "Ipau\u00e1-Pixuna",
        "Pauapixuna"
    ],
    "wof:name":"Pauapixuna",
    "wof:placetype":"locality"
},
  "geometry": {"coordinates":[-65.78333000000001,-2.75],"type":"Point"}
}