{
  "type": "Feature",
  "properties": {
    "gn:admin1_code":"26.0",
    "gn:admin2_code":"4215000.0",
    "gn:asciiname":"Cerro Azul",
    "gn:country_code":"BR",
    "gn:dem":925,
    "gn:feature_class":"P",
    "gn:feature_code":"PPLL",
    "gn:name":"Cerro Azul",
    "gn:population":0,
    "gn:timezone":"America/Sao_Paulo",
    "iso:country":"BR",
    "name:por_x_preferred":[
        "Cerro Azul"
    ],
    "wof:name":"Cerro Azul",
    "wof:placetype":"locality"
},
  "geometry": {"coordinates":[-49.62291,-26.58911],"type":"Point"}
}