{
  "type": "Feature",
  "properties": {
    "gn:admin1_code":"26.0",
    "gn:admin2_code":"4215000.0",
    "gn:asciiname":"Cerro Azul",
    "gn:country_code":"BR",
    "gn:dem":925,
    "gn:feature_class":"P",
    "gn:feature_code":"PPLL",
    "gn:name":"Cerro Azul",
    "gn:population":0,
    "gn:timezone":"America/Sao_Paulo",
    "iso:country":"BR",
    "name:bpy_x_preferred":[
        "\u09b8\u09c7\u09b0\u09cd\u09b0\u09cb \u0986\u099c\u09c1\u09b2"
    ],
    "name:ceb_x_preferred":[
        "Cerro Azul"
    ],
    "name:ces_x_preferred":[
        "Cerro Azul"
    ],
    "name:deu_x_preferred":[
        "Cerro Azul"
    ],
    "name:est_x_preferred":[
        "Cerro Azul"
    ],
    "name:fra_x_preferred":[
        "Cerro Azul"
    ],
    "name:ita_x_preferred":[
        "Cerro Azul"
    ],
    "name:kor_x_preferred":[
        "\uc138\ub85c\uc544\uc904"
    ],
    "name:nld_x_preferred":[
        "Cerro Azul"
    ],
    "name:por_x_preferred":[
        "Cerro Azul"
    ],
    "name:rus_x_preferred":[
        "\u0421\u0435\u0440\u0440\u043e-\u0410\u0441\u0443\u043b\u044c"
    ],
    "name:sco_x_preferred":[
        "Cerro Azul"
    ],
    "name:slk_x_preferred":[
        "Cerro Azul"
    ],
    "name:spa_x_preferred":[
        "Cerro Azul"
    ],
    "name:swe_x_preferred":[
        "Cerro Azul"
    ],
    "name:vie_x_preferred":[
        "Cerro Azul"
    ],
    "wof:name":"Cerro Azul",
    "wof:placetype":"locality"
},
  "geometry": {"coordinates":[-49.62291,-26.58911],"type":"Point"}
}