{
  "type": "Feature",
  "properties": {
    "gn:admin1_code":"30",
    "gn:admin2_code":"2613701.0",
    "gn:asciiname":"Sao Bento",
    "gn:country_code":"BR",
    "gn:dem":92,
    "gn:feature_class":"P",
    "gn:feature_code":"PPL",
    "gn:name":"S\u00e3o Bento",
    "gn:population":0,
    "gn:timezone":"America/Recife",
    "iso:country":"BR",
    "wof:name":"Sao Bento",
    "wof:placetype":"locality"
},
  "geometry": {"coordinates":[-35.18333,-8.05],"type":"Point"}
}