{
  "type": "Feature",
  "properties": {
    "gn:admin1_code":"22",
    "gn:admin2_code":"2408003.0",
    "gn:asciiname":"Poco das Pedras",
    "gn:country_code":"BR",
    "gn:dem":6,
    "gn:feature_class":"P",
    "gn:feature_code":"PPL",
    "gn:name":"Po\u00e7o das Pedras",
    "gn:population":0,
    "gn:timezone":"America/Fortaleza",
    "iso:country":"BR",
    "wof:name":"Poco das Pedras",
    "wof:placetype":"locality"
},
  "geometry": {"coordinates":[-37.23556,-5.19139],"type":"Point"}
}