{
  "type": "Feature",
  "properties": {
    "gn:admin1_code":"27.0",
    "gn:admin2_code":"3551108.0",
    "gn:asciiname":"Cabacais",
    "gn:country_code":"BR",
    "gn:dem":670,
    "gn:feature_class":"P",
    "gn:feature_code":"PPLL",
    "gn:name":"Caba\u00e7ais",
    "gn:population":0,
    "gn:timezone":"America/Sao_Paulo",
    "iso:country":"BR",
    "name:por_x_preferred":[
        "Caba\u00e7ais"
    ],
    "wof:name":"Cabacais",
    "wof:placetype":"locality"
},
  "geometry": {"coordinates":[-47.84707,-23.67888],"type":"Point"}
}