{
  "type": "Feature",
  "properties": {
    "gn:admin1_code":"18.0",
    "gn:admin2_code":"4125506.0",
    "gn:asciiname":"Sitio Antonio Grochi",
    "gn:country_code":"BR",
    "gn:dem":820,
    "gn:feature_class":"P",
    "gn:feature_code":"PPL",
    "gn:name":"S\u00edtio Ant\u00f4nio Grochi",
    "gn:population":0,
    "gn:timezone":"America/Sao_Paulo",
    "iso:country":"BR",
    "name:por_x_preferred":[
        "S\u00edtio Ant\u00f4nio Grochi"
    ],
    "wof:name":"Sitio Antonio Grochi",
    "wof:placetype":"locality"
},
  "geometry": {"coordinates":[-48.99126,-25.77119],"type":"Point"}
}