{
  "type": "Feature",
  "properties": {
    "gn:admin1_code":"14",
    "gn:admin2_code":"5108857.0",
    "gn:asciiname":"Joao Ferreira",
    "gn:cc2":"BR",
    "gn:country_code":"BR",
    "gn:dem":301,
    "gn:feature_class":"P",
    "gn:feature_code":"PPL",
    "gn:name":"Jo\u00e3o Ferreira",
    "gn:population":0,
    "gn:timezone":"America/Cuiaba",
    "iso:country":"BR",
    "name:und_x_variant":[
        "Toh\u00earoa",
        "Maloca do Jo\u00e3o Ferreira",
        "Maloca Jo\u00e3o Ferreira",
        "Jo\u00e3o Ferreira"
    ],
    "wof:name":"Joao Ferreira",
    "wof:placetype":"locality"
},
  "geometry": {"coordinates":[-57.33333,-14.26667],"type":"Point"}
}