{
  "type": "Feature",
  "properties": {
    "gn:admin1_code":"23",
    "gn:admin2_code":"4313102.0",
    "gn:asciiname":"Sao Joao",
    "gn:cc2":"BR",
    "gn:country_code":"BR",
    "gn:dem":404,
    "gn:feature_class":"P",
    "gn:feature_code":"PPL",
    "gn:name":"S\u00e3o Jo\u00e3o",
    "gn:population":0,
    "gn:timezone":"America/Sao_Paulo",
    "iso:country":"BR",
    "name:und_x_variant":[
        "Barraca do Alian\u00e7a",
        "Barraca do Allian\u00e7a",
        "S\u00e3o Jo\u00e3o"
    ],
    "wof:name":"Sao Joao",
    "wof:placetype":"locality"
},
  "geometry": {"coordinates":[-53.45,-29.41667],"type":"Point"}
}