{
  "type": "Feature",
  "properties": {
    "gn:admin1_code":"8",
    "gn:admin2_code":"3201902.0",
    "gn:asciiname":"Maximim",
    "gn:country_code":"BR",
    "gn:dem":914,
    "gn:feature_class":"P",
    "gn:feature_code":"PPL",
    "gn:name":"Maximim",
    "gn:population":0,
    "gn:timezone":"America/Sao_Paulo",
    "iso:country":"BR",
    "name:por_x_preferred":[
        "Maximim"
    ],
    "wof:name":"Maximim",
    "wof:placetype":"locality"
},
  "geometry": {"coordinates":[-40.96667,-20.26667],"type":"Point"}
}