{
  "type": "Feature",
  "properties": {
    "gn:admin1_code":"20",
    "gn:admin2_code":"2205409.0",
    "gn:asciiname":"Baixao das Cajazeiras",
    "gn:country_code":"BR",
    "gn:dem":46,
    "gn:feature_class":"P",
    "gn:feature_code":"PPL",
    "gn:name":"Baix\u00e3o das Cajazeiras",
    "gn:population":0,
    "gn:timezone":"America/Fortaleza",
    "iso:country":"BR",
    "wof:name":"Baixao das Cajazeiras",
    "wof:placetype":"locality"
},
  "geometry": {"coordinates":[-42.07889,-3.4575],"type":"Point"}
}