{
  "type": "Feature",
  "properties": {
    "gn:admin1_code":"16",
    "gn:admin2_code":"1506708.0",
    "gn:asciiname":"Barreirinha",
    "gn:country_code":"BR",
    "gn:dem":167,
    "gn:feature_class":"P",
    "gn:feature_code":"PPL",
    "gn:name":"Barreirinha",
    "gn:population":0,
    "gn:timezone":"America/Belem",
    "iso:country":"BR",
    "name:ara_x_preferred":[
        "\u0628\u0627\u0631\u064a\u0631\u064a\u0646\u0627"
    ],
    "name:bpy_x_preferred":[
        "\u09ac\u09be\u09b0\u09cd\u09b0\u09c7\u0987\u09b0\u09bf\u09a8\u09b9\u09be"
    ],
    "name:deu_x_preferred":[
        "Barreirinha"
    ],
    "name:epo_x_preferred":[
        "Barreirinha"
    ],
    "name:eus_x_preferred":[
        "Barreirinha"
    ],
    "name:fra_x_preferred":[
        "Barreirinha"
    ],
    "name:hye_x_preferred":[
        "\u0532\u0561\u057c\u0565\u0575\u0580\u056b\u0576\u056b\u0561"
    ],
    "name:ita_x_preferred":[
        "Barreirinha"
    ],
    "name:kat_x_preferred":[
        "\u10d1\u10d0\u10e0\u10d4\u10d8\u10e0\u10d8\u10dc\u10d8\u10d0"
    ],
    "name:kaz_x_preferred":[
        "\u0411\u0430\u0440\u0440\u0435\u0439\u0440\u0438\u043d\u044c\u044f"
    ],
    "name:mlg_x_preferred":[
        "Barreirinha"
    ],
    "name:nld_x_preferred":[
        "Barreirinha"
    ],
    "name:nor_x_preferred":[
        "Barreirinha"
    ],
    "name:pol_x_preferred":[
        "Barreirinha"
    ],
    "name:por_x_preferred":[
        "Barreirinha"
    ],
    "name:ron_x_preferred":[
        "Barreirinha"
    ],
    "name:rus_x_preferred":[
        "\u0411\u0430\u0440\u0440\u0435\u0439\u0440\u0438\u043d\u044c\u044f"
    ],
    "name:spa_x_preferred":[
        "Barreirinha"
    ],
    "name:vie_x_preferred":[
        "Barreirinha"
    ],
    "name:vol_x_preferred":[
        "Barreirinha"
    ],
    "name:war_x_preferred":[
        "Barreirinha"
    ],
    "name:zho_x_preferred":[
        "\u5df4\u96f7\u91cc\u7d0d"
    ],
    "wof:name":"Barreirinha",
    "wof:placetype":"locality"
},
  "geometry": {"coordinates":[-50.13333,-9.46667],"type":"Point"}
}