{
  "type": "Feature",
  "properties": {
    "gn:admin1_code":"16",
    "gn:admin2_code":"1506708.0",
    "gn:asciiname":"Barreirinha",
    "gn:country_code":"BR",
    "gn:dem":167,
    "gn:feature_class":"P",
    "gn:feature_code":"PPL",
    "gn:name":"Barreirinha",
    "gn:population":0,
    "gn:timezone":"America/Belem",
    "iso:country":"BR",
    "wof:name":"Barreirinha",
    "wof:placetype":"locality"
},
  "geometry": {"coordinates":[-50.13333,-9.46667],"type":"Point"}
}