{
  "type": "Feature",
  "properties": {
    "gn:admin1_code":"18",
    "gn:admin2_code":"4122008.0",
    "gn:asciiname":"Faxinal dos Paula",
    "gn:country_code":"BR",
    "gn:dem":893,
    "gn:feature_class":"P",
    "gn:feature_code":"PPL",
    "gn:name":"Faxinal dos Paula",
    "gn:population":0,
    "gn:timezone":"America/Sao_Paulo",
    "iso:country":"BR",
    "name:por_x_preferred":[
        "Faxinal dos Paula"
    ],
    "wof:name":"Faxinal dos Paula",
    "wof:placetype":"locality"
},
  "geometry": {"coordinates":[-50.73781,-25.69275],"type":"Point"}
}