{
  "type": "Feature",
  "properties": {
    "gn:admin1_code":"26.0",
    "gn:admin2_code":"4205407.0",
    "gn:asciiname":"Morro do Geraldo",
    "gn:country_code":"BR",
    "gn:dem":35,
    "gn:feature_class":"P",
    "gn:feature_code":"PPLL",
    "gn:name":"Morro do Geraldo",
    "gn:population":0,
    "gn:timezone":"America/Sao_Paulo",
    "iso:country":"BR",
    "wof:name":"Morro do Geraldo",
    "wof:placetype":"locality"
},
  "geometry": {"coordinates":[-48.58575,-27.59829],"type":"Point"}
}