{
  "type": "Feature",
  "properties": {
    "gn:admin1_code":"23.0",
    "gn:admin2_code":"4322400.0",
    "gn:asciiname":"Centro, Urugraiana",
    "gn:country_code":"BR",
    "gn:dem":79,
    "gn:feature_class":"P",
    "gn:feature_code":"PPL",
    "gn:name":"Centro, Urugraiana",
    "gn:population":0,
    "gn:timezone":"America/Sao_Paulo",
    "iso:country":"BR",
    "wof:name":"Centro, Urugraiana",
    "wof:placetype":"locality"
},
  "geometry": {"coordinates":[-57.08642,-29.75454],"type":"Point"}
}