{
  "type": "Feature",
  "properties": {
    "gn:admin1_code":"27.0",
    "gn:admin2_code":"3509254.0",
    "gn:asciiname":"Sitio Jaboticaba",
    "gn:country_code":"BR",
    "gn:dem":61,
    "gn:feature_class":"P",
    "gn:feature_code":"PPL",
    "gn:name":"S\u00edtio Jaboticaba",
    "gn:population":0,
    "gn:timezone":"America/Sao_Paulo",
    "iso:country":"BR",
    "name:por_x_preferred":[
        "S\u00edtio Jaboticaba"
    ],
    "wof:name":"Sitio Jaboticaba",
    "wof:placetype":"locality"
},
  "geometry": {"coordinates":[-48.17967,-24.72876],"type":"Point"}
}