{
  "type": "Feature",
  "properties": {
    "gn:admin1_code":"26",
    "gn:admin2_code":"4210100.0",
    "gn:asciiname":"Sitio Lucia Schafaschek",
    "gn:country_code":"BR",
    "gn:dem":881,
    "gn:feature_class":"P",
    "gn:feature_code":"PPL",
    "gn:name":"S\u00edtio L\u00facia Schafaschek",
    "gn:population":0,
    "gn:timezone":"America/Sao_Paulo",
    "iso:country":"BR",
    "name:por_x_preferred":[
        "S\u00edtio L\u00facia Schafaschek"
    ],
    "wof:name":"Sitio Lucia Schafaschek",
    "wof:placetype":"locality"
},
  "geometry": {"coordinates":[-49.758,-26.1732],"type":"Point"}
}