{
  "type": "Feature",
  "properties": {
    "gn:admin1_code":"14",
    "gn:admin2_code":"5102504.0",
    "gn:asciiname":"Porto Bom Jardim",
    "gn:country_code":"BR",
    "gn:dem":127,
    "gn:feature_class":"P",
    "gn:feature_code":"PPL",
    "gn:name":"P\u00f4rto Bom Jardim",
    "gn:population":0,
    "gn:timezone":"America/Cuiaba",
    "iso:country":"BR",
    "wof:name":"Porto Bom Jardim",
    "wof:placetype":"locality"
},
  "geometry": {"coordinates":[-58.08333,-16.05],"type":"Point"}
}