{
  "type": "Feature",
  "properties": {
    "gn:admin1_code":"5",
    "gn:admin2_code":"2929206.0",
    "gn:asciiname":"Sao Bento das Lajes",
    "gn:country_code":"BR",
    "gn:dem":64,
    "gn:feature_class":"P",
    "gn:feature_code":"PPL",
    "gn:name":"S\u00e3o Bento das Lajes",
    "gn:population":0,
    "gn:timezone":"America/Bahia",
    "iso:country":"BR",
    "wof:name":"Sao Bento das Lajes",
    "wof:placetype":"locality"
},
  "geometry": {"coordinates":[-38.68333,-12.61667],"type":"Point"}
}