{
  "type": "Feature",
  "properties": {
    "gn:admin1_code":"18.0",
    "gn:admin2_code":"4126603.0",
    "gn:asciiname":"Sitio Antonio Galvao",
    "gn:country_code":"BR",
    "gn:dem":817,
    "gn:feature_class":"P",
    "gn:feature_code":"PPL",
    "gn:name":"S\u00edtio Ant\u00f4nio Galv\u00e3o",
    "gn:population":0,
    "gn:timezone":"America/Sao_Paulo",
    "iso:country":"BR",
    "name:por_x_preferred":[
        "S\u00edtio Ant\u00f4nio Galv\u00e3o"
    ],
    "wof:name":"Sitio Antonio Galvao",
    "wof:placetype":"locality"
},
  "geometry": {"coordinates":[-49.8577,-23.66],"type":"Point"}
}