{
  "type": "Feature",
  "properties": {
    "gn:admin1_code":"13",
    "gn:admin2_code":"2102200.0",
    "gn:asciiname":"Bacaba",
    "gn:country_code":"BR",
    "gn:dem":109,
    "gn:feature_class":"P",
    "gn:feature_code":"PPL",
    "gn:name":"Bacaba",
    "gn:population":0,
    "gn:timezone":"America/Fortaleza",
    "iso:country":"BR",
    "wof:name":"Bacaba",
    "wof:placetype":"locality"
},
  "geometry": {"coordinates":[-43.08306,-3.91944],"type":"Point"}
}