{
  "type": "Feature",
  "properties": {
    "gn:admin1_code":"18.0",
    "gn:admin2_code":"4106209.0",
    "gn:asciiname":"Sitio Pedro Sendeski",
    "gn:country_code":"BR",
    "gn:dem":912,
    "gn:feature_class":"P",
    "gn:feature_code":"PPL",
    "gn:name":"S\u00edtio Pedro Sendeski",
    "gn:population":0,
    "gn:timezone":"America/Sao_Paulo",
    "iso:country":"BR",
    "name:por_x_preferred":[
        "S\u00edtio Pedro Sendeski"
    ],
    "wof:name":"Sitio Pedro Sendeski",
    "wof:placetype":"locality"
},
  "geometry": {"coordinates":[-49.3992,-25.7842],"type":"Point"}
}