{
  "type": "Feature",
  "properties": {
    "gn:admin1_code":"20.0",
    "gn:admin2_code":"2206654.0",
    "gn:asciiname":"Lagoa da Pedra",
    "gn:country_code":"BR",
    "gn:dem":466,
    "gn:feature_class":"P",
    "gn:feature_code":"PPL",
    "gn:name":"Lagoa da Pedra",
    "gn:population":0,
    "gn:timezone":"America/Fortaleza",
    "iso:country":"BR",
    "name:por_x_preferred":[
        "Lagoa da Pedra"
    ],
    "wof:name":"Lagoa da Pedra",
    "wof:placetype":"locality"
},
  "geometry": {"coordinates":[-43.84856,-10.0309],"type":"Point"}
}