{
  "type": "Feature",
  "properties": {
    "gn:admin1_code":"20",
    "gn:admin2_code":"2211407.0",
    "gn:asciiname":"Coco",
    "gn:country_code":"BR",
    "gn:dem":258,
    "gn:feature_class":"P",
    "gn:feature_code":"PPL",
    "gn:name":"Coco",
    "gn:population":0,
    "gn:timezone":"America/Fortaleza",
    "iso:country":"BR",
    "name:ben_x_preferred":[
        "\u0995\u09cb\u0995\u09cb"
    ],
    "name:cat_x_preferred":[
        "Coco"
    ],
    "name:ceb_x_preferred":[
        "Coco"
    ],
    "name:ces_x_preferred":[
        "Coco"
    ],
    "name:deu_x_preferred":[
        "Coco"
    ],
    "name:fas_x_preferred":[
        "\u06a9\u0648\u06a9\u0648"
    ],
    "name:fin_x_preferred":[
        "Coco"
    ],
    "name:fra_x_preferred":[
        "Coco"
    ],
    "name:glg_x_preferred":[
        "Coco"
    ],
    "name:heb_x_preferred":[
        "\u05e7\u05d5\u05e7\u05d5"
    ],
    "name:hin_x_preferred":[
        "\u0915\u094b\u0915\u094b"
    ],
    "name:hun_x_preferred":[
        "Coco"
    ],
    "name:ind_x_preferred":[
        "Coco"
    ],
    "name:ita_x_preferred":[
        "Coco"
    ],
    "name:kor_x_preferred":[
        "\ucf54\ucf54\uc2a4"
    ],
    "name:nld_x_preferred":[
        "Coco"
    ],
    "name:pol_x_preferred":[
        "Coco"
    ],
    "name:por_x_preferred":[
        "Coco"
    ],
    "name:spa_x_preferred":[
        "Coco"
    ],
    "name:swe_x_preferred":[
        "Coco"
    ],
    "name:tur_x_preferred":[
        "Coco"
    ],
    "name:ukr_x_preferred":[
        "\u041a\u043e\u043a\u043e"
    ],
    "name:urd_x_preferred":[
        "\u06a9\u0648\u06a9\u0648"
    ],
    "name:vie_x_preferred":[
        "S\u00f4ng Coco"
    ],
    "name:zho_x_preferred":[
        "CoCo"
    ],
    "wof:name":"Coco",
    "wof:placetype":"locality"
},
  "geometry": {"coordinates":[-42.15,-6.55],"type":"Point"}
}