{
  "type": "Feature",
  "properties": {
    "gn:admin1_code":"21",
    "gn:admin2_code":"3302205.0",
    "gn:asciiname":"Santa Quiteria",
    "gn:country_code":"BR",
    "gn:dem":122,
    "gn:feature_class":"P",
    "gn:feature_code":"PPL",
    "gn:name":"Santa Quit\u00e9ria",
    "gn:population":0,
    "gn:timezone":"America/Sao_Paulo",
    "iso:country":"BR",
    "name:ceb_x_preferred":[
        "Santa Quiteria"
    ],
    "name:por_x_preferred":[
        "Santa Quit\u00e9ria"
    ],
    "name:swe_x_preferred":[
        "Santa Quiteria"
    ],
    "wof:name":"Santa Quiteria",
    "wof:placetype":"locality"
},
  "geometry": {"coordinates":[-41.73333,-21.33333],"type":"Point"}
}