{
  "type": "Feature",
  "properties": {
    "gn:admin1_code":"18",
    "gn:admin2_code":"4121208.0",
    "gn:asciiname":"Sitio Salvador B. de Lima",
    "gn:country_code":"BR",
    "gn:dem":850,
    "gn:feature_class":"P",
    "gn:feature_code":"PPL",
    "gn:name":"S\u00edtio Salvador B. de Lima",
    "gn:population":0,
    "gn:timezone":"America/Sao_Paulo",
    "iso:country":"BR",
    "name:por_x_preferred":[
        "S\u00edtio Salvador B. de Lima"
    ],
    "wof:name":"Sitio Salvador B. de Lima",
    "wof:placetype":"locality"
},
  "geometry": {"coordinates":[-49.51917,-25.90361],"type":"Point"}
}