{
  "type": "Feature",
  "properties": {
    "gn:admin1_code":"5",
    "gn:admin2_code":"2901304.0",
    "gn:asciiname":"Passagem",
    "gn:country_code":"BR",
    "gn:dem":328,
    "gn:feature_class":"P",
    "gn:feature_code":"PPL",
    "gn:name":"Passagem",
    "gn:population":0,
    "gn:timezone":"America/Bahia",
    "iso:country":"BR",
    "wof:name":"Passagem",
    "wof:placetype":"locality"
},
  "geometry": {"coordinates":[-41.31667,-12.83333],"type":"Point"}
}