{
  "type": "Feature",
  "properties": {
    "gn:admin1_code":"27",
    "gn:admin2_code":"3526209.0",
    "gn:asciiname":"Juquia-Guacu",
    "gn:country_code":"BR",
    "gn:dem":717,
    "gn:feature_class":"P",
    "gn:feature_code":"PPLL",
    "gn:name":"Juquia-Gua\u00e7u",
    "gn:population":0,
    "gn:timezone":"America/Sao_Paulo",
    "iso:country":"BR",
    "name:por_x_preferred":[
        "Juquia-Gua\u00e7u"
    ],
    "name:por_x_variant":[
        "Juqui\u00e1-G\u00faa\u00e7u"
    ],
    "wof:name":"Juquia-Guacu",
    "wof:placetype":"locality"
},
  "geometry": {"coordinates":[-47.19335,-23.9484],"type":"Point"}
}