{
  "type": "Feature",
  "properties": {
    "gn:admin1_code":"18.0",
    "gn:admin2_code":"4117214.0",
    "gn:asciiname":"Sitio Linco Macuta",
    "gn:country_code":"BR",
    "gn:dem":775,
    "gn:feature_class":"P",
    "gn:feature_code":"PPL",
    "gn:name":"S\u00edtio Linco Macuta",
    "gn:population":0,
    "gn:timezone":"America/Sao_Paulo",
    "iso:country":"BR",
    "name:por_x_preferred":[
        "S\u00edtio Linco Macuta"
    ],
    "wof:name":"Sitio Linco Macuta",
    "wof:placetype":"locality"
},
  "geometry": {"coordinates":[-50.69279,-23.57],"type":"Point"}
}