{
  "type": "Feature",
  "properties": {
    "gn:admin1_code":"18.0",
    "gn:admin2_code":"4104006.0",
    "gn:asciiname":"Sitio Walcir",
    "gn:country_code":"BR",
    "gn:dem":807,
    "gn:feature_class":"P",
    "gn:feature_code":"PPL",
    "gn:name":"S\u00edtio Walcir",
    "gn:population":0,
    "gn:timezone":"America/Sao_Paulo",
    "iso:country":"BR",
    "name:por_x_preferred":[
        "S\u00edtio Walcir"
    ],
    "wof:name":"Sitio Walcir",
    "wof:placetype":"locality"
},
  "geometry": {"coordinates":[-48.87682,-25.17273],"type":"Point"}
}