{
  "type": "Feature",
  "properties": {
    "gn:admin1_code":"22",
    "gn:admin2_code":"2400208.0",
    "gn:asciiname":"Caatinga",
    "gn:country_code":"BR",
    "gn:dem":110,
    "gn:feature_class":"P",
    "gn:feature_code":"PPL",
    "gn:name":"Caatinga",
    "gn:population":0,
    "gn:timezone":"America/Fortaleza",
    "iso:country":"BR",
    "name:bel_x_preferred":[
        "\u041a\u0430\u0430\u0442\u044b\u043d\u0433\u0430"
    ],
    "name:bul_x_preferred":[
        "\u041a\u0430\u0430\u0442\u0438\u043d\u0433\u0430"
    ],
    "name:cat_x_preferred":[
        "Caatinga"
    ],
    "name:ces_x_preferred":[
        "Caatinga"
    ],
    "name:deu_x_preferred":[
        "Caatinga"
    ],
    "name:epo_x_preferred":[
        "Caatinga"
    ],
    "name:est_x_preferred":[
        "Kaatinga"
    ],
    "name:eus_x_preferred":[
        "Katinga"
    ],
    "name:fin_x_preferred":[
        "Caatinga"
    ],
    "name:fra_x_preferred":[
        "Caatinga"
    ],
    "name:grn_x_preferred":[
        "Ka'at\u0129nga"
    ],
    "name:ita_x_preferred":[
        "Caatinga"
    ],
    "name:kat_x_preferred":[
        "\u10d9\u10d0\u10d0\u10e2\u10d8\u10dc\u10d2\u10d0"
    ],
    "name:kaz_x_preferred":[
        "\u041a\u0430\u0430\u0442\u0438\u043d\u0433\u0430"
    ],
    "name:kir_x_preferred":[
        "\u041a\u0430\u0430\u0442\u0438\u043d\u0433\u0430"
    ],
    "name:lit_x_preferred":[
        "Kaatinga"
    ],
    "name:mal_x_preferred":[
        "\u0d15\u0d3e\u0d1a\u0d4d\u0d1a\u0d3f\u0d19\u0d4d\u0d17 \u0d2e\u0d41\u0d7e\u0d15\u0d4d\u0d15\u0d3e\u0d1f\u0d4d"
    ],
    "name:nep_x_preferred":[
        "\u0915\u093e\u091f\u093f\u0917\u093e"
    ],
    "name:nld_x_preferred":[
        "Caatinga"
    ],
    "name:nor_x_preferred":[
        "Caatinga"
    ],
    "name:oci_x_preferred":[
        "Caatinga"
    ],
    "name:pol_x_preferred":[
        "Caatinga"
    ],
    "name:por_x_preferred":[
        "Caatinga"
    ],
    "name:rus_x_preferred":[
        "\u041a\u0430\u0430\u0442\u0438\u043d\u0433\u0430"
    ],
    "name:spa_x_preferred":[
        "Caatinga"
    ],
    "name:swe_x_preferred":[
        "Caatinga"
    ],
    "name:ukr_x_preferred":[
        "\u041a\u0430\u0430\u0442\u0438\u043d\u0433\u0430"
    ],
    "wof:name":"Caatinga",
    "wof:placetype":"locality"
},
  "geometry": {"coordinates":[-37.04361,-5.62917],"type":"Point"}
}