{
  "type": "Feature",
  "properties": {
    "gn:admin1_code":"22",
    "gn:admin2_code":"2400208.0",
    "gn:asciiname":"Caatinga",
    "gn:country_code":"BR",
    "gn:dem":110,
    "gn:feature_class":"P",
    "gn:feature_code":"PPL",
    "gn:name":"Caatinga",
    "gn:population":0,
    "gn:timezone":"America/Fortaleza",
    "iso:country":"BR",
    "wof:name":"Caatinga",
    "wof:placetype":"locality"
},
  "geometry": {"coordinates":[-37.04361,-5.62917],"type":"Point"}
}