{
  "type": "Feature",
  "properties": {
    "gn:admin1_code":"20",
    "gn:admin2_code":"2205854.0",
    "gn:asciiname":"Serragem",
    "gn:country_code":"BR",
    "gn:dem":43,
    "gn:feature_class":"P",
    "gn:feature_code":"PPL",
    "gn:name":"Serragem",
    "gn:population":0,
    "gn:timezone":"America/Fortaleza",
    "iso:country":"BR",
    "wof:name":"Serragem",
    "wof:placetype":"locality"
},
  "geometry": {"coordinates":[-42.57833,-3.62472],"type":"Point"}
}