{
  "type": "Feature",
  "properties": {
    "gn:admin1_code":"20",
    "gn:admin2_code":"2202901.0",
    "gn:asciiname":"Pocoes",
    "gn:cc2":"BR",
    "gn:country_code":"BR",
    "gn:dem":426,
    "gn:feature_class":"P",
    "gn:feature_code":"PPL",
    "gn:name":"Po\u00e7\u00f5es",
    "gn:population":0,
    "gn:timezone":"America/Fortaleza",
    "iso:country":"BR",
    "name:und_x_variant":[
        "Po\u00e7\u00e3o",
        "Po\u00e7\u00f5es"
    ],
    "wof:name":"Pocoes",
    "wof:placetype":"locality"
},
  "geometry": {"coordinates":[-45.11667,-10.46667],"type":"Point"}
}