{
  "type": "Feature",
  "properties": {
    "gn:admin1_code":"11",
    "gn:admin2_code":"5005806.0",
    "gn:asciiname":"Oriente",
    "gn:country_code":"BR",
    "gn:dem":196,
    "gn:feature_class":"P",
    "gn:feature_code":"PPL",
    "gn:name":"Oriente",
    "gn:population":0,
    "gn:timezone":"America/Campo_Grande",
    "iso:country":"BR",
    "wof:name":"Oriente",
    "wof:placetype":"locality"
},
  "geometry": {"coordinates":[-55.91667,-20.96667],"type":"Point"}
}