{
  "type": "Feature",
  "properties": {
    "gn:admin1_code":"11",
    "gn:admin2_code":"5005806.0",
    "gn:asciiname":"Oriente",
    "gn:country_code":"BR",
    "gn:dem":196,
    "gn:feature_class":"P",
    "gn:feature_code":"PPL",
    "gn:name":"Oriente",
    "gn:population":0,
    "gn:timezone":"America/Campo_Grande",
    "iso:country":"BR",
    "name:ast_x_preferred":[
        "Oriente"
    ],
    "name:bre_x_preferred":[
        "Oriente"
    ],
    "name:ceb_x_preferred":[
        "Oriente"
    ],
    "name:deu_x_preferred":[
        "Oriente"
    ],
    "name:epo_x_preferred":[
        "Oriente"
    ],
    "name:fra_x_preferred":[
        "Oriente"
    ],
    "name:ita_x_preferred":[
        "Oriente"
    ],
    "name:nld_x_preferred":[
        "Oriente"
    ],
    "name:por_x_preferred":[
        "Oriente"
    ],
    "name:spa_x_preferred":[
        "Oriente"
    ],
    "name:swe_x_preferred":[
        "Oriente"
    ],
    "wof:name":"Oriente",
    "wof:placetype":"locality"
},
  "geometry": {"coordinates":[-55.91667,-20.96667],"type":"Point"}
}