{
  "type": "Feature",
  "properties": {
    "iso:country":"BR",
    "name:bpy_x_preferred":[
        "\u0987\u099f\u09be\u09aa\u09be\u0997\u09bf\u09aa\u09c7"
    ],
    "name:ceb_x_preferred":[
        "Itapagipe"
    ],
    "name:epo_x_preferred":[
        "Itapagipe"
    ],
    "name:eus_x_preferred":[
        "Itapagipe"
    ],
    "name:fra_x_preferred":[
        "Itapagipe"
    ],
    "name:hye_x_preferred":[
        "\u053b\u057f\u0561\u057a\u0561\u056a\u056b\u057a\u056b"
    ],
    "name:ita_x_preferred":[
        "Itapagipe"
    ],
    "name:jpn_x_preferred":[
        "\u30a4\u30bf\u30d1\u30b8\u30da"
    ],
    "name:kat_x_preferred":[
        "\u10d8\u10e2\u10d0\u10de\u10d0\u10df\u10d8\u10de\u10d8"
    ],
    "name:kaz_x_preferred":[
        "\u0418\u0442\u0430\u043f\u0430\u0436\u0438\u043f\u0438"
    ],
    "name:kor_x_preferred":[
        "\uc774\ud0c0\ud30c\uc9c0\ud53c"
    ],
    "name:mlg_x_preferred":[
        "Itapagipe"
    ],
    "name:nld_x_preferred":[
        "Itapagipe"
    ],
    "name:nor_x_preferred":[
        "Itapagipe"
    ],
    "name:pol_x_preferred":[
        "Itapagipe"
    ],
    "name:por_x_preferred":[
        "Itapagipe"
    ],
    "name:ron_x_preferred":[
        "Itapagipe"
    ],
    "name:rus_x_preferred":[
        "\u0418\u0442\u0430\u043f\u0430\u0436\u0438\u043f\u0438"
    ],
    "name:swe_x_preferred":[
        "Itapagipe"
    ],
    "name:unk_x_variant":[
        "Itapagipe"
    ],
    "name:vie_x_preferred":[
        "Itapagipe"
    ],
    "name:vol_x_preferred":[
        "Itapagipe"
    ],
    "name:war_x_preferred":[
        "Itapagipe"
    ],
    "name:zho_x_preferred":[
        "\u4f0a\u5854\u5e15\u65e5\u76ae"
    ],
    "qs:gn_adm0_cc":"BR",
    "qs:gn_fcode":"PPLX",
    "qs:gn_local":3450554,
    "qs:gn_nam_loc":"Salvador, Salvador Bahia, BA, BR",
    "qs:gn_namadm1":"05",
    "qs:gn_name":"Itapagipe",
    "qs:local_max":5672,
    "qs:local_sum":33335,
    "qs:localhoods":16,
    "qs:name":"Itapagipe",
    "qs:name_adm0":"Brasil",
    "qs:name_adm1":"Bahia",
    "qs:name_adm2":"Salvador",
    "qs:name_local":"Salvador",
    "qs:photo_max":97,
    "qs:photo_sum":842,
    "qs:placetype":"Suburb",
    "qs:quad_count":54,
    "qs:woe_adm0":23424768,
    "qs:woe_adm1":2344848,
    "qs:woe_adm2":12578564,
    "qs:woe_lau":0,
    "qs:woe_local":455826,
    "qs:woe_ver":"7.10.0",
    "wof:lang":[
        "por"
    ],
    "wof:name":"Itapagipe",
    "wof:placetype":"neighbourhood"
},
  "geometry": {"coordinates":[-38.491852,-12.918396],"type":"Point"}
}