{
  "type": "Feature",
  "properties": {
    "gn:admin1_code":"18.0",
    "gn:admin2_code":"4124707.0",
    "gn:asciiname":"Sitio Izana P. de Melo",
    "gn:country_code":"BR",
    "gn:dem":980,
    "gn:feature_class":"P",
    "gn:feature_code":"PPL",
    "gn:name":"S\u00edtio Izan\u00e3 P. de Melo",
    "gn:population":0,
    "gn:timezone":"America/Sao_Paulo",
    "iso:country":"BR",
    "name:por_x_preferred":[
        "S\u00edtio Izan\u00e3 P. de Melo"
    ],
    "wof:name":"Sitio Izana P. de Melo",
    "wof:placetype":"locality"
},
  "geometry": {"coordinates":[-50.72597,-23.74969],"type":"Point"}
}