{
  "type": "Feature",
  "properties": {
    "gn:admin1_code":"8",
    "gn:admin2_code":"3200201.0",
    "gn:asciiname":"Segredo",
    "gn:country_code":"BR",
    "gn:dem":794,
    "gn:feature_class":"P",
    "gn:feature_code":"PPL",
    "gn:name":"Segr\u00eado",
    "gn:population":0,
    "gn:timezone":"America/Sao_Paulo",
    "iso:country":"BR",
    "name:bpy_x_preferred":[
        "\u09b8\u09c7\u0997\u09cd\u09b0\u09c7\u09a1\u09cb"
    ],
    "name:ceb_x_preferred":[
        "Segredo"
    ],
    "name:epo_x_preferred":[
        "Segredo"
    ],
    "name:fra_x_preferred":[
        "Segredo"
    ],
    "name:ita_x_preferred":[
        "Segredo"
    ],
    "name:kaz_x_preferred":[
        "\u0421\u0435\u0433\u0440\u0435\u0434\u0443"
    ],
    "name:mlg_x_preferred":[
        "Segredo"
    ],
    "name:nld_x_preferred":[
        "Segredo"
    ],
    "name:nor_x_preferred":[
        "Segredo"
    ],
    "name:pol_x_preferred":[
        "Segredo"
    ],
    "name:por_x_preferred":[
        "Segr\u00eado"
    ],
    "name:ron_x_preferred":[
        "Segredo"
    ],
    "name:rus_x_preferred":[
        "\u0421\u0435\u0433\u0440\u0435\u0434\u0443"
    ],
    "name:spa_x_preferred":[
        "Segredo"
    ],
    "name:swe_x_preferred":[
        "Segredo"
    ],
    "name:vie_x_preferred":[
        "Segredo"
    ],
    "name:vol_x_preferred":[
        "Segredo"
    ],
    "name:war_x_preferred":[
        "Segredo"
    ],
    "name:zho_x_preferred":[
        "\u585e\u683c\u96f7\u675c"
    ],
    "wof:name":"Segredo",
    "wof:placetype":"locality"
},
  "geometry": {"coordinates":[-41.61667,-20.83333],"type":"Point"}
}