{
  "type": "Feature",
  "properties": {
    "gn:admin1_code":"8",
    "gn:admin2_code":"3200201.0",
    "gn:asciiname":"Segredo",
    "gn:country_code":"BR",
    "gn:dem":794,
    "gn:feature_class":"P",
    "gn:feature_code":"PPL",
    "gn:name":"Segr\u00eado",
    "gn:population":0,
    "gn:timezone":"America/Sao_Paulo",
    "iso:country":"BR",
    "name:por_x_preferred":[
        "Segr\u00eado"
    ],
    "wof:name":"Segredo",
    "wof:placetype":"locality"
},
  "geometry": {"coordinates":[-41.61667,-20.83333],"type":"Point"}
}