{
  "type": "Feature",
  "properties": {
    "gn:admin1_code":"5",
    "gn:admin2_code":"2927705.0",
    "gn:asciiname":"Baleia",
    "gn:country_code":"BR",
    "gn:dem":86,
    "gn:feature_class":"P",
    "gn:feature_code":"PPL",
    "gn:name":"Baleia",
    "gn:population":0,
    "gn:timezone":"America/Bahia",
    "iso:country":"BR",
    "name:por_x_preferred":[
        "Baleia"
    ],
    "wof:name":"Baleia",
    "wof:placetype":"locality"
},
  "geometry": {"coordinates":[-39.18333,-16.26667],"type":"Point"}
}