{
  "type": "Feature",
  "properties": {
    "gn:admin1_code":"11",
    "gn:admin2_code":"5003207.0",
    "gn:asciiname":"Laranjeiras",
    "gn:country_code":"BR",
    "gn:dem":97,
    "gn:feature_class":"P",
    "gn:feature_code":"PPL",
    "gn:name":"Laranjeiras",
    "gn:population":0,
    "gn:timezone":"America/Campo_Grande",
    "iso:country":"BR",
    "wof:name":"Laranjeiras",
    "wof:placetype":"locality"
},
  "geometry": {"coordinates":[-57.45,-18.56667],"type":"Point"}
}