{
  "type": "Feature",
  "properties": {
    "gn:admin1_code":"11",
    "gn:admin2_code":"5007109.0",
    "gn:asciiname":"Porto Alegre",
    "gn:country_code":"BR",
    "gn:dem":320,
    "gn:feature_class":"P",
    "gn:feature_code":"PPL",
    "gn:name":"P\u00f4rto Alegre",
    "gn:population":0,
    "gn:timezone":"America/Campo_Grande",
    "iso:country":"BR",
    "wof:name":"Porto Alegre",
    "wof:placetype":"locality"
},
  "geometry": {"coordinates":[-53.48333,-21.56667],"type":"Point"}
}