{
  "type": "Feature",
  "properties": {
    "gn:admin1_code":"22",
    "gn:admin2_code":"2414605.0",
    "gn:asciiname":"Retiro",
    "gn:country_code":"BR",
    "gn:dem":115,
    "gn:feature_class":"P",
    "gn:feature_code":"PPL",
    "gn:name":"Retiro",
    "gn:population":0,
    "gn:timezone":"America/Fortaleza",
    "iso:country":"BR",
    "wof:name":"Retiro",
    "wof:placetype":"locality"
},
  "geometry": {"coordinates":[-37.38194,-5.68889],"type":"Point"}
}