{
  "type": "Feature",
  "properties": {
    "gn:admin1_code":"15",
    "gn:admin2_code":"3101706.0",
    "gn:asciiname":"Limoeiro",
    "gn:country_code":"BR",
    "gn:dem":292,
    "gn:feature_class":"P",
    "gn:feature_code":"PPL",
    "gn:name":"Limoeiro",
    "gn:population":0,
    "gn:timezone":"America/Sao_Paulo",
    "iso:country":"BR",
    "name:por_x_preferred":[
        "Limoeiro"
    ],
    "wof:name":"Limoeiro",
    "wof:placetype":"locality"
},
  "geometry": {"coordinates":[-40.83333,-16.03333],"type":"Point"}
}