{
  "type": "Feature",
  "properties": {
    "gn:admin1_code":"15",
    "gn:admin2_code":"3101706.0",
    "gn:asciiname":"Limoeiro",
    "gn:country_code":"BR",
    "gn:dem":292,
    "gn:feature_class":"P",
    "gn:feature_code":"PPL",
    "gn:name":"Limoeiro",
    "gn:population":0,
    "gn:timezone":"America/Sao_Paulo",
    "iso:country":"BR",
    "name:bpy_x_preferred":[
        "\u09b2\u09bf\u09ae\u09cb\u09af\u09bc\u09c7\u0987\u09b0\u09cb"
    ],
    "name:ceb_x_preferred":[
        "Limoeiro"
    ],
    "name:eus_x_preferred":[
        "Limoeiro"
    ],
    "name:fra_x_preferred":[
        "Limoeiro"
    ],
    "name:ita_x_preferred":[
        "Limoeiro"
    ],
    "name:kat_x_preferred":[
        "\u10da\u10d8\u10db\u10e3\u10d4\u10d8\u10e0\u10e3"
    ],
    "name:kaz_x_preferred":[
        "\u041b\u0438\u043c\u0443\u044d\u0439\u0440\u0443"
    ],
    "name:mlg_x_preferred":[
        "Limoeiro"
    ],
    "name:nld_x_preferred":[
        "Limoeiro"
    ],
    "name:nor_x_preferred":[
        "Limoeiro"
    ],
    "name:por_x_preferred":[
        "Limoeiro"
    ],
    "name:ron_x_preferred":[
        "Limoeiro"
    ],
    "name:rus_x_preferred":[
        "\u041b\u0438\u043c\u0443\u044d\u0439\u0440\u0443"
    ],
    "name:swe_x_preferred":[
        "Limoeiro"
    ],
    "name:vie_x_preferred":[
        "Limoeiro"
    ],
    "name:vol_x_preferred":[
        "Limoeiro"
    ],
    "name:war_x_preferred":[
        "Limoeiro"
    ],
    "name:zho_x_preferred":[
        "\u5229\u7a46\u57c3\u9c81"
    ],
    "wof:name":"Limoeiro",
    "wof:placetype":"locality"
},
  "geometry": {"coordinates":[-40.83333,-16.03333],"type":"Point"}
}