{
  "type": "Feature",
  "properties": {
    "gn:admin1_code":"17",
    "gn:admin2_code":"2509008.0",
    "gn:asciiname":"Pocos",
    "gn:country_code":"BR",
    "gn:dem":630,
    "gn:feature_class":"P",
    "gn:feature_code":"PPL",
    "gn:name":"Po\u00e7os",
    "gn:population":0,
    "gn:timezone":"America/Fortaleza",
    "iso:country":"BR",
    "wof:name":"Pocos",
    "wof:placetype":"locality"
},
  "geometry": {"coordinates":[-38.16667,-7.63333],"type":"Point"}
}