{
  "type": "Feature",
  "properties": {
    "gn:admin1_code":"18",
    "gn:admin2_code":"4124103.0",
    "gn:asciiname":"Nova Granada",
    "gn:country_code":"BR",
    "gn:dem":466,
    "gn:feature_class":"P",
    "gn:feature_code":"PPL",
    "gn:name":"Nova Granada",
    "gn:population":0,
    "gn:timezone":"America/Sao_Paulo",
    "iso:country":"BR",
    "name:bpy_x_preferred":[
        "\u09a8\u09cb\u09ad\u09be \u0997\u09cd\u09b0\u09be\u09a8\u09be\u09a1\u09be"
    ],
    "name:ceb_x_preferred":[
        "Nova Granada"
    ],
    "name:epo_x_preferred":[
        "Nova Granada"
    ],
    "name:eus_x_preferred":[
        "Nova Granada"
    ],
    "name:fra_x_preferred":[
        "Nova Granada"
    ],
    "name:ita_x_preferred":[
        "Nova Granada"
    ],
    "name:kaz_x_preferred":[
        "\u041d\u043e\u0432\u0430-\u0413\u0440\u0430\u043d\u0430\u0434\u0430"
    ],
    "name:mlg_x_preferred":[
        "Nova Granada"
    ],
    "name:nld_x_preferred":[
        "Nova Granada"
    ],
    "name:nor_x_preferred":[
        "Nova Granada"
    ],
    "name:pol_x_preferred":[
        "Nova Granada"
    ],
    "name:por_x_preferred":[
        "Nova Granada"
    ],
    "name:ron_x_preferred":[
        "Nova Granada"
    ],
    "name:rus_x_preferred":[
        "\u041d\u043e\u0432\u0430-\u0413\u0440\u0430\u043d\u0430\u0434\u0430"
    ],
    "name:spa_x_preferred":[
        "Nova Granada"
    ],
    "name:swe_x_preferred":[
        "Nova Granada"
    ],
    "name:vie_x_preferred":[
        "Nova Granada"
    ],
    "name:vol_x_preferred":[
        "Nova Granada"
    ],
    "name:war_x_preferred":[
        "Nova Granada"
    ],
    "name:zho_x_preferred":[
        "\u65b0\u683c\u62c9\u7eb3\u8fbe"
    ],
    "wof:name":"Nova Granada",
    "wof:placetype":"locality"
},
  "geometry": {"coordinates":[-50.18333,-23.18333],"type":"Point"}
}