{
  "type": "Feature",
  "properties": {
    "gn:admin1_code":"18",
    "gn:admin2_code":"4124103.0",
    "gn:asciiname":"Nova Granada",
    "gn:country_code":"BR",
    "gn:dem":466,
    "gn:feature_class":"P",
    "gn:feature_code":"PPL",
    "gn:name":"Nova Granada",
    "gn:population":0,
    "gn:timezone":"America/Sao_Paulo",
    "iso:country":"BR",
    "wof:name":"Nova Granada",
    "wof:placetype":"locality"
},
  "geometry": {"coordinates":[-50.18333,-23.18333],"type":"Point"}
}