{
  "type": "Feature",
  "properties": {
    "gn:admin1_code":"21",
    "gn:admin2_code":"3304557.0",
    "gn:asciiname":"Quinta da Boa Vista",
    "gn:country_code":"BR",
    "gn:dem":20,
    "gn:feature_class":"P",
    "gn:feature_code":"PPL",
    "gn:name":"Quinta da Boa Vista",
    "gn:population":0,
    "gn:timezone":"America/Sao_Paulo",
    "iso:country":"BR",
    "name:por_x_preferred":[
        "Quinta da Boa Vista"
    ],
    "wof:name":"Quinta da Boa Vista",
    "wof:placetype":"locality"
},
  "geometry": {"coordinates":[-43.22472,-22.90572],"type":"Point"}
}