{
  "type": "Feature",
  "properties": {
    "gn:admin1_code":"15",
    "gn:admin2_code":"3120904.0",
    "gn:asciiname":"Jatai",
    "gn:country_code":"BR",
    "gn:dem":666,
    "gn:feature_class":"P",
    "gn:feature_code":"PPL",
    "gn:name":"Jata\u00ed",
    "gn:population":0,
    "gn:timezone":"America/Sao_Paulo",
    "iso:country":"BR",
    "name:por_x_preferred":[
        "Jata\u00ed"
    ],
    "wof:name":"Jatai",
    "wof:placetype":"locality"
},
  "geometry": {"coordinates":[-44.16667,-18.88333],"type":"Point"}
}