{
  "type": "Feature",
  "properties": {
    "gn:admin1_code":"4",
    "gn:admin2_code":"1301308.0",
    "gn:asciiname":"Sao Bras",
    "gn:country_code":"BR",
    "gn:dem":17,
    "gn:feature_class":"P",
    "gn:feature_code":"PPL",
    "gn:name":"S\u00e3o Br\u00e1s",
    "gn:population":0,
    "gn:timezone":"America/Manaus",
    "iso:country":"BR",
    "wof:name":"Sao Bras",
    "wof:placetype":"locality"
},
  "geometry": {"coordinates":[-62.76667,-3.43333],"type":"Point"}
}