{
  "type": "Feature",
  "properties": {
    "gn:admin1_code":"27.0",
    "gn:admin2_code":"3542107.0",
    "gn:asciiname":"Matao",
    "gn:country_code":"BR",
    "gn:dem":560,
    "gn:feature_class":"P",
    "gn:feature_code":"PPLL",
    "gn:name":"Mat\u00e3o",
    "gn:population":0,
    "gn:timezone":"America/Sao_Paulo",
    "iso:country":"BR",
    "name:ceb_x_preferred":[
        "Matao"
    ],
    "name:por_x_preferred":[
        "Mat\u00e3o"
    ],
    "name:swe_x_preferred":[
        "Matao"
    ],
    "wof:name":"Matao",
    "wof:placetype":"locality"
},
  "geometry": {"coordinates":[-47.618,-23.0564],"type":"Point"}
}