{
  "type": "Feature",
  "properties": {
    "gn:admin1_code":"18.0",
    "gn:admin2_code":"4124301.0",
    "gn:asciiname":"Sitio Ogata",
    "gn:country_code":"BR",
    "gn:dem":739,
    "gn:feature_class":"P",
    "gn:feature_code":"PPL",
    "gn:name":"S\u00edtio Ogata",
    "gn:population":0,
    "gn:timezone":"America/Sao_Paulo",
    "iso:country":"BR",
    "name:por_x_preferred":[
        "S\u00edtio Ogata"
    ],
    "wof:name":"Sitio Ogata",
    "wof:placetype":"locality"
},
  "geometry": {"coordinates":[-50.67636,-23.52923],"type":"Point"}
}