{
  "type": "Feature",
  "properties": {
    "gn:admin1_code":"20",
    "gn:admin2_code":"2206696.0",
    "gn:asciiname":"Cocal",
    "gn:country_code":"BR",
    "gn:dem":52,
    "gn:feature_class":"P",
    "gn:feature_code":"PPL",
    "gn:name":"Cocal",
    "gn:population":0,
    "gn:timezone":"America/Fortaleza",
    "iso:country":"BR",
    "wof:name":"Cocal",
    "wof:placetype":"locality"
},
  "geometry": {"coordinates":[-42.06333,-3.41806],"type":"Point"}
}