{
  "type": "Feature",
  "properties": {
    "gn:admin1_code":"29",
    "gn:admin2_code":"5220702.0",
    "gn:asciiname":"Capao",
    "gn:country_code":"BR",
    "gn:dem":783,
    "gn:feature_class":"P",
    "gn:feature_code":"PPL",
    "gn:name":"Cap\u00e3o",
    "gn:population":0,
    "gn:timezone":"America/Sao_Paulo",
    "iso:country":"BR",
    "wof:name":"Capao",
    "wof:placetype":"locality"
},
  "geometry": {"coordinates":[-46.35,-14.68333],"type":"Point"}
}