{
  "type": "Feature",
  "properties": {
    "gn:admin1_code":"18.0",
    "gn:admin2_code":"4122305.0",
    "gn:asciiname":"Lajeado do Cacador",
    "gn:country_code":"BR",
    "gn:dem":816,
    "gn:feature_class":"P",
    "gn:feature_code":"PPL",
    "gn:name":"Lajeado do Ca\u00e7ador",
    "gn:population":0,
    "gn:timezone":"America/Sao_Paulo",
    "iso:country":"BR",
    "name:por_x_preferred":[
        "Lajeado do Ca\u00e7ador"
    ],
    "wof:name":"Lajeado do Cacador",
    "wof:placetype":"locality"
},
  "geometry": {"coordinates":[-49.51109,-26.1391],"type":"Point"}
}