{
  "type": "Feature",
  "properties": {
    "gn:admin1_code":"11",
    "gn:admin2_code":"5006002.0",
    "gn:asciiname":"Saltinho",
    "gn:country_code":"BR",
    "gn:dem":420,
    "gn:feature_class":"P",
    "gn:feature_code":"PPL",
    "gn:name":"Saltinho",
    "gn:population":0,
    "gn:timezone":"America/Campo_Grande",
    "iso:country":"BR",
    "name:ceb_x_preferred":[
        "Saltinho"
    ],
    "name:deu_x_preferred":[
        "Saltinho"
    ],
    "name:fra_x_preferred":[
        "Saltinho"
    ],
    "name:ita_x_preferred":[
        "Saltinho"
    ],
    "name:nld_x_preferred":[
        "Saltinho"
    ],
    "name:nor_x_preferred":[
        "Saltinho"
    ],
    "name:por_x_preferred":[
        "Saltinho"
    ],
    "name:rus_x_preferred":[
        "\u0421\u0430\u043b\u0442\u0438\u043d\u044c\u044e"
    ],
    "name:swe_x_preferred":[
        "Saltinho"
    ],
    "name:vol_x_preferred":[
        "Saltinho"
    ],
    "wof:name":"Saltinho",
    "wof:placetype":"locality"
},
  "geometry": {"coordinates":[-54.41667,-21.06667],"type":"Point"}
}