{
  "type": "Feature",
  "properties": {
    "gn:admin1_code":"11",
    "gn:admin2_code":"5006002.0",
    "gn:asciiname":"Saltinho",
    "gn:country_code":"BR",
    "gn:dem":420,
    "gn:feature_class":"P",
    "gn:feature_code":"PPL",
    "gn:name":"Saltinho",
    "gn:population":0,
    "gn:timezone":"America/Campo_Grande",
    "iso:country":"BR",
    "wof:name":"Saltinho",
    "wof:placetype":"locality"
},
  "geometry": {"coordinates":[-54.41667,-21.06667],"type":"Point"}
}