{
  "type": "Feature",
  "properties": {
    "gn:admin1_code":"30",
    "gn:admin2_code":"2602407.0",
    "gn:asciiname":"Brasileiras",
    "gn:country_code":"BR",
    "gn:dem":719,
    "gn:feature_class":"P",
    "gn:feature_code":"PPL",
    "gn:name":"Brasileiras",
    "gn:population":0,
    "gn:timezone":"America/Recife",
    "iso:country":"BR",
    "wof:name":"Brasileiras",
    "wof:placetype":"locality"
},
  "geometry": {"coordinates":[-36.56667,-9.05],"type":"Point"}
}