{
  "type": "Feature",
  "properties": {
    "gn:admin1_code":"17",
    "gn:admin2_code":"2514206.0",
    "gn:asciiname":"Cacare",
    "gn:country_code":"BR",
    "gn:dem":273,
    "gn:feature_class":"P",
    "gn:feature_code":"PPL",
    "gn:name":"Cacar\u00e9",
    "gn:population":0,
    "gn:timezone":"America/Fortaleza",
    "iso:country":"BR",
    "wof:name":"Cacare",
    "wof:placetype":"locality"
},
  "geometry": {"coordinates":[-38.15,-6.96667],"type":"Point"}
}