{
  "type": "Feature",
  "properties": {
    "gn:admin1_code":"5",
    "gn:admin2_code":"2904001.0",
    "gn:asciiname":"Goncalo",
    "gn:country_code":"BR",
    "gn:dem":1254,
    "gn:feature_class":"P",
    "gn:feature_code":"PPL",
    "gn:name":"Gon\u00e7alo",
    "gn:population":0,
    "gn:timezone":"America/Bahia",
    "iso:country":"BR",
    "wof:name":"Goncalo",
    "wof:placetype":"locality"
},
  "geometry": {"coordinates":[-41.66667,-12.93333],"type":"Point"}
}