{
  "type": "Feature",
  "properties": {
    "gn:admin1_code":"27.0",
    "gn:admin2_code":"3521200.0",
    "gn:asciiname":"Nhunguara",
    "gn:country_code":"BR",
    "gn:dem":148,
    "gn:feature_class":"P",
    "gn:feature_code":"PPLL",
    "gn:name":"Nhunguara",
    "gn:population":0,
    "gn:timezone":"America/Sao_Paulo",
    "iso:country":"BR",
    "name:por_x_preferred":[
        "Nhunguara"
    ],
    "wof:name":"Nhunguara",
    "wof:placetype":"locality"
},
  "geometry": {"coordinates":[-48.4704,-24.60268],"type":"Point"}
}