{
  "type": "Feature",
  "properties": {
    "gn:admin1_code":"18",
    "gn:admin2_code":"4114302.0",
    "gn:asciiname":"Sitio Ricardo Ribeiro",
    "gn:country_code":"BR",
    "gn:dem":894,
    "gn:feature_class":"P",
    "gn:feature_code":"PPL",
    "gn:name":"S\u00edtio Ricardo Ribeiro",
    "gn:population":0,
    "gn:timezone":"America/Sao_Paulo",
    "iso:country":"BR",
    "name:por_x_preferred":[
        "S\u00edtio Ricardo Ribeiro"
    ],
    "wof:name":"Sitio Ricardo Ribeiro",
    "wof:placetype":"locality"
},
  "geometry": {"coordinates":[-49.2483,-25.88300000000001],"type":"Point"}
}