{
  "type": "Feature",
  "properties": {
    "gn:admin1_code":"27.0",
    "gn:admin2_code":"3509254.0",
    "gn:asciiname":"Sitio Guarau",
    "gn:country_code":"BR",
    "gn:dem":30,
    "gn:feature_class":"P",
    "gn:feature_code":"PPL",
    "gn:name":"S\u00edtio Guara\u00fa",
    "gn:population":0,
    "gn:timezone":"America/Sao_Paulo",
    "iso:country":"BR",
    "name:por_x_preferred":[
        "S\u00edtio Guara\u00fa"
    ],
    "wof:name":"Sitio Guarau",
    "wof:placetype":"locality"
},
  "geometry": {"coordinates":[-48.05291,-24.71977],"type":"Point"}
}