{
  "type": "Feature",
  "properties": {
    "gn:admin1_code":"5",
    "gn:admin2_code":"2929602.0",
    "gn:asciiname":"Macauba",
    "gn:country_code":"BR",
    "gn:dem":239,
    "gn:feature_class":"P",
    "gn:feature_code":"PPL",
    "gn:name":"Maca\u00faba",
    "gn:population":0,
    "gn:timezone":"America/Bahia",
    "iso:country":"BR",
    "wof:name":"Macauba",
    "wof:placetype":"locality"
},
  "geometry": {"coordinates":[-39.21667,-12.71667],"type":"Point"}
}