{
  "type": "Feature",
  "properties": {
    "gn:admin1_code":"18.0",
    "gn:admin2_code":"4121208.0",
    "gn:asciiname":"Sitio Carlos P. da Silva",
    "gn:country_code":"BR",
    "gn:dem":823,
    "gn:feature_class":"P",
    "gn:feature_code":"PPL",
    "gn:name":"S\u00edtio Carlos P. da Silva",
    "gn:population":0,
    "gn:timezone":"America/Sao_Paulo",
    "iso:country":"BR",
    "name:por_x_preferred":[
        "S\u00edtio Carlos P. da Silva"
    ],
    "wof:name":"Sitio Carlos P. da Silva",
    "wof:placetype":"locality"
},
  "geometry": {"coordinates":[-49.6116,-25.8896],"type":"Point"}
}