{
  "type": "Feature",
  "properties": {
    "gn:admin1_code":"18.0",
    "gn:admin2_code":"4112306.0",
    "gn:asciiname":"Sitio Barba de Bode",
    "gn:country_code":"BR",
    "gn:dem":609,
    "gn:feature_class":"P",
    "gn:feature_code":"PPL",
    "gn:name":"S\u00edtio Barba de Bode",
    "gn:population":0,
    "gn:timezone":"America/Sao_Paulo",
    "iso:country":"BR",
    "name:por_x_preferred":[
        "S\u00edtio Barba de Bode"
    ],
    "wof:name":"Sitio Barba de Bode",
    "wof:placetype":"locality"
},
  "geometry": {"coordinates":[-50.09723,-23.80765],"type":"Point"}
}