{
  "type": "Feature",
  "properties": {
    "gn:admin1_code":"27.0",
    "gn:admin2_code":"3550308.0",
    "gn:asciiname":"Sitio Monte Azul",
    "gn:country_code":"BR",
    "gn:dem":791,
    "gn:feature_class":"P",
    "gn:feature_code":"PPL",
    "gn:name":"S\u00edtio Monte Azul",
    "gn:population":0,
    "gn:timezone":"America/Sao_Paulo",
    "iso:country":"BR",
    "name:por_x_preferred":[
        "S\u00edtio Monte Azul"
    ],
    "wof:name":"Sitio Monte Azul",
    "wof:placetype":"locality"
},
  "geometry": {"coordinates":[-46.72193,-23.75017],"type":"Point"}
}